{
    "text": "COMMUNICATION\nFINANCIÈRE\nConseil d’Administration\ndu 7 mars 2024\nLe Conseil d’administration de la société AUTO Le résultat net pour l’année 2023 a été arrêté à\nNEJMA MAROC S.A. s’est réuni le jeudi 7 mars 2024 160 MDh, en dminution de 14% par rapport à celui\nà 10h en visioconférence, sous la présidence de de 2022.\nMonsieur Abdellatif HAKAM. Le Conseil d’Administration a décidé de soumettre\nLe Conseil d’Administration a arrêté les comptes les comptes à l’approbation de la prochaine\nde l’exercice 2023, avec un chiffre d’affaires de Assemblée Générale Ordinaire dont la date\n2 225 MDh, en hausse de 6% par rapport à l’année a été fixée pour le lundi 8 avril à 13h00 en\n2022 suite à l’augmentation du volume des ventes visioconférence.\nde prés de 12%. Le Conseil d’Administration proposera à cette\nLe résultat d’exploitation pour l’année 2023 a été Assemblée Générale la distribution d’un dividende\narrêté à 269 MDh, en baisse de 6% par rapport à ordinaire au titre de l’exercice 2023 de 94 dirhams\ncelui de 2022. par action.\nVolume Chiffre d’affaires Résultat d’exploitation Résultat net\nPerspectives\nAuto nejma a lancé un nouveau plan stratégique visant à se diversifier autour du secteur automobile tout en\nrenforçant son positionnement dans le segment du luxe. En effet, Auto Nejma Maroc continue sa dynamique\nd’électrification à travers le lancement de la gamme Mercedes EQ et les nouveaux modèles électriques de\nla marque BYD à zéro émission.\nPar ailleurs, et dans ses objectifs de réduire l’empreinte écologique, Auto Nejma Maroc diversifie ses activités\navec la création de Hakam Technology Solutions, société de vente de solutions technologiques avancées\ndans la mobilité ainsi qu’une société de participation Hakam Capital Ventures qui portera les investissements\nde diversification future du groupe.\nSociété Anonyme au capital de 102 326 400 Dhs | Siège Social : Km 10, Route d’El Jadida - Casablanca\nR.C. N°28.743 | ICE 001524856000053 | Tél :0522650990 | Fax : 0522652908\nRelation Investisseurs : youssef.eliraki@autonejma.ma | Site web : wwwa. utonejma.ma\n2202 3202\n3 378\n3 027\n2202 3202\n2 225\n2 101\n2202 3202\n287 269\n2202 3202\n187 160\nLe 08 Mars 2024\nAVIS DE CONVOCATION À L’ASSEMBLÉE GÉNÉRALE ORDINAIRE DU 8 AVRIL 2024\nLes actionnaires de la Société Auto Nejma Maroc, société anonyme au capital de 102.326.400 dirhams, dont le siège social sis KM 10, Route d’El Jadida Casablanca, inscrite au Registre de Commerce\nde Casablanca sous le n° 28.743, sont convoqués le 08 avril 2024 à 13 h par visioconférence, en Assemblée Générale Ordinaire à l’effet de délibérer sur l’ordre du jour ci-dessous: :\n5 Approbation des modalités de convocation ;\n5 Examen et approbation des états de synthèse de l’exercice clos le 31/12/2023 ;\n5 Rapport du Conseil d’administration sur la gestion, les opérations et les comptes de l’exercice 2023 ;\n5 Approbation des conventions autorisées par le Conseil d’Administration en vertu de l’article 56 de la Loi 17-95 ;\n5 Rapport général des commissaires aux comptes de l’exercice arrêté au 31/12/2023 ;\n5 Rapport d’audit sur les comptes consolidés de l’exercice arrêté au 31/12/2023 ;\n5 Rapport spécial des commissaires aux comptes sur les conventions visées à l’article 56 et suivant de la loi n° 17-95 telle que modifiée et complétée ;\n5 Quitus au Conseil d’administration et aux commissaires aux comptes ;\n5 Affectation des résultats et fixation des dividendes ;\n5 Fixation des jetons de présence ;\n5 Nomination des Commissaires aux Comptes ;\n5 Renouvellement des mandats des administrateurs ;\n5 Vote sur toutes propositions accessoires ;\n5 Pouvoirs pour dépôt et publicité.\nUn actionnaire dans l’impossibilité d’assister personnellement à l’Assemblée Générale peut exercer son droit de vote en votant par procuration. À cet effet, il est rappelé que :\n(Un actionnaire peut se faire représenter par un autre actionnaire, par son conjoint, par un ascendant ou descendant ; dans les sociétés qui font appel public à l’épargne, il peut également se faire\nreprésenter par toute personne morale ayant pour objet social la gestionORDINAIRE de portefeuilles de valeurs mobilières ;\n(Toute procuration d’un actionnaire adressée à la société sans indication de mandataire, le président de l’assemblée générale émet un vote favorable à l’adoption des projets de résolutions\nprésentés ou agréés par le conseil d’administration et un vote défavorable à l’adoption de tous les autres projets de résolution.\nLa Société tient à la disposition des actionnaires des formulaires de vote par correspondance ou par procuration sur son site internet : www.autonejma.ma.\nLes formulaires de vote par correspondance ou par procuration devront être réceptionnés par la Société au moins quarante-huit (48) heures avant la tenue de l’Assemblée à l’adresse mail suivante:\nago@autonejma.ma, ou par lettre au porteur contre récépissé, ou par lettre recommandée avec demande d’avis de réception au siège social.\nLes titulaires d’actions nominatives devront être inscrits sur les registres de la Société cinq (5) jours ouvrés au moins avant la date de l’Assemblée ;\nLes titulaires d’actions au porteur devront déposer ou faire adresser par leur banque au siège social, cinq (5) jours ouvrés au moins avant la date de l’Assemblée, les attestations constatant leur\ninscription en compte auprès d’un intermédiaire financier habilité.\nLes documents requis par la loi sont mis à la disposition des actionnaires au siège social de la société.\nConformément aux dispositions des articles 121 et 121 bis de la loi n° 17-95 relative aux sociétés anonymes telle que modifiée et complétée, la demande d’inscription de projets de résolutions\nà l’ordre du jour de cette Assemblée par les actionnaires détenteurs du pourcentage d’actions prévu par l’article 117 de ladite loi, doit être adressée au siège social par lettre recommandée avec\naccusé de réception dans le délai de dix (10) jours à compter de la publication du présent avis.\nLes documents et informations prévus aux articles 121,121 bis et 141 de la loi° 17-95 peuvent être consultés sur notre site internet : www.autonejma.ma\nLes actionnaires trouveront ci-dessous, le projet des résolutions proposé à cette Assemblée.\nPROJET DES RÉSOLUTIONS DE L’ASSEMBLÉE GÉNÉRALE ORDINAIRE DU 08 AVRIL 2024\nPREMIÈRE RÉSOLUTION SEPTIÈME RÉSOLUTION\nL’Assemblée Générale, approuve les modalités de convocation faites par le Conseil L’Assemblée générale, prend acte de la demission de Monsieur Azzeddine BENMOUSSA de\nd’Administration et lui en donne décharge définitive. son mandat d’administrateur independent à compter de la date de l’Assemblée Généralrale\nOrdinaire du 8 acril 2024 et le remercie pour sa contribution durant ses mandats.\nDEUXIÈME RÉSOLUTION\nL’Assemblée Générale Ordinaire, après avoir entendu la lecture du rapport de gestion et les HUITIÈME RÉSOLUTION\nexplications du Conseil d’Administration, ainsi que la lecture des rapports des Commissaires L’Assemblée générale, conformément à l’article 15 des statuts, constate que les mandats des\naux Comptes, approuve expressément le rapport de gestion, de même qu’elle approuve administrateurs ci-dessous sont arrivés à terme, et approuve leurs renouvellements pour la\nintégralement les comptes de l’exercice clos le 31 décembre 2023 tels qu’ils résultent du bilan durée statutaire d’une année :\narrêté à cette date et qui présentent un bénéfice net de 160.304.136,06 dirhams.\n- Monsieur Abdellatif HAKAM\n- Monsieur El Abbès HAKAM\nTROISIÈME RÉSOLUTION\nL’Assemblée Générale donne au Conseil d’Administration quitus entier, définitif et sans réserve - Monsieur Abdelkrim HAKAM\npour sa gestion au cours de l’exercice clos le 31 décembre 2023.\n- Monsieur Hamza HAKAM\n- Madame Naoual HAKAM\nQUATRIÈME RÉSOLUTION\nL’Assemblée Générale donne quitus aux Commissaires aux Comptes de leur mandat pour En tant qu’Administrateur Indépendant Madame Janie Carmen Madeleine LETROT.\nl’exercice clos le 31 décembre 2023.\nCes mandats prendront fin avec l’Assemblée générale ordinaire qui aura à statuer sur les\ncomptes de l’exercice 2024.\nCINQUIÈME RÉSOLUTION\nL’Assemblée Générale Ordinaire décide d’affecter le bénéfice net qui s’élève à 160.304.136,06\nNEUVIÈME RÉSOLUTION\ndirhams de la façon suivante :\nL’Assemblée Générale fixe le montant des jetons de presence à allouer aux members du conseil\n- Bénéfice net 160 304 136,06 dhs d’administration au titre de l’exercice 2023 à 1 845 000 dirhams.\n- Report antérieur 866 722 666 ,47 dhs Le Conseil d’Administration répartira cette somme entre ses membres, dans les proportions qu’il\njugera convenables.\n- Bénéfice distribuable 1 027 026 802,53 dhs\n- Dividendes ordinaires 96 186 816,00 dhs\nDIXIÈME RÉSOLUTION\n- Solde à reporter à nouveau 930 839 986,53 dhs L’Assemblée Générale constate l’arrivée à terme des mandats des commissaires aux comptes,\net sur proposition du conseil d’administration décide de nommer pour un mandat de 3 ans\nles cabinets Pwc Maroc représenté par Monsieur Mohamed RQIBATE et Fidaroc Grant Thornton\nreprésenté par Monsieur Faiçal MEKOUAR. Ces mandats prendront fin à l’issue de l’Assemblée\nÀ la suite de cette affectation, il sera attribué à chacune des 1 023 264 actions composant le Générale Ordinaire qui statuera sur les comptes de l’exercice 2026.\ncapital social, un dividende ordinaire de 94 Dirhams (quatre vingt-quatorze dirhams) par action\navec mise en paiement pour le 3 juin 2024.\nONZIÈME RÉSOLUTION\nL’Assemblée donne tout pouvoir au porteur d’une copie ou d’un extrait des présentes pour\nSIXIÈME RÉSOLUTION effectuer les formalités prévues par la loi.\nL’Assemblée Générale Ordinaire, après avoir entendu lecture du rapport spécial des commissaires\naux comptes sur les conventions relevant de l’article 56 et suivants de la loi du 17-95, telle que\nmodifiée et complétée, approuve lesdites conventions.\nLe Conseil d’Administration\nBILAN ACTIF\nACTIF PE réx ce érc dic ee n t Brut « eA tm po rort vis iss ie om nse »nt Net 31/1« 2N /2e 0t 2 2»\nIMMOBILISATIONS EN NON VALEURS (A) 41.324.931,59 21.319.619,26 20.005.312,33 9.534.074,24\n* Frais préliminaires 2.180.000,00 412.920,55 1.767.079,45\n* Charges à repartir sur plusieurs exercices 39.144.931,59 20.906.698,71 18.238.232,88 9.534.074,24\n* Primes de remboursement des obligations\nIMMOBILISATIONS INCORPORELLES (B) 21.650.719,06 10.329.396,64 11.321.322,42 10.285.089,41\n* Immobilisation en recherche et développement\n* Brevets, marques, droits et valeurs similaires 0,00\n* Fonds commercial\n* Autres immobilisations incorporelles 21.650.719,06 10.329.396,64 11.321.322,42 10.285.089,41\nIMMOBILISATIONS CORPORELLES (C) 691.565.063,03 301.529.487,39 390.035.575,64 381.555.136,32\n* Terrains 219.833.048,00 219.833.048,00 219.833.048,00\n* Constructions 333.726.738,73 205.939.002,68 127.787.736,05 129.717.753,27\n* Installations techniques, matériel et outillage 62.797.915,22 48.941.024,26 13.856.890,96 10.539.104,32\n* Matériel transport 29.112.149,65 18.769.416,75 10.342.732,90 9.892.402,65\n* Mobilier, matériel de bureau et aménagements divers 40.762.696,87 27.880.043,70 12.882.653,17 7.041.891,03\n* Autres immobilisations corporelles\n* Immobilisations corporelles en cours 5.332.514,56 5.332.514,56 4.530.937,05\nIMMOBILISATIONS FINANCIERES (D) 12.738.949,46 12.738.949,46 238.949,46\n* Prêts immobilisés 0,00\n* Autres créances financières 238.949,46 238.949,46 238.949,46\n* Titres de participation 12.500.000,00 12.500.000,00\n* Autres titres immobilisés\nECARTS DE CONVERSION -ACTIF (E)\n* Diminution des créances immobilisées\n* Augmentation des dettes financières\nTOTAL I (A+B+C+D+E) 767.279.663,14 333.178.503,29 434.101.159,85 401.613.249,43\nSTOCKS (F) 868.259.698,40 4.965.749,55 863.293.948,85 550.882.220,79\n* Marchandises 860.277.287,31 4.965.749,55 855.311.537,76 546.087.126,79\n* Matières et fournitures, consommables\n* Produits en cours 7.982.411,09 7.982.411,09 4.795.094,00\n* produits intermédiaires et produits résiduels\n* Produits finis\nCREANCES DE L'ACTIF CIRCULANT (G) 763.344.370,29 5.905.919,32 757.438.450,97 426.825.515,58\n* Fournis. débiteurs, avances et acomptes 27.298.688,64 27.298.688,64 24.408.502,05\n* Clients et comptes rattachés 395.882.862,08 5.905.919,32 389.976.942,76 337.864.770,78\n* Personnel 935.463,11 935.463,11 803.623,26\n* Etat 75.994.689,61 75.994.689,61 29.585.768,23\n* Comptes d'associés 0,00\n* Autres débiteurs 250.950.532,76 250.950.532,76 26.128.552,01\n* Comptes de régularisation-Actif 12.282.134,09 12.282.134,09 8.034.299,25\nTITRES VALEURS DE PLACEMENT ( H) 8.916.907,14 8.916.907,14 278.375.309,61\nTitres et valeurs de placement 8.916.907,14 8.916.907,14 278.375.309,61\nECARTS DE CONVERSION-ACTIF ( I ) 268.692,13 268.692,13 442.520,92\n. (Eléments circulants) 268.692,13 268.692,13 442.520,92\nTOTAL II ( F+G+H+I ) 1.640.789.667,96 10.871.668,87 1.629.917.999,09 1.256.525.566,90\nTRESORERIE-ACTIF 6.320.631,26 6.320.631,26 40.230.345,28\n* Chéques et valeurs à encaisser 6.028.796,19 6.028.796,19 23.617.841,56\n* Banques, TG et CCP 0,00 0,00 16.080.684,47\n* Caisse, Régie d'avances et accréditifs 291.835,07 291.835,07 531.819,25\nTOTAL III 6.320.631,26 6.320.631,26 40.230.345,28\nTOTAL GENERAL I+II+III 2.414.389.962,36 344.050.172,16 2.070.339.790,20 1.698.369.161,61\nESILIBOMMI\nFITCA\nTNALUCRIC\nFITCA\nEIREROSÉRT\nBILAN PASSIF\nPASSIF Exercice Précede\"E nx te 3r 1c /ic 1e 2 /2022\"\nCAPITAUX PROPRES 1.148.138.116,33 1.115.741.980,46\n* Capital social ou personnel (1) 102.326.400,00 102.326.400,00\n* Moins : actionnaires, capital souscrit non appelé\ncapital appelé\ndont versé.......\n* Prime d'émission, de fusion, d'apport\n* Ecarts de réevaluation\n* Réserve légale 10.232.640,00 10.232.640,00\n* Autres réserves 8.552.273,80 8.552.273,80\n* Report à nouveau (2) 866.722.666,47 807.476.867,04\n* Résultat nets en instance d'affectation (2)\n* Résultat net de l'exercice (2) 160.304.136,06 187.153.799,62\nTotal des capitaux propres (A) 1.148.138.116,33 1.115.741.980,46\nCAPITAUX PROPRES ASSIMILES (B)\n* Subvention d'investissement\n* Provisions réglementées\nDETTES DE FINANCEMENT (C) 122.271.803,29\n* Emprunts obligataires 122.271.803,29\n* Autres dettes de financement\nPROVISIONS DURABLES POUR RISQUES ET CHARGES (D)\n* Provisions pour risques\n* Provisions pour charges\nECARTS DE CONVERSION-PASSIF (E)\n* Augmentation des créances immobilisées\n* Diminution des dettes de financement\nTotal I(A+B+C+D+E) 1.270.409.919,62 1.115.741.980,46\nDETTES DU PASSIF CIRCULANT (F) 501.633.935,47 558.067.774,48\n* Fournisseurs et comptes rattachés 233.315.994,02 298.403.999,58\n* Clients créditeurs, avances et acomptes 43.689.673,45 54.171.780,69\n* Personnel 17.292.737,05 17.418.918,29\n* Organisme sociaux 9.950.951,62 10.107.151,32\n* Etat 40.085.353,76 43.251.896,07\n* Comptes d'associés 9.790.000,00 415.000,00\n* Autres créanciers 26.365.808,37 14.327.009,37\n* Comptes de regularisation passif 121.143.417,20 119.972.019,16\nAUTRES PROVISIONS POUR RISQUES ET CHARGES (G) 27.036.358,34 24.257.873,68\nECARTS DE CONVERSION-PASSIF (Elements circulants) (H) 65.062,20 301.532,99\nTotal II (F+G+H) 528.735.356,01 582.627.181,15\nTRESORERIE-PASSIF 271.194.514,57\n* Crédits d'escompte\n* Crédits de trésorerie 170.000.000,00\n* Banques de régularisation 101.194.514,57\nTotal III 271.194.514,57\nTOTAL GENERAL I+II+III 2.070.339.790,20 1.698.369.161,61\n(1) Capital personnel débiteur\n(2) Bénéficiaire (+). déficitaire (-)\nTNENAMREP\nTNEMECNANIF\nTNALUCRIC\nFISSAP\nEIREROSÉRT\nCOMPTE DE PRODUITS ET CHARGES (Hors Taxes)\nEXERCICE CLOS LE 31/12/2023\nNATURE à P l’r eo xp 1er re cs iO c e P ERATIO l peN c ro sS é n e cc éxe der r en c na ic tn e 2t s T LO ’E 3T XA =EU 2RX +C 1I CD EE AuPT L O ’ 3RE 1ET XA C /E 1EU R 2DX C /E 2I C ND 0E TE 2 2\nI PRODUITS D'EXPLOITATION\n* Ventes de marchandises (en l'état) 2.161.833.906,89 2.161.833.906,89 2.025.563.561,89\n* c V he ifn frt ees d d ’ae ff b ai ie ren ss et services produits 63.665.227,75 63.665.227,75 75.215.824,20\n* Variation de stocks de produits (1) 3.187.317,09 3.187.317,09 1.279.623,63\n* Immobilisations produites par l'entreprise pour elle-même\n* Subventions d'exploitation\n* Autres produits d'exploitation 4.647.998,61 4.647.998,61 4.487.999,46\n* R eprises d'exploitation: transferts de charges 15.625.477,37 15.625.477,37 16.615.577,30\nTotal I 2.248.959.927,71 2.248.959.927,71 2.123.162.586,48\nII CHARGES D'EXPLOITATION\n* Achats revendus(2) de marchandises 1.706.694.905,01 1.706.694.905,01 1.575.802.284,35\n* Achats consommés(2) de matières et fournitures 20.805.686,37 20.805.686,37 17.577.399,44\n* Autres charges externes 81.271.319,79 81.271.319,79 66.022.064,76\n* Impôts et taxes 5.012.014,28 5.012.014,28 3.274.353,56\n* Charges de personnel 125.353.974,60 125.353.974,60 125.029.659,57\n* Autres charges d'exploitation 1.852.162,76 1.852.162,76 1.853.318,70\n* Dotations d'exploitation 38.604.227,37 38.604.227,37 46.889.251,91\nTotal II 1.979.594.290,18 0,00 1.979.594.290,18 1.836.448.332,29\nIII RESULTAT D'EXPLOITATION (I-II) 269.365.637,53 286.714.254,19\nIV PRODUITS FINANCIERS\n* Produits des titres de partic. et autres titres immobilisés\n* Gains de change 10.072.000,63 10.072.000,63 2.826.810,99\n* Interêts et autres produits financiers 7.522.971,62 7.522.971,62 15.758.329,90\n* Reprises financier : transfert charges 566.827,60 566.827,60 488.837,33\nTotal IV 18.161.799,85 18.161.799,85 19.073.978,22\nV CHARGES FINANCIERES\n* Charges d'interêts 4.174.567,19 4.174.567,19 10.691.709,97\n* Pertes de change 2.456.930,73 2.456.930,73 5.498.880,66\n* Autres charges financières\n* Dotations finacières 268.692,13 268.692,13 442.520,92\nTotal V 6.900.190,05 6.900.190,05 16.633.111,55\nVI RESULTAT FINANCIER (IV-V) 11.261.609,80 2.440.866,67\nVII RESULTAT COURANT (III+VI) 280.627.247,33 289.155.120,86\nVII RESULTAT COURANT (reports) 280.627.247,33 289.155.120,86\nVIII PRODUITS NON COURANTS\n* Produits des cessions d'immobilisations 3.740.251,04 3.740.251,04 1.733.845,64\n* Subventions d'équilibre\n* Reprises sur subventions d'investissement\n* Autres produits non courants 8.941.733,48 8.941.733,48 10.149.165,64\n* Reprises non courantes ; transferts de charges 0,00 0,00\nTotal VIII 12.681.984,52 12.681.984,52 11.883.011,28\nIX CHARGES NON COURANTES\n* Valeurs nettes d'amortissements des immobilisations cédées 2.704.356,00 2.704.356,00 891.407,78\n* Subventions accordées\n* Autres charges non courantes 35.372.246,79 35.372.246,79 17.947.618,74\n* Dotations non courantes aux amortissements et aux provisions 5.000.000,00 5.000.000,00 3.000.000,00\nTotal IX 43.076.602,79 43.076.602,79 21.839.026,52\nX RESULTAT NON COURANT (VIII-IX) -30.394.618,27 -9.956.015,24\nXI RESULTAT AVANT IMPÔTS (VII+X) 250.232.629,06 279.199.105,62\nXII IMPÔTS SUR LES BENEFICES 89.928.493,00 89.928.493,00 92.045.306,00\nXIII RESULTAT NET (XI-XII) 160.304.136,06 187.153.799,62\nXIV TOTAL DES PRODUITS. (I+IV+VIII) 2.279.803.712,08 2.154.119.575,98\nXV TOTAL DES CHARGES. (II+V+IX+XIII) 2.119.499.576,02 1.966.965.776,36\nXVI RESULTAT NET. (total des produits-total des charges) 160.304.136,06 187.153.799,62\nNOITATIOLPXE\nREICNANIF\nTNARUOC\nNON\nÉTATS FINANCIERS CONSOLIDÉS\nAU 31 DÉCEMBRE 2023\nPÉRIMÈTRE ET MÉTHODES DE CONSOLIDATION\nCOMPTE DE RESULTAT Proforma\n31-déc-2023 31 décembre 2022\n(En KMAD) 31 décembre 2022\nLe périmètre au 31 décembre 2023 ainsi que les méthodes de consolidation utilisées se\nProduits d'exploitation 2 305 757 2 156 600 2 123 163\nprésentent comme suit :\nChiffre d'affaires 2 274 525 2 135 819 2 100 779\nVariation des stocks 10 922 323 1 280\n31-déc-2023 31-déc-2022 Production immobilisée 153 - -\n% d’intérêt\n% de dM\ne\né ct oh no sd oe\nli- % d’intérêt\n% de dM\ne\né ct oh no sd oe\nli-\nA tau tt iore ns produits d'exploi- 4 488 4 488 4 488\ncontrôle contrôle\ndation dation Reprises d'exploitation 15 669 16 616 16 616\nA (sU oT cO ié tN éE JMA 100 100 I.G 100 100 I.G Charges d'exploitation 2 040 928 1 872 906 1 835 523\nconsolidante)\nA mc ah ta ièt rs e c so en ts fo om urm nié tus r ed se 1 765 841 1 616 254 1 593 380\nSEDEC 100 100 I.G * * *\nAutres charges externes 95 841 70 201 67 619\nHCV 100 100 I.G * * *\nImpôts et taxes 5 283 3 549 3 274\nHTS 100 100 I.G * * *\nCharges de personnel 134 908 135 653 125 030\nAutres charges d'exploitation 2 152 2 453 1 853\nLes sociétés dans lesquelles le Groupe exerce directement ou indirectement un contrôle exclusif\nsont consolidées par intégration globale. Celui-ci est présumé pour les sociétés contrôlées à plus Dotations d'exploitation 36 904 44 795 44 368\nde 50% ou celles où le Groupe est majoritaire au Conseil d’Administration et dont le pourcentage\nRésultat d'exploitation 264 829 283 694 287 639\nde contrôle dépasse 40%.\nProduits financiers 15 215 19 126 18 928\nLes sociétés sous contrôle conjoint sont consolidées par intégration proportionnelle.\nCharges financières 3 989 12 924 12 905\nLa méthode de la mise en équivalence est appliquée pour les sociétés sur lesquelles le Groupe\nexerce une influence notable. L’influence notable est le pouvoir de participer aux politiques Résultat financier 11 226 6 202 6 023\nfinancières et opérationnelles d’une société sans en détenir le contrôle. L’influence notable est\nProduits non courants 13 242 12 053 11 883\nprésumée lorsque le Groupe dispose, directement ou indirectement, d’une fraction comprise\nentre 20% et 40% des droits de vote de cette société. Charges non courantes 46 399 19 035 18 839\nRésultat non courant - 33 156 - 6 982 - 6 956\nProforma\nACTIF (En KMAD) 31-déc-2023 31 décembre 2022 31 décembre 2022 Résultat avant impôt 242 899 282 914 286 706\nEcart d'acquisition - 129 444 - Impôts sur les sociétés 90 074 92 257 92 045\nImmobilisation incorporelles 11 454 10 296 10 285 Impôts différés -3 103 1 268 1 268\nImmobilisations corporelles 704 759 477 274 476 548 R sue rp éri cse as rt sd ’ da ’m aco qrt uis iss ie tiom nent 1 846\nImmobilisation financières 343 531 239\nImpôts différés actifs 12 002 7 544 7 544\nR coé nsu solta lidt énet de l'ensemble 157 773 189 389 193 392\nACTIF IMMOBILISE 728 558 625 089 494 616\nRésultat net part du Groupe 157 773 189 389 193 392\nStocks et en-cours 888 141 568 761 550 882\nF ao cu or mni pss tee surs, avances et 27 370 24 475 24 409 TABLEAU DES FLUX DE TRÉSORERIE\nClient et comptes rattachés 433 833 369 631 337 865 31 décembre 2022 31-déc-2022\nPersonnel 1 036 875 804\nRÉSULTAT NET CONSOLIDÉ 157 773 193 392\nEtat débiteur 82 727 35 492 29 586\nDotations aux amortissements nettes des reprises 24 095 25 459\nAutres débiteurs 41 444 26 617 26 129\nQuote-part du résultat des sociétés mises en équivalence - -\nC aco tm ifptes de régularisation 9 603 8 244 8 034 Résultat de cession - -\nT ci etr mes e ne tt valeurs de pla- 8 917 203 375 278 375 C DA E P LA ’EC NI DTÉ E TD T’ EA MU ET NO TF I FN INA AN NC CEM IEREN NT E A T P DR ’IÈ MS P C ÔO TÛ T 181 869 218 851\nACTIF CIRCULANT 1 493 072 1 237 469 1 256 083 Elimination du coût de l’endettement financier net - -\nDISPONIBILITES 32 814 74 568 40 230 C DA E P LA ’EC NI DTÉ E TD T’ EA MU ET NO TF I FN INA AN NC CEM IEREN NT E A TV DA ’N IMT P C ÔO TÛ T 181 869 218 851\nTOTAL ACTIF 2 254 444 1 937 126 1 790 930\nIncidence de variation du BFR lié à l’activité - 271 956 - 112 064\nVariation des impôts différés 66 027 1 268\nPASSIF (En KMAD) 31-déc-2023 Proforma 31 décembre 2022 FLUX NETS DE TRÉSORERIE GÉNÉRÉS PAR L’ACTIVITÉ -24 060 108 055\n31 décembre 2022\nIncidence de variation de périmètre 7 385 -\nCapital 102 326 102 326 102 326\nAcquisition d’immobilisations incorporelles - 4 843 - 747\nRéserves consolidées 888 332 826 850 824 884\nAcquisition d’immobilisations corporelles - 250 478 - 13 796\nR (Pé as ru tl t da ut n ge rot ud pe e l )'exercice 157 773 189 389 193 392 Acquisition de titres non consolidés - -\nC l’ea np si eta mu bx l ep r co op nr se os l id de é 1 148 431 1 118 566 1 120 603 Flux de trésorerie nette des prêts à long terme - -\nEcart d'acquisition 7 385 - - F DL ’U INX V EN SE TT ISS S D EE M T ER NÉ TS ORERIE LIÉS AUX OPÉRATIONS -247 936 -14 542\nDettes financières 206 656 220 362 85 362 Augmentation de capital - -\nImpôts différés passifs 73 567 3 082 3 082 Dividendes mis en paiement au cours de l’exercice - 127 908 - 88 001\nPASSIF IMMOBILISE 287 608 223 444 88 444 E rem mis bs oio un rs d ee m n eo nu tsv eaux emprunts, nets des 121 293 -\nF rao tu tarn cis hs ée surs et comptes 246 584 304 182 298 404\nF DL EU FX IN N AE NT CS ED ME E T NR TÉ SORERIE LIÉS AUX OPÉRATIONS - 6 615 - 88 001\nC aclie on mts p, ta esvances et 46 034 54 467 54 172\nVARIATION DE TRÉSORERIE NETTE - 278 611 5 512\nP soe crs iao un xnel et organismes 28 532 28 809 27 526 TRÉSORERIE NETTE D’OUVERTURE 40 230 34 718\nTRÉSORERIE NETTE DE CLÔTURE - 238 381 40 230\nEtat créditeur 49 619 49 113 43 252\nC –o pm ap st se if de régularisation 122 867 119 977 119 972 TABLEAU DE VARIATION DES CAPITAUX PROPRES CONSOLIDES\nA risu qtr ue es s p ero t v chis aio rn ges s pour 26 768 23 815 23 815 Résultat\nPrimes Réserves consolidé\nC soo cm iép stes courants d'as- 424 425 415 (En KMAD) Capital d'émission consolidées part du Total\ngroupe\nAutres dettes 26 382 14 327 14 327\nCapitaux propres au 01/01/2023 102 326 - 824 884 193 392 1 120 603\nPASSIF CIRCULANT 547 210 595 116 581 883\nAffectation résultat - - 193 392 -193 392 -\nTRESORERIE - PASSIF 271 195 - -\nDividendes - - -127 908 - -127 908\nTOTAL PASSIF 2 254 444 1 937 126 1 790 930\nRésultat net de l'exercice - - - 157 773 157 773\nAutres retraitements - - -2 037 - -2 037\nCapitaux propres au 31/12/2023 102 326 - 888 332 157 773 1 148 431\nSociété Anonyme au capital de 102 326 400 Dhs | Siège Social : Km 10, Route d’El Jadida - Casablanca - R.C. N°28.743 | ICE 001524856000053 | Tél :0522650990 | Fax : 0522652908\nRelation Investisseurs : youssef.eliraki@autonejma.ma | Le rapport financier annuel est disponible sur le site internet : www.autonejma.ma\nÉTATS FINANCIERS CONSOLIDÉS\nAU 31 DÉCEMBRE 2023\nSociété Anonyme au capital de 102 326 400 Dhs | Siège Social : Km 10, Route d’El Jadida - Casablanca - R.C. N°28.743 | ICE 001524856000053 | Tél :0522650990 | Fax : 0522652908\nRelation Investisseurs : youssef.eliraki@autonejma.ma | Le rapport financier annuel est disponible sur le site internet : www.autonejma.ma",
    "tables": [
        [
            {
                "ACTIF": "",
                "null": "Net",
                "Exercice\nPrécédent": "«Net\n31/12/2022»"
            },
            {
                "ACTIF": "ESILIBOMMI\nFITCA",
                "null": "20.005.312,33",
                "Exercice\nPrécédent": "9.534.074,24"
            },
            {
                "ACTIF": "",
                "null": "1.767.079,45",
                "Exercice\nPrécédent": ""
            },
            {
                "ACTIF": "",
                "null": "18.238.232,88",
                "Exercice\nPrécédent": "9.534.074,24"
            },
            {
                "ACTIF": "",
                "null": "",
                "Exercice\nPrécédent": ""
            },
            {
                "ACTIF": "",
                "null": "11.321.322,42",
                "Exercice\nPrécédent": "10.285.089,41"
            },
            {
                "ACTIF": "",
                "null": "",
                "Exercice\nPrécédent": ""
            },
            {
                "ACTIF": "",
                "null": "0,00",
                "Exercice\nPrécédent": ""
            },
            {
                "ACTIF": "",
                "null": "",
                "Exercice\nPrécédent": ""
            },
            {
                "ACTIF": "",
                "null": "11.321.322,42",
                "Exercice\nPrécédent": "10.285.089,41"
            },
            {
                "ACTIF": "",
                "null": "390.035.575,64",
                "Exercice\nPrécédent": "381.555.136,32"
            },
            {
                "ACTIF": "",
                "null": "219.833.048,00",
                "Exercice\nPrécédent": "219.833.048,00"
            },
            {
                "ACTIF": "",
                "null": "127.787.736,05",
                "Exercice\nPrécédent": "129.717.753,27"
            },
            {
                "ACTIF": "",
                "null": "13.856.890,96",
                "Exercice\nPrécédent": "10.539.104,32"
            },
            {
                "ACTIF": "",
                "null": "10.342.732,90",
                "Exercice\nPrécédent": "9.892.402,65"
            },
            {
                "ACTIF": "",
                "null": "12.882.653,17",
                "Exercice\nPrécédent": "7.041.891,03"
            },
            {
                "ACTIF": "",
                "null": "",
                "Exercice\nPrécédent": ""
            },
            {
                "ACTIF": "",
                "null": "5.332.514,56",
                "Exercice\nPrécédent": "4.530.937,05"
            },
            {
                "ACTIF": "",
                "null": "12.738.949,46",
                "Exercice\nPrécédent": "238.949,46"
            },
            {
                "ACTIF": "",
                "null": "0,00",
                "Exercice\nPrécédent": ""
            },
            {
                "ACTIF": "",
                "null": "238.949,46",
                "Exercice\nPrécédent": "238.949,46"
            },
            {
                "ACTIF": "",
                "null": "12.500.000,00",
                "Exercice\nPrécédent": ""
            },
            {
                "ACTIF": "",
                "null": "",
                "Exercice\nPrécédent": ""
            },
            {
                "ACTIF": "",
                "null": "",
                "Exercice\nPrécédent": ""
            },
            {
                "ACTIF": "",
                "null": "",
                "Exercice\nPrécédent": ""
            },
            {
                "ACTIF": "",
                "null": "",
                "Exercice\nPrécédent": ""
            },
            {
                "ACTIF": "",
                "null": "434.101.159,85",
                "Exercice\nPrécédent": "401.613.249,43"
            },
            {
                "ACTIF": "TNALUCRIC\nFITCA",
                "null": "863.293.948,85",
                "Exercice\nPrécédent": "550.882.220,79"
            },
            {
                "ACTIF": "",
                "null": "855.311.537,76",
                "Exercice\nPrécédent": "546.087.126,79"
            },
            {
                "ACTIF": "",
                "null": "",
                "Exercice\nPrécédent": ""
            },
            {
                "ACTIF": "",
                "null": "7.982.411,09",
                "Exercice\nPrécédent": "4.795.094,00"
            },
            {
                "ACTIF": "",
                "null": "",
                "Exercice\nPrécédent": ""
            },
            {
                "ACTIF": "",
                "null": "",
                "Exercice\nPrécédent": ""
            },
            {
                "ACTIF": "",
                "null": "757.438.450,97",
                "Exercice\nPrécédent": "426.825.515,58"
            },
            {
                "ACTIF": "",
                "null": "27.298.688,64",
                "Exercice\nPrécédent": "24.408.502,05"
            },
            {
                "ACTIF": "",
                "null": "389.976.942,76",
                "Exercice\nPrécédent": "337.864.770,78"
            },
            {
                "ACTIF": "",
                "null": "935.463,11",
                "Exercice\nPrécédent": "803.623,26"
            },
            {
                "ACTIF": "",
                "null": "75.994.689,61",
                "Exercice\nPrécédent": "29.585.768,23"
            },
            {
                "ACTIF": "",
                "null": "0,00",
                "Exercice\nPrécédent": ""
            },
            {
                "ACTIF": "",
                "null": "250.950.532,76",
                "Exercice\nPrécédent": "26.128.552,01"
            },
            {
                "ACTIF": "",
                "null": "12.282.134,09",
                "Exercice\nPrécédent": "8.034.299,25"
            },
            {
                "ACTIF": "",
                "null": "8.916.907,14",
                "Exercice\nPrécédent": "278.375.309,61"
            },
            {
                "ACTIF": "",
                "null": "8.916.907,14",
                "Exercice\nPrécédent": "278.375.309,61"
            },
            {
                "ACTIF": "",
                "null": "268.692,13",
                "Exercice\nPrécédent": "442.520,92"
            },
            {
                "ACTIF": "",
                "null": "268.692,13",
                "Exercice\nPrécédent": "442.520,92"
            },
            {
                "ACTIF": "",
                "null": "1.629.917.999,09",
                "Exercice\nPrécédent": "1.256.525.566,90"
            },
            {
                "ACTIF": "EIREROSÉRT",
                "null": "6.320.631,26",
                "Exercice\nPrécédent": "40.230.345,28"
            },
            {
                "ACTIF": "",
                "null": "6.028.796,19",
                "Exercice\nPrécédent": "23.617.841,56"
            },
            {
                "ACTIF": "",
                "null": "0,00",
                "Exercice\nPrécédent": "16.080.684,47"
            },
            {
                "ACTIF": "",
                "null": "291.835,07",
                "Exercice\nPrécédent": "531.819,25"
            },
            {
                "ACTIF": "",
                "null": "6.320.631,26",
                "Exercice\nPrécédent": "40.230.345,28"
            },
            {
                "ACTIF": "",
                "null": "2.070.339.790,20",
                "Exercice\nPrécédent": "1.698.369.161,61"
            }
        ],
        [
            {
                "": "",
                "NATURE": "",
                "OPERATIONS": "Propres\nà l’exercice\n1",
                "null": "concernant\nles exercices\nprécédent 2",
                "TOTAUX DE\nL’EXERCICE\n3=2+1": "",
                "TOTAUX DE\nL’EXERCICE\nPRECEDENT\nAu 31/12/2022": ""
            },
            {
                "": "I",
                "NATURE": "PRODUITS D'EXPLOITATION",
                "OPERATIONS": "",
                "null": "",
                "TOTAUX DE\nL’EXERCICE\n3=2+1": "",
                "TOTAUX DE\nL’EXERCICE\nPRECEDENT\nAu 31/12/2022": ""
            },
            {
                "": "",
                "NATURE": "* Ventes de marchandises (en l'état)",
                "OPERATIONS": "2.161.833.906,89",
                "null": "",
                "TOTAUX DE\nL’EXERCICE\n3=2+1": "2.161.833.906,89",
                "TOTAUX DE\nL’EXERCICE\nPRECEDENT\nAu 31/12/2022": "2.025.563.561,89"
            },
            {
                "": "",
                "NATURE": "* Ventes de biens et services produits\nchiffre d’affaires",
                "OPERATIONS": "63.665.227,75",
                "null": "",
                "TOTAUX DE\nL’EXERCICE\n3=2+1": "63.665.227,75",
                "TOTAUX DE\nL’EXERCICE\nPRECEDENT\nAu 31/12/2022": "75.215.824,20"
            },
            {
                "": "",
                "NATURE": "* Variation de stocks de produits (1)",
                "OPERATIONS": "3.187.317,09",
                "null": "",
                "TOTAUX DE\nL’EXERCICE\n3=2+1": "3.187.317,09",
                "TOTAUX DE\nL’EXERCICE\nPRECEDENT\nAu 31/12/2022": "1.279.623,63"
            },
            {
                "": "",
                "NATURE": "* Immobilisations produites par l'entreprise pour elle-même",
                "OPERATIONS": "",
                "null": "",
                "TOTAUX DE\nL’EXERCICE\n3=2+1": "",
                "TOTAUX DE\nL’EXERCICE\nPRECEDENT\nAu 31/12/2022": ""
            },
            {
                "": "",
                "NATURE": "* Subventions d'exploitation",
                "OPERATIONS": "",
                "null": "",
                "TOTAUX DE\nL’EXERCICE\n3=2+1": "",
                "TOTAUX DE\nL’EXERCICE\nPRECEDENT\nAu 31/12/2022": ""
            },
            {
                "": "",
                "NATURE": "* Autres produits d'exploitation",
                "OPERATIONS": "4.647.998,61",
                "null": "",
                "TOTAUX DE\nL’EXERCICE\n3=2+1": "4.647.998,61",
                "TOTAUX DE\nL’EXERCICE\nPRECEDENT\nAu 31/12/2022": "4.487.999,46"
            },
            {
                "": "",
                "NATURE": "* R eprises d'exploitation: transferts de charges",
                "OPERATIONS": "15.625.477,37",
                "null": "",
                "TOTAUX DE\nL’EXERCICE\n3=2+1": "15.625.477,37",
                "TOTAUX DE\nL’EXERCICE\nPRECEDENT\nAu 31/12/2022": "16.615.577,30"
            },
            {
                "": "Total I",
                "NATURE": "",
                "OPERATIONS": "2.248.959.927,71",
                "null": "",
                "TOTAUX DE\nL’EXERCICE\n3=2+1": "2.248.959.927,71",
                "TOTAUX DE\nL’EXERCICE\nPRECEDENT\nAu 31/12/2022": "2.123.162.586,48"
            },
            {
                "": "II",
                "NATURE": "CHARGES D'EXPLOITATION",
                "OPERATIONS": "",
                "null": "",
                "TOTAUX DE\nL’EXERCICE\n3=2+1": "",
                "TOTAUX DE\nL’EXERCICE\nPRECEDENT\nAu 31/12/2022": ""
            },
            {
                "": "",
                "NATURE": "* Achats revendus(2) de marchandises",
                "OPERATIONS": "1.706.694.905,01",
                "null": "",
                "TOTAUX DE\nL’EXERCICE\n3=2+1": "1.706.694.905,01",
                "TOTAUX DE\nL’EXERCICE\nPRECEDENT\nAu 31/12/2022": "1.575.802.284,35"
            },
            {
                "": "",
                "NATURE": "* Achats consommés(2) de matières et fournitures",
                "OPERATIONS": "20.805.686,37",
                "null": "",
                "TOTAUX DE\nL’EXERCICE\n3=2+1": "20.805.686,37",
                "TOTAUX DE\nL’EXERCICE\nPRECEDENT\nAu 31/12/2022": "17.577.399,44"
            },
            {
                "": "",
                "NATURE": "* Autres charges externes",
                "OPERATIONS": "81.271.319,79",
                "null": "",
                "TOTAUX DE\nL’EXERCICE\n3=2+1": "81.271.319,79",
                "TOTAUX DE\nL’EXERCICE\nPRECEDENT\nAu 31/12/2022": "66.022.064,76"
            },
            {
                "": "",
                "NATURE": "* Impôts et taxes",
                "OPERATIONS": "5.012.014,28",
                "null": "",
                "TOTAUX DE\nL’EXERCICE\n3=2+1": "5.012.014,28",
                "TOTAUX DE\nL’EXERCICE\nPRECEDENT\nAu 31/12/2022": "3.274.353,56"
            },
            {
                "": "",
                "NATURE": "* Charges de personnel",
                "OPERATIONS": "125.353.974,60",
                "null": "",
                "TOTAUX DE\nL’EXERCICE\n3=2+1": "125.353.974,60",
                "TOTAUX DE\nL’EXERCICE\nPRECEDENT\nAu 31/12/2022": "125.029.659,57"
            },
            {
                "": "",
                "NATURE": "* Autres charges d'exploitation",
                "OPERATIONS": "1.852.162,76",
                "null": "",
                "TOTAUX DE\nL’EXERCICE\n3=2+1": "1.852.162,76",
                "TOTAUX DE\nL’EXERCICE\nPRECEDENT\nAu 31/12/2022": "1.853.318,70"
            },
            {
                "": "",
                "NATURE": "* Dotations d'exploitation",
                "OPERATIONS": "38.604.227,37",
                "null": "",
                "TOTAUX DE\nL’EXERCICE\n3=2+1": "38.604.227,37",
                "TOTAUX DE\nL’EXERCICE\nPRECEDENT\nAu 31/12/2022": "46.889.251,91"
            },
            {
                "": "Total II",
                "NATURE": "",
                "OPERATIONS": "1.979.594.290,18",
                "null": "0,00",
                "TOTAUX DE\nL’EXERCICE\n3=2+1": "1.979.594.290,18",
                "TOTAUX DE\nL’EXERCICE\nPRECEDENT\nAu 31/12/2022": "1.836.448.332,29"
            },
            {
                "": "III",
                "NATURE": "RESULTAT D'EXPLOITATION (I-II)",
                "OPERATIONS": "",
                "null": "",
                "TOTAUX DE\nL’EXERCICE\n3=2+1": "269.365.637,53",
                "TOTAUX DE\nL’EXERCICE\nPRECEDENT\nAu 31/12/2022": "286.714.254,19"
            },
            {
                "": "IV",
                "NATURE": "PRODUITS FINANCIERS",
                "OPERATIONS": "",
                "null": "",
                "TOTAUX DE\nL’EXERCICE\n3=2+1": "",
                "TOTAUX DE\nL’EXERCICE\nPRECEDENT\nAu 31/12/2022": ""
            },
            {
                "": "",
                "NATURE": "* Produits des titres de partic. et autres titres immobilisés",
                "OPERATIONS": "",
                "null": "",
                "TOTAUX DE\nL’EXERCICE\n3=2+1": "",
                "TOTAUX DE\nL’EXERCICE\nPRECEDENT\nAu 31/12/2022": ""
            },
            {
                "": "",
                "NATURE": "* Gains de change",
                "OPERATIONS": "10.072.000,63",
                "null": "",
                "TOTAUX DE\nL’EXERCICE\n3=2+1": "10.072.000,63",
                "TOTAUX DE\nL’EXERCICE\nPRECEDENT\nAu 31/12/2022": "2.826.810,99"
            },
            {
                "": "",
                "NATURE": "* Interêts et autres produits financiers",
                "OPERATIONS": "7.522.971,62",
                "null": "",
                "TOTAUX DE\nL’EXERCICE\n3=2+1": "7.522.971,62",
                "TOTAUX DE\nL’EXERCICE\nPRECEDENT\nAu 31/12/2022": "15.758.329,90"
            },
            {
                "": "",
                "NATURE": "* Reprises financier : transfert charges",
                "OPERATIONS": "566.827,60",
                "null": "",
                "TOTAUX DE\nL’EXERCICE\n3=2+1": "566.827,60",
                "TOTAUX DE\nL’EXERCICE\nPRECEDENT\nAu 31/12/2022": "488.837,33"
            },
            {
                "": "",
                "NATURE": "Total IV",
                "OPERATIONS": "18.161.799,85",
                "null": "",
                "TOTAUX DE\nL’EXERCICE\n3=2+1": "18.161.799,85",
                "TOTAUX DE\nL’EXERCICE\nPRECEDENT\nAu 31/12/2022": "19.073.978,22"
            },
            {
                "": "V",
                "NATURE": "CHARGES FINANCIERES",
                "OPERATIONS": "",
                "null": "",
                "TOTAUX DE\nL’EXERCICE\n3=2+1": "",
                "TOTAUX DE\nL’EXERCICE\nPRECEDENT\nAu 31/12/2022": ""
            },
            {
                "": "",
                "NATURE": "* Charges d'interêts",
                "OPERATIONS": "4.174.567,19",
                "null": "",
                "TOTAUX DE\nL’EXERCICE\n3=2+1": "4.174.567,19",
                "TOTAUX DE\nL’EXERCICE\nPRECEDENT\nAu 31/12/2022": "10.691.709,97"
            },
            {
                "": "",
                "NATURE": "* Pertes de change",
                "OPERATIONS": "2.456.930,73",
                "null": "",
                "TOTAUX DE\nL’EXERCICE\n3=2+1": "2.456.930,73",
                "TOTAUX DE\nL’EXERCICE\nPRECEDENT\nAu 31/12/2022": "5.498.880,66"
            },
            {
                "": "",
                "NATURE": "* Autres charges financières",
                "OPERATIONS": "",
                "null": "",
                "TOTAUX DE\nL’EXERCICE\n3=2+1": "",
                "TOTAUX DE\nL’EXERCICE\nPRECEDENT\nAu 31/12/2022": ""
            },
            {
                "": "",
                "NATURE": "* Dotations finacières",
                "OPERATIONS": "268.692,13",
                "null": "",
                "TOTAUX DE\nL’EXERCICE\n3=2+1": "268.692,13",
                "TOTAUX DE\nL’EXERCICE\nPRECEDENT\nAu 31/12/2022": "442.520,92"
            },
            {
                "": "Total V",
                "NATURE": "",
                "OPERATIONS": "6.900.190,05",
                "null": "",
                "TOTAUX DE\nL’EXERCICE\n3=2+1": "6.900.190,05",
                "TOTAUX DE\nL’EXERCICE\nPRECEDENT\nAu 31/12/2022": "16.633.111,55"
            },
            {
                "": "VI",
                "NATURE": "RESULTAT FINANCIER (IV-V)",
                "OPERATIONS": "",
                "null": "",
                "TOTAUX DE\nL’EXERCICE\n3=2+1": "11.261.609,80",
                "TOTAUX DE\nL’EXERCICE\nPRECEDENT\nAu 31/12/2022": "2.440.866,67"
            },
            {
                "": "VII",
                "NATURE": "RESULTAT COURANT (III+VI)",
                "OPERATIONS": "",
                "null": "",
                "TOTAUX DE\nL’EXERCICE\n3=2+1": "280.627.247,33",
                "TOTAUX DE\nL’EXERCICE\nPRECEDENT\nAu 31/12/2022": "289.155.120,86"
            },
            {
                "": "VII",
                "NATURE": "RESULTAT COURANT (reports)",
                "OPERATIONS": "",
                "null": "",
                "TOTAUX DE\nL’EXERCICE\n3=2+1": "280.627.247,33",
                "TOTAUX DE\nL’EXERCICE\nPRECEDENT\nAu 31/12/2022": "289.155.120,86"
            },
            {
                "": "VIII",
                "NATURE": "PRODUITS NON COURANTS",
                "OPERATIONS": "",
                "null": "",
                "TOTAUX DE\nL’EXERCICE\n3=2+1": "",
                "TOTAUX DE\nL’EXERCICE\nPRECEDENT\nAu 31/12/2022": ""
            },
            {
                "": "",
                "NATURE": "* Produits des cessions d'immobilisations",
                "OPERATIONS": "3.740.251,04",
                "null": "",
                "TOTAUX DE\nL’EXERCICE\n3=2+1": "3.740.251,04",
                "TOTAUX DE\nL’EXERCICE\nPRECEDENT\nAu 31/12/2022": "1.733.845,64"
            },
            {
                "": "",
                "NATURE": "* Subventions d'équilibre",
                "OPERATIONS": "",
                "null": "",
                "TOTAUX DE\nL’EXERCICE\n3=2+1": "",
                "TOTAUX DE\nL’EXERCICE\nPRECEDENT\nAu 31/12/2022": ""
            },
            {
                "": "",
                "NATURE": "* Reprises sur subventions d'investissement",
                "OPERATIONS": "",
                "null": "",
                "TOTAUX DE\nL’EXERCICE\n3=2+1": "",
                "TOTAUX DE\nL’EXERCICE\nPRECEDENT\nAu 31/12/2022": ""
            },
            {
                "": "",
                "NATURE": "* Autres produits non courants",
                "OPERATIONS": "8.941.733,48",
                "null": "",
                "TOTAUX DE\nL’EXERCICE\n3=2+1": "8.941.733,48",
                "TOTAUX DE\nL’EXERCICE\nPRECEDENT\nAu 31/12/2022": "10.149.165,64"
            },
            {
                "": "",
                "NATURE": "* Reprises non courantes ; transferts de charges",
                "OPERATIONS": "",
                "null": "",
                "TOTAUX DE\nL’EXERCICE\n3=2+1": "0,00",
                "TOTAUX DE\nL’EXERCICE\nPRECEDENT\nAu 31/12/2022": "0,00"
            },
            {
                "": "",
                "NATURE": "Total VIII",
                "OPERATIONS": "12.681.984,52",
                "null": "",
                "TOTAUX DE\nL’EXERCICE\n3=2+1": "12.681.984,52",
                "TOTAUX DE\nL’EXERCICE\nPRECEDENT\nAu 31/12/2022": "11.883.011,28"
            },
            {
                "": "IX",
                "NATURE": "CHARGES NON COURANTES",
                "OPERATIONS": "",
                "null": "",
                "TOTAUX DE\nL’EXERCICE\n3=2+1": "",
                "TOTAUX DE\nL’EXERCICE\nPRECEDENT\nAu 31/12/2022": ""
            },
            {
                "": "",
                "NATURE": "* Valeurs nettes d'amortissements des immobilisations cédées",
                "OPERATIONS": "2.704.356,00",
                "null": "",
                "TOTAUX DE\nL’EXERCICE\n3=2+1": "2.704.356,00",
                "TOTAUX DE\nL’EXERCICE\nPRECEDENT\nAu 31/12/2022": "891.407,78"
            },
            {
                "": "",
                "NATURE": "* Subventions accordées",
                "OPERATIONS": "",
                "null": "",
                "TOTAUX DE\nL’EXERCICE\n3=2+1": "",
                "TOTAUX DE\nL’EXERCICE\nPRECEDENT\nAu 31/12/2022": ""
            },
            {
                "": "",
                "NATURE": "* Autres charges non courantes",
                "OPERATIONS": "35.372.246,79",
                "null": "",
                "TOTAUX DE\nL’EXERCICE\n3=2+1": "35.372.246,79",
                "TOTAUX DE\nL’EXERCICE\nPRECEDENT\nAu 31/12/2022": "17.947.618,74"
            },
            {
                "": "",
                "NATURE": "* Dotations non courantes aux amortissements et aux provisions",
                "OPERATIONS": "5.000.000,00",
                "null": "",
                "TOTAUX DE\nL’EXERCICE\n3=2+1": "5.000.000,00",
                "TOTAUX DE\nL’EXERCICE\nPRECEDENT\nAu 31/12/2022": "3.000.000,00"
            },
            {
                "": "",
                "NATURE": "Total IX",
                "OPERATIONS": "43.076.602,79",
                "null": "",
                "TOTAUX DE\nL’EXERCICE\n3=2+1": "43.076.602,79",
                "TOTAUX DE\nL’EXERCICE\nPRECEDENT\nAu 31/12/2022": "21.839.026,52"
            },
            {
                "": "X",
                "NATURE": "RESULTAT NON COURANT (VIII-IX)",
                "OPERATIONS": "",
                "null": "",
                "TOTAUX DE\nL’EXERCICE\n3=2+1": "-30.394.618,27",
                "TOTAUX DE\nL’EXERCICE\nPRECEDENT\nAu 31/12/2022": "-9.956.015,24"
            },
            {
                "": "XI",
                "NATURE": "RESULTAT AVANT IMPÔTS (VII+X)",
                "OPERATIONS": "",
                "null": "",
                "TOTAUX DE\nL’EXERCICE\n3=2+1": "250.232.629,06",
                "TOTAUX DE\nL’EXERCICE\nPRECEDENT\nAu 31/12/2022": "279.199.105,62"
            },
            {
                "": "XII",
                "NATURE": "IMPÔTS SUR LES BENEFICES",
                "OPERATIONS": "89.928.493,00",
                "null": "",
                "TOTAUX DE\nL’EXERCICE\n3=2+1": "89.928.493,00",
                "TOTAUX DE\nL’EXERCICE\nPRECEDENT\nAu 31/12/2022": "92.045.306,00"
            },
            {
                "": "XIII",
                "NATURE": "RESULTAT NET (XI-XII)",
                "OPERATIONS": "",
                "null": "",
                "TOTAUX DE\nL’EXERCICE\n3=2+1": "160.304.136,06",
                "TOTAUX DE\nL’EXERCICE\nPRECEDENT\nAu 31/12/2022": "187.153.799,62"
            },
            {
                "": "",
                "NATURE": "TOTAL DES PRODUITS. (I+IV+VIII)",
                "OPERATIONS": "",
                "null": "",
                "TOTAUX DE\nL’EXERCICE\n3=2+1": "2.279.803.712,08",
                "TOTAUX DE\nL’EXERCICE\nPRECEDENT\nAu 31/12/2022": "2.154.119.575,98"
            },
            {
                "": "",
                "NATURE": "TOTAL DES CHARGES. (II+V+IX+XIII)",
                "OPERATIONS": "",
                "null": "",
                "TOTAUX DE\nL’EXERCICE\n3=2+1": "2.119.499.576,02",
                "TOTAUX DE\nL’EXERCICE\nPRECEDENT\nAu 31/12/2022": "1.966.965.776,36"
            },
            {
                "": "",
                "NATURE": "RESULTAT NET. (total des produits-total des charges)",
                "OPERATIONS": "",
                "null": "",
                "TOTAUX DE\nL’EXERCICE\n3=2+1": "160.304.136,06",
                "TOTAUX DE\nL’EXERCICE\nPRECEDENT\nAu 31/12/2022": "187.153.799,62"
            }
        ],
        [
            {
                "": "TNENAMREP\nTNEMECNANIF",
                "PASSIF": "CAPITAUX PROPRES",
                "Exercice": "1.148.138.116,33",
                "\"Exercice\nPrécedent 31/12/2022\"": "1.115.741.980,46"
            },
            {
                "": "",
                "PASSIF": "* Capital social ou personnel (1)",
                "Exercice": "102.326.400,00",
                "\"Exercice\nPrécedent 31/12/2022\"": "102.326.400,00"
            },
            {
                "": "",
                "PASSIF": "* Moins : actionnaires, capital souscrit non appelé\ncapital appelé\ndont versé.......",
                "Exercice": "",
                "\"Exercice\nPrécedent 31/12/2022\"": ""
            },
            {
                "": "",
                "PASSIF": "* Prime d'émission, de fusion, d'apport",
                "Exercice": "",
                "\"Exercice\nPrécedent 31/12/2022\"": ""
            },
            {
                "": "",
                "PASSIF": "* Ecarts de réevaluation",
                "Exercice": "",
                "\"Exercice\nPrécedent 31/12/2022\"": ""
            },
            {
                "": "",
                "PASSIF": "* Réserve légale",
                "Exercice": "10.232.640,00",
                "\"Exercice\nPrécedent 31/12/2022\"": "10.232.640,00"
            },
            {
                "": "",
                "PASSIF": "* Autres réserves",
                "Exercice": "8.552.273,80",
                "\"Exercice\nPrécedent 31/12/2022\"": "8.552.273,80"
            },
            {
                "": "",
                "PASSIF": "* Report à nouveau (2)",
                "Exercice": "866.722.666,47",
                "\"Exercice\nPrécedent 31/12/2022\"": "807.476.867,04"
            },
            {
                "": "",
                "PASSIF": "* Résultat nets en instance d'affectation (2)",
                "Exercice": "",
                "\"Exercice\nPrécedent 31/12/2022\"": ""
            },
            {
                "": "",
                "PASSIF": "* Résultat net de l'exercice (2)",
                "Exercice": "160.304.136,06",
                "\"Exercice\nPrécedent 31/12/2022\"": "187.153.799,62"
            },
            {
                "": "",
                "PASSIF": "Total des capitaux propres (A)",
                "Exercice": "1.148.138.116,33",
                "\"Exercice\nPrécedent 31/12/2022\"": "1.115.741.980,46"
            },
            {
                "": "",
                "PASSIF": "CAPITAUX PROPRES ASSIMILES (B)",
                "Exercice": "",
                "\"Exercice\nPrécedent 31/12/2022\"": ""
            },
            {
                "": "",
                "PASSIF": "* Subvention d'investissement",
                "Exercice": "",
                "\"Exercice\nPrécedent 31/12/2022\"": ""
            },
            {
                "": "",
                "PASSIF": "* Provisions réglementées",
                "Exercice": "",
                "\"Exercice\nPrécedent 31/12/2022\"": ""
            },
            {
                "": "",
                "PASSIF": "DETTES DE FINANCEMENT (C)",
                "Exercice": "122.271.803,29",
                "\"Exercice\nPrécedent 31/12/2022\"": ""
            },
            {
                "": "",
                "PASSIF": "* Emprunts obligataires",
                "Exercice": "122.271.803,29",
                "\"Exercice\nPrécedent 31/12/2022\"": ""
            },
            {
                "": "",
                "PASSIF": "* Autres dettes de financement",
                "Exercice": "",
                "\"Exercice\nPrécedent 31/12/2022\"": ""
            },
            {
                "": "",
                "PASSIF": "PROVISIONS DURABLES POUR RISQUES ET CHARGES (D)",
                "Exercice": "",
                "\"Exercice\nPrécedent 31/12/2022\"": ""
            },
            {
                "": "",
                "PASSIF": "* Provisions pour risques",
                "Exercice": "",
                "\"Exercice\nPrécedent 31/12/2022\"": ""
            },
            {
                "": "",
                "PASSIF": "* Provisions pour charges",
                "Exercice": "",
                "\"Exercice\nPrécedent 31/12/2022\"": ""
            },
            {
                "": "",
                "PASSIF": "ECARTS DE CONVERSION-PASSIF (E)",
                "Exercice": "",
                "\"Exercice\nPrécedent 31/12/2022\"": ""
            },
            {
                "": "",
                "PASSIF": "* Augmentation des créances immobilisées",
                "Exercice": "",
                "\"Exercice\nPrécedent 31/12/2022\"": ""
            },
            {
                "": "",
                "PASSIF": "* Diminution des dettes de financement",
                "Exercice": "",
                "\"Exercice\nPrécedent 31/12/2022\"": ""
            },
            {
                "": "",
                "PASSIF": "Total I(A+B+C+D+E)",
                "Exercice": "1.270.409.919,62",
                "\"Exercice\nPrécedent 31/12/2022\"": "1.115.741.980,46"
            },
            {
                "": "TNALUCRIC\nFISSAP",
                "PASSIF": "DETTES DU PASSIF CIRCULANT (F)",
                "Exercice": "501.633.935,47",
                "\"Exercice\nPrécedent 31/12/2022\"": "558.067.774,48"
            },
            {
                "": "",
                "PASSIF": "* Fournisseurs et comptes rattachés",
                "Exercice": "233.315.994,02",
                "\"Exercice\nPrécedent 31/12/2022\"": "298.403.999,58"
            },
            {
                "": "",
                "PASSIF": "* Clients créditeurs, avances et acomptes",
                "Exercice": "43.689.673,45",
                "\"Exercice\nPrécedent 31/12/2022\"": "54.171.780,69"
            },
            {
                "": "",
                "PASSIF": "* Personnel",
                "Exercice": "17.292.737,05",
                "\"Exercice\nPrécedent 31/12/2022\"": "17.418.918,29"
            },
            {
                "": "",
                "PASSIF": "* Organisme sociaux",
                "Exercice": "9.950.951,62",
                "\"Exercice\nPrécedent 31/12/2022\"": "10.107.151,32"
            },
            {
                "": "",
                "PASSIF": "* Etat",
                "Exercice": "40.085.353,76",
                "\"Exercice\nPrécedent 31/12/2022\"": "43.251.896,07"
            },
            {
                "": "",
                "PASSIF": "* Comptes d'associés",
                "Exercice": "9.790.000,00",
                "\"Exercice\nPrécedent 31/12/2022\"": "415.000,00"
            },
            {
                "": "",
                "PASSIF": "* Autres créanciers",
                "Exercice": "26.365.808,37",
                "\"Exercice\nPrécedent 31/12/2022\"": "14.327.009,37"
            },
            {
                "": "",
                "PASSIF": "* Comptes de regularisation passif",
                "Exercice": "121.143.417,20",
                "\"Exercice\nPrécedent 31/12/2022\"": "119.972.019,16"
            },
            {
                "": "",
                "PASSIF": "AUTRES PROVISIONS POUR RISQUES ET CHARGES (G)",
                "Exercice": "27.036.358,34",
                "\"Exercice\nPrécedent 31/12/2022\"": "24.257.873,68"
            },
            {
                "": "",
                "PASSIF": "ECARTS DE CONVERSION-PASSIF (Elements circulants) (H)",
                "Exercice": "65.062,20",
                "\"Exercice\nPrécedent 31/12/2022\"": "301.532,99"
            },
            {
                "": "",
                "PASSIF": "Total II (F+G+H)",
                "Exercice": "528.735.356,01",
                "\"Exercice\nPrécedent 31/12/2022\"": "582.627.181,15"
            },
            {
                "": "EIREROSÉRT",
                "PASSIF": "TRESORERIE-PASSIF",
                "Exercice": "271.194.514,57",
                "\"Exercice\nPrécedent 31/12/2022\"": ""
            },
            {
                "": "",
                "PASSIF": "* Crédits d'escompte",
                "Exercice": "",
                "\"Exercice\nPrécedent 31/12/2022\"": ""
            },
            {
                "": "",
                "PASSIF": "* Crédits de trésorerie",
                "Exercice": "170.000.000,00",
                "\"Exercice\nPrécedent 31/12/2022\"": ""
            },
            {
                "": "",
                "PASSIF": "* Banques de régularisation",
                "Exercice": "101.194.514,57",
                "\"Exercice\nPrécedent 31/12/2022\"": ""
            },
            {
                "": "",
                "PASSIF": "Total III",
                "Exercice": "271.194.514,57",
                "\"Exercice\nPrécedent 31/12/2022\"": ""
            },
            {
                "": "",
                "PASSIF": "TOTAL GENERAL I+II+III",
                "Exercice": "2.070.339.790,20",
                "\"Exercice\nPrécedent 31/12/2022\"": "1.698.369.161,61"
            }
        ],
        [
            {
                "COMPTE DE RESULTAT\n(En KMAD)": "",
                "31-déc-2023": "",
                "Proforma\n31 décembre 2022": "2 156 600",
                "31 décembre 2022": ""
            },
            {
                "COMPTE DE RESULTAT\n(En KMAD)": "",
                "31-déc-2023": "",
                "Proforma\n31 décembre 2022": "2 135 819",
                "31 décembre 2022": ""
            },
            {
                "COMPTE DE RESULTAT\n(En KMAD)": "",
                "31-déc-2023": "",
                "Proforma\n31 décembre 2022": "323",
                "31 décembre 2022": ""
            },
            {
                "COMPTE DE RESULTAT\n(En KMAD)": "",
                "31-déc-2023": "",
                "Proforma\n31 décembre 2022": "-",
                "31 décembre 2022": ""
            },
            {
                "COMPTE DE RESULTAT\n(En KMAD)": "",
                "31-déc-2023": "",
                "Proforma\n31 décembre 2022": "4 488",
                "31 décembre 2022": ""
            },
            {
                "COMPTE DE RESULTAT\n(En KMAD)": "",
                "31-déc-2023": "",
                "Proforma\n31 décembre 2022": "16 616",
                "31 décembre 2022": ""
            },
            {
                "COMPTE DE RESULTAT\n(En KMAD)": "",
                "31-déc-2023": "",
                "Proforma\n31 décembre 2022": "1 872 906",
                "31 décembre 2022": ""
            },
            {
                "COMPTE DE RESULTAT\n(En KMAD)": "",
                "31-déc-2023": "",
                "Proforma\n31 décembre 2022": "1 616 254",
                "31 décembre 2022": ""
            },
            {
                "COMPTE DE RESULTAT\n(En KMAD)": "",
                "31-déc-2023": "",
                "Proforma\n31 décembre 2022": "70 201",
                "31 décembre 2022": ""
            },
            {
                "COMPTE DE RESULTAT\n(En KMAD)": "",
                "31-déc-2023": "",
                "Proforma\n31 décembre 2022": "3 549",
                "31 décembre 2022": ""
            },
            {
                "COMPTE DE RESULTAT\n(En KMAD)": "",
                "31-déc-2023": "",
                "Proforma\n31 décembre 2022": "135 653",
                "31 décembre 2022": ""
            },
            {
                "COMPTE DE RESULTAT\n(En KMAD)": "",
                "31-déc-2023": "",
                "Proforma\n31 décembre 2022": "2 453",
                "31 décembre 2022": ""
            },
            {
                "COMPTE DE RESULTAT\n(En KMAD)": "",
                "31-déc-2023": "",
                "Proforma\n31 décembre 2022": "44 795",
                "31 décembre 2022": ""
            },
            {
                "COMPTE DE RESULTAT\n(En KMAD)": "",
                "31-déc-2023": "",
                "Proforma\n31 décembre 2022": "283 694",
                "31 décembre 2022": ""
            },
            {
                "COMPTE DE RESULTAT\n(En KMAD)": "",
                "31-déc-2023": "",
                "Proforma\n31 décembre 2022": "19 126",
                "31 décembre 2022": ""
            },
            {
                "COMPTE DE RESULTAT\n(En KMAD)": "",
                "31-déc-2023": "",
                "Proforma\n31 décembre 2022": "12 924",
                "31 décembre 2022": ""
            },
            {
                "COMPTE DE RESULTAT\n(En KMAD)": "",
                "31-déc-2023": "",
                "Proforma\n31 décembre 2022": "6 202",
                "31 décembre 2022": ""
            },
            {
                "COMPTE DE RESULTAT\n(En KMAD)": "",
                "31-déc-2023": "",
                "Proforma\n31 décembre 2022": "12 053",
                "31 décembre 2022": ""
            },
            {
                "COMPTE DE RESULTAT\n(En KMAD)": "",
                "31-déc-2023": "",
                "Proforma\n31 décembre 2022": "19 035",
                "31 décembre 2022": ""
            },
            {
                "COMPTE DE RESULTAT\n(En KMAD)": "",
                "31-déc-2023": "",
                "Proforma\n31 décembre 2022": "- 6 982",
                "31 décembre 2022": ""
            },
            {
                "COMPTE DE RESULTAT\n(En KMAD)": "",
                "31-déc-2023": "",
                "Proforma\n31 décembre 2022": "282 914",
                "31 décembre 2022": ""
            },
            {
                "COMPTE DE RESULTAT\n(En KMAD)": "",
                "31-déc-2023": "",
                "Proforma\n31 décembre 2022": "92 257",
                "31 décembre 2022": ""
            },
            {
                "COMPTE DE RESULTAT\n(En KMAD)": "",
                "31-déc-2023": "",
                "Proforma\n31 décembre 2022": "1 268",
                "31 décembre 2022": ""
            },
            {
                "COMPTE DE RESULTAT\n(En KMAD)": "",
                "31-déc-2023": "",
                "Proforma\n31 décembre 2022": "",
                "31 décembre 2022": ""
            },
            {
                "COMPTE DE RESULTAT\n(En KMAD)": "",
                "31-déc-2023": "",
                "Proforma\n31 décembre 2022": "",
                "31 décembre 2022": ""
            },
            {
                "COMPTE DE RESULTAT\n(En KMAD)": "",
                "31-déc-2023": "",
                "Proforma\n31 décembre 2022": "189 389",
                "31 décembre 2022": ""
            },
            {
                "COMPTE DE RESULTAT\n(En KMAD)": "Résultat net part du Groupe",
                "31-déc-2023": "157 773",
                "Proforma\n31 décembre 2022": "189 389",
                "31 décembre 2022": "193 392"
            }
        ],
        [
            {
                "null": "Méthode\nde consoli-\ndation",
                "31-déc-2023": "% d’intérêt",
                "31-déc-2022": "% d’intérêt"
            },
            {
                "null": "I.G",
                "31-déc-2023": "100",
                "31-déc-2022": "100"
            },
            {
                "null": "*",
                "31-déc-2023": "100",
                "31-déc-2022": "*"
            },
            {
                "null": "*",
                "31-déc-2023": "100",
                "31-déc-2022": "*"
            },
            {
                "null": "*",
                "31-déc-2023": "100",
                "31-déc-2022": "*"
            }
        ],
        [
            {
                "ACTIF (En KMAD)": "",
                "31-déc-2023": "",
                "Proforma\n31 décembre 2022": "129 444",
                "31 décembre 2022": ""
            },
            {
                "ACTIF (En KMAD)": "",
                "31-déc-2023": "",
                "Proforma\n31 décembre 2022": "10 296",
                "31 décembre 2022": ""
            },
            {
                "ACTIF (En KMAD)": "",
                "31-déc-2023": "",
                "Proforma\n31 décembre 2022": "477 274",
                "31 décembre 2022": ""
            },
            {
                "ACTIF (En KMAD)": "",
                "31-déc-2023": "",
                "Proforma\n31 décembre 2022": "531",
                "31 décembre 2022": ""
            },
            {
                "ACTIF (En KMAD)": "",
                "31-déc-2023": "",
                "Proforma\n31 décembre 2022": "7 544",
                "31 décembre 2022": ""
            },
            {
                "ACTIF (En KMAD)": "",
                "31-déc-2023": "",
                "Proforma\n31 décembre 2022": "625 089",
                "31 décembre 2022": ""
            },
            {
                "ACTIF (En KMAD)": "",
                "31-déc-2023": "",
                "Proforma\n31 décembre 2022": "568 761",
                "31 décembre 2022": ""
            },
            {
                "ACTIF (En KMAD)": "",
                "31-déc-2023": "",
                "Proforma\n31 décembre 2022": "24 475",
                "31 décembre 2022": ""
            },
            {
                "ACTIF (En KMAD)": "",
                "31-déc-2023": "",
                "Proforma\n31 décembre 2022": "369 631",
                "31 décembre 2022": ""
            },
            {
                "ACTIF (En KMAD)": "",
                "31-déc-2023": "",
                "Proforma\n31 décembre 2022": "875",
                "31 décembre 2022": ""
            },
            {
                "ACTIF (En KMAD)": "",
                "31-déc-2023": "",
                "Proforma\n31 décembre 2022": "35 492",
                "31 décembre 2022": ""
            },
            {
                "ACTIF (En KMAD)": "",
                "31-déc-2023": "",
                "Proforma\n31 décembre 2022": "26 617",
                "31 décembre 2022": ""
            },
            {
                "ACTIF (En KMAD)": "",
                "31-déc-2023": "",
                "Proforma\n31 décembre 2022": "8 244",
                "31 décembre 2022": ""
            },
            {
                "ACTIF (En KMAD)": "",
                "31-déc-2023": "",
                "Proforma\n31 décembre 2022": "203 375",
                "31 décembre 2022": ""
            },
            {
                "ACTIF (En KMAD)": "",
                "31-déc-2023": "",
                "Proforma\n31 décembre 2022": "1 237 469",
                "31 décembre 2022": ""
            },
            {
                "ACTIF (En KMAD)": "",
                "31-déc-2023": "",
                "Proforma\n31 décembre 2022": "74 568",
                "31 décembre 2022": ""
            },
            {
                "ACTIF (En KMAD)": "TOTAL ACTIF",
                "31-déc-2023": "2 254 444",
                "Proforma\n31 décembre 2022": "1 937 126",
                "31 décembre 2022": "1 790 930"
            }
        ],
        [
            {
                "": "",
                "31 décembre 2022": "157 773",
                "31-déc-2022": ""
            },
            {
                "": "",
                "31 décembre 2022": "24 095",
                "31-déc-2022": ""
            },
            {
                "": "",
                "31 décembre 2022": "-",
                "31-déc-2022": ""
            },
            {
                "": "",
                "31 décembre 2022": "-",
                "31-déc-2022": ""
            },
            {
                "": "",
                "31 décembre 2022": "181 869",
                "31-déc-2022": ""
            },
            {
                "": "",
                "31 décembre 2022": "-",
                "31-déc-2022": ""
            },
            {
                "": "",
                "31 décembre 2022": "181 869",
                "31-déc-2022": ""
            },
            {
                "": "",
                "31 décembre 2022": "- 271 956",
                "31-déc-2022": ""
            },
            {
                "": "",
                "31 décembre 2022": "66 027",
                "31-déc-2022": ""
            },
            {
                "": "",
                "31 décembre 2022": "-24 060",
                "31-déc-2022": ""
            },
            {
                "": "",
                "31 décembre 2022": "7 385",
                "31-déc-2022": ""
            },
            {
                "": "",
                "31 décembre 2022": "- 4 843",
                "31-déc-2022": ""
            },
            {
                "": "",
                "31 décembre 2022": "- 250 478",
                "31-déc-2022": ""
            },
            {
                "": "",
                "31 décembre 2022": "-",
                "31-déc-2022": ""
            },
            {
                "": "",
                "31 décembre 2022": "-",
                "31-déc-2022": ""
            },
            {
                "": "",
                "31 décembre 2022": "-247 936",
                "31-déc-2022": ""
            },
            {
                "": "",
                "31 décembre 2022": "-",
                "31-déc-2022": ""
            },
            {
                "": "",
                "31 décembre 2022": "- 127 908",
                "31-déc-2022": ""
            },
            {
                "": "",
                "31 décembre 2022": "121 293",
                "31-déc-2022": ""
            },
            {
                "": "",
                "31 décembre 2022": "- 6 615",
                "31-déc-2022": ""
            },
            {
                "": "VARIATION DE TRÉSORERIE NETTE",
                "31 décembre 2022": "- 278 611",
                "31-déc-2022": "5 512"
            },
            {
                "": "",
                "31 décembre 2022": "40 230",
                "31-déc-2022": ""
            },
            {
                "": "",
                "31 décembre 2022": "- 238 381",
                "31-déc-2022": ""
            }
        ],
        [
            {
                "PASSIF (En KMAD)": "",
                "31-déc-2023": "",
                "Proforma\n31 décembre 2022": "102 326",
                "31 décembre 2022": ""
            },
            {
                "PASSIF (En KMAD)": "",
                "31-déc-2023": "",
                "Proforma\n31 décembre 2022": "826 850",
                "31 décembre 2022": ""
            },
            {
                "PASSIF (En KMAD)": "",
                "31-déc-2023": "",
                "Proforma\n31 décembre 2022": "189 389",
                "31 décembre 2022": ""
            },
            {
                "PASSIF (En KMAD)": "",
                "31-déc-2023": "",
                "Proforma\n31 décembre 2022": "1 118 566",
                "31 décembre 2022": ""
            },
            {
                "PASSIF (En KMAD)": "",
                "31-déc-2023": "",
                "Proforma\n31 décembre 2022": "-",
                "31 décembre 2022": ""
            },
            {
                "PASSIF (En KMAD)": "",
                "31-déc-2023": "",
                "Proforma\n31 décembre 2022": "220 362",
                "31 décembre 2022": ""
            },
            {
                "PASSIF (En KMAD)": "",
                "31-déc-2023": "",
                "Proforma\n31 décembre 2022": "3 082",
                "31 décembre 2022": ""
            },
            {
                "PASSIF (En KMAD)": "",
                "31-déc-2023": "",
                "Proforma\n31 décembre 2022": "223 444",
                "31 décembre 2022": ""
            },
            {
                "PASSIF (En KMAD)": "",
                "31-déc-2023": "",
                "Proforma\n31 décembre 2022": "304 182",
                "31 décembre 2022": ""
            },
            {
                "PASSIF (En KMAD)": "",
                "31-déc-2023": "",
                "Proforma\n31 décembre 2022": "54 467",
                "31 décembre 2022": ""
            },
            {
                "PASSIF (En KMAD)": "",
                "31-déc-2023": "",
                "Proforma\n31 décembre 2022": "28 809",
                "31 décembre 2022": ""
            },
            {
                "PASSIF (En KMAD)": "",
                "31-déc-2023": "",
                "Proforma\n31 décembre 2022": "49 113",
                "31 décembre 2022": ""
            },
            {
                "PASSIF (En KMAD)": "",
                "31-déc-2023": "",
                "Proforma\n31 décembre 2022": "119 977",
                "31 décembre 2022": ""
            },
            {
                "PASSIF (En KMAD)": "",
                "31-déc-2023": "",
                "Proforma\n31 décembre 2022": "23 815",
                "31 décembre 2022": ""
            },
            {
                "PASSIF (En KMAD)": "",
                "31-déc-2023": "",
                "Proforma\n31 décembre 2022": "425",
                "31 décembre 2022": ""
            },
            {
                "PASSIF (En KMAD)": "",
                "31-déc-2023": "",
                "Proforma\n31 décembre 2022": "14 327",
                "31 décembre 2022": ""
            },
            {
                "PASSIF (En KMAD)": "",
                "31-déc-2023": "",
                "Proforma\n31 décembre 2022": "595 116",
                "31 décembre 2022": ""
            },
            {
                "PASSIF (En KMAD)": "",
                "31-déc-2023": "",
                "Proforma\n31 décembre 2022": "-",
                "31 décembre 2022": ""
            },
            {
                "PASSIF (En KMAD)": "TOTAL PASSIF",
                "31-déc-2023": "2 254 444",
                "Proforma\n31 décembre 2022": "1 937 126",
                "31 décembre 2022": "1 790 930"
            }
        ],
        [
            {
                "(En KMAD)": "",
                "Capital": "102 326",
                "Primes\nd'émission": "-",
                "Réserves\nconsolidées": "824 884",
                "Résultat\nconsolidé\npart du\ngroupe": "193 392",
                "Total": "1 120 603"
            },
            {
                "(En KMAD)": "",
                "Capital": "-",
                "Primes\nd'émission": "-",
                "Réserves\nconsolidées": "193 392",
                "Résultat\nconsolidé\npart du\ngroupe": "-193 392",
                "Total": "-"
            },
            {
                "(En KMAD)": "",
                "Capital": "-",
                "Primes\nd'émission": "-",
                "Réserves\nconsolidées": "-127 908",
                "Résultat\nconsolidé\npart du\ngroupe": "-",
                "Total": "-127 908"
            },
            {
                "(En KMAD)": "",
                "Capital": "-",
                "Primes\nd'émission": "-",
                "Réserves\nconsolidées": "-",
                "Résultat\nconsolidé\npart du\ngroupe": "157 773",
                "Total": "157 773"
            },
            {
                "(En KMAD)": "",
                "Capital": "-",
                "Primes\nd'émission": "-",
                "Réserves\nconsolidées": "-2 037",
                "Résultat\nconsolidé\npart du\ngroupe": "-",
                "Total": "-2 037"
            },
            {
                "(En KMAD)": "Capitaux propres au 31/12/2023",
                "Capital": "102 326",
                "Primes\nd'émission": "-",
                "Réserves\nconsolidées": "888 332",
                "Résultat\nconsolidé\npart du\ngroupe": "157 773",
                "Total": "1 148 431"
            }
        ]
    ]
}