{
    "text": "TE\nRV\nI\nL\nRE\nI\nC\nNA\nNI\nF\nSREICNANIF\nSTATLUSÉR\nwww creditdumaroc ma\nJUIN 2024\nRÉSULTATS CONSOLIDÉS\nAU 30 JUIN 2024\nDES RÉSULTATS EN CROISSANCE CONTINUE PORTÉS PAR\nUN PLAN D’AMÉLIORATION DE LA PERFORMANCE GLOBALE\nDE LA BANQUE\nLe Conseil de Surveillance de Crédit du Maroc s’est réuni le 26 juillet 2024, sous la présidence de Monsieur\nMohamed Hassan BENSALAH, pour examiner l’activité et les comptes arrêtés au 30 juin 2024.\nNETTE PROGRESSION DES PERFORMANCES\nENCOURS CRÉDITS ENCOURS RESSOURCES BILAN COMMERCIALES ET DES INDICATEURS FINANCIERS\n+7,9% +4,8%\nCROISSANCE SOUTENUE DES CREDITS +7,9 %\n54 911 52 288 54 778 Crédit du Maroc confirme son engagement d’accom-\n50 902\npagner les efforts du Royaume en matière de dévelop-\n+7,9 % +4,8% pement des investissements avec des emplois clientèle\nqui ont augmenté de 7,9 % sur un an, pour se hisser à\n54 911 MDH.\nCette progression est notamment soutenue par les\ncrédits aux entreprises. Ces derniers qui ont atteint,\nà fin juin 2024, 32 727 MDH, affichent une hausse\nJuin 23 Juin 24 Juin 23 Juin 24\nsignificative de 13,5 %, attribuable aux performances\nEn millions de dirhams\ndu crédit aux promoteurs immobiliers (+40 %), du\ncrédit-bail (+33,7 %), du crédit à l’équipement (+27,2 %)\nCRÉDITS HABITAT CRÉDIT À LA CONSOMMATION et du crédit court terme (+3,1 %).\n+3,6% +6,7% Pour leur part, les crédits aux ménages ont évolué de\n17 203 4,1 % et se situent à 21 063 MDH, bénéficiant de la\n16 609 bonne tenue tant du crédit à la consommation que du\ncrédit à l’habitat qui se sont appréciés respectivement\n+3,6 %\nde 6,7 % et de 3,6 %.\n3 619 3 860 BONNE DYNAMIQUE DE LA COLLECTE BILAN +4,8 %\n+6,7%\nA fin juin 2024, les ressources bilan se sont améliorées,\nsur les douze derniers mois, de 4,8 % à 54 778 MDH.\nJuin 23 Juin 24 Juin 23 Juin 24\nCette évolution positive a été portée par les ressources\nEn millions de dirhams\nà vue et les ressources d’épargne qui ont progressé\nrespectivement de 6,2 % et de 2,4 % pour s’établir à\n38 829 MDH et à 10 192 MDH. Les dépôts à terme se\nRESSOURCES À VUE RESSOURCES D’ÉPARGNE sont élevés, quant à eux, à 4 458 MDH, soit en hausse\n+6,2% +2,4% de 31,8 %.\n38 829\n36 572 POURSUITE DE LA PROGRESSION DU PRODUIT NET\nBANCAIRE +12,6 %\n+6,2%\nLe produit net bancaire consolidé s’est élevé, au titre\ndu premier semestre 2024, à 1 606 MDH, enregistrant\n10 192\n9 952 une progression de 12,6 % par rapport au premier\n+2,4%\nsemestre 2023. Cette performance résulte de la\ncontribution positive de l’ensemble des lignes métiers\nJuin 23 Juin 24 Juin 23 Juin 24 de la banque :\nEn millions de dirhams - la marge nette d’intérêt a atteint 1 186 MDH, en\nhausse de 9,6 %, bénéficiant du dynamisme continu\nde l’activité commerciale et du renforcement du fonds\nde commerce ;\nPRODUIT NET BANCAIRE CHARGES D’EXPLOITATION\n- la marge sur commissions s’est établie à 246 MDH,\n+12,6% +2,4%\nen évolution de 9,1 %, profitant de la croissance\n1 606 des revenus des filières spécialisées en monétique,\n1 426\ncommerce international, banque transactionnelle et\ncash management ;\n+12,6% 782\n726 - le résultat des opérations de marché a atteint\n+2,4%\n219 MDH, en hausse de 30,2 %.\nD’autre part, les filiales de Crédit du Maroc ont\ncontribué positivement au PNB global, avec un revenu\nJuin 23 Juin 24 Juin 23 Juin 24 de l’ordre de 105 MDH, en hausse de 8,3 % par rapport\nEn millions de dirhams au premier semestre 2023.\n2\nwww.creditdumaroc.ma\nPERFORMANCE NOTABLE DU RÉSULTAT BRUT\nRÉSULTAT BRUT D’EXPLOITATION COÛT DU RISQUE\nD’EXPLOITATION +17,6 %\n+17,6% -32,6%\nPorté par l’évolution positive du PNB consolidé, le\nrésultat brut d’exploitation s’est renforcé de 17,6 % à\n824\n824 MDH au premier semestre 2024. Le coefficient\n700\nd’exploitation a connu une amélioration de 218 points\nde base pour se situer à 48,7 %.\n+17,6%\nA noter que Crédit du Maroc a engagé sur le premier\nsemestre 2024 un montant total de 133 MDH 166 -32,6%\n112\nd’investissements dont l’essentiel a porté sur le\nrenforcement des performances de la plateforme\nJuin 23 Juin 24 Juin 23 Juin 24\ntechnologique de la banque.\nEn millions de dirhams\nNET REPLI DU COÛT DU RISQUE\nLe coût du risque consolidé s’est replié de 32,6 %\nà 112 MDH, résultat d’une sinistralité maîtrisée et\nRÉSULTAT NET RATIO DE SOLVABILITÉ\nanticipée. Dans le cadre de sa politique de gestion PART DU GROUPE\nprudente et anticipative des risques, Crédit du Maroc\n+36,8% min 12 %\naffiche un taux de couverture de 85,3 % à fin juin 2024,\nen renforcement de 156 points de base par rapport au\npremier semestre 2023. 391\n286\nLes créances en souffrance ont limité leur croissance\nà 2,1 % pour se situer à 4 080 MDH, avec un taux de\n+36,8%\ncréances douteuses et litigieuses qui s’est amélioré de\n42 bps à 7,4 %. 14,19 % 13,36%\nHAUSSE DE LA CAPACITÉ BÉNÉFICIAIRE +36,8 %\nJuin 23 Juin 24 Juin 23 Juin 24\nLe résultat net part du groupe Crédit du Maroc s’est\nélevé à 391 MDH, en hausse de 36,8 % par rapport\nEn millions de dirhams\nau premier semestre 2023, bénéficiant d’une bonne\ndynamique commerciale et d’une évolution favorable\ndu coût du risque.\nFINALISATION DE L’AUTONOMISATION DE LA BANQUE APRÉS LE RACHAT DE LA TOTALITÉ DES PARTS\nDÉTENUES PAR CRÉDIT AGRICOLE S.A. DANS LE GROUPE CRÉDIT DU MAROC\nSelon les accords conclus en décembre 2022, le plan de transition de la banque s’est déroulé conformément aux\nengagements pris par le Groupe Holmarcom et Crédit Agricole S.A., ce qui a donné lieu à l’autonomisation complète\nde Crédit du Maroc, tant au niveau de ses activités qu’au niveau de son fonctionnement opérationnel et du système\nd’information.\nPar ailleurs, la sortie programmée de Crédit Agricole S.A. du tour de table de la banque a été finalisée lors du premier\nsemestre 2024, après la réalisation de ces opérations :\n- le 15 mai 2024 , Crédit du Maroc a procédé à l’acquisition de 33,33 % du capital social et des droits de vote de\nCrédit du Maroc Leasing et Factoring détenus par Crédit Agricole Leasing & Factoring. Crédit du Maroc détient\ndésormais 100 % du capital de Crédit du Maroc Leasing et Factoring ;\n- le 7 juin 2024, le groupe Holmarcom, via Holmarcom Finance Company, a procédé à l’acquisition de la seconde\ntranche de la participation détenue par Crédit Agricole S.A. dans Crédit du Maroc, portant sur 15 % du capital et\ndes droits de vote de la banque. À la suite de cette opération, le groupe Holmarcom détient 78,7 % du capital de\nCrédit du Maroc.\nPOURSUITE DU DÉPLOIEMENT DE LA VISION STRATÉGIQUE DU GROUPE HOLMARCOM\nSous l’égide de son nouvel actionnaire, Crédit du Maroc s’est fixé des objectifs de croissance ambitieux dans le cadre\nde son plan quinquennal, en ligne avec la stratégie mise en place par le Groupe Holmarcom pour un développement\ndurable et responsable.\nPorté par le nouveau positionnement autour de la famille, le plan vise l’accélération de la dynamique commerciale\nsupportée essentiellement par la refonte de l’offre et des parcours clients, l’accélération de la transformation digitale\net l’amélioration continue du service client.\nPour accompagner cette nouvelle dynamique, la banque mène un renforcement continu de son modèle opérationnel\nainsi que de son système de gouvernance et de pilotage des risques et de la conformité et s’appuie sur une équipe\ndynamique et mobilisée autour de la vision, des ambitions et des valeurs du Groupe Holmarcom.\nListe des communiqués de presse publiés au 30 juin 2024 :\n• IFC et Crédit du Maroc signent un accord pour la mise en place d’une ligne de financement en faveur de Crédit du Maroc\nde 1 milliard de dirhams.\n• Présentation des résultats annuels de Crédit du Maroc au 31 décembre 2023.\n• Les résultats financiers au 31 mars 2024.\n• Crédit du Maroc organise une rencontre autour du thème : « Les nouveaux mécanismes pour accélérer vos investissements ».\n• Crédit du Maroc et Mastercard s’associent pour contribuer à faire avancer la transformation numérique au Maroc.\nContact Presse - Communication financière : Mouna Benrhanem - mouna.benrhanem@cdm.ma\nSite web : wwww.creditdumaroc.ma – Centre de Relation Clients : 3232\nLien pour télécharger le livret financier : https://www.creditdumaroc.ma/sites/default/files/livret financier resultats au 30 juin 2024.pdf\n3\nÉTATS FINANCIERS CONSOLIDÉS IFRS\nBILAN CONSOLIDÉ IFRS\nAU 30 JUIN 2024\n(En milliers de DH) (En milliers de DH)\nACTIF CONSOLIDÉ NOTES 30/06/2024 31/12/2023 PASSIF CONSOLIDÉ NOTES 30/06/2024 31/12/2023\nV dea sle cu hr ès qe un\ne\nc sa pis os se t,\na\nB ua xnques centrales, Trésor public, Service 1 848 172 2 265 791 B poa sn tq au ue xs centrakes, Trésor public, Service des chèques 844 884\nPassifs financiers à la juste valeur par résultat 3.9 6 901 15 984\nActifs financiers à la juste valeur par résultat 3.5 3 714 436 2 596 910\nPassifs financiers détenus à des fins de transaction 3.9 6 901 15 984\nActifs financiers détenus à des fins de transactions 3.5 3 491 844 2 366 801\nPassifs financiers à la juste valeur par résultat sur option - -\nAutres actifs financiers à la juste valeur par résultat 3.5 222 592 230 109 Instruments dérivés de couverture - -\nInstruments dérivés de couverture - - Dettes envers les Etablissements de crédit et assimilés 3.1 1 470 234 1 137 272\nActifs financiers à la juste valeur par capitaux propres 3.3 1 608 810 1 054 279 Dettes envers la clientèle 3.1 54 778 179 51 755 426\nInstruments de dettes comptabilisés à la juste valeur par Titres de créance émis 3.1 3 501 597 3 424 402\n3.3 1 608 810 1 054 279\ncapitaux prores recyclables\nPassifs d'impôt exigibles 3.8 100 429 125 097\nInstruments de capitaux propres comptabilisés à la juste\n- - Passifs d'impôt différé 3.8 14 664 17 885\nvaleur par capitaux propres non recyclables\nComptes de régularisation et autres passifs 3.4 2 292 820 1 891 556\nTitres au coût amorti 3.2 909 118 1 397 240\nDettes liées aux actifs non courants destinés à être cédés - -\nPrêts et créances sur les Etablissements de crédit et\nassimilés,au coût amorti 3.2 5 099 485 6 012 399 Provisions techniques des contrats d'assurance - -\nProvisions 3.7 555 324 565 955\nPrêts et créances sur la clientèle, au coût amorti 3.2 54 911 005 51 061 669\nSubventions et fonds assimilés - -\nEcart de réévaluation actif des portefeuilles couvert en taux - -\nDettes subordonnées et fonds spéciaux de garantie 1 275 929 1 250 969\nPlacements des activités d'assurance - -\nCapitaux propres 7 048 980 7 079 907\nActifs d'Impôt Exigible 3.8 4 807 3 253 Capital et réserves liées 4 346 514 4 346 514\nActifs d'impôt différé 3.8 135 551 159 789 Réserves consolidées 2 272 908 2 197 909\nComptes de régularisation et autres actifs 3.4 497 847 422 280 Part du groupe 2 272 908 2 147 334\nActifs non courants destinés à être cédés - - Part des minoritaires - 50 576\nParticipations dans des entreprises mises en équivalence - - Gains et pertes comptabilisés directement en capitaux propres 38 724 37 259\nPart du groupe 38 724 37 259\nImmeubles de placement - -\nPart des minoritaires - -\nImmobilisations corporelles 3.6 1 491 718 1 495 747\nRésultat net de l’exercice 390 835 498 225\nImmobilisations incorporelles 3.6 824 953 795 981\nPart du groupe 390 835 503 089\nEcarts d'acquisition - -\nPart des minoritaires - -4 864\nTOTAL 71 045 901 67 265 338\nTOTAL 71 045 901 67 265 338\nCOMPTE DE RÉSULTAT CONSOLIDÉ IFRS TABLEAU DES FLUX DE TRÉSORERIE\nAU 30 JUIN 2024 AU 30 JUIN 2024\n(En milliers de DH) (En milliers de DH)\nCOMPTE DE RÉSULTAT NOTES 30/06/2024 30/06/2023 FLUX DE TRESORERIE 30/06/2024 31/12/2023\nIntérêts, rémunérations et produits assimilés 2.2 1 544 030 1 311 552 Résultat avant impôts 708 293 878 307\nIntérêts, rémunérations et charges assimilés 2.2 357 557 228 765 Résultat net des activités abandonnées - -\nMarge d'Intérêt 1 186 473 1 082 787 +/- Dotations nettes aux amortissements des immobilisations 132 295 232 914\ncorporelles et incorporelles\nCommissions (Produits) 2.3 270 788 247 749\n+/- Dotations nettes pour dépréciation des écarts d’acquisition et des\nCommissions (Charges) 2.3 24 519 21 935 autres immobilisations - -\nMarge sur Commissions 246 269 225 813 +/- Dotations nettes pour dépréciation des actifs financiers 107 404 289 796\nGains ou pertes nets résultant des couvertures de position nette - - +/- Dotations nettes aux provisions -9 439 -41 381\nGains ou pertes nets sur instruments financiers à la juste valeur\n2.5 218 885 168 156 +/- Quote-part de résultat liée aux sociétés mises en équivalence - -\npar résultat\nGains ou pertes nets sur actifs/passifs de transaction 211 835 169 760 +/- Perte nette/(gain net) des activités d’investissement -3 547 -4 425\nGains ou pertes nets sur autres actifs/passifs à la juste valeur +/- Perte nette/(gain net) des activités de financement 44 155 11 890\n7 049 -1 604\npar résultat +/- Autres mouvements 97 985 -102 184\nGains ou pertes nets des instruments financiers à la juste\nvaleur par capitaux propres 2.6 - - Total des éléments non monétaires inclus dans le résultat net avant 368 854 386 610\nGains ou pertes nets sur instruments de dettes comptabilisés impôts et des autres ajustements\nen capitaux propres recyclables - - +/- Flux liés aux opérations avec les établissements de crédit et 3 376 972 -3 644 519\nRémunération des instruments de capitaux propres assimilés\n- -\ncomptabilisés en capitaux propres non recyclables (dividendes) +/- Flux liés aux opérations avec la clientèle -976 664 356 201\nGains ou pertes nets sur actifs financiers disponibles à la vente - - +/- Flux liés aux autres opérations affectant des actifs ou passifs\n-1 170 329 -465 570\nGains ou pertes nets résultant de la décomptabilisation d'actifs financiers\nfinanciers au coût amorti - - +/- Flux liés aux autres opérations affectant des actifs ou passifs non 152 338 595 979\nGains ou pertes nets résultant du reclassement d'actifs financiers\nfinanciers au coût amorti en actifs financiers à la juste valeur - - +/- Flux liés aux activités destinées à être cédées - -\npar résultat - Impôts versés -297 557 -396 449\nGains ou pertes nets résultant du reclassement d'actifs Diminution/(augmentation) nette des actifs et des passifs provenant\nfinanciers à la juste valeur par capitaux propres en actifs - - des activités opérationnelles 1 084 760 -3 554 358\nfinanciers à la juste valeur par résultat\nFlux nets de trésorerie généré par l’activité opérationnelle 2 161 907 -2 289 440\nProduits des autres activités 16 522 10 839\n+/- Flux liés aux actifs financiers et aux participations - -\nCharges des autres activités 62 169 61 559\n+/- Flux liés aux immeubles de placement - -\nPRODUIT NET BANCAIRE 1 605 979 1 426 037\n+/- Flux liés aux immobilisations corporelles et incorporelles -153 691 -441 626\nCharges générales d'exploitation 649 974 627 155\nFlux nets de trésorerie lié aux opérations d’investissement -153 691 -441 626\nDotations aux amortissements et aux dépréciations des\n132 295 98 490\nimmobilisations incorporelles et corporelles +/- Flux de trésorerie provenant ou à destination des actionnaires -372 138 200 138\nRésultat Brut d'Exploitation 823 709 700 391 +/- Autres flux de trésorerie nets provenant des activités de financement 58 000 1 800 000\nCoût du risque 2.1 -111 870 -166 067 Flux nets de trésorerie lié aux opérations de financement -314 138 2 000 138\nRésultat d'Exploitation 711 839 534 325 Effet de la variation des taux de change sur la trésorerie et équivalent\n186 -2 924\nQuote-Part du résultat net des entreprises associées et des de trésorerie\n- -\ncoentreprises mises en équivalence Augmentation/(diminution) nette de la trésorerie et des équivalents\n1 694 265 -733 852\nGains ou pertes nets sur autres actifs 2.4 -3 547 -7 273 de trésorerie\nVariations de valeur des écarts d'aquisition - -\nRésultat avant Impôt 708 293 527 051 COMPOSITION DE LA TRESORERIE 30/06/2024 31/12/2023\nImpôts sur les résultats 3.8 317 458 239 565 Trésorerie et équivalents de trésorerie à l’ouverture 2 525 258 3 259 110\nRésultat net d'impôt des activités arrêtées ou en cours de Caisse, Banques centrales, CCP (actif & passif) 2 265 415 1 868 563\n- -\ncession\nComptes (actif & passif) et prêts/emprunts à vue auprès des\nRésultat net (*) 390 835 287 487 établissements de crédit 259 842 1 390 546\nIntérêts minoritaires - 1 694 Trésorerie et équivalents de trésorerie à la clôture 4 219 522 2 525 258\nRésultat net Part du groupe 390 835 285 793 Caisse, Banques centrales, CCP (actif & passif) 1 848 123 2 265 415\nRésultat par action 35,92 26,26 Comptes (actif & passif) et prêts/emprunts à vue auprès des\n2 371 399 259 842\nRésultat dilué par action 35,92 26,26 établissements de crédit\nVariation de la trésorerie nette 1 694 265 -733 852\n4\nwww.creditdumaroc.ma\nRÉSULTAT NET, GAINS ET PERTES COMPTABILISÉS DIRECTEMENT EN CAPITAUX PROPRES\nAU 30 JUIN 2024\n(En milliers de DH)\nRésultat net et gains et pertes comptabilisés directement en capitaux propres 30/06/2024 31/12/2023\nRésultat net 390 835 498 225\nÉléments recyclables en résultat net : 826 28 175\nÉcarts de conversion 186 -2 924\nRéévaluation des actifs financiers à la juste valeur par capitaux propres recyclables 1 390 50 292\nRéévaluation des instruments dérivés de couverture d’éléments recyclables - -\nQuote-part des gains et pertes comptabilisés directement en capitaux propres des entreprises mises en équivalence - -\nAutres éléments comptabilisés par capitaux propres et recyclables - -\nImpôts liés 750 19 193\nÉléments non recyclables en résultat net : 825 -4 116\nRéévaluation des immobilisations - -\nRéévaluation (ou écarts actuariels) au titre des régimes à prestations définies 1 191 -6 929\nRéévaluation du risque de crédit propre des passifs financiers ayant fait l‘objet d’une option de comptabilisation à la juste valeur par résultat - -\nRéévaluation des instruments de capitaux propres comptabilisés à la juste valeur par capitaux propres - -\nQuote-part des gains et pertes comptabilisés directement en capitaux propres sur entreprises mises en équivalence non recyclables - -\nAutres éléments comptabilisés par capitaux propres non recyclables - -\nImpôts liés 366 -2 813\nTotal des gains et pertes comptabilisés directement en capitaux propres 1 651 24 058\n- -\nRésultat net et gains et pertes comptabilisés directement en capitaux propres 392 486 522 283\nDont part du Groupe (ou des propriétaires de la société mère) 392 486 527 147\nDont part des intérêts minoritaires (ou participations ne donnant pas le contrôle) - -4 864\nTABLEAU DE VARIATION DES CAPITAUX PROPRES\nAU 30 JUIN 2024\n(En milliers de DH)\nGains et pertes Gains et pertes\nRéserves Réserves comptabilisés comptabilisés Capitaux\nActions Intérêts\nCapital liées au et résultats directement en directement en propres part Total\npropres minoritaires\ncapital consolidés capitaux propres capitaux propres Groupe\nrecyclables non recyclables\nCAPITAUX PROPRES CLÔTURE AU 31 DÉCEMBRE 2022 1 088 121 2 766 149 - 2 444 050 10 567 - 6 308 887 50 576 6 359 463\nOpérations sur capital - - - - - - - -\nPaiements fondés sur des actions - - - - - - - -\nOpérations sur actions propres - - - - - - - -\nDividendes - - - -293 793 - -293 793 - -293 793\nAutres - 492 244 - - - 492 244 - 492 244\nChangements de méthodes comptables - - - - - - - -\nRésultat de l'exercice - - - 503 089 - 503 089 -4 864 498 225\nImmobilisations corporelles et incorporelles : Réevaluations et\n- - - - - - - -\ncessions\nInstruments financiers : variations de juste valeur et transferts en\n- - - - 31 099 31 099 - 31 099\nrésultat\nEcarts actuariels sur les régimes à prestations définies - - - -4 406 -4 406 - -4 406\nEcarts de conversion : variations et transferts en résultat - - - -2 924 - -2 924 - -2 924\nGains ou pertes latents ou différés - - - -2 924 26 693 - 23 768 - 23 768\nAutres - - - - - - - -\nVariations de périmètre - - - - - - - -\nCAPITAUX PROPRES CLÔTURE AU 31 DÉCEMBRE 2023 1 088 121 3 258 393 - 2 650 422 37 259 - 7 034 195 45 712 7 079 907\nOpérations sur capital - - - - - - - -\nPaiements fondés sur des actions - - - - - - - -\nOpérations sur actions propres - - - - - - - -\nDividendes - - - -372 138 - -372 138 - -372 138\nAutres - - - - - - - -\nChangements de méthodes comptables - - - - - - - -\nRésultat de l'exercice - - - 390 835 - 390 835 - 390 835\nImmobilisations corporelles et incorporelles : Réevaluations et\n- - - - - - - -\ncessions\nInstruments financiers : variations de juste valeur et transferts en\n- - - - 640 640 - 640\nrésultat\nEcarts actuariels sur les régimes à prestations définies - - - 825 825 - 825\nEcarts de conversion : variations et transferts en résultat - - - 186 - 186 - 186\nGains ou pertes latents ou différés - - - 186 1 465 - 1 651 - 1 651\nAutres - - - 155 - 155 - 155\nVariations de périmètre - - - -5 718 - -5 718 -45 712 -51 429\nCAPITAUX PROPRES CLÔTURE AU 30 JUIN 2024 1 088 121 3 258 393 - 2 663 743 38 724 - 7 048 980 - 7 048 980\n5\nNOTES ET ANNEXES IFRS\nNORMES ET PRINCIPES COMPTABLES APPLIQUÉS PAR LE GROUPE\nLes normes et principes comptables n’ont subi aucun changement par rapport à la publication effectuée au 31/12/2023.\nPRINCIPES ET PÉRIMÈTRE DE CONSOLIDATION\nPérimètre de consolidation actifs, ses passifs, ses produits et ses charges Les états financiers des entités représentant une «\nLes états financiers consolidés incluent les comptes y compris sa quote-part de ces actifs, passifs, activité à l’étranger » (filiale, succursale, entreprise\nde Crédit du Maroc et ceux de toutes les sociétés produits et charges, relatifs à ses intérêts dans associée ou une coentreprise) sont convertis en\nsur lesquelles Crédit du Maroc dispose d’un pouvoir l’entreprise commune. dirhams en deux étapes :\nde contrôle. • Coentreprise : les coentrepreneurs ont des droits\n• conversion, le cas échéant, de la monnaie locale\nPar exception, les entités ayant un impact non sur l’actif net de celle-ci Cette coentreprise est\nde tenue de compte en monnaie fonctionnelle\nsignificatif sur les comptes consolidés de l’ensemble comptabilisée selon la méthode de la mise en\nne sont pas incluses dans le périmètre de équivalence. (monnaie de l’environnement économique principal\nconsolidation. dans lequel opère l’entité) La conversion se fait\nLes méthodes de consolidation\nLe caractère significatif de cet impact peut comme si les éléments avaient été comptabilisés\nnotamment être apprécié au travers de divers Les méthodes de consolidation sont fixées initialement dans la monnaie fonctionnelle (mêmes\ncritères tels que l’importance du résultat ou des respectivement par les normes IFRS 10 et 11 Elles\nprincipes de conversion que pour les transactions\ncapitaux propres de la société à consolider par résultent de la nature de contrôle exercée par\nen monnaie étrangère) ;\nrapport au résultat ou aux capitaux propres de Crédit du Maroc sur les entités consolidables,\nl’ensemble consolidé. quelle qu’en soit l’activité et qu’elles aient ou non la • conversion de la monnaie fonctionnelle en dirhams,\npersonnalité morale : monnaie de présentation des comptes consolidés\nLes notions de contrôle\n• l’intégration globale, applicable selon les conditions du Groupe CDM Les actifs et les passifs, y compris\nConformément aux normes internationales, la\ncitées par la norme IFRS 10 ; les écarts d’acquisition, sont convertis au cours de\ndéfinition de contrôle, selon IFRS 10 comporte les\ntrois éléments suivants : • la mise en équivalence, pour les coentreprises clôture Les éléments de capitaux propres, tels\n• Le pouvoir détenu sur l’entité émettrice ; ayant des droits sur l’actif net, tel que cité par la que le capital social ou les réserves, sont convertis\nnorme IFRS 11 ;\nà leur cours de change historique Les produits et\n• L’exposition ou le droit à des rendements variables,\nen raison des liens avec l’entité émettrice ; • la quote-part des actifs, passifs, charges et les charges du compte de résultat sont convertis\nproduits, pour les entreprises communes ayant\n• La capacité de Crédit du Maroc d’exercer son au cours moyen de la période Les écarts de\ndes droits sur les actifs et des obligations au titre\npouvoir sur l’entité émettrice de manière à influer change résultant de cette conversion sont\ndes passifs, selon la norme IFRS 11.\nsur le montant des rendements qu’il obtient comptabilisés en tant que composante distincte\nCrédit du Maroc contrôle une entité émettrice si et Retraitements et éliminations des capitaux propres Ces écarts de conversion\nseulement si ces trois éléments sont réunis. Les retraitements nécessaires à l’harmonisation des sont comptabilisés en résultat en cas de sortie de\nméthodes d’évaluation des sociétés consolidées l’activité à l’étranger (cession, remboursement de\nsont effectués, sauf s’ils sont jugés non significatifs.\nL’IFRS 11 porte sur le classement d’un partenariat capital, liquidation, abandon d’activité) ou en cas\nL’effet sur le bilan et le compte de résultat consolidés\nsur lequel deux parties ou plus exercent un contrôle de déconsolidation due à une perte de contrôle\ndes opérations internes au Groupe est éliminé.\nconjoint Selon IFRS 11, il existe deux types de\nLes plus ou moins-values provenant de cessions (même sans cession) lors de la comptabilisation\npartenariat : les entreprises communes et les\nd’actifs entre les entreprises consolidées sont du résultat de sortie ou de perte de contrôle.\ncoentreprises Ces deux types de partenariats se\néliminées ; les éventuelles dépréciations durables\ndistinguent par les droits et obligations des parties\nRegroupements d’entreprises – écarts\nmesurées à l’occasion d’une cession interne, sont\nà l’entreprise.\nconstatées. d’acquisition (IFRS 3)\n• Entreprise commune : les coparticipants ont des\ndroits sur les actifs, et des obligations au titre des Conversion des états financiers des activités à Le Groupe Crédit du Maroc n’a pas effectué de\npassifs Chaque coparticipant comptabilise ses l’étranger (IAS21) regroupement courant 2024.\nPérimètre de consolidation du Groupe Crédit du Maroc au 30 juin 2024\nCapital social Capital social % Méthode de consolidation\nSociétés Consolidées\n(KDH) (KUSD) de contrôle d’intérêts (*)\nCrédit du Maroc 1 088 121 100,00 100,00 E C\nCrédit du Maroc Capital Bourse 5 000 100,00 100,00 I G\nCrédit du Maroc Leasing & Factoring 124 000 100,00 100,00 I G\nCrédit du Maroc Patrimoine 1 000 100,00 100,00 I G\nCrédit du Maroc Assurances 200 100,00 100,00 I G\nCrédit du Maroc International 1 655 100,00 100,00 I G\nS I F I M 168 321 100,00 100,00 I G\n* E C : Etablissement consolidant - IG : Intégration globale\n6\nwww.creditdumaroc.ma\nEXPOSITION AUX RISQUES ET STRATÉGIE DE COUVERTURE\nLA GOUVERNANCE 1. Le Conseil de Surveillance b) Rôle et pouvoirs du Directoire en application du\n1.1 Composition du Conseil de Surveillance règlement intérieur\nDepuis le 24 septembre 1999, Crédit du Maroc a opté\npour une structure de gouvernance duale reposant Conformément à l’article 15 des statuts de Crédit du Le règlement intérieur du Directoire décrit les modalités\nsur un Directoire et un Conseil de Surveillance, Maroc, le Conseil de Surveillance est composé d’un d’organisation et le mode de fonctionnement Il a un\ndissociant ainsi les pouvoirs de gestion et de contrôle minimum de trois membres et d’un maximum de caractère purement interne et n’est opposable ni aux\nLe Directoire dirige et gère la Banque sous le contrôle quinze membres, nommés par l’Assemblée Générale actionnaires, ni aux tiers Les règles instituées par le\ndu Conseil de Surveillance dans les limites du cadre et pouvant être renouvelés ou révoqués par cette règlement intérieur le sont sans préjudice de celles\nfixé par la loi 17-95 relative aux sociétés anonymes dernière. contenues dans les statuts de la Banque ou imposées\ntelle que modifiée et complétée (la « Loi 17-95 «), Au 30 juin 2024, le Conseil de Surveillance est par les lois et règlement en vigueur, lesquelles prévalent.\nla loi 103-12 relative aux établissements de crédits composé de sept membres EXPOSITION AUX RISQUES ET STRATÉGIE\net organismes assimilées (la « Loi Bancaire «) et les Le Conseil de Surveillance est composé de neuf DE COUVERTURE\nstatuts de la Banque. membres. 2.1 Risque de crédit\nPremière Dernier Membre Politique générale\nPrénom et nom Fonction Echéance du mandat en cours\nélection renouvellement d’un Comité La politique de crédit du Crédit du Maroc s’inscrit dans\nMOHAMED HASSAN Président du Assemblée générale ordinaire annuelle le cadre de principes généraux et dans le respect des\n12/2022 _ statuant sur les comptes de l’exercice\nBENSALAH Conseil clos le 31 décembre 2024 normes édictées par le régulateur\nAssemblée générale ordinaire annuelle Elle couvre les aspects relatifs à la déontologie, l’indépendance,\nMembre du\nKARIM CHIOUAR Conseil 12/2022 _ statuant sur les comptes de l’exercice A et R la responsabilité, la collégialité des décisions, la maîtrise et\nclos le 31 décembre 2024\nle suivi des risques, la rémunération des opérations, etc.\nMembre du AGOA statuant sur les comptes de\nZouhair Chorfi (2) 12/2022 _ C et R\nConseil l’exercice clos le 31 décembre 2024 Elle est revue chaque année, dans le cadre de la\nAtlantaSanad S A représentée Assemblée générale ordinaire annuelle stratégie risques qui examine toutes les activités de la\nMembre du\npar Madame Fatima Zahra Conseil 12/2022 _ statuant sur les comptes de l’exercice C banque et les risques qu’elles induisent et fixe des limites\nBensalah (4) clos le 31 décembre 2024\nopérationnelles en termes de segment de clientèle, de\nHOLMARCOM FINANCE Assemblée générale ordinaire annuelle\nCOMPANY S A REPRÉSENTÉE Membre du 12/2022 _ statuant sur les comptes de l’exercice A secteurs d’activité, de concentration, etc\nConseil\nPAR MADAME LAMIAE KENDILI clos le 31 décembre 2024 Cette stratégie est présentée par le Directoire au\nMembre AGOA statuant sur les comptes de Conseil de surveillance qui la valide.\nMohammed Ali Kadiri (1,3) indépendant du 12/2022 _ A et C\nConseil l’exercice clos le 31 décembre 2024 Dispositif de décision et de gestion des risques\nMembre AGOA statuant sur les comptes de Étude et décision\nNadine Koniski-Ziadé (1) indépendant du 03/2024 _ R\nConseil l’exercice clos le 31 décembre 2024 Le processus de décision découle des pouvoirs détenus\npar le Président du Directoire et des subdélégations qu’il\n(A) Comité d’Audit\n(R) Comité des Risques a distribué aux acteurs, selon un mode intuitu-personae,\n(C) Comité de Nomination et de Rémunération décliné en fonction des marchés Au-delà des limites\n(1) Membre indépendant subdéléguées, les décisions sont prises par le Comité\n(2) Président par intérim du Comité des Risques\n(3) Président du Comité d’Audit des crédits dont les décisions sont collégiales\n(4) Président du Comité de Nomination et de Rémunération Le processus de décision est géré par un applicatif\ninformatique centralisé et intégré qui détermine en\nfonction de normes et de critères paramétrés, les\nniveaux de délégation requis Les décisions en faveur\n1.2 Fonctionnement du Conseil de Surveillance Le Conseil de Surveillance peut décider la création des clients professionnels et entreprises nécessitent un\nLe fonctionnement du Conseil de Surveillance est régi de comités permanents et/ou temporaires chargés double regard de la ligne commerciale et des risques\npar les dispositions légales et statutaires ainsi que par d’étudier les questions que lui-même ou son Président Les filiales ont recours à un avis des lignes spécialisées\nson règlement intérieur Il en est de même pour les voudrait soumettre, pour avis, à leur examen destinées à du Crédit du Maroc qui conditionne l’octroi\nComités spécialisés. faciliter le bon fonctionnement du Conseil de Surveillance Les demandes de crédit formulées par les lignes\na) Rôle et pouvoirs du Conseil de Surveillance en et à concourir efficacement à la préparation de ses commerciales sont formalisées et documentées en\napplication des dispositions légales et statutaires décisions Il n’existe, à date, aucun comité de ce type application des règles du régulateur et des normes de\nLe Conseil de Surveillance exerce le contrôle permanent autre que ceux sus-cités. la banque.\nde la gestion de la Banque par le Directoire, et s’appuie 2. Le Directoire Mise en place - Garanties\nsur des Comités spécialisés détaillés ci-après A ce titre, 2.1 Composition du Directoire La mise en place des crédits est opérée après vérification\nune fois par trimestre au moins, le Directoire lui présente Selon l’article 14 1 des statuts de la Banque, le Directoire du respect des conditions d’octroi.\nun rapport sur la marche des affaires sociales et après est constitué de deux à sept membres désignés par La gestion des dossiers de garanties est centralisée\nla clôture de chaque exercice et dans le délai de trois le Conseil de Surveillance. Surveillance des risques et déclassement des créances\nmois, le Directoire présente au Conseil de Surveillance, Au 30 juin 2024, le Directoire est composé des trois Elle est à la charge d’une structure dédiée et indépendante,\naux fins de vérification et de contrôle, les documents membres suivants : appuyée par des correspondants dans les différents\nprévus par la Loi 17-95.\nmarchés et dans les régions.\nA toute époque de l’année, le Conseil de Surveillance Nom Fonction P ér le em cti iè or ne renoD ue vr en lli ee mr ent maE nc dhé aa t n ec ne c d ou u rs Elle est à la charge d’une structure dédiée et indépendante,\nopère les vérifications et les contrôles qu’il juge opportuns\nappuyée par des correspondants dans les différents\net peut se faire communiquer les documents qu’il estime Assemblée générale\nConseil de ordinaire annuelle marchés et dans les régions.\nutiles à l’accomplissement de sa mission. Ali Président du Surveillance Conseil de statuant sur\nSurveillance du Cette structure qui dispose d’un accès à tous les\nb) Rôle et pouvoirs du Conseil de Surveillance en Benkirane Directoire 06/12d /u 2 022 13/06/2024 l’ele xes rc co icm e p ct loe ss ld ee 3 1 systèmes d’information de la banque a pour mission de\napplication du règlement intérieur décembre 2026 surveiller la qualité des engagements, d’appréhender\nLe règlement intérieur du Conseil de Surveillance décrit, Membre du Assemblée générale dans une optique préventive les dégradations des risques\nConseil de ordinaire annuelle\nd’une part, les modalités d’organisation, le mode de Saïd Directoire en Surveillance Conseil de statuant sur (impayés, gel des comptes, etc ) et d’en assurer un suivi.\ncharge de Surveillance du\nfonctionnement, les pouvoirs et les attributions du Jabrani la Banque du 13/06/2024 les comptes de Elle organise sur la base d’indicateurs internes un suivi\n07/03/2023 l’exercice clos le 31\nConseil de Surveillance et, d’autre part les règles de Commerciale décembre 2026 rapproché des créances sensibles qui est opéré par\ndéontologie qui s’imposent à ses membres Il a un Assemblée un Comité mensuel dédié.\ncaractère purement interne et n’est opposable ni aux Younes DM ire em ctb or ire e d eu n SC uo rvn es ie llail nd ce e Conseil de g aé nn né ur ea lll ee o strd atin ua ai nre t Elle identifie les créances qui relèvent du déclassement en\nactionnaires, ni aux tiers Les règles instituées par le Lahlou charge du du Surveillance du sur les comptes de « souffrance », selon les critères édictés par le régulateur\n13/06/2024\nrèglement intérieur le sont sans préjudice de celles Fonctionnement 07/11/2023 l’exercice clos le 31 en la matière et les provisionne en conséquence Ces\ncontenues dans les statuts de la Banque ou imposées décembre 2026 décisions sont validées par un Comité dédié pour assurer\npar les lois et règlements en vigueur, lesquelles prévalent. une parfaite couverture des risques et conformité aux\n2.2 Fonctionnement du Directoire\n1.3 Les Comités du Conseil de Surveillance normes réglementaires.\nLe fonctionnement du Directoire est régi par les\nLe Conseil de Surveillance a créé, en son sein, trois Recouvrement\ndispositions légales et statutaires ainsi que par son\nComités spécialisés dont il a fixé la composition et les Pour le marché Retail et PRO/TPE, le réseau réalise\nrèglement intérieur.\nattributions : le Comité d’Audit, le Comité des Risques le recouvrement du premier impayé sur les clients\net le Comité de Nomination et de Rémunération a) Rôle et pouvoirs du Directoire en application des segmentés risque faible et sur les débits jusqu’à 30 jours\nDans le cadre de l’activité de la fenêtre participative, dispositions légales et statutaires de retards Les structures centrales de recouvrement\nle Conseil de Surveillance, conformément à la Loi Le Directoire est investi des pouvoirs les plus étendus prennent en charge le recouvrement dès le premier\nBancaire 103-12, a constitué, au sein du Comité des pour prendre en toutes circonstances, au nom de la impayé sur les clients segmentés risque moyen et élevé\nRisques, un sous-Comité chargé du suivi du processus Banque, toutes décisions concourant à la réalisation de ainsi que le débit dès 30 jours de retard.\nd’identification et de gestion des risques et au sein du son objet social et pour faire ou autoriser tous actes Pour le marché PME/PMI et Grandes Entreprises, il est\nComité d’Audit, un sous-Comité chargé de la surveillance de gestion et de disposition, et ce, sous réserve des assuré par les chargés d’affaires avec, selon les cas et\net de l’évaluation de la mise en œuvre des dispositifs pouvoirs attribués par la Loi 17-95 et les statuts au sur décision de comité dédié ou à la demande de la ligne\nde contrôle interne. Conseil de Surveillance et aux Assemblées d’Actionnaires. commerciale, l’appui d’une structure centrale dédiée\n7\nau Recouvrement et Restructuration de créances. • la surveillance des risques et des résultats en liaison Ces risques sont encadrés par des limites individuelles\nSi le dossier passe en ”Compromis”, il est pris en avec l’évolution des marchés ; sur les contreparties y compris les correspondants de\ncharge par la Direction du Recouvrement qui poursuit • l’analyse et le contrôle des P&L de gestion ; la salle des marchés et accordées par la banque dans\nle recouvrement et opère en parallèle les poursuites • la production et le contrôle de la qualité des indicateurs le cadre de l’étude de risque annuelle.\njudiciaires. de risques ; Le calcul des consommations de VaR (Value at Risk)\nTout le processus de décision et de surveillance des • le Back testing de la VaR (Value at Risk) ; du CDM est réalisé via l’outil Global View Risk alimenté\nrisques est traçable et auditable. en données de risques de marché (vecteurs de\n• la production et l’analyse des stress scenarii ;\nNotation interne sensibilités, positions de change, courbe de taux MAD)\n• la vérification des données de marché ;\npar les outils de CDM.\nLe Crédit du Maroc dispose d’un système de notation • la vérification que le Back Office s’est assuré de la\nIl couvre toutes les créances entreprises (PME/PMI, Aussi, GVR calcule aussi de manière automatisée des\ncohérence des stocks entre outil Front Office et\nGrandes entreprises et entreprises des secteurs de stress historiques (crises de 1994, de 1997, subprimes,\ndonnées comptables ;\nla promotion immobilière et de l’hôtellerie), sauf les Covid-19, etc ) selon des chocs observés qui sont\nbanques et les institutions financières qui disposent • la production et analyse des états de suivi de paramétrés dans l’outil, ainsi que des stress hypothétiques\nd’une notation spécifique. l’exposition aux risques. (resserrement liquidité, tensions internationales, etc ).\nLe système de notation du Crédit du Maroc est Il est rattaché hiérarchiquement à la Direction Contrôle Enfin, les résultats quotidiens des activités de trading\nconforme aux préconisations de Bâle 2. Central des Risques. (sur bonds et sur le change) sont alimentés dans un\nLe suivi des risques doit être effectué aux différents autre outil et la VaR fait l’objet d’un back-testing\nLe système repose sur une appréciation quantitative\net qualitative Il fait intervenir les différents acteurs niveaux de l’établissement avec des séparations de Des travaux de remplacement de GVR et de CADRE\ndu processus de décision : les chargés d’affaires, les pouvoir entre le front office, le middle office, le back par un outil disposant des mêmes fonctionnalités\nrisques et les décisionnaires. office, les risques et le contrôle financier, autrement sont en cours afin d’autonomiser le CDM avant la fin\ndit entre ceux qui passent les ordres et ceux qui les du premier semestre 2023.\nLe système de notation du Crédit du Maroc est\ncontrôlent. Ségrégation des Banking et Trading books\nbacktesté annuellement.\nAinsi, cette organisation permet : Afin d’assurer d’une gestion saine et prudente de sa\nPour la Banque de Réseau, tous les crédits à la\n• de s’assurer en permanence du respect des Trésorerie ainsi que de la couverture de ses risques\nconsommation sont soumis à un score d’octroi soit\nprocédures, des normes et des limites mises en propres, le CdM a mis en place une réorganisation de\npropre au Crédit du Maroc, ou soit celui du partenaire\nplace ; ses portefeuilles et centres de profits (découpage\nWafasalaf et ce, en fonction de critères bien définis\n• d’analyser les causes du non-respect éventuel des des activités par desk) en phase avec l’arborescence\nGrille de notation Corporate.\nprocédures et des limites ; risques Cette réorganisation assure une séparation\nElle comporte 13 échelons de A à E, avec des échelons\n• d’informer les entités et / ou les personnes désignées entre le banking book (ALM & activités de trésorerie)\nintermédiaires, pour les contreparties saines et 2\nà cet effet de l’ampleur des dépassements et des et les activités de la direction des marchés de capitaux\néchelons F et Z, pour les contreparties en défaut, dont\nactions correctrices qui sont proposées ou entreprises. (DMC) dont le rôle est d’assurer des opérations\nle dernier pour les contreparties en recouvrement\nd’intermédiation avec la clientèle.\njuridique. En termes d’outils informatiques, la banque dispose d’un\nsystème front-to-back Arpson avec des fonctionnalités 2.3 Risques Opérationnels\nCes échelons sont compatibles avec les échelles de\nde suivi des risques et de calcul des résultats Le Pôle Le Crédit du Maroc a adopté la définition issue des\nnotation des principales sociétés de rating internationales :\ndes Risques de Marché et Financier a accès à ces recommandations de Bâle 2 pour le risque opérationnel\nStandard&Poor et Moody’s\ninformations et dispose d’outils complémentaires pour Il s’agit des pertes résultant de l’inadéquation ou de\nDélégation mener à bien ses analyses. la défaillance des processus internes, des personnes,\nLa notation est un élément essentiel du processus des systèmes ou d’événements extérieurs, risque\nPrincipaux risques et dispositif de contrôle\nde décision Elle conditionne le niveau de délégation juridique inclus.\nLes risques de marché ou risques de variation de\nRisques sensibles : Les contreparties présentants des prix, représentent les pertes potentielles suite à Dispositif de gestion des risques opérationnels\nsignes de fragilités sont suivies dans le cadre du comité mis en œuvre\ndes mouvements adverses de cours, de prix ou de\nmensuel d’anticipation et de suivi des Risques Sensibles\nniveaux de taux. Le dispositif de gestion des risques opérationnels mis\nsur la base de critères qualitatifs et quantitatifs.\nRisques de taux : Ils représentent les risques d’encourir en place par la banque vise à identifier l’ensemble\n2.2 Risque de marché des pertes suite aux variations du niveau absolu du des sources de risques majeurs en vue de les couvrir\nLes activités de marché sont encadrées par des limites taux d’intérêt, d’un spread entre deux courbes de taux (fraude interne, fraude externe, pratiques en matière\nglobales et opérationnelles définies dans le cadre de ou de la déformation de la courbe Il existe plusieurs d’emploi et sécurité sur le lieu de travail, clients produits\nla stratégie risques de la banque. composantes pour ce risque : risque directionnel, risque et pratiques commerciales, dommages aux actifs\nLe format de limites, qu’elles soient globales ou de pente et risque de base ou de spread. corporels, dysfonctionnements de l’activité et des\nopérationnelles, sont de trois natures : quantitative systèmes, exécution livraison et gestion des processus).\nCe risque concerne le trading sur titres et la trésorerie\n(VaR, Stress, sensibilités détaillées), qualitatif (produits Il est encadré par un dispositif de limites quantitatives 1. Les principaux enjeux\nautorisés, devises autorisées, maturité max…) et des\n(VaR, Stress, nominal et sensibilités détaillées). • La maîtrise du coût des risques opérationnels ;\nseuils de perte Les sets de limites concernent les\nRisque de change : C’est le risque d’encourir des pertes • La Prévention des grands risques ;\nactivités de la direction marchés des capitaux dont\nle rôle est d’assurer des opérations d’intermédiation suite aux variations du cours des devises étrangères par • L’optimisation de la couverture des risques ;\navec la clientèle (Activités FX, obligataires, prêts/ rapport à la monnaie de référence ou monnaie locale. • L’intégration du triple impact réglementaire à savoir\nemprunts, Repos) ainsi que les activités de marché Les positions sont encadrées par des limites le pilotage par les fonds propres, la supervision\nde la trésorerie de la banque. réglementaires et des limites internes (VaR, Stress, réglementaire et la communication financière.\nnominal individuelle et globale, Loss alert…).\nOrganisation de la filière 2. Les composantes du dispositif\nRisques liés aux défauts : une part importante des\nLes activités de marchés sont organisées en trois Le dispositif de gestion des risques opérationnels mis\nrisques pris par les établissements financiers sur les\ndomaines indépendants : en œuvre s’articule autour de quatre composantes :\nmarchés se trouve liée aux événements de défauts\n- Le Front Office (défaillance d’une ou plusieurs contreparties, risque La composante organisationnelle\nLe Front Office eest littéralement l’interface de la de non-transfert…). La surveillance des risques opérationnels est confiée à\nbanque avec le marché Il centralise et traite tous Les opérations de marché peuvent générer : une entité relevant des Risques et contrôles permanents,\nles besoins de la banque et de ses clients en termes structure faîtière du dispositif de contrôle interne de\n• des risques de règlement/livraison ;\nde couverture et financement Il engage la banque la banque.\ndans le respect des limites internes de marché, des • des risques de variation.\nLe système d’audit interne vérifie périodiquement que\nlimites réglementaires et des lignes de crédit qui lui Une transaction peut comporter un seul de ces risques\nle dispositif de gestion des risques opérationnels est\nsont accordées. ou une combinaison de deux ou trois Une opération\nmis en œuvre avec efficacité au niveau de l’ensemble\nIl est rattaché hiérarchiquement à la DGA Corporate de change à terme génère des risques de variation de l’établissement.\ndu pôle Développement. et de livraison.\nLe Directoire assure un suivi régulier de la situation\n- Le Middle Office En effet, si l’un des intervenants fait défaut alors des risques via le Comité de Contrôle Interne présidé\nque l’autre contrepartie a déjà rempli ses propres\nLe Middle Office assure les contrôles et le respect des par le Président du Directoire.\nobligations, à savoir ; livrer des fonds, alors la perte\nlimites fixées par les Risques. Le Conseil de Surveillance, via le Comité d’Audit et le\nporte sur la totalité du montant (nominal) de la\n- Le Back-Office Comité des Risques, est informé des risques importants\ntransaction (à la livraison), c’est le risque de livraison\nLOffice suit le traitement post –marché des opérations : et s’assure de la prise en compte de ces risques.\nou non concomitance des flux échangés.\nconfirmation, paiement, règlement – livraison et La composante qualitative\nCe risque affecte le change (comptant et terme), les\ncomptabilité. swaps de change (swaps de trésorerie ou cambiste) Elle permet d’évaluer et de prévenir les risques à\nIl est rattaché hiérarchiquement à la Direction des travers la cartographie des risques opérationnels.\nPour les opérations sur tires (ferme ou temporaire),\nServices Bancaires à la Clientèle. ce risque n’existe pas du fait que les transactions La composante quantitative\n• Pôle RMF (Risques de Marché et Financier) sont effectuées via un système DVP (Delevery Versus Elle permet de mesurer et surveiller le coût du risque\nEn matière de suivi et de contrôle des activités de la Payment). et les incidents à travers le suivi des pertes et la\nSalle des Marchés, RMF a en charge : Si par contre la défaillance intervient entre la négociation mise en place d’un dispositif d’alerte Elle permet de\n• le suivi du respect des limites, que celles-ci soient et la livraison, alors la perte potentielle correspond à la mesurer et surveiller le coût du risque et les incidents\nquantitatives (niveaux de risque), qualitatives variation du cours de change entre le cours négocié et à travers le suivi des pertes et la mise en place d’un\n(instruments, devises ou maturités autorisés) ou le cours prévalant sur le marché au moment où il faut dispositif d’alerte.\nrelatives aux niveaux de perte tolérée ; trouver une nouvelle contrepartie de remplacement, La composante d’allocation de fonds propres\n• le traitement des dépassements (analyse des raisons, il s’agit du coût de remplacement et c’est le risque Par prudence, l’établissement a retenu une allocation\nmode et délai de régularisation…) ; de variation.\n8\nwww.creditdumaroc.ma\ndes fonds propres basée sur la méthode « indicateurs 20 tranches de maturités. Les règles d’écoulement se fondent sur une approche\nde base » avec l’objectif d’évoluer rapidement vers la • La limite réglementaire sur les Fonds Propres est segmentée des encours Par cette segmentation, elles\nméthode « standard ». revue à la baisse passant de 20% des fonds propres s’appuient sur la définition de populations homogènes\n3. Sécurité des systèmes d’information globales à 15% des fonds propres de catégorie 1 en termes de « comportement » (au sens statistique).\nLa sécurité des systèmes d’informations est assurée (CET1) A noter que le régulateur a prévu une période Ces modèles sont le socle commun à la mesure des\navec la mise en place d’une politique de sécurité et d’un transitoire pour le respect du minimum réglementaire risques de taux et de liquidité et au pilotage de la\ndispositif de contrôle permanent Des tests annuels sur le Δ EvE : 20% des FP globales au 31-12-21, 20% marge Ils servent :\nd’intrusions et de vulnérabilité, ainsi que des évaluations des FP CET1 au 31-01-22, 15% des FP CET1 au • d’une part pour le calcul du RTIG et donc influencent\nde la sécurité des systèmes d’informations sont réalisés. 01-01-23. les prises de décisions en matière de couverture.\n4. Plan de Continuation des Activités • L’identification du risque de base en précisant pour • d’autre part pour le calcul des taux de cession internes\nPour assurer la continuité des activités de la banque les instruments à taux variables, la date de révision, entre le pool commercial et le pool ALM A ce titre, ils\nen cas de sinistre, l’établissement dispose d’un Plan la référence considérée pour l’indexation et les taux déterminent les marges analytiques des crédits et\nde Continuité d’Activités(PCA), composé : appliqués. de la collecte.\n• d’un Plan de Secours informatique pour secourir • Le calcul de la durée de vie moyenne des flux du Les modèles ALM, calibrés et revus annuellement,\nles services informatiques critiques ; bilan et du hors bilan actualisés, conformément à doivent minimiser le risque de sur-couverture ; dans\n• d’un Plan de Repli Utilisateurs avec aménagement une formule de duration spécifique. ce sens l’étude statistique a pour principaux objectifs:\nd’un site de repli devant servir en cas de sinistre ; • L’application de 6 scénarii de chocs de taux d’intérêt • Éliminer le risque de concentration : Si une faible\n• d’un dispositif de gestion de crise ; sur trois devises : MAD / EUR / USD. fraction de clients détient une forte proportion de\n• d’un dispositif de continuité d’activité spécifique au Un dispositif d’encadrement et de contrôle a été mis l’encours, l’encours global est susceptible de chuter\nscénario de pandémie grippale. en place au Crédit du Maroc Des limites en volume brutalement de façon imprédictible La règle de\nont été fixées. prudence demande donc à ce que cette fraction\nCe PCA est régulièrement testé et amélioré.\nLe risque de liquidité d’encours soit retirée (part volatile).\n5. Prestations de services essentielles\nexternalisées Il est défini comme étant le risque pour la banque de ne • Tenir compte des cycles / saisonnalités : Si l’historique\npas pouvoir s’acquitter, dans des conditions normales, d’encours présente des saisonnalités, la variable «\nElles sont encadrées par un dispositif spécifique.\nde ses engagements à leur échéance Il peut prendre solde des comptes » sera remplacée par « moyenne\nLes Conventions de services comprenant des indicateurs\ndeux formes : glissante des soldes des comptes », cette moyenne\nde qualité ont permis à l’établissement d’intégrer le suivi\n• Risque d’illiquidité : se traduisant par l’incapacité de étant calculée sur une période suffisamment longue\nde ces activités dans le dispositif de contrôle interne.\nla banque à se procurer les fonds nécessaires pour pour s’affranchir des effets de cycle.\n2.4 Gestion Actif - Passif\nfaire face à des obligations inattendues survenues à • Conserver la pertinence sur la durée afin de garder\nLa démarche de la gestion Actif-Passif (ALM) est une court terme, notamment un retrait massif de dépôts ; une logique commerciale d’écoulement.\ndémarche d’identification, de mesure, de contrôle et\n• Risque de transformation : où le terme des emplois Risque de change (Banking Book)\nde couverture des risques financiers pouvant affecter\nest en général supérieur au terme des ressources, Le risque de change du Banking book est suivi et\nle bilan de la banque.\ntransformation inhérente à l’activité bancaire. géré par le Comité ALM qui prend connaissance des\nIl s’agit principalement des risques de liquidité, de taux\nLe risque de liquidité se situe à trois niveaux : expositions et de leur évolution à travers les reportings\net de change.\n• Funding risk : risque qui se traduit par la nécessité trimestriels mis en place.\nGouvernance\nd’obtenir de nouvelles ressources lorsqu’une des La fonction ALM suit l’ensemble des positions de change\nAu Crédit du Maroc, la gestion Actif-Passif est assurée\nressources dont la banque disposait par le passé de la banque, à l’exception des positions gérées dans\npar la Direction Gestion Financière qui rapporte à la\nn’est plus disponible (par exemple lors de retrait le cadre des activités de trading, et ce dans le cadre\nDirection Finances Groupe et au comité ALM.\nmassif sur les dépôts à vue). des normes internationales relatives à la mesure et\nRisque de taux d’intérêt global (RTIG) • Time risk : risque qui apparaît lorsque la banque ne l’encadrement du risque de change.\nC’est le risque de voir les résultats de la banque peut obtenir des rentrées d’argent pourtant attendues Dans le cadre du risque de change, le Comité ALM a\naffectés défavorablement par les mouvements de taux (par exemple, incapacité de remboursement d’un comme principaux objectifs :\nd’intérêt Ces mouvements ont une influence sur les prêt par un client). • Analyser le risque\nrémunérations et les coûts générés par les produits et • Call risk : risque relatif à l’obtention de nouvelles • Valider la proposition de limites et leur compatibilité\ninstruments financiers (actifs, passifs et instruments de ressources (suite par exemple à des emprunts avec les limites globales et réglementaires\nhors bilan), dont dispose la banque. En conséquence,\nimportants sur des lignes de crédits). • Vérifier le respect de ces limites\nleurs mouvements ont un impact direct sur le résultat\nL’approche en liquidité met en évidence la situation de\ngénéré mais aussi sur la valeur actuelle des différents • Valider les propositions de gestion\ntransformation de la banque Elle permet de mesurer\nrevenus futurs. Les Positions de Change Opérationnelles (PCO) peuvent\nles besoins de funding à court, moyen et long terme\nIl convient donc d’appréhender correctement la manière ou l’importance des excédents de liquidité à replacer se mesurer en méthode « flux » ou « stock » Pour le Crédit\ndont les mouvements de la courbe des taux peuvent par type de maturité. du Maroc, cette position se compose des positions de\nimpacter les marges de la banque. change virement bilan et hors bilan de la clientèle, ainsi\nDans le cadre de la gestion du risque de liquidité, le\nque l’encaisse en billets de banque\nLa mesure du RTIG fait appel à une approche statique, Comité ALM a pour fonction de :\nLes positions de change structurelles (PCS) résultent\nbasée sur plusieurs modèles afin de transformer les\n• Approuver la stratégie globale en matière de gestion principalement des prises de participations dans des\ndonnées mensuelles en indicateurs de risque quantifiables\ndu risque de liquidité. établissements en devises étrangères. A noter, toutefois,\nsur toute la durée de vie future du bilan.\n• Gérer la trésorerie MLT de la banque. l’exception des participations en devise comptabilisées\nLa mesure principale et obligatoire du RTIG est le gap\n• Mettre en place une approche pour mesurer et suivre à la JVR (juste valeur par résultat) qui sont à prendre\nde taux d’intérêt qui représente sur chaque période la\ndu risque de liquidité. en compte dans la position de change opérationnelle\ndifférence signée entre les passifs et les actifs à taux\nfixe (encours et taux de cession interne associés) dans • Etablir un système de limites appropriées encadrant et non structurelle dans la mesure où la position de\nune devise donnée. les principaux indicateurs utilisés. change induite est réévaluée par contrepartie du\ncompte de résultat Pour le Crédit Du Maroc, cette\nLe Risque de Taux d’Intérêt Global est la résultante de • Veiller à ce que des simulations de scénarios de stress\nposition se compose de la position en USD sur les\ndifférentes composantes de risque qui sont notamment soient effectuées en vue d’évaluer la capacité de\ntitres de participation de la filiale « CDM International »\nreprésentées par des gaps : la banque à faire face à des situations de crise de\nqui fait l’objet d’un encadrement par une limite globale\nliquidité.\n• Un risque directionnel sur opérations à taux fixe : Le en montant.\ngap « Taux fixe ». • Décider du plan d’urgence destiné à être mis en\nœuvre en cas de tensions ou de crises de liquidité. Système de mesure\n• Un risque optionnel sur les options explicites (caps,\nfloors …) si la banque a développé des modèles • Prévoir les instruments et les stratégies de couverture Le pilotage des risques financiers est géré dans ATLAS,\nd’options, et implicites s’agissant notamment des du risque de liquidité. outil opérationnel depuis 2008.\n3. Application des recommandations du Comité\nremboursements anticipés sur les crédits. • Définir le système de reporting dans les situations\nde Bâle\n• Un risque de base sur les opérations à taux révisable normales ou de crise de liquidité.\nL’accord de Bâle 2 repose sur 3 piliers :\net variable induit par des dé-corrélations entre les • Veiller au respect des coefficients réglementaires,\nindex : Les gaps d’Index. dont le Liquidity Coverage Ratio (LCR). Pilier 1 : Calcul des exigences minimales en fonds propres\nIl couvre trois types des risques : Risque de crédit,\nBank Al-Maghrib a publié en mars 2021 une nouvelle En plus du Comité ALM trimestriel, un Comité Trésorerie\nRisque opérationnel et Risque de marché Plusieurs\ncirculaire qui encadre la mesure du risque de taux mensuel a été instauré en janvier 2016 avec pour\nméthodes sont proposées aux banques selon les risques,\nd’intérêt inhérent au portefeuille bancaire et fixe de objectif, entre autres, de piloter de façon opérationnelle\nnotamment « standard » et « notation interne », pour\nnouvelles exigences en matière de fonds propres la trésorerie court terme de la banque.\nles risques de crédit, « indicateur de base », « standard\néconomiques Cette circulaire est entrée en vigueur\nConventions d’écoulement » et « standard avancé », pour le risque opérationnel.\nen juin 2021.\nLes modèles ALM au sein de la banque suivent une\nLes principaux changements introduits par cette\nlogique de « Run Off » à partir d’un bilan constaté\nnouvelle réglementation qui impacte considérablement\nà la date de calcul Cette approche permet d’avoir\nl’appréciation du risque de taux du Banking Book : Pilier 2 : Dispositif sur les processus de surveillance\nune vision sur l’écoulement du bilan dans le temps\n• Les postes non sensibles aux taux d’intérêts notamment des risques et l’adéquation des fonds propres internes.\net d’avoir une mesure précise de la marge sous une\nles Fonds Propres de Base, les titres de transactions, Pilier 3 : Dispositif sur la discipline de marché imposant\nhypothèse de cessation d’activité dénuée de toute\nles titres de négociation ainsi que leurs ressources de une transparence accrue en matière d’information sur\nprise en compte d’une production commerciale ou\nmarché ne sont pas pris en compte dans l’exposition les publications financières et sur les risques.\nactivité financière future.\nau risque de taux. Dès la publication des textes par le Régulateur, le Crédit\n• Les flux de Trésorerie prévisionnels sont ventilés sur du Maroc a engagé un chantier de mise en conformité\n9\navec les dispositions réglementaires. Pilier I Évolution des risques pondérés du Crédit du Maroc.\nP « o su tar nle d p ail rie dr 1 », l ee nC r cé ed i qt ud iu c M oa nr co ec r a ne o p leté r p iso qu ur e la d m e é ct rh éo dd ie t, Risque couvert Méth eo td de e d g’é ev sta il ou nation 42,4 46,7 En milliards de dirhams\nRisque de crédit ✓ Méthode standard\nla « Méthode de base » pour le risque opérationnel. Risque de marché ✓ Méthode standard\n4. Perspectives Risque opérationnel ✓ BIA\n(Basic Indicator Approach)\nLe Crédit du Maroc compte poursuivre la mise en\nœuvre de l’usage des indicateurs bâlois avancés,\nqui entraîneront de profonds changements dans la 0,8 0,9 5,0 5,2\nconduite des activités.\nRisque Risque Risque\nCes changements visent notamment à : de Crédit de Marché Opérationnel\n• adapter la politique d’allocation des fonds propres Déc. 2023 Juin 2024\naux activités ;\nDétail et variation des RWA\n• mieux prendre en compte les évolutions dans les (en milliers de dirhams)\nprocessus d’octroi (consommation des Fonds propres,\ndéc-23 juin-24 Variation\nrentabilité, coût du risque, etc…) ; Actifs Exigences Actifs Exigences Actifs Exigences\npondérés en fonds propres pondérés en fonds propres pondérés en fonds propres\n• garantir la fiabilité des informations sur les risques,\nRisque de crédit 42 375 958 3 390 077 46 660 407 3 732 833 4 284 449 342 756\netc…\nDont Souverain 8 167 653 40 774 3 262 32 607 2 609\n• renforcer la capacité d’anticipation des risques Dont Établissements 2 870 776 229 662 3 018 021 241 442 147 245 11 780\nDont Entreprises 26 987 922 2 159 034 30 032 475 2 402 598 3 044 554 243 564\nLes processus impactés ont été identifiés et les\nDont Clientèle de détail 9 696 433 775 715 10 384 646 830 772 688 212 55 057\nchantiers nécessaires à leur adaptation sont engagés Risque de Marché 755 608 60 449 920 776 73 662 165 168 13 213\nselon un planning établi par une équipe projet et validé Risque Opérationnel 4 970 090 397 607 5 221 726 417 738 251 636 20 131\npar le Comité de pilotage des risques, présidé par le Total 48 101 656 3 848 133 52 802 909 4 224 233 4 701 252 376 100\nPrésident du Directoire.\n1. Risque de crédit 3. Risque opérationnel\n5. Gestion du capital et adéquation des fonds propres Le montant du risque de crédit pondéré est calculé l’aide des PNB annuels des trois derniers exercices\ndu groupe en multipliant les éléments d’actifs et du hors en utilisant la méthode des indicateurs de base\nbilan par les coefficients de pondération prévus L’exigence en fonds propres est 15% x la moyenne du\nLe troisième pilier de l’accord de Bâle vise à promouvoir\npar la réglementation Le risque de crédit dépend PNB des trois derniers exercices.\nla discipline du marché à travers la publication d’un\nessentiellement de la nature de l’engagement et de\nensemble de données venant compléter la communication\nla contrepartie. 5.4 ICAAP (Internal Capital Adequacy Process)\nfinancière L’objectif de cette communication est de Le risque pondéré est calculé à partir de l’exposition Le processus d’évaluation et d’adéquation du capital\npermettre aux acteurs du marché d’apprécier les nette atténuée par les garanties ou les suretés et interne est un processus qui vise, d’une part à\néléments d’information essentiels sur les fonds propres, pondérée par le taux de pondération. assurer en permanence un équilibre entre les fonds\nles expositions aux différents types de risques, le Les engagements hors bilan sont également propres de la banque et l’ensemble des risques\npilotage interne des fonds propres et, par conséquent, pondérés par le facteur de conversion risque crédit. encourus, et anticiper tout déséquilibre pouvant\nl’adéquation des fonds propres du groupe Crédit du 2. Risque de marché nuire à sa viabilité financière et la continuité de\nMaroc à son profil de risque. Les risques de marché sont définis comme les son activité et d’autre part, à mettre en œuvre les\nrisques de pertes liés aux variations des prix de\n5.1 Composition des Fonds Propres solutions de rétablissement appropriées.\nmarché Ils recouvrent :\nLe groupe est tenu de respecter sur base individuelle C’est un processus qui apporte une contribution\n• les risques relatifs aux instruments inclus dans le\net consolidée un ratio sur fonds propres de base au portefeuille de négociation ; substantielle à l’évaluation :\nmoins égal à 8,0% (incluant un coussin de conservation • le risque de change et le risque sur produits de • Du modèle d’activité de la banque ;\nde 2,5%), un ratio sur fonds propres de catégorie 1 au base encourus pour l’ensemble des éléments du • De la gouvernance interne et la gestion globale des\nmoins égal à 9,0% et un ratio sur total fonds propres bilan et du hors bilan autres que ceux inclus dans le risques ;\nde catégorie 1 et de catégorie 2 au moins égal à 12,0% portefeuille de négociation. • Des risques majeurs – appétence aux risques ;\nLes fonds propres prudentiels du groupe Crédit du Le risque de marché est composé du : • Des exigences en capital réglementaire et interne ;\nMaroc sont composés des fonds propres de catégorie • Risque de taux d’intérêt • Du pilotage des fonds propres prudentiels (pilier 1\n1 et des fonds propres de catégorie 2. Le calcul du risque de taux d’intérêt concerne les et 2).\nproduits de taux faisant partie du portefeuille La démarche ICAAP est un processus en\nLes fonds propres de catégorie 1 sont déterminés à\ntrading Celui-ci est la somme du risque général de enrichissement continu, qui évolue à la demande des\npartir des fonds propres de base et des fonds propres\ntaux et risque spécifique de taux. dirigeants, pour prendre en compte les évolutions\nadditionnels en tenant compte des retraitements\nLe calcul des exigences en fonds propres au titre réglementaires (Directive 3/W/2021 et exigences\nprudentiels Ces retraitements consistent principalement\ndu risque de taux d’intérêt général se fait selon la croissantes de BAM) et intégrer les meilleures\nen l’anticipation des dividendes à distribuer, de la méthode de l’échéancier Le risque spécifique est pratiques internationales.\ndéduction des écarts d’acquisition et des actifs calculé à partir de la position nette, sa pondération\nLe cadre général d’appétence aux risques présente\nincorporels ainsi que des participations ne figurant pas dépend de la nature de l’émetteur du titre et de la\nl’ICAAP comme l’un de ses dispositifs opérationnels\ndans le périmètre de consolidation et détenues dans maturité.\nclés.\nle capital des établissements de crédit et assimilés • Risque sur titres de propriété\nPour l’exercice ICAAP 2021, ce cadre a été respecté\nau Maroc et à l’étranger et des entités exerçant les Le calcul du risque sur les titres de propriété\net enrichi Ainsi, le Conseil de Surveillance a été\nopérations connexes à l’activité bancaire au Maroc et concerne : les positions sur actions, options sur\nrégulièrement informé des évolutions significatives\nà l’étranger ainsi que des filtres prudentiels. actions, futures sur actions, options sur index, autres\ndérivés avec comme sous-jacent une action ou un de l’ICAAP, les comptes rendus du Comité des\nLes fonds propres de catégorie 2 sont composés\nindex Celui-ci est la somme du risque général sur risques lui ont été régulièrement faits Les dernières\nessentiellement de dettes subordonnées dont l’échéance\ntitre de propriété et du risque spécifique sur titre de évolutions de l’ICAAP ont été inscrites à l’ordre du\ninitiale est d’au moins 5 ans Une décote de 20%\npropriété. jour de la réunion du Directoire\nannuellement est appliquée aux dettes subordonnées L’exigence en fonds propres au titre du risque L’appropriation du dispositif s’est enfin renforcée\nde maturité résiduelle inférieure à 5 ans. général sur titres de propriétés représente 8% de la via :\n5.2 Ratio de Solvabilité position nette globale. • Une formation ICAAP dispensée aux membres\nAu 30 Juin 2024, les ratios du Groupe se présentant Le risque spécifique est calculé sur la position du Directoire ainsi qu’aux membres du Conseil de\nglobale en appliquant les pondérations listées par le Surveillance en 2021 ;\ncomme suit :\nrégulateur suivant la nature de l’actif. • Une prise en charge renforcée par la Direction\nEvolution Ratio de solvabilité. • Risque de change Financière, qui assure la centralisation du\n(en milliers de dirhams) L’exigence en Fonds propres au titre du risque de dispositif ICAAP, et qui a réalisé, sur l’exercice\n30/06/2024 31/12/2023 change est calculée lorsque la position nette globale écoulé, d’importants travaux d’amélioration et de\nFonds propres de catégorie 1 6 030 376 5 986 956 dépasse 2% des capitaux de base. La position nette renforcement du dispositif (Cf Evolutions majeurs\nTotal fonds propres 7 052 492 7 008 784 globale correspond à la position la plus forte entre la intégrées dans le dispositif ICAAP 2021) ;\nRisques pondérés 52 802 909 48 101 656 somme des positions courtes et celle des positions • Un appui technique d’un cabinet externe dans une\nRatio sur fonds propres de base (T1) 11,42% 12,45% longues pour la même devise.\nperspective d’amélioration continue du dispositif\nRatio de solvabilité 13,36% 14,57%\nDétail Risque de marché ICAAP et afin d’intégrer les meilleures pratiques\n(en milliers de dirhams) internationales ;\n5.3 Exigence en fonds propres et actifs pondérés\nExigences en fonds propres 31/12/2023 30/06/2024 • Les éléments clés de l’ICAAP sont intégrés aux états\ndu groupe Crédit du Maroc\nRisque de taux 44 534 48 160 de reporting adressés aux instances dirigeantes,\nLes risques pondérés sont calculés en approche Risque spécifique de taux 2 487 5 354 ainsi qu’au Conseil Surveillance, et enrichis d’une\nstandard pour les risques de crédit, de contrepartie Risque général de taux 42 047 42 806 dimension prospective régulièrement actualisée.\net les risques du marché et en méthode d’indicateurs Risque de change 15 914 25 502\nde base pour les risques opérationnels. Total 60 449 73 662\n10\nwww.creditdumaroc.ma\nCOÛT DU RISQUE (2.1) PRODUITS ET CHARGES D’INTÉRÊTS (2.2)\n(En milliers de DH) (En milliers de DH)\nCONSOLIDE 30/06/2024 30/06/2023 30/06/2024 30/06/2023\nDépréciations sur actifs sains (Bucket 1 et Bucket 2) -24 673 1 200 Sur les actifs financiers au coût amorti 1 504 590 1 273 639\nBucket 1 : Pertes évaluées au montant des pertes de crédit attendues -4 358 10 967 Opérations avec les établissements de crédit 126 206 76 753\npour les 12 mois à venir\nInstruments de dettes comptabilisés à la juste valeur par capitaux Opérations internes au Crédit du Maroc - -\n522 3 420\npropres recyclables Opérations avec la clientèle 1 330 400 1 155 843\nInstruments de dettes comptabilisés au coût amorti -4 264 8 216 Opérations de location-financement 47 984 41 043\nEngagements par signature -616 -669\nTitres de dettes - -\nBucket 2 : Pertes évaluées au montant des pertes de crédit attendues\npour la durée de vie -20 315 -9 767 Sur les actifs financiers à la juste valeur par capitaux propres 34 371 31 813\nInstruments de dettes comptabilisés à la juste valeur par capitaux - - Opérations avec les établissements de crédit - -\npropres recyclables\nOpérations avec la clientèle - -\nInstruments de dettes comptabilisés au coût amorti -11 016 -10 891\nEngagements par signature -9 299 1 124 Titres de dettes 34 371 31 813\nDépréciations sur actifs dépréciés (Bucket 3) - - Intérêts courus et échus des instruments de couverture - -\nBucket 3 : Actifs dépréciés -43 742 -27 733 Autres intérêts et produits assimilés 5 069 6 099\nInstruments de dettes comptabilisés à la juste valeur par capitaux - - Produits d'intérêts 1 544 030 1 311 552\npropres recyclables\nSur les passifs financiers au coût amorti 262 412 181 187\nInstruments de dettes comptabilisés au coût amorti -73 959 -3 569\nEngagements par signature 30 216 -24 164 Opérations avec les établissements de crédit 36 422 35 027\nAutres actifs -18 688 -23 666 Opérations internes au Crédit du Maroc - -\nRisques et charges -18 874 17 017 Opérations avec la clientèle 225 990 146 161\nDotations nettes de reprises des dépréciations et provisions -105 978 -33 182 Opérations de location-financement - -\nPlus ou moins-values de cessions réalisées sur instruments de dettes - - Dettes représentées par un titre - -\ncomptabilisés en capitaux propres recyclables dépréciés\nGains ou pertes réalisés sur instruments de dettes comptabilisés au coût Dettes subordonnées - -\n- -\namorti dépréciés Intérêts courus et échus des instruments de couverture - -\nPertes sur prêts et créances irrécouvrables -14 673 -142 735 Autres intérêts et charges assimilées 95 146 47 577\nRécupérations sur prêts et créances 8 780 9 850\nCharges d'intérêts 357 557 228 765\ncomptabilisés au coût amorti 8 780 9 850\ncomptabilisés en capitaux propres recyclables - -\nDécotes sur crédits restructurés - -\nPertes sur engagements par signature - -\nAutres pertes - -\nAutres produits - -\nCoût du risque de crédit -111 870 -166 067\nPRODUITS ET CHARGES DE COMMISSIONS (2.3)\n(En milliers de DH)\n30/06/2024 30/06/2023\nLIBELLE\nProduits Charges Net Produits Charges Net\nSur opérations avec les établissements de crédit - - - - - -\nSur opérations internes - - - - - -\nSur opérations avec la clientèle 32 887 - 32 887 30 672 - 30 672\nSur opérations sur titres - - - - - -\nSur opérations de change 4 848 1 502 3 345 7 779 1 981 5 798\nSur opérations sur instruments dérivés et autres opérations de hors bilan - - - - - -\nSur moyens de paiement et autres prestations de services bancaires et financiers 215 466 22 872 192 594 194 926 19 476 175 450\nGestion d'OPCVM, fiducie et activités analogues 17 587 144 17 443 14 372 478 13 894\nProduits nets des commissions 270 788 24 519 246 269 247 749 21 935 225 813\nGAINS ET PERTES SUR AUTRES ACTIFS (2.4) DETTES ENVERS LES ÉTABLISSEMENTS DE CRÉDIT (3.1)\n(En milliers de DH) (En milliers de DH)\n30/06/2024 30/06/2023 30/06/2024 31/12/2023\nImmobilisations corporelles et incorporelles d’exploitation -3 547 -7 273 Comptes ordinaires créditeurs 81 063 614 030\nPlus values de cession 35 11 Emprunts de trésorerie au jour le jour -0 -0\nMoins value de cession -3 582 -7 284 Emprunts de trésorerie à terme 292 516 326 783\nTitres de capitaux propres consolidés - - Valeurs données en pension au jour le jour - -\nValeurs données en pension à terme - -\nPlus values de cession - -\nEmprunts financiers 756 876 37 320\nMoins value de cession - -\nAutres 339 779 159 139\nGains ou pertes sur autres actifs -3 547 -7 273 Valeur au bilan 1 470 234 1 137 272\nDETTES ENVERS LA CLIENTÈLE (3.1)\nGAINS OU PERTES NETS SUR INSTRUMENTS FINANCIERS\n(En milliers de DH)\nÀ LA JUSTE VALEUR PAR RÉSULTAT (2.5)\n30/06/2024 31/12/2023\n(En milliers de DH)\nComptes ordinaires créditeurs 38 792 116 36 071 327\n30/06/2024 30/06/2023 Comptes à terme 4 457 603 3 993 319\nDividendes reçus 393 - Comptes d'épargne 10 192 159 10 070 845\nPlus ou moins values latentes ou réalisées sur actif/passif détenus à Autres comptes créditeurs 1 336 300 1 619 935\n63 683 23 932\ndes fins de transaction Valeur au bilan 54 778 179 51 755 426\nPlus ou moins values de cessions réalisées sur instruments de\ncapitaux propres à la juste valeur par résultat 6 656 -1 604 DETTES REPRÉSENTÉES PAR UN TITRE (3.1)\nPlus ou moins values de cessions réalisées sur instruments de dette (En milliers de DH)\n- -\nne remplissant pas les critères SPPI 30/06/2024 31/12/2023\nGains ou pertes nets sur actifs représentatifs de contrats en unités - - Bons de caisse - -\nde compte Certificats de dépôt 3 501 597 3 424 402\nPlus ou moins values latentes ou réalisées sur actif/passif à la juste - - Titres de créances négociables - -\nvaleur par résultat sur option Emprunts obligataires - -\nSolde des opérations de change et instruments financiers assimilés Autres dettes représentées par un titre - -\n(hors résultat des couvertures d'investissements nets des activités 148 152 145 828 Valeur au bilan 3 501 597 3 424 402\nà l'étranger)\nRésultat de la comptabilité de couverture - - ACTIFS FINANCIERS AU COÛT AMORTI (3.2)\nGains ou pertes nets sur instruments financiers à la juste valeur 218 885 168 156 (En milliers de DH)\npar résultat\n30/06/2024 31/12/2023\nPrêts et créances sur les établissements de crédit 5 099 485 6 012 399\nGAINS OU PERTES NETS SUR INSTRUMENTS FINANCIERS Prêts et créances sur la clientèle 54 911 005 51 061 669\nÀ LA JUSTE VALEUR PAR CAPITAUX PROPRES (2.6) Titres de dettes 909 118 1 397 240\n(En milliers de DH) Valeur au bilan 60 919 608 58 471 308\n30/06/2024 30/06/2023 TITRES AU COÛT AMORTI (3.2)\nGains ou pertes nets sur instruments de dettes comptabilisés en - - (En milliers de DH)\ncapitaux propres recyclables\n30/06/2024 31/12/2023\nRémunération des instruments de capitaux propres comptabilisés en\ncapitaux propres non recyclables (dividendes) - - Effets publics et valeurs assimilées -\nDont dividendes sur instruments décomptabilisés au cours de la Obligations et autres titres à revenu fixe 909 118 1 397 240\npériode - - Total 909 118 1 397 240\nGains ou pertes nets sur instruments financiers à la juste valeur Dépréciations - -\npar capitaux propres - - Valeur au bilan 909 118 1 397 240\n11\nPRÊTS ET CRÉANCES SUR LES ÉTABLISSEMENTS PRÊTS ET CRÉANCES SUR LA CLIENTÈLE AU COÛT AMORTI\nDE CRÉDIT ET ASSIMILÉS AU COÛT AMORTI (3.2) (3.2)\n(En milliers de DH) (En milliers de DH)\n30/06/2024 31/12/2023 30/06/2024 31/12/2023\nEtablissements de crédit Opérations avec la clientèle\nComptes et prêts 3 513 483 3 455 408 Créances commerciales 13 699 276 12 320 104\ndont comptes ordinaires débiteurs non douteux (1) 3 513 483 3 455 408 Autres concours à la clientèle 39 227 854 37 016 848\ndont comptes et prêts au jour le jour non douteux (1) - - Valeurs reçues en pension 756 409 1 087 882\nTitres reçus en pension livrée - -\nValeurs reçues en pension 1 010 448 2 201 870\nPrêts subordonnés - -\nTitres reçus en pension livrée - -\nCréances nées d’opérations d’assurance directe - -\nPrêts subordonnés - - Créances nées d’opérations de réassurance - -\nAutres prêts et créances 579 391 359 336 Avances en comptes courants d'associés - -\nValeur brute 5 103 322 6 016 614 Comptes ordinaires débiteurs 3 036 694 2 733 370\nDépréciations -3 837 -4 215 Valeur brute 56 720 233 53 214 603\nDépréciations -3 716 834 -3 627 722\nValeur nette des prêts et créances auprès des établissements de\ncrédit 5 099 485 6 012 399 Valeur nette des prêts et créances auprès de la clientèle 53 003 400 49 586 881\nOpérations internes au Crédit du Maroc - - Opérations de location-financement - -\nComptes ordinaires - - Location-financement immobilier 617 059 494 767\nLocation-financement mobilier, location simple et opérations assimilées 1 435 087 1 185 098\nComptes et avances à terme - -\nValeur brute 2 052 147 1 679 865\nPrêts subordonnés - - Dépréciations -144 542 -148 678\nTotal prêts et créances internes au Crédit du Maroc - - Valeur nette des opérations de location-financement 1 907 605 1 531 187\nValeur au bilan 5 099 485 6 012 399 Valeur au bilan 54 911 005 51 061 669\nRÉPARTITION DES CRÉANCES, ENGAGEMENTS ET DÉPRÉCIATIONS PAR BUCKETS SOUS IFRS 9 (3.2)\n(En milliers de DH)\nCréances et engagements Dépréciations\n30/06/2024\nBucket 1 Bucket 2 Bucket 3 Bucket 1 Bucket 2 Bucket 3\nActifs financiers à la juste valeur par capitaux propres 1 609 788 - - 978 - -\nPrêts et créances sur les établissements de crédit - - - - - -\nPrêts et créances sur la clientèle - - - - - -\nTitres de dettes 1 609 788 - - 978 - -\nActifs financiers au coût amorti 55 081 143 5 368 573 4 333 784 177 904 428 461 3 257 528\nPrêts et créances sur les établissements de crédit et banques centrales 4 878 289 225 034 - 3 836 1 -\nPrêts et créances sur la clientèle 49 293 736 5 143 539 4 333 784 174 068 428 460 3 257 528\nTitres de dettes 909 118 - - - - -\nActifs financiers 56 690 932 5 368 573 4 333 784 178 883 428 461 3 257 528\nEngagements Hors bilan 4 559 122 233 927 160 463 15 268 41 411 155 776\nCréances et engagements Dépréciations\n31/12/2023\nBucket 1 Bucket 2 Bucket 3 Bucket 1 Bucket 2 Bucket 3\nActifs financiers à la juste valeur par capitaux propres 1 055 779 - - 1 500 - -\nPrêts et créances sur les établissements de crédit - - - - - -\nPrêts et créances sur la clientèle - - - - - -\nTitres de dettes 1 055 779 - - 1 500 - -\nActifs financiers au coût amorti 52 306 681 5 650 246 4 294 996 174 488 417 444 3 188 682\nPrêts et créances sur les établissements de crédit et banques centrales 5 791 580 225 034 - 4 202 13 -\nPrêts et créances sur la clientèle 45 117 861 5 425 212 4 294 996 170 287 417 431 3 188 682\nTitres de dettes 1 397 240 - - - - -\nActifs financiers 53 362 459 5 650 246 4 294 996 175 988 417 444 3 188 682\nEngagements Hors bilan 4 073 638 265 724 213 142 14 653 32 112 185 992\nACTIFS FINANCIERS À LA JUSTE VALEUR PAR CAPITAUX PROPRES (3.3)\n(En milliers de DH)\n30/06/2024 31/12/2023\nValeur au bilan Gains latents Pertes latentes Valeur au bilan Gains latents Pertes latentes\nInstruments de dettes comptabilisés à la juste valeur par capitaux propres recyclables 1 608 810 1 938 - 1 054 279 548 -\nInstruments de capitaux propres comptabilisés à la juste valeur par capitaux propres\n- - - - - -\nnon recyclables\nTotal 1 608 810 1 938 - 1 054 279 548 -\nINSTRUMENTS DE DETTES COMPTABILISÉS À LA JUSTE COMPTES DE RÉGULARISATION, AUTRES ACTIFS\nVALEUR PAR CAPITAUX PROPRES RECYCLABLES (3.3) ET PASSIFS (3.4)\n(En milliers de DH) (En milliers de DH)\nValeur au Gains Pertes 30/06/2024 31/12/2023\n30/06/2024\nbilan latents latentes\nDépôts de garantie versés et cautionnements constitués 2 872 2 955\nEffets publics et valeurs assimilées 1 606 043 1 938 -\nComptes de règlement relatifs aux opérations sur titres 24 082 -\nObligations et autres titres à revenu fixe 2 767 - -\nTotal des titres de dettes 1 608 810 1 938 - Comptes d'encaissement - -\nPrêts et créances sur les établissements de crédit - - - Part des réassureurs dans les provisions techniques - -\nPrêts et créances sur la clientèle - - -\nProduits à recevoir et charges comptabilisées d'avance 85 386 16 185\nTotal des prêts et créances - - -\nTotal Instruments de dettes comptabilisés à la juste valeur Autres débiteurs et actifs divers 385 507 403 139\n1 608 810 1 938 -\npar capitaux propres recyclables TOTAL DES COMPTES DE REGULARISATION ET ACTIFS DIVERS 497 847 422 280\nImpôts -761 -\nDépôts de garantie reçus - -\nGains et pertes comptabilisés directement en capitaux Comptes de règlement relatifs aux opérations sur titres 5 619 79 856\npropres sur instruments de dettes comptabilisés à la juste 1 178 -\nvaleur par capitaux propres recyclables (nets d'impôts) Comptes d'encaissement - -\ncharges à payer et produits constatés d'avance 347 895 367 800\nValeur au Gains Pertes\n31/12/2023 bilan latents latentes Autres créditeurs et passifs divers 1 939 306 1 443 901\nEffets publics et valeurs assimilées 1 063 414 548 - TOTAL DES COMPTES DE REGULARISATION ET PASSIFS DIVERS 2 292 820 1 891 556\nObligations et autres titres à revenu fixe -9 135 - -\nTotal des titres de dettes 1 054 279 548 -\nPrêts et créances sur les établissements de crédit - - -\nPrêts et créances sur la clientèle - - -\nTotal des prêts et créances - - -\nTotal Instruments de dettes comptabilisés à la juste valeur\n1 054 279 548 -\npar capitaux propres recyclables\nImpôts -211 -\nGains et pertes comptabilisés directement en capitaux\npropres sur instruments de dettes comptabilisés à la juste 337 -\nvaleur par capitaux propres recyclables (nets d'impôts)\n12\nwww.creditdumaroc.ma\nAUTRES ACTIFS FINANCIERS À LA JUSTE VALEUR CONTRATS DE LOCATION - ACTIFS AU TITRE DE DROITS\nPAR RÉSULTAT (3.5) D’UTILISATION : VARIATION (PRENEUR) (3.6)\n(En milliers de DH) (En milliers de DH)\n30/06/2024 31/12/2023 31/12/2023 Augmentations Diminutions 30/06/2024\n(acquisitions) (cessions)\nActions et autres titres à revenu variable 188 257 195 774\nImmobilier\nTitres de participation non consolidés 34 334 34 335\nValeur brute 105 212 251 - 105 463\nTotal Instruments de capitaux propres à la juste valeur par résultat 222 592 230 109 Amortissements et\n-54 101 4 395 -5 995 -55 701\ndépréciations\nACTIFS FINANCIERS DÉTENUS À DES FINS DE TRANSACTION Total Immobilier 51 111 4 647 -5 995 49 762\nMobilier\n(3.5) Valeur brute 17 095 1 509 - 18 604\n(En milliers de DH) Amortissements et -9 334 -1 771 -11 105\ndépréciations\n30/06/2024 31/12/2023 Total Mobilier 7 761 1 509 -1 771 7 499\nIntruments de capitaux propres - -\nTotal Droits d'utilisation 58 872 6 156 -7 766 57 261\nActions et autres titres à revenu variable - -\nTitres de dettes 3 474 711 2 339 859\nACTIFS AU TITRE DE DROITS D’UTILISATION (PRENEUR (3.6)\nEffets publics et valeurs assimilées 2 535 773 2 014 378\nObligations et autres titres à revenu fixe 938 938 325 480 (En milliers de DH)\nOPCVM - - 30/06/2024 31/12/2023\nPrêts et créances - - Immobilisations corporelles 1 491 718 1 495 747\nCréances sur les établissements de crédit - -\ndont : Droits d'utilisation des contrats de location 57 261 58 872\nCréances sur la clientèle - -\nTitres reçus en pension livrée - -\nValeurs reçues en pension - - PASSIFS AU TITRE DE LA DETTE LOCATIVE (3.6)\nInstruments dérivés 17 133 26 942 (En milliers de DH)\nValeur au bilan 3 491 844 2 366 801 30/06/2024 31/12/2023\nComptes de régularisation et autres passifs 2 337 031 1 891 556\nAUTRES ACTIFS FINANCIERS À LA JUSTE VALEUR\ndont : Dettes locatives 60 485 62 303\nPAR RÉSULTAT (3.5)\n(En milliers de DH)\nDÉTAIL DES CHARGES DE CONTRATS DE LOCATION (3.6)\n30/06/2024 31/12/2023\n(En milliers de DH)\nActifs financiers détenus à des fins de transaction 3 491 844 2 366 801\nAutres actifs financiers à la juste valeur par résultat 222 592 230 109 30/06/2024 31/12/2023\nInstruments de capitaux propres 222 592 230 109 Intérêts et charges assimilées -357 557 -595 229\nInstruments de dettes ne remplissant pas les critères SPPI - - dont : Charges d'intérêts sur dettes locatives -950 -1 000\nCharges générales d'exploitation -649 974 -1 365 976\nActifs représentatifs de contrats en unités de compte - -\ndont : Charges relatives aux contrats de location court terme et de\nActifs financiers à la juste valeur par résultat sur option - - faible valeur 8 374 -6 097\nValeur au bilan 3 714 436 2 596 910 Dotations aux amortissements des immobilisations corporelles -132 295 -232 914\nDont Titres prêtés - - dont : Dotations aux amortissements sur droits d'utilisation -7 766 -18 432\nIMMOBILISATIONS CORPORELLES ET INCORPORELLES (3.6)\n(En milliers de DH)\n30/06/2024 31/12/2023\nValeur comptable totale Valeur comptable totale Valeur comptable totale Valeur comptable totale\n(de toutes les immo incorporelles) (de toutes les immo corporelles) (de toutes les immo incorporelles) (de toutes les immo corporelles)\nPertes de valeur comptabilisées en résultat - - - -\nReprises de pertes de valeur en résultat - - - -\nSolde de clôture 1 512 368 2 665 065 1 404 112 2 622 287\nCumul des dépréciations - - - -\nCumul des amortissements 687 415 1 173 348 608 131 1 126 540\nActifs détenus dans le cadre d'un contrat de location-\n- - - -\nfinancement\nActifs loués en location-simple - - - -\nPROVISIONS PASSIF (3.7)\n(En milliers de DH)\nRisques légaux et Obligations au titre des Engagements de prêts\nContrats déficitaires Autres provisions Valeur comptable totale\nfiscaux avantages postérieurs à l'emploi et garanties (Les EPS)\nSolde de clôture au 31.12.2023 95 843 91 437 232 756 - 145 919 565 955\nDotations 17 498 2 878 9 915 17 773 48 063\nMontants utilisés 12 734 13 4 841 17 588\nMontants non utilisés repris au cours de la période 4 722 30 216 4 821 39 759\nAutres mouvements -1 346 -1 346\nSolde de clôture au 30.06.2024 95 884 92 956 212 455 - 154 029 555 324\nIMPÔTS EXIGIBLES ET DIFFÉRÉS (3.8) PASSIFS FINANCIERS À LA JUSTE VALEUR PAR RÉSULTAT\n(En milliers de DH) (3.9)\nImpôts courants et impôts différés 30/06/2024 31/12/2023\n(En milliers de DH)\nImpôts courants 4 807 3 253\nImpôts différés 135 551 159 789 30/06/2024 31/12/2023\nActifs d’impôts courants et différés 140 358 163 043 Passifs financiers détenus à des fins de transaction 6 901 15 984\nImpôts courants 100 429 125 097\nPassifs financiers à la juste valeur par résultat sur option - -\nImpôts différés 14 664 17 885\nPassifs d’impôts courants et différés 115 092 142 982 Valeur au bilan 6 901 15 984\nCharge d'impôts courants 297 557 396 449\nCharge nette d'impôts différés de l'exercice 19 902 -16 367\nCharges nette de l’impôt sur les bénéfices 317 458 380 083\nPASSIFS FINANCIERS DÉTENUS À DES FINS DE\nLe taux effectif d'impôt 30/06/2024 31/12/2023 TRANSACTION (3.9)\nRésultat net 390 835 498 225 (En milliers de DH)\nCharges d’impôt sur les bénéfices 317 458 380 083\n30/06/2024 31/12/2023\nTaux d'impôt effectif moyen en % 44,82% 43,27%\nTitres vendus à découvert\nAnalyse du taux effectif d'impôt 30/06/2024 31/12/2023 Titres donnés en pension livrée\nTaux d'impôt en vigueur en % 39,25% 38,50% Dettes représentées par un titre\nDifférentiel de taux d'imposition des entités étrangères - -\nDettes envers la clientèle\nImposition forfaitaire - -\nDifférences permanentes - - Dettes envers les établissements de crédit\nChangement de taux - - Instruments dérivés 6 901 15 984\nDéficit reportable - -\nValeur au bilan 6 901 15 984\nAutres éléments 5,57% 4,77%\nTaux d'impôt effectif moyen 44,82% 43,27%\n13\nTRANSFERT PAR BUCKETS DES ACTIFS FINANCIERS AU COÛT AMORTI : PRÊTS ET CRÉANCES CLIENTÈLE\n(En milliers de DH)\nActifs sains\nActifs soumis à une ECL 12 mois Actifs soumis à une ECL Actifs dépréciés (Bucket 3) Total\n(Bucket 1) à maturité (Bucket 2)\nCorrection de Correction de Correction de\nValeur comp- Correction de Valeur Valeur Valeur comp- Valeur nette\nValeur pour Valeur pour Valeur pour pertes\ntable brute Valeur pour pertes comptable brute comptable brute table brute (a) comptable (a)+(b)\npertes pertes (b)\nAu 31 décembre 2023 45 117 861 -170 287 5 425 212 -417 431 4 294 996 -3 188 682 54 838 069 -3 776 400 51 061 669\nTransfert d'actifs en cours de vie d'un\n-335 851 -15 025 -8 554 -18 541 344 405 -419 627 - -453 192\nbucket à l'autre\nTransfert de ECL 12 mois ( Bucket 1) vers ECL\n-654 250 8 754 654 250 -65 130 - -56 375\nMaturité ( Bucket 2)\nRetour de ECL Maturité ( Bucket 2) vers ECL\n421 016 -24 459 -421 016 4 141 - -20 318\n12 mois ( Bucket 1)\nTransfert vers ECL Maturité Dépréciés\n-113 527 712 -285 511 48 099 399 038 -451 763 - -402 952\n(Bucket 3)\nRetour de ECL Maturité Dépréciés ( Bucket\n3) vers ECL Maturité ( Bucket 2) / ECL 12 10 909 -33 43 723 -5 651 -54 633 32 136 - 26 453\nmois (Bucket 1)\nTotal apès transfert 44 782 010 -185 311 5 416 658 -435 972 4 639 401 -3 608 309 54 838 069 -4 229 592 50 608 477\nVariation des Valeurs comptables brutes et\n4 511 726 11 243 -273 118 7 512 -305 617 350 781 3 932 991 369 537\ndes corrections de valeur pour pertes\nNouvelles production : achat, octroi,\n15 730 721 -34 894 874 453 -44 772 16 605 173 -79 666\norganisation\nDécomptabilisation : cessoin,\n-10 235 342 17 880 -1 006 394 84 226 -451 763 271 220 -11 693 498 373 327\nrembourssement, arrivée à échéance…\nPassage à perte -6 069 6 069 -6 069 6 069\nModification de flux sur restructurations pour\n- - - - - - - -\ncause de difficultés financières\nEvolution des paramètres de risque de crédit\n- - - -\ndes modéles sur la période\nChangements dans le modèle / méthodologie - - - -\nVariation de périmètre - - - - - - - -\nAutres -983 653 28 257 -141 178 -31 942 152 214 73 492 -972 616 69 807\nTotal 49 293 736 -174 068 5 143 539 -428 460 4 333 784 -3 257 528 58 771 060 -3 860 056 54 911 005\nVariations de la Valeur comptable - - - - - - - - -\nAttribuables à des modalités d’évaluation\ncomptable spécifiques (sans impact\n-\nsignificatif sur le montant de correction de\nvaleur pour perte)(1)\nAu 30 juin 2024 49 293 736 -174 068 5 143 539 -428 460 4 333 784 -3 257 528 58 771 060 -3 860 056 54 911 005\nEncours contractuels des actifs financiers\nqui ont été sortis du bilan au cours de la\n- - - - - - - - -\npériode et qui font encore l’objet de mesures\nd’exécution\nINFORMATIONS SUR LES CONTRATS DE LOCATION FINANCEMENT\nLes contrats de Leasing sont classés en tant que contrats date à laquelle l’option peut être levée En effet, la valeur La valeur actualisée des paiements minimaux au titre de la\nde location financement La quasi-totalité des risques et résiduelle est de 1% du montant de financement pour le location s’élève à la totalité de la juste valeur de l’actif loué.\ndes avantages inhérents à la propriété est transférée au mobilier et de 10% pour l’immobilier. Dans le bilan, les actifs donnés en location sont\npreneur locataire. La durée du contrat de location couvre la majeure partie de comptabilisés comme des créances pour un montant égal\nLe contrat de location donne au preneur l’option d’acheter la vie économique de l’actif loué. à l’investissement net dans le contrat de location.\nl’actif à un prix suffisamment inférieur à sa juste valeur à la\n(En milliers de DH)\nPour le Bailleur\nDurée résiduelle Valeur actualisée des paiements minimaux Correction de valeur cumulée des paiements minimaux\nInvestissement brut total Produits financiers non acquis\nà recevoir au titre de la location au titre de la location non recouvrables\n≤ 1 an 714 049 592 079 121 970 571 239\n> 1 an ≤ 5 ans 1 480 640 1 282 346 198 294 1 184 512\n> 5 ans 232 968 207 048 25 919 186 374\nTOTAL 2 427 657 2 081 474 346 183 1 942 125\nINFORMATIONS RELATIVES AUX PARTIES LIÉES\n(En milliers de DH)\nMontants à payer aux parties liées et Principaux dirigeants de l'entité Entités contrôlées par la\nSociété-mère Filiales Autres parties liées Total\nmontants à en recevoir ou de sa société-mère même société mère\nActifs : prêts et avances 152 238 216 080 - 181 721 - 550 039\nInstruments de capitaux propres - - - - - -\nAutres créances - - - - - -\nTotal des actifs 152 238 216 080 - 181 721 - 550 039\nPassifs : dépôts et emprunts - 2 040 102 - 3 742 - 2 043 844\nAutres passifs financiers - - - - - -\nTitres de dette - - - - - -\nPassifs subordonnés - - - - - -\nPaiements fondés sur des actions - 679 - - - 679\nAutres passifs - 64 789 - - - 64 789\nTotal des passifs - 2 105 570 - 3 742 - 2 109 312\nGaranties émises par le groupe - 1 164 976 - - - 1 164 976\nGaranties reçues par le groupe - - - - - -\nDépréciations des créances douteuses - - - - - -\nCharges et produits générés par des Principaux dirigeants de l'entité Entités contrôlées par la\nSociété-mère Filiales Autres parties liées Total\ntransactions entre parties liées ou de sa société-mère même société mère\nTotal des charges dont :\nCharges d'intérêts - 31 520 - - - 31 520\nHonoraires et commissions - 25 268 - - - 25 268\nAutres charges - 56 - - - 56\nTotal des produits dont : - 6 195 - - - 6 195\nProduits d'intérêts 1 761 69 153 - 1 585 - 72 499\nHonoraires et commissions 1 694 1 255 - 1 443 - 4 392\nAutres produits 67 - - 141 - 208\nProduits de dividendes - 108 - - - 108\nLes parties liées au Crédit du Maroc sont les filiales consolidées, la société mère Holmarcom ainsi que les entités contrôlées par le groupe Holmarcom.\nConformément aux mécanismes financiers internes au Crédit du Maroc, les opérations conclues entre Crédit du Maroc et ses filiales sont présentées au bilan et au compte de résultat\nen opérations internes au Crédit du Maroc (notes 2 2 “Produits et charges d’intérêts”, 2 3 “Produits et charges de commissions” et 3 2 “Actifs financiers au coût amorti” et 3 4 « Comptes\nde régularisation Autres Actifs et Passifs ».\n14\nwww.creditdumaroc.ma\nVENTILATION DES ACTIFS ET PASSIFS FINANCIERS PAR ÉCHÉANCE CONTRACTUELLE\n(En milliers de DH)\n30/06/2024\n≤ 3 mois > 3 mois à ≤ 1 an > 1 an à ≤ 5 ans > 5 ans Indéterminée Total\nCaisse, banques centrales 1 848 172 - - - - 1 848 172\nActifs financiers à la juste valeur par résultat 16 315 1 758 117 982 483 956 703 818 3 714 436\nInstruments dérivés de couverture - - - - - -\nActifs financiers à la juste valeur par capitaux propres 943 920 550 756 49 920 29 117 35 096 1 608 810\nActifs financiers au coût amorti 7 571 791 4 828 923 13 453 988 20 818 306 14 246 600 60 919 608\nEcart de réévaluation des portefeuilles couverts en taux - -\nTotal Actifs financiers par échéance 10 380 198 7 137 797 14 486 391 21 804 126 14 282 514 68 091 025\nBanques centrales - - - - 844 844\nPassifs financiers à la juste valeur par résultat 6 901 - - - - 6 901\nInstruments dérivés de couverture - - - - - -\nPassifs financiers au coût amorti 2 031 878 3 444 135 165 662 - 50 606 737 56 248 413\nDettes subordonnées 25 929 - - 1 250 000 - 1 275 929\nEcart de réévaluation des portefeuilles couverts en taux - -\nTotal Passifs financiers par échéance 2 064 708 3 444 135 165 662 1 250 000 50 607 581 57 532 087\n31/12/2023\n≤ 3 mois > 3 mois à ≤ 1 an > 1 an à ≤ 5 ans > 5 ans Indéterminée Total\nCaisse, banques centrales 2 265 791 - - - - 2 265 791\nActifs financiers à la juste valeur par résultat 26 124 1 120 612 273 720 945 527 818 2 366 801\nInstruments dérivés de couverture - - - - - -\nActifs financiers à la juste valeur par capitaux propres 184 526 514 569 318 204 - 36 980 1 054 279\nActifs financiers au coût amorti 8 866 126 4 436 785 8 916 762 21 338 632 14 913 002 58 471 308\nEcart de réévaluation des portefeuilles couverts en taux - -\nTotal Actifs financiers par échéance 11 342 568 6 071 965 9 508 686 22 284 159 14 950 800 64 158 179\nBanques centrales - - - - 884 884\nPassifs financiers à la juste valeur par résultat 15 984 - - - - 15 984\nInstruments dérivés de couverture - - - - - -\nPassifs financiers au coût amorti 2 170 834 2 204 506 108 745 - 48 408 613 52 892 698\nDettes subordonnées 969 - - 1 250 000 - 1 250 969\nEcart de réévaluation des portefeuilles couverts en taux - -\nTotal Passifs financiers par échéance 2 187 788 2 204 506 108 745 1 250 000 48 409 497 54 160 536\nINFORMATION SECTORIELLE ENGAGEMENTS DE PRÊTS, GARANTIES FINANCIÈRES\nL’information sectorielle de Crédit du Maroc, filiale du Groupe Holmarcom S A , ET AUTRES ENGAGEMENTS AU 30/06/2024\n(En milliers de DH)\nest articulée autour des pôles d’activités suivants :\nMontants\nBANQUE MAROC ET INTERNATIONALE\nEngagements de prêt 8 111 187\ncomprenant Crédit du Maroc SA, Crédit du Maroc capital Bourse, Crédit du Donnés : 8 111 187\nMaroc Patrimoine, Crédit du Maroc Assurance, Société Financière et Immobilière Administrations centrales -\nMarocaine et Crédit du Maroc Internationale ; Etablissements de crédit 11 757\nInstitutions non établissements de crédit -\nSOCIÉTÉS DE FINANCEMENT SPÉCIALISÉES\nGrandes entreprises 7 999 640\ncomprenant Crédit du Maroc Leasing et Factoring. Clientèle de détail 99 789\nReçus : -\nChacun de ces métiers enregistre les charges et produits, actifs et passifs qui lui Garanties financières 4 991 576\nsont rattachés après élimination des transactions intragroupe. Données : 2 753 733\n(En milliers de DH) Administrations centrales -\nEtablissements de crédit 619 397\nSociétés de\nBanque Maroc et Institutions non établissements de crédit -\nCompte de Résultat Juin 2024 financement Eliminations Total\ninternationale spécialisés Grandes entreprises 2 110 923\nClientèle de détail 23 412\nMarge d'intérêts 1 154 918 31 555 - 1 186 473\nReçues : 2 237 843\nMarge sur commissions 247 374 -55 -1 051 246 269\nAdministrations centrales -\nProduit net bancaire 1 646 314 37 262 -77 598 1 605 979\nEtablissements de crédit 2 237 843\nCharges de fonctionnement -641 328 -15 029 6 383 -649 974\nInstitutions non établissements de crédit -\nRésultat d'exploitation 765 379 17 675 -71 215 711 839\nGrandes entreprises -\nRésultat net 449 841 10 623 -69 629 390 835\nClientèle de détail -\nRésultat net part groupe 449 841 10 623 -69 629 390 835\nDérivés de crédit reçus -\n(En milliers de DH) Autres engagements -\nSociétés de Donnés -\nBanque Maroc et\nBilan Juin 2024 internationale financement Eliminations Total Reçus -\nspécialisés Engagements et garanties financières en défaut -\nTotal Bilan 71 682 143 2 218 116 -2 854 358 71 045 901 – Engagements de prêt donnés : -\ndont - - - – Garanties financières données : -\nÉléments de l'Actif - - - 66 825 453 – Autres engagements donnés à une autre contrepartie : -\nActifs financiers à la juste valeur par\n4 047 589 - -333 154 3 714 436\nrésultat\nActifs financiers à la juste valeur par\ncapitaux propres 1 608 810 - -0 1 608 810 ÉVOLUTION DU CAPITAL ET RÉSULTAT PAR ACTION\nPrêts et créances sur les Etablissemts de\ncrédit et assimilés,au coût amorti 7 358 393 3 -2 258 911 5 099 485 COMPOSITION DU CAPITAL AU 30 JUIN 2024\nPrêts et créances sur la clientèle, au coût\namorti 52 888 217 2 085 825 -63 037 54 911 005 Au 30 juin 2024, la répartition du capital et des droits de vote est la suivante :\nImmobilisations corporelles 1 616 696 3 571 -128 549 1 491 718\nÉléments du Passif - - - 56 248 413 Actionnaires Nombred’actions % du capital % des droits de vote\nDettes envers les Établissement de crédit A - ACTIONNAIRES MAROCAINS\n1 833 609 1 679 455 -2 042 831 1 470 234\net assimilés HOLMARCOM FINANCE COMPANY 7 171 545 65,91 65,91\nDettes envers la clientèle 54 897 147 161 149 -280 117 54 778 179 ATLANTASANAD 1 394 744 12,82 12,82\nCapitaux propres 7 360 844 151 595 -463 459 7 048 980 WAFA ASSURANCE 1 168 523 10,74 10,74\nAUTRES 1 146 402 10,53 10,53\nOPÉRATIONS EFFECTUÉES EN DEVISES Total 10 881 214 100,00 100,00\n(En milliers de DH)\nLa valeur nominale des actions est de 100 DH. Ces actions sont entièrement\n30/06/2024 31/12/2023\nlibérées.\nActif Passif Actif Passif\nA la connaissance de la société, il n’existe pas d’autre actionnaire détenant\nEURO 1 338 318 1 343 239 1 185 155 1 185 155\ndirectement ou indirectement 5% ou plus du capital ou des droits de vote.\nUSD 1 086 751 1 086 751 899 196 899 196\nGBP 14 846 14 846 13 361 13 361 DIVIDENDES\nJPY 185 185 20 20\nAu titre de l’exercice 2023, le conseil de surveillance décide de proposer aux\nAutres devises 13 055 8 134 22 395 22 395\nactionnaires un dividende brut par action de 34,20 DH.\nTOTAL 2 453 155 2 453 155 2 120 127 2 120 127\n2023 2022 2021\nDividendes (en dirhams)\nDividende par action 34,20 27,00 25,90\nRésultat net par action (en dirhams)\nRésultat net part du groupe par action 46,23 37,15 57,66\n15\nACTIFS FINANCIERS VALORISÉS À LA JUSTE VALEUR\n(En milliers de DH) (En milliers de DH)\n30/06/2024 a P d c in ir te dsii s fx ets rm nc upo ta m iot qré u e ucs rh n e s dé t su ses r s d oV f e boa s snl o eddr roéi vs ne aa n bst éui lo eern ss fo d oV n o ba d n sl éo ener réi v es s aa su b t r ni lo d o en n se s 31/12/2023 a P d c in ir te dsii s fx ets rm nc upo ta m iot qré u e ucs rh n e s dé t su ses r s d oV f e boa s snl o eddr roéi vs ne aa n bst éui lo eern ss fo d oV n o ba d n sl éo ener réi v es s aa su b t r ni lo d o en n se s\nNiveau 1 Niveau 2 Niveau 3 Niveau 1 Niveau 2 Niveau 3\nActifs financiers détenus à des fins de Actifs financiers détenus à des fins\n3 491 844 - 3 491 844 - 2 366 801 - 2 366 801 -\ntransaction de transaction\nCréances sur les établissements de Créances sur les établissements de\n- -\ncrédit crédit\nCréances sur la clientèle - Créances sur la clientèle -\nTitres reçus en pension livrée - Titres reçus en pension livrée -\nValeurs reçues en pension - Valeurs reçues en pension -\nTitres détenus à des fins de Titres détenus à des fins de\n3 475 529 - 3 475 529 - 2 340 677 - 2 340 677 -\ntransaction transaction\nEffets publics et valeurs assimilées 2 536 591 2 536 591 Effets publics et valeurs assimilées 2 014 378 2 014 378\nObligations et autres titres à revenu Obligations et autres titres à revenu\n938 938 938 938 326 298 326 298\nfixe fixe\nOPCVM - - OPCVM - -\nActions et autres titres à revenu Actions et autres titres à revenu\n- - - -\nvariable variable\nInstruments dérivés 16 315 - 16 315 - Instruments dérivés 26 124 - 26 124 -\nAutres actifs financiers à la juste Autres actifs financiers à la juste\n222 592 - - 222 592 230 109 - - 230 109\nvaleur par résultat valeur par résultat\nInstruments de capitaux propres à la Instruments de capitaux propres à la\n38 082 - - 38 082 38 728 - - 38 728\njuste valeur par résultat juste valeur par résultat\nActions et autres titres à revenu Actions et autres titres à revenu\n- -\nvariable variable\nTitres de participation non consolidés 38 082 38 082 Titres de participation non consolidés 38 728 38 728\nInstruments de dettes ne remplissant\npas les critères SPPI 184 510 - - 184 510 Instruments de dettes ne remplissant 191 380 - - 191 380\npas les critères SPPI\nCréances sur les établissements de\ncrédit - - Créances sur les établissements de - -\ncrédit\nCréances sur la clientèle - -\nCréances sur la clientèle - -\nTitres de dettes - - - -\nTitres de dettes - - - -\nEffets publics et valeurs assimilées - -\nObligations et autres titres à revenu Effets publics et valeurs assimilées - -\n- -\nfixe Obligations et autres titres à revenu\n- -\nOPCVM 184 510 - 184 510 fixe\nActifs représentatifs de contrats en OPCVM 191 380 - 191 380\n- - - -\nunités de compte Actifs représentatifs de contrats en\n- - - -\nEffets publics et valeurs assimilées - unités de compte\nObligations et autres titres à revenu Effets publics et valeurs assimilées -\n-\nfixe Obligations et autres titres à revenu\n-\nActions et autres titres à revenu fixe\n-\nvariable Actions et autres titres à revenu\n-\nOPCVM - variable\nActifs financiers à la juste valeur par OPCVM -\n- - - -\nrésultat sur option Actifs financiers à la juste valeur par\n- - - -\nCréances sur les établissements de résultat sur option\n-\ncrédit Créances sur les établissements de\n-\nCréances sur la clientèle - crédit\nTitres à la juste valeur par résultat - - - - Créances sur la clientèle -\nsur option\nTitres à la juste valeur par résultat\nEffets publics et valeurs assimilées - - - - -\nsur option\nObligations et autres titres à revenu\n- Effets publics et valeurs assimilées -\nfixe\nObligations et autres titres à revenu\nActifs financiers à la juste valeur par -\n1 608 810 - 1 608 810 - fixe\ncapitaux propres\nActifs financiers à la juste valeur par\nInstruments de capitaux propres 1 054 279 - 1 054 279 -\n- - - - capitaux propres\ncomptabilisés en capitaux\nInstruments de capitaux propres\npropres non recyclables - - - - -\ncomptabilisés en capitaux\nActions et autres titres à revenu\n- propres non recyclables -\nvariable\nActions et autres titres à revenu\nTitres de participation non consolidés - variable -\nInstruments de dettes comptabilisés - - - - Titres de participation non consolidés -\nen capitaux propres recyclables\nInstruments de dettes comptabilisés\nCréances sur les établissements de 1 054 279 - 1 054 279 -\n- en capitaux propres recyclables\ncrédit\nCréances sur les établissements de\nCréances sur la clientèle - crédit -\nTitres de dettes - - - - Créances sur la clientèle -\nTitres de dettes - - - -\nEffets publics et valeurs assimilées 1 608 810 1 608 810\nEffets publics et valeurs assimilées 1 054 279 1 054 279\nObligations et autres titres à revenu\n- - Obligations et autres titres à revenu\nfixe\nfixe\nInstruments dérivés de couverture - Instruments dérivés de couverture -\nTotal Actifs financiers valorisés à la\nTotal Actifs financiers valorisés à la 3 651 188 - 3 421 079 230 109\n5 323 246 - 5 100 654 222 592 juste valeur\njuste valeur\nTransferts issus du Niveau 1 : Prix\nTransferts issus du Niveau 1 : Prix\ncotés sur des marchés actifs pour\ncotés sur des marchés actifs pour des\ndes instruments identiques\ninstruments identiques\nTransferts issus du Niveau 2 :\nTransferts issus du Niveau 2 :\nValorisation fondée sur des données\nValorisation fondée sur des données\nobservables\nobservables\nTransferts issus du Niveau 3 :\nTransferts issus du Niveau 3 :\nValorisation fondée sur des données\nValorisation fondée sur des données\nnon observables\nnon observables\nTotal des transferts vers chacun des\nTotal des transferts vers chacun des - - -\n- - - niveaux\nniveaux\n16\nwww.creditdumaroc.ma\nAVANTAGES AU PERSONNEL\nL’engagement actualisé est calculé selon la méthode des unités de crédits INDEMNITÉS DE FIN CONTRAT DE TRAVAIL\nprojetées en tenant compte des hypothèses actuarielles, des augmentations Indemnité de départ volontaire\nde salaires, de l’âge de départ en retraite, de la mortalité, de la rotation du\n• Régie par un protocole d’accord au niveau du GPBM, l’indemnité de départ\npersonnel ainsi que des taux d’actualisation.\nvolontaire permet aux salariés, et après accord du Directoire, de faire valoir\nLes modifications d’hypothèses actuarielles, ou la différence entre ces leur droit à la retraite anticipée selon les critères d’éligibilité suivants :\nhypothèses et la réalité, donnent lieu à des écarts actuariels relatifs aux\n- à partir de 50 ans révolus pour les femmes.\navantages postérieurs à l’emploi et qui sont comptabilisés en capitaux propres\n- à partir de 55 ans révolus pour les hommes.\nselon la méthode du SORIE, par contre, pour les avantages à long terme et les\n- avoir une ancienneté minimum de 21 ans de service.\nindemnités de fin de contrat de travail, ils continueront à être comptabilisés\ndirectement en résultat. • Le montant de l’indemnité est calculé en fonction du salaire au moment du\ndépart et d’un barème basé sur l’âge du collaborateur.\nLe calcul est effectué par individu et la population est sélectionnée à la date de\nl’arrêté. • Le montant de l’engagement dépend :\n- de l’évolution du salaire,\nRÉGIME À PRESTATIONS DÉFINIES : - de l’âge au moment du départ (barème),\nPrime fin de carrière - de la proportion des collaborateurs intéressés par le départ volontaire,\n• Prime servie aux collaborateurs au moment de leur départ en retraite ou en cas - de la probabilité de survie (table de mortalité),\nde décès ; - de la probabilité de présence (turn over),\n• L’ancienneté minimum requise est de 20 ans ; - du nombre d’années restant à l’octroi et du taux d’actualisation.\n• Le montant de la prime est calculé en fonction du salaire au moment de la (En milliers de DH)\nretraite et d’un coefficient déterminé par le nombre d’années d’ancienneté ; 30/06/2024 31/12/2023\n• Le montant de l’engagement dépend : Provisions pour prime de fin carrière 42 661 41 687\n- de l’évolution du salaire, Provisions pour indemnité de départ volontaire 9 494 9 374\nProvisions pour prime de fidélité 40 640 40 034\n- du nombre d’années d’ancienneté,\nTotal 92 794 91 095\n- de la probabilité de survie (table de mortalité),\n- de la probabilité de présence (turn over), 30/06/2024 31/12/2023\n- du nombre d’années restant à la retraite et du taux d’actualisation. Taux d'actualisation 3,1% 3,4%\nPrime de Fidélité\nCOMPTABILISATION ENGAGEMENTS SOCIAUX\n• Prime servie aux collaborateurs à l’ancienneté de 15, 20, 25, 30, 35 et 45 ans.\nLe Groupe Crédit du Maroc a opté pour la comptabilisation des écarts actuariels\n• Le montant de la prime est déterminé à partir d’un barème et du salaire au\nrelatifs aux engagements sociaux postérieurs à l’emploi (prime de fin de carrière)\nmoment de l’octroi.\nen capitaux propres selon la méthode du SoRIE (Statement Of Recognised\n• Le montant de l’engagement dépend : Income and Expenses).\n- de l’évolution du salaire, Les avantages au personnel entrant dans les catégories IAS 19 des autres\n- du nombre d’années d’ancienneté (barème), avantages long terme (Prime de fidélité) et des indemnités de fin de contrat\n- de la probabilité de survie (table de mortalité), de travail (Prime de départ volontaire) continueront à être comptabilisés en\n- de la probabilité de présence (turn over), résultat.\n- du nombre d’années restant à l’octroi et du taux d’actualisation. L’impact des écarts actuariels sur engagements sociaux à fin Juin 2024 se\nCouverture Médicale présente comme suit :\nLa CMIM, système de couverture médicale, est considérée comme un régime (En milliers de DH)\nmulti-employeurs à prestations définies En l’absence d’informations suffisantes Brut ID Net\npour déterminer la part d’obligation qui revient au Crédit du Maroc, elle est Impact Compte de Résultat\ntraitée comptablement comme un régime à cotisations définies.\nDotation Provision Engagements Sociaux -1 244 488 -756\nImpact Capitaux Propres\nGains et Pertes actuariels / avantages post emploi 44 103 -23 100 21 003\n17\nATTESTATION DES COMMISSAIRES AUX COMPTES\n(COMPTES CONSOLIDÉS)\nEXERCICE DU 1ER JANVIER AU 30 JUIN 2024\n76, Bd Abdelmoumen\n37, Bd Abdellatif Ben Kaddour\nRésidence Koutoubia, 7ème étage\n20 050 Casablanca\nCasablanca -Maroc\nMaroc\nGROUPE CREDIT DU MAROC\nATTESTATION D'EXAMEN LIMITE DE LA\nSITUATION INTERMEDIAIRE CONSOLIDEE AU 30 JUIN 2024\nNous avons procédé à un examen limité de la situation intermédiaire de Crédit Du Maroc et ses filiales\n(Groupe Crédit du Maroc) comprenant le bilan et le compte de résultat, l'état du résultat global, le\ntableau des flux de trésorerie, l’état de variation des capitaux propres et une sélection de notes\nexplicatives relatifs à la période du 1er janvier au 30 juin 2024. Cette situation intermédiaire fait\nressortir un montant de capitaux propres consolidés totalisant KMAD 7.048.980, dont un bénéfice net\nde KMAD 390.835.\nNous avons effectué notre examen limité selon les normes de la Profession au Maroc relatives aux\nmissions d'examen limité. Ces normes requièrent que l'examen limité soit planifié et réalisé en vue\nd'obtenir une assurance modérée que la situation intermédiaire ne comporte pas d'anomalie\nsignificative. Un examen limité comporte essentiellement des entretiens avec le personnel de la\nsociété et des vérifications analytiques appliquées aux données financières ; il fournit donc un niveau\nd'assurance moins élevé qu'un audit. Nous n'avons pas effectué un audit et, en conséquence, nous\nn'exprimons donc pas d'opinion d'audit.\nSur la base de notre examen limité, nous n'avons pas relevé de faits qui nous laissent penser que la\nsituation intermédiaire consolidée ci-jointe, ne donne pas une image fidèle du résultat des opérations\nde la période écoulée ainsi que de la situation financière et du patrimoine du Groupe Crédit du Maroc\narrêtés au 30 juin 2024, conformément aux normes comptables internationales (IAS/IFRS).\nCasablanca, le 23 juillet 2024\nLes Commissaires aux Comptes\nERNST & YOUNG FORVIS MAZARS\nAbdeslam BERRADA ALLAM Taha FERDAOUS\nAssocié Associé\n18\nwww.creditdumaroc.ma\nCOMPTES SOCIAUX AU 30 JUIN 2024\nBILAN AU 30 JUIN 2024\n(En milliers de DH) (En milliers de DH)\nACTIF 30/06/2024 31/12/2023 PASSIF 30/06/2024 31/12/2023\nValeurs en caisse, Banques centrales, Trésor public, Service des 1 848 958 2 265 665 Banques centrales, Trésor public, Service des chèques postaux 844 247\nchèques postaux\nDettes envers les établissements de crédit et assimilés 1 218 610 1 113 484\nCréances sur les établissements de crédit et assimilés 6 810 224 7 405 972\nA vue 405 637 751 840\nA vue 2 890 028 917 518\nA terme 3 920 196 6 488 454 A terme 812 973 361 644\nCréances sur la clientèle 52 220 642 49 036 683 Dépôts de la clientèle 54 528 328 51 678 073\nCrédits de trésorerie et à la consommation 20 239 424 18 561 119 Comptes à vue créditeurs 38 828 155 35 888 190\nCrédits à l'équipement 10 702 731 9 663 379 Comptes d'épargne 10 192 159 10 070 845\nCrédits immobiliers 19 475 696 18 581 240 Dépôts à terme 4 487 603 4 133 319\nAutres crédits 1 802 791 2 230 945 Autres comptes créditeurs 1 012 388 1 573 233\nCréances acquises par affacturage 665 222 715 251 Dettes envers la clientèle sur produits participatifs 8 022 12 485\nTitres de transaction et de placement 5 167 834 3 491 778\nTitres de créance émis 3 501 597 3 424 402\nBons du Trésor et valeurs assimilées 4 113 700 3 051 102\nTitres de créance négociables 3 501 597 3 424 402\nAutres titres de créance 938 995 325 537\nEmprunts obligataires - -\nTitres de propriété 115 139 115 139\nAutres actifs 408 338 368 111 Autres titres de créance émis - -\nTitres d'investissement 887 861 1 373 511 Autres passifs 2 044 112 1 747 310\nBons du Trésor et valeurs assimilées 887 861 1 373 511 Provisions pour risques et charges 1 104 240 1 120 134\nAutres titres de créance Provisions réglementées - -\nTitres de participation et emplois assimilés 348 787 303 775 Subventions, fonds publics affectés et fonds spéciaux de garantie - -\nParticipations dans les entreprises liées 306 235 260 577 Dettes subordonnées 1 966 807 1 923 507\nAutres titres de participation et emplois assimilés 42 552 43 198 Dépôts d'investissement reçus 46 504 -\nTitres de Moudaraba et Mouchraka - -\nEcarts de réévaluation - -\nCréances subordonnées - -\nRéserves et primes liées au capital 2 625 959 2 625 959\nDépôts d'investissement placés - -\nImmobilisations données en crédit-bail et en location - - Capital 1 088 121 1 088 121\nImmobilisations données en Ijara - - Actionnaires Capital non versé (-) - -\nImmobilisations incorporelles 799 388 773 454 Report à nouveau (+/-) 1 763 793 1 603 139\nImmobilisations corporelles 1 113 004 1 122 969 Résultats nets en instance d'affectation (+/-) - -\nTotal de l'Actif 70 270 258 66 857 168 Résultat net de l'exercice (+/-) 381 342 532 791\nTotal du Passif 70 270 258 66 857 168\nHORS BILAN 30/06/2024 31/12/2023\nENGAGEMENTS DONNES 13 189 791 12 181 574 ÉTAT DES SOLDES DE GESTION AU 30 JUIN 2024\nEngagements de financement donnés en faveur d'établissements de\n- - (En milliers de DH)\ncrédit et assimilés\nEngagements de financement donnés en faveur de la clientèle 5 602 632 5 698 327 I- TABLEAU DE FORMATION DES RÉSULTATS 30/06/2024 30/06/2023\nEngagements de garantie d'ordre d'établissements de crédit et assi- + Intérêts et produits assimilés 1 444 384 1 216 634\nmilés 2 707 117 2 293 488 - Intérêts et charges assimilées 363 312 223 558\nEngagements de garantie d'ordre de la clientèle 4 880 042 4 189 759 MARGE D'INTERET 1 081 072 993 077\nTitres achetés à réméré - - + Produits sur financements participatifs 32 238 26 042\n- Charges sur financements participatifs - -\nAutres titres à livrer - -\nMarge sur financements participatifs 32 238 26 042\nENGAGEMENTS RECUS 2 846 821 2 998 300\n+ Produits sur immobilisations en crédit-bail et en location - -\nEngagements de financement reçus d'établissements de crédit et 498 465 - - Charges sur immobilisations en crédit-bail et en location - -\nassimilés Résultat des opérations de crédit-bail et de location - -\nEngagements de garantie reçus d'établissements de crédit et assimilés 2 348 356 2 998 300 + Produits sur immobilisations données en Ijara - -\nEngagements de garantie reçus de l'Etat et d'organismes de garantie - - - Charges sur immobilisations données en Ijara - -\ndivers Résultat des opérations d'Ijara - -\nTitres vendus à réméré - - + Commissions perçues 214 340 194 659\nAutres titres à recevoir - - - Commissions servies 24 519 21 935\nMarge sur commissions 189 821 172 723\nCOMPTE DE PRODUITS ET CHARGES AU 30 JUIN 2024 + Résultat des opérations sur titres de transaction 63 683 23 932\n(En milliers de DH) + Résultat des opérations sur titres de placement 476 -1 454\n+ Résultat des opérations de change 146 245 148 980\nLIBELLE 30/06/2024 30/06/2023\n+ Résultat des opérations sur produits dérivés - -\nPRODUITS D'EXPLOITATION BANCAIRE 2 026 938 1 714 007\nRésultat des opérations de marché 210 404 171 458\nIntérêts, rémunérations et produits assimilés sur opérations avec les\nétablissements 146 615 91 404 + Divers autres produits bancaires 66 697 82 661\nIntérêts, rémunérations et produits assimilés sur opérations avec la clientèle 1 295 636 1 119 459 - Diverses autres charges bancaires 55 225 53 348\n± Part des titulaires de comptes de dépôts d'investissement -217 -\nIntérêts et produits assimilés sur titres de créance 34 371 31 813\nPRODUIT NET BANCAIRE 1 524 791 1 392 612\nProduits sur titres de propriété et certificats de Sukuk 66 697 82 661\n+ Résultat des opérations sur immobilisations financières 6 741 3 132\nProduits sur titres de Moudaraba et moucharaka - - + Autres produits d'exploitation non bancaire 17 009 28 242\nProduits sur immobilisations en crédit-bail et en location - - - Autres charges d'exploitation non bancaire - -\nProduits sur immobilisations données en Ijara - - - Charges générales d'exploitation 785 058 752 066\nCommissions sur prestations de service 211 823 190 213 RESULTAT BRUT D'EXPLOITATION 763 483 671 920\nTA ru at nre sfs e p rtr o dd eu cit hs a b ra gen sc a si ure r s dépôts d'investissement reçus 271 79 6 - 198 45 7 - e+ n D gao gta et mio en ns t n s e pt ate r s s id ge ns a tr ue rp er i es ne s s oa uu fx f rp ar no cv eis ions pour créances et -89 092 -141 082\nCHARGES D'EXPLOITATION BANCAIRE 502 147 321 394 + Autres dotations nettes des reprises aux provisions -10 168 46 790\nIntérêts et charges assimilées sur opérations avec les établissements 45 559 32 370 RESULTAT COURANT 664 222 577 628\nRESULTAT NON COURANT -65 043 -54 701\nIntérêts et charges assimilées sur opérations avec la clientèle 239 697 152 858\n- Impôts sur les résultats 217 837 165 125\nIntérêts et charges assimilées sur titres de créance émis 78 055 38 330\nRESULTAT NET DE L'EXERCICE 381 342 357 802\nCharges sur titres de Moudaraba et Moucharaka - -\nCharges sur immobilisations en crédit-bail et en location - - II- CAPACITÉ D’AUTOFINANCEMENT 30/06/2024 30/06/2023\nCharges sur immobilisations données en Ijara - - + RESULTAT NET DE L'EXERCICE 381 342 357 802\nAutres charges bancaires 138 619 97 837 + Dotations aux amortissements et aux provisions des immobilisations 128 808 91 964\nincorporelles et corporelles\nTransfert de produits sur dépôts d'investissement reçus 217 -\n+ Dotations aux provisions pour dépréciation des immobilisations\nPRODUIT NET BANCAIRE 1 524 791 1 392 612 - 3 696\nfinancières\nProduits d'exploitation non bancaire 17 009 28 242 + Dotations aux provisions pour risques généraux 8 165 21 353\nCharges d'exploitation non bancaire - - + Dotations aux provisions réglementées - -\nCHARGES GENERALES D'EXPLOITATION 785 058 752 066 + Dotations non courantes - 2 451\nCharges de personnel 394 926 394 840 - Reprises de provisions 25 647 48 490\nImpôts et taxes 25 838 15 287 - Plus-values de cession sur immobilisations incorporelles et corporelles 35 11\nCharges externes 234 760 249 498 + Moins-values de cession sur immobilisations incorporelles et corporelles - -\nAutres charges générales d'exploitation 726 477 - Plus-values de cession sur immobilisations financières - -\nDotations aux amortissements et aux provisions des immobilisations + Moins-values de cession sur immobilisations financières - -\nincorporelles et corporelles 128 808 91 964 - Reprises de subventions d'investissement reçues - -\nDOTATIONS AUX PROVISIONS ET PERTES SUR CREANCES + CAPACITE D'AUTOFINANCEMENT 492 633 428 764\n420 669 561 378\nIRRECOUVRABLES - Bénéfices distribués - -\nDotations aux provisions pour créances et engagements par signature 369 918 384 302 + AUTOFINANCEMENT 492 633 428 764\nen souffrance\nPertes sur créances irrécouvrables 6 069 133 415\nÉTAT DES CRÉANCES EN SOUFFRANCE ET DES\nAutres dotations aux provisions 44 682 43 661\nREPRISES DE PROVISIONS ET RECUPERATIONS SUR CREANCES 328 149 470 218 PROVISIONS CORRESPONDANTES AU 30 JUIN 2024\nAMORTIES\nReprises de provisions pour créances et engagements par signature en (En milliers de DH)\n278 114 366 784\nsouffrance\nMontants au 31/12/2023 Montants au 30/06/2024\nRécupérations sur créances amorties 8 780 9 850\nCréances Provisions Créances Provisions\nAutres reprises de provisions 41 255 93 583\nRESULTAT COURANT 664 222 577 628 Créances pré-douteuses 241 590 29 211 391 446 34 575\nProduits non courants 13 539 10 880 Créances douteuses 625 935 463 508 522 015 441 454\nCharges non courantes 78 582 65 582 Créances compromises 3 228 974 2 497 237 3 226 989 2 628 379\nRESULTAT AVANT IMPOTS 599 179 522 927 TOTAL 4 096 500 2 989 956 4 140 450 3 104 408\nImpôts sur les résultats 217 837 165 125\nRESULTAT NET DE L'EXERCICE 381 342 357 802\n19\nTABLEAU DE FLUX DE TRÉSORERIE AU 30 JUIN 2024 ÉTAT B1- CRÉANCES SUR LES ÉTABLISSEMENTS\n(En milliers de DH) DE CRÉDIT ET ASSIMILÉS AU 30 JUIN 2024\n30/06/2024 31/12/2023 (En milliers de DH)\nProduits d'exploitation bancaire perçus 1 945 660 3 435 942 Bank Al-Maghrib, Autres éta- Etablisse-\nblissements\nRécupérations sur créances amorties 8 780 25 122 Trésor Public Banques au ments de Total Total\nCREANCES de crédit et\nProduits d'exploitation non bancaire perçus 26 544 64 546 et Service des Maroc assimilés au crédit à 30/06/2024 31/12/2023\nCharges d'exploitation bancaire versées -458 847 -722 749 Chèques Postaux Maroc l'étranger\nCharges d'exploitation non bancaire versées -78 582 -217 772 COMPTES\nCharges générales d'exploitation versées -656 250 -1 322 653 ORDINAIRES 1 143 848 9 289 417 940 895 810 2 466 887 2 266 529\nImpôts sur les résultats versés -217 837 -312 367 DEBITEURS\ncI h - a F rl gu ex s de trésorerie nets provenant du compte de produits et 569 468 950 069 EV NA L PE EU NR SS IO R NE CUES - 1 010 217 - - 1 010 217 2 201 870\nVariation de :\n- au jour le jour - - - - - 2 201 870\nCréances sur les établissements de crédit et assimilés 595 747 -591 335\n- à terme - 1 010 217 - - 1 010 217 -\nCréances sur la clientèle -3 247 156 -3 194 893\nTitres de transaction et de placement -1 189 929 -463 103 PRETS DE TRESO- - 1 000 000 799 606 - 1 799 606 1 893 759\nRERIE\nAutres actifs -40 227 84 350\nImmobilisations données en crédit-bail et en location - - - au jour le jour - 200 000 - - 200 000 830 000\nDettes envers les établissements de crédit et assimilés 105 126 -1 584 035 - à terme - 800 000 799 606 - 1 599 606 1 063 759\nDépôts de la clientèle 2 896 759 3 116 297 PRETS FINANCIERS - - 2 296 012 - 2 296 012 2 364 558\nTitres de créance émis 77 195 1 811 997 AUTRES CREANCES - - 354 358 - 354 358 134 256\nAutres passifs 296 802 448 315\nINTERETS COURUS\nII - Solde des variations des actifs et passifs d'exploitation -505 682 -372 407 - 11 102 15 891 - 26 993 24 516\nA RECEVOIR\nIII - FLUX DE TRESORERIE NETS PROVENANT DES ACTIVITES\nD'EXPLOITATION ( I + II ) 63 786 577 662 CREANCES EN - - - - - -\nProduit des cessions d'immobilisations financières - - SOUFFRANCE\nProduit des cessions d'immobilisations incorporelles et corporelles 35 40 TOTAL 1 143 848 2 030 608 3 883 806 895 810 7 954 073 8 885 488\nAcquisition d'immobilisations financières -45 012 -7 059\nAcquisition d'immobilisations incorporelles et corporelles -144 777 -445 752\nÉTAT B3 - VENTILATION DES TITRES DE TRANSACTION\nIntérêts perçus 14 104 35 539\nDividendes perçus 66 697 88 238 ET DE PLACEMENT ET DES TITRES D’INVESTISSEMENT\nIV - FLUX DE TRESORERIE NETS PROVENANT DES ACTIVITES PAR CATÉGORIE D’ÉMETTEUR AU 30 JUIN 2024\n-108 952 -328 995\nD'INVESTISSEMENT\nSubventions, fonds publics et fonds spéciaux de garantie reçus - - (En milliers de DH)\nEmission de dettes subordonnées - 500 000 Etablissements Emetteurs privés\nEmetteurs Total Total\nE Rm emis bsi oo un r sd e'a mct eio nn t s des capitaux propres et assimilés - - TITRES d ae s c sr ié md ilit é set publics financiers finan no cn ie rs 30/06/2024 31/12/2023\nIntérêts versés - -58 013 TITRES COTES - - - - - -\nDividendes versés -372 138 -293 793 BONS DU TRESOR ET - - - - - -\nV - FLUX DE TRESORERIE NETS PROVENANT DES ACTIVITES DE VALEURS ASSIMILEES\nFINANCEMENT -372 138 148 194 OBLIGATIONS - - - - - -\nVI - VARIATION NETTE DE LA TRESORERIE ( III + IV + V ) -417 304 396 862 AUTRES TITRES DE\n- - - - - -\nVII - TRESORERIE A L'OUVERTURE DE L'EXERCICE 2 265 417 1 868 556 CREANCE\nVIII - TRESORERIE A LA CLOTURE DE L'EXERCICE 1 848 114 2 265 417 TITRES DE PROPRIETE - - - - - -\nTITRES NON COTES 938 995 5 001 561 115 073 67 6 055 695 4 865 289\nÉTAT A1 - PRINCIPALES MÉTHODES D’ÉVALUATION BONS DU TRESOR ET\n- 5 001 561 - - 5 001 561 4 424 613\nVALEURS ASSIMILEES\nAPPLIQUÉES AU 30 JUIN 2024\nOBLIGATIONS - - - - - -\nINDICATION DES METHODES D'EVALUATION APPLIQUEES PAR L'ETABLISSEMENT AUTRES TITRES DE 938 995 - - - 938 995 325 537\nCREANCE\nApplication des méthodes d'évaluation prévues par le plan comptable des établissements de crédit (P TITRES DE PROPRIETE - - 115 073 67 115 139 115 139\nC E C) entré en vigueur depuis le 01/01/2000\nTOTAL 938 995 5 001 561 115 073 67 6 055 695 4 865 289\nLes états de synthèse sont présentés conformément aux dispositions du P C E C\nÉTAT B5 - DÉTAIL DES AUTRES ACTIFS AU 30 JUIN 2024\nÉTAT A2 - ÉTAT DES DÉROGATIONS AU 30 JUIN 2024\n(En milliers de DH)\nInfluence des dérogations\nIndications des dérogations Justifications sur le patrimoine, la situation Actif 30/06/2024 31/12/2023\ndes dérogations financière et les résultats Instruments optionnels achetés\nI Dérogations aux principes comptables Opérations diverses sur titres 24 082 -\nN E A N T\nfondamentaux Débiteurs divers 46 170 84 688\nII Dérogations aux méthodes d’évaluation N E A N T sommes dues par l'état 14 941 30 106\nIII Dérogations aux règles d’établissement et de sommes dues par les organismes de prévoyance - -\nprésentation des états de synthèse N E A N T sommes diverses dues par le personnel 2 404 1 500\ncomptes clients de prestations non bancaires - -\ndivers autres débiteurs 28 824 53 082\nÉTAT A3 - ÉTAT DES CHANGEMENTS DE MÉTHODES\nValeurs et emplois divers 2 756 1 885\nAU 30 JUIN 2024 Vomptes de régularisation 335 330 281 539\nJustifications Influence sur le patrimoine, comptes d'ajustement des opérations de hors bilan\nNature des changements des la situation financière comptes d'écarts sur devises et titres 25 472 27 472\nchangements et les résultats résultats sur produits dérivés de couverture - -\nI Changements affectant les méthodes d’évaluation N E A N T charges à répartir sur plusieurs exercices 41 674 68 498\nII Changements affectant les règles de présentation N E A N T comptes de liaison entre siège, succursales et agences au Maroc 175 1 512\nProduits à recevoir 76 844 11 747\nCharges constatées d'avances 58 096 8 317\nCHIFFRE D’AFFAIRES HORS TAXES AU 30 JUIN 2024\nAutres comptes de régularisation 133 070 163 992\n(En milliers de DH) Créances en souffrance sur opérations diverses\nPremier semestre 2024 deuxieme semestre 2023 Premier semestre 2023 TOTAL 408 338 368 111\n2 026 938 1 846 412 1 714 007\nÉTAT B10 - DETTES ENVERS LES ÉTABLISSEMENTS DE CRÉDIT\nÉTAT B2 - CRÉANCES SUR LA CLIENTÈLE ET ASSIMILÉS AU 30 JUIN 2024\nAU 30 JUIN 2024 (En milliers de DH)\n(En milliers de DH) Établissements de crédit et assimilés au Maroc\nÉtablisse-\nCRÉANCES S pe uc bte liu cr Entreprises EnS te rc et pe ru isr e p sr niv oé n Autre 30/0 T 6ot /a 2l 0 24 31/1 T 2o /t 2a 0l 23 DETTES Ba Tn rk é A sol- r M Pa ubgh licri b, Banques A mu etr ne ts s é dt ea cb rl éis ds ie t- m cre én dts it d àe 30/0 T 6ot /a 2l 0 2431/1 T 2o /t 2a 0l 23\nfinancières financières clientèle et Service des au Maroc et assimilés au l’étranger\nCrédits de trésorerie 2 858 587 10 451 13 027 413 303 598 16 200 049 14 825 681 Chèques Postaux Maroc\nComptes à vue débiteurs 10 252 10 451 2 791 794 122 464 2 934 961 2 645 395 Comptes ordinaires\nCréances commerciales sur 1 021 865 - 1 560 523 - 2 582 388 2 116 678 créditeurs 844 2 537 11 024 62 769 77 174 594 649\nle Maroc\nCrédits à l'exportation - - 206 749 - 206 749 238 922 Valeurs données - - - - - -\nen pension\nAutres crédits de trésorerie 1 826 470 - 8 468 347 181 134 10 475 952 9 824 685\nCrédits à la consommation - - - 3 843 942 3 843 942 3 547 160 - Au jour le jour - - - - - -\nCrédits à l'équipement 2 769 829 9 491 7 797 240 - 10 576 560 9 570 148 - À terme - - - - - -\nCrédits immobiliers - - 2 240 833 17 156 427 19 397 260 18 503 111\nAutres crédits - 758 288 8 157 - 766 445 1 123 949 Emprunts de trésorerie - - 203 196 39 703 242 899 295 437\nCréances acquises par 665 222 - - - 665 222 715 251 - Au jour le jour - - - - - -\naffacturage\nIntérêts courus à recevoir - 95 249 305 095 - 400 344 360 091 - À terme - - 203 196 39 703 242 899 295 437\nCréances en souffrance - - 247 517 788 525 1 036 042 1 106 544 Emprunts financiers - 2 179 - 523 386 525 565 33 615\nCréances pré-douteuses - - 21 378 335 493 356 871 212 379\nCréances douteuses - - 5 786 74 775 80 560 162 427 Autres dettes - 339 779 339 779 159 139\nCréances compromises - - 220 353 378 258 598 611 731 737 Intérêts courus à payer - 34 037 - - 34 037 30 891\nTOTAL 6 293 638 873 479 23 626 254 22 092 493 52 885 864 49 751 934\nTOTAL 844 38 753 553 999 625 858 1 219 455 1 113 731\n20\nwww.creditdumaroc.ma\nÉTAT B9 - IMMOBILISATIONS INCORPORELLES ET CORPORELLES AU 30 JUIN 2024\n(En milliers de DH)\nAmortissements et/ou provisions\nNature M ao u l’n e d xt éa ebn rcut i t cb edru et M a ac lo u ’q en c xut o ea is u rn i crtt s ii co d d ene ess c te rM das eo s it n i lso ’et n aa xs u en o rt c c u od ic ue r ee rs s - lM b ’er fo xu in en t rt dà ca e i n cl a et M ma po em rn n oot t va r s it s n ei ist ots /d ne o se - u s a lD ’u eo xtt eia t rrt cei io cdn ee M ia mmo m mn eot n oa r t btn si is lt s is sud e are - - s Cumul moA uvu et mre es n ts M à lo ’e n la xt e a f rin n ct i d c n eee t\nau début de\ntions sortie\nl’exercice\nIMMOBILISATIONS INCORPORELLES 1 370 388 198 380 94 427 1 471 465 596 934 75 143 - 672 077 - 799 388\n- Droit au bail 20 829 - 3 400 17 429 - - - - - 17 429\n- Immobilisations en recherche et développement - - - - - - - - - -\n- Autres immobilisations incorporelles d'exploitation 1 349 560 198 380 91 027 1 454 036 596 934 75 143 - 672 077 - 781 959\n- Immobilisations incorporelles hors exploitation - - - - - - - - - -\nIMMOBILISATIONS CORPORELLES 2 542 060 43 875 5 743 2 582 998 1 419 091 53 662 -2 759 1 469 994 - 1 113 004\n- Immeubles d'exploitation 1 237 611 3 909 - 1 241 520 475 909 15 129 - 491 038 - 750 482\nTerrains d'exploitation 357 875 - - 357 875 - - - - - 357 875\nImmeubles d'exploitation Bureaux 851 927 3 909 - 855 836 448 155 15 120 - 463 275 - 392 561\nImmeubles d'exploitation Logements de fonction 27 808 - - 27 808 27 754 9 - 27 763 - 45\n- Mobilier et matériel d'exploitation 582 356 26 081 4 177 607 136 458 211 20 787 -1 296 477 702 - 129 434\nMobilier de bureau d'exploitation 109 304 485 586 109 203 84 850 3 714 -586 87 978 - 21 225\nMatériel de bureau d'exploitation 22 714 530 551 22 693 13 827 559 -551 13 835 - 8 857\nMatériel de bureau Telecom 86 091 4 125 - 90 216 62 441 3 298 - 65 738 - 24 477\nMatériel Informatique 298 025 20 333 2 876 318 358 236 245 12 175 - 248 420 - 69 938\nMatériel roulant rattaché à l'exploitation 401 - - 401 387 2 - 389 - 12\nAutres matériels d'exploitation 65 820 608 164 66 265 60 461 1 039 -158 61 341 - 4 924\n- Autres immobilisations corporelles d’exploitation 639 351 13 591 1 555 651 315 427 366 16 147 -1 452 442 061 - 209 253\n- Immobilisations corporelles hors exploitation 82 743 294 11 83 028 57 605 1 599 -11 59 193 - 23 835\nTerrains hors exploitation 2 152 - - 2 152 - - - - - 2 152\nImmeubles hors exploitation 49 093 - - 49 093 36 748 640 - 37 389 - 11 704\nMobiliers et matériel hors exploitation 9 641 20 11 9 650 8 600 299 -11 8 888 - 762\nAutres immobilisations corporelles hors exploi-\n21 857 274 - 22 133 12 257 659 - 12 916 - 9 218\ntation\n- Écart de conversion - -\nTotal 3 912 448 242 255 100 170 4 054 463 2 016 026 128 804 -2 759 2 142 071 - 1 912 392\nÉTAT B11- DÉPÔTS DE LA CLIENTÈLE AU 30 JUIN 2024 ÉTAT B14 - PROVISIONS AU 30 JUIN 2024\n(En milliers de DH) (En milliers de DH)\nSecteur privé PROVISIONS Encours Dotations Reprises Autres Encours\nSecteur Total Total 31/12/2023 variations 30/06/2024\nDÉPÔTS public Entreprises Entreprises Autre 30/06/2024 31/12/2023\nfinancières non financières clientèle PROVISIONS DEDUITES DE 2 916 170 367 931 267 991 23 3 016 133\nL'ACTIF, SUR :\nComptes à vue créditeurs 340 507 101 351 12 047 614 26 345 665 38 835 137 35 899 634\nCréances sur les établissements de\n- - - - -\nComptes d'épargne - - - 10 122 215 10 122 215 9 989 903 crédit et assimilés\nDépôts à terme - 600 000 737 892 3 098 690 4 436 582 4 090 027 Créances sur la clientèle 2 865 464 367 931 260 773 23 2 972 645\nTitres de placement 18 124 - 2 947 - 15 177\nAutres comptes créditeurs 3 181 - 751 337 255 256 1 009 774 1 578 426\nTitres de participation et emplois\nIntérêts courus à payer - - - 124 620 124 620 120 083 assimilés 32 582 - 4 270 - 28 311\nTOTAL 343 688 701 351 13 536 843 39 946 447 54 528 328 51 678 073 Immobilisations en crédit-bail et en\n- - - - -\nlocation\nAutres actifs - - - - -\nÉTAT B12 - ÉTAT DES SOUSCRIPTIONS DE CERTIFICATS\nPROVISIONS INSCRITES AU\n1 120 135 46 669 62 564 - 1 104 240\nDE DÉPÔT INSCRITS EN COMPTE AU 30 JUIN 2024 PASSIF :\n(En milliers de DH) Provisions pour risques d'exécution 99 545 1 987 17 340 - 84 192\nd'engagements par signature\nNature Date de Date Valeur nomi- Taux Mode de rem- Montant\ndes Titres jouissance d’échéance nale unitaire nominal boursement Global Provisions pour risques de change - - - - -\nCertificats Provisions pour risques généraux 758 337 8 165 18 906 - 747 596\n30/11/2023 30/08/2024 100,00 3,27% INFINE 615 000,00\nde Dépots Provisions pour pensions de retraite\n88 873 1 257 - - 90 130\nCertificats et obligations similaires\n30/11/2023 28/11/2024 100,00 3,35% INFINE 885 000,00\nde Dépots Provisions pour autres risques et\nCertificats 29/03/2024 27/09/2024 100,00 3,25% INFINE 548 000,00 charges 173 380 35 260 26 318 - 182 321\nde Dépots\nProvisions réglementées - - - - -\nCertificats\nde Dépots 29/03/2024 27/12/2024 100,00 3,31% INFINE 352 000,00 TOTAL GENERAL 4 036 305 414 600 330 555 23 4 120 373\nCertificats\n30/04/2024 29/07/2024 100,00 3,17% INFINE 500 000,00\nde Dépots\nCertificats 30/04/2024 29/10/2024 100,00 3,28% INFINE 500 000,00 État B22 -VENTILATION DES EMPLOIS ET DES RESSOURCES\nde Dépots\nCertificats SUIVANT LA DURÉE RÉSIDUELLE AU 30 JUIN 2024\n31/05/2024 30/05/2025 100,00 3,40% INFINE 58 000,00\nde Dépots (En milliers de DH)\nTotal 3 458 000,00 1 mois < D 3 mois < D 1 an < D\nD ≤ 1 mois D > 5 ans TOTAL\n≤ 3 mois ≤ 1 an ≤ 5 ans\nACTIF\nÉTAT B13 - DÉTAIL DES AUTRES PASSIFS AU 30 JUIN 2024 Créances sur les\nétablissements de 1 107 169 396 417 930 168 1 416 437 70 006 3 920 196\n(En milliers de DH) crédit et assimilés\nPassif 30/06/2024 31/12/2023 Créances sur la clientèle 7 015 827 3 704 689 4 807 810 13 502 999 23 189 318 52 220 643\nInstruments optionnels vendus Titres de créance 907 917 1 314 337 1 723 186 1 371 775 738 477 6 055 692\nCréances subordonnées - - - - - -\nOpérations diverses sur titres 5 619 79 856\nCrédit-bail et assimilé - - - - - -\nCréditeurs divers 993 049 721 968\nTOTAL 9 030 913 5 415 443 7 461 164 16 291 211 23 997 800 62 196 532\nSommes dues à l'état 255 085 263 839 PASSIF\nSommes dues aux organismes de prévoyance 29 368 27 394 Dettes envers les\nSommes diverses dues au personnel - - établissements de - - 93 190 680 080 39 703 812 974\ncrédit et assimilés\nSommes diverses dues aux actionnaires et associés 376 559 5 567\nDettes envers\nFournisseurs de biens et services 39 352 la clientèle 862 538 1 056 293 2 403 236 165 536 - 4 487 603\nDivers autres créditeurs 331 998 424 816 Titres de créance émis 500 000 1 163 000 1 838 597 - - 3 501 597\nComptes de régularisation 1 045 445 945 487 Emprunts subordonnés - - - 1 308 938 657 869 1 966 807\nTOTAL 1 362 538 2 219 293 4 335 023 2 154 555 697 572 10 768 981\nComptes d'ajustement des opérations de hors bilan 0 0\nComptes d'écarts sur devises et titres 0 0\nRésultats sur produits dérivés de couverture 0 0\nPassifs Eventuels\nComptes de liaison entre sièges, succursales et agences au Maroc 717 566\nLe Crédit du Maroc a reçu de la part de l’administration fiscale, en juin 2023, un\nCharges à payer 374 056 379 328 avis de vérification portant sur l’impôt sur les sociétés (IS), l’impôts sur le revenus\nProduits constatés d'avance 570 658 521 539 (IR) et la taxe sur la valeur ajoutée (TVA) au titre des exercices 2019 à 2022 La\nAutres comptes de régularisation 100 014 44 054 vérification sur place est en cours et la banque n’a reçu aucune notification au\nTotal 2 044 112 1 747 310 27 juillet 2023\n21\nÉTAT B16 - DETTES SUBORDONNÉES AU 30 JUIN 2024\n(En milliers de DH)\ndont entreprises liées dont autres apparentés\nCondition de\nMontant Montant de l’emprunt\nMonnaie en monnaie Cours Taux Durée remboursement anticipé, en monnaie nationale Montant N Montant N-1 Montant N Montant N-1\nde l’emprunt de l'emprunt subordination et (ou contrevaleur en KDH) (en contrevaleur (en contrevaleur (en contrevaleur (en contrevaleur\nconvertibilité KDH) KDH) KDH) KDH)\nMAD 55 000,00 1 3,93% 10 ANS INFINE 55 000,00\nMAD 445 000,00 1 3,75% 10 ANS INFINE 445 000,00\nMAD 197 500,00 1 4,05% 10 ANS INFINE 197 500,00\nMAD 552 500,00 1 4,05% 10 ANS INFINE 552 500,00\nTOTAL 1 250 000,00 1 250 000,00\n(En milliers de DH)\nSoucripteur COV Nbre Bons Catégorie Nominal Nominal Global Maturité Taux en % Date de Jouissance\nCASA 18540 1 OB PERPETUELLE 136 116,26 136 116 Indéterminée 5,475% 14/12/2020\nWAFA ASSUR 18541 1 OB PERPETUELLE 21 752,85 21 753 Indéterminée 5,475% 14/12/2020\nDIVERS 9582 5000 OB PERPETUELLE 100,00 500 000 Indéterminée 5,450% 20/07/2023\nTOTAL 657 869\n22\nwww.creditdumaroc.ma\nÉTATS DE SYNTHÈSE ARREDA AU 30 JUIN 2024\nBILAN ARREDA AU 30 JUIN 2024 COMPTE DE PRODUITS ET CHARGES ARREDA\n(En milliers de DH) AU 30 JUIN 2024\nACTIF 30/06/2024 31/12/2023 (En milliers de DH)\nValeurs en caisse, Banques centrales, Trésor public, Service des\nchèques postaux 33 929 38 169 30/06/2024 30/06/2023\nCréances sur les établissements de crédit et assimilés 1 145 46 PRODUITS D'EXPLOITATION BANCAIRE 33 183 26 647\nRémunérations et produits assimilés sur opérations avec les\nCréances sur la clientèle 2 174 967 1 929 760 - -\nétablissements de crédit\nCréances sur Mourabaha 2 155 514 1 917 836 Rémunérations et produits assimilés sur opérations avec la clientèle 32 238 26 042\nCréances sur Salam - - Produits sur titres de propriété et certificats de Sukuk - -\nCréances sur autres financements participatifs - - Produits sur titres de Moudaraba et Moucharaka - -\nProduits sur immobilisations données en Ijara - -\nAutres créances sur la clientèle 19 453 11 924\nCommissions sur prestations de service 945 605\nTitres de transaction et de placement - -\nAutres produits bancaires - -\ndont certificat de Sukuk - - Transfert de charges sur dépôts d'investissement et Wakala Istithmar\n- -\nBiens acquis dans le cadre de financements participatifs 32 833 73 798 reçus\nCHARGES D'EXPLOITATION BANCAIRE 562 238\nImmobilisations données en Ijara - -\nCharges sur opérations avec les établissements de crédit et assimilés 1 1\nTitres d'investissement titres de participation et emplois divers - -\nCharges sur opérations avec la clientèle - -\ndont certificats de Sukuk - - Charges sur titres de Moudaraba et Moucharaka - -\nDont titres de Moudaraba et Moucharaka - - Charges sur immobilisations données en Ijara - -\ndépôts d'investissement et Wakala Istithmar placés - - Autres charges bancaires 344 237\nTransfert de produits sur dépôts d'investissement et Wakala Bil\nAutres actifs 1 946 763 217 -\nIstithmar reçus\nTOTAL DE L'ACTIF 2 244 821 2 042 537 PRODUIT NET BANCAIRE 32 621 26 409\nProduits d'exploitation non bancaire - -\n(En milliers de DH) Charges d'exploitation non bancaire - -\nPASSIF 30/06/2024 31/12/2023 CHARGES GENERALES D'EXPLOITATION 14 018 13 881\nBanques centrales, Trésor public, Service des chèques postaux - - DOTATIONS AUX PROVISIONS ET PERTES SUR CREANCES 3 715 1 941\nIRRECOUVRABLES\nDettes envers les établissements de crédit et assimilés 1 119 569 1 015 316 REPRISES DE PROVISIONS ET RECUPERATIONS SUR CREANCES\n3 151 1 767\nDettes sur Mourabaha - - AMORTIES\nDettes sur Salam - - RESULTAT COURANT 18 039 12 354\nDettes sur autres financements participatifs - - RESULTAT AVANT IMPOTS SUR LES RESULTATS 18 039 12 354\nAutres dettes sur les établissements de crédit et assimilés 1 119 569 1 015 316 Impôts sur les résultats 6 945 1 491\nDépôts de la clientèle 188 262 179 662 RESULTAT APRES IMPOT 11 094 10 864\nComptes à vue créditeurs 158 071 173 462\nAutres comptes créditeurs 30 191 6 200 DETTES ENVERS LA CLIENTÈLE SUR PRODUITS PARTICIPATIFS\nDettes envers la clientèle sur produits participatifs 8 023 12 485 AU 30 JUIN 2024\nDettes sur Mourabaha 8 023 12 485 (En milliers de DH)\nDettes sur Salam - -\nSecteur privé\nDettes sur autres financements participatifs - -\nSecteur\nAutres passifs 627 978 579 974 DETTES public Entreprises Entr ne op nr i ses Autre clientèle30/0To 6t /a 2l 0 24 31/1T 2o /t 2a 0l 23\nProvisions pour risques et charges 3 390 3 390 financières\nfinancières\nDépôts d'investissement et Wakala Istithmar reçus 46 504 -\nDETTES ENVERS LA\nDotation en capital 240 000 240 000 CLIENTELE SUR PRO- - - - 8 023 8 023 12 485\nReports - -8 406 DUITS PARTICIPATIFS\nRésultat de l'exercice 11 094 20 116 - Mourabaha (1) - - - 8 023 8 023 12 485\nTOTAL DU PASSIF 2 244 821 2 042 537 - Salam - - - - - -\n- Autres financements\n- - - - - -\nparticipatifs\nTOTAL - - - 8 023 8 023 12 485\n(1) principalement les avances sur Mourabaha\nTABLEAU DES MARGES CONSTATEES D’AVANCE SUR MOURABAHA DU 01/01/2024 AU 30/06/2024\n(En milliers de DH)\nEncours des créances\nMontant brut au Marges sur opérations Quote-part reprise en Quote-part constatée en Quote-part de marge Montant brut\nBiens Mourabaha à la fin\ndébut de l'exercice de l'exercice compte de résultat rémunération réservée abandonnée (1) à la fin de l'exercice\nde l’exercice\nMARGES CONSTATEES\nD'AVANCE - MOURABAHA AVEC\n- - - - - - -\nLES ETABLISSEMENTS DE CREDIT\nET ASSIMILES\nMARGES CONSTATEES D'AVANCE -\n486 562 101 143 32 238 8 504 1 169 545 794 2 155 514\nMOURABAHA AVEC LA CLIENTELE\nMourabaha - - - - - - -\nMourabaha pour donneur d'ordre 486 562 101 143 32 238 8 504 1 169 545 794 2 155 514\nTOTAL 486 562 101 143 32 238 8 504 1 169 545 794 2 155 514\n(1) Par remboursement anticipé ou autres\nTABLEAU DE VARIATION DES BIENS ACQUIS DANS LE CADRE DE FINANCEMENTS PARTICIPATIFS DU 01/01/2024 AU 30/06/2024\n(En milliers de DH)\nMontant des cessions\nMontant des au cours de l’exercice Provisions\nMontant brut acquisitions Montant brut Montant net\nBIENS au l’e d xe eb rcu it c ede dou ea t lu ’r\ne\na c xon eus rf cre s icr et Ex bp al no cit aa it ri eon nE ox np l bo (ai 1t n )a ct aio irn e à l’e la xe f rin ci d cee M ap uo r n dot v ea i bsn uit o\nt\nd n dse\ne\ns a lD 'u eo xtt eia t rrt cei io cdn ee M r beo iepn nrt i sa s e sn ost rsd tue isrs bM r ieeo npn srt i ea s nen s t\ns\ns td oue crs\nk\nlC 'l eau\nx\nfm ein ru\nc\ndl\ni\ncà e\ne\nà l’e la xe f rin ci d cee\nl'exercice\nBiens acquis - mourabaha - - - - - - - - - - -\nBiens mobiliers - - - - - - - - - - -\nBiens immobiliers - - - - - - - - - - -\nBiens acquis - mourabaha\n73 798 293 217 334 182 - 32 833 - - - - - 32 833\npour donneur d'ordre\nBiens mobiliers 1 833 17 700 18 339 - 1 194 - - - - - 1 194\nBiens immobiliers 71 965 275 517 315 843 - 31 639 - - - - - 31 639\nBiens acquis - Salam - - - - - - - - - - -\nBiens acquis - autres\n- - - - - - - - - - -\nfinancements participatifs\n(1) Biens cédés en dehors des contrats de finance participative dont les produits de cession sont constatés en hors exploitation bancaire dans le compte 7613\n23\nDÉPÔTS D’INVESTISSEMENTS NON RESTREINTS AU 30 JUIN 2024\n(En milliers de DH)\nDépots d'investissment Encours 01/01/2024 Affectation des résultats Dépôts collectés Dépôts restitués Autres variations Encours 30/06/2024\nDépôts d'investissement recus - - 47 851 1 559 - 46 292\nÉtablissement de crédit - - - - -\nclientèle - - 47 851 1 559 - 46 292\nRéserve de prequération des profits - - - - - -\nÉtablissement de crédit - - - - - -\nclientèle - - - - - -\nRéserve pour risques d'investissements - - - - - -\nÉtablissement de crédit - - - - - -\nclientèle - - - - - -\nRémunération distribuée aux titulaires de\n- 217 - 5 - 212\ncomptes\nÉtablissement de crédit - - - - - -\nclientèle - 217 - 5 - 212\nRésultats en instance d'affectation (+/-) - - - - - -\nTOTAL - 217 47 851 1 564 - 46 504\nATTESTATION DES COMMISSAIRES AUX COMPTES\n(COMPTES SOCIAUX)\nEXERCICE DU 1ER JANVIER AU 30 JUIN 2024\n76, Bd Abdelmoumen\n37, Bd Abdellatif Ben Kaddour\nRésidence Koutoubia, 7ème étage\n20 050 Casablanca\nCasablanca -Maroc\nMaroc\nCREDIT DU MAROC\nATTESTATION D'EXAMEN LIMITE SUR LA SITUATION INTERMEDIAIRE\nDES COMPTES SOCIAUX AU 30 JUIN 2024\nEn application des dispositions du Dahir n° 1-93-212 du 21 septembre 1993 tel que modifié et\ncomplété, nous avons procédé à un examen limité de la situation intermédiaire de Crédit Du Maroc\ncomprenant le bilan et le compte de produits et charges, l'état des soldes de gestion, le tableau de\nflux de trésorerie et une sélection d'états de l'Etat des Informations Complémentaires (ETIC) relatifs\nà la période du 1er janvier au 30 juin 2024. Cette situation intermédiaire qui fait ressortir un montant\nde capitaux propres et assimilés totalisant KMAD 7.826.023 dont un bénéfice net de KMAD 381.342\nrelève de la responsabilité des organes de gestion de la banque.\nNous avons effectué notre mission selon les normes de la Profession au Maroc relatives aux missions\nd'examen limité. Ces normes requièrent que l'examen limité soit planifié et réalisé en vue d'obtenir\nune assurance modérée que la situation intermédiaire ne comporte pas d'anomalie significative. Un\nexamen limité comporte essentiellement des entretiens avec le personnel de la société et des\nvérifications analytiques appliquées aux données financières ; il fournit donc un niveau d'assurance\nmoins élevé qu'un audit. Nous n'avons pas effectué un audit et, en conséquence, nous n'exprimons\ndonc pas d'opinion d'audit.\nSur la base de notre examen limité, nous n'avons pas relevé de faits qui nous laissent penser que la\nsituation intermédiaire, ci-jointe, ne donne pas une image fidèle du résultat des opérations de la\npériode écoulée ainsi que de la situation financière et du patrimoine de la banque arrêtés au 30\njuin 2024, conformément au référentiel comptable admis au Maroc.\nCasablanca, le 23 juillet 2024\nLes Commissaires aux Comptes\nERNST & YOUNG FORVIS MAZARS\nAbdeslam BERRADA ALLAM Taha FERDAOUS\nAssocié Associé\nCRÉDIT DU MAROC, société anonyme à Directoire et à Conseil de Surveillance, au capital de 1 088 121 400 Dhs, RC n° 28 717, agréée en qualité d’établissement de crédit par arrêté du Ministre des Finances et des\n24 Investissements n° 2348-94 du 23 août 1994 relatif aux établissements de crédit agréés de plein droit en qualité de banque Siège social : 201, boulevard d’Anfa, Casablanca - Site web : www creditdumaroc ma",
    "tables": [
        [
            {
                "ACTIF CONSOLIDÉ": "",
                "NOTES": "",
                "30/06/2024": "1 848 172",
                "31/12/2023": ""
            },
            {
                "ACTIF CONSOLIDÉ": "",
                "NOTES": "",
                "30/06/2024": "3 714 436",
                "31/12/2023": ""
            },
            {
                "ACTIF CONSOLIDÉ": "",
                "NOTES": "",
                "30/06/2024": "3 491 844",
                "31/12/2023": ""
            },
            {
                "ACTIF CONSOLIDÉ": "",
                "NOTES": "",
                "30/06/2024": "222 592",
                "31/12/2023": ""
            },
            {
                "ACTIF CONSOLIDÉ": "",
                "NOTES": "",
                "30/06/2024": "-",
                "31/12/2023": ""
            },
            {
                "ACTIF CONSOLIDÉ": "",
                "NOTES": "",
                "30/06/2024": "1 608 810",
                "31/12/2023": ""
            },
            {
                "ACTIF CONSOLIDÉ": "",
                "NOTES": "",
                "30/06/2024": "1 608 810",
                "31/12/2023": ""
            },
            {
                "ACTIF CONSOLIDÉ": "",
                "NOTES": "",
                "30/06/2024": "-",
                "31/12/2023": ""
            },
            {
                "ACTIF CONSOLIDÉ": "",
                "NOTES": "",
                "30/06/2024": "909 118",
                "31/12/2023": ""
            },
            {
                "ACTIF CONSOLIDÉ": "",
                "NOTES": "",
                "30/06/2024": "5 099 485",
                "31/12/2023": ""
            },
            {
                "ACTIF CONSOLIDÉ": "",
                "NOTES": "",
                "30/06/2024": "54 911 005",
                "31/12/2023": ""
            },
            {
                "ACTIF CONSOLIDÉ": "",
                "NOTES": "",
                "30/06/2024": "-",
                "31/12/2023": ""
            },
            {
                "ACTIF CONSOLIDÉ": "",
                "NOTES": "",
                "30/06/2024": "-",
                "31/12/2023": ""
            },
            {
                "ACTIF CONSOLIDÉ": "",
                "NOTES": "",
                "30/06/2024": "4 807",
                "31/12/2023": ""
            },
            {
                "ACTIF CONSOLIDÉ": "",
                "NOTES": "",
                "30/06/2024": "135 551",
                "31/12/2023": ""
            },
            {
                "ACTIF CONSOLIDÉ": "",
                "NOTES": "",
                "30/06/2024": "497 847",
                "31/12/2023": ""
            },
            {
                "ACTIF CONSOLIDÉ": "",
                "NOTES": "",
                "30/06/2024": "-",
                "31/12/2023": ""
            },
            {
                "ACTIF CONSOLIDÉ": "",
                "NOTES": "",
                "30/06/2024": "-",
                "31/12/2023": ""
            },
            {
                "ACTIF CONSOLIDÉ": "",
                "NOTES": "",
                "30/06/2024": "-",
                "31/12/2023": ""
            },
            {
                "ACTIF CONSOLIDÉ": "",
                "NOTES": "",
                "30/06/2024": "1 491 718",
                "31/12/2023": ""
            },
            {
                "ACTIF CONSOLIDÉ": "",
                "NOTES": "",
                "30/06/2024": "824 953",
                "31/12/2023": ""
            },
            {
                "ACTIF CONSOLIDÉ": "",
                "NOTES": "",
                "30/06/2024": "-",
                "31/12/2023": ""
            },
            {
                "ACTIF CONSOLIDÉ": "TOTAL",
                "NOTES": "",
                "30/06/2024": "71 045 901",
                "31/12/2023": "67 265 338"
            }
        ],
        [
            {
                "PASSIF CONSOLIDÉ": "",
                "NOTES": "",
                "30/06/2024": "844",
                "31/12/2023": ""
            },
            {
                "PASSIF CONSOLIDÉ": "",
                "NOTES": "",
                "30/06/2024": "6 901",
                "31/12/2023": ""
            },
            {
                "PASSIF CONSOLIDÉ": "",
                "NOTES": "",
                "30/06/2024": "6 901",
                "31/12/2023": ""
            },
            {
                "PASSIF CONSOLIDÉ": "",
                "NOTES": "",
                "30/06/2024": "-",
                "31/12/2023": ""
            },
            {
                "PASSIF CONSOLIDÉ": "",
                "NOTES": "",
                "30/06/2024": "-",
                "31/12/2023": ""
            },
            {
                "PASSIF CONSOLIDÉ": "",
                "NOTES": "",
                "30/06/2024": "1 470 234",
                "31/12/2023": ""
            },
            {
                "PASSIF CONSOLIDÉ": "",
                "NOTES": "",
                "30/06/2024": "54 778 179",
                "31/12/2023": ""
            },
            {
                "PASSIF CONSOLIDÉ": "",
                "NOTES": "",
                "30/06/2024": "3 501 597",
                "31/12/2023": ""
            },
            {
                "PASSIF CONSOLIDÉ": "",
                "NOTES": "",
                "30/06/2024": "100 429",
                "31/12/2023": ""
            },
            {
                "PASSIF CONSOLIDÉ": "",
                "NOTES": "",
                "30/06/2024": "14 664",
                "31/12/2023": ""
            },
            {
                "PASSIF CONSOLIDÉ": "",
                "NOTES": "",
                "30/06/2024": "2 292 820",
                "31/12/2023": ""
            },
            {
                "PASSIF CONSOLIDÉ": "",
                "NOTES": "",
                "30/06/2024": "-",
                "31/12/2023": ""
            },
            {
                "PASSIF CONSOLIDÉ": "",
                "NOTES": "",
                "30/06/2024": "-",
                "31/12/2023": ""
            },
            {
                "PASSIF CONSOLIDÉ": "",
                "NOTES": "",
                "30/06/2024": "555 324",
                "31/12/2023": ""
            },
            {
                "PASSIF CONSOLIDÉ": "",
                "NOTES": "",
                "30/06/2024": "-",
                "31/12/2023": ""
            },
            {
                "PASSIF CONSOLIDÉ": "",
                "NOTES": "",
                "30/06/2024": "1 275 929",
                "31/12/2023": ""
            },
            {
                "PASSIF CONSOLIDÉ": "",
                "NOTES": "",
                "30/06/2024": "7 048 980",
                "31/12/2023": ""
            },
            {
                "PASSIF CONSOLIDÉ": "",
                "NOTES": "",
                "30/06/2024": "4 346 514",
                "31/12/2023": ""
            },
            {
                "PASSIF CONSOLIDÉ": "",
                "NOTES": "",
                "30/06/2024": "2 272 908",
                "31/12/2023": ""
            },
            {
                "PASSIF CONSOLIDÉ": "",
                "NOTES": "",
                "30/06/2024": "2 272 908",
                "31/12/2023": ""
            },
            {
                "PASSIF CONSOLIDÉ": "",
                "NOTES": "",
                "30/06/2024": "-",
                "31/12/2023": ""
            },
            {
                "PASSIF CONSOLIDÉ": "",
                "NOTES": "",
                "30/06/2024": "38 724",
                "31/12/2023": ""
            },
            {
                "PASSIF CONSOLIDÉ": "",
                "NOTES": "",
                "30/06/2024": "38 724",
                "31/12/2023": ""
            },
            {
                "PASSIF CONSOLIDÉ": "",
                "NOTES": "",
                "30/06/2024": "-",
                "31/12/2023": ""
            },
            {
                "PASSIF CONSOLIDÉ": "",
                "NOTES": "",
                "30/06/2024": "390 835",
                "31/12/2023": ""
            },
            {
                "PASSIF CONSOLIDÉ": "",
                "NOTES": "",
                "30/06/2024": "390 835",
                "31/12/2023": ""
            },
            {
                "PASSIF CONSOLIDÉ": "",
                "NOTES": "",
                "30/06/2024": "-",
                "31/12/2023": ""
            },
            {
                "PASSIF CONSOLIDÉ": "TOTAL",
                "NOTES": "",
                "30/06/2024": "71 045 901",
                "31/12/2023": "67 265 338"
            }
        ],
        [
            {
                "COMPTE DE RÉSULTAT": "",
                "NOTES": "",
                "30/06/2024": "1 544 030",
                "30/06/2023": "1 311 552"
            },
            {
                "COMPTE DE RÉSULTAT": "",
                "NOTES": "",
                "30/06/2024": "357 557",
                "30/06/2023": "228 765"
            },
            {
                "COMPTE DE RÉSULTAT": "Marge d'Intérêt",
                "NOTES": "",
                "30/06/2024": "1 186 473",
                "30/06/2023": "1 082 787"
            },
            {
                "COMPTE DE RÉSULTAT": "",
                "NOTES": "",
                "30/06/2024": "270 788",
                "30/06/2023": "247 749"
            },
            {
                "COMPTE DE RÉSULTAT": "",
                "NOTES": "",
                "30/06/2024": "24 519",
                "30/06/2023": "21 935"
            },
            {
                "COMPTE DE RÉSULTAT": "Marge sur Commissions",
                "NOTES": "",
                "30/06/2024": "246 269",
                "30/06/2023": "225 813"
            },
            {
                "COMPTE DE RÉSULTAT": "",
                "NOTES": "",
                "30/06/2024": "-",
                "30/06/2023": "-"
            },
            {
                "COMPTE DE RÉSULTAT": "",
                "NOTES": "",
                "30/06/2024": "218 885",
                "30/06/2023": "168 156"
            },
            {
                "COMPTE DE RÉSULTAT": "",
                "NOTES": "",
                "30/06/2024": "211 835",
                "30/06/2023": "169 760"
            },
            {
                "COMPTE DE RÉSULTAT": "",
                "NOTES": "",
                "30/06/2024": "7 049",
                "30/06/2023": "-1 604"
            },
            {
                "COMPTE DE RÉSULTAT": "",
                "NOTES": "",
                "30/06/2024": "-",
                "30/06/2023": "-"
            },
            {
                "COMPTE DE RÉSULTAT": "",
                "NOTES": "",
                "30/06/2024": "-",
                "30/06/2023": "-"
            },
            {
                "COMPTE DE RÉSULTAT": "",
                "NOTES": "",
                "30/06/2024": "-",
                "30/06/2023": "-"
            },
            {
                "COMPTE DE RÉSULTAT": "",
                "NOTES": "",
                "30/06/2024": "-",
                "30/06/2023": "-"
            },
            {
                "COMPTE DE RÉSULTAT": "",
                "NOTES": "",
                "30/06/2024": "-",
                "30/06/2023": "-"
            },
            {
                "COMPTE DE RÉSULTAT": "",
                "NOTES": "",
                "30/06/2024": "-",
                "30/06/2023": "-"
            },
            {
                "COMPTE DE RÉSULTAT": "",
                "NOTES": "",
                "30/06/2024": "-",
                "30/06/2023": "-"
            },
            {
                "COMPTE DE RÉSULTAT": "",
                "NOTES": "",
                "30/06/2024": "16 522",
                "30/06/2023": "10 839"
            },
            {
                "COMPTE DE RÉSULTAT": "",
                "NOTES": "",
                "30/06/2024": "62 169",
                "30/06/2023": "61 559"
            },
            {
                "COMPTE DE RÉSULTAT": "PRODUIT NET BANCAIRE",
                "NOTES": "",
                "30/06/2024": "1 605 979",
                "30/06/2023": "1 426 037"
            },
            {
                "COMPTE DE RÉSULTAT": "",
                "NOTES": "",
                "30/06/2024": "649 974",
                "30/06/2023": "627 155"
            },
            {
                "COMPTE DE RÉSULTAT": "",
                "NOTES": "",
                "30/06/2024": "132 295",
                "30/06/2023": "98 490"
            },
            {
                "COMPTE DE RÉSULTAT": "Résultat Brut d'Exploitation",
                "NOTES": "",
                "30/06/2024": "823 709",
                "30/06/2023": "700 391"
            },
            {
                "COMPTE DE RÉSULTAT": "",
                "NOTES": "",
                "30/06/2024": "-111 870",
                "30/06/2023": "-166 067"
            },
            {
                "COMPTE DE RÉSULTAT": "Résultat d'Exploitation",
                "NOTES": "",
                "30/06/2024": "711 839",
                "30/06/2023": "534 325"
            },
            {
                "COMPTE DE RÉSULTAT": "",
                "NOTES": "",
                "30/06/2024": "-",
                "30/06/2023": "-"
            },
            {
                "COMPTE DE RÉSULTAT": "",
                "NOTES": "",
                "30/06/2024": "-3 547",
                "30/06/2023": "-7 273"
            },
            {
                "COMPTE DE RÉSULTAT": "",
                "NOTES": "",
                "30/06/2024": "-",
                "30/06/2023": "-"
            },
            {
                "COMPTE DE RÉSULTAT": "Résultat avant Impôt",
                "NOTES": "",
                "30/06/2024": "708 293",
                "30/06/2023": "527 051"
            },
            {
                "COMPTE DE RÉSULTAT": "",
                "NOTES": "",
                "30/06/2024": "317 458",
                "30/06/2023": "239 565"
            },
            {
                "COMPTE DE RÉSULTAT": "",
                "NOTES": "",
                "30/06/2024": "-",
                "30/06/2023": "-"
            },
            {
                "COMPTE DE RÉSULTAT": "Résultat net (*)",
                "NOTES": "",
                "30/06/2024": "390 835",
                "30/06/2023": "287 487"
            },
            {
                "COMPTE DE RÉSULTAT": "",
                "NOTES": "",
                "30/06/2024": "-",
                "30/06/2023": "1 694"
            },
            {
                "COMPTE DE RÉSULTAT": "Résultat net Part du groupe",
                "NOTES": "",
                "30/06/2024": "390 835",
                "30/06/2023": "285 793"
            },
            {
                "COMPTE DE RÉSULTAT": "",
                "NOTES": "",
                "30/06/2024": "35,92",
                "30/06/2023": "26,26"
            },
            {
                "COMPTE DE RÉSULTAT": "",
                "NOTES": "",
                "30/06/2024": "35,92",
                "30/06/2023": "26,26"
            }
        ],
        [
            {
                "FLUX DE TRESORERIE": "Résultat avant impôts",
                "30/06/2024": "708 293",
                "31/12/2023": "878 307"
            },
            {
                "FLUX DE TRESORERIE": "Résultat net des activités abandonnées",
                "30/06/2024": "-",
                "31/12/2023": "-"
            },
            {
                "FLUX DE TRESORERIE": "",
                "30/06/2024": "132 295",
                "31/12/2023": "232 914"
            },
            {
                "FLUX DE TRESORERIE": "",
                "30/06/2024": "-",
                "31/12/2023": "-"
            },
            {
                "FLUX DE TRESORERIE": "",
                "30/06/2024": "107 404",
                "31/12/2023": "289 796"
            },
            {
                "FLUX DE TRESORERIE": "",
                "30/06/2024": "-9 439",
                "31/12/2023": "-41 381"
            },
            {
                "FLUX DE TRESORERIE": "",
                "30/06/2024": "-",
                "31/12/2023": "-"
            },
            {
                "FLUX DE TRESORERIE": "",
                "30/06/2024": "-3 547",
                "31/12/2023": "-4 425"
            },
            {
                "FLUX DE TRESORERIE": "",
                "30/06/2024": "44 155",
                "31/12/2023": "11 890"
            },
            {
                "FLUX DE TRESORERIE": "",
                "30/06/2024": "97 985",
                "31/12/2023": "-102 184"
            },
            {
                "FLUX DE TRESORERIE": "Total des éléments non monétaires inclus dans le résultat net avant\nimpôts et des autres ajustements",
                "30/06/2024": "368 854",
                "31/12/2023": "386 610"
            },
            {
                "FLUX DE TRESORERIE": "",
                "30/06/2024": "3 376 972",
                "31/12/2023": "-3 644 519"
            },
            {
                "FLUX DE TRESORERIE": "",
                "30/06/2024": "-976 664",
                "31/12/2023": "356 201"
            },
            {
                "FLUX DE TRESORERIE": "",
                "30/06/2024": "-1 170 329",
                "31/12/2023": "-465 570"
            },
            {
                "FLUX DE TRESORERIE": "",
                "30/06/2024": "152 338",
                "31/12/2023": "595 979"
            },
            {
                "FLUX DE TRESORERIE": "",
                "30/06/2024": "-",
                "31/12/2023": "-"
            },
            {
                "FLUX DE TRESORERIE": "",
                "30/06/2024": "-297 557",
                "31/12/2023": "-396 449"
            },
            {
                "FLUX DE TRESORERIE": "Diminution/(augmentation) nette des actifs et des passifs provenant\ndes activités opérationnelles",
                "30/06/2024": "1 084 760",
                "31/12/2023": "-3 554 358"
            },
            {
                "FLUX DE TRESORERIE": "Flux nets de trésorerie généré par l’activité opérationnelle",
                "30/06/2024": "2 161 907",
                "31/12/2023": "-2 289 440"
            },
            {
                "FLUX DE TRESORERIE": "",
                "30/06/2024": "-",
                "31/12/2023": "-"
            },
            {
                "FLUX DE TRESORERIE": "",
                "30/06/2024": "-",
                "31/12/2023": "-"
            },
            {
                "FLUX DE TRESORERIE": "",
                "30/06/2024": "-153 691",
                "31/12/2023": "-441 626"
            },
            {
                "FLUX DE TRESORERIE": "Flux nets de trésorerie lié aux opérations d’investissement",
                "30/06/2024": "-153 691",
                "31/12/2023": "-441 626"
            },
            {
                "FLUX DE TRESORERIE": "",
                "30/06/2024": "-372 138",
                "31/12/2023": "200 138"
            },
            {
                "FLUX DE TRESORERIE": "",
                "30/06/2024": "58 000",
                "31/12/2023": "1 800 000"
            },
            {
                "FLUX DE TRESORERIE": "Flux nets de trésorerie lié aux opérations de financement",
                "30/06/2024": "-314 138",
                "31/12/2023": "2 000 138"
            },
            {
                "FLUX DE TRESORERIE": "Effet de la variation des taux de change sur la trésorerie et équivalent\nde trésorerie",
                "30/06/2024": "186",
                "31/12/2023": "-2 924"
            },
            {
                "FLUX DE TRESORERIE": "Augmentation/(diminution) nette de la trésorerie et des équivalents\nde trésorerie",
                "30/06/2024": "1 694 265",
                "31/12/2023": "-733 852"
            }
        ],
        [
            {
                "COMPOSITION DE LA TRESORERIE": "Trésorerie et équivalents de trésorerie à l’ouverture",
                "30/06/2024": "2 525 258",
                "31/12/2023": "3 259 110"
            },
            {
                "COMPOSITION DE LA TRESORERIE": "",
                "30/06/2024": "2 265 415",
                "31/12/2023": "1 868 563"
            },
            {
                "COMPOSITION DE LA TRESORERIE": "",
                "30/06/2024": "259 842",
                "31/12/2023": "1 390 546"
            },
            {
                "COMPOSITION DE LA TRESORERIE": "Trésorerie et équivalents de trésorerie à la clôture",
                "30/06/2024": "4 219 522",
                "31/12/2023": "2 525 258"
            },
            {
                "COMPOSITION DE LA TRESORERIE": "",
                "30/06/2024": "1 848 123",
                "31/12/2023": "2 265 415"
            },
            {
                "COMPOSITION DE LA TRESORERIE": "",
                "30/06/2024": "2 371 399",
                "31/12/2023": "259 842"
            },
            {
                "COMPOSITION DE LA TRESORERIE": "Variation de la trésorerie nette",
                "30/06/2024": "1 694 265",
                "31/12/2023": "-733 852"
            }
        ],
        [
            {
                "Résultat net et gains et pertes comptabilisés directement en capitaux propres": "Résultat net",
                "30/06/2024": "390 835",
                "31/12/2023": "498 225"
            },
            {
                "Résultat net et gains et pertes comptabilisés directement en capitaux propres": "",
                "30/06/2024": "826",
                "31/12/2023": "28 175"
            },
            {
                "Résultat net et gains et pertes comptabilisés directement en capitaux propres": "",
                "30/06/2024": "186",
                "31/12/2023": "-2 924"
            },
            {
                "Résultat net et gains et pertes comptabilisés directement en capitaux propres": "",
                "30/06/2024": "1 390",
                "31/12/2023": "50 292"
            },
            {
                "Résultat net et gains et pertes comptabilisés directement en capitaux propres": "",
                "30/06/2024": "-",
                "31/12/2023": "-"
            },
            {
                "Résultat net et gains et pertes comptabilisés directement en capitaux propres": "",
                "30/06/2024": "-",
                "31/12/2023": "-"
            },
            {
                "Résultat net et gains et pertes comptabilisés directement en capitaux propres": "",
                "30/06/2024": "-",
                "31/12/2023": "-"
            },
            {
                "Résultat net et gains et pertes comptabilisés directement en capitaux propres": "",
                "30/06/2024": "750",
                "31/12/2023": "19 193"
            },
            {
                "Résultat net et gains et pertes comptabilisés directement en capitaux propres": "",
                "30/06/2024": "825",
                "31/12/2023": "-4 116"
            },
            {
                "Résultat net et gains et pertes comptabilisés directement en capitaux propres": "",
                "30/06/2024": "-",
                "31/12/2023": "-"
            },
            {
                "Résultat net et gains et pertes comptabilisés directement en capitaux propres": "",
                "30/06/2024": "1 191",
                "31/12/2023": "-6 929"
            },
            {
                "Résultat net et gains et pertes comptabilisés directement en capitaux propres": "",
                "30/06/2024": "-",
                "31/12/2023": "-"
            },
            {
                "Résultat net et gains et pertes comptabilisés directement en capitaux propres": "",
                "30/06/2024": "-",
                "31/12/2023": "-"
            },
            {
                "Résultat net et gains et pertes comptabilisés directement en capitaux propres": "",
                "30/06/2024": "-",
                "31/12/2023": "-"
            },
            {
                "Résultat net et gains et pertes comptabilisés directement en capitaux propres": "",
                "30/06/2024": "-",
                "31/12/2023": "-"
            },
            {
                "Résultat net et gains et pertes comptabilisés directement en capitaux propres": "",
                "30/06/2024": "366",
                "31/12/2023": "-2 813"
            },
            {
                "Résultat net et gains et pertes comptabilisés directement en capitaux propres": "Total des gains et pertes comptabilisés directement en capitaux propres",
                "30/06/2024": "1 651",
                "31/12/2023": "24 058"
            }
        ],
        [
            {
                "392 486": "392 486",
                "522 283": "527 147"
            },
            {
                "392 486": "-",
                "522 283": "-4 864"
            }
        ],
        [
            {
                "": "CAPITAUX PROPRES CLÔTURE AU 31 DÉCEMBRE 2022",
                "Capital": "1 088 121",
                "Réserves\nliées au\ncapital": "2 766 149",
                "Actions\npropres": "-",
                "Réserves\net résultats\nconsolidés": "2 444 050",
                "Gains et pertes\ncomptabilisés\ndirectement en\ncapitaux propres\nrecyclables": "10 567",
                "Gains et pertes\ncomptabilisés\ndirectement en\ncapitaux propres\nnon recyclables": "-",
                "Capitaux\npropres part\nGroupe": "6 308 887",
                "Intérêts\nminoritaires": "50 576",
                "Total": "6 359 463"
            },
            {
                "": "",
                "Capital": "",
                "Réserves\nliées au\ncapital": "",
                "Actions\npropres": "",
                "Réserves\net résultats\nconsolidés": "",
                "Gains et pertes\ncomptabilisés\ndirectement en\ncapitaux propres\nrecyclables": "",
                "Gains et pertes\ncomptabilisés\ndirectement en\ncapitaux propres\nnon recyclables": "",
                "Capitaux\npropres part\nGroupe": "",
                "Intérêts\nminoritaires": "",
                "Total": "-"
            },
            {
                "": "",
                "Capital": "",
                "Réserves\nliées au\ncapital": "",
                "Actions\npropres": "",
                "Réserves\net résultats\nconsolidés": "",
                "Gains et pertes\ncomptabilisés\ndirectement en\ncapitaux propres\nrecyclables": "",
                "Gains et pertes\ncomptabilisés\ndirectement en\ncapitaux propres\nnon recyclables": "",
                "Capitaux\npropres part\nGroupe": "",
                "Intérêts\nminoritaires": "",
                "Total": "-"
            },
            {
                "": "",
                "Capital": "",
                "Réserves\nliées au\ncapital": "",
                "Actions\npropres": "",
                "Réserves\net résultats\nconsolidés": "",
                "Gains et pertes\ncomptabilisés\ndirectement en\ncapitaux propres\nrecyclables": "",
                "Gains et pertes\ncomptabilisés\ndirectement en\ncapitaux propres\nnon recyclables": "",
                "Capitaux\npropres part\nGroupe": "",
                "Intérêts\nminoritaires": "",
                "Total": "-"
            },
            {
                "": "",
                "Capital": "",
                "Réserves\nliées au\ncapital": "",
                "Actions\npropres": "",
                "Réserves\net résultats\nconsolidés": "",
                "Gains et pertes\ncomptabilisés\ndirectement en\ncapitaux propres\nrecyclables": "",
                "Gains et pertes\ncomptabilisés\ndirectement en\ncapitaux propres\nnon recyclables": "",
                "Capitaux\npropres part\nGroupe": "",
                "Intérêts\nminoritaires": "",
                "Total": "-293 793"
            },
            {
                "": "",
                "Capital": "",
                "Réserves\nliées au\ncapital": "",
                "Actions\npropres": "",
                "Réserves\net résultats\nconsolidés": "",
                "Gains et pertes\ncomptabilisés\ndirectement en\ncapitaux propres\nrecyclables": "",
                "Gains et pertes\ncomptabilisés\ndirectement en\ncapitaux propres\nnon recyclables": "",
                "Capitaux\npropres part\nGroupe": "",
                "Intérêts\nminoritaires": "",
                "Total": "492 244"
            },
            {
                "": "",
                "Capital": "",
                "Réserves\nliées au\ncapital": "",
                "Actions\npropres": "",
                "Réserves\net résultats\nconsolidés": "",
                "Gains et pertes\ncomptabilisés\ndirectement en\ncapitaux propres\nrecyclables": "",
                "Gains et pertes\ncomptabilisés\ndirectement en\ncapitaux propres\nnon recyclables": "",
                "Capitaux\npropres part\nGroupe": "",
                "Intérêts\nminoritaires": "",
                "Total": "-"
            },
            {
                "": "",
                "Capital": "",
                "Réserves\nliées au\ncapital": "",
                "Actions\npropres": "",
                "Réserves\net résultats\nconsolidés": "",
                "Gains et pertes\ncomptabilisés\ndirectement en\ncapitaux propres\nrecyclables": "",
                "Gains et pertes\ncomptabilisés\ndirectement en\ncapitaux propres\nnon recyclables": "",
                "Capitaux\npropres part\nGroupe": "",
                "Intérêts\nminoritaires": "",
                "Total": "498 225"
            },
            {
                "": "",
                "Capital": "",
                "Réserves\nliées au\ncapital": "",
                "Actions\npropres": "",
                "Réserves\net résultats\nconsolidés": "",
                "Gains et pertes\ncomptabilisés\ndirectement en\ncapitaux propres\nrecyclables": "",
                "Gains et pertes\ncomptabilisés\ndirectement en\ncapitaux propres\nnon recyclables": "",
                "Capitaux\npropres part\nGroupe": "",
                "Intérêts\nminoritaires": "",
                "Total": "-"
            },
            {
                "": "",
                "Capital": "",
                "Réserves\nliées au\ncapital": "",
                "Actions\npropres": "",
                "Réserves\net résultats\nconsolidés": "",
                "Gains et pertes\ncomptabilisés\ndirectement en\ncapitaux propres\nrecyclables": "",
                "Gains et pertes\ncomptabilisés\ndirectement en\ncapitaux propres\nnon recyclables": "",
                "Capitaux\npropres part\nGroupe": "",
                "Intérêts\nminoritaires": "",
                "Total": "31 099"
            },
            {
                "": "",
                "Capital": "",
                "Réserves\nliées au\ncapital": "",
                "Actions\npropres": "",
                "Réserves\net résultats\nconsolidés": "",
                "Gains et pertes\ncomptabilisés\ndirectement en\ncapitaux propres\nrecyclables": "",
                "Gains et pertes\ncomptabilisés\ndirectement en\ncapitaux propres\nnon recyclables": "",
                "Capitaux\npropres part\nGroupe": "",
                "Intérêts\nminoritaires": "",
                "Total": "-4 406"
            },
            {
                "": "",
                "Capital": "",
                "Réserves\nliées au\ncapital": "",
                "Actions\npropres": "",
                "Réserves\net résultats\nconsolidés": "",
                "Gains et pertes\ncomptabilisés\ndirectement en\ncapitaux propres\nrecyclables": "",
                "Gains et pertes\ncomptabilisés\ndirectement en\ncapitaux propres\nnon recyclables": "",
                "Capitaux\npropres part\nGroupe": "",
                "Intérêts\nminoritaires": "",
                "Total": "-2 924"
            },
            {
                "": "",
                "Capital": "",
                "Réserves\nliées au\ncapital": "",
                "Actions\npropres": "",
                "Réserves\net résultats\nconsolidés": "",
                "Gains et pertes\ncomptabilisés\ndirectement en\ncapitaux propres\nrecyclables": "",
                "Gains et pertes\ncomptabilisés\ndirectement en\ncapitaux propres\nnon recyclables": "",
                "Capitaux\npropres part\nGroupe": "",
                "Intérêts\nminoritaires": "",
                "Total": "23 768"
            },
            {
                "": "",
                "Capital": "",
                "Réserves\nliées au\ncapital": "",
                "Actions\npropres": "",
                "Réserves\net résultats\nconsolidés": "",
                "Gains et pertes\ncomptabilisés\ndirectement en\ncapitaux propres\nrecyclables": "",
                "Gains et pertes\ncomptabilisés\ndirectement en\ncapitaux propres\nnon recyclables": "",
                "Capitaux\npropres part\nGroupe": "",
                "Intérêts\nminoritaires": "",
                "Total": "-"
            },
            {
                "": "",
                "Capital": "",
                "Réserves\nliées au\ncapital": "",
                "Actions\npropres": "",
                "Réserves\net résultats\nconsolidés": "",
                "Gains et pertes\ncomptabilisés\ndirectement en\ncapitaux propres\nrecyclables": "",
                "Gains et pertes\ncomptabilisés\ndirectement en\ncapitaux propres\nnon recyclables": "",
                "Capitaux\npropres part\nGroupe": "",
                "Intérêts\nminoritaires": "",
                "Total": "-"
            },
            {
                "": "CAPITAUX PROPRES CLÔTURE AU 31 DÉCEMBRE 2023",
                "Capital": "1 088 121",
                "Réserves\nliées au\ncapital": "3 258 393",
                "Actions\npropres": "-",
                "Réserves\net résultats\nconsolidés": "2 650 422",
                "Gains et pertes\ncomptabilisés\ndirectement en\ncapitaux propres\nrecyclables": "37 259",
                "Gains et pertes\ncomptabilisés\ndirectement en\ncapitaux propres\nnon recyclables": "-",
                "Capitaux\npropres part\nGroupe": "7 034 195",
                "Intérêts\nminoritaires": "45 712",
                "Total": "7 079 907"
            },
            {
                "": "",
                "Capital": "",
                "Réserves\nliées au\ncapital": "",
                "Actions\npropres": "",
                "Réserves\net résultats\nconsolidés": "",
                "Gains et pertes\ncomptabilisés\ndirectement en\ncapitaux propres\nrecyclables": "",
                "Gains et pertes\ncomptabilisés\ndirectement en\ncapitaux propres\nnon recyclables": "",
                "Capitaux\npropres part\nGroupe": "",
                "Intérêts\nminoritaires": "",
                "Total": "-"
            },
            {
                "": "",
                "Capital": "",
                "Réserves\nliées au\ncapital": "",
                "Actions\npropres": "",
                "Réserves\net résultats\nconsolidés": "",
                "Gains et pertes\ncomptabilisés\ndirectement en\ncapitaux propres\nrecyclables": "",
                "Gains et pertes\ncomptabilisés\ndirectement en\ncapitaux propres\nnon recyclables": "",
                "Capitaux\npropres part\nGroupe": "",
                "Intérêts\nminoritaires": "",
                "Total": "-"
            },
            {
                "": "",
                "Capital": "",
                "Réserves\nliées au\ncapital": "",
                "Actions\npropres": "",
                "Réserves\net résultats\nconsolidés": "",
                "Gains et pertes\ncomptabilisés\ndirectement en\ncapitaux propres\nrecyclables": "",
                "Gains et pertes\ncomptabilisés\ndirectement en\ncapitaux propres\nnon recyclables": "",
                "Capitaux\npropres part\nGroupe": "",
                "Intérêts\nminoritaires": "",
                "Total": "-"
            },
            {
                "": "",
                "Capital": "",
                "Réserves\nliées au\ncapital": "",
                "Actions\npropres": "",
                "Réserves\net résultats\nconsolidés": "",
                "Gains et pertes\ncomptabilisés\ndirectement en\ncapitaux propres\nrecyclables": "",
                "Gains et pertes\ncomptabilisés\ndirectement en\ncapitaux propres\nnon recyclables": "",
                "Capitaux\npropres part\nGroupe": "",
                "Intérêts\nminoritaires": "",
                "Total": "-372 138"
            },
            {
                "": "",
                "Capital": "",
                "Réserves\nliées au\ncapital": "",
                "Actions\npropres": "",
                "Réserves\net résultats\nconsolidés": "",
                "Gains et pertes\ncomptabilisés\ndirectement en\ncapitaux propres\nrecyclables": "",
                "Gains et pertes\ncomptabilisés\ndirectement en\ncapitaux propres\nnon recyclables": "",
                "Capitaux\npropres part\nGroupe": "",
                "Intérêts\nminoritaires": "",
                "Total": "-"
            },
            {
                "": "",
                "Capital": "",
                "Réserves\nliées au\ncapital": "",
                "Actions\npropres": "",
                "Réserves\net résultats\nconsolidés": "",
                "Gains et pertes\ncomptabilisés\ndirectement en\ncapitaux propres\nrecyclables": "",
                "Gains et pertes\ncomptabilisés\ndirectement en\ncapitaux propres\nnon recyclables": "",
                "Capitaux\npropres part\nGroupe": "",
                "Intérêts\nminoritaires": "",
                "Total": "-"
            },
            {
                "": "",
                "Capital": "",
                "Réserves\nliées au\ncapital": "",
                "Actions\npropres": "",
                "Réserves\net résultats\nconsolidés": "",
                "Gains et pertes\ncomptabilisés\ndirectement en\ncapitaux propres\nrecyclables": "",
                "Gains et pertes\ncomptabilisés\ndirectement en\ncapitaux propres\nnon recyclables": "",
                "Capitaux\npropres part\nGroupe": "",
                "Intérêts\nminoritaires": "",
                "Total": "390 835"
            },
            {
                "": "",
                "Capital": "",
                "Réserves\nliées au\ncapital": "",
                "Actions\npropres": "",
                "Réserves\net résultats\nconsolidés": "",
                "Gains et pertes\ncomptabilisés\ndirectement en\ncapitaux propres\nrecyclables": "",
                "Gains et pertes\ncomptabilisés\ndirectement en\ncapitaux propres\nnon recyclables": "",
                "Capitaux\npropres part\nGroupe": "",
                "Intérêts\nminoritaires": "",
                "Total": "-"
            },
            {
                "": "",
                "Capital": "",
                "Réserves\nliées au\ncapital": "",
                "Actions\npropres": "",
                "Réserves\net résultats\nconsolidés": "",
                "Gains et pertes\ncomptabilisés\ndirectement en\ncapitaux propres\nrecyclables": "",
                "Gains et pertes\ncomptabilisés\ndirectement en\ncapitaux propres\nnon recyclables": "",
                "Capitaux\npropres part\nGroupe": "",
                "Intérêts\nminoritaires": "",
                "Total": "640"
            },
            {
                "": "",
                "Capital": "",
                "Réserves\nliées au\ncapital": "",
                "Actions\npropres": "",
                "Réserves\net résultats\nconsolidés": "",
                "Gains et pertes\ncomptabilisés\ndirectement en\ncapitaux propres\nrecyclables": "",
                "Gains et pertes\ncomptabilisés\ndirectement en\ncapitaux propres\nnon recyclables": "",
                "Capitaux\npropres part\nGroupe": "",
                "Intérêts\nminoritaires": "",
                "Total": "825"
            },
            {
                "": "",
                "Capital": "",
                "Réserves\nliées au\ncapital": "",
                "Actions\npropres": "",
                "Réserves\net résultats\nconsolidés": "",
                "Gains et pertes\ncomptabilisés\ndirectement en\ncapitaux propres\nrecyclables": "",
                "Gains et pertes\ncomptabilisés\ndirectement en\ncapitaux propres\nnon recyclables": "",
                "Capitaux\npropres part\nGroupe": "",
                "Intérêts\nminoritaires": "",
                "Total": "186"
            },
            {
                "": "",
                "Capital": "",
                "Réserves\nliées au\ncapital": "",
                "Actions\npropres": "",
                "Réserves\net résultats\nconsolidés": "",
                "Gains et pertes\ncomptabilisés\ndirectement en\ncapitaux propres\nrecyclables": "",
                "Gains et pertes\ncomptabilisés\ndirectement en\ncapitaux propres\nnon recyclables": "",
                "Capitaux\npropres part\nGroupe": "",
                "Intérêts\nminoritaires": "",
                "Total": "1 651"
            },
            {
                "": "",
                "Capital": "",
                "Réserves\nliées au\ncapital": "",
                "Actions\npropres": "",
                "Réserves\net résultats\nconsolidés": "",
                "Gains et pertes\ncomptabilisés\ndirectement en\ncapitaux propres\nrecyclables": "",
                "Gains et pertes\ncomptabilisés\ndirectement en\ncapitaux propres\nnon recyclables": "",
                "Capitaux\npropres part\nGroupe": "",
                "Intérêts\nminoritaires": "",
                "Total": "155"
            },
            {
                "": "",
                "Capital": "",
                "Réserves\nliées au\ncapital": "",
                "Actions\npropres": "",
                "Réserves\net résultats\nconsolidés": "",
                "Gains et pertes\ncomptabilisés\ndirectement en\ncapitaux propres\nrecyclables": "",
                "Gains et pertes\ncomptabilisés\ndirectement en\ncapitaux propres\nnon recyclables": "",
                "Capitaux\npropres part\nGroupe": "",
                "Intérêts\nminoritaires": "",
                "Total": "-51 429"
            },
            {
                "": "CAPITAUX PROPRES CLÔTURE AU 30 JUIN 2024",
                "Capital": "1 088 121",
                "Réserves\nliées au\ncapital": "3 258 393",
                "Actions\npropres": "-",
                "Réserves\net résultats\nconsolidés": "2 663 743",
                "Gains et pertes\ncomptabilisés\ndirectement en\ncapitaux propres\nrecyclables": "38 724",
                "Gains et pertes\ncomptabilisés\ndirectement en\ncapitaux propres\nnon recyclables": "-",
                "Capitaux\npropres part\nGroupe": "7 048 980",
                "Intérêts\nminoritaires": "-",
                "Total": "7 048 980"
            }
        ],
        [
            {
                "Sociétés Consolidées": "",
                "Capital social\n(KDH)": "",
                "Capital social\n(KUSD)": "",
                "%": "de contrôle",
                "null": "d’intérêts",
                "Méthode de consolidation\n(*)": ""
            }
        ],
        [],
        [],
        [
            {
                "Pilier I": "Risque couvert",
                "null": "Méthode d’évaluation\net de gestion"
            }
        ],
        [
            {
                "null": "",
                "": ""
            },
            {
                "null": "",
                "": ""
            },
            {
                "null": "",
                "": ""
            },
            {
                "null": "",
                "": ""
            }
        ],
        [],
        [],
        [
            {
                "": "",
                "null": "Exigences\nen fonds propres",
                "déc-23": "Actifs\npondérés",
                "juin-24": "Actifs\npondérés",
                "Variation": "Actifs\npondérés"
            },
            {
                "": "",
                "null": "342 756",
                "déc-23": "42 375 958",
                "juin-24": "46 660 407",
                "Variation": "4 284 449"
            },
            {
                "": "",
                "null": "2 609",
                "déc-23": "8 167",
                "juin-24": "40 774",
                "Variation": "32 607"
            },
            {
                "": "",
                "null": "11 780",
                "déc-23": "2 870 776",
                "juin-24": "3 018 021",
                "Variation": "147 245"
            },
            {
                "": "",
                "null": "243 564",
                "déc-23": "26 987 922",
                "juin-24": "30 032 475",
                "Variation": "3 044 554"
            },
            {
                "": "",
                "null": "55 057",
                "déc-23": "9 696 433",
                "juin-24": "10 384 646",
                "Variation": "688 212"
            },
            {
                "": "",
                "null": "13 213",
                "déc-23": "755 608",
                "juin-24": "920 776",
                "Variation": "165 168"
            },
            {
                "": "",
                "null": "20 131",
                "déc-23": "4 970 090",
                "juin-24": "5 221 726",
                "Variation": "251 636"
            },
            {
                "": "",
                "null": "376 100",
                "déc-23": "48 101 656",
                "juin-24": "52 802 909",
                "Variation": "4 701 252"
            }
        ],
        [],
        [
            {
                "11,42%": "13,36%"
            }
        ],
        [
            {
                "Exigences en fonds propres": "",
                "31/12/2023": "",
                "30/06/2024": "48 160"
            },
            {
                "Exigences en fonds propres": "",
                "31/12/2023": "",
                "30/06/2024": "5 354"
            },
            {
                "Exigences en fonds propres": "",
                "31/12/2023": "",
                "30/06/2024": "42 806"
            },
            {
                "Exigences en fonds propres": "",
                "31/12/2023": "",
                "30/06/2024": "25 502"
            },
            {
                "Exigences en fonds propres": "Total",
                "31/12/2023": "60 449",
                "30/06/2024": "73 662"
            }
        ],
        [
            {
                "CONSOLIDE": "",
                "30/06/2024": "-24 673",
                "30/06/2023": ""
            },
            {
                "CONSOLIDE": "",
                "30/06/2024": "-4 358",
                "30/06/2023": ""
            },
            {
                "CONSOLIDE": "",
                "30/06/2024": "522",
                "30/06/2023": ""
            },
            {
                "CONSOLIDE": "",
                "30/06/2024": "-4 264",
                "30/06/2023": ""
            },
            {
                "CONSOLIDE": "",
                "30/06/2024": "-616",
                "30/06/2023": ""
            },
            {
                "CONSOLIDE": "",
                "30/06/2024": "-20 315",
                "30/06/2023": ""
            },
            {
                "CONSOLIDE": "",
                "30/06/2024": "-",
                "30/06/2023": ""
            },
            {
                "CONSOLIDE": "",
                "30/06/2024": "-11 016",
                "30/06/2023": ""
            },
            {
                "CONSOLIDE": "",
                "30/06/2024": "-9 299",
                "30/06/2023": ""
            },
            {
                "CONSOLIDE": "",
                "30/06/2024": "-",
                "30/06/2023": ""
            },
            {
                "CONSOLIDE": "",
                "30/06/2024": "-43 742",
                "30/06/2023": ""
            },
            {
                "CONSOLIDE": "",
                "30/06/2024": "-",
                "30/06/2023": ""
            },
            {
                "CONSOLIDE": "",
                "30/06/2024": "-73 959",
                "30/06/2023": ""
            },
            {
                "CONSOLIDE": "",
                "30/06/2024": "30 216",
                "30/06/2023": ""
            },
            {
                "CONSOLIDE": "",
                "30/06/2024": "-18 688",
                "30/06/2023": ""
            },
            {
                "CONSOLIDE": "",
                "30/06/2024": "-18 874",
                "30/06/2023": ""
            },
            {
                "CONSOLIDE": "",
                "30/06/2024": "-105 978",
                "30/06/2023": ""
            },
            {
                "CONSOLIDE": "",
                "30/06/2024": "-",
                "30/06/2023": ""
            },
            {
                "CONSOLIDE": "",
                "30/06/2024": "-",
                "30/06/2023": ""
            },
            {
                "CONSOLIDE": "",
                "30/06/2024": "-14 673",
                "30/06/2023": ""
            },
            {
                "CONSOLIDE": "",
                "30/06/2024": "8 780",
                "30/06/2023": ""
            },
            {
                "CONSOLIDE": "",
                "30/06/2024": "8 780",
                "30/06/2023": ""
            },
            {
                "CONSOLIDE": "",
                "30/06/2024": "-",
                "30/06/2023": ""
            },
            {
                "CONSOLIDE": "",
                "30/06/2024": "-",
                "30/06/2023": ""
            },
            {
                "CONSOLIDE": "",
                "30/06/2024": "-",
                "30/06/2023": ""
            },
            {
                "CONSOLIDE": "",
                "30/06/2024": "-",
                "30/06/2023": ""
            },
            {
                "CONSOLIDE": "",
                "30/06/2024": "-",
                "30/06/2023": ""
            },
            {
                "CONSOLIDE": "Coût du risque de crédit",
                "30/06/2024": "-111 870",
                "30/06/2023": "-166 067"
            }
        ],
        [
            {
                "": "",
                "30/06/2024": "1 504 590",
                "30/06/2023": ""
            },
            {
                "": "",
                "30/06/2024": "126 206",
                "30/06/2023": ""
            },
            {
                "": "",
                "30/06/2024": "-",
                "30/06/2023": ""
            },
            {
                "": "",
                "30/06/2024": "1 330 400",
                "30/06/2023": ""
            },
            {
                "": "",
                "30/06/2024": "47 984",
                "30/06/2023": ""
            },
            {
                "": "",
                "30/06/2024": "-",
                "30/06/2023": ""
            },
            {
                "": "",
                "30/06/2024": "34 371",
                "30/06/2023": ""
            },
            {
                "": "",
                "30/06/2024": "-",
                "30/06/2023": ""
            },
            {
                "": "",
                "30/06/2024": "-",
                "30/06/2023": ""
            },
            {
                "": "",
                "30/06/2024": "34 371",
                "30/06/2023": ""
            },
            {
                "": "",
                "30/06/2024": "-",
                "30/06/2023": ""
            },
            {
                "": "",
                "30/06/2024": "5 069",
                "30/06/2023": ""
            },
            {
                "": "Produits d'intérêts",
                "30/06/2024": "1 544 030",
                "30/06/2023": "1 311 552"
            },
            {
                "": "",
                "30/06/2024": "262 412",
                "30/06/2023": ""
            },
            {
                "": "",
                "30/06/2024": "36 422",
                "30/06/2023": ""
            },
            {
                "": "",
                "30/06/2024": "-",
                "30/06/2023": ""
            },
            {
                "": "",
                "30/06/2024": "225 990",
                "30/06/2023": ""
            },
            {
                "": "",
                "30/06/2024": "-",
                "30/06/2023": ""
            },
            {
                "": "",
                "30/06/2024": "-",
                "30/06/2023": ""
            },
            {
                "": "",
                "30/06/2024": "-",
                "30/06/2023": ""
            },
            {
                "": "",
                "30/06/2024": "-",
                "30/06/2023": ""
            },
            {
                "": "",
                "30/06/2024": "95 146",
                "30/06/2023": ""
            },
            {
                "": "Charges d'intérêts",
                "30/06/2024": "357 557",
                "30/06/2023": "228 765"
            }
        ],
        [
            {
                "LIBELLE": "",
                "30/06/2024": "Produits",
                "null": "Net",
                "30/06/2023": "Produits"
            },
            {
                "LIBELLE": "",
                "30/06/2024": "-",
                "null": "",
                "30/06/2023": ""
            },
            {
                "LIBELLE": "",
                "30/06/2024": "-",
                "null": "",
                "30/06/2023": ""
            },
            {
                "LIBELLE": "",
                "30/06/2024": "32 887",
                "null": "",
                "30/06/2023": ""
            },
            {
                "LIBELLE": "",
                "30/06/2024": "-",
                "null": "",
                "30/06/2023": ""
            },
            {
                "LIBELLE": "",
                "30/06/2024": "4 848",
                "null": "",
                "30/06/2023": ""
            },
            {
                "LIBELLE": "",
                "30/06/2024": "-",
                "null": "",
                "30/06/2023": ""
            },
            {
                "LIBELLE": "",
                "30/06/2024": "215 466",
                "null": "",
                "30/06/2023": ""
            },
            {
                "LIBELLE": "",
                "30/06/2024": "17 587",
                "null": "",
                "30/06/2023": ""
            },
            {
                "LIBELLE": "Produits nets des commissions",
                "30/06/2024": "270 788",
                "null": "225 813",
                "30/06/2023": "247 749"
            }
        ],
        [
            {
                "": "",
                "30/06/2024": "-3 547",
                "30/06/2023": ""
            },
            {
                "": "",
                "30/06/2024": "35",
                "30/06/2023": ""
            },
            {
                "": "",
                "30/06/2024": "-3 582",
                "30/06/2023": ""
            },
            {
                "": "",
                "30/06/2024": "-",
                "30/06/2023": ""
            },
            {
                "": "",
                "30/06/2024": "-",
                "30/06/2023": ""
            },
            {
                "": "",
                "30/06/2024": "-",
                "30/06/2023": ""
            },
            {
                "": "",
                "30/06/2024": "-3 547",
                "30/06/2023": ""
            }
        ],
        [
            {
                "": "",
                "30/06/2024": "81 063",
                "31/12/2023": ""
            },
            {
                "": "",
                "30/06/2024": "-0",
                "31/12/2023": ""
            },
            {
                "": "",
                "30/06/2024": "292 516",
                "31/12/2023": ""
            },
            {
                "": "",
                "30/06/2024": "-",
                "31/12/2023": ""
            },
            {
                "": "",
                "30/06/2024": "-",
                "31/12/2023": ""
            },
            {
                "": "",
                "30/06/2024": "756 876",
                "31/12/2023": ""
            },
            {
                "": "",
                "30/06/2024": "339 779",
                "31/12/2023": ""
            },
            {
                "": "Valeur au bilan",
                "30/06/2024": "1 470 234",
                "31/12/2023": "1 137 272"
            }
        ],
        [
            {
                "": "",
                "30/06/2024": "38 792 116",
                "31/12/2023": ""
            },
            {
                "": "",
                "30/06/2024": "4 457 603",
                "31/12/2023": ""
            },
            {
                "": "",
                "30/06/2024": "10 192 159",
                "31/12/2023": ""
            },
            {
                "": "",
                "30/06/2024": "1 336 300",
                "31/12/2023": ""
            },
            {
                "": "Valeur au bilan",
                "30/06/2024": "54 778 179",
                "31/12/2023": "51 755 426"
            }
        ],
        [
            {
                "": "",
                "30/06/2024": "393",
                "30/06/2023": ""
            },
            {
                "": "",
                "30/06/2024": "63 683",
                "30/06/2023": ""
            },
            {
                "": "",
                "30/06/2024": "6 656",
                "30/06/2023": ""
            },
            {
                "": "",
                "30/06/2024": "-",
                "30/06/2023": ""
            },
            {
                "": "",
                "30/06/2024": "-",
                "30/06/2023": ""
            },
            {
                "": "",
                "30/06/2024": "-",
                "30/06/2023": ""
            },
            {
                "": "",
                "30/06/2024": "148 152",
                "30/06/2023": ""
            },
            {
                "": "",
                "30/06/2024": "-",
                "30/06/2023": ""
            },
            {
                "": "Gains ou pertes nets sur instruments financiers à la juste valeur\npar résultat",
                "30/06/2024": "218 885",
                "30/06/2023": "168 156"
            }
        ],
        [
            {
                "": "",
                "30/06/2024": "-",
                "31/12/2023": ""
            },
            {
                "": "",
                "30/06/2024": "3 501 597",
                "31/12/2023": ""
            },
            {
                "": "",
                "30/06/2024": "-",
                "31/12/2023": ""
            },
            {
                "": "",
                "30/06/2024": "-",
                "31/12/2023": ""
            },
            {
                "": "",
                "30/06/2024": "-",
                "31/12/2023": ""
            },
            {
                "": "Valeur au bilan",
                "30/06/2024": "3 501 597",
                "31/12/2023": "3 424 402"
            }
        ],
        [
            {
                "": "",
                "30/06/2024": "5 099 485",
                "31/12/2023": ""
            },
            {
                "": "",
                "30/06/2024": "54 911 005",
                "31/12/2023": ""
            },
            {
                "": "",
                "30/06/2024": "909 118",
                "31/12/2023": ""
            },
            {
                "": "Valeur au bilan",
                "30/06/2024": "60 919 608",
                "31/12/2023": "58 471 308"
            }
        ],
        [
            {
                "": "",
                "30/06/2024": "-",
                "30/06/2023": ""
            },
            {
                "": "",
                "30/06/2024": "-",
                "30/06/2023": ""
            },
            {
                "": "",
                "30/06/2024": "-",
                "30/06/2023": ""
            },
            {
                "": "Gains ou pertes nets sur instruments financiers à la juste valeur\npar capitaux propres",
                "30/06/2024": "-",
                "30/06/2023": "-"
            }
        ],
        [
            {
                "": "",
                "30/06/2024": "",
                "31/12/2023": "-"
            },
            {
                "": "",
                "30/06/2024": "909 118",
                "31/12/2023": "1 397 240"
            },
            {
                "": "Total",
                "30/06/2024": "909 118",
                "31/12/2023": "1 397 240"
            },
            {
                "": "",
                "30/06/2024": "-",
                "31/12/2023": "-"
            },
            {
                "": "Valeur au bilan",
                "30/06/2024": "909 118",
                "31/12/2023": "1 397 240"
            }
        ],
        [
            {
                "": "",
                "30/06/2024": "",
                "31/12/2023": ""
            },
            {
                "": "",
                "30/06/2024": "3 513 483",
                "31/12/2023": ""
            },
            {
                "": "",
                "30/06/2024": "3 513 483",
                "31/12/2023": ""
            },
            {
                "": "",
                "30/06/2024": "-",
                "31/12/2023": ""
            },
            {
                "": "",
                "30/06/2024": "1 010 448",
                "31/12/2023": ""
            },
            {
                "": "",
                "30/06/2024": "-",
                "31/12/2023": ""
            },
            {
                "": "",
                "30/06/2024": "-",
                "31/12/2023": ""
            },
            {
                "": "",
                "30/06/2024": "579 391",
                "31/12/2023": ""
            },
            {
                "": "",
                "30/06/2024": "5 103 322",
                "31/12/2023": ""
            },
            {
                "": "",
                "30/06/2024": "-3 837",
                "31/12/2023": ""
            },
            {
                "": "",
                "30/06/2024": "5 099 485",
                "31/12/2023": ""
            },
            {
                "": "",
                "30/06/2024": "-",
                "31/12/2023": ""
            },
            {
                "": "",
                "30/06/2024": "-",
                "31/12/2023": ""
            },
            {
                "": "",
                "30/06/2024": "-",
                "31/12/2023": ""
            },
            {
                "": "",
                "30/06/2024": "-",
                "31/12/2023": ""
            },
            {
                "": "",
                "30/06/2024": "-",
                "31/12/2023": ""
            },
            {
                "": "Valeur au bilan",
                "30/06/2024": "5 099 485",
                "31/12/2023": "6 012 399"
            }
        ],
        [
            {
                "": "",
                "30/06/2024": "",
                "31/12/2023": ""
            },
            {
                "": "",
                "30/06/2024": "13 699 276",
                "31/12/2023": "12 320 104"
            },
            {
                "": "",
                "30/06/2024": "39 227 854",
                "31/12/2023": "37 016 848"
            },
            {
                "": "",
                "30/06/2024": "756 409",
                "31/12/2023": "1 087 882"
            },
            {
                "": "",
                "30/06/2024": "-",
                "31/12/2023": "-"
            },
            {
                "": "",
                "30/06/2024": "-",
                "31/12/2023": "-"
            },
            {
                "": "",
                "30/06/2024": "-",
                "31/12/2023": "-"
            },
            {
                "": "",
                "30/06/2024": "-",
                "31/12/2023": "-"
            },
            {
                "": "",
                "30/06/2024": "-",
                "31/12/2023": "-"
            },
            {
                "": "",
                "30/06/2024": "3 036 694",
                "31/12/2023": "2 733 370"
            },
            {
                "": "",
                "30/06/2024": "56 720 233",
                "31/12/2023": "53 214 603"
            },
            {
                "": "",
                "30/06/2024": "-3 716 834",
                "31/12/2023": "-3 627 722"
            },
            {
                "": "",
                "30/06/2024": "53 003 400",
                "31/12/2023": "49 586 881"
            },
            {
                "": "",
                "30/06/2024": "-",
                "31/12/2023": "-"
            },
            {
                "": "",
                "30/06/2024": "617 059",
                "31/12/2023": "494 767"
            },
            {
                "": "",
                "30/06/2024": "1 435 087",
                "31/12/2023": "1 185 098"
            },
            {
                "": "",
                "30/06/2024": "2 052 147",
                "31/12/2023": "1 679 865"
            },
            {
                "": "",
                "30/06/2024": "-144 542",
                "31/12/2023": "-148 678"
            },
            {
                "": "",
                "30/06/2024": "1 907 605",
                "31/12/2023": "1 531 187"
            },
            {
                "": "Valeur au bilan",
                "30/06/2024": "54 911 005",
                "31/12/2023": "51 061 669"
            }
        ],
        [
            {
                "30/06/2024": "",
                "Créances et engagements": "Bucket 1",
                "null": "Bucket 3",
                "Dépréciations": "Bucket 1"
            },
            {
                "30/06/2024": "",
                "Créances et engagements": "1 609 788",
                "null": "-",
                "Dépréciations": "978"
            },
            {
                "30/06/2024": "",
                "Créances et engagements": "-",
                "null": "-",
                "Dépréciations": "-"
            },
            {
                "30/06/2024": "",
                "Créances et engagements": "-",
                "null": "-",
                "Dépréciations": "-"
            },
            {
                "30/06/2024": "",
                "Créances et engagements": "1 609 788",
                "null": "-",
                "Dépréciations": "978"
            },
            {
                "30/06/2024": "",
                "Créances et engagements": "55 081 143",
                "null": "3 257 528",
                "Dépréciations": "177 904"
            },
            {
                "30/06/2024": "",
                "Créances et engagements": "4 878 289",
                "null": "-",
                "Dépréciations": "3 836"
            },
            {
                "30/06/2024": "",
                "Créances et engagements": "49 293 736",
                "null": "3 257 528",
                "Dépréciations": "174 068"
            },
            {
                "30/06/2024": "",
                "Créances et engagements": "909 118",
                "null": "-",
                "Dépréciations": "-"
            },
            {
                "30/06/2024": "Actifs financiers",
                "Créances et engagements": "56 690 932",
                "null": "3 257 528",
                "Dépréciations": "178 883"
            },
            {
                "30/06/2024": "Engagements Hors bilan",
                "Créances et engagements": "4 559 122",
                "null": "155 776",
                "Dépréciations": "15 268"
            }
        ],
        [
            {
                "31/12/2023": "",
                "Créances et engagements": "Bucket 1",
                "null": "Bucket 3",
                "Dépréciations": "Bucket 1"
            },
            {
                "31/12/2023": "",
                "Créances et engagements": "",
                "null": "",
                "Dépréciations": ""
            },
            {
                "31/12/2023": "",
                "Créances et engagements": "",
                "null": "",
                "Dépréciations": ""
            },
            {
                "31/12/2023": "",
                "Créances et engagements": "",
                "null": "",
                "Dépréciations": ""
            },
            {
                "31/12/2023": "",
                "Créances et engagements": "",
                "null": "",
                "Dépréciations": ""
            },
            {
                "31/12/2023": "",
                "Créances et engagements": "",
                "null": "",
                "Dépréciations": ""
            },
            {
                "31/12/2023": "",
                "Créances et engagements": "",
                "null": "",
                "Dépréciations": ""
            },
            {
                "31/12/2023": "",
                "Créances et engagements": "",
                "null": "",
                "Dépréciations": ""
            },
            {
                "31/12/2023": "",
                "Créances et engagements": "",
                "null": "",
                "Dépréciations": ""
            },
            {
                "31/12/2023": "Actifs financiers",
                "Créances et engagements": "53 362 459",
                "null": "3 188 682",
                "Dépréciations": "175 988"
            },
            {
                "31/12/2023": "Engagements Hors bilan",
                "Créances et engagements": "4 073 638",
                "null": "185 992",
                "Dépréciations": "14 653"
            }
        ],
        [
            {
                "": "",
                "30/06/2024": "Valeur au bilan",
                "null": "Pertes latentes",
                "31/12/2023": "Valeur au bilan"
            },
            {
                "": "",
                "30/06/2024": "1 608 810",
                "null": "",
                "31/12/2023": "1 054 279"
            },
            {
                "": "",
                "30/06/2024": "-",
                "null": "",
                "31/12/2023": "-"
            },
            {
                "": "Total",
                "30/06/2024": "1 608 810",
                "null": "-",
                "31/12/2023": "1 054 279"
            }
        ],
        [
            {
                "30/06/2024": "",
                "Valeur au\nbilan": "1 606 043",
                "Gains\nlatents": "1 938",
                "Pertes\nlatentes": "-"
            },
            {
                "30/06/2024": "",
                "Valeur au\nbilan": "2 767",
                "Gains\nlatents": "-",
                "Pertes\nlatentes": "-"
            },
            {
                "30/06/2024": "Total des titres de dettes",
                "Valeur au\nbilan": "1 608 810",
                "Gains\nlatents": "1 938",
                "Pertes\nlatentes": "-"
            },
            {
                "30/06/2024": "",
                "Valeur au\nbilan": "-",
                "Gains\nlatents": "-",
                "Pertes\nlatentes": "-"
            },
            {
                "30/06/2024": "",
                "Valeur au\nbilan": "-",
                "Gains\nlatents": "-",
                "Pertes\nlatentes": "-"
            },
            {
                "30/06/2024": "Total des prêts et créances",
                "Valeur au\nbilan": "-",
                "Gains\nlatents": "-",
                "Pertes\nlatentes": "-"
            },
            {
                "30/06/2024": "",
                "Valeur au\nbilan": "1 608 810",
                "Gains\nlatents": "1 938",
                "Pertes\nlatentes": "-"
            },
            {
                "30/06/2024": "",
                "Valeur au\nbilan": "",
                "Gains\nlatents": "-761",
                "Pertes\nlatentes": "-"
            },
            {
                "30/06/2024": "",
                "Valeur au\nbilan": "",
                "Gains\nlatents": "1 178",
                "Pertes\nlatentes": "-"
            }
        ],
        [
            {
                "": "",
                "30/06/2024": "2 872",
                "31/12/2023": "2 955"
            },
            {
                "": "",
                "30/06/2024": "24 082",
                "31/12/2023": "-"
            },
            {
                "": "",
                "30/06/2024": "-",
                "31/12/2023": "-"
            },
            {
                "": "",
                "30/06/2024": "-",
                "31/12/2023": "-"
            },
            {
                "": "",
                "30/06/2024": "85 386",
                "31/12/2023": "16 185"
            },
            {
                "": "",
                "30/06/2024": "385 507",
                "31/12/2023": "403 139"
            },
            {
                "": "TOTAL DES COMPTES DE REGULARISATION ET ACTIFS DIVERS",
                "30/06/2024": "497 847",
                "31/12/2023": "422 280"
            },
            {
                "": "",
                "30/06/2024": "-",
                "31/12/2023": "-"
            },
            {
                "": "",
                "30/06/2024": "5 619",
                "31/12/2023": "79 856"
            },
            {
                "": "",
                "30/06/2024": "-",
                "31/12/2023": "-"
            },
            {
                "": "",
                "30/06/2024": "347 895",
                "31/12/2023": "367 800"
            },
            {
                "": "",
                "30/06/2024": "1 939 306",
                "31/12/2023": "1 443 901"
            },
            {
                "": "TOTAL DES COMPTES DE REGULARISATION ET PASSIFS DIVERS",
                "30/06/2024": "2 292 820",
                "31/12/2023": "1 891 556"
            }
        ],
        [
            {
                "31/12/2023": "",
                "Valeur au\nbilan": "1 063 414",
                "Gains\nlatents": "548",
                "Pertes\nlatentes": "-"
            },
            {
                "31/12/2023": "",
                "Valeur au\nbilan": "-9 135",
                "Gains\nlatents": "-",
                "Pertes\nlatentes": "-"
            },
            {
                "31/12/2023": "Total des titres de dettes",
                "Valeur au\nbilan": "1 054 279",
                "Gains\nlatents": "548",
                "Pertes\nlatentes": "-"
            },
            {
                "31/12/2023": "",
                "Valeur au\nbilan": "-",
                "Gains\nlatents": "-",
                "Pertes\nlatentes": "-"
            },
            {
                "31/12/2023": "",
                "Valeur au\nbilan": "-",
                "Gains\nlatents": "-",
                "Pertes\nlatentes": "-"
            },
            {
                "31/12/2023": "Total des prêts et créances",
                "Valeur au\nbilan": "-",
                "Gains\nlatents": "-",
                "Pertes\nlatentes": "-"
            },
            {
                "31/12/2023": "",
                "Valeur au\nbilan": "1 054 279",
                "Gains\nlatents": "548",
                "Pertes\nlatentes": "-"
            },
            {
                "31/12/2023": "",
                "Valeur au\nbilan": "",
                "Gains\nlatents": "-211",
                "Pertes\nlatentes": "-"
            },
            {
                "31/12/2023": "",
                "Valeur au\nbilan": "",
                "Gains\nlatents": "337",
                "Pertes\nlatentes": "-"
            }
        ],
        [
            {
                "": "",
                "30/06/2024": "188 257",
                "31/12/2023": "195 774"
            },
            {
                "": "",
                "30/06/2024": "34 334",
                "31/12/2023": "34 335"
            },
            {
                "": "Total Instruments de capitaux propres à la juste valeur par résultat",
                "30/06/2024": "222 592",
                "31/12/2023": "230 109"
            }
        ],
        [
            {
                "": "",
                "31/12/2023": "",
                "Augmentations\n(acquisitions)": "",
                "Diminutions\n(cessions)": "",
                "30/06/2024": ""
            },
            {
                "": "",
                "31/12/2023": "105 212",
                "Augmentations\n(acquisitions)": "251 -",
                "Diminutions\n(cessions)": "",
                "30/06/2024": "105 463"
            },
            {
                "": "",
                "31/12/2023": "-54 101",
                "Augmentations\n(acquisitions)": "4 395 -5 995",
                "Diminutions\n(cessions)": "",
                "30/06/2024": "-55 701"
            },
            {
                "": "Total Immobilier",
                "31/12/2023": "51 111",
                "Augmentations\n(acquisitions)": "4 647",
                "Diminutions\n(cessions)": "-5 995",
                "30/06/2024": "49 762"
            },
            {
                "": "",
                "31/12/2023": "",
                "Augmentations\n(acquisitions)": "",
                "Diminutions\n(cessions)": "",
                "30/06/2024": ""
            },
            {
                "": "",
                "31/12/2023": "17 095",
                "Augmentations\n(acquisitions)": "1 509 -",
                "Diminutions\n(cessions)": "",
                "30/06/2024": "18 604"
            },
            {
                "": "",
                "31/12/2023": "-9 334",
                "Augmentations\n(acquisitions)": "-1 771",
                "Diminutions\n(cessions)": "",
                "30/06/2024": "-11 105"
            },
            {
                "": "Total Mobilier",
                "31/12/2023": "7 761",
                "Augmentations\n(acquisitions)": "1 509",
                "Diminutions\n(cessions)": "-1 771",
                "30/06/2024": "7 499"
            },
            {
                "": "",
                "31/12/2023": "",
                "Augmentations\n(acquisitions)": "",
                "Diminutions\n(cessions)": "",
                "30/06/2024": ""
            },
            {
                "": "Total Droits d'utilisation",
                "31/12/2023": "58 872",
                "Augmentations\n(acquisitions)": "6 156",
                "Diminutions\n(cessions)": "-7 766",
                "30/06/2024": "57 261"
            }
        ],
        [
            {
                "": "",
                "30/06/2024": "-",
                "31/12/2023": "-"
            },
            {
                "": "",
                "30/06/2024": "-",
                "31/12/2023": "-"
            },
            {
                "": "",
                "30/06/2024": "3 474 711",
                "31/12/2023": "2 339 859"
            },
            {
                "": "",
                "30/06/2024": "2 535 773",
                "31/12/2023": "2 014 378"
            },
            {
                "": "",
                "30/06/2024": "938 938",
                "31/12/2023": "325 480"
            },
            {
                "": "",
                "30/06/2024": "-",
                "31/12/2023": "-"
            },
            {
                "": "",
                "30/06/2024": "-",
                "31/12/2023": "-"
            },
            {
                "": "",
                "30/06/2024": "-",
                "31/12/2023": "-"
            },
            {
                "": "",
                "30/06/2024": "-",
                "31/12/2023": "-"
            },
            {
                "": "",
                "30/06/2024": "-",
                "31/12/2023": "-"
            },
            {
                "": "",
                "30/06/2024": "-",
                "31/12/2023": "-"
            },
            {
                "": "",
                "30/06/2024": "17 133",
                "31/12/2023": "26 942"
            },
            {
                "": "Valeur au bilan",
                "30/06/2024": "3 491 844",
                "31/12/2023": "2 366 801"
            }
        ],
        [
            {
                "": "",
                "30/06/2024": "1 491 718",
                "31/12/2023": "1 495 747"
            },
            {
                "": "",
                "30/06/2024": "57 261",
                "31/12/2023": "58 872"
            }
        ],
        [
            {
                "": "",
                "30/06/2024": "2 337 031",
                "31/12/2023": "1 891 556"
            },
            {
                "": "",
                "30/06/2024": "60 485",
                "31/12/2023": "62 303"
            }
        ],
        [
            {
                "": "",
                "30/06/2024": "3 491 844",
                "31/12/2023": "2 366 801"
            },
            {
                "": "",
                "30/06/2024": "222 592",
                "31/12/2023": "230 109"
            },
            {
                "": "",
                "30/06/2024": "222 592",
                "31/12/2023": "230 109"
            },
            {
                "": "",
                "30/06/2024": "-",
                "31/12/2023": "-"
            },
            {
                "": "",
                "30/06/2024": "-",
                "31/12/2023": "-"
            },
            {
                "": "",
                "30/06/2024": "-",
                "31/12/2023": "-"
            },
            {
                "": "Valeur au bilan",
                "30/06/2024": "3 714 436",
                "31/12/2023": "2 596 910"
            },
            {
                "": "",
                "30/06/2024": "-",
                "31/12/2023": "-"
            }
        ],
        [
            {
                "": "",
                "30/06/2024": "-357 557",
                "31/12/2023": "-595 229"
            },
            {
                "": "",
                "30/06/2024": "-950",
                "31/12/2023": "-1 000"
            },
            {
                "": "",
                "30/06/2024": "-649 974",
                "31/12/2023": "-1 365 976"
            },
            {
                "": "",
                "30/06/2024": "8 374",
                "31/12/2023": "-6 097"
            },
            {
                "": "",
                "30/06/2024": "-132 295",
                "31/12/2023": "-232 914"
            },
            {
                "": "",
                "30/06/2024": "-7 766",
                "31/12/2023": "-18 432"
            }
        ],
        [
            {
                "30/06/2024": "Valeur comptable totale\n(de toutes les immo incorporelles)",
                "null": "Valeur comptable totale\n(de toutes les immo corporelles)",
                "31/12/2023": "Valeur comptable totale\n(de toutes les immo incorporelles)"
            },
            {
                "30/06/2024": "-",
                "null": "",
                "31/12/2023": ""
            },
            {
                "30/06/2024": "-",
                "null": "",
                "31/12/2023": ""
            },
            {
                "30/06/2024": "1 512 368",
                "null": "",
                "31/12/2023": ""
            },
            {
                "30/06/2024": "-",
                "null": "",
                "31/12/2023": ""
            },
            {
                "30/06/2024": "687 415",
                "null": "",
                "31/12/2023": ""
            },
            {
                "30/06/2024": "-",
                "null": "",
                "31/12/2023": ""
            },
            {
                "30/06/2024": "-",
                "null": "",
                "31/12/2023": ""
            }
        ],
        [
            {
                "": "Solde de clôture au 31.12.2023",
                "Risques légaux et\nfiscaux": "95 843",
                "Obligations au titre des\navantages postérieurs à l'emploi": "91 437",
                "Engagements de prêts\net garanties (Les EPS)": "232 756",
                "Contrats déficitaires": "-",
                "Autres provisions": "145 919",
                "Valeur comptable totale": "565 955"
            }
        ],
        [],
        [
            {
                "Impôts courants et impôts différés": "",
                "30/06/2024": "4 807",
                "31/12/2023": "3 253"
            },
            {
                "Impôts courants et impôts différés": "",
                "30/06/2024": "135 551",
                "31/12/2023": "159 789"
            },
            {
                "Impôts courants et impôts différés": "Actifs d’impôts courants et différés",
                "30/06/2024": "140 358",
                "31/12/2023": "163 043"
            },
            {
                "Impôts courants et impôts différés": "",
                "30/06/2024": "100 429",
                "31/12/2023": "125 097"
            },
            {
                "Impôts courants et impôts différés": "",
                "30/06/2024": "14 664",
                "31/12/2023": "17 885"
            },
            {
                "Impôts courants et impôts différés": "Passifs d’impôts courants et différés",
                "30/06/2024": "115 092",
                "31/12/2023": "142 982"
            },
            {
                "Impôts courants et impôts différés": "",
                "30/06/2024": "297 557",
                "31/12/2023": "396 449"
            },
            {
                "Impôts courants et impôts différés": "",
                "30/06/2024": "19 902",
                "31/12/2023": "-16 367"
            },
            {
                "Impôts courants et impôts différés": "Charges nette de l’impôt sur les bénéfices",
                "30/06/2024": "317 458",
                "31/12/2023": "380 083"
            }
        ],
        [
            {
                "": "",
                "30/06/2024": "6 901",
                "31/12/2023": "15 984"
            },
            {
                "": "",
                "30/06/2024": "-",
                "31/12/2023": "-"
            },
            {
                "": "Valeur au bilan",
                "30/06/2024": "6 901",
                "31/12/2023": "15 984"
            }
        ],
        [
            {
                "Le taux effectif d'impôt": "",
                "30/06/2024": "390 835",
                "31/12/2023": "498 225"
            },
            {
                "Le taux effectif d'impôt": "",
                "30/06/2024": "317 458",
                "31/12/2023": "380 083"
            },
            {
                "Le taux effectif d'impôt": "Taux d'impôt effectif moyen en %",
                "30/06/2024": "44,82%",
                "31/12/2023": "43,27%"
            }
        ],
        [
            {
                "": "",
                "30/06/2024": "",
                "31/12/2023": ""
            },
            {
                "": "",
                "30/06/2024": "",
                "31/12/2023": ""
            },
            {
                "": "",
                "30/06/2024": "",
                "31/12/2023": ""
            },
            {
                "": "",
                "30/06/2024": "",
                "31/12/2023": ""
            },
            {
                "": "",
                "30/06/2024": "",
                "31/12/2023": ""
            },
            {
                "": "",
                "30/06/2024": "6 901",
                "31/12/2023": "15 984"
            },
            {
                "": "Valeur au bilan",
                "30/06/2024": "6 901",
                "31/12/2023": "15 984"
            }
        ],
        [
            {
                "Analyse du taux effectif d'impôt": "",
                "30/06/2024": "39,25%",
                "31/12/2023": "38,50%"
            },
            {
                "Analyse du taux effectif d'impôt": "",
                "30/06/2024": "-",
                "31/12/2023": "-"
            },
            {
                "Analyse du taux effectif d'impôt": "",
                "30/06/2024": "-",
                "31/12/2023": "-"
            },
            {
                "Analyse du taux effectif d'impôt": "",
                "30/06/2024": "-",
                "31/12/2023": "-"
            },
            {
                "Analyse du taux effectif d'impôt": "",
                "30/06/2024": "-",
                "31/12/2023": "-"
            },
            {
                "Analyse du taux effectif d'impôt": "",
                "30/06/2024": "-",
                "31/12/2023": "-"
            },
            {
                "Analyse du taux effectif d'impôt": "",
                "30/06/2024": "5,57%",
                "31/12/2023": "4,77%"
            },
            {
                "Analyse du taux effectif d'impôt": "Taux d'impôt effectif moyen",
                "30/06/2024": "44,82%",
                "31/12/2023": "43,27%"
            }
        ],
        [
            {
                "": "",
                "Actifs sains": "Actifs soumis à une ECL 12 mois\n(Bucket 1)",
                "null": "",
                "Actifs dépréciés (Bucket 3)": "",
                "Total": ""
            },
            {
                "": "",
                "Actifs sains": "Valeur comp-\ntable brute",
                "null": "Valeur nette\ncomptable (a)+(b)",
                "Actifs dépréciés (Bucket 3)": "Valeur\ncomptable brute",
                "Total": "Valeur comp-\ntable brute (a)"
            },
            {
                "": "Au 31 décembre 2023",
                "Actifs sains": "45 117 861",
                "null": "51 061 669",
                "Actifs dépréciés (Bucket 3)": "4 294 996",
                "Total": "54 838 069"
            }
        ],
        [],
        [],
        [],
        [
            {
                "Durée résiduelle": "",
                "Pour le Bailleur": "Investissement brut total",
                "null": "Correction de valeur cumulée des paiements minimaux\nau titre de la location non recouvrables"
            }
        ],
        [],
        [],
        [],
        [],
        [
            {
                "Charges et produits générés par des\ntransactions entre parties liées": "Total des charges dont :",
                "Société-mère": "",
                "Filiales": "",
                "Principaux dirigeants de l'entité\nou de sa société-mère": "",
                "Entités contrôlées par la\nmême société mère": "",
                "Autres parties liées": "",
                "Total": ""
            }
        ],
        [],
        [
            {
                "": "",
                "30/06/2024": "≤ 3 mois",
                "null": "Total"
            }
        ],
        [],
        [],
        [
            {
                "": "",
                "31/12/2023": "≤ 3 mois",
                "null": "Total"
            }
        ],
        [],
        [],
        [
            {
                "": "Engagements de prêt",
                "Montants": "8 111 187"
            }
        ],
        [],
        [],
        [],
        [
            {
                "Bilan Juin 2024": "Total Bilan",
                "Banque Maroc et\ninternationale": "71 682 143",
                "Sociétés de\nfinancement\nspécialisés": "2 218 116",
                "Eliminations": "-2 854 358",
                "Total": "71 045 901"
            }
        ],
        [],
        [],
        [],
        [
            {
                "Actionnaires": "A - ACTIONNAIRES MAROCAINS",
                "Nombred’actions": "",
                "% du capital": "",
                "% des droits de vote": ""
            }
        ],
        [],
        [],
        [
            {
                "": "",
                "30/06/2024": "Actif",
                "null": "Passif",
                "31/12/2023": "Actif"
            },
            {
                "": "",
                "30/06/2024": "1 338 318",
                "null": "1 185 155",
                "31/12/2023": "1 185 155"
            },
            {
                "": "",
                "30/06/2024": "1 086 751",
                "null": "899 196",
                "31/12/2023": "899 196"
            },
            {
                "": "",
                "30/06/2024": "14 846",
                "null": "13 361",
                "31/12/2023": "13 361"
            },
            {
                "": "",
                "30/06/2024": "185",
                "null": "20",
                "31/12/2023": "20"
            },
            {
                "": "",
                "30/06/2024": "13 055",
                "null": "22 395",
                "31/12/2023": "22 395"
            },
            {
                "": "TOTAL",
                "30/06/2024": "2 453 155",
                "null": "2 120 127",
                "31/12/2023": "2 120 127"
            }
        ],
        [
            {
                "": "",
                "2023": "",
                "2022": "",
                "2021": ""
            },
            {
                "": "",
                "2023": "34,20",
                "2022": "",
                "2021": ""
            },
            {
                "": "",
                "2023": "",
                "2022": "",
                "2021": ""
            },
            {
                "": "",
                "2023": "46,23",
                "2022": "",
                "2021": ""
            }
        ],
        [
            {
                "": "",
                "30/06/2024": "",
                "Prix cotés sur\ndes marchés\nactifs pour des\ninstruments\nidentiques": "Niveau 1",
                "Valorisation\nfondée sur\ndes données\nobservables": "Niveau 2",
                "Valorisation\nfondée sur des\ndonnées non\nobservables": "Niveau 3"
            },
            {
                "": "Actifs financiers détenus à des fins de\ntransaction",
                "30/06/2024": "3 491 844",
                "Prix cotés sur\ndes marchés\nactifs pour des\ninstruments\nidentiques": "-",
                "Valorisation\nfondée sur\ndes données\nobservables": "3 491 844",
                "Valorisation\nfondée sur des\ndonnées non\nobservables": "-"
            },
            {
                "": "",
                "30/06/2024": "-",
                "Prix cotés sur\ndes marchés\nactifs pour des\ninstruments\nidentiques": "",
                "Valorisation\nfondée sur\ndes données\nobservables": "",
                "Valorisation\nfondée sur des\ndonnées non\nobservables": ""
            },
            {
                "": "",
                "30/06/2024": "-",
                "Prix cotés sur\ndes marchés\nactifs pour des\ninstruments\nidentiques": "",
                "Valorisation\nfondée sur\ndes données\nobservables": "",
                "Valorisation\nfondée sur des\ndonnées non\nobservables": ""
            },
            {
                "": "",
                "30/06/2024": "-",
                "Prix cotés sur\ndes marchés\nactifs pour des\ninstruments\nidentiques": "",
                "Valorisation\nfondée sur\ndes données\nobservables": "",
                "Valorisation\nfondée sur des\ndonnées non\nobservables": ""
            },
            {
                "": "",
                "30/06/2024": "-",
                "Prix cotés sur\ndes marchés\nactifs pour des\ninstruments\nidentiques": "",
                "Valorisation\nfondée sur\ndes données\nobservables": "",
                "Valorisation\nfondée sur des\ndonnées non\nobservables": ""
            },
            {
                "": "",
                "30/06/2024": "3 475 529",
                "Prix cotés sur\ndes marchés\nactifs pour des\ninstruments\nidentiques": "-",
                "Valorisation\nfondée sur\ndes données\nobservables": "3 475 529",
                "Valorisation\nfondée sur des\ndonnées non\nobservables": ""
            },
            {
                "": "",
                "30/06/2024": "2 536 591",
                "Prix cotés sur\ndes marchés\nactifs pour des\ninstruments\nidentiques": "",
                "Valorisation\nfondée sur\ndes données\nobservables": "2 536 591",
                "Valorisation\nfondée sur des\ndonnées non\nobservables": ""
            },
            {
                "": "",
                "30/06/2024": "938 938",
                "Prix cotés sur\ndes marchés\nactifs pour des\ninstruments\nidentiques": "",
                "Valorisation\nfondée sur\ndes données\nobservables": "938 938",
                "Valorisation\nfondée sur des\ndonnées non\nobservables": ""
            },
            {
                "": "",
                "30/06/2024": "-",
                "Prix cotés sur\ndes marchés\nactifs pour des\ninstruments\nidentiques": "",
                "Valorisation\nfondée sur\ndes données\nobservables": "-",
                "Valorisation\nfondée sur des\ndonnées non\nobservables": ""
            },
            {
                "": "",
                "30/06/2024": "-",
                "Prix cotés sur\ndes marchés\nactifs pour des\ninstruments\nidentiques": "",
                "Valorisation\nfondée sur\ndes données\nobservables": "-",
                "Valorisation\nfondée sur des\ndonnées non\nobservables": ""
            },
            {
                "": "",
                "30/06/2024": "16 315",
                "Prix cotés sur\ndes marchés\nactifs pour des\ninstruments\nidentiques": "-",
                "Valorisation\nfondée sur\ndes données\nobservables": "16 315",
                "Valorisation\nfondée sur des\ndonnées non\nobservables": ""
            },
            {
                "": "Autres actifs financiers à la juste\nvaleur par résultat",
                "30/06/2024": "222 592",
                "Prix cotés sur\ndes marchés\nactifs pour des\ninstruments\nidentiques": "-",
                "Valorisation\nfondée sur\ndes données\nobservables": "-",
                "Valorisation\nfondée sur des\ndonnées non\nobservables": "222 592"
            }
        ],
        [
            {
                "": "",
                "31/12/2023": "",
                "Prix cotés sur\ndes marchés\nactifs pour des\ninstruments\nidentiques": "Niveau 1",
                "Valorisation\nfondée sur\ndes données\nobservables": "Niveau 2",
                "Valorisation\nfondée sur des\ndonnées non\nobservables": "Niveau 3"
            },
            {
                "": "Actifs financiers détenus à des fins\nde transaction",
                "31/12/2023": "2 366 801",
                "Prix cotés sur\ndes marchés\nactifs pour des\ninstruments\nidentiques": "-",
                "Valorisation\nfondée sur\ndes données\nobservables": "2 366 801",
                "Valorisation\nfondée sur des\ndonnées non\nobservables": "-"
            },
            {
                "": "",
                "31/12/2023": "-",
                "Prix cotés sur\ndes marchés\nactifs pour des\ninstruments\nidentiques": "",
                "Valorisation\nfondée sur\ndes données\nobservables": "",
                "Valorisation\nfondée sur des\ndonnées non\nobservables": ""
            },
            {
                "": "",
                "31/12/2023": "-",
                "Prix cotés sur\ndes marchés\nactifs pour des\ninstruments\nidentiques": "",
                "Valorisation\nfondée sur\ndes données\nobservables": "",
                "Valorisation\nfondée sur des\ndonnées non\nobservables": ""
            },
            {
                "": "",
                "31/12/2023": "-",
                "Prix cotés sur\ndes marchés\nactifs pour des\ninstruments\nidentiques": "",
                "Valorisation\nfondée sur\ndes données\nobservables": "",
                "Valorisation\nfondée sur des\ndonnées non\nobservables": ""
            },
            {
                "": "",
                "31/12/2023": "-",
                "Prix cotés sur\ndes marchés\nactifs pour des\ninstruments\nidentiques": "",
                "Valorisation\nfondée sur\ndes données\nobservables": "",
                "Valorisation\nfondée sur des\ndonnées non\nobservables": ""
            },
            {
                "": "",
                "31/12/2023": "2 340 677",
                "Prix cotés sur\ndes marchés\nactifs pour des\ninstruments\nidentiques": "-",
                "Valorisation\nfondée sur\ndes données\nobservables": "2 340 677",
                "Valorisation\nfondée sur des\ndonnées non\nobservables": ""
            },
            {
                "": "",
                "31/12/2023": "2 014 378",
                "Prix cotés sur\ndes marchés\nactifs pour des\ninstruments\nidentiques": "",
                "Valorisation\nfondée sur\ndes données\nobservables": "2 014 378",
                "Valorisation\nfondée sur des\ndonnées non\nobservables": ""
            },
            {
                "": "",
                "31/12/2023": "326 298",
                "Prix cotés sur\ndes marchés\nactifs pour des\ninstruments\nidentiques": "",
                "Valorisation\nfondée sur\ndes données\nobservables": "326 298",
                "Valorisation\nfondée sur des\ndonnées non\nobservables": ""
            },
            {
                "": "",
                "31/12/2023": "-",
                "Prix cotés sur\ndes marchés\nactifs pour des\ninstruments\nidentiques": "",
                "Valorisation\nfondée sur\ndes données\nobservables": "-",
                "Valorisation\nfondée sur des\ndonnées non\nobservables": ""
            },
            {
                "": "",
                "31/12/2023": "-",
                "Prix cotés sur\ndes marchés\nactifs pour des\ninstruments\nidentiques": "",
                "Valorisation\nfondée sur\ndes données\nobservables": "-",
                "Valorisation\nfondée sur des\ndonnées non\nobservables": ""
            },
            {
                "": "",
                "31/12/2023": "26 124",
                "Prix cotés sur\ndes marchés\nactifs pour des\ninstruments\nidentiques": "-",
                "Valorisation\nfondée sur\ndes données\nobservables": "26 124",
                "Valorisation\nfondée sur des\ndonnées non\nobservables": ""
            },
            {
                "": "Autres actifs financiers à la juste\nvaleur par résultat",
                "31/12/2023": "230 109",
                "Prix cotés sur\ndes marchés\nactifs pour des\ninstruments\nidentiques": "-",
                "Valorisation\nfondée sur\ndes données\nobservables": "-",
                "Valorisation\nfondée sur des\ndonnées non\nobservables": "230 109"
            },
            {
                "": "",
                "31/12/2023": "38 728",
                "Prix cotés sur\ndes marchés\nactifs pour des\ninstruments\nidentiques": "-",
                "Valorisation\nfondée sur\ndes données\nobservables": "-",
                "Valorisation\nfondée sur des\ndonnées non\nobservables": ""
            },
            {
                "": "",
                "31/12/2023": "-",
                "Prix cotés sur\ndes marchés\nactifs pour des\ninstruments\nidentiques": "",
                "Valorisation\nfondée sur\ndes données\nobservables": "",
                "Valorisation\nfondée sur des\ndonnées non\nobservables": ""
            },
            {
                "": "",
                "31/12/2023": "38 728",
                "Prix cotés sur\ndes marchés\nactifs pour des\ninstruments\nidentiques": "",
                "Valorisation\nfondée sur\ndes données\nobservables": "",
                "Valorisation\nfondée sur des\ndonnées non\nobservables": ""
            },
            {
                "": "",
                "31/12/2023": "191 380",
                "Prix cotés sur\ndes marchés\nactifs pour des\ninstruments\nidentiques": "-",
                "Valorisation\nfondée sur\ndes données\nobservables": "-",
                "Valorisation\nfondée sur des\ndonnées non\nobservables": ""
            },
            {
                "": "",
                "31/12/2023": "-",
                "Prix cotés sur\ndes marchés\nactifs pour des\ninstruments\nidentiques": "",
                "Valorisation\nfondée sur\ndes données\nobservables": "",
                "Valorisation\nfondée sur des\ndonnées non\nobservables": ""
            },
            {
                "": "",
                "31/12/2023": "-",
                "Prix cotés sur\ndes marchés\nactifs pour des\ninstruments\nidentiques": "",
                "Valorisation\nfondée sur\ndes données\nobservables": "",
                "Valorisation\nfondée sur des\ndonnées non\nobservables": ""
            },
            {
                "": "",
                "31/12/2023": "-",
                "Prix cotés sur\ndes marchés\nactifs pour des\ninstruments\nidentiques": "-",
                "Valorisation\nfondée sur\ndes données\nobservables": "-",
                "Valorisation\nfondée sur des\ndonnées non\nobservables": ""
            },
            {
                "": "",
                "31/12/2023": "-",
                "Prix cotés sur\ndes marchés\nactifs pour des\ninstruments\nidentiques": "",
                "Valorisation\nfondée sur\ndes données\nobservables": "",
                "Valorisation\nfondée sur des\ndonnées non\nobservables": ""
            },
            {
                "": "",
                "31/12/2023": "-",
                "Prix cotés sur\ndes marchés\nactifs pour des\ninstruments\nidentiques": "",
                "Valorisation\nfondée sur\ndes données\nobservables": "",
                "Valorisation\nfondée sur des\ndonnées non\nobservables": ""
            },
            {
                "": "",
                "31/12/2023": "191 380",
                "Prix cotés sur\ndes marchés\nactifs pour des\ninstruments\nidentiques": "",
                "Valorisation\nfondée sur\ndes données\nobservables": "-",
                "Valorisation\nfondée sur des\ndonnées non\nobservables": ""
            },
            {
                "": "",
                "31/12/2023": "-",
                "Prix cotés sur\ndes marchés\nactifs pour des\ninstruments\nidentiques": "-",
                "Valorisation\nfondée sur\ndes données\nobservables": "-",
                "Valorisation\nfondée sur des\ndonnées non\nobservables": ""
            },
            {
                "": "",
                "31/12/2023": "-",
                "Prix cotés sur\ndes marchés\nactifs pour des\ninstruments\nidentiques": "",
                "Valorisation\nfondée sur\ndes données\nobservables": "",
                "Valorisation\nfondée sur des\ndonnées non\nobservables": ""
            },
            {
                "": "",
                "31/12/2023": "-",
                "Prix cotés sur\ndes marchés\nactifs pour des\ninstruments\nidentiques": "",
                "Valorisation\nfondée sur\ndes données\nobservables": "",
                "Valorisation\nfondée sur des\ndonnées non\nobservables": ""
            },
            {
                "": "",
                "31/12/2023": "-",
                "Prix cotés sur\ndes marchés\nactifs pour des\ninstruments\nidentiques": "",
                "Valorisation\nfondée sur\ndes données\nobservables": "",
                "Valorisation\nfondée sur des\ndonnées non\nobservables": ""
            },
            {
                "": "",
                "31/12/2023": "-",
                "Prix cotés sur\ndes marchés\nactifs pour des\ninstruments\nidentiques": "",
                "Valorisation\nfondée sur\ndes données\nobservables": "",
                "Valorisation\nfondée sur des\ndonnées non\nobservables": ""
            },
            {
                "": "",
                "31/12/2023": "-",
                "Prix cotés sur\ndes marchés\nactifs pour des\ninstruments\nidentiques": "-",
                "Valorisation\nfondée sur\ndes données\nobservables": "-",
                "Valorisation\nfondée sur des\ndonnées non\nobservables": ""
            },
            {
                "": "",
                "31/12/2023": "-",
                "Prix cotés sur\ndes marchés\nactifs pour des\ninstruments\nidentiques": "",
                "Valorisation\nfondée sur\ndes données\nobservables": "",
                "Valorisation\nfondée sur des\ndonnées non\nobservables": ""
            }
        ],
        [
            {
                "null": "",
                "-": ""
            },
            {
                "null": "",
                "-": ""
            },
            {
                "null": "-",
                "-": "1 054 279"
            },
            {
                "null": "",
                "-": "-"
            },
            {
                "null": "",
                "-": ""
            },
            {
                "null": "",
                "-": ""
            },
            {
                "null": "",
                "-": ""
            }
        ],
        [
            {
                "Actifs financiers à la juste valeur par\ncapitaux propres": "",
                "1 608 810": "-",
                "-": ""
            },
            {
                "Actifs financiers à la juste valeur par\ncapitaux propres": "",
                "1 608 810": "",
                "-": ""
            },
            {
                "Actifs financiers à la juste valeur par\ncapitaux propres": "",
                "1 608 810": "",
                "-": ""
            },
            {
                "Actifs financiers à la juste valeur par\ncapitaux propres": "",
                "1 608 810": "",
                "-": ""
            },
            {
                "Actifs financiers à la juste valeur par\ncapitaux propres": "",
                "1 608 810": "-",
                "-": ""
            },
            {
                "Actifs financiers à la juste valeur par\ncapitaux propres": "",
                "1 608 810": "",
                "-": ""
            },
            {
                "Actifs financiers à la juste valeur par\ncapitaux propres": "",
                "1 608 810": "",
                "-": ""
            },
            {
                "Actifs financiers à la juste valeur par\ncapitaux propres": "",
                "1 608 810": "-",
                "-": ""
            }
        ],
        [
            {
                "Instruments dérivés de couverture": "Total Actifs financiers valorisés à la\njuste valeur",
                "-": "5 323 246",
                "": "222 592"
            },
            {
                "Instruments dérivés de couverture": "",
                "-": "",
                "": ""
            }
        ],
        [
            {
                "Instruments dérivés de couverture": "Total Actifs financiers valorisés à la\njuste valeur",
                "-": "3 651 188",
                "": "230 109"
            }
        ],
        [],
        [],
        [
            {
                "": "",
                "30/06/2024": "42 661",
                "31/12/2023": ""
            },
            {
                "": "",
                "30/06/2024": "9 494",
                "31/12/2023": ""
            },
            {
                "": "",
                "30/06/2024": "40 640",
                "31/12/2023": ""
            },
            {
                "": "Total",
                "30/06/2024": "92 794",
                "31/12/2023": "91 095"
            }
        ],
        [
            {
                "": "",
                "30/06/2024": "3,1%",
                "31/12/2023": ""
            }
        ],
        [
            {
                "": "Impact Compte de Résultat",
                "Brut": "",
                "ID": "",
                "Net": ""
            }
        ],
        [],
        [
            {
                "76, Bd Abdelmoumen\n37, Bd Abdellatif Ben Kaddour\nRésidence Koutoubia, 7ème étage\n20 050 Casablanca\nCasablanca -Maroc\nMaroc\nGROUPE CREDIT DU MAROC\nATTESTATION D'EXAMEN LIMITE DE LA\nSITUATION INTERMEDIAIRE CONSOLIDEE AU 30 JUIN 2024\nNous avons procédé à un examen limité de la situation intermédiaire de Crédit Du Maroc et ses filiales\n(Groupe Crédit du Maroc) comprenant le bilan et le compte de résultat, l'état du résultat global, le\ntableau des flux de trésorerie, l’état de variation des capitaux propres et une sélection de notes\nexplicatives relatifs à la période du 1er janvier au 30 juin 2024. Cette situation intermédiaire fait\nressortir un montant de capitaux propres consolidés totalisant KMAD 7.048.980, dont un bénéfice net\nde KMAD 390.835.\nNous avons effectué notre examen limité selon les normes de la Profession au Maroc relatives aux\nmissions d'examen limité. Ces normes requièrent que l'examen limité soit planifié et réalisé en vue\nd'obtenir une assurance modérée que la situation intermédiaire ne comporte pas d'anomalie\nsignificative. Un examen limité comporte essentiellement des entretiens avec le personnel de la\nsociété et des vérifications analytiques appliquées aux données financières ; il fournit donc un niveau\nd'assurance moins élevé qu'un audit. Nous n'avons pas effectué un audit et, en conséquence, nous\nn'exprimons donc pas d'opinion d'audit.\nSur la base de notre examen limité, nous n'avons pas relevé de faits qui nous laissent penser que la\nsituation intermédiaire consolidée ci-jointe, ne donne pas une image fidèle du résultat des opérations\nde la période écoulée ainsi que de la situation financière et du patrimoine du Groupe Crédit du Maroc\narrêtés au 30 juin 2024, conformément aux normes comptables internationales (IAS/IFRS).\nCasablanca, le 23 juillet 2024\nLes Commissaires aux Comptes\nERNST & YOUNG FORVIS MAZARS\nAbdeslam BERRADA ALLAM Taha FERDAOUS\nAssocié Associé": "",
                "null": "76, Bd Abdelmoumen\n37, Bd Abdellatif Ben Kaddour\nRésidence Koutoubia, 7ème étage\n20 050 Casablanca\nCasablanca -Maroc\nMaroc\nGROUPE CREDIT DU MAROC\nATTESTATION D'EXAMEN LIMITE DE LA\nSITUATION INTERMEDIAIRE CONSOLIDEE AU 30 JUIN 2024\nNous avons procédé à un examen limité de la situation intermédiaire de Crédit Du Maroc et ses filiales\n(Groupe Crédit du Maroc) comprenant le bilan et le compte de résultat, l'état du résultat global, le\ntableau des flux de trésorerie, l’état de variation des capitaux propres et une sélection de notes\nexplicatives relatifs à la période du 1er janvier au 30 juin 2024. Cette situation intermédiaire fait\nressortir un montant de capitaux propres consolidés totalisant KMAD 7.048.980, dont un bénéfice net\nde KMAD 390.835.\nNous avons effectué notre examen limité selon les normes de la Profession au Maroc relatives aux\nmissions d'examen limité. Ces normes requièrent que l'examen limité soit planifié et réalisé en vue\nd'obtenir une assurance modérée que la situation intermédiaire ne comporte pas d'anomalie\nsignificative. Un examen limité comporte essentiellement des entretiens avec le personnel de la\nsociété et des vérifications analytiques appliquées aux données financières ; il fournit donc un niveau\nd'assurance moins élevé qu'un audit. Nous n'avons pas effectué un audit et, en conséquence, nous\nn'exprimons donc pas d'opinion d'audit.\nSur la base de notre examen limité, nous n'avons pas relevé de faits qui nous laissent penser que la\nsituation intermédiaire consolidée ci-jointe, ne donne pas une image fidèle du résultat des opérations\nde la période écoulée ainsi que de la situation financière et du patrimoine du Groupe Crédit du Maroc\narrêtés au 30 juin 2024, conformément aux normes comptables internationales (IAS/IFRS).\nCasablanca, le 23 juillet 2024\nLes Commissaires aux Comptes\nERNST & YOUNG FORVIS MAZARS\nAbdeslam BERRADA ALLAM Taha FERDAOUS\nAssocié Associé"
            }
        ],
        [
            {
                "ACTIF": "",
                "30/06/2024": "1 848 958",
                "31/12/2023": ""
            },
            {
                "ACTIF": "",
                "30/06/2024": "6 810 224",
                "31/12/2023": ""
            },
            {
                "ACTIF": "",
                "30/06/2024": "2 890 028",
                "31/12/2023": ""
            },
            {
                "ACTIF": "",
                "30/06/2024": "3 920 196",
                "31/12/2023": ""
            },
            {
                "ACTIF": "",
                "30/06/2024": "52 220 642",
                "31/12/2023": ""
            },
            {
                "ACTIF": "",
                "30/06/2024": "20 239 424",
                "31/12/2023": ""
            },
            {
                "ACTIF": "",
                "30/06/2024": "10 702 731",
                "31/12/2023": ""
            },
            {
                "ACTIF": "",
                "30/06/2024": "19 475 696",
                "31/12/2023": ""
            },
            {
                "ACTIF": "",
                "30/06/2024": "1 802 791",
                "31/12/2023": ""
            },
            {
                "ACTIF": "",
                "30/06/2024": "665 222",
                "31/12/2023": ""
            },
            {
                "ACTIF": "",
                "30/06/2024": "5 167 834",
                "31/12/2023": ""
            },
            {
                "ACTIF": "",
                "30/06/2024": "4 113 700",
                "31/12/2023": ""
            },
            {
                "ACTIF": "",
                "30/06/2024": "938 995",
                "31/12/2023": ""
            },
            {
                "ACTIF": "",
                "30/06/2024": "115 139",
                "31/12/2023": ""
            },
            {
                "ACTIF": "",
                "30/06/2024": "408 338",
                "31/12/2023": ""
            },
            {
                "ACTIF": "",
                "30/06/2024": "887 861",
                "31/12/2023": ""
            },
            {
                "ACTIF": "",
                "30/06/2024": "887 861",
                "31/12/2023": ""
            },
            {
                "ACTIF": "",
                "30/06/2024": "",
                "31/12/2023": ""
            },
            {
                "ACTIF": "",
                "30/06/2024": "348 787",
                "31/12/2023": ""
            },
            {
                "ACTIF": "",
                "30/06/2024": "306 235",
                "31/12/2023": ""
            },
            {
                "ACTIF": "",
                "30/06/2024": "42 552",
                "31/12/2023": ""
            },
            {
                "ACTIF": "",
                "30/06/2024": "-",
                "31/12/2023": ""
            },
            {
                "ACTIF": "",
                "30/06/2024": "-",
                "31/12/2023": ""
            },
            {
                "ACTIF": "",
                "30/06/2024": "-",
                "31/12/2023": ""
            },
            {
                "ACTIF": "",
                "30/06/2024": "-",
                "31/12/2023": ""
            },
            {
                "ACTIF": "",
                "30/06/2024": "-",
                "31/12/2023": ""
            },
            {
                "ACTIF": "",
                "30/06/2024": "799 388",
                "31/12/2023": ""
            },
            {
                "ACTIF": "",
                "30/06/2024": "1 113 004",
                "31/12/2023": ""
            },
            {
                "ACTIF": "Total de l'Actif",
                "30/06/2024": "70 270 258",
                "31/12/2023": "66 857 168"
            }
        ],
        [
            {
                "PASSIF": "",
                "30/06/2024": "844",
                "31/12/2023": ""
            },
            {
                "PASSIF": "",
                "30/06/2024": "1 218 610",
                "31/12/2023": ""
            },
            {
                "PASSIF": "",
                "30/06/2024": "405 637",
                "31/12/2023": ""
            },
            {
                "PASSIF": "",
                "30/06/2024": "812 973",
                "31/12/2023": ""
            },
            {
                "PASSIF": "",
                "30/06/2024": "54 528 328",
                "31/12/2023": ""
            },
            {
                "PASSIF": "",
                "30/06/2024": "38 828 155",
                "31/12/2023": ""
            },
            {
                "PASSIF": "",
                "30/06/2024": "10 192 159",
                "31/12/2023": ""
            },
            {
                "PASSIF": "",
                "30/06/2024": "4 487 603",
                "31/12/2023": ""
            },
            {
                "PASSIF": "",
                "30/06/2024": "1 012 388",
                "31/12/2023": ""
            },
            {
                "PASSIF": "",
                "30/06/2024": "8 022",
                "31/12/2023": ""
            },
            {
                "PASSIF": "",
                "30/06/2024": "3 501 597",
                "31/12/2023": ""
            },
            {
                "PASSIF": "",
                "30/06/2024": "3 501 597",
                "31/12/2023": ""
            },
            {
                "PASSIF": "",
                "30/06/2024": "-",
                "31/12/2023": ""
            },
            {
                "PASSIF": "",
                "30/06/2024": "-",
                "31/12/2023": ""
            },
            {
                "PASSIF": "",
                "30/06/2024": "2 044 112",
                "31/12/2023": ""
            },
            {
                "PASSIF": "",
                "30/06/2024": "1 104 240",
                "31/12/2023": ""
            },
            {
                "PASSIF": "",
                "30/06/2024": "-",
                "31/12/2023": ""
            },
            {
                "PASSIF": "",
                "30/06/2024": "-",
                "31/12/2023": ""
            },
            {
                "PASSIF": "",
                "30/06/2024": "1 966 807",
                "31/12/2023": ""
            },
            {
                "PASSIF": "",
                "30/06/2024": "46 504",
                "31/12/2023": ""
            },
            {
                "PASSIF": "",
                "30/06/2024": "-",
                "31/12/2023": ""
            },
            {
                "PASSIF": "",
                "30/06/2024": "2 625 959",
                "31/12/2023": ""
            },
            {
                "PASSIF": "",
                "30/06/2024": "1 088 121",
                "31/12/2023": ""
            },
            {
                "PASSIF": "",
                "30/06/2024": "-",
                "31/12/2023": ""
            },
            {
                "PASSIF": "",
                "30/06/2024": "1 763 793",
                "31/12/2023": ""
            },
            {
                "PASSIF": "",
                "30/06/2024": "-",
                "31/12/2023": ""
            },
            {
                "PASSIF": "",
                "30/06/2024": "381 342",
                "31/12/2023": ""
            },
            {
                "PASSIF": "Total du Passif",
                "30/06/2024": "70 270 258",
                "31/12/2023": "66 857 168"
            }
        ],
        [
            {
                "HORS BILAN": "ENGAGEMENTS DONNES",
                "30/06/2024": "13 189 791",
                "31/12/2023": "12 181 574"
            },
            {
                "HORS BILAN": "",
                "30/06/2024": "-",
                "31/12/2023": ""
            },
            {
                "HORS BILAN": "",
                "30/06/2024": "5 602 632",
                "31/12/2023": ""
            },
            {
                "HORS BILAN": "",
                "30/06/2024": "2 707 117",
                "31/12/2023": ""
            },
            {
                "HORS BILAN": "",
                "30/06/2024": "4 880 042",
                "31/12/2023": ""
            },
            {
                "HORS BILAN": "",
                "30/06/2024": "-",
                "31/12/2023": ""
            },
            {
                "HORS BILAN": "",
                "30/06/2024": "-",
                "31/12/2023": ""
            },
            {
                "HORS BILAN": "ENGAGEMENTS RECUS",
                "30/06/2024": "2 846 821",
                "31/12/2023": "2 998 300"
            },
            {
                "HORS BILAN": "",
                "30/06/2024": "498 465",
                "31/12/2023": ""
            },
            {
                "HORS BILAN": "",
                "30/06/2024": "2 348 356",
                "31/12/2023": ""
            },
            {
                "HORS BILAN": "",
                "30/06/2024": "-",
                "31/12/2023": ""
            },
            {
                "HORS BILAN": "",
                "30/06/2024": "-",
                "31/12/2023": ""
            },
            {
                "HORS BILAN": "",
                "30/06/2024": "-",
                "31/12/2023": ""
            }
        ],
        [
            {
                "I- TABLEAU DE FORMATION DES RÉSULTATS": "",
                "30/06/2024": "1 444 384",
                "30/06/2023": ""
            },
            {
                "I- TABLEAU DE FORMATION DES RÉSULTATS": "",
                "30/06/2024": "363 312",
                "30/06/2023": ""
            },
            {
                "I- TABLEAU DE FORMATION DES RÉSULTATS": "MARGE D'INTERET",
                "30/06/2024": "1 081 072",
                "30/06/2023": "993 077"
            },
            {
                "I- TABLEAU DE FORMATION DES RÉSULTATS": "",
                "30/06/2024": "32 238",
                "30/06/2023": ""
            },
            {
                "I- TABLEAU DE FORMATION DES RÉSULTATS": "",
                "30/06/2024": "-",
                "30/06/2023": ""
            },
            {
                "I- TABLEAU DE FORMATION DES RÉSULTATS": "Marge sur financements participatifs",
                "30/06/2024": "32 238",
                "30/06/2023": "26 042"
            },
            {
                "I- TABLEAU DE FORMATION DES RÉSULTATS": "",
                "30/06/2024": "-",
                "30/06/2023": ""
            },
            {
                "I- TABLEAU DE FORMATION DES RÉSULTATS": "",
                "30/06/2024": "-",
                "30/06/2023": ""
            },
            {
                "I- TABLEAU DE FORMATION DES RÉSULTATS": "Résultat des opérations de crédit-bail et de location",
                "30/06/2024": "-",
                "30/06/2023": "-"
            },
            {
                "I- TABLEAU DE FORMATION DES RÉSULTATS": "",
                "30/06/2024": "-",
                "30/06/2023": ""
            },
            {
                "I- TABLEAU DE FORMATION DES RÉSULTATS": "",
                "30/06/2024": "-",
                "30/06/2023": ""
            },
            {
                "I- TABLEAU DE FORMATION DES RÉSULTATS": "Résultat des opérations d'Ijara",
                "30/06/2024": "-",
                "30/06/2023": "-"
            },
            {
                "I- TABLEAU DE FORMATION DES RÉSULTATS": "",
                "30/06/2024": "214 340",
                "30/06/2023": ""
            },
            {
                "I- TABLEAU DE FORMATION DES RÉSULTATS": "",
                "30/06/2024": "24 519",
                "30/06/2023": ""
            },
            {
                "I- TABLEAU DE FORMATION DES RÉSULTATS": "Marge sur commissions",
                "30/06/2024": "189 821",
                "30/06/2023": "172 723"
            },
            {
                "I- TABLEAU DE FORMATION DES RÉSULTATS": "",
                "30/06/2024": "63 683",
                "30/06/2023": ""
            },
            {
                "I- TABLEAU DE FORMATION DES RÉSULTATS": "",
                "30/06/2024": "476",
                "30/06/2023": ""
            },
            {
                "I- TABLEAU DE FORMATION DES RÉSULTATS": "",
                "30/06/2024": "146 245",
                "30/06/2023": ""
            },
            {
                "I- TABLEAU DE FORMATION DES RÉSULTATS": "",
                "30/06/2024": "-",
                "30/06/2023": ""
            },
            {
                "I- TABLEAU DE FORMATION DES RÉSULTATS": "Résultat des opérations de marché",
                "30/06/2024": "210 404",
                "30/06/2023": "171 458"
            },
            {
                "I- TABLEAU DE FORMATION DES RÉSULTATS": "",
                "30/06/2024": "66 697",
                "30/06/2023": ""
            },
            {
                "I- TABLEAU DE FORMATION DES RÉSULTATS": "",
                "30/06/2024": "55 225",
                "30/06/2023": ""
            },
            {
                "I- TABLEAU DE FORMATION DES RÉSULTATS": "",
                "30/06/2024": "-217",
                "30/06/2023": ""
            },
            {
                "I- TABLEAU DE FORMATION DES RÉSULTATS": "PRODUIT NET BANCAIRE",
                "30/06/2024": "1 524 791",
                "30/06/2023": "1 392 612"
            },
            {
                "I- TABLEAU DE FORMATION DES RÉSULTATS": "",
                "30/06/2024": "6 741",
                "30/06/2023": ""
            },
            {
                "I- TABLEAU DE FORMATION DES RÉSULTATS": "",
                "30/06/2024": "17 009",
                "30/06/2023": ""
            },
            {
                "I- TABLEAU DE FORMATION DES RÉSULTATS": "",
                "30/06/2024": "-",
                "30/06/2023": ""
            },
            {
                "I- TABLEAU DE FORMATION DES RÉSULTATS": "",
                "30/06/2024": "785 058",
                "30/06/2023": ""
            },
            {
                "I- TABLEAU DE FORMATION DES RÉSULTATS": "RESULTAT BRUT D'EXPLOITATION",
                "30/06/2024": "763 483",
                "30/06/2023": "671 920"
            },
            {
                "I- TABLEAU DE FORMATION DES RÉSULTATS": "",
                "30/06/2024": "-89 092",
                "30/06/2023": ""
            },
            {
                "I- TABLEAU DE FORMATION DES RÉSULTATS": "",
                "30/06/2024": "-10 168",
                "30/06/2023": ""
            },
            {
                "I- TABLEAU DE FORMATION DES RÉSULTATS": "RESULTAT COURANT",
                "30/06/2024": "664 222",
                "30/06/2023": "577 628"
            },
            {
                "I- TABLEAU DE FORMATION DES RÉSULTATS": "RESULTAT NON COURANT",
                "30/06/2024": "-65 043",
                "30/06/2023": "-54 701"
            },
            {
                "I- TABLEAU DE FORMATION DES RÉSULTATS": "",
                "30/06/2024": "217 837",
                "30/06/2023": ""
            },
            {
                "I- TABLEAU DE FORMATION DES RÉSULTATS": "RESULTAT NET DE L'EXERCICE",
                "30/06/2024": "381 342",
                "30/06/2023": "357 802"
            }
        ],
        [
            {
                "LIBELLE": "PRODUITS D'EXPLOITATION BANCAIRE",
                "30/06/2024": "2 026 938",
                "30/06/2023": "1 714 007"
            },
            {
                "LIBELLE": "",
                "30/06/2024": "146 615",
                "30/06/2023": ""
            },
            {
                "LIBELLE": "",
                "30/06/2024": "1 295 636",
                "30/06/2023": ""
            },
            {
                "LIBELLE": "",
                "30/06/2024": "34 371",
                "30/06/2023": ""
            },
            {
                "LIBELLE": "",
                "30/06/2024": "66 697",
                "30/06/2023": ""
            },
            {
                "LIBELLE": "",
                "30/06/2024": "-",
                "30/06/2023": ""
            },
            {
                "LIBELLE": "",
                "30/06/2024": "-",
                "30/06/2023": ""
            },
            {
                "LIBELLE": "",
                "30/06/2024": "-",
                "30/06/2023": ""
            },
            {
                "LIBELLE": "",
                "30/06/2024": "211 823",
                "30/06/2023": ""
            },
            {
                "LIBELLE": "",
                "30/06/2024": "271 796",
                "30/06/2023": ""
            },
            {
                "LIBELLE": "",
                "30/06/2024": "-",
                "30/06/2023": ""
            },
            {
                "LIBELLE": "CHARGES D'EXPLOITATION BANCAIRE",
                "30/06/2024": "502 147",
                "30/06/2023": "321 394"
            },
            {
                "LIBELLE": "",
                "30/06/2024": "45 559",
                "30/06/2023": ""
            },
            {
                "LIBELLE": "",
                "30/06/2024": "239 697",
                "30/06/2023": ""
            },
            {
                "LIBELLE": "",
                "30/06/2024": "78 055",
                "30/06/2023": ""
            },
            {
                "LIBELLE": "",
                "30/06/2024": "-",
                "30/06/2023": ""
            },
            {
                "LIBELLE": "",
                "30/06/2024": "-",
                "30/06/2023": ""
            },
            {
                "LIBELLE": "",
                "30/06/2024": "-",
                "30/06/2023": ""
            },
            {
                "LIBELLE": "",
                "30/06/2024": "138 619",
                "30/06/2023": ""
            },
            {
                "LIBELLE": "",
                "30/06/2024": "217",
                "30/06/2023": ""
            },
            {
                "LIBELLE": "PRODUIT NET BANCAIRE",
                "30/06/2024": "1 524 791",
                "30/06/2023": "1 392 612"
            },
            {
                "LIBELLE": "",
                "30/06/2024": "17 009",
                "30/06/2023": ""
            },
            {
                "LIBELLE": "",
                "30/06/2024": "-",
                "30/06/2023": ""
            },
            {
                "LIBELLE": "CHARGES GENERALES D'EXPLOITATION",
                "30/06/2024": "785 058",
                "30/06/2023": "752 066"
            },
            {
                "LIBELLE": "",
                "30/06/2024": "394 926",
                "30/06/2023": ""
            },
            {
                "LIBELLE": "",
                "30/06/2024": "25 838",
                "30/06/2023": ""
            },
            {
                "LIBELLE": "",
                "30/06/2024": "234 760",
                "30/06/2023": ""
            },
            {
                "LIBELLE": "",
                "30/06/2024": "726",
                "30/06/2023": ""
            },
            {
                "LIBELLE": "",
                "30/06/2024": "128 808",
                "30/06/2023": ""
            },
            {
                "LIBELLE": "DOTATIONS AUX PROVISIONS ET PERTES SUR CREANCES\nIRRECOUVRABLES",
                "30/06/2024": "420 669",
                "30/06/2023": "561 378"
            },
            {
                "LIBELLE": "",
                "30/06/2024": "369 918",
                "30/06/2023": ""
            },
            {
                "LIBELLE": "",
                "30/06/2024": "6 069",
                "30/06/2023": ""
            },
            {
                "LIBELLE": "",
                "30/06/2024": "44 682",
                "30/06/2023": ""
            },
            {
                "LIBELLE": "REPRISES DE PROVISIONS ET RECUPERATIONS SUR CREANCES\nAMORTIES",
                "30/06/2024": "328 149",
                "30/06/2023": "470 218"
            },
            {
                "LIBELLE": "",
                "30/06/2024": "278 114",
                "30/06/2023": ""
            },
            {
                "LIBELLE": "",
                "30/06/2024": "8 780",
                "30/06/2023": ""
            },
            {
                "LIBELLE": "",
                "30/06/2024": "41 255",
                "30/06/2023": ""
            },
            {
                "LIBELLE": "RESULTAT COURANT",
                "30/06/2024": "664 222",
                "30/06/2023": "577 628"
            },
            {
                "LIBELLE": "",
                "30/06/2024": "13 539",
                "30/06/2023": ""
            },
            {
                "LIBELLE": "",
                "30/06/2024": "78 582",
                "30/06/2023": ""
            },
            {
                "LIBELLE": "RESULTAT AVANT IMPOTS",
                "30/06/2024": "599 179",
                "30/06/2023": "522 927"
            },
            {
                "LIBELLE": "",
                "30/06/2024": "217 837",
                "30/06/2023": ""
            },
            {
                "LIBELLE": "RESULTAT NET DE L'EXERCICE",
                "30/06/2024": "381 342",
                "30/06/2023": "357 802"
            }
        ],
        [
            {
                "II- CAPACITÉ D’AUTOFINANCEMENT": "+ RESULTAT NET DE L'EXERCICE",
                "30/06/2024": "381 342",
                "30/06/2023": "357 802"
            },
            {
                "II- CAPACITÉ D’AUTOFINANCEMENT": "",
                "30/06/2024": "128 808",
                "30/06/2023": ""
            },
            {
                "II- CAPACITÉ D’AUTOFINANCEMENT": "",
                "30/06/2024": "-",
                "30/06/2023": ""
            },
            {
                "II- CAPACITÉ D’AUTOFINANCEMENT": "",
                "30/06/2024": "8 165",
                "30/06/2023": ""
            },
            {
                "II- CAPACITÉ D’AUTOFINANCEMENT": "",
                "30/06/2024": "-",
                "30/06/2023": ""
            },
            {
                "II- CAPACITÉ D’AUTOFINANCEMENT": "",
                "30/06/2024": "-",
                "30/06/2023": ""
            },
            {
                "II- CAPACITÉ D’AUTOFINANCEMENT": "",
                "30/06/2024": "25 647",
                "30/06/2023": ""
            },
            {
                "II- CAPACITÉ D’AUTOFINANCEMENT": "",
                "30/06/2024": "35",
                "30/06/2023": ""
            },
            {
                "II- CAPACITÉ D’AUTOFINANCEMENT": "",
                "30/06/2024": "-",
                "30/06/2023": ""
            },
            {
                "II- CAPACITÉ D’AUTOFINANCEMENT": "",
                "30/06/2024": "-",
                "30/06/2023": ""
            },
            {
                "II- CAPACITÉ D’AUTOFINANCEMENT": "",
                "30/06/2024": "-",
                "30/06/2023": ""
            },
            {
                "II- CAPACITÉ D’AUTOFINANCEMENT": "",
                "30/06/2024": "-",
                "30/06/2023": ""
            },
            {
                "II- CAPACITÉ D’AUTOFINANCEMENT": "+ CAPACITE D'AUTOFINANCEMENT",
                "30/06/2024": "492 633",
                "30/06/2023": "428 764"
            },
            {
                "II- CAPACITÉ D’AUTOFINANCEMENT": "",
                "30/06/2024": "-",
                "30/06/2023": ""
            },
            {
                "II- CAPACITÉ D’AUTOFINANCEMENT": "+ AUTOFINANCEMENT",
                "30/06/2024": "492 633",
                "30/06/2023": "428 764"
            }
        ],
        [
            {
                "": "",
                "Montants au 31/12/2023": "Créances",
                "null": "Provisions",
                "Montants au 30/06/2024": "Créances"
            },
            {
                "": "",
                "Montants au 31/12/2023": "",
                "null": "34 575",
                "Montants au 30/06/2024": "391 446"
            },
            {
                "": "",
                "Montants au 31/12/2023": "",
                "null": "441 454",
                "Montants au 30/06/2024": "522 015"
            },
            {
                "": "",
                "Montants au 31/12/2023": "",
                "null": "2 628 379",
                "Montants au 30/06/2024": "3 226 989"
            },
            {
                "": "TOTAL",
                "Montants au 31/12/2023": "4 096 500",
                "null": "3 104 408",
                "Montants au 30/06/2024": "4 140 450"
            }
        ],
        [
            {
                "": "",
                "30/06/2024": "1 945 660",
                "31/12/2023": ""
            },
            {
                "": "",
                "30/06/2024": "8 780",
                "31/12/2023": ""
            },
            {
                "": "",
                "30/06/2024": "26 544",
                "31/12/2023": ""
            },
            {
                "": "",
                "30/06/2024": "-458 847",
                "31/12/2023": ""
            },
            {
                "": "",
                "30/06/2024": "-78 582",
                "31/12/2023": ""
            },
            {
                "": "",
                "30/06/2024": "-656 250",
                "31/12/2023": ""
            },
            {
                "": "",
                "30/06/2024": "-217 837",
                "31/12/2023": ""
            },
            {
                "": "I - Flux de trésorerie nets provenant du compte de produits et\ncharges",
                "30/06/2024": "569 468",
                "31/12/2023": "950 069"
            },
            {
                "": "",
                "30/06/2024": "",
                "31/12/2023": ""
            },
            {
                "": "",
                "30/06/2024": "595 747",
                "31/12/2023": ""
            },
            {
                "": "",
                "30/06/2024": "-3 247 156",
                "31/12/2023": ""
            },
            {
                "": "",
                "30/06/2024": "-1 189 929",
                "31/12/2023": ""
            },
            {
                "": "",
                "30/06/2024": "-40 227",
                "31/12/2023": ""
            },
            {
                "": "",
                "30/06/2024": "-",
                "31/12/2023": ""
            },
            {
                "": "",
                "30/06/2024": "105 126",
                "31/12/2023": ""
            },
            {
                "": "",
                "30/06/2024": "2 896 759",
                "31/12/2023": ""
            },
            {
                "": "",
                "30/06/2024": "77 195",
                "31/12/2023": ""
            },
            {
                "": "",
                "30/06/2024": "296 802",
                "31/12/2023": ""
            },
            {
                "": "II - Solde des variations des actifs et passifs d'exploitation",
                "30/06/2024": "-505 682",
                "31/12/2023": "-372 407"
            },
            {
                "": "III - FLUX DE TRESORERIE NETS PROVENANT DES ACTIVITES\nD'EXPLOITATION ( I + II )",
                "30/06/2024": "63 786",
                "31/12/2023": "577 662"
            },
            {
                "": "",
                "30/06/2024": "-",
                "31/12/2023": ""
            },
            {
                "": "",
                "30/06/2024": "35",
                "31/12/2023": ""
            },
            {
                "": "",
                "30/06/2024": "-45 012",
                "31/12/2023": ""
            },
            {
                "": "",
                "30/06/2024": "-144 777",
                "31/12/2023": ""
            },
            {
                "": "",
                "30/06/2024": "14 104",
                "31/12/2023": ""
            },
            {
                "": "",
                "30/06/2024": "66 697",
                "31/12/2023": ""
            },
            {
                "": "IV - FLUX DE TRESORERIE NETS PROVENANT DES ACTIVITES\nD'INVESTISSEMENT",
                "30/06/2024": "-108 952",
                "31/12/2023": "-328 995"
            },
            {
                "": "",
                "30/06/2024": "-",
                "31/12/2023": ""
            },
            {
                "": "",
                "30/06/2024": "-",
                "31/12/2023": ""
            },
            {
                "": "",
                "30/06/2024": "-",
                "31/12/2023": ""
            },
            {
                "": "",
                "30/06/2024": "-",
                "31/12/2023": ""
            },
            {
                "": "",
                "30/06/2024": "-",
                "31/12/2023": ""
            },
            {
                "": "",
                "30/06/2024": "-372 138",
                "31/12/2023": ""
            },
            {
                "": "V - FLUX DE TRESORERIE NETS PROVENANT DES ACTIVITES DE\nFINANCEMENT",
                "30/06/2024": "-372 138",
                "31/12/2023": "148 194"
            },
            {
                "": "VI - VARIATION NETTE DE LA TRESORERIE ( III + IV + V )",
                "30/06/2024": "-417 304",
                "31/12/2023": "396 862"
            },
            {
                "": "VII - TRESORERIE A L'OUVERTURE DE L'EXERCICE",
                "30/06/2024": "2 265 417",
                "31/12/2023": "1 868 556"
            },
            {
                "": "VIII - TRESORERIE A LA CLOTURE DE L'EXERCICE",
                "30/06/2024": "1 848 114",
                "31/12/2023": "2 265 417"
            }
        ],
        [
            {
                "CREANCES": "COMPTES\nORDINAIRES\nDEBITEURS",
                "Bank Al-Maghrib,\nTrésor Public\net Service des\nChèques Postaux": "1 143 848",
                "Banques au\nMaroc": "9 289",
                "Autres éta-\nblissements\nde crédit et\nassimilés au\nMaroc": "417 940",
                "Etablisse-\nments de\ncrédit à\nl'étranger": "895 810",
                "Total\n30/06/2024": "2 466 887",
                "Total\n31/12/2023": "2 266 529"
            },
            {
                "CREANCES": "VALEURS RECUES\nEN PENSION",
                "Bank Al-Maghrib,\nTrésor Public\net Service des\nChèques Postaux": "-",
                "Banques au\nMaroc": "1 010 217",
                "Autres éta-\nblissements\nde crédit et\nassimilés au\nMaroc": "-",
                "Etablisse-\nments de\ncrédit à\nl'étranger": "-",
                "Total\n30/06/2024": "1 010 217",
                "Total\n31/12/2023": "2 201 870"
            },
            {
                "CREANCES": "",
                "Bank Al-Maghrib,\nTrésor Public\net Service des\nChèques Postaux": "",
                "Banques au\nMaroc": "",
                "Autres éta-\nblissements\nde crédit et\nassimilés au\nMaroc": "",
                "Etablisse-\nments de\ncrédit à\nl'étranger": "",
                "Total\n30/06/2024": "-",
                "Total\n31/12/2023": ""
            },
            {
                "CREANCES": "",
                "Bank Al-Maghrib,\nTrésor Public\net Service des\nChèques Postaux": "",
                "Banques au\nMaroc": "",
                "Autres éta-\nblissements\nde crédit et\nassimilés au\nMaroc": "",
                "Etablisse-\nments de\ncrédit à\nl'étranger": "",
                "Total\n30/06/2024": "1 010 217",
                "Total\n31/12/2023": ""
            },
            {
                "CREANCES": "PRETS DE TRESO-\nRERIE",
                "Bank Al-Maghrib,\nTrésor Public\net Service des\nChèques Postaux": "-",
                "Banques au\nMaroc": "1 000 000",
                "Autres éta-\nblissements\nde crédit et\nassimilés au\nMaroc": "799 606",
                "Etablisse-\nments de\ncrédit à\nl'étranger": "-",
                "Total\n30/06/2024": "1 799 606",
                "Total\n31/12/2023": "1 893 759"
            },
            {
                "CREANCES": "",
                "Bank Al-Maghrib,\nTrésor Public\net Service des\nChèques Postaux": "",
                "Banques au\nMaroc": "",
                "Autres éta-\nblissements\nde crédit et\nassimilés au\nMaroc": "",
                "Etablisse-\nments de\ncrédit à\nl'étranger": "",
                "Total\n30/06/2024": "200 000",
                "Total\n31/12/2023": ""
            },
            {
                "CREANCES": "",
                "Bank Al-Maghrib,\nTrésor Public\net Service des\nChèques Postaux": "",
                "Banques au\nMaroc": "",
                "Autres éta-\nblissements\nde crédit et\nassimilés au\nMaroc": "",
                "Etablisse-\nments de\ncrédit à\nl'étranger": "",
                "Total\n30/06/2024": "1 599 606",
                "Total\n31/12/2023": ""
            },
            {
                "CREANCES": "PRETS FINANCIERS",
                "Bank Al-Maghrib,\nTrésor Public\net Service des\nChèques Postaux": "-",
                "Banques au\nMaroc": "-",
                "Autres éta-\nblissements\nde crédit et\nassimilés au\nMaroc": "2 296 012",
                "Etablisse-\nments de\ncrédit à\nl'étranger": "-",
                "Total\n30/06/2024": "2 296 012",
                "Total\n31/12/2023": "2 364 558"
            },
            {
                "CREANCES": "AUTRES CREANCES",
                "Bank Al-Maghrib,\nTrésor Public\net Service des\nChèques Postaux": "-",
                "Banques au\nMaroc": "-",
                "Autres éta-\nblissements\nde crédit et\nassimilés au\nMaroc": "354 358",
                "Etablisse-\nments de\ncrédit à\nl'étranger": "-",
                "Total\n30/06/2024": "354 358",
                "Total\n31/12/2023": "134 256"
            },
            {
                "CREANCES": "INTERETS COURUS\nA RECEVOIR",
                "Bank Al-Maghrib,\nTrésor Public\net Service des\nChèques Postaux": "-",
                "Banques au\nMaroc": "11 102",
                "Autres éta-\nblissements\nde crédit et\nassimilés au\nMaroc": "15 891",
                "Etablisse-\nments de\ncrédit à\nl'étranger": "-",
                "Total\n30/06/2024": "26 993",
                "Total\n31/12/2023": "24 516"
            },
            {
                "CREANCES": "CREANCES EN\nSOUFFRANCE",
                "Bank Al-Maghrib,\nTrésor Public\net Service des\nChèques Postaux": "-",
                "Banques au\nMaroc": "-",
                "Autres éta-\nblissements\nde crédit et\nassimilés au\nMaroc": "-",
                "Etablisse-\nments de\ncrédit à\nl'étranger": "-",
                "Total\n30/06/2024": "-",
                "Total\n31/12/2023": "-"
            },
            {
                "CREANCES": "TOTAL",
                "Bank Al-Maghrib,\nTrésor Public\net Service des\nChèques Postaux": "1 143 848",
                "Banques au\nMaroc": "2 030 608",
                "Autres éta-\nblissements\nde crédit et\nassimilés au\nMaroc": "3 883 806",
                "Etablisse-\nments de\ncrédit à\nl'étranger": "895 810",
                "Total\n30/06/2024": "7 954 073",
                "Total\n31/12/2023": "8 885 488"
            }
        ],
        [
            {
                "TITRES": "",
                "Etablissements\nde crédit et\nassimilés": "",
                "Emetteurs\npublics": "",
                "Emetteurs privés": "financiers",
                "null": "non\nfinanciers",
                "Total\n30/06/2024": "",
                "Total\n31/12/2023": ""
            },
            {
                "TITRES": "TITRES COTES",
                "Etablissements\nde crédit et\nassimilés": "-",
                "Emetteurs\npublics": "-",
                "Emetteurs privés": "-",
                "null": "-",
                "Total\n30/06/2024": "-",
                "Total\n31/12/2023": "-"
            },
            {
                "TITRES": "",
                "Etablissements\nde crédit et\nassimilés": "",
                "Emetteurs\npublics": "",
                "Emetteurs privés": "",
                "null": "",
                "Total\n30/06/2024": "-",
                "Total\n31/12/2023": ""
            },
            {
                "TITRES": "",
                "Etablissements\nde crédit et\nassimilés": "",
                "Emetteurs\npublics": "",
                "Emetteurs privés": "",
                "null": "",
                "Total\n30/06/2024": "-",
                "Total\n31/12/2023": ""
            },
            {
                "TITRES": "",
                "Etablissements\nde crédit et\nassimilés": "",
                "Emetteurs\npublics": "",
                "Emetteurs privés": "",
                "null": "",
                "Total\n30/06/2024": "-",
                "Total\n31/12/2023": ""
            },
            {
                "TITRES": "",
                "Etablissements\nde crédit et\nassimilés": "",
                "Emetteurs\npublics": "",
                "Emetteurs privés": "",
                "null": "",
                "Total\n30/06/2024": "-",
                "Total\n31/12/2023": ""
            },
            {
                "TITRES": "TITRES NON COTES",
                "Etablissements\nde crédit et\nassimilés": "938 995",
                "Emetteurs\npublics": "5 001 561",
                "Emetteurs privés": "115 073",
                "null": "67",
                "Total\n30/06/2024": "6 055 695",
                "Total\n31/12/2023": "4 865 289"
            },
            {
                "TITRES": "",
                "Etablissements\nde crédit et\nassimilés": "",
                "Emetteurs\npublics": "",
                "Emetteurs privés": "",
                "null": "",
                "Total\n30/06/2024": "5 001 561",
                "Total\n31/12/2023": ""
            },
            {
                "TITRES": "",
                "Etablissements\nde crédit et\nassimilés": "",
                "Emetteurs\npublics": "",
                "Emetteurs privés": "",
                "null": "",
                "Total\n30/06/2024": "-",
                "Total\n31/12/2023": ""
            },
            {
                "TITRES": "",
                "Etablissements\nde crédit et\nassimilés": "",
                "Emetteurs\npublics": "",
                "Emetteurs privés": "",
                "null": "",
                "Total\n30/06/2024": "938 995",
                "Total\n31/12/2023": ""
            },
            {
                "TITRES": "",
                "Etablissements\nde crédit et\nassimilés": "",
                "Emetteurs\npublics": "",
                "Emetteurs privés": "",
                "null": "",
                "Total\n30/06/2024": "115 139",
                "Total\n31/12/2023": ""
            },
            {
                "TITRES": "TOTAL",
                "Etablissements\nde crédit et\nassimilés": "938 995",
                "Emetteurs\npublics": "5 001 561",
                "Emetteurs privés": "115 073",
                "null": "67",
                "Total\n30/06/2024": "6 055 695",
                "Total\n31/12/2023": "4 865 289"
            }
        ],
        [],
        [
            {
                "Actif": "Instruments optionnels achetés",
                "30/06/2024": "",
                "31/12/2023": ""
            },
            {
                "Actif": "Opérations diverses sur titres",
                "30/06/2024": "24 082",
                "31/12/2023": "-"
            },
            {
                "Actif": "Débiteurs divers",
                "30/06/2024": "46 170",
                "31/12/2023": "84 688"
            },
            {
                "Actif": "",
                "30/06/2024": "14 941",
                "31/12/2023": ""
            },
            {
                "Actif": "",
                "30/06/2024": "-",
                "31/12/2023": ""
            },
            {
                "Actif": "",
                "30/06/2024": "2 404",
                "31/12/2023": ""
            },
            {
                "Actif": "",
                "30/06/2024": "-",
                "31/12/2023": ""
            },
            {
                "Actif": "",
                "30/06/2024": "28 824",
                "31/12/2023": ""
            },
            {
                "Actif": "Valeurs et emplois divers",
                "30/06/2024": "2 756",
                "31/12/2023": "1 885"
            },
            {
                "Actif": "Vomptes de régularisation",
                "30/06/2024": "335 330",
                "31/12/2023": "281 539"
            },
            {
                "Actif": "",
                "30/06/2024": "",
                "31/12/2023": ""
            },
            {
                "Actif": "",
                "30/06/2024": "25 472",
                "31/12/2023": ""
            },
            {
                "Actif": "",
                "30/06/2024": "-",
                "31/12/2023": ""
            },
            {
                "Actif": "",
                "30/06/2024": "41 674",
                "31/12/2023": ""
            },
            {
                "Actif": "",
                "30/06/2024": "175",
                "31/12/2023": ""
            },
            {
                "Actif": "",
                "30/06/2024": "76 844",
                "31/12/2023": ""
            },
            {
                "Actif": "",
                "30/06/2024": "58 096",
                "31/12/2023": ""
            },
            {
                "Actif": "",
                "30/06/2024": "133 070",
                "31/12/2023": ""
            },
            {
                "Actif": "Créances en souffrance sur opérations diverses",
                "30/06/2024": "",
                "31/12/2023": ""
            },
            {
                "Actif": "TOTAL",
                "30/06/2024": "408 338",
                "31/12/2023": "368 111"
            }
        ],
        [],
        [],
        [
            {
                "DETTES": "",
                "Établissements de crédit et assimilés au Maroc": "Bank Al-Maghrib,\nTrésor Public\net Service des\nChèques Postaux",
                "null": "Autres établisse-\nments de crédit\net assimilés au\nMaroc",
                "Établisse-\nments de\ncrédit à\nl’étranger": "",
                "Total\n30/06/2024": "",
                "Total\n31/12/2023": ""
            },
            {
                "DETTES": "Comptes ordinaires\ncréditeurs",
                "Établissements de crédit et assimilés au Maroc": "844",
                "null": "11 024",
                "Établisse-\nments de\ncrédit à\nl’étranger": "62 769",
                "Total\n30/06/2024": "77 174",
                "Total\n31/12/2023": "594 649"
            },
            {
                "DETTES": "Valeurs données\nen pension",
                "Établissements de crédit et assimilés au Maroc": "-",
                "null": "-",
                "Établisse-\nments de\ncrédit à\nl’étranger": "-",
                "Total\n30/06/2024": "-",
                "Total\n31/12/2023": "-"
            },
            {
                "DETTES": "",
                "Établissements de crédit et assimilés au Maroc": "",
                "null": "",
                "Établisse-\nments de\ncrédit à\nl’étranger": "",
                "Total\n30/06/2024": "-",
                "Total\n31/12/2023": ""
            },
            {
                "DETTES": "",
                "Établissements de crédit et assimilés au Maroc": "",
                "null": "",
                "Établisse-\nments de\ncrédit à\nl’étranger": "",
                "Total\n30/06/2024": "-",
                "Total\n31/12/2023": ""
            },
            {
                "DETTES": "Emprunts de trésorerie",
                "Établissements de crédit et assimilés au Maroc": "-",
                "null": "203 196",
                "Établisse-\nments de\ncrédit à\nl’étranger": "39 703",
                "Total\n30/06/2024": "242 899",
                "Total\n31/12/2023": "295 437"
            },
            {
                "DETTES": "",
                "Établissements de crédit et assimilés au Maroc": "",
                "null": "",
                "Établisse-\nments de\ncrédit à\nl’étranger": "",
                "Total\n30/06/2024": "-",
                "Total\n31/12/2023": ""
            },
            {
                "DETTES": "",
                "Établissements de crédit et assimilés au Maroc": "",
                "null": "",
                "Établisse-\nments de\ncrédit à\nl’étranger": "",
                "Total\n30/06/2024": "242 899",
                "Total\n31/12/2023": ""
            },
            {
                "DETTES": "Emprunts financiers",
                "Établissements de crédit et assimilés au Maroc": "-",
                "null": "-",
                "Établisse-\nments de\ncrédit à\nl’étranger": "523 386",
                "Total\n30/06/2024": "525 565",
                "Total\n31/12/2023": "33 615"
            },
            {
                "DETTES": "Autres dettes",
                "Établissements de crédit et assimilés au Maroc": "",
                "null": "339 779",
                "Établisse-\nments de\ncrédit à\nl’étranger": "",
                "Total\n30/06/2024": "339 779",
                "Total\n31/12/2023": "159 139"
            },
            {
                "DETTES": "Intérêts courus à payer",
                "Établissements de crédit et assimilés au Maroc": "-",
                "null": "-",
                "Établisse-\nments de\ncrédit à\nl’étranger": "-",
                "Total\n30/06/2024": "34 037",
                "Total\n31/12/2023": "30 891"
            },
            {
                "DETTES": "TOTAL",
                "Établissements de crédit et assimilés au Maroc": "844",
                "null": "553 999",
                "Établisse-\nments de\ncrédit à\nl’étranger": "625 858",
                "Total\n30/06/2024": "1 219 455",
                "Total\n31/12/2023": "1 113 731"
            }
        ],
        [
            {
                "CRÉANCES": "",
                "Secteur\npublic": "",
                "Secteur privé": "Entreprises\nfinancières",
                "null": "Autre\nclientèle",
                "Total\n30/06/2024": "",
                "Total\n31/12/2023": ""
            },
            {
                "CRÉANCES": "Crédits de trésorerie",
                "Secteur\npublic": "2 858 587",
                "Secteur privé": "10 451",
                "null": "303 598",
                "Total\n30/06/2024": "16 200 049",
                "Total\n31/12/2023": "14 825 681"
            },
            {
                "CRÉANCES": "",
                "Secteur\npublic": "",
                "Secteur privé": "",
                "null": "",
                "Total\n30/06/2024": "2 934 961",
                "Total\n31/12/2023": ""
            },
            {
                "CRÉANCES": "",
                "Secteur\npublic": "",
                "Secteur privé": "",
                "null": "",
                "Total\n30/06/2024": "2 582 388",
                "Total\n31/12/2023": ""
            },
            {
                "CRÉANCES": "",
                "Secteur\npublic": "",
                "Secteur privé": "",
                "null": "",
                "Total\n30/06/2024": "206 749",
                "Total\n31/12/2023": ""
            },
            {
                "CRÉANCES": "",
                "Secteur\npublic": "",
                "Secteur privé": "",
                "null": "",
                "Total\n30/06/2024": "10 475 952",
                "Total\n31/12/2023": ""
            },
            {
                "CRÉANCES": "Crédits à la consommation",
                "Secteur\npublic": "-",
                "Secteur privé": "-",
                "null": "3 843 942",
                "Total\n30/06/2024": "3 843 942",
                "Total\n31/12/2023": "3 547 160"
            },
            {
                "CRÉANCES": "Crédits à l'équipement",
                "Secteur\npublic": "2 769 829",
                "Secteur privé": "9 491",
                "null": "-",
                "Total\n30/06/2024": "10 576 560",
                "Total\n31/12/2023": "9 570 148"
            },
            {
                "CRÉANCES": "Crédits immobiliers",
                "Secteur\npublic": "-",
                "Secteur privé": "-",
                "null": "17 156 427",
                "Total\n30/06/2024": "19 397 260",
                "Total\n31/12/2023": "18 503 111"
            },
            {
                "CRÉANCES": "Autres crédits",
                "Secteur\npublic": "-",
                "Secteur privé": "758 288",
                "null": "-",
                "Total\n30/06/2024": "766 445",
                "Total\n31/12/2023": "1 123 949"
            },
            {
                "CRÉANCES": "Créances acquises par\naffacturage",
                "Secteur\npublic": "665 222",
                "Secteur privé": "-",
                "null": "-",
                "Total\n30/06/2024": "665 222",
                "Total\n31/12/2023": "715 251"
            },
            {
                "CRÉANCES": "Intérêts courus à recevoir",
                "Secteur\npublic": "-",
                "Secteur privé": "95 249",
                "null": "-",
                "Total\n30/06/2024": "400 344",
                "Total\n31/12/2023": "360 091"
            },
            {
                "CRÉANCES": "Créances en souffrance",
                "Secteur\npublic": "-",
                "Secteur privé": "-",
                "null": "788 525",
                "Total\n30/06/2024": "1 036 042",
                "Total\n31/12/2023": "1 106 544"
            },
            {
                "CRÉANCES": "",
                "Secteur\npublic": "",
                "Secteur privé": "",
                "null": "",
                "Total\n30/06/2024": "356 871",
                "Total\n31/12/2023": ""
            },
            {
                "CRÉANCES": "",
                "Secteur\npublic": "",
                "Secteur privé": "",
                "null": "",
                "Total\n30/06/2024": "80 560",
                "Total\n31/12/2023": ""
            },
            {
                "CRÉANCES": "",
                "Secteur\npublic": "",
                "Secteur privé": "",
                "null": "",
                "Total\n30/06/2024": "598 611",
                "Total\n31/12/2023": ""
            },
            {
                "CRÉANCES": "TOTAL",
                "Secteur\npublic": "6 293 638",
                "Secteur privé": "873 479",
                "null": "22 092 493",
                "Total\n30/06/2024": "52 885 864",
                "Total\n31/12/2023": "49 751 934"
            }
        ],
        [
            {
                "Nature": "",
                "Montant brut\nau début de\nl’exercice": "",
                "Montant des\nacquisitions\nau cours de\nl’exercice": "",
                "Montant des\ncessions ou re-\ntraits au cours\nde l’exercice": "",
                "Montant\nbrut à la\nfin de\nl’exercice": "",
                "Amortissements et/ou provisions": "Montant des\namortisse-\nments et/ou\nprovisions\nau début de\nl’exercice",
                "null": "Cumul",
                "Autres\nmouvements": "",
                "Montant net\nà la fin de\nl’exercice": ""
            },
            {
                "Nature": "IMMOBILISATIONS INCORPORELLES",
                "Montant brut\nau début de\nl’exercice": "1 370 388",
                "Montant des\nacquisitions\nau cours de\nl’exercice": "198 380",
                "Montant des\ncessions ou re-\ntraits au cours\nde l’exercice": "94 427",
                "Montant\nbrut à la\nfin de\nl’exercice": "1 471 465",
                "Amortissements et/ou provisions": "596 934",
                "null": "672 077",
                "Autres\nmouvements": "-",
                "Montant net\nà la fin de\nl’exercice": "799 388"
            },
            {
                "Nature": "",
                "Montant brut\nau début de\nl’exercice": "",
                "Montant des\nacquisitions\nau cours de\nl’exercice": "",
                "Montant des\ncessions ou re-\ntraits au cours\nde l’exercice": "",
                "Montant\nbrut à la\nfin de\nl’exercice": "",
                "Amortissements et/ou provisions": "",
                "null": "",
                "Autres\nmouvements": "",
                "Montant net\nà la fin de\nl’exercice": "17 429"
            },
            {
                "Nature": "",
                "Montant brut\nau début de\nl’exercice": "",
                "Montant des\nacquisitions\nau cours de\nl’exercice": "",
                "Montant des\ncessions ou re-\ntraits au cours\nde l’exercice": "",
                "Montant\nbrut à la\nfin de\nl’exercice": "",
                "Amortissements et/ou provisions": "",
                "null": "",
                "Autres\nmouvements": "",
                "Montant net\nà la fin de\nl’exercice": "-"
            },
            {
                "Nature": "",
                "Montant brut\nau début de\nl’exercice": "",
                "Montant des\nacquisitions\nau cours de\nl’exercice": "",
                "Montant des\ncessions ou re-\ntraits au cours\nde l’exercice": "",
                "Montant\nbrut à la\nfin de\nl’exercice": "",
                "Amortissements et/ou provisions": "",
                "null": "",
                "Autres\nmouvements": "",
                "Montant net\nà la fin de\nl’exercice": "781 959"
            },
            {
                "Nature": "",
                "Montant brut\nau début de\nl’exercice": "",
                "Montant des\nacquisitions\nau cours de\nl’exercice": "",
                "Montant des\ncessions ou re-\ntraits au cours\nde l’exercice": "",
                "Montant\nbrut à la\nfin de\nl’exercice": "",
                "Amortissements et/ou provisions": "",
                "null": "",
                "Autres\nmouvements": "",
                "Montant net\nà la fin de\nl’exercice": "-"
            },
            {
                "Nature": "IMMOBILISATIONS CORPORELLES",
                "Montant brut\nau début de\nl’exercice": "2 542 060",
                "Montant des\nacquisitions\nau cours de\nl’exercice": "43 875",
                "Montant des\ncessions ou re-\ntraits au cours\nde l’exercice": "5 743",
                "Montant\nbrut à la\nfin de\nl’exercice": "2 582 998",
                "Amortissements et/ou provisions": "1 419 091",
                "null": "1 469 994",
                "Autres\nmouvements": "-",
                "Montant net\nà la fin de\nl’exercice": "1 113 004"
            },
            {
                "Nature": "",
                "Montant brut\nau début de\nl’exercice": "",
                "Montant des\nacquisitions\nau cours de\nl’exercice": "",
                "Montant des\ncessions ou re-\ntraits au cours\nde l’exercice": "",
                "Montant\nbrut à la\nfin de\nl’exercice": "",
                "Amortissements et/ou provisions": "",
                "null": "",
                "Autres\nmouvements": "",
                "Montant net\nà la fin de\nl’exercice": "750 482"
            },
            {
                "Nature": "",
                "Montant brut\nau début de\nl’exercice": "",
                "Montant des\nacquisitions\nau cours de\nl’exercice": "",
                "Montant des\ncessions ou re-\ntraits au cours\nde l’exercice": "",
                "Montant\nbrut à la\nfin de\nl’exercice": "",
                "Amortissements et/ou provisions": "",
                "null": "",
                "Autres\nmouvements": "",
                "Montant net\nà la fin de\nl’exercice": "357 875"
            },
            {
                "Nature": "",
                "Montant brut\nau début de\nl’exercice": "",
                "Montant des\nacquisitions\nau cours de\nl’exercice": "",
                "Montant des\ncessions ou re-\ntraits au cours\nde l’exercice": "",
                "Montant\nbrut à la\nfin de\nl’exercice": "",
                "Amortissements et/ou provisions": "",
                "null": "",
                "Autres\nmouvements": "",
                "Montant net\nà la fin de\nl’exercice": "392 561"
            },
            {
                "Nature": "",
                "Montant brut\nau début de\nl’exercice": "",
                "Montant des\nacquisitions\nau cours de\nl’exercice": "",
                "Montant des\ncessions ou re-\ntraits au cours\nde l’exercice": "",
                "Montant\nbrut à la\nfin de\nl’exercice": "",
                "Amortissements et/ou provisions": "",
                "null": "",
                "Autres\nmouvements": "",
                "Montant net\nà la fin de\nl’exercice": "45"
            },
            {
                "Nature": "",
                "Montant brut\nau début de\nl’exercice": "",
                "Montant des\nacquisitions\nau cours de\nl’exercice": "",
                "Montant des\ncessions ou re-\ntraits au cours\nde l’exercice": "",
                "Montant\nbrut à la\nfin de\nl’exercice": "",
                "Amortissements et/ou provisions": "",
                "null": "",
                "Autres\nmouvements": "",
                "Montant net\nà la fin de\nl’exercice": "129 434"
            },
            {
                "Nature": "",
                "Montant brut\nau début de\nl’exercice": "",
                "Montant des\nacquisitions\nau cours de\nl’exercice": "",
                "Montant des\ncessions ou re-\ntraits au cours\nde l’exercice": "",
                "Montant\nbrut à la\nfin de\nl’exercice": "",
                "Amortissements et/ou provisions": "",
                "null": "",
                "Autres\nmouvements": "",
                "Montant net\nà la fin de\nl’exercice": "21 225"
            },
            {
                "Nature": "",
                "Montant brut\nau début de\nl’exercice": "",
                "Montant des\nacquisitions\nau cours de\nl’exercice": "",
                "Montant des\ncessions ou re-\ntraits au cours\nde l’exercice": "",
                "Montant\nbrut à la\nfin de\nl’exercice": "",
                "Amortissements et/ou provisions": "",
                "null": "",
                "Autres\nmouvements": "",
                "Montant net\nà la fin de\nl’exercice": "8 857"
            },
            {
                "Nature": "",
                "Montant brut\nau début de\nl’exercice": "",
                "Montant des\nacquisitions\nau cours de\nl’exercice": "",
                "Montant des\ncessions ou re-\ntraits au cours\nde l’exercice": "",
                "Montant\nbrut à la\nfin de\nl’exercice": "",
                "Amortissements et/ou provisions": "",
                "null": "",
                "Autres\nmouvements": "",
                "Montant net\nà la fin de\nl’exercice": "24 477"
            },
            {
                "Nature": "",
                "Montant brut\nau début de\nl’exercice": "",
                "Montant des\nacquisitions\nau cours de\nl’exercice": "",
                "Montant des\ncessions ou re-\ntraits au cours\nde l’exercice": "",
                "Montant\nbrut à la\nfin de\nl’exercice": "",
                "Amortissements et/ou provisions": "",
                "null": "",
                "Autres\nmouvements": "",
                "Montant net\nà la fin de\nl’exercice": "69 938"
            },
            {
                "Nature": "",
                "Montant brut\nau début de\nl’exercice": "",
                "Montant des\nacquisitions\nau cours de\nl’exercice": "",
                "Montant des\ncessions ou re-\ntraits au cours\nde l’exercice": "",
                "Montant\nbrut à la\nfin de\nl’exercice": "",
                "Amortissements et/ou provisions": "",
                "null": "",
                "Autres\nmouvements": "",
                "Montant net\nà la fin de\nl’exercice": "12"
            },
            {
                "Nature": "",
                "Montant brut\nau début de\nl’exercice": "",
                "Montant des\nacquisitions\nau cours de\nl’exercice": "",
                "Montant des\ncessions ou re-\ntraits au cours\nde l’exercice": "",
                "Montant\nbrut à la\nfin de\nl’exercice": "",
                "Amortissements et/ou provisions": "",
                "null": "",
                "Autres\nmouvements": "",
                "Montant net\nà la fin de\nl’exercice": "4 924"
            },
            {
                "Nature": "",
                "Montant brut\nau début de\nl’exercice": "",
                "Montant des\nacquisitions\nau cours de\nl’exercice": "",
                "Montant des\ncessions ou re-\ntraits au cours\nde l’exercice": "",
                "Montant\nbrut à la\nfin de\nl’exercice": "",
                "Amortissements et/ou provisions": "",
                "null": "",
                "Autres\nmouvements": "",
                "Montant net\nà la fin de\nl’exercice": "209 253"
            },
            {
                "Nature": "",
                "Montant brut\nau début de\nl’exercice": "",
                "Montant des\nacquisitions\nau cours de\nl’exercice": "",
                "Montant des\ncessions ou re-\ntraits au cours\nde l’exercice": "",
                "Montant\nbrut à la\nfin de\nl’exercice": "",
                "Amortissements et/ou provisions": "",
                "null": "",
                "Autres\nmouvements": "",
                "Montant net\nà la fin de\nl’exercice": "23 835"
            },
            {
                "Nature": "",
                "Montant brut\nau début de\nl’exercice": "",
                "Montant des\nacquisitions\nau cours de\nl’exercice": "",
                "Montant des\ncessions ou re-\ntraits au cours\nde l’exercice": "",
                "Montant\nbrut à la\nfin de\nl’exercice": "",
                "Amortissements et/ou provisions": "",
                "null": "",
                "Autres\nmouvements": "",
                "Montant net\nà la fin de\nl’exercice": "2 152"
            },
            {
                "Nature": "",
                "Montant brut\nau début de\nl’exercice": "",
                "Montant des\nacquisitions\nau cours de\nl’exercice": "",
                "Montant des\ncessions ou re-\ntraits au cours\nde l’exercice": "",
                "Montant\nbrut à la\nfin de\nl’exercice": "",
                "Amortissements et/ou provisions": "",
                "null": "",
                "Autres\nmouvements": "",
                "Montant net\nà la fin de\nl’exercice": "11 704"
            },
            {
                "Nature": "",
                "Montant brut\nau début de\nl’exercice": "",
                "Montant des\nacquisitions\nau cours de\nl’exercice": "",
                "Montant des\ncessions ou re-\ntraits au cours\nde l’exercice": "",
                "Montant\nbrut à la\nfin de\nl’exercice": "",
                "Amortissements et/ou provisions": "",
                "null": "",
                "Autres\nmouvements": "",
                "Montant net\nà la fin de\nl’exercice": "762"
            },
            {
                "Nature": "",
                "Montant brut\nau début de\nl’exercice": "",
                "Montant des\nacquisitions\nau cours de\nl’exercice": "",
                "Montant des\ncessions ou re-\ntraits au cours\nde l’exercice": "",
                "Montant\nbrut à la\nfin de\nl’exercice": "",
                "Amortissements et/ou provisions": "",
                "null": "",
                "Autres\nmouvements": "",
                "Montant net\nà la fin de\nl’exercice": "9 218"
            },
            {
                "Nature": "",
                "Montant brut\nau début de\nl’exercice": "",
                "Montant des\nacquisitions\nau cours de\nl’exercice": "",
                "Montant des\ncessions ou re-\ntraits au cours\nde l’exercice": "",
                "Montant\nbrut à la\nfin de\nl’exercice": "",
                "Amortissements et/ou provisions": "",
                "null": "",
                "Autres\nmouvements": "",
                "Montant net\nà la fin de\nl’exercice": "-"
            },
            {
                "Nature": "Total",
                "Montant brut\nau début de\nl’exercice": "3 912 448",
                "Montant des\nacquisitions\nau cours de\nl’exercice": "242 255",
                "Montant des\ncessions ou re-\ntraits au cours\nde l’exercice": "100 170",
                "Montant\nbrut à la\nfin de\nl’exercice": "4 054 463",
                "Amortissements et/ou provisions": "2 016 026",
                "null": "2 142 071",
                "Autres\nmouvements": "-",
                "Montant net\nà la fin de\nl’exercice": "1 912 392"
            }
        ],
        [
            {
                "DÉPÔTS": "",
                "Secteur\npublic": "",
                "Secteur privé": "Entreprises\nfinancières",
                "null": "Autre\nclientèle",
                "Total\n30/06/2024": "",
                "Total\n31/12/2023": ""
            },
            {
                "DÉPÔTS": "",
                "Secteur\npublic": "",
                "Secteur privé": "",
                "null": "",
                "Total\n30/06/2024": "38 835 137",
                "Total\n31/12/2023": ""
            },
            {
                "DÉPÔTS": "",
                "Secteur\npublic": "",
                "Secteur privé": "",
                "null": "",
                "Total\n30/06/2024": "10 122 215",
                "Total\n31/12/2023": ""
            },
            {
                "DÉPÔTS": "",
                "Secteur\npublic": "",
                "Secteur privé": "",
                "null": "",
                "Total\n30/06/2024": "4 436 582",
                "Total\n31/12/2023": ""
            },
            {
                "DÉPÔTS": "",
                "Secteur\npublic": "",
                "Secteur privé": "",
                "null": "",
                "Total\n30/06/2024": "1 009 774",
                "Total\n31/12/2023": ""
            },
            {
                "DÉPÔTS": "",
                "Secteur\npublic": "",
                "Secteur privé": "",
                "null": "",
                "Total\n30/06/2024": "124 620",
                "Total\n31/12/2023": ""
            },
            {
                "DÉPÔTS": "TOTAL",
                "Secteur\npublic": "343 688",
                "Secteur privé": "701 351",
                "null": "39 946 447",
                "Total\n30/06/2024": "54 528 328",
                "Total\n31/12/2023": "51 678 073"
            }
        ],
        [
            {
                "PROVISIONS": "PROVISIONS DEDUITES DE\nL'ACTIF, SUR :",
                "Encours\n31/12/2023": "2 916 170",
                "Dotations": "367 931",
                "Reprises": "267 991",
                "Autres\nvariations": "23",
                "Encours\n30/06/2024": "3 016 133"
            },
            {
                "PROVISIONS": "",
                "Encours\n31/12/2023": "",
                "Dotations": "",
                "Reprises": "",
                "Autres\nvariations": "",
                "Encours\n30/06/2024": "-"
            },
            {
                "PROVISIONS": "",
                "Encours\n31/12/2023": "",
                "Dotations": "",
                "Reprises": "",
                "Autres\nvariations": "",
                "Encours\n30/06/2024": "2 972 645"
            },
            {
                "PROVISIONS": "",
                "Encours\n31/12/2023": "",
                "Dotations": "",
                "Reprises": "",
                "Autres\nvariations": "",
                "Encours\n30/06/2024": "15 177"
            },
            {
                "PROVISIONS": "",
                "Encours\n31/12/2023": "",
                "Dotations": "",
                "Reprises": "",
                "Autres\nvariations": "",
                "Encours\n30/06/2024": "28 311"
            },
            {
                "PROVISIONS": "",
                "Encours\n31/12/2023": "",
                "Dotations": "",
                "Reprises": "",
                "Autres\nvariations": "",
                "Encours\n30/06/2024": "-"
            },
            {
                "PROVISIONS": "",
                "Encours\n31/12/2023": "",
                "Dotations": "",
                "Reprises": "",
                "Autres\nvariations": "",
                "Encours\n30/06/2024": "-"
            },
            {
                "PROVISIONS": "PROVISIONS INSCRITES AU\nPASSIF :",
                "Encours\n31/12/2023": "1 120 135",
                "Dotations": "46 669",
                "Reprises": "62 564",
                "Autres\nvariations": "-",
                "Encours\n30/06/2024": "1 104 240"
            },
            {
                "PROVISIONS": "",
                "Encours\n31/12/2023": "",
                "Dotations": "",
                "Reprises": "",
                "Autres\nvariations": "",
                "Encours\n30/06/2024": "84 192"
            },
            {
                "PROVISIONS": "",
                "Encours\n31/12/2023": "",
                "Dotations": "",
                "Reprises": "",
                "Autres\nvariations": "",
                "Encours\n30/06/2024": "-"
            },
            {
                "PROVISIONS": "",
                "Encours\n31/12/2023": "",
                "Dotations": "",
                "Reprises": "",
                "Autres\nvariations": "",
                "Encours\n30/06/2024": "747 596"
            },
            {
                "PROVISIONS": "",
                "Encours\n31/12/2023": "",
                "Dotations": "",
                "Reprises": "",
                "Autres\nvariations": "",
                "Encours\n30/06/2024": "90 130"
            },
            {
                "PROVISIONS": "",
                "Encours\n31/12/2023": "",
                "Dotations": "",
                "Reprises": "",
                "Autres\nvariations": "",
                "Encours\n30/06/2024": "182 321"
            },
            {
                "PROVISIONS": "",
                "Encours\n31/12/2023": "",
                "Dotations": "",
                "Reprises": "",
                "Autres\nvariations": "",
                "Encours\n30/06/2024": "-"
            },
            {
                "PROVISIONS": "TOTAL GENERAL",
                "Encours\n31/12/2023": "4 036 305",
                "Dotations": "414 600",
                "Reprises": "330 555",
                "Autres\nvariations": "23",
                "Encours\n30/06/2024": "4 120 373"
            }
        ],
        [],
        [],
        [
            {
                "": "ACTIF",
                "D ≤ 1 mois": "",
                "1 mois < D\n≤ 3 mois": "",
                "3 mois < D\n≤ 1 an": "",
                "1 an < D\n≤ 5 ans": "",
                "D > 5 ans": "",
                "TOTAL": ""
            },
            {
                "": "",
                "D ≤ 1 mois": "",
                "1 mois < D\n≤ 3 mois": "",
                "3 mois < D\n≤ 1 an": "",
                "1 an < D\n≤ 5 ans": "",
                "D > 5 ans": "",
                "TOTAL": "3 920 196"
            },
            {
                "": "",
                "D ≤ 1 mois": "",
                "1 mois < D\n≤ 3 mois": "",
                "3 mois < D\n≤ 1 an": "",
                "1 an < D\n≤ 5 ans": "",
                "D > 5 ans": "",
                "TOTAL": "52 220 643"
            },
            {
                "": "",
                "D ≤ 1 mois": "",
                "1 mois < D\n≤ 3 mois": "",
                "3 mois < D\n≤ 1 an": "",
                "1 an < D\n≤ 5 ans": "",
                "D > 5 ans": "",
                "TOTAL": "6 055 692"
            },
            {
                "": "",
                "D ≤ 1 mois": "",
                "1 mois < D\n≤ 3 mois": "",
                "3 mois < D\n≤ 1 an": "",
                "1 an < D\n≤ 5 ans": "",
                "D > 5 ans": "",
                "TOTAL": "-"
            },
            {
                "": "",
                "D ≤ 1 mois": "",
                "1 mois < D\n≤ 3 mois": "",
                "3 mois < D\n≤ 1 an": "",
                "1 an < D\n≤ 5 ans": "",
                "D > 5 ans": "",
                "TOTAL": "-"
            },
            {
                "": "TOTAL",
                "D ≤ 1 mois": "9 030 913",
                "1 mois < D\n≤ 3 mois": "5 415 443",
                "3 mois < D\n≤ 1 an": "7 461 164",
                "1 an < D\n≤ 5 ans": "16 291 211",
                "D > 5 ans": "23 997 800",
                "TOTAL": "62 196 532"
            },
            {
                "": "PASSIF",
                "D ≤ 1 mois": "",
                "1 mois < D\n≤ 3 mois": "",
                "3 mois < D\n≤ 1 an": "",
                "1 an < D\n≤ 5 ans": "",
                "D > 5 ans": "",
                "TOTAL": ""
            },
            {
                "": "",
                "D ≤ 1 mois": "",
                "1 mois < D\n≤ 3 mois": "",
                "3 mois < D\n≤ 1 an": "",
                "1 an < D\n≤ 5 ans": "",
                "D > 5 ans": "",
                "TOTAL": "812 974"
            },
            {
                "": "",
                "D ≤ 1 mois": "",
                "1 mois < D\n≤ 3 mois": "",
                "3 mois < D\n≤ 1 an": "",
                "1 an < D\n≤ 5 ans": "",
                "D > 5 ans": "",
                "TOTAL": "4 487 603"
            },
            {
                "": "",
                "D ≤ 1 mois": "",
                "1 mois < D\n≤ 3 mois": "",
                "3 mois < D\n≤ 1 an": "",
                "1 an < D\n≤ 5 ans": "",
                "D > 5 ans": "",
                "TOTAL": "3 501 597"
            },
            {
                "": "",
                "D ≤ 1 mois": "",
                "1 mois < D\n≤ 3 mois": "",
                "3 mois < D\n≤ 1 an": "",
                "1 an < D\n≤ 5 ans": "",
                "D > 5 ans": "",
                "TOTAL": "1 966 807"
            },
            {
                "": "TOTAL",
                "D ≤ 1 mois": "1 362 538",
                "1 mois < D\n≤ 3 mois": "2 219 293",
                "3 mois < D\n≤ 1 an": "4 335 023",
                "1 an < D\n≤ 5 ans": "2 154 555",
                "D > 5 ans": "697 572",
                "TOTAL": "10 768 981"
            }
        ],
        [],
        [
            {
                "Opérations diverses sur titres": "Créditeurs divers",
                "5 619": "993 049",
                "79 856": "721 968"
            },
            {
                "Opérations diverses sur titres": "",
                "5 619": "255 085",
                "79 856": ""
            },
            {
                "Opérations diverses sur titres": "",
                "5 619": "29 368",
                "79 856": ""
            },
            {
                "Opérations diverses sur titres": "",
                "5 619": "-",
                "79 856": ""
            },
            {
                "Opérations diverses sur titres": "",
                "5 619": "376 559",
                "79 856": ""
            },
            {
                "Opérations diverses sur titres": "",
                "5 619": "39",
                "79 856": ""
            },
            {
                "Opérations diverses sur titres": "",
                "5 619": "331 998",
                "79 856": ""
            },
            {
                "Opérations diverses sur titres": "Comptes de régularisation",
                "5 619": "1 045 445",
                "79 856": "945 487"
            },
            {
                "Opérations diverses sur titres": "",
                "5 619": "0",
                "79 856": ""
            },
            {
                "Opérations diverses sur titres": "",
                "5 619": "0",
                "79 856": ""
            },
            {
                "Opérations diverses sur titres": "",
                "5 619": "0",
                "79 856": ""
            },
            {
                "Opérations diverses sur titres": "",
                "5 619": "717",
                "79 856": ""
            },
            {
                "Opérations diverses sur titres": "",
                "5 619": "374 056",
                "79 856": ""
            },
            {
                "Opérations diverses sur titres": "",
                "5 619": "570 658",
                "79 856": ""
            },
            {
                "Opérations diverses sur titres": "",
                "5 619": "100 014",
                "79 856": ""
            },
            {
                "Opérations diverses sur titres": "Total",
                "5 619": "2 044 112",
                "79 856": "1 747 310"
            }
        ],
        [
            {
                "Monnaie\nde l’emprunt": "",
                "Montant\nen monnaie\nde l'emprunt": "",
                "Cours": "",
                "Taux": "",
                "Durée": "",
                "Condition de\nremboursement anticipé,\nsubordination et\nconvertibilité": "",
                "Montant de l’emprunt\nen monnaie nationale\n(ou contrevaleur en KDH)": "",
                "dont entreprises liées": "Montant N\n(en contrevaleur\nKDH)",
                "null": "Montant N-1\n(en contrevaleur\nKDH)",
                "dont autres apparentés": "Montant N\n(en contrevaleur\nKDH)"
            }
        ],
        [],
        [],
        [],
        [
            {
                "ACTIF": "Valeurs en caisse, Banques centrales, Trésor public, Service des\nchèques postaux",
                "30/06/2024": "33 929",
                "31/12/2023": "38 169"
            },
            {
                "ACTIF": "Créances sur les établissements de crédit et assimilés",
                "30/06/2024": "1 145",
                "31/12/2023": "46"
            },
            {
                "ACTIF": "Créances sur la clientèle",
                "30/06/2024": "2 174 967",
                "31/12/2023": "1 929 760"
            },
            {
                "ACTIF": "",
                "30/06/2024": "2 155 514",
                "31/12/2023": "1 917 836"
            },
            {
                "ACTIF": "",
                "30/06/2024": "-",
                "31/12/2023": "-"
            },
            {
                "ACTIF": "",
                "30/06/2024": "-",
                "31/12/2023": "-"
            },
            {
                "ACTIF": "",
                "30/06/2024": "19 453",
                "31/12/2023": "11 924"
            },
            {
                "ACTIF": "Titres de transaction et de placement",
                "30/06/2024": "-",
                "31/12/2023": "-"
            },
            {
                "ACTIF": "",
                "30/06/2024": "-",
                "31/12/2023": "-"
            },
            {
                "ACTIF": "Biens acquis dans le cadre de financements participatifs",
                "30/06/2024": "32 833",
                "31/12/2023": "73 798"
            },
            {
                "ACTIF": "Immobilisations données en Ijara",
                "30/06/2024": "-",
                "31/12/2023": "-"
            },
            {
                "ACTIF": "Titres d'investissement titres de participation et emplois divers",
                "30/06/2024": "-",
                "31/12/2023": "-"
            },
            {
                "ACTIF": "",
                "30/06/2024": "-",
                "31/12/2023": "-"
            },
            {
                "ACTIF": "",
                "30/06/2024": "-",
                "31/12/2023": "-"
            },
            {
                "ACTIF": "dépôts d'investissement et Wakala Istithmar placés",
                "30/06/2024": "-",
                "31/12/2023": "-"
            },
            {
                "ACTIF": "Autres actifs",
                "30/06/2024": "1 946",
                "31/12/2023": "763"
            },
            {
                "ACTIF": "TOTAL DE L'ACTIF",
                "30/06/2024": "2 244 821",
                "31/12/2023": "2 042 537"
            }
        ],
        [
            {
                "": "PRODUITS D'EXPLOITATION BANCAIRE",
                "30/06/2024": "33 183",
                "30/06/2023": "26 647"
            },
            {
                "": "",
                "30/06/2024": "-",
                "30/06/2023": "-"
            },
            {
                "": "",
                "30/06/2024": "32 238",
                "30/06/2023": "26 042"
            },
            {
                "": "",
                "30/06/2024": "-",
                "30/06/2023": "-"
            },
            {
                "": "",
                "30/06/2024": "-",
                "30/06/2023": "-"
            },
            {
                "": "",
                "30/06/2024": "-",
                "30/06/2023": "-"
            },
            {
                "": "",
                "30/06/2024": "945",
                "30/06/2023": "605"
            },
            {
                "": "",
                "30/06/2024": "-",
                "30/06/2023": "-"
            },
            {
                "": "",
                "30/06/2024": "-",
                "30/06/2023": "-"
            },
            {
                "": "CHARGES D'EXPLOITATION BANCAIRE",
                "30/06/2024": "562",
                "30/06/2023": "238"
            },
            {
                "": "",
                "30/06/2024": "1",
                "30/06/2023": "1"
            },
            {
                "": "",
                "30/06/2024": "-",
                "30/06/2023": "-"
            },
            {
                "": "",
                "30/06/2024": "-",
                "30/06/2023": "-"
            },
            {
                "": "",
                "30/06/2024": "-",
                "30/06/2023": "-"
            },
            {
                "": "",
                "30/06/2024": "344",
                "30/06/2023": "237"
            },
            {
                "": "",
                "30/06/2024": "217",
                "30/06/2023": "-"
            },
            {
                "": "PRODUIT NET BANCAIRE",
                "30/06/2024": "32 621",
                "30/06/2023": "26 409"
            },
            {
                "": "",
                "30/06/2024": "-",
                "30/06/2023": "-"
            },
            {
                "": "",
                "30/06/2024": "-",
                "30/06/2023": "-"
            },
            {
                "": "CHARGES GENERALES D'EXPLOITATION",
                "30/06/2024": "14 018",
                "30/06/2023": "13 881"
            },
            {
                "": "DOTATIONS AUX PROVISIONS ET PERTES SUR CREANCES\nIRRECOUVRABLES",
                "30/06/2024": "3 715",
                "30/06/2023": "1 941"
            },
            {
                "": "REPRISES DE PROVISIONS ET RECUPERATIONS SUR CREANCES\nAMORTIES",
                "30/06/2024": "3 151",
                "30/06/2023": "1 767"
            },
            {
                "": "RESULTAT COURANT",
                "30/06/2024": "18 039",
                "30/06/2023": "12 354"
            },
            {
                "": "RESULTAT AVANT IMPOTS SUR LES RESULTATS",
                "30/06/2024": "18 039",
                "30/06/2023": "12 354"
            },
            {
                "": "",
                "30/06/2024": "6 945",
                "30/06/2023": "1 491"
            },
            {
                "": "RESULTAT APRES IMPOT",
                "30/06/2024": "11 094",
                "30/06/2023": "10 864"
            }
        ],
        [
            {
                "PASSIF": "Banques centrales, Trésor public, Service des chèques postaux",
                "30/06/2024": "-",
                "31/12/2023": "-"
            },
            {
                "PASSIF": "Dettes envers les établissements de crédit et assimilés",
                "30/06/2024": "1 119 569",
                "31/12/2023": "1 015 316"
            },
            {
                "PASSIF": "",
                "30/06/2024": "-",
                "31/12/2023": "-"
            },
            {
                "PASSIF": "",
                "30/06/2024": "-",
                "31/12/2023": "-"
            },
            {
                "PASSIF": "",
                "30/06/2024": "-",
                "31/12/2023": "-"
            },
            {
                "PASSIF": "",
                "30/06/2024": "1 119 569",
                "31/12/2023": "1 015 316"
            },
            {
                "PASSIF": "Dépôts de la clientèle",
                "30/06/2024": "188 262",
                "31/12/2023": "179 662"
            },
            {
                "PASSIF": "",
                "30/06/2024": "158 071",
                "31/12/2023": "173 462"
            },
            {
                "PASSIF": "",
                "30/06/2024": "30 191",
                "31/12/2023": "6 200"
            },
            {
                "PASSIF": "Dettes envers la clientèle sur produits participatifs",
                "30/06/2024": "8 023",
                "31/12/2023": "12 485"
            },
            {
                "PASSIF": "",
                "30/06/2024": "8 023",
                "31/12/2023": "12 485"
            },
            {
                "PASSIF": "",
                "30/06/2024": "-",
                "31/12/2023": "-"
            },
            {
                "PASSIF": "",
                "30/06/2024": "-",
                "31/12/2023": "-"
            },
            {
                "PASSIF": "Autres passifs",
                "30/06/2024": "627 978",
                "31/12/2023": "579 974"
            },
            {
                "PASSIF": "Provisions pour risques et charges",
                "30/06/2024": "3 390",
                "31/12/2023": "3 390"
            },
            {
                "PASSIF": "Dépôts d'investissement et Wakala Istithmar reçus",
                "30/06/2024": "46 504",
                "31/12/2023": "-"
            },
            {
                "PASSIF": "Dotation en capital",
                "30/06/2024": "240 000",
                "31/12/2023": "240 000"
            },
            {
                "PASSIF": "Reports",
                "30/06/2024": "-",
                "31/12/2023": "-8 406"
            },
            {
                "PASSIF": "Résultat de l'exercice",
                "30/06/2024": "11 094",
                "31/12/2023": "20 116"
            },
            {
                "PASSIF": "TOTAL DU PASSIF",
                "30/06/2024": "2 244 821",
                "31/12/2023": "2 042 537"
            }
        ],
        [
            {
                "DETTES": "",
                "Secteur\npublic": "",
                "Secteur privé": "Entreprises\nfinancières",
                "null": "Autre clientèle",
                "Total\n30/06/2024": "",
                "Total\n31/12/2023": ""
            },
            {
                "DETTES": "DETTES ENVERS LA\nCLIENTELE SUR PRO-\nDUITS PARTICIPATIFS",
                "Secteur\npublic": "-",
                "Secteur privé": "-",
                "null": "8 023",
                "Total\n30/06/2024": "8 023",
                "Total\n31/12/2023": "12 485"
            },
            {
                "DETTES": "",
                "Secteur\npublic": "",
                "Secteur privé": "",
                "null": "",
                "Total\n30/06/2024": "8 023",
                "Total\n31/12/2023": ""
            },
            {
                "DETTES": "",
                "Secteur\npublic": "",
                "Secteur privé": "",
                "null": "",
                "Total\n30/06/2024": "-",
                "Total\n31/12/2023": ""
            },
            {
                "DETTES": "",
                "Secteur\npublic": "",
                "Secteur privé": "",
                "null": "",
                "Total\n30/06/2024": "-",
                "Total\n31/12/2023": ""
            },
            {
                "DETTES": "TOTAL",
                "Secteur\npublic": "-",
                "Secteur privé": "-",
                "null": "8 023",
                "Total\n30/06/2024": "8 023",
                "Total\n31/12/2023": "12 485"
            }
        ],
        [
            {
                "Biens": "",
                "Montant brut au\ndébut de l'exercice": "",
                "Marges sur opérations\nde l'exercice": "",
                "Quote-part reprise en\ncompte de résultat": "",
                "Quote-part constatée en\nrémunération réservée": "-",
                "Quote-part de marge\nabandonnée (1)": "-",
                "Montant brut\nà la fin de l'exercice": "-",
                "Encours des créances\nMourabaha à la fin\nde l’exercice": "-"
            },
            {
                "Biens": "",
                "Montant brut au\ndébut de l'exercice": "",
                "Marges sur opérations\nde l'exercice": "",
                "Quote-part reprise en\ncompte de résultat": "",
                "Quote-part constatée en\nrémunération réservée": "8 504",
                "Quote-part de marge\nabandonnée (1)": "1 169",
                "Montant brut\nà la fin de l'exercice": "545 794",
                "Encours des créances\nMourabaha à la fin\nde l’exercice": "2 155 514"
            },
            {
                "Biens": "",
                "Montant brut au\ndébut de l'exercice": "",
                "Marges sur opérations\nde l'exercice": "",
                "Quote-part reprise en\ncompte de résultat": "",
                "Quote-part constatée en\nrémunération réservée": "-",
                "Quote-part de marge\nabandonnée (1)": "-",
                "Montant brut\nà la fin de l'exercice": "-",
                "Encours des créances\nMourabaha à la fin\nde l’exercice": "-"
            },
            {
                "Biens": "",
                "Montant brut au\ndébut de l'exercice": "",
                "Marges sur opérations\nde l'exercice": "",
                "Quote-part reprise en\ncompte de résultat": "",
                "Quote-part constatée en\nrémunération réservée": "8 504",
                "Quote-part de marge\nabandonnée (1)": "1 169",
                "Montant brut\nà la fin de l'exercice": "545 794",
                "Encours des créances\nMourabaha à la fin\nde l’exercice": "2 155 514"
            },
            {
                "Biens": "TOTAL",
                "Montant brut au\ndébut de l'exercice": "486 562",
                "Marges sur opérations\nde l'exercice": "101 143",
                "Quote-part reprise en\ncompte de résultat": "32 238",
                "Quote-part constatée en\nrémunération réservée": "8 504",
                "Quote-part de marge\nabandonnée (1)": "1 169",
                "Montant brut\nà la fin de l'exercice": "545 794",
                "Encours des créances\nMourabaha à la fin\nde l’exercice": "2 155 514"
            }
        ],
        [
            {
                "BIENS": "",
                "Montant brut\nau debut de\nl’exercice": "",
                "Montant des\nacquisitions\nou transfert\nau cours\nde l’exercice": "",
                "Montant des cessions\nau cours de l’exercice": "Exploitation\nbancaire",
                "null": "Cumul à\nla fin de\nl'exercice",
                "Montant brut\nà la fin de\nl’exercice": "",
                "Provisions": "Montant des\nprovisions\nau debut de\nl'exercice",
                "Montant net\nà la fin de\nl’exercice": ""
            },
            {
                "BIENS": "",
                "Montant brut\nau debut de\nl’exercice": "",
                "Montant des\nacquisitions\nou transfert\nau cours\nde l’exercice": "",
                "Montant des cessions\nau cours de l’exercice": "",
                "null": "-",
                "Montant brut\nà la fin de\nl’exercice": "-",
                "Provisions": "-",
                "Montant net\nà la fin de\nl’exercice": "-"
            },
            {
                "BIENS": "",
                "Montant brut\nau debut de\nl’exercice": "",
                "Montant des\nacquisitions\nou transfert\nau cours\nde l’exercice": "",
                "Montant des cessions\nau cours de l’exercice": "",
                "null": "-",
                "Montant brut\nà la fin de\nl’exercice": "-",
                "Provisions": "-",
                "Montant net\nà la fin de\nl’exercice": "-"
            },
            {
                "BIENS": "",
                "Montant brut\nau debut de\nl’exercice": "",
                "Montant des\nacquisitions\nou transfert\nau cours\nde l’exercice": "",
                "Montant des cessions\nau cours de l’exercice": "",
                "null": "-",
                "Montant brut\nà la fin de\nl’exercice": "-",
                "Provisions": "-",
                "Montant net\nà la fin de\nl’exercice": "-"
            },
            {
                "BIENS": "",
                "Montant brut\nau debut de\nl’exercice": "",
                "Montant des\nacquisitions\nou transfert\nau cours\nde l’exercice": "",
                "Montant des cessions\nau cours de l’exercice": "",
                "null": "-",
                "Montant brut\nà la fin de\nl’exercice": "32 833",
                "Provisions": "-",
                "Montant net\nà la fin de\nl’exercice": "32 833"
            },
            {
                "BIENS": "",
                "Montant brut\nau debut de\nl’exercice": "",
                "Montant des\nacquisitions\nou transfert\nau cours\nde l’exercice": "",
                "Montant des cessions\nau cours de l’exercice": "",
                "null": "-",
                "Montant brut\nà la fin de\nl’exercice": "1 194",
                "Provisions": "-",
                "Montant net\nà la fin de\nl’exercice": "1 194"
            },
            {
                "BIENS": "",
                "Montant brut\nau debut de\nl’exercice": "",
                "Montant des\nacquisitions\nou transfert\nau cours\nde l’exercice": "",
                "Montant des cessions\nau cours de l’exercice": "",
                "null": "-",
                "Montant brut\nà la fin de\nl’exercice": "31 639",
                "Provisions": "-",
                "Montant net\nà la fin de\nl’exercice": "31 639"
            },
            {
                "BIENS": "",
                "Montant brut\nau debut de\nl’exercice": "",
                "Montant des\nacquisitions\nou transfert\nau cours\nde l’exercice": "",
                "Montant des cessions\nau cours de l’exercice": "",
                "null": "-",
                "Montant brut\nà la fin de\nl’exercice": "-",
                "Provisions": "-",
                "Montant net\nà la fin de\nl’exercice": "-"
            },
            {
                "BIENS": "",
                "Montant brut\nau debut de\nl’exercice": "",
                "Montant des\nacquisitions\nou transfert\nau cours\nde l’exercice": "",
                "Montant des cessions\nau cours de l’exercice": "",
                "null": "-",
                "Montant brut\nà la fin de\nl’exercice": "-",
                "Provisions": "-",
                "Montant net\nà la fin de\nl’exercice": "-"
            }
        ],
        [],
        []
    ]
}