{
    "text": "RÉSULTATS ANNUELS EXERCICE CLOS LE 31 DÉCEMBRE 2023\nCOMPTE DE PRODUITS ET CHARGES (Hors Taxes)\n(Montants en dhs) Exercice du 1er janvier 2023 au 31 décembre 2023\nOPÉRATIONS\nConcernant TOTAUX DE TOTAUX DE\nPropres à\nNATURE les exercices L’EXERCICE L’EXERCICE\nl’exercice\nprécédents PRÉCÉDENT\n(1) (2) 3= 1 + 2\nN\nO\nI\nT A T I\nO L P\nX E\nI Produits d’exploitation 541 044 365,25 541 044 365,25 503 670 276,02\nVentes de marchandises (en l’état) 539 246 594,47 539 246 594,47 493 257 977,44\nVentes de biens et services produits 1 583 297,96 1 583 297,96 3 327 948,62\nChiffre d’affaires 540 829 892,43 540 829 892,43 496 585 926,06\nVariation de stocks de produits ( + ou - ) (1)\nI mmobilisations produites par l’entreprise pour\nelle-même\nSubventions d’exploitation\nAutres produits d’exploitation\nReprises d’exploitation : transferts de charges 214 472,82 214 472,82 7 084 349,96 TOTAL I 541 044 365,25 541 044 365,25 503 670 276,02\nII Charges d’exploitation 511 873 964,21 25 098,52 511 899 062,73 477 326 370,67 Achats revendus (2) de marchandises 482 256 911,86 482 256 911,86 442 191 680,01\nAchats consommés (2) de matières et fournitures 3 435 783,76 25 098,52 3 460 882,28 3 253 595,33\nAutres charges externes 13 762 029,40 13 762 029,40 18 937 638,50\nImpôts et taxes 118 243,87 118 243,87 123 283,03\nCharges de personnel 10 502 940,98 10 502 940,98 10 951 720,10\nAutres charges d’exploitation 500 000,00 500 000,00\nDotations d’exploitation 1 298 054,34 1 298 054,34 1 868 453,70\nTOTAL II 511 873 964,21 25 098,52 511 899 062,73 477 326 370,67\nIII RÉSULTAT D’EXPLOITATION ( I - II ) 29 145 302,52 26 343 905,35\nR\nE\nI\nC\nN\nA\nN\nI\nF\nBILAN ACTIF\nEXERCICE EXERCICE\n(Montants en dhs) Amortissement PRÉCÉDENT\nBrut et provisions Net Net\nIV Produits financiers 6 182 379,92 6 182 379,92 3 207 050,06\nProduits des titres de participation et autres titres\nimmobilisés\nGains de change 4 378 175,21 4 378 175,21 2 798 367,85\nIntérêts et autres produits financiers 987 302,05 987 302,05 4 780,42\nReprises financières : transferts de charges 816 902,66 816 902,66 403 901,79\nTOTAL IV 6 182 379,92 6 182 379,92 3 207 050,06\nV Charges financières 13 311 361,62 13 311 361,62 20 973 153,23\nCharges d’intérêts 10 550 985,28 10 550 985,28 6 023 635,10\nPertes de change 2 278 363,32 2 278 363,32 14 219 975,45\nAutres charges financières\nDotations financières 482 013,02 482 013,02 729 542,68\nTOTAL V 13 311 361,62 13 311 361,62 20 973 153,23\nVI RÉSULTAT FINANCIER ( IV - V ) -7 128 981,70 -17 766 103,17\nVII RÉSULTAT COURANT ( III + VI ) 22 016 320,82 8 577 802,18\nÉ S\nI L\nI B\nO\nM\nM\nI\nF\nI T\nC A\nImmobilisations en non valeurs (A) 2 697 069,61 1 499 117,62 1 197 951,99 1 268 688,08\nFrais préliminaires 208 972,80 83 589,12 125 383,68 167 178,24\nCharges à répartir sur plusieurs exercices 2 488 096,81 1 415 528,50 1 072 568,31 1 101 509,84\nPrimes de remboursement des obligations\nImmobilisations incorporelles (B) 1 871 128,27 1 255 046,16 616 082,11 798 479,63\nImmobilisations en recherche et développement\nBrevets, marques, droits et valeurs similaires\nFonds commercial Autres immobilisations incorporelles 1 871 128,27 1 255 046,16 616 082,11 798 479,63\nImmobilisations corporelles (C) 3 666 440,15 2 228 445,16 1 437 994,99 1 501 838,16\nTerrains\nConstructions\nInstallations techniques, matériel et outillage 508 280,00 339 975,30 168 304,70 204 251,56\nMatériel de transport 214 213,39 73 185,20 141 028,19 165 123,64\nMobilier, matériel de bureau et aménagements divers 2 943 946,76 1 815 284,66 1 128 662,10 1 132 462,96\nAutres immobilisations corporelles\nImmobilisations corporelles en cours\nImmobilisations financières (D) 320 200,00 320 200,00 320 200,00 Prêts immobilisés\nAutres créances financières 220 200,00 220 200,00 220 200,00\nTitres de participation 100 000,00 100 000,00 100 000,00\nAutres titres immobilisés\nÉcarts de conversion - Actif (E)\nDiminution des créances immobilisées\nAugmentation des dettes de financement\nTOTAL I ( A + B + C + D + E ) 8 554 838,03 4 982 608,94 3 572 229,09 3 889 205,87\nT\nN A\nL U\nC\nR I C\nF I\nT C\nA\nStocks (F) 89 361 830,53 97 463,36 89 264 367,17 119 384 853,11\nMarchandises 89 361 830,53 97 463,36 89 264 367,17 119 384 853,11\nMatières et fournitures consommables\nProduits en cours\nProduits intermédiaires et produits résiduels\nProduits finis Créances de l’actif circulant (G) 345 363 235,28 12 536 081,64 332 827 153,64 272 160 412,58\nFournisseurs débiteurs, avances & acomptes 8 003 745,93 8 003 745,93 6 035 941,39\nClients et comptes rattachés 210 531 936,23 12 536 081,64 197 995 854,59 164 263 430,10 Personnel\nÉtat 70 853 245,69 70 853 245,69 70 104 648,16 Compte d’associés\nAutres débiteurs\nComptes de régularisation - Actif 55 974 307,43 55 974 307,43 31 756 392,93\nTitres et valeurs de placement (H)\nÉcarts de conversion - Actif (I) (Eléments circulants) 394 653,04 394 653,04 729 542,80\nTOTAL II ( F + G + H + I ) 435 119 718,85 12 633 545,00 422 486 173,85 392 274 808,49\nEIREROSÉRT\nBILAN PASSIF\nEXERCICE\n(Montants en dhs) EXERCICE\nPRÉCÉDENT\nTrésorerie - Actif 10 446 121,29 10 446 121,29 17 052 068,81\nChèques et valeurs à encaisser\nBanques, T.G et C.C.P 10 427 568,90 10 427 568,90 17 038 823,02\nCaisses, Régies d’avances et accréditifs 18 552,39 18 552,39 13 245,79\nTOTAL III 10 446 121,29 10 446 121,29 17 052 068,81\nTOTAL GÉNÉRAL ( I + II + III ) 454 120 678,17 17 616 153,94 436 504 524,23 413 216 083,17\nT\nN E N\nA\nM\nR\nE\nP\nT\nN\nE\nM\nE C N\nA\nN\nI F\nCapitaux propres 171 233 239,00 162 429 915,14\nCapital social ou personnel (1) 99 811 000,00 99 811 000,00\nMoins : actionnaires, capital souscrit non appelé\nCapital appelé\ndont versé\nPrimes d’émission, de fusion, d’apport 35 612 905,04 35 612 905,04\nÉcarts de réévaluation Réserve légale 3 197 382,99 2 990 660,37\nAutres réserves\nReport à nouveau (2) 13 827 527,11 19 880 897,24\nRésultats nets en instance d’affectation (2)\nRésultat net de l’exercice (2) 18 784 423,86 4 134 452,49\nTotal des capitaux propres (A) 171 233 239,00 162 429 915,14\nCapitaux propres assimilés (B)\nSubventions d’investissement\nProvisions réglementées\nDettes de financement (C) 4 164 942,77 6 092 742,27 Emprunts obligataires\nAutres dettes de financement 4 164 942,77 6 092 742,27\nProvisions durables pour risques et charges (D) Provisions pour risques\nProvisions pour charges\nÉcarts de conversion - Passif (E)\nAugmentation des créances immobilisées\nDiminution des dettes de financement\nTOTAL I ( A + B + C + D + E ) 175 398 181,77 168 522 657,41\nT N\nA L U\nC\nR I C\nF I S S\nA P\nDettes du passif circulant (F) 114 735 315,79 90 606 781,33\nFournisseurs et comptes rattachés 74 298 593,66 54 186 644,89\nClients créditeurs, avances et acomptes 2 969 583,06 4 182 866,34\nPersonnel 1 088 537,14 913 546,13 Organismes sociaux 329 860,27 355 547,49\nÉtat 34 914 004,81 30 138 712,42 Comptes d’associés\nAutres créanciers Comptes de régularisation - Passif 1 134 736,85 829 464,06\nAutres provisions pour risques et charges (G) 394 653,04 729 542,68\nÉcarts de conversion - Passif ( Éléments circulants ) (H) 187 097,61 1 531 934,89\nTOTAL II ( F + G + H ) 115 317 066,44 92 868 258,90\nEIREROSÉRT Trésorerie - Passif 145 789 276,02 151 825 166,86\nCrédits d’escompte 27 055 690,01 43 634 795,43\nCrédits de trésorerie\nBanques (soldes créditeurs) 118 733 586,01 108 190 371,43\nTOTAL III 145 789 276,02 151 825 166,86\nTOTAL GÉNÉRAL ( I + II + III ) 436 504 524,23 413 216 083,17\nCOMPTE DE PRODUITS ET CHARGES (Hors Taxes) Suite\n(Montants en dhs) Exercice du 1er janvier 2023 au 31 décembre 2023\nOPÉRATIONS\nConcernant TOTAUX DE TOTAUX DE\nPropres à\nNATURE les exercices L’EXERCICE L’EXERCICE\nl’exercice\nprécédents PRÉCÉDENT\n(1) (2) 3= 1 + 2\nT\nN\nA\nR\nU O C\nN O\nN\n(1) Capital personnel debiteur\n(2) Beneficiaire (+) . deficitaire (-)\nVIII Produits non courants 71 464,69 71 464,69 210 267,19\nProduits des cessions d’immobilisations 52 500,00 52 500,00\nSubventions d’équilibre\nR eprises sur subventions\nd’investissement\nAutres produits non courants 18 964,69 18 964,69 210 267,19\nR eprises non courantes : transferts de\ncharges\nTOTAL VIII 71 464,69 71 464,69 210 267,19 IX Charges non courantes 374 491,45 0,20 374 491,65 1 456 366,88\nValeurs nettes d’amortissement des immobilisations cédées\nSubventions accordées\nAutres charges non courantes 374 491,45 0,20 374 491,65 1 456 366,88\nDotations non courantes aux\namortissements et aux provisions\nTOTAL IX 374 491,45 0,20 374 491,65 1 456 366,88\nX RÉSULTAT NON COURANT ( VIII - IX ) -303 026,96 -1 246 099,69\nXI RÉSULTAT AVANT IMPÔTS ( VII + X ) 21 713 293,86 7 331 702,49\nXII IMPÔTS SUR LES RÉSULTATS 2 928 870,00 2 928 870,00 3 197 250,00\nXIII RÉSULTAT NET ( XI - XII ) 18 784 423,86 4 134 452,49\nXIV TOTAL DES PRODUITS ( I + IV + VIII ) 547 298 209,86 507 087 593,27\nTOTAL DES CHARGES ( II + V + IX XV 528 513 786,00 502 953 140,78\n+ XII )\nRÉSULTAT NET ( total produits - total XVI 18 784 423,86 4 134 452,49\ncharges )\n1) Variation de stocks : stock final - stock initial ; augmentation (+) diminution (-)\n2) Achats revendus ou consommés : achats - variation de stock\nRapport Financier Annuel 2023\nLe Rapport Financier Annuel 2023, comprenant le jeu complet des états financiers sociaux et\nconsolidés du Groupe au 31 décembre 2023, sera mis en ligne à partir du 30 avril 2024 sur le site\ninternet de Disty, à l’adresse suivante : https://disty.ma/infos-financieres\ndisty 12, Boulevard Mohamed Abdou,\nwww.disty.ma\nQuartier Maarif, Casablanca.\ndisty-technologies\nRéponse d’audit :\nDans le cadre de nos diligences, nous avons examiné les principes d’identification des créances\ndouteuses et les méthodes de dépréciation des créances clients, en procédant à :\n‒ L’analyse des hypothèses retenues pour calculer les provisions pour dépréciation des créances\nclients, notamment à travers l’examen de la balance âgée et de l’analyse des retards de paiement ;\n‒ L’analyse des paiements reçus après la date de clôture pour les créances clients les plus\nsignificatives ;\n‒ La vérification du calcul de la provision pour dépréciation afin de s’assurer de sa conformité avec les\nrègles de provisionnement définies par la société ;\n‒ La circularisation des avocats et l’analyse des réponses reçues, afin d’identifier d’éventuelles\ndifficultés de recouvrement qui n’auraient pas donné lieu au traitement comptable approprié.\n Dépréciation des stocks de marchandises\nRisque identifié\nAu 31 décembre 2023, la valeur nette des stocks de marchandises s’élève à 89 264 KMAD représentant\n20% du total bilan de la société. Une dépréciation sur les stocks est constatée sur la base de leur\nobsolescence et s'ils sont endommagés.\nNous avons considéré ce sujet comme un point clé de l’audit pour l’exercice 2023, compte tenu du\ncaractère significatif du montant des stocks dans le bilan au 31 décembre 2023 et du degré de jugement\ninhérent à certaines hypothèses relatives à l'obsolescence qui sous-tendent l'évaluation de la\ndépréciation des stocks.\nRéponse d’audit :\nDans le cadre de nos diligences, nous avons procédé à :\nRÉSULTATS ANNUELS ‒ L’examen dEes XdonEnéRes Cet dIeCs hyEpo thCèseLs OreteSnue sL pEar la3 D1ire cDtionÉ poCur EdépMréciBer lRes Estoc k2s 0au 23\nregard de leurs perspectives d'écoulement et de leur ancienneté ;\n‒ La prise de connaissance des procédures de contrôle interne mises en place pour identifier les\narticles à rotation lente ;\n‒ La vérification du calcul de la provision pour dépréciation.\nResponsabilités de la direction et des responsables de la gouvernance à l’égard des états de synthèse\nLa direction est responsable de la préparation et de la présentation fidèle des états de synthèse, conformément\nau référentiel comptable en vigueur au Maroc, ainsi que du contrôle interne qu'elle considère comme\nnécessaire pour permettre la préparation d'états de synthèse exempts d'anomalies significatives, que celles-\nci résultent de fraudes ou d'erreurs.\nLors de la préparation des états de synthèse, c’est à la direction qu’il incombe d’évaluer la capacité de la\nAvia Business Center, 44,, RRuuee MMaaaattiiJJaazzoouullii ((eexx rruuee FFrriiooll)) s o c i é t é à p o u r s u i v r e s o n e x p lo itation, de communiquer, le cas échéant, les questions se rapportant à la\nB Cd aS said bi\nl\naA nb cd ae -ll a Mh\na\nC roh ce rif A MMn aaf rra oo- ccCC aassaabbllaannccaa continuité de l’exploitation et d’appliquer le principe comptable de continuité d’exploitation, sauf si la direction\na l’intention de liquider la société ou de cesser son activité ou si aucune autre solution réaliste ne s’offre à elle.\nIl incombe aux responsables de la gouvernance de surveiller le processus d’information financière de la\nAux Actionnaires de la société société.\nDISTY TECHNOLOGIES S.A.\n12, BBdd MMoohhaammeedd AAbbddoouu,, QQuuaarrttiieerr PPaallmmiieerr,, MMaaaarriiff R esponsabilités de l’auditeur à l’égard de l’audit des états de synthèse\nCasablanca.\nN os objectifs sont d’obtenir l’assurance raisonnable que les états de synthèse pris dans leur ensemble sont\nexempts d’anomalies significatives, que celles-ci résultent de fraudes ou d’erreurs et de délivrer un rapport de\nRAPPORT GENERAL DES CCOOMMMMIISSSSAAIIRREESS AAUUXX CCOOMMPTES l’auditeur contenant notre opinion. L’assurance raisonna2 ble correspond à un niveau élevé d’assurance, qui ne\nEXERCICE DU 1ER JJAANNVVIIEERR AAUU 3311 DDEECCEEMMBBRE 2023 garantit toutefois pas qu’un audit réalisé conformémen t aux normes de la profession au Maroc permettra\ntoujours de détecter toute anomalie significative qui pourrait exister. Les anomalies peuvent résulter de fraudes\nou d’erreurs et elles sont considérées comme significatives lorsqu’il est raisonnable de s’attendre à ce que,\nindividuellement ou collectivement, elles puissent influer sur les décisions économiques que les utilisateurs\nAAUUDDIITT DDEESS EETTAATTSS DDEE SSYYNNTTHHEESSEE\ndes états de synthèse prennent en se fondant sur ceux-ci.\nDans le cadre d’un audit réalisé conformément aux normes de la profession au Maroc, nous exerçons notre\nOpinion jugement professionnel et faisons preuve d’esprit critique tout au long de cet audit. En outre :\nCCCooonnnfffooorrrmmmééémmmeeennnttt ààà lllaaa mmmiiissssssiiiooonnn qqquuuiii nnnooouuusss aaa ééétttééé cccooonnnfffiiiéééeee pppaaarrr vvvoootttrrreee AAAsssssseeemmmbbbllléééeee GGGééénnnééérrraaallleee,,, nnnooouuusss aaavvvooonnnsss eeeffffffeeeccctttuuuééé - nous identifions et évaluons les risques que les états de synthèse comportent des anomalies\nl'audit des états de synthèse ci-jjooiinnttss ddee llaa ssoocciiééttéé Disty Technologies S.A, qquuii ccoommpprreennnneent le bilan au significatives, que celles-ci résultent de fraudes ou d’erreurs, concevons et mettons en œuvre des\n31 décembre 2023,, llee ccoommppttee ddee pprroodduuiittss eett cchhaarrggeess,, ll''ééttaatt ddeess ssoollddeess ddee ggeessttiioonn,, llee ttaabblleeaauu ddee ffiinnaanncceemmeenntt procédures d’audit en réponse à ces risques, et réunissons des éléments probants suffisants et\nppoouurr ll’’eexxeerrcciiccee ccllooss àà cceettttee ddaattee,, aaiinnssii qquuee ll’’ééttaatt ddeess iinnffoorrmmaattiioonnss ccoommpplléémmeennttaaiirreess ((EETTIICC))..CCeess ééttaattss ddee appropriés pour fonder notre opinion. Le risque de non-détection d’une anomalie significative résultant\nssyynntthhèèssee ffoonntt rreessssoorrttiirr uunn mmoonnttaanntt ddee ccaappiittaauuxx pprroopprreess eett aassssiimmiillééss ddee 117711 223333 223399MAD dont un bénéfice d’une fraude est plus élevé que celui d’une anomalie significative résultant d’une erreur, car la fraude\nnet de 18 784 424MAD. peut impliquer la collusion, la falsification, les omissions volontaires, les fausses déclarations ou le\ncontournement du contrôle interne ;\nNNoouuss cceerrttiiffiioonnss qquuee lleess ééttaattss ddee ssyynntthhèèssee cciittééss aauu pprreemmiieerr ppaarraaggrraapphhee ccii-ddeessssuuss ssoonntt rréégguulliieerrss eett ssiinnccèèrreess eett\ndddooonnnnnneeennnttt,,, dddaaannnsss tttooouuusss llleeeuuurrrsss aaassspppeeeccctttsss sssiiigggnnniiifffiiicccaaatttiiifffsss,,, uuunnneee iiimmmaaagggeee fffiiidddèèèllleee ddduuu rrrééésssuuullltttaaattt dddeeesss ooopppééérrraaatttiiiooonnnsss dddeee lll’’’eeexxxeeerrrccciiiccceee - nous acquérons une compréhension des éléments du contrôle interne pertinents pour l’audit afin de\nécoulé aaiinnssii qquuee ddee llaa ssiittuuaattiioonn ffiinnancière et du patrimoine de la société DDiissttyy TTeecchhnnoollooggiieessS.A au 31 concevoir des procédures d’audit appropriées aux circonstances, et non dans le but d’exprimer une\ndécembre 2023, ccoonnffoorrmméémmeenntt aauu rrééfféérreennttiieell ccoommppttaabbllee en vigueur au Maroc. opinion sur l’efficacité du contrôle interne de la société ;\n- nous apprécions le caractère approprié des méthodes comptables retenues et le caractère\nFondement de l’opinion raisonnable des estimations comptables faites par la direction, de même que des informations y\nNNoouuss aavvoonnss eeffffeeccttuuéé nnoottrree aauuddiitt sseelloonn lleess NNoorrmmeess ddee llaa PPrrooffeessssiioonn aauu MMaarroocc.. LLeess rreessppoonnssaabbiilliittééss qquuii nnoouuss afférentes fournies par cette dernière ;\niiinnncccooommmbbbeeennnttt eeennn vvveeerrrtttuuu dddeee ccceeesss nnnooorrrmmmeeesss sssooonnnttt pppllluuusss aaammmpppllleeemmmeeennnttt dddééécccrrriiittteeesss dddaaannnsss lllaaa ssseeeccctttiiiooonnn ««« RRReeessspppooonnnsssaaabbbiiillliiitttééésss dddeee - nous tirons une conclusion quant au caractère approprié de l’utilisation par la direction du principe\nlll’’’aaauuudddiiittteeeuuurrr ààà lll’’’ééégggaaarrrddd dddeee lll’’’aaauuudddiiittt dddeeesss ééétttaaatttsss dddeee sssyyynnnttthhhèèèssseee »»» ddduuu ppprrréééssseeennnttt rrraaappppppooorrrttt... NNNooouuusss sssooommmmmmeeesss iiinnndddééépppeeennndddaaannntttsss dddeee lllaaa comptable de continuité d’exploitation et, selon les éléments probants obtenus, quant à l’existence ou\nsociété cccooonnnfffooorrrmmmééémmmeeennnttt aaauuuxxx rrrèèègggllleeesss dddeee dddéééooonnntttooolllooogggiiieee qqquuuiii sss’’’aaappppppllliiiqqquuueeennnttt ààà lll’’’aaauuudddiiittt dddeeesss ééétttaaatttsss dddeee sssyyynnnttthhhèèèssseee aaauuu MMMaaarrroooccc eeettt non d’une incertitude significative liée à des événements ou situations susceptibles de jeter un doute\nnnnooouuusss nnnooouuusss sssooommmmmmeeesss aaacccqqquuuiiittttttééésss dddeeesss aaauuutttrrreeesss rrreeessspppooonnnsssaaabbbiiillliiitttééésss dddéééooonnntttooolllooogggiiiqqquuueeesss qqquuuiii nnnooouuusss iiinnncccooommmbbbeeennnttt ssseeelllooonnn ccceeesss important sur la capacité de la société à poursuivre son exploitation. Si nous concluons à l’existence\nrrèègglleess.. NNoouuss eessttiimmoonnss qquuee lleess éélléémmeennttss pprroobbaannttss qquuee nnoouuss aavvoonnss oobbtteennuuss ssoonntt ssuuffffiissaannttss eett aapppprroopprriiééss ppoouurr d’une incertitude significative, nous sommes tenus d’attirer l’attention des lecteurs de notre rapport sur\nfonder notre opinion d’audit. les informations fournies dans les états de synthèse au sujet de cette incertitude ou, si ces informations\nne sont pas adéquates, d’exprimer une opinion modifiée. Nos conclusions s’appuient sur les éléments\nQuestions clés de l’audit probants obtenus jusqu’à la date de notre rapport. Des événements ou situations futurs pourraient par\nLLLeeesss qqquuueeessstttiiiooonnnsss ccclllééésss dddeee lll’’’aaauuudddiiittt sssooonnnttt llleeesss qqquuueeessstttiiiooonnnsss qqquuuiii,,, ssseeelllooonnn nnnoootttrrreee jjjuuugggeeemmmeeennnttt ppprrrooofffeeessssssiiiooonnnnnneeelll,,, ooonnnttt ééétttééé llleeesss pppllluuusss ailleurs amener la société à cesser son exploitation ;\niimmppoorrttaanntteess ddaannss ll’’aauuddiitt ddeess ééttaattss ddee ssyynntthhèèssee ddee llaa ppéérriiooddee ccoonnssiiddéérrééee.. CCeess qquueessttiioonnss oonntt ééttéé ttrraaiittééeess ddaannss - nous évaluons la présentation d’ensemble, la structure et le contenu des états de synthèse, y compris\nllleee cccooonnnttteeexxxttteee dddeee nnnoootttrrreee aaauuudddiiittt dddeeesss ééétttaaatttsss dddeee sssyyynnnttthhhèèèssseee ppprrriiisss dddaaannnsss llleeeuuurrr eeennnssseeemmmbbbllleee eeettt aaauuuxxx fffiiinnnsss dddeee lllaaa fffooorrrmmmaaatttiiiooonnn dddeee nnnoootttrrreee les informations fournies dans l’ETIC, et apprécions si les états de synthèse représentent les\nopinion sur ceux-ccii,, eett nnoouuss nn’’eexxpprriimmoonnss ppaass uunnee ooppiinniioonn ddiissttiinnccttee ssuurr cceess qquueessttiioonnss.. opérations et événements sous-jacents d’une manière propre à donner une image fidèle.\n Dépréciation ddeess ccrrééaanncceess cclliieennttss Nous communiquons aux responsables de la gouvernance notamment l’étendue et le calendrier prévus des\ntravaux d’audit et nos constatations importantes, y compris toute déficience importante du contrôle interne que\nRisque identifié nous aurions relevée au cours de notre audit.\nAu 31 décembre 2023,, llaa vvaalleeuurr nettedes créances clients s’élève à 197996 KKMAD représentant 45%\ndu total bilan de la société. LLLaaa DDDiiirrreeeccctttiiiooonnn ééévvvaaallluuueee llleeesss cccrrréééaaannnccceeesss cccllliiieeennntttsss ssseeelllooonnn llleeesss mmmooodddaaallliiitttééésss eeexxxpppooossséééeeesss dddaaannnsss\nla note A1 dddeee lll’’’ééétttaaattt dddeeesss iiinnnfffooorrrmmmaaatttiiiooonnnsss cccooommmppplllééémmmeeennntttaaaiiirrreeesss (((EEETTTIIICCC)))...LLLaaa dddéééppprrréééccciiiaaatttiiiooonnn fffaaaiiittt lll’’’ooobbbjjjeeettt ddd’’’uuunnneee\naapppprréécciiaattiioonn aauu ccaass ppaarr ccaass eenn ffoonnccttiioonn ddeess rriissqquueess eennccoouurruuss..\nEn conséquence, nous aaavvvooonnnsss cccooonnnsssiiidddééérrrééé ccceee sssuuujjjeeettt cccooommmmmmeee uuunnn pppoooiiinnnttt ccclllééé dddeee lll’’’aaauuudddiiitttpour l’exercice 2023,\ndans un contexte ééccoonnoommiiqquuee ddiiffffiicciillee, compte tenu dee ll’’iimmppoorrttaannccee ddee ccee ppoossttee ddaannss lleess ééttaattss ddee\nsynthèse eett dduu nniivveeaauu ddee jjuuggeemmeenntt rreeqquuiiss ppaarr llaa ddiirreeccttiioonn ppoouurr ll’’eessttiimmaattiioonn ddeess pprroovisions.\nRéponse d’audit :\nDans le cadre de nos diligences, nous avons examiné les principes d’identification des créances\ndouteuses et les méthodes de dépréciation des c1ré ances clients, en procédant à :\n‒ L’analyse des hypothèses retenues pour calculer les provisions pour dépréciation des créances 3\nclients, notamment à travers l’examen de la balance âgée et de l’analyse des retards de paiement ;\n‒ L’analyse des paiements reçus après la date de clôture pour les créances clients les plus\nsignificatives ;\n‒ La vérification du calcul de la provision pour dépréciation afin de s’assurer de sa conformité avec les\nrègles de provisionnement définies par la société ;\n‒ La circularisation des avocats et l’analyse des réponses reçues, afin d’identifier d’éventuelles\ndifficultés de recouvrement qui n’auraient pas donné lieu au traitement comptable approprié.\n Dépréciation des stocks de marchandises\nRisque identifié\nAu 31 décembre 2023, la valeur nette des stocks de marchandises s’élève à 89 264 KMAD représentant\n20% du total bilan de la société. Une dépréciation sur les stocks est constatée sur la base de leur\nobsolescence et s'ils sont endommagés.\nNous avons considéré ce sujet comme un point clé de l’audit pour l’exercice 2023, compte tenu du\ncaractère significatif du montant des stocks dans le bilan au 31 décembre 2023 et du degré de jugement\ninhérent à certaines hypothèses relatives à l'obsolescence qui sous-tendent l'évaluation de la\ndépréciation des stocks.\nRéponse d’audit :\nDans le cadre de nos diligences, nous avons procédé à :\n‒ L’examen des données et des hypothèses retenues par la Direction pour déprécier les stocks au\nregard de leurs perspectives d'écoulement et de leur ancienneté ;\n‒ La prise de connaissance des procédures de contrôle interne mises en place pour identifier les\narticles à rotation lente ;\n‒ La vérification du calcul de la provision pour dépréciation.\nResponsabilités de la direction et des responsables de la gouvernance à l’égard des états de synthèse\nLa direction est responsable de la préparation et de la présentation fidèle des états de synthèse, conformément\nau référentiel comptable en vigueur au Maroc, ainsi que du contrôle interne qu'elle considère comme\nnécessaire pour permettre la préparation d'états de synthèse exempts d'anomalies significatives, que celles-\nci résultent de fraudes ou d'erreurs.\nLors de la préparation des états de synthèse, c’est à la direction qu’il incombe d’évaluer la capacité de la\nsociété à poursuivre son exploitation, de communiquer, le cas échéant, les questions se rapportant à la\ncontinuité de l’exploitation et d’appliquer le principe comptable de continuité d’exploitation, sauf si la direction\na l’intention de liquider la société ou de cesser son activité ou si aucune autre solution réaliste ne s’offre à elle.\nIl incombe aux responsables de la gouvernance de surveiller le processus d’information financière de la\nsociété.\n2 disty 12, Boulevard Mohamed Abdou,\nwww.disty.ma\nQuartier Maarif, Casablanca.\ndisty-technologies",
    "tables": [
        [
            {
                "BILAN ACTIF": "(Montants en dhs)",
                "null": "EXERCICE\nPRÉCÉDENT\nNet"
            },
            {
                "BILAN ACTIF": "",
                "null": ""
            },
            {
                "BILAN ACTIF": "É\nS\nI\nL\nI\nB\nO\nM\nM\nI\nF\nI\nT\nC\nA",
                "null": "1 268 688,08\n167 178,24\n1 101 509,84\n798 479,63\n798 479,63\n1 501 838,16\n204 251,56\n165 123,64\n1 132 462,96\n320 200,00\n220 200,00\n100 000,00"
            },
            {
                "BILAN ACTIF": "",
                "null": ""
            },
            {
                "BILAN ACTIF": "",
                "null": ""
            },
            {
                "BILAN ACTIF": "",
                "null": ""
            },
            {
                "BILAN ACTIF": "",
                "null": ""
            },
            {
                "BILAN ACTIF": "",
                "null": ""
            },
            {
                "BILAN ACTIF": "",
                "null": ""
            },
            {
                "BILAN ACTIF": "",
                "null": ""
            },
            {
                "BILAN ACTIF": "",
                "null": ""
            },
            {
                "BILAN ACTIF": "",
                "null": ""
            },
            {
                "BILAN ACTIF": "",
                "null": ""
            },
            {
                "BILAN ACTIF": "",
                "null": ""
            },
            {
                "BILAN ACTIF": "",
                "null": ""
            },
            {
                "BILAN ACTIF": "",
                "null": ""
            },
            {
                "BILAN ACTIF": "",
                "null": ""
            },
            {
                "BILAN ACTIF": "",
                "null": ""
            },
            {
                "BILAN ACTIF": "",
                "null": ""
            },
            {
                "BILAN ACTIF": "",
                "null": ""
            },
            {
                "BILAN ACTIF": "",
                "null": ""
            },
            {
                "BILAN ACTIF": "",
                "null": ""
            },
            {
                "BILAN ACTIF": "",
                "null": ""
            },
            {
                "BILAN ACTIF": "",
                "null": ""
            },
            {
                "BILAN ACTIF": "",
                "null": ""
            },
            {
                "BILAN ACTIF": "",
                "null": ""
            },
            {
                "BILAN ACTIF": "",
                "null": ""
            },
            {
                "BILAN ACTIF": "",
                "null": "3 889 205,87"
            },
            {
                "BILAN ACTIF": "T\nN\nA\nL\nU\nC\nR\nI\nC\nF\nI\nT\nC\nA",
                "null": "119 384 853,11\n119 384 853,11\n272 160 412,58\n6 035 941,39\n164 263 430,10\n70 104 648,16\n31 756 392,93\n729 542,80"
            },
            {
                "BILAN ACTIF": "",
                "null": ""
            },
            {
                "BILAN ACTIF": "",
                "null": ""
            },
            {
                "BILAN ACTIF": "",
                "null": ""
            },
            {
                "BILAN ACTIF": "",
                "null": ""
            },
            {
                "BILAN ACTIF": "",
                "null": ""
            },
            {
                "BILAN ACTIF": "",
                "null": ""
            },
            {
                "BILAN ACTIF": "",
                "null": ""
            },
            {
                "BILAN ACTIF": "",
                "null": ""
            },
            {
                "BILAN ACTIF": "",
                "null": ""
            },
            {
                "BILAN ACTIF": "",
                "null": ""
            },
            {
                "BILAN ACTIF": "",
                "null": ""
            },
            {
                "BILAN ACTIF": "",
                "null": ""
            },
            {
                "BILAN ACTIF": "",
                "null": ""
            },
            {
                "BILAN ACTIF": "",
                "null": ""
            },
            {
                "BILAN ACTIF": "",
                "null": ""
            },
            {
                "BILAN ACTIF": "",
                "null": "392 274 808,49"
            },
            {
                "BILAN ACTIF": "EIREROSÉRT",
                "null": "17 052 068,81"
            },
            {
                "BILAN ACTIF": "",
                "null": "17 038 823,02\n13 245,79"
            },
            {
                "BILAN ACTIF": "",
                "null": ""
            },
            {
                "BILAN ACTIF": "",
                "null": ""
            },
            {
                "BILAN ACTIF": "",
                "null": "17 052 068,81"
            },
            {
                "BILAN ACTIF": "",
                "null": "413 216 083,17"
            }
        ],
        [
            {
                "BILAN PASSIF": "(Montants en dhs)",
                "null": "EXERCICE\nPRÉCÉDENT"
            },
            {
                "BILAN PASSIF": "T\nN\nE\nN\nA\nM\nR\nE\nP\nT\nN\nE\nM\nE\nC\nN\nA\nN\nI\nF",
                "null": "162 429 915,14\n99 811 000,00\n35 612 905,04\n2 990 660,37\n19 880 897,24\n4 134 452,49"
            },
            {
                "BILAN PASSIF": "",
                "null": ""
            },
            {
                "BILAN PASSIF": "",
                "null": ""
            },
            {
                "BILAN PASSIF": "",
                "null": ""
            },
            {
                "BILAN PASSIF": "",
                "null": ""
            },
            {
                "BILAN PASSIF": "",
                "null": ""
            },
            {
                "BILAN PASSIF": "",
                "null": ""
            },
            {
                "BILAN PASSIF": "",
                "null": ""
            },
            {
                "BILAN PASSIF": "",
                "null": ""
            },
            {
                "BILAN PASSIF": "",
                "null": ""
            },
            {
                "BILAN PASSIF": "",
                "null": ""
            },
            {
                "BILAN PASSIF": "",
                "null": ""
            },
            {
                "BILAN PASSIF": "",
                "null": "162 429 915,14"
            },
            {
                "BILAN PASSIF": "",
                "null": "6 092 742,27\n6 092 742,27"
            },
            {
                "BILAN PASSIF": "",
                "null": ""
            },
            {
                "BILAN PASSIF": "",
                "null": ""
            },
            {
                "BILAN PASSIF": "",
                "null": ""
            },
            {
                "BILAN PASSIF": "",
                "null": ""
            },
            {
                "BILAN PASSIF": "",
                "null": ""
            },
            {
                "BILAN PASSIF": "",
                "null": ""
            },
            {
                "BILAN PASSIF": "",
                "null": ""
            },
            {
                "BILAN PASSIF": "",
                "null": ""
            },
            {
                "BILAN PASSIF": "",
                "null": ""
            },
            {
                "BILAN PASSIF": "",
                "null": ""
            },
            {
                "BILAN PASSIF": "",
                "null": ""
            },
            {
                "BILAN PASSIF": "",
                "null": "168 522 657,41"
            },
            {
                "BILAN PASSIF": "T\nN\nA\nL\nU\nC\nR\nI C\nF\nI S\nS\nA\nP",
                "null": "90 606 781,33\n54 186 644,89\n4 182 866,34\n913 546,13\n355 547,49\n30 138 712,42\n829 464,06\n729 542,68\n1 531 934,89"
            },
            {
                "BILAN PASSIF": "",
                "null": ""
            },
            {
                "BILAN PASSIF": "",
                "null": ""
            },
            {
                "BILAN PASSIF": "",
                "null": ""
            },
            {
                "BILAN PASSIF": "",
                "null": ""
            },
            {
                "BILAN PASSIF": "",
                "null": ""
            },
            {
                "BILAN PASSIF": "",
                "null": ""
            },
            {
                "BILAN PASSIF": "",
                "null": ""
            },
            {
                "BILAN PASSIF": "",
                "null": ""
            },
            {
                "BILAN PASSIF": "",
                "null": ""
            },
            {
                "BILAN PASSIF": "",
                "null": ""
            },
            {
                "BILAN PASSIF": "",
                "null": "92 868 258,90"
            },
            {
                "BILAN PASSIF": "EIREROSÉRT",
                "null": "151 825 166,86"
            },
            {
                "BILAN PASSIF": "",
                "null": "43 634 795,43\n108 190 371,43"
            },
            {
                "BILAN PASSIF": "",
                "null": ""
            },
            {
                "BILAN PASSIF": "",
                "null": ""
            },
            {
                "BILAN PASSIF": "",
                "null": "151 825 166,86"
            },
            {
                "BILAN PASSIF": "",
                "null": "413 216 083,17"
            }
        ],
        [
            {
                "COMPTE DE PRODUITS ET CHARGES (Hors Taxes)": "",
                "null": ""
            },
            {
                "COMPTE DE PRODUITS ET CHARGES (Hors Taxes)": "",
                "null": "TOTAUX DE\nL’EXERCICE\nPRÉCÉDENT"
            },
            {
                "COMPTE DE PRODUITS ET CHARGES (Hors Taxes)": "",
                "null": ""
            },
            {
                "COMPTE DE PRODUITS ET CHARGES (Hors Taxes)": "",
                "null": ""
            },
            {
                "COMPTE DE PRODUITS ET CHARGES (Hors Taxes)": "N\nO\nI\nT\nA\nT\nI\nO\nL\nP\nX\nE",
                "null": "503 670 276,02\n493 257 977,44\n3 327 948,62"
            },
            {
                "COMPTE DE PRODUITS ET CHARGES (Hors Taxes)": "",
                "null": ""
            },
            {
                "COMPTE DE PRODUITS ET CHARGES (Hors Taxes)": "",
                "null": ""
            },
            {
                "COMPTE DE PRODUITS ET CHARGES (Hors Taxes)": "",
                "null": "496 585 926,06"
            },
            {
                "COMPTE DE PRODUITS ET CHARGES (Hors Taxes)": "",
                "null": "7 084 349,96"
            },
            {
                "COMPTE DE PRODUITS ET CHARGES (Hors Taxes)": "",
                "null": ""
            },
            {
                "COMPTE DE PRODUITS ET CHARGES (Hors Taxes)": "",
                "null": ""
            },
            {
                "COMPTE DE PRODUITS ET CHARGES (Hors Taxes)": "",
                "null": ""
            },
            {
                "COMPTE DE PRODUITS ET CHARGES (Hors Taxes)": "",
                "null": ""
            },
            {
                "COMPTE DE PRODUITS ET CHARGES (Hors Taxes)": "",
                "null": "503 670 276,02"
            },
            {
                "COMPTE DE PRODUITS ET CHARGES (Hors Taxes)": "",
                "null": "477 326 370,67\n442 191 680,01\n3 253 595,33\n18 937 638,50\n123 283,03\n10 951 720,10\n1 868 453,70"
            },
            {
                "COMPTE DE PRODUITS ET CHARGES (Hors Taxes)": "",
                "null": ""
            },
            {
                "COMPTE DE PRODUITS ET CHARGES (Hors Taxes)": "",
                "null": ""
            },
            {
                "COMPTE DE PRODUITS ET CHARGES (Hors Taxes)": "",
                "null": ""
            },
            {
                "COMPTE DE PRODUITS ET CHARGES (Hors Taxes)": "",
                "null": ""
            },
            {
                "COMPTE DE PRODUITS ET CHARGES (Hors Taxes)": "",
                "null": ""
            },
            {
                "COMPTE DE PRODUITS ET CHARGES (Hors Taxes)": "",
                "null": ""
            },
            {
                "COMPTE DE PRODUITS ET CHARGES (Hors Taxes)": "",
                "null": ""
            },
            {
                "COMPTE DE PRODUITS ET CHARGES (Hors Taxes)": "",
                "null": "477 326 370,67"
            },
            {
                "COMPTE DE PRODUITS ET CHARGES (Hors Taxes)": "",
                "null": "26 343 905,35"
            },
            {
                "COMPTE DE PRODUITS ET CHARGES (Hors Taxes)": "R\nE\nI\nC\nN\nA\nN\nI\nF",
                "null": "3 207 050,06\n2 798 367,85\n4 780,42\n403 901,79"
            },
            {
                "COMPTE DE PRODUITS ET CHARGES (Hors Taxes)": "",
                "null": ""
            },
            {
                "COMPTE DE PRODUITS ET CHARGES (Hors Taxes)": "",
                "null": ""
            },
            {
                "COMPTE DE PRODUITS ET CHARGES (Hors Taxes)": "",
                "null": ""
            },
            {
                "COMPTE DE PRODUITS ET CHARGES (Hors Taxes)": "",
                "null": ""
            },
            {
                "COMPTE DE PRODUITS ET CHARGES (Hors Taxes)": "",
                "null": "3 207 050,06"
            },
            {
                "COMPTE DE PRODUITS ET CHARGES (Hors Taxes)": "",
                "null": "20 973 153,23\n6 023 635,10\n14 219 975,45\n729 542,68"
            },
            {
                "COMPTE DE PRODUITS ET CHARGES (Hors Taxes)": "",
                "null": ""
            },
            {
                "COMPTE DE PRODUITS ET CHARGES (Hors Taxes)": "",
                "null": ""
            },
            {
                "COMPTE DE PRODUITS ET CHARGES (Hors Taxes)": "",
                "null": ""
            },
            {
                "COMPTE DE PRODUITS ET CHARGES (Hors Taxes)": "",
                "null": ""
            },
            {
                "COMPTE DE PRODUITS ET CHARGES (Hors Taxes)": "",
                "null": "20 973 153,23"
            },
            {
                "COMPTE DE PRODUITS ET CHARGES (Hors Taxes)": "",
                "null": "-17 766 103,17"
            },
            {
                "COMPTE DE PRODUITS ET CHARGES (Hors Taxes)": "",
                "null": "8 577 802,18"
            }
        ],
        [
            {
                "COMPTE DE PRODUITS ET CHARGES (Hors Taxes) Suite": "",
                "null": ""
            },
            {
                "COMPTE DE PRODUITS ET CHARGES (Hors Taxes) Suite": "",
                "null": "TOTAUX DE\nL’EXERCICE\nPRÉCÉDENT"
            },
            {
                "COMPTE DE PRODUITS ET CHARGES (Hors Taxes) Suite": "",
                "null": ""
            },
            {
                "COMPTE DE PRODUITS ET CHARGES (Hors Taxes) Suite": "",
                "null": ""
            },
            {
                "COMPTE DE PRODUITS ET CHARGES (Hors Taxes) Suite": "T\nN\nA\nR\nU\nO\nC\nN\nO\nN",
                "null": "210 267,19\n210 267,19"
            },
            {
                "COMPTE DE PRODUITS ET CHARGES (Hors Taxes) Suite": "",
                "null": ""
            },
            {
                "COMPTE DE PRODUITS ET CHARGES (Hors Taxes) Suite": "",
                "null": ""
            },
            {
                "COMPTE DE PRODUITS ET CHARGES (Hors Taxes) Suite": "",
                "null": ""
            },
            {
                "COMPTE DE PRODUITS ET CHARGES (Hors Taxes) Suite": "",
                "null": ""
            },
            {
                "COMPTE DE PRODUITS ET CHARGES (Hors Taxes) Suite": "",
                "null": ""
            },
            {
                "COMPTE DE PRODUITS ET CHARGES (Hors Taxes) Suite": "",
                "null": "210 267,19"
            },
            {
                "COMPTE DE PRODUITS ET CHARGES (Hors Taxes) Suite": "",
                "null": "1 456 366,88\n1 456 366,88"
            },
            {
                "COMPTE DE PRODUITS ET CHARGES (Hors Taxes) Suite": "",
                "null": ""
            },
            {
                "COMPTE DE PRODUITS ET CHARGES (Hors Taxes) Suite": "",
                "null": ""
            },
            {
                "COMPTE DE PRODUITS ET CHARGES (Hors Taxes) Suite": "",
                "null": ""
            },
            {
                "COMPTE DE PRODUITS ET CHARGES (Hors Taxes) Suite": "",
                "null": ""
            },
            {
                "COMPTE DE PRODUITS ET CHARGES (Hors Taxes) Suite": "",
                "null": "1 456 366,88"
            },
            {
                "COMPTE DE PRODUITS ET CHARGES (Hors Taxes) Suite": "",
                "null": "-1 246 099,69"
            },
            {
                "COMPTE DE PRODUITS ET CHARGES (Hors Taxes) Suite": "",
                "null": "7 331 702,49"
            },
            {
                "COMPTE DE PRODUITS ET CHARGES (Hors Taxes) Suite": "",
                "null": "3 197 250,00"
            },
            {
                "COMPTE DE PRODUITS ET CHARGES (Hors Taxes) Suite": "",
                "null": "4 134 452,49"
            },
            {
                "COMPTE DE PRODUITS ET CHARGES (Hors Taxes) Suite": "",
                "null": "507 087 593,27"
            },
            {
                "COMPTE DE PRODUITS ET CHARGES (Hors Taxes) Suite": "",
                "null": "502 953 140,78"
            },
            {
                "COMPTE DE PRODUITS ET CHARGES (Hors Taxes) Suite": "",
                "null": "4 134 452,49"
            }
        ],
        [],
        []
    ]
}