{
    "text": "COMMUNICATION FINANCIÈRE\nAssemblée Générale Ordinaire Du 17 Mai 2024\nComptes Consolidés au 31 Décembre 2023\nDISWAY - Société Anonyme au capital de 188.576.200 DH - Registre du Commerce de Casablanca N° 41253\nAVIS DE CONVOCATION PROJET DES RESOLUTIONS PROPOSEES A L'ASSEMBLEE GENERALE ORDINAIRE\nLes actionnaires de la société Disway, Société Anonyme, au capital de 188.576.200 Dirhams, PREMIERE RESOLUTION\nsont convoqués en Assemblée Générale Ordinaire, le 17 Mai 2024 à 10 heures au siège social L’Assemblée Générale Ordinaire, après avoir entendu la lecture du rapport de gestion présenté par le\nde la société sis à Casablanca, Lotissement La Colline II, n°8, Sidi Maârouf, en vue de délibérer Directoire, du Rapport Général des Commissaires aux Comptes et des observations du Conseil de\nsur l’ordre du jour suivant : Surveillance, approuve tels qu’ils sont présentés les comptes et les états de synthèses de l’exercice 2023 se\nsoldant par un bénéfice net comptable de 56.354.103,92 Dirhams.\n1 Lecture du rapport de gestion du directoire et des rapports des commissaires aux\nDEUXIEME RESOLUTION\ncomptes sur l’exercice clos au 31 décembre 2023 ;\nL’Assemblée Générale Ordinaire, après avoir entendu lecture du Rapport Spécial des Commissaires aux\n2 Lecture des observations du conseil de surveillance sur le rapport du directoire et Comptes sur les conventions visées à l’article 95 de la loi 17-95 relative aux Sociétés Anonymes telles que\nles comptes de l’exercice clos au 31 décembre 2023 modifiée et complétée par les lois 20-05 ,78-12, 20-19 et 19-20, en prend acte et approuve ledit rapport.\n3 Approbation des comptes de l’exercice clos au 31 décembre 2023 ; TROISIEME RESOLUTION\n4 Affectation du résultat de l’exercice clos au 31 décembre 2023 ; L’Assemblée Générale Ordinaire décide d’affecter le résultat de l’exercice 2023 comme suit :\n5 Quitus de leur gestion aux membres du directoire et de l’exécution de leur mandat Résultat Net de l’exercice 56.354.103,92\naux membres du conseil de surveillance ; - Réserve légale 0,00\n= Résultat net distribuable de l'exercice 56.354.103,92\n6 Approbation du rapport spécial des commissaires aux comptes relatif aux\nconventions réglementées visées à l’article 95 et suivants de la loi 17/95 ; + Report à nouveau créditeur antérieur 123.786.584,76\n7 Fixation du montant des jetons de présence pour l’exercice 2023 ; = Solde distribuable 180.140.688,68\n- Dividendes distribués 66.001.670,00\n8 Pouvoirs en vue des formalités légales ;\n= Solde au compte report à nouveau 114.139.018,68\n9 Questions diverses.\nLe dividende ainsi fixé à 35 dhs par action, sera mis en paiement à compter du 04/07/2024.\nLes détenteurs d’actions au porteur doivent, pour être admis à cette Assemblée, déposer au\nQUATRIEME RESOLUTION\nsiège de la société une attestation émanant d’un intermédiaire financier habilité, justifiant la\nL’Assemblée Générale Ordinaire donne aux membres du Conseil de Surveillance et aux membres du\nqualité de l’actionnaire et le nombre de titres détenus par lui, et ce, au plus tard cinq jours avant\nDirectoire quitus entier et sans réserve de l’exécution de leurs mandats au cours de l’exercice 2023.\nla tenue de l’Assemblée Générale.\nCINQUIEME RESOLUTION\nLes détenteurs d’actions nominatives doivent avoir été inscrits en compte au plus tard cinq\nL’Assemblée Générale Ordinaire décide de fixer le montant des jetons de présence, à allouer aux membres\njours avant la tenue de l’Assemblée Générale.\ndu Conseil de Surveillance au titre de l’exercice 2023, à un montant global brut de 1.400.000,00 Dirhams.\nTout actionnaire remplissant les conditions prévues par la loi 17-95 sur les sociétés a la faculté\nde requérir l’inscription d’un ou plusieurs projets de résolutions à l’ordre du jour. La demande Le Conseil de Surveillance répartira cette somme entre ses membres dans les proportions qu’il jugera\nd’inscription de ces projets de résolutions doit être adressée au siège de la société par lettre convenables.\nrecommandée avec accusé de réception dans un délai de dix jours à compter de la publication\nSIXIEME RESOLUTION\nde l’avis de convocation.\nTous les pouvoirs sont donnés au porteur d’un original ou d’une copie des présentes pour effectuer les\nLes documents et informations prévus à l’article 121, 121 bis et 141 de la loi 17-95 relative aux formalités de dépôt et de publicité prévues par la loi.\nSociétés Anonymes peuvent être consultés sur notre site Internet : www.disway.com.\nLe Directoire\nBILAN CONSOLIDE En Dirhams COMPTE DE PRODUITS ET CHARGES CONSOLIDE En Dirhams\nACTIF 31/12/2023 31/12/2022 31/12/2023 31/12/2022\nACTIF IMMOBILISE 359 7 73 6 25,76 343 1 01 8 84,59 Produits d'exploitation 1 910 075 707,3 7 1 969 99 2 5 42,91\n* Ecarts d'acquisition * Chiffre d'affaires 1 869 587 153,14 1 950 400 911,41\n* Immobilisations incorporelles 172 6 48 0 41,65 171 7 91 234,90 * Autres produits 40 488 554,23 19 591 631,50\n* Immobilisations corporelles 185 9 35 6 32,68 169 8 44 2 84,99 Charges d'exploitation 1 783 949 402,47 1 847 696 878,78\n* Immobilisations financières 1 1 89 9 51,43 1 4 66 3 64,70 * Achats revendus & consommés 1 666 132 976,77 1 731 520 070,13\n* Titres mis en équivalence * Autres charges externes 28 180 866,86 25 795 741,84\n* Impôts et taxes 1 525 268,58 2 130 091,41\nACTIF CIRCULANT 820 9 15 5 52,08 1 065 297 663,66\n* Charges de personnel 54 553 688,92 54 666 200,97\n* Stocks et en-cours 215 6 93 2 39,83 366 8 49 6 74,28 * Autres charges d'exploitation 1 400 000,00 1 400 000,00\n*Clients et comptes rattachés 499 4 30 0 57,81 572 824 9 19,07 * Dotations d'exploitation 32 156 601,34 32 184 774,43\n* Autres créances et comptes de régularisation 89 5 51 8 91,42 125 2 45 8 97,60 Résultat d'exploitation 126 126 304,90 122 295 664,13\n* Titres et valeurs de placement 16 240 3 63,02 377 1 72,71 Charges et produits financiers -2 317 234,40 4 577 224,05\nRésultat courant des entreprises intégrées 123 809 070,5 0 126 872 888,18\n* Disponibilités 40 4 23 685,47 36 796 341,26\nCharges et produits non courant -31 322 009,99 -7 135 357,14\nImpôts sur les bénéfices 26 968 529,77 35 097 054,85\nTOTAL ACTIF 1 221 112 863,32 1 4 45 1 95 8 89,52 Résultat net des entreprises intégrées 65 518 530,74 84 640 476,19\nQuote part dans le résultat des entreprises incluses\nPASSIF 31/12/2023 31/12/2022\npar mise en équivalence\nCAPITAUX PROPRES DE L'ENSEMBLE 668 495 031,74 669 082 796,86\nDotations aux amortissements des écarts d'acquisition\n* Capitaux propres (part de groupe) 668 495 031,74 669 082 796,86\nRésultat net de l'ensemble consolidé 65 518 530,74 84 640 476,19\n* Capital 188 576 200,00 188 576 200,00 Résultat minoritaire\n* Prime d'émission, de fusion, d'apport 224 782 325,40 224 782 325,40 Résultat net part du groupe 65 518 530,74 84 640 476,19\n* Réserves consolidées 216 475 744,00 194 413 847,93\nRésultat net consolidé par action en dirhams 34,74 44,88\n* Résultat net consolidé part du groupe 65 518 530,74 84 640 476,19\n* Ecarts de conversion -26 857 768,40 -23 330 052,66 INFORMATIONS RELATIVES AU PÉRIMÈTRE DE CONSOLIDATION\n* Intérêts minoritaires\nProvision pour risques et charges Liste des Sociétés % D'intérêt % de contrôle Méthode de consolidation\nDettes 319 969 440,38 484 695 805,03 Disway Mère Mère Intégration globale\n* Emprunts et dettes financières 83 711 348,18 99 358 340,71 Blueway Technology 100% 100% Intégration globale\n* Fournisseurs et comptes rattachés 139 132 459,11 266 902 928,56 Experience Store 100% 100% Intégration globale\n* Autres dettes et comptes de régularisation 97 125 633,09 118 434 535,76 Disway Logistic Services 100% 100% Intégration globale\n* Trésorerie-passif 232 648 391,20 291 417 287,63 Disway MEA 100% 100% Intégration globale\nDisway Tunisie 100% 100% Intégration globale\nTOTAL PASSIF 1 221 112 863,32 1 445 195 889,52\nLe rapport financier annuel 2023 est disponible sur notre site internet sous le lien : www.disway.com/rfa2023\nEn Dirhams BILAN (PASSIF) En Dirhams\nCOMPTE DE PRODUITS ET CHARGES ( HORS TAXES ) En Dirhams TABLEAU DE FINANCEMENT DE L'EXERCICE\n31/12/2023 31/12/2022\nI PRODUITS D'EXPLOITATION\nVentes de marchandises\nVentes de biens et services produits\nChiffres d'affaires\nVariation de stock de produits\nImmobilisations produites pour l'Ese p/elle même Subvention d'exploitation\nAutres produits d'exploitation\nReprises d'exploitation; transfert de charges\nTOTAL I\nII CHARGES D'EXPLOITATION\nAchats revendus de marchandises\nAchat consommes de matières et de fournitures\nAutres charges externes\nImpôts et taxes\nCharges de personnel\nAutres charges d'exploitation\nDotations d'exploitation\nTOTAL II\nIII RESULTAT D'EXPLOITATION ( I - II )\nIV PRODUITS FINANCIERS\nProduits des titres de participation et autres titres immobilises\nGains de change\nIntérêts et autres produits financiers\nReprises financières; transfert de charges\nTOTAL IV\nV CHARGES FINANCIERES\nCharges d'intérêts\nPertes de changes\nAutres charges financières\nDotations financières\nTOTAL V\nVIRESULTAT FINANCIER ( IV - V )\nVIIRESULTAT COURANT ( III - V I)\nVIIIPRODUITS NON COURANTS\nProduits des cessions d'immobilisations\nSubventions d'équilibre\nReprises sur subventions d'investissement\nAutres produits non courants\nReprises non courantes; transferts de charges\nTOTAL VIII\nIXCHARGES NON COURANTES\nValeurs nettes d'amortissements des immobilisations cédées\nSubventions accordées\nAutres charges non courantes\nDotations non courantes aux amortiss. et provision\nTOTAL IX\nX RESULTAT NON COURANT ( VIII- IV )\nXI RESULTAT AVANT IMPOTS ( VII+ X )\nXIIIMPOTS SUR LES RESULTATS\nXIIIRESULTAT NET ( XI - XII )\nXIVTOTAL DES PRODUITS ( I + IV + VIII )\nXVTOTAL DES CHARGES ( II + V + IX + XII )\nXVIRESULTAT NET ( XIV - XV )\nNOITATIOLPXE\nREICNANIF\nTNARUOC\nNON\nACTIF\n188 576 200,00\nIMMOBILISATION EN NON VALEUR (a) 1 846 175,00 1 476 940,00 369 235,00 738 470,00 0,00\nFrais préliminaires 0,00 0,00 0,00 0,00 224 782 325,40\nCharges à repartir sur plusieurs exercices 1 846 175,00 1 476 940,00 369 235,00 738 470,00 0,00\nPrimes de remboursement des obligations 0,00 0,00 0,00 0,00 18 857 620,00\nIMMOBILISATIONS INCORPORELLES (b) 175 058 613,83 2 473 179,42 172 585 434,41 171 643 958,89\n11 900 222,38 Immobilisations en recherche et développement 0,00 0,00 0,00 0,00\nBrevets, marques, droits et valeurs similaires 67 498,20 34 522,28 32 975,92 46 475,56 123 786 584,76\nFonds commercial 171 367 483,33 0,00 171 367 483,33 171 367 483,33 0,00\nAutres immobilisations incorporelles 3 623 632,30 2 438 657,14 1 184 975,16 230 000,00 56 354 103,92\nIMMOBILISATIONS CORPORELLES (c) 290 839 580,55 106 748 961,84 184 090 618,71 167 627 155,81 624 257 056,46\nTerrains 54 921 250,00 0,00 54 921 250,00 54 921 250,00 662 643,00\nConstructions 144 583 018,41 86 614 556,43 57 968 461,98 63 819 095,99\nInstallations techniques, matériel et outillage 2 303 177,43 1 920 190,77 382 986,66 560 646,66 0,00\nMatériel de transport 4 909 156,96 4 073 837,63 835 319,33 627 190,21 662 643,00\nMobilier, matériel de bureau et aménagements divers 14 791 988,84 13 888 710,45 903 278,39 1 066 484,40\nAutres immobilisations corporelles 270 241,55 251 666,56 18 574,99 3 735,85 83 606 393,48 Immobilisations corporelles en cours 69 060 747,36 0,00 69 060 747,36 46 628 752,70\nIMMOBILISATIONS FINANCIERES (d) 108 279 992,90 14 000 000,00 94 279 992,90 86 647 567,03 0,00\nPrêts immobilisés 497 310,47 0,00 497 310,47 364 884,60 83 606 393,48\nAutres créances financières 217 584,17 0,00 217 584,17 217 584,17\nTitres de participation 107 565 098,26 14 000 000,00 93 565 098,26 86 065 098,26\n0,00 Autres titres immobilisés 0,00 0,00 0,00 0,00\nECARTS DE CONVERSION - ACTIF (e) 0,00 0,00 0,00 0,00 0,00\nDiminution des créances immobilisées 0,00 0,00 0,00 0,00 0,00\nAugmentation des dettes de finance 0,00 0,00 0,00 0,00 0,00\nTOTAL I ( a+b+c+d+e) 576 024 362,28 124 699 081,26 451 325 281,02 426 657 151,73\n0,00 STOCKS (f) 186 375 605,22 11 669 996,88 174 705 608,34 313 712 752,01\nMarchandises 186 375 605,22 11 669 996,88 174 705 608,34 313 712 752,01 0,00\nMatières et fournitures consommables 0,00 0,00 0,00 0,00 708 526 092,94\nProduits en cours 0,00 0,00 0,00 0,00 213 986 104,74\nProduits interm et produits résiduels 0,00 0,00 0,00 0,00\n130 998 400,95 Produits finis 0,00 0,00 0,00 0,00\nCREANCES DE L'ACTIF CIRCULANT (g) 507 548 618,41 10 803 571,95 496 745 046,46 602 289 296,22 172 408,00\nFournis. débiteurs, avances et acomptes 22 073 110,67 0,00 22 073 110,67 16 905 592,28 54 681,75\nClients et comptes rattaches 444 552 949,83 10 803 571,95 433 749 377,88 501 642 061,79 1 652 202,06\nPersonnel 20 700,00 0,00 20 700,00 30 000,00 80 282 727,76\nEtat 39 944 292,44 0,00 39 944 292,44 82 584 493,94 4 650,00\nComptes d'associés 0,00 0,00 0,00 0,00 0,00\nAutres débiteurs 0,00 0,00 0,00 316 082,28\n821 034,22 Compte de régularisation actif 957 565,47 0,00 957 565,47 811 065,93\nTITRES ET VALEUR DE PLACEMENT (h) 0,00 0,00 0,00 372 082,50 6 325 771,41\nECART DE CONVERSION - ACTIF (i) 139 479,41 0,00 139 479,41 1 152 863,17 2 520 804,48\nTOTAL II ( f+g+h+i) 694 063 703,04 22 473 568,83 671 590 134,21 917 526 993,90 222 832 680,63 TRESORERIE - ACTIF 24 156 359,74 0,00 24 156 359,74 20 186 736,72\nChèques et valeurs à encaisser 21 365 704,69 0,00 21 365 704,69 15 237 482,16 215 713 001,40\nBanques, T.G & CCP 2 757 368,30 0,00 2 757 368,30 4 907 374,93 0,00\nCaisses, régies d'avances et accréditifs 33 286,75 0,00 33 286,75 41 879,63 133 725 363,13\nTOTAL III 24 156 359,74 0,00 24 156 359,74 20 186 736,72 81 987 638,27\nTOTAL GENERAL I+II+III 1 294 244 425,06 147 172 650,09 1 147 071 774,97 1 364 370 882,35\n215 713 001,40\n1 147 071 774,97\n1 555 601 944,88 1 585 647 500,83\n19 011 927,65 16 615 028,37\n1 574 613 872,53 1 602 262 529,20\n0,00 0,00\n0,00 0,00 0,00 0,00\n0,00 0,00\n31 941 174,06 10 057 048,18\n1 606 555 046,59 1 612 319 577,38\n1 413 382 217,02 1 428 781 555,30\n2 004 219,65 1 833 426,96\n21 081 718,68 18 261 673,70\n658 830,84 1 125 456,99\n47 771 496,46 48 332 350,92\n1 400 000,00 1 400 000,00\n26 227 239,91 26 301 924,58\n1 512 525 722,56 1 526 036 388,45\n94 029 324,03 86 283 188,93\n0,00 0,00\n14 222 065,19 14 256 703,48\n11 447 920,20 9 485 542,19\n8 652 863,17 1 463 129,91\n34 322 848,56 25 205 375,58\n15 645 348,95 8 960 492,13\n6 918 718,24 8 831 675,82\n0,00 0,00\n139 479,41 1 152 863,17\n22 703 546,60 18 945 031,12\n11 619 301,96 6 260 344,46\n105 648 625,99 92 543 533,39\n170 000,00 345 000,00\n0,00 0,00\n0,00 0,00\n3 456 456,42 2 107 548,11\n0,00 0,00\n3 626 456,42 2 452 548,11\n0,00 1 932,46\n0,00 0,00\n30 049 785,49 7 345 931,45\n0,00 0,00\n30 049 785,49 7 347 863,91\n-26 423 329,07 -4 895 315,80\n79 225 296,92 87 648 217,59\n22 871 193,00 30 767 413,00\n56 354 103,92 56 880 804,59\n1 644 504 351,57 1 639 977 501,07\n1 588 150 247,65 1 583 096 696,48\n56 354 103,92 56 880 804,59\nESILIBOMMI\nFITCA\nTNALUCRIC\nFITCA\nEIREROSERT\nPASSIF 31/12/2023 31/12/2022\nCAPITAUX PROPRES\nCapital social ou personnel (1) 188 576 200,00\nmoins: Actionnaires, capital souscrit non appelé dont versé.. 0,00\nPrime d'émission, de fusion, d'apport 224 782 325,40\nEcarts de réévaluation 0,00\nRéserve légale 18 857 620,00\nAutres réserves 11 900 222,38\nReport à nouveau (2) 132 907 450,17\nRésultats nets en instance d'affectation (2) 0,00\nRésultat net de l'exercice (2) 56 880 804,59\nTOTAL DES CAPITAUX PROPRES (a) 633 904 622,54\nCAPITAUX PROPRES ASSIMILES (b) 662 643,00\nSubventions d'investissement 0,00\nProvisions réglementées 662 643,00\nDETTES DE FINANCEMENT (c) 98 838 690,69\nEmprunts obligataires 0,00\nAutres dettes de financement 98 838 690,69\nPROVISIONS DURABLES POUR RISQUES ET CHARGES (d) 0,00\nProvisions pour risques 0,00\nProvisions pour charges 0,00\nECARTS DE CONVERSION - PASSIF (e) 0,00\nAugmentation des créances immobilisées 0,00\nDiminution des dettes de financement 0,00\nTOTAL I ( a+b+c+d+e ) 733 405 956,23\nDETTES DU PASSIF CIRCULANT (f) 360 336 761,54\nFournisseurs et comptes rattachés 264 819 420,71\nClients créditeurs, avances et acomptes 0,00\nPersonnel 46 001,93\nOrganismes sociaux 1 412 227,81\nEtat 92 561 654,12\nComptes d'associés 4 650,00\nAutres créanciers 343,00\nComptes de régularisation - passif 1 492 463,97\nAUTRES PROVISIONS POUR RISQUES ET CHARGES (g) 9 172 355,17\nECARTS DE CONVERSION - PASSIF (h)( Eléments circulants ) 5 094 292,89\nTOTAL II ( f+g+h ) 374 603 409,60\nTRESORERIE PASSIF 256 361 516,52\nCrédits d'escompte 0,00\nCrédits de trésorerie 200 000 000,00\nBanques ( soldes créditeurs ) 56 361 516,52\nTOTAL III 256 361 516,52\nTOTAL I+II+III 1 364 370 882,35\nTNENAMREP\nTNEMECNANIF\nTNALUCRIC\nFISSAP\nEIREROSERT\nCOMMUNICATION FINANCIÈRE\nComptes Sociaux au 31 Décembre 2023\nBILAN (ACTIF)\n31/12/2023 31/12/2022\nBrut Amortissements Net Net\net Provisions\n(modèle normal)\nI SYNTHESE DES MASSES DU BILAN Exercice du 01/01/2023 au 31/12/2023\nExercice Variations a-b\nMASSES Exercice précédent Emplois Ressources\na b c d\n1 Financement Permanent 708 526 092,94 733 405 956,23 24 879 863,29\n2 Moins actif immobilisé 451 325 281,02 426 657 151,73 24 668 129,29\n3 = Fonds de Roulement Fonctionnel (1-2) (A) 257 200 811,92 306 748 804,50 49 547 992,58\n4 Actif circulant 671 590 134,21 917 526 993,90 245 936 859,69\n5 Moins passif circulant 222 832 680,63 374 603 409,60 151 770 728,97\n6 = Besoin de Financement global (4-5) (B) 448 757 453,58 542 923 584,30 94 166 130,72\n7 TRESORERIE NETTE (Actif-Passif) = A-B -191 556 641,66 -236 174 779,80 44 618 138,14\nII EMPLOIS ET RESSOURCES\nEXERCICE EXERCICE PRECEDENT\nEMPLOIS RESSOURCES EMPLOI RESSOURCES\nI RESSOURCES STABLES DE\nL'EXERCICE (FLUX)\n* AUTOFINANCEMENT (A) -8 989 217,78 -67 043 514,28\n+ Capacité d'autofinancement 57 012 452,22 64 959 825,72\n- Distributions de bénéfices 66 001 670,00 132 003 340,00\n* CESSIONS ET REDUCTIONS\nD'IMMOBILISATIONS (B) 473 574,13 643 749,02\n+ Cessions d'immobilisations incorpor. 0,00\n+ Cessions d'immobilisation corporelles 170 000,00 345 000,00\n+ Cessions d'immobilisation financières 0,00 0,00\n+ récupérations sur créances immobilisées 303 574,13 298 749,02\n* AUGMENTATION DES CAPITAUX\nPROPRES ET ASSIMILES (C) 0,00 0,00 0,00 0,00\n+ Augmentation du capital , apports\n+ Subventions d'investissement 0,00 0,00\nAUGMENTATION DES DETTES\nDE FINANCEMENT (D) 0,00 90 343 200,00\n(nettes de primes de remboursement)\nTOTAL RESSOURCES STABLES\n(A+B+C+D) -8 515 643,65 23 943 434,74\nII EMPLOIS STABLES DE L'EXERCICE (FLUX)\nACQUISITIONS ET AUGMENTATIONS\nD'IMMOBILISATIONS (E) 25 800 051,72 81 117 053,85\n+ Acquisitions d'immobilisations incorpor. 954 975,16 0,00\n+ Acquisitions d'immobilisation corporelles 24 409 076,56 47 605 109,29\n+ Acquisitions d'immobilisation financières 0,00 33 511 944,56\n+ Augmentation des créances immob. 436 000,00 0,00\n* REMBOURSEMENT DES CAPITAUX\nPROPRES (F) 0,00 0,00\n* REMBOURSEMENTS DES DETTES\nDE FINANCEMENT (G) 15 232 297,21 7 856 689,64\n* EMPLOIS EN NON VALEURS (H) 0,00 0,00\nTOTAL II - EMPLOIS STABLES\n(E+F+G+H) 41 032 348,93 88 973 743,49\nIII VARIATION DU BESOIN DE FINANCEMENT\nGLOBAL (B.F.G) 0,00 94 166 130,72 195 420 318,31 0,00\nIV VARIATION DE LA TRESORERIE 44 618 138,14 0,00 0,00 260 450 627,06\nTOTAL GENERAL 85 650 487,07 85 650 487,07 284 394 061,80 284 394 061,80\nCOMMUNICATION FINANCIÈRE\nRapports des commissaires aux comptes 2023\nAux Actionnaires de la société Aux Actionnaires de la société\nDISWAY S.A. DISWAY S.A.\n8, Lot La Colline II-Sidi Mâarouf, 8, Lot La Colline II-Sidi Mâarouf,\nCasablanca Casablanca\nRapport des commissaires aux comptes Rapport Général des commissaires aux comptes\nExercice du 1er janvier au 31 décembre 2023 Exercice du 1er janvier au 31 décembre 2023\nAudit des états de synthèse consolidés Audit des états de synthèse\nOpinion Opinion\nNous avons effectué l'audit des états de synthèse consolidés de la société DISWAY et de ses filiales (« le groupe »), qui comprennent Conformément à la mission qui nous a été confiée par votre Assemblée Générale, nous avons effectué l'audit des états de synthèse\nle bilan consolidé au 31 décembre 2023, ainsi que le compte de produits et charges consolidé, le tableau consolidé des flux de ci-joints de la société DISWAY S.A., qui comprennent le bilan, le compte de produits et charges, l’état des soldes de gestion et l’état des\ntrésorerie pour l’exercice clos à cette date, ainsi que l’état des informations complémentaires (ETIC), y compris un résumé des informations complémentaires (ETIC) relatifs à l’exercice clos le 31 décembre 2023. Ces états de synthèse font ressortir un montant de\nprincipales méthodes comptables. Ces états de synthèse consolidés font ressortir un montant de capitaux propres consolidés de KMAD capitaux propres et assimilés de MAD 624 919 699,46 dont un bénéfice net de MAD 56 354 103,92.\n668 495 dont un bénéfice net consolidé de KMAD 65 519.\nNous certifions que les états de synthèse cités au premier paragraphe ci-dessus sont réguliers et sincères et donnent, dans tous leurs\nNous certifions que les états de synthèse consolidés cités au premier paragraphe ci-dessus, sont réguliers et sincères et donnent, dans aspects significatifs, une image fidèle du résultat des opérations de l’exercice écoulé ainsi que de la situation financière et du patrimoine\ntous leurs aspects significatifs, une image fidèle du patrimoine et de la situation financière du groupe DISWAY au 31 décembre 2023 de la société DISWAY S.A. au 31 décembre 2023 conformément au référentiel comptable en vigueur au Maroc.\nainsi que du résultat de l’ensemble consolidé pour l’exercice clos à cette date, conformément au référentiel comptable en vigueur au\nFondement de l’opinion\nMaroc.\nNous avons effectué notre audit selon les Normes de la Profession au Maroc. Les responsabilités qui nous incombent en vertu de ces\nFondement de l’opinion normes sont plus amplement décrites dans la section « Responsabilités de l’auditeur à l’égard de l’audit des états de synthèse »du\nNous avons effectué notre audit selon les Normes de la Profession au Maroc. Les responsabilités qui nous incombent en vertu de ces présent rapport. Nous sommes indépendants de la société conformément aux règles de déontologie qui s’appliquent à l’audit des états\nnormes sont plus amplement décrites dans la section « Responsabilités de l’auditeur à l’égard de l’audit des états consolidés » du de synthèse au Maroc et nous nous sommes acquittés des autres responsabilités déontologiques qui nous incombent selon ces règles.\nprésent rapport. Nous sommes indépendants du groupe conformément aux règles de déontologie qui s’appliquent à l’audit des états de Nous estimons que les éléments probants que nous avons obtenus sont suffisants et appropriés pour fonder notre opinion d’audit.\nsynthèse au Maroc et nous nous sommes acquittés des autres responsabilités déontologiques qui nous incombent selon ces règles.\nNous estimons que les éléments probants que nous avons obtenus sont suffisants et appropriés pour fonder notre opinion d’audit. Questions clés de l’audit\nLes questions clés de l’audit sont les questions qui, selon notre jugement professionnel, ont été les plus importantes dans l’audit des\nQuestions clés de l’audit\nétats de synthèse de la période considérée. Ces questions ont été traitées dans le contexte de notre audit des états de synthèse pris\nLes questions clés de l’audit sont les questions qui, selon notre jugement professionnel, ont été les plus importantes dans l’audit des dans leur ensemble et aux fins de la formation de notre opinion sur ceux-ci, et nous n’exprimons pas une opinion distincte sur ces\nétats de synthèse consolidés de la période considérée. Ces questions ont été traitées dans le contexte de notre audit des états questions.\nsynthèse consolidés pris dans leur ensemble et aux fins de la formation de notre opinion sur ceux-ci, et nous n’exprimons pas une\nopinion distincte sur ces questions. Nous avons déterminé que les questions décrites ci-après constituent les questions clés de l’audit qui doivent être communiquées dans\nnotre rapport :\nNous avons déterminé que les questions décrites ci-après constituent les questions clés de l’audit qui doivent être communiquées dans\nnotre rapport : 1 Dépréciation des créances clients\n- Risque identifié\n1 Dépréciation des créances clients\nAu 31 décembre 2023, la valeur des créances clients est inscrite au bilan pour une valeur brute d’environ KMAD 444 553 et une\n- Risque identifié valeur nette comptable d’environ KMAD 433 749, soit 37,81% du total de l’actif de la Société.\nAu 31 décembre 2023, la valeur des clients et comptes rattachés est inscrite au bilan consolidé pour une valeur nette comptable La provision pour dépréciation des créances clients, quant à elle, s’élève à environ KMAD 10 804, est calculée en fonction de\nd’environ KMAD 499 430 soit 40,90% du total de l’actif du groupe. l’ancienneté et du suivi, effectué par le comité de pilotage, des créances impayées ou présentant des difficultés de recouvrement.\nLa provision pour dépréciation des créances clients et comptes rattachés du groupe, qui s’élève à environ KMAD 29 206 au 31 Nous avons considéré que la dépréciation des créances clients est un point clé d’audit compte tenu de l’importance de ces\ndécembre 2023, est calculée par le groupe en fonction de l’ancienneté et du suivi du comité de pilotage des créances impayées créances dans le bilan de la société, soit KMAD 433 749 en 2023 et KMAD 501 642 en 2022 et de la sensibilité du processus de\nou présentant des difficultés de recouvrement. recouvrement.\nNous avons considéré que la dépréciation des créances clients et comptes rattachés est un point clé d’audit compte tenu de - Procédures d’audit mises en œuvre en réponse à ce risque\nl’importance de ces créances dans le bilan du groupe, soit KMAD 499 430 en 2023 et KMAD 572 825 en 2022 et de la sensibilité Nos contrôles relatifs à la dépréciation des créances clients ont notamment consisté à :\ndu processus de recouvrement dans le contexte de la crise liée au Covid-19. • Examiner la balance âgée, analyser les retards de paiement et discuter avec la direction les raisons du retard dans le\n- Procédures d’audit mises en œuvre en réponse à ce risque recouvrement de certaines créances significatives ;\nNos contrôles relatifs à la dépréciation des créances clients ont notamment consisté à : • Analyser les paiements reçus postérieurement à la date de clôture pour les créances les plus significatives ;\n• Contrôler le calcul de la provision pour dépréciation et sa conformité avec la règle de provisionnement adoptée par la société.\n• Examiner la balance âgée, analyser les retards de paiement et discuter avec la direction les raisons du retard dans le\nrecouvrement de certaines créances significatives ; 2 Dépréciation des stocks de marchandises\n• Analyser les paiements reçus postérieurement à la date de clôture pour les créances les plus significatives ; - Risque identifié\n• Contrôler le calcul de la provision pour dépréciation et sa conformité avec la règle de provisionnement adoptée par le groupe. Le stock des marchandises affiche une valeur nette comptable de l’ordre de KMAD 174 706 au 31 décembre 2023.\n2 Dépréciation des stocks de marchandises La dépréciation du stock des marchandises est basée sur un modèle de dépréciation mis en place pour chaque famille de produit\net selon l’antériorité du stock détenu.\n- Risque identifié\nLe stock des marchandises affiche une valeur nette comptable de l’ordre de 215 693 KMAD au 31 décembre 2023. Nous avons considéré que la dépréciation du stock est un point clé d’audit, du fait que le marché du matériel informatique et\nLa dépréciation du stock des marchandises est basée sur un modèle de dépréciation mis en place pour chaque famille de produit électronique est très sensible aux évolutions technologiques ainsi que les mutations dans la nature des besoins des utilisateurs\net selon l’antériorité du stock détenu. sur le plan international, ayant un effet significatif sur l’évolution des prix.\nNous avons considéré que la dépréciation du stock est un point clé d’audit, du fait que le marché du matériel informatique et - Procédures d’audit mises en œuvre en réponse à ce risque\nélectronique est très sensible aux évolutions technologiques ainsi que les mutations dans la nature des besoins des utilisateurs Nos travaux relatifs à la dépréciation du stock ont notamment consisté à :\nsur le plan international, ayant un effet significatif sur l’évolution des prix. • Identifier les données et les hypothèses retenues par la Direction pour déterminer la valeur d’inventaire et identifier les articles\n- Procédures d’audit mises en œuvre en réponse à ce risque\nqui doivent être comptabilisés à cette valeur ;\n• Prendre connaissance des procédures de contrôle interne mises en place pour identifier les articles à rotation lente ;\nNos travaux relatifs à la dépréciation du stock ont notamment consisté à : • Tester l’efficacité des contrôles clés relatifs à ces procédures ;\n• dentifier les données et les hypothèses retenues par la Direction pour déterminer la valeur d’inventaire et identifier les articles • Comparer par sondages le coût des articles en stock avec le prix net de réalisation afin de confirmer le montant de la dépréciation\nqui doivent être comptabilisés à cette valeur ; constatée dans les comptes ;\n• Prendre connaissance des procédures de contrôle interne mises en place pour identifier les articles à rotation lente ; • Identifier les articles à rotation lente et vérifier leur correcte évaluation.\n• Tester l’efficacité des contrôles clés relatifs à ces procédures ; Responsabilités de la direction et des responsables de la gouvernance à l’égard des états de synthèse\n• Comparer par sondages le coût des articles en stock avec le prix net de réalisation afin de confirmer le montant de la La direction est responsable de l'établissement et de la présentation sincère de ces états de synthèse, conformément au référentiel\ndépréciation constatée dans les comptes. comptable admis au Maroc. Cette responsabilité comprend la conception, la mise en place et le suivi d'un contrôle interne relatif à\n• Identifier les articles à rotation lente et vérifier leur correcte évaluation. l'établissement et la présentation des états de synthèse ne comportant pas d'anomalie significative, ainsi que la détermination\nd'estimations comptables raisonnables au regard des circonstances.\nResponsabilités de la direction et des responsables de la gouvernance à l’égard des états de synthèse consolidés Lors de la préparation des états de synthèse, c’est à la direction qu’il incombe d’évaluer la capacité de la société à poursuivre son\nLa direction est responsable de l'établissement et de la présentation sincère de ces états de synthèse, conformément au référentiel exploitation, de communiquer, le cas échéant, les questions se rapportant à la continuité de l’exploitation et d’appliquer le principe\ncomptable admis au Maroc. Cette responsabilité comprend la conception, la mise en place et le suivi d'un contrôle interne relatif à comptable de continuité d’exploitation, sauf si la direction a l’intention de liquider la société ou de cesser son activité ou si aucune autre\nl'établissement et la présentation des états de synthèse ne comportant pas d'anomalie significative, ainsi que la détermination solution réaliste ne s’offre à elle.\nd'estimations comptables raisonnables au regard des circonstances.\nIl incombe aux responsables de la gouvernance de surveiller le processus d’information financière de la société.\nLors de la préparation des états de synthèse consolidés, c’est à la direction qu’il incombe d’évaluer la capacité du groupe à poursuivre\nson exploitation, de communiquer, le cas échéant, les questions se rapportant à la continuité de l’exploitation et d’appliquer le principe Responsabilités de l’auditeur à l’égard de l’audit des états de synthèse\ncomptable de continuité d’exploitation, sauf si la direction a l’intention de liquider le groupe ou de cesser son activité ou si aucune autre Notre responsabilité est d'exprimer une opinion sur ces états de synthèse sur la base de notre audit. Nous avons effectué notre audit\nsolution réaliste ne s’offre à elle. selon les Normes de la Profession au Maroc.\nIl incombe aux responsables de la gouvernance de surveiller le processus d’information financière du groupe. Nos objectifs sont d’obtenir l’assurance raisonnable que les états de synthèse pris dans leur ensemble sont exempts d’anomalies\nsignificatives, que celles-ci résultent de fraudes ou d’erreurs et de délivrer un rapport de l’auditeur contenant notre opinion. L’assurance\nResponsabilités de l’auditeur à l’égard de l’audit des états de synthèse consolidés raisonnable correspond à un niveau élevé d’assurance, qui ne garantit toutefois pas qu’un audit réalisé conformément aux normes de\nNotre responsabilité est d'exprimer une opinion sur ces états de synthèse sur la base de notre audit. Nous avons effectué notre audit la profession au Maroc permettra toujours de détecter toute anomalie significative qui pourrait exister. Les anomalies peuvent résulter\nselon les Normes de la Profession au Maroc. de fraudes ou d’erreurs et elles sont considérées comme significatives lorsqu’il est raisonnable de s’attendre à ce que, individuellement\nNos objectifs sont d’obtenir l’assurance raisonnable que les états de synthèse consolidés pris dans leur ensemble sont exempts ou collectivement, elles puissent influer sur les décisions économiques que les utilisateurs des états de synthèse prennent en se\nd’anomalies significatives, que celles-ci résultent de fraudes ou d’erreurs et de délivrer un rapport de l’auditeur contenant notre opinion. fondant sur ceux-ci.\nL’assurance raisonnable correspond à un niveau élevé d’assurance, qui ne garantit toutefois pas qu’un audit réalisé conformément aux Dans le cadre d’un audit réalisé conformément aux normes de la profession au Maroc, nous exerçons notre jugement professionnel et\nnormes de la profession au Maroc permettra toujours de détecter toute anomalie significative qui pourrait exister. Les anomalies faisons preuve d’esprit critique tout au long de cet audit. En outre :\npeuvent résulter de fraudes ou d’erreurs et elles sont considérées comme significatives lorsqu’il est raisonnable de s’attendre à ce que,\nindividuellement ou collectivement, elles puissent influer sur les décisions économiques que les utilisateurs des états de synthèse • Nous identifions et évaluons les risques que les états de synthèse comportent des anomalies significatives, que celles-ci\nconsolidés prennent en se fondant sur ceux-ci. résultent de fraudes ou d’erreurs, concevons et mettons en œuvre des procédures d’audit en réponse à ces risques, et\nréunissons des éléments probants suffisants et appropriés pour fonder notre opinion. Le risque de non- détection d’une\nDans le cadre d’un audit réalisé conformément aux normes de la profession au Maroc, nous exerçons notre jugement professionnel et anomalie significative résultant d’une fraude est plus élevé que celui d’une anomalie significative résultant d’une erreur,\nfaisons preuve d’esprit critique tout au long de cet audit. En outre : car la fraude peut impliquer la collusion, la falsification, les omissions volontaires, les fausses déclarations ou le\n• Nous identifions et évaluons les risques que les états de synthèse consolidés comportent des anomalies significatives, que contournement du contrôle interne ;\ncelles-ci résultent de fraudes ou d’erreurs, concevons et mettons en œuvre des procédures d’audit en réponse à ces risques, et • Nous acquérons une compréhension des éléments du contrôle interne pertinents pour l’audit afin de concevoir des procédures\nréunissons des éléments probants suffisants et appropriés pour fonder notre opinion. Le risque de non-détection d’une anomalie d’audit appropriées aux circonstances, et non dans le but d’exprimer une opinion sur l’efficacité du contrôle interne de la société ;\nsignificative résultant d’une fraude est plus élevé que celui d’une anomalie significative résultant d’une erreur, car la fraude peut • Nous apprécions le caractère approprié des méthodes comptables retenues et le caractère raisonnable des estimations\nimpliquer la collusion, la falsification, les omissions volontaires, les fausses déclarations ou le contournement du contrôle interne ;\ncomptables faites par la direction, de même que des informations y afférentes fournies par cette dernière ;\n• Nous acquérons une compréhension des éléments du contrôle interne pertinents pour l’audit afin de concevoir des procédures\nd’audit appropriées aux circonstances, et non dans le but d’exprimer une opinion sur l’efficacité du contrôle interne du groupe ; • Nous tirons une conclusion quant au caractère approprié de l’utilisation par la direction du principe comptable de continuité\nd’exploitation et, selon les éléments probants obtenus, quant à l’existence ou non d’une incertitude significative liée à des\n• Nous apprécions le caractère approprié des méthodes comptables retenues et le caractère raisonnable des événements ou situations susceptibles de jeter un doute important sur la capacité de la société à poursuivre son exploitation.\nestimations comptables faites par la direction, de même que des informations y afférentes fournies par cette dernière ; Si nous concluons à l’existence d’une incertitude significative, nous sommes tenus d’attirer l’attention des lecteurs de notre\n• Nous tirons une conclusion quant au caractère approprié de l’utilisation par la direction du principe comptable de continuité rapport sur les informations fournies dans les états de synthèse au sujet de cette incertitude ou, si ces informations ne sont\nd’exploitation et, selon les éléments probants obtenus, quant à l’existence ou non d’une incertitude significative liée à des pas adéquates, d’exprimer une opinion modifiée. Nos conclusions s’appuient sur les éléments probants obtenus jusqu’à la\névénements ou situations susceptibles de jeter un doute important sur la capacité du groupe à poursuivre son exploitation. Si date de notre rapport. Des événements ou situations futurs pourraient par ailleurs amener la société à cesser son exploitation ;\nnous concluons à l’existence d’une incertitude significative, nous sommes tenus d’attirer l’attention des lecteurs de notre rapport\nsur les informations fournies dans les états de synthèse consolidés au sujet de cette incertitude ou, si ces informations ne sont • Nous évaluons la présentation d’ensemble, la structure et le contenu des états de synthèse, y compris les informations fournies\npas adéquates, d’exprimer une opinion modifiée. Nos conclusions s’appuient sur les éléments probants obtenus jusqu’à la date dans l’ETIC, et apprécions si les états de synthèse représentent les opérations et événements sous-jacents d’une manière\nde notre rapport. Des événements ou situations futurs pourraient par ailleurs amener le groupe à cesser son exploitation ; propre à donner une image fidèle.\n• Nous évaluons la présentation d’ensemble, la structure et le contenu des états de synthèse consolidés, y compris les informations Nous communiquons aux responsables de la gouvernance notamment l’étendue et le calendrier prévus des travaux d’audit et nos\nfournies dans les notes, et apprécions si les états de synthèse consolidés représentent les opérations et événements constatations importantes, y compris toute déficience importante du contrôle interne que nous aurions relevée au cours de notre audit.\nsous-jacents d’une manière propre à donner une image fidèle ; Vérifications et informations spécifiques\n• Nous obtenons des éléments probants suffisants et appropriés concernant les informations financières des entités et activités du Nous avons procédé également aux vérifications spécifiques prévues par la loi et nous nous sommes assurés notamment de la\ngroupe pour exprimer une opinion sur les états de synthèse consolidés. Nous sommes responsables de la direction, de la sincérité et la concordance, des informations données dans le rapport de gestion du Conseil d’administration destiné aux actionnaires\nsupervision et de la réalisation de l’audit du groupe. Nous assumons l’entière responsabilité de l’opinion d’audit. avec les états de synthèse de la société.\nNous communiquons aux responsables de la gouvernance notamment l’étendue et le calendrier prévus des travaux d’audit et nos Casablanca, le 15 avril 2024\nconstatations importantes, y compris toute déficience importante du contrôle interne que nous aurions relevée au cours de notre audit.\nCasablanca, le 15 avril 2024",
    "tables": [
        [
            {
                "Liste des Sociétés": "Disway",
                "% D'intérêt": "Mère",
                "% de contrôle": "Mère",
                "Méthode de consolidation": "Intégration globale"
            },
            {
                "Liste des Sociétés": "Blueway Technology",
                "% D'intérêt": "100%",
                "% de contrôle": "100%",
                "Méthode de consolidation": "Intégration globale"
            },
            {
                "Liste des Sociétés": "Experience Store",
                "% D'intérêt": "100%",
                "% de contrôle": "100%",
                "Méthode de consolidation": "Intégration globale"
            },
            {
                "Liste des Sociétés": "Disway Logistic Services",
                "% D'intérêt": "100%",
                "% de contrôle": "100%",
                "Méthode de consolidation": "Intégration globale"
            },
            {
                "Liste des Sociétés": "Disway MEA",
                "% D'intérêt": "100%",
                "% de contrôle": "100%",
                "Méthode de consolidation": "Intégration globale"
            },
            {
                "Liste des Sociétés": "Disway Tunisie",
                "% D'intérêt": "100%",
                "% de contrôle": "100%",
                "Méthode de consolidation": "Intégration globale"
            }
        ],
        [
            {
                "MASSES": "1\n2",
                "null": "Financement Permanent",
                "Exercice\na": "708 526 092,94",
                "Exercice\nprécédent\nb": "733 405 956,23"
            },
            {
                "MASSES": "",
                "null": "Moins actif immobilisé",
                "Exercice\na": "451 325 281,02",
                "Exercice\nprécédent\nb": "426 657 151,73"
            },
            {
                "MASSES": "3",
                "null": "= Fonds de Roulement Fonctionnel (1-2) (A)",
                "Exercice\na": "257 200 811,92",
                "Exercice\nprécédent\nb": "306 748 804,50"
            },
            {
                "MASSES": "4\n5",
                "null": "Actif circulant",
                "Exercice\na": "671 590 134,21",
                "Exercice\nprécédent\nb": "917 526 993,90"
            },
            {
                "MASSES": "",
                "null": "Moins passif circulant",
                "Exercice\na": "222 832 680,63",
                "Exercice\nprécédent\nb": "374 603 409,60"
            },
            {
                "MASSES": "6",
                "null": "= Besoin de Financement global (4-5) (B)",
                "Exercice\na": "448 757 453,58",
                "Exercice\nprécédent\nb": "542 923 584,30"
            },
            {
                "MASSES": "7",
                "null": "TRESORERIE NETTE (Actif-Passif) = A-B",
                "Exercice\na": "-191 556 641,66",
                "Exercice\nprécédent\nb": "-236 174 779,80"
            }
        ],
        [
            {
                "Variations a-b": "Emplois\nc",
                "null": "Ressources\nd"
            },
            {
                "Variations a-b": "24 879 863,29",
                "null": ""
            },
            {
                "Variations a-b": "24 668 129,29",
                "null": ""
            },
            {
                "Variations a-b": "49 547 992,58",
                "null": ""
            },
            {
                "Variations a-b": "",
                "null": "245 936 859,69"
            },
            {
                "Variations a-b": "151 770 728,97",
                "null": ""
            },
            {
                "Variations a-b": "",
                "null": "94 166 130,72"
            },
            {
                "Variations a-b": "44 618 138,14",
                "null": ""
            }
        ],
        [
            {
                "I RESSOURCES STABLES DE": "",
                "EXERCICE": "EMPLOIS",
                "null": "RESSOURCES"
            },
            {
                "I RESSOURCES STABLES DE": "L'EXERCICE (FLUX)",
                "EXERCICE": "",
                "null": ""
            },
            {
                "I RESSOURCES STABLES DE": "* AUTOFINANCEMENT (A)\n+ Capacité d'autofinancement",
                "EXERCICE": "",
                "null": "-8 989 217,78\n57 012 452,22"
            },
            {
                "I RESSOURCES STABLES DE": "- Distributions de bénéfices",
                "EXERCICE": "66 001 670,00",
                "null": ""
            },
            {
                "I RESSOURCES STABLES DE": "* CESSIONS ET REDUCTIONS\nD'IMMOBILISATIONS (B)",
                "EXERCICE": "",
                "null": "473 574,13"
            },
            {
                "I RESSOURCES STABLES DE": "+ Cessions d'immobilisations incorpor.",
                "EXERCICE": "",
                "null": ""
            },
            {
                "I RESSOURCES STABLES DE": "+ Cessions d'immobilisation corporelles",
                "EXERCICE": "",
                "null": "170 000,00"
            },
            {
                "I RESSOURCES STABLES DE": "+ Cessions d'immobilisation financières",
                "EXERCICE": "",
                "null": "0,00"
            },
            {
                "I RESSOURCES STABLES DE": "+ récupérations sur créances immobilisées",
                "EXERCICE": "",
                "null": "303 574,13"
            },
            {
                "I RESSOURCES STABLES DE": "* AUGMENTATION DES CAPITAUX\nPROPRES ET ASSIMILES (C)",
                "EXERCICE": "0,00",
                "null": "0,00"
            },
            {
                "I RESSOURCES STABLES DE": "+ Augmentation du capital , apports",
                "EXERCICE": "",
                "null": ""
            },
            {
                "I RESSOURCES STABLES DE": "+ Subventions d'investissement",
                "EXERCICE": "",
                "null": "0,00"
            },
            {
                "I RESSOURCES STABLES DE": "AUGMENTATION DES DETTES\nDE FINANCEMENT (D)\n(nettes de primes de remboursement)",
                "EXERCICE": "",
                "null": "0,00"
            },
            {
                "I RESSOURCES STABLES DE": "TOTAL RESSOURCES STABLES\n(A+B+C+D)",
                "EXERCICE": "",
                "null": "-8 515 643,65"
            },
            {
                "I RESSOURCES STABLES DE": "II EMPLOIS STABLES DE L'EXERCICE (FLUX)",
                "EXERCICE": "",
                "null": ""
            },
            {
                "I RESSOURCES STABLES DE": "ACQUISITIONS ET AUGMENTATIONS\nD'IMMOBILISATIONS (E)",
                "EXERCICE": "25 800 051,72",
                "null": ""
            },
            {
                "I RESSOURCES STABLES DE": "+ Acquisitions d'immobilisations incorpor.",
                "EXERCICE": "954 975,16",
                "null": ""
            },
            {
                "I RESSOURCES STABLES DE": "+ Acquisitions d'immobilisation corporelles",
                "EXERCICE": "24 409 076,56",
                "null": ""
            },
            {
                "I RESSOURCES STABLES DE": "+ Acquisitions d'immobilisation financières",
                "EXERCICE": "0,00",
                "null": ""
            },
            {
                "I RESSOURCES STABLES DE": "+ Augmentation des créances immob.",
                "EXERCICE": "436 000,00",
                "null": ""
            },
            {
                "I RESSOURCES STABLES DE": "* REMBOURSEMENT DES CAPITAUX\nPROPRES (F)",
                "EXERCICE": "0,00",
                "null": ""
            },
            {
                "I RESSOURCES STABLES DE": "* REMBOURSEMENTS DES DETTES\nDE FINANCEMENT (G)",
                "EXERCICE": "15 232 297,21",
                "null": ""
            },
            {
                "I RESSOURCES STABLES DE": "* EMPLOIS EN NON VALEURS (H)",
                "EXERCICE": "0,00",
                "null": ""
            },
            {
                "I RESSOURCES STABLES DE": "TOTAL II - EMPLOIS STABLES\n(E+F+G+H)",
                "EXERCICE": "41 032 348,93",
                "null": ""
            },
            {
                "I RESSOURCES STABLES DE": "III VARIATION DU BESOIN DE FINANCEMENT\nGLOBAL (B.F.G)",
                "EXERCICE": "0,00",
                "null": "94 166 130,72"
            },
            {
                "I RESSOURCES STABLES DE": "IV VARIATION DE LA TRESORERIE",
                "EXERCICE": "44 618 138,14",
                "null": "0,00"
            },
            {
                "I RESSOURCES STABLES DE": "TOTAL GENERAL",
                "EXERCICE": "85 650 487,07",
                "null": "85 650 487,07"
            }
        ],
        [
            {
                "EXERCICE PRECEDENT": "EMPLOI",
                "null": "RESSOURCES"
            },
            {
                "EXERCICE PRECEDENT": "",
                "null": ""
            },
            {
                "EXERCICE PRECEDENT": "",
                "null": "-67 043 514,28\n64 959 825,72"
            },
            {
                "EXERCICE PRECEDENT": "132 003 340,00",
                "null": ""
            },
            {
                "EXERCICE PRECEDENT": "",
                "null": "643 749,02"
            },
            {
                "EXERCICE PRECEDENT": "",
                "null": "0,00"
            },
            {
                "EXERCICE PRECEDENT": "",
                "null": "345 000,00"
            },
            {
                "EXERCICE PRECEDENT": "",
                "null": "0,00"
            },
            {
                "EXERCICE PRECEDENT": "",
                "null": "298 749,02"
            },
            {
                "EXERCICE PRECEDENT": "0,00",
                "null": "0,00"
            },
            {
                "EXERCICE PRECEDENT": "",
                "null": ""
            },
            {
                "EXERCICE PRECEDENT": "",
                "null": "0,00"
            },
            {
                "EXERCICE PRECEDENT": "",
                "null": "90 343 200,00"
            },
            {
                "EXERCICE PRECEDENT": "",
                "null": "23 943 434,74"
            },
            {
                "EXERCICE PRECEDENT": "",
                "null": ""
            },
            {
                "EXERCICE PRECEDENT": "81 117 053,85",
                "null": ""
            },
            {
                "EXERCICE PRECEDENT": "0,00",
                "null": ""
            },
            {
                "EXERCICE PRECEDENT": "47 605 109,29",
                "null": ""
            },
            {
                "EXERCICE PRECEDENT": "33 511 944,56",
                "null": ""
            },
            {
                "EXERCICE PRECEDENT": "0,00",
                "null": ""
            },
            {
                "EXERCICE PRECEDENT": "0,00",
                "null": ""
            },
            {
                "EXERCICE PRECEDENT": "7 856 689,64",
                "null": ""
            },
            {
                "EXERCICE PRECEDENT": "0,00",
                "null": ""
            },
            {
                "EXERCICE PRECEDENT": "88 973 743,49",
                "null": ""
            },
            {
                "EXERCICE PRECEDENT": "195 420 318,31",
                "null": "0,00"
            },
            {
                "EXERCICE PRECEDENT": "0,00",
                "null": "260 450 627,06"
            },
            {
                "EXERCICE PRECEDENT": "284 394 061,80",
                "null": "284 394 061,80"
            }
        ]
    ]
}