{
    "text": "Société Fenie Brossette\nS.A au capital de 143.898.400 dirhams www.feniebrossette.ma\nRapport Financier Annuel 2023\nR.C. Casablanca 865 / IF : 01620962 Tél. : +212 (0) 5 22 63 91 00 à 07\nDisponible sur le lien :\nICE : 000084803000004 Fax : +212 (0) 5 22 49 02 27 / 24 91 32\nhttps://www.feniebrossette.ma/communiques-des-resultats/\n284, Boulevard Zerktouni – Casablanca Contact : s.meksi@fenie-brossette.ma\nESILIBOMMI\nFITCA\nTNALUCRIC\nFITCA\nEIREROSERT\nFEN IE B R O SSETTE\nELEM EN TS\nIM M O B ILISA TIO N EN N O N V A LEU R S (A )Frais\nprélim inaires\nCharges à répartir sur plusieurs exercices\nPrim es de rem boursem ent des obligations\nIM M O B ILISA TIO N S IN CO R PO R ELLES (B )Im\nm obilisations en recherche et développem ent\nB revets, m arques, droits et valeurs sim ilaires\nFonds com m ercial\nA utres im m obilisations incorporelles\nIM M O B ILISA TIO N S CO R PO R ELLES ( C )Terrains\nConstructions\nInstallations techniques, m atériel et outillage\nM atériel de transportM\nobilier, M atériel de bureau et am énagem ent divers\nA utres im m obilisations corporelles\nIm m obilisations corporelles en cours\nIM M O B ILISA TIO N S FIN A N CIER ES (D )Prêts\nim m obilisés\nA utres créances financières\nTitres de participation\nA utres titres im m obilisés\nECA R TS D E CO N V ER SIO N A CTIF ( E )D\nim inution des créances im m obilisées\nA ugm entations des dettes de financem ent\nTO TA L I (A + B + C+ D + E)\nStocks (F)M\narchandises\nM atières et fournitures consom m ables\nProduits en cours\nProduits interm édiaires et produits résiduels\nProduits finis\nCR EA N CES D E L'A CTIF CIR CU LA N T (G )Fournis.\ndébiteurs, avances et acom ptes Clients et com ptes rattachés\nPersonnel Etat Com ptes d'associés\nA utres débiteurs\nCom ptes de régularisation - A ctif (H )TITR\nES ET V A LEU R S D E PLA CEM EN T\nECA R TS D E CO N V ER SIO N - A CTIF (I)TO\nTA L II (F+ G + H + I)\nTrésorerie-A ctif\nChèques et valeurs à encaisser\nB anques, T.G et C.C.P\nCaisse, R égie d'avances et accréditifs\nTO TA L III\nT O T A L G EN ER A L I+ II+ III\nB IL A N A C T IF\nB R U T\n6 705 388,90\n6 705 388,90\n5 451 588,99\n5 011 487,99440\n101,00\n237 487 162,7817\n700 000,0061\n577 828,17105\n650 767,999\n392 016,5443\n166 550,08\n482 172,50\n307 299,86174\n872,64\n250 126 313,17182\n201 484,88178\n859 823,02\n3 341 661,86\n463 067 593,9312\n823 109,36402 370 957,33514\n993,8229 522 999,67\n17 835 533,75216\n262,80\n127 437,68645\n612 779,292\n571 325,42101\n125,452\n287 603,35182\n596,622\n571 325,428\n9 8 3 1 0 4 1 7 ,8 8\nA M O R TISSEM EN TS\nET PR O V ISIO N S6\n468 922,15\n6 468 922,15\n4 853 257,06\n4 853 257,06\n179 819 388,95\n42 333 262,4587\n721 497,758\n276 815,0941\n487 813,66\n0,00\n191 141 568,1621\n880 277,5021\n880 277,50\n96 879 073,55\n96 879 073,55\n118 759 351,05\n0,003\n0 9 9 0 0 9 1 9 ,2 1\nEX\nN\nER CICE D U 01/01/2023 A U 31/12/2023\nET A U 31/12/2023 N ET A U 31/12/2022\n236 466,75 220 745,78\n236 466,75 220 745,78\n598 331,93 632 207,79\n158 230,93 192 106,79440\n101,00 440 101,00\n57 667 773,83 62 066 801,5117\n700 000,00 17 700 000,0019\n244 565,72 22 345 908,2417\n929 270,24 20 000 142,651\n115 201,45 127 061,401\n678 736,42 1 893 689,22\n482 172,50 482 172,50\n307 299,86 307 299,86174\n872,64 174 872,64\n58 984 745,01 63 401 927,58160\n321 207,38 209 217 868,14156\n979 545,52 208 814 819,98\n3 341 661,86 403 048,16\n366 188 520,38 301 722 890,3312\n823 109,36 9 803 204,63305 491 883,78 237 238 402,03514\n993,82 453 121,6929 522 999,67 32 259 447,47\n17 835 533,75 21 926 318,21216\n262,80 42 396,30\n127 437,68 1 983 787,43526\n853 428,24 512 924 545,902\n571 325,42 2 310 786,89101\n125,45 64 269,892\n287 603,35 644 314,78182\n596,62 1 602 202,222\n571 325,42 2 310 786,895\n8 8 4 0 9 4 9 8 ,6 7 5 7 8 6 3 7 2 6 0 ,3 7\nCommunication financière au 31 décembre 2023\nComptes sociaux au 31 décembre 2023\nEn mad En mad\nBILAN PASSIF\nFENIE BROSSETTE EXERCICE DU 01/01/2023 AU 31/12/2023\nELEMENTS NET AU 31/12/2023 NET AU 31/12/2022\nTotal des capitaux propres (A) 144 589 725,31 132 850 373,60\nCapital social ou personnel (1) 143 898 400,00 143 898 400,00\nMoins : actionnaires, capital souscrit non appelé\nMoins : Capital appelé 143 898 400,00 143 898 400,00\nMoins : Dont versé 143 898 400,00 143 898 400,00\nPrime d'émission, de fusion, d'apport 66 101 880,00 66 101 880,00\nEcarts de réévaluation\nRéserve légale 14 389 840,00 14 389 840,00\nAutres réserves 37 968 940,64 37 968 940,64\nReport à nouveau (2) -129 508 687,04 -154 032 731,52\nTN Résultats nets en instance d'affectation (2)\nEN\nA M\nR Caé psu itl ata ut\nx\nn pe rt\no\nd pe\nre\nl s' e ax se sr ic mic ie\nlé\n( s2 ()\nB )\n11 739 351,71 24 524 044,48\nR EP Subvention d'investissement\nTN\nEM\nP Pr ro ov vi is si io on ns\ns\nr pé og ul re m amen ot ré tie ss\ns ements dérogatoires\nECN\nA\nP Pr ro ov vi is si io on ns\ns\np po ou ur\nr\np inlu ves- sv ta isl su ee ms ee nn\nt\ni sn stance d'affectation\nN IF Provisions pour acquisition et construction de logement\nAutres provisions réglementées\nDettes de financement (C) 7 593 750,32 13 281 591,64\nEmprunts obligataires\nAutres dettes de financement 7 593 750,32 13 281 591,64\nProvisions durables pour risques et charges (D)\nProvisions pour risques\nProvisions pour charges\nEcarts de conversion-passif (E)\nAugmentation des créances immobilisées\nDiminution des dettes de financement\nTOTAL I (A+B+C+D+E) 152 183 475,63 146 131 965,24\nDettes du passif circulant (F) 304 744 253,32 310 948 086,98\nFournisseurs et comptes rattachés 190 390 651,89 221 318 179,82\nClients créditeurs, avances et acomptes 48 895 572,13 24 544 719,52\nTN A LU\nCR IC FISSA\nP O\nE C\nAte\no\nur agr\nm\ntts ra o\np\nenn sti\ne\nn s csme\nr\nél de a's\na\nn\nss cso ieoc rci sa\nié\nu sx 394 4\n3\n05 0 063 7 605 5\n5\n83 5 146 7 272 5 8,, , ,40 7 398 6\n8\n353 3\n2\n89 8 823 9 742 7\n5\n89 7 104 6 203 9 8,, , ,90 5 305 0\n8\nP Comptes de régularisation passif 14 721 115,59 18 554 545,81\nAutres provisions pour risques et charges (G) 81 004 955,60 85 512 716,68\nEcarts de conversion - passif (Eléments circulants) (H) 899 718,83 439 164,50\nTOTAL II (F+G+H) 386 648 927,75 396 899 968,16\nEIR\nER\nO SER\nT\nT\nC\nC\nBR\nr\nr\naé\né\nnÉ\nd\ndS\nqi\niO\nut ts\ns\neR\nsd\ndE\n'\neR\n(e\ns\nI\ns\nt\noE\nc\nr\nl\néo\nd-\nsm\neP\no\nsA\np\nr\ncetS\nre\nrS\néi\nI\ne\ndF\ni teurs)\n4 49\n63\n5 417 257\n70\n0 009 905 50, ,,2 209\n90\n3 25\n77\n6 780 635\n78\n3 022 846 60, ,,9 807\n89\nTOTAL III 49 577 095,29 35 605 326,97\nTOTAL GENERAL I+II+III 588 409 498,67 578 637 260,37\nEn mad En mad\nCOMPTE DE PRODUITS ET CHARGES (hors taxes) ETAT DES SOLDES DE GESTION (ESG)\nFENIE BROSSETTE EXERCICE DU 01/01/2023 AU 31/12/2023\nFENIE BROSSETTE EXERCICE DU 01/01/2023 AU 31/12/2023\nOPERATIONS OPERATIONS Totaux Totaux\nMODELE NORMAL\nPROPRE A L'EXERCICE EXERCICE PRECEDENT 31/12/2023 31/12/2022 ELEMENTS\nTotaux Totaux\n31/12/2023 31/12/2022\nI - PRODUITS D'EXPLOITATION 614 254 448,17 614 254 448,17 579 832 930,12\nVentes de marchandises (en l'état) 484 268 252,88 484 268 252,88 469 749 652,01 1 Ventes de Marchandises ( en l'état) 484 268 252,88 469 749 652,01\nVentes de biens et services produits 118 698 447,85 118 698 447,85 99 331 627,97 2 - Achats revendus de marchandises 416 791 649,61 387 604 754,12\nChiffre d'affaires 602 966 700,73 602 966 700,73 569 081 279,98\nI MARGE BRUTE SUR VENTES EN L'ETAT 67 476 603,27 82 144 897,89\nVariations des stocks de produits (±) (1)\nImmobilisations produites par l'entreprise pour elle-même 4 049 132,17 4 049 132,17 232 860,30 II + PRODUCTION DE L'EXERCICE 122 747 580,02 99 564 488,27\nN OS Au ub trv ee sn t pi ro on ds\nu\nd it' se x dp 'elo xi pt la ot ii to an\ntion 73 670,50 73 670,50 5 425,12\n3 Ventes de biens et services produits 118 698 447,85 99 331 627,97\nITAReprises d'exploitation; transferts de charges 7 164 944,77 7 164 944,77 10 513 364,72 4 Variation stocks produits\nTIO\nLP X\nET\nI\nAIO\nc\n-\nhT\nC\naA\nH\ntL\nsA\nrRI\neG veE nS dD u' sE X dP eL mOI aT rA chT aIO ndN\nises (2)\n6\n5\n41\n9\n14\n6\n6\n2\n7\n75\n7\n94\n9\n1\n4\n0\n64\n1\n48\n6\n9,\n,\n,1\n0\n67\n2\n1\n6\n5\n41\n9\n14\n6\n6\n2\n7\n75\n7\n94\n9\n1\n4\n0\n64\n1\n48\n6\n9,\n,\n,1\n0\n67\n2\n1\n5\n5\n37\n6\n89\n3\n7\n8\n6\n63\n2\n02\n5\n4\n9\n4\n73\n8\n50\n8\n4,\n,\n,1\n3\n12\n8\n2\nIII\n5\n-\nI Cm Om NSo Ob Mili Msa At Tio In Os\nN\np Sr Dod Eu Li 't Ee Xs\nE\np Ra Cr\nI\nCl' Eentreprise pour elle-même 1224 30 84 99 31 03 02 ,, 41 57\n114\n32 23 02 18 86 10 ,, 83 30\nAchats consommés de matières et de fournitures (2) 69 535 186,56 69 535 186,56 72 832 911,51 6 Achats consommés de matières et fournitures 69 535 186,56 72 832 911,51\nAutres charges externes 52 854 113,89 52 854 113,89 41 487 270,32 7 Autres charges externes 52 854 113,89 41 487 270,32\nImpôts et taxes 332 681,69 332 681,69 1 291 810,45\nIV VALEUR AJOUTEE 67 834 882,84 67 389 204,33\nCharges de personnel 39 843 417,24 39 843 417,24 39 164 675,14\nAutres charges d'exploitation 469 416,54 469 416,54 400 161,87 8 + Subventions d'exploitation\nDotations d'exploitation 16 952 550,49 16 952 550,49 20 843 904,97 9 - Impôts et taxes 332 681,69 1 291 810,45\nTOTAL II 596 779 016,02 596 779 016,02 563 625 488,38\n10 - Charges de personnel 39 843 417,24 39 164 675,14\nIII - RESULTAT D'EXPLOITATION ( I - II ) 17 475 432,15 17 475 432,15 16 207 441,74\nIV - PRODUITS FINANCIERS 3 146 858,32 3 146 858,32 1 250 552,28 EXCEDENT BRUT D'EXPLOITATION (EBE) OU INSUFFISANCE\nProduits des titres de participation et autres titres immobilisés\nV\nBRUTE D'EXPLOITATION(IBE)\n27 658 783,91 26 932 718,74\nGains de change 1 144 202,41 1 144 202,41 972 317,42\nIntérêts et autres produits financiers 18 868,48 18 868,48 12 581,95\n11+ Autres produits d'exploitation 73 670,50 5 425,12\nR EICN AR TOep Tr Ais Le s\nI\nVfinancières; transferts de charges 1\n3\n9 18 43\n6\n7 88 57 8, ,4 33\n2\n1\n3\n9 18 43\n6\n7 88 57 8, ,4 33\n2 1\n22 56 05 56 55 22 ,, 29 81 1 12 3+- A Reu ptr re iss\ne\nc sh da 'r eg xe ps\nl\nod i' te ax tp iolo ni ,t a trt aio nn\nsferts de charges 7\n14 66 49 94 41 46 ,, 75 74\n10\n54 10 30 31 66 41 ,, 78 27\nNV - CHARGES FINANCIERES 7 077 158,15 7 077 158,15 7 084 849,66\nIFCharges\nd'intérêts 5 153 367,13 5 153 367,13 3 295 457,13\n14 - Dotations d'exploitation 16 952 550,49 20 843 904,97\nPertes de change 1 796 353,34 1 796 353,34 1 805 605,10 VI RESULTAT D'EXPLOITATION 17 475 432,15 16 207 441,74\nAutres charges financières VII ± RESULTAT FINANCIER -3 930 299,83 -5 834 297,38\nDotations financières 127 437,68 127 437,68 1 983 787,43\nTOTAL V 7 077 158,15 7 077 158,15 7 084 849,66 VIII RESULTAT COURANT 13 545 132,32 10 373 144,36\nVI - RESULTAT FINANCIER ( IV - V ) -3 930 299,83 -3 930 299,83 -5 834 297,38 IX ± RESULTAT NON COURANT -33 025,61 16 431 956,12\nVII - RESULTAT COURANT ( III + V I) 13 545 132,32 13 545 132,32 10 373 144,36\n15 - Impôts sur les résultats 1 772 755,00 2 281 056,00\nVIII - PRODUITS NON COURANTS 9 343 924,96 9 343 924,96 55 205 722,94\nProduits des cessions d'immobilisations 3 404 124,67 3 404 124,67 55 013 466,48 X RESULTAT NET DE L'EXERCICE 11-2 7,43995 39541E-,0771 247 5,02748 00454E,-4088\nSubventions d'équilibre\nReprises sur subventions d'investissement\nRésultat net de l'exercice 11 739 351,71 24 524 044,48\nTN A\nR U\nO C N O\nNA\nR\nT I\nVXOeu\na\np\nlt\nT -\ne\nr\nr\nA\nCe\nuis\nHLs\nre\nsA\np\ns\nV nR\nr\nn\nIo eGIod\ntI\nEn\ntu\nS\ne\ni\nc\nst\nNo\ns\ndu\nOn\n'r\naNo\na\nmn\nn\nC\nt\noc\nOe\nro\nUs\ntu\n.;\nR\nr dta\nAr\nen\na\nN\nst\nn\nTs\nis mEf Se mrt os\n.\nd ce\né\ndc éh ea srges 5\n9 9\n6\n3\n32\n35\n4\n78\n07\n3\n62\n1\n7\n9\n90\n03\n2\n56\n81\n4\n09\n4,\n,\n,,\n,2\n9\n50\n95\n6\n74\n4\n5\n9 9\n6\n3\n32\n35\n4\n78\n07\n3\n62\n1\n7\n9\n90\n03\n2\n56\n81\n4\n09\n4,\n,\n,,\n,2\n9\n50\n95\n6\n74\n4\n5 3 35 8\n7\n2 7\n51\n0 7\n09\n5 3\n22\n7 7\n92\n2 6\n15\n2 6\n86\n, ,\n,,\n9 8\n54\n4 2\n76 1\n1\n2\n3\n+\n+\nB\nP\nD\nDeé\no\norn\nt\ntt\na\naé\ne\nt\ntf\ni\nii\no\noce\nn ns\ns\nd fi' ne ax np clo ièi rt ea stion\n11\n8\n7 83 19\n4\n3 15 61 2, ,7 01\n9\n24\n9\n5 42 54\n8\n0 24 64 1, ,4 78\n9\nSubventions accordées 4 + Dotations non courantes\nAutres charges non courantes 6 069 545,71 6 069 545,71 680 919,00\n5 - Reprises d'exploitation\nDotations non courantes aux amortisements et aux provisions 3 006 319,92 3 006 319,92 589 929,25\nTOTAL IX 9 376 950,57 9 376 950,57 38 773 766,82 6 - Reprises financières\nX - RESULTAT NON COURANT ( VIII- IX ) -33 025,61 -33 025,61 16 431 956,12 7 - Reprises non courantes (2)(3)\nXI - RESULTAT AVANT IMPOTS ( VII+ X ) 13 512 106,71 13 512 106,71 26 805 100,48 8 - Produits des cessions d'immobilisations (1) 3 404 124,67 55 013 466,48\nXII - IMPOTS SUR LES RESULTATS 1 772 755,00 1 772 755,00 2 281 056,00\nXIII - RESULTAT NET ( XI - XII ) 11 739 351,71 11 739 351,71 24 524 044,48 9 + Valeur nette d'amortissement des immo. cédées 301 084,94 37 502 918,57\nXIV - TOTAL DES PRODUITS ( I + IV + VIII ) 626 745 231,45 626 745 231,45 636 289 205,34 I CAPACITE D'AUTOFINANCEMENT 17 450 474,07 16 471 758,36\nXV - TOTAL DES CHARGES ( II + V + IX + XII ) 615 005 879,74 615 005 879,74 611 765 160,86 10 - Distribution des bénéfices\nXVI - RESULTAT NET ( XIV - XV ) 11 739 351,71 11 739 351,71 24 524 044,48 II AUTOFINANCEMENT 17 450 474,07 16 471 758,36\nSociété Fenie Brossette\nS.A au capital de 143.898.400 dirhams www.feniebrossette.ma\nRapport Financier Annuel 2023\nR.C. Casablanca 865 / IF : 01620962 Tél. : +212 (0) 5 22 63 91 00 à 07\nDisponible sur le lien :\nICE : 000084803000004 Fax : +212 (0) 5 22 49 02 27 / 24 91 32\nhttps://www.feniebrossette.ma/communiques-des-resultats/\n284, Boulevard Zerktouni – Casablanca Contact : s.meksi@fenie-brossette.ma\nFEN IE BROSSETTE\nN ATURE\nIM M OBILISATION EN N ON VALEURSFrais\nprélim inairesCharges\nà répartir sur plusieurs exercicesPrim\ne de rem boursem ent des obligationsIM\nM OBILISATION S IN CORPORELLESIm\nm obilisations en recherche et développem entBrevets,\nm arques, droits et valeurs sim ilairesFonds\ncom m ercialAutres\nim m obilisations incorporellesIM\nM OBILISATION S CORPORELLESTerrainsConstructionsInstallations\ntechniques, m ateriel et outillageM\natériel de transportM\nobilier, m atériel de bureau et am énagem entAutres\nim m obilisations corporellesIm\nm obilisations corporelles en coursTO\nTA L G EN ERA L\nT A B LE A U\nCUM UL\nDEBUT D'EXERCICE\n6 391 717,12\n6 391 717,12\n4 798 236,20\n4 798 236,20\n168 785 026,29\n39 231 919,9380\n429 783,628\n154 760,4540\n968 562,29\n179 974 979,61\nD E S A M O R T ISSE\nDOTATION S\nDE L'EXERCICE\n77 205,03\n77 205,03\n55 020,86\n55 020,86\n8 681 936,20\n3 101 342,514\n898 576,42157\n665,89524\n351,38\n8 814 162,09\nM E N T S\nAM ORTISSEM EN TS SUR\nIM M OBILISATION S SORTIES\n0,00\n1 809 845,11\n1 769 133,8535\n611,255\n100,01\n1 809 845,11\nEXERCICE DU 01/01/2023 AU 31/12/2023\nCUM UL DES AM ORTISSEM EN TS FIN\nD'EXERCICE\n6 468 922,15\n6 468 922,15\n4 853 257,06\n4 853 257,06\n175 657 117,38\n42 333 262,4483\n559 226,198\n276 815,0941\n487 813,66\n186 979 296,59\nTABLEAU DE FINANCEMENT DE L'EXERCICE\nFENIE BROSSETTE EXERCICE DU 01/01/2023 AU 31/12/2023\nI SYNTHESE DES MASSES DU BILAN\nVARIATIONS A-B\nMASSES EX 2E 0R 2C 3I CE EX 2E 0R 2C 2I CE EMPLOIS RESSOURCES\nFinancement Permanent 152 183 475,63 146 131 965,24 6 051 510,39\nMoins actif immobilisé 58 984 745,01 63 401 927,58 4 417 182,57\n= Fonds de Roulement Fonctionnel (1-2) (A) 93 198 730,62 82 730 037,66 10 468 692,96\nActif circulant 526 853 428,24 512 924 545,90 13 928 882,34\nMoins passif circulant 386 648 927,75 396 899 968,35 10 251 040,60\nBESOINS DE FINANCEMENT GLOBAL 140 204 500,49 116 024 577,55 24 179 922,94\nTRESORERIE NETTE (Actif-Passif) = A-B -47 005 769,87 -33 294 539,89 13 711 229,98\nII EMPLOIS ET RESSOURCES\nEXERCICE 2023 EXERCICE 2022\nL'EXERCICE (FLUX)\nEMPLOIS RESSOURCES EMPLOIS RESSOURCES\nAUTOFINANCEMENT (A) 17 450 474,07 16 471 758,36\n+ Capacité d'autofinancement 17 450 474,07 16 471 758,36\n- Distributions de bénéfices\nCESSIONS ET REDUCTIONS D'IMMOBILISATIONS (B) 3 404 124,67 54 998 834,75\nCession d'immob. incorporelles\nCession d'immob. corporelles 3 404 124,67 54 998 834,75\nCession d'immob. financières\nRécupération sur créances immobilisées\nAUGMENTATION DES CAPITAUX PROPRES ET ASSIMILES (C)\n+ Augmentation du capital , apports\n+ Subventions d'investissement\nAUGMENTATION DES DETTES DE FINANCEMENT (D)\nTOTAL RESSOURCES STABLES 20 854 598,74 71 470 593,11\nACQUISITIONS ET AUGMENTATIONS D'IMMOBILISATIONS (E) 4 605 138,46 36 850 077,92\nAcquisitions d'immob. incorporelles 21 145,00\nAcquisitions d'immob. corporelles 4 583 993,46 36 850 077,92\nAcquisitions d'immob. financières\nAcquisitions des créances immob\n* REMBOURSEMENT DES CAPITAUX PROPRES (F)\nREMBOURSSEMENT DES DETTES DE FINANCEMENT (G) 5 687 841,32 10 066 594,08\nEMPLOIS EN NON VALEURS (H) 92 926,00 2 571 972,00\nTOTAL II-EMPLOIS STABLES (E+F+G+H) 10 385 905,78 49 488 644,00\nIII VARIATION DU BESOIN DE FINANCEMENT GLOBAL (B.F.G) 24 179 922,94 58 099 282,73\nIV VARIATION DE LA TRESORERIE 13 711 229,98 36 117 333,62\nTOTAL GENERAL 34 565 828,72 34 565 828,72 107 587 926,73 107 587 926,73\nT A B LE A U D E S IM\nFEN IE B R O SSETTE\nN A TU R E\nIM M O B ILISA TIO N EN N O N V A LEU R SFra\nis p rélim in a iresC\nh a rg es à rép a rtir su r p lu sieu rs exercicesP\nrim e d e rem b ou rsem en t d es ob lig a tion sIM\nM O B ILISA TIO N S IN C O R P O R ELLESIm\nm ob ilisa tion en rech erch e et d évelop p em en tB\nrevets, m a rq u es, d roits et va leu rs sim ila iresFon\nd s com m ercia lA\nu tres im m ob ilisa tion s in corp orellesIM\nM O B ILISA TIO N S C O R P O R ELLESTerra\nin sC\non stru ction sIn\nsta lla tion s tech n iq u es, m a teriel et ou tilla g eM\na tériel d e tra n sp ortM\nob ilier, m a tériel d e b u rea u et a m én a g em en tA\nu tres im m ob ilisa tion s corp orellesIm\nm ob ilisa tion s corp orelles en cou rsT\nO T A L G E N E R A L\nM O B ILIS A T IO N S A U\nM O N TA N T B R U T\nD EB U T D 'EX ER C IC E\n6 6 1 2 4 6 2 ,9 0\n6 6 1 2 4 6 2 ,9 0\n5 4 3 0 4 4 3 ,9 9\n4 9 9 0 3 4 2 ,9 94\n4 0 1 0 1 ,0 0\n2 3 5 0 1 4 0 9 9 ,3 61\n7 7 0 0 0 0 0 ,0 06\n1 5 7 7 8 2 8 ,1 71\n0 4 5 9 2 1 9 7 ,8 38\n2 8 1 8 2 1 ,8 54\n2 8 6 2 2 5 1 ,5 1\n2 4 7 0 5 7 0 0 6 ,2 5\nT R E S Q U E FIN A N\nA U G M EN TA TIO N(A\nq u isition )\n9 2 9 2 6 ,0 0\n9 2 9 2 6 ,0 0\n2 1 1 4 5 ,0 0\n2 1 1 4 5 ,0 0\n4 5 8 3 9 9 3 ,4 6\n2 9 2 6 9 9 1 ,9 01\n3 4 7 6 0 2 ,9 93\n0 9 3 9 8 ,5 7\n4 6 9 8 0 6 4 ,4 6\nC IE R E S\nD U 0 1 /0 1\nD IM IN U TIO N(C\nession )\n2 1 1 0 9 3 0 ,0 4\n1 8 6 8 4 2 1 ,7 42\n3 7 4 0 8 ,3 05\n1 0 0 ,0 0\n2 1 1 0 9 3 0 ,0 4\n/2 0\nM\n2\nO\n3 A U 3 1 /1 2 /2 2 0 2 3\nN TA N T B R U T FIN\nD 'EX ER C IC E\n6 7 0 5 3 8 8 ,9 0\n6 7 0 5 3 8 8 ,9 0\n5 4 5 1 5 8 8 ,9 9\n5 0 1 1 4 8 7 ,9 94\n4 0 1 0 1 ,0 0\n2 3 7 4 8 7 1 6 2 ,7 81\n7 7 0 0 0 0 0 ,0 06\n1 5 7 7 8 2 8 ,1 71\n0 5 6 5 0 7 6 7 ,9 99\n3 9 2 0 1 6 ,5 44\n3 1 6 6 5 5 0 ,0 8\n2 4 9 6 4 4 1 4 0 ,6 7\nTABLEAU DES AMORTISSEMENTS\nFENIE BROSSETTE EXERCICE DU 01/01/2023 AU 31/12/2023\nCUMUL DOTATIONS AMORTISSEMENTS SUR CUMUL DES AMORTISSEMENTS FIN\nNATURE DEBUT D'EXERCICE DE L'EXERCICE IMMOBILISATIONS SORTIES D'EXERCICE\nIMMOBILISATION EN NON VALEURS 6 391 717,12 77 205,03 6 468 922,15\nFrais préliminaires\nCharges à répartir sur plusieurs exercices 6 391 717,12 77 205,03 6 468 922,15\nPrime de remboursement des obligations\nIMMOBILISATIONS INCORPORELLES 4 798 236,20 55 020,86 4 853 257,06\nImmobilisations en recherche et développement\nBrevets, marques, droits et valeurs similaires 4 798 236,20 55 020,86 0,00 4 853 257,06\nFonds commercial\nAutres immobilisations incorporelles\nIMMOBILISATIONS CORPORELLES 168 785 026,29 8 681 936,20 1 809 845,11 175 657 117,38\nTerrains\nConstructions 39 231 919,93 3 101 342,51 42 333 262,44\nInstallations techniques, materiel et outillage 80 429 783,62 4 898 576,42 1 769 133,85 83 559 226,19\nMatériel de transport 8 154 760,45 157 665,89 35 611,25 8 276 815,09\nMobilier, matériel de bureau et aménagement 40 968 562,29 524 351,38 5 100,01 41 487 813,66\nAutres immobilisations corporelles\nImmobilisations corporelles en cours\nTOTAL GENERAL 179 974 979,61 8 814 162,09 1 809 845,11 186 979 296,59\nTABLEAU DES TITRES DE PARTICIPATION\nFENIE BROSSETTE EXERCICE DU 01/01/2023 AU 31/12/2023\nPrix\nRaison sociale de la société Participation au Valeur\nI.F Secteur d'activité Capital social d'acquisition\némettrice capital en % comptable nette\nglobal\nImmobilière le Nôtre 1111111 Immobilière 1% 3 000,00 3 000,00\nSMIRRI 2222222 BTP 1% 100,00 100,00\nFenie Brossette Sénègale 3333333 Autres secteurs 100% 171 772,64 171 772,64\nTOTAL 174 872,64 174 872,64\nT A B L E A U D E C R E A N C E S D E L 'A C T IF C IR C U L A N T\nF E N IE B R O S S E T T E E x e rcice d u 0 1 /0 1 /2 0 2 3 a u 3 1 /1 2 /2 0 2 3\nM o n ta n t a u 3 1 /1 2 /2 0 2 3C\no m p te s M o in s P lu s\nIn tra g ro u p e T o ta ld\n'u n a n d 'u n a nV\nA L E U R S B R U T E SF\no u rn isse u rs d é b ite u rs, a v a n ce s e t a co m p te s 1 2 8 2 3 1 2 8 2 3\nC lie n ts e t co m p te s ra tta ch é s 1 5 5 9 7 3 1 7 5 1 7 8 7 1 2 2 0 4 0 2 3 7 1\nC lie n ts d o u te u x o u litig ie u x - -\nA u tre s clie n ts e t co m p te ra tta ch é s -\nP e rso n n e l : D é b ite u r 5 1 5 5 1 5\nE ta t 2 9 5 2 3 2 9 5 2 3\nC o m p te s d 'a sso cié s - -\nA u tre s d é b ite u rs 1 0 3 6 1 4 7 7 5 1 5 8 1 1\nC ré a n ce s su r ce ssio n d 'a ctifs 2 0 2 4 2 0 2 4\nC o m p te s d e ré g u la risa tio n a ctif 2 1 6 2 1 6\nE ca rt d e C o n v e rsio n A C T IF 1 2 7 1 2 7\nT O T A L D E S C R E A N C E S D E L 'A C T IF C IR C U L A N T 2 0 1 2 0 1 1 7 6 2 1 4 8 5 9 9 5 4 6 3 4 1 0\nP R O V IS IO N SP\nro v isio n s 6 4 8 7 9 3 2 0 0 0 9 6 8 7 9\nV A L E U R S N E T T E ST\nO T A L D E S C R E A N C E S D E L 'A C T IF C IR C U L A N T 2 0 1 2 0 1 1 1 1 3 3 5 5 3 9 9 5 3 6 6 5 3 1\nE N G A G E M E N T S H O R S B IL A N\nFEN IE B R O SSETTE Exercice d u 0 1 /0 1 /2 0 2 3 a u 3 1 /1 2 /2 0 2 3Exercice\n2 0 2 3 Exercice 2 0 2 2ELEM\nEN TS Société Société H ors Société Société H ors\nG rou p e G rou p e G rou p e G rou p eEN\nG A G EM EN TS D O N N ESA\nva ls, ca u tion s & g a ra n ties d on n és 7 8 5 7 9 7 3 0 0 8A\nu tres en g a g em en ts d on n és (C red it d 'en levem en t) 3 5 5 6 7 5 9 4TO\nTA L 8 2 1 3 5 8 0 6 0 1EN\nG A G EM EN TS R EC U STO\nTA L\nCommunication financière au 31 décembre 2023\nComptes sociaux au 31 décembre 2023\nTABLEAU DE FINANCEMENT TABLEAU DES DETTES\nEn mad\nEn K mad\nTABLEAU DES CREANCES\nEn K mad\nTABLEAU DES IMMOBILISATIONS ET AMORTISSEMENTS\nEn mad\nENGAGEMENTS FINANCIERS RECUS OU DONNES HORS OPERATIONS DE CREDIT BAIL\nEn K mad\nEn mad\nCOMMUNICATION FINANCIERE\nRESULTATS AU 31 DECEMBRE 2023\nLe Conseil d’Administration de Fenie Brossette, réuni le 4 mars 2024 sous la Présidence\nde Monsieur Jamal BENYAHIA a examiné l’activité de la société au terme de l’exercice\n2023 et arrêté les comptes au 31 décembre 2023.\nTABLEAU DES PROVISIONS\nEn mad\nFenie Brossette a réalisé au terme de l’exercice 2023 un chiffre d’affaires consolidé de\n603 M MAD enregistrant ainsi une progression de 6% par rapport à l’année précédente.\nCette croissance est le résultat de l’évolution favorable des activités BTP et Industries\nainsi que du Négoce traduisant la continuité de la dynamique commerciale positive\nenregistrée au niveau de toutes ses activités.\nLe résultat d’exploitation a enregistré une progression de 8% soit + 1,2 M MAD et le\nrésultat financier s’est amélioré de +1,9 M MAD. Quant au résultat non courant, il\ns’établit à -0,03 M MAD en 2023 contre 16,4 M MAD à fin décembre 2022 qui\ncorrespondait à une plus-value de cession d’un showroom hors exploitation.\nAinsi, le résultat net social ressort à 11,7 M MAD et le résultat net part du groupe s’établit\nà 7,2 M MAD au titre de l’exercice 2023.\nL’endettement net consolidé se situe à 55 M MAD, en hausse de 8 M MAD par rapport\nà décembre 2022 en raison d’un besoin en fonds de roulement pour accompagner la\nTABLEAU TITRES DE PARTICIPATION\ncroissance de business.\nEn mad\nPerspectives\nFenie Brossette se projette avec dynamisme dans le cadre favorable des projets\nd’infrastructures à l’horizon 2030 ce qui conforte le choix de son plan de développement\npour continuer à assurer la croissance de son chiffre d’affaires et de sa rentabilité.\nCommunication financière au 31 décembre 2023\nComptes sociaux au 31 décembre 2023\nRAPPORT GENERAL DES COMMISSAIRES AUX COMPTES\nSociété Fenie Brossette\nS.A au capital de 143.898.400 dirhams www.feniebrossette.ma\nRapport Financier Annuel 2023\nR.C. Casablanca 865 / IF : 01620962 Tél. : +212 (0) 5 22 63 91 00 à 07\nDisponible sur le lien :\nICE : 000084803000004 Fax : +212 (0) 5 22 49 02 27 / 24 91 32\nhttps://www.feniebrossette.ma/communiques-des-resultats/\n284, Boulevard Zerktouni – Casablanca Contact : s.meksi@fenie-brossette.ma\nELEMENTS\nSociété Fenie Brossette\nS.A au capital de 143.898.400 dirhams www.feniebrossette.ma\nRapport Financier Annuel 2023\nR.C. Casablanca 865 / IF : 01620962 Tél. : +212 (0) 5 22 63 91 00 à 07\nDisponible sur le lien :\nICE : 000084803000004 Fax : +212 (0) 5 22 49 02 27 / 24 91 32\nhttps://www.feniebrossette.ma/communiques-des-resultats/\n284, Boulevard Zerktouni – Casablanca Contact : s.meksi@fenie-brossette.ma\nC P so cia l FB M a ro c 3 1 .1 2 .2 0C\nP co n so lid és G ro u p e FBEC\nA R TP\nro visio n filia les A frica in esSN\nfilia les A frica in esV\na ria tio n réservesElim\ntitresElim\nn o n va leu rsIm\np a ct créd it b a ilIm\np a ct éca rts d e co n versio nR\necla ssem en tEC\nA R T\n2 3\n3 1 -d éc.-2 31\n41\n31-88\n1\n412195\n2\n5\n8\n7\n8\n8\n032\n-9\n7\n8 83\n15\n77\n78\n84\n66\n93\n600\n0-55\n7\n3 1 -d éc.-2 21\n3 21\n2 48-8\n18\n45\n8\n8\n6\n2\n8\n9\n032\n-4\n2\n5 00\n84\n26\n71\n94\n66\n92\n0\n4 1-54\n2\nCommunication financière au 31 décembre 2023\nComptes consolidés au 31 décembre 2023\nBILAN ACTIF CONSOLIDE BILAN PASSIF CONSOLIDE CPC\nEn K mad\nTFT\nVariation Capitaux Propres\nE L E M E N T S\nA ctif im m o b iliséIm\nm o b ilisa tio n s in co rp o re lle sIm\nm o b ilisa tio n s co rp o re lle sIm\nm o b ilisa tio n s fin a n ciè re s\nA ctif circu la n tS\nto ck s e t e n -co u rsC\nré a n ce s clie n tsA\nu tre s d é b ite u rs\nD isp o n ib ilité s & V a le u rs d e p la\nT O T A L A C T IF\nce m e n t\nd é c.-2 3\n5 9 0 4 1\n5 9 85\n7 7 7 36\n7 0\n4 8 3 0 1 6\n1 6 0 3 2 22\n6 6 9 4 45\n5 7 5 0\n2 7 9 3\n5 4 4 8 5 0\nd é c.-2 2\n6 3 5 0 8\n6 3 26\n2 2 0 86\n6 9\n4 6 7 3 5 5\n2 0 9 2 1 71\n9 8 6 9 05\n9 4 4 8\n2 5 3 3\n5 3 3 3 9 7\nE L E M E N T S\nC a p ita u x p ro p re sC\na p ita lC\na p ita l so u scrit n o n a p p e léP\nrim e s d 'é m issio n , d e fu sio n eA\nu tre s re se rv e sR\né su lta t d e l'e x e rciceC\na p ita u x p ro p re s p a rt d u G ro uP\nro v isio n sP\nro v isio n s p o u r risq u e sP\nro v isio n s p o u r ch a rg e sE\nca rt d e co n v e rsio n - p a ssifD\ne tte s fin a n ciè re sD\ne tte s d u p a ssif circu la n tD\ne tte s fo u rn isse u rsA\nu tre s cré d ite u rsT\nré so re rie - P a ssif\nT O T A L P A S S IF\nt d\np e\n'a p p o rts\nd é c.-2 3\n1 3 1 8 3 11\n4 3 8 9 7\n6 6 1 0 2-8\n5 3 9 0\n7 2 2 2\n3 7 0 7 73\n7 0 7 7\n7 6 2 53\n1 8 6 2 81\n9 2 8 7 71\n2 5 7 5 14\n9 6 8 8\n5 4 4 8 5 0\nd é c.-2 2\n1 2 4 6 0 91\n4 3 8 9 7\n6 6 1 0 2-1\n0 5 9 0 02\n0 5 1 0\n3 7 2 1 53\n7 2 1 5\n1 3 3 1 43\n2 2 5 7 42\n2 2 1 6 21\n0 0 4 1 23\n5 6 8 5\n5 3 3 3 9 7\nEn K mad En K mad\nELEM EN TS\nProduits d'exploitation\nChiffre d'affairesA\nutres produits d'exploitationA\nutres reprises d'exploitation\nCharges d'exploitation\nA chats revendus de m archandisesA\nchats consom m és de m atières et fournituresA\nutres charges externesIm\npôts et taxesA\nutres charges d'exploitationFrais\nde personnelD\notations d'exploitationA\nutres dotations d'exploitation\nRésultat d'exploitation\nRésultat financier\nRésultat courant\nRésultat non courant\nRésultat avant im pôts\nIm pôts sur le résultat\nR ésu ltat n et\nR ésu ltat n et part du G rou pe\nIn térêts m in oritaires\ndéc.-2 3\n614 265\n602 9674\n1237\n175\n-597 145\n-416 792-69\n536-53\n117-334-562-39\n843-16\n911-50\n17 120\n-5 120\n12 000\n-3 005\n8 995\n-1 773\n7 2 2 2\n7 2 2 2\n-\ndéc.-2 2\n582 410\n569 08223813\n090\n-563 046\n-387 604-72\n833-40\n156-1\n292-520-39\n165-21\n426-50\n19 364\n-5 272\n14 092\n8 700\n22 791\n-2 281\n2 0 5 1 0\n2 0 5 1 0\n-\nEn K mad\nEn EKL EmMaEdN TS 31-déc-23 31-déc-22\nRésultat net consolidé 7 222 20 510\nVariation des provisions non courantes -139 1 676\nDotations aux amortissements des immobilisations 8 773 10 039\nPrix de cession des immobilisations cédées -3 404 -55 013\nValeur nette comptable des immobilisations cédées 301 38 436\nCapacité d’autofinancement des sociétés intégrées 12 754 15 648\nVariation du Besoin en Fonds de Roulement lié à l’activité -19 605 -58 061\nFlux nets de trésorerie générés par l’activité -6 851 -42 413\nPrix de cession des immobilisations cédées 3 404 55 013\nAcquisition des immobilisations corporelles -4 606 -1 863\nVariation des immobilisations financières -1 1\nFlux nets de trésorerie liés aux opérations d’investissement -1 203 53 151\nEmissions / remboursements d'emprunts -5 689 -41 897\nFlux net de trésorerie liés aux opérations de financement -5 689 -41 897\nRéduction des Capitaux Propres -5 046\nVariation de trésorerie nette -13 743 -36 206\nTrésorerie nette d’ouverture -33 153 3 053\nTrésorerie nette de clôture -46 896 -33 153\nVariation de trésorerie nette -13 743 -36 206\nEn K mad\nCommunication financière au 31 décembre 2023\nNotes relatives aux comptes consolidés\nREFERENTIEL COMPTABLE ✓ Stocks et travaux en cours\nLes stocks et travaux en cours sont évalués au prix de revient sans que celui-ci puisse excéder la valeur\nLes comptes consolidés du Groupe FENIE BROSSETTE sont établis conformément aux normes nationales\nnette de réalisation. Les stocks sont évalués, au coût moyen pondéré ou selon la méthode du premier\nprescrites par la Méthodologie adoptée par le Conseil National de Comptabilité (CNC) dans son avis No\n5 du 26 mai 2005.\nentré - premier sorti (FIFO).\nLes frais financiers ne sont pas pris en compte pour l’évaluation des stocks.\nMODALITES DE CONSOLIDATION Les provisions pour dépréciation des stocks sont constituées le cas échéant pour ramener la valeur nette\ncomptable à la valeur probable de réalisation.\n• Méthode de comptabilisation\nLe Groupe FENIE BROSSETTE contrôle de manière exclusive toutes les entités incluses dans son périmètre ✓ Créances et dettes d’exploitation\nde consolidation. Par conséquent, ces entités sont consolidées par la méthode l’intégration\nLes créances et dettes sont enregistrées à leur valeur nominale. Une provision pour dépréciation des\nglobale.\ncréances est pratiquée à l’apparition d’un risque de non-recouvrement.\nLe contrôle exclusif s’apprécie par le pouvoir de diriger les politiques financières et opérationnelles. Il\nrésulte : Les transactions exprimées en devises étrangères sont converties au cours de change en vigueur au\nmoment de la transaction.\n▪ Soit de la détention directe ou indirecte de la majorité des droits de vote ;\nLors de l'arrêté des comptes, les soldes monétaires en devises sont convertis au taux de clôture par la\n▪ Soit de la désignation, pendant deux exercices successifs, de la majorité des membres des\ncontrepartie du compte de résultat.\norganes d'administration, de direction ou de surveillance.\n• Date de clôture\nINFORMATIONS RELATIVES AU PERIMETRE\nToutes les entités du Groupe clôturent leurs comptes au 31 décembre 2023.\nLa liste des sociétés consolidées au 31 décembre 2023 est la suivante :\n• Principaux retraitements\nLa consolidation est effectuée à partir des comptes individuels des entités comprises dans le périmètre\nde consolidation du Groupe.\nLes principaux retraitements se déclinent comme suit :\n✓ Elimination des opérations intragroupes :\nLes opérations significatives entre les sociétés intégrées sont éliminées du bilan et du compte de produits\net charges consolidés. COMPARABILITE DES COMPTES\n✓ Impôts :\nLa charge d’impôt comprend l’impôt courant de l’exercice et l’impôt différé résultant des décalages Les principes et méthodes de consolidation retenus pour l’exercice 2023 sont les mêmes que ceux\ntemporaires entre le résultat comptable et le résultat fiscal et les retraitements de consolidation. retenus pour l’exercice précédent.\nLes impôts différés actifs résultant des décalages temporaires, des retraitements de consolidatio n et des\ndéficits fiscaux reportables, sont constatés eu égard la situation fiscale de chaque entité, lorsq u’il est INFORMATIONS COMPLEMENTAIRES\nprobable que des bénéfices futurs seront disponibles pour absorber ces impôts différés actifs.\n▪ Actif immobilisé\n✓ Crédit-bail :\nLa société a pris l’option de retraiter les contrats de crédit-bail significatifs. Ce retraitement consiste à ✓ Immobilisations corporelles\ncomptabiliser les immobilisations financées par crédit-bail au bilan en contrepartie d’une dette financière\nLe détail des immobilisations corporelles par nature s’analyse comme suit :\nd’un montant équivalent.\nAu niveau du compte de produits et charges, les redevances sont éliminées et des amortissem ents et des\ncharges d’intérêts sont constatés.\nSur le 1er semestre 2022, le retraitement a été observé pour la période de janvier à mars 2 022. Le\ndénouement de l’opération de lease-back réalisée initialement en avril 2022, s’est opérée par le compte\nde résultat pour solder définitivement les impacts se rapportant à cette opération.\nMETHODES ET REGLES D’EVALUATION\nLes principales méthodes et règles d’évaluation sont les suivantes :\n✓ Immobilisations incorporelles\nLes immobilisations incorporelles sont généralement amorties sur une durée ne dépassant pas cinq ans\n(licences de logiciels).\n✓ Immobilisations corporelles\nLes immobilisations corporelles sont enregistrées à leur coût d’acquisition ou de production. Elles sont\nLa variation des immobilisations corporelles s’analyse comme suit :\namorties sur la durée de vie estimée de chaque catégorie d’immobilisation.\nLes principales durées d’amortissement utilisées sont les suivantes :\nLes plus-values de cession intragroupe sont annulées en consolidation.\nSociété Fenie Brossette\nS.A au capital de 143.898.400 dirhams www.feniebrossette.ma\nRapport Financier Annuel 2023\nR.C. Casablanca 865 / IF : 01620962 Tél. : +212 (0) 5 22 63 91 00 à 07\nDisponible sur le lien :\nICE : 000084803000004 Fax : +212 (0) 5 22 49 02 27 / 24 91 32\nhttps://www.feniebrossette.ma/communiques-des-resultats/\n284, Boulevard Zerktouni – Casablanca Contact : s.meksi@fenie-brossette.ma\nE n K m a d\nImmobilisations corporelles 31-déc.-23 31-déc.-22\nTerrains 17 700 17 700\nConstructions 61 578 61 578\nInstallations techniques, matériel et outillage 106 462 105 403\nMatériel de transport 11 387 10 277\nMobilier, matériel de bureau & aménagements divers44 061 43 756\nImmobilisations corporelles en cours 65 65\nValeurs brutes 241 253 238 779\nAmortissements 183 480 176 571\nValeurs nettes 57 773 62 208\nEn K mad\nCommunication financière au 31 décembre 2023\nNotes relatives aux c omptes consolidés\n✓ Immobilisations financières\nLes immobilisations financières se composent essentiellement des prêts et créances.\n▪ Actif circulant\n✓ Stocks et en cours\nLe détail des stocks et encours par nature s’analyse comme suit :\n(en milliers de DH)\n✓ Autres débiteurs\nLe détail des autres débiteurs par nature s’analyse comme suit :\n▪ Capitaux propres\nVariation des capitaux propres consolidés (et part du groupe)\n▪ Dettes de financement\nLe détail des dettes de financement par nature se présente comme suit\n:\n▪ Provisions non courantes pour risques et charges\nLes provisions non courantes couvrent les risques constitués par les filiales\n▪ Autres créditeurs\nLe détail des autres créditeurs par nature s’analyse comme suit :\nSociété Fenie Brossette\nS.A au capital de 143.898.400 dirhams www.feniebrossette.ma\nRapport Financier Annuel 2023\nR.C. Casablanca 865 / IF : 01620962\nDisponible sur le lien :\nTél. : +212 (0) 5 22 63 91 00 à 07\nICE : 000084803000004 Fax : +212 (0) 5 22 49 02 27 / 24 91 32\nhttps://www.feniebrossette.ma/communiques-des-resultats/\n284, Boulevard Zerktouni – Casablanca Contact : s.meksi@fenie-brossette.ma\nMTBMPN a rch a n d ise sra\nv a u x e n coru\nta\nrch a n d ise sro\nv isio n se\nt\nu rs\n3 1 -d é c.-2 31\n8 3 1 1 3\n3 3 4 2\n1 8 6 4 5 5-\n2 6 1 3 3\n- 2 6 1 3 3\n1 6 0 3 2 2\n3 1 -d é c.-2 22\n3 5 0 2 9\n4 0 3\n2 3 5 4 3 2-\n2 6 2 1 5\n- 2 6 2 1 5\n2 0 9 2 1 7\n(en milliers de DH)\nFo u rn isseu rs d éb iteu rs, a v a n ce s et aP\nerso n n elEta\ntA\nu tres d éb iteu rs d 'ex p lo ita tio nC\no m p tes d e rég u la risa tio n a ctifT\no ta l\nco m p tes\n3 1 -d éc.-2 31\n2 8 6 45\n1 52\n9 6 0 43\n3 3 9\n9 4 2 8\n5 5 7 5 0\n3 1 -d éc.-2 29\n8 4 54\n5 33\n2 3 0 77\n4 3 1\n9 4 1 2\n5 9 4 4 8\n(en milliers de DH)\nC\nC\na p\nRA\na p\nita u x p ro p re s a u 0\né su lta t co n so lid é du\ntre s v a ria tio n s\nita u x p ro p re s a u 3\n1\ne\n1\nja n v ie r 2 0 2\nl’e x e rcice\nd é ce m b re 2\n3\n0 2 3\nT o ta\n1\n1\nl\n2\n3\n4 6 0 8\n7 2 2 2\n1 8 3 1\n(en milliers de DH)\nA utres dettes de financemD\nettes de crédit bailTotal\nent\n31-déc.-237\n625-\n7 625\n31-déc.-2213\n314-\n13 314\n(en milliers de DH)\nAT u tres po\nta l\nro visio n s p o u r risq u es et ch a rg es\n3 1 -d éc.-2 33\n7 0 7 7\n3 7 0 7 7\n3 1 -d éc.-2 23\n7 2 1 5\n3 7 2 1 5\n▪ Chiffre d'affaires\nLe détail du chiffre d’affaires s’analyse comme suit :\n(en milliers de DH) 31-déc.-23 31-déc.-22\nVentes de marchandises en l'état 484 268 469 750\nVentes de biens et services produits 118 699 99 332\nTOTAL 125 751 100 412\n▪ Achats et autres charges externes\nLe détail des achats et autres charges externes s’analyse comme suit :\n(en milliers de DH)\n▪ Résultat financier\nLe détail du résultat financier s’analyse comme suit :\n▪ Résultat non courant\nLe résultat non courant s’analyse comme suit :\n▪ Impôt sur le résultat\nL’impôt sur le résultat s’analyse comme suit :\nLe groupe n’a pas procédé à la comptabilisation des impôts différés actifs sur les déficits fiscaux\nreportables.\nLes impôts différés actifs sur les différences temporaires entre le résultat comptable et le résultat fiscal\net sur les retraitements de consolidation ont été limités à hauteur des impôts différés passifs pour les\ncompenser.\n(en milliers de DH) 31-déc.-23 31-déc.-22\nClients créditeurs, avances et acomptes 48 896 24 544\nPersonnel 4 729 4 127\nOrganismes sociaux 4 131 3 953\nEtat 50 372 46 864\nComptes d'associés\nAutres créanciers 2 860 2 230\nComptes de régularisation passif 14 764 18 694\nTOTAL 125 751 100 412\nAAAT ch a ts reven d u s d e m a rch a n d isesch\na ts co n so m m és d e m a tières et fou\ntres ch a rg es ex tern esO\nT A L\nu rn itu res\n3 1 -d éc.-2 3-4\n1 6 7 9 2-6\n9 5 3 6-5\n3 1 1 7-\n5 3 9 4 4 5\n3 1 -d éc.-2 2-3\n8 7 6 0 4-7\n2 8 3 3-4\n0 1 5 6-\n5 0 0 5 9 3\n(en milliers de DH)\nIm(C(C p ô t ex ig ib leh\na rg es) / p roh\na rg es) / p ro\ndd uu its dits\nd\n’im’im pp ôô ts d ifférést\nco n so lid é\n3 1 -d éc.-2 3-1\n7 7 3\n-\n- 1 7 7 3\n3 1 -d éc.-2 2-2\n2 8 1\n-\n- 2 2 8 1",
    "tables": [
        [
            {
                "BILAN PASSIF\nFENIE BROSSETTE EXERCICE DU 01/01/2023 AU 31/12/2023\nELEMENTS NET AU 31/12/2023 NET AU 31/12/2022\nTotal des capitaux propres (A) 144 589 725,31 132 850 373,60\nCapital social ou personnel (1) 143 898 400,00 143 898 400,00\nMoins : actionnaires, capital souscrit non appelé\nMoins : Capital appelé 143 898 400,00 143 898 400,00\nMoins : Dont versé 143 898 400,00 143 898 400,00\nPrime d'émission, de fusion, d'apport 66 101 880,00 66 101 880,00\nEcarts de réévaluation\nRéserve légale 14 389 840,00 14 389 840,00\nAutres réserves 37 968 940,64 37 968 940,64\nReport à nouveau (2) -129 508 687,04 -154 032 731,52\nTN Résultats nets en instance d'affectation (2)\nEN Résultat net de l'exercice (2) 11 739 351,71 24 524 044,48\nA M Capitaux propres assimilés (B)\nR EP Subvention d'investissement\nTN P Pr ro ov vi is si io on ns r pé og ul re m amen ot ré tie ss\nEM s s ements dérogatoires\nECN P Pr ro ov vi is si io on ns p po ou ur p inlu ves- sv ta isl su ee ms ee nn i sn stance d'affectation\nA s r t\nN IF Provisions pour acquisition et construction de logement\nAutres provisions réglementées\nDettes de financement (C) 7 593 750,32 13 281 591,64\nEmprunts obligataires\nAutres dettes de financement 7 593 750,32 13 281 591,64\nProvisions durables pour risques et charges (D)\nProvisions pour risques\nProvisions pour charges\nEcarts de conversion-passif (E)\nAugmentation des créances immobilisées\nDiminution des dettes de financement\nTOTAL I (A+B+C+D+E) 152 183 475,63 146 131 965,24\nDettes du passif circulant (F) 304 744 253,32 310 948 086,98\nFournisseurs et comptes rattachés 190 390 651,89 221 318 179,82\nClients créditeurs, avances et acomptes 48 895 572,13 24 544 719,52\nTN\nA Personnel 4 535 362,08 3 932 943,05\nLU Organismes sociaux 4 075 575,76 3 897 769,50\nCR\nIC E At ua tt 39 0 06 60 8 14 27 8, ,4 39 35 8 82 74 8 10 20 8, ,9 30\nFISSA C o m p este cs éd a'a ns cs ieo rc sié s\nr r 3 5 8 2 5 8\nP Comptes de régularisation passif 14 721 115,59 18 554 545,81\nAutres provisions pour risques et charges (G) 81 004 955,60 85 512 716,68\nEcarts de conversion - passif (Eléments circulants) (H) 899 718,83 439 164,50\nTOTAL II (F+G+H) 386 648 927,75 396 899 968,16\nEIR T CR réÉ dS iO tsR dE 'R eI sE o- mPA ptS eS IF 49 577 095,29 35 605 326,97\nER c\nO SER C Br aé nd qi uts sd e t or lé ds eo sr ce rr éie 463 41 25 70 00 90 50 ,, 20 90 277 78 63 78 02 84 60 ,, 80 89\nT e (s d iteurs)\nTOTAL III 49 577 095,29 35 605 326,97\nTOTAL GENERAL I+II+III 588 409 498,67 578 637 260,37": "ELEMENTS",
                "null": "NET AU 31/12/2023"
            },
            {
                "BILAN PASSIF\nFENIE BROSSETTE EXERCICE DU 01/01/2023 AU 31/12/2023\nELEMENTS NET AU 31/12/2023 NET AU 31/12/2022\nTotal des capitaux propres (A) 144 589 725,31 132 850 373,60\nCapital social ou personnel (1) 143 898 400,00 143 898 400,00\nMoins : actionnaires, capital souscrit non appelé\nMoins : Capital appelé 143 898 400,00 143 898 400,00\nMoins : Dont versé 143 898 400,00 143 898 400,00\nPrime d'émission, de fusion, d'apport 66 101 880,00 66 101 880,00\nEcarts de réévaluation\nRéserve légale 14 389 840,00 14 389 840,00\nAutres réserves 37 968 940,64 37 968 940,64\nReport à nouveau (2) -129 508 687,04 -154 032 731,52\nTN Résultats nets en instance d'affectation (2)\nEN Résultat net de l'exercice (2) 11 739 351,71 24 524 044,48\nA M Capitaux propres assimilés (B)\nR EP Subvention d'investissement\nTN P Pr ro ov vi is si io on ns r pé og ul re m amen ot ré tie ss\nEM s s ements dérogatoires\nECN P Pr ro ov vi is si io on ns p po ou ur p inlu ves- sv ta isl su ee ms ee nn i sn stance d'affectation\nA s r t\nN IF Provisions pour acquisition et construction de logement\nAutres provisions réglementées\nDettes de financement (C) 7 593 750,32 13 281 591,64\nEmprunts obligataires\nAutres dettes de financement 7 593 750,32 13 281 591,64\nProvisions durables pour risques et charges (D)\nProvisions pour risques\nProvisions pour charges\nEcarts de conversion-passif (E)\nAugmentation des créances immobilisées\nDiminution des dettes de financement\nTOTAL I (A+B+C+D+E) 152 183 475,63 146 131 965,24\nDettes du passif circulant (F) 304 744 253,32 310 948 086,98\nFournisseurs et comptes rattachés 190 390 651,89 221 318 179,82\nClients créditeurs, avances et acomptes 48 895 572,13 24 544 719,52\nTN\nA Personnel 4 535 362,08 3 932 943,05\nLU Organismes sociaux 4 075 575,76 3 897 769,50\nCR\nIC E At ua tt 39 0 06 60 8 14 27 8, ,4 39 35 8 82 74 8 10 20 8, ,9 30\nFISSA C o m p este cs éd a'a ns cs ieo rc sié s\nr r 3 5 8 2 5 8\nP Comptes de régularisation passif 14 721 115,59 18 554 545,81\nAutres provisions pour risques et charges (G) 81 004 955,60 85 512 716,68\nEcarts de conversion - passif (Eléments circulants) (H) 899 718,83 439 164,50\nTOTAL II (F+G+H) 386 648 927,75 396 899 968,16\nEIR T CR réÉ dS iO tsR dE 'R eI sE o- mPA ptS eS IF 49 577 095,29 35 605 326,97\nER c\nO SER C Br aé nd qi uts sd e t or lé ds eo sr ce rr éie 463 41 25 70 00 90 50 ,, 20 90 277 78 63 78 02 84 60 ,, 80 89\nT e (s d iteurs)\nTOTAL III 49 577 095,29 35 605 326,97\nTOTAL GENERAL I+II+III 588 409 498,67 578 637 260,37": "TN\nEN\nA\nM\nR\nEP\nTN\nEM\nECN\nA\nN\nIF",
                "null": "144 589 725,31"
            },
            {
                "BILAN PASSIF\nFENIE BROSSETTE EXERCICE DU 01/01/2023 AU 31/12/2023\nELEMENTS NET AU 31/12/2023 NET AU 31/12/2022\nTotal des capitaux propres (A) 144 589 725,31 132 850 373,60\nCapital social ou personnel (1) 143 898 400,00 143 898 400,00\nMoins : actionnaires, capital souscrit non appelé\nMoins : Capital appelé 143 898 400,00 143 898 400,00\nMoins : Dont versé 143 898 400,00 143 898 400,00\nPrime d'émission, de fusion, d'apport 66 101 880,00 66 101 880,00\nEcarts de réévaluation\nRéserve légale 14 389 840,00 14 389 840,00\nAutres réserves 37 968 940,64 37 968 940,64\nReport à nouveau (2) -129 508 687,04 -154 032 731,52\nTN Résultats nets en instance d'affectation (2)\nEN Résultat net de l'exercice (2) 11 739 351,71 24 524 044,48\nA M Capitaux propres assimilés (B)\nR EP Subvention d'investissement\nTN P Pr ro ov vi is si io on ns r pé og ul re m amen ot ré tie ss\nEM s s ements dérogatoires\nECN P Pr ro ov vi is si io on ns p po ou ur p inlu ves- sv ta isl su ee ms ee nn i sn stance d'affectation\nA s r t\nN IF Provisions pour acquisition et construction de logement\nAutres provisions réglementées\nDettes de financement (C) 7 593 750,32 13 281 591,64\nEmprunts obligataires\nAutres dettes de financement 7 593 750,32 13 281 591,64\nProvisions durables pour risques et charges (D)\nProvisions pour risques\nProvisions pour charges\nEcarts de conversion-passif (E)\nAugmentation des créances immobilisées\nDiminution des dettes de financement\nTOTAL I (A+B+C+D+E) 152 183 475,63 146 131 965,24\nDettes du passif circulant (F) 304 744 253,32 310 948 086,98\nFournisseurs et comptes rattachés 190 390 651,89 221 318 179,82\nClients créditeurs, avances et acomptes 48 895 572,13 24 544 719,52\nTN\nA Personnel 4 535 362,08 3 932 943,05\nLU Organismes sociaux 4 075 575,76 3 897 769,50\nCR\nIC E At ua tt 39 0 06 60 8 14 27 8, ,4 39 35 8 82 74 8 10 20 8, ,9 30\nFISSA C o m p este cs éd a'a ns cs ieo rc sié s\nr r 3 5 8 2 5 8\nP Comptes de régularisation passif 14 721 115,59 18 554 545,81\nAutres provisions pour risques et charges (G) 81 004 955,60 85 512 716,68\nEcarts de conversion - passif (Eléments circulants) (H) 899 718,83 439 164,50\nTOTAL II (F+G+H) 386 648 927,75 396 899 968,16\nEIR T CR réÉ dS iO tsR dE 'R eI sE o- mPA ptS eS IF 49 577 095,29 35 605 326,97\nER c\nO SER C Br aé nd qi uts sd e t or lé ds eo sr ce rr éie 463 41 25 70 00 90 50 ,, 20 90 277 78 63 78 02 84 60 ,, 80 89\nT e (s d iteurs)\nTOTAL III 49 577 095,29 35 605 326,97\nTOTAL GENERAL I+II+III 588 409 498,67 578 637 260,37": "",
                "null": "143 898 400,00\n143 898 400,00\n143 898 400,00\n66 101 880,00\n14 389 840,00\n37 968 940,64\n-129 508 687,04\n11 739 351,71"
            },
            {
                "BILAN PASSIF\nFENIE BROSSETTE EXERCICE DU 01/01/2023 AU 31/12/2023\nELEMENTS NET AU 31/12/2023 NET AU 31/12/2022\nTotal des capitaux propres (A) 144 589 725,31 132 850 373,60\nCapital social ou personnel (1) 143 898 400,00 143 898 400,00\nMoins : actionnaires, capital souscrit non appelé\nMoins : Capital appelé 143 898 400,00 143 898 400,00\nMoins : Dont versé 143 898 400,00 143 898 400,00\nPrime d'émission, de fusion, d'apport 66 101 880,00 66 101 880,00\nEcarts de réévaluation\nRéserve légale 14 389 840,00 14 389 840,00\nAutres réserves 37 968 940,64 37 968 940,64\nReport à nouveau (2) -129 508 687,04 -154 032 731,52\nTN Résultats nets en instance d'affectation (2)\nEN Résultat net de l'exercice (2) 11 739 351,71 24 524 044,48\nA M Capitaux propres assimilés (B)\nR EP Subvention d'investissement\nTN P Pr ro ov vi is si io on ns r pé og ul re m amen ot ré tie ss\nEM s s ements dérogatoires\nECN P Pr ro ov vi is si io on ns p po ou ur p inlu ves- sv ta isl su ee ms ee nn i sn stance d'affectation\nA s r t\nN IF Provisions pour acquisition et construction de logement\nAutres provisions réglementées\nDettes de financement (C) 7 593 750,32 13 281 591,64\nEmprunts obligataires\nAutres dettes de financement 7 593 750,32 13 281 591,64\nProvisions durables pour risques et charges (D)\nProvisions pour risques\nProvisions pour charges\nEcarts de conversion-passif (E)\nAugmentation des créances immobilisées\nDiminution des dettes de financement\nTOTAL I (A+B+C+D+E) 152 183 475,63 146 131 965,24\nDettes du passif circulant (F) 304 744 253,32 310 948 086,98\nFournisseurs et comptes rattachés 190 390 651,89 221 318 179,82\nClients créditeurs, avances et acomptes 48 895 572,13 24 544 719,52\nTN\nA Personnel 4 535 362,08 3 932 943,05\nLU Organismes sociaux 4 075 575,76 3 897 769,50\nCR\nIC E At ua tt 39 0 06 60 8 14 27 8, ,4 39 35 8 82 74 8 10 20 8, ,9 30\nFISSA C o m p este cs éd a'a ns cs ieo rc sié s\nr r 3 5 8 2 5 8\nP Comptes de régularisation passif 14 721 115,59 18 554 545,81\nAutres provisions pour risques et charges (G) 81 004 955,60 85 512 716,68\nEcarts de conversion - passif (Eléments circulants) (H) 899 718,83 439 164,50\nTOTAL II (F+G+H) 386 648 927,75 396 899 968,16\nEIR T CR réÉ dS iO tsR dE 'R eI sE o- mPA ptS eS IF 49 577 095,29 35 605 326,97\nER c\nO SER C Br aé nd qi uts sd e t or lé ds eo sr ce rr éie 463 41 25 70 00 90 50 ,, 20 90 277 78 63 78 02 84 60 ,, 80 89\nT e (s d iteurs)\nTOTAL III 49 577 095,29 35 605 326,97\nTOTAL GENERAL I+II+III 588 409 498,67 578 637 260,37": "",
                "null": ""
            },
            {
                "BILAN PASSIF\nFENIE BROSSETTE EXERCICE DU 01/01/2023 AU 31/12/2023\nELEMENTS NET AU 31/12/2023 NET AU 31/12/2022\nTotal des capitaux propres (A) 144 589 725,31 132 850 373,60\nCapital social ou personnel (1) 143 898 400,00 143 898 400,00\nMoins : actionnaires, capital souscrit non appelé\nMoins : Capital appelé 143 898 400,00 143 898 400,00\nMoins : Dont versé 143 898 400,00 143 898 400,00\nPrime d'émission, de fusion, d'apport 66 101 880,00 66 101 880,00\nEcarts de réévaluation\nRéserve légale 14 389 840,00 14 389 840,00\nAutres réserves 37 968 940,64 37 968 940,64\nReport à nouveau (2) -129 508 687,04 -154 032 731,52\nTN Résultats nets en instance d'affectation (2)\nEN Résultat net de l'exercice (2) 11 739 351,71 24 524 044,48\nA M Capitaux propres assimilés (B)\nR EP Subvention d'investissement\nTN P Pr ro ov vi is si io on ns r pé og ul re m amen ot ré tie ss\nEM s s ements dérogatoires\nECN P Pr ro ov vi is si io on ns p po ou ur p inlu ves- sv ta isl su ee ms ee nn i sn stance d'affectation\nA s r t\nN IF Provisions pour acquisition et construction de logement\nAutres provisions réglementées\nDettes de financement (C) 7 593 750,32 13 281 591,64\nEmprunts obligataires\nAutres dettes de financement 7 593 750,32 13 281 591,64\nProvisions durables pour risques et charges (D)\nProvisions pour risques\nProvisions pour charges\nEcarts de conversion-passif (E)\nAugmentation des créances immobilisées\nDiminution des dettes de financement\nTOTAL I (A+B+C+D+E) 152 183 475,63 146 131 965,24\nDettes du passif circulant (F) 304 744 253,32 310 948 086,98\nFournisseurs et comptes rattachés 190 390 651,89 221 318 179,82\nClients créditeurs, avances et acomptes 48 895 572,13 24 544 719,52\nTN\nA Personnel 4 535 362,08 3 932 943,05\nLU Organismes sociaux 4 075 575,76 3 897 769,50\nCR\nIC E At ua tt 39 0 06 60 8 14 27 8, ,4 39 35 8 82 74 8 10 20 8, ,9 30\nFISSA C o m p este cs éd a'a ns cs ieo rc sié s\nr r 3 5 8 2 5 8\nP Comptes de régularisation passif 14 721 115,59 18 554 545,81\nAutres provisions pour risques et charges (G) 81 004 955,60 85 512 716,68\nEcarts de conversion - passif (Eléments circulants) (H) 899 718,83 439 164,50\nTOTAL II (F+G+H) 386 648 927,75 396 899 968,16\nEIR T CR réÉ dS iO tsR dE 'R eI sE o- mPA ptS eS IF 49 577 095,29 35 605 326,97\nER c\nO SER C Br aé nd qi uts sd e t or lé ds eo sr ce rr éie 463 41 25 70 00 90 50 ,, 20 90 277 78 63 78 02 84 60 ,, 80 89\nT e (s d iteurs)\nTOTAL III 49 577 095,29 35 605 326,97\nTOTAL GENERAL I+II+III 588 409 498,67 578 637 260,37": "",
                "null": ""
            },
            {
                "BILAN PASSIF\nFENIE BROSSETTE EXERCICE DU 01/01/2023 AU 31/12/2023\nELEMENTS NET AU 31/12/2023 NET AU 31/12/2022\nTotal des capitaux propres (A) 144 589 725,31 132 850 373,60\nCapital social ou personnel (1) 143 898 400,00 143 898 400,00\nMoins : actionnaires, capital souscrit non appelé\nMoins : Capital appelé 143 898 400,00 143 898 400,00\nMoins : Dont versé 143 898 400,00 143 898 400,00\nPrime d'émission, de fusion, d'apport 66 101 880,00 66 101 880,00\nEcarts de réévaluation\nRéserve légale 14 389 840,00 14 389 840,00\nAutres réserves 37 968 940,64 37 968 940,64\nReport à nouveau (2) -129 508 687,04 -154 032 731,52\nTN Résultats nets en instance d'affectation (2)\nEN Résultat net de l'exercice (2) 11 739 351,71 24 524 044,48\nA M Capitaux propres assimilés (B)\nR EP Subvention d'investissement\nTN P Pr ro ov vi is si io on ns r pé og ul re m amen ot ré tie ss\nEM s s ements dérogatoires\nECN P Pr ro ov vi is si io on ns p po ou ur p inlu ves- sv ta isl su ee ms ee nn i sn stance d'affectation\nA s r t\nN IF Provisions pour acquisition et construction de logement\nAutres provisions réglementées\nDettes de financement (C) 7 593 750,32 13 281 591,64\nEmprunts obligataires\nAutres dettes de financement 7 593 750,32 13 281 591,64\nProvisions durables pour risques et charges (D)\nProvisions pour risques\nProvisions pour charges\nEcarts de conversion-passif (E)\nAugmentation des créances immobilisées\nDiminution des dettes de financement\nTOTAL I (A+B+C+D+E) 152 183 475,63 146 131 965,24\nDettes du passif circulant (F) 304 744 253,32 310 948 086,98\nFournisseurs et comptes rattachés 190 390 651,89 221 318 179,82\nClients créditeurs, avances et acomptes 48 895 572,13 24 544 719,52\nTN\nA Personnel 4 535 362,08 3 932 943,05\nLU Organismes sociaux 4 075 575,76 3 897 769,50\nCR\nIC E At ua tt 39 0 06 60 8 14 27 8, ,4 39 35 8 82 74 8 10 20 8, ,9 30\nFISSA C o m p este cs éd a'a ns cs ieo rc sié s\nr r 3 5 8 2 5 8\nP Comptes de régularisation passif 14 721 115,59 18 554 545,81\nAutres provisions pour risques et charges (G) 81 004 955,60 85 512 716,68\nEcarts de conversion - passif (Eléments circulants) (H) 899 718,83 439 164,50\nTOTAL II (F+G+H) 386 648 927,75 396 899 968,16\nEIR T CR réÉ dS iO tsR dE 'R eI sE o- mPA ptS eS IF 49 577 095,29 35 605 326,97\nER c\nO SER C Br aé nd qi uts sd e t or lé ds eo sr ce rr éie 463 41 25 70 00 90 50 ,, 20 90 277 78 63 78 02 84 60 ,, 80 89\nT e (s d iteurs)\nTOTAL III 49 577 095,29 35 605 326,97\nTOTAL GENERAL I+II+III 588 409 498,67 578 637 260,37": "",
                "null": "7 593 750,32"
            },
            {
                "BILAN PASSIF\nFENIE BROSSETTE EXERCICE DU 01/01/2023 AU 31/12/2023\nELEMENTS NET AU 31/12/2023 NET AU 31/12/2022\nTotal des capitaux propres (A) 144 589 725,31 132 850 373,60\nCapital social ou personnel (1) 143 898 400,00 143 898 400,00\nMoins : actionnaires, capital souscrit non appelé\nMoins : Capital appelé 143 898 400,00 143 898 400,00\nMoins : Dont versé 143 898 400,00 143 898 400,00\nPrime d'émission, de fusion, d'apport 66 101 880,00 66 101 880,00\nEcarts de réévaluation\nRéserve légale 14 389 840,00 14 389 840,00\nAutres réserves 37 968 940,64 37 968 940,64\nReport à nouveau (2) -129 508 687,04 -154 032 731,52\nTN Résultats nets en instance d'affectation (2)\nEN Résultat net de l'exercice (2) 11 739 351,71 24 524 044,48\nA M Capitaux propres assimilés (B)\nR EP Subvention d'investissement\nTN P Pr ro ov vi is si io on ns r pé og ul re m amen ot ré tie ss\nEM s s ements dérogatoires\nECN P Pr ro ov vi is si io on ns p po ou ur p inlu ves- sv ta isl su ee ms ee nn i sn stance d'affectation\nA s r t\nN IF Provisions pour acquisition et construction de logement\nAutres provisions réglementées\nDettes de financement (C) 7 593 750,32 13 281 591,64\nEmprunts obligataires\nAutres dettes de financement 7 593 750,32 13 281 591,64\nProvisions durables pour risques et charges (D)\nProvisions pour risques\nProvisions pour charges\nEcarts de conversion-passif (E)\nAugmentation des créances immobilisées\nDiminution des dettes de financement\nTOTAL I (A+B+C+D+E) 152 183 475,63 146 131 965,24\nDettes du passif circulant (F) 304 744 253,32 310 948 086,98\nFournisseurs et comptes rattachés 190 390 651,89 221 318 179,82\nClients créditeurs, avances et acomptes 48 895 572,13 24 544 719,52\nTN\nA Personnel 4 535 362,08 3 932 943,05\nLU Organismes sociaux 4 075 575,76 3 897 769,50\nCR\nIC E At ua tt 39 0 06 60 8 14 27 8, ,4 39 35 8 82 74 8 10 20 8, ,9 30\nFISSA C o m p este cs éd a'a ns cs ieo rc sié s\nr r 3 5 8 2 5 8\nP Comptes de régularisation passif 14 721 115,59 18 554 545,81\nAutres provisions pour risques et charges (G) 81 004 955,60 85 512 716,68\nEcarts de conversion - passif (Eléments circulants) (H) 899 718,83 439 164,50\nTOTAL II (F+G+H) 386 648 927,75 396 899 968,16\nEIR T CR réÉ dS iO tsR dE 'R eI sE o- mPA ptS eS IF 49 577 095,29 35 605 326,97\nER c\nO SER C Br aé nd qi uts sd e t or lé ds eo sr ce rr éie 463 41 25 70 00 90 50 ,, 20 90 277 78 63 78 02 84 60 ,, 80 89\nT e (s d iteurs)\nTOTAL III 49 577 095,29 35 605 326,97\nTOTAL GENERAL I+II+III 588 409 498,67 578 637 260,37": "",
                "null": "7 593 750,32"
            },
            {
                "BILAN PASSIF\nFENIE BROSSETTE EXERCICE DU 01/01/2023 AU 31/12/2023\nELEMENTS NET AU 31/12/2023 NET AU 31/12/2022\nTotal des capitaux propres (A) 144 589 725,31 132 850 373,60\nCapital social ou personnel (1) 143 898 400,00 143 898 400,00\nMoins : actionnaires, capital souscrit non appelé\nMoins : Capital appelé 143 898 400,00 143 898 400,00\nMoins : Dont versé 143 898 400,00 143 898 400,00\nPrime d'émission, de fusion, d'apport 66 101 880,00 66 101 880,00\nEcarts de réévaluation\nRéserve légale 14 389 840,00 14 389 840,00\nAutres réserves 37 968 940,64 37 968 940,64\nReport à nouveau (2) -129 508 687,04 -154 032 731,52\nTN Résultats nets en instance d'affectation (2)\nEN Résultat net de l'exercice (2) 11 739 351,71 24 524 044,48\nA M Capitaux propres assimilés (B)\nR EP Subvention d'investissement\nTN P Pr ro ov vi is si io on ns r pé og ul re m amen ot ré tie ss\nEM s s ements dérogatoires\nECN P Pr ro ov vi is si io on ns p po ou ur p inlu ves- sv ta isl su ee ms ee nn i sn stance d'affectation\nA s r t\nN IF Provisions pour acquisition et construction de logement\nAutres provisions réglementées\nDettes de financement (C) 7 593 750,32 13 281 591,64\nEmprunts obligataires\nAutres dettes de financement 7 593 750,32 13 281 591,64\nProvisions durables pour risques et charges (D)\nProvisions pour risques\nProvisions pour charges\nEcarts de conversion-passif (E)\nAugmentation des créances immobilisées\nDiminution des dettes de financement\nTOTAL I (A+B+C+D+E) 152 183 475,63 146 131 965,24\nDettes du passif circulant (F) 304 744 253,32 310 948 086,98\nFournisseurs et comptes rattachés 190 390 651,89 221 318 179,82\nClients créditeurs, avances et acomptes 48 895 572,13 24 544 719,52\nTN\nA Personnel 4 535 362,08 3 932 943,05\nLU Organismes sociaux 4 075 575,76 3 897 769,50\nCR\nIC E At ua tt 39 0 06 60 8 14 27 8, ,4 39 35 8 82 74 8 10 20 8, ,9 30\nFISSA C o m p este cs éd a'a ns cs ieo rc sié s\nr r 3 5 8 2 5 8\nP Comptes de régularisation passif 14 721 115,59 18 554 545,81\nAutres provisions pour risques et charges (G) 81 004 955,60 85 512 716,68\nEcarts de conversion - passif (Eléments circulants) (H) 899 718,83 439 164,50\nTOTAL II (F+G+H) 386 648 927,75 396 899 968,16\nEIR T CR réÉ dS iO tsR dE 'R eI sE o- mPA ptS eS IF 49 577 095,29 35 605 326,97\nER c\nO SER C Br aé nd qi uts sd e t or lé ds eo sr ce rr éie 463 41 25 70 00 90 50 ,, 20 90 277 78 63 78 02 84 60 ,, 80 89\nT e (s d iteurs)\nTOTAL III 49 577 095,29 35 605 326,97\nTOTAL GENERAL I+II+III 588 409 498,67 578 637 260,37": "",
                "null": ""
            },
            {
                "BILAN PASSIF\nFENIE BROSSETTE EXERCICE DU 01/01/2023 AU 31/12/2023\nELEMENTS NET AU 31/12/2023 NET AU 31/12/2022\nTotal des capitaux propres (A) 144 589 725,31 132 850 373,60\nCapital social ou personnel (1) 143 898 400,00 143 898 400,00\nMoins : actionnaires, capital souscrit non appelé\nMoins : Capital appelé 143 898 400,00 143 898 400,00\nMoins : Dont versé 143 898 400,00 143 898 400,00\nPrime d'émission, de fusion, d'apport 66 101 880,00 66 101 880,00\nEcarts de réévaluation\nRéserve légale 14 389 840,00 14 389 840,00\nAutres réserves 37 968 940,64 37 968 940,64\nReport à nouveau (2) -129 508 687,04 -154 032 731,52\nTN Résultats nets en instance d'affectation (2)\nEN Résultat net de l'exercice (2) 11 739 351,71 24 524 044,48\nA M Capitaux propres assimilés (B)\nR EP Subvention d'investissement\nTN P Pr ro ov vi is si io on ns r pé og ul re m amen ot ré tie ss\nEM s s ements dérogatoires\nECN P Pr ro ov vi is si io on ns p po ou ur p inlu ves- sv ta isl su ee ms ee nn i sn stance d'affectation\nA s r t\nN IF Provisions pour acquisition et construction de logement\nAutres provisions réglementées\nDettes de financement (C) 7 593 750,32 13 281 591,64\nEmprunts obligataires\nAutres dettes de financement 7 593 750,32 13 281 591,64\nProvisions durables pour risques et charges (D)\nProvisions pour risques\nProvisions pour charges\nEcarts de conversion-passif (E)\nAugmentation des créances immobilisées\nDiminution des dettes de financement\nTOTAL I (A+B+C+D+E) 152 183 475,63 146 131 965,24\nDettes du passif circulant (F) 304 744 253,32 310 948 086,98\nFournisseurs et comptes rattachés 190 390 651,89 221 318 179,82\nClients créditeurs, avances et acomptes 48 895 572,13 24 544 719,52\nTN\nA Personnel 4 535 362,08 3 932 943,05\nLU Organismes sociaux 4 075 575,76 3 897 769,50\nCR\nIC E At ua tt 39 0 06 60 8 14 27 8, ,4 39 35 8 82 74 8 10 20 8, ,9 30\nFISSA C o m p este cs éd a'a ns cs ieo rc sié s\nr r 3 5 8 2 5 8\nP Comptes de régularisation passif 14 721 115,59 18 554 545,81\nAutres provisions pour risques et charges (G) 81 004 955,60 85 512 716,68\nEcarts de conversion - passif (Eléments circulants) (H) 899 718,83 439 164,50\nTOTAL II (F+G+H) 386 648 927,75 396 899 968,16\nEIR T CR réÉ dS iO tsR dE 'R eI sE o- mPA ptS eS IF 49 577 095,29 35 605 326,97\nER c\nO SER C Br aé nd qi uts sd e t or lé ds eo sr ce rr éie 463 41 25 70 00 90 50 ,, 20 90 277 78 63 78 02 84 60 ,, 80 89\nT e (s d iteurs)\nTOTAL III 49 577 095,29 35 605 326,97\nTOTAL GENERAL I+II+III 588 409 498,67 578 637 260,37": "",
                "null": ""
            },
            {
                "BILAN PASSIF\nFENIE BROSSETTE EXERCICE DU 01/01/2023 AU 31/12/2023\nELEMENTS NET AU 31/12/2023 NET AU 31/12/2022\nTotal des capitaux propres (A) 144 589 725,31 132 850 373,60\nCapital social ou personnel (1) 143 898 400,00 143 898 400,00\nMoins : actionnaires, capital souscrit non appelé\nMoins : Capital appelé 143 898 400,00 143 898 400,00\nMoins : Dont versé 143 898 400,00 143 898 400,00\nPrime d'émission, de fusion, d'apport 66 101 880,00 66 101 880,00\nEcarts de réévaluation\nRéserve légale 14 389 840,00 14 389 840,00\nAutres réserves 37 968 940,64 37 968 940,64\nReport à nouveau (2) -129 508 687,04 -154 032 731,52\nTN Résultats nets en instance d'affectation (2)\nEN Résultat net de l'exercice (2) 11 739 351,71 24 524 044,48\nA M Capitaux propres assimilés (B)\nR EP Subvention d'investissement\nTN P Pr ro ov vi is si io on ns r pé og ul re m amen ot ré tie ss\nEM s s ements dérogatoires\nECN P Pr ro ov vi is si io on ns p po ou ur p inlu ves- sv ta isl su ee ms ee nn i sn stance d'affectation\nA s r t\nN IF Provisions pour acquisition et construction de logement\nAutres provisions réglementées\nDettes de financement (C) 7 593 750,32 13 281 591,64\nEmprunts obligataires\nAutres dettes de financement 7 593 750,32 13 281 591,64\nProvisions durables pour risques et charges (D)\nProvisions pour risques\nProvisions pour charges\nEcarts de conversion-passif (E)\nAugmentation des créances immobilisées\nDiminution des dettes de financement\nTOTAL I (A+B+C+D+E) 152 183 475,63 146 131 965,24\nDettes du passif circulant (F) 304 744 253,32 310 948 086,98\nFournisseurs et comptes rattachés 190 390 651,89 221 318 179,82\nClients créditeurs, avances et acomptes 48 895 572,13 24 544 719,52\nTN\nA Personnel 4 535 362,08 3 932 943,05\nLU Organismes sociaux 4 075 575,76 3 897 769,50\nCR\nIC E At ua tt 39 0 06 60 8 14 27 8, ,4 39 35 8 82 74 8 10 20 8, ,9 30\nFISSA C o m p este cs éd a'a ns cs ieo rc sié s\nr r 3 5 8 2 5 8\nP Comptes de régularisation passif 14 721 115,59 18 554 545,81\nAutres provisions pour risques et charges (G) 81 004 955,60 85 512 716,68\nEcarts de conversion - passif (Eléments circulants) (H) 899 718,83 439 164,50\nTOTAL II (F+G+H) 386 648 927,75 396 899 968,16\nEIR T CR réÉ dS iO tsR dE 'R eI sE o- mPA ptS eS IF 49 577 095,29 35 605 326,97\nER c\nO SER C Br aé nd qi uts sd e t or lé ds eo sr ce rr éie 463 41 25 70 00 90 50 ,, 20 90 277 78 63 78 02 84 60 ,, 80 89\nT e (s d iteurs)\nTOTAL III 49 577 095,29 35 605 326,97\nTOTAL GENERAL I+II+III 588 409 498,67 578 637 260,37": "",
                "null": ""
            },
            {
                "BILAN PASSIF\nFENIE BROSSETTE EXERCICE DU 01/01/2023 AU 31/12/2023\nELEMENTS NET AU 31/12/2023 NET AU 31/12/2022\nTotal des capitaux propres (A) 144 589 725,31 132 850 373,60\nCapital social ou personnel (1) 143 898 400,00 143 898 400,00\nMoins : actionnaires, capital souscrit non appelé\nMoins : Capital appelé 143 898 400,00 143 898 400,00\nMoins : Dont versé 143 898 400,00 143 898 400,00\nPrime d'émission, de fusion, d'apport 66 101 880,00 66 101 880,00\nEcarts de réévaluation\nRéserve légale 14 389 840,00 14 389 840,00\nAutres réserves 37 968 940,64 37 968 940,64\nReport à nouveau (2) -129 508 687,04 -154 032 731,52\nTN Résultats nets en instance d'affectation (2)\nEN Résultat net de l'exercice (2) 11 739 351,71 24 524 044,48\nA M Capitaux propres assimilés (B)\nR EP Subvention d'investissement\nTN P Pr ro ov vi is si io on ns r pé og ul re m amen ot ré tie ss\nEM s s ements dérogatoires\nECN P Pr ro ov vi is si io on ns p po ou ur p inlu ves- sv ta isl su ee ms ee nn i sn stance d'affectation\nA s r t\nN IF Provisions pour acquisition et construction de logement\nAutres provisions réglementées\nDettes de financement (C) 7 593 750,32 13 281 591,64\nEmprunts obligataires\nAutres dettes de financement 7 593 750,32 13 281 591,64\nProvisions durables pour risques et charges (D)\nProvisions pour risques\nProvisions pour charges\nEcarts de conversion-passif (E)\nAugmentation des créances immobilisées\nDiminution des dettes de financement\nTOTAL I (A+B+C+D+E) 152 183 475,63 146 131 965,24\nDettes du passif circulant (F) 304 744 253,32 310 948 086,98\nFournisseurs et comptes rattachés 190 390 651,89 221 318 179,82\nClients créditeurs, avances et acomptes 48 895 572,13 24 544 719,52\nTN\nA Personnel 4 535 362,08 3 932 943,05\nLU Organismes sociaux 4 075 575,76 3 897 769,50\nCR\nIC E At ua tt 39 0 06 60 8 14 27 8, ,4 39 35 8 82 74 8 10 20 8, ,9 30\nFISSA C o m p este cs éd a'a ns cs ieo rc sié s\nr r 3 5 8 2 5 8\nP Comptes de régularisation passif 14 721 115,59 18 554 545,81\nAutres provisions pour risques et charges (G) 81 004 955,60 85 512 716,68\nEcarts de conversion - passif (Eléments circulants) (H) 899 718,83 439 164,50\nTOTAL II (F+G+H) 386 648 927,75 396 899 968,16\nEIR T CR réÉ dS iO tsR dE 'R eI sE o- mPA ptS eS IF 49 577 095,29 35 605 326,97\nER c\nO SER C Br aé nd qi uts sd e t or lé ds eo sr ce rr éie 463 41 25 70 00 90 50 ,, 20 90 277 78 63 78 02 84 60 ,, 80 89\nT e (s d iteurs)\nTOTAL III 49 577 095,29 35 605 326,97\nTOTAL GENERAL I+II+III 588 409 498,67 578 637 260,37": "",
                "null": ""
            },
            {
                "BILAN PASSIF\nFENIE BROSSETTE EXERCICE DU 01/01/2023 AU 31/12/2023\nELEMENTS NET AU 31/12/2023 NET AU 31/12/2022\nTotal des capitaux propres (A) 144 589 725,31 132 850 373,60\nCapital social ou personnel (1) 143 898 400,00 143 898 400,00\nMoins : actionnaires, capital souscrit non appelé\nMoins : Capital appelé 143 898 400,00 143 898 400,00\nMoins : Dont versé 143 898 400,00 143 898 400,00\nPrime d'émission, de fusion, d'apport 66 101 880,00 66 101 880,00\nEcarts de réévaluation\nRéserve légale 14 389 840,00 14 389 840,00\nAutres réserves 37 968 940,64 37 968 940,64\nReport à nouveau (2) -129 508 687,04 -154 032 731,52\nTN Résultats nets en instance d'affectation (2)\nEN Résultat net de l'exercice (2) 11 739 351,71 24 524 044,48\nA M Capitaux propres assimilés (B)\nR EP Subvention d'investissement\nTN P Pr ro ov vi is si io on ns r pé og ul re m amen ot ré tie ss\nEM s s ements dérogatoires\nECN P Pr ro ov vi is si io on ns p po ou ur p inlu ves- sv ta isl su ee ms ee nn i sn stance d'affectation\nA s r t\nN IF Provisions pour acquisition et construction de logement\nAutres provisions réglementées\nDettes de financement (C) 7 593 750,32 13 281 591,64\nEmprunts obligataires\nAutres dettes de financement 7 593 750,32 13 281 591,64\nProvisions durables pour risques et charges (D)\nProvisions pour risques\nProvisions pour charges\nEcarts de conversion-passif (E)\nAugmentation des créances immobilisées\nDiminution des dettes de financement\nTOTAL I (A+B+C+D+E) 152 183 475,63 146 131 965,24\nDettes du passif circulant (F) 304 744 253,32 310 948 086,98\nFournisseurs et comptes rattachés 190 390 651,89 221 318 179,82\nClients créditeurs, avances et acomptes 48 895 572,13 24 544 719,52\nTN\nA Personnel 4 535 362,08 3 932 943,05\nLU Organismes sociaux 4 075 575,76 3 897 769,50\nCR\nIC E At ua tt 39 0 06 60 8 14 27 8, ,4 39 35 8 82 74 8 10 20 8, ,9 30\nFISSA C o m p este cs éd a'a ns cs ieo rc sié s\nr r 3 5 8 2 5 8\nP Comptes de régularisation passif 14 721 115,59 18 554 545,81\nAutres provisions pour risques et charges (G) 81 004 955,60 85 512 716,68\nEcarts de conversion - passif (Eléments circulants) (H) 899 718,83 439 164,50\nTOTAL II (F+G+H) 386 648 927,75 396 899 968,16\nEIR T CR réÉ dS iO tsR dE 'R eI sE o- mPA ptS eS IF 49 577 095,29 35 605 326,97\nER c\nO SER C Br aé nd qi uts sd e t or lé ds eo sr ce rr éie 463 41 25 70 00 90 50 ,, 20 90 277 78 63 78 02 84 60 ,, 80 89\nT e (s d iteurs)\nTOTAL III 49 577 095,29 35 605 326,97\nTOTAL GENERAL I+II+III 588 409 498,67 578 637 260,37": "TOTAL I (A+B+C+D+E)",
                "null": "152 183 475,63"
            },
            {
                "BILAN PASSIF\nFENIE BROSSETTE EXERCICE DU 01/01/2023 AU 31/12/2023\nELEMENTS NET AU 31/12/2023 NET AU 31/12/2022\nTotal des capitaux propres (A) 144 589 725,31 132 850 373,60\nCapital social ou personnel (1) 143 898 400,00 143 898 400,00\nMoins : actionnaires, capital souscrit non appelé\nMoins : Capital appelé 143 898 400,00 143 898 400,00\nMoins : Dont versé 143 898 400,00 143 898 400,00\nPrime d'émission, de fusion, d'apport 66 101 880,00 66 101 880,00\nEcarts de réévaluation\nRéserve légale 14 389 840,00 14 389 840,00\nAutres réserves 37 968 940,64 37 968 940,64\nReport à nouveau (2) -129 508 687,04 -154 032 731,52\nTN Résultats nets en instance d'affectation (2)\nEN Résultat net de l'exercice (2) 11 739 351,71 24 524 044,48\nA M Capitaux propres assimilés (B)\nR EP Subvention d'investissement\nTN P Pr ro ov vi is si io on ns r pé og ul re m amen ot ré tie ss\nEM s s ements dérogatoires\nECN P Pr ro ov vi is si io on ns p po ou ur p inlu ves- sv ta isl su ee ms ee nn i sn stance d'affectation\nA s r t\nN IF Provisions pour acquisition et construction de logement\nAutres provisions réglementées\nDettes de financement (C) 7 593 750,32 13 281 591,64\nEmprunts obligataires\nAutres dettes de financement 7 593 750,32 13 281 591,64\nProvisions durables pour risques et charges (D)\nProvisions pour risques\nProvisions pour charges\nEcarts de conversion-passif (E)\nAugmentation des créances immobilisées\nDiminution des dettes de financement\nTOTAL I (A+B+C+D+E) 152 183 475,63 146 131 965,24\nDettes du passif circulant (F) 304 744 253,32 310 948 086,98\nFournisseurs et comptes rattachés 190 390 651,89 221 318 179,82\nClients créditeurs, avances et acomptes 48 895 572,13 24 544 719,52\nTN\nA Personnel 4 535 362,08 3 932 943,05\nLU Organismes sociaux 4 075 575,76 3 897 769,50\nCR\nIC E At ua tt 39 0 06 60 8 14 27 8, ,4 39 35 8 82 74 8 10 20 8, ,9 30\nFISSA C o m p este cs éd a'a ns cs ieo rc sié s\nr r 3 5 8 2 5 8\nP Comptes de régularisation passif 14 721 115,59 18 554 545,81\nAutres provisions pour risques et charges (G) 81 004 955,60 85 512 716,68\nEcarts de conversion - passif (Eléments circulants) (H) 899 718,83 439 164,50\nTOTAL II (F+G+H) 386 648 927,75 396 899 968,16\nEIR T CR réÉ dS iO tsR dE 'R eI sE o- mPA ptS eS IF 49 577 095,29 35 605 326,97\nER c\nO SER C Br aé nd qi uts sd e t or lé ds eo sr ce rr éie 463 41 25 70 00 90 50 ,, 20 90 277 78 63 78 02 84 60 ,, 80 89\nT e (s d iteurs)\nTOTAL III 49 577 095,29 35 605 326,97\nTOTAL GENERAL I+II+III 588 409 498,67 578 637 260,37": "TN\nA\nLU\nCR\nIC\nFISSA\nP",
                "null": "304 744 253,32"
            },
            {
                "BILAN PASSIF\nFENIE BROSSETTE EXERCICE DU 01/01/2023 AU 31/12/2023\nELEMENTS NET AU 31/12/2023 NET AU 31/12/2022\nTotal des capitaux propres (A) 144 589 725,31 132 850 373,60\nCapital social ou personnel (1) 143 898 400,00 143 898 400,00\nMoins : actionnaires, capital souscrit non appelé\nMoins : Capital appelé 143 898 400,00 143 898 400,00\nMoins : Dont versé 143 898 400,00 143 898 400,00\nPrime d'émission, de fusion, d'apport 66 101 880,00 66 101 880,00\nEcarts de réévaluation\nRéserve légale 14 389 840,00 14 389 840,00\nAutres réserves 37 968 940,64 37 968 940,64\nReport à nouveau (2) -129 508 687,04 -154 032 731,52\nTN Résultats nets en instance d'affectation (2)\nEN Résultat net de l'exercice (2) 11 739 351,71 24 524 044,48\nA M Capitaux propres assimilés (B)\nR EP Subvention d'investissement\nTN P Pr ro ov vi is si io on ns r pé og ul re m amen ot ré tie ss\nEM s s ements dérogatoires\nECN P Pr ro ov vi is si io on ns p po ou ur p inlu ves- sv ta isl su ee ms ee nn i sn stance d'affectation\nA s r t\nN IF Provisions pour acquisition et construction de logement\nAutres provisions réglementées\nDettes de financement (C) 7 593 750,32 13 281 591,64\nEmprunts obligataires\nAutres dettes de financement 7 593 750,32 13 281 591,64\nProvisions durables pour risques et charges (D)\nProvisions pour risques\nProvisions pour charges\nEcarts de conversion-passif (E)\nAugmentation des créances immobilisées\nDiminution des dettes de financement\nTOTAL I (A+B+C+D+E) 152 183 475,63 146 131 965,24\nDettes du passif circulant (F) 304 744 253,32 310 948 086,98\nFournisseurs et comptes rattachés 190 390 651,89 221 318 179,82\nClients créditeurs, avances et acomptes 48 895 572,13 24 544 719,52\nTN\nA Personnel 4 535 362,08 3 932 943,05\nLU Organismes sociaux 4 075 575,76 3 897 769,50\nCR\nIC E At ua tt 39 0 06 60 8 14 27 8, ,4 39 35 8 82 74 8 10 20 8, ,9 30\nFISSA C o m p este cs éd a'a ns cs ieo rc sié s\nr r 3 5 8 2 5 8\nP Comptes de régularisation passif 14 721 115,59 18 554 545,81\nAutres provisions pour risques et charges (G) 81 004 955,60 85 512 716,68\nEcarts de conversion - passif (Eléments circulants) (H) 899 718,83 439 164,50\nTOTAL II (F+G+H) 386 648 927,75 396 899 968,16\nEIR T CR réÉ dS iO tsR dE 'R eI sE o- mPA ptS eS IF 49 577 095,29 35 605 326,97\nER c\nO SER C Br aé nd qi uts sd e t or lé ds eo sr ce rr éie 463 41 25 70 00 90 50 ,, 20 90 277 78 63 78 02 84 60 ,, 80 89\nT e (s d iteurs)\nTOTAL III 49 577 095,29 35 605 326,97\nTOTAL GENERAL I+II+III 588 409 498,67 578 637 260,37": "",
                "null": "190 390 651,89\n48 895 572,13\n4 535 362,08\n4 075 575,76\n39 060 847,49\n3 065 128,38\n14 721 115,59"
            },
            {
                "BILAN PASSIF\nFENIE BROSSETTE EXERCICE DU 01/01/2023 AU 31/12/2023\nELEMENTS NET AU 31/12/2023 NET AU 31/12/2022\nTotal des capitaux propres (A) 144 589 725,31 132 850 373,60\nCapital social ou personnel (1) 143 898 400,00 143 898 400,00\nMoins : actionnaires, capital souscrit non appelé\nMoins : Capital appelé 143 898 400,00 143 898 400,00\nMoins : Dont versé 143 898 400,00 143 898 400,00\nPrime d'émission, de fusion, d'apport 66 101 880,00 66 101 880,00\nEcarts de réévaluation\nRéserve légale 14 389 840,00 14 389 840,00\nAutres réserves 37 968 940,64 37 968 940,64\nReport à nouveau (2) -129 508 687,04 -154 032 731,52\nTN Résultats nets en instance d'affectation (2)\nEN Résultat net de l'exercice (2) 11 739 351,71 24 524 044,48\nA M Capitaux propres assimilés (B)\nR EP Subvention d'investissement\nTN P Pr ro ov vi is si io on ns r pé og ul re m amen ot ré tie ss\nEM s s ements dérogatoires\nECN P Pr ro ov vi is si io on ns p po ou ur p inlu ves- sv ta isl su ee ms ee nn i sn stance d'affectation\nA s r t\nN IF Provisions pour acquisition et construction de logement\nAutres provisions réglementées\nDettes de financement (C) 7 593 750,32 13 281 591,64\nEmprunts obligataires\nAutres dettes de financement 7 593 750,32 13 281 591,64\nProvisions durables pour risques et charges (D)\nProvisions pour risques\nProvisions pour charges\nEcarts de conversion-passif (E)\nAugmentation des créances immobilisées\nDiminution des dettes de financement\nTOTAL I (A+B+C+D+E) 152 183 475,63 146 131 965,24\nDettes du passif circulant (F) 304 744 253,32 310 948 086,98\nFournisseurs et comptes rattachés 190 390 651,89 221 318 179,82\nClients créditeurs, avances et acomptes 48 895 572,13 24 544 719,52\nTN\nA Personnel 4 535 362,08 3 932 943,05\nLU Organismes sociaux 4 075 575,76 3 897 769,50\nCR\nIC E At ua tt 39 0 06 60 8 14 27 8, ,4 39 35 8 82 74 8 10 20 8, ,9 30\nFISSA C o m p este cs éd a'a ns cs ieo rc sié s\nr r 3 5 8 2 5 8\nP Comptes de régularisation passif 14 721 115,59 18 554 545,81\nAutres provisions pour risques et charges (G) 81 004 955,60 85 512 716,68\nEcarts de conversion - passif (Eléments circulants) (H) 899 718,83 439 164,50\nTOTAL II (F+G+H) 386 648 927,75 396 899 968,16\nEIR T CR réÉ dS iO tsR dE 'R eI sE o- mPA ptS eS IF 49 577 095,29 35 605 326,97\nER c\nO SER C Br aé nd qi uts sd e t or lé ds eo sr ce rr éie 463 41 25 70 00 90 50 ,, 20 90 277 78 63 78 02 84 60 ,, 80 89\nT e (s d iteurs)\nTOTAL III 49 577 095,29 35 605 326,97\nTOTAL GENERAL I+II+III 588 409 498,67 578 637 260,37": "",
                "null": "81 004 955,60"
            },
            {
                "BILAN PASSIF\nFENIE BROSSETTE EXERCICE DU 01/01/2023 AU 31/12/2023\nELEMENTS NET AU 31/12/2023 NET AU 31/12/2022\nTotal des capitaux propres (A) 144 589 725,31 132 850 373,60\nCapital social ou personnel (1) 143 898 400,00 143 898 400,00\nMoins : actionnaires, capital souscrit non appelé\nMoins : Capital appelé 143 898 400,00 143 898 400,00\nMoins : Dont versé 143 898 400,00 143 898 400,00\nPrime d'émission, de fusion, d'apport 66 101 880,00 66 101 880,00\nEcarts de réévaluation\nRéserve légale 14 389 840,00 14 389 840,00\nAutres réserves 37 968 940,64 37 968 940,64\nReport à nouveau (2) -129 508 687,04 -154 032 731,52\nTN Résultats nets en instance d'affectation (2)\nEN Résultat net de l'exercice (2) 11 739 351,71 24 524 044,48\nA M Capitaux propres assimilés (B)\nR EP Subvention d'investissement\nTN P Pr ro ov vi is si io on ns r pé og ul re m amen ot ré tie ss\nEM s s ements dérogatoires\nECN P Pr ro ov vi is si io on ns p po ou ur p inlu ves- sv ta isl su ee ms ee nn i sn stance d'affectation\nA s r t\nN IF Provisions pour acquisition et construction de logement\nAutres provisions réglementées\nDettes de financement (C) 7 593 750,32 13 281 591,64\nEmprunts obligataires\nAutres dettes de financement 7 593 750,32 13 281 591,64\nProvisions durables pour risques et charges (D)\nProvisions pour risques\nProvisions pour charges\nEcarts de conversion-passif (E)\nAugmentation des créances immobilisées\nDiminution des dettes de financement\nTOTAL I (A+B+C+D+E) 152 183 475,63 146 131 965,24\nDettes du passif circulant (F) 304 744 253,32 310 948 086,98\nFournisseurs et comptes rattachés 190 390 651,89 221 318 179,82\nClients créditeurs, avances et acomptes 48 895 572,13 24 544 719,52\nTN\nA Personnel 4 535 362,08 3 932 943,05\nLU Organismes sociaux 4 075 575,76 3 897 769,50\nCR\nIC E At ua tt 39 0 06 60 8 14 27 8, ,4 39 35 8 82 74 8 10 20 8, ,9 30\nFISSA C o m p este cs éd a'a ns cs ieo rc sié s\nr r 3 5 8 2 5 8\nP Comptes de régularisation passif 14 721 115,59 18 554 545,81\nAutres provisions pour risques et charges (G) 81 004 955,60 85 512 716,68\nEcarts de conversion - passif (Eléments circulants) (H) 899 718,83 439 164,50\nTOTAL II (F+G+H) 386 648 927,75 396 899 968,16\nEIR T CR réÉ dS iO tsR dE 'R eI sE o- mPA ptS eS IF 49 577 095,29 35 605 326,97\nER c\nO SER C Br aé nd qi uts sd e t or lé ds eo sr ce rr éie 463 41 25 70 00 90 50 ,, 20 90 277 78 63 78 02 84 60 ,, 80 89\nT e (s d iteurs)\nTOTAL III 49 577 095,29 35 605 326,97\nTOTAL GENERAL I+II+III 588 409 498,67 578 637 260,37": "",
                "null": "899 718,83"
            },
            {
                "BILAN PASSIF\nFENIE BROSSETTE EXERCICE DU 01/01/2023 AU 31/12/2023\nELEMENTS NET AU 31/12/2023 NET AU 31/12/2022\nTotal des capitaux propres (A) 144 589 725,31 132 850 373,60\nCapital social ou personnel (1) 143 898 400,00 143 898 400,00\nMoins : actionnaires, capital souscrit non appelé\nMoins : Capital appelé 143 898 400,00 143 898 400,00\nMoins : Dont versé 143 898 400,00 143 898 400,00\nPrime d'émission, de fusion, d'apport 66 101 880,00 66 101 880,00\nEcarts de réévaluation\nRéserve légale 14 389 840,00 14 389 840,00\nAutres réserves 37 968 940,64 37 968 940,64\nReport à nouveau (2) -129 508 687,04 -154 032 731,52\nTN Résultats nets en instance d'affectation (2)\nEN Résultat net de l'exercice (2) 11 739 351,71 24 524 044,48\nA M Capitaux propres assimilés (B)\nR EP Subvention d'investissement\nTN P Pr ro ov vi is si io on ns r pé og ul re m amen ot ré tie ss\nEM s s ements dérogatoires\nECN P Pr ro ov vi is si io on ns p po ou ur p inlu ves- sv ta isl su ee ms ee nn i sn stance d'affectation\nA s r t\nN IF Provisions pour acquisition et construction de logement\nAutres provisions réglementées\nDettes de financement (C) 7 593 750,32 13 281 591,64\nEmprunts obligataires\nAutres dettes de financement 7 593 750,32 13 281 591,64\nProvisions durables pour risques et charges (D)\nProvisions pour risques\nProvisions pour charges\nEcarts de conversion-passif (E)\nAugmentation des créances immobilisées\nDiminution des dettes de financement\nTOTAL I (A+B+C+D+E) 152 183 475,63 146 131 965,24\nDettes du passif circulant (F) 304 744 253,32 310 948 086,98\nFournisseurs et comptes rattachés 190 390 651,89 221 318 179,82\nClients créditeurs, avances et acomptes 48 895 572,13 24 544 719,52\nTN\nA Personnel 4 535 362,08 3 932 943,05\nLU Organismes sociaux 4 075 575,76 3 897 769,50\nCR\nIC E At ua tt 39 0 06 60 8 14 27 8, ,4 39 35 8 82 74 8 10 20 8, ,9 30\nFISSA C o m p este cs éd a'a ns cs ieo rc sié s\nr r 3 5 8 2 5 8\nP Comptes de régularisation passif 14 721 115,59 18 554 545,81\nAutres provisions pour risques et charges (G) 81 004 955,60 85 512 716,68\nEcarts de conversion - passif (Eléments circulants) (H) 899 718,83 439 164,50\nTOTAL II (F+G+H) 386 648 927,75 396 899 968,16\nEIR T CR réÉ dS iO tsR dE 'R eI sE o- mPA ptS eS IF 49 577 095,29 35 605 326,97\nER c\nO SER C Br aé nd qi uts sd e t or lé ds eo sr ce rr éie 463 41 25 70 00 90 50 ,, 20 90 277 78 63 78 02 84 60 ,, 80 89\nT e (s d iteurs)\nTOTAL III 49 577 095,29 35 605 326,97\nTOTAL GENERAL I+II+III 588 409 498,67 578 637 260,37": "TOTAL II (F+G+H)",
                "null": "386 648 927,75"
            },
            {
                "BILAN PASSIF\nFENIE BROSSETTE EXERCICE DU 01/01/2023 AU 31/12/2023\nELEMENTS NET AU 31/12/2023 NET AU 31/12/2022\nTotal des capitaux propres (A) 144 589 725,31 132 850 373,60\nCapital social ou personnel (1) 143 898 400,00 143 898 400,00\nMoins : actionnaires, capital souscrit non appelé\nMoins : Capital appelé 143 898 400,00 143 898 400,00\nMoins : Dont versé 143 898 400,00 143 898 400,00\nPrime d'émission, de fusion, d'apport 66 101 880,00 66 101 880,00\nEcarts de réévaluation\nRéserve légale 14 389 840,00 14 389 840,00\nAutres réserves 37 968 940,64 37 968 940,64\nReport à nouveau (2) -129 508 687,04 -154 032 731,52\nTN Résultats nets en instance d'affectation (2)\nEN Résultat net de l'exercice (2) 11 739 351,71 24 524 044,48\nA M Capitaux propres assimilés (B)\nR EP Subvention d'investissement\nTN P Pr ro ov vi is si io on ns r pé og ul re m amen ot ré tie ss\nEM s s ements dérogatoires\nECN P Pr ro ov vi is si io on ns p po ou ur p inlu ves- sv ta isl su ee ms ee nn i sn stance d'affectation\nA s r t\nN IF Provisions pour acquisition et construction de logement\nAutres provisions réglementées\nDettes de financement (C) 7 593 750,32 13 281 591,64\nEmprunts obligataires\nAutres dettes de financement 7 593 750,32 13 281 591,64\nProvisions durables pour risques et charges (D)\nProvisions pour risques\nProvisions pour charges\nEcarts de conversion-passif (E)\nAugmentation des créances immobilisées\nDiminution des dettes de financement\nTOTAL I (A+B+C+D+E) 152 183 475,63 146 131 965,24\nDettes du passif circulant (F) 304 744 253,32 310 948 086,98\nFournisseurs et comptes rattachés 190 390 651,89 221 318 179,82\nClients créditeurs, avances et acomptes 48 895 572,13 24 544 719,52\nTN\nA Personnel 4 535 362,08 3 932 943,05\nLU Organismes sociaux 4 075 575,76 3 897 769,50\nCR\nIC E At ua tt 39 0 06 60 8 14 27 8, ,4 39 35 8 82 74 8 10 20 8, ,9 30\nFISSA C o m p este cs éd a'a ns cs ieo rc sié s\nr r 3 5 8 2 5 8\nP Comptes de régularisation passif 14 721 115,59 18 554 545,81\nAutres provisions pour risques et charges (G) 81 004 955,60 85 512 716,68\nEcarts de conversion - passif (Eléments circulants) (H) 899 718,83 439 164,50\nTOTAL II (F+G+H) 386 648 927,75 396 899 968,16\nEIR T CR réÉ dS iO tsR dE 'R eI sE o- mPA ptS eS IF 49 577 095,29 35 605 326,97\nER c\nO SER C Br aé nd qi uts sd e t or lé ds eo sr ce rr éie 463 41 25 70 00 90 50 ,, 20 90 277 78 63 78 02 84 60 ,, 80 89\nT e (s d iteurs)\nTOTAL III 49 577 095,29 35 605 326,97\nTOTAL GENERAL I+II+III 588 409 498,67 578 637 260,37": "EIR\nER\nO\nSER\nT",
                "null": "49 577 095,29"
            },
            {
                "BILAN PASSIF\nFENIE BROSSETTE EXERCICE DU 01/01/2023 AU 31/12/2023\nELEMENTS NET AU 31/12/2023 NET AU 31/12/2022\nTotal des capitaux propres (A) 144 589 725,31 132 850 373,60\nCapital social ou personnel (1) 143 898 400,00 143 898 400,00\nMoins : actionnaires, capital souscrit non appelé\nMoins : Capital appelé 143 898 400,00 143 898 400,00\nMoins : Dont versé 143 898 400,00 143 898 400,00\nPrime d'émission, de fusion, d'apport 66 101 880,00 66 101 880,00\nEcarts de réévaluation\nRéserve légale 14 389 840,00 14 389 840,00\nAutres réserves 37 968 940,64 37 968 940,64\nReport à nouveau (2) -129 508 687,04 -154 032 731,52\nTN Résultats nets en instance d'affectation (2)\nEN Résultat net de l'exercice (2) 11 739 351,71 24 524 044,48\nA M Capitaux propres assimilés (B)\nR EP Subvention d'investissement\nTN P Pr ro ov vi is si io on ns r pé og ul re m amen ot ré tie ss\nEM s s ements dérogatoires\nECN P Pr ro ov vi is si io on ns p po ou ur p inlu ves- sv ta isl su ee ms ee nn i sn stance d'affectation\nA s r t\nN IF Provisions pour acquisition et construction de logement\nAutres provisions réglementées\nDettes de financement (C) 7 593 750,32 13 281 591,64\nEmprunts obligataires\nAutres dettes de financement 7 593 750,32 13 281 591,64\nProvisions durables pour risques et charges (D)\nProvisions pour risques\nProvisions pour charges\nEcarts de conversion-passif (E)\nAugmentation des créances immobilisées\nDiminution des dettes de financement\nTOTAL I (A+B+C+D+E) 152 183 475,63 146 131 965,24\nDettes du passif circulant (F) 304 744 253,32 310 948 086,98\nFournisseurs et comptes rattachés 190 390 651,89 221 318 179,82\nClients créditeurs, avances et acomptes 48 895 572,13 24 544 719,52\nTN\nA Personnel 4 535 362,08 3 932 943,05\nLU Organismes sociaux 4 075 575,76 3 897 769,50\nCR\nIC E At ua tt 39 0 06 60 8 14 27 8, ,4 39 35 8 82 74 8 10 20 8, ,9 30\nFISSA C o m p este cs éd a'a ns cs ieo rc sié s\nr r 3 5 8 2 5 8\nP Comptes de régularisation passif 14 721 115,59 18 554 545,81\nAutres provisions pour risques et charges (G) 81 004 955,60 85 512 716,68\nEcarts de conversion - passif (Eléments circulants) (H) 899 718,83 439 164,50\nTOTAL II (F+G+H) 386 648 927,75 396 899 968,16\nEIR T CR réÉ dS iO tsR dE 'R eI sE o- mPA ptS eS IF 49 577 095,29 35 605 326,97\nER c\nO SER C Br aé nd qi uts sd e t or lé ds eo sr ce rr éie 463 41 25 70 00 90 50 ,, 20 90 277 78 63 78 02 84 60 ,, 80 89\nT e (s d iteurs)\nTOTAL III 49 577 095,29 35 605 326,97\nTOTAL GENERAL I+II+III 588 409 498,67 578 637 260,37": "",
                "null": "3 150 000,00\n46 427 095,29"
            },
            {
                "BILAN PASSIF\nFENIE BROSSETTE EXERCICE DU 01/01/2023 AU 31/12/2023\nELEMENTS NET AU 31/12/2023 NET AU 31/12/2022\nTotal des capitaux propres (A) 144 589 725,31 132 850 373,60\nCapital social ou personnel (1) 143 898 400,00 143 898 400,00\nMoins : actionnaires, capital souscrit non appelé\nMoins : Capital appelé 143 898 400,00 143 898 400,00\nMoins : Dont versé 143 898 400,00 143 898 400,00\nPrime d'émission, de fusion, d'apport 66 101 880,00 66 101 880,00\nEcarts de réévaluation\nRéserve légale 14 389 840,00 14 389 840,00\nAutres réserves 37 968 940,64 37 968 940,64\nReport à nouveau (2) -129 508 687,04 -154 032 731,52\nTN Résultats nets en instance d'affectation (2)\nEN Résultat net de l'exercice (2) 11 739 351,71 24 524 044,48\nA M Capitaux propres assimilés (B)\nR EP Subvention d'investissement\nTN P Pr ro ov vi is si io on ns r pé og ul re m amen ot ré tie ss\nEM s s ements dérogatoires\nECN P Pr ro ov vi is si io on ns p po ou ur p inlu ves- sv ta isl su ee ms ee nn i sn stance d'affectation\nA s r t\nN IF Provisions pour acquisition et construction de logement\nAutres provisions réglementées\nDettes de financement (C) 7 593 750,32 13 281 591,64\nEmprunts obligataires\nAutres dettes de financement 7 593 750,32 13 281 591,64\nProvisions durables pour risques et charges (D)\nProvisions pour risques\nProvisions pour charges\nEcarts de conversion-passif (E)\nAugmentation des créances immobilisées\nDiminution des dettes de financement\nTOTAL I (A+B+C+D+E) 152 183 475,63 146 131 965,24\nDettes du passif circulant (F) 304 744 253,32 310 948 086,98\nFournisseurs et comptes rattachés 190 390 651,89 221 318 179,82\nClients créditeurs, avances et acomptes 48 895 572,13 24 544 719,52\nTN\nA Personnel 4 535 362,08 3 932 943,05\nLU Organismes sociaux 4 075 575,76 3 897 769,50\nCR\nIC E At ua tt 39 0 06 60 8 14 27 8, ,4 39 35 8 82 74 8 10 20 8, ,9 30\nFISSA C o m p este cs éd a'a ns cs ieo rc sié s\nr r 3 5 8 2 5 8\nP Comptes de régularisation passif 14 721 115,59 18 554 545,81\nAutres provisions pour risques et charges (G) 81 004 955,60 85 512 716,68\nEcarts de conversion - passif (Eléments circulants) (H) 899 718,83 439 164,50\nTOTAL II (F+G+H) 386 648 927,75 396 899 968,16\nEIR T CR réÉ dS iO tsR dE 'R eI sE o- mPA ptS eS IF 49 577 095,29 35 605 326,97\nER c\nO SER C Br aé nd qi uts sd e t or lé ds eo sr ce rr éie 463 41 25 70 00 90 50 ,, 20 90 277 78 63 78 02 84 60 ,, 80 89\nT e (s d iteurs)\nTOTAL III 49 577 095,29 35 605 326,97\nTOTAL GENERAL I+II+III 588 409 498,67 578 637 260,37": "TOTAL III",
                "null": "49 577 095,29"
            },
            {
                "BILAN PASSIF\nFENIE BROSSETTE EXERCICE DU 01/01/2023 AU 31/12/2023\nELEMENTS NET AU 31/12/2023 NET AU 31/12/2022\nTotal des capitaux propres (A) 144 589 725,31 132 850 373,60\nCapital social ou personnel (1) 143 898 400,00 143 898 400,00\nMoins : actionnaires, capital souscrit non appelé\nMoins : Capital appelé 143 898 400,00 143 898 400,00\nMoins : Dont versé 143 898 400,00 143 898 400,00\nPrime d'émission, de fusion, d'apport 66 101 880,00 66 101 880,00\nEcarts de réévaluation\nRéserve légale 14 389 840,00 14 389 840,00\nAutres réserves 37 968 940,64 37 968 940,64\nReport à nouveau (2) -129 508 687,04 -154 032 731,52\nTN Résultats nets en instance d'affectation (2)\nEN Résultat net de l'exercice (2) 11 739 351,71 24 524 044,48\nA M Capitaux propres assimilés (B)\nR EP Subvention d'investissement\nTN P Pr ro ov vi is si io on ns r pé og ul re m amen ot ré tie ss\nEM s s ements dérogatoires\nECN P Pr ro ov vi is si io on ns p po ou ur p inlu ves- sv ta isl su ee ms ee nn i sn stance d'affectation\nA s r t\nN IF Provisions pour acquisition et construction de logement\nAutres provisions réglementées\nDettes de financement (C) 7 593 750,32 13 281 591,64\nEmprunts obligataires\nAutres dettes de financement 7 593 750,32 13 281 591,64\nProvisions durables pour risques et charges (D)\nProvisions pour risques\nProvisions pour charges\nEcarts de conversion-passif (E)\nAugmentation des créances immobilisées\nDiminution des dettes de financement\nTOTAL I (A+B+C+D+E) 152 183 475,63 146 131 965,24\nDettes du passif circulant (F) 304 744 253,32 310 948 086,98\nFournisseurs et comptes rattachés 190 390 651,89 221 318 179,82\nClients créditeurs, avances et acomptes 48 895 572,13 24 544 719,52\nTN\nA Personnel 4 535 362,08 3 932 943,05\nLU Organismes sociaux 4 075 575,76 3 897 769,50\nCR\nIC E At ua tt 39 0 06 60 8 14 27 8, ,4 39 35 8 82 74 8 10 20 8, ,9 30\nFISSA C o m p este cs éd a'a ns cs ieo rc sié s\nr r 3 5 8 2 5 8\nP Comptes de régularisation passif 14 721 115,59 18 554 545,81\nAutres provisions pour risques et charges (G) 81 004 955,60 85 512 716,68\nEcarts de conversion - passif (Eléments circulants) (H) 899 718,83 439 164,50\nTOTAL II (F+G+H) 386 648 927,75 396 899 968,16\nEIR T CR réÉ dS iO tsR dE 'R eI sE o- mPA ptS eS IF 49 577 095,29 35 605 326,97\nER c\nO SER C Br aé nd qi uts sd e t or lé ds eo sr ce rr éie 463 41 25 70 00 90 50 ,, 20 90 277 78 63 78 02 84 60 ,, 80 89\nT e (s d iteurs)\nTOTAL III 49 577 095,29 35 605 326,97\nTOTAL GENERAL I+II+III 588 409 498,67 578 637 260,37": "TOTAL GENERAL I+II+III",
                "null": "588 409 498,67"
            }
        ],
        [
            {
                "En mad\nCOMPTE DE PRODUITS ET CHARGES (hors taxes)": "FENIE BROSSETTE EXERCICE DU 01/01/2023 AU 31/12/2023",
                "null": ""
            },
            {
                "En mad\nCOMPTE DE PRODUITS ET CHARGES (hors taxes)": "MODELE NORMAL",
                "null": "Totaux\n31/12/2022"
            },
            {
                "En mad\nCOMPTE DE PRODUITS ET CHARGES (hors taxes)": "N\nO\nITA\nTIO\nLP\nX\nE",
                "null": "579 832 930,12\n469 749 652,01\n99 331 627,97\n569 081 279,98\n232 860,30\n5 425,12\n10 513 364,72"
            },
            {
                "En mad\nCOMPTE DE PRODUITS ET CHARGES (hors taxes)": "",
                "null": ""
            },
            {
                "En mad\nCOMPTE DE PRODUITS ET CHARGES (hors taxes)": "",
                "null": "579 832 930,12"
            },
            {
                "En mad\nCOMPTE DE PRODUITS ET CHARGES (hors taxes)": "",
                "null": "563 625 488,38\n387 604 754,12\n72 832 911,51\n41 487 270,32\n1 291 810,45\n39 164 675,14\n400 161,87\n20 843 904,97"
            },
            {
                "En mad\nCOMPTE DE PRODUITS ET CHARGES (hors taxes)": "",
                "null": ""
            },
            {
                "En mad\nCOMPTE DE PRODUITS ET CHARGES (hors taxes)": "",
                "null": "563 625 488,38"
            },
            {
                "En mad\nCOMPTE DE PRODUITS ET CHARGES (hors taxes)": "",
                "null": "16 207 441,74"
            },
            {
                "En mad\nCOMPTE DE PRODUITS ET CHARGES (hors taxes)": "R\nEICN\nA\nN\nIF",
                "null": "1 250 552,28\n972 317,42\n12 581,95\n265 652,91"
            },
            {
                "En mad\nCOMPTE DE PRODUITS ET CHARGES (hors taxes)": "",
                "null": ""
            },
            {
                "En mad\nCOMPTE DE PRODUITS ET CHARGES (hors taxes)": "",
                "null": "1 250 552,28"
            },
            {
                "En mad\nCOMPTE DE PRODUITS ET CHARGES (hors taxes)": "",
                "null": "7 084 849,66\n3 295 457,13\n1 805 605,10\n1 983 787,43"
            },
            {
                "En mad\nCOMPTE DE PRODUITS ET CHARGES (hors taxes)": "",
                "null": ""
            },
            {
                "En mad\nCOMPTE DE PRODUITS ET CHARGES (hors taxes)": "",
                "null": "7 084 849,66"
            },
            {
                "En mad\nCOMPTE DE PRODUITS ET CHARGES (hors taxes)": "",
                "null": "-5 834 297,38\n10 373 144,36"
            },
            {
                "En mad\nCOMPTE DE PRODUITS ET CHARGES (hors taxes)": "",
                "null": ""
            },
            {
                "En mad\nCOMPTE DE PRODUITS ET CHARGES (hors taxes)": "TN\nA\nR\nU\nO\nC\nN\nO\nN",
                "null": "55 205 722,94\n55 013 466,48\n192 256,46"
            },
            {
                "En mad\nCOMPTE DE PRODUITS ET CHARGES (hors taxes)": "",
                "null": ""
            },
            {
                "En mad\nCOMPTE DE PRODUITS ET CHARGES (hors taxes)": "",
                "null": "55 205 722,94"
            },
            {
                "En mad\nCOMPTE DE PRODUITS ET CHARGES (hors taxes)": "",
                "null": "38 773 766,82\n37 502 918,57\n680 919,00\n589 929,25"
            },
            {
                "En mad\nCOMPTE DE PRODUITS ET CHARGES (hors taxes)": "",
                "null": ""
            },
            {
                "En mad\nCOMPTE DE PRODUITS ET CHARGES (hors taxes)": "",
                "null": "38 773 766,82"
            },
            {
                "En mad\nCOMPTE DE PRODUITS ET CHARGES (hors taxes)": "",
                "null": "16 431 956,12\n26 805 100,48\n2 281 056,00\n24 524 044,48"
            },
            {
                "En mad\nCOMPTE DE PRODUITS ET CHARGES (hors taxes)": "",
                "null": ""
            },
            {
                "En mad\nCOMPTE DE PRODUITS ET CHARGES (hors taxes)": "",
                "null": ""
            },
            {
                "En mad\nCOMPTE DE PRODUITS ET CHARGES (hors taxes)": "",
                "null": ""
            },
            {
                "En mad\nCOMPTE DE PRODUITS ET CHARGES (hors taxes)": "",
                "null": "636 289 205,34\n611 765 160,86\n24 524 044,48"
            },
            {
                "En mad\nCOMPTE DE PRODUITS ET CHARGES (hors taxes)": "",
                "null": ""
            },
            {
                "En mad\nCOMPTE DE PRODUITS ET CHARGES (hors taxes)": "",
                "null": ""
            }
        ],
        [
            {
                "En mad\nETAT DES SOLDES DE GESTION (ESG)": "FENIE BROSSETTE EXERCICE DU 01/01/2023 AU 31/12/2023",
                "null": ""
            },
            {
                "En mad\nETAT DES SOLDES DE GESTION (ESG)": "ELEMENTS",
                "null": "Totaux\n31/12/2022"
            },
            {
                "En mad\nETAT DES SOLDES DE GESTION (ESG)": "",
                "null": "469 749 652,01\n387 604 754,12"
            },
            {
                "En mad\nETAT DES SOLDES DE GESTION (ESG)": "",
                "null": ""
            },
            {
                "En mad\nETAT DES SOLDES DE GESTION (ESG)": "I",
                "null": "82 144 897,89"
            },
            {
                "En mad\nETAT DES SOLDES DE GESTION (ESG)": "II",
                "null": "99 564 488,27"
            },
            {
                "En mad\nETAT DES SOLDES DE GESTION (ESG)": "",
                "null": "99 331 627,97\n232 860,30"
            },
            {
                "En mad\nETAT DES SOLDES DE GESTION (ESG)": "",
                "null": ""
            },
            {
                "En mad\nETAT DES SOLDES DE GESTION (ESG)": "",
                "null": ""
            },
            {
                "En mad\nETAT DES SOLDES DE GESTION (ESG)": "III",
                "null": "114 320 181,83"
            },
            {
                "En mad\nETAT DES SOLDES DE GESTION (ESG)": "",
                "null": "72 832 911,51\n41 487 270,32"
            },
            {
                "En mad\nETAT DES SOLDES DE GESTION (ESG)": "",
                "null": ""
            },
            {
                "En mad\nETAT DES SOLDES DE GESTION (ESG)": "IV",
                "null": "67 389 204,33"
            },
            {
                "En mad\nETAT DES SOLDES DE GESTION (ESG)": "",
                "null": "1 291 810,45\n39 164 675,14"
            },
            {
                "En mad\nETAT DES SOLDES DE GESTION (ESG)": "",
                "null": ""
            },
            {
                "En mad\nETAT DES SOLDES DE GESTION (ESG)": "",
                "null": ""
            },
            {
                "En mad\nETAT DES SOLDES DE GESTION (ESG)": "V",
                "null": "26 932 718,74"
            },
            {
                "En mad\nETAT DES SOLDES DE GESTION (ESG)": "",
                "null": "5 425,12\n400 161,87\n10 513 364,72\n20 843 904,97"
            },
            {
                "En mad\nETAT DES SOLDES DE GESTION (ESG)": "",
                "null": ""
            },
            {
                "En mad\nETAT DES SOLDES DE GESTION (ESG)": "",
                "null": ""
            },
            {
                "En mad\nETAT DES SOLDES DE GESTION (ESG)": "",
                "null": ""
            },
            {
                "En mad\nETAT DES SOLDES DE GESTION (ESG)": "VI",
                "null": "16 207 441,74"
            },
            {
                "En mad\nETAT DES SOLDES DE GESTION (ESG)": "VII",
                "null": "-5 834 297,38"
            },
            {
                "En mad\nETAT DES SOLDES DE GESTION (ESG)": "VIII",
                "null": "10 373 144,36"
            },
            {
                "En mad\nETAT DES SOLDES DE GESTION (ESG)": "IX",
                "null": "16 431 956,12"
            },
            {
                "En mad\nETAT DES SOLDES DE GESTION (ESG)": "",
                "null": "2 281 056,00"
            },
            {
                "En mad\nETAT DES SOLDES DE GESTION (ESG)": "X",
                "null": "247 5,02748 00454E,-4088"
            },
            {
                "En mad\nETAT DES SOLDES DE GESTION (ESG)": "",
                "null": "24 524 044,48"
            },
            {
                "En mad\nETAT DES SOLDES DE GESTION (ESG)": "",
                "null": "24 524 044,48\n9 458 261,79\n55 013 466,48\n37 502 918,57"
            },
            {
                "En mad\nETAT DES SOLDES DE GESTION (ESG)": "",
                "null": ""
            },
            {
                "En mad\nETAT DES SOLDES DE GESTION (ESG)": "",
                "null": ""
            },
            {
                "En mad\nETAT DES SOLDES DE GESTION (ESG)": "",
                "null": ""
            },
            {
                "En mad\nETAT DES SOLDES DE GESTION (ESG)": "",
                "null": ""
            },
            {
                "En mad\nETAT DES SOLDES DE GESTION (ESG)": "",
                "null": ""
            },
            {
                "En mad\nETAT DES SOLDES DE GESTION (ESG)": "",
                "null": ""
            },
            {
                "En mad\nETAT DES SOLDES DE GESTION (ESG)": "",
                "null": ""
            },
            {
                "En mad\nETAT DES SOLDES DE GESTION (ESG)": "",
                "null": ""
            },
            {
                "En mad\nETAT DES SOLDES DE GESTION (ESG)": "",
                "null": ""
            },
            {
                "En mad\nETAT DES SOLDES DE GESTION (ESG)": "I",
                "null": "16 471 758,36"
            },
            {
                "En mad\nETAT DES SOLDES DE GESTION (ESG)": "",
                "null": ""
            },
            {
                "En mad\nETAT DES SOLDES DE GESTION (ESG)": "II",
                "null": "16 471 758,36"
            }
        ],
        [
            {
                "TABLEAU DE FINANCEMENT DE L'EXERCICE En mad\nFENIE BROSSETTE EXERCICE DU 01/01/2023 AU 31/12/2023\nI SYNTHESE DES MASSES DU BILAN\nVARIATIONS A-B\nMASSES EX 2E 0R 2C 3I CE EX 2E 0R 2C 2I CE EMPLOIS RESSOURCES\nFinancement Permanent 152 183 475,63 146 131 965,24 6 051 510,39\nMoins actif immobilisé 58 984 745,01 63 401 927,58 4 417 182,57\n= Fonds de Roulement Fonctionnel (1-2) (A) 93 198 730,62 82 730 037,66 10 468 692,96\nActif circulant 526 853 428,24 512 924 545,90 13 928 882,34\nMoins passif circulant 386 648 927,75 396 899 968,35 10 251 040,60": "",
                "null": ""
            },
            {
                "TABLEAU DE FINANCEMENT DE L'EXERCICE En mad\nFENIE BROSSETTE EXERCICE DU 01/01/2023 AU 31/12/2023\nI SYNTHESE DES MASSES DU BILAN\nVARIATIONS A-B\nMASSES EX 2E 0R 2C 3I CE EX 2E 0R 2C 2I CE EMPLOIS RESSOURCES\nFinancement Permanent 152 183 475,63 146 131 965,24 6 051 510,39\nMoins actif immobilisé 58 984 745,01 63 401 927,58 4 417 182,57\n= Fonds de Roulement Fonctionnel (1-2) (A) 93 198 730,62 82 730 037,66 10 468 692,96\nActif circulant 526 853 428,24 512 924 545,90 13 928 882,34\nMoins passif circulant 386 648 927,75 396 899 968,35 10 251 040,60": "",
                "null": ""
            },
            {
                "TABLEAU DE FINANCEMENT DE L'EXERCICE En mad\nFENIE BROSSETTE EXERCICE DU 01/01/2023 AU 31/12/2023\nI SYNTHESE DES MASSES DU BILAN\nVARIATIONS A-B\nMASSES EX 2E 0R 2C 3I CE EX 2E 0R 2C 2I CE EMPLOIS RESSOURCES\nFinancement Permanent 152 183 475,63 146 131 965,24 6 051 510,39\nMoins actif immobilisé 58 984 745,01 63 401 927,58 4 417 182,57\n= Fonds de Roulement Fonctionnel (1-2) (A) 93 198 730,62 82 730 037,66 10 468 692,96\nActif circulant 526 853 428,24 512 924 545,90 13 928 882,34\nMoins passif circulant 386 648 927,75 396 899 968,35 10 251 040,60": "",
                "null": "6 051 510,39\n4 417 182,57"
            },
            {
                "TABLEAU DE FINANCEMENT DE L'EXERCICE En mad\nFENIE BROSSETTE EXERCICE DU 01/01/2023 AU 31/12/2023\nI SYNTHESE DES MASSES DU BILAN\nVARIATIONS A-B\nMASSES EX 2E 0R 2C 3I CE EX 2E 0R 2C 2I CE EMPLOIS RESSOURCES\nFinancement Permanent 152 183 475,63 146 131 965,24 6 051 510,39\nMoins actif immobilisé 58 984 745,01 63 401 927,58 4 417 182,57\n= Fonds de Roulement Fonctionnel (1-2) (A) 93 198 730,62 82 730 037,66 10 468 692,96\nActif circulant 526 853 428,24 512 924 545,90 13 928 882,34\nMoins passif circulant 386 648 927,75 396 899 968,35 10 251 040,60": "",
                "null": ""
            },
            {
                "TABLEAU DE FINANCEMENT DE L'EXERCICE En mad\nFENIE BROSSETTE EXERCICE DU 01/01/2023 AU 31/12/2023\nI SYNTHESE DES MASSES DU BILAN\nVARIATIONS A-B\nMASSES EX 2E 0R 2C 3I CE EX 2E 0R 2C 2I CE EMPLOIS RESSOURCES\nFinancement Permanent 152 183 475,63 146 131 965,24 6 051 510,39\nMoins actif immobilisé 58 984 745,01 63 401 927,58 4 417 182,57\n= Fonds de Roulement Fonctionnel (1-2) (A) 93 198 730,62 82 730 037,66 10 468 692,96\nActif circulant 526 853 428,24 512 924 545,90 13 928 882,34\nMoins passif circulant 386 648 927,75 396 899 968,35 10 251 040,60": "",
                "null": "10 468 692,96"
            },
            {
                "TABLEAU DE FINANCEMENT DE L'EXERCICE En mad\nFENIE BROSSETTE EXERCICE DU 01/01/2023 AU 31/12/2023\nI SYNTHESE DES MASSES DU BILAN\nVARIATIONS A-B\nMASSES EX 2E 0R 2C 3I CE EX 2E 0R 2C 2I CE EMPLOIS RESSOURCES\nFinancement Permanent 152 183 475,63 146 131 965,24 6 051 510,39\nMoins actif immobilisé 58 984 745,01 63 401 927,58 4 417 182,57\n= Fonds de Roulement Fonctionnel (1-2) (A) 93 198 730,62 82 730 037,66 10 468 692,96\nActif circulant 526 853 428,24 512 924 545,90 13 928 882,34\nMoins passif circulant 386 648 927,75 396 899 968,35 10 251 040,60": "",
                "null": ""
            },
            {
                "TABLEAU DE FINANCEMENT DE L'EXERCICE En mad\nFENIE BROSSETTE EXERCICE DU 01/01/2023 AU 31/12/2023\nI SYNTHESE DES MASSES DU BILAN\nVARIATIONS A-B\nMASSES EX 2E 0R 2C 3I CE EX 2E 0R 2C 2I CE EMPLOIS RESSOURCES\nFinancement Permanent 152 183 475,63 146 131 965,24 6 051 510,39\nMoins actif immobilisé 58 984 745,01 63 401 927,58 4 417 182,57\n= Fonds de Roulement Fonctionnel (1-2) (A) 93 198 730,62 82 730 037,66 10 468 692,96\nActif circulant 526 853 428,24 512 924 545,90 13 928 882,34\nMoins passif circulant 386 648 927,75 396 899 968,35 10 251 040,60": "",
                "null": ""
            },
            {
                "TABLEAU DE FINANCEMENT DE L'EXERCICE En mad\nFENIE BROSSETTE EXERCICE DU 01/01/2023 AU 31/12/2023\nI SYNTHESE DES MASSES DU BILAN\nVARIATIONS A-B\nMASSES EX 2E 0R 2C 3I CE EX 2E 0R 2C 2I CE EMPLOIS RESSOURCES\nFinancement Permanent 152 183 475,63 146 131 965,24 6 051 510,39\nMoins actif immobilisé 58 984 745,01 63 401 927,58 4 417 182,57\n= Fonds de Roulement Fonctionnel (1-2) (A) 93 198 730,62 82 730 037,66 10 468 692,96\nActif circulant 526 853 428,24 512 924 545,90 13 928 882,34\nMoins passif circulant 386 648 927,75 396 899 968,35 10 251 040,60": "",
                "null": ""
            },
            {
                "TABLEAU DE FINANCEMENT DE L'EXERCICE En mad\nFENIE BROSSETTE EXERCICE DU 01/01/2023 AU 31/12/2023\nI SYNTHESE DES MASSES DU BILAN\nVARIATIONS A-B\nMASSES EX 2E 0R 2C 3I CE EX 2E 0R 2C 2I CE EMPLOIS RESSOURCES\nFinancement Permanent 152 183 475,63 146 131 965,24 6 051 510,39\nMoins actif immobilisé 58 984 745,01 63 401 927,58 4 417 182,57\n= Fonds de Roulement Fonctionnel (1-2) (A) 93 198 730,62 82 730 037,66 10 468 692,96\nActif circulant 526 853 428,24 512 924 545,90 13 928 882,34\nMoins passif circulant 386 648 927,75 396 899 968,35 10 251 040,60": "TRESORERIE NETTE (Actif-Passif) = A-B -47 005 769,87 -33 294 539,89 13 711 229,98\nII EMPLOIS ET RESSOURCES\nEXERCICE 2023 EXERCICE 2022\nL'EXERCICE (FLUX)\nEMPLOIS RESSOURCES EMPLOIS RESSOURCES\nAUTOFINANCEMENT (A) 17 450 474,07 16 471 758,36\n+ Capacité d'autofinancement 17 450 474,07 16 471 758,36\n- Distributions de bénéfices\nCESSIONS ET REDUCTIONS D'IMMOBILISATIONS (B) 3 404 124,67 54 998 834,75\nCession d'immob. incorporelles\nCession d'immob. corporelles 3 404 124,67 54 998 834,75\nCession d'immob. financières\nRécupération sur créances immobilisées\nAUGMENTATION DES CAPITAUX PROPRES ET ASSIMILES (C)\n+ Augmentation du capital , apports\n+ Subventions d'investissement\nAUGMENTATION DES DETTES DE FINANCEMENT (D)\nTOTAL RESSOURCES STABLES 20 854 598,74 71 470 593,11\nACQUISITIONS ET AUGMENTATIONS D'IMMOBILISATIONS (E) 4 605 138,46 36 850 077,92\nAcquisitions d'immob. incorporelles 21 145,00\nAcquisitions d'immob. corporelles 4 583 993,46 36 850 077,92\nAcquisitions d'immob. financières\nAcquisitions des créances immob\n* REMBOURSEMENT DES CAPITAUX PROPRES (F)\nREMBOURSSEMENT DES DETTES DE FINANCEMENT (G) 5 687 841,32 10 066 594,08\nEMPLOIS EN NON VALEURS (H) 92 926,00 2 571 972,00\nTOTAL II-EMPLOIS STABLES (E+F+G+H) 10 385 905,78 49 488 644,00\nIII VARIATION DU BESOIN DE FINANCEMENT GLOBAL (B.F.G) 24 179 922,94 58 099 282,73\nIV VARIATION DE LA TRESORERIE 13 711 229,98 36 117 333,62\nTOTAL GENERAL 34 565 828,72 34 565 828,72 107 587 926,73 107 587 926,73",
                "null": "13 711 229,98"
            },
            {
                "TABLEAU DE FINANCEMENT DE L'EXERCICE En mad\nFENIE BROSSETTE EXERCICE DU 01/01/2023 AU 31/12/2023\nI SYNTHESE DES MASSES DU BILAN\nVARIATIONS A-B\nMASSES EX 2E 0R 2C 3I CE EX 2E 0R 2C 2I CE EMPLOIS RESSOURCES\nFinancement Permanent 152 183 475,63 146 131 965,24 6 051 510,39\nMoins actif immobilisé 58 984 745,01 63 401 927,58 4 417 182,57\n= Fonds de Roulement Fonctionnel (1-2) (A) 93 198 730,62 82 730 037,66 10 468 692,96\nActif circulant 526 853 428,24 512 924 545,90 13 928 882,34\nMoins passif circulant 386 648 927,75 396 899 968,35 10 251 040,60": "",
                "null": ""
            },
            {
                "TABLEAU DE FINANCEMENT DE L'EXERCICE En mad\nFENIE BROSSETTE EXERCICE DU 01/01/2023 AU 31/12/2023\nI SYNTHESE DES MASSES DU BILAN\nVARIATIONS A-B\nMASSES EX 2E 0R 2C 3I CE EX 2E 0R 2C 2I CE EMPLOIS RESSOURCES\nFinancement Permanent 152 183 475,63 146 131 965,24 6 051 510,39\nMoins actif immobilisé 58 984 745,01 63 401 927,58 4 417 182,57\n= Fonds de Roulement Fonctionnel (1-2) (A) 93 198 730,62 82 730 037,66 10 468 692,96\nActif circulant 526 853 428,24 512 924 545,90 13 928 882,34\nMoins passif circulant 386 648 927,75 396 899 968,35 10 251 040,60": "",
                "null": "RESSOURCES"
            },
            {
                "TABLEAU DE FINANCEMENT DE L'EXERCICE En mad\nFENIE BROSSETTE EXERCICE DU 01/01/2023 AU 31/12/2023\nI SYNTHESE DES MASSES DU BILAN\nVARIATIONS A-B\nMASSES EX 2E 0R 2C 3I CE EX 2E 0R 2C 2I CE EMPLOIS RESSOURCES\nFinancement Permanent 152 183 475,63 146 131 965,24 6 051 510,39\nMoins actif immobilisé 58 984 745,01 63 401 927,58 4 417 182,57\n= Fonds de Roulement Fonctionnel (1-2) (A) 93 198 730,62 82 730 037,66 10 468 692,96\nActif circulant 526 853 428,24 512 924 545,90 13 928 882,34\nMoins passif circulant 386 648 927,75 396 899 968,35 10 251 040,60": "",
                "null": "16 471 758,36\n16 471 758,36"
            },
            {
                "TABLEAU DE FINANCEMENT DE L'EXERCICE En mad\nFENIE BROSSETTE EXERCICE DU 01/01/2023 AU 31/12/2023\nI SYNTHESE DES MASSES DU BILAN\nVARIATIONS A-B\nMASSES EX 2E 0R 2C 3I CE EX 2E 0R 2C 2I CE EMPLOIS RESSOURCES\nFinancement Permanent 152 183 475,63 146 131 965,24 6 051 510,39\nMoins actif immobilisé 58 984 745,01 63 401 927,58 4 417 182,57\n= Fonds de Roulement Fonctionnel (1-2) (A) 93 198 730,62 82 730 037,66 10 468 692,96\nActif circulant 526 853 428,24 512 924 545,90 13 928 882,34\nMoins passif circulant 386 648 927,75 396 899 968,35 10 251 040,60": "",
                "null": ""
            },
            {
                "TABLEAU DE FINANCEMENT DE L'EXERCICE En mad\nFENIE BROSSETTE EXERCICE DU 01/01/2023 AU 31/12/2023\nI SYNTHESE DES MASSES DU BILAN\nVARIATIONS A-B\nMASSES EX 2E 0R 2C 3I CE EX 2E 0R 2C 2I CE EMPLOIS RESSOURCES\nFinancement Permanent 152 183 475,63 146 131 965,24 6 051 510,39\nMoins actif immobilisé 58 984 745,01 63 401 927,58 4 417 182,57\n= Fonds de Roulement Fonctionnel (1-2) (A) 93 198 730,62 82 730 037,66 10 468 692,96\nActif circulant 526 853 428,24 512 924 545,90 13 928 882,34\nMoins passif circulant 386 648 927,75 396 899 968,35 10 251 040,60": "",
                "null": "54 998 834,75\n54 998 834,75"
            },
            {
                "TABLEAU DE FINANCEMENT DE L'EXERCICE En mad\nFENIE BROSSETTE EXERCICE DU 01/01/2023 AU 31/12/2023\nI SYNTHESE DES MASSES DU BILAN\nVARIATIONS A-B\nMASSES EX 2E 0R 2C 3I CE EX 2E 0R 2C 2I CE EMPLOIS RESSOURCES\nFinancement Permanent 152 183 475,63 146 131 965,24 6 051 510,39\nMoins actif immobilisé 58 984 745,01 63 401 927,58 4 417 182,57\n= Fonds de Roulement Fonctionnel (1-2) (A) 93 198 730,62 82 730 037,66 10 468 692,96\nActif circulant 526 853 428,24 512 924 545,90 13 928 882,34\nMoins passif circulant 386 648 927,75 396 899 968,35 10 251 040,60": "",
                "null": ""
            },
            {
                "TABLEAU DE FINANCEMENT DE L'EXERCICE En mad\nFENIE BROSSETTE EXERCICE DU 01/01/2023 AU 31/12/2023\nI SYNTHESE DES MASSES DU BILAN\nVARIATIONS A-B\nMASSES EX 2E 0R 2C 3I CE EX 2E 0R 2C 2I CE EMPLOIS RESSOURCES\nFinancement Permanent 152 183 475,63 146 131 965,24 6 051 510,39\nMoins actif immobilisé 58 984 745,01 63 401 927,58 4 417 182,57\n= Fonds de Roulement Fonctionnel (1-2) (A) 93 198 730,62 82 730 037,66 10 468 692,96\nActif circulant 526 853 428,24 512 924 545,90 13 928 882,34\nMoins passif circulant 386 648 927,75 396 899 968,35 10 251 040,60": "",
                "null": ""
            },
            {
                "TABLEAU DE FINANCEMENT DE L'EXERCICE En mad\nFENIE BROSSETTE EXERCICE DU 01/01/2023 AU 31/12/2023\nI SYNTHESE DES MASSES DU BILAN\nVARIATIONS A-B\nMASSES EX 2E 0R 2C 3I CE EX 2E 0R 2C 2I CE EMPLOIS RESSOURCES\nFinancement Permanent 152 183 475,63 146 131 965,24 6 051 510,39\nMoins actif immobilisé 58 984 745,01 63 401 927,58 4 417 182,57\n= Fonds de Roulement Fonctionnel (1-2) (A) 93 198 730,62 82 730 037,66 10 468 692,96\nActif circulant 526 853 428,24 512 924 545,90 13 928 882,34\nMoins passif circulant 386 648 927,75 396 899 968,35 10 251 040,60": "",
                "null": ""
            },
            {
                "TABLEAU DE FINANCEMENT DE L'EXERCICE En mad\nFENIE BROSSETTE EXERCICE DU 01/01/2023 AU 31/12/2023\nI SYNTHESE DES MASSES DU BILAN\nVARIATIONS A-B\nMASSES EX 2E 0R 2C 3I CE EX 2E 0R 2C 2I CE EMPLOIS RESSOURCES\nFinancement Permanent 152 183 475,63 146 131 965,24 6 051 510,39\nMoins actif immobilisé 58 984 745,01 63 401 927,58 4 417 182,57\n= Fonds de Roulement Fonctionnel (1-2) (A) 93 198 730,62 82 730 037,66 10 468 692,96\nActif circulant 526 853 428,24 512 924 545,90 13 928 882,34\nMoins passif circulant 386 648 927,75 396 899 968,35 10 251 040,60": "",
                "null": ""
            },
            {
                "TABLEAU DE FINANCEMENT DE L'EXERCICE En mad\nFENIE BROSSETTE EXERCICE DU 01/01/2023 AU 31/12/2023\nI SYNTHESE DES MASSES DU BILAN\nVARIATIONS A-B\nMASSES EX 2E 0R 2C 3I CE EX 2E 0R 2C 2I CE EMPLOIS RESSOURCES\nFinancement Permanent 152 183 475,63 146 131 965,24 6 051 510,39\nMoins actif immobilisé 58 984 745,01 63 401 927,58 4 417 182,57\n= Fonds de Roulement Fonctionnel (1-2) (A) 93 198 730,62 82 730 037,66 10 468 692,96\nActif circulant 526 853 428,24 512 924 545,90 13 928 882,34\nMoins passif circulant 386 648 927,75 396 899 968,35 10 251 040,60": "",
                "null": ""
            },
            {
                "TABLEAU DE FINANCEMENT DE L'EXERCICE En mad\nFENIE BROSSETTE EXERCICE DU 01/01/2023 AU 31/12/2023\nI SYNTHESE DES MASSES DU BILAN\nVARIATIONS A-B\nMASSES EX 2E 0R 2C 3I CE EX 2E 0R 2C 2I CE EMPLOIS RESSOURCES\nFinancement Permanent 152 183 475,63 146 131 965,24 6 051 510,39\nMoins actif immobilisé 58 984 745,01 63 401 927,58 4 417 182,57\n= Fonds de Roulement Fonctionnel (1-2) (A) 93 198 730,62 82 730 037,66 10 468 692,96\nActif circulant 526 853 428,24 512 924 545,90 13 928 882,34\nMoins passif circulant 386 648 927,75 396 899 968,35 10 251 040,60": "",
                "null": ""
            },
            {
                "TABLEAU DE FINANCEMENT DE L'EXERCICE En mad\nFENIE BROSSETTE EXERCICE DU 01/01/2023 AU 31/12/2023\nI SYNTHESE DES MASSES DU BILAN\nVARIATIONS A-B\nMASSES EX 2E 0R 2C 3I CE EX 2E 0R 2C 2I CE EMPLOIS RESSOURCES\nFinancement Permanent 152 183 475,63 146 131 965,24 6 051 510,39\nMoins actif immobilisé 58 984 745,01 63 401 927,58 4 417 182,57\n= Fonds de Roulement Fonctionnel (1-2) (A) 93 198 730,62 82 730 037,66 10 468 692,96\nActif circulant 526 853 428,24 512 924 545,90 13 928 882,34\nMoins passif circulant 386 648 927,75 396 899 968,35 10 251 040,60": "",
                "null": "71 470 593,11"
            },
            {
                "TABLEAU DE FINANCEMENT DE L'EXERCICE En mad\nFENIE BROSSETTE EXERCICE DU 01/01/2023 AU 31/12/2023\nI SYNTHESE DES MASSES DU BILAN\nVARIATIONS A-B\nMASSES EX 2E 0R 2C 3I CE EX 2E 0R 2C 2I CE EMPLOIS RESSOURCES\nFinancement Permanent 152 183 475,63 146 131 965,24 6 051 510,39\nMoins actif immobilisé 58 984 745,01 63 401 927,58 4 417 182,57\n= Fonds de Roulement Fonctionnel (1-2) (A) 93 198 730,62 82 730 037,66 10 468 692,96\nActif circulant 526 853 428,24 512 924 545,90 13 928 882,34\nMoins passif circulant 386 648 927,75 396 899 968,35 10 251 040,60": "",
                "null": ""
            },
            {
                "TABLEAU DE FINANCEMENT DE L'EXERCICE En mad\nFENIE BROSSETTE EXERCICE DU 01/01/2023 AU 31/12/2023\nI SYNTHESE DES MASSES DU BILAN\nVARIATIONS A-B\nMASSES EX 2E 0R 2C 3I CE EX 2E 0R 2C 2I CE EMPLOIS RESSOURCES\nFinancement Permanent 152 183 475,63 146 131 965,24 6 051 510,39\nMoins actif immobilisé 58 984 745,01 63 401 927,58 4 417 182,57\n= Fonds de Roulement Fonctionnel (1-2) (A) 93 198 730,62 82 730 037,66 10 468 692,96\nActif circulant 526 853 428,24 512 924 545,90 13 928 882,34\nMoins passif circulant 386 648 927,75 396 899 968,35 10 251 040,60": "",
                "null": ""
            },
            {
                "TABLEAU DE FINANCEMENT DE L'EXERCICE En mad\nFENIE BROSSETTE EXERCICE DU 01/01/2023 AU 31/12/2023\nI SYNTHESE DES MASSES DU BILAN\nVARIATIONS A-B\nMASSES EX 2E 0R 2C 3I CE EX 2E 0R 2C 2I CE EMPLOIS RESSOURCES\nFinancement Permanent 152 183 475,63 146 131 965,24 6 051 510,39\nMoins actif immobilisé 58 984 745,01 63 401 927,58 4 417 182,57\n= Fonds de Roulement Fonctionnel (1-2) (A) 93 198 730,62 82 730 037,66 10 468 692,96\nActif circulant 526 853 428,24 512 924 545,90 13 928 882,34\nMoins passif circulant 386 648 927,75 396 899 968,35 10 251 040,60": "",
                "null": ""
            },
            {
                "TABLEAU DE FINANCEMENT DE L'EXERCICE En mad\nFENIE BROSSETTE EXERCICE DU 01/01/2023 AU 31/12/2023\nI SYNTHESE DES MASSES DU BILAN\nVARIATIONS A-B\nMASSES EX 2E 0R 2C 3I CE EX 2E 0R 2C 2I CE EMPLOIS RESSOURCES\nFinancement Permanent 152 183 475,63 146 131 965,24 6 051 510,39\nMoins actif immobilisé 58 984 745,01 63 401 927,58 4 417 182,57\n= Fonds de Roulement Fonctionnel (1-2) (A) 93 198 730,62 82 730 037,66 10 468 692,96\nActif circulant 526 853 428,24 512 924 545,90 13 928 882,34\nMoins passif circulant 386 648 927,75 396 899 968,35 10 251 040,60": "",
                "null": ""
            },
            {
                "TABLEAU DE FINANCEMENT DE L'EXERCICE En mad\nFENIE BROSSETTE EXERCICE DU 01/01/2023 AU 31/12/2023\nI SYNTHESE DES MASSES DU BILAN\nVARIATIONS A-B\nMASSES EX 2E 0R 2C 3I CE EX 2E 0R 2C 2I CE EMPLOIS RESSOURCES\nFinancement Permanent 152 183 475,63 146 131 965,24 6 051 510,39\nMoins actif immobilisé 58 984 745,01 63 401 927,58 4 417 182,57\n= Fonds de Roulement Fonctionnel (1-2) (A) 93 198 730,62 82 730 037,66 10 468 692,96\nActif circulant 526 853 428,24 512 924 545,90 13 928 882,34\nMoins passif circulant 386 648 927,75 396 899 968,35 10 251 040,60": "",
                "null": ""
            },
            {
                "TABLEAU DE FINANCEMENT DE L'EXERCICE En mad\nFENIE BROSSETTE EXERCICE DU 01/01/2023 AU 31/12/2023\nI SYNTHESE DES MASSES DU BILAN\nVARIATIONS A-B\nMASSES EX 2E 0R 2C 3I CE EX 2E 0R 2C 2I CE EMPLOIS RESSOURCES\nFinancement Permanent 152 183 475,63 146 131 965,24 6 051 510,39\nMoins actif immobilisé 58 984 745,01 63 401 927,58 4 417 182,57\n= Fonds de Roulement Fonctionnel (1-2) (A) 93 198 730,62 82 730 037,66 10 468 692,96\nActif circulant 526 853 428,24 512 924 545,90 13 928 882,34\nMoins passif circulant 386 648 927,75 396 899 968,35 10 251 040,60": "",
                "null": ""
            },
            {
                "TABLEAU DE FINANCEMENT DE L'EXERCICE En mad\nFENIE BROSSETTE EXERCICE DU 01/01/2023 AU 31/12/2023\nI SYNTHESE DES MASSES DU BILAN\nVARIATIONS A-B\nMASSES EX 2E 0R 2C 3I CE EX 2E 0R 2C 2I CE EMPLOIS RESSOURCES\nFinancement Permanent 152 183 475,63 146 131 965,24 6 051 510,39\nMoins actif immobilisé 58 984 745,01 63 401 927,58 4 417 182,57\n= Fonds de Roulement Fonctionnel (1-2) (A) 93 198 730,62 82 730 037,66 10 468 692,96\nActif circulant 526 853 428,24 512 924 545,90 13 928 882,34\nMoins passif circulant 386 648 927,75 396 899 968,35 10 251 040,60": "",
                "null": ""
            },
            {
                "TABLEAU DE FINANCEMENT DE L'EXERCICE En mad\nFENIE BROSSETTE EXERCICE DU 01/01/2023 AU 31/12/2023\nI SYNTHESE DES MASSES DU BILAN\nVARIATIONS A-B\nMASSES EX 2E 0R 2C 3I CE EX 2E 0R 2C 2I CE EMPLOIS RESSOURCES\nFinancement Permanent 152 183 475,63 146 131 965,24 6 051 510,39\nMoins actif immobilisé 58 984 745,01 63 401 927,58 4 417 182,57\n= Fonds de Roulement Fonctionnel (1-2) (A) 93 198 730,62 82 730 037,66 10 468 692,96\nActif circulant 526 853 428,24 512 924 545,90 13 928 882,34\nMoins passif circulant 386 648 927,75 396 899 968,35 10 251 040,60": "",
                "null": ""
            },
            {
                "TABLEAU DE FINANCEMENT DE L'EXERCICE En mad\nFENIE BROSSETTE EXERCICE DU 01/01/2023 AU 31/12/2023\nI SYNTHESE DES MASSES DU BILAN\nVARIATIONS A-B\nMASSES EX 2E 0R 2C 3I CE EX 2E 0R 2C 2I CE EMPLOIS RESSOURCES\nFinancement Permanent 152 183 475,63 146 131 965,24 6 051 510,39\nMoins actif immobilisé 58 984 745,01 63 401 927,58 4 417 182,57\n= Fonds de Roulement Fonctionnel (1-2) (A) 93 198 730,62 82 730 037,66 10 468 692,96\nActif circulant 526 853 428,24 512 924 545,90 13 928 882,34\nMoins passif circulant 386 648 927,75 396 899 968,35 10 251 040,60": "",
                "null": "36 117 333,62"
            },
            {
                "TABLEAU DE FINANCEMENT DE L'EXERCICE En mad\nFENIE BROSSETTE EXERCICE DU 01/01/2023 AU 31/12/2023\nI SYNTHESE DES MASSES DU BILAN\nVARIATIONS A-B\nMASSES EX 2E 0R 2C 3I CE EX 2E 0R 2C 2I CE EMPLOIS RESSOURCES\nFinancement Permanent 152 183 475,63 146 131 965,24 6 051 510,39\nMoins actif immobilisé 58 984 745,01 63 401 927,58 4 417 182,57\n= Fonds de Roulement Fonctionnel (1-2) (A) 93 198 730,62 82 730 037,66 10 468 692,96\nActif circulant 526 853 428,24 512 924 545,90 13 928 882,34\nMoins passif circulant 386 648 927,75 396 899 968,35 10 251 040,60": "",
                "null": "107 587 926,73"
            }
        ],
        [
            {
                "T A B LE A U D E S IM M O B ILIS A T IO N S A U T R E S Q U E FIN A N C IE R E S En mad\nFEN IE B R O SSETTE D U 0 1 /0 1 /2 0 2 3 A U 3 1 /1 2 /2 2 0 2 3\nM O N TA N T B R U T A U G M EN TA TIO N(A D IM IN U TIO N(C M O N TA N T B R U T FIN\nN A TU R E\nD EB U T D 'EX ER C IC E q u isition ) ession ) D 'EX ER C IC E\nIM M O B ILISA TIO N EN N O N V A LEU R SFra 6 6 1 2 4 6 2 ,9 0 9 2 9 2 6 ,0 0 6 7 0 5 3 8 8 ,9 0\nis p rélim in a iresC\nh a rg es à rép a rtir su r p lu sieu rs exercicesP 6 6 1 2 4 6 2 ,9 0 9 2 9 2 6 ,0 0 6 7 0 5 3 8 8 ,9 0\nrim e d e rem b ou rsem en t d es ob lig a tion sIM\nM O B ILISA TIO N S IN C O R P O R ELLESIm 5 4 3 0 4 4 3 ,9 9 2 1 1 4 5 ,0 0 5 4 5 1 5 8 8 ,9 9\nm ob ilisa tion en rech erch e et d évelop p em en tB\nrevets, m a rq u es, d roits et va leu rs sim ila iresFon 4 9 9 0 3 4 2 ,9 94 2 1 1 4 5 ,0 0 5 0 1 1 4 8 7 ,9 94\nd s com m ercia lA 4 0 1 0 1 ,0 0 4 0 1 0 1 ,0 0\nu tres im m ob ilisa tion s in corp orellesIM\nM O B ILISA TIO N S C O R P O R ELLESTerra 2 3 5 0 1 4 0 9 9 ,3 61 4 5 8 3 9 9 3 ,4 6 2 1 1 0 9 3 0 ,0 4 2 3 7 4 8 7 1 6 2 ,7 81\nin sC 7 7 0 0 0 0 0 ,0 06 7 7 0 0 0 0 0 ,0 06\non stru ction sIn 1 5 7 7 8 2 8 ,1 71 1 5 7 7 8 2 8 ,1 71\nsta lla tion s tech n iq u es, m a teriel et ou tilla g eM 0 4 5 9 2 1 9 7 ,8 38 2 9 2 6 9 9 1 ,9 01 1 8 6 8 4 2 1 ,7 42 0 5 6 5 0 7 6 7 ,9 99\na tériel d e tra n sp ortM 2 8 1 8 2 1 ,8 54 3 4 7 6 0 2 ,9 93 3 7 4 0 8 ,3 05 3 9 2 0 1 6 ,5 44\nob ilier, m a tériel d e b u rea u et a m én a g em en tA 2 8 6 2 2 5 1 ,5 1 0 9 3 9 8 ,5 7 1 0 0 ,0 0 3 1 6 6 5 5 0 ,0 8\nu tres im m ob ilisa tion s corp orellesIm\nm ob ilisa tion s corp orelles en cou rsT\nO T A L G E N E R A L 2 4 7 0 5 7 0 0 6 ,2 5 4 6 9 8 0 6 4 ,4 6 2 1 1 0 9 3 0 ,0 4 2 4 9 6 4 4 1 4 0 ,6 7": "",
                "null": ""
            },
            {
                "T A B LE A U D E S IM M O B ILIS A T IO N S A U T R E S Q U E FIN A N C IE R E S En mad\nFEN IE B R O SSETTE D U 0 1 /0 1 /2 0 2 3 A U 3 1 /1 2 /2 2 0 2 3\nM O N TA N T B R U T A U G M EN TA TIO N(A D IM IN U TIO N(C M O N TA N T B R U T FIN\nN A TU R E\nD EB U T D 'EX ER C IC E q u isition ) ession ) D 'EX ER C IC E\nIM M O B ILISA TIO N EN N O N V A LEU R SFra 6 6 1 2 4 6 2 ,9 0 9 2 9 2 6 ,0 0 6 7 0 5 3 8 8 ,9 0\nis p rélim in a iresC\nh a rg es à rép a rtir su r p lu sieu rs exercicesP 6 6 1 2 4 6 2 ,9 0 9 2 9 2 6 ,0 0 6 7 0 5 3 8 8 ,9 0\nrim e d e rem b ou rsem en t d es ob lig a tion sIM\nM O B ILISA TIO N S IN C O R P O R ELLESIm 5 4 3 0 4 4 3 ,9 9 2 1 1 4 5 ,0 0 5 4 5 1 5 8 8 ,9 9\nm ob ilisa tion en rech erch e et d évelop p em en tB\nrevets, m a rq u es, d roits et va leu rs sim ila iresFon 4 9 9 0 3 4 2 ,9 94 2 1 1 4 5 ,0 0 5 0 1 1 4 8 7 ,9 94\nd s com m ercia lA 4 0 1 0 1 ,0 0 4 0 1 0 1 ,0 0\nu tres im m ob ilisa tion s in corp orellesIM\nM O B ILISA TIO N S C O R P O R ELLESTerra 2 3 5 0 1 4 0 9 9 ,3 61 4 5 8 3 9 9 3 ,4 6 2 1 1 0 9 3 0 ,0 4 2 3 7 4 8 7 1 6 2 ,7 81\nin sC 7 7 0 0 0 0 0 ,0 06 7 7 0 0 0 0 0 ,0 06\non stru ction sIn 1 5 7 7 8 2 8 ,1 71 1 5 7 7 8 2 8 ,1 71\nsta lla tion s tech n iq u es, m a teriel et ou tilla g eM 0 4 5 9 2 1 9 7 ,8 38 2 9 2 6 9 9 1 ,9 01 1 8 6 8 4 2 1 ,7 42 0 5 6 5 0 7 6 7 ,9 99\na tériel d e tra n sp ortM 2 8 1 8 2 1 ,8 54 3 4 7 6 0 2 ,9 93 3 7 4 0 8 ,3 05 3 9 2 0 1 6 ,5 44\nob ilier, m a tériel d e b u rea u et a m én a g em en tA 2 8 6 2 2 5 1 ,5 1 0 9 3 9 8 ,5 7 1 0 0 ,0 0 3 1 6 6 5 5 0 ,0 8\nu tres im m ob ilisa tion s corp orellesIm\nm ob ilisa tion s corp orelles en cou rsT\nO T A L G E N E R A L 2 4 7 0 5 7 0 0 6 ,2 5 4 6 9 8 0 6 4 ,4 6 2 1 1 0 9 3 0 ,0 4 2 4 9 6 4 4 1 4 0 ,6 7": "T A B LE A U D E S A M O R T ISSE M E N T S En mad\nFEN IE BROSSETTE EXERCICE DU 01/01/2023 AU 31/12/2023\nCUM UL DOTATION S AM ORTISSEM EN TS SUR CUM UL DES AM ORTISSEM EN TS FIN\nN ATURE\nDEBUT D'EXERCICE DE L'EXERCICE IM M OBILISATION S SORTIES D'EXERCICE\nIM M OBILISATION EN N ON VALEURSFrais 6 391 717,12 77 205,03 6 468 922,15\nprélim inairesCharges\nà répartir sur plusieurs exercicesPrim 6 391 717,12 77 205,03 6 468 922,15\ne de rem boursem ent des obligationsIM\nM OBILISATION S IN CORPORELLESIm 4 798 236,20 55 020,86 4 853 257,06\nm obilisations en recherche et développem entBrevets,\nm arques, droits et valeurs sim ilairesFonds 4 798 236,20 55 020,86 0,00 4 853 257,06\ncom m ercialAutres\nim m obilisations incorporellesIM\nM OBILISATION S CORPORELLESTerrainsConstructionsInstallations 168 785 026,29 8 681 936,20 1 809 845,11 175 657 117,38\n39 231 919,9380 3 101 342,514 42 333 262,4483\ntechniques, m ateriel et outillageM 429 783,628 898 576,42157 1 769 133,8535 559 226,198\natériel de transportM 154 760,4540 665,89524 611,255 276 815,0941\nobilier, m atériel de bureau et am énagem entAutres 968 562,29 351,38 100,01 487 813,66\nim m obilisations corporellesIm\nm obilisations corporelles en coursTO\nTA L G EN ERA L 179 974 979,61 8 814 162,09 1 809 845,11 186 979 296,59",
                "null": ""
            }
        ],
        [
            {
                "TABLEAU DES AMORTISSEMENTS En mad": "FENIE BROSSETTE EXERCICE DU 01/01/2023 AU 31/12/2023",
                "null": ""
            },
            {
                "TABLEAU DES AMORTISSEMENTS En mad": "NATURE",
                "null": "CUMUL DES AMORTISSEMENTS FIN\nD'EXERCICE"
            },
            {
                "TABLEAU DES AMORTISSEMENTS En mad": "IMMOBILISATION EN NON VALEURS",
                "null": "6 468 922,15"
            },
            {
                "TABLEAU DES AMORTISSEMENTS En mad": "Frais préliminaires\nCharges à répartir sur plusieurs exercices\nPrime de remboursement des obligations",
                "null": "6 468 922,15"
            },
            {
                "TABLEAU DES AMORTISSEMENTS En mad": "IMMOBILISATIONS INCORPORELLES",
                "null": "4 853 257,06"
            },
            {
                "TABLEAU DES AMORTISSEMENTS En mad": "Immobilisations en recherche et développement\nBrevets, marques, droits et valeurs similaires\nFonds commercial\nAutres immobilisations incorporelles",
                "null": "4 853 257,06"
            },
            {
                "TABLEAU DES AMORTISSEMENTS En mad": "IMMOBILISATIONS CORPORELLES",
                "null": "175 657 117,38"
            },
            {
                "TABLEAU DES AMORTISSEMENTS En mad": "Terrains\nConstructions\nInstallations techniques, materiel et outillage\nMatériel de transport\nMobilier, matériel de bureau et aménagement\nAutres immobilisations corporelles\nImmobilisations corporelles en cours",
                "null": "42 333 262,44\n83 559 226,19\n8 276 815,09\n41 487 813,66"
            },
            {
                "TABLEAU DES AMORTISSEMENTS En mad": "TOTAL GENERAL",
                "null": "186 979 296,59"
            }
        ],
        [
            {
                "TABLEAU DES TITRES DE PARTICIPATION En mad\nFENIE BROSSETTE EXERCICE DU 01/01/2023 AU 31/12/2023\nPrix\nRaison sociale de la société Participation au Valeur\nI.F Secteur d'activité Capital social d'acquisition\némettrice capital en % comptable nette\nglobal\nImmobilière le Nôtre 1111111 Immobilière 1% 3 000,00 3 000,00\nSMIRRI 2222222 BTP 1% 100,00 100,00\nFenie Brossette Sénègale 3333333 Autres secteurs 100% 171 772,64 171 772,64\nTOTAL 174 872,64 174 872,64": "Raison sociale de la société\némettrice",
                "null": "Prix\nd'acquisition\nglobal"
            },
            {
                "TABLEAU DES TITRES DE PARTICIPATION En mad\nFENIE BROSSETTE EXERCICE DU 01/01/2023 AU 31/12/2023\nPrix\nRaison sociale de la société Participation au Valeur\nI.F Secteur d'activité Capital social d'acquisition\némettrice capital en % comptable nette\nglobal\nImmobilière le Nôtre 1111111 Immobilière 1% 3 000,00 3 000,00\nSMIRRI 2222222 BTP 1% 100,00 100,00\nFenie Brossette Sénègale 3333333 Autres secteurs 100% 171 772,64 171 772,64\nTOTAL 174 872,64 174 872,64": "Immobilière le Nôtre\nSMIRRI\nFenie Brossette Sénègale",
                "null": "3 000,00\n100,00\n171 772,64"
            },
            {
                "TABLEAU DES TITRES DE PARTICIPATION En mad\nFENIE BROSSETTE EXERCICE DU 01/01/2023 AU 31/12/2023\nPrix\nRaison sociale de la société Participation au Valeur\nI.F Secteur d'activité Capital social d'acquisition\némettrice capital en % comptable nette\nglobal\nImmobilière le Nôtre 1111111 Immobilière 1% 3 000,00 3 000,00\nSMIRRI 2222222 BTP 1% 100,00 100,00\nFenie Brossette Sénègale 3333333 Autres secteurs 100% 171 772,64 171 772,64\nTOTAL 174 872,64 174 872,64": "TOTAL",
                "null": "174 872,64"
            }
        ],
        [
            {
                "Fenie Brossette se projette avec dynamisme dans le cadre favorable des projets": "d’infrastructures à l’horizon 2030 ce qui conforte le choix de son plan de développement"
            },
            {
                "Fenie Brossette se projette avec dynamisme dans le cadre favorable des projets": ""
            }
        ],
        [
            {
                "": "En EKL EmMaEdN TS 31-déc-23 31-déc-22"
            },
            {
                "": "Résultat net consolidé 7 222 20 510"
            },
            {
                "": "Variation des provisions non courantes -139 1 676\nDotations aux amortissements des immobilisations 8 773 10 039\nPrix de cession des immobilisations cédées -3 404 -55 013\nValeur nette comptable des immobilisations cédées 301 38 436"
            },
            {
                "": "Capacité d’autofinancement des sociétés intégrées 12 754 15 648"
            },
            {
                "": "Variation du Besoin en Fonds de Roulement lié à l’activité -19 605 -58 061"
            },
            {
                "": "Flux nets de trésorerie générés par l’activité -6 851 -42 413"
            },
            {
                "": "Prix de cession des immobilisations cédées 3 404 55 013\nAcquisition des immobilisations corporelles -4 606 -1 863\nVariation des immobilisations financières -1 1"
            },
            {
                "": "Flux nets de trésorerie liés aux opérations d’investissement -1 203 53 151"
            },
            {
                "": "Emissions / remboursements d'emprunts -5 689 -41 897"
            },
            {
                "": "Flux net de trésorerie liés aux opérations de financement -5 689 -41 897"
            },
            {
                "": "Réduction des Capitaux Propres -5 046"
            },
            {
                "": "Variation de trésorerie nette -13 743 -36 206"
            },
            {
                "": ""
            },
            {
                "": "Trésorerie nette d’ouverture -33 153 3 053\nTrésorerie nette de clôture -46 896 -33 153"
            },
            {
                "": "Variation de trésorerie nette -13 743 -36 206"
            },
            {
                "": ""
            }
        ],
        [
            {
                "(en milliers de DH)": "Clients créditeurs, avances et acomptes",
                "31-déc.-23": "48 896",
                "31-déc.-22": "24 544"
            },
            {
                "(en milliers de DH)": "Personnel",
                "31-déc.-23": "4 729",
                "31-déc.-22": "4 127"
            },
            {
                "(en milliers de DH)": "Organismes sociaux",
                "31-déc.-23": "4 131",
                "31-déc.-22": "3 953"
            },
            {
                "(en milliers de DH)": "",
                "31-déc.-23": "50 372",
                "31-déc.-22": ""
            },
            {
                "(en milliers de DH)": "Comptes d'associés",
                "31-déc.-23": "",
                "31-déc.-22": ""
            },
            {
                "(en milliers de DH)": "Autres créanciers",
                "31-déc.-23": "2 860",
                "31-déc.-22": "2 230"
            },
            {
                "(en milliers de DH)": "Comptes de régularisation passif",
                "31-déc.-23": "14 764",
                "31-déc.-22": "18 694"
            },
            {
                "(en milliers de DH)": "TOTAL",
                "31-déc.-23": "125 751",
                "31-déc.-22": "100 412"
            }
        ]
    ]
}