{
    "text": "LE LOYER TRANQUILLE POUR TOUS\nCOMMUNICATION FINANCIÈRE\nAU 31 DÉCEMBRE 2023\nImmorente Invest est une société propriétaire d’usines, de bureaux et d’actifs logistiques, tous\nloués à de grandes entreprises multinationales et à de grands groupes marocains. Immorente\nInvest perçoit ces loyers et les reverse à ses actionnaires. Historiquement, pour une part achetée\nautour de 100 DH, Immorente a payé 5,0 à 6,5 DH par an.\nImmorente Invest est une société cotée à la bourse de Casablanca, dont les actions sont\ndisponibles tous les jours et peuvent être acquises auprès des réseaux bancaires et sociétés de\nbourse.\nLien vers la communication financière : https://immorente.ma/relations-investisseurs/communication_\nfinanciere/2023-2/\nContact relation investisseurs : relation.investisseurs@immorente.ma\nwww.immorente.ma\nCOMMUNICATION FINANCIÈRE\nAU 31 DÉCEMBRE 2023\nLe Conseil d’Administration d’Immorente Invest s’est réuni le 23 février 2024 sous la présidence de Madame\nSouad BENBACHIR en vue d’examiner l’activité de la société au 31 décembre 2023.\nCHIFFRE D’AFFAIRES ET FFO EN HAUSSE RESPECTIVEMENT DE 8% ET 5 %\n• Loyers de 64 MDH en hausse de 8% par rapport à 2022\n• FFO (Résultat de l’exercice analytique) de 46,7 MDH en hausse de +5%\n• 160 MDH investis : 110 MDH dans une usine à Tanger Automotive City et 50 MDH dans l’OPCI Syhati IMMO\n• Rendement total payé en 2023 de 5 DH/action\n• Passage des normes comptables marocaines consolidées aux normes comptables IFRS consolidées\nACTIFS ET LOCATAIRES DIVERSIFIÉS ET DE QUALITÉ\n• Le portefeuille d’Immorente Invest est composé d’actifs prémium Ventilation du portefeuille par Ventilation des loyers par\nloués à des locataires de renom (Faurecia, SFC, Butec, Aptiv, catégorie d’actifs typologie de locataires\nFRI master franchisé de Mcdonald’s, Huawei, Groupe Société PME\nGénérale, etc..). Actifs Commerces 9%\nIndustriels 5%\n• La Société poursuit sa stratégie d’investissement à travers 47% Santé\nl’acquisition des murs d’une usine à TAC pour 110 MDH et 5%\nl’investissement dans l’OPCI Syhati IMMO pour 50 MDH. 970 MDH\nGrands\n• Lancement de la construction de l’extension d’une usine louée Bureaux Groupes\npar Faurecia à Atlantic Free Zone pour un investissement de 43% Marocains et\nInternationaux\nprès de 130 MDH. Le projet, dont la livraison est prévue pour le\n91%\nT4 2024, couvrira une surface de près de 9.000 m².\nCA CONSOLIDÉ IFRS : 72,2 MDH (+8%)\n• Le Chiffre d’affaires et les loyers en hausse de 8% vs 2022 Chiffre d’affaires(1) Loyers(2)\n• Le taux d’occupation est de 93% vs 92% à fin 2022 72,2 MDH\n• Par ailleurs le chiffre d’affaires social s’établie à 42,7 MDH 67,1 MDH 64,0 MDH\n59,3 MDH\n+8%\n+8%\n(1) Incluant loyers et refacturations des charges communes et de la taxe sur services communaux (TSC)\n(2) Loyers perçus : chiffre d’affaires diminué des taxes et charges locatives refacturées aux locataires\n2022 2023 2022 2023\nFFO (RESULTAT DE L’EXERCICE ANALYTIQUE) : 46,7 MDH (+5%)\n• Le FFO(3) (résultat de l’exercice(4) analytique) correspond à la FFO Résultat Consolidé IFRS\ncapacité distributive aux actionnaires : 46,7 MDH vs 44,7 MDH 46,7 MDH\nen 2022 44,7 MDH 42,8 MDH\n• Résultat net consolidé IFRS : 42,8 MDH\n+5%\n• Résultat net social : 4,4 MDH 15,8 MDH\nx3\n(3) FFO : Funds From Operations\n(4) Résultat de l’exercice (analytique) : conforme aux directives de l’EPRA), ne prend pas en compte des\néléments non cash comme les amortissements, les frais d’acquisition et les impôts différés, ne permettant pas\nd’apprécier la performance opérationnelle de la foncière\n2022 2023 2022 2023\nRATIO D’ENDETTEMENT : LOAN TO VALUE5 8% RENDEMENT PAYÉ ACTIF NET REEVALUE6 : 103,5 DH/ACTION\nPAR ACTION\n• Le ratio Loan to Value s’établit à 8% au 103 DH/ 103,5 DH/\n31 décembre 2023 action action\n8% 5,5 DH\n0% 5 DH 5,2 DH\nLTV LTV\n31/12/22 31/12/23 2022 2023 2024e ANR ANR\n(à distribuer) 31/12/22 31/12/23\n(5) LTV : ratio de la dette nette /par la valeur actualisée des (6) ANR de reconstitution : calculé sur la base des expertises immobilières\ninvestissements ht, incluant les frais d’acquisition réalisées par Cap Eval le 31 décembre 2023 (cf sur www.immorente.ma)\nGUIDANCE 2024\n• La Société anticipe une augmentation de 8% à 10% du chiffre d’affaires sur l’année 2024 sous l’effet conjugué de l’élargissement\ndu périmètre des actifs avec un investissement prévu courant l’année et la commercialisation de certains actifs bureaux.\n• La livraison de l’extension de l’usine Faurecia lors du T4 2024 augmenterait la part de l’industrie dans le portefeuille à prés de\n50% et réduirait celle du bureau à prés d’un tiers.\n• En conséquence, nous prévoyons un rendement à verser en 2024 de 5,2 dh/action en quatre distributions trimestrielles.\nwww.immorente.ma\nLE LOYER TRANQUILLE POUR TOUS Contact relation investisseurs :\nrelation.investisseurs@immorente.ma\nCOMPTES CONSOLIDÉS EN NORMES IFRS\nAU 31 DÉCEMBRE 2023\nBILAN ACTIF (EN KMAD) BILAN PASSIF (EN KMAD)\nExercice 2023.12 Exercice 2022.12 Exercice 2023.12 Exercice 2022.12\nGoodwill 2.583 2.583 Capital 563.298 563.298\nRéserves 220.935 250.431\nImmeubles de placement 934.366 822.625\nRésultat de l'exercice 42.783 15.812\nAutres actifs financiers 50.005 5\nTotal Capitaux propres, part du groupe 827.016 829.540\nImpôts différés 0 0\nIntérêts minoritaires 0 0\nActifs non-courants 986.954 825.213 Total Intérêts minoritaires 0 0\nStocks et en-cours 0 0 Total des capitaux propres 827.016 829.540\nClients et comptes rattachés 4.843 2.565 Emprunts et dettes financières 120.000 0\nComptes d'état 12.447 21.619 Dépôts et cautionnements des locataires 13.293 8.383\nAutres débiteurs 15 15 Impôts différés 54.342 51.242\nAutres actifs courants 325 268 Autres passifs long terme 0 0\nVMP et autres placements 7.588 43.105 Total Passifs non courants 187.635 59.625\nTrésorerie et équivalents de trésorerie 28.096 18.141 Emprunts et crédit à moins d'un an 150 0\nActifs courants 53.315 85.714 Banques (soldes créditeurs) 0 0\nProvisions (part à moins d'un an) 3.852 5.424\nActifs non courants et groupes d’actifs destinés à être cédés - - Dettes fournisseurs 10.674 7.206\nTotal Actif 1.040.269 910.927 Comptes d'Etat 9.035 8.492\nAutres créditeurs 1.906 638\nTotal Passifs courants 25.618 21.762\nCOMPTE DE RÉSULTAT CONSOLIDÉ IFRS (EN KMAD)\nTotal Passifs liés à un groupe d’actifs destinés à être cédés - -\nExercice 2023.12 Exercice 2022.12\nTotal des passifs 213.253 81.386\nChiffres d’affaires 72.215 67.055\nAchats consommés -2.248 -2.373 Total passif 1.040.269 910.927\nCharges de personnel - 0\nCharges externes -15.248 -13.573\nImpôts et taxes -5.999 -6.844 TABLEAU DE FLUX DE TRÉSORERIE CONSOLIDÉ EN KMAD\nRésultat d’exploitation 48.720 44.265\nDotations nettes de reprises aux provisions courantes 960 4.258 31/12/2023 31/12/2022\nAutres produits et charges d'exploitation -300 -300 Résultat net total des sociétés consolidées 42.783 15.812\nRésultat opérationnel courant 49.381 48.223 Elim. du résultat des mises en équivalence - 0\nAutres produits et charges opérationnels 296 -233 Elim. des amortissements et provisions -1.572 1.184\nRésultat opérationnel 49.677 47.990\nElim. des profits / pertes de réévaluation (juste valeur) 414 20.354\nProduits de trésorerie et d'équivalents de trésorerie 1.285 1.450\nCapacité d'autofinancement après coût de l'endettement 41.624 37.350\nCoût de l'endettement financier brut -1.133 -1.002 financier net et impôt\nProduits de placements financiers nets des charges 153 448\nElim. de la charge (produit) d'impôt 6.299 3.740\nd'intérêts\nRésultat de change -424 933 Capacité d'autofinancement avant coût de l'endettement financier 47.923 41.090\nnet et impôt\nPlus ou moins values sur réévaluations sur immeubles de -324 -29.400\nIncidence de la variation du BFR 9.481 -2.621\nplacement\nAutres produits et charges financiers - -420 Impôts payés -654 5.235\nFlux de trésorerie liés aux activités opérationnelles 56.750 43.705\nRésultat financier consolidé -595 -28.438 Augmentation des prises de participation dans les filiales -272 0\nRésultat avant impôt 49.082 19.552 consolidées\nImpôts sur les bénéfices -3.199 -3.565 Acquisition d'immobilisations corporelles et incorporelles -112.065 -30\nImpôts différés -3.100 -175 Flux de trésorerie liés aux activités d'investissement -162.337 -30\nTotal Impôts sur les bénéfices -6.299 -3.740 Emission d'emprunts 125.099 1.116\nRésultat après impôt 42.783 15.812 Dividendes payés aux actionnaires du groupe -45.035 -49.539\nDividendes payés aux minoritaires - 0\nRésultat net total 42.783 15.812\nVariation des crédits de trésorerie - 0\nImpot différé 3.100 175\nPlus ou moins values sur réévaluations sur immeubles de 324 29.400 Flux de trésorerie liés aux activités de financement 79.876 -100.355\nplacement Incidence de la variation des taux de change\nAutres retraitements 445 -727 Incidence des changements de principes comptables\nFFO (1) (Résultat analytique de l’exercice) 46.651 44.660\nVariation de trésorerie -25.711 -56.680\n(1) FFO : Fund From Opérations (Résultat de l’exercice analytique) : Résultat net consolidé IFRS corrigé des\nTrésorerie d'ouverture 61.246 117.926\néléments non cash tels que les impôts différés, la variation de la juste valeur des actifs et autres\nretraitements non cash. Trésorerie de clôture 35.534 61.246\nTABLEAU DE VARIATION DES CAPITAUX PROPRES CONSOLIDÉS EN KMAD\nAutres réserves groupe Autres\nPrimes Total Capitaux Total\nActions réserves et Intérêts\nCapital l cié ae ps it a au l propres conR vé es rse ir ov ne s g rd oe u pe A hou rtr se cs o r né vs ee rr sv ioe ns Total cr oé ns su ol lt ia dt és s pr do up gr re os u p pa ert minoritaires C pa rp oi pt ra eu sx\nSituation à l'ouverture de l'exercice 2022.12 563.298 177.696 - - 22.465 22.465 99.808 863.267 - 863.267\nIncidence des changements de méthode comptable : - - - - - - - - - -\nSituation ajustée à l'ouverture de l'exercice 2022.12 563.298 177.696 - - 22.465 22.465 99.808 863.267 - 863.267\nRéévaluation des immobilisations corporelle et incorporelles - - - - - -\nVar. nette de juste valeur des instruments financiers - - - - - - - - - -\nRésultat de la période - - - - - - 15.812 15.812 - 15.812\nTotal des pertes et profits de la période - - - - - - 15.812 15.812 - 15.812\nDividendes versés - -18.014 - - - - -31.525 -49.539 - -49.539\nAugmentation de capital - - - - - - - -\nAutres variations - - - - - - - - - -\nSituation à la clôture de l'exercice 2022.12 563.298 159.682 - - 22.465 22.465 84.095 829.540 - 829.540\nSituation à l'ouverture de l'exercice 2023.12 563.298 159.682 - - 22.465 22.465 84.095 829.540 - 829.540\nIncidence des changements de méthode comptable : - - - - - - - - - 0\nSituation ajustée à l'ouverture de l'exercice 2023.12 563.298 159.682 - - 22.465 22.465 84.095 829.540 - 829.540\nRéévaluation des immobilisations corporelle et incorporelles - - - - - - - - - -\nVar. nette de juste valeur des instruments financiers - - - - - - - - - -\nCouverture de flux de trésorerie - - - - - - - - - -\nEcarts de conversion - - - - - - - - - -\nRésultat de la période - - - - - - 42.783 42.783 - 42.783\nTotal des pertes et profits de la période - - - - - - 42.783 42.783 - 42.783\nDividendes versés - -36.028 - - - - -9.007 -45.035 - -45.035\nAugmentation de capital - - - - - -\nAutres variations - - - - - - -272 -272 - -272\nSituation à la clôture de l'exercice 2023.12 563.298 123.654 - - 22.465 22.465 117.599 827.016 - 827.016\nCOMPTES CONSOLIDÉS EN NORMES IFRS\nAU 31 DÉCEMBRE 2023\n1. REGLES ET METHODES COMPTABLES\n1.1 REFERENTIEL COMPTABLE 1.7.4 Actifs non courants destinés à être abandonnés ou cédés\nLes états financiers consolidés du Groupe Immorente Invest sont préparés en conformité avec Ces actifs sont reclassés sur décision du management des filiales et de la holding. Ils sont évalués\nles normes comptables internationales adoptées au sein de l’Union Européenne au 31 décembre au plus petits entre le coût amortis et la valeur nette de réalisation. Au 31 Décembre 2023, le\n2023 et telles que publiées à cette même date. groupe ne dispose pas d’actifs non courants destinés à être abandonnés ou cédés.\nCes normes sont disponibles sur le site : http://ec.europa.eu/internal_market/accounting/ias/\nindex_fr.htm. 1.7.5 Evaluation des créances clients\nLes normes comptables internationales comprennent les IFRS (International Financial Reporting Les créances clients sont comptabilisées pour leur valeur nominale.\nStandards), les IAS (International Accounting Standards) et leurs interprétations SIC (Standard Le Groupe comptabilise une provision pour correction de valeur des créances clients lorsqu’il\nInterpretation Commitee) et IFRIC (International Financial Reporting Interpretation Commitee). existe une probabilité objective de perte de crédit conformément à la norme IFRS 9.\n1.2 PERIMETRE DE CONSOLIDATION 1.7.6 Autres débiteurs courants\n1.2.1 Périmètre Les autres débiteurs correspondent à des créances à moins d’un an ne correspondant pas à\ndes créances clients.\nClôture Ouverture Une provision pour dépréciation est comptabilisée lorsque le montant actualisé des flux de\ntrésorerie futurs est inférieur à la valeur comptable d’une créance.\nTaux Taux de Méthode Taux Taux de Méthode\nUnités\nd’intérêt contrôle de conso d’intérêt contrôle de conso\n1.7.7 Trésorerie et équivalents de trésorerie\nImmorente SA 100,00 % 100,00 % IG 100,00 % 100,00 % IG\nLa trésorerie et équivalent de trésorerie, comprend :\nIMR FREE ZONE 100,00 % 100,00 % IG 100,00 % 100,00 % IG\n• Les fonds en caisse ;\nAmlak Atrium 100,00 % 100,00 % IG 100,00 % 100,00 % IG • Les chèques et valeurs à l’encaissement ;\nAmlak Contempo 100,00 % 100,00 % IG 100,00 % 100,00 % IG • Les fonds déposés en banque.\nIG signifie Intégration Globale Les découverts bancaires, crédits de trésorerie et les remboursements prévisionnels des dettes\nfinancières dont l’échéance est inférieure à 1 an sont comptabilisés en dettes financières courantes\n(soldes créditeurs des banques, emprunts et crédits à moins d’un an).\n1.2.2 Autres participations\nLe groupe ne détient pas d’autres participations ou des structures non consolidées en dehors 1.7.8 Passifs financiers\ndes instruments de capitaux propres par le biais des autres éléments du résultat global, détaillés\nau paragraphe (4.3). Les emprunts et autres passifs financiers porteurs d’intérêt sont évalués à leur valeur nominale.\nImmrente Invest a contracté une dette de financement de 90 millions de Dirhams, et un crédit à\nLe groupe ne détient pas d’intérêts dans des partenariats ou des entreprises associées. court terme destiné à être consolidé en crédit à moyen terme au cours de la période.\n1.3 RETRAITEMENTS DE CONSOLIDATION Dettes financières en KMAD\nLes transactions intervenues au cours de l’exercice entre les différentes filiales ont été éliminées.\nL Le es g a roc uti pfs e e nt ep a gs és ni èfs r eré pc aip sr doq ’ou pe és r ao tn iot né st é g é él nim érin aé ns t . des résultats internes. E 2x 0e 2r 2c .i 1c 2e Augmentation Remb. cV ouar ri sa dti eo n cs h ad ne gs e Va Pr éi ra it mio èn ts r ede Autres E 2x 0e 2r 3c .i 1c 2e\nEmprunts obligataires\n1.4 DATE DE CLOTURE E étm abp lr isu sn ets m a eu np tr sè ds e d ce rs é dit 120.000 120.000\nL da e d toa ute te sd e le c sl ô fit lu iar le e sd .u Groupe est le 31 décembre. Cette date correspond à la date de clôture A asu str imes il ée em sprunts et dettes 8.383 5.099 -188 13.293\nE finm ap nr cu ièn rt es s et dettes 8.383 125.099 -188 133.293\n1.5 CHANGEMENT D’ESTIMATIONS COMPTABLES ET ERREURS I en ct hé urê st às pco au yeru rs et non 150 150\nNéant.\nCrédits de trésorerie\n1.6 GOODWILL E d'm unp r au nnts et crédit à moins 150 150\nLe goodwill ou l’écart d’acquisition positif est défini comme étant la différence entre le coût du Banques (solde créditeurs)\nr ee t g dr eo su p pe am sse ifn st . d’entreprise et la part d’intérêts de l’acquéreur dans la juste valeur nette des actifs E finm ap nr cu ièn rts e set dettes 8.383 125.249 -188 133.443\nLe goodwill est évalué en Dirham marocain. Il fait l’objet d’un test de perte de valeur annuel.\n1.7.9 Provisions\nL’acquisition de la société AMLAK ATRIUM a généré un écart d’acquisition négatif de KMAD\n3.875, lors de la prise de participation de la société en 2019. Les provisions sont comptabilisées lorsqu’il existe une obligation légale ou implicite envers un\ntiers qui se traduira par une sortie de ressources, sans contrepartie attendue, nécessaire pour\nL’écart d’acquisition positif fait l’objet d’un test de dépréciation annuel. Ce test est basé sur une\néteindre cette obligation et pouvant être estimée de façon fiable.\nactualisation des cash-flow futurs des différentes filiales au coût moyen pondéré du capital.\nLes provisions comptabilisées par la société concernent certains actifs : clients et stocks. Le\nAu 31 décembre 2023, aucune provision n’a été constatée sur les écarts d’acquisition montant de ces provisions est destiné à couvrir les pertes éventuelles liées au recouvrement ou\ncomptabilisés par le Groupe. à la réalisation des stocks.\nLes provisions concernent également certaines obligations notamment fiscales, pour lesquelles,\nle Groupe ne dispose pas de visibilité quant à leurs échéances.\nTableau de variatin des écarts d’acquisition/Goodwill en KMAD\nE 2x 0e 2r 2c .i 1c 2e E pn ét rr imée ès t rd ee pS éo rr it mie ès td re e va pr éA i rau it mt ior èe n ts s r ede lD 'eo xta edt rei co in ces dV d ea e r s ci ha ct aoi nuo gn rs es Autres E 2x 0e 2r 3c .i 1c 2e Provisions en KMAD\nE A d'c m aa ctr q/t P u d e i' sra it tc e iq osu n vis ai lt .i o én cart 2.583 2.583 E 2x 0e 2r 2c .i 1c 2e lD 'eo xta edt rei co in ces uR ( te p ilp r isr o éi vs e.e ) uR ( te p in lp r io sr o n éi vs e.e ) dV d ea e cr s hi a c at o ni uo gn r ess s pV éa rr ii d ma et èi o tn res Re mcl ea ns ts se- I cn dhc eai d mne g én e tc hme os e d nd ete sss E 2x 0e 2r 3c .i 1c 2e\nTotal Valeur Nette 2.583 2.583 Autres\nprovisions 4.346 309 -1.886 2.769\npour impôts\n1.7 PRINCIPALES METHODES D’EVALUATION Total\nProvisions 4.346 309 -1.886 2.769\n1.7.1 Immobilisations incorporelles pour risques\nLa société ne détient pas d’immobilisations incorporelles. P poro uv ri s ci ho an rs g es 5 5\nAutres\n1.7.2 Immobilisations corporelles p pr oo uv ri s ri io sn qus es 1.079 1.079\nLa société ne détient pas d’immobilisations corporelles. et charges\nTotal\nProvisions 1.079 5 1.084\n1.7.3 Immeubles de placement pour charges\nLes immeubles de placement détenus correspondent à des bâtiments ayant fait l’objet d’un\ncontrat de location pour en retirer des loyers.\nDépréciation de l’actif circulant en KMAD\nLes immeubles de placement sont évalués à leur juste valeur. La périodicité de réévaluation de\nl L ea a x pj u ju es s rt te t e e v sva ta le il neu dur r é e d ps e et s na din m an nmu te e el ul te b d. le iss p d oe se p dla ’c ue nm e e qn ut a e lis fit c d até iote nr m prin oé fee s sp ia or n u nn e le lex p pe er rt t id nea nn ts e l e e td ro em coa nin ne u. e C le ut i E 2x 0e 2r 2c .i 1c 2e lD 'eo xta edt rei co in ces uR ( te p ilp r isr o éi vs e.e ) uR ( te p in lp r io sr o n éi vs e.e ) dV d ea e cr s hi a c at o ni uo gn r ess s pV éa rr ii d ma et èi o tn res Re mcl ea ns ts se- c dhI en a mc ni gdd éeee thmsn o c e de n es t s s E 2x 0e 2r 3c .i 1c 2e\npermettant d’apprécier les immeubles en question. Provisions pour\nLes immeubles de placement ne font pas l’objet de restrictions quant à leur utilisation. Il n’existe dép. des cptes -1.481 -2.091 1.465 -2.107\npas d’obligations contractuelles sur ces biens. clients ratt.\nTotal Dép. s/\nLes immeubles de placement du groupe génèrent un loyer constaté en chiffre d’affaires. c cr lié ea nn tsc e es t cptes. -1.481 -2.091 1.465 -2.107\nLe montant cumulé des plus-values constatées sur les immeubles de placement s’élève à KMAD rattachés\n80 801 au 31 Décembre 2023 :\nTotal -\nDépréciation de -1.481 -2.091 1.465 -2.107\nImmeubles de placement en KMAD l'actif circulant\nE 2x 0e 2r 2c .i 1c 2e Ac tiq ou ni ssi- C e ae ut s m rs eii so ben uss\nt\nlD 'eo xta edt rei co in ces PVa ér ri ida meti\nè\no tn res dV ea\nv\nr l ai aa\nl\net jui uo s rn tes Re mcl ea ns ts se- I c dn h ec a i mnde g én e thmce oe dd n ee t sss E 2x 0e 2r 3c .i 1c 2e 1.7.10 Coût d’emprunt\nLes coûts d’emprunt liés à l’acquisition ou à la production d’un actif sont intégrés au coût de cet actif.\nI pm lam cee mub el ne ts de 822.625 112.065 -324 934.366 Pour l’exercice 2023, les coûts d’emprunt ne sont pas intégrés dans le coût de l’actif. Le groupe\nAmortisse-ments estime que le montant correspondant n’est pas significatif.\ndes immeubles\nde placement\nTotal Valeur 1.8 PASSIFS EVENTUELS\nNette Immeubles 822.625 112.065 -324 934.366 Les sociétés du Groupe pourraient faire l’objet de contrôles fiscaux pour les exercices non prescrits.\nde placement\nCOMPTES CONSOLIDÉS EN NORMES IFRS\nAU 31 DÉCEMBRE 2023\n1.9 JUSTE VALEUR\n3. ENGAGEMENTS HORS BILAN\nLe groupe ne détient pas de passifs évalués à la juste valeur.\nLes actifs évalués à la juste valeur sont composés de :\n3.1 TABLEAU DES SURETES REELLES DONNEES OU REÇUES\n• Les immeubles de placement : la juste valeur de ces actifs est fondée sur des données non\no db os me ar iv na eb . l Ces e. t L ea x pju es rt te e v sa t l ie nu dr é d pe es n dim anm t e eu t b dl ie ss p d ose e p dla ’uc ne em qe un at le ifis ct ad té iot ne r pm roin fé ee ss p ioa nr nu en l lee x pp ee rr tit n d ea nn tes ele t Tiers créditeurs ou tiers débiteurs sc ûo ruM ev teo érn t (t K a p Mn at Ar Dla ) Nature dD ’ia nt se c e rit p l tie iou n Objet n de at ttV eea dsle û eu r cer l t ôc é to udm ro ep n t (na Kéb Mele A à D l )a\nreconnue, et dispose des qualifications professionnelles lui permettant d’apprécier la valeur des Sûretés données\nimmeubles en question. Il se base sur sa connaissance du marché ainsi que sur les informations Hypothèque de premier rang sur le TF\nqu’il peut récupérer sur des transactions similaires ; N le° c8 a9 d5 r7 e/ 7 d1 ’u a nu c p rr éo df ii tt àd e lo C nF gG te B rmAN eK d ed ans 100000 Hypothèque 18/09/23 E bam np cr au irn et Non définie\n• Les valeurs mobilières de placement et autres placements, sont évaluées à la juste valeur MAD 90.000.000.\npar le biais du compte de résultat. La juste valeur de ces actifs est basée sur des données Nantissement de 700000 actions\nobservables : marché actif par exemple ou assimilé… ; d c Aaé Tpt Re it In Uau l\nM\ne ss o\na\ncp uia a pr l\nr\ndl o’ ee\nfi\nm tl a dp esr o u Ccn Fiét Ge téu\nd\nr A\na\nd nMa sLn lAs\ne\nK l ce\na dre\n90 000 000 Nantissement 18/09/23 E bam np cr au irn et Non définie\n• Les actifs financiers non courants comprennent des instruments de capitaux propres évalués d’un crédit de MAD 90.000.000.\nà la juste valeur par les capitaux propres. Les données concernant la juste valeur de ces actifs Sûretés reçues NEANT\nsont fondées sur des données non observables. Par conséquent, ces actifs sont évalués au\ncoût d’achat, sauf en cas de constatation d’opération sur les capitaux propres de ces entités 3.2 AUTRES ENGAGEMENTS FINANCIERS DONNES OU REÇUS\n(augmentation de capital, cession d’action dans des proportions significatives…). Dans ce cas, la\njuste valeur correspond à la valorisation utilisée pour ces opérations. Engagements donnés EN KMAD Montants exercice Montants exercice précédent\nNEANT\nL’impact des évaluations sur le résultat (en KMAD avant impôts différés) est détaillé comme suit :\nCatégorie Méthode de valorisation l’oIm uvp ea rc tt u à r e Imp pa éc rt io s du er la Im cp lôa tc ut rà e la E Can ug tioa ng pe em rsoe nn nt es lle r ee tç su os lid E aiN re K deM MA . D YO UNATHAN HARROCH au profit de GYMNAS AVENUE pour toute somme relative M exo en rt ca in ct es Mon pta rn ét cs é de exe nr tcice\nau reliquat de créance telle que définie dans le protocole d’accord signé le 29 décembre 2021 dont elle sera redevable en\nImmeubles de placement Evaluation par un expert indépendant 81.125 -324 80.801 principal outre intérêts et frais à l’égard de AMLAK ATRIUM. Renonciation expresse au bénéfice de division et de discussion Non défini Non défini\nVMP et autres placements Prix observable sur un marché actif 457 -45 412 en cas d’exécution forcée pour payer à première demande AMLAK ATRIUM.\nEngagement de GYMNAS AVENUE à remettre à AMLAK ATRIUM, au plus tard le 31 décembre 2022, une garantie bancaire à\nAucun impact significatif n’a été observé sur ces actifs du fait de la réalisation des placements première demande consentie par une banque marocaine, d’un montant de MAD 1.521.180 correspondant à neuf mois de\nloyers hors taxes et hors charges au profit de AMLAK ATRIUM en vue de garantir toute somme qui pourrait être due au titre de\nle dernier jour de l’exercice. l’exécution et/ou de la résiliation du bail, de ses avenants et du protocole et ce dans la limite d’un montant maximum de MAD 1 521 180 1 521 180\n1.521.180. Engagement de GYMNAS AVENUE de libérer les locaux au plus tard le 31 janvier 2023 en cas de non présentation\nde la garantie ci-dessus au delà de la date du 31 décembre 2022.\n1.10 IMPOTS DIFFERES E dn e g laa g de am tee dn et d rée c l ea p B tia on nq pu ae r C lar é Bd ait n d qu u eM da er o lac dd ee m pr ao nc dé ed e cor ra ru e sv pir oe nm dae nn tt e d . e (Asd Mit Le As K s Ao Tm Rm IUe Ms )dans un délai de 15 jours à compter Non défini Non défini\nLes impôts différés actifs proviennent des différences temporaires liées aux retraitements sur les Caution personnelle et solidaire de M. YOUNATHAN HARROCH au profit de GYMNAS AVENUE pour toute somme relative\ncomptes consolidés et des différences temporelles déductibles entre les valeurs comptables et a eu n r pe rl ii nq cu ipa at ld oe u c trr eé a inn tc ée r êt te sl le e tq fu rae i sd é àfi ln ’éie g ad ra dn s d ele A p Mro Lt Ao Kc o Cle O Nd’ Ta Ec Mco Pr Od . s Rig en né o nle c ia2 t9 io nd é ec xe pm reb sr se e 2 a0 u2 1 b éd no én fit c e el l de es e dr iva i sr ie od ne eva t b dl ee Non défini Non défini\nfiscales des actifs et passifs. discussion en cas d’exécution forcée pour payer à première demande AMLAK CONTEMPO.\nLe groupe n’a pas de déficits fiscaux. Engagement de GYMNAS AVENUE à remettre à AMLAK CONTEMPO, au plus tard le 31 décembre 2022, une garantie bancaire\nLa politique de distribution des dividendes n’a pas d’impact sur l’impôt sur le résultat du groupe. à première demande consentie par une banque marocaine, d’un montant de MAD 1.194.750 correspondant à neuf mois de\nloyers hors taxes et hors charges au profit de AMLAK CONTEMPO en vue de garantir toute somme qui pourrait être due au\ntitre de l’exécution et/ou de la résiliation du bail, de ses avenants et du protocole et ce dans la limite d’un montant maximum Non défini Non défini\nImpôts différés en KMAD de MAD 1.194.750,25. Engagement de GYMNAS AVENUE de libérer les locaux au plus tard le 31 janvier 2023 en cas de non\nprésentation de la garantie ci-dessus au delà de la date du 31 décembre 2022\nE 2x 0e 2r 2c .i 1c 2e In réci sd ue ln tac te cV ouar ri sa dti eo n cs h ad ne gs e Va pr éi ra it mio èn ts r ede Autres E 2x 0e 2r 3c .i 1c 2e E dn e g laa g de am tee dn et d rée c l ea p B tia on nq pu ae r C lar é Bd ait n d qu u eM da er o lac dd ee m pr ao nc dé ed e cr o ra ru e pv sir oe nm dae nn tt e d . e Ts (Ad Mite Ls A s Ko m COm Ne Ts E d Ma Pn Os )un délai de 15 jours à compter Non défini Non défini\nImpôts différés - actif\nImpôts différés - passif 51.242 3.010 90 54.342 RÉSUMÉ DU RAPPORT GÉNÉRAL DES COMMISSAIRES AUX\nSolde net d'impôt différé -51.242 -3.010 -90 -54.342 COMPTES SUR LES COMPTES CONSOLIDÉS\nE 2x 0e 2r 2c .i 1c 2e In réci sd ue ln tac te cV ouar ri sa dti eo n cs h ad ne gs e Va pr éi ra it mio èn ts r ede Autres E 2x 0e 2r 3c .i 1c 2e\nID / différences temporaires 2.847 -464 2.383\nID / Autres retraitements -5 -5\nID sur écart d'évaluation 100% -21.373 -155 591 -20.937 7, Boulevard Driss Slaoui 4, Place Maréchal\nCasablanca Casablanca\nID/ autres retraitements IFRS (*) -32.672 33 -694 -33.333\nAux actionnaires de la société\nID / Annulation frais d'établissement 90 -2.436 -2.346 IMMORENTE INVEST S.A.\n5/7 – Rue Ibnou Toufail Palmiers\nID/ Retrait. juste valeur instrum. financiers -129 11 13 -105 Casablanca\nRapport des commissaires aux comptes sur les états financiers consolidés\nSolde net d'impôt différé par Nature -51.242 -3.010 -90 -54.342 Exercice du 1er janvier au 31 décembre 2023\nOpinion\nNous avons effectué l’audit des états financiers consolidés de la société IMMORENTE INVEST S.A et de ses filiales (le « Groupe »), qui comprennent\nl’état consolidé de la situation financière au 31 décembre 2023, ainsi que l’état consolidé du résultat global, l’état consolidé des variations des\nImpôts sur les bénéfices / ventilation impôt exigible/différé en KMAD capitaux propres et le tableau consolidé des flux de trésorerie pour l’exercice clos à cette date, ainsi que les notes annexes, y compris un résumé\ndes principales méthodes comptables. Ces états financiers consolidés font ressortir un montant de capitaux propres consolidés de KMAD 827.016\nExercice 2023.12 Exercice 2022.12 d No on ut s u cn e rb tié fin oné sfi c qe u en e let sc o én tas to sl i fd iné a d ne ci eK rsM cA oD n s4 o2 li. d7 é8 s3 c. ités au premier paragraphe ci-dessus, sont réguliers et sincères et donnent dans tous leurs aspects\nImpôt différé - 3 100 - 175 significatifs, une image fidèle de la situation financière consolidée du groupe au 31 décembre 2023, ainsi que de sa performance financière consolidée et\nde ses flux de trésorerie consolidés pour l’exercice clos à cette date, conformément aux Normes Internationales d’Information Financière (IFRS).\nImpôts sur les bénéfices -3.199 -3.565 Fondement de l’opinion\nImpôts sur les bénéfices - 6 299 - 3 740 N plo uu s s a mav po len ms e ef nfe t c dt éu cé r in teo st r de a a nu sd lait s se el co tn io nle «s RN eo srm poe ns s d ae b il la ité P sr o df ee ls ’as uio dn it ea uu r M à a l’r éo gc a. rL de ds e r e l’as up do in t s da eb si l éit té as t sq fu ini an no cu is e ri sn c co om nsb oe lin dt é e sn » v de urt u p rd ée s ec ne ts r an po prm ore t.s N s oo un st\nsommes indépendants du groupe conformément aux règles de déontologie qui s’appliquent à l’audit des états financiers consolidés au Maroc et nous\nnous sommes acquittés des autres responsabilités déontologiques qui nous incombent selon ces règles. Nous estimons que les éléments probants\nque nous avons obtenus sont suffisants et appropriés pour fonder notre opinion d’audit.\n1.11 AVANTAGE AU PERSONNEL\nQuestions clés de l’audit\nLe groupe ne dispose pas de personnel. L coe ns sq ou lie ds ét sio dn es c lalé ps é d re io l d’a eu cd oit n s so idn ét rle és e .q Cue es st i qo un es s q tiu oi n, ss e olo nn t én to ét r te ra ju itég ee sm de an nt sp r lo ef e cs os ni to en xn tee l, d o en nt oé tt ré e le as u dp il tu ds e im s p éo tar tt sa n fit ne as n d ca ien rs s l’ ca ou nd sit o d lide és s é t pa rt is s f din aa nn sc li ee urs r\nensemble et aux fins de la formation de notre opinion sur ceux-ci, et nous n’exprimons pas une opinion distincte sur ces questions.\nRisque identifié Notre réponse\n1.12 PRODUITS DES ACTIVITES ORDINAIRES Evaluation des immeubles de placement Nos contrôles consistent à :\nAu 31 décembre 2023, la juste valeur des immeubles de placement du groupe - Prise de connaissance du processus d’évaluation des\nLes produits des activités ordinaires sont composés des catégories suivantes : s’élève à 934,36 MMAD. Ces immeubles de placement représentent 89,81% du immeubles de placement mis en place par le groupe ;\ntotal actif consolidé du groupe. - Appréciation de la compétence et de l’indépendance de\n• Loyer ; La détermination de la juste valeur s’appuie sur des évaluations externes l’évaluateur externe mandaté par le groupe\n• Refacturation des Charges locatives. i ln ed s é mpe én thd oa dn ete ss e. tC he ys p oé tv ha èl su ea sti o un ts ili sf éo en st a ep t p tie el n na eu n j tu cg oe mm pe tn et pp rr io nf ce ipss ai lo en mn ee nl t p do eu sr - d eA p vp ar lé oc rii sa ati to ion n d re e tl ea n p ue er sm pa an re n l’éce va e lut ad te e ula r ep xe tr eti rn ne en , c le e d pe és ri mm èé tt rh eo d de es s\ncaractéristiques intrinsèques des actifs, en l’occurrence, les états locatifs, actifs expertisés ainsi que les hypothèses de valorisation retenues ;\ndonnées commerciales des loyers, taux de recouvrement des loyers et taux de - Rapprochement des valeurs comptabilisées à la juste valeur\n1.13 ACTIFS NON COURANTS DETENUS EN VUE DE LA VENTE ET ACTIVITES r ae inn sd ie qm ue en dt. eC s e t eta rmux e sd e d er se n cd oe nm trae tn st dtie en bt ac io l.mpte des caractéristiques de l’actif a - v De ic s cle us s sd ioo nn n aé ve es c re les s mo art na an gt ed mu era np t p so ur rt d lee cl’ ae rx ap ce tèrt r ein d raé ip se on nd na an bt l e;\nDESTINEES A ETRE ABANDONNEES L coe ûs t i jm usm qe uu ’àb le les u rd e a chp èla vc ee mm ee nn tt . Le en s c io mu mrs e ud be l esc o dn est r pu lc at cio en m eso nn t t ené va colu ué rs s da eu d de és v elh oy pp po eth mès ee ns t retenues en liaison avec les projets en\nAu 31 Décembre 2023, le Groupe ne dispose pas d’activités destinées à être abandonnées. c Lo ’én vs at lr uu ac tt ii oo nn ds eo sn t imév ma elu ué bs le sa u d ec oû pt la cju es mq eu n’à t , le yu r c oa mch pè risv em lese nt im. meubles de - a cqTe us ist is ti ons su bs at ua n tt ii tf rs e d de e s dé at ca ti il fs s ep na r cé oc uh rsa n vti allo lon rn isa ég se as uu r c ol ûe ts .\nplacement en cours de construction, constitue un point clé de l’audit en raison - Examen de la conformité de la méthodologie appliquée par le\ndu niveau de jugement requis par l’expert indépendant pour ces évaluations et groupe aux normes comptables en vigueur et de la pertinence de\nde l’importance de ce poste dans l’état de la situation financière consolidée et l’information présentée dans les comptes consolidés.\nl’état du résultat global consolidé.\n2. DETAIL DES ETATS FINANCIERS Responsabilités de la direction et des responsables de la gouvernance à l’égard des états financiers consolidés\nLa direction est responsable de la préparation et de la présentation fidèle des états financiers conformément aux Normes Internationale d’Information\nFinancière (IFRS), ainsi que du contrôle interne qu’elle considère comme nécessaire pour permettre la préparation d’états financiers consolidés\nexempts d’anomalies significatives, que celles-ci résultent de fraudes ou d’erreurs.\n2.1 TABLEAU DES FLUX DE TRESORERIE Lors de la préparation des états financiers consolidés, c’est à la direction qu’il incombe d’évaluer la capacité du groupe à poursuivre son exploitation, de\ncommuniquer, le cas échéant, les questions se rapportant à la continuité de l’exploitation et d’appliquer le principe comptable de continuité d’exploitation,\n• Les montants correspondants à de la trésorerie et équivalents de trésorerie sont disponibles et s Il a inu cf osi m la b ed ir ae uc xti o ren s a p ol’i nn ste an bt lio en s dde e l li aq u gi od ue vr ele r ng aro nu cp ee d o eu s d ue rv c ee ils les re lr e s po rn o ca ect siv si uté s o du ’i ns fi o a ru mc au tn ioe n a fu intr ae n s co ièlu retio dn u r é ga rolis ut pe e n .e s’offre à elle.\nn’ont pas fait l’objet d’aucune restriction. Responsabilités de l’auditeur à l’égard de l’audit des états synthèse consolidés\n• La société a payé une correction de prix pour les participations AMLAK ATRIUM et AMLAK Nos objectifs sont d’obtenir l’assurance raisonnable que les états financiers consolidés pris dans leur ensemble sont exempts d’anomalies\nsignificatives, que celles-ci résultent de fraudes ou d’erreurs et de délivrer un rapport de l’auditeur contenant notre opinion. L’assurance raisonnable\nCONTEMPO. correspond à un niveau élevé d’assurance, qui ne garantit toutefois pas qu’un audit réalisé conformément aux normes de la profession au Maroc\npermettra toujours de détecter toute anomalie significative qui pourrait exister. Les anomalies peuvent résulter de fraudes ou d’erreurs et elles sont\nconsidérées comme significatives lorsqu’il est raisonnable de s’attendre à ce que, individuellement ou collectivement, elles puissent influer sur les\ndécisions économiques que les utilisateurs des états financiers consolidés prennent en se fondant sur ceux-ci.\n2.2 ACTIFS FINANCIERS Dans le cadre d’un audit réalisé conformément aux normes de la profession au Maroc, nous exerçons notre jugement professionnel et faisons\npreuve d’esprit critique tout au long de cet audit. En outre :\nLes actifs financiers sont composés de 2 catégories : ▪ fr an uo du es sid oe un t dif ’i eo rn res ue rt s é , v ca ol nu co en vs o l ne ss eri ts mqu ee tts o nq su e e nle s œ é ut va rt es f din ea sn pc ri oe crs é dc uo rn es so l did ’aé us d c ito em np ro ér pte on nt s d ee às ca en so m risa qli ue es s s , ig en t i rf éic ua nti iv se sos, n q s u de e c se éll le és m-c ei n r té ss pu rlt oe bn at nd te s\n• Dépôts, cautionnements, créances et prêts financiers dont les bénéficiaires sont le personnel s qu uf efi s ca en luts i de ’ut na ep p ar no op mrié as li ep o siu gr n f io ficn ad te ivr en ro étr se u lo tap nin t i do ’n u. n L ee e r ri rs eq uu r,e c d ae r ln ao frn a- ud dé ete pct eio un t imd’u pn liqe u a en r o lam ca oli le lu ss ii og nn ,if i lc aa ft aiv lse if ir cé as tu iolt na ,n let sd ’ ou mne is f sra iou nd se v e os lot np tl au is re é sl ,e lv eé s\nou d’autres tiers. Ces éléments sont évalués au coût amorti. Ces actifs sont considérés comme fausses déclarations ou le contournement du contrôle interne ;\n• nous acquérons une compréhension des éléments du contrôle interne pertinents pour l’audit afin de concevoir des procédures d’audit\nétant non courants si leur échéance dépasse l’exercice suivant la date de clôture. Le montant appropriées aux circonstances, et non dans le but d’exprimer une opinion sur l’efficacité du contrôle interne du groupe ;\nde ces actifs s’élève à KMAD 5 ; • la n do iu res c a tip op nr , é dc eio mns ê mle e c a qr ua ec t dè ere s ia np fop rr mop ar ti ié o nd se s y m affé ét rh eo nd te es s c foo um rnp it ea sb ple as r r ce ete ttn eu de es r ne it è l re e c ;a ractère raisonnable des estimations comptables faites par\n• nous tirons une conclusion quant au caractère approprié de l’utilisation par la direction du principe comptable de continuité d’exploitation et,\n• Actifs financiers évalués à la juste valeur par le biais du compte de résultat. Ces actifs sont selon les éléments probants obtenus, quant à l’existence ou non d’une incertitude significative liée à des événements ou situations susceptibles\ncomposés de placement de trésorerie (OPCVM) ou titres cotés détenus pour des fins de d ne o uje st e sr o u mn m d eo su t te e nim up s o dr ’t aa tn tit r esu r r l ’ala t tc ea np tia oc ni té d ed su lg er co teu up re s à d p eo nu ors tru eiv rr ae p s po on r te sx up rl o leita st i io nn fo. rS mi an to iou ns s c o fon uc rl nu io en ss d à a l n’e sx li est se n éc tae t sd ’ fu inn ae n i cn ic ee rsrt i atu ud e s us ji eg tn difi ec a ct eiv te te,\nplacement de trésorerie. Le montant de ces actifs s’élève à KMAD 7.588. L’évolution de ces incertitude ou, si ces informations ne sont pas adéquates, d’exprimer une opinion modifiée. Nos conclusions s’appuient sur les éléments probants\nobtenus jusqu’à la date de notre rapport. Des événements ou situations futurs pourraient par ailleurs amener le groupe à cesser son exploitation ;\nactifs est détaillée au niveau de la note 3.9 ; • nous évaluons la présentation d’ensemble, la structure et le contenu des états financiers consolidés, y compris les informations fournies dans\nles notes, et apprécions si les états financiers consolidés représentent les opérations et événements sous-jacents d’une manière propre à\n• Des instruments de capitaux propres évalués à la juste valeur par le biais des autres éléments donner une image fidèle.\n• nous obtenons des éléments probants suffisants et appropriés concernant les informations financières des entités et activités du groupe pour\ndu résultat global. Le montant de ces actifs s’élève à KMAD 50.000. L’évolution de ces actifs est exprimer une opinion sur les états financiers consolidés. Nous sommes responsables de la direction, de la supervision et de la réalisation de\ndétaillée au niveau de la note 3.9. l’audit du groupe. Nous assumons l’entière responsabilité de l’opinion d’audit.\nNous communiquons aux responsables de la gouvernance notamment l’étendue et le calendrier prévus des travaux d’audit et nos constatations\nAu cours de l’exercice, le Groupe n’a pas procédé à des reclassements d’actifs financiers. importantes, y compris toute déficience importante du contrôle interne que nous aurions relevée au cours de notre audit.\nCasablanca, le 26 février 2024\nLes Commissaires aux Comptes\n2.3 RESULTAT PAR ACTION\nLe résultat par action est calculé par référence au nombre moyen d’actions émises à la date de\nclôture. Aucun effet dilutif n’est observé au cours des 2 derniers exercices.\nLe résultat utilisé pour le calcul du résultat par action correspond au résultat net part du groupe.\nCOMPTES CONSOLIDÉS EN NORMES MAROCAINES\nAU 31 DÉCEMBRE 2023\nBILAN CONSOLIDÉ (En kDH) TABLEAU DE FLUX DE TRÉSORERIE CONSOLIDÉ EN KMAD\nExercice 31/12/2023 31/12/2022\n12/2023\n12/2022 Résultat net total des sociétés consolidées 1.589 8.411\nValeurs Amort. Valeurs Valeurs Elimination des amortissements et provisions 32.931 34.164\nACTIF\nbrutes prov. nettes nettes Elimination de la variation des impôts différés 1.895 4.415\nEcarts d'acquisition 88.782 -26.802 61.980 65.980 Elimination des plus ou moins values de cession\nImmobilisations incorporelles - - - - Elimination de la quote-part de résultat des mises en équivalence\nImmobilisations corporelles 823.684 -153.269 670.415 597.118 Autres produits et charges non liés aux activités opérationnelles\nImmobilisations financières 50.005 - 50.005 5 Total marge brute d'autofinancement 36.415 46.990\nDividendes reçus des mises en équivalence\nTitres mis en équivalence - - -\nVariation du BFR lié à l'activité 12.115 -2.866\nTotal Actif Immobilisé 962.471 -180.072 782.399 663.103\nFlux net généré par (affecté à) l'activité 48.530 44.125\nStocks et en-cours - - -\nAcquisition d'immobilisations -153.799 -30\nClients et comptes rattachés 6.951 -2.107 4.843 2.565\nCession d'immobilisations\nAutres créances et comptes de 16.837 - 16.837 27.847\nIncidence des variations de périmètre -272\nrégularisation\nVariation nette des placements court terme\nTotal Actif Circulant 23.788 -2.107 21.681 30.412\nFlux net provenant des (affecté aux) investissements -154.072 -30\nValeurs mobilières de placement 7.176 - 7.176 42.648\nDividendes versés par la société mère -45.035 -49.539\nDisponibilités 28.096 28.096 18.141 Dividendes versés aux minoritaires\nTotal Valeurs mobilières de 35.272 - 35.272 60.789 Augmentations (réductions) de capital\nplacements et disponibilité\nSubventions d'investissements reçues\nTotal Actif 1.021.531 -182.179 839.352 754.303 Emissions d’emprunts / Augmentation des dpôts reçus 95.099 1.116\nRemboursements d’emprunts / Remboursement des dépôts reçus -188 -51.933\nPASSIF Exercice 12/2023 Exercice 12/2022 Cession (acq.) nette actions propres\nVariation nette des concours bancaires 30.000\nCapital 563.298 563.298\nFlux net provenant du (affecté au) financement 79.876 -100.355\nPrimes liées au capital 123.654 159.682 Incidence de la variation des taux de change\nEcart de réévaluation 17.495 17.495 Incidence des changements de principes comptables\nRéserves -25.596 -24.727 Variation de trésorerie -25.666 -56.260\nRéserves de conversion groupe - - Trésorerie d'ouverture 60.788 117.048\nTrésorerie de clôture 35.122 60.788\nRésultat de l'exercice 1.589 8.411\nAutres - -\nRAPPORT DU COMMISSAIRE AUX COMPTES\nTotal Capitaux Propres 680.440 724.159\nSUR LES COMPTES CONSOLIDÉS\nIntérêts hors groupe - -\nAutres fonds propres - -\nProvisions 3.852 5.424\nEmprunts et dettes financières 103.293 8.383\nTotal Passif à long terme 107.146 13.807 7, Boulevard Driss Slaoui 4, Place Maréchal\nCasablanca Casablanca\nFournisseurs et comptes rattachés 10.674 7.206\nAux actionnaires de la société\nAutres dettes et comptes de régularisation 10.942 9.131 IMMORENTE INVEST S.A.\n5/7 – Rue Ibnou Toufail Palmiers\nEmprunts et concours bancaires à moins d'un an 30.150 1 Casablanca Rapport des commissaires aux comptes sur les états de synthèse consolidés\nExercice du 1er janvier au 31 décembre 2023\nTotal Passif à court terme 51.766 16.337 Opinion\nNous avons effectué l’audit des états de synthèse consolidés de la société IMMORENTE INVEST S.A et de ses filiales (le « groupe »), qui\ncomprennent le bilan consolidé au 31 décembre 2023, ainsi que le compte de produits et charges consolidé, l’état consolidé des variations des\ncapitaux propres et le tableau consolidé des flux de trésorerie pour l’exercice clos à cette date, ainsi que l’état des informations complémentaires\nTotal Passif 839.352 754.303 (ETIC), y compris un résumé des principales méthodes comptables.\nCes états de synthèse consolidés font ressortir un montant de capitaux propres consolidés de KMAD 680.440 dont un bénéfice net consolidé\nde KMAD 1.589.\nNous certifions que les de synthèse consolidés cités au premier paragraphe ci-dessus, sont réguliers et sincères et donnent dans tous leurs\naspects significatifs, une image fidèle du patrimoine et de la situation financière du groupe au 31 décembre 2023, ainsi que du résultat de\nl’ensemble consolidé pour l’exercice clos à cette date, conformément au référentiel comptable en vigueur au Maroc.\nCOMPTE DE PRODUITS ET CHARGES CONSOLIDÉ (En kDH)\nFondement de l’opinion\nNous avons effectué notre audit selon les Normes de la Profession au Maroc. Les responsabilités qui nous incombent en vertu de ces normes\nsont plus amplement décrites dans la section « Responsabilités de l’auditeur à l’égard de l’audit des états de synthèse consolidés » du présent\n12/2023 12/2022 rapport. Nous sommes indépendants du groupe conformément aux règles de déontologie qui s’appliquent à l’audit des états de synthèse au\nMaroc et nous nous sommes acquittés des autres responsabilités déontologiques qui nous incombent selon ces règles. Nous estimons que les\néléments probants que nous avons obtenus sont suffisants et appropriés pour fonder notre opinion d’audit.\nChiffre d'affaires 72.215 67.055\nQuestions clés de l’audit\nAutres produits d'exploitation -0 - Les questions clés de l’audit sont les questions qui, selon notre jugement professionnel, ont été les plus importantes dans l’audit des états\nfinanciers consolidés de la période considérée. Ces questions ont été traitées dans le contexte de notre audit des états financiers consolidés\nAchats et autres charges externes -20.134 -15.946 pris dans leur ensemble et aux fins de la formation de notre opinion sur ceux-ci, et nous n’exprimons pas une opinion distincte sur ces questions.\nRisque identifié Notre réponse\nCharges de personnel - - Dépréciation des immobilisations corporelles et des écarts d’acquisition Nos contrôles consistent à :\nLes immobilisations corporelles et les écarts d’acquisition représentent une valeur - Examiner le correct calcul des dotations aux\nAutres charges d'exploitation -300 -300 nette de KMAD 732.394 soit 87,26% du total de l’actif du bilan consolidé. amortissements au sein du groupe, s’assurer de\nCes immobilisations figurent au bilan à la valeur la plus faible entre la valeur nette l’application homogène des durées d’amortissements\nImpôts et taxes -12.462 -6.844 d L’ ea m gro or uti ps es e pm roe cn èt d e et dla e v ma ale nu ièr rv eé an na nle u. elle à une évaluation de ces actifs immobiliers, p - Pou rir s el ’ de en s ce om nnb ale is sad ne cs e de en sti t éé vs a lud au t iog nr so ru ep tee n. ues par les\npour en dégager la valeur vénale. Cette dernière est ensuite comparée à la valeur évaluateurs immobiliers.\nDotations aux amortissements des immobilisations -30.502 -28.980 nette d’amortissement pour s’assurer de l’absence de moins-value latente. - Procéder à une comparaison entre la valeur nette\nL’estimation de la valeur vénale est effectuée par des évaluateurs immobiliers d’amortissement des actifs immobiliers et de la valeur\nDotations nettes de reprises des provisions et des dépréciations 960 4.258 externes et indépendants vis-à-vis du groupe. vénale telle qu’elle ressort des évaluations immobilières,\nNous avons considéré l’évaluation des actifs comme un point clé de l’audit, au vu de pour s’assurer de l’absence de moins-value latente.\nRésultat d'exploitation 9.777 19.243 l’importance des actifs immobiliers dans le total bilan du groupe.\nProduits de placements financiers nets des charges d'intérêts 198 448 R Lae s dp iro en cts ioa nb i elit sé t s r ed se p ola n d sair be lc et i do en le at pd re és p are ras tp ioo nn s ea t b dl ee s la d pe r l éa s eg no tu av tioe nrn fa idn èc le e à d el’ sé g éa tard ts d de es sé yta nt ts h èd se e s cy on nt sh oè lis de é sc o cn os no foli rd mé és ment au référentiel\ncomptable en vigueur au Maroc, ainsi que du contrôle interne qu’elle considère comme nécessaire pour permettre la préparation d’états de\nAutres produits et charges financières -424 933 synthèse consolidés exempts d’anomalies significatives, que celles-ci résultent de fraudes ou d’erreurs.\nLors de la préparation des états de synthèse consolidés, c’est à la direction qu’il incombe d’évaluer la capacité du groupe à poursuivre son\nRésultat financier -226 1.382 exploitation, de communiquer, le cas échéant, les questions se rapportant à la continuité de l’exploitation et d’appliquer le principe comptable\nde continuité d’exploitation, sauf si la direction a l’intention de liquider le groupe ou de cesser son activité ou si aucune autre solution réaliste\nRésultat courant des sociétés intégrées 9.551 20.625 n Il e in s c’ oo mffr be e à a e ul xle r. esponsables de la gouvernance de surveiller le processus d’information financière du groupe.\nCharges et produits exceptionnels 1.132 -233 Responsabilités de l’auditeur à l’égard de l’audit des états synthèse consolidés\nNos objectifs sont d’obtenir l’assurance raisonnable que les états de synthèse consolidés pris dans leur ensemble sont exempts d’anomalies\nImpôt sur les bénéfices -3.199 -3.565 s raig isn oif nic na at biv le es c, oq ru ree s pc oe nlle ds à-c i u r né s nu ivlt ee an ut d ée le vfr éa u dd ’ae ss s uo ru a nd c’e er ,r e qu ur i s n e et gd ae r ad né til ti v tr oe ur t eu fn o isra pp ap so r qt ud ’ue n l ’a au ud di it te ru ér a c liso én te con na fn ot r mno ét mre e no tp i an uio xn n. oL r’a ms es su r da en c le a\nprofession au Maroc permettra toujours de détecter toute anomalie significative qui pourrait exister. Les anomalies peuvent résulter de fraudes\nImpôts différés -1.895 -4.415 ou d’erreurs et elles sont considérées comme significatives lorsqu’il est raisonnable de s’attendre à ce que, individuellement ou collectivement,\nelles puissent influer sur les décisions économiques que les utilisateurs des états de synthèse consolidés prennent en se fondant sur ceux-ci.\nRésultat net des entreprises intégrées 5.589 12.412 Dans le cadre d’un audit réalisé conformément aux normes de la profession au Maroc, nous exerçons notre jugement professionnel et faisons\npreuve d’esprit critique tout au long de cet audit. En outre :\n▪ nous identifions et évaluons les risques que les états de synthèse consolidés comportent des anomalies significatives, que celles-ci\nQuote-part de résultat des sociétés mises en équivalence - - résultent de fraudes ou d’erreurs, concevons et mettons en œuvre des procédures d’audit en réponse à ces risques, et réunissons des\néléments probants suffisants et appropriés pour fonder notre opinion. Le risque de non-détection d’une anomalie significative résultant d’une\nDotations aux amortissements des écarts d'acquisition -4.001 -4.001 fraude est plus élevé que celui d’une anomalie significative résultant d’une erreur, car la fraude peut impliquer la collusion, la falsification, les\nomissions volontaires, les fausses déclarations ou le contournement du contrôle interne ;\nRésultat net de l'ensemble consolidé 1.589 8.411 • a pn po ru os p ra iéc eq su é ar uo xn s c iu rcn oe n sc to am ncp eré sh , e en t s ni oo nn dd ae ns sé ll eé m be un t t ds ’ ed xu p rc imon et rr ô ule n ein ote pr in ne io np e sr uti rn e l’en ft fs ic ap co iu tér l d’a uu cd oit na trf ôin le d ie n tc eo rnn ec e dv uo i gr rd oe us p ep r ;océdures d’audit\n• nous apprécions le caractère approprié des méthodes comptables retenues et le caractère raisonnable des estimations comptables faites\nIntérêts minoritaires - - par la direction, de même que des informations y afférentes fournies par cette dernière ;\n• nous tirons une conclusion quant au caractère approprié de l’utilisation par la direction du principe comptable de continuité d’exploitation\nRésultat net (part du groupe) 1.589 8.411 e sut, s s ce el po tn ib ll ee ss dé elé m jee ten rt s u np r do ob ua tn et s im o pb ote rtn au ns t , sq uu r a lan t cà a pl’ ae cx ii ts ét e dn uc e g ro ou u pn eo n à d p’ ou un re s uin ivc re er t sit ou nd e e xs pig lon ii tf aic tia ot niv . e S l ii é ne o uà s d ce os n cé lv ué on ne sm àe ln ’ets x iso tu e ns cit eu a dt ’i uo nn es\nincertitude significative, nous sommes tenus d’attirer l’attention des lecteurs de notre rapport sur les informations fournies dans les états\nde synthèse au sujet de cette incertitude ou, si ces informations ne sont pas adéquates, d’exprimer une opinion modifiée. Nos conclusions\ns’appuient sur les éléments probants obtenus jusqu’à la date de notre rapport. Des événements ou situations futurs pourraient par ailleurs\namener le groupe à cesser son exploitation ;\n• nous évaluons la présentation d’ensemble, la structure et le contenu des états de synthèse consolidés, y compris les informations fournies\ndans les notes, et apprécions si les états de synthèse consolidés représentent les opérations et événements sous-jacents d’une manière\nPÉRIMÈTRE propre à donner une image fidèle.\n• nous obtenons des éléments probants suffisants et appropriés concernant les informations financières des entités et activités du groupe\npour exprimer une opinion sur les états de synthèse consolidés. Nous sommes responsables de la direction, de la supervision et de la\nClôture Ouverture réalisation de l’audit du groupe. Nous assumons l’entière responsabilité de l’opinion d’audit.\nNous communiquons aux responsables de la gouvernance notamment l’étendue et le calendrier prévus des travaux d’audit et nos constatations\nACTIF Taux d'intérêt Taux de contrôle Mé ct oh no sd oe . de Taux d'intérêt Taux de contrôle Mé ct oh no sd oe . de i Cm ap so ar bta lan nte cs a, ,y l ec o 2m 6p fr éis v rt io eu rt e 2 0d 2é 4ficience importante du contrôle interne que nous aurions relevée au cours de notre audit.\nLes Commissaires aux Comptes\nImmorente Invest SA 100,00 % 100,00 % IG 100,00 % 100,00 % IG\nIMR FREE ZONE I 100,00 % 100,00 % IG 100,00 % 100,00 % IG\nAmlak Atrium 100,00 % 100,00 % IG 100,00 % 100,00 % IG\nAmlak Contempo 100,00 % 100,00 % IG 100,00 % 100,00 % IG\nIG signifie Intégration Globale\nCOMPTES SOCIAUX\nAU 31 DÉCEMBRE 2023\nBILAN (ACTIF) (En DH) COMPTE DE PRODUITS ET CHARGES (En DH)\nACTIF BrutAU Am 3 o e1 r t/ t Pi1 s rs2 oe v/ m i2 se i0 on2 nts s3 Net AU 31/12/20 N2 e2 t P l’ero xp e 1r re cis c eà leC pso r én e cc x ée e 2dr r en c na icn te st s LT ’O E 3T X =A E 1U R +X C I 2D CE E PLT R’O E ET X CA E E 4U R DX C E ID C NE E T\nIMMOBILISATIONS EN NON VALEURS (a) 37.549.410,42 30.508.463,93 7.040.946,49 14.550.828,58 I - PRODUITS D’EXPLOITATION 43.961.577,93 43.961.577,93 40.640.496,78\nFrais préliminaires 10.559.261,12 8.511.856,90 2.047.404,22 4.159.256,45 Ventes de marchandises\nCharges à repartir sur plusieurs exercices 26.990.149,30 21.996.607,03 4.993.542,27 10.391.572,13 Ventes de biens et services produits 42.690.912,73 42.690.912,73 40.047.376,78\nPrimes de remboursement des obligations Chiffres d’Affaires 42.690.912,73 42.690.912,73 40.047.376,78\nIMMOBILISATIONS INCORPORELLES (b) E Variation de stock de produits (1)\nAImmobilisations en recherche et développement X Immobilisations produites pour l'Ese p/elle-même\nCBrevets, marques, droits et valeurs similaires P Subvention d'exploitation\nT Fonds commercial L Autres produits d'exploitation\nI Autres immobilisations incorporelles O Reprises d'exploitation; transfert de charges 1.270.665,20 1.270.665,20 593.120,00\nF IMMOBILISATIONS CORPORELLES (c) 363.027.458,93 56.519.338,83 306.508.120,10 320.343.364,66 I TOTAL I 43.961.577,93 43.961.577,93 40.640.496,78\nTerrains 64.151.122,86 64.151.122,86 64.151.122,86 T II- CHARGES D'EXPLOITATION 38.996.289,66 3.985,73 39.000.275,39 39.518.486,72\nConstructions 298.876.336,07 56.519.338,83 242.356.997,24 256.192.241,80 A Achats revendus de marchandises (2)\nI Installations techniques, matériel et outillage T Achat consommés de matières et de fournitures (2) 60,00 60,00 5.945,21\nM Matériel de transport I Autres charges externes 14.088.372,35 3.985,73 14.092.358,08 12.714.513,78\nM BOM Auo tb ri eli se ir ms,\nm\nm oa bt ié lir sie al\nt\nid oe\nn\nsb u core rpa ou\nr\ne et\nl\nla em sénagements divers NO I Cm hp aô rgts\ne\nse t\nd\nt ea x pe es\nrsonnel\n2.964.233,84 2.964.233,84 2.943.055,52\nI Immobilisations corporelles en cours Autres charges d'exploitation 300.000,00 300.000,00 300.000,00\nL IMMOBILISATIONS FINANCIERES (d) 519.808.140,82 519.808.140,82 392.744.497,29 Dotations d'exploitation 21.643.623,47 21.643.623,47 23.554.972,21\nI Prêts immobilisés TOTAL II 38.996.289,66 3.985,73 39.000.275,39 39.518.486,72\nSAutres créances financières 20.899.016,00 20.899.016,00 20.784.523,66 III- RESULTAT D'EXPLOITATION ( I - II ) 4.965.288,27 -3.985,73 4.961.302,54 1.122.010,06\nETitres de participation 498.909.124,82 498.909.124,82 371.959.973,63 IV- PRODUITS FINANCIERS 1.545.000,90 1.545.000,90 1.906.063,21\nAutres titres immobilises Produits des titres de participation et autres titres\nimmobilisés\nECARTS DE CONVERSION - ACTIF (e)\nDiminution des créances immobilisées F Gains de change\nAugmentation des dettes financières I Intérêts et autres produits financiers 1.545.000,90 1.545.000,90 1.906.063,21\nTOTAL I ( a+b+c+d+e) 920.385.010,17 87.027.802,76 833.357.207,41 727.638.690,53 N Reprises financières; transfert de charges\nSTOCKS (f) A TOTAL IV 1.545.000,90 1.545.000,90 1.906.063,21\nN V- CHARGES FINANCIERES 1.195.938,03 1.195.938,03 1.231,11\nMarchandises\nC Charges d'intérêts 1.125.406,37 1.125.406,37 1.231,11\nAMatières et fournitures consommables\nI Pertes de changes\nCProduits en cours\nT\nI\nP Pr ro od du ui it ts\ns\ni fn int ie srm. et produits résiduels RE A Du ot tr ae tis\no\nnch\ns\na fir ng ae ns\nc\nf ii èn ra en scières 70.531,66 70.531,66\nF CREANCES DE L'ACTIF CIRCULANT (g) 18.869.712,85 18.869.712,85 35.505.925,81 TOTAL V 1.195.938,03 1.195.938,03 1.231,11\nVI- RESULTAT FINANCIER ( IV - V ) 349.062,87 349.062,87 1.904.832,10\nFournis. débiteurs, avances et acomptes 1.200,00 1.200,00 1.200,00\nCClients et comptes rattachés 6.682.191,87 6.682.191,87 13.548.771,54 VII- RESULTAT COURANT ( III - VI) 5.314.351,14 -3.985,73 5.310.365,41 3.026.842,16\nI Personnel VIII- PRODUITS NON COURANTS 199.628,54 199.628,54 5.410,05\nR Etat 11.602.103,02 11.602.103,02 19.113.039,15 Produits de cessions d'immobilisations\nC Comptes d'associés Subventions d'équilibre\nNU AL A C TIu o Tmt Rre p Es t Se d Edé Teb i Vrte é Au g Lr u Es l Uar Ris Da Etio Pn\nL\na Ac Cti Ef\nMENT (h)\n4.04 1 61 6 26 7 .. . 25 6 89 2 11 6 ,, , 76 3 31 5 4.04 1 61 6 26 7 .. . 25 6 89 2 11 6 ,, , 76 3 31 5 182 .. 16 1 38 5 38 4 .. . 33 6 51 0 94 0 ,, , 19 1 83 9 N NO R A Ru ee t pp r rr e ii sss\ne\ne p ss r o ns d ou u nr i t cs s ou unb rov ane\nn\nn c to eti u so rn ;a ts n\nr\nad ts n'i sn fv ee rs tst i ds es e cm hae rn\ng\nTt\ne Os\nTAL VIII\n11 99 99 .. 66 22 88 ,, 55 44 11 99 99 .. 66 22 88 ,, 55 44 55 .. 44 11 00 ,, 00 55\nT\nECART DE CONVERSION - ACTIF (i) C IX- CHARGES NON COURANTES 65.144,46 65.144,46 436.394,30\n(Eléments circulants) O Valeurs nettes d'amort. des Immo cédées\nTOTAL II (f+g+h+i) 22.931.994,58 22.931.994,58 53.639.284,99 U Subventions accordées\nT TRESORERIE - ACTIF 680.820,59 680.820,59 765.468,16 R Autres charges non courantes 60.237,46 60.237,46 436.394,30\nR EChèques et valeurs à encaisser 739.065,60 A Dotations non courantes aux amortiss. et provision 4.907,00 4.907,00\nSBanques, T.G & CP 676.296,59 676.296,59 26.232,56 N TOTAL IX 65.144,46 65.144,46 436.394,30\nRO . Caisses, régies d'avances et accréditifs 4.524,00 4.524,00 170,00 T X- RESULTAT NON COURANT ( VIII- IV ) 134.484,08 134.484,08 -430.984,25\nTOTAL III 680.820,59 680.820,59 765.468,16 XI- RESULTAT AVANT IMPOTS ( VII+ ou - X)) 5.448.835,22 -3.985,73 5.444.849,49 2.595.857,91\nTOTAL GENERAL I+II+III 943.997.825,34 87.027.802,76 856.970.022,58 782.043.443,68 XII- IMPOTS SUR LES RESULTATS 1.018.402,00 1.018.402,00 1.201.164,00\nXIII- RESULTAT NET ( XI - XII ) 4.430.433,22 -3.985,73 4.426.447,49 1.394.693,91\nBILAN (PASSIF) (En DH)\nXIV- TOTAL DES PRODUITS ( I + IV + VIII ) 45.706.207,37 45.706.207,37 42.551.970,04\nXV- TOTAL DES CHARGES ( II + V + IX + XII ) 41.275.774,15 3.985,73 41.279.759,88 41.157.276,13\nPASSIF AU 31/12/2023 AU 31/12/2022 XVI- RESULTAT NET (Total Produits - Total Charges) 4.430.433,22 -3.985,73 4.426.447,49 1.394.693,91\nCAPITAUX PROPRES 722.516.792,15 763.125.344,66 (1) Variation de Stocks: Stock Final - Stock Initial (Augmentation (+) ; Diminution (-)\n(2) Achats Revendus ou Consommés: Achats - Variation de Stocks\n* Capital Social ou Personnel (1) 563.297.780,00 563.297.780,00\n* Moins : actionnaires, capital Souscrit non appelé ETAT DES SOLDES INTERMEDIAIRES DE GESTION (E.S.G) (En DH)\nCapital appelé 563.297.780,00 563.297.780,00\nDont versé 563.297.780,00 563.297.780,00 31/12/2023 31/12/2022\n* Primes d'Emission, de Fusion, d'Apport 123.654.128,34 159.682.128,34 1 Ventes de marchandises (en l'état)\nCA * Ecarts de Réévaluation 24.993.336,70 24.993.336,70\nI =\nA Mc Ah Ra Gts\nE\nr Se v Be Rn Ud Tu Es Sd e\nS\nUm Ra r Vc Eh Na Tn Edi Ss e Es\nN L'ETAT\nT * Réserve Légale 2.506.274,98 2.436.540,28 II + PRODUCTION DE L'EXERCICE (3+4+5) 42.690.912,73 40.047.376,78\nI * Autres Réserves\n3 = Ventes de biens et services produits 42.690.912,73 40.047.376,78\nF * Report à Nouveau (2) 3.638.824,64 11.320.865,43\n4 + Variation de stocks de produits\n* Résultats Nets en Instance d'Affectation (2)\n5 Immobilisations produites par lEse pour elle-même\nMI * Résultat net de l’exercice (2) TOTAUX DES CAPITAUX PROPRES (A) 7224 .. 54 12 66 .. 74 94 27 ,, 14 59 7631 .. 13 29 54 .. 36 49 43 ,, 69 61 III 6 - AC cO hN aS tsO M coM nsA oT mIO mN é D sE d eL ' mEX aE tiR èrC eI sC E et ( 6 fo+ u7 r) nitures 14.092.4 618 0, ,0 08 0 12.72 50 .. 94 458 5, ,9 29 1\nMCAPITAUX PROPRES ASSIMILES (b) 7 Autres charges externes 14.092.358,08 12.714.513,78\nO* Subventions d'Investissement IV = VALEUR AJOUTEE (I+II+III) 28.598.494,65 27.326.917,79\nB* Provisions Réglementées 8 + Subventions d'exploitation\nI DETTES DE FINANCEMENT (c) 125.072.056,99 5.072.056,99 V 9 - Impôts et taxes 2.964.233,84 2.943.055,52\nL * Emprunts Obligataires 10 - Charges de personnel\nI * Autres Dettes de Financement 125.072.056,99 5.072.056,99 = EXCEDENT BRUT D'EXPLOITATION (E.B.E) OU INSUFFISANCE BRUT 25.634.260,81 24.383.862,27\nS D'EXPLOITATION (I.B.E)\nPROVISIONS DURABLES POUR RISQUES ET CHARGES (d)\nE 11 + Autres produits d'exploitation\n* Provisions pour Risques\n12 - Autres charges d'exploitation 300.000,00 300.000,00\n* Provisions pour Charges 13 + Reprises d'exploitation : transfert de charges 1.270.665,20 593.120,00\nECARTS DE CONVERSION - PASSIF (e) 14 - Dotations d'exploitation 21.643.623,47 23.554.972,21\n* Augmentation des Créances Immobilisées VI = RESULTAT D'EXPLOITATION (+ ou -) 4.961.302,54 1.122.010,06\n* Diminution des Dettes de Financement VII RESULTAT FINANCIER 349.062,87 1.904.832,10\nTOTAL I ( a+b+c+d+e ) 847.588.849,14 768.197.401,65 VIII = RESULTAT COURANT (+ ou -) 5.310.365,41 3.026.842,16\nADETTES DU PASSIF CIRCULANT (f) 9.376.266,44 9.967.572,61 IX RESULTAT NON COURANT (+ ou -) 134.484,08 -430.984,25\nC* Fournisseurs et Comptes Rattachés 6.578.336,00 5.662.774,60 15 - Impôts sur les résultats 1.018.402,00 1.201.164,00\nT * Clients Créditeurs, Avances et Acomptes X = RESULTAT NET DE L'EXERCICE ( + ou - ) 4.426.447,49 1.394.693,91\nI\nF* Personnel\nCAPACITE D’AUTOFINANCEMENT (C.A.F) - AUTOFINANCEMENT\n* Organismes Sociaux\nC I * Etat 2.437.952,66 4.094.598,01 1 Résultat de l'Exercice 4.426.447,49 1.394.693,91\nR* Comptes d'Associés Bénéfice 4.426.447,49 1.394.693,91\nC* Autres Créanciers 210.200,00 210.200,00 Perte\nU* Comptes de Régularisation - Passif 149.777,78 2 + Dotations d'Exploitation (1) 21.643.623,47 22.622.053,83\nL\nAAUTRES PROVISIONS POUR RISQUES ET CHARGES (g) 4.907,00 932.918,38 3 + Dotations financières (1)\nNECARTS DE CONVERSION - PASSIF (h) (Elements circulants) 4 + Dotations non courantes (1)\nT TOTAL II ( f+g+h ) 9.381.173,44 10.900.490,99 5 - Reprises d'exploitation (2) 293.996,82 240.780,00\nT TRESORERIE PASSIF 2.945.551,04 6 - Reprises financières (2 )\nRCrédits d'escompte 7 - Reprises non courantes (2) (3)\nE 8 - Produits de cession d'immobilisations\nSCrédit de trésorerie\nO 9 + Valeurs nettes d'amortissement des imm. cédées\nR.Banques (soldes créditeurs ) 2.945.551,04\nI CAPACITE D'AUTOFINANCEMENT (C.A.F) 25.776.074,14 23.775.967,74\nTOTAL III 2.945.551,04 10 - Distributions de bénéfices 45.035.000,00 49.538.500,00\nTOTAL I+II+III 856.970.022,58 782.043.443,68 II AUTOFINANCEMENT -19.258.925,86-25.762.532,26\n(1) Capital Personnel Débiteur (1) à l’exclusion des dotations relatives aux actifs et passifs circulants et à la trésorerie\n(2) Bénéficiaire (+), Déficitaire (-) (2) à l’exclusion des reprises relatives aux actifs circulants et à la trésorerie\n(3) y compris les reprises sur les subventions d’investissement\nCOMPTES SOCIAUX\nAU 31 DÉCEMBRE 2023\nTABLEAU DE FINANCEMENT AU 31/12/2023 (En DH) ETAT DES DEROGATIONS\nI. SYNTHESE DES MASSES DU BILAN VARIATION A-B IN DED RIC OA GT AIO TIN O NDE SS JUSTIFICATION DES DEROGATIONS PIN ATF RL IU ME ON IC N EE E T , D LLE EAS S S D RITE EUR SAO UTG LI TA O AT N TI O F SN INS A S NU CR IE L RE E\nMASSES EXERCICE EXERCICE Emplois Ressources Conformément aux dispositions de l'article 328\nN N-1 C D de la loi 17-95 sur la SA telle que modifiée et\ncomplétée, les frais d'augmentation de capital\n1 Financement Permanent 847.588.849,14 768.197.401,65 79.391.447,49 réalisées au cours des exercices antérieurs ont\n2 Moins actif immobilisé 833.357.207,41 727.638.690,53 105.718.516,88 été imputés sur la prime d'émission.\n3 = Fonds de Roulement Fonctionnel (1-2) (A) 14.231.641,73 40.558.711,12 26.327.069,39 Aussi, les frais engagés dans le cadre de l’opération\n4 Actif circulant 22.931.994,58 53.639.284,99 30.707.290,41 d’introduction en bourse ont été imputés sur\nI- Dérogations aux le montant de la prime d’émission afférente à\n5 Moins passif circulant 9.381.173,44 10.900.490,99 1.519.317,55 principes comptables cette opération tel que décidé par l’assemblée\n6 = Besoin de Financement global (4-5) (B) 13.550.821,14 42.738.794,00 29.187.972,86 fondamentaux générale extraordinaire du 11 mai 2018.\nCes frais totalisent KMAD 13.230 au 31\n7 TRESORERIE NETTE (Actif-Passif) = A-B 680.820,59 -2.180.082,88 2.860.903,47 décembre 2018 et se composent de :\n- Frais de communication pour KMAD 2.332 ;\nII EMPLOIS ET RESSOURCES - Honoraires et débours des commissaires aux\ncomptes, conseil et assistance juridique et fiscale\nd’experts comptables et avocats pour KMAD 3.822 ;\nEXERCICE EXERCICE PRECEDENT - Commissions relatives à la\nI RESSOURCES STABLES DE L’EXERCICE (FLUX) EMPLOIS RESSOURCES EMPLOIS RESSOURCES soucription pour KMAD 7.050 ;\n- Frais de débours liés à l’opération pour KMAD 25.\n* AUTOFINANCEMENT (A) -19.258.925,86 -25.762.532,26\nRéévaluation de la valeur d’acquisition des Ecart de réévaluation de KMAD 24.993\n+ Capacité d'autofinancement 25.776.074,14 23.775.967,74 constructions portant les titres fonciers N° constatés à l’actif en Immobilisations\n- Distributions de bénéfices 45.035.000,00 49.538.500,00 TF 5677/50, TF 100426/C, TF 115270/01 et TF corporelles et au passif en Ecarts de\n115269/01. réévaluation.\n* CESSIONS ET REDUCTIONS D'IMMOBILISATIONS (B) 28.779.807,66 Dotations aux amortissements\n+ Cessions d'immobilisations incorporelles complémetaires résultant de la réévaluation\nde KMAD 69 pour l’exercice 2023.\n+ Cessions d'immobilisations corporelles\n++ RC ée cs us pio én rs a td io' nim s m suo rb ci rli és aa nti co en ss i mfin ma on bc ii lè isr ée es s 28.779.807,66 I a dI u ’- é xD v m aé lr uéo t ag h ta io ot di no en ss B c 2o 0a n 2is 0ss t .re u d ce ti ola n sd u dr eé 4e 0 d à’a 2m 5o ar nti ss s àe pm ae rtn irt d de es j anvier 2 -H . H2a 2 au 0 us . ss 5 se 6 e 1d , de 3 es 5 s d d ao e mt ca o ot mi ro tn p iss o s sa eéu mex e ca nom tm so m rr ét ei ss uss lue taim t n :e t n dt es l: a\n* AUGMENTATION DES CAPITAUX PROPRES ET réévaluation : 248.358,64\nASSIMILES (C) - Hausse des amortissements suite à\nla baisse de durée d’amortissement :\n+ Augmentation du capital, apports 1.972.202,71\n+ Subventions d'investissement Soit :\n- Impact sur le résultat de l’exercice : -\nAUGMENTATION DES DETTES DE FINANCEMENT (D) 120.000.000,00 519.105,60 2.220.561,35\n(nettes de primes de remboursement) - Impact sur l’actif net : - 2.220.561,35\nTOTAL RESSOURCES STABLES (A+B+C+D)\nIII- Dérogations\naux règles\nII EMPLOIS STABLES DE L’EXERCICE (FLUX) d'établissement et Néant Néant\nde présentation des\nACQUISITIONS ET AUGMENTATIONS D’IMMOBILISA- 155.847.951,19 16.710,00 états de syntèse\nTIONS (E)\n+ Acquisitions d'immobilisations incorpor.\n+ Acquisitions d'immobilisation corporelles 4.500,00 16.510,00\n+ Acquisitions d'immobilisation financières 155.843.451,19 200,00 ETAT DES CHANGEMENTS DE METHODES\n+ Augmentation des créances immob.\nNATURE DES JUSTIFICATION DES INFLUENCE SUR LE PATRIMOINE, LA SITUATION FINANCIERE ET\n* REMBOURSEMENT DES CAPITAUX PROPRES (F) CHANGEMENTS CHANGEMENTS LES RESULTATS\n* REMBOURSEMENTS DES DETTES DE FINANCE-\nMENT (G) Hausse des dotations aux amortissements : 2.220.561,35 decomposée\n* GI II LE I T I OM .O BVP T A AL A R LO L II\n(\nAS -\nB\nT E .E FIM ON .GNP N\n)\nL DO O UN IS BV S EA T SL A OE B IU NLR E DS S E ( (H FE) I+ NF A+ NG C+ EH M) ENT 155.847.951,19 29.187.972,86 3 35 62 9. .3 04 50 0, ,0 000 22.515.110,78 I a m d f- ’éf é C e vtc hh at oa la udn n aeg t tse il o m e nse nts B d c a 2o 0n’a a n 2si ms 0s às to re pr u atd ci rse t tis iol rea n m d sd e eu d jnr e aé t n 4e d v0 e i es à r 25 c - - d S\n-\no ’ oH H Ia mm ima a t pu um :o as s re cs s t te e is s\ns\nu d d s ui ee et\nr\nms s :\nl\nea a e m m n réto o s:r r u1t ti i l.s s t9 as s 7 te e 2 m m d.2 ee e 0 ln n 2 ’et t ,s s 7\nx\n1 er s ré u cs i itu cel\ne\nt à a\n:\nn l -at\n2\nbd .a 2e i\n2\nsl 0a s\n.\ne 5r é 6dé 1ev\n,\n3a d 5l uu ra ét eio n : 248.358,64\n- Impact sur l’actif net : - 2.220.561,35\nIV. VARIATION DE LA TRESORERIE 2.860.903,47 3.097.365,88 II - Changements\naffectant les règles Néant Néant\nTOTAL GENERAL 158.708.854,66 158.708.854,66 369.050,00 369.050,00 de présentation\nTABLEAU DES AMORTISSEMENTS\nNATURE Cumul début exercice 1 Dotation de l’exercice 2 Amortissements sur immobilis- sortie 3s Cumul d’amortissement fin 4 e =x e 1r +c 2ic -e 3\nIMMOBILISATION EN NON-VALEURS 27.462.192,19 7.509.882,09 4.463.610,35 30.508.463,93\n* Frais préliminaires 6.400.004,67 2.111.852,23 8.511.856,90\n* Charges à répartir sur plusieurs exercices 21.062.187,52 5.398.029,86 4.463.610,35 21.996.607,03\n* Primes de remboursement des obligations\nIMMOBILISATIONS INCORPORELLES\n* Immobilisation en recherche et développement\n* Brevets, marques droits et valeurs similaires\n* Fonds commercial\n* Autres immobilisations incorporelles\nIMMOBILISATIONS CORPORELLES 42.679.594,27 13.839.744,56 56.519.338,83\n* Terrains\n* Constructions 42.679.594,27 13.839.744,56 56.519.338,83\n* Installations techniques; matériel et outillage\n* Matériel de transport\n* Mobilier, matériel de bureau et aménagements\n* Autres immobilisations corporelles\n* Immobilisations corporelles en cours\nTOTAL GENERAL 70.141.786,46 21.349.626,65 4.463.610,35 87.027.802,76\nTABLEAU DES TITRES DE PARTICIPATION\nR dea i ls ao sn o s co iéc tia él ée mettrice N° IF dS ’ae cc 1tt ie vu itr é C sa op c 2i it aa ll Part eic n 3i p %ation Prix d g’a loc 4q bu alisition compV ta al b 5e lu er nette Date de 6 c E lôx tt ura reit des de Sr in tuie ar ts io 7é nt a nt es t td ee synthèse de la so Rc éié st ué l 8 té am t ne ett trice au P Cr .o Pd .Cu i dts e 9 i ln ’es xc eri rt cs i ce\nIMR FREE ZONE 24917016 IMMOBILIER 234.876.379,99 100,00 234.876.559,10 234.876.559,10 31/12/2022 126.067.739,15 -150.320,49\nAMLAK ATRIUM 40222202 IMMOBILIER 66.000.000,00 100,00 105.302.840,57 105.302.840,57 31/12/2022 69.704.220,29 4.043.424,14\nAMLAK CONTEMPO 40241136 IMMOBILIER 66.000.000,00 100,00 108.729.725,15 108.729.725,15 31/12/2022 77.752.310,10 3.295.631,45\nSPI SYHATI IMMO 0 IMMOBILIER 00,00 0,00 50.000.000,00 50.000.000,00 31/12/2022 0,00 0,00\nTOTAL 366.876.379,99 498.909.124,82 498.909.124,82 273.524.269,54 7.188.735,10\nTABLEAU DES PROVISIONS\nNATURE Monta en xt ed ré cb icu et D'exploitation DOT FA iT nI aO nN cS ières Non courantes D'exploitation FR iE nP anR cIS ièE rS es Non courantes Mon et xa en rt c if cin e\n1. Provisions pour dépréciation de l’actif immobilisé\n2. Provisions réglementées\n3. Provisions durables pour risques et charges\nSOUS TOTAL (A)\n4. Provisions pour dépréciation de l’actif circulant (hors trésorerie)\n5. Autres Provisions pour risques et charge 932.918,38 4.907,00 932.918,38 4.907,00\n6. Provisions pour dépréciation des comptes de trésorerie\nSOUS TOTAL (B) 932.918,38 4.907,00 932.918,38 4.907,00\nTOTAL (A+B) 932.918,38 4.907,00 932.918,38 4.907,00\nCOMPTES SOCIAUX\nAU 31 DÉCEMBRE 2023\nTABLEAU DES CREANCES TABLEAU DES DETTES\nANALYSE PAR ECHEANCE AUTRES ANALYSES ANALYSE PAR ECHEANCE AUTRES ANALYSES\nCREANCES TOTAL Plus d'1 an Moins d'1 an reE ce oc th u nu vo re n és e s Mo dn et va in st es s en os rM u g pro a u ln n' bét i la st ia cn m stt s ee st enM s tr luo ie én r p et l ra e sin s st e s re pM p ao r rén est fa e fn ent tts sé s DETTES TOTAL Plus d'1 an Moins d'1 an reE ce oc th u nu vo re n és e s M do en vet in sa en sts os rM u g pro a u ln n' bét i la st ia cn m stt s ee st enM s tr luo ie én r p et l ra e sin s st e s re pM p ao r rén est fa e fn ent tts sé s\nDE L'ACTIF 20.899.016,00 0,0020.899.016,00 0,00 20.899.016,00 0,00 20.899.016,00 0,00 DE FINANCEMENT 125.072.056,995.072.056,99 120.000.000,00 0,00 0,00 0,00 0,00 0,00\nIMMOBILISE\nEmprunts\nPrêts obligataires\nimmobilisés Autres dettes de 125.072.056,99 5.072.056,99 120.000.000,00\nAutres 20.899.016,00 20.899.016,00 20.899.016,00 20.899.016,00 financement\ncréances\nfinancières DU PASSIF 9.376.266,441.803.223,85 7.384.042,59 0,00 0,00 2.437.952,66 6.131.745,33 0,00\nCIRCULANT\nD CIE R L C' UA LC AT NIF T 18.869.712,854.133.567,0914.736.145,76 0,00 0,0011.602.103,02 5.156.096,04 0,00 Fournisseurs, 6.578.336,00 6.578.336,00 6.131.500,00\net acomptes\nFournisseurs 1.200,00 1.200,00 rattachés\nd avé ab nit ce eu sr s e t Clients créditeurs\nacomptes Personnel\nClients et 6.682.191,87 6.682.191,87 4.739.504,43 Organismes\ncomptes sociaux\nrattachés Etat 2.437.952,66 1.803.023,85 634.928,81 2.437.952,66 45,33\nPersonnel Comptes\nEtat 11.602.103,02 4.118.567,09 7.483.535,93 11.602.103,02 d'associés\nComptes Autres créanciers 210.200,00 200,00 21.000,00 200,00\nd’associés Comptes de 149.777,78 149.777,78\nAutres 416.591,61 416.591,61 416.591,61 régularisation-\ndébiteurs passif\nCompte de 167.626,35 13.800,00 153.826,35 Totaux 134.448.323,436.875.280,84 127.384.042,59 0,00 0,00 2.437.952,66 6.131.745,33 0,00\nrégularisation\nactif\nTotaux 39.768.728,854.133.567,0935.635.161,76 0,00 20.899.016,0011.602.103,02 26.055.112,04 0,00 RÉSUMÉ DU RAPPORT GÉNÉRAL DES COMMISSAIRES\nAUX COMPTES SUR LES COMPTES SOCIAUX\nTABLEAU DES SURETES REELLES DONNEES OU RECUES\nT oi ue r ts ie c rr sé dd éit be iu ter us rs paM rc o lo aun v st ea ûrn rt et té Na ( t 1u )re d D ’ina ste c re it p l ti ie ou n (2 O ) b j e (3t ) à V la s al û e n dru ae er tt t et éc e o dd dm eoe n cp l n lt a ôa é tb e ul re e 7 C, a B sao bu ll ae nva card Driss Slaoui 4 C, a P sala bc le a nM ca aréchal\nSûretés données Aux actionnaires de la société\nIMMORENTE INVEST S.A.\nHypothèque de premier rang sur le TF 5/7, Rue Ibnou Toufaïl\nN le° c8 a9 d5 r7 e/ 7 d1 ’u a nu c p rr éo df ii tt àd e lo C nF gG t eB rA mN eK d d ea Mn As D 100.000,00 Hypothèque 2023/09/18 E bam np cr au irn et non définie Casablanca Rapport Général des commissaires aux comptes\n90.000.000. Exercic Ae ud du i t1 der e j sa n év taie tr s a du e 3 s1 y nd té hc èe sm ebre 203\nNantissement de 700000 actions détenues Opinion\np d da e er l\nC\nal F’ e s Gm o c dp i aér nu té sn t A lee M u cr L\na\nAd dKa ren A s dT ’l uRe\nn\nIc U ca M rp éi at da u il\nt\nps dro eoc Mfi ia t Al\nD\n90.000.000,00 Nantissement 2023/09/18 E bam np cr au irn et non définie C d\ne\ncoe to\nm\ncn s hf y po an lér rtm gh meèé essm n,e te\nl\na’c én ii rtt -\na e\njà o\nt (\nil En da t\ne T\nsm\ns I\nCd i ss e )os\n.\nli\nl\nCao\nd\nn\ne\nes\ns\nsoq cu édii teé an t tgéo\nse\nu I dM ss\net\nia M\no s\nné yO\n,\nnt é R\nl te h\nc E èo tN\na\nsn ebTfi lEé\nfe\noe aI\nn\nN up\nt\na V\nrd\ner E\ne\nsv S so\nfi\noT ntr\nr\nae tS\nin r\nA . cA us\ne\nn.s ,\nm\ne mq em u onib\nn\ntc l té po ae om\nn u\ntG p drr é ee l’n\ne\nn cé xn ar ee pa rn il\nc\nte at\ni\ncd l ue eu\nx\nb\nc\np1 i ll\no\nr3 a\nos\nna\np\nv\nà\nra er ui\nc\nsl e2 3 et0 1\nt te\n2 ad 1 sdé,\nsa\ncn\nit\nmeo emu\n, i\nlés ab\ns\nira\nn\ne dv\ns\neo 2\ni\nn q0 Ms u2 Ae3e D,f lf ’le ée 7c\nt\n2actu 2o\nt\né .m\nd 5\nel 1p’a\ns\n6tu e .id\n7n\ndi 9ft e\no\n2d\nr\n,p me 1rs 5o\na\né d\nt\ndiot u oa ni ntt ss\ns t\n90.000.000. un bénéfice net de MAD 4.426.447,49.\nSûretés reçues Nous certifions que les états de synthèse cités au premier paragraphe ci-dessus sont réguliers et sincères et donnent, dans tous leurs\naspects significatifs, une image fidèle du résultat des opérations de l’exercice écoulé ainsi que de la situation financière et du patrimoine de\nla société IMMORENTE INVEST S.A. au 31 décembre 2023 conformément au référentiel comptable en vigueur au Maroc.\nNEANT Fondement de l’opinion\nNous avons effectué notre audit selon les Normes de la Profession au Maroc. Les responsabilités qui nous incombent en vertu de ces\nnormes sont plus amplement décrites dans la section « Responsabilités de l’auditeur à l’égard de l’audit des états de synthèse » du\n(1) Gage : 1- Hypothèque : 2- Nantissement : 3- Warrant : 4- Autres : 5- (à préciser). présent rapport. Nous sommes indépendants de la société conformément aux règles de déontologie qui s’appliquent à l’audit des états\n(2) Préciser si la sûreté est donnée au profit d’entreprises ou de personnes tierces (sûretés données) (entreprises liées, associés, nombre du personnel). de synthèse au Maroc et nous nous sommes acquittés des autres responsabilités déontologiques qui nous incombent selon ces règles.\n(3) Préciser si la sûreté reçue par l’entreprise provient de personnes tierces autres que le débiteur (sûretés reçues). Nous estimons que les éléments probants que nous avons obtenus sont suffisants et appropriés pour fonder notre opinion d’audit.\nQuestions clés de l’audit\nLes questions clés de l’audit sont les questions qui, selon notre jugement professionnel, ont été les plus importantes dans l’audit des états\nENGAGEMENTS FINANCIERS RECUS OU DONNES HORS OPERATIONS DE CREDIT-BAIL de synthèse de la période considérée. Ces questions ont été traitées dans le contexte de notre audit des états de synthèse pris dans leur\nensemble et aux fins de la formation de notre opinion sur ceux-ci, et nous n’exprimons pas une opinion distincte sur ces questions.\nRisque identifié Notre réponse\nENGAGEMENTS DONNES M Exo en rta cin ct es M cio cn et Pa rn éts c éE dx ee nr t- T Ai utr 3e 1s dd ée c p ea mrt bi rc eip 2a 0t 2io 3n , les titres de participation sont inscrits au bilan pour une P lao vu ar lea up rp dré ’uc ti ie lir té l e d ec sa r ta itc retè sr e d er a pis ao rtn icn ipa ab tle io nd ,e s ul’e r s latim ba at sio en d d ee s\n- Avals et cautions Néant Néant v pa ril xe u hr i sb toru rit qe u ee t dn ’ae ctt he a c t.omptable de KMAD 498.909. Ils sont comptabilisés au i on nfo t r cm oa nt sio isn tés q pu rini cn io pu as le mon et n é t t àé :c ommuniquées, nos travaux\n- Engagements en matière de pensions de retraites et obligations similaires Néant Néant La Société procède, à chaque clôture annuelle, à l’évaluation de la valeur Pour les évaluations reposant sur des éléments historiques\nactuelle de ses titres de participation. Cette valeur actuelle est estimée soit - Vérifier que les quotes-parts d’actif net retenues\n- Autres engagements donnés Néant Néant en fonction de l’actif net comptable, soit en fonction de la rentabilité et des concordent avec les comptes des entités et que les\nEngagement envers CFG de ne pas constituer une garantie, sureté un droit réel, une charge ou un p Ee nr s cp ae sc dtiv ee bs a id s’ sa ev e dn uir r abd lu e dtit ere l. a valeur actuelle et si celle-ci est inférieure à la r dé oé cv ua mlu ea nti to an tis o no pé pr ré oe bs a, nle te c as ; échéant, sont fondées sur une\nprivilège quelconque sur les biens donnés en garantie en faveur de la Banque et sur le bien objet Non défini Néant valeur nette comptable, une provision pour dépréciation est constituée. Pour les évaluations reposant sur des éléments prévisionnels\ndu titre foncier n°44835/61 dans le cadre du crédit de MAD 90.000.000. L’estimation de la valeur actuelle des titres requiert l’exercice du jugement de - Prise de connaissance de la méthode d’évaluation, des\nE den sg ta ing ae tm ioe nn dt ae nn sv e ler s c aC dF rG e dd ue cn re é dp ia t s d ea l Mté Are Dr 9la 0 .0va 0l 0e .u 00r 0d .e s garanties ou en changer la nature ou la Non défini Néant l c Da o a nD nci sr e e r cc n et éi o e cn s o .d na ten xs t es ,o nn o c uh so i ax v d oe ns s é elé sm time én ts q uà e c o lan s ci od ré rr ee cr t es e élo vn a ll ue as t ip oa nr t dic eip sa tt ii to ren ss a é - c vt a Pif l rs u o a ci tm ée dum erso r b ii àmlie mr us o nbd eié lit ee cr on s mu s ; p ap ra ar i sl oe ns f eili na tl re es , lr ae te vn au lee u rp a nr el te tes\nE non tg aa mge mm ee nn t,t p e an rv ae vr as l C s F oG u cd ae u n te io p na ss d d aé nl sé lg eu ce ar d o ru e c dé ud ce rr é s de its dr ee v Me Anu Ds 9 e 0t . 0g 0a 0r .a 0n 0t 0ie .s des dettes de tiers, Non défini Néant d ae ct ifp sa r dti ac nip sa lt eio n b ilc ao nn , s dti etu la ’ii mt u pn o rtp ao ni cn et c dlé e d lae pl a’a ru t d dit e, se jn u gr ea miso en n tsd u d ep o laid s D id ree c tc ioe ns c teo llm e p qt ua ’b el le le d re es s sti otr re t s d d ae n sp a ler stic éip va at li uo an ts io, ne st d ime mla o v ba ill ie èu rer sv ,é pn oa ule r\net des incertitudes dans la détermination des hypothèses de flux de trésorerie, s’assurer de l’absence de moins-value latente.\nEngagement envers CFG de ne pas aliéner, transférer, céder ou faire apport à une autre société notamment la probabilité de réalisation des prévisions retenues par la Direction.\net plus particuliérement à un tiers de tout ou partie des biens donnés en garantie en faveur de la Non défini Néant\nbanque et du bien objet du titre n°44853/61 dans le cadre du prétt à long terme de MAD 90.000.000. Responsabilités de la direction et des responsables de la gouvernance à l’égard des états de synthèse\nLa direction est responsable de la préparation et de la présentation fidèle des états de synthèse, conformément au référentiel comptable\nEngagement envers CFG de ne pas contracter des dettes dont les charges cumulées avec celles en vigueur au Maroc, ainsi que du contrôle interne qu’elle considère comme nécessaire pour permettre la préparation d’états de\ndu présent prét risquent d’excéder sa capacité de remboursement dans le cadre du crédit de MAD Non défini Néant synthèse exempts d’anomalies significatives, que celles-ci résultent de fraudes ou d’erreurs.\n90.000.000. Lors de la préparation des états de synthèse, c’est à la direction qu’il incombe d’évaluer la capacité de la société à poursuivre son\nexploitation, de communiquer, le cas échéant, les questions se rapportant à la continuité de l’exploitation et d’appliquer le principe\nEngagement envers CFG de ne pas procéder à toute opération de fusion ou dissolution, ou réduc- comptable de continuité d’exploitation, sauf si la direction a l’intention de liquider la société ou de cesser son activité ou si aucune autre\nt si ao n s id tue a c ta iop nit a jul rq idu ii q n ue e s oe ura fi it n p aa ns c il èé rg ea dle em l’e En mt r pe rq uu ni ts ee u e r t e p t/lu ous g laé n Cé ar ua tl ie om n se an nt sà lt ’o au ct c c oh rdan pn rg ée am labe ln et dd ea n las Non défini Néant s Il o inlu ct oio mn b r eé a al uis xte r en se p os n’o sff ar be l eà s e dll ee . la gouvernance de surveiller le processus d’information financière de la société.\nbanque dans le cadre du crédit de MAD 90.000.000.\nResponsabilités de l’auditeur à l’égard de l’audit des états de synthèse\nEngagement envers CFG de rerspecter l’affectation du crédit et plus généralement tout fait sus- Nos objectifs sont d’obtenir l’assurance raisonnable que les états de synthèse pris dans leur ensemble sont exempts d’anomalies significatives,\nc lae p Ct aib ul te io d n’ ,a off ue c dt ’e ar u s gé mri ee nu ts ee rm see nn st il b’i lm empo er nt ta n lec e v oo lu u mla e v da ele lu er u d rsu ep na gtr ai gm eo min ee n td se t el’ lE qm up er u pn réte vu ur e e dt a/o nu s Non défini Néant q àu ue n c ne ivlle es a- uc i é ré les vu élt e dn ’at s d se u rfr aa nu cd ee , s q uo iu n d e’e gr are rau nrs ti te tt o d ue te d foé il siv r pe ar s u qn u r ’a up np ao urt d d ite r él’a au lisd éit e cu or n c foo rn mte én man et n n t o at ure x o np oi rn mio en s. dL’ ea s las u pr ra on fec se s r ioa nis o an un Mab al re o c co pr ere rmsp eo tn trd a\nl’article 2 du contrat du crédit de MAD 90.000.000. toujours de détecter toute anomalie significative qui pourrait exister. Les anomalies peuvent résulter de fraudes ou d’erreurs et elles sont\nconsidérées comme significatives lorsqu’il est raisonnable de s’attendre à ce que, individuellement ou collectivement, elles puissent influer sur\nDélégation envers CFG BANK de la totalité des dividendes rattachés aux actions nanties qui lui les décisions économiques que les utilisateurs des états de synthèse prennent en se fondant sur ceux-ci.\nserait servis par la société AMALK ATRIUM à hauteur du montant de chacune des échéances de Non défini Néant Dans le cadre d’un audit réalisé conformément aux normes de la profession au Maroc, nous exerçons notre jugement professionnel et\nremboursement du crédit dans le cadre du crédit de MAD 90.000.000. faisons preuve d’esprit critique tout au long de cet audit. En outre :\n• nous identifions et évaluons les risques que les états de synthèse comportent des anomalies significatives, que celles-ci résultent\nE non tg aa mge mm ee nn t,t pe an rv ae vrs a lC s F oG u d cae u n te io p na ss d d aé nl sé g leu ce ar do ru e c dé ud ce rr é s de its dr ee v Men Au Ds 3 e 0t . 0g 0a 0ra .0n 0t 0ir . des dettes de tiers, Non défini Néant d ée lé mfra eu nd tse s p ro ou b ad n’e tsrr e su ur ffs is, ac no tn sc e ev t o an ps p re ot p m riée stt o pn os u re n fo nœ du ev r re n od tre es op pro inc ioé nd .u r Le es rd is’a qu ud ei t de en nré op no -dn és te e cà ti oc ne s d ’r uis nq eu e as n, o e mt ar lé ieu n si is gs no ifn ics a d tive es\nEngagement envers CFG de ne pas aliéner, transférer, céder ou faire apport à une autre société et résultant d’une fraude est plus élevé que celui d’une anomalie significative résultant d’une erreur, car la fraude peut impliquer la\nplus partuculiérement à un tiers de tout ou partie des biens que l’Emprunteur a donné en garantie Non défini Néant collusion, la falsification, les omissions volontaires, les fausses déclarations ou le contournement du contrôle interne ;\nen faveur de la Banque dans le cadre du crédit de MAD 30.000.000. • d ’n ao uu ds it a ac pq pu roé pro rin és e su n ae u xc co im rcp or né sh tae nn cs eio sn , ed te ns oé nlé dm ae nn st s le d bu u tc o dn ’et xrô pl re im in et re r un ne e p oe pr it nin ioe nn t ss u p r o l’u er ff il c’a au cd iti ét a df uin c d oe n trc ôo ln ec ie nv teo ri nr ed e ds e p laro sc oé cd iéu tr ée s ;\nEngagement vers CFG de ne pas contracter des dettes dont les charges éventuelles, cumulées • nous tirons une conclusion quant au caractère approprié de l’utilisation par la direction du principe comptable de continuité\navec celles des emprunts actuels de l’Emprunteur, risquent d’excéder sa capacité de rembouse- Non défini Néant d’exploitation et, selon les éléments probants obtenus, quant à l’existence ou non d’une incertitude significative liée à des\nment dans le cadre du crédit de MAD 30.000.000. événements ou situations susceptibles de jeter un doute important sur la capacité de la société à poursuivre son exploitation. Si\nnous concluons à l’existence d’une incertitude significative, nous sommes tenus d’attirer l’attention des lecteurs de notre rapport\nEngagement envers CFG de ne pas procéder à toute opération de fusion, dissollution, ou réduc- sur les informations fournies dans les états de synthèse au sujet de cette incertitude ou, si ces informations ne sont pas adéquates,\nt ci oo nn t rd ôe l ec a cp oi nta fol rq mu éi mne e nse t r àa li ’t a p rta ics l elé 1g 4a 4le dm e e lan t l or ie 1q 7u -i 9s 5e re et l ap tl iu vs e g aé un x é sr oa cl ie ém tée sn at n à o nto yu mt ec sh da an ng se m lee cn at d d re e Non défini Néant d é’ ve éx np eri mm ee nr tu sn oe u o p sii tn uio an tio m nso d fuifi té ue re. sN o ps o uc ro rn ac ielu ns t io pn as r s a’ ia llep up ru sie an mt s eu nr e le r s la é l sé om cie én téts àp r co eb sa sn ets r so ob nte n eu xps lj ou is taq tu io’à n l ;a date de notre rapport. Des\ndu crédit de MAD 30.000.000. • nous évaluons la présentation d’ensemble, la structure et le contenu des états de synthèse, y compris les informations fournies\ndans l’ETIC, et apprécions si les états de synthèse représentent les opérations et événements sous-jacents d’une manière propre\nEngagement envers CFG de respecter l’affectation du crédit et plus généralement tout fait suscep- à donner une image fidèle.\nt mib ele n td e’ ra sff ee nc ste ibr l es mér eie nu ts le em voe ln ut m l’ eim dp eo sr eta sn ec ne g o au g el ma v ea nl te su tr e d l u qu p ea ptr ri ém vo ui en e d ad ne s l l’ ’E am rtip cr lu en 2t e du ur co ou n td r’ aa tu dg u- Non défini Néant N coo nu ss t ac tao tm iom nsu n imiq pu oo rn tas n a teu sx , yre cs op mon ps ria sb tl oe us t ed e d éla fic g ieo nu cv ee r imna pn oc re ta nn to et a dm u m coe nn tt r ôl’ lé et e inn td eu rne e e qt ul ee nc oa ule sn ad uri re ior np sr é rv eu les v éd ee s a utr a cv oa uu rsx dd e’a nu od ti rt e e at un do its .\nprét de MAD 30.000.000. Vérifications et informations spécifiques\nEngagement envers CFG à domicilier irrévocablement, les flux de la société sur le compte ban- Nous avons procédé également aux vérifications spécifiques prévues par la loi et nous nous sommes assurés notamment de la\ncaire ouvert dans les livres de CFG BANK au prorata des financements bancaires octroyés par la Non défini Néant sincérité et de la concordance, des informations données dans le rapport de gestion du Président du Conseil d’Administration\nbanque dans le cadre du crédit de MAD 30.000.000. destiné aux actionnaires avec les états de synthèse de la société.\nConformément aux dispositions de l’article 172 de la loi n° 17-95 telle que modifiée et complétée, nous portons à votre\nTOTAL (Dont engagements à l’égard d’entreprises liées) connaissance qu’au cours de cet exercice, la Société Immorente Invest a souscrit une participation pour un montant de DH 50\nmillions dans le capital de la SPI « SYHATI IMMO SPI ».\nCasablanca, le 26 février 2024\nENGAGEMENTS RECUS M Exo en rta cin ct es M cio cn et Pa rn éts c éE dx ee nr t- Les Commissaires aux Comptes\n- Avals et cautions Néant Néant\n- Autres engagements donnés\nGarantie Actif Passif donnée à IMMORENTE INVEST par les actionnaires cédant les Non défini Non défini\nfiliales AMLAK ATRIUM et AMLAK CONTEMPO (fiscal et social)\nTOTAL\nAVIS DE CONVOCATION\nSociété Anonyme faisant appel public à l’épargne\nCapital social 563.297.780 dirhams\nSiège social : 5/7, rue Ibnou Toufail, Palmiers, Casablanca\nRegistre du commerce de Casablanca numéro 238.255\nAVIS DE REUNION VALANT AVIS DE CONVOCATION\nA L’ASSEMBLEE GENERALE ORDINAIRE ANNUELLE\nLe 04 avril 2024 à 10h30\nMesdames et Messieurs les actionnaires de la société IMMORENTE INVEST,Société dix (10) jours à compter de la publication du présent avis pour demander l’inscription de\nAnonyme faisant appel public à l’épargne, au capital de 563.297.780 dirhams, immatriculée projets de résolutions à l’ordre du jour de l’Assemblée Générale. La demande d’inscription\nau Registre du Commerce de Casablanca sous le n° 238.255, (ci-après la « Société »), de projets de résolutions à l’ordre du jour doit être déposée ou adressée au siège social\nsont convoqués à l’Assemblée Générale Ordinaire Annuelle qui se tiendra au siège social de la Société contre accusé de réception dans le délai précité.\nde la Société établi au 5/7, rue Ibnou Toufail, Casablanca, Maroc, le 04 avril 2024 à 10 Tous les documents et informations prévus à l’article 121, 121 bis et 141 de la loi n° 17-95\nheures 30 minutes (ci-après « l’Assemblée Générale »). relative aux Sociétés Anonymes telle que modifiée et complétée peuvent être consultés\nCi-après l’ordre du jour de cette Assemblée Générale, les modalités pratiques de sur notre site Internet : www.immorente.ma.\nparticipation à cette Assemblée Générale, et le texte des résolutions qui seront soumises Le présent avis vaut avis de convocation, sous réserve qu’aucune modification ne soit\nà votre approbation. apportée à l’ordre du jour, par suite d’éventuelles demandes d’inscriptions de projets de\nLes actionnaires réunissant les conditions exigées par l’article 117 de la loi n°17-95 résolutions ou de points à l’ordre du jour présentés par les actionnaires de la Société.\nrelative aux Sociétés Anonymes telle que modifiée et complétée disposent d’un délai de LE CONSEIL D’ADMINISTRATION\nORDRE DU JOUR personnellement, par correspondance ou en donnant pouvoir à une personne de son choix\n1. Présentation du rapport du Conseil d’Administration et du rapport général des parmi les personnes énumérées ci-après.\nCommissaires aux Comptes sur les comptes sociaux arrêtés au 31 décembre 2023 et Modalités de vote par pouvoir\napprobation des comptes clos à cette date ; Un actionnaire ne peut se faire représenter que par son conjoint, un ascendant, descendant\n2. Présentation du rapport du Conseil d’Administration et du rapport des Commissaires aux ou par un autre actionnaire justifiant d’un pouvoir. Il peut également se faire représenter par\nComptes sur les comptes consolidés au 31 décembre 2023 et approbation des comptes toute personne morale ayant pour objet social la gestion de portefeuilles de valeurs mobilières.\nconsolidés clos à cette date ; Pour tout pouvoir d’un actionnaire adressé à la Société sans indication de mandataire, la\n3. Affectation du résultat de l’exercice clos le 31 décembre 2023 et distribution de sommes présidente de l’Assemblée Générale émet un vote favorable à l’adoption des projets de\nen numéraire ; résolutions présentés par le Conseil d’Administration et un vote défavorable à l’adoption de\n4. Quitus à conférer aux Administrateurs ; tous les autres projets de résolutions.\n5. Renouvellement des mandats de certains Administrateurs ; Le modèle de pouvoir est mis à la disposition des actionnaires au siège social de la Société.\n6. Rémunération des Administrateurs (fixation des jetons de présence) au titre de l’exercice 2024 ; Il peut également être téléchargé sur le site internet de la Société : www.immorente.ma.\n7. Présentation du rapport spécial des Commissaires aux Comptes sur les conventions Le pouvoir doit être accompagné de l’attestation originale délivrée par l’organisme dépositaire des\nréglementées et approbation desdites conventions ; actions et, (i) soit envoyée par courrier recommandé avec accusé de réception, (ii) soit déposé\n8. Décharge aux Commissaires aux Comptes pour leur mission au titre de l’exercice clos le contre accusé (remise en mains propres), au siège social d’IMMORENTE INVEST SA au 5/7,\n31 décembre 2023 ; rue Ibnou Toufail, Casablanca, cinq (5) jours au moins avant la réunion de l’Assemblée Générale.\n9. Mandats des Commissaires aux Comptes ; Tout pouvoir non accompagné de l’original de l’attestation de propriété des actions et/ou non\n10. Pouvoirs en vue des formalités ; reçu dans le délai mentionné ci-dessus, ne sera pas pris en compte pour le vote des résolutions.\n11. Questions diverses. Modalités de vote par correspondance\nLes actionnaires peuvent voter au moyen d’un formulaire de vote par correspondance.\nMODALITES DE PARTICIPATION Ce formulaire est mis à la disposition des actionnaires au siège social d’IMMORENTE\nTout actionnaire quel que soit le nombre d’actions qu’il possède peut participer à l’Assemblée INVEST SA. Il peut également être téléchargé sur le site internet d’IMMORENTE\nGénérale sur simple justification de son identité et de la propriété de ses actions. INVEST : www.immorente.ma. Il doit être envoyé au siège social de la Société au 5/7,\nrue Ibnou Toufail, Casablanca, accompagné de l’attestation originale délivrée par l’organisme\nLes propriétaires d’actions au porteur doivent, pour avoir le droit de participer à cette\ndépositaire des actions soit par courrier recommandé avec accusé de réception, soit déposé\nAssemblée Générale, déposer au siège social d’IMMORENTE INVEST SA au 5/7, rue Ibnou contre accusé (remise en mains propres), à l’adresse ci-dessus indiqué, au plus tard deux\nToufail, Casablanca, cinq (5) jours au plus avant la date de la réunion, un certificat de dépôt (2) jours avant la réunion de l’Assemblée Générale.\ndélivré par l’établissement dépositaire de ces actions ;\nTout formulaire non accompagné de l’original de l’attestation de propriété des actions et/ou non\nTout actionnaire quel que soit le nombre d’actions qu’il possède peut y participer reçu dans le délai mentionné ci-dessus, ne sera pas pris en compte pour le vote des résolutions.\nPROJET DE RESOLUTIONS DE L’ASSEMBLEE GENERALE ORDINAIRE REUNIE EXTRAORDINAIREMENT\nCONVOQUEE POUR LE 04 AVRIL 2024 A 10H30\nPREMIERE RESOLUTION SIXIEME RESOLUTION\nL’Assemblée Générale, après avoir entendu lecture du rapport du Conseil d’Administration L’Assemblée Générale, décide d’allouer aux Administrateurs de la Société, des jetons\net lecture du rapport général des Commissaires aux Comptes, approuve les comptes de présence d’un montant de trois cent mille dirhams (MAD 300.000) bruts, au titre de\nsociaux arrêtés au 31 décembre 2023, tels qu’ils lui ont été présentés, lesquels font l’exercice 2024.\nressortir un bénéfice net comptable de 4.426.447,49 dirhams. Le Conseil d’Administration répartira cette somme entre ses membres, dans les proportions\nqu’il jugera convenables.\nDEUXIEME RESOLUTION\nL’Assemblée Générale, après avoir pris connaissance du rapport du Conseil d’Administration SEPTIEME RESOLUTION\net du rapport des Commissaires aux Comptes sur les comptes consolidés, approuve les L’Assemblée Générale, après avoir entendu le rapport spécial des Commissaires aux\ncomptes consolidés arrêtés au 31 décembre 2023, tels qu’ils lui ont été présentés, lesquels Comptes sur les conventions visées notamment à l’article 56 de la loi n°17-95 relative à\nfont ressortir un résultat consolidé part du groupe positif de 42.782.803,125 dirhams dirhams. la Société Anonyme telle que modifiée et complétée, déclare approuver ce rapport dans\ntoutes ses dispositions, ainsi que les conventions, engagements et opérations, dont il fait\nTROISIEME RESOLUTION état, conclus ou exécutés au cours de l’exercice clos le 31 décembre 2023.\nL’Assemblée Générale décide d’affecter le résultat bénéficiaire de l’exercice clos le 31\ndécembre 2023 de 4.426.447,49 dirhams comme suit : HUITIEME RESOLUTION\nBénéfice net comptable de l’exercice 4.426.447,49 dirhams L’Assemblée Générale, donne décharge aux Commissaires aux Comptes, le cabinet « A.\nRéserve légale (5%) à déduire -221.322,37 dirhams SAAIDI & Associés » représenté par Madame Bahaa SAAIDI et le cabinet « FIDAROC\nGRANT THORNTON » représenté par Monsieur Tarik MAAROUF pour leur mission au titre\nReport à nouveau des exercices précédents 3.638.824,64 dirhams\nde l’exercice clos le 31 décembre 2023.\nSommes distribuables 7.843.949,76 dirhams\nMontant à affecter au compte Report à Nouveau 7.843.949,76 dirhams NEUVIEME RESOLUTION\nL’Assemblée Générale, décide également de distribuer un montant de 3,2 dirhams par L’Assemblée Générale, après avoir constaté que les mandats des Commissaires aux\naction, soit un montant total de 28.822.400,00 dirhams, à imputer sur la prime d’émission. comptes de la Société, le cabinet « A. SAAIDI & ASSOCIES » représenté par Madame\nLe paiement sera effectué en deux tranches étant précisé que chaque paiement sera Bahaa SAAIDI et le cabinet « FIDAROC GRANT THORNTON » représenté par Monsieur\nprécédé par un détachement à la bourse. Tarik MAAROUF, arrivent à expiration à l’issue de la présente Assemblée, décide de :\n• Le premier versement, interviendra à partir du 1er avril 2024 et consistera, en la distribution • Renouveler le mandat du cabinet « FIDAROC GRANT THORNTON » représenté par\nde 1 dirham par action, soit un total de 9.007.000,00 dirhams ; Monsieur Tarik MAAROUF pour une durée de trois (3) exercices, soit jusqu’à l’issue de\n• Le deuxième versement, interviendra à partir du 1er juin 2024 et consistera, en la l’Assemblée Générale Ordinaire Annuelle appelée à statuer sur les comptes de l’exercice\ndistribution de 2,2 dirhams par action, soit un total de 19.815.400 dirhams. clos le 31 décembre 2026 ;\n• Ne pas renouveler le mandat du cabinet « A. SAAIDI & ASSOCIES » représenté par\nQUATRIEME RESOLUTION Madame Bahaa SAAIDI ; et\nL’Assemblée Générale Ordinaire, donne quitus aux Administrateurs pour leur gestion au • Nommer le cabinet HDID & Associés représenté par Monsieur Mohamed HDID en\ncours de l’exercice clos le 31 décembre 2023. qualité de nouveau Commissaire aux Comptes pour une durée de trois (3) exercices,\nsoit jusqu’à l’issue de l’Assemblée Générale Ordinaire Annuelle appelée à statuer sur les\nCINQUIEME RESOLUTION comptes de l’exercice clos le 31 décembre 2026.\nL’Assemblée Générale, (i) constatant l’expiration des mandats de certains Administrateurs\nde la Société à savoir la société CAT ASSURANCE ET REASSURANCE et la société DIXIEME RESOLUTION\nCentrale de Réassurance, décide de les renouveler et ce, pour une durée de six (6) L’Assemblée Générale confère tous pouvoirs au porteur d’un original, d’une copie ou\nexercices, soit jusqu’à l’issue de l’Assemblée Générale Ordinaire Annuelle qui sera appelée d’un extrait du présent procès-verbal aux fins d’accomplir toutes formalités de dépôt, de\nà statuer sur les comptes de l’exercice clos le 31 décembre 2029. publicité et autres qu’il appartiendra de faire.\nwww.immorente.ma\nLE LOYER TRANQUILLE POUR TOUS\nContact relation investisseurs : relation.investisseurs@immorente.ma",
    "tables": [
        [
            {
                "LE LOYER TRANQUILLE POUR TOUS": "COMMUNICATION FINANCIÈRE\nAU 31 DÉCEMBRE 2023\nImmorente Invest est une société propriétaire d’usines, de bureaux et d’actifs logistiques, tous\nloués à de grandes entreprises multinationales et à de grands groupes marocains. Immorente\nInvest perçoit ces loyers et les reverse à ses actionnaires. Historiquement, pour une part achetée\nautour de 100 DH, Immorente a payé 5,0 à 6,5 DH par an.\nImmorente Invest est une société cotée à la bourse de Casablanca, dont les actions sont\ndisponibles tous les jours et peuvent être acquises auprès des réseaux bancaires et sociétés de\nbourse.\nLien vers la communication financière : https://immorente.ma/relations-investisseurs/communication_\nfinanciere/2023-2/\nContact relation investisseurs : relation.investisseurs@immorente.ma\nwww.immorente.ma"
            }
        ],
        [],
        [
            {
                "GUIDANCE 2024": ""
            },
            {
                "GUIDANCE 2024": "• La Société anticipe une augmentation de 8% à 10% du chiffre d’affaires sur l’année 2024 sous l’effet conjugué de l’élargissement\ndu périmètre des actifs avec un investissement prévu courant l’année et la commercialisation de certains actifs bureaux.\n• La livraison de l’extension de l’usine Faurecia lors du T4 2024 augmenterait la part de l’industrie dans le portefeuille à prés de\n50% et réduirait celle du bureau à prés d’un tiers.\n• En conséquence, nous prévoyons un rendement à verser en 2024 de 5,2 dh/action en quatre distributions trimestrielles."
            }
        ],
        [
            {
                "COMPTES CONSOLIDÉS EN NORMES IFRS\nAU 31 DÉCEMBRE 2023": "BILAN ACTIF (EN KMAD) BILAN PASSIF (EN KMAD)\nExercice 2023.12 Exercice 2022.12 Exercice 2023.12 Exercice 2022.12\nGoodwill 2.583 2.583 Capital 563.298 563.298\nRéserves 220.935 250.431\nImmeubles de placement 934.366 822.625\nRésultat de l'exercice 42.783 15.812\nAutres actifs financiers 50.005 5\nTotal Capitaux propres, part du groupe 827.016 829.540\nImpôts différés 0 0\nIntérêts minoritaires 0 0\nActifs non-courants 986.954 825.213 Total Intérêts minoritaires 0 0\nStocks et en-cours 0 0 Total des capitaux propres 827.016 829.540\nClients et comptes rattachés 4.843 2.565 Emprunts et dettes financières 120.000 0\nComptes d'état 12.447 21.619 Dépôts et cautionnements des locataires 13.293 8.383\nAutres débiteurs 15 15 Impôts différés 54.342 51.242\nAutres actifs courants 325 268 Autres passifs long terme 0 0\nVMP et autres placements 7.588 43.105 Total Passifs non courants 187.635 59.625\nTrésorerie et équivalents de trésorerie 28.096 18.141 Emprunts et crédit à moins d'un an 150 0\nActifs courants 53.315 85.714 Banques (soldes créditeurs) 0 0\nProvisions (part à moins d'un an) 3.852 5.424\nActifs non courants et groupes d’actifs destinés à être cédés - - Dettes fournisseurs 10.674 7.206\nTotal Actif 1.040.269 910.927 Comptes d'Etat 9.035 8.492\nAutres créditeurs 1.906 638\nTotal Passifs courants 25.618 21.762\nCOMPTE DE RÉSULTAT CONSOLIDÉ IFRS (EN KMAD)\nTotal Passifs liés à un groupe d’actifs destinés à être cédés - -\nExercice 2023.12 Exercice 2022.12\nTotal des passifs 213.253 81.386\nChiffres d’affaires 72.215 67.055\nAchats consommés -2.248 -2.373 Total passif 1.040.269 910.927\nCharges de personnel - 0\nCharges externes -15.248 -13.573\nImpôts et taxes -5.999 -6.844 TABLEAU DE FLUX DE TRÉSORERIE CONSOLIDÉ EN KMAD\nRésultat d’exploitation 48.720 44.265\nDotations nettes de reprises aux provisions courantes 960 4.258 31/12/2023 31/12/2022\nAutres produits et charges d'exploitation -300 -300 Résultat net total des sociétés consolidées 42.783 15.812\nRésultat opérationnel courant 49.381 48.223 Elim. du résultat des mises en équivalence - 0\nAutres produits et charges opérationnels 296 -233 Elim. des amortissements et provisions -1.572 1.184\nRésultat opérationnel 49.677 47.990\nElim. des profits / pertes de réévaluation (juste valeur) 414 20.354\nProduits de trésorerie et d'équivalents de trésorerie 1.285 1.450\nCapacité d'autofinancement après coût de l'endettement 41.624 37.350\nCoût de l'endettement financier brut -1.133 -1.002 financier net et impôt\nProduits de placements financiers nets des charges 153 448\nElim. de la charge (produit) d'impôt 6.299 3.740\nd'intérêts\nRésultat de change -424 933 Capacité d'autofinancement avant coût de l'endettement financier 47.923 41.090\nnet et impôt\nPlus ou moins values sur réévaluations sur immeubles de -324 -29.400\nIncidence de la variation du BFR 9.481 -2.621\nplacement\nAutres produits et charges financiers - -420 Impôts payés -654 5.235\nFlux de trésorerie liés aux activités opérationnelles 56.750 43.705\nRésultat financier consolidé -595 -28.438 Augmentation des prises de participation dans les filiales -272 0\nRésultat avant impôt 49.082 19.552 consolidées\nImpôts sur les bénéfices -3.199 -3.565 Acquisition d'immobilisations corporelles et incorporelles -112.065 -30\nImpôts différés -3.100 -175 Flux de trésorerie liés aux activités d'investissement -162.337 -30\nTotal Impôts sur les bénéfices -6.299 -3.740 Emission d'emprunts 125.099 1.116\nRésultat après impôt 42.783 15.812 Dividendes payés aux actionnaires du groupe -45.035 -49.539\nDividendes payés aux minoritaires - 0\nRésultat net total 42.783 15.812\nVariation des crédits de trésorerie - 0\nImpot différé 3.100 175\nPlus ou moins values sur réévaluations sur immeubles de 324 29.400 Flux de trésorerie liés aux activités de financement 79.876 -100.355\nplacement Incidence de la variation des taux de change\nAutres retraitements 445 -727 Incidence des changements de principes comptables\nFFO (1) (Résultat analytique de l’exercice) 46.651 44.660\nVariation de trésorerie -25.711 -56.680\n(1) FFO : Fund From Opérations (Résultat de l’exercice analytique) : Résultat net consolidé IFRS corrigé des\nTrésorerie d'ouverture 61.246 117.926\néléments non cash tels que les impôts différés, la variation de la juste valeur des actifs et autres\nretraitements non cash. Trésorerie de clôture 35.534 61.246\nTABLEAU DE VARIATION DES CAPITAUX PROPRES CONSOLIDÉS EN KMAD\nAutres réserves groupe Autres\nPrimes Total Capitaux Total\nActions réserves et Intérêts\nCapital l cié ae ps it a au l propres conR vé es rse ir ov ne s g rd oe u pe A hou rtr se cs o r né vs ee rr sv ioe ns Total cr oé ns su ol lt ia dt és s pr do up gr re os u p pa ert minoritaires C pa rp oi pt ra eu sx\nSituation à l'ouverture de l'exercice 2022.12 563.298 177.696 - - 22.465 22.465 99.808 863.267 - 863.267\nIncidence des changements de méthode comptable : - - - - - - - - - -\nSituation ajustée à l'ouverture de l'exercice 2022.12 563.298 177.696 - - 22.465 22.465 99.808 863.267 - 863.267\nRéévaluation des immobilisations corporelle et incorporelles - - - - - -\nVar. nette de juste valeur des instruments financiers - - - - - - - - - -\nRésultat de la période - - - - - - 15.812 15.812 - 15.812\nTotal des pertes et profits de la période - - - - - - 15.812 15.812 - 15.812\nDividendes versés - -18.014 - - - - -31.525 -49.539 - -49.539\nAugmentation de capital - - - - - - - -\nAutres variations - - - - - - - - - -\nSituation à la clôture de l'exercice 2022.12 563.298 159.682 - - 22.465 22.465 84.095 829.540 - 829.540\nSituation à l'ouverture de l'exercice 2023.12 563.298 159.682 - - 22.465 22.465 84.095 829.540 - 829.540\nIncidence des changements de méthode comptable : - - - - - - - - - 0\nSituation ajustée à l'ouverture de l'exercice 2023.12 563.298 159.682 - - 22.465 22.465 84.095 829.540 - 829.540\nRéévaluation des immobilisations corporelle et incorporelles - - - - - - - - - -\nVar. nette de juste valeur des instruments financiers - - - - - - - - - -\nCouverture de flux de trésorerie - - - - - - - - - -\nEcarts de conversion - - - - - - - - - -\nRésultat de la période - - - - - - 42.783 42.783 - 42.783\nTotal des pertes et profits de la période - - - - - - 42.783 42.783 - 42.783\nDividendes versés - -36.028 - - - - -9.007 -45.035 - -45.035\nAugmentation de capital - - - - - -\nAutres variations - - - - - - -272 -272 - -272\nSituation à la clôture de l'exercice 2023.12 563.298 123.654 - - 22.465 22.465 117.599 827.016 - 827.016"
            }
        ],
        [
            {
                "": "",
                "Exercice 2023.12": "2.583",
                "Exercice 2022.12": "2.583"
            },
            {
                "": "",
                "Exercice 2023.12": "934.366",
                "Exercice 2022.12": "822.625"
            },
            {
                "": "",
                "Exercice 2023.12": "50.005",
                "Exercice 2022.12": "5"
            },
            {
                "": "",
                "Exercice 2023.12": "0",
                "Exercice 2022.12": "0"
            },
            {
                "": "Actifs non-courants",
                "Exercice 2023.12": "986.954",
                "Exercice 2022.12": "825.213"
            },
            {
                "": "",
                "Exercice 2023.12": "0",
                "Exercice 2022.12": "0"
            },
            {
                "": "",
                "Exercice 2023.12": "4.843",
                "Exercice 2022.12": "2.565"
            },
            {
                "": "",
                "Exercice 2023.12": "12.447",
                "Exercice 2022.12": "21.619"
            },
            {
                "": "",
                "Exercice 2023.12": "15",
                "Exercice 2022.12": "15"
            },
            {
                "": "",
                "Exercice 2023.12": "325",
                "Exercice 2022.12": "268"
            },
            {
                "": "",
                "Exercice 2023.12": "7.588",
                "Exercice 2022.12": "43.105"
            },
            {
                "": "",
                "Exercice 2023.12": "28.096",
                "Exercice 2022.12": "18.141"
            },
            {
                "": "Actifs courants",
                "Exercice 2023.12": "53.315",
                "Exercice 2022.12": "85.714"
            },
            {
                "": "",
                "Exercice 2023.12": "",
                "Exercice 2022.12": ""
            },
            {
                "": "Actifs non courants et groupes d’actifs destinés à être cédés",
                "Exercice 2023.12": "-",
                "Exercice 2022.12": "-"
            },
            {
                "": "Total Actif",
                "Exercice 2023.12": "1.040.269",
                "Exercice 2022.12": "910.927"
            }
        ],
        [
            {
                "": "",
                "Exercice 2023.12": "563.298",
                "Exercice 2022.12": "563.298"
            },
            {
                "": "",
                "Exercice 2023.12": "220.935",
                "Exercice 2022.12": "250.431"
            },
            {
                "": "",
                "Exercice 2023.12": "42.783",
                "Exercice 2022.12": "15.812"
            },
            {
                "": "Total Capitaux propres, part du groupe",
                "Exercice 2023.12": "827.016",
                "Exercice 2022.12": "829.540"
            },
            {
                "": "",
                "Exercice 2023.12": "0",
                "Exercice 2022.12": "0"
            },
            {
                "": "",
                "Exercice 2023.12": "0",
                "Exercice 2022.12": "0"
            },
            {
                "": "Total des capitaux propres",
                "Exercice 2023.12": "827.016",
                "Exercice 2022.12": "829.540"
            },
            {
                "": "",
                "Exercice 2023.12": "120.000",
                "Exercice 2022.12": "0"
            },
            {
                "": "",
                "Exercice 2023.12": "13.293",
                "Exercice 2022.12": "8.383"
            },
            {
                "": "",
                "Exercice 2023.12": "54.342",
                "Exercice 2022.12": "51.242"
            },
            {
                "": "",
                "Exercice 2023.12": "0",
                "Exercice 2022.12": "0"
            },
            {
                "": "Total Passifs non courants",
                "Exercice 2023.12": "187.635",
                "Exercice 2022.12": "59.625"
            },
            {
                "": "",
                "Exercice 2023.12": "150",
                "Exercice 2022.12": "0"
            },
            {
                "": "",
                "Exercice 2023.12": "0",
                "Exercice 2022.12": "0"
            },
            {
                "": "",
                "Exercice 2023.12": "3.852",
                "Exercice 2022.12": "5.424"
            },
            {
                "": "",
                "Exercice 2023.12": "10.674",
                "Exercice 2022.12": "7.206"
            },
            {
                "": "",
                "Exercice 2023.12": "9.035",
                "Exercice 2022.12": "8.492"
            },
            {
                "": "",
                "Exercice 2023.12": "1.906",
                "Exercice 2022.12": "638"
            },
            {
                "": "Total Passifs courants",
                "Exercice 2023.12": "25.618",
                "Exercice 2022.12": "21.762"
            },
            {
                "": "",
                "Exercice 2023.12": "",
                "Exercice 2022.12": ""
            },
            {
                "": "Total Passifs liés à un groupe d’actifs destinés à être cédés",
                "Exercice 2023.12": "-",
                "Exercice 2022.12": "-"
            },
            {
                "": "Total des passifs",
                "Exercice 2023.12": "213.253",
                "Exercice 2022.12": "81.386"
            },
            {
                "": "",
                "Exercice 2023.12": "",
                "Exercice 2022.12": ""
            },
            {
                "": "Total passif",
                "Exercice 2023.12": "1.040.269",
                "Exercice 2022.12": "910.927"
            }
        ],
        [
            {
                "": "",
                "Exercice 2023.12": "72.215",
                "Exercice 2022.12": "67.055"
            },
            {
                "": "",
                "Exercice 2023.12": "-2.248",
                "Exercice 2022.12": "-2.373"
            },
            {
                "": "",
                "Exercice 2023.12": "-",
                "Exercice 2022.12": "0"
            },
            {
                "": "",
                "Exercice 2023.12": "-15.248",
                "Exercice 2022.12": "-13.573"
            },
            {
                "": "",
                "Exercice 2023.12": "-5.999",
                "Exercice 2022.12": "-6.844"
            },
            {
                "": "Résultat d’exploitation",
                "Exercice 2023.12": "48.720",
                "Exercice 2022.12": "44.265"
            },
            {
                "": "",
                "Exercice 2023.12": "960",
                "Exercice 2022.12": "4.258"
            },
            {
                "": "",
                "Exercice 2023.12": "-300",
                "Exercice 2022.12": "-300"
            },
            {
                "": "Résultat opérationnel courant",
                "Exercice 2023.12": "49.381",
                "Exercice 2022.12": "48.223"
            },
            {
                "": "",
                "Exercice 2023.12": "296",
                "Exercice 2022.12": "-233"
            },
            {
                "": "Résultat opérationnel",
                "Exercice 2023.12": "49.677",
                "Exercice 2022.12": "47.990"
            },
            {
                "": "",
                "Exercice 2023.12": "1.285",
                "Exercice 2022.12": "1.450"
            },
            {
                "": "",
                "Exercice 2023.12": "-1.133",
                "Exercice 2022.12": "-1.002"
            },
            {
                "": "Produits de placements financiers nets des charges\nd'intérêts",
                "Exercice 2023.12": "153",
                "Exercice 2022.12": "448"
            },
            {
                "": "Résultat de change",
                "Exercice 2023.12": "-424",
                "Exercice 2022.12": "933"
            },
            {
                "": "Plus ou moins values sur réévaluations sur immeubles de\nplacement",
                "Exercice 2023.12": "-324",
                "Exercice 2022.12": "-29.400"
            },
            {
                "": "Autres produits et charges financiers",
                "Exercice 2023.12": "-",
                "Exercice 2022.12": "-420"
            },
            {
                "": "",
                "Exercice 2023.12": "",
                "Exercice 2022.12": ""
            },
            {
                "": "Résultat financier consolidé",
                "Exercice 2023.12": "-595",
                "Exercice 2022.12": "-28.438"
            },
            {
                "": "Résultat avant impôt",
                "Exercice 2023.12": "49.082",
                "Exercice 2022.12": "19.552"
            },
            {
                "": "",
                "Exercice 2023.12": "-3.199",
                "Exercice 2022.12": "-3.565"
            },
            {
                "": "",
                "Exercice 2023.12": "-3.100",
                "Exercice 2022.12": "-175"
            },
            {
                "": "",
                "Exercice 2023.12": "-6.299",
                "Exercice 2022.12": "-3.740"
            },
            {
                "": "Résultat après impôt",
                "Exercice 2023.12": "42.783",
                "Exercice 2022.12": "15.812"
            },
            {
                "": "",
                "Exercice 2023.12": "",
                "Exercice 2022.12": ""
            },
            {
                "": "Résultat net total",
                "Exercice 2023.12": "42.783",
                "Exercice 2022.12": "15.812"
            },
            {
                "": "",
                "Exercice 2023.12": "3.100",
                "Exercice 2022.12": "175"
            },
            {
                "": "",
                "Exercice 2023.12": "324",
                "Exercice 2022.12": "29.400"
            },
            {
                "": "",
                "Exercice 2023.12": "445",
                "Exercice 2022.12": "-727"
            },
            {
                "": "",
                "Exercice 2023.12": "46.651",
                "Exercice 2022.12": "44.660"
            }
        ],
        [
            {
                "": "",
                "31/12/2023": "42.783",
                "31/12/2022": ""
            },
            {
                "": "",
                "31/12/2023": "-",
                "31/12/2022": ""
            },
            {
                "": "",
                "31/12/2023": "-1.572",
                "31/12/2022": ""
            },
            {
                "": "",
                "31/12/2023": "414",
                "31/12/2022": ""
            },
            {
                "": "",
                "31/12/2023": "41.624",
                "31/12/2022": ""
            },
            {
                "": "",
                "31/12/2023": "6.299",
                "31/12/2022": ""
            },
            {
                "": "",
                "31/12/2023": "47.923",
                "31/12/2022": ""
            },
            {
                "": "",
                "31/12/2023": "9.481",
                "31/12/2022": ""
            },
            {
                "": "",
                "31/12/2023": "-654",
                "31/12/2022": ""
            },
            {
                "": "Flux de trésorerie liés aux activités opérationnelles",
                "31/12/2023": "56.750",
                "31/12/2022": "43.705"
            },
            {
                "": "",
                "31/12/2023": "-272",
                "31/12/2022": ""
            },
            {
                "": "",
                "31/12/2023": "-112.065",
                "31/12/2022": ""
            },
            {
                "": "Flux de trésorerie liés aux activités d'investissement",
                "31/12/2023": "-162.337",
                "31/12/2022": "-30"
            },
            {
                "": "",
                "31/12/2023": "125.099",
                "31/12/2022": ""
            },
            {
                "": "",
                "31/12/2023": "-45.035",
                "31/12/2022": ""
            },
            {
                "": "",
                "31/12/2023": "-",
                "31/12/2022": ""
            },
            {
                "": "",
                "31/12/2023": "-",
                "31/12/2022": ""
            },
            {
                "": "Flux de trésorerie liés aux activités de financement",
                "31/12/2023": "79.876",
                "31/12/2022": "-100.355"
            },
            {
                "": "",
                "31/12/2023": "",
                "31/12/2022": ""
            },
            {
                "": "",
                "31/12/2023": "",
                "31/12/2022": ""
            },
            {
                "": "Variation de trésorerie",
                "31/12/2023": "-25.711",
                "31/12/2022": "-56.680"
            },
            {
                "": "",
                "31/12/2023": "61.246",
                "31/12/2022": ""
            },
            {
                "": "",
                "31/12/2023": "35.534",
                "31/12/2022": ""
            }
        ],
        [
            {
                "": "",
                "Capital": "",
                "Primes\nliées au\ncapital": "",
                "Actions\npropres": "",
                "Autres réserves groupe": "Réserves de\nconversion groupe",
                "null": "Total",
                "Autres\nréserves et\nrésultats\nconsolidés": "",
                "Total Capitaux\npropres part\ndu groupe": "",
                "Intérêts\nminoritaires": "",
                "Total\nCapitaux\npropres": ""
            },
            {
                "": "Situation à l'ouverture de l'exercice 2022.12",
                "Capital": "563.298",
                "Primes\nliées au\ncapital": "177.696",
                "Actions\npropres": "-",
                "Autres réserves groupe": "-",
                "null": "22.465",
                "Autres\nréserves et\nrésultats\nconsolidés": "99.808",
                "Total Capitaux\npropres part\ndu groupe": "863.267",
                "Intérêts\nminoritaires": "-",
                "Total\nCapitaux\npropres": "863.267"
            },
            {
                "": "",
                "Capital": "",
                "Primes\nliées au\ncapital": "",
                "Actions\npropres": "",
                "Autres réserves groupe": "",
                "null": "-",
                "Autres\nréserves et\nrésultats\nconsolidés": "-",
                "Total Capitaux\npropres part\ndu groupe": "-",
                "Intérêts\nminoritaires": "",
                "Total\nCapitaux\npropres": ""
            },
            {
                "": "Situation ajustée à l'ouverture de l'exercice 2022.12",
                "Capital": "563.298",
                "Primes\nliées au\ncapital": "177.696",
                "Actions\npropres": "-",
                "Autres réserves groupe": "-",
                "null": "22.465",
                "Autres\nréserves et\nrésultats\nconsolidés": "99.808",
                "Total Capitaux\npropres part\ndu groupe": "863.267",
                "Intérêts\nminoritaires": "-",
                "Total\nCapitaux\npropres": "863.267"
            },
            {
                "": "",
                "Capital": "",
                "Primes\nliées au\ncapital": "",
                "Actions\npropres": "",
                "Autres réserves groupe": "",
                "null": "-",
                "Autres\nréserves et\nrésultats\nconsolidés": "-",
                "Total Capitaux\npropres part\ndu groupe": "-",
                "Intérêts\nminoritaires": "",
                "Total\nCapitaux\npropres": ""
            },
            {
                "": "",
                "Capital": "",
                "Primes\nliées au\ncapital": "",
                "Actions\npropres": "",
                "Autres réserves groupe": "",
                "null": "-",
                "Autres\nréserves et\nrésultats\nconsolidés": "-",
                "Total Capitaux\npropres part\ndu groupe": "-",
                "Intérêts\nminoritaires": "",
                "Total\nCapitaux\npropres": ""
            },
            {
                "": "",
                "Capital": "",
                "Primes\nliées au\ncapital": "",
                "Actions\npropres": "",
                "Autres réserves groupe": "",
                "null": "-",
                "Autres\nréserves et\nrésultats\nconsolidés": "15.812",
                "Total Capitaux\npropres part\ndu groupe": "15.812",
                "Intérêts\nminoritaires": "",
                "Total\nCapitaux\npropres": ""
            },
            {
                "": "",
                "Capital": "",
                "Primes\nliées au\ncapital": "",
                "Actions\npropres": "",
                "Autres réserves groupe": "",
                "null": "-",
                "Autres\nréserves et\nrésultats\nconsolidés": "15.812",
                "Total Capitaux\npropres part\ndu groupe": "15.812",
                "Intérêts\nminoritaires": "",
                "Total\nCapitaux\npropres": ""
            },
            {
                "": "",
                "Capital": "",
                "Primes\nliées au\ncapital": "",
                "Actions\npropres": "",
                "Autres réserves groupe": "",
                "null": "-",
                "Autres\nréserves et\nrésultats\nconsolidés": "-31.525",
                "Total Capitaux\npropres part\ndu groupe": "-49.539",
                "Intérêts\nminoritaires": "",
                "Total\nCapitaux\npropres": ""
            },
            {
                "": "",
                "Capital": "",
                "Primes\nliées au\ncapital": "",
                "Actions\npropres": "",
                "Autres réserves groupe": "",
                "null": "-",
                "Autres\nréserves et\nrésultats\nconsolidés": "",
                "Total Capitaux\npropres part\ndu groupe": "-",
                "Intérêts\nminoritaires": "",
                "Total\nCapitaux\npropres": ""
            },
            {
                "": "",
                "Capital": "",
                "Primes\nliées au\ncapital": "",
                "Actions\npropres": "",
                "Autres réserves groupe": "",
                "null": "-",
                "Autres\nréserves et\nrésultats\nconsolidés": "-",
                "Total Capitaux\npropres part\ndu groupe": "-",
                "Intérêts\nminoritaires": "",
                "Total\nCapitaux\npropres": ""
            },
            {
                "": "Situation à la clôture de l'exercice 2022.12",
                "Capital": "563.298",
                "Primes\nliées au\ncapital": "159.682",
                "Actions\npropres": "-",
                "Autres réserves groupe": "-",
                "null": "22.465",
                "Autres\nréserves et\nrésultats\nconsolidés": "84.095",
                "Total Capitaux\npropres part\ndu groupe": "829.540",
                "Intérêts\nminoritaires": "-",
                "Total\nCapitaux\npropres": "829.540"
            },
            {
                "": "Situation à l'ouverture de l'exercice 2023.12",
                "Capital": "563.298",
                "Primes\nliées au\ncapital": "159.682",
                "Actions\npropres": "-",
                "Autres réserves groupe": "-",
                "null": "22.465",
                "Autres\nréserves et\nrésultats\nconsolidés": "84.095",
                "Total Capitaux\npropres part\ndu groupe": "829.540",
                "Intérêts\nminoritaires": "-",
                "Total\nCapitaux\npropres": "829.540"
            },
            {
                "": "",
                "Capital": "",
                "Primes\nliées au\ncapital": "",
                "Actions\npropres": "",
                "Autres réserves groupe": "",
                "null": "-",
                "Autres\nréserves et\nrésultats\nconsolidés": "-",
                "Total Capitaux\npropres part\ndu groupe": "-",
                "Intérêts\nminoritaires": "",
                "Total\nCapitaux\npropres": ""
            },
            {
                "": "Situation ajustée à l'ouverture de l'exercice 2023.12",
                "Capital": "563.298",
                "Primes\nliées au\ncapital": "159.682",
                "Actions\npropres": "-",
                "Autres réserves groupe": "-",
                "null": "22.465",
                "Autres\nréserves et\nrésultats\nconsolidés": "84.095",
                "Total Capitaux\npropres part\ndu groupe": "829.540",
                "Intérêts\nminoritaires": "-",
                "Total\nCapitaux\npropres": "829.540"
            },
            {
                "": "",
                "Capital": "",
                "Primes\nliées au\ncapital": "",
                "Actions\npropres": "",
                "Autres réserves groupe": "",
                "null": "-",
                "Autres\nréserves et\nrésultats\nconsolidés": "-",
                "Total Capitaux\npropres part\ndu groupe": "-",
                "Intérêts\nminoritaires": "",
                "Total\nCapitaux\npropres": ""
            },
            {
                "": "",
                "Capital": "",
                "Primes\nliées au\ncapital": "",
                "Actions\npropres": "",
                "Autres réserves groupe": "",
                "null": "-",
                "Autres\nréserves et\nrésultats\nconsolidés": "-",
                "Total Capitaux\npropres part\ndu groupe": "-",
                "Intérêts\nminoritaires": "",
                "Total\nCapitaux\npropres": ""
            },
            {
                "": "",
                "Capital": "",
                "Primes\nliées au\ncapital": "",
                "Actions\npropres": "",
                "Autres réserves groupe": "",
                "null": "-",
                "Autres\nréserves et\nrésultats\nconsolidés": "-",
                "Total Capitaux\npropres part\ndu groupe": "-",
                "Intérêts\nminoritaires": "",
                "Total\nCapitaux\npropres": ""
            },
            {
                "": "",
                "Capital": "",
                "Primes\nliées au\ncapital": "",
                "Actions\npropres": "",
                "Autres réserves groupe": "",
                "null": "-",
                "Autres\nréserves et\nrésultats\nconsolidés": "-",
                "Total Capitaux\npropres part\ndu groupe": "-",
                "Intérêts\nminoritaires": "",
                "Total\nCapitaux\npropres": ""
            },
            {
                "": "",
                "Capital": "",
                "Primes\nliées au\ncapital": "",
                "Actions\npropres": "",
                "Autres réserves groupe": "",
                "null": "-",
                "Autres\nréserves et\nrésultats\nconsolidés": "42.783",
                "Total Capitaux\npropres part\ndu groupe": "42.783",
                "Intérêts\nminoritaires": "",
                "Total\nCapitaux\npropres": ""
            },
            {
                "": "",
                "Capital": "",
                "Primes\nliées au\ncapital": "",
                "Actions\npropres": "",
                "Autres réserves groupe": "",
                "null": "-",
                "Autres\nréserves et\nrésultats\nconsolidés": "42.783",
                "Total Capitaux\npropres part\ndu groupe": "42.783",
                "Intérêts\nminoritaires": "",
                "Total\nCapitaux\npropres": ""
            },
            {
                "": "",
                "Capital": "",
                "Primes\nliées au\ncapital": "",
                "Actions\npropres": "",
                "Autres réserves groupe": "",
                "null": "-",
                "Autres\nréserves et\nrésultats\nconsolidés": "-9.007",
                "Total Capitaux\npropres part\ndu groupe": "-45.035",
                "Intérêts\nminoritaires": "",
                "Total\nCapitaux\npropres": ""
            },
            {
                "": "",
                "Capital": "",
                "Primes\nliées au\ncapital": "",
                "Actions\npropres": "",
                "Autres réserves groupe": "",
                "null": "-",
                "Autres\nréserves et\nrésultats\nconsolidés": "",
                "Total Capitaux\npropres part\ndu groupe": "-",
                "Intérêts\nminoritaires": "",
                "Total\nCapitaux\npropres": ""
            },
            {
                "": "",
                "Capital": "",
                "Primes\nliées au\ncapital": "",
                "Actions\npropres": "",
                "Autres réserves groupe": "",
                "null": "-",
                "Autres\nréserves et\nrésultats\nconsolidés": "-272",
                "Total Capitaux\npropres part\ndu groupe": "-272",
                "Intérêts\nminoritaires": "",
                "Total\nCapitaux\npropres": ""
            },
            {
                "": "Situation à la clôture de l'exercice 2023.12",
                "Capital": "563.298",
                "Primes\nliées au\ncapital": "123.654",
                "Actions\npropres": "-",
                "Autres réserves groupe": "-",
                "null": "22.465",
                "Autres\nréserves et\nrésultats\nconsolidés": "117.599",
                "Total Capitaux\npropres part\ndu groupe": "827.016",
                "Intérêts\nminoritaires": "-",
                "Total\nCapitaux\npropres": "827.016"
            }
        ],
        [
            {
                "COMPTES CONSOLIDÉS EN NORMES IFRS\nAU 31 DÉCEMBRE 2023": "1. REGLES ET METHODES COMPTABLES\n1.1 REFERENTIEL COMPTABLE 1.7.4 Actifs non courants destinés à être abandonnés ou cédés\nLes états financiers consolidés du Groupe Immorente Invest sont préparés en conformité avec Ces actifs sont reclassés sur décision du management des filiales et de la holding. Ils sont évalués\nles normes comptables internationales adoptées au sein de l’Union Européenne au 31 décembre au plus petits entre le coût amortis et la valeur nette de réalisation. Au 31 Décembre 2023, le\n2023 et telles que publiées à cette même date. groupe ne dispose pas d’actifs non courants destinés à être abandonnés ou cédés.\nCes normes sont disponibles sur le site : http://ec.europa.eu/internal_market/accounting/ias/\nindex_fr.htm. 1.7.5 Evaluation des créances clients\nLes normes comptables internationales comprennent les IFRS (International Financial Reporting Les créances clients sont comptabilisées pour leur valeur nominale.\nStandards), les IAS (International Accounting Standards) et leurs interprétations SIC (Standard Le Groupe comptabilise une provision pour correction de valeur des créances clients lorsqu’il\nInterpretation Commitee) et IFRIC (International Financial Reporting Interpretation Commitee). existe une probabilité objective de perte de crédit conformément à la norme IFRS 9.\n1.2 PERIMETRE DE CONSOLIDATION 1.7.6 Autres débiteurs courants\n1.2.1 Périmètre Les autres débiteurs correspondent à des créances à moins d’un an ne correspondant pas à\ndes créances clients.\nClôture Ouverture Une provision pour dépréciation est comptabilisée lorsque le montant actualisé des flux de\ntrésorerie futurs est inférieur à la valeur comptable d’une créance.\nTaux Taux de Méthode Taux Taux de Méthode\nUnités\nd’intérêt contrôle de conso d’intérêt contrôle de conso\n1.7.7 Trésorerie et équivalents de trésorerie\nImmorente SA 100,00 % 100,00 % IG 100,00 % 100,00 % IG\nLa trésorerie et équivalent de trésorerie, comprend :\nIMR FREE ZONE 100,00 % 100,00 % IG 100,00 % 100,00 % IG\n• Les fonds en caisse ;\nAmlak Atrium 100,00 % 100,00 % IG 100,00 % 100,00 % IG • Les chèques et valeurs à l’encaissement ;\nAmlak Contempo 100,00 % 100,00 % IG 100,00 % 100,00 % IG • Les fonds déposés en banque.\nIG signifie Intégration Globale Les découverts bancaires, crédits de trésorerie et les remboursements prévisionnels des dettes\nfinancières dont l’échéance est inférieure à 1 an sont comptabilisés en dettes financières courantes\n(soldes créditeurs des banques, emprunts et crédits à moins d’un an).\n1.2.2 Autres participations\nLe groupe ne détient pas d’autres participations ou des structures non consolidées en dehors 1.7.8 Passifs financiers\ndes instruments de capitaux propres par le biais des autres éléments du résultat global, détaillés\nau paragraphe (4.3). Les emprunts et autres passifs financiers porteurs d’intérêt sont évalués à leur valeur nominale.\nImmrente Invest a contracté une dette de financement de 90 millions de Dirhams, et un crédit à\nLe groupe ne détient pas d’intérêts dans des partenariats ou des entreprises associées. court terme destiné à être consolidé en crédit à moyen terme au cours de la période.\n1.3 RETRAITEMENTS DE CONSOLIDATION Dettes financières en KMAD\nLes transactions intervenues au cours de l’exercice entre les différentes filiales ont été éliminées.\nL Le es g a roc uti pfs e e nt ep a gs és ni èfs r eré pc aip sr doq ’ou pe és r ao tn iot né st é g é él nim érin aé ns t . des résultats internes. E 2x 0e 2r 2c .i 1c 2e Augmentation Remb. cV ouar ri sa dti eo n cs h ad ne gs e Va Pr éi ra it mio èn ts r ede Autres E 2x 0e 2r 3c .i 1c 2e\nEmprunts obligataires\n1.4 DATE DE CLOTURE E étm abp lr isu sn ets m a eu np tr sè ds e d ce rs é dit 120.000 120.000\nL da e d toa ute te sd e le c sl ô fit lu iar le e sd .u Groupe est le 31 décembre. Cette date correspond à la date de clôture A asu str imes il ée em sprunts et dettes 8.383 5.099 -188 13.293\nE finm ap nr cu ièn rt es s et dettes 8.383 125.099 -188 133.293\n1.5 CHANGEMENT D’ESTIMATIONS COMPTABLES ET ERREURS I en ct hé urê st às pco au yeru rs et non 150 150\nNéant.\nCrédits de trésorerie\n1.6 GOODWILL E d'm unp r au nnts et crédit à moins 150 150\nLe goodwill ou l’écart d’acquisition positif est défini comme étant la différence entre le coût du Banques (solde créditeurs)\nr ee t g dr eo su p pe am sse ifn st . d’entreprise et la part d’intérêts de l’acquéreur dans la juste valeur nette des actifs E finm ap nr cu ièn rts e set dettes 8.383 125.249 -188 133.443\nLe goodwill est évalué en Dirham marocain. Il fait l’objet d’un test de perte de valeur annuel.\n1.7.9 Provisions\nL’acquisition de la société AMLAK ATRIUM a généré un écart d’acquisition négatif de KMAD\n3.875, lors de la prise de participation de la société en 2019. Les provisions sont comptabilisées lorsqu’il existe une obligation légale ou implicite envers un\ntiers qui se traduira par une sortie de ressources, sans contrepartie attendue, nécessaire pour\nL’écart d’acquisition positif fait l’objet d’un test de dépréciation annuel. Ce test est basé sur une\néteindre cette obligation et pouvant être estimée de façon fiable.\nactualisation des cash-flow futurs des différentes filiales au coût moyen pondéré du capital.\nLes provisions comptabilisées par la société concernent certains actifs : clients et stocks. Le\nAu 31 décembre 2023, aucune provision n’a été constatée sur les écarts d’acquisition montant de ces provisions est destiné à couvrir les pertes éventuelles liées au recouvrement ou\ncomptabilisés par le Groupe. à la réalisation des stocks.\nLes provisions concernent également certaines obligations notamment fiscales, pour lesquelles,\nle Groupe ne dispose pas de visibilité quant à leurs échéances.\nTableau de variatin des écarts d’acquisition/Goodwill en KMAD\nE 2x 0e 2r 2c .i 1c 2e E pn ét rr imée ès t rd ee pS éo rr it mie ès td re e va pr éA i rau it mt ior èe n ts s r ede lD 'eo xta edt rei co in ces dV d ea e r s ci ha ct aoi nuo gn rs es Autres E 2x 0e 2r 3c .i 1c 2e Provisions en KMAD\nE A d'c m aa ctr q/t P u d e i' sra it tc e iq osu n vis ai lt .i o én cart 2.583 2.583 E 2x 0e 2r 2c .i 1c 2e lD 'eo xta edt rei co in ces uR ( te p ilp r isr o éi vs e.e ) uR ( te p in lp r io sr o n éi vs e.e ) dV d ea e cr s hi a c at o ni uo gn r ess s pV éa rr ii d ma et èi o tn res Re mcl ea ns ts se- I cn dhc eai d mne g én e tc hme os e d nd ete sss E 2x 0e 2r 3c .i 1c 2e\nTotal Valeur Nette 2.583 2.583 Autres\nprovisions 4.346 309 -1.886 2.769\npour impôts\n1.7 PRINCIPALES METHODES D’EVALUATION Total\nProvisions 4.346 309 -1.886 2.769\n1.7.1 Immobilisations incorporelles pour risques\nLa société ne détient pas d’immobilisations incorporelles. P poro uv ri s ci ho an rs g es 5 5\nAutres\n1.7.2 Immobilisations corporelles p pr oo uv ri s ri io sn qus es 1.079 1.079\nLa société ne détient pas d’immobilisations corporelles. et charges\nTotal\nProvisions 1.079 5 1.084\n1.7.3 Immeubles de placement pour charges\nLes immeubles de placement détenus correspondent à des bâtiments ayant fait l’objet d’un\ncontrat de location pour en retirer des loyers.\nDépréciation de l’actif circulant en KMAD\nLes immeubles de placement sont évalués à leur juste valeur. La périodicité de réévaluation de\nl L ea a x pj u ju es s rt te t e e v sva ta le il neu dur r é e d ps e et s na din m an nmu te e el ul te b d. le iss p d oe se p dla ’c ue nm e e qn ut a e lis fit c d até iote nr m prin oé fee s sp ia or n u nn e le lex p pe er rt t id nea nn ts e l e e td ro em coa nin ne u. e C le ut i E 2x 0e 2r 2c .i 1c 2e lD 'eo xta edt rei co in ces uR ( te p ilp r isr o éi vs e.e ) uR ( te p in lp r io sr o n éi vs e.e ) dV d ea e cr s hi a c at o ni uo gn r ess s pV éa rr ii d ma et èi o tn res Re mcl ea ns ts se- c dhI en a mc ni gdd éeee thmsn o c e de n es t s s E 2x 0e 2r 3c .i 1c 2e\npermettant d’apprécier les immeubles en question. Provisions pour\nLes immeubles de placement ne font pas l’objet de restrictions quant à leur utilisation. Il n’existe dép. des cptes -1.481 -2.091 1.465 -2.107\npas d’obligations contractuelles sur ces biens. clients ratt.\nTotal Dép. s/\nLes immeubles de placement du groupe génèrent un loyer constaté en chiffre d’affaires. c cr lié ea nn tsc e es t cptes. -1.481 -2.091 1.465 -2.107\nLe montant cumulé des plus-values constatées sur les immeubles de placement s’élève à KMAD rattachés\n80 801 au 31 Décembre 2023 :\nTotal -\nDépréciation de -1.481 -2.091 1.465 -2.107\nImmeubles de placement en KMAD l'actif circulant\nE 2x 0e 2r 2c .i 1c 2e Ac tiq ou ni ssi- C e ae ut s m rs eii so ben uss lD 'eo xta edt rei co in ces PVa ér ri ida meti o tn res dV ea r l ai aa et jui uo s rn tes Re mcl ea ns ts se- I c dn h ec a i mnde g én e thmce oe dd n ee t sss E 2x 0e 2r 3c .i 1c 2e 1.7.10 Coût d’emprunt\nt è v l\nLes coûts d’emprunt liés à l’acquisition ou à la production d’un actif sont intégrés au coût de cet actif.\nI pm lam cee mub el ne ts de 822.625 112.065 -324 934.366 Pour l’exercice 2023, les coûts d’emprunt ne sont pas intégrés dans le coût de l’actif. Le groupe\nAmortisse-ments estime que le montant correspondant n’est pas significatif.\ndes immeubles\nde placement\nTotal Valeur 1.8 PASSIFS EVENTUELS\nNette Immeubles 822.625 112.065 -324 934.366 Les sociétés du Groupe pourraient faire l’objet de contrôles fiscaux pour les exercices non prescrits.\nde placement"
            }
        ],
        [
            {
                "": "Unités",
                "Clôture": "Taux\nd’intérêt",
                "null": "Méthode\nde conso",
                "Ouverture": "Taux\nd’intérêt"
            },
            {
                "": "",
                "Clôture": "100,00 %",
                "null": "",
                "Ouverture": "100,00 %"
            },
            {
                "": "",
                "Clôture": "100,00 %",
                "null": "",
                "Ouverture": "100,00 %"
            },
            {
                "": "",
                "Clôture": "100,00 %",
                "null": "",
                "Ouverture": "100,00 %"
            },
            {
                "": "",
                "Clôture": "100,00 %",
                "null": "",
                "Ouverture": "100,00 %"
            }
        ],
        [
            {
                "": "",
                "Exercice\n2022.12": "",
                "Augmentation": "",
                "Remb.": "",
                "Variations des\ncours de change": "",
                "Variations de\nPérimètre": "",
                "Autres": "",
                "Exercice\n2023.12": ""
            },
            {
                "": "",
                "Exercice\n2022.12": "",
                "Augmentation": "120.000",
                "Remb.": "",
                "Variations des\ncours de change": "",
                "Variations de\nPérimètre": "",
                "Autres": "",
                "Exercice\n2023.12": "120.000"
            },
            {
                "": "",
                "Exercice\n2022.12": "8.383",
                "Augmentation": "5.099",
                "Remb.": "-188",
                "Variations des\ncours de change": "",
                "Variations de\nPérimètre": "",
                "Autres": "",
                "Exercice\n2023.12": "13.293"
            },
            {
                "": "",
                "Exercice\n2022.12": "8.383",
                "Augmentation": "125.099",
                "Remb.": "-188",
                "Variations des\ncours de change": "",
                "Variations de\nPérimètre": "",
                "Autres": "",
                "Exercice\n2023.12": "133.293"
            },
            {
                "": "",
                "Exercice\n2022.12": "",
                "Augmentation": "150",
                "Remb.": "",
                "Variations des\ncours de change": "",
                "Variations de\nPérimètre": "",
                "Autres": "",
                "Exercice\n2023.12": "150"
            },
            {
                "": "",
                "Exercice\n2022.12": "",
                "Augmentation": "",
                "Remb.": "",
                "Variations des\ncours de change": "",
                "Variations de\nPérimètre": "",
                "Autres": "",
                "Exercice\n2023.12": ""
            },
            {
                "": "",
                "Exercice\n2022.12": "",
                "Augmentation": "150",
                "Remb.": "",
                "Variations des\ncours de change": "",
                "Variations de\nPérimètre": "",
                "Autres": "",
                "Exercice\n2023.12": "150"
            },
            {
                "": "",
                "Exercice\n2022.12": "",
                "Augmentation": "",
                "Remb.": "",
                "Variations des\ncours de change": "",
                "Variations de\nPérimètre": "",
                "Autres": "",
                "Exercice\n2023.12": ""
            },
            {
                "": "Emprunts et dettes\nfinancières",
                "Exercice\n2022.12": "8.383",
                "Augmentation": "125.249",
                "Remb.": "-188",
                "Variations des\ncours de change": "",
                "Variations de\nPérimètre": "",
                "Autres": "",
                "Exercice\n2023.12": "133.443"
            }
        ],
        [
            {
                "Tableau de variatin des écarts d’acquisition/Goodwill en KMAD": "",
                "null": "Exercice\n2023.12"
            },
            {
                "Tableau de variatin des écarts d’acquisition/Goodwill en KMAD": "",
                "null": "2.583"
            },
            {
                "Tableau de variatin des écarts d’acquisition/Goodwill en KMAD": "",
                "null": ""
            },
            {
                "Tableau de variatin des écarts d’acquisition/Goodwill en KMAD": "Total Valeur Nette",
                "null": "2.583"
            }
        ],
        [
            {
                "": "",
                "Exercice\n2022.12": "4.346",
                "Dotations\nde\nl'exercice": "309",
                "Reprise\n(prov.\nutilisée)": "-1.886",
                "Reprise\n(prov.\nnon\nutilisée)": "",
                "Variations\ndes cours\nde changes": "",
                "Variations\nde\npérimètre": "",
                "Reclasse-\nments": "",
                "Incidences des\nchangements\nde méthodes": "",
                "Exercice\n2023.12": "2.769"
            },
            {
                "": "Total\nProvisions\npour risques",
                "Exercice\n2022.12": "4.346",
                "Dotations\nde\nl'exercice": "309",
                "Reprise\n(prov.\nutilisée)": "-1.886",
                "Reprise\n(prov.\nnon\nutilisée)": "",
                "Variations\ndes cours\nde changes": "",
                "Variations\nde\npérimètre": "",
                "Reclasse-\nments": "",
                "Incidences des\nchangements\nde méthodes": "",
                "Exercice\n2023.12": "2.769"
            },
            {
                "": "",
                "Exercice\n2022.12": "",
                "Dotations\nde\nl'exercice": "5",
                "Reprise\n(prov.\nutilisée)": "",
                "Reprise\n(prov.\nnon\nutilisée)": "",
                "Variations\ndes cours\nde changes": "",
                "Variations\nde\npérimètre": "",
                "Reclasse-\nments": "",
                "Incidences des\nchangements\nde méthodes": "",
                "Exercice\n2023.12": "5"
            },
            {
                "": "",
                "Exercice\n2022.12": "1.079",
                "Dotations\nde\nl'exercice": "",
                "Reprise\n(prov.\nutilisée)": "",
                "Reprise\n(prov.\nnon\nutilisée)": "",
                "Variations\ndes cours\nde changes": "",
                "Variations\nde\npérimètre": "",
                "Reclasse-\nments": "",
                "Incidences des\nchangements\nde méthodes": "",
                "Exercice\n2023.12": "1.079"
            },
            {
                "": "Total\nProvisions\npour charges",
                "Exercice\n2022.12": "1.079",
                "Dotations\nde\nl'exercice": "5",
                "Reprise\n(prov.\nutilisée)": "",
                "Reprise\n(prov.\nnon\nutilisée)": "",
                "Variations\ndes cours\nde changes": "",
                "Variations\nde\npérimètre": "",
                "Reclasse-\nments": "",
                "Incidences des\nchangements\nde méthodes": "",
                "Exercice\n2023.12": "1.084"
            }
        ],
        [
            {
                "": "",
                "Exercice\n2022.12": "-1.481",
                "Dotations\nde\nl'exercice": "-2.091",
                "Reprise\n(prov.\nutilisée)": "1.465",
                "Reprise\n(prov.\nnon\nutilisée)": "",
                "Variations\ndes cours\nde changes": "",
                "Variations\nde\npérimètre": "",
                "Reclasse-\nments": "",
                "Incidences\ndes\nchangements\nde méthodes": "",
                "Exercice\n2023.12": "-2.107"
            },
            {
                "": "Total Dép. s/\ncréances\nclients et cptes.\nrattachés",
                "Exercice\n2022.12": "-1.481",
                "Dotations\nde\nl'exercice": "-2.091",
                "Reprise\n(prov.\nutilisée)": "1.465",
                "Reprise\n(prov.\nnon\nutilisée)": "",
                "Variations\ndes cours\nde changes": "",
                "Variations\nde\npérimètre": "",
                "Reclasse-\nments": "",
                "Incidences\ndes\nchangements\nde méthodes": "",
                "Exercice\n2023.12": "-2.107"
            },
            {
                "": "Total -\nDépréciation de\nl'actif circulant",
                "Exercice\n2022.12": "-1.481",
                "Dotations\nde\nl'exercice": "-2.091",
                "Reprise\n(prov.\nutilisée)": "1.465",
                "Reprise\n(prov.\nnon\nutilisée)": "",
                "Variations\ndes cours\nde changes": "",
                "Variations\nde\npérimètre": "",
                "Reclasse-\nments": "",
                "Incidences\ndes\nchangements\nde méthodes": "",
                "Exercice\n2023.12": "-2.107"
            }
        ],
        [
            {
                "": "",
                "Exercice\n2022.12": "822.625",
                "Acquisi-\ntions": "112.065",
                "Cessions\net mises\nau rebut": "",
                "Dotations\nde\nl'exercice": "",
                "Variations\nde\nPérimètre": "",
                "Variations\nde la juste\nvaleur": "-324",
                "Reclasse-\nments": "",
                "Incidence des\nchangements\nde méthodes": "",
                "Exercice\n2023.12": "934.366"
            },
            {
                "": "",
                "Exercice\n2022.12": "",
                "Acquisi-\ntions": "",
                "Cessions\net mises\nau rebut": "",
                "Dotations\nde\nl'exercice": "",
                "Variations\nde\nPérimètre": "",
                "Variations\nde la juste\nvaleur": "",
                "Reclasse-\nments": "",
                "Incidence des\nchangements\nde méthodes": "",
                "Exercice\n2023.12": ""
            },
            {
                "": "Total Valeur\nNette Immeubles\nde placement",
                "Exercice\n2022.12": "822.625",
                "Acquisi-\ntions": "112.065",
                "Cessions\net mises\nau rebut": "",
                "Dotations\nde\nl'exercice": "",
                "Variations\nde\nPérimètre": "",
                "Variations\nde la juste\nvaleur": "-324",
                "Reclasse-\nments": "",
                "Incidence des\nchangements\nde méthodes": "",
                "Exercice\n2023.12": "934.366"
            }
        ],
        [
            {
                "COMPTES CONSOLIDÉS EN NORMES IFRS\nAU 31 DÉCEMBRE 2023": "1.9 JUSTE VALEUR\n3. ENGAGEMENTS HORS BILAN\nLe groupe ne détient pas de passifs évalués à la juste valeur.\nLes actifs évalués à la juste valeur sont composés de :\n3.1 TABLEAU DES SURETES REELLES DONNEES OU REÇUES\n• Les immeubles de placement : la juste valeur de ces actifs est fondée sur des données non\no db os me ar iv na eb . l Ces e. t L ea x pju es rt te e v sa t l ie nu dr é d pe es n dim anm t e eu t b dl ie ss p d ose e p dla ’uc ne em qe un at le ifis ct ad té iot ne r pm roin fé ee ss p ioa nr nu en l lee x pp ee rr tit n d ea nn tes ele t Tiers créditeurs ou tiers débiteurs sc ûo ruM ev teo érn t (t K a p Mn at Ar Dla ) Nature dD ’ia nt se c e rit p l tie iou n Objet n de at ttV eea dsle û eu r cer l t ôc é to udm ro ep n t (na Kéb Mele A à D l )a\nreconnue, et dispose des qualifications professionnelles lui permettant d’apprécier la valeur des Sûretés données\nimmeubles en question. Il se base sur sa connaissance du marché ainsi que sur les informations Hypothèque de premier rang sur le TF\nqu’il peut récupérer sur des transactions similaires ; N le° c8 a9 d5 r7 e/ 7 d1 ’u a nu c p rr éo df ii tt àd e lo C nF gG te B rmAN eK d ed ans 100000 Hypothèque 18/09/23 E bam np cr au irn et Non définie\n• Les valeurs mobilières de placement et autres placements, sont évaluées à la juste valeur MAD 90.000.000.\npar le biais du compte de résultat. La juste valeur de ces actifs est basée sur des données Nantissement de 700000 actions\nobservables : marché actif par exemple ou assimilé… ; d c Aaé Tpt Re it In Uau l e ss o cp uia a pr l dl o’ ee m tl a dp esr o u Ccn Fiét Ge téu r A d nMa sLn lAs K l ce 90 000 000 Nantissement 18/09/23 E bam np cr au irn et Non définie\nM a r fi d a e a dre\n• Les actifs financiers non courants comprennent des instruments de capitaux propres évalués d’un crédit de MAD 90.000.000.\nà la juste valeur par les capitaux propres. Les données concernant la juste valeur de ces actifs Sûretés reçues NEANT\nsont fondées sur des données non observables. Par conséquent, ces actifs sont évalués au\ncoût d’achat, sauf en cas de constatation d’opération sur les capitaux propres de ces entités 3.2 AUTRES ENGAGEMENTS FINANCIERS DONNES OU REÇUS\n(augmentation de capital, cession d’action dans des proportions significatives…). Dans ce cas, la\njuste valeur correspond à la valorisation utilisée pour ces opérations. Engagements donnés EN KMAD Montants exercice Montants exercice précédent\nNEANT\nL’impact des évaluations sur le résultat (en KMAD avant impôts différés) est détaillé comme suit :\nCatégorie Méthode de valorisation l’oIm uvp ea rc tt u à r e Imp pa éc rt io s du er la Im cp lôa tc ut rà e la E Can ug tioa ng pe em rsoe nn nt es lle r ee tç su os lid E aiN re K deM MA . D YO UNATHAN HARROCH au profit de GYMNAS AVENUE pour toute somme relative M exo en rt ca in ct es Mon pta rn ét cs é de exe nr tcice\nau reliquat de créance telle que définie dans le protocole d’accord signé le 29 décembre 2021 dont elle sera redevable en\nImmeubles de placement Evaluation par un expert indépendant 81.125 -324 80.801 principal outre intérêts et frais à l’égard de AMLAK ATRIUM. Renonciation expresse au bénéfice de division et de discussion Non défini Non défini\nVMP et autres placements Prix observable sur un marché actif 457 -45 412 en cas d’exécution forcée pour payer à première demande AMLAK ATRIUM.\nEngagement de GYMNAS AVENUE à remettre à AMLAK ATRIUM, au plus tard le 31 décembre 2022, une garantie bancaire à\nAucun impact significatif n’a été observé sur ces actifs du fait de la réalisation des placements première demande consentie par une banque marocaine, d’un montant de MAD 1.521.180 correspondant à neuf mois de\nloyers hors taxes et hors charges au profit de AMLAK ATRIUM en vue de garantir toute somme qui pourrait être due au titre de\nle dernier jour de l’exercice. l’exécution et/ou de la résiliation du bail, de ses avenants et du protocole et ce dans la limite d’un montant maximum de MAD 1 521 180 1 521 180\n1.521.180. Engagement de GYMNAS AVENUE de libérer les locaux au plus tard le 31 janvier 2023 en cas de non présentation\nde la garantie ci-dessus au delà de la date du 31 décembre 2022.\n1.10 IMPOTS DIFFERES E dn e g laa g de am tee dn et d rée c l ea p B tia on nq pu ae r C lar é Bd ait n d qu u eM da er o lac dd ee m pr ao nc dé ed e cor ra ru e sv pir oe nm dae nn tt e d . e (Asd Mit Le As K s Ao Tm Rm IUe Ms )dans un délai de 15 jours à compter Non défini Non défini\nLes impôts différés actifs proviennent des différences temporaires liées aux retraitements sur les Caution personnelle et solidaire de M. YOUNATHAN HARROCH au profit de GYMNAS AVENUE pour toute somme relative\ncomptes consolidés et des différences temporelles déductibles entre les valeurs comptables et a eu n r pe rl ii nq cu ipa at ld oe u c trr eé a inn tc ée r êt te sl le e tq fu rae i sd é àfi ln ’éie g ad ra dn s d ele A p Mro Lt Ao Kc o Cle O Nd’ Ta Ec Mco Pr Od . s Rig en né o nle c ia2 t9 io nd é ec xe pm reb sr se e 2 a0 u2 1 b éd no én fit c e el l de es e dr iva i sr ie od ne eva t b dl ee Non défini Non défini\nfiscales des actifs et passifs. discussion en cas d’exécution forcée pour payer à première demande AMLAK CONTEMPO.\nLe groupe n’a pas de déficits fiscaux. Engagement de GYMNAS AVENUE à remettre à AMLAK CONTEMPO, au plus tard le 31 décembre 2022, une garantie bancaire\nLa politique de distribution des dividendes n’a pas d’impact sur l’impôt sur le résultat du groupe. à première demande consentie par une banque marocaine, d’un montant de MAD 1.194.750 correspondant à neuf mois de\nloyers hors taxes et hors charges au profit de AMLAK CONTEMPO en vue de garantir toute somme qui pourrait être due au\ntitre de l’exécution et/ou de la résiliation du bail, de ses avenants et du protocole et ce dans la limite d’un montant maximum Non défini Non défini\nImpôts différés en KMAD de MAD 1.194.750,25. Engagement de GYMNAS AVENUE de libérer les locaux au plus tard le 31 janvier 2023 en cas de non\nprésentation de la garantie ci-dessus au delà de la date du 31 décembre 2022\nE 2x 0e 2r 2c .i 1c 2e In réci sd ue ln tac te cV ouar ri sa dti eo n cs h ad ne gs e Va pr éi ra it mio èn ts r ede Autres E 2x 0e 2r 3c .i 1c 2e E dn e g laa g de am tee dn et d rée c l ea p B tia on nq pu ae r C lar é Bd ait n d qu u eM da er o lac dd ee m pr ao nc dé ed e cr o ra ru e pv sir oe nm dae nn tt e d . e Ts (Ad Mite Ls A s Ko m COm Ne Ts E d Ma Pn Os )un délai de 15 jours à compter Non défini Non défini\nImpôts différés - actif\nImpôts différés - passif 51.242 3.010 90 54.342 RÉSUMÉ DU RAPPORT GÉNÉRAL DES COMMISSAIRES AUX\nSolde net d'impôt différé -51.242 -3.010 -90 -54.342 COMPTES SUR LES COMPTES CONSOLIDÉS\nE 2x 0e 2r 2c .i 1c 2e In réci sd ue ln tac te cV ouar ri sa dti eo n cs h ad ne gs e Va pr éi ra it mio èn ts r ede Autres E 2x 0e 2r 3c .i 1c 2e\nID / différences temporaires 2.847 -464 2.383\nID / Autres retraitements -5 -5\nID sur écart d'évaluation 100% -21.373 -155 591 -20.937 7, Boulevard Driss Slaoui 4, Place Maréchal\nCasablanca Casablanca\nID/ autres retraitements IFRS (*) -32.672 33 -694 -33.333\nAux actionnaires de la société\nID / Annulation frais d'établissement 90 -2.436 -2.346 IMMORENTE INVEST S.A.\n5/7 – Rue Ibnou Toufail Palmiers\nID/ Retrait. juste valeur instrum. financiers -129 11 13 -105 Casablanca\nRapport des commissaires aux comptes sur les états financiers consolidés\nSolde net d'impôt différé par Nature -51.242 -3.010 -90 -54.342 Exercice du 1er janvier au 31 décembre 2023\nOpinion\nNous avons effectué l’audit des états financiers consolidés de la société IMMORENTE INVEST S.A et de ses filiales (le « Groupe »), qui comprennent\nl’état consolidé de la situation financière au 31 décembre 2023, ainsi que l’état consolidé du résultat global, l’état consolidé des variations des\nImpôts sur les bénéfices / ventilation impôt exigible/différé en KMAD capitaux propres et le tableau consolidé des flux de trésorerie pour l’exercice clos à cette date, ainsi que les notes annexes, y compris un résumé\ndes principales méthodes comptables. Ces états financiers consolidés font ressortir un montant de capitaux propres consolidés de KMAD 827.016\nExercice 2023.12 Exercice 2022.12 d No on ut s u cn e rb tié fin oné sfi c qe u en e let sc o én tas to sl i fd iné a d ne ci eK rsM cA oD n s4 o2 li. d7 é8 s3 c. ités au premier paragraphe ci-dessus, sont réguliers et sincères et donnent dans tous leurs aspects\nImpôt différé - 3 100 - 175 significatifs, une image fidèle de la situation financière consolidée du groupe au 31 décembre 2023, ainsi que de sa performance financière consolidée et\nde ses flux de trésorerie consolidés pour l’exercice clos à cette date, conformément aux Normes Internationales d’Information Financière (IFRS).\nImpôts sur les bénéfices -3.199 -3.565 Fondement de l’opinion\nImpôts sur les bénéfices - 6 299 - 3 740 N plo uu s s a mav po len ms e ef nfe t c dt éu cé r in teo st r de a a nu sd lait s se el co tn io nle «s RN eo srm poe ns s d ae b il la ité P sr o df ee ls ’as uio dn it ea uu r M à a l’r éo gc a. rL de ds e r e l’as up do in t s da eb si l éit té as t sq fu ini an no cu is e ri sn c co om nsb oe lin dt é e sn » v de urt u p rd ée s ec ne ts r an po prm ore t.s N s oo un st\nsommes indépendants du groupe conformément aux règles de déontologie qui s’appliquent à l’audit des états financiers consolidés au Maroc et nous\nnous sommes acquittés des autres responsabilités déontologiques qui nous incombent selon ces règles. Nous estimons que les éléments probants\nque nous avons obtenus sont suffisants et appropriés pour fonder notre opinion d’audit.\n1.11 AVANTAGE AU PERSONNEL\nQuestions clés de l’audit\nLe groupe ne dispose pas de personnel. L coe ns sq ou lie ds ét sio dn es c lalé ps é d re io l d’a eu cd oit n s so idn ét rle és e .q Cue es st i qo un es s q tiu oi n, ss e olo nn t én to ét r te ra ju itég ee sm de an nt sp r lo ef e cs os ni to en xn tee l, d o en nt oé tt ré e le as u dp il tu ds e im s p éo tar tt sa n fit ne as n d ca ien rs s l’ ca ou nd sit o d lide és s é t pa rt is s f din aa nn sc li ee urs r\nensemble et aux fins de la formation de notre opinion sur ceux-ci, et nous n’exprimons pas une opinion distincte sur ces questions.\nRisque identifié Notre réponse\n1.12 PRODUITS DES ACTIVITES ORDINAIRES Evaluation des immeubles de placement Nos contrôles consistent à :\nAu 31 décembre 2023, la juste valeur des immeubles de placement du groupe - Prise de connaissance du processus d’évaluation des\nLes produits des activités ordinaires sont composés des catégories suivantes : s’élève à 934,36 MMAD. Ces immeubles de placement représentent 89,81% du immeubles de placement mis en place par le groupe ;\ntotal actif consolidé du groupe. - Appréciation de la compétence et de l’indépendance de\n• Loyer ; La détermination de la juste valeur s’appuie sur des évaluations externes l’évaluateur externe mandaté par le groupe\n• Refacturation des Charges locatives. i ln ed s é mpe én thd oa dn ete ss e. tC he ys p oé tv ha èl su ea sti o un ts ili sf éo en st a ep t p tie el n na eu n j tu cg oe mm pe tn et pp rr io nf ce ipss ai lo en mn ee nl t p do eu sr - d eA p vp ar lé oc rii sa ati to ion n d re e tl ea n p ue er sm pa an re n l’éce va e lut ad te e ula r ep xe tr eti rn ne en , c le e d pe és ri mm èé tt rh eo d de es s\ncaractéristiques intrinsèques des actifs, en l’occurrence, les états locatifs, actifs expertisés ainsi que les hypothèses de valorisation retenues ;\ndonnées commerciales des loyers, taux de recouvrement des loyers et taux de - Rapprochement des valeurs comptabilisées à la juste valeur\n1.13 ACTIFS NON COURANTS DETENUS EN VUE DE LA VENTE ET ACTIVITES r ae inn sd ie qm ue en dt. eC s e t eta rmux e sd e d er se n cd oe nm trae tn st dtie en bt ac io l.mpte des caractéristiques de l’actif a - v De ic s cle us s sd ioo nn n aé ve es c re les s mo art na an gt ed mu era np t p so ur rt d lee cl’ ae rx ap ce tèrt r ein d raé ip se on nd na an bt l e;\nDESTINEES A ETRE ABANDONNEES L coe ûs t i jm usm qe uu ’àb le les u rd e a chp èla vc ee mm ee nn tt . Le en s c io mu mrs e ud be l esc o dn est r pu lc at cio en m eso nn t t ené va colu ué rs s da eu d de és v elh oy pp po eth mès ee ns t retenues en liaison avec les projets en\nAu 31 Décembre 2023, le Groupe ne dispose pas d’activités destinées à être abandonnées. c Lo ’én vs at lr uu ac tt ii oo nn ds eo sn t imév ma elu ué bs le sa u d ec oû pt la cju es mq eu n’à t , le yu r c oa mch pè risv em lese nt im. meubles de - a cqTe us ist is ti ons su bs at ua n tt ii tf rs e d de e s dé at ca ti il fs s ep na r cé oc uh rsa n vti allo lon rn isa ég se as uu r c ol ûe ts .\nplacement en cours de construction, constitue un point clé de l’audit en raison - Examen de la conformité de la méthodologie appliquée par le\ndu niveau de jugement requis par l’expert indépendant pour ces évaluations et groupe aux normes comptables en vigueur et de la pertinence de\nde l’importance de ce poste dans l’état de la situation financière consolidée et l’information présentée dans les comptes consolidés.\nl’état du résultat global consolidé.\n2. DETAIL DES ETATS FINANCIERS Responsabilités de la direction et des responsables de la gouvernance à l’égard des états financiers consolidés\nLa direction est responsable de la préparation et de la présentation fidèle des états financiers conformément aux Normes Internationale d’Information\nFinancière (IFRS), ainsi que du contrôle interne qu’elle considère comme nécessaire pour permettre la préparation d’états financiers consolidés\nexempts d’anomalies significatives, que celles-ci résultent de fraudes ou d’erreurs.\n2.1 TABLEAU DES FLUX DE TRESORERIE Lors de la préparation des états financiers consolidés, c’est à la direction qu’il incombe d’évaluer la capacité du groupe à poursuivre son exploitation, de\ncommuniquer, le cas échéant, les questions se rapportant à la continuité de l’exploitation et d’appliquer le principe comptable de continuité d’exploitation,\n• Les montants correspondants à de la trésorerie et équivalents de trésorerie sont disponibles et s Il a inu cf osi m la b ed ir ae uc xti o ren s a p ol’i nn ste an bt lio en s dde e l li aq u gi od ue vr ele r ng aro nu cp ee d o eu s d ue rv c ee ils les re lr e s po rn o ca ect siv si uté s o du ’i ns fi o a ru mc au tn ioe n a fu intr ae n s co ièlu retio dn u r é ga rolis ut pe e n .e s’offre à elle.\nn’ont pas fait l’objet d’aucune restriction. Responsabilités de l’auditeur à l’égard de l’audit des états synthèse consolidés\n• La société a payé une correction de prix pour les participations AMLAK ATRIUM et AMLAK Nos objectifs sont d’obtenir l’assurance raisonnable que les états financiers consolidés pris dans leur ensemble sont exempts d’anomalies\nsignificatives, que celles-ci résultent de fraudes ou d’erreurs et de délivrer un rapport de l’auditeur contenant notre opinion. L’assurance raisonnable\nCONTEMPO. correspond à un niveau élevé d’assurance, qui ne garantit toutefois pas qu’un audit réalisé conformément aux normes de la profession au Maroc\npermettra toujours de détecter toute anomalie significative qui pourrait exister. Les anomalies peuvent résulter de fraudes ou d’erreurs et elles sont\nconsidérées comme significatives lorsqu’il est raisonnable de s’attendre à ce que, individuellement ou collectivement, elles puissent influer sur les\ndécisions économiques que les utilisateurs des états financiers consolidés prennent en se fondant sur ceux-ci.\n2.2 ACTIFS FINANCIERS Dans le cadre d’un audit réalisé conformément aux normes de la profession au Maroc, nous exerçons notre jugement professionnel et faisons\npreuve d’esprit critique tout au long de cet audit. En outre :\nLes actifs financiers sont composés de 2 catégories : ▪ fr an uo du es sid oe un t dif ’i eo rn res ue rt s é , v ca ol nu co en vs o l ne ss eri ts mqu ee tts o nq su e e nle s œ é ut va rt es f din ea sn pc ri oe crs é dc uo rn es so l did ’aé us d c ito em np ro ér pte on nt s d ee às ca en so m risa qli ue es s s , ig en t i rf éic ua nti iv se sos, n q s u de e c se éll le és m-c ei n r té ss pu rlt oe bn at nd te s\n• Dépôts, cautionnements, créances et prêts financiers dont les bénéficiaires sont le personnel s qu uf efi s ca en luts i de ’ut na ep p ar no op mrié as li ep o siu gr n f io ficn ad te ivr en ro étr se u lo tap nin t i do ’n u. n L ee e r ri rs eq uu r,e c d ae r ln ao frn a- ud dé ete pct eio un t imd’u pn liqe u a en r o lam ca oli le lu ss ii og nn ,if i lc aa ft aiv lse if ir cé as tu iolt na ,n let sd ’ ou mne is f sra iou nd se v e os lot np tl au is re é sl ,e lv eé s\nou d’autres tiers. Ces éléments sont évalués au coût amorti. Ces actifs sont considérés comme fausses déclarations ou le contournement du contrôle interne ;\n• nous acquérons une compréhension des éléments du contrôle interne pertinents pour l’audit afin de concevoir des procédures d’audit\nétant non courants si leur échéance dépasse l’exercice suivant la date de clôture. Le montant appropriées aux circonstances, et non dans le but d’exprimer une opinion sur l’efficacité du contrôle interne du groupe ;\nde ces actifs s’élève à KMAD 5 ; • la n do iu res c a tip op nr , é dc eio mns ê mle e c a qr ua ec t dè ere s ia np fop rr mop ar ti ié o nd se s y m affé ét rh eo nd te es s c foo um rnp it ea sb ple as r r ce ete ttn eu de es r ne it è l re e c ;a ractère raisonnable des estimations comptables faites par\n• nous tirons une conclusion quant au caractère approprié de l’utilisation par la direction du principe comptable de continuité d’exploitation et,\n• Actifs financiers évalués à la juste valeur par le biais du compte de résultat. Ces actifs sont selon les éléments probants obtenus, quant à l’existence ou non d’une incertitude significative liée à des événements ou situations susceptibles\ncomposés de placement de trésorerie (OPCVM) ou titres cotés détenus pour des fins de d ne o uje st e sr o u mn m d eo su t te e nim up s o dr ’t aa tn tit r esu r r l ’ala t tc ea np tia oc ni té d ed su lg er co teu up re s à d p eo nu ors tru eiv rr ae p s po on r te sx up rl o leita st i io nn fo. rS mi an to iou ns s c o fon uc rl nu io en ss d à a l n’e sx li est se n éc tae t sd ’ fu inn ae n i cn ic ee rsrt i atu ud e s us ji eg tn difi ec a ct eiv te te,\nplacement de trésorerie. Le montant de ces actifs s’élève à KMAD 7.588. L’évolution de ces incertitude ou, si ces informations ne sont pas adéquates, d’exprimer une opinion modifiée. Nos conclusions s’appuient sur les éléments probants\nobtenus jusqu’à la date de notre rapport. Des événements ou situations futurs pourraient par ailleurs amener le groupe à cesser son exploitation ;\nactifs est détaillée au niveau de la note 3.9 ; • nous évaluons la présentation d’ensemble, la structure et le contenu des états financiers consolidés, y compris les informations fournies dans\nles notes, et apprécions si les états financiers consolidés représentent les opérations et événements sous-jacents d’une manière propre à\n• Des instruments de capitaux propres évalués à la juste valeur par le biais des autres éléments donner une image fidèle.\n• nous obtenons des éléments probants suffisants et appropriés concernant les informations financières des entités et activités du groupe pour\ndu résultat global. Le montant de ces actifs s’élève à KMAD 50.000. L’évolution de ces actifs est exprimer une opinion sur les états financiers consolidés. Nous sommes responsables de la direction, de la supervision et de la réalisation de\ndétaillée au niveau de la note 3.9. l’audit du groupe. Nous assumons l’entière responsabilité de l’opinion d’audit.\nNous communiquons aux responsables de la gouvernance notamment l’étendue et le calendrier prévus des travaux d’audit et nos constatations\nAu cours de l’exercice, le Groupe n’a pas procédé à des reclassements d’actifs financiers. importantes, y compris toute déficience importante du contrôle interne que nous aurions relevée au cours de notre audit.\nCasablanca, le 26 février 2024\nLes Commissaires aux Comptes\n2.3 RESULTAT PAR ACTION\nLe résultat par action est calculé par référence au nombre moyen d’actions émises à la date de\nclôture. Aucun effet dilutif n’est observé au cours des 2 derniers exercices.\nLe résultat utilisé pour le calcul du résultat par action correspond au résultat net part du groupe."
            }
        ],
        [
            {
                "Tiers créditeurs ou tiers débiteurs": "",
                "Montant\ncouvert par la\nsûreté (KMAD)": "",
                "Nature": "",
                "Date et lieu\nd’inscription": "",
                "Objet": "",
                "Valeur comptable\nnette sûreté donnée à la\ndate de clôture (KMAD)": ""
            },
            {
                "Tiers créditeurs ou tiers débiteurs": "",
                "Montant\ncouvert par la\nsûreté (KMAD)": "100000",
                "Nature": "Hypothèque",
                "Date et lieu\nd’inscription": "18/09/23",
                "Objet": "Emprunt\nbancaire",
                "Valeur comptable\nnette sûreté donnée à la\ndate de clôture (KMAD)": "Non définie"
            },
            {
                "Tiers créditeurs ou tiers débiteurs": "",
                "Montant\ncouvert par la\nsûreté (KMAD)": "90 000 000",
                "Nature": "Nantissement",
                "Date et lieu\nd’inscription": "18/09/23",
                "Objet": "Emprunt\nbancaire",
                "Valeur comptable\nnette sûreté donnée à la\ndate de clôture (KMAD)": "Non définie"
            },
            {
                "Tiers créditeurs ou tiers débiteurs": "",
                "Montant\ncouvert par la\nsûreté (KMAD)": "NEANT",
                "Nature": "",
                "Date et lieu\nd’inscription": "",
                "Objet": "",
                "Valeur comptable\nnette sûreté donnée à la\ndate de clôture (KMAD)": ""
            }
        ],
        [
            {
                "Engagements donnés EN KMAD": "",
                "Montants exercice": "",
                "Montants exercice précédent": ""
            }
        ],
        [
            {
                "Catégorie": "Immeubles de placement",
                "Méthode de valorisation": "Evaluation par un expert indépendant",
                "Impact à\nl’ouverture": "81.125",
                "Impact sur la\npériode": "-324",
                "Impact à la\nclôture": "80.801"
            },
            {
                "Catégorie": "VMP et autres placements",
                "Méthode de valorisation": "Prix observable sur un marché actif",
                "Impact à\nl’ouverture": "457",
                "Impact sur la\npériode": "-45",
                "Impact à la\nclôture": "412"
            }
        ],
        [
            {
                "Engagements reçus EN KMAD": "",
                "Montants\nexercice": "Non défini",
                "Montants exercice\nprécédent": "Non défini"
            },
            {
                "Engagements reçus EN KMAD": "",
                "Montants\nexercice": "1 521 180",
                "Montants exercice\nprécédent": "1 521 180"
            },
            {
                "Engagements reçus EN KMAD": "",
                "Montants\nexercice": "Non défini",
                "Montants exercice\nprécédent": "Non défini"
            },
            {
                "Engagements reçus EN KMAD": "",
                "Montants\nexercice": "Non défini",
                "Montants exercice\nprécédent": "Non défini"
            },
            {
                "Engagements reçus EN KMAD": "",
                "Montants\nexercice": "Non défini",
                "Montants exercice\nprécédent": "Non défini"
            },
            {
                "Engagements reçus EN KMAD": "",
                "Montants\nexercice": "Non défini",
                "Montants exercice\nprécédent": "Non défini"
            }
        ],
        [
            {
                "": "",
                "Exercice\n2022.12": "",
                "Incidence\nrésultat": "",
                "Variations des\ncours de change": "",
                "Variations de\npérimètre": "",
                "Autres": "",
                "Exercice\n2023.12": ""
            },
            {
                "": "",
                "Exercice\n2022.12": "51.242",
                "Incidence\nrésultat": "3.010",
                "Variations des\ncours de change": "",
                "Variations de\npérimètre": "",
                "Autres": "90",
                "Exercice\n2023.12": "54.342"
            },
            {
                "": "Solde net d'impôt différé",
                "Exercice\n2022.12": "-51.242",
                "Incidence\nrésultat": "-3.010",
                "Variations des\ncours de change": "",
                "Variations de\npérimètre": "",
                "Autres": "-90",
                "Exercice\n2023.12": "-54.342"
            }
        ],
        [
            {
                "RÉSUMÉ DU RAPPORT GÉNÉRAL DES COMMISSAIRES AUX\nCOMPTES SUR LES COMPTES CONSOLIDÉS": "7, Boulevard Driss Slaoui 4, Place Maréchal\nCasablanca Casablanca\nAux actionnaires de la société\nIMMORENTE INVEST S.A.\n5/7 – Rue Ibnou Toufail Palmiers\nCasablanca\nRapport des commissaires aux comptes sur les états financiers consolidés\nExercice du 1er janvier au 31 décembre 2023\nOpinion\nNous avons effectué l’audit des états financiers consolidés de la société IMMORENTE INVEST S.A et de ses filiales (le « Groupe »), qui comprennent\nl’état consolidé de la situation financière au 31 décembre 2023, ainsi que l’état consolidé du résultat global, l’état consolidé des variations des\ncapitaux propres et le tableau consolidé des flux de trésorerie pour l’exercice clos à cette date, ainsi que les notes annexes, y compris un résumé\ndes principales méthodes comptables. Ces états financiers consolidés font ressortir un montant de capitaux propres consolidés de KMAD 827.016\ndont un bénéfice net consolidé de KMAD 42.783.\nNous certifions que les états financiers consolidés cités au premier paragraphe ci-dessus, sont réguliers et sincères et donnent dans tous leurs aspects\nsignificatifs, une image fidèle de la situation financière consolidée du groupe au 31 décembre 2023, ainsi que de sa performance financière consolidée et\nde ses flux de trésorerie consolidés pour l’exercice clos à cette date, conformément aux Normes Internationales d’Information Financière (IFRS).\nFondement de l’opinion\nNous avons effectué notre audit selon les Normes de la Profession au Maroc. Les responsabilités qui nous incombent en vertu de ces normes sont\nplus amplement décrites dans la section « Responsabilités de l’auditeur à l’égard de l’audit des états financiers consolidés » du présent rapport. Nous\nsommes indépendants du groupe conformément aux règles de déontologie qui s’appliquent à l’audit des états financiers consolidés au Maroc et nous\nnous sommes acquittés des autres responsabilités déontologiques qui nous incombent selon ces règles. Nous estimons que les éléments probants\nque nous avons obtenus sont suffisants et appropriés pour fonder notre opinion d’audit.\nQuestions clés de l’audit\nLes questions clés de l’audit sont les questions qui, selon notre jugement professionnel, ont été les plus importantes dans l’audit des états financiers\nconsolidés de la période considérée. Ces questions ont été traitées dans le contexte de notre audit des états financiers consolidés pris dans leur\nensemble et aux fins de la formation de notre opinion sur ceux-ci, et nous n’exprimons pas une opinion distincte sur ces questions.\nRisque identifié Notre réponse\nEvaluation des immeubles de placement Nos contrôles consistent à :\nAu 31 décembre 2023, la juste valeur des immeubles de placement du groupe - Prise de connaissance du processus d’évaluation des\ns’élève à 934,36 MMAD. Ces immeubles de placement représentent 89,81% du immeubles de placement mis en place par le groupe ;\ntotal actif consolidé du groupe. - Appréciation de la compétence et de l’indépendance de\nLa détermination de la juste valeur s’appuie sur des évaluations externes l’évaluateur externe mandaté par le groupe\nindépendantes. Ces évaluations font appel au jugement professionnel pour - Appréciation de la permanence et de la pertinence des méthodes\nles méthodes et hypothèses utilisées et tiennent compte principalement des de valorisation retenues par l’évaluateur externe, le périmètre des\ncaractéristiques intrinsèques des actifs, en l’occurrence, les états locatifs, actifs expertisés ainsi que les hypothèses de valorisation retenues ;\ndonnées commerciales des loyers, taux de recouvrement des loyers et taux de - Rapprochement des valeurs comptabilisées à la juste valeur\nrendement. Ce taux de rendement tient compte des caractéristiques de l’actif avec les données ressortant du rapport de l’expert indépendant ;\nainsi que des termes des contrats de bail. - Discussion avec le management sur le caractère raisonnable\nLes immeubles de placement en cours de construction sont évalués au des hypothèses retenues en liaison avec les projets en\ncoût jusqu’à leur achèvement. Les immeubles de placement en cours de développement\nconstruction sont évalués au coût jusqu’à leur achèvement. - Tests substantifs de détails par échantillonnage sur les\nL’évaluation des immeubles de placement, y compris les immeubles de acquisitions au titre des actifs en cours valorisés au coût.\nplacement en cours de construction, constitue un point clé de l’audit en raison - Examen de la conformité de la méthodologie appliquée par le\ndu niveau de jugement requis par l’expert indépendant pour ces évaluations et groupe aux normes comptables en vigueur et de la pertinence de\nde l’importance de ce poste dans l’état de la situation financière consolidée et l’information présentée dans les comptes consolidés.\nl’état du résultat global consolidé.\nResponsabilités de la direction et des responsables de la gouvernance à l’égard des états financiers consolidés\nLa direction est responsable de la préparation et de la présentation fidèle des états financiers conformément aux Normes Internationale d’Information\nFinancière (IFRS), ainsi que du contrôle interne qu’elle considère comme nécessaire pour permettre la préparation d’états financiers consolidés\nexempts d’anomalies significatives, que celles-ci résultent de fraudes ou d’erreurs.\nLors de la préparation des états financiers consolidés, c’est à la direction qu’il incombe d’évaluer la capacité du groupe à poursuivre son exploitation, de\ncommuniquer, le cas échéant, les questions se rapportant à la continuité de l’exploitation et d’appliquer le principe comptable de continuité d’exploitation,\nsauf si la direction a l’intention de liquider le groupe ou de cesser son activité ou si aucune autre solution réaliste ne s’offre à elle.\nIl incombe aux responsables de la gouvernance de surveiller le processus d’information financière du groupe.\nResponsabilités de l’auditeur à l’égard de l’audit des états synthèse consolidés\nNos objectifs sont d’obtenir l’assurance raisonnable que les états financiers consolidés pris dans leur ensemble sont exempts d’anomalies\nsignificatives, que celles-ci résultent de fraudes ou d’erreurs et de délivrer un rapport de l’auditeur contenant notre opinion. L’assurance raisonnable\ncorrespond à un niveau élevé d’assurance, qui ne garantit toutefois pas qu’un audit réalisé conformément aux normes de la profession au Maroc\npermettra toujours de détecter toute anomalie significative qui pourrait exister. Les anomalies peuvent résulter de fraudes ou d’erreurs et elles sont\nconsidérées comme significatives lorsqu’il est raisonnable de s’attendre à ce que, individuellement ou collectivement, elles puissent influer sur les\ndécisions économiques que les utilisateurs des états financiers consolidés prennent en se fondant sur ceux-ci.\nDans le cadre d’un audit réalisé conformément aux normes de la profession au Maroc, nous exerçons notre jugement professionnel et faisons\npreuve d’esprit critique tout au long de cet audit. En outre :\n▪ nous identifions et évaluons les risques que les états financiers consolidés comportent des anomalies significatives, que celles-ci résultent de\nfraudes ou d’erreurs, concevons et mettons en œuvre des procédures d’audit en réponse à ces risques, et réunissons des éléments probants\nsuffisants et appropriés pour fonder notre opinion. Le risque de non-détection d’une anomalie significative résultant d’une fraude est plus élevé\nque celui d’une anomalie significative résultant d’une erreur, car la fraude peut impliquer la collusion, la falsification, les omissions volontaires, les\nfausses déclarations ou le contournement du contrôle interne ;\n• nous acquérons une compréhension des éléments du contrôle interne pertinents pour l’audit afin de concevoir des procédures d’audit\nappropriées aux circonstances, et non dans le but d’exprimer une opinion sur l’efficacité du contrôle interne du groupe ;\n• nous apprécions le caractère approprié des méthodes comptables retenues et le caractère raisonnable des estimations comptables faites par\nla direction, de même que des informations y afférentes fournies par cette dernière ;\n• nous tirons une conclusion quant au caractère approprié de l’utilisation par la direction du principe comptable de continuité d’exploitation et,\nselon les éléments probants obtenus, quant à l’existence ou non d’une incertitude significative liée à des événements ou situations susceptibles\nde jeter un doute important sur la capacité du groupe à poursuivre son exploitation. Si nous concluons à l’existence d’une incertitude significative,\nnous sommes tenus d’attirer l’attention des lecteurs de notre rapport sur les informations fournies dans les états financiers au sujet de cette\nincertitude ou, si ces informations ne sont pas adéquates, d’exprimer une opinion modifiée. Nos conclusions s’appuient sur les éléments probants\nobtenus jusqu’à la date de notre rapport. Des événements ou situations futurs pourraient par ailleurs amener le groupe à cesser son exploitation ;\n• nous évaluons la présentation d’ensemble, la structure et le contenu des états financiers consolidés, y compris les informations fournies dans\nles notes, et apprécions si les états financiers consolidés représentent les opérations et événements sous-jacents d’une manière propre à\ndonner une image fidèle.\n• nous obtenons des éléments probants suffisants et appropriés concernant les informations financières des entités et activités du groupe pour\nexprimer une opinion sur les états financiers consolidés. Nous sommes responsables de la direction, de la supervision et de la réalisation de\nl’audit du groupe. Nous assumons l’entière responsabilité de l’opinion d’audit.\nNous communiquons aux responsables de la gouvernance notamment l’étendue et le calendrier prévus des travaux d’audit et nos constatations\nimportantes, y compris toute déficience importante du contrôle interne que nous aurions relevée au cours de notre audit.\nCasablanca, le 26 février 2024\nLes Commissaires aux Comptes"
            }
        ],
        [
            {
                "": "",
                "Exercice\n2022.12": "2.847",
                "Incidence\nrésultat": "-464",
                "Variations des\ncours de change": "",
                "Variations de\npérimètre": "",
                "Autres": "",
                "Exercice\n2023.12": "2.383"
            },
            {
                "": "",
                "Exercice\n2022.12": "-5",
                "Incidence\nrésultat": "",
                "Variations des\ncours de change": "",
                "Variations de\npérimètre": "",
                "Autres": "",
                "Exercice\n2023.12": "-5"
            },
            {
                "": "",
                "Exercice\n2022.12": "-21.373",
                "Incidence\nrésultat": "-155",
                "Variations des\ncours de change": "",
                "Variations de\npérimètre": "",
                "Autres": "591",
                "Exercice\n2023.12": "-20.937"
            },
            {
                "": "",
                "Exercice\n2022.12": "-32.672",
                "Incidence\nrésultat": "33",
                "Variations des\ncours de change": "",
                "Variations de\npérimètre": "",
                "Autres": "-694",
                "Exercice\n2023.12": "-33.333"
            },
            {
                "": "",
                "Exercice\n2022.12": "90",
                "Incidence\nrésultat": "-2.436",
                "Variations des\ncours de change": "",
                "Variations de\npérimètre": "",
                "Autres": "",
                "Exercice\n2023.12": "-2.346"
            },
            {
                "": "",
                "Exercice\n2022.12": "-129",
                "Incidence\nrésultat": "11",
                "Variations des\ncours de change": "",
                "Variations de\npérimètre": "",
                "Autres": "13",
                "Exercice\n2023.12": "-105"
            },
            {
                "": "Solde net d'impôt différé par Nature",
                "Exercice\n2022.12": "-51.242",
                "Incidence\nrésultat": "-3.010",
                "Variations des\ncours de change": "",
                "Variations de\npérimètre": "",
                "Autres": "-90",
                "Exercice\n2023.12": "-54.342"
            }
        ],
        [
            {
                "": "",
                "Exercice 2023.12": "- 3 100",
                "Exercice 2022.12": "- 175"
            },
            {
                "": "",
                "Exercice 2023.12": "-3.199",
                "Exercice 2022.12": "-3.565"
            },
            {
                "": "Impôts sur les bénéfices",
                "Exercice 2023.12": "- 6 299",
                "Exercice 2022.12": "- 3 740"
            }
        ],
        [],
        [
            {
                "": "ACTIF",
                "12/2023": "Valeurs\nbrutes",
                "null": "Valeurs\nnettes",
                "Exercice\n12/2022": "Valeurs\nnettes"
            },
            {
                "": "",
                "12/2023": "88.782",
                "null": "61.980",
                "Exercice\n12/2022": ""
            },
            {
                "": "",
                "12/2023": "-",
                "null": "-",
                "Exercice\n12/2022": ""
            },
            {
                "": "",
                "12/2023": "823.684",
                "null": "670.415",
                "Exercice\n12/2022": ""
            },
            {
                "": "",
                "12/2023": "50.005",
                "null": "50.005",
                "Exercice\n12/2022": ""
            },
            {
                "": "",
                "12/2023": "-",
                "null": "-",
                "Exercice\n12/2022": ""
            },
            {
                "": "Total Actif Immobilisé",
                "12/2023": "962.471",
                "null": "782.399",
                "Exercice\n12/2022": "663.103"
            },
            {
                "": "",
                "12/2023": "-",
                "null": "-",
                "Exercice\n12/2022": ""
            },
            {
                "": "",
                "12/2023": "6.951",
                "null": "4.843",
                "Exercice\n12/2022": ""
            },
            {
                "": "",
                "12/2023": "16.837",
                "null": "16.837",
                "Exercice\n12/2022": ""
            },
            {
                "": "Total Actif Circulant",
                "12/2023": "23.788",
                "null": "21.681",
                "Exercice\n12/2022": "30.412"
            },
            {
                "": "",
                "12/2023": "7.176",
                "null": "7.176",
                "Exercice\n12/2022": ""
            },
            {
                "": "",
                "12/2023": "28.096",
                "null": "28.096",
                "Exercice\n12/2022": ""
            },
            {
                "": "Total Valeurs mobilières de\nplacements et disponibilité",
                "12/2023": "35.272",
                "null": "35.272",
                "Exercice\n12/2022": "60.789"
            },
            {
                "": "Total Actif",
                "12/2023": "1.021.531",
                "null": "839.352",
                "Exercice\n12/2022": "754.303"
            }
        ],
        [
            {
                "": "",
                "31/12/2023": "1.589",
                "31/12/2022": ""
            },
            {
                "": "",
                "31/12/2023": "32.931",
                "31/12/2022": ""
            },
            {
                "": "",
                "31/12/2023": "1.895",
                "31/12/2022": ""
            },
            {
                "": "",
                "31/12/2023": "",
                "31/12/2022": ""
            },
            {
                "": "",
                "31/12/2023": "",
                "31/12/2022": ""
            },
            {
                "": "",
                "31/12/2023": "",
                "31/12/2022": ""
            },
            {
                "": "",
                "31/12/2023": "36.415",
                "31/12/2022": ""
            },
            {
                "": "",
                "31/12/2023": "",
                "31/12/2022": ""
            },
            {
                "": "",
                "31/12/2023": "12.115",
                "31/12/2022": ""
            },
            {
                "": "Flux net généré par (affecté à) l'activité",
                "31/12/2023": "48.530",
                "31/12/2022": "44.125"
            },
            {
                "": "",
                "31/12/2023": "-153.799",
                "31/12/2022": ""
            },
            {
                "": "",
                "31/12/2023": "",
                "31/12/2022": ""
            },
            {
                "": "",
                "31/12/2023": "-272",
                "31/12/2022": ""
            },
            {
                "": "",
                "31/12/2023": "",
                "31/12/2022": ""
            },
            {
                "": "Flux net provenant des (affecté aux) investissements",
                "31/12/2023": "-154.072",
                "31/12/2022": "-30"
            },
            {
                "": "",
                "31/12/2023": "-45.035",
                "31/12/2022": ""
            },
            {
                "": "",
                "31/12/2023": "",
                "31/12/2022": ""
            },
            {
                "": "",
                "31/12/2023": "",
                "31/12/2022": ""
            },
            {
                "": "",
                "31/12/2023": "",
                "31/12/2022": ""
            },
            {
                "": "",
                "31/12/2023": "95.099",
                "31/12/2022": ""
            },
            {
                "": "",
                "31/12/2023": "-188",
                "31/12/2022": ""
            },
            {
                "": "",
                "31/12/2023": "",
                "31/12/2022": ""
            },
            {
                "": "",
                "31/12/2023": "30.000",
                "31/12/2022": ""
            },
            {
                "": "Flux net provenant du (affecté au) financement",
                "31/12/2023": "79.876",
                "31/12/2022": "-100.355"
            },
            {
                "": "",
                "31/12/2023": "",
                "31/12/2022": ""
            },
            {
                "": "",
                "31/12/2023": "",
                "31/12/2022": ""
            },
            {
                "": "Variation de trésorerie",
                "31/12/2023": "-25.666",
                "31/12/2022": "-56.260"
            },
            {
                "": "",
                "31/12/2023": "60.788",
                "31/12/2022": ""
            },
            {
                "": "",
                "31/12/2023": "35.122",
                "31/12/2022": ""
            }
        ],
        [
            {
                "PASSIF": "",
                "Exercice 12/2023": "563.298",
                "Exercice 12/2022": ""
            },
            {
                "PASSIF": "",
                "Exercice 12/2023": "123.654",
                "Exercice 12/2022": ""
            },
            {
                "PASSIF": "",
                "Exercice 12/2023": "17.495",
                "Exercice 12/2022": ""
            },
            {
                "PASSIF": "",
                "Exercice 12/2023": "-25.596",
                "Exercice 12/2022": ""
            },
            {
                "PASSIF": "",
                "Exercice 12/2023": "-",
                "Exercice 12/2022": ""
            },
            {
                "PASSIF": "",
                "Exercice 12/2023": "1.589",
                "Exercice 12/2022": ""
            },
            {
                "PASSIF": "",
                "Exercice 12/2023": "-",
                "Exercice 12/2022": ""
            },
            {
                "PASSIF": "Total Capitaux Propres",
                "Exercice 12/2023": "680.440",
                "Exercice 12/2022": "724.159"
            },
            {
                "PASSIF": "",
                "Exercice 12/2023": "-",
                "Exercice 12/2022": ""
            },
            {
                "PASSIF": "",
                "Exercice 12/2023": "-",
                "Exercice 12/2022": ""
            },
            {
                "PASSIF": "",
                "Exercice 12/2023": "3.852",
                "Exercice 12/2022": ""
            },
            {
                "PASSIF": "",
                "Exercice 12/2023": "103.293",
                "Exercice 12/2022": ""
            },
            {
                "PASSIF": "Total Passif à long terme",
                "Exercice 12/2023": "107.146",
                "Exercice 12/2022": "13.807"
            },
            {
                "PASSIF": "",
                "Exercice 12/2023": "10.674",
                "Exercice 12/2022": ""
            },
            {
                "PASSIF": "",
                "Exercice 12/2023": "10.942",
                "Exercice 12/2022": ""
            },
            {
                "PASSIF": "",
                "Exercice 12/2023": "30.150",
                "Exercice 12/2022": ""
            },
            {
                "PASSIF": "Total Passif à court terme",
                "Exercice 12/2023": "51.766",
                "Exercice 12/2022": "16.337"
            },
            {
                "PASSIF": "",
                "Exercice 12/2023": "",
                "Exercice 12/2022": ""
            },
            {
                "PASSIF": "Total Passif",
                "Exercice 12/2023": "839.352",
                "Exercice 12/2022": "754.303"
            }
        ],
        [
            {
                "": "",
                "12/2023": "72.215",
                "12/2022": ""
            },
            {
                "": "",
                "12/2023": "-0",
                "12/2022": ""
            },
            {
                "": "",
                "12/2023": "-20.134",
                "12/2022": ""
            },
            {
                "": "",
                "12/2023": "-",
                "12/2022": ""
            },
            {
                "": "",
                "12/2023": "-300",
                "12/2022": ""
            },
            {
                "": "",
                "12/2023": "-12.462",
                "12/2022": ""
            },
            {
                "": "",
                "12/2023": "-30.502",
                "12/2022": ""
            },
            {
                "": "",
                "12/2023": "960",
                "12/2022": ""
            },
            {
                "": "Résultat d'exploitation",
                "12/2023": "9.777",
                "12/2022": "19.243"
            },
            {
                "": "",
                "12/2023": "198",
                "12/2022": ""
            },
            {
                "": "",
                "12/2023": "-424",
                "12/2022": ""
            },
            {
                "": "Résultat financier",
                "12/2023": "-226",
                "12/2022": "1.382"
            },
            {
                "": "Résultat courant des sociétés intégrées",
                "12/2023": "9.551",
                "12/2022": "20.625"
            },
            {
                "": "",
                "12/2023": "1.132",
                "12/2022": ""
            },
            {
                "": "",
                "12/2023": "-3.199",
                "12/2022": ""
            },
            {
                "": "",
                "12/2023": "-1.895",
                "12/2022": ""
            },
            {
                "": "Résultat net des entreprises intégrées",
                "12/2023": "5.589",
                "12/2022": "12.412"
            },
            {
                "": "",
                "12/2023": "-",
                "12/2022": ""
            },
            {
                "": "",
                "12/2023": "-4.001",
                "12/2022": ""
            },
            {
                "": "Résultat net de l'ensemble consolidé",
                "12/2023": "1.589",
                "12/2022": "8.411"
            },
            {
                "": "",
                "12/2023": "-",
                "12/2022": ""
            },
            {
                "": "Résultat net (part du groupe)",
                "12/2023": "1.589",
                "12/2022": "8.411"
            }
        ],
        [
            {
                "": "ACTIF",
                "Clôture": "Taux d'intérêt",
                "null": "Méthode de\nconso.",
                "Ouverture": "Taux d'intérêt"
            },
            {
                "": "",
                "Clôture": "100,00 %",
                "null": "IG",
                "Ouverture": "100,00 %"
            },
            {
                "": "",
                "Clôture": "100,00 %",
                "null": "IG",
                "Ouverture": "100,00 %"
            },
            {
                "": "",
                "Clôture": "100,00 %",
                "null": "IG",
                "Ouverture": "100,00 %"
            },
            {
                "": "",
                "Clôture": "100,00 %",
                "null": "IG",
                "Ouverture": "100,00 %"
            }
        ],
        [
            {
                "COMPTES SOCIAUX\nAU 31 DÉCEMBRE 2023": "BILAN (ACTIF) (En DH) COMPTE DE PRODUITS ET CHARGES (En DH)\nACTIF BrutAU Am 3 o e1 r t/ t Pi1 s rs2 oe v/ m i2 se i0 on2 nts s3 Net AU 31/12/20 N2 e2 t P l’ero xp e 1r re cis c eà leC pso r én e cc x ée e 2dr r en c na icn te st s LT ’O E 3T X =A E 1U R +X C I 2D CE E PLT R’O E ET X CA E E 4U R DX C E ID C NE E T\nIMMOBILISATIONS EN NON VALEURS (a) 37.549.410,42 30.508.463,93 7.040.946,49 14.550.828,58 I - PRODUITS D’EXPLOITATION 43.961.577,93 43.961.577,93 40.640.496,78\nFrais préliminaires 10.559.261,12 8.511.856,90 2.047.404,22 4.159.256,45 Ventes de marchandises\nCharges à repartir sur plusieurs exercices 26.990.149,30 21.996.607,03 4.993.542,27 10.391.572,13 Ventes de biens et services produits 42.690.912,73 42.690.912,73 40.047.376,78\nPrimes de remboursement des obligations Chiffres d’Affaires 42.690.912,73 42.690.912,73 40.047.376,78\nIMMOBILISATIONS INCORPORELLES (b) E Variation de stock de produits (1)\nAImmobilisations en recherche et développement X Immobilisations produites pour l'Ese p/elle-même\nCBrevets, marques, droits et valeurs similaires P Subvention d'exploitation\nT Fonds commercial L Autres produits d'exploitation\nI Autres immobilisations incorporelles O Reprises d'exploitation; transfert de charges 1.270.665,20 1.270.665,20 593.120,00\nF IMMOBILISATIONS CORPORELLES (c) 363.027.458,93 56.519.338,83 306.508.120,10 320.343.364,66 I TOTAL I 43.961.577,93 43.961.577,93 40.640.496,78\nTerrains 64.151.122,86 64.151.122,86 64.151.122,86 T II- CHARGES D'EXPLOITATION 38.996.289,66 3.985,73 39.000.275,39 39.518.486,72\nConstructions 298.876.336,07 56.519.338,83 242.356.997,24 256.192.241,80 A Achats revendus de marchandises (2)\nI Installations techniques, matériel et outillage T Achat consommés de matières et de fournitures (2) 60,00 60,00 5.945,21\nM Matériel de transport I Autres charges externes 14.088.372,35 3.985,73 14.092.358,08 12.714.513,78\nM BOM Auo tb ri eli se ir ms, m oa bt ié lir sie al id oe sb u core rpa ou e et la em sénagements divers NO I Cm hp aô rgts se t t ea x pe es 2.964.233,84 2.964.233,84 2.943.055,52\nm t n r l e d rsonnel\nI Immobilisations corporelles en cours Autres charges d'exploitation 300.000,00 300.000,00 300.000,00\nL IMMOBILISATIONS FINANCIERES (d) 519.808.140,82 519.808.140,82 392.744.497,29 Dotations d'exploitation 21.643.623,47 21.643.623,47 23.554.972,21\nI Prêts immobilisés TOTAL II 38.996.289,66 3.985,73 39.000.275,39 39.518.486,72\nSAutres créances financières 20.899.016,00 20.899.016,00 20.784.523,66 III- RESULTAT D'EXPLOITATION ( I - II ) 4.965.288,27 -3.985,73 4.961.302,54 1.122.010,06\nETitres de participation 498.909.124,82 498.909.124,82 371.959.973,63 IV- PRODUITS FINANCIERS 1.545.000,90 1.545.000,90 1.906.063,21\nAutres titres immobilises Produits des titres de participation et autres titres\nimmobilisés\nECARTS DE CONVERSION - ACTIF (e)\nDiminution des créances immobilisées F Gains de change\nAugmentation des dettes financières I Intérêts et autres produits financiers 1.545.000,90 1.545.000,90 1.906.063,21\nTOTAL I ( a+b+c+d+e) 920.385.010,17 87.027.802,76 833.357.207,41 727.638.690,53 N Reprises financières; transfert de charges\nSTOCKS (f) A TOTAL IV 1.545.000,90 1.545.000,90 1.906.063,21\nN V- CHARGES FINANCIERES 1.195.938,03 1.195.938,03 1.231,11\nMarchandises\nC Charges d'intérêts 1.125.406,37 1.125.406,37 1.231,11\nAMatières et fournitures consommables\nI Pertes de changes\nCProduits en cours\nT P Pr ro od du ui it ts i fn int ie srm. et produits résiduels RE A Du ot tr ae tis nch a fir ng ae ns f ii èn ra en scières 70.531,66 70.531,66\nI s o s c\nF CREANCES DE L'ACTIF CIRCULANT (g) 18.869.712,85 18.869.712,85 35.505.925,81 TOTAL V 1.195.938,03 1.195.938,03 1.231,11\nVI- RESULTAT FINANCIER ( IV - V ) 349.062,87 349.062,87 1.904.832,10\nFournis. débiteurs, avances et acomptes 1.200,00 1.200,00 1.200,00\nCClients et comptes rattachés 6.682.191,87 6.682.191,87 13.548.771,54 VII- RESULTAT COURANT ( III - VI) 5.314.351,14 -3.985,73 5.310.365,41 3.026.842,16\nI Personnel VIII- PRODUITS NON COURANTS 199.628,54 199.628,54 5.410,05\nR Etat 11.602.103,02 11.602.103,02 19.113.039,15 Produits de cessions d'immobilisations\nC Comptes d'associés Subventions d'équilibre\nNU AL A C TIu o Tmt Rre p Es t Se d Edé Teb i Vrte é Au g Lr u Es l Uar Ris Da Etio Pn a Ac Cti Ef 4.04 1 61 6 26 7 .. . 25 6 89 2 11 6 ,, , 76 3 31 5 4.04 1 61 6 26 7 .. . 25 6 89 2 11 6 ,, , 76 3 31 5 182 .. 16 1 38 5 38 4 .. . 33 6 51 0 94 0 ,, , 19 1 83 9 N NO R A Ru ee t pp r rr e ii sss e p ss r o ns d ou u nr i t cs s ou unb rov ane n c to eti u so rn ;a ts n ad ts n'i sn fv ee rs tst i ds es e cm hae rn Tt 11 99 99 .. 66 22 88 ,, 55 44 11 99 99 .. 66 22 88 ,, 55 44 55 .. 44 11 00 ,, 00 55\nL MENT (h) e n r g e Os\nTAL VIII\nT\nECART DE CONVERSION - ACTIF (i) C IX- CHARGES NON COURANTES 65.144,46 65.144,46 436.394,30\n(Eléments circulants) O Valeurs nettes d'amort. des Immo cédées\nTOTAL II (f+g+h+i) 22.931.994,58 22.931.994,58 53.639.284,99 U Subventions accordées\nT TRESORERIE - ACTIF 680.820,59 680.820,59 765.468,16 R Autres charges non courantes 60.237,46 60.237,46 436.394,30\nR EChèques et valeurs à encaisser 739.065,60 A Dotations non courantes aux amortiss. et provision 4.907,00 4.907,00\nSBanques, T.G & CP 676.296,59 676.296,59 26.232,56 N TOTAL IX 65.144,46 65.144,46 436.394,30\nRO . Caisses, régies d'avances et accréditifs 4.524,00 4.524,00 170,00 T X- RESULTAT NON COURANT ( VIII- IV ) 134.484,08 134.484,08 -430.984,25\nTOTAL III 680.820,59 680.820,59 765.468,16 XI- RESULTAT AVANT IMPOTS ( VII+ ou - X)) 5.448.835,22 -3.985,73 5.444.849,49 2.595.857,91\nTOTAL GENERAL I+II+III 943.997.825,34 87.027.802,76 856.970.022,58 782.043.443,68 XII- IMPOTS SUR LES RESULTATS 1.018.402,00 1.018.402,00 1.201.164,00\nXIII- RESULTAT NET ( XI - XII ) 4.430.433,22 -3.985,73 4.426.447,49 1.394.693,91\nBILAN (PASSIF) (En DH)\nXIV- TOTAL DES PRODUITS ( I + IV + VIII ) 45.706.207,37 45.706.207,37 42.551.970,04\nXV- TOTAL DES CHARGES ( II + V + IX + XII ) 41.275.774,15 3.985,73 41.279.759,88 41.157.276,13\nPASSIF AU 31/12/2023 AU 31/12/2022 XVI- RESULTAT NET (Total Produits - Total Charges) 4.430.433,22 -3.985,73 4.426.447,49 1.394.693,91\nCAPITAUX PROPRES 722.516.792,15 763.125.344,66 (1) Variation de Stocks: Stock Final - Stock Initial (Augmentation (+) ; Diminution (-)\n(2) Achats Revendus ou Consommés: Achats - Variation de Stocks\n* Capital Social ou Personnel (1) 563.297.780,00 563.297.780,00\n* Moins : actionnaires, capital Souscrit non appelé ETAT DES SOLDES INTERMEDIAIRES DE GESTION (E.S.G) (En DH)\nCapital appelé 563.297.780,00 563.297.780,00\nDont versé 563.297.780,00 563.297.780,00 31/12/2023 31/12/2022\n* Primes d'Emission, de Fusion, d'Apport 123.654.128,34 159.682.128,34 1 Ventes de marchandises (en l'état)\nCA * Ecarts de Réévaluation 24.993.336,70 24.993.336,70 A Mc Ah Ra Gts r Se v Be Rn Ud Tu Es Sd e Um Ra r Vc Eh Na Tn Edi Ss e Es\nI = E S N L'ETAT\nT * Réserve Légale 2.506.274,98 2.436.540,28 II + PRODUCTION DE L'EXERCICE (3+4+5) 42.690.912,73 40.047.376,78\nI * Autres Réserves\n3 = Ventes de biens et services produits 42.690.912,73 40.047.376,78\nF * Report à Nouveau (2) 3.638.824,64 11.320.865,43\n4 + Variation de stocks de produits\n* Résultats Nets en Instance d'Affectation (2)\n5 Immobilisations produites par lEse pour elle-même\nMI * Résultat net de l’exercice (2) TOTAUX DES CAPITAUX PROPRES (A) 7224 .. 54 12 66 .. 74 94 27 ,, 14 59 7631 .. 13 29 54 .. 36 49 43 ,, 69 61 III 6 - AC cO hN aS tsO M coM nsA oT mIO mN é D sE d eL ' mEX aE tiR èrC eI sC E et ( 6 fo+ u7 r) nitures 14.092.4 618 0, ,0 08 0 12.72 50 .. 94 458 5, ,9 29 1\nMCAPITAUX PROPRES ASSIMILES (b) 7 Autres charges externes 14.092.358,08 12.714.513,78\nO* Subventions d'Investissement IV = VALEUR AJOUTEE (I+II+III) 28.598.494,65 27.326.917,79\nB* Provisions Réglementées 8 + Subventions d'exploitation\nI DETTES DE FINANCEMENT (c) 125.072.056,99 5.072.056,99 V 9 - Impôts et taxes 2.964.233,84 2.943.055,52\nL * Emprunts Obligataires 10 - Charges de personnel\nI * Autres Dettes de Financement 125.072.056,99 5.072.056,99 = EXCEDENT BRUT D'EXPLOITATION (E.B.E) OU INSUFFISANCE BRUT 25.634.260,81 24.383.862,27\nS D'EXPLOITATION (I.B.E)\nPROVISIONS DURABLES POUR RISQUES ET CHARGES (d)\nE 11 + Autres produits d'exploitation\n* Provisions pour Risques\n12 - Autres charges d'exploitation 300.000,00 300.000,00\n* Provisions pour Charges 13 + Reprises d'exploitation : transfert de charges 1.270.665,20 593.120,00\nECARTS DE CONVERSION - PASSIF (e) 14 - Dotations d'exploitation 21.643.623,47 23.554.972,21\n* Augmentation des Créances Immobilisées VI = RESULTAT D'EXPLOITATION (+ ou -) 4.961.302,54 1.122.010,06\n* Diminution des Dettes de Financement VII RESULTAT FINANCIER 349.062,87 1.904.832,10\nTOTAL I ( a+b+c+d+e ) 847.588.849,14 768.197.401,65 VIII = RESULTAT COURANT (+ ou -) 5.310.365,41 3.026.842,16\nADETTES DU PASSIF CIRCULANT (f) 9.376.266,44 9.967.572,61 IX RESULTAT NON COURANT (+ ou -) 134.484,08 -430.984,25\nC* Fournisseurs et Comptes Rattachés 6.578.336,00 5.662.774,60 15 - Impôts sur les résultats 1.018.402,00 1.201.164,00\nT * Clients Créditeurs, Avances et Acomptes X = RESULTAT NET DE L'EXERCICE ( + ou - ) 4.426.447,49 1.394.693,91\nI\nF* Personnel\nCAPACITE D’AUTOFINANCEMENT (C.A.F) - AUTOFINANCEMENT\n* Organismes Sociaux\nC I * Etat 2.437.952,66 4.094.598,01 1 Résultat de l'Exercice 4.426.447,49 1.394.693,91\nR* Comptes d'Associés Bénéfice 4.426.447,49 1.394.693,91\nC* Autres Créanciers 210.200,00 210.200,00 Perte\nU* Comptes de Régularisation - Passif 149.777,78 2 + Dotations d'Exploitation (1) 21.643.623,47 22.622.053,83\nL\nAAUTRES PROVISIONS POUR RISQUES ET CHARGES (g) 4.907,00 932.918,38 3 + Dotations financières (1)\nNECARTS DE CONVERSION - PASSIF (h) (Elements circulants) 4 + Dotations non courantes (1)\nT TOTAL II ( f+g+h ) 9.381.173,44 10.900.490,99 5 - Reprises d'exploitation (2) 293.996,82 240.780,00\nT TRESORERIE PASSIF 2.945.551,04 6 - Reprises financières (2 )\nRCrédits d'escompte 7 - Reprises non courantes (2) (3)\nE 8 - Produits de cession d'immobilisations\nSCrédit de trésorerie\nO 9 + Valeurs nettes d'amortissement des imm. cédées\nR.Banques (soldes créditeurs ) 2.945.551,04\nI CAPACITE D'AUTOFINANCEMENT (C.A.F) 25.776.074,14 23.775.967,74\nTOTAL III 2.945.551,04 10 - Distributions de bénéfices 45.035.000,00 49.538.500,00\nTOTAL I+II+III 856.970.022,58 782.043.443,68 II AUTOFINANCEMENT -19.258.925,86-25.762.532,26\n(1) Capital Personnel Débiteur (1) à l’exclusion des dotations relatives aux actifs et passifs circulants et à la trésorerie\n(2) Bénéficiaire (+), Déficitaire (-) (2) à l’exclusion des reprises relatives aux actifs circulants et à la trésorerie\n(3) y compris les reprises sur les subventions d’investissement"
            }
        ],
        [
            {
                "null": "Net",
                "": "ACTIF",
                "AU 31/12/2023": "Brut",
                "AU 31/12/2022": "Net"
            },
            {
                "null": "7.040.946,49",
                "": "IMMOBILISATIONS EN NON VALEURS (a)",
                "AU 31/12/2023": "37.549.410,42",
                "AU 31/12/2022": "14.550.828,58"
            },
            {
                "null": "",
                "": "Frais préliminaires",
                "AU 31/12/2023": "10.559.261,12 8.511.856,90 2.047.404,22",
                "AU 31/12/2022": ""
            },
            {
                "null": "",
                "": "Charges à repartir sur plusieurs exercices",
                "AU 31/12/2023": "26.990.149,30 21.996.607,03 4.993.542,27",
                "AU 31/12/2022": ""
            },
            {
                "null": "",
                "": "Primes de remboursement des obligations",
                "AU 31/12/2023": "",
                "AU 31/12/2022": ""
            },
            {
                "null": "",
                "": "IMMOBILISATIONS INCORPORELLES (b)",
                "AU 31/12/2023": "",
                "AU 31/12/2022": ""
            },
            {
                "null": "",
                "": "Immobilisations en recherche et développement",
                "AU 31/12/2023": "",
                "AU 31/12/2022": ""
            },
            {
                "null": "",
                "": "Brevets, marques, droits et valeurs similaires",
                "AU 31/12/2023": "",
                "AU 31/12/2022": ""
            },
            {
                "null": "",
                "": "Fonds commercial",
                "AU 31/12/2023": "",
                "AU 31/12/2022": ""
            },
            {
                "null": "",
                "": "Autres immobilisations incorporelles",
                "AU 31/12/2023": "",
                "AU 31/12/2022": ""
            },
            {
                "null": "306.508.120,10",
                "": "IMMOBILISATIONS CORPORELLES (c)",
                "AU 31/12/2023": "363.027.458,93",
                "AU 31/12/2022": "320.343.364,66"
            },
            {
                "null": "",
                "": "Terrains",
                "AU 31/12/2023": "64.151.122,86 64.151.122,86",
                "AU 31/12/2022": ""
            },
            {
                "null": "",
                "": "Constructions",
                "AU 31/12/2023": "298.876.336,07 56.519.338,83 242.356.997,24",
                "AU 31/12/2022": ""
            },
            {
                "null": "",
                "": "Installations techniques, matériel et outillage",
                "AU 31/12/2023": "",
                "AU 31/12/2022": ""
            },
            {
                "null": "",
                "": "Matériel de transport",
                "AU 31/12/2023": "",
                "AU 31/12/2022": ""
            },
            {
                "null": "",
                "": "Mobiliers, matériel de bureau et aménagements divers",
                "AU 31/12/2023": "",
                "AU 31/12/2022": ""
            },
            {
                "null": "",
                "": "Autres immobilisations corporelles",
                "AU 31/12/2023": "",
                "AU 31/12/2022": ""
            },
            {
                "null": "",
                "": "Immobilisations corporelles en cours",
                "AU 31/12/2023": "",
                "AU 31/12/2022": ""
            },
            {
                "null": "519.808.140,82",
                "": "IMMOBILISATIONS FINANCIERES (d)",
                "AU 31/12/2023": "519.808.140,82",
                "AU 31/12/2022": "392.744.497,29"
            },
            {
                "null": "",
                "": "Prêts immobilisés",
                "AU 31/12/2023": "",
                "AU 31/12/2022": ""
            },
            {
                "null": "",
                "": "Autres créances financières",
                "AU 31/12/2023": "20.899.016,00 20.899.016,00",
                "AU 31/12/2022": ""
            },
            {
                "null": "",
                "": "Titres de participation",
                "AU 31/12/2023": "498.909.124,82 498.909.124,82",
                "AU 31/12/2022": ""
            },
            {
                "null": "",
                "": "Autres titres immobilises",
                "AU 31/12/2023": "",
                "AU 31/12/2022": ""
            },
            {
                "null": "",
                "": "ECARTS DE CONVERSION - ACTIF (e)",
                "AU 31/12/2023": "",
                "AU 31/12/2022": ""
            },
            {
                "null": "",
                "": "Diminution des créances immobilisées",
                "AU 31/12/2023": "",
                "AU 31/12/2022": ""
            },
            {
                "null": "",
                "": "Augmentation des dettes financières",
                "AU 31/12/2023": "",
                "AU 31/12/2022": ""
            },
            {
                "null": "833.357.207,41",
                "": "TOTAL I ( a+b+c+d+e)",
                "AU 31/12/2023": "920.385.010,17",
                "AU 31/12/2022": "727.638.690,53"
            },
            {
                "null": "",
                "": "STOCKS (f)",
                "AU 31/12/2023": "",
                "AU 31/12/2022": ""
            },
            {
                "null": "",
                "": "Marchandises",
                "AU 31/12/2023": "",
                "AU 31/12/2022": ""
            },
            {
                "null": "",
                "": "Matières et fournitures consommables",
                "AU 31/12/2023": "",
                "AU 31/12/2022": ""
            },
            {
                "null": "",
                "": "Produits en cours",
                "AU 31/12/2023": "",
                "AU 31/12/2022": ""
            },
            {
                "null": "",
                "": "Produits interm. et produits résiduels",
                "AU 31/12/2023": "",
                "AU 31/12/2022": ""
            },
            {
                "null": "",
                "": "Produits finis",
                "AU 31/12/2023": "",
                "AU 31/12/2022": ""
            },
            {
                "null": "18.869.712,85",
                "": "CREANCES DE L'ACTIF CIRCULANT (g)",
                "AU 31/12/2023": "18.869.712,85",
                "AU 31/12/2022": "35.505.925,81"
            },
            {
                "null": "",
                "": "Fournis. débiteurs, avances et acomptes",
                "AU 31/12/2023": "1.200,00 1.200,00",
                "AU 31/12/2022": ""
            },
            {
                "null": "",
                "": "Clients et comptes rattachés",
                "AU 31/12/2023": "6.682.191,87 6.682.191,87",
                "AU 31/12/2022": ""
            },
            {
                "null": "",
                "": "Personnel",
                "AU 31/12/2023": "",
                "AU 31/12/2022": ""
            },
            {
                "null": "",
                "": "Etat",
                "AU 31/12/2023": "11.602.103,02 11.602.103,02",
                "AU 31/12/2022": ""
            },
            {
                "null": "",
                "": "Comptes d'associés",
                "AU 31/12/2023": "",
                "AU 31/12/2022": ""
            },
            {
                "null": "",
                "": "Autres débiteurs",
                "AU 31/12/2023": "416.591,61 416.591,61",
                "AU 31/12/2022": ""
            },
            {
                "null": "",
                "": "Compte de régularisation actif",
                "AU 31/12/2023": "167.626,35 167.626,35",
                "AU 31/12/2022": ""
            },
            {
                "null": "4.062.281,73",
                "": "TITRES ET VALEUR DE PLACEMENT (h)",
                "AU 31/12/2023": "4.062.281,73",
                "AU 31/12/2022": "18.133.359,18"
            },
            {
                "null": "",
                "": "",
                "AU 31/12/2023": "",
                "AU 31/12/2022": ""
            },
            {
                "null": "",
                "": "ECART DE CONVERSION - ACTIF (i)\n(Eléments circulants)",
                "AU 31/12/2023": "",
                "AU 31/12/2022": ""
            },
            {
                "null": "22.931.994,58",
                "": "TOTAL II (f+g+h+i)",
                "AU 31/12/2023": "22.931.994,58",
                "AU 31/12/2022": "53.639.284,99"
            },
            {
                "null": "680.820,59",
                "": "TRESORERIE - ACTIF",
                "AU 31/12/2023": "680.820,59",
                "AU 31/12/2022": "765.468,16"
            },
            {
                "null": "",
                "": "Chèques et valeurs à encaisser",
                "AU 31/12/2023": "",
                "AU 31/12/2022": ""
            },
            {
                "null": "",
                "": "Banques, T.G & CP",
                "AU 31/12/2023": "676.296,59 676.296,59",
                "AU 31/12/2022": ""
            },
            {
                "null": "",
                "": "Caisses, régies d'avances et accréditifs",
                "AU 31/12/2023": "4.524,00 4.524,00",
                "AU 31/12/2022": ""
            },
            {
                "null": "680.820,59",
                "": "TOTAL III",
                "AU 31/12/2023": "680.820,59",
                "AU 31/12/2022": "765.468,16"
            },
            {
                "null": "856.970.022,58",
                "": "TOTAL GENERAL I+II+III",
                "AU 31/12/2023": "943.997.825,34",
                "AU 31/12/2022": "782.043.443,68"
            }
        ],
        [
            {
                "null": "E\nX\nP\nL\nO\nI\nT\nA\nT\nI\nO\nN",
                "": "I - PRODUITS D’EXPLOITATION",
                "Propres à\nl’exercice\n1": "43.961.577,93",
                "Concernant\nles exercices\nprécédents\n2": "",
                "TOTAUX DE\nL’EXERCICE\n3 = 1 + 2": "43.961.577,93",
                "TOTAUX DE\nL’EXERCICE\nPRECEDENT\n4": "40.640.496,78"
            },
            {
                "null": "F\nI\nN\nA\nN\nC\nI\nE\nR",
                "": "IV- PRODUITS FINANCIERS",
                "Propres à\nl’exercice\n1": "1.545.000,90",
                "Concernant\nles exercices\nprécédents\n2": "",
                "TOTAUX DE\nL’EXERCICE\n3 = 1 + 2": "1.545.000,90",
                "TOTAUX DE\nL’EXERCICE\nPRECEDENT\n4": "1.906.063,21"
            },
            {
                "null": "",
                "": "TOTAL V",
                "Propres à\nl’exercice\n1": "1.195.938,03",
                "Concernant\nles exercices\nprécédents\n2": "",
                "TOTAUX DE\nL’EXERCICE\n3 = 1 + 2": "1.195.938,03",
                "TOTAUX DE\nL’EXERCICE\nPRECEDENT\n4": "1.231,11"
            },
            {
                "null": "",
                "": "VI- RESULTAT FINANCIER ( IV - V )",
                "Propres à\nl’exercice\n1": "349.062,87",
                "Concernant\nles exercices\nprécédents\n2": "",
                "TOTAUX DE\nL’EXERCICE\n3 = 1 + 2": "349.062,87",
                "TOTAUX DE\nL’EXERCICE\nPRECEDENT\n4": "1.904.832,10"
            },
            {
                "null": "",
                "": "VII- RESULTAT COURANT ( III - VI)",
                "Propres à\nl’exercice\n1": "5.314.351,14",
                "Concernant\nles exercices\nprécédents\n2": "-3.985,73",
                "TOTAUX DE\nL’EXERCICE\n3 = 1 + 2": "5.310.365,41",
                "TOTAUX DE\nL’EXERCICE\nPRECEDENT\n4": "3.026.842,16"
            },
            {
                "null": "N\nO\nN\nC\nO\nU\nR\nA\nN\nT",
                "": "VIII- PRODUITS NON COURANTS",
                "Propres à\nl’exercice\n1": "199.628,54",
                "Concernant\nles exercices\nprécédents\n2": "",
                "TOTAUX DE\nL’EXERCICE\n3 = 1 + 2": "199.628,54",
                "TOTAUX DE\nL’EXERCICE\nPRECEDENT\n4": "5.410,05"
            },
            {
                "null": "",
                "": "TOTAL IX",
                "Propres à\nl’exercice\n1": "65.144,46",
                "Concernant\nles exercices\nprécédents\n2": "",
                "TOTAUX DE\nL’EXERCICE\n3 = 1 + 2": "65.144,46",
                "TOTAUX DE\nL’EXERCICE\nPRECEDENT\n4": "436.394,30"
            },
            {
                "null": "",
                "": "X- RESULTAT NON COURANT ( VIII- IV )",
                "Propres à\nl’exercice\n1": "134.484,08",
                "Concernant\nles exercices\nprécédents\n2": "",
                "TOTAUX DE\nL’EXERCICE\n3 = 1 + 2": "134.484,08",
                "TOTAUX DE\nL’EXERCICE\nPRECEDENT\n4": "-430.984,25"
            },
            {
                "null": "",
                "": "XI- RESULTAT AVANT IMPOTS ( VII+ ou - X))",
                "Propres à\nl’exercice\n1": "5.448.835,22",
                "Concernant\nles exercices\nprécédents\n2": "-3.985,73",
                "TOTAUX DE\nL’EXERCICE\n3 = 1 + 2": "5.444.849,49",
                "TOTAUX DE\nL’EXERCICE\nPRECEDENT\n4": "2.595.857,91"
            },
            {
                "null": "",
                "": "XII- IMPOTS SUR LES RESULTATS",
                "Propres à\nl’exercice\n1": "1.018.402,00",
                "Concernant\nles exercices\nprécédents\n2": "",
                "TOTAUX DE\nL’EXERCICE\n3 = 1 + 2": "1.018.402,00",
                "TOTAUX DE\nL’EXERCICE\nPRECEDENT\n4": "1.201.164,00"
            },
            {
                "null": "",
                "": "XIII- RESULTAT NET ( XI - XII )",
                "Propres à\nl’exercice\n1": "4.430.433,22",
                "Concernant\nles exercices\nprécédents\n2": "-3.985,73",
                "TOTAUX DE\nL’EXERCICE\n3 = 1 + 2": "4.426.447,49",
                "TOTAUX DE\nL’EXERCICE\nPRECEDENT\n4": "1.394.693,91"
            },
            {
                "null": "",
                "": "XIV- TOTAL DES PRODUITS ( I + IV + VIII )",
                "Propres à\nl’exercice\n1": "45.706.207,37",
                "Concernant\nles exercices\nprécédents\n2": "",
                "TOTAUX DE\nL’EXERCICE\n3 = 1 + 2": "45.706.207,37",
                "TOTAUX DE\nL’EXERCICE\nPRECEDENT\n4": "42.551.970,04"
            },
            {
                "null": "",
                "": "XV- TOTAL DES CHARGES ( II + V + IX + XII )",
                "Propres à\nl’exercice\n1": "41.275.774,15",
                "Concernant\nles exercices\nprécédents\n2": "3.985,73",
                "TOTAUX DE\nL’EXERCICE\n3 = 1 + 2": "41.279.759,88",
                "TOTAUX DE\nL’EXERCICE\nPRECEDENT\n4": "41.157.276,13"
            },
            {
                "null": "",
                "": "XVI- RESULTAT NET (Total Produits - Total Charges)",
                "Propres à\nl’exercice\n1": "4.430.433,22",
                "Concernant\nles exercices\nprécédents\n2": "-3.985,73",
                "TOTAUX DE\nL’EXERCICE\n3 = 1 + 2": "4.426.447,49",
                "TOTAUX DE\nL’EXERCICE\nPRECEDENT\n4": "1.394.693,91"
            }
        ],
        [],
        [
            {
                "TOTAL IV": "V- CHARGES FINANCIERES",
                "1.545.000,90": "1.195.938,03",
                "": "",
                "1.906.063,21": "1.231,11"
            }
        ],
        [
            {
                "TOTAL VIII": "IX- CHARGES NON COURANTES",
                "199.628,54": "65.144,46",
                "": "",
                "5.410,05": "436.394,30"
            }
        ],
        [
            {
                "null": "A\nC\nT\nI\nF\nI\nM\nM\nO\nB\nI\nL\nI\nS\nE",
                "PASSIF": "CAPITAUX PROPRES",
                "AU 31/12/2023": "722.516.792,15",
                "AU 31/12/2022": "763.125.344,66"
            },
            {
                "null": "",
                "PASSIF": "TOTAL I ( a+b+c+d+e )",
                "AU 31/12/2023": "847.588.849,14",
                "AU 31/12/2022": "768.197.401,65"
            },
            {
                "null": "A\nC\nT\nI\nF\nC\nI\nR\nC\nU\nL\nA\nN\nT",
                "PASSIF": "DETTES DU PASSIF CIRCULANT (f)",
                "AU 31/12/2023": "9.376.266,44",
                "AU 31/12/2022": "9.967.572,61"
            },
            {
                "null": "",
                "PASSIF": "AUTRES PROVISIONS POUR RISQUES ET CHARGES (g)",
                "AU 31/12/2023": "4.907,00",
                "AU 31/12/2022": "932.918,38"
            },
            {
                "null": "",
                "PASSIF": "ECARTS DE CONVERSION - PASSIF (h) (Elements circulants)",
                "AU 31/12/2023": "",
                "AU 31/12/2022": ""
            },
            {
                "null": "",
                "PASSIF": "TOTAL II ( f+g+h )",
                "AU 31/12/2023": "9.381.173,44",
                "AU 31/12/2022": "10.900.490,99"
            },
            {
                "null": "T\nR\nE\nS\nO\nR.",
                "PASSIF": "TRESORERIE PASSIF",
                "AU 31/12/2023": "",
                "AU 31/12/2022": "2.945.551,04"
            },
            {
                "null": "",
                "PASSIF": "TOTAL III",
                "AU 31/12/2023": "",
                "AU 31/12/2022": "2.945.551,04"
            },
            {
                "null": "",
                "PASSIF": "TOTAL I+II+III",
                "AU 31/12/2023": "856.970.022,58",
                "AU 31/12/2022": "782.043.443,68"
            }
        ],
        [
            {
                "ETAT DES SOLDES INTERMEDIAIRES DE GESTION (E.S.G) (En DH": "",
                "null": "31/12/2022"
            }
        ],
        [
            {
                "I": "II",
                "": "40.047.376,78",
                "=": "+",
                "MARGES BRUTES SUR VENTES EN L'ETAT": "PRODUCTION DE L'EXERCICE (3+4+5)"
            }
        ],
        [],
        [
            {
                "TOTAUX DES CAPITAUX PROPRES (A)": "CAPITAUX PROPRES ASSIMILES (b)",
                "722.516.792,15": "",
                "763.125.344,66": ""
            }
        ],
        [],
        [],
        [],
        [],
        [],
        [
            {
                "VI": "VII",
                "": "",
                "=": "",
                "RESULTAT D'EXPLOITATION (+ ou -)": "RESULTAT FINANCIER",
                "4.961.302,54": "349.062,87",
                "1.122.010,06": "1.904.832,10"
            },
            {
                "VI": "VIII",
                "": "",
                "=": "=",
                "RESULTAT D'EXPLOITATION (+ ou -)": "RESULTAT COURANT (+ ou -)",
                "4.961.302,54": "5.310.365,41",
                "1.122.010,06": "3.026.842,16"
            },
            {
                "VI": "IX",
                "": "",
                "=": "",
                "RESULTAT D'EXPLOITATION (+ ou -)": "RESULTAT NON COURANT (+ ou -)",
                "4.961.302,54": "134.484,08",
                "1.122.010,06": "-430.984,25"
            }
        ],
        [],
        [
            {
                "COMPTES SOCIAUX\nAU 31 DÉCEMBRE 2023": "TABLEAU DE FINANCEMENT AU 31/12/2023 (En DH) ETAT DES DEROGATIONS\nI. SYNTHESE DES MASSES DU BILAN VARIATION A-B IN DED RIC OA GT AIO TIN O NDE SS JUSTIFICATION DES DEROGATIONS PIN ATF RL IU ME ON IC N EE E T , D LLE EAS S S D RITE EUR SAO UTG LI TA O AT N TI O F SN INS A S NU CR IE L RE E\nMASSES EXERCICE EXERCICE Emplois Ressources Conformément aux dispositions de l'article 328\nN N-1 C D de la loi 17-95 sur la SA telle que modifiée et\ncomplétée, les frais d'augmentation de capital\n1 Financement Permanent 847.588.849,14 768.197.401,65 79.391.447,49 réalisées au cours des exercices antérieurs ont\n2 Moins actif immobilisé 833.357.207,41 727.638.690,53 105.718.516,88 été imputés sur la prime d'émission.\n3 = Fonds de Roulement Fonctionnel (1-2) (A) 14.231.641,73 40.558.711,12 26.327.069,39 Aussi, les frais engagés dans le cadre de l’opération\n4 Actif circulant 22.931.994,58 53.639.284,99 30.707.290,41 d’introduction en bourse ont été imputés sur\nI- Dérogations aux le montant de la prime d’émission afférente à\n5 Moins passif circulant 9.381.173,44 10.900.490,99 1.519.317,55 principes comptables cette opération tel que décidé par l’assemblée\n6 = Besoin de Financement global (4-5) (B) 13.550.821,14 42.738.794,00 29.187.972,86 fondamentaux générale extraordinaire du 11 mai 2018.\nCes frais totalisent KMAD 13.230 au 31\n7 TRESORERIE NETTE (Actif-Passif) = A-B 680.820,59 -2.180.082,88 2.860.903,47 décembre 2018 et se composent de :\n- Frais de communication pour KMAD 2.332 ;\nII EMPLOIS ET RESSOURCES - Honoraires et débours des commissaires aux\ncomptes, conseil et assistance juridique et fiscale\nd’experts comptables et avocats pour KMAD 3.822 ;\nEXERCICE EXERCICE PRECEDENT - Commissions relatives à la\nI RESSOURCES STABLES DE L’EXERCICE (FLUX) EMPLOIS RESSOURCES EMPLOIS RESSOURCES soucription pour KMAD 7.050 ;\n- Frais de débours liés à l’opération pour KMAD 25.\n* AUTOFINANCEMENT (A) -19.258.925,86 -25.762.532,26\nRéévaluation de la valeur d’acquisition des Ecart de réévaluation de KMAD 24.993\n+ Capacité d'autofinancement 25.776.074,14 23.775.967,74 constructions portant les titres fonciers N° constatés à l’actif en Immobilisations\n- Distributions de bénéfices 45.035.000,00 49.538.500,00 TF 5677/50, TF 100426/C, TF 115270/01 et TF corporelles et au passif en Ecarts de\n115269/01. réévaluation.\n* CESSIONS ET REDUCTIONS D'IMMOBILISATIONS (B) 28.779.807,66 Dotations aux amortissements\n+ Cessions d'immobilisations incorporelles complémetaires résultant de la réévaluation\nde KMAD 69 pour l’exercice 2023.\n+ Cessions d'immobilisations corporelles\n++ RC ée cs us pio én rs a td io' nim s m suo rb ci rli és aa nti co en ss i mfin ma on bc ii lè isr ée es s 28.779.807,66 I a dI u ’- é xD v m aé lr uéo t ag h ta io ot di no en ss B c 2o 0a n 2is 0ss t .re u d ce ti ola n sd u dr eé 4e 0 d à’a 2m 5o ar nti ss s àe pm ae rtn irt d de es j anvier 2 -H . H2a 2 au 0 us . ss 5 se 6 e 1d , de 3 es 5 s d d ao e mt ca o ot mi ro tn p iss o s sa eéu mex e ca nom tm so m rr ét ei ss uss lue taim t n :e t n dt es l: a\n* AUGMENTATION DES CAPITAUX PROPRES ET réévaluation : 248.358,64\nASSIMILES (C) - Hausse des amortissements suite à\nla baisse de durée d’amortissement :\n+ Augmentation du capital, apports 1.972.202,71\n+ Subventions d'investissement Soit :\n- Impact sur le résultat de l’exercice : -\nAUGMENTATION DES DETTES DE FINANCEMENT (D) 120.000.000,00 519.105,60 2.220.561,35\n(nettes de primes de remboursement) - Impact sur l’actif net : - 2.220.561,35\nTOTAL RESSOURCES STABLES (A+B+C+D)\nIII- Dérogations\naux règles\nII EMPLOIS STABLES DE L’EXERCICE (FLUX) d'établissement et Néant Néant\nde présentation des\nACQUISITIONS ET AUGMENTATIONS D’IMMOBILISA- 155.847.951,19 16.710,00 états de syntèse\nTIONS (E)\n+ Acquisitions d'immobilisations incorpor.\n+ Acquisitions d'immobilisation corporelles 4.500,00 16.510,00\n+ Acquisitions d'immobilisation financières 155.843.451,19 200,00 ETAT DES CHANGEMENTS DE METHODES\n+ Augmentation des créances immob.\nNATURE DES JUSTIFICATION DES INFLUENCE SUR LE PATRIMOINE, LA SITUATION FINANCIERE ET\n* REMBOURSEMENT DES CAPITAUX PROPRES (F) CHANGEMENTS CHANGEMENTS LES RESULTATS\n* REMBOURSEMENTS DES DETTES DE FINANCE-\nMENT (G) Hausse des dotations aux amortissements : 2.220.561,35 decomposée\n* GI II LE I T I OM .O BVP T A AL A R LO L II AS - T E .E FIM ON .GNP N L DO O UN IS BV S EA T SL A OE B IU NLR E DS S E ( (H FE) I+ NF A+ NG C+ EH M) ENT 155.847.951,19 29.187.972,86 3 35 62 9. .3 04 50 0, ,0 000 22.515.110,78 I a m d f- ’éf é C e vtc hh at oa la udn n aeg t tse il o m e nse nts B d c a 2o 0n’a a n 2si ms 0s às to re pr u atd ci rse t tis iol rea n m d sd e eu d jnr e aé t n 4e d v0 e i es à r 25 c - - d S o ’ oH H Ia mm ima a t pu um :o as s re cs s t te e is s u d d s ui ee et ms s : ea a e m m n réto o s:r r u1t ti i l.s s t9 as s 7 te e 2 m m d.2 ee e 0 ln n 2 ’et t ,s s 7 1 er s ré u cs i itu cel t à a n l -at bd .a 2e i sl 0a s e 5r é 6dé 1ev 3a d 5l uu ra ét eio n : 248.358,64\n( B ) - s r l x e : 2 2 . ,\n- Impact sur l’actif net : - 2.220.561,35\nIV. VARIATION DE LA TRESORERIE 2.860.903,47 3.097.365,88 II - Changements\naffectant les règles Néant Néant\nTOTAL GENERAL 158.708.854,66 158.708.854,66 369.050,00 369.050,00 de présentation\nTABLEAU DES AMORTISSEMENTS\nNATURE Cumul début exercice 1 Dotation de l’exercice 2 Amortissements sur immobilis- sortie 3s Cumul d’amortissement fin 4 e =x e 1r +c 2ic -e 3\nIMMOBILISATION EN NON-VALEURS 27.462.192,19 7.509.882,09 4.463.610,35 30.508.463,93\n* Frais préliminaires 6.400.004,67 2.111.852,23 8.511.856,90\n* Charges à répartir sur plusieurs exercices 21.062.187,52 5.398.029,86 4.463.610,35 21.996.607,03\n* Primes de remboursement des obligations\nIMMOBILISATIONS INCORPORELLES\n* Immobilisation en recherche et développement\n* Brevets, marques droits et valeurs similaires\n* Fonds commercial\n* Autres immobilisations incorporelles\nIMMOBILISATIONS CORPORELLES 42.679.594,27 13.839.744,56 56.519.338,83\n* Terrains\n* Constructions 42.679.594,27 13.839.744,56 56.519.338,83\n* Installations techniques; matériel et outillage\n* Matériel de transport\n* Mobilier, matériel de bureau et aménagements\n* Autres immobilisations corporelles\n* Immobilisations corporelles en cours\nTOTAL GENERAL 70.141.786,46 21.349.626,65 4.463.610,35 87.027.802,76\nTABLEAU DES TITRES DE PARTICIPATION\nR dea i ls ao sn o s co iéc tia él ée mettrice N° IF dS ’ae cc 1tt ie vu itr é C sa op c 2i it aa ll Part eic n 3i p %ation Prix d g’a loc 4q bu alisition compV ta al b 5e lu er nette Date de 6 c E lôx tt ura reit des de Sr in tuie ar ts io 7é nt a nt es t td ee synthèse de la so Rc éié st ué l 8 té am t ne ett trice au P Cr .o Pd .Cu i dts e 9 i ln ’es xc eri rt cs i ce\nIMR FREE ZONE 24917016 IMMOBILIER 234.876.379,99 100,00 234.876.559,10 234.876.559,10 31/12/2022 126.067.739,15 -150.320,49\nAMLAK ATRIUM 40222202 IMMOBILIER 66.000.000,00 100,00 105.302.840,57 105.302.840,57 31/12/2022 69.704.220,29 4.043.424,14\nAMLAK CONTEMPO 40241136 IMMOBILIER 66.000.000,00 100,00 108.729.725,15 108.729.725,15 31/12/2022 77.752.310,10 3.295.631,45\nSPI SYHATI IMMO 0 IMMOBILIER 00,00 0,00 50.000.000,00 50.000.000,00 31/12/2022 0,00 0,00\nTOTAL 366.876.379,99 498.909.124,82 498.909.124,82 273.524.269,54 7.188.735,10\nTABLEAU DES PROVISIONS\nNATURE Monta en xt ed ré cb icu et D'exploitation DOT FA iT nI aO nN cS ières Non courantes D'exploitation FR iE nP anR cIS ièE rS es Non courantes Mon et xa en rt c if cin e\n1. Provisions pour dépréciation de l’actif immobilisé\n2. Provisions réglementées\n3. Provisions durables pour risques et charges\nSOUS TOTAL (A)\n4. Provisions pour dépréciation de l’actif circulant (hors trésorerie)\n5. Autres Provisions pour risques et charge 932.918,38 4.907,00 932.918,38 4.907,00\n6. Provisions pour dépréciation des comptes de trésorerie\nSOUS TOTAL (B) 932.918,38 4.907,00 932.918,38 4.907,00\nTOTAL (A+B) 932.918,38 4.907,00 932.918,38 4.907,00"
            }
        ],
        [],
        [
            {
                "MASSES": "",
                "": "Ressources\nD",
                "VARIATION A-B": "Emplois\nC"
            }
        ],
        [
            {
                "I RESSOURCES STABLES DE L’EXERCICE (FLUX)": "",
                "EXERCICE": "EMPLOIS",
                "null": "RESSOURCES",
                "EXERCICE PRECEDENT": "EMPLOIS"
            }
        ],
        [],
        [],
        [],
        [],
        [],
        [],
        [
            {
                "Raison sociale\nde la société émettrice": "",
                "N° IF": "",
                "Secteur\nd’activité\n1": "",
                "Capital\nsocial\n2": "",
                "Participation\nen %\n3": "",
                "Prix d’acquisition\nglobal\n4": "",
                "Valeur\ncomptable nette\n5": "",
                "Extrait des derniers états de synthèse de la société émettrice": "Date de clôture\n6",
                "null": "Résultat net\n8",
                "Produits inscrits\nau C.P.C de l’exercice\n9": ""
            }
        ],
        [
            {
                "NATURE": "",
                "Montant début\nexercice": "",
                "DOTATIONS": "D'exploitation",
                "null": "Non courantes",
                "REPRISES": "D'exploitation",
                "Montant fin\nexercice": ""
            }
        ],
        [
            {
                "COMPTES SOCIAUX\nAU 31 DÉCEMBRE 2023": "TABLEAU DES CREANCES TABLEAU DES DETTES\nANALYSE PAR ECHEANCE AUTRES ANALYSES ANALYSE PAR ECHEANCE AUTRES ANALYSES\nCREANCES TOTAL Plus d'1 an Moins d'1 an reE ce oc th u nu vo re n és e s Mo dn et va in st es s en os rM u g pro a u ln n' bét i la st ia cn m stt s ee st enM s tr luo ie én r p et l ra e sin s st e s re pM p ao r rén est fa e fn ent tts sé s DETTES TOTAL Plus d'1 an Moins d'1 an reE ce oc th u nu vo re n és e s M do en vet in sa en sts os rM u g pro a u ln n' bét i la st ia cn m stt s ee st enM s tr luo ie én r p et l ra e sin s st e s re pM p ao r rén est fa e fn ent tts sé s\nDE L'ACTIF 20.899.016,00 0,0020.899.016,00 0,00 20.899.016,00 0,00 20.899.016,00 0,00 DE FINANCEMENT 125.072.056,995.072.056,99 120.000.000,00 0,00 0,00 0,00 0,00 0,00\nIMMOBILISE\nEmprunts\nPrêts obligataires\nimmobilisés Autres dettes de 125.072.056,99 5.072.056,99 120.000.000,00\nAutres 20.899.016,00 20.899.016,00 20.899.016,00 20.899.016,00 financement\ncréances\nfinancières DU PASSIF 9.376.266,441.803.223,85 7.384.042,59 0,00 0,00 2.437.952,66 6.131.745,33 0,00\nCIRCULANT\nD CIE R L C' UA LC AT NIF T 18.869.712,854.133.567,0914.736.145,76 0,00 0,0011.602.103,02 5.156.096,04 0,00 Fournisseurs, 6.578.336,00 6.578.336,00 6.131.500,00\net acomptes\nFournisseurs 1.200,00 1.200,00 rattachés\nd avé ab nit ce eu sr s e t Clients créditeurs\nacomptes Personnel\nClients et 6.682.191,87 6.682.191,87 4.739.504,43 Organismes\ncomptes sociaux\nrattachés Etat 2.437.952,66 1.803.023,85 634.928,81 2.437.952,66 45,33\nPersonnel Comptes\nEtat 11.602.103,02 4.118.567,09 7.483.535,93 11.602.103,02 d'associés\nComptes Autres créanciers 210.200,00 200,00 21.000,00 200,00\nd’associés Comptes de 149.777,78 149.777,78\nAutres 416.591,61 416.591,61 416.591,61 régularisation-\ndébiteurs passif\nCompte de 167.626,35 13.800,00 153.826,35 Totaux 134.448.323,436.875.280,84 127.384.042,59 0,00 0,00 2.437.952,66 6.131.745,33 0,00\nrégularisation\nactif\nTotaux 39.768.728,854.133.567,0935.635.161,76 0,00 20.899.016,0011.602.103,02 26.055.112,04 0,00 RÉSUMÉ DU RAPPORT GÉNÉRAL DES COMMISSAIRES\nAUX COMPTES SUR LES COMPTES SOCIAUX\nTABLEAU DES SURETES REELLES DONNEES OU RECUES\nT oi ue r ts ie c rr sé dd éit be iu ter us rs paM rc o lo aun v st ea ûrn rt et té Na ( t 1u )re d D ’ina ste c re it p l ti ie ou n (2 O ) b j e (3t ) à V la s al û e n dru ae er tt t et éc e o dd dm eoe n cp l n lt a ôa é tb e ul re e 7 C, a B sao bu ll ae nva card Driss Slaoui 4 C, a P sala bc le a nM ca aréchal\nSûretés données Aux actionnaires de la société\nIMMORENTE INVEST S.A.\nHypothèque de premier rang sur le TF 5/7, Rue Ibnou Toufaïl\nN le° c8 a9 d5 r7 e/ 7 d1 ’u a nu c p rr éo df ii tt àd e lo C nF gG t eB rA mN eK d d ea Mn As D 100.000,00 Hypothèque 2023/09/18 E bam np cr au irn et non définie Casablanca Rapport Général des commissaires aux comptes\n90.000.000. Exercic Ae ud du i t1 der e j sa n év taie tr s a du e 3 s1 y nd té hc èe sm ebre 203\nNantissement de 700000 actions détenues Opinion\np d da e er l al F’ e s Gm o c dp i aér nu té sn t A lee M u cr L Ad dKa ren A s dT ’l uRe Ic U ca M rp éi at da u il ps dro eoc Mfi ia t Al 90.000.000,00 Nantissement 2023/09/18 E bam np cr au irn et non définie C d coe to cn s hf y po an lér rtm gh meèé essm n,e te a’c én ii rtt - jà o il En da t sm Cd i ss e )os li Cao n es soq cu édii teé an t tgéo u I dM ss ia M né yO nt é R c E èo tN sn ebTfi lEé oe aI N up a V er E sv S so oT ntr ae tS A . cA us n.s , e mq em u onib tc l té po ae om tG p drr é ee l’n n cé xn ar ee pa rn il te at cd l ue eu b p1 i ll r3 a na v ra er ui sl e2 3 et0 1 2 ad 1 sdé, cn meo emu lés ab ira e dv eo 2 n q0 Ms u2 Ae3e D,f lf ’le ée 7c 2actu 2o é .m el 1p’a 6tu e .id di 9ft e 2d ,p me 1rs 5o é d diot u oa ni ntt ss\nC a n t D e m l a e t ( e T s I . l d e s se et o s , l te h a fe n t rd e fi r in r e m n n u e c i x c o os p à c t te sa it , i s n s i t t d 5 s 7n o r a t s t\n90.000.000. un bénéfice net de MAD 4.426.447,49.\nSûretés reçues Nous certifions que les états de synthèse cités au premier paragraphe ci-dessus sont réguliers et sincères et donnent, dans tous leurs\naspects significatifs, une image fidèle du résultat des opérations de l’exercice écoulé ainsi que de la situation financière et du patrimoine de\nla société IMMORENTE INVEST S.A. au 31 décembre 2023 conformément au référentiel comptable en vigueur au Maroc.\nNEANT Fondement de l’opinion\nNous avons effectué notre audit selon les Normes de la Profession au Maroc. Les responsabilités qui nous incombent en vertu de ces\nnormes sont plus amplement décrites dans la section « Responsabilités de l’auditeur à l’égard de l’audit des états de synthèse » du\n(1) Gage : 1- Hypothèque : 2- Nantissement : 3- Warrant : 4- Autres : 5- (à préciser). présent rapport. Nous sommes indépendants de la société conformément aux règles de déontologie qui s’appliquent à l’audit des états\n(2) Préciser si la sûreté est donnée au profit d’entreprises ou de personnes tierces (sûretés données) (entreprises liées, associés, nombre du personnel). de synthèse au Maroc et nous nous sommes acquittés des autres responsabilités déontologiques qui nous incombent selon ces règles.\n(3) Préciser si la sûreté reçue par l’entreprise provient de personnes tierces autres que le débiteur (sûretés reçues). Nous estimons que les éléments probants que nous avons obtenus sont suffisants et appropriés pour fonder notre opinion d’audit.\nQuestions clés de l’audit\nLes questions clés de l’audit sont les questions qui, selon notre jugement professionnel, ont été les plus importantes dans l’audit des états\nENGAGEMENTS FINANCIERS RECUS OU DONNES HORS OPERATIONS DE CREDIT-BAIL de synthèse de la période considérée. Ces questions ont été traitées dans le contexte de notre audit des états de synthèse pris dans leur\nensemble et aux fins de la formation de notre opinion sur ceux-ci, et nous n’exprimons pas une opinion distincte sur ces questions.\nRisque identifié Notre réponse\nENGAGEMENTS DONNES M Exo en rta cin ct es M cio cn et Pa rn éts c éE dx ee nr t- T Ai utr 3e 1s dd ée c p ea mrt bi rc eip 2a 0t 2io 3n , les titres de participation sont inscrits au bilan pour une P lao vu ar lea up rp dré ’uc ti ie lir té l e d ec sa r ta itc retè sr e d er a pis ao rtn icn ipa ab tle io nd ,e s ul’e r s latim ba at sio en d d ee s\n- Avals et cautions Néant Néant v pa ril xe u hr i sb toru rit qe u ee t dn ’ae ctt he a c t.omptable de KMAD 498.909. Ils sont comptabilisés au i on nfo t r cm oa nt sio isn tés q pu rini cn io pu as le mon et n é t t àé :c ommuniquées, nos travaux\n- Engagements en matière de pensions de retraites et obligations similaires Néant Néant La Société procède, à chaque clôture annuelle, à l’évaluation de la valeur Pour les évaluations reposant sur des éléments historiques\nactuelle de ses titres de participation. Cette valeur actuelle est estimée soit - Vérifier que les quotes-parts d’actif net retenues\n- Autres engagements donnés Néant Néant en fonction de l’actif net comptable, soit en fonction de la rentabilité et des concordent avec les comptes des entités et que les\nEngagement envers CFG de ne pas constituer une garantie, sureté un droit réel, une charge ou un p Ee nr s cp ae sc dtiv ee bs a id s’ sa ev e dn uir r abd lu e dtit ere l. a valeur actuelle et si celle-ci est inférieure à la r dé oé cv ua mlu ea nti to an tis o no pé pr ré oe bs a, nle te c as ; échéant, sont fondées sur une\nprivilège quelconque sur les biens donnés en garantie en faveur de la Banque et sur le bien objet Non défini Néant valeur nette comptable, une provision pour dépréciation est constituée. Pour les évaluations reposant sur des éléments prévisionnels\ndu titre foncier n°44835/61 dans le cadre du crédit de MAD 90.000.000. L’estimation de la valeur actuelle des titres requiert l’exercice du jugement de - Prise de connaissance de la méthode d’évaluation, des\nE den sg ta ing ae tm ioe nn dt ae nn sv e ler s c aC dF rG e dd ue cn re é dp ia t s d ea l Mté Are Dr 9la 0 .0va 0l 0e .u 00r 0d .e s garanties ou en changer la nature ou la Non défini Néant l c Da o a nD nci sr e e r cc n et éi o e cn s o .d na ten xs t es ,o nn o c uh so i ax v d oe ns s é elé sm time én ts q uà e c o lan s ci od ré rr ee cr t es e élo vn a ll ue as t ip oa nr t dic eip sa tt ii to ren ss a é - c vt a Pif l rs u o a ci tm ée dum erso r b ii àmlie mr us o nbd eié lit ee cr on s mu s ; p ap ra ar i sl oe ns f eili na tl re es , lr ae te vn au lee u rp a nr el te tes\nE non tg aa mge mm ee nn t,t p e an rv ae vr as l C s F oG u cd ae u n te io p na ss d d aé nl sé lg eu ce ar d o ru e c dé ud ce rr é s de its dr ee v Me Anu Ds 9 e 0t . 0g 0a 0r .a 0n 0t 0ie .s des dettes de tiers, Non défini Néant d ae ct ifp sa r dti ac nip sa lt eio n b ilc ao nn , s dti etu la ’ii mt u pn o rtp ao ni cn et c dlé e d lae pl a’a ru t d dit e, se jn u gr ea miso en n tsd u d ep o laid s D id ree c tc ioe ns c teo llm e p qt ua ’b el le le d re es s sti otr re t s d d ae n sp a ler stic éip va at li uo an ts io, ne st d ime mla o v ba ill ie èu rer sv ,é pn oa ule r\net des incertitudes dans la détermination des hypothèses de flux de trésorerie, s’assurer de l’absence de moins-value latente.\nEngagement envers CFG de ne pas aliéner, transférer, céder ou faire apport à une autre société notamment la probabilité de réalisation des prévisions retenues par la Direction.\net plus particuliérement à un tiers de tout ou partie des biens donnés en garantie en faveur de la Non défini Néant\nbanque et du bien objet du titre n°44853/61 dans le cadre du prétt à long terme de MAD 90.000.000. Responsabilités de la direction et des responsables de la gouvernance à l’égard des états de synthèse\nLa direction est responsable de la préparation et de la présentation fidèle des états de synthèse, conformément au référentiel comptable\nEngagement envers CFG de ne pas contracter des dettes dont les charges cumulées avec celles en vigueur au Maroc, ainsi que du contrôle interne qu’elle considère comme nécessaire pour permettre la préparation d’états de\ndu présent prét risquent d’excéder sa capacité de remboursement dans le cadre du crédit de MAD Non défini Néant synthèse exempts d’anomalies significatives, que celles-ci résultent de fraudes ou d’erreurs.\n90.000.000. Lors de la préparation des états de synthèse, c’est à la direction qu’il incombe d’évaluer la capacité de la société à poursuivre son\nexploitation, de communiquer, le cas échéant, les questions se rapportant à la continuité de l’exploitation et d’appliquer le principe\nEngagement envers CFG de ne pas procéder à toute opération de fusion ou dissolution, ou réduc- comptable de continuité d’exploitation, sauf si la direction a l’intention de liquider la société ou de cesser son activité ou si aucune autre\nt si ao n s id tue a c ta iop nit a jul rq idu ii q n ue e s oe ura fi it n p aa ns c il èé rg ea dle em l’e En mt r pe rq uu ni ts ee u e r t e p t/lu ous g laé n Cé ar ua tl ie om n se an nt sà lt ’o au ct c c oh rdan pn rg ée am labe ln et dd ea n las Non défini Néant s Il o inlu ct oio mn b r eé a al uis xte r en se p os n’o sff ar be l eà s e dll ee . la gouvernance de surveiller le processus d’information financière de la société.\nbanque dans le cadre du crédit de MAD 90.000.000.\nResponsabilités de l’auditeur à l’égard de l’audit des états de synthèse\nEngagement envers CFG de rerspecter l’affectation du crédit et plus généralement tout fait sus- Nos objectifs sont d’obtenir l’assurance raisonnable que les états de synthèse pris dans leur ensemble sont exempts d’anomalies significatives,\nc lae p Ct aib ul te io d n’ ,a off ue c dt ’e ar u s gé mri ee nu ts ee rm see nn st il b’i lm empo er nt ta n lec e v oo lu u mla e v da ele lu er u d rsu ep na gtr ai gm eo min ee n td se t el’ lE qm up er u pn réte vu ur e e dt a/o nu s Non défini Néant q àu ue n c ne ivlle es a- uc i é ré les vu élt e dn ’at s d se u rfr aa nu cd ee , s q uo iu n d e’e gr are rau nrs ti te tt o d ue te d foé il siv r pe ar s u qn u r ’a up np ao urt d d ite r él’a au lisd éit e cu or n c foo rn mte én man et n n t o at ure x o np oi rn mio en s. dL’ ea s las u pr ra on fec se s r ioa nis o an un Mab al re o c co pr ere rmsp eo tn trd a\nl’article 2 du contrat du crédit de MAD 90.000.000. toujours de détecter toute anomalie significative qui pourrait exister. Les anomalies peuvent résulter de fraudes ou d’erreurs et elles sont\nconsidérées comme significatives lorsqu’il est raisonnable de s’attendre à ce que, individuellement ou collectivement, elles puissent influer sur\nDélégation envers CFG BANK de la totalité des dividendes rattachés aux actions nanties qui lui les décisions économiques que les utilisateurs des états de synthèse prennent en se fondant sur ceux-ci.\nserait servis par la société AMALK ATRIUM à hauteur du montant de chacune des échéances de Non défini Néant Dans le cadre d’un audit réalisé conformément aux normes de la profession au Maroc, nous exerçons notre jugement professionnel et\nremboursement du crédit dans le cadre du crédit de MAD 90.000.000. faisons preuve d’esprit critique tout au long de cet audit. En outre :\n• nous identifions et évaluons les risques que les états de synthèse comportent des anomalies significatives, que celles-ci résultent\nE non tg aa mge mm ee nn t,t pe an rv ae vrs a lC s F oG u d cae u n te io p na ss d d aé nl sé g leu ce ar do ru e c dé ud ce rr é s de its dr ee v Men Au Ds 3 e 0t . 0g 0a 0ra .0n 0t 0ir . des dettes de tiers, Non défini Néant d ée lé mfra eu nd tse s p ro ou b ad n’e tsrr e su ur ffs is, ac no tn sc e ev t o an ps p re ot p m riée stt o pn os u re n fo nœ du ev r re n od tre es op pro inc ioé nd .u r Le es rd is’a qu ud ei t de en nré op no -dn és te e cà ti oc ne s d ’r uis nq eu e as n, o e mt ar lé ieu n si is gs no ifn ics a d tive es\nEngagement envers CFG de ne pas aliéner, transférer, céder ou faire apport à une autre société et résultant d’une fraude est plus élevé que celui d’une anomalie significative résultant d’une erreur, car la fraude peut impliquer la\nplus partuculiérement à un tiers de tout ou partie des biens que l’Emprunteur a donné en garantie Non défini Néant collusion, la falsification, les omissions volontaires, les fausses déclarations ou le contournement du contrôle interne ;\nen faveur de la Banque dans le cadre du crédit de MAD 30.000.000. • d ’n ao uu ds it a ac pq pu roé pro rin és e su n ae u xc co im rcp or né sh tae nn cs eio sn , ed te ns oé nlé dm ae nn st s le d bu u tc o dn ’et xrô pl re im in et re r un ne e p oe pr it nin ioe nn t ss u p r o l’u er ff il c’a au cd iti ét a df uin c d oe n trc ôo ln ec ie nv teo ri nr ed e ds e p laro sc oé cd iéu tr ée s ;\nEngagement vers CFG de ne pas contracter des dettes dont les charges éventuelles, cumulées • nous tirons une conclusion quant au caractère approprié de l’utilisation par la direction du principe comptable de continuité\navec celles des emprunts actuels de l’Emprunteur, risquent d’excéder sa capacité de rembouse- Non défini Néant d’exploitation et, selon les éléments probants obtenus, quant à l’existence ou non d’une incertitude significative liée à des\nment dans le cadre du crédit de MAD 30.000.000. événements ou situations susceptibles de jeter un doute important sur la capacité de la société à poursuivre son exploitation. Si\nnous concluons à l’existence d’une incertitude significative, nous sommes tenus d’attirer l’attention des lecteurs de notre rapport\nEngagement envers CFG de ne pas procéder à toute opération de fusion, dissollution, ou réduc- sur les informations fournies dans les états de synthèse au sujet de cette incertitude ou, si ces informations ne sont pas adéquates,\nt ci oo nn t rd ôe l ec a cp oi nta fol rq mu éi mne e nse t r àa li ’t a p rta ics l elé 1g 4a 4le dm e e lan t l or ie 1q 7u -i 9s 5e re et l ap tl iu vs e g aé un x é sr oa cl ie ém tée sn at n à o nto yu mt ec sh da an ng se m lee cn at d d re e Non défini Néant d é’ ve éx np eri mm ee nr tu sn oe u o p sii tn uio an tio m nso d fuifi té ue re. sN o ps o uc ro rn ac ielu ns t io pn as r s a’ ia llep up ru sie an mt s eu nr e le r s la é l sé om cie én téts àp r co eb sa sn ets r so ob nte n eu xps lj ou is taq tu io’à n l ;a date de notre rapport. Des\ndu crédit de MAD 30.000.000. • nous évaluons la présentation d’ensemble, la structure et le contenu des états de synthèse, y compris les informations fournies\ndans l’ETIC, et apprécions si les états de synthèse représentent les opérations et événements sous-jacents d’une manière propre\nEngagement envers CFG de respecter l’affectation du crédit et plus généralement tout fait suscep- à donner une image fidèle.\nt mib ele n td e’ ra sff ee nc ste ibr l es mér eie nu ts le em voe ln ut m l’ eim dp eo sr eta sn ec ne g o au g el ma v ea nl te su tr e d l u qu p ea ptr ri ém vo ui en e d ad ne s l l’ ’E am rtip cr lu en 2t e du ur co ou n td r’ aa tu dg u- Non défini Néant N coo nu ss t ac tao tm iom nsu n imiq pu oo rn tas n a teu sx , yre cs op mon ps ria sb tl oe us t ed e d éla fic g ieo nu cv ee r imna pn oc re ta nn to et a dm u m coe nn tt r ôl’ lé et e inn td eu rne e e qt ul ee nc oa ule sn ad uri re ior np sr é rv eu les v éd ee s a utr a cv oa uu rsx dd e’a nu od ti rt e e at un do its .\nprét de MAD 30.000.000. Vérifications et informations spécifiques\nEngagement envers CFG à domicilier irrévocablement, les flux de la société sur le compte ban- Nous avons procédé également aux vérifications spécifiques prévues par la loi et nous nous sommes assurés notamment de la\ncaire ouvert dans les livres de CFG BANK au prorata des financements bancaires octroyés par la Non défini Néant sincérité et de la concordance, des informations données dans le rapport de gestion du Président du Conseil d’Administration\nbanque dans le cadre du crédit de MAD 30.000.000. destiné aux actionnaires avec les états de synthèse de la société.\nConformément aux dispositions de l’article 172 de la loi n° 17-95 telle que modifiée et complétée, nous portons à votre\nTOTAL (Dont engagements à l’égard d’entreprises liées) connaissance qu’au cours de cet exercice, la Société Immorente Invest a souscrit une participation pour un montant de DH 50\nmillions dans le capital de la SPI « SYHATI IMMO SPI ».\nCasablanca, le 26 février 2024\nENGAGEMENTS RECUS M Exo en rta cin ct es M cio cn et Pa rn éts c éE dx ee nr t- Les Commissaires aux Comptes\n- Avals et cautions Néant Néant\n- Autres engagements donnés\nGarantie Actif Passif donnée à IMMORENTE INVEST par les actionnaires cédant les Non défini Non défini\nfiliales AMLAK ATRIUM et AMLAK CONTEMPO (fiscal et social)\nTOTAL"
            }
        ],
        [
            {
                "CREANCES": "",
                "TOTAL": "",
                "ANALYSE PAR ECHEANCE": "Plus d'1 an",
                "null": "Montants\nreprésentés\npar effets",
                "AUTRES ANALYSES": "Montants en\ndevises"
            }
        ],
        [
            {
                "DETTES": "",
                "TOTAL": "",
                "ANALYSE PAR ECHEANCE": "Plus d'1 an",
                "null": "Montants\nre pp ar ré es fe fen tt sés",
                "AUTRES ANALYSES": "Montants\nen\ndevises"
            }
        ],
        [],
        [],
        [],
        []
    ]
}