{
    "text": "COMMUNIQUÉ FINANCIER ANNUEL\nÉTATS DE SYNTHÈSE SOCIAUX ET CONSOLIDÉS\nEXERCICE CLOS LE 31 DÉCEMBRE 2023\nFaits marquants et analyses des principaux indicateurs de résultats\nEngagement en faveur du pouvoir d’achat et baisse des prix en 2023\nRépercussions défavorables sur les marges et les résultats 2023\nAnticipation d’un retour à un niveau normatif pour 2024\nIndicateurs consolidés IFRS\nEn MDh 2022 2023 Variation\nChiffre d'affaires 6 897 5 934 -14%\nRésultat d'exploitation 463 74 -84%\nRésultat net part du groupe 206 2,5 -99%\nAu cours de l’exercice 2023, Lesieur Cristal, forte de son empreinte citoyenne et responsable, a baissé les prix des huiles\nde table pour répondre aux préoccupations économiques et sociales des consommateurs marocains. Elle a également\nmaintenu son engagement de non-répercussion de la hausse des prix des matières premières sur les consommateurs eu\négard à un contexte inflationniste persistant. Parallèlement, une évolution des habitudes de consommation a été observée,\navec une orientation vers les produits d’entrée de gamme. Les autres segments d’activité du Groupe, à savoir, l’huile\nd’olive, le savon et la margarine, ont quant à eux affiché des performances solides, ce qui a permis d’atténuer l’impact\nde l’activité huiles de table sur le chiffre d’affaires du Groupe. Lesieur Cristal a clôturé l’exercice avec un chiffre d’affaires\nannuel de 5 934 MDH, marquant une baisse de 14%.\nLa mise en place d’une stratégie de couverture à long terme des matières premières, amorcée au second semestre\n2022, a certes permis d’assurer la continuité de l’approvisionnement du marché, mais a cependant pesé sur les marges\nen raison des coûts élevés d’acquisition des stocks. Pour atténuer ces effets, des efforts soutenus en matière d’efficacité\nopérationnelle ont été déployés. Le résultat d’exploitation et le résultat net part du groupe s’établissent respectivement à\n74 MDH et 2,5 MDH.\nEn alignement avec ses objectifs stratégiques, Lesieur Cristal a poursuivi le déploiement de sa nouvelle Route-to-Market,\ninitié en 2022, qui couvre désormais plus de 80% du territoire national. Par ailleurs, dans une démarche visant à renforcer\nson lien avec les consommateurs, le Groupe a lancé de nouvelles plateformes de communication pour promouvoir ses\nmarques phares.\nEn 2023, fidèle à ses valeurs, Lesieur Cristal a revu sa stratégie RSE, désormais au cœur de son plan stratégique à horizon\n2027. Cette nouvelle politique engage le Groupe à créer une valeur durable pour toutes ses parties prenantes, tout en\npréservant ses ressources et son environnement.\nPerspectives & stratégie de développement\nGrâce à la baisse des prix des intrants conjuguée à une stratégie de couverture adaptée au contexte actuel, le Groupe\nanticipe un redressement des marges et un retour à un niveau normatif en 2024.\nCapitalisant sur les contrats programmes signés lors du SIAM 2023, Lesieur Cristal s’inscrit dans la stratégie nationale «\nGénération Green » et renforce son ambition de développer l’amont agricole contribuant à répondre ainsi aux enjeux de\nsécurité alimentaire du Maroc et dans les pays dans lesquels elle opère.\nLe Groupe a également pour ambition d’élargir sa présence en Afrique à travers notamment des opérations d’acquisitions,\navec un modèle opératoire d’un acteur local engagé et la promotion d’un amont agricole durable.\nSiège social : 1, rue caporal Corbi, Pour consulter le Rapport Financier Annuel comprenant les états financiers\n20 300 Roches Noires - Casablanca - R.C 4171 ICE sociaux et consolidés de Lesieur Cristal au 31 décembre 2023 :\n001569079000005 - Tél. : (+212) 522 67 93 00 https://www.lesieur-cristal.com/communication_financiere/rapports-financiers/\nÉTATS FINANCIERS CONSOLIDÉS\nEXERCICE CLOS LE 31 DÉCEMBRE 2023\nBILAN ACTIF COMPTE DE RÉSULTAT CONSOLIDÉ\nACTIF (En millions de dirhams) 31-déc-23 31-déc-22 (En millions de dirhams) 31-déc-23 31-déc-22\nGoodwill 109 109 Chiffre d'affaires 5 934 6 897\nAutres produits de l'activité 222 261\nImmobilisations incorporelles, net 201 205\nProduits des activités ordinaires 6 156 7 157\nImmobilisations corporelles, net 1 038 1 027\nAchats -5 324 -5 646\nActifs biologiques 38 38 Autres charges externes -380 -444\nImmeubles de placement, net 4 4 Frais de personnel -284 -318\nParticipations dans les entreprises associées 24 26 Impôts et taxes -12 -14\nAmortissements et provisions d'exploitation -78 -270\nAutres actifs financiers 28 29\nAutres produits et charges d'exploitation nets -4 -2\n- Prêts et créances, net 7 9\nCharges d'exploitation courantes -6 082 -6 694\n- dont titres de participation consolidés -1 -1 RÉSULTAT D'EXPLOITATION COURANT 74 463\n- Actifs financiers disponibles à la vente 21 21 Autres produits et charges d'exploitation non courants -1 -83\nAutres débiteurs non courants 80 88 Autres produits et charges d'exploitation -1 -83\nRésultat des activités opérationnelles 72 380\nImpôts différés actifs 31 43\nProduits d'intérêts 19 14\nActif non courant 1 553 1 570\nCharges d'intérêts -38 -28\nAutres actifs financiers 610 490 Résultats sur instruments financiers 2 -11\n- Instruments financiers dérivés 604 484 Autres produits et charges financiers -17 -3\nRésultat financier -34 -28\n- Prêts et créances et placements, net 6 6\nRésultat avant impôt des entreprises intégrées 38 352\nStocks et en-cours, net 1 485 1 770\nImpôts sur les bénéfices -75 -195\nCréances clients, net 812 995 Impôts différés 33 33\nAutres débiteurs courants, net 406 463 Résultat net des entreprises intégrées -3 190\nTrésorerie et équivalent de trésorerie 373 1 452 Part dans les résultats des sociétés mises en équivalence 0 3\nRésultat net des activités poursuivies -3 193\nActif courant 3 687 5 170\nRésultat net des activités abandonnées\nTOTAL ACTIF 5 240 6 740\nRésultat de l'ensemble consolidé -3 193\nDont Intérêts minoritaires 5 12\nDont Résultat net - Part du Groupe 2 206\nRésultat net par action en dirhams\nBILAN PASSIF - de base 0 7\n- dilué 0 7\nPASSIF (En millions de dirhams) 31-déc-23 31-déc-22\nCapital 276 276\nRéserves 1 544 1 401\nTABLEAU DES FLUX DE TRÉSORERIE CONSOLIDÉ\nÉcarts de conversion -11 -12\nRésultat net part du groupe 2 206 (En millions de dirhams) 31-déc-23 31-déc-22\nCapitaux propres attribuables aux actionnaires ordinaires de la société Résultat net de l’ensemble consolidé -3 193\n1 812 1 871\nmère\nAjustements pour :\nIntérêts minoritaires -10 -5\nRésultats des sociétés mises en équivalence -0 -3\nCapitaux propres de l’ensemble consolidé 1 802 1 866\nDotations aux amortissements et provisions, pertes de valeur 106 166\nProvisions 83 95\nProfits / pertes de réévaluation (juste valeur) 94 -20\nAvantages du personnel 206 269\nRésultats de cession et des pertes et profits de dilution -23 -20\nDettes financières non courantes 191 173\nCapacité d’autofinancement après coût de l’endettement financier net et\n173 316\n- Dettes envers les établissements de crédit 1 0 impôt\n- Dettes liées aux contrat de location financement 190 173 Élimination de la charge (produit) d’impôts 42 164\nDettes d’impôts sur les sociétés 12 12 Élimination du coût de l’endettement financier net 38 28\nImpôts différés Passifs 48 48 Capacité d’autofinancement avant coût de l’endettement financier net\n253 507\nimpôt\nPassif non courant 540 596\nIncidence de la variation du BFR -946 279\nDettes financières courantes 1 021 804\nImpôts différés 4 -8\n- Instruments financiers dérivés 612 442\nImpôts payés -231 -112\n- Dettes envers les établissements de crédit 409 362\nFlux net de trésorerie liés aux activités opérationnelles -919 666\nDettes fournisseurs courantes 1 712 3 209\nAcquisition d’immobilisations corporelles et incorporelles -81 -93\nAutres créditeurs courants 165 266\nVariation des autres actifs financiers 1 -\nPassif courant 2 898 4 278\nCessions d’immobilisations corporelles et incorporelles - 0\nTOTAL PASSIF 3 438 4 875\nDividendes reçus 1 0\nTOTAL CAPITAUX PROPRES ET PASSIF 5 240 6 740\nIntérêts financiers versés -38 -28\nFlux net de trésorerie liés aux activités d’investissement -116 -120\nAugmentation et Réduction de capital - 7\nETAT DES AUTRES ÉLÉMENTS DU RÉSULTAT GLOBAL\nÉmission de nouveaux emprunts 1 0\n(En millions de dirhams) 31-déc.-23 31-déc.-22 Dividendes payés aux actionnaires de la société mère -124 -97\nRésultat de l’exercice -3 193\nVariation de comptes courants associés 26 -13\nAutres éléments du résultat global (bruts d’impôts)\nPartie efficace des produits ou pertes sur instruments de couverture de flux Flux net de trésorerie provenant des activités de financement -98 -102\n41 -65\nde trésorerie Incidence de la variation des taux de change 7 -12\nÉcarts actuariels sur les obligations des régimes à prestations définies 66 13\nImpôt sur le résultat sur les autres éléments du résultat global -39 21 VARIATION DE LA TRÉSORERIE ET ÉQUIVALENTS DE TRÉSORERIE -1 126 433\nAutres éléments du résultat global nets d’impôts 68 -31 Trésorerie et équivalents de trésorerie net à l’ouverture 1 092 657\nRÉSULTAT GLOBAL TOTAL DE L’ANNÉE 65 162\nTrésorerie et équivalents de trésorerie net à la clôture -34 1 090\nDont Intérêts minoritaires 5 -12\nDont Résultat global net - Part du Groupe 60 175 VARIATION DE LA TRÉSORERIE ET ÉQUIVALENTS DE TRÉSORERIE -1 126 433\nÉTATS FINANCIERS CONSOLIDÉS\nEXERCICE CLOS LE 31 DÉCEMBRE 2023\nTABLEAU DE VARIATION DES CAPITAUX PROPRES CONSOLIDÉS\nRéserves Non Réserves Réserves des opérations Total Capitaux propres Total capitaux\nEn millions de dirhams Capital Intérêt minoritaire\nDistribués de conversion de couverture part du groupe propres\nAu 1er janvier 2022 276 1 560 -10 -28 1 798 2 1 800\nEffets des changements de méthode comptable/correction d’erreur -6 -6 -6\nMontants retraités à l’ouverture 276 1 555 -10 -28 1 792 2 1 794\nVariation des capitaux propres\nRésultat de l’exercice - 206 - - 206 -12 193\nVariation nette de juste valeur des instruments financiers - - - -41 -41 - -41\nPertes et profits de conversion - - -1 - -1 -0 -1\nVariation de juste valeur écarts actuariels - - - 10 10 - 10\nRésultat global total de l’année - 206 -1 -31 174 -13 161\nDividendes distribués - -97 - - -97 - -97\nAugmentation de capital - 1 - - 1 6 7\nTotal des transactions avec les actionnaires - -96 - - -96 6 -90\nAu 31 décembre 2022 276 1 664 -11 -59 1 870 -5 1 866\nAu 1er janvier 2023 276 1 664 -11 -59 1 870 -5 1 866\nMontants retraités à l’ouverture 276 1 664 -11 -59 1 870 -5 1 866\nVariation des capitaux propres - - - - - - 0\nRésultat de l’exercice - 2 - - 2 -5 -3\nVariation nette de juste valeur des instruments financiers - - - 21 21 - 21\nPertes et profits de conversion - - 1 - 43 0 43\nRésultat global total de l’année - 2 1 63 67 -5 61\nDividendes distribués - -124 - - -124 - -124\nChangement de périmètre - -1 - - -1 0 -1\nTotal des transactions avec les actionnaires - -126 - - -126 0 -126\nAu 31 décembre 2023 276 1 541 -10 4 1 811 -10 1 802\nNOTES AUX COMPTES CONSOLIDÉS\nNOTE 1. DESCRIPTION DE L’ACTIVITÉ\nLesieur Cristal est une société anonyme de droit marocain, soumise à l’ensemble des textes régissant les sociétés commerciales au Maroc. La société a son siège social au 1, Rue du Caporal Corbi, Roches\nNoires – Casablanca et est cotée à la Bourse de Casablanca au 1er compartiment.\nLe Groupe Lesieur Cristal est spécialisé dans le secteur des corps gras (huiles alimentaires et margarines).\nLes comptes et informations sont présentés en millions de dirhams Marocains (MDH), sauf les informations par action qui sont présentées en dirhams.\nNOTE 2. ÉVÈNEMENTS SIGNIFICATIFS INTERVENUS AU COURS DE LA PÉRIODE\nAu cours de l’exercice 2023, le périmètre du Groupe Lesieur Cristal n’a pas connu de variations par rapport au 31 décembre 2022.\nNOTE 3. RÈGLES ET MÉTHODES COMPTABLES\nEn application de l’avis n°5 du Conseil National de la Comptabilité (CNC) du 26 mai 2005 et conformément aux dispositions des articles 2.7 et 2.8 de la circulaire 03/19 de l’Autorité Marocaine du Marché des\ncapitaux , les états financiers consolidés du Groupe Lesieur Cristal sont préparés en conformité avec les normes comptables internationales adoptées au sein de l’Union Européenne au 30 Juin 2023 et telles\nque publiées à cette même date.\nLes normes comptables internationales comprennent les IFRS (International Financial Reporting Standards), les IAS (International Accounting Standards) et leurs interprétations SIC et IFRIC (Standards\nInterpretations Committee et International Financial Reporting Interpretations Committee).\nLe Groupe suit régulièrement les dernières publications de l’IASB et de l’IFRIC.\nNOTE 4. PÉRIMÈTRE DE CONSOLIDATION AU 31 DÉCEMBRE 2023\nLESIEUR CRISTAL\nIG IG IG IG IG IG\n100% 100% 100% 93,9% 100% 99,96%\nSociété Les\nd’Exploitation de Domaines Olivco Cristal Indusalim Fireal\nTunisie\nl’Olive Jawhara\nIG IG MEE IG IG IG IG\n100% 100% 34% 93,9% 100% 100% 90,16%\nOleor Hay Al Habaib La Raffinerie Africaine Cristal Distribution Tawzii Lesieur Cristal Lesieur Cristal Inc. Oleosen\nNOTE 5. PRINCIPAUX IMPACTS DES RETRAITEMENTS IFRS\nLe résultat consolidé IFRS au 31 Décembre 2023 du Groupe Lesieur Cristal est impacté par les principaux retraitements suivants :\nIAS 37 Provisions : -18 MDH.\nÉlimination des dotations et reprises des provisions ne répondant pas aux critères de comptabilisation selon les normes IFRS.\nIAS 19 Avantage du personnel : -3 MDH.\nConstatation des avantages post emploi relatifs à la couverture médicale et aux indemnités de fin de carrière.\nIAS 39 Instruments Financiers : -6 MDH.\nReprise du solde d’actualisation du crédit de TVA (-8MDH), et la valorisation à la juste valeur des instruments financiers (2MDH).\nIAS 16 Immobilisations corporelles : +2.0 MDH.\nRetraitement des amortissements des immobilisations selon des durées économiques.\nIAS 38 Immobilisations incorporelles : -29 MDH.\nAnnulation des charges à répartir.\nIAS 12 Impôts sur le résultat : +33 MDH.\nConstatation des ID sur différences temporaires pour 4 MDH et 29 MDH relatifs aux ID des différents retraitements.\nÉTATS FINANCIERS CONSOLIDÉS\nEXERCICE CLOS LE 31 DÉCEMBRE 2023\n2. DEPRECIATION DES CREANCES CLIENTS\nRisque identifié Notre réponse\n4, Rue Maati Jazouli (Ex Rue Friol),l)\n3 2 M7 0 a, 0 rB o5 cd 0 A Cb ad se al bla latif n B caen Kaddour A Mn af ra o c– Casablanca L v mae ols e n uc tarr é nna t en dtc t ee e s a Mc uli Me n 3 At 1 Ds s d’ 2éé 1clè e 8v m e dbn ert e à p 2M r0 oM 2 vi3A s iD od no8 n1 pt2 o ue unn r L 2e 0s 2 3t ,r oa nva t u nx o tas mur m l ee ns t cc oo nm sip st te és e na u : 31 décembre\ndépréciation.\nC d’e us n ep r mov éis thio on ds e s so tn at t isd té iqte ur em i qn ué ie s s es ur b ala s eb a ss ue r  La fiabilisation de la balance âgée des\nAux Actionnaires de la société l’ancienneté de la créance (100% de solde pour créances clients en testant pour un\nL 1,E rS uI eE CU aR p C orR aI l S CT oA rbL i S.A. l ce rs é ac nré ca en sc ae ns t éa rn ieté ur ri ee su r àe s 6 à m 1 o a isn ) .e Ct 5 e0 p% en p do au nr t ,l e les  Lé ach an rétil alo lin sa l’ ta ion nc ien dn ee té tr ee st te sn ue r e; latifs à\nCasablanca management complète éventuellement cette l’apurement des créances en période\nrègle par une analyse au cas par cas intégrant subséquente ;\nd’autres indices de dépréciation (relation  Le recalcul de la provision sur la base de\nR S EU XA ERP R P L CO E IR S CT EE G T DAE UTN 1SE e R rF JA IN AL A N D N VE IC ES I RE C R AO S UM C 3M O 1I NS DSS EOA CI L ER I MDES E B S RA EU X 20 C 2O 3MPTES c d No e om s u som p ae é vr rc oai na ti sl oe n, c n oc eo nlu ss.v id.e . é)r . rt éu re l’e a ss tis mu ara tin oc ne d, ufe med o- nb ta ac nk t  Ll Ga a r om u répé aeth l i; so ad te io ns ta dt eis st iq eu ne t rer te iete nn su e a vep ca r lele s\nde la provision pour dépréciation des créances opérationnels pour s’assurer de l’absence\nclients comme un point clé de l’audit compte de créances clients bien que récentes\nOpinion tenu du caractère estimatif de ce processus et présentant un risque de recouvrement ;\nson impact significatif sur les comptes.\nNous avons effectué l’audit des états financiers consolidés de la société Lesieur Cristal S.A. et de ses\nfiliales (Groupe Lesieur Cristal), qui comprennent l’état consolidé de la situation financière au 31\ndécembre 2023, ainsi que le compte de résultat consolidé et l’état consolidé du résultat global, l'état\nconsolidé des variations des capitaux propres et le tableau consolidé des flux de trésorerie pour\nl’exercice clos à cette date, ainsi que les notes annexes, y compris des informations significatives sur\nles méthodes comptables. Ces états financiers consolidés font ressortir un montant de capitaux\npropres consolidés de MMAD 1.802 compte tenu d’un déficit net consolidé de MMAD 2,85.\nNous certifions que les états financiers consolidés cités au premier paragraphe ci-dessus sont réguliers\net sincères et donnent, dans tous leurs aspects significatifs, une image fidèle du résultat des opérations Responsabilités de la direction et des responsables de la gouvernance à l’égard des états\nde l’exercice écoulé ainsi que de la situation financière et du patrimoine du Groupe LESIEUR CRISTAL financiers consolidés\narrêtée au 31 décembre 2023, conformément aux Normes Internationales d’Information Financière\n(IFRS). La direction est responsable de la préparation et de la présentation fidèle des états financiers consolidés,\nconformément aux IFRS, ainsi que du contrôle interne qu'elle considère comme nécessaire pour permettre\nFondement de l’opinion la préparation des états financiers consolidés d'anomalies significatives, que celles-ci résultent de fraudes\nNous avons effectué notre audit selon les Normes de la Profession au Maroc. Les responsabilités qui ou d'erreurs.\nnous incombent en vertu de ces normes sont plus amplement décrites dans la section « Lors de la préparation des états financiers consolidés, c’est à la direction qu’il incombe d’évaluer la capacité\nResponsabilités de l’auditeur à l’égard de l’audit des états financiers consolidés » du présent rapport. du Groupe à poursuivre son exploitation, de communiquer, le cas échéant, les questions se rapportant à\nNous sommes indépendants du Groupe conformément aux règles de déontologie qui s’appliquent à la continuité de l’exploitation et d’appliquer le principe comptable de continuité d’exploitation, sauf si la\nl’audit des états financiers consolidés au Maroc et nous nous sommes acquittés des autres direction a l’intention de liquider le Groupe ou de cesser son activité ou si aucune autre solution réaliste ne\nresponsabilités déontologiques qui nous incombent selon ces règles. Nous estimons que les éléments s’offre à elle.\nprobants que nous avons obtenus sont suffisants et appropriés pour fonder notre opinion d’audit. Il incombe aux responsables de la gouvernance de surveiller le processus d’information financière du\nGroupe.\nQuestions clés de l’audit\nResponsabilités de l’auditeur à l’égard de l’audit des états financiers consolidés\nLes questions clés de l’audit sont les questions qui, selon notre jugement professionnel, ont été les plus\nimportantes dans l’audit des états financiers consolidés de la période considérée. Ces questions ont été\ntraitées dans le contexte de notre audit des états financiers consolidés pris dans leur ensemble et aux fins Notre responsabilité est d'exprimer une opinion sur ces états financiers consolidés sur la base de notre\nde la formation de notre opinion sur ceux-ci, et nous n’exprimons pas une opinion distincte sur ces audit. Nous avons effectué notre audit selon les Normes de la Profession au Maroc.\nquestions.\n1. GOODWILL\nRisque identifié Notre réponse\nLe Groupe Lesieur Cristal a réalisé des Notre approche d’audit se fonde sur un examen des\nopérations de croissance externes ayant procédures relatives aux tests de dépréciation des\nconduit à la comptabilisation des écarts écarts d’acquisition et des contrôles mis en place au\nd’acquisition à l’actif du bilan consolidé. Ces sein de Lesieur Cristal pour identifier les indices de1 3\nécarts correspondent à la différence entre le pertes de valeur de ces actifs.\nprix d’acquisition des sociétés acquises et les\njuste-valeurs des actifs et passifs identifiables Les travaux sur les comptes au 31 décembre 2023,\nrepris à la date d’acquisition. Au 31 décembre ont notamment consisté en :\n2023, la valeur de ces écarts d’acquisition\ns’élève à MMAD 109.  Une analyse de la méthodologie retenue par\nLesieur Cristal ;\nLes écarts d’acquisition sont affectés à des  Un examen des plans d’affaires approuvés\nUnités Génératrices de trésorerie et font l’objet par la Direction Générale de Lesieur Cristal\nde tests de dépréciation au moins une fois par pour s’assurer du caractère raisonnable des\nan ou dès la présence d’un indice de perte de estimations de flux futurs dégagés ;\nvaleur. Lorsque leur valeur recouvrable devient  Une analyse des principales hypothèses et\ninférieure à la valeur comptable, une paramètres utilisés (taux de croissance,\ndépréciation est comptabilisée. coût du capital, taux d’actualisation) au\nregard des données de marché\nLes informations concernant les méthodes de disponibles ;\ndétermination de la valeur recouvrable sont  Un examen des analyses de sensibilité des\ndétaillées dans la note «16 » de l’annexe aux estimations aux paramètres clés (en\ncomptes consolidés. particulier lorsque la valeur recouvrable est\nproche de la valeur nette comptable) ;\nNous avons considéré que l’évaluation des  Le recalcul des valeurs d’utilités\nécarts d’acquisition constituait un point clé de déterminées pour les principaux écarts\nnotre audit en raison de : d’acquisition.\nEnfin, nous avons examiné les informations\n Leur montant significatif au bilan relatives aux résultats de ces tests de\nconsolidé du Groupe ; dépréciation et tests de sensibilité présentés\n L’importance du jugement de la dans les notes annexes aux états financiers.\ndirection dans le choix de la méthode\nde détermination de la valeur\nrecouvrable et, dans le cas de la valeur\nd’utilité, des hypothèses de résultats\nfuturs des sociétés concernées et du\ntaux d’actualisation appliqué aux flux\nde trésorerie prévisionnels.\n2\nBILAN ACTIF\ndu 01/01/2023 au 31/12/2023\nEXERCICE EXERCICE\n(Montants en dhs) Amortissements PRÉCÉDENT\nBrut et provisions Net Net\n(1) Capital personnel débiteur\n(2) Bénéficiaire (+), déficitaire (-)\n1)Variation de stock : Stock final-Stock initial : Augmentation(+); Diminution(-)\n2)Achats revendus ou achats consommés : Achats - variation de stock.\nE\nS I L I B\nO M\nM\nI\nF\nI T\nC\nA\nImmobilisations en non valeur (A) 88 634 261,74 49 964 921,84 38 669 339,90 15 694 581,38\nFrais préliminaires\nCharges à répartir sur plusieurs exercices 88 634 261,74 49 964 921,84 38 669 339,90 15 694 581,38\nPrimes de remboursement des obligations\nImmobilisations incorporelles (B) 232 950 561,51 70 289 398,50 162 661 163,01 166 846 787,42\nImmobilisations en recherche et développement\nBrevets, marques, droits et valeurs similaires 142 681 873,13 48 386 918,12 94 294 955,01 98 480 579,42\nFonds commercial 90 268 688,38 21 902 480,38 68 366 208,00 68 366 208,00\nAutres immobilisations incorporelles Immobilisations corporelles (C) 2 205 921 185,77 1 842 503 997,59 363 417 188,18 353 939 646,32 Terrains 64 771 013,48 64 771 013,48 64 771 013,48\nConstructions 296 002 078,38 232 618 712,11 63 383 366,27 61 140 878,02 Installations techniques, matériel et outillage 1 608 769 040,12 1 441 267 179,78 167 501 860,34 182 165 335,45\nMatériel de transport 69 348 854,15 69 348 854,15\nMobilier, matériel de bureau, aménagements divers 107 041 637,53 99 269 251,55 7 772 385,98 3 474 671,76\nAutres immobilisations corporelles\nImmobilisations corporelles en cours 59 988 562,11 59 988 562,11 42 387 747,61\nImmobilisations financières (D) 564 297 971,50 172 180 362,45 392 117 609,05 417 745 941,19\nPrêts immobilisés 5 136 224,66 5 136 224,66 7 241 017,87\nAutres créances financières 3 121 663,22 3 121 663,22 3 121 663,22\nTitres de participation 556 040 083,62 172 180 362,45 383 859 721,17 407 383 260,10\nAutres titres immobilisés\nÉcart de conversion - Actif (E)\nDiminution des créances immobilisées\nAugmentations des dettes de financement\nTOTAL I (A+B+C+D+E) 3 091 803 980,52 2 134 938 680,38 956 865 300,14 954 226 956,31\nT N\nA L U\nC R I C\nF I T\nC\nA\nStocks (F) 1 291 540 948,50 49 609 063,20 1 241 931 885,30 1 482 036 212,94\nMarchandises 19 959 678,96 3 637 918,52 16 321 760,44 8 528 444,66\nMatières et fournitures consommables 658 467 714,41 45 901 369,68 612 566 344,73 1 019 658 480,34\nProduits en cours 146 291 769,44 146 291 769,44 159 942 162,12\nProduits intermédiaires et produits résiduels 1 151 170,89 1 151 170,89 541 949,31 Produits finis 465 670 614,80 69 775,00 465 600 839,80 293 365 176,51 Créances de l’actif circulant (G) 1 533 342 046,49 273 387 823,36 1 259 954 223,13 1 603 586 955,61\nFournisseurs débiteurs, avances & acomptes 45 903 965,65 45 903 965,65 32 460 398,31 Clients et comptes rattachés 880 011 155,82 218 302 998,75 661 708 157,07 892 847 482,20 Personnel 11 160 202,68 2 978 242,92 8 181 959,76 6 429 895,57\nÉtat 335 000 184,68 335 000 184,68 283 321 559,98 Compte d’associés 249 035 571,67 46 922 694,42 202 112 877,25 318 868 215,95\nAutres débiteurs 7 655 418,54 5 183 887,27 2 471 531,27 61 367 224,11\nComptes de régularisation actif 4 575 547,45 4 575 547,45 8 292 179,49\nTitres et valeurs de placement (H) 146 191 674,26 146 191 674,26 1 338 225 099,36\nÉcarts de conversion-Actif (I) Eléments circulants\nTOTAL II (F+G+H+I) 2 971 074 669,25 322 996 886,56 2 648 077 782,69 4 423 848 267,91\nEIREROSÉRT\nBILAN PASSIF\ndu 01/01/2023 au 31/12/2023\nEXERCICE\n(Montants en dhs) EXERCICE PRÉCÉDENT\nTrésorerie-Actif 206 510 470,67 206 510 470,67 86 599 959,80\nChèques et valeurs à encaisser 99 694 286,39 99 694 286,39 50 490 780,50\nBanques, T.G et C.C.P 100 121 781,97 100 121 781,97 26 723 110,45\nCaisses, Régies d’avances et accréditifs 6 694 402,31 6 694 402,31 9 386 068,85\nTOTAL III 206 510 470,67 206 510 470,67 86 599 959,80\nTOTAL GÉNÉRAL 6 269 389 120,44 2 457 935 566,94 3 811 453 553,50 5 464 675 184,02\nT N\nE\nN A M R\nE P\nT\nN\nE\nM E\nC\nN\nA N\nI\nF\nCAPITAUX PROPRES 1 656 124 468,47 1 771 593 689,18\nCapital social ou personnel ( 1) 276 315 100,00 276 315 100,00\nMoins : actionnaires, capital souscrit non appelé\nCapital appelé 276 315 100,00 276 315 100,00\ndont versé 276 315 100,00 276 315 100,00\nPrimes d’émission, de fusion, d’apport\nÉcarts de réevaluation\nRéserve légale 27 631 510,00 27 631 510,00\nAutres réserves 827 623 799,70 827 623 799,70 Report à nouveau ( 2 ) 515 681 484,48 422 907 256,64 Résultats nets en instance d’affectation 0,00\nRésultat net de l’exercice ( 2) 8 872 574,29 217 116 022,84\nTotal des capitaux propres (A) 1 656 124 468,47 1 771 593 689,18\nCapitaux propres assimilés (B) 77 807 424,74 96 235 942,59\nSubventions d’investissement\nProvisions réglementées 77 807 424,74 96 235 942,59\nDettes de financement (C)\nEmprunts obligataires\nAutres dettes de financement\nProvisions durables pour risques et charges (D) 20 461 623,56 9 928 656,78\nProvisions pour risques 20 461 623,56 9 928 656,78\nProvisions pour charges\nÉcart de conversion - Passif (E)\nAugmentation des créances immobilisées\nDiminution des dettes de financement\nTOTAL I ( A + B + C + D + E ) 1 754 393 516,77 1 877 758 288,55\nT N A L\nU C R I C\nF I S S\nA P\nDettes du passif circulant (F) 1 995 378 776,99 3 460 725 741,40\nFournisseurs et comptes rattachés 1 735 521 090,72 3 107 713 660,67\nClients créditeurs, avances et acomptes 1 228 870,14 3 936 348,48 Personnel 34 412 303,65 56 128 600,65\nOrganismes sociaux 21 790 866,30 16 704 918,10 État 41 070 289,20 122 325 422,30 Comptes d’associés 154 563 640,45 148 843 465,75\nAutres créanciers 5 770 062,96 2 055 371,60 Comptes de régularisation - passif 1 021 653,57 3 017 953,85\nAutres provisions pour risques et charges (G) 59 428 626,13 86 230 743,53\nÉcarts de conversion Passif ( éléments circulants ) (H)\nTOTAL II ( F + G + H ) 2 054 807 403,12 3 546 956 484,93\nEIREROSERT Trésorerie-Passif 2 252 633,61 39 960 410,54\nCrédits d’escompte\nCrédits de trésorerie\nBanques (Soldes créditeurs) 2 252 633,61 39 960 410,54\nTOTAL III 2 252 633,61 39 960 410,54\nTOTAL GÉNÉRAL ( I + II + III ) 3 811 453 553,50 5 464 675 184,02\nCOMPTE DE PRODUITS ET CHARGES (Hors Taxes)\n(Montants en dhs) Exercice du 1 janvier 2023 au 31 Décembre 2023\nOPÉRATIONS\nConcernant TOTAUX DE TOTAUX DE\nPropres à\nNATURE les exercices L’EXERCICE L’EXERCICE\nl’exercice\nprécédents PRÉCÉDENT\n(1) (2) 3= 1 + 2\nN\nO\nI T\nA\nT\nI O\nL P\nX\nE\nI Produits d’exploitation 6 325 733 397,70 6 325 733 397,70 5 976 163 603,18\nVentes de marchandises (en l’état) 390 466 281,17 390 466 281,17 405 119 220,95\nVentes de biens et services produits 4 838 519 668,05 4 838 519 668,05 5 581 147 007,12\nChiffre d’affaires 5 228 985 949,22 5 228 985 949,22 5 986 266 228,07\nVariation de stocks de produits ( + ou -) (1) 925 022 185,55 925 022 185,55 -94 424 628,72\nI mmobilisations produites par l’entreprise pour\nelle-même\nSubventions d’exploitation 1 611 618,61 1 611 618,61 402 575,67\nAutres produits d’exploitation 27 851 379,42 27 851 379,42 39 876 445,97\nReprises d’exploitation : transferts de charges 142 262 264,90 142 262 264,90 44 042 982,19\nTOTAL I 6 325 733 397,70 6 325 733 397,70 5 976 163 603,18\nII Charges d’exploitation 6 273 447 310,88 1 956 495,49 6 275 403 806,37 5 472 119 371,60\nAchats revendus (2) de marchandises 526 766 178,24 526 766 178,24 442 478 804,42\nAchats consommés (2) de matières et fournitures 4 944 197 071,22 276 982,01 4 944 474 053,23 4 194 687 346,71\nAutres charges externes 329 310 230,90 946 351,04 330 256 581,94 373 683 290,43\nImpôts et taxes 5 414 760,65 733 162,44 6 147 923,09 5 753 375,92\nCharges de personnel 247 008 895,08 247 008 895,08 267 761 477,90\nAutres charges d’exploitation 4 330 038,64 4 330 038,64 5 577 687,07\nDotations d’exploitation 216 420 136,15 216 420 136,15 182 177 389,15\nTOTAL II 6 273 447 310,88 1 956 495,49 6 275 403 806,37 5 472 119 371,60\nIII RÉSULTAT D’EXPLOITATION ( I - II ) 52 286 086,82 -1 956 495,49 50 329 591,33 504 044 231,58\nR E\nI\nC\nN\nA\nN\nI\nF\nCOMPTE DE PRODUITS ET CHARGES (Hors Taxes) Suite\n(Montants en dhs) Exercice du 1 janvier 2023 au 31 décembre 2023\nOPÉRATIONS\nConcernant TOTAUX DE TOTAUX DE\nPropres à\nNATURE les exercices L’EXERCICE L’EXERCICE\nl’exercice\nprécédents PRÉCÉDENT\n(1) (2) 3= 1 + 2\nIV Produits financiers 29 600 395,65 29 600 395,65 40 870 331,04\nProduits des titres de participation et autres titres immobilisés 2 972 202,08 2 972 202,08 475 002,00\nGains de change 4 598 334,62 4 598 334,62 3 551 045,49\nIntérêts et autres produits financiers 20 404 731,09 20 404 731,09 24 058 516,94\nReprises financières : transferts de charges 1 625 127,86 1 625 127,86 12 785 766,61\nTOTAL IV 29 600 395,65 29 600 395,65 40 870 331,04\nV Charges financières 42 135 632,29 42 135 632,29 72 516 645,68\nCharges d’intérêts 12 459 735,29 12 459 735,29 11 639 667,43\nPertes de change 5 341 368,48 5 341 368,48 4 371 727,70\nAutres charges financières -5 377 000,43 -5 377 000,43 -7,06\nDotations financières 29 711 528,95 29 711 528,95 56 505 257,61\nTOTAL V 42 135 632,29 42 135 632,29 72 516 645,68\nVI RÉSULTAT FINANCIER ( IV - V ) -12 535 236,64 -12 535 236,64 -31 646 314,64\nVII RÉSULTAT COURANT ( III + VI ) 39 750 850,18 -1 956 495,49 37 794 354,69 472 397 916,94\nT N\nA\nR\nU\nO C\nN\nO\nN\nÉTATS FINANCIERS SOCIAUX\nEXERCICE CLOS LE 31 DÉCEMBRE 2023\nVIII Produits non courants 50 452 492,63 50 452 492,63 25 642 096,93\nProduits de cessions d’immobilisations 280 000,00 280 000,00\nSubventions d’équilibre\nReprises sur subventions\nd’investissement\nAutres produits non courants 0,09 0,09 1,07\nReprises non courantes : transferts de 50 172 492,54 50 172 492,54 25 642 095,86\ncharges\nTOTAL VIII 50 452 492,63 50 452 492,63 25 642 096,93\nIX Charges non courantes 59 235 719,03 1 103 939,00 60 339 658,03 95 877 831,03\nValeurs nettes d’amortissement des\nimmobilisations cédées\nSubventions accordées\nAutres charges non courantes 49 085 704,66 1 103 939,00 50 189 643,66 67 545 921,81\nDotations non courantes aux\namortissements et aux provisions 10 150 014,37 10 150 014,37 28 331 909,22\nTOTAL IX 59 235 719,03 1 103 939,00 60 339 658,03 95 877 831,03\nX RÉSULTAT NON COURANT ( VIII - IX ) -8 783 226,40 -1 103 939,00 -9 887 165,40 -70 235 734,10\nXI RÉSULTAT AVANT IMPÔTS ( VII+ ou - X) 30 967 623,78-3 060 434,49 27 907 189,29 402 162 182,84\nXII IMPÔTS SUR LES RÉSULTATS 19 034 615,00 19 034 615,00 185 046 160,00\nXIII RÉSULTAT NET ( XI - XII ) 11 933 008,78-3 060 434,49 8 872 574,29 217 116 022,84\nXIV TOTAL DES PRODUITS ( I + IV + VIII ) 6 405 786 285,98 6 405 786 285,98 6 042 676 031,15\nXV TOTAL DES CHARGES ( II + V + IX + XII ) 6 393 853 277,20 3 060 434,49 6 396 913 711,69 5 825 560 008,31\nRÉSULTAT NET ( total produits - total XVI 11 933 008,78-3 060 434,49 8 872 574,29 217 116 022,84\ncharges )\nÉTATS FINANCIERS SOCIAUX\nEXERCICE CLOS LE 31 DÉCEMBRE 2023\nÉTAT DES SOLDES DE GESTION PRINCIPALES MÉTHODES D’EVALUATION SPÉCIFIQUES\ndu 01/01/2023 au 31/12/2023\nÀ L’ENTREPRISE\nEXERCICE du 01/01/2023 au 31/12/2023\nDÉSIGNATION EXERCICE\nPRÉCÉDENT I- ACTIF IMMOBILISE\n1 Ventes de Marchandises ( en l’état) 390 466 281,17 405 119 220,95 A- Évaluation à l’entrée\n2 - Achats revendus de marchandises 526 766 178,24 442 478 804,42 1- Immobilisations en non valeurs\nI = MARGE BRUTES VENTES EN L’ÉTAT -136 299 897,07 -37 359 583,47\n+ PRODUCTION DE L’EXERCICE (3+4+5) 5 763 541 853,60 5 486 722 378,40 La valeur d’entrée est constituée par le coût de revient de l’immobilisation.\nII 3 Ventes de biens et services produits 4 838 519 668,05 5 581 147 007,12 2- Immobilisations incorporelles\n4 Variation stocks produits 925 022 185,55 -94 424 628,72 La valeur d’entrée est constituée par le coût de revient de l’immobilisation.\n5 Immobilisations produites par l’entreprise pour elle-même 3- Immobilisations corporelles\n- CONSOMMATIONS DE L’EXERCICE(6+7) 5 274 730 635,17 4 568 370 637,14 Les immobilisations corporelles sont évaluées à leur coût d’acquisition ou de production, compte tenu des frais\nIII 6 Achats consommés de matières et fournitures 4 944 474 053,23 4 194 687 346,71 nécessaires à la mise en état d’utilisation de ces biens.\n7 Autres charges externes 330 256 581,94 373 683 290,43 4- Immobilisations financières\n= VALEUR AJOUTÉE (I+II+III) 352 511 321,36 880 992 157,79 Sont portées dans ce poste de bilan, les sommes payées pour l’acquisition des titres de participation, ainsi que\nIV 8 + Subventions d’exploitation 1 611 618,61 402 575,67 pour les dépôts et cautionnements.\n9 - Impôts et taxes 6 147 923,09 5 753 375,92 B- Création des valeurs\n10 - Charges de personnel 247 008 895,08 267 761 477,90 1- Méthodes d’amortissements\n= EXCÉDENT BRUT D’EXPLOITATION (EBE) |OU INSUFFISANCE 100 966 121,80 607 879 879,64 Les méthodes d’amortissement pratiquées sont les méthodes prévues par les règles fiscales en vigueur pour\nBRUTE D’EXPLOITATION(IBE) chaque catégorie d’immobilisation\nV 11 + Autres produits d’exploitation 27 851 379,42 39 876 445,97 2- Méthodes d’évaluation des provisions pour dépréciation\n12 - Autres charges d’exploitation 4 330 038,64 5 577 687,07 Lorsque la valeur d’inventaire est inférieure à la valeur brute, une provision pour dépréciation est constituée du\n13 + Reprises d’exploitation, transferts de charges 142 262 264,90 44 042 982,19 montant de la différence.\n14 - Dotations d’exploitation 216 420 136,15 182 177 389,15 3- Méthodes de détermination des écarts de Conversion - Actif\nVI = RÉSULTAT D’EXPLOITATION(+ou-) 50 329 591,33 504 044 231,58\nLes écarts de conversion sont calculés d’après le taux de change à la date de clôture.\nVII + RÉSULTAT FINANCIER -12 535 236,64 -31 646 314,64\nVIII = RÉSULTAT COURANT (+ou-) 37 794 354,69 472 397 916,94 II- ACTIF CIRCULANT\nIX + RÉSULTAT NON COURANT -9 887 165,40 -70 235 734,10 A- Évaluation à l’entrée\n15 - Impôts sur les résultats 19 034 615,00 185 046 160,00 1- Stocks\nX = RÉSULTAT NET DE L’EXERCICE 8 872 574,29 217 116 022,84 La méthode d’évaluation du Stock à la fin d’exercice est la méthode du premier entrée, premier sorti (FIFO).\n- TABLEAU DE FORMATION DES RÉSULTATS (T.F.R) 2- Créances\n1 Résultat net de l’exercice 8 872 574,29 217 116 022,84 Les créances sont inscrites en comptabilité pour leur montant nominal. Les créances clients font l’objet, le cas\nBénéfice + 8 872 574,29 217 116 022,84 échéant, d’une provision calculée sur la base du risque de non recouvrement.\nPerte - 3- Titres et valeurs de placement\n2 + Dotations d’exploitation (1) 87 169 456,33 66 747 906,53 Les titres et valeurs de placement sont estimés à la date de clôture au cours de la valeur à la date de fin\n3 + Dotations financières (1) 24 801 156,48 54 690 063,03 d’exercice.\n4 + Dotations non courantes (1) 3 550 014,37 7 593 507,28 B- Création des valeurs\n5 - Reprises d’exploitation (2) 1 976 332,22 830 000,00 1- Méthodes d’évaluation des provisions pour dépréciation\n6 - Reprises financières (2) 1 277 617,55 12 785 766,61\nLorsque la valeur d’inventaire est inférieure à la valeur nominale brute, une provision pour dépréciation est\n7 - Reprises non courantes (2) 21 978 532,22 19 642 095,86 constituée du montant de la différence.\n8 - Produits des cessions d’immobilisation 280 000,00\n2- Méthodes de détermination des écarts de Conversion - Actif\n9 + Valeurs nettes d’amortiss. Des immo. Cédées\nLes écarts de conversion sont calculés d’après le taux de change à la date de clôture.\nI 10 - C DiA stP rA ibC uI tT ioÉ n D s ’A deU T bO énF éIN fiA cN esCEMENT (C.A.F.) 19 28 4 8 38 40 1 77 91 59 ,, 04 08 3 91 62 78 18 09 2 6 83 57 ,, 02 01 III- FINANCEMENT PERMANENT\nII = AUTOFINANCEMENT -25 461 075,52 216 179 352,21 1- Méthodes de réévaluation\nLes capitaux propres et dettes de financement sont inscrites à leur valeur nominale.\n( 1 ) A l’exclusion des dotations relatives aux actifs et passif circulants et à la trésorerie.\n( 2 ) A l’exclusion des reprises relatives aux actifs circulants et à la trésorerie. 2- Méthodes d’évaluation des provisions réglementées\n( 3 ) Y compris reprises sur subventions d’investissements. Lorsque la valeur d’inventaire est inférieure à la valeur nominale brute, une provision pour dépréciation est\nconstituée du montant de la différence.\n3- Dettes de financement permanent\nTABLEAU DE FINANCEMENT (MODÈLE NORMAL) du 01/01/2023 au 31/12/2023 Les dettes de financement sont inscrites en comptabilité pour leur montant nominal.\n4- Méthodes d’évaluation des provisions durables pour risques et charges\nExercice Exercice a - b\nI. SYNTHÈSES DES MASSES DU BILAN Exercice précédent Emplois Ressources Une provision pour risques et charges est constituée pour faire face à la charge future ou au risque créés au\ncours de l’exercice.\nb a c d\nFinancement permanent 1 754 393 516,77 1 877 758 288,55 123 364 771,78 5- Méthodes de détermination des écarts de Conversion - Passif\nMoins actif immobilisé 956 865 300,14 954 226 956,31 2 638 343,83 Les écarts de conversion sont calculés d’après le taux de change à la date de clôture.\n= FONDS DE ROULEMENT FONCTIONNEL (1-2) (A) 797 528 216,63 923 531 332,24 126 003 115,61 IV- PASSIF CIRCULANT (Hors trésorerie)\n1- Dettes du passif circulant\nActif circulant 2 648 077 782,69 4 423 848 267,91 1 775 770 485,22\nLes dettes du passif circulant sont inscrites pour leur montant nominal.\nMoins Passif circulant 2 054 807 403,12 3 546 956 484,93 1 492 149 081,81\n= BESOINS DE FINANCEMENT GLOBAL (4-5) (B) 593 270 379,57 876 891 782,98 283 621 403,41 2- Méthodes d’évaluation des autres provisions pour risques et charges\nTRÉSORERIE NETTE (ACTIF -PASSIF) A - B 204 257 837,06 46 639 549,26 157 618 287,80 Une provision pour risques et charges est constituée pour faire face à la charge future ou au risque créés au\ncours de l’exercice.\nExercice Exercice précédent\n3- Méthodes de détermination des écarts de Conversion - Passif\nII. EMPLOIS ET RESSOURCES\nEmplois Ressources Emplois Ressources Les écarts de conversion sont calculés d’après le taux de change à la date de clôture.\nI. RESSOURCES STABLES DE L’EXERCICE V- TRESORERIE\nAUTOFINANCEMENT (A) -25 461 075,61 216 179 352,21 1- Trésorerie - Actif\n+ Capacité d’autofinancement 98 880 719,39 312 889 637,21\n- Distributions de bénéfices 124 341 795,00 96 710 285,00 La trésorerie est comptabilisée à la date de son engagement. La société utilise le rapprochement bancaire\nCESSIONS ET RÉDUCTIONS D’IMMOBILISATIONS (B) 5 007 577,73 2 918 272,56 pour rapprocher ses soldes comptables aux soldes bancaires.\n+ Cessions d’immobilisations incorporelles 2- Trésorerie - Passif\n+ Cessions d’immobilisations corporelles 280 000,00 La trésorerie est comptabilisée à la date de son engagement. La société utilise le rapprochement bancaire\n+ Cessions d’immobilisations financières pour rapprocher ses soldes comptables aux soldes bancaires.\n+ Récupérations sur créances immobilisées 4 727 577,73 2 918 272,56\n3- Méthodes d’évaluation des provisions pour dépréciation\nAUGMENTATIONS DES CAPITAUX PROPRES ET\nASSIMILÉS (C) Lorsque la valeur d’inventaire est inférieure à la valeur nominale brute, une provision pour dépréciation est\n+ Augmentations de capital, apports constituée du montant de la différence.\n+ Subventions d’investissement\nAUGMENTATION DES DETTES DE FINANCEMENT (D)\n(nettes de primes de remboursement)\nTOTAL I. RESSOURCES STABLES (A+B+C+D)\nII.EMPLOIS STABLES DE L’EXERCICE ÉTAT DES DÉROGATIONS du 01/01/2023 au 31/12/2023\nACQUISITIONS ET AUGMENTATIONS\nD’IMMOBILISATIONS (E ) 81 128 755,91 119 053 998,66 Justifications des Influence des Dérogations\n+ Acquisitions d’immobilisations incorporelles 15 000,00 Indication des Dérogations Dérogations sur le Patrimoine, la Situation\n+ Acquisitions d’immobilisations corporelles 78 505 971,39 59 033 584,31 Financière et les Résultats\n+ Acquisitions d’immobilisations financières 56 482 804,98 INDICATION DES DÉROGATIONS\n+ Augmentation des créances immobilisées 2 622 784,52 3 522 609,37 I- Dérogations aux principes comptables fondamentaux NÉANT NÉANT\nREMBOURSEMENT DES CAPITAUX PROPRES (F) 24 420 861,83 II- Dérogations aux méthodes d’évaluation NÉANT NÉANT\nREMBOURSEMENT DES DETTES DE FINANCEMENT III- Dérogations aux règles d’établissement et de\nNÉANT NÉANT\n(G) présentation des états de synthèse\nEMPLOIS EN NON VALEURS (H)\nTOTAL II. EMPLOIS STABLES (E+F+G+H) 105 549 617,74 119 053 998,66\nIII. VARIATION DU BESOIN DE FINANCEMENT GLOBAL DÉTAIL DES NON-VALEURS\n283 621 403,41 6 077 137,33 du 01/01/2023 au 31/12/2023\n(B.F.G.)\nIV. VARIATION DE LA TRÉSORERIE 157 618 287,80 106 120 763,44 Compte Principal Intitulé Montant\nTOTAL GÉNÉRAL 263 167 905,54 263 167 905,53 225 174 762,10 225 174 762,10 211 FRAIS PRELIMINAIRES\n2111 Frais de constitution\nÉTAT DES CHANGEMENTS DE MÉTHODES du 01/01/2023 au 31/12/2023 2112 Frais préalables au démarrage\n2113 Frais d’augmentation du capital\nInfluence sur le Patrimoine, la 2114 Frais sur opérations de fusions, scissions et transformations\nNature des Changements Justification des Changements Situation Financière et 2116 Frais de prospection\nles Résultats 2117 Frais de publicité\nI CHANGEMENT AFFECTANT LES METHODES D’EVALUATION 2118 Autres frais préléminaires\nNEANT NEANT NEANT 212 CHARGES A REPARTIR SUR PLUSIEURS EXERCICES 88 634 261,74\nNEANT NEANT NEANT 2121 Frais d’acquisitions des immobilisations\nNEANT NEANT NEANT 2125 Frais d’émission des emprunts\nII CHANGEMENT AFFECTANT LES RECLES DE PRESENTATION 2128 Autres charges à répartir\nNEANT NEANT NEANT 213 PRIME DE REMBOURSEMENT DES OBLIGATIONS\nNEANT NEANT NEANT 2130 Primes de reboursements des obligations\nNEANT NEANT NEANT T O T A L 88 634 261,74\nÉTATS FINANCIERS SOCIAUX\nEXERCICE CLOS LE 31 DÉCEMBRE 2023\nTABLEAU DES IMMOBILISATIONS AUTRES QUE FINANCIÈRES\ndu 01/01/2023 au 31/12/2023\nAUGMENTATION DIMINUTION\nMONTANT BRUT DEBUT MONTANT BRUT\nN A T U R E EXERCICE Acquisition Production par l’entre- Virement Cession Retrait Virement FIN EXERCICE\nprise pour elle-même\nIMMOBILISATION EN NON-VALEURS 50 619 597,87 24 420 861,83 13 593 802,04 88 634 261,74\n* Frais préliminaires\n* Charges à répartir sur plusieurs exercices 50 619 597,87 24 420 861,83 13 593 802,04 88 634 261,74\n* Primes de remboursement obligations\nIMMOBILISATIONS INCORPORELLES 232 950 561,51 232 950 561,51\n* Immobilisation en recherche et développement\n* Brevets, marques, droits et valeurs similaires 142 681 873,13 142 681 873,13\n* Fonds commercial 90 268 688,38 90 268 688,38\n* Autres immobilisations incorporelles\nIMMOBILISATIONS CORPORELLES 2 151 795 755,55 79 701 009,58 20 155 059,85 10 786 739,18 34 943 900,03 2 205 921 185,77\n* Terrains 64 771 013,48 64 771 013,48\n* Constructions 283 096 117,39 910 342,66 11 995 618,33 296 002 078,38\n* Installat. techniques, matériel et outillage 1 579 559 416,52 21 050 182,08 8 159 441,52 1 608 769 040,12\n* Matériel de transport 80 135 593,33 10 786 739,18 69 348 854,15\n* Mobilier, matériel bureau et aménagements 101 845 867,22 5 195 770,31 107 041 637,53\n* Autres immobilisations corporelles\n* Immobilisations corporelles en cours 42 387 747,61 52 544 714,53 34 943 900,03 59 988 562,11\nTOTAL GÉNÉRAL 2 435 365 914,93 104 121 871,41 33 748 861,89 10 786 739,18 34 943 900,03 2 527 506 009,02\nTABLEAU DES AMORTISSEMENTS\ndu 01/01/2023 au 31/12/2023\nCumul début exercice Dotation de l’exercice Amortissement sur les immobilisations sorties Cumul d’amortissement en fin d’exercice\nN A T U R E\n1 2 3 4 = 1 + 2 - 3\nIMMOBILISATION EN NON-VALEURS 34 925 016,49 8 859 479,99 43 784 496,48\n* Frais préliminaires\n* Charges à répartir sur plusieurs exercices 34 925 016,49 8 859 479,99 43 784 496,48\n* Primes de remboursement des obligations\nIMMOBILISATIONS INCORPORELLES 44 201 293,71 4 185 624,41 48 386 918,12\n* Immobilisation en recherche et développement\n* Brevets, marques droits et valeurs similaires 44 201 293,71 4 185 624,41 48 386 918,12\n* Fonds commercial\n* Autres immobilisations incorporelles\nIMMOBILISATIONS CORPORELLES 1 796 067 566,72 55 734 485,47 10 786 739,18 1 841 015 313,01\n* Terrains\n* Constructions 221 955 239,37 10 663 472,74 232 618 712,11\n* Installations techniques, matériel et outillage 1 395 605 538,56 44 172 956,64 1 439 778 495,20\n* Matériel de transport 80 135 593,33 10 786 739,18 69 348 854,15\n* Mobilier, matériel de bureau et aménagements divers 98 371 195,46 898 056,09 99 269 251,55\n* Autres immobilisations corporelles\n* Immobilisations corporelles en cours\nTOTAL GÉNÉRAL 1 875 193 876,92 68 779 589,87 10 786 739,18 1 933 186 727,61\nTABLEAU DES TITRES DE PARTICIPATION\ndu 01/01/2023 au 31/12/2023\nExtrait des derniers états de synthèse de la société émettrice Produits inscrits\nParticipation au Prix d’acquisition Valeur nette\ntR ra icis eon sociale de la société émet- Secteur d’activité Capital social capital en % global comptable Date de clôture Situation nette Résultat net au l ’C ex.P e. rC c id ce e\n1 2 3 4 5 6 7 8 9\nSCI YAM IMMOBILIER 10 000,00 50,00 5 000,00 5 000,00 31/12/2023 -532 294,01 -34 676,47 0,00\nD A M A IMMOBILIER 4 000,00 98,75 217 250,00 217 250,00 31/12/2023 0,00 0,00 0,00\nC E L A C O DISTRIBUTION 3 000 000,00 23,99 719 700,00 0,00 31/12/2023 0,00 0,00 0,00\nASTRA MAROC DIVERS 400 000,00 99,93 566 923,30 0,00 31/12/2023 -1 403 009,02 -128 715,25 0,00\nFIREAL (C & F ) DIVERS 4 000 000,00 99,96 19 420 445,71 19 420 445,71 31/12/2023 29 739 042,64 853 125,78 1 253 626,99\nS O T R A N I DIVERS 250 000,00 2,51 6 280,00 0,00 31/12/2023 0,00 0,00 0,00\nLA RAFFINERIE AFRICAINE OLEAGINEUX 12 678 084,06 34,00 17 163 234,01 17 163 234,01 31/12/2023 2 275 590,52 162 017,97 3 829 918,96\nCRISTAL TUNISIE OLEAGINEUX 20 697 509,55 93,88 48 398 062,04 0,00 31/12/2023 -7 989 900,74 -29 298 827,90 274 102 407,58\nSTE D EXPLOITATION OLIVE OLEOCULTURE 32 000 000,00 100,00 31 999 700,00 31 999 700,00 31/12/2023 33 682 422,16 -4 097 923,65 296 080 903,29\nLES DOMAINES JAWHARA OLEOCULTURE 32 000 000,00 100,00 32 000 000,00 32 000 000,00 31/12/2023 32 208 626,28 32 953 831,87 90 049 392,63\nGIOM GIE - OLEAGINEUX 300 000,00 66,67 200 000,00 0,00 31/12/2023 -9 767 757,44 -2 910 634,40 57 600 893,42\nLESIEUR CRISTAL COTE D IVOIRE INDUSTRIEM 166 398,08 100,00 166 398,08 0,00 31/12/2023 0,00 0,00 0,00\nOLIVCO OLEOCULTURE 100 000,00 100,00 5 000 000,00 5 000 000,00 31/12/2023 -20 787 716,43 1 353 089,25 13 396 811,42\nLESIEUR CRISTAL INC HUIILE D OLIVE 9 929 000,00 100,00 9 929 000,00 0,00 31/12/2023 0,00 0,00 0,00\nINDUSALIM MARGARINE 10 000 000,00 100,00 175 000 000,00 175 000 000,00 31/12/2023 88 787 995,73 30 919 993,02 205 928 361,17\nTLC DISTRIBUTION 3 000 000,00 100,00 3 000 000,00 0,00 31/12/2023 -9 718 115,62 -585 484,99 0,00\nC O S T O M A OLEAGINEUX 5 400,00 0,00 1 082,00 1 082,00 31/12/2023 0,00 0,00 0,00\nC I C A V E T PROVENDIERS 10 000,00 0,00 500,00 500,00 31/12/2023 0,00 0,00 0,00\nCITE III DES JEUNES IMMOBILIER 1 598 000,00 0,00 4 505,00 4 505,00 31/12/2023 0,00 0,00 0,00\nH S M DIVERS 2 760 000,00 0,00 359,10 359,10 31/12/2023 0,00 0,00 0,00\nS G A DIVERS 0,00 0,00 100,00 100,00 31/12/2023 0,00 0,00 0,00\nDISTRA DIVERS 127 936 000,00 0,00 1,00 1,00 31/12/2023 0,00 0,00 0,00\nO LEOR OLEAGINEUX 20 250 000,00 100,00 90 000 000,00 45 357 154,57 31/12/2023 45 357 154,57 1 235 522,80 1 772 657,80\nC O M A H A OLEAGINEUX 21 000,00 49,05 9 984,00 0,00 31/12/2023 0,00 0,00 0,00\nS I K A F OLEAGINEUX 300 000,00 99,90 499 624,43 0,00 30/09/2023 -4 472 455,89 -53 545,35 0,00\nH G M O OLEAGINEUX 1 500 000,00 99,96 4 874 940,92 1 350 520,58 31/12/2023 1 351 061,00 37 109,59 57 585,52\nSous-Total 282 915 391,69 -- 439 183 089,59 327 519 851,97 -- 178 730 643,75 30 404 882,27 944 072 558,78\nÉTATS FINANCIERS SOCIAUX\nEXERCICE CLOS LE 31 DÉCEMBRE 2023\nTABLEAU DES TITRES DE PARTICIPATION du 01/01/2023 au 31/12/2023\nExtrait des derniers états de synthèse de la société émettrice Produits inscrits\nParticipation au Prix d’acquisition Valeur nette\nR tra icis eon sociale de la société émet- Secteur d’activité Capital social capital en % global comptable Date de clôture Situation nette Résultat net au l ’C ex.P e. rC c id ce e\n1 2 3 4 5 6 7 8 9\nS O P R O T A PROVENDIERS 5 000 000,00 73,61 3 926 778,98 0,00 31/12/2023 -27 425 028,45 -1 254 022,19 0,00\nS H O M SAVONNERIE 100 000,00 99,70 9 310 687,78 9 310 687,78 31/12/2023 12 586 123,06 426 101,97 548 161,46\nP O S A M A PRODUITS MER 400 000,00 99,63 912 191,38 912 191,38 31/12/2023 0,00 0,00 0,00\nHAY EL HABAIB IMMOBILIER 100 000,00 100,00 46 083 755,04 46 083 755,04 31/12/2023 57 111 182,09 566 175,61 880 622,81\nCITE MNE SIDI OTHMANE IMMOBILIER 1 097 660,00 0,24 2 630,00 2 630,00 31/12/2023 0,00 0,00 0,00\nCITE I DES JEUNES IMMOBILIER 739 200,00 0,34 2 500,00 2 500,00 31/12/2023 0,00 0,00 0,00\nCITE II DES JEUNES IMMOBILIER 1 458 000,00 0,69 14 500,00 14 500,00 31/12/2023 0,00 0,00 0,00\nS O C I C A IMMOBILIER 956 760,00 2,25 13 605,00 13 605,00 31/12/2023 0,00 0,00 0,00\nOLEOSEN OLEAGINEUX 142 563 330,00 90,16 56 590 345,85 0,00 31/12/2023 -45 762 735,94 -34 637 898,03 296 764 052,28\nT o t a l 435 330 341,69 -- 556 040 083,62 383 859 721,17 -- 175 240 184,51 -4 494 760,37 1 242 265 395,33\nTABLEAU DES PROVISIONS\ndu 01/01/2023 au 31/12/2023\nMONTANT DEBUT DOTATIONS REPRISES\nN A T U R E MONTANT FIN EXERCICE\nEXERCICE D’exploitation Financières Non courantes D’exploitation Financières Non courantes\n1. Provisions pour dépréciation de l’actif immobilisé 172 347 846,41 5 880 567,43 24 801 156,48 1 277 617,55 201 751 952,77\n2. Provisions réglementées 96 235 942,59 3 550 014,37 21 978 532,22 77 807 424,74\n3. Provisons durables pour risques et charges 9 928 656,78 12 509 299,00 1 976 332,22 20 461 623,56\nSOUS TOTAL (A) 278 512 445,78 18 389 866,43 24 801 156,48 3 550 014,37 1 976 332,22 1 277 617,55 21 978 532,22 300 021 001,07\n4. Provisions pour dépréciation de l’actif circulant\n321 261 120,18 45 626 059,72 4 910 372,47 48 453 155,50 347 510,31 322 996 886,56\n(hors trésorerie)\n5. Autres Provisions pour risques et charge 86 230 743,53 40 392 318,92 42 000 476,00 25 193 960,32 59 428 626,13\n6. Provisions pour dépréciation des comptes de\ntrésorerie\nSOUS TOTAL (B) 407 491 863,71 86 018 378,64 4 910 372,47 90 453 631,50 347 510,31 25 193 960,32 382 425 512,69\nTOTAL (A+B) 686 004 309,49 104 408 245,07 29 711 528,95 3 550 014,37 92 429 963,72 1 625 127,86 47 172 492,54 682 446 513,76\nTABLEAU DES CRÉANCES\ndu 01/01/2023 au 31/12/2023\nAnalyse par Échéance Autres Analyses\nCréances Total Montants sur l’État Montants sur Montants\nPlus d’un an Moins d’un an Échues et non recouvrées Montants en Devises et Organismes les Entreprises Représentés par\nPublics liées Effets\nDe l’Actif Immobilisé 8 257 887,88 8 257 887,88\n- Prêts immobilisés 5 136 224,66 5 136 224,66\n- Autres créances financières 3 121 663,22 3 121 663,22\nDe l’actif circulant 1 533 342 046,49 110 293 555,64 959 730 490,53 463 318 000,32 72 183 627,14 335 000 184,68 257 925 601,78 23 573 756,55\n- Fournisseurs débiteurs avances et acomptes 45 903 965,65 26 733 926,24 19 170 039,41 38 791 541,24\n- Clients et comptes rattachés 880 011 155,82 72 023 392,28 631 983 945,36 176 003 818,18 11 530 452,66 10 646 889,48 23 573 756,55\n- Personnel 11 160 202,68 6 182 815,63 4 977 387,05\n- État 335 000 184,68 53 764 262,59 281 235 922,09 335 000 184,68\n- Comptes d’associés 249 035 571,67 1 756 859,37 247 278 712,30 21 861 633,24 247 278 712,30\n- Autres débiteurs 7 655 418,54 3 596 562,12 2 957 983,42 1 100 873,00\n- Compte de régularisation actif 4 575 547,45 4 575 547,45\nT O T A U X 1 541 599 934,37 118 551 443,52 959 730 490,53 463 318 000,32 72 183 627,14 335 000 184,68 257 925 601,78 23 573 756,55\nTABLEAU DES DETTES\ndu 01/01/2023 au 31/12/2023\nAnalyse par Échéance Autres Analyses\nDettes Total Montants sur l’État Montants sur Montants\nPlus d’un an Moins d’un an Échues et non payées Montants en Devises et Organismes les Entreprises Représentés par\nPublics liées Effets\nDE FINANCEMENT\n- Emprunts obligataires\n- Autres dettes de financement\nDU PASSIF CIRCULANT 1 995 378 776,99 543 967 636,97 1 451 411 140,02 1 061 148 606,17 62 861 155,50 172 561 603,01 1 055 462 994,31\n- Fournisseurs et comptes rattachés 1 735 521 090,72 393 661 759,49 1 341 859 331,23 1 061 148 606,17 28 829 725,53 1 055 462 994,31\n- Clients créditeurs, avances et acomptes 1 228 870,14 1 026 246,69 202 623,45\n- Personnel 34 412 303,65 72 118,13 34 340 185,52\n- Organismes sociaux 21 790 866,30 21 790 866,30 21 790 866,30\n- État 41 070 289,20 15 988 499,97 25 081 789,23 41 070 289,20\n- Comptes d’associés 154 563 640,45 131 142 085,96 23 421 554,49 143 731 877,48\n- Autres créanciers 5 770 062,96 2 076 926,73 3 693 136,23\n- Comptes de régularisation - Passif 1 021 653,57 1 021 653,57\nT O T A U X 1 995 378 776,99 543 967 636,97 1 451 411 140,02 1 061 148 606,17 62 861 155,50 172 561 603,01 1 055 462 994,31\nTABLEAU DES SURETES RÉELLES DONNÉES OU REÇUES ENGAGEMENTS FINANCIERS REÇUS OU DONNÉS HORS\ndu 01/01/2023 au 31/12/2023\nOPÉRATIONS DE CRÉDIT-BAIL\ndu 01/01/2023 au 31/12/2023\nMontant\nTiers Débiteurs ou V.N.C. de la\ncouvert par la Nature (1) Date et Lieu d’inscription Objet (2)(3) Montants Montants Exercice\nTiers Créditeurs sureté donnée Engagements Donnés\nsureté Exercice Précèdent\nSureté donnée Engagement donné\nSureté reçue Avals et cautions 382 468 866,99 359 956 098,02\nDonnées par les Engagements en matière de pensions de retraites et obligations 200 045 817,00 263 258 801,00\nHypothèques sur prêts 1 170 000,00 2 1990 à 1996 - Casablanca\nbénéficiaires Autres engagements donnés (1) 1 627 868 537,26 3 969 610 631,09\n* Couvertures à terme en devise, soit :\n- 151 574 931,18 $ au cours moyen de 9,8870 soit 1 498 620 171,45 DH\n- 12 060 730,09 € au cours moyen de 10,7165 soit 129 248 365,82 DH\nEngagements reçus\nEngagements reçus (2) 111 217 890,13 275 485 583,50\n* Couvertures à terme en devise , soit :\n- 774 079,98 $ au cours moyen de 9,8380 soit 7 615 399,55 DH\n- 9 719 585,43€ au cours moyen de 10,6591 soit 103 602 490,58 DH\n2. DEPRECIATION DES CREANCES CLIENTS\nRisque identifié Notre réponse\nLes créances clients s’élèvent à KMAD 661.708 Les travaux sur les comptes au 31 décembre\nen valeur nette au 31 décembre 2023 dont un 2023, ont notamment consisté en :\nÉTATS FINANCIERS SOCIAUX montant de KMAD 218.303 de provision pour\ndépréciation. - La fiabilisation de la balance âgée des\ncréances clients en testant pour un\nEXERCICE CLOS LE 31 DÉCEMBRE 2023 Ces provisions sont déterminées sur la base échantillon l’ancienneté retenue ;\nd’une méthode statistique qui se base sur - La réalisation de tests relatifs à l’apurement\nl’ancienneté de la créance (100% de solde pour des créances en période subséquente ;\nles créances antérieures à 1 an et 50% pour les - Le recalcul de la provision sur la base de la\ncréances antérieures à 6 mois). Cependant, le méthode statistique retenue par la société ;\nmanagement complète éventuellement cette - L’examen des PV de réunions tenues par\nrègle par une analyse au cas par cas intégrant les responsables commerciaux pour\nd’autres indices de dépréciation (relation l’estimation du risque de recouvrement sur\ncommerciale, couverture assurance, feed-back les créances clients ;\ndes opérationnels...). - L’établissement des entretiens avec les\nopérationnels pour s’assurer de l’absence\nNous avons considéré l’estimation du montant de créances clients bien que récentes\nde la provision pour dépréciation des créances présentant un risque de recouvrement ;\nclients comme un point clé de l’audit compte\ntenu du caractère estimatif de ce processus et\n4, Rue Maati Jazouli (ex rue Friol) son impact significatif sur les comptes.\nAnfa- Casablanca\nMaroc\n37, Bd Abdellatif Ben Kaddour\n20 050 Casablanca\nMaroc\nResponsabilités de la direction et des responsables de la gouvernance à l’égard des\nétats de synthèse\nLa direction est responsable de la préparation et de la présentation fidèle des états de\nAux Actionnaires de la société\nsynthèse, conformément au référentiel comptable en vigueur au Maroc, ainsi que du contrôle\nLESIEUR CRISTAL S.A.\n1, rue Caporal Corbi interne qu’elle considère comme nécessaire pour permettre la préparation d’états de\nCasablanca synthèse exempts d’anomalies significatives, que celles-ci résultent de fraudes ou d’erreurs.\nLors de la préparation des états de synthèse, c’est à la direction qu’il incombe d’évaluer la\nRAPPORT GENERAL DES COMMISSAIRES AUX COMPTES capacité de la société à poursuivre son exploitation, de communiquer, le cas échéant, les\nEXERCICE DU 1er JANVIER AU 31 DECEMBRE 2023 questions se rapportant à la continuité de l’exploitation et d’appliquer le principe comptable\nde continuité d’exploitation, sauf si la direction a l’intention de liquider la société ou de cesser\nOpinion son activité ou si aucune autre solution réaliste ne s’offre à elle.\nConformément à la mission qui nous a été confiée par votre Assemblée Générale, nous Il incombe aux responsables de la gouvernance de surveiller le processus d’information\navons effectué l'audit des états de synthèse ci-joints de la société Lesieur Cristal S.A., qui fRineasnpcoiènrsea dbeil ilaté sso dceié tlé’a.uditeur à l’égard de l’audit des états de synthèse\ncomprennent le bilan au 31 décembre 2023, le compte de produits et charges, l'état des\nsoldes de gestion, le tableau de financement pour l’exercice clos à cette date, ainsi que l’état Nos objectifs sont d’obtenir l’assurance raisonnable que les états de synthèse pris dans leur\ndes informations complémentaires (ETIC). Ces états de synthèse font ressortir un montant ensemble sont exempts d’anomalies significatives, que celles-ci résultent de fraudes ou\nde capitaux propres et assimilés de MAD 1.733.931.893,21 dont un bénéfice net de MAD d’erreurs et de délivrer un rapport de l’auditeur contenant notre opinion. L’assurance\n8.872.574,29. raisonnable correspond à un niveau élevé d’assurance, qui ne garantit toutefois pas qu’un\naudit réalisé conformément aux normes de la profession au Maroc permettra toujours de\nNous certifions que les états de synthèse cités au premier paragraphe ci-dessus sont détecter toute anomalie significative qui pourrait exister. Les anomalies peuvent résulter de\nréguliers et sincères et donnent, dans tous leurs aspects significatifs, une image fidèle du fraudes ou d’erreurs et elles sont considérées comme significatives lorsqu’il est raisonnable\nrésultat des opérations de l’exercice écoulé ainsi que de la situation financière et du de s’attendre à ce que, individuellement ou collectivement, elles puissent influer sur les\npatrimoine de la société Lesieur Cristal S.A. au 31 décembre 2023, conformément au décisions économiques que les utilisateurs des états de synthèse prennent en se fondant\nréférentiel comptable admis au Maroc. sur ceux-ci.\n3\nDans le cadre d’un audit réalisé conformément aux normes de la profession au Maroc, nous\nFondement de l’opinion\nexerçons notre jugement professionnel et faisons preuve d’esprit critique tout au long de cet\naudit. En outre :\nNous avons effectué notre audit selon les Normes de la Profession au Maroc. Les\nresponsabilités qui nous incombent en vertu de ces normes sont plus amplement décrites\ndans la section « Responsabilités de l’auditeur à l’égard de l’audit des états de synthèse » o nous identifions et évaluons les risques que les états de synthèse comportent des\nanomalies significatives, que celles-ci résultent de fraudes ou d’erreurs, concevons et\ndu présent rapport. Nous sommes indépendants de la société conformément aux règles de\nmettons en œuvre des procédures d’audit en réponse à ces risques, et réunissons des\ndéontologie qui s’appliquent à l’audit des états de synthèse au Maroc et nous nous sommes\néléments probants suffisants et appropriés pour fonder notre opinion. Le risque de non-\nacquittés des autres responsabilités déontologiques qui nous incombent selon ces règles.\ndétection d’une anomalie significative résultant d’une fraude est plus élevé que celui\nNous estimons que les éléments probants que nous avons obtenus sont suffisants et\nd’une anomalie significative résultant d’une erreur, car la fraude peut impliquer la\nappropriés pour fonder notre opinion d’audit.\ncollusion, la falsification, les omissions volontaires, les fausses déclarations ou le\nQuestions clés de l’audit contournement du contrôle interne ;\nLes questions clés de l’audit sont les questions qui, selon notre jugement professionnel, ont o nous acquérons une compréhension des éléments du contrôle interne pertinents pour\nété les plus importantes dans l’audit des états de synthèse de la période considérée. Ces l’audit afin de concevoir des procédures d’audit appropriées aux circonstances, et non\nquestions ont été traitées dans le contexte de notre audit des états de synthèse pris dans dans le but d’exprimer une opinion sur l’efficacité du contrôle interne de la société ;\nleur ensemble et aux fins de la formation de notre opinion sur ceux-ci, et nous n’exprimons\npas une opinion distincte sur ces questions. o nous apprécions le caractère approprié des méthodes comptables retenues et le\ncaractère raisonnable des estimations comptables faites par la direction, de même que\ndes informations y afférentes fournies par cette dernière ;\n1\n1. TITRES DE PARTICIPATION\no nous tirons une conclusion quant au caractère approprié de l’utilisation par la direction\nRisque identifié Notre réponse du principe comptable de continuité d’exploitatio²n et, selon les éléments probants\nobtenus, quant à l’existence ou non d’une incertitude significative liée à des événements\nou situations susceptibles de jeter un doute important sur la capacité de la société à\nLes titres de participation sont comptabilisés au Nos travaux ont consisté principalement à :\npoursuivre son exploitation. Si nous concluons à l’existence d’une incertitude\nbilan pour une valeur nette comptable de KMAD\n383.860 - Examiner, sur la base d’échantillons, la significative, nous sommes tenus d’attirer l’attention des lecteurs de notre rapport sur les\njustification des méthodes d’évaluation et informations fournies dans les états de synthèse au sujet de cette incertitude ou, si ces\nIls sont comptabilisés individuellement à leur des éléments chiffrés utilisés par la société informations ne sont pas adéquates, d’exprimer une opinion modifiée. Nos conclusions\nvaleur d’acquisition et lorsque la valeur actuelle pour déterminer les valeurs actuelles, s’appuient sur les éléments probants obtenus jusqu’à la date de notre rapport. Des\ndes titres est inférieure à la valeur nette - S’assurer que les données retenues dans la événements ou situations futurs pourraient par ailleurs amener la société à cesser son\ncomptable, une analyse est effectuée par le réalisation des tests de dépréciation des exploitation ;\nmanagement pour déterminer la dépréciation à titres de participation sont cohérentes avec\nconstater. - Tle es s d teo rn nées p as ro urce s od ne ds ae gn eti tés ; l’exactitude o n syo nu ts h èé sv ea , lu yo cn os m l pa r isp r lé es se in nt fa ot ri mon a tid o’ ne sn s foe um rnb il ee s, dla a ns str u l’Ect Tu Ir Ce , e et t ale p pc ro én ct ioe nn su sd i e les s é ét ta at ts s dde e\nLa valeur actuelle est déterminée, pour chaque arithmétique des calculs des valeurs d’utilité synthèse représentent les opérations et événements sous-jacents d’une manière propre\ntitre, par référence à une méthode d’évaluation retenues par la société. à donner une image fidèle.\nfondée sur les éléments disponibles tels que\nl’actualisation des flux futurs, la juste valeur Enfin, nous avons examiné les informations\npour le cas des actifs biologiques ou l’actif net relatives aux titres de participation publiées dans\nréévalué communément utilisés qui leurs sont l’état des informations complémentaires (ETIC).\nrelatifs pour apprécier les perspectives de\nrentabilité.\n4\nCompte tenu du poids des titres de participation\nau bilan, du niveau de jugement exercé pour\nl’estimation du risque sur les titres de\nparticipation ainsi que le degré d’incertitude lié\nà cette estimation à cause de la sensibilité des\nmodèles utilisés ou variations de données et\nd’hypothèses sur lesquelles se fondent ces\nestimations, nous avons considéré que\nl’évaluation des titres de participation constituait\n2. uDnE pPoRinEt CclIéA dTeIO nNot rDeE aSu dCitR.EANCES CLIENTS\nRisque identifié Notre réponse\nLes créances clients s’élèvent à KMAD 661.708 Les travaux sur les comptes au 31 décembre\nen valeur nette au 31 décembre 2023 dont un 2023, ont notamment consisté en :\nmontant de KMAD 218.303 de provision pour\ndépréciation. - La fiabilisation de la balance âgée des\ncréances clients en testant pour un\nCes provisions sont déterminées sur la base échantillon l’ancienneté retenue ;\nd’une méthode statistique qui se base sur - La réalisation de tests relatifs à l’apurement\nl’ancienneté de la créance (100% de solde pour des créances en période subséquente ;\nles créances antérieures à 1 an et 50% pour les - Le recalcul de la provision sur la base de la\ncréances antérieures à 6 mois). Cependant, le méthode statistique retenue par la société ;\nmanagement complète éventuellement cette - L’examen des PV de réunions tenues par\nrègle par une analyse au cas par cas intégrant les responsables commerciaux pour\nd’autres indices de dépréciation (relation l’estimation du risque de recouvrement sur2\ncommerciale, couverture assurance, feed-back les créances clients ;\ndes opérationnels...). - L’établissement des entretiens avec les\nopérationnels pour s’assurer de l’absence\nNous avons considéré l’estimation du montant de créances clients bien que récentes\nde la provision pour dépréciation des créances présentant un risque de recouvrement ;\nclients comme un point clé de l’audit compte\ntenu du caractère estimatif de ce processus et\nson impact significatif sur les comptes.\nSiège social : 1, rue caporal Corbi, Pour consulter les états financiers de Lesieur Cristal :\n20 300 Roches Noires - Casablanca - R.C 4171 https://www.lesieur-cristal.com/communication_\nICE 001569079000005 - Tél. : (+212) 522 67 93 00 financiere/etats-financiers/\nResponsabilités de la direction et des responsables de la gouvernance à l’égard des\nétats de synthèse\nLa direction est responsable de la préparation et de la présentation fidèle des états de\nsynthèse, conformément au référentiel comptable en vigueur au Maroc, ainsi que du contrôle\ninterne qu’elle considère comme nécessaire pour permettre la préparation d’états de\nsynthèse exempts d’anomalies significatives, que celles-ci résultent de fraudes ou d’erreurs.\nLors de la préparation des états de synthèse, c’est à la direction qu’il incombe d’évaluer la\ncapacité de la société à poursuivre son exploitation, de communiquer, le cas échéant, les\nquestions se rapportant à la continuité de l’exploitation et d’appliquer le principe comptable\nde continuité d’exploitation, sauf si la direction a l’intention de liquider la société ou de cesser\nson activité ou si aucune autre solution réaliste ne s’offre à elle.\nIl incombe aux responsables de la gouvernance de surveiller le processus d’information\nfinancière de la société.\n3",
    "tables": [
        [
            {
                "COMMUNIQUÉ FINANCIER ANNUEL\nÉTATS DE SYNTHÈSE SOCIAUX ET CONSOLIDÉS\nEXERCICE CLOS LE 31 DÉCEMBRE 2023": "Faits marquants et analyses des principaux indicateurs de résultats\nEngagement en faveur du pouvoir d’achat et baisse des prix en 2023\nRépercussions défavorables sur les marges et les résultats 2023\nAnticipation d’un retour à un niveau normatif pour 2024\nIndicateurs consolidés IFRS\nEn MDh 2022 2023 Variation\nChiffre d'affaires 6 897 5 934 -14%\nRésultat d'exploitation 463 74 -84%\nRésultat net part du groupe 206 2,5 -99%\nAu cours de l’exercice 2023, Lesieur Cristal, forte de son empreinte citoyenne et responsable, a baissé les prix des huiles\nde table pour répondre aux préoccupations économiques et sociales des consommateurs marocains. Elle a également\nmaintenu son engagement de non-répercussion de la hausse des prix des matières premières sur les consommateurs eu\négard à un contexte inflationniste persistant. Parallèlement, une évolution des habitudes de consommation a été observée,\navec une orientation vers les produits d’entrée de gamme. Les autres segments d’activité du Groupe, à savoir, l’huile\nd’olive, le savon et la margarine, ont quant à eux affiché des performances solides, ce qui a permis d’atténuer l’impact\nde l’activité huiles de table sur le chiffre d’affaires du Groupe. Lesieur Cristal a clôturé l’exercice avec un chiffre d’affaires\nannuel de 5 934 MDH, marquant une baisse de 14%.\nLa mise en place d’une stratégie de couverture à long terme des matières premières, amorcée au second semestre\n2022, a certes permis d’assurer la continuité de l’approvisionnement du marché, mais a cependant pesé sur les marges\nen raison des coûts élevés d’acquisition des stocks. Pour atténuer ces effets, des efforts soutenus en matière d’efficacité\nopérationnelle ont été déployés. Le résultat d’exploitation et le résultat net part du groupe s’établissent respectivement à\n74 MDH et 2,5 MDH.\nEn alignement avec ses objectifs stratégiques, Lesieur Cristal a poursuivi le déploiement de sa nouvelle Route-to-Market,\ninitié en 2022, qui couvre désormais plus de 80% du territoire national. Par ailleurs, dans une démarche visant à renforcer\nson lien avec les consommateurs, le Groupe a lancé de nouvelles plateformes de communication pour promouvoir ses\nmarques phares.\nEn 2023, fidèle à ses valeurs, Lesieur Cristal a revu sa stratégie RSE, désormais au cœur de son plan stratégique à horizon\n2027. Cette nouvelle politique engage le Groupe à créer une valeur durable pour toutes ses parties prenantes, tout en\npréservant ses ressources et son environnement.\nPerspectives & stratégie de développement\nGrâce à la baisse des prix des intrants conjuguée à une stratégie de couverture adaptée au contexte actuel, le Groupe\nanticipe un redressement des marges et un retour à un niveau normatif en 2024.\nCapitalisant sur les contrats programmes signés lors du SIAM 2023, Lesieur Cristal s’inscrit dans la stratégie nationale «\nGénération Green » et renforce son ambition de développer l’amont agricole contribuant à répondre ainsi aux enjeux de\nsécurité alimentaire du Maroc et dans les pays dans lesquels elle opère.\nLe Groupe a également pour ambition d’élargir sa présence en Afrique à travers notamment des opérations d’acquisitions,\navec un modèle opératoire d’un acteur local engagé et la promotion d’un amont agricole durable.\nSiège social : 1, rue caporal Corbi, Pour consulter le Rapport Financier Annuel comprenant les états financiers\n20 300 Roches Noires - Casablanca - R.C 4171 ICE sociaux et consolidés de Lesieur Cristal au 31 décembre 2023 :\n001569079000005 - Tél. : (+212) 522 67 93 00 https://www.lesieur-cristal.com/communication_financiere/rapports-financiers/"
            }
        ],
        [
            {
                "Indicateurs consolidés IFRS": "En MDh",
                "null": "Variation"
            },
            {
                "Indicateurs consolidés IFRS": "",
                "null": ""
            },
            {
                "Indicateurs consolidés IFRS": "",
                "null": ""
            },
            {
                "Indicateurs consolidés IFRS": "",
                "null": ""
            }
        ],
        [
            {
                "ÉTATS FINANCIERS CONSOLIDÉS\nEXERCICE CLOS LE 31 DÉCEMBRE 2023": "BILAN ACTIF COMPTE DE RÉSULTAT CONSOLIDÉ\nACTIF (En millions de dirhams) 31-déc-23 31-déc-22 (En millions de dirhams) 31-déc-23 31-déc-22\nGoodwill 109 109 Chiffre d'affaires 5 934 6 897\nAutres produits de l'activité 222 261\nImmobilisations incorporelles, net 201 205\nProduits des activités ordinaires 6 156 7 157\nImmobilisations corporelles, net 1 038 1 027\nAchats -5 324 -5 646\nActifs biologiques 38 38 Autres charges externes -380 -444\nImmeubles de placement, net 4 4 Frais de personnel -284 -318\nParticipations dans les entreprises associées 24 26 Impôts et taxes -12 -14\nAmortissements et provisions d'exploitation -78 -270\nAutres actifs financiers 28 29\nAutres produits et charges d'exploitation nets -4 -2\n- Prêts et créances, net 7 9\nCharges d'exploitation courantes -6 082 -6 694\n- dont titres de participation consolidés -1 -1 RÉSULTAT D'EXPLOITATION COURANT 74 463\n- Actifs financiers disponibles à la vente 21 21 Autres produits et charges d'exploitation non courants -1 -83\nAutres débiteurs non courants 80 88 Autres produits et charges d'exploitation -1 -83\nRésultat des activités opérationnelles 72 380\nImpôts différés actifs 31 43\nProduits d'intérêts 19 14\nActif non courant 1 553 1 570\nCharges d'intérêts -38 -28\nAutres actifs financiers 610 490 Résultats sur instruments financiers 2 -11\n- Instruments financiers dérivés 604 484 Autres produits et charges financiers -17 -3\nRésultat financier -34 -28\n- Prêts et créances et placements, net 6 6\nRésultat avant impôt des entreprises intégrées 38 352\nStocks et en-cours, net 1 485 1 770\nImpôts sur les bénéfices -75 -195\nCréances clients, net 812 995 Impôts différés 33 33\nAutres débiteurs courants, net 406 463 Résultat net des entreprises intégrées -3 190\nTrésorerie et équivalent de trésorerie 373 1 452 Part dans les résultats des sociétés mises en équivalence 0 3\nRésultat net des activités poursuivies -3 193\nActif courant 3 687 5 170\nRésultat net des activités abandonnées\nTOTAL ACTIF 5 240 6 740\nRésultat de l'ensemble consolidé -3 193\nDont Intérêts minoritaires 5 12\nDont Résultat net - Part du Groupe 2 206\nRésultat net par action en dirhams\nBILAN PASSIF - de base 0 7\n- dilué 0 7\nPASSIF (En millions de dirhams) 31-déc-23 31-déc-22\nCapital 276 276\nRéserves 1 544 1 401\nTABLEAU DES FLUX DE TRÉSORERIE CONSOLIDÉ\nÉcarts de conversion -11 -12\nRésultat net part du groupe 2 206 (En millions de dirhams) 31-déc-23 31-déc-22\nCapitaux propres attribuables aux actionnaires ordinaires de la société Résultat net de l’ensemble consolidé -3 193\n1 812 1 871\nmère\nAjustements pour :\nIntérêts minoritaires -10 -5\nRésultats des sociétés mises en équivalence -0 -3\nCapitaux propres de l’ensemble consolidé 1 802 1 866\nDotations aux amortissements et provisions, pertes de valeur 106 166\nProvisions 83 95\nProfits / pertes de réévaluation (juste valeur) 94 -20\nAvantages du personnel 206 269\nRésultats de cession et des pertes et profits de dilution -23 -20\nDettes financières non courantes 191 173\nCapacité d’autofinancement après coût de l’endettement financier net et\n173 316\n- Dettes envers les établissements de crédit 1 0 impôt\n- Dettes liées aux contrat de location financement 190 173 Élimination de la charge (produit) d’impôts 42 164\nDettes d’impôts sur les sociétés 12 12 Élimination du coût de l’endettement financier net 38 28\nImpôts différés Passifs 48 48 Capacité d’autofinancement avant coût de l’endettement financier net\n253 507\nimpôt\nPassif non courant 540 596\nIncidence de la variation du BFR -946 279\nDettes financières courantes 1 021 804\nImpôts différés 4 -8\n- Instruments financiers dérivés 612 442\nImpôts payés -231 -112\n- Dettes envers les établissements de crédit 409 362\nFlux net de trésorerie liés aux activités opérationnelles -919 666\nDettes fournisseurs courantes 1 712 3 209\nAcquisition d’immobilisations corporelles et incorporelles -81 -93\nAutres créditeurs courants 165 266\nVariation des autres actifs financiers 1 -\nPassif courant 2 898 4 278\nCessions d’immobilisations corporelles et incorporelles - 0\nTOTAL PASSIF 3 438 4 875\nDividendes reçus 1 0\nTOTAL CAPITAUX PROPRES ET PASSIF 5 240 6 740\nIntérêts financiers versés -38 -28\nFlux net de trésorerie liés aux activités d’investissement -116 -120\nAugmentation et Réduction de capital - 7\nETAT DES AUTRES ÉLÉMENTS DU RÉSULTAT GLOBAL\nÉmission de nouveaux emprunts 1 0\n(En millions de dirhams) 31-déc.-23 31-déc.-22 Dividendes payés aux actionnaires de la société mère -124 -97\nRésultat de l’exercice -3 193\nVariation de comptes courants associés 26 -13\nAutres éléments du résultat global (bruts d’impôts)\nPartie efficace des produits ou pertes sur instruments de couverture de flux Flux net de trésorerie provenant des activités de financement -98 -102\n41 -65\nde trésorerie Incidence de la variation des taux de change 7 -12\nÉcarts actuariels sur les obligations des régimes à prestations définies 66 13\nImpôt sur le résultat sur les autres éléments du résultat global -39 21 VARIATION DE LA TRÉSORERIE ET ÉQUIVALENTS DE TRÉSORERIE -1 126 433\nAutres éléments du résultat global nets d’impôts 68 -31 Trésorerie et équivalents de trésorerie net à l’ouverture 1 092 657\nRÉSULTAT GLOBAL TOTAL DE L’ANNÉE 65 162\nTrésorerie et équivalents de trésorerie net à la clôture -34 1 090\nDont Intérêts minoritaires 5 -12\nDont Résultat global net - Part du Groupe 60 175 VARIATION DE LA TRÉSORERIE ET ÉQUIVALENTS DE TRÉSORERIE -1 126 433"
            }
        ],
        [
            {
                "BILAN ACTIF": "ACTIF (En millions de dirhams)",
                "null": "31-déc-22"
            },
            {
                "BILAN ACTIF": "Goodwill",
                "null": "109"
            },
            {
                "BILAN ACTIF": "Immobilisations incorporelles, net",
                "null": "205"
            },
            {
                "BILAN ACTIF": "Immobilisations corporelles, net",
                "null": "1 027"
            },
            {
                "BILAN ACTIF": "Actifs biologiques",
                "null": "38"
            },
            {
                "BILAN ACTIF": "Immeubles de placement, net",
                "null": "4"
            },
            {
                "BILAN ACTIF": "Participations dans les entreprises associées",
                "null": "26"
            },
            {
                "BILAN ACTIF": "Autres actifs financiers",
                "null": "29"
            },
            {
                "BILAN ACTIF": "- Prêts et créances, net",
                "null": "9"
            },
            {
                "BILAN ACTIF": "- dont titres de participation consolidés",
                "null": "-1"
            },
            {
                "BILAN ACTIF": "- Actifs financiers disponibles à la vente",
                "null": "21"
            },
            {
                "BILAN ACTIF": "Autres débiteurs non courants",
                "null": "88"
            },
            {
                "BILAN ACTIF": "Impôts différés actifs",
                "null": "43"
            },
            {
                "BILAN ACTIF": "Actif non courant",
                "null": "1 570"
            },
            {
                "BILAN ACTIF": "Autres actifs financiers",
                "null": "490"
            },
            {
                "BILAN ACTIF": "- Instruments financiers dérivés",
                "null": "484"
            },
            {
                "BILAN ACTIF": "- Prêts et créances et placements, net",
                "null": "6"
            },
            {
                "BILAN ACTIF": "Stocks et en-cours, net",
                "null": "1 770"
            },
            {
                "BILAN ACTIF": "Créances clients, net",
                "null": "995"
            },
            {
                "BILAN ACTIF": "Autres débiteurs courants, net",
                "null": "463"
            },
            {
                "BILAN ACTIF": "Trésorerie et équivalent de trésorerie",
                "null": "1 452"
            },
            {
                "BILAN ACTIF": "Actif courant",
                "null": "5 170"
            },
            {
                "BILAN ACTIF": "TOTAL ACTIF",
                "null": "6 740"
            }
        ],
        [
            {
                "COMPTE DE RÉSULTAT CONSOLIDÉ": "(En millions de dirhams)",
                "null": "31-déc-22"
            },
            {
                "COMPTE DE RÉSULTAT CONSOLIDÉ": "Chiffre d'affaires",
                "null": "6 897"
            },
            {
                "COMPTE DE RÉSULTAT CONSOLIDÉ": "Autres produits de l'activité",
                "null": "261"
            },
            {
                "COMPTE DE RÉSULTAT CONSOLIDÉ": "Produits des activités ordinaires",
                "null": "7 157"
            },
            {
                "COMPTE DE RÉSULTAT CONSOLIDÉ": "Achats",
                "null": "-5 646"
            },
            {
                "COMPTE DE RÉSULTAT CONSOLIDÉ": "Autres charges externes",
                "null": "-444"
            },
            {
                "COMPTE DE RÉSULTAT CONSOLIDÉ": "Frais de personnel",
                "null": "-318"
            },
            {
                "COMPTE DE RÉSULTAT CONSOLIDÉ": "Impôts et taxes",
                "null": "-14"
            },
            {
                "COMPTE DE RÉSULTAT CONSOLIDÉ": "Amortissements et provisions d'exploitation",
                "null": "-270"
            },
            {
                "COMPTE DE RÉSULTAT CONSOLIDÉ": "Autres produits et charges d'exploitation nets",
                "null": "-2"
            },
            {
                "COMPTE DE RÉSULTAT CONSOLIDÉ": "Charges d'exploitation courantes",
                "null": "-6 694"
            },
            {
                "COMPTE DE RÉSULTAT CONSOLIDÉ": "RÉSULTAT D'EXPLOITATION COURANT",
                "null": "463"
            },
            {
                "COMPTE DE RÉSULTAT CONSOLIDÉ": "Autres produits et charges d'exploitation non courants",
                "null": "-83"
            },
            {
                "COMPTE DE RÉSULTAT CONSOLIDÉ": "Autres produits et charges d'exploitation",
                "null": "-83"
            },
            {
                "COMPTE DE RÉSULTAT CONSOLIDÉ": "Résultat des activités opérationnelles",
                "null": "380"
            },
            {
                "COMPTE DE RÉSULTAT CONSOLIDÉ": "Produits d'intérêts",
                "null": "14"
            },
            {
                "COMPTE DE RÉSULTAT CONSOLIDÉ": "Charges d'intérêts",
                "null": "-28"
            },
            {
                "COMPTE DE RÉSULTAT CONSOLIDÉ": "Résultats sur instruments financiers",
                "null": "-11"
            },
            {
                "COMPTE DE RÉSULTAT CONSOLIDÉ": "Autres produits et charges financiers",
                "null": "-3"
            },
            {
                "COMPTE DE RÉSULTAT CONSOLIDÉ": "Résultat financier",
                "null": "-28"
            },
            {
                "COMPTE DE RÉSULTAT CONSOLIDÉ": "Résultat avant impôt des entreprises intégrées",
                "null": "352"
            },
            {
                "COMPTE DE RÉSULTAT CONSOLIDÉ": "Impôts sur les bénéfices",
                "null": "-195"
            },
            {
                "COMPTE DE RÉSULTAT CONSOLIDÉ": "Impôts différés",
                "null": "33"
            },
            {
                "COMPTE DE RÉSULTAT CONSOLIDÉ": "Résultat net des entreprises intégrées",
                "null": "190"
            },
            {
                "COMPTE DE RÉSULTAT CONSOLIDÉ": "Part dans les résultats des sociétés mises en équivalence",
                "null": "3"
            },
            {
                "COMPTE DE RÉSULTAT CONSOLIDÉ": "Résultat net des activités poursuivies",
                "null": "193"
            },
            {
                "COMPTE DE RÉSULTAT CONSOLIDÉ": "Résultat net des activités abandonnées",
                "null": ""
            },
            {
                "COMPTE DE RÉSULTAT CONSOLIDÉ": "Résultat de l'ensemble consolidé",
                "null": "193"
            },
            {
                "COMPTE DE RÉSULTAT CONSOLIDÉ": "Dont Intérêts minoritaires",
                "null": "12"
            },
            {
                "COMPTE DE RÉSULTAT CONSOLIDÉ": "Dont Résultat net - Part du Groupe",
                "null": "206"
            },
            {
                "COMPTE DE RÉSULTAT CONSOLIDÉ": "Résultat net par action en dirhams",
                "null": ""
            },
            {
                "COMPTE DE RÉSULTAT CONSOLIDÉ": "- de base",
                "null": "7"
            },
            {
                "COMPTE DE RÉSULTAT CONSOLIDÉ": "- dilué",
                "null": "7"
            }
        ],
        [
            {
                "BILAN PASSIF": "PASSIF (En millions de dirhams)",
                "null": "31-déc-22"
            },
            {
                "BILAN PASSIF": "Capital",
                "null": "276"
            },
            {
                "BILAN PASSIF": "Réserves",
                "null": "1 401"
            },
            {
                "BILAN PASSIF": "Écarts de conversion",
                "null": "-12"
            },
            {
                "BILAN PASSIF": "Résultat net part du groupe",
                "null": "206"
            },
            {
                "BILAN PASSIF": "Capitaux propres attribuables aux actionnaires ordinaires de la société\nmère",
                "null": "1 871"
            },
            {
                "BILAN PASSIF": "Intérêts minoritaires",
                "null": "-5"
            },
            {
                "BILAN PASSIF": "Capitaux propres de l’ensemble consolidé",
                "null": "1 866"
            },
            {
                "BILAN PASSIF": "Provisions",
                "null": "95"
            },
            {
                "BILAN PASSIF": "Avantages du personnel",
                "null": "269"
            },
            {
                "BILAN PASSIF": "Dettes financières non courantes",
                "null": "173"
            },
            {
                "BILAN PASSIF": "- Dettes envers les établissements de crédit",
                "null": "0"
            },
            {
                "BILAN PASSIF": "- Dettes liées aux contrat de location financement",
                "null": "173"
            },
            {
                "BILAN PASSIF": "Dettes d’impôts sur les sociétés",
                "null": "12"
            },
            {
                "BILAN PASSIF": "Impôts différés Passifs",
                "null": "48"
            },
            {
                "BILAN PASSIF": "Passif non courant",
                "null": "596"
            },
            {
                "BILAN PASSIF": "Dettes financières courantes",
                "null": "804"
            },
            {
                "BILAN PASSIF": "- Instruments financiers dérivés",
                "null": "442"
            },
            {
                "BILAN PASSIF": "- Dettes envers les établissements de crédit",
                "null": "362"
            },
            {
                "BILAN PASSIF": "Dettes fournisseurs courantes",
                "null": "3 209"
            },
            {
                "BILAN PASSIF": "Autres créditeurs courants",
                "null": "266"
            },
            {
                "BILAN PASSIF": "Passif courant",
                "null": "4 278"
            },
            {
                "BILAN PASSIF": "TOTAL PASSIF",
                "null": "4 875"
            },
            {
                "BILAN PASSIF": "TOTAL CAPITAUX PROPRES ET PASSIF",
                "null": "6 740"
            }
        ],
        [
            {
                "TABLEAU DES FLUX DE TRÉSORERIE CONSOLIDÉ": "(En millions de dirhams)",
                "null": "31-déc-22"
            },
            {
                "TABLEAU DES FLUX DE TRÉSORERIE CONSOLIDÉ": "Résultat net de l’ensemble consolidé",
                "null": "193"
            },
            {
                "TABLEAU DES FLUX DE TRÉSORERIE CONSOLIDÉ": "Ajustements pour :",
                "null": ""
            },
            {
                "TABLEAU DES FLUX DE TRÉSORERIE CONSOLIDÉ": "Résultats des sociétés mises en équivalence",
                "null": "-3"
            },
            {
                "TABLEAU DES FLUX DE TRÉSORERIE CONSOLIDÉ": "Dotations aux amortissements et provisions, pertes de valeur",
                "null": "166"
            },
            {
                "TABLEAU DES FLUX DE TRÉSORERIE CONSOLIDÉ": "Profits / pertes de réévaluation (juste valeur)",
                "null": "-20"
            },
            {
                "TABLEAU DES FLUX DE TRÉSORERIE CONSOLIDÉ": "Résultats de cession et des pertes et profits de dilution",
                "null": "-20"
            },
            {
                "TABLEAU DES FLUX DE TRÉSORERIE CONSOLIDÉ": "Capacité d’autofinancement après coût de l’endettement financier net et\nimpôt",
                "null": "316"
            },
            {
                "TABLEAU DES FLUX DE TRÉSORERIE CONSOLIDÉ": "Élimination de la charge (produit) d’impôts",
                "null": "164"
            },
            {
                "TABLEAU DES FLUX DE TRÉSORERIE CONSOLIDÉ": "Élimination du coût de l’endettement financier net",
                "null": "28"
            },
            {
                "TABLEAU DES FLUX DE TRÉSORERIE CONSOLIDÉ": "Capacité d’autofinancement avant coût de l’endettement financier net\nimpôt",
                "null": "507"
            },
            {
                "TABLEAU DES FLUX DE TRÉSORERIE CONSOLIDÉ": "Incidence de la variation du BFR",
                "null": "279"
            },
            {
                "TABLEAU DES FLUX DE TRÉSORERIE CONSOLIDÉ": "Impôts différés",
                "null": "-8"
            },
            {
                "TABLEAU DES FLUX DE TRÉSORERIE CONSOLIDÉ": "Impôts payés",
                "null": "-112"
            },
            {
                "TABLEAU DES FLUX DE TRÉSORERIE CONSOLIDÉ": "Flux net de trésorerie liés aux activités opérationnelles",
                "null": "666"
            },
            {
                "TABLEAU DES FLUX DE TRÉSORERIE CONSOLIDÉ": "Acquisition d’immobilisations corporelles et incorporelles",
                "null": "-93"
            },
            {
                "TABLEAU DES FLUX DE TRÉSORERIE CONSOLIDÉ": "Variation des autres actifs financiers",
                "null": "-"
            },
            {
                "TABLEAU DES FLUX DE TRÉSORERIE CONSOLIDÉ": "Cessions d’immobilisations corporelles et incorporelles",
                "null": "0"
            },
            {
                "TABLEAU DES FLUX DE TRÉSORERIE CONSOLIDÉ": "Dividendes reçus",
                "null": "0"
            },
            {
                "TABLEAU DES FLUX DE TRÉSORERIE CONSOLIDÉ": "Intérêts financiers versés",
                "null": "-28"
            },
            {
                "TABLEAU DES FLUX DE TRÉSORERIE CONSOLIDÉ": "Flux net de trésorerie liés aux activités d’investissement",
                "null": "-120"
            },
            {
                "TABLEAU DES FLUX DE TRÉSORERIE CONSOLIDÉ": "Augmentation et Réduction de capital",
                "null": "7"
            },
            {
                "TABLEAU DES FLUX DE TRÉSORERIE CONSOLIDÉ": "Émission de nouveaux emprunts",
                "null": "0"
            },
            {
                "TABLEAU DES FLUX DE TRÉSORERIE CONSOLIDÉ": "Dividendes payés aux actionnaires de la société mère",
                "null": "-97"
            },
            {
                "TABLEAU DES FLUX DE TRÉSORERIE CONSOLIDÉ": "Variation de comptes courants associés",
                "null": "-13"
            },
            {
                "TABLEAU DES FLUX DE TRÉSORERIE CONSOLIDÉ": "Flux net de trésorerie provenant des activités de financement",
                "null": "-102"
            },
            {
                "TABLEAU DES FLUX DE TRÉSORERIE CONSOLIDÉ": "Incidence de la variation des taux de change",
                "null": "-12"
            },
            {
                "TABLEAU DES FLUX DE TRÉSORERIE CONSOLIDÉ": "VARIATION DE LA TRÉSORERIE ET ÉQUIVALENTS DE TRÉSORERIE",
                "null": "433"
            },
            {
                "TABLEAU DES FLUX DE TRÉSORERIE CONSOLIDÉ": "Trésorerie et équivalents de trésorerie net à l’ouverture",
                "null": "657"
            },
            {
                "TABLEAU DES FLUX DE TRÉSORERIE CONSOLIDÉ": "Trésorerie et équivalents de trésorerie net à la clôture",
                "null": "1 090"
            },
            {
                "TABLEAU DES FLUX DE TRÉSORERIE CONSOLIDÉ": "VARIATION DE LA TRÉSORERIE ET ÉQUIVALENTS DE TRÉSORERIE",
                "null": "433"
            }
        ],
        [
            {
                "ETAT DES AUTRES ÉLÉMENTS DU RÉSULTAT GLOBAL": "(En millions de dirhams)",
                "null": "31-déc.-22"
            },
            {
                "ETAT DES AUTRES ÉLÉMENTS DU RÉSULTAT GLOBAL": "Résultat de l’exercice",
                "null": "193"
            },
            {
                "ETAT DES AUTRES ÉLÉMENTS DU RÉSULTAT GLOBAL": "Autres éléments du résultat global (bruts d’impôts)",
                "null": ""
            },
            {
                "ETAT DES AUTRES ÉLÉMENTS DU RÉSULTAT GLOBAL": "Partie efficace des produits ou pertes sur instruments de couverture de flux\nde trésorerie",
                "null": "-65"
            },
            {
                "ETAT DES AUTRES ÉLÉMENTS DU RÉSULTAT GLOBAL": "Écarts actuariels sur les obligations des régimes à prestations définies",
                "null": "13"
            },
            {
                "ETAT DES AUTRES ÉLÉMENTS DU RÉSULTAT GLOBAL": "Impôt sur le résultat sur les autres éléments du résultat global",
                "null": "21"
            },
            {
                "ETAT DES AUTRES ÉLÉMENTS DU RÉSULTAT GLOBAL": "Autres éléments du résultat global nets d’impôts",
                "null": "-31"
            },
            {
                "ETAT DES AUTRES ÉLÉMENTS DU RÉSULTAT GLOBAL": "RÉSULTAT GLOBAL TOTAL DE L’ANNÉE",
                "null": "162"
            },
            {
                "ETAT DES AUTRES ÉLÉMENTS DU RÉSULTAT GLOBAL": "Dont Intérêts minoritaires",
                "null": "-12"
            },
            {
                "ETAT DES AUTRES ÉLÉMENTS DU RÉSULTAT GLOBAL": "Dont Résultat global net - Part du Groupe",
                "null": "175"
            }
        ],
        [
            {
                "ÉTATS FINANCIERS CONSOLIDÉS\nEXERCICE CLOS LE 31 DÉCEMBRE 2023": "TABLEAU DE VARIATION DES CAPITAUX PROPRES CONSOLIDÉS\nRéserves Non Réserves Réserves des opérations Total Capitaux propres Total capitaux\nEn millions de dirhams Capital Intérêt minoritaire\nDistribués de conversion de couverture part du groupe propres\nAu 1er janvier 2022 276 1 560 -10 -28 1 798 2 1 800\nEffets des changements de méthode comptable/correction d’erreur -6 -6 -6\nMontants retraités à l’ouverture 276 1 555 -10 -28 1 792 2 1 794\nVariation des capitaux propres\nRésultat de l’exercice - 206 - - 206 -12 193\nVariation nette de juste valeur des instruments financiers - - - -41 -41 - -41\nPertes et profits de conversion - - -1 - -1 -0 -1\nVariation de juste valeur écarts actuariels - - - 10 10 - 10\nRésultat global total de l’année - 206 -1 -31 174 -13 161\nDividendes distribués - -97 - - -97 - -97\nAugmentation de capital - 1 - - 1 6 7\nTotal des transactions avec les actionnaires - -96 - - -96 6 -90\nAu 31 décembre 2022 276 1 664 -11 -59 1 870 -5 1 866\nAu 1er janvier 2023 276 1 664 -11 -59 1 870 -5 1 866\nMontants retraités à l’ouverture 276 1 664 -11 -59 1 870 -5 1 866\nVariation des capitaux propres - - - - - - 0\nRésultat de l’exercice - 2 - - 2 -5 -3\nVariation nette de juste valeur des instruments financiers - - - 21 21 - 21\nPertes et profits de conversion - - 1 - 43 0 43\nRésultat global total de l’année - 2 1 63 67 -5 61\nDividendes distribués - -124 - - -124 - -124\nChangement de périmètre - -1 - - -1 0 -1\nTotal des transactions avec les actionnaires - -126 - - -126 0 -126\nAu 31 décembre 2023 276 1 541 -10 4 1 811 -10 1 802\nNOTES AUX COMPTES CONSOLIDÉS\nNOTE 1. DESCRIPTION DE L’ACTIVITÉ\nLesieur Cristal est une société anonyme de droit marocain, soumise à l’ensemble des textes régissant les sociétés commerciales au Maroc. La société a son siège social au 1, Rue du Caporal Corbi, Roches\nNoires – Casablanca et est cotée à la Bourse de Casablanca au 1er compartiment.\nLe Groupe Lesieur Cristal est spécialisé dans le secteur des corps gras (huiles alimentaires et margarines).\nLes comptes et informations sont présentés en millions de dirhams Marocains (MDH), sauf les informations par action qui sont présentées en dirhams.\nNOTE 2. ÉVÈNEMENTS SIGNIFICATIFS INTERVENUS AU COURS DE LA PÉRIODE\nAu cours de l’exercice 2023, le périmètre du Groupe Lesieur Cristal n’a pas connu de variations par rapport au 31 décembre 2022.\nNOTE 3. RÈGLES ET MÉTHODES COMPTABLES\nEn application de l’avis n°5 du Conseil National de la Comptabilité (CNC) du 26 mai 2005 et conformément aux dispositions des articles 2.7 et 2.8 de la circulaire 03/19 de l’Autorité Marocaine du Marché des\ncapitaux , les états financiers consolidés du Groupe Lesieur Cristal sont préparés en conformité avec les normes comptables internationales adoptées au sein de l’Union Européenne au 30 Juin 2023 et telles\nque publiées à cette même date.\nLes normes comptables internationales comprennent les IFRS (International Financial Reporting Standards), les IAS (International Accounting Standards) et leurs interprétations SIC et IFRIC (Standards\nInterpretations Committee et International Financial Reporting Interpretations Committee).\nLe Groupe suit régulièrement les dernières publications de l’IASB et de l’IFRIC.\nNOTE 4. PÉRIMÈTRE DE CONSOLIDATION AU 31 DÉCEMBRE 2023\nLESIEUR CRISTAL\nIG IG IG IG IG IG\n100% 100% 100% 93,9% 100% 99,96%\nSociété Les\nd’Exploitation de Domaines Olivco Cristal Indusalim Fireal\nTunisie\nl’Olive Jawhara\nIG IG MEE IG IG IG IG\n100% 100% 34% 93,9% 100% 100% 90,16%\nOleor Hay Al Habaib La Raffinerie Africaine Cristal Distribution Tawzii Lesieur Cristal Lesieur Cristal Inc. Oleosen\nNOTE 5. PRINCIPAUX IMPACTS DES RETRAITEMENTS IFRS\nLe résultat consolidé IFRS au 31 Décembre 2023 du Groupe Lesieur Cristal est impacté par les principaux retraitements suivants :\nIAS 37 Provisions : -18 MDH.\nÉlimination des dotations et reprises des provisions ne répondant pas aux critères de comptabilisation selon les normes IFRS.\nIAS 19 Avantage du personnel : -3 MDH.\nConstatation des avantages post emploi relatifs à la couverture médicale et aux indemnités de fin de carrière.\nIAS 39 Instruments Financiers : -6 MDH.\nReprise du solde d’actualisation du crédit de TVA (-8MDH), et la valorisation à la juste valeur des instruments financiers (2MDH).\nIAS 16 Immobilisations corporelles : +2.0 MDH.\nRetraitement des amortissements des immobilisations selon des durées économiques.\nIAS 38 Immobilisations incorporelles : -29 MDH.\nAnnulation des charges à répartir.\nIAS 12 Impôts sur le résultat : +33 MDH.\nConstatation des ID sur différences temporaires pour 4 MDH et 29 MDH relatifs aux ID des différents retraitements."
            }
        ],
        [
            {
                "TABLEAU DE VARIATION DES CAPITAUX PROPRES CONSOLIDÉS": "Réserves Non Réserves Réserves des opérations Total Capitaux propres Total capitaux\nEn millions de dirhams Capital Intérêt minoritaire\nDistribués de conversion de couverture part du groupe propres",
                "null": ""
            },
            {
                "TABLEAU DE VARIATION DES CAPITAUX PROPRES CONSOLIDÉS": "Au 1er janvier 2022",
                "null": "1 800"
            },
            {
                "TABLEAU DE VARIATION DES CAPITAUX PROPRES CONSOLIDÉS": "Effets des changements de méthode comptable/correction d’erreur -6 -6 -6",
                "null": ""
            },
            {
                "TABLEAU DE VARIATION DES CAPITAUX PROPRES CONSOLIDÉS": "Montants retraités à l’ouverture 276 1 555 -10 -28 1 792 2 1 794",
                "null": ""
            },
            {
                "TABLEAU DE VARIATION DES CAPITAUX PROPRES CONSOLIDÉS": "Variation des capitaux propres",
                "null": ""
            },
            {
                "TABLEAU DE VARIATION DES CAPITAUX PROPRES CONSOLIDÉS": "Résultat de l’exercice - 206 - - 206 -12 193",
                "null": ""
            },
            {
                "TABLEAU DE VARIATION DES CAPITAUX PROPRES CONSOLIDÉS": "Variation nette de juste valeur des instruments financiers - - - -41 -41 - -41",
                "null": ""
            },
            {
                "TABLEAU DE VARIATION DES CAPITAUX PROPRES CONSOLIDÉS": "Pertes et profits de conversion - - -1 - -1 -0 -1",
                "null": ""
            },
            {
                "TABLEAU DE VARIATION DES CAPITAUX PROPRES CONSOLIDÉS": "Variation de juste valeur écarts actuariels - - - 10 10 - 10",
                "null": ""
            },
            {
                "TABLEAU DE VARIATION DES CAPITAUX PROPRES CONSOLIDÉS": "Résultat global total de l’année - 206 -1 -31 174 -13 161",
                "null": ""
            },
            {
                "TABLEAU DE VARIATION DES CAPITAUX PROPRES CONSOLIDÉS": "Dividendes distribués - -97 - - -97 - -97",
                "null": ""
            },
            {
                "TABLEAU DE VARIATION DES CAPITAUX PROPRES CONSOLIDÉS": "Augmentation de capital - 1 - - 1 6 7",
                "null": ""
            },
            {
                "TABLEAU DE VARIATION DES CAPITAUX PROPRES CONSOLIDÉS": "Total des transactions avec les actionnaires - -96 - - -96 6 -90",
                "null": ""
            },
            {
                "TABLEAU DE VARIATION DES CAPITAUX PROPRES CONSOLIDÉS": "Au 31 décembre 2022",
                "null": "1 866"
            },
            {
                "TABLEAU DE VARIATION DES CAPITAUX PROPRES CONSOLIDÉS": "Au 1er janvier 2023",
                "null": "1 866"
            },
            {
                "TABLEAU DE VARIATION DES CAPITAUX PROPRES CONSOLIDÉS": "Montants retraités à l’ouverture 276 1 664 -11 -59 1 870 -5 1 866",
                "null": ""
            },
            {
                "TABLEAU DE VARIATION DES CAPITAUX PROPRES CONSOLIDÉS": "Variation des capitaux propres - - - - - - 0",
                "null": ""
            },
            {
                "TABLEAU DE VARIATION DES CAPITAUX PROPRES CONSOLIDÉS": "Résultat de l’exercice - 2 - - 2 -5 -3",
                "null": ""
            },
            {
                "TABLEAU DE VARIATION DES CAPITAUX PROPRES CONSOLIDÉS": "Variation nette de juste valeur des instruments financiers - - - 21 21 - 21",
                "null": ""
            },
            {
                "TABLEAU DE VARIATION DES CAPITAUX PROPRES CONSOLIDÉS": "Pertes et profits de conversion - - 1 - 43 0 43",
                "null": ""
            },
            {
                "TABLEAU DE VARIATION DES CAPITAUX PROPRES CONSOLIDÉS": "Résultat global total de l’année - 2 1 63 67 -5 61",
                "null": ""
            },
            {
                "TABLEAU DE VARIATION DES CAPITAUX PROPRES CONSOLIDÉS": "Dividendes distribués - -124 - - -124 - -124",
                "null": ""
            },
            {
                "TABLEAU DE VARIATION DES CAPITAUX PROPRES CONSOLIDÉS": "Changement de périmètre - -1 - - -1 0 -1",
                "null": ""
            },
            {
                "TABLEAU DE VARIATION DES CAPITAUX PROPRES CONSOLIDÉS": "Total des transactions avec les actionnaires - -126 - - -126 0 -126",
                "null": ""
            },
            {
                "TABLEAU DE VARIATION DES CAPITAUX PROPRES CONSOLIDÉS": "Au 31 décembre 2023",
                "null": "1 802"
            }
        ],
        [],
        [],
        [],
        [],
        [],
        [],
        [],
        [],
        [],
        [],
        [],
        [],
        [
            {
                "ÉTATS FINANCIERS CONSOLIDÉS\nEXERCICE CLOS LE 31 DÉCEMBRE 2023": "2. DEPRECIATION DES CREANCES CLIENTS\nRisque identifié Notre réponse\n4, Rue Maati Jazouli (Ex Rue Friol),l)\n3 2 M7 0 a, 0 rB o5 cd 0 A Cb ad se al bla latif n B caen Kaddour A Mn af ra o c– Casablanca L v mae ols e n uc tarr é nna t en dtc t ee e s a Mc uli Me n 3 At 1 Ds s d’ 2éé 1clè e 8v m e dbn ert e à p 2M r0 oM 2 vi3A s iD od no8 n1 pt2 o ue unn r L 2e 0s 2 3t ,r oa nva t u nx o tas mur m l ee ns t cc oo nm sip st te és e na u : 31 décembre\ndépréciation.\nC d’e us n ep r mov éis thio on ds e s so tn at t isd té iqte ur em i qn ué ie s s es ur b ala s eb a ss ue r  La fiabilisation de la balance âgée des\nAux Actionnaires de la société l’ancienneté de la créance (100% de solde pour créances clients en testant pour un\nL 1,E rS uI eE CU aR p C orR aI l S CT oA rbL i S.A. l ce rs é ac nré ca en sc ae ns t éa rn ieté ur ri ee su r àe s 6 à m 1 o a isn ) .e Ct 5 e0 p% en p do au nr t ,l e les  Lé ach an rétil alo lin sa l’ ta ion nc ien dn ee té tr ee st te sn ue r e; latifs à\nCasablanca management complète éventuellement cette l’apurement des créances en période\nrègle par une analyse au cas par cas intégrant subséquente ;\nd’autres indices de dépréciation (relation  Le recalcul de la provision sur la base de\nR S EU XA ERP R P L CO E IR S CT EE G T DAE UTN 1SE e R rF JA IN AL A N D N VE IC ES I RE C R AO S UM C 3M O 1I NS DSS EOA CI L ER I MDES E B S RA EU X 20 C 2O 3MPTES c d No e om s u som p ae é vr rc oai na ti sl oe n, c n oc eo nlu ss.v id.e . é)r . rt éu re l’e a ss tis mu ara tin oc ne d, ufe med o- nb ta ac nk t  Ll Ga a r om u répé aeth l i; so ad te io ns ta dt eis st iq eu ne t rer te iete nn su e a vep ca r lele s\nde la provision pour dépréciation des créances opérationnels pour s’assurer de l’absence\nclients comme un point clé de l’audit compte de créances clients bien que récentes\nOpinion tenu du caractère estimatif de ce processus et présentant un risque de recouvrement ;\nson impact significatif sur les comptes.\nNous avons effectué l’audit des états financiers consolidés de la société Lesieur Cristal S.A. et de ses\nfiliales (Groupe Lesieur Cristal), qui comprennent l’état consolidé de la situation financière au 31\ndécembre 2023, ainsi que le compte de résultat consolidé et l’état consolidé du résultat global, l'état\nconsolidé des variations des capitaux propres et le tableau consolidé des flux de trésorerie pour\nl’exercice clos à cette date, ainsi que les notes annexes, y compris des informations significatives sur\nles méthodes comptables. Ces états financiers consolidés font ressortir un montant de capitaux\npropres consolidés de MMAD 1.802 compte tenu d’un déficit net consolidé de MMAD 2,85.\nNous certifions que les états financiers consolidés cités au premier paragraphe ci-dessus sont réguliers\net sincères et donnent, dans tous leurs aspects significatifs, une image fidèle du résultat des opérations Responsabilités de la direction et des responsables de la gouvernance à l’égard des états\nde l’exercice écoulé ainsi que de la situation financière et du patrimoine du Groupe LESIEUR CRISTAL financiers consolidés\narrêtée au 31 décembre 2023, conformément aux Normes Internationales d’Information Financière\n(IFRS). La direction est responsable de la préparation et de la présentation fidèle des états financiers consolidés,\nconformément aux IFRS, ainsi que du contrôle interne qu'elle considère comme nécessaire pour permettre\nFondement de l’opinion la préparation des états financiers consolidés d'anomalies significatives, que celles-ci résultent de fraudes\nNous avons effectué notre audit selon les Normes de la Profession au Maroc. Les responsabilités qui ou d'erreurs.\nnous incombent en vertu de ces normes sont plus amplement décrites dans la section « Lors de la préparation des états financiers consolidés, c’est à la direction qu’il incombe d’évaluer la capacité\nResponsabilités de l’auditeur à l’égard de l’audit des états financiers consolidés » du présent rapport. du Groupe à poursuivre son exploitation, de communiquer, le cas échéant, les questions se rapportant à\nNous sommes indépendants du Groupe conformément aux règles de déontologie qui s’appliquent à la continuité de l’exploitation et d’appliquer le principe comptable de continuité d’exploitation, sauf si la\nl’audit des états financiers consolidés au Maroc et nous nous sommes acquittés des autres direction a l’intention de liquider le Groupe ou de cesser son activité ou si aucune autre solution réaliste ne\nresponsabilités déontologiques qui nous incombent selon ces règles. Nous estimons que les éléments s’offre à elle.\nprobants que nous avons obtenus sont suffisants et appropriés pour fonder notre opinion d’audit. Il incombe aux responsables de la gouvernance de surveiller le processus d’information financière du\nGroupe.\nQuestions clés de l’audit\nResponsabilités de l’auditeur à l’égard de l’audit des états financiers consolidés\nLes questions clés de l’audit sont les questions qui, selon notre jugement professionnel, ont été les plus\nimportantes dans l’audit des états financiers consolidés de la période considérée. Ces questions ont été\ntraitées dans le contexte de notre audit des états financiers consolidés pris dans leur ensemble et aux fins Notre responsabilité est d'exprimer une opinion sur ces états financiers consolidés sur la base de notre\nde la formation de notre opinion sur ceux-ci, et nous n’exprimons pas une opinion distincte sur ces audit. Nous avons effectué notre audit selon les Normes de la Profession au Maroc.\nquestions.\n1. GOODWILL\nRisque identifié Notre réponse\nLe Groupe Lesieur Cristal a réalisé des Notre approche d’audit se fonde sur un examen des\nopérations de croissance externes ayant procédures relatives aux tests de dépréciation des\nconduit à la comptabilisation des écarts écarts d’acquisition et des contrôles mis en place au\nd’acquisition à l’actif du bilan consolidé. Ces sein de Lesieur Cristal pour identifier les indices de1 3\nécarts correspondent à la différence entre le pertes de valeur de ces actifs.\nprix d’acquisition des sociétés acquises et les\njuste-valeurs des actifs et passifs identifiables Les travaux sur les comptes au 31 décembre 2023,\nrepris à la date d’acquisition. Au 31 décembre ont notamment consisté en :\n2023, la valeur de ces écarts d’acquisition\ns’élève à MMAD 109.  Une analyse de la méthodologie retenue par\nLesieur Cristal ;\nLes écarts d’acquisition sont affectés à des  Un examen des plans d’affaires approuvés\nUnités Génératrices de trésorerie et font l’objet par la Direction Générale de Lesieur Cristal\nde tests de dépréciation au moins une fois par pour s’assurer du caractère raisonnable des\nan ou dès la présence d’un indice de perte de estimations de flux futurs dégagés ;\nvaleur. Lorsque leur valeur recouvrable devient  Une analyse des principales hypothèses et\ninférieure à la valeur comptable, une paramètres utilisés (taux de croissance,\ndépréciation est comptabilisée. coût du capital, taux d’actualisation) au\nregard des données de marché\nLes informations concernant les méthodes de disponibles ;\ndétermination de la valeur recouvrable sont  Un examen des analyses de sensibilité des\ndétaillées dans la note «16 » de l’annexe aux estimations aux paramètres clés (en\ncomptes consolidés. particulier lorsque la valeur recouvrable est\nproche de la valeur nette comptable) ;\nNous avons considéré que l’évaluation des  Le recalcul des valeurs d’utilités\nécarts d’acquisition constituait un point clé de déterminées pour les principaux écarts\nnotre audit en raison de : d’acquisition.\nEnfin, nous avons examiné les informations\n Leur montant significatif au bilan relatives aux résultats de ces tests de\nconsolidé du Groupe ; dépréciation et tests de sensibilité présentés\n L’importance du jugement de la dans les notes annexes aux états financiers.\ndirection dans le choix de la méthode\nde détermination de la valeur\nrecouvrable et, dans le cas de la valeur\nd’utilité, des hypothèses de résultats\nfuturs des sociétés concernées et du\ntaux d’actualisation appliqué aux flux\nde trésorerie prévisionnels.\n2"
            }
        ],
        [
            {
                "ÉTATS FINANCIERS SOCIAUX\nEXERCICE CLOS LE 31 DÉCEMBRE 2023": "BILAN ACTIF BILAN PASSIF\ndu 01/01/2023 au 31/12/2023 du 01/01/2023 au 31/12/2023\nEXERCICE EXERCICE EXERCICE\n(Montants en dhs) Amortissements PRÉCÉDENT (Montants en dhs) EXERCICE PRÉCÉDENT\nBrut et provisions Net Net CAPITAUX PROPRES 1 656 124 468,47 1 771 593 689,18\nImmobilisations en non valeur (A) 88 634 261,74 49 964 921,84 38 669 339,90 15 694 581,38\nCapital social ou personnel ( 1) 276 315 100,00 276 315 100,00\nFrais préliminaires\nCharges à répartir sur plusieurs exercices 88 634 261,74 49 964 921,84 38 669 339,90 15 694 581,38 Moins : actionnaires, capital souscrit non appelé\nPrimes de remboursement des obligations Capital appelé 276 315 100,00 276 315 100,00\nImmobilisations incorporelles (B) 232 950 561,51 70 289 398,50 162 661 163,01 166 846 787,42 dont versé 276 315 100,00 276 315 100,00\nImmobilisations en recherche et développement Primes d’émission, de fusion, d’apport\nBrevets, marques, droits et valeurs similaires 142 681 873,13 48 386 918,12 94 294 955,01 98 480 579,42 T N Écarts de réevaluation\nE Fonds commercial 90 268 688,38 21 902 480,38 68 366 208,00 68 366 208,00 E Réserve légale 27 631 510,00 27 631 510,00\nS I L I B Autres immobilisations incorporelles Immobilisations corporelles (C) 2 205 921 185,77 1 842 503 997,59 363 417 188,18 353 939 646,32 Terrains 64 771 013,48 64 771 013,48 64 771 013,48 N A M R Autres réserves 827 623 799,70 827 623 799,70 Report à nouveau ( 2 ) 515 681 484,48 422 907 256,64 Résultats nets en instance d’affectation 0,00\nO M Constructions 296 002 078,38 232 618 712,11 63 383 366,27 61 140 878,02 Installations techniques, matériel et outillage 1 608 769 040,12 1 441 267 179,78 167 501 860,34 182 165 335,45 E P Résultat net de l’exercice ( 2) 8 872 574,29 217 116 022,84\nM Matériel de transport 69 348 854,15 69 348 854,15 T Total des capitaux propres (A) 1 656 124 468,47 1 771 593 689,18\nI Mobilier, matériel de bureau, aménagements divers 107 041 637,53 99 269 251,55 7 772 385,98 3 474 671,76 N Capitaux propres assimilés (B) 77 807 424,74 96 235 942,59\nF Autres immobilisations corporelles E Subventions d’investissement\nI T Immobilisations corporelles en cours 59 988 562,11 59 988 562,11 42 387 747,61 M E Provisions réglementées 77 807 424,74 96 235 942,59\nC Immobilisations financières (D) 564 297 971,50 172 180 362,45 392 117 609,05 417 745 941,19 C Dettes de financement (C)\nA Prêts immobilisés 5 136 224,66 5 136 224,66 7 241 017,87 N Emprunts obligataires\nAutres créances financières 3 121 663,22 3 121 663,22 3 121 663,22 A N Autres dettes de financement\nTitres de participation 556 040 083,62 172 180 362,45 383 859 721,17 407 383 260,10 I Provisions durables pour risques et charges (D) 20 461 623,56 9 928 656,78\nAutres titres immobilisés F\nProvisions pour risques 20 461 623,56 9 928 656,78\nÉcart de conversion - Actif (E)\nDiminution des créances immobilisées Provisions pour charges\nAugmentations des dettes de financement Écart de conversion - Passif (E)\nTOTAL I (A+B+C+D+E) 3 091 803 980,52 2 134 938 680,38 956 865 300,14 954 226 956,31 Augmentation des créances immobilisées\nStocks (F) 1 291 540 948,50 49 609 063,20 1 241 931 885,30 1 482 036 212,94 Diminution des dettes de financement\nMarchandises 19 959 678,96 3 637 918,52 16 321 760,44 8 528 444,66 TOTAL I ( A + B + C + D + E ) 1 754 393 516,77 1 877 758 288,55\nMatières et fournitures consommables 658 467 714,41 45 901 369,68 612 566 344,73 1 019 658 480,34 Dettes du passif circulant (F) 1 995 378 776,99 3 460 725 741,40\nT N Produits en cours 146 291 769,44 146 291 769,44 159 942 162,12 Fournisseurs et comptes rattachés 1 735 521 090,72 3 107 713 660,67\nA L U Produits intermédiaires et produits résiduels 1 151 170,89 1 151 170,89 541 949,31 Produits finis 465 670 614,80 69 775,00 465 600 839,80 293 365 176,51 Créances de l’actif circulant (G) 1 533 342 046,49 273 387 823,36 1 259 954 223,13 1 603 586 955,61 T N A L Clients créditeurs, avances et acomptes 1 228 870,14 3 936 348,48 Personnel 34 412 303,65 56 128 600,65\nC R I C Fournisseurs débiteurs, avances & acomptes 45 903 965,65 45 903 965,65 32 460 398,31 Clients et comptes rattachés 880 011 155,82 218 302 998,75 661 708 157,07 892 847 482,20 Personnel 11 160 202,68 2 978 242,92 8 181 959,76 6 429 895,57 U C R I C Organismes sociaux 21 790 866,30 16 704 918,10 État 41 070 289,20 122 325 422,30 Comptes d’associés 154 563 640,45 148 843 465,75\nF I T État 335 000 184,68 335 000 184,68 283 321 559,98 Compte d’associés 249 035 571,67 46 922 694,42 202 112 877,25 318 868 215,95 F I S S Autres créanciers 5 770 062,96 2 055 371,60 Comptes de régularisation - passif 1 021 653,57 3 017 953,85\nC Autres débiteurs 7 655 418,54 5 183 887,27 2 471 531,27 61 367 224,11 A P Autres provisions pour risques et charges (G) 59 428 626,13 86 230 743,53\nA Comptes de régularisation actif 4 575 547,45 4 575 547,45 8 292 179,49 Écarts de conversion Passif ( éléments circulants ) (H)\nTitres et valeurs de placement (H) 146 191 674,26 146 191 674,26 1 338 225 099,36\nTOTAL II ( F + G + H ) 2 054 807 403,12 3 546 956 484,93\nÉcarts de conversion-Actif (I) Eléments circulants\nTOTAL II (F+G+H+I) 2 971 074 669,25 322 996 886,56 2 648 077 782,69 4 423 848 267,91 EIREROSERT Trésorerie-Passif 2 252 633,61 39 960 410,54\nEIREROSÉRT Trésorerie-Actif 206 510 470,67 206 510 470,67 86 599 959,80 Crédits d’escompte\nChèques et valeurs à encaisser 99 694 286,39 99 694 286,39 50 490 780,50 Crédits de trésorerie\nBanques, T.G et C.C.P 100 121 781,97 100 121 781,97 26 723 110,45 Banques (Soldes créditeurs) 2 252 633,61 39 960 410,54\nCaisses, Régies d’avances et accréditifs 6 694 402,31 6 694 402,31 9 386 068,85 TOTAL III 2 252 633,61 39 960 410,54\nTOTAL III 206 510 470,67 206 510 470,67 86 599 959,80 TOTAL GÉNÉRAL ( I + II + III ) 3 811 453 553,50 5 464 675 184,02\n(1) Capital personnel débiteur TOTAL GÉNÉRAL 6 269 389 120,44 2 457 935 566,94 3 811 453 553,50 5 464 675 184,02\n(2) Bénéficiaire (+), déficitaire (-)\nCOMPTE DE PRODUITS ET CHARGES (Hors Taxes) COMPTE DE PRODUITS ET CHARGES (Hors Taxes) Suite\n(Montants en dhs) Exercice du 1 janvier 2023 au 31 Décembre 2023 (Montants en dhs) Exercice du 1 janvier 2023 au 31 décembre 2023\nOPÉRATIONS OPÉRATIONS\nConcernant TOTAUX DE TOTAUX DE Concernant TOTAUX DE TOTAUX DE\nPropres à Propres à\nNATURE les exercices L’EXERCICE L’EXERCICE NATURE les exercices L’EXERCICE L’EXERCICE\nl’exercice l’exercice\nprécédents PRÉCÉDENT précédents PRÉCÉDENT\n(1) (2) 3= 1 + 2 (1) (2) 3= 1 + 2\nI Produits d’exploitation 6 325 733 397,70 6 325 733 397,70 5 976 163 603,18 VIII Produits non courants 50 452 492,63 50 452 492,63 25 642 096,93\nVentes de marchandises (en l’état) 390 466 281,17 390 466 281,17 405 119 220,95\nVentes de biens et services produits 4 838 519 668,05 4 838 519 668,05 5 581 147 007,12 Produits de cessions d’immobilisations 280 000,00 280 000,00\nChiffre d’affaires 5 228 985 949,22 5 228 985 949,22 5 986 266 228,07\nSubventions d’équilibre\nVariation de stocks de produits ( + ou -) (1) 925 022 185,55 925 022 185,55 -94 424 628,72\nI mmobilisations produites par l’entreprise pour Reprises sur subventions\nelle-même d’investissement\nN Subventions d’exploitation 1 611 618,61 1 611 618,61 402 575,67 Autres produits non courants 0,09 0,09 1,07\nO Autres produits d’exploitation 27 851 379,42 27 851 379,42 39 876 445,97\nI T Reprises d’exploitation : transferts de charges 142 262 264,90 142 262 264,90 44 042 982,19 T N Reprises non courantes : transferts de 50 172 492,54 50 172 492,54 25 642 095,86\nA A charges\nT TOTAL I 6 325 733 397,70 6 325 733 397,70 5 976 163 603,18 R\nI O II Charges d’exploitation 6 273 447 310,88 1 956 495,49 6 275 403 806,37 5 472 119 371,60 U TOTAL VIII 50 452 492,63 50 452 492,63 25 642 096,93\nL P Achats revendus (2) de marchandises 526 766 178,24 526 766 178,24 442 478 804,42 O C IX Charges non courantes 59 235 719,03 1 103 939,00 60 339 658,03 95 877 831,03\nX Achats consommés (2) de matières et fournitures 4 944 197 071,22 276 982,01 4 944 474 053,23 4 194 687 346,71 N\nE O Valeurs nettes d’amortissement des\nAutres charges externes 329 310 230,90 946 351,04 330 256 581,94 373 683 290,43 N immobilisations cédées\nImpôts et taxes 5 414 760,65 733 162,44 6 147 923,09 5 753 375,92\nSubventions accordées\nCharges de personnel 247 008 895,08 247 008 895,08 267 761 477,90\nAutres charges d’exploitation 4 330 038,64 4 330 038,64 5 577 687,07 Autres charges non courantes 49 085 704,66 1 103 939,00 50 189 643,66 67 545 921,81\nDotations d’exploitation 216 420 136,15 216 420 136,15 182 177 389,15\nDotations non courantes aux\nTOTAL II 6 273 447 310,88 1 956 495,49 6 275 403 806,37 5 472 119 371,60 amortissements et aux provisions 10 150 014,37 10 150 014,37 28 331 909,22\nIII RÉSULTAT D’EXPLOITATION ( I - II ) 52 286 086,82 -1 956 495,49 50 329 591,33 504 044 231,58 TOTAL IX 59 235 719,03 1 103 939,00 60 339 658,03 95 877 831,03\nIV Produits financiers 29 600 395,65 29 600 395,65 40 870 331,04\nProduits des titres de participation et autres titres immobilisés 2 972 202,08 2 972 202,08 475 002,00 X RÉSULTAT NON COURANT ( VIII - IX ) -8 783 226,40 -1 103 939,00 -9 887 165,40 -70 235 734,10\nGains de change 4 598 334,62 4 598 334,62 3 551 045,49 XI RÉSULTAT AVANT IMPÔTS ( VII+ ou - X) 30 967 623,78-3 060 434,49 27 907 189,29 402 162 182,84\nIntérêts et autres produits financiers 20 404 731,09 20 404 731,09 24 058 516,94\nR E Reprises financières : transferts de charges 1 625 127,86 1 625 127,86 12 785 766,61 XII IMPÔTS SUR LES RÉSULTATS 19 034 615,00 19 034 615,00 185 046 160,00\nI\nC TOTAL IV 29 600 395,65 29 600 395,65 40 870 331,04 XIII RÉSULTAT NET ( XI - XII ) 11 933 008,78-3 060 434,49 8 872 574,29 217 116 022,84\nN V Charges financières 42 135 632,29 42 135 632,29 72 516 645,68\nA\nN Charges d’intérêts 12 459 735,29 12 459 735,29 11 639 667,43 XIV TOTAL DES PRODUITS ( I + IV + VIII ) 6 405 786 285,98 6 405 786 285,98 6 042 676 031,15\nI\nF Pertes de change 5 341 368,48 5 341 368,48 4 371 727,70\nXV TOTAL DES CHARGES ( II + V + IX + XII ) 6 393 853 277,20 3 060 434,49 6 396 913 711,69 5 825 560 008,31\nAutres charges financières -5 377 000,43 -5 377 000,43 -7,06\nDotations financières 29 711 528,95 29 711 528,95 56 505 257,61 RÉSULTAT NET ( total produits - total XVI 11 933 008,78-3 060 434,49 8 872 574,29 217 116 022,84\ncharges )\nTOTAL V 42 135 632,29 42 135 632,29 72 516 645,68\nVI RÉSULTAT FINANCIER ( IV - V ) -12 535 236,64 -12 535 236,64 -31 646 314,64\n1)Variation de stock : Stock final-Stock initial : Augmentation(+); Diminution(-)\n2)Achats revendus ou achats consommés : Achats - variation de stock. VII RÉSULTAT COURANT ( III + VI ) 39 750 850,18 -1 956 495,49 37 794 354,69 472 397 916,94"
            }
        ],
        [
            {
                "BILAN ACTIF\ndu 01/01/2023 au 31/12/2023": "(Montants en dhs)",
                "null": "EXERCICE\nPRÉCÉDENT\nNet"
            },
            {
                "BILAN ACTIF\ndu 01/01/2023 au 31/12/2023": "",
                "null": ""
            },
            {
                "BILAN ACTIF\ndu 01/01/2023 au 31/12/2023": "E\nS\nI\nL\nI\nB\nO\nM\nM\nI\nF\nI\nT\nC\nA",
                "null": "15 694 581,38\n15 694 581,38\n166 846 787,42\n98 480 579,42\n68 366 208,00\n353 939 646,32\n64 771 013,48\n61 140 878,02\n182 165 335,45\n3 474 671,76\n42 387 747,61\n417 745 941,19\n7 241 017,87\n3 121 663,22\n407 383 260,10"
            },
            {
                "BILAN ACTIF\ndu 01/01/2023 au 31/12/2023": "",
                "null": ""
            },
            {
                "BILAN ACTIF\ndu 01/01/2023 au 31/12/2023": "",
                "null": ""
            },
            {
                "BILAN ACTIF\ndu 01/01/2023 au 31/12/2023": "",
                "null": ""
            },
            {
                "BILAN ACTIF\ndu 01/01/2023 au 31/12/2023": "",
                "null": ""
            },
            {
                "BILAN ACTIF\ndu 01/01/2023 au 31/12/2023": "",
                "null": ""
            },
            {
                "BILAN ACTIF\ndu 01/01/2023 au 31/12/2023": "",
                "null": ""
            },
            {
                "BILAN ACTIF\ndu 01/01/2023 au 31/12/2023": "",
                "null": ""
            },
            {
                "BILAN ACTIF\ndu 01/01/2023 au 31/12/2023": "",
                "null": ""
            },
            {
                "BILAN ACTIF\ndu 01/01/2023 au 31/12/2023": "",
                "null": ""
            },
            {
                "BILAN ACTIF\ndu 01/01/2023 au 31/12/2023": "",
                "null": ""
            },
            {
                "BILAN ACTIF\ndu 01/01/2023 au 31/12/2023": "",
                "null": ""
            },
            {
                "BILAN ACTIF\ndu 01/01/2023 au 31/12/2023": "",
                "null": ""
            },
            {
                "BILAN ACTIF\ndu 01/01/2023 au 31/12/2023": "",
                "null": ""
            },
            {
                "BILAN ACTIF\ndu 01/01/2023 au 31/12/2023": "",
                "null": ""
            },
            {
                "BILAN ACTIF\ndu 01/01/2023 au 31/12/2023": "",
                "null": ""
            },
            {
                "BILAN ACTIF\ndu 01/01/2023 au 31/12/2023": "",
                "null": ""
            },
            {
                "BILAN ACTIF\ndu 01/01/2023 au 31/12/2023": "",
                "null": ""
            },
            {
                "BILAN ACTIF\ndu 01/01/2023 au 31/12/2023": "",
                "null": ""
            },
            {
                "BILAN ACTIF\ndu 01/01/2023 au 31/12/2023": "",
                "null": ""
            },
            {
                "BILAN ACTIF\ndu 01/01/2023 au 31/12/2023": "",
                "null": ""
            },
            {
                "BILAN ACTIF\ndu 01/01/2023 au 31/12/2023": "",
                "null": ""
            },
            {
                "BILAN ACTIF\ndu 01/01/2023 au 31/12/2023": "",
                "null": ""
            },
            {
                "BILAN ACTIF\ndu 01/01/2023 au 31/12/2023": "",
                "null": ""
            },
            {
                "BILAN ACTIF\ndu 01/01/2023 au 31/12/2023": "",
                "null": ""
            },
            {
                "BILAN ACTIF\ndu 01/01/2023 au 31/12/2023": "",
                "null": "954 226 956,31"
            },
            {
                "BILAN ACTIF\ndu 01/01/2023 au 31/12/2023": "T\nN\nA\nL\nU\nC\nR\nI\nC\nF\nI\nT\nC\nA",
                "null": "1 482 036 212,94\n8 528 444,66\n1 019 658 480,34\n159 942 162,12\n541 949,31\n293 365 176,51\n1 603 586 955,61\n32 460 398,31\n892 847 482,20\n6 429 895,57\n283 321 559,98\n318 868 215,95\n61 367 224,11\n8 292 179,49\n1 338 225 099,36"
            },
            {
                "BILAN ACTIF\ndu 01/01/2023 au 31/12/2023": "",
                "null": ""
            },
            {
                "BILAN ACTIF\ndu 01/01/2023 au 31/12/2023": "",
                "null": ""
            },
            {
                "BILAN ACTIF\ndu 01/01/2023 au 31/12/2023": "",
                "null": ""
            },
            {
                "BILAN ACTIF\ndu 01/01/2023 au 31/12/2023": "",
                "null": ""
            },
            {
                "BILAN ACTIF\ndu 01/01/2023 au 31/12/2023": "",
                "null": ""
            },
            {
                "BILAN ACTIF\ndu 01/01/2023 au 31/12/2023": "",
                "null": ""
            },
            {
                "BILAN ACTIF\ndu 01/01/2023 au 31/12/2023": "",
                "null": ""
            },
            {
                "BILAN ACTIF\ndu 01/01/2023 au 31/12/2023": "",
                "null": ""
            },
            {
                "BILAN ACTIF\ndu 01/01/2023 au 31/12/2023": "",
                "null": ""
            },
            {
                "BILAN ACTIF\ndu 01/01/2023 au 31/12/2023": "",
                "null": ""
            },
            {
                "BILAN ACTIF\ndu 01/01/2023 au 31/12/2023": "",
                "null": ""
            },
            {
                "BILAN ACTIF\ndu 01/01/2023 au 31/12/2023": "",
                "null": ""
            },
            {
                "BILAN ACTIF\ndu 01/01/2023 au 31/12/2023": "",
                "null": ""
            },
            {
                "BILAN ACTIF\ndu 01/01/2023 au 31/12/2023": "",
                "null": ""
            },
            {
                "BILAN ACTIF\ndu 01/01/2023 au 31/12/2023": "",
                "null": ""
            },
            {
                "BILAN ACTIF\ndu 01/01/2023 au 31/12/2023": "",
                "null": "4 423 848 267,91"
            },
            {
                "BILAN ACTIF\ndu 01/01/2023 au 31/12/2023": "EIREROSÉRT",
                "null": "86 599 959,80"
            },
            {
                "BILAN ACTIF\ndu 01/01/2023 au 31/12/2023": "",
                "null": "50 490 780,50\n26 723 110,45\n9 386 068,85"
            },
            {
                "BILAN ACTIF\ndu 01/01/2023 au 31/12/2023": "",
                "null": ""
            },
            {
                "BILAN ACTIF\ndu 01/01/2023 au 31/12/2023": "",
                "null": ""
            },
            {
                "BILAN ACTIF\ndu 01/01/2023 au 31/12/2023": "",
                "null": "86 599 959,80"
            },
            {
                "BILAN ACTIF\ndu 01/01/2023 au 31/12/2023": "",
                "null": "5 464 675 184,02"
            }
        ],
        [
            {
                "BILAN PASSIF\ndu 01/01/2023 au 31/12/2023": "(Montants en dhs)",
                "null": "EXERCICE\nPRÉCÉDENT"
            },
            {
                "BILAN PASSIF\ndu 01/01/2023 au 31/12/2023": "T\nN\nE\nN\nA\nM\nR\nE\nP\nT\nN\nE\nM\nE\nC\nN\nA\nN\nI\nF",
                "null": "1 771 593 689,18\n276 315 100,00\n276 315 100,00\n276 315 100,00\n27 631 510,00\n827 623 799,70\n422 907 256,64\n217 116 022,84"
            },
            {
                "BILAN PASSIF\ndu 01/01/2023 au 31/12/2023": "",
                "null": ""
            },
            {
                "BILAN PASSIF\ndu 01/01/2023 au 31/12/2023": "",
                "null": ""
            },
            {
                "BILAN PASSIF\ndu 01/01/2023 au 31/12/2023": "",
                "null": ""
            },
            {
                "BILAN PASSIF\ndu 01/01/2023 au 31/12/2023": "",
                "null": ""
            },
            {
                "BILAN PASSIF\ndu 01/01/2023 au 31/12/2023": "",
                "null": ""
            },
            {
                "BILAN PASSIF\ndu 01/01/2023 au 31/12/2023": "",
                "null": ""
            },
            {
                "BILAN PASSIF\ndu 01/01/2023 au 31/12/2023": "",
                "null": ""
            },
            {
                "BILAN PASSIF\ndu 01/01/2023 au 31/12/2023": "",
                "null": ""
            },
            {
                "BILAN PASSIF\ndu 01/01/2023 au 31/12/2023": "",
                "null": ""
            },
            {
                "BILAN PASSIF\ndu 01/01/2023 au 31/12/2023": "",
                "null": ""
            },
            {
                "BILAN PASSIF\ndu 01/01/2023 au 31/12/2023": "",
                "null": ""
            },
            {
                "BILAN PASSIF\ndu 01/01/2023 au 31/12/2023": "",
                "null": "1 771 593 689,18"
            },
            {
                "BILAN PASSIF\ndu 01/01/2023 au 31/12/2023": "",
                "null": "96 235 942,59\n96 235 942,59\n9 928 656,78\n9 928 656,78"
            },
            {
                "BILAN PASSIF\ndu 01/01/2023 au 31/12/2023": "",
                "null": ""
            },
            {
                "BILAN PASSIF\ndu 01/01/2023 au 31/12/2023": "",
                "null": ""
            },
            {
                "BILAN PASSIF\ndu 01/01/2023 au 31/12/2023": "",
                "null": ""
            },
            {
                "BILAN PASSIF\ndu 01/01/2023 au 31/12/2023": "",
                "null": ""
            },
            {
                "BILAN PASSIF\ndu 01/01/2023 au 31/12/2023": "",
                "null": ""
            },
            {
                "BILAN PASSIF\ndu 01/01/2023 au 31/12/2023": "",
                "null": ""
            },
            {
                "BILAN PASSIF\ndu 01/01/2023 au 31/12/2023": "",
                "null": ""
            },
            {
                "BILAN PASSIF\ndu 01/01/2023 au 31/12/2023": "",
                "null": ""
            },
            {
                "BILAN PASSIF\ndu 01/01/2023 au 31/12/2023": "",
                "null": ""
            },
            {
                "BILAN PASSIF\ndu 01/01/2023 au 31/12/2023": "",
                "null": ""
            },
            {
                "BILAN PASSIF\ndu 01/01/2023 au 31/12/2023": "",
                "null": ""
            },
            {
                "BILAN PASSIF\ndu 01/01/2023 au 31/12/2023": "",
                "null": "1 877 758 288,55"
            },
            {
                "BILAN PASSIF\ndu 01/01/2023 au 31/12/2023": "T\nN\nA\nL\nU\nC\nR\nI C\nF\nI S\nS\nA\nP",
                "null": "3 460 725 741,40\n3 107 713 660,67\n3 936 348,48\n56 128 600,65\n16 704 918,10\n122 325 422,30\n148 843 465,75\n2 055 371,60\n3 017 953,85\n86 230 743,53"
            },
            {
                "BILAN PASSIF\ndu 01/01/2023 au 31/12/2023": "",
                "null": ""
            },
            {
                "BILAN PASSIF\ndu 01/01/2023 au 31/12/2023": "",
                "null": ""
            },
            {
                "BILAN PASSIF\ndu 01/01/2023 au 31/12/2023": "",
                "null": ""
            },
            {
                "BILAN PASSIF\ndu 01/01/2023 au 31/12/2023": "",
                "null": ""
            },
            {
                "BILAN PASSIF\ndu 01/01/2023 au 31/12/2023": "",
                "null": ""
            },
            {
                "BILAN PASSIF\ndu 01/01/2023 au 31/12/2023": "",
                "null": ""
            },
            {
                "BILAN PASSIF\ndu 01/01/2023 au 31/12/2023": "",
                "null": ""
            },
            {
                "BILAN PASSIF\ndu 01/01/2023 au 31/12/2023": "",
                "null": ""
            },
            {
                "BILAN PASSIF\ndu 01/01/2023 au 31/12/2023": "",
                "null": ""
            },
            {
                "BILAN PASSIF\ndu 01/01/2023 au 31/12/2023": "",
                "null": ""
            },
            {
                "BILAN PASSIF\ndu 01/01/2023 au 31/12/2023": "",
                "null": "3 546 956 484,93"
            },
            {
                "BILAN PASSIF\ndu 01/01/2023 au 31/12/2023": "EIREROSERT",
                "null": "39 960 410,54\n39 960 410,54"
            },
            {
                "BILAN PASSIF\ndu 01/01/2023 au 31/12/2023": "",
                "null": ""
            },
            {
                "BILAN PASSIF\ndu 01/01/2023 au 31/12/2023": "",
                "null": ""
            },
            {
                "BILAN PASSIF\ndu 01/01/2023 au 31/12/2023": "",
                "null": ""
            },
            {
                "BILAN PASSIF\ndu 01/01/2023 au 31/12/2023": "",
                "null": "39 960 410,54"
            },
            {
                "BILAN PASSIF\ndu 01/01/2023 au 31/12/2023": "",
                "null": "5 464 675 184,02"
            }
        ],
        [
            {
                "COMPTE DE PRODUITS ET CHARGES (Hors Taxes)": "",
                "null": ""
            },
            {
                "COMPTE DE PRODUITS ET CHARGES (Hors Taxes)": "",
                "null": "TOTAUX DE\nL’EXERCICE\nPRÉCÉDENT"
            },
            {
                "COMPTE DE PRODUITS ET CHARGES (Hors Taxes)": "",
                "null": ""
            },
            {
                "COMPTE DE PRODUITS ET CHARGES (Hors Taxes)": "",
                "null": ""
            },
            {
                "COMPTE DE PRODUITS ET CHARGES (Hors Taxes)": "N\nO\nI\nT\nA\nT\nI\nO\nL\nP\nX\nE",
                "null": "5 976 163 603,18\n405 119 220,95\n5 581 147 007,12"
            },
            {
                "COMPTE DE PRODUITS ET CHARGES (Hors Taxes)": "",
                "null": ""
            },
            {
                "COMPTE DE PRODUITS ET CHARGES (Hors Taxes)": "",
                "null": ""
            },
            {
                "COMPTE DE PRODUITS ET CHARGES (Hors Taxes)": "",
                "null": "5 986 266 228,07"
            },
            {
                "COMPTE DE PRODUITS ET CHARGES (Hors Taxes)": "",
                "null": "-94 424 628,72\n402 575,67\n39 876 445,97\n44 042 982,19"
            },
            {
                "COMPTE DE PRODUITS ET CHARGES (Hors Taxes)": "",
                "null": ""
            },
            {
                "COMPTE DE PRODUITS ET CHARGES (Hors Taxes)": "",
                "null": ""
            },
            {
                "COMPTE DE PRODUITS ET CHARGES (Hors Taxes)": "",
                "null": ""
            },
            {
                "COMPTE DE PRODUITS ET CHARGES (Hors Taxes)": "",
                "null": ""
            },
            {
                "COMPTE DE PRODUITS ET CHARGES (Hors Taxes)": "",
                "null": "5 976 163 603,18"
            },
            {
                "COMPTE DE PRODUITS ET CHARGES (Hors Taxes)": "",
                "null": "5 472 119 371,60\n442 478 804,42\n4 194 687 346,71\n373 683 290,43\n5 753 375,92\n267 761 477,90\n5 577 687,07\n182 177 389,15"
            },
            {
                "COMPTE DE PRODUITS ET CHARGES (Hors Taxes)": "",
                "null": ""
            },
            {
                "COMPTE DE PRODUITS ET CHARGES (Hors Taxes)": "",
                "null": ""
            },
            {
                "COMPTE DE PRODUITS ET CHARGES (Hors Taxes)": "",
                "null": ""
            },
            {
                "COMPTE DE PRODUITS ET CHARGES (Hors Taxes)": "",
                "null": ""
            },
            {
                "COMPTE DE PRODUITS ET CHARGES (Hors Taxes)": "",
                "null": ""
            },
            {
                "COMPTE DE PRODUITS ET CHARGES (Hors Taxes)": "",
                "null": ""
            },
            {
                "COMPTE DE PRODUITS ET CHARGES (Hors Taxes)": "",
                "null": ""
            },
            {
                "COMPTE DE PRODUITS ET CHARGES (Hors Taxes)": "",
                "null": "5 472 119 371,60"
            },
            {
                "COMPTE DE PRODUITS ET CHARGES (Hors Taxes)": "",
                "null": "504 044 231,58"
            },
            {
                "COMPTE DE PRODUITS ET CHARGES (Hors Taxes)": "R\nE\nI\nC\nN\nA\nN\nI\nF",
                "null": "40 870 331,04\n475 002,00\n3 551 045,49\n24 058 516,94\n12 785 766,61"
            },
            {
                "COMPTE DE PRODUITS ET CHARGES (Hors Taxes)": "",
                "null": ""
            },
            {
                "COMPTE DE PRODUITS ET CHARGES (Hors Taxes)": "",
                "null": ""
            },
            {
                "COMPTE DE PRODUITS ET CHARGES (Hors Taxes)": "",
                "null": ""
            },
            {
                "COMPTE DE PRODUITS ET CHARGES (Hors Taxes)": "",
                "null": ""
            },
            {
                "COMPTE DE PRODUITS ET CHARGES (Hors Taxes)": "",
                "null": "40 870 331,04"
            },
            {
                "COMPTE DE PRODUITS ET CHARGES (Hors Taxes)": "",
                "null": "72 516 645,68\n11 639 667,43\n4 371 727,70\n-7,06\n56 505 257,61"
            },
            {
                "COMPTE DE PRODUITS ET CHARGES (Hors Taxes)": "",
                "null": ""
            },
            {
                "COMPTE DE PRODUITS ET CHARGES (Hors Taxes)": "",
                "null": ""
            },
            {
                "COMPTE DE PRODUITS ET CHARGES (Hors Taxes)": "",
                "null": ""
            },
            {
                "COMPTE DE PRODUITS ET CHARGES (Hors Taxes)": "",
                "null": ""
            },
            {
                "COMPTE DE PRODUITS ET CHARGES (Hors Taxes)": "",
                "null": "72 516 645,68"
            },
            {
                "COMPTE DE PRODUITS ET CHARGES (Hors Taxes)": "",
                "null": "-31 646 314,64"
            },
            {
                "COMPTE DE PRODUITS ET CHARGES (Hors Taxes)": "",
                "null": "472 397 916,94"
            }
        ],
        [
            {
                "COMPTE DE PRODUITS ET CHARGES (Hors Taxes) Suite": "",
                "null": ""
            },
            {
                "COMPTE DE PRODUITS ET CHARGES (Hors Taxes) Suite": "",
                "null": "TOTAUX DE\nL’EXERCICE\nPRÉCÉDENT"
            },
            {
                "COMPTE DE PRODUITS ET CHARGES (Hors Taxes) Suite": "",
                "null": ""
            },
            {
                "COMPTE DE PRODUITS ET CHARGES (Hors Taxes) Suite": "",
                "null": ""
            },
            {
                "COMPTE DE PRODUITS ET CHARGES (Hors Taxes) Suite": "T\nN\nA\nR\nU\nO\nC\nN\nO\nN",
                "null": "25 642 096,93\n1,07\n25 642 095,86"
            },
            {
                "COMPTE DE PRODUITS ET CHARGES (Hors Taxes) Suite": "",
                "null": ""
            },
            {
                "COMPTE DE PRODUITS ET CHARGES (Hors Taxes) Suite": "",
                "null": ""
            },
            {
                "COMPTE DE PRODUITS ET CHARGES (Hors Taxes) Suite": "",
                "null": ""
            },
            {
                "COMPTE DE PRODUITS ET CHARGES (Hors Taxes) Suite": "",
                "null": ""
            },
            {
                "COMPTE DE PRODUITS ET CHARGES (Hors Taxes) Suite": "",
                "null": ""
            },
            {
                "COMPTE DE PRODUITS ET CHARGES (Hors Taxes) Suite": "",
                "null": "25 642 096,93"
            },
            {
                "COMPTE DE PRODUITS ET CHARGES (Hors Taxes) Suite": "",
                "null": "95 877 831,03\n67 545 921,81\n28 331 909,22"
            },
            {
                "COMPTE DE PRODUITS ET CHARGES (Hors Taxes) Suite": "",
                "null": ""
            },
            {
                "COMPTE DE PRODUITS ET CHARGES (Hors Taxes) Suite": "",
                "null": ""
            },
            {
                "COMPTE DE PRODUITS ET CHARGES (Hors Taxes) Suite": "",
                "null": ""
            },
            {
                "COMPTE DE PRODUITS ET CHARGES (Hors Taxes) Suite": "",
                "null": ""
            },
            {
                "COMPTE DE PRODUITS ET CHARGES (Hors Taxes) Suite": "",
                "null": "95 877 831,03"
            },
            {
                "COMPTE DE PRODUITS ET CHARGES (Hors Taxes) Suite": "",
                "null": "-70 235 734,10"
            },
            {
                "COMPTE DE PRODUITS ET CHARGES (Hors Taxes) Suite": "",
                "null": "402 162 182,84"
            },
            {
                "COMPTE DE PRODUITS ET CHARGES (Hors Taxes) Suite": "",
                "null": "185 046 160,00"
            },
            {
                "COMPTE DE PRODUITS ET CHARGES (Hors Taxes) Suite": "",
                "null": "217 116 022,84"
            },
            {
                "COMPTE DE PRODUITS ET CHARGES (Hors Taxes) Suite": "",
                "null": "6 042 676 031,15"
            },
            {
                "COMPTE DE PRODUITS ET CHARGES (Hors Taxes) Suite": "",
                "null": "5 825 560 008,31"
            },
            {
                "COMPTE DE PRODUITS ET CHARGES (Hors Taxes) Suite": "",
                "null": "217 116 022,84"
            }
        ],
        [
            {
                "ÉTATS FINANCIERS SOCIAUX\nEXERCICE CLOS LE 31 DÉCEMBRE 2023": "ÉTAT DES SOLDES DE GESTION PRINCIPALES MÉTHODES D’EVALUATION SPÉCIFIQUES\ndu 01/01/2023 au 31/12/2023\nÀ L’ENTREPRISE\nEXERCICE du 01/01/2023 au 31/12/2023\nDÉSIGNATION EXERCICE\nPRÉCÉDENT I- ACTIF IMMOBILISE\n1 Ventes de Marchandises ( en l’état) 390 466 281,17 405 119 220,95 A- Évaluation à l’entrée\n2 - Achats revendus de marchandises 526 766 178,24 442 478 804,42 1- Immobilisations en non valeurs\nI = MARGE BRUTES VENTES EN L’ÉTAT -136 299 897,07 -37 359 583,47\n+ PRODUCTION DE L’EXERCICE (3+4+5) 5 763 541 853,60 5 486 722 378,40 La valeur d’entrée est constituée par le coût de revient de l’immobilisation.\nII 3 Ventes de biens et services produits 4 838 519 668,05 5 581 147 007,12 2- Immobilisations incorporelles\n4 Variation stocks produits 925 022 185,55 -94 424 628,72 La valeur d’entrée est constituée par le coût de revient de l’immobilisation.\n5 Immobilisations produites par l’entreprise pour elle-même 3- Immobilisations corporelles\n- CONSOMMATIONS DE L’EXERCICE(6+7) 5 274 730 635,17 4 568 370 637,14 Les immobilisations corporelles sont évaluées à leur coût d’acquisition ou de production, compte tenu des frais\nIII 6 Achats consommés de matières et fournitures 4 944 474 053,23 4 194 687 346,71 nécessaires à la mise en état d’utilisation de ces biens.\n7 Autres charges externes 330 256 581,94 373 683 290,43 4- Immobilisations financières\n= VALEUR AJOUTÉE (I+II+III) 352 511 321,36 880 992 157,79 Sont portées dans ce poste de bilan, les sommes payées pour l’acquisition des titres de participation, ainsi que\nIV 8 + Subventions d’exploitation 1 611 618,61 402 575,67 pour les dépôts et cautionnements.\n9 - Impôts et taxes 6 147 923,09 5 753 375,92 B- Création des valeurs\n10 - Charges de personnel 247 008 895,08 267 761 477,90 1- Méthodes d’amortissements\n= EXCÉDENT BRUT D’EXPLOITATION (EBE) |OU INSUFFISANCE 100 966 121,80 607 879 879,64 Les méthodes d’amortissement pratiquées sont les méthodes prévues par les règles fiscales en vigueur pour\nBRUTE D’EXPLOITATION(IBE) chaque catégorie d’immobilisation\nV 11 + Autres produits d’exploitation 27 851 379,42 39 876 445,97 2- Méthodes d’évaluation des provisions pour dépréciation\n12 - Autres charges d’exploitation 4 330 038,64 5 577 687,07 Lorsque la valeur d’inventaire est inférieure à la valeur brute, une provision pour dépréciation est constituée du\n13 + Reprises d’exploitation, transferts de charges 142 262 264,90 44 042 982,19 montant de la différence.\n14 - Dotations d’exploitation 216 420 136,15 182 177 389,15 3- Méthodes de détermination des écarts de Conversion - Actif\nVI = RÉSULTAT D’EXPLOITATION(+ou-) 50 329 591,33 504 044 231,58\nLes écarts de conversion sont calculés d’après le taux de change à la date de clôture.\nVII + RÉSULTAT FINANCIER -12 535 236,64 -31 646 314,64\nVIII = RÉSULTAT COURANT (+ou-) 37 794 354,69 472 397 916,94 II- ACTIF CIRCULANT\nIX + RÉSULTAT NON COURANT -9 887 165,40 -70 235 734,10 A- Évaluation à l’entrée\n15 - Impôts sur les résultats 19 034 615,00 185 046 160,00 1- Stocks\nX = RÉSULTAT NET DE L’EXERCICE 8 872 574,29 217 116 022,84 La méthode d’évaluation du Stock à la fin d’exercice est la méthode du premier entrée, premier sorti (FIFO).\n- TABLEAU DE FORMATION DES RÉSULTATS (T.F.R) 2- Créances\n1 Résultat net de l’exercice 8 872 574,29 217 116 022,84 Les créances sont inscrites en comptabilité pour leur montant nominal. Les créances clients font l’objet, le cas\nBénéfice + 8 872 574,29 217 116 022,84 échéant, d’une provision calculée sur la base du risque de non recouvrement.\nPerte - 3- Titres et valeurs de placement\n2 + Dotations d’exploitation (1) 87 169 456,33 66 747 906,53 Les titres et valeurs de placement sont estimés à la date de clôture au cours de la valeur à la date de fin\n3 + Dotations financières (1) 24 801 156,48 54 690 063,03 d’exercice.\n4 + Dotations non courantes (1) 3 550 014,37 7 593 507,28 B- Création des valeurs\n5 - Reprises d’exploitation (2) 1 976 332,22 830 000,00 1- Méthodes d’évaluation des provisions pour dépréciation\n6 - Reprises financières (2) 1 277 617,55 12 785 766,61\nLorsque la valeur d’inventaire est inférieure à la valeur nominale brute, une provision pour dépréciation est\n7 - Reprises non courantes (2) 21 978 532,22 19 642 095,86 constituée du montant de la différence.\n8 - Produits des cessions d’immobilisation 280 000,00\n2- Méthodes de détermination des écarts de Conversion - Actif\n9 + Valeurs nettes d’amortiss. Des immo. Cédées\nLes écarts de conversion sont calculés d’après le taux de change à la date de clôture.\nI 10 - C DiA stP rA ibC uI tT ioÉ n D s ’A deU T bO énF éIN fiA cN esCEMENT (C.A.F.) 19 28 4 8 38 40 1 77 91 59 ,, 04 08 3 91 62 78 18 09 2 6 83 57 ,, 02 01 III- FINANCEMENT PERMANENT\nII = AUTOFINANCEMENT -25 461 075,52 216 179 352,21 1- Méthodes de réévaluation\nLes capitaux propres et dettes de financement sont inscrites à leur valeur nominale.\n( 1 ) A l’exclusion des dotations relatives aux actifs et passif circulants et à la trésorerie.\n( 2 ) A l’exclusion des reprises relatives aux actifs circulants et à la trésorerie. 2- Méthodes d’évaluation des provisions réglementées\n( 3 ) Y compris reprises sur subventions d’investissements. Lorsque la valeur d’inventaire est inférieure à la valeur nominale brute, une provision pour dépréciation est\nconstituée du montant de la différence.\n3- Dettes de financement permanent\nTABLEAU DE FINANCEMENT (MODÈLE NORMAL) du 01/01/2023 au 31/12/2023 Les dettes de financement sont inscrites en comptabilité pour leur montant nominal.\n4- Méthodes d’évaluation des provisions durables pour risques et charges\nExercice Exercice a - b\nI. SYNTHÈSES DES MASSES DU BILAN Exercice précédent Emplois Ressources Une provision pour risques et charges est constituée pour faire face à la charge future ou au risque créés au\ncours de l’exercice.\nb a c d\nFinancement permanent 1 754 393 516,77 1 877 758 288,55 123 364 771,78 5- Méthodes de détermination des écarts de Conversion - Passif\nMoins actif immobilisé 956 865 300,14 954 226 956,31 2 638 343,83 Les écarts de conversion sont calculés d’après le taux de change à la date de clôture.\n= FONDS DE ROULEMENT FONCTIONNEL (1-2) (A) 797 528 216,63 923 531 332,24 126 003 115,61 IV- PASSIF CIRCULANT (Hors trésorerie)\n1- Dettes du passif circulant\nActif circulant 2 648 077 782,69 4 423 848 267,91 1 775 770 485,22\nLes dettes du passif circulant sont inscrites pour leur montant nominal.\nMoins Passif circulant 2 054 807 403,12 3 546 956 484,93 1 492 149 081,81\n= BESOINS DE FINANCEMENT GLOBAL (4-5) (B) 593 270 379,57 876 891 782,98 283 621 403,41 2- Méthodes d’évaluation des autres provisions pour risques et charges\nTRÉSORERIE NETTE (ACTIF -PASSIF) A - B 204 257 837,06 46 639 549,26 157 618 287,80 Une provision pour risques et charges est constituée pour faire face à la charge future ou au risque créés au\ncours de l’exercice.\nExercice Exercice précédent\n3- Méthodes de détermination des écarts de Conversion - Passif\nII. EMPLOIS ET RESSOURCES\nEmplois Ressources Emplois Ressources Les écarts de conversion sont calculés d’après le taux de change à la date de clôture.\nI. RESSOURCES STABLES DE L’EXERCICE V- TRESORERIE\nAUTOFINANCEMENT (A) -25 461 075,61 216 179 352,21 1- Trésorerie - Actif\n+ Capacité d’autofinancement 98 880 719,39 312 889 637,21\n- Distributions de bénéfices 124 341 795,00 96 710 285,00 La trésorerie est comptabilisée à la date de son engagement. La société utilise le rapprochement bancaire\nCESSIONS ET RÉDUCTIONS D’IMMOBILISATIONS (B) 5 007 577,73 2 918 272,56 pour rapprocher ses soldes comptables aux soldes bancaires.\n+ Cessions d’immobilisations incorporelles 2- Trésorerie - Passif\n+ Cessions d’immobilisations corporelles 280 000,00 La trésorerie est comptabilisée à la date de son engagement. La société utilise le rapprochement bancaire\n+ Cessions d’immobilisations financières pour rapprocher ses soldes comptables aux soldes bancaires.\n+ Récupérations sur créances immobilisées 4 727 577,73 2 918 272,56\n3- Méthodes d’évaluation des provisions pour dépréciation\nAUGMENTATIONS DES CAPITAUX PROPRES ET\nASSIMILÉS (C) Lorsque la valeur d’inventaire est inférieure à la valeur nominale brute, une provision pour dépréciation est\n+ Augmentations de capital, apports constituée du montant de la différence.\n+ Subventions d’investissement\nAUGMENTATION DES DETTES DE FINANCEMENT (D)\n(nettes de primes de remboursement)\nTOTAL I. RESSOURCES STABLES (A+B+C+D)\nII.EMPLOIS STABLES DE L’EXERCICE ÉTAT DES DÉROGATIONS du 01/01/2023 au 31/12/2023\nACQUISITIONS ET AUGMENTATIONS\nD’IMMOBILISATIONS (E ) 81 128 755,91 119 053 998,66 Justifications des Influence des Dérogations\n+ Acquisitions d’immobilisations incorporelles 15 000,00 Indication des Dérogations Dérogations sur le Patrimoine, la Situation\n+ Acquisitions d’immobilisations corporelles 78 505 971,39 59 033 584,31 Financière et les Résultats\n+ Acquisitions d’immobilisations financières 56 482 804,98 INDICATION DES DÉROGATIONS\n+ Augmentation des créances immobilisées 2 622 784,52 3 522 609,37 I- Dérogations aux principes comptables fondamentaux NÉANT NÉANT\nREMBOURSEMENT DES CAPITAUX PROPRES (F) 24 420 861,83 II- Dérogations aux méthodes d’évaluation NÉANT NÉANT\nREMBOURSEMENT DES DETTES DE FINANCEMENT III- Dérogations aux règles d’établissement et de\nNÉANT NÉANT\n(G) présentation des états de synthèse\nEMPLOIS EN NON VALEURS (H)\nTOTAL II. EMPLOIS STABLES (E+F+G+H) 105 549 617,74 119 053 998,66\nIII. VARIATION DU BESOIN DE FINANCEMENT GLOBAL DÉTAIL DES NON-VALEURS\n283 621 403,41 6 077 137,33 du 01/01/2023 au 31/12/2023\n(B.F.G.)\nIV. VARIATION DE LA TRÉSORERIE 157 618 287,80 106 120 763,44 Compte Principal Intitulé Montant\nTOTAL GÉNÉRAL 263 167 905,54 263 167 905,53 225 174 762,10 225 174 762,10 211 FRAIS PRELIMINAIRES\n2111 Frais de constitution\nÉTAT DES CHANGEMENTS DE MÉTHODES du 01/01/2023 au 31/12/2023 2112 Frais préalables au démarrage\n2113 Frais d’augmentation du capital\nInfluence sur le Patrimoine, la 2114 Frais sur opérations de fusions, scissions et transformations\nNature des Changements Justification des Changements Situation Financière et 2116 Frais de prospection\nles Résultats 2117 Frais de publicité\nI CHANGEMENT AFFECTANT LES METHODES D’EVALUATION 2118 Autres frais préléminaires\nNEANT NEANT NEANT 212 CHARGES A REPARTIR SUR PLUSIEURS EXERCICES 88 634 261,74\nNEANT NEANT NEANT 2121 Frais d’acquisitions des immobilisations\nNEANT NEANT NEANT 2125 Frais d’émission des emprunts\nII CHANGEMENT AFFECTANT LES RECLES DE PRESENTATION 2128 Autres charges à répartir\nNEANT NEANT NEANT 213 PRIME DE REMBOURSEMENT DES OBLIGATIONS\nNEANT NEANT NEANT 2130 Primes de reboursements des obligations\nNEANT NEANT NEANT T O T A L 88 634 261,74"
            }
        ],
        [
            {
                "ÉTAT DES SOLDES DE GESTION\ndu 01/01/2023 au 31/12/2023": "",
                "null": "EXERCICE\nPRÉCÉDENT"
            },
            {
                "ÉTAT DES SOLDES DE GESTION\ndu 01/01/2023 au 31/12/2023": "",
                "null": ""
            },
            {
                "ÉTAT DES SOLDES DE GESTION\ndu 01/01/2023 au 31/12/2023": "I",
                "null": ""
            },
            {
                "ÉTAT DES SOLDES DE GESTION\ndu 01/01/2023 au 31/12/2023": "II",
                "null": ""
            },
            {
                "ÉTAT DES SOLDES DE GESTION\ndu 01/01/2023 au 31/12/2023": "",
                "null": ""
            },
            {
                "ÉTAT DES SOLDES DE GESTION\ndu 01/01/2023 au 31/12/2023": "III",
                "null": ""
            },
            {
                "ÉTAT DES SOLDES DE GESTION\ndu 01/01/2023 au 31/12/2023": "",
                "null": ""
            },
            {
                "ÉTAT DES SOLDES DE GESTION\ndu 01/01/2023 au 31/12/2023": "IV",
                "null": ""
            },
            {
                "ÉTAT DES SOLDES DE GESTION\ndu 01/01/2023 au 31/12/2023": "",
                "null": ""
            },
            {
                "ÉTAT DES SOLDES DE GESTION\ndu 01/01/2023 au 31/12/2023": "V",
                "null": ""
            },
            {
                "ÉTAT DES SOLDES DE GESTION\ndu 01/01/2023 au 31/12/2023": "",
                "null": ""
            },
            {
                "ÉTAT DES SOLDES DE GESTION\ndu 01/01/2023 au 31/12/2023": "VI",
                "null": ""
            },
            {
                "ÉTAT DES SOLDES DE GESTION\ndu 01/01/2023 au 31/12/2023": "VII",
                "null": ""
            },
            {
                "ÉTAT DES SOLDES DE GESTION\ndu 01/01/2023 au 31/12/2023": "VIII",
                "null": ""
            },
            {
                "ÉTAT DES SOLDES DE GESTION\ndu 01/01/2023 au 31/12/2023": "IX",
                "null": ""
            },
            {
                "ÉTAT DES SOLDES DE GESTION\ndu 01/01/2023 au 31/12/2023": "",
                "null": ""
            },
            {
                "ÉTAT DES SOLDES DE GESTION\ndu 01/01/2023 au 31/12/2023": "X",
                "null": ""
            },
            {
                "ÉTAT DES SOLDES DE GESTION\ndu 01/01/2023 au 31/12/2023": "- TABLEAU DE FORMATION DES RÉSULTATS (T.F.R)",
                "null": ""
            },
            {
                "ÉTAT DES SOLDES DE GESTION\ndu 01/01/2023 au 31/12/2023": "",
                "null": ""
            },
            {
                "ÉTAT DES SOLDES DE GESTION\ndu 01/01/2023 au 31/12/2023": "",
                "null": ""
            },
            {
                "ÉTAT DES SOLDES DE GESTION\ndu 01/01/2023 au 31/12/2023": "",
                "null": ""
            },
            {
                "ÉTAT DES SOLDES DE GESTION\ndu 01/01/2023 au 31/12/2023": "I",
                "null": ""
            },
            {
                "ÉTAT DES SOLDES DE GESTION\ndu 01/01/2023 au 31/12/2023": "",
                "null": ""
            },
            {
                "ÉTAT DES SOLDES DE GESTION\ndu 01/01/2023 au 31/12/2023": "II",
                "null": ""
            }
        ],
        [
            {
                "PRINCIPALES MÉTHODES D’EVALUATION SPÉCIFIQUES\nÀ L’ENTREPRISE\ndu 01/01/2023 au 31/12/2023": "I- ACTIF IMMOBILISE\nA- Évaluation à l’entrée\n1- Immobilisations en non valeurs\nLa valeur d’entrée est constituée par le coût de revient de l’immobilisation.\n2- Immobilisations incorporelles\nLa valeur d’entrée est constituée par le coût de revient de l’immobilisation.\n3- Immobilisations corporelles\nLes immobilisations corporelles sont évaluées à leur coût d’acquisition ou de production, compte tenu des frais\nnécessaires à la mise en état d’utilisation de ces biens.\n4- Immobilisations financières\nSont portées dans ce poste de bilan, les sommes payées pour l’acquisition des titres de participation, ainsi que\npour les dépôts et cautionnements.\nB- Création des valeurs\n1- Méthodes d’amortissements\nLes méthodes d’amortissement pratiquées sont les méthodes prévues par les règles fiscales en vigueur pour\nchaque catégorie d’immobilisation\n2- Méthodes d’évaluation des provisions pour dépréciation\nLorsque la valeur d’inventaire est inférieure à la valeur brute, une provision pour dépréciation est constituée du\nmontant de la différence.\n3- Méthodes de détermination des écarts de Conversion - Actif\nLes écarts de conversion sont calculés d’après le taux de change à la date de clôture.\nII- ACTIF CIRCULANT\nA- Évaluation à l’entrée\n1- Stocks\nLa méthode d’évaluation du Stock à la fin d’exercice est la méthode du premier entrée, premier sorti (FIFO).\n2- Créances\nLes créances sont inscrites en comptabilité pour leur montant nominal. Les créances clients font l’objet, le cas\néchéant, d’une provision calculée sur la base du risque de non recouvrement.\n3- Titres et valeurs de placement\nLes titres et valeurs de placement sont estimés à la date de clôture au cours de la valeur à la date de fin\nd’exercice.\nB- Création des valeurs\n1- Méthodes d’évaluation des provisions pour dépréciation\nLorsque la valeur d’inventaire est inférieure à la valeur nominale brute, une provision pour dépréciation est\nconstituée du montant de la différence.\n2- Méthodes de détermination des écarts de Conversion - Actif\nLes écarts de conversion sont calculés d’après le taux de change à la date de clôture.\nIII- FINANCEMENT PERMANENT\n1- Méthodes de réévaluation\nLes capitaux propres et dettes de financement sont inscrites à leur valeur nominale.\n2- Méthodes d’évaluation des provisions réglementées\nLorsque la valeur d’inventaire est inférieure à la valeur nominale brute, une provision pour dépréciation est\nconstituée du montant de la différence.\n3- Dettes de financement permanent\nLes dettes de financement sont inscrites en comptabilité pour leur montant nominal.\n4- Méthodes d’évaluation des provisions durables pour risques et charges\nUne provision pour risques et charges est constituée pour faire face à la charge future ou au risque créés au\ncours de l’exercice.\n5- Méthodes de détermination des écarts de Conversion - Passif\nLes écarts de conversion sont calculés d’après le taux de change à la date de clôture.\nIV- PASSIF CIRCULANT (Hors trésorerie)\n1- Dettes du passif circulant\nLes dettes du passif circulant sont inscrites pour leur montant nominal.\n2- Méthodes d’évaluation des autres provisions pour risques et charges\nUne provision pour risques et charges est constituée pour faire face à la charge future ou au risque créés au\ncours de l’exercice.\n3- Méthodes de détermination des écarts de Conversion - Passif\nLes écarts de conversion sont calculés d’après le taux de change à la date de clôture.\nV- TRESORERIE\n1- Trésorerie - Actif\nLa trésorerie est comptabilisée à la date de son engagement. La société utilise le rapprochement bancaire\npour rapprocher ses soldes comptables aux soldes bancaires.\n2- Trésorerie - Passif\nLa trésorerie est comptabilisée à la date de son engagement. La société utilise le rapprochement bancaire\npour rapprocher ses soldes comptables aux soldes bancaires.\n3- Méthodes d’évaluation des provisions pour dépréciation\nLorsque la valeur d’inventaire est inférieure à la valeur nominale brute, une provision pour dépréciation est\nconstituée du montant de la différence."
            }
        ],
        [
            {
                "TABLEAU DE FINANCEMENT\n(MODÈLE NORMAL) du 01/01/2023 au 31/12/2023": "I. SYNTHÈSES DES MASSES DU BILAN",
                "null": ""
            },
            {
                "TABLEAU DE FINANCEMENT\n(MODÈLE NORMAL) du 01/01/2023 au 31/12/2023": "",
                "null": "Ressources"
            },
            {
                "TABLEAU DE FINANCEMENT\n(MODÈLE NORMAL) du 01/01/2023 au 31/12/2023": "",
                "null": "d"
            },
            {
                "TABLEAU DE FINANCEMENT\n(MODÈLE NORMAL) du 01/01/2023 au 31/12/2023": "Financement permanent 1 754 393 516,77 1 877 758 288,55 123 364 771,78\nMoins actif immobilisé 956 865 300,14 954 226 956,31 2 638 343,83",
                "null": ""
            },
            {
                "TABLEAU DE FINANCEMENT\n(MODÈLE NORMAL) du 01/01/2023 au 31/12/2023": "= FONDS DE ROULEMENT FONCTIONNEL (1-2) (A) 797 528 216,63 923 531 332,24 126 003 115,61",
                "null": ""
            },
            {
                "TABLEAU DE FINANCEMENT\n(MODÈLE NORMAL) du 01/01/2023 au 31/12/2023": "Actif circulant 2 648 077 782,69 4 423 848 267,91 1 775 770 485,22\nMoins Passif circulant 2 054 807 403,12 3 546 956 484,93 1 492 149 081,81",
                "null": ""
            },
            {
                "TABLEAU DE FINANCEMENT\n(MODÈLE NORMAL) du 01/01/2023 au 31/12/2023": "= BESOINS DE FINANCEMENT GLOBAL (4-5) (B) 593 270 379,57 876 891 782,98 283 621 403,41",
                "null": ""
            },
            {
                "TABLEAU DE FINANCEMENT\n(MODÈLE NORMAL) du 01/01/2023 au 31/12/2023": "TRÉSORERIE NETTE (ACTIF -PASSIF) A - B 204 257 837,06 46 639 549,26 157 618 287,80",
                "null": ""
            },
            {
                "TABLEAU DE FINANCEMENT\n(MODÈLE NORMAL) du 01/01/2023 au 31/12/2023": "",
                "null": ""
            },
            {
                "TABLEAU DE FINANCEMENT\n(MODÈLE NORMAL) du 01/01/2023 au 31/12/2023": "II. EMPLOIS ET RESSOURCES",
                "null": ""
            },
            {
                "TABLEAU DE FINANCEMENT\n(MODÈLE NORMAL) du 01/01/2023 au 31/12/2023": "",
                "null": "Ressources"
            },
            {
                "TABLEAU DE FINANCEMENT\n(MODÈLE NORMAL) du 01/01/2023 au 31/12/2023": "I. RESSOURCES STABLES DE L’EXERCICE",
                "null": ""
            },
            {
                "TABLEAU DE FINANCEMENT\n(MODÈLE NORMAL) du 01/01/2023 au 31/12/2023": "AUTOFINANCEMENT (A) -25 461 075,61 216 179 352,21",
                "null": ""
            },
            {
                "TABLEAU DE FINANCEMENT\n(MODÈLE NORMAL) du 01/01/2023 au 31/12/2023": "+ Capacité d’autofinancement 98 880 719,39 312 889 637,21\n- Distributions de bénéfices 124 341 795,00 96 710 285,00",
                "null": ""
            },
            {
                "TABLEAU DE FINANCEMENT\n(MODÈLE NORMAL) du 01/01/2023 au 31/12/2023": "CESSIONS ET RÉDUCTIONS D’IMMOBILISATIONS (B) 5 007 577,73 2 918 272,56",
                "null": ""
            },
            {
                "TABLEAU DE FINANCEMENT\n(MODÈLE NORMAL) du 01/01/2023 au 31/12/2023": "+ Cessions d’immobilisations incorporelles\n+ Cessions d’immobilisations corporelles 280 000,00\n+ Cessions d’immobilisations financières\n+ Récupérations sur créances immobilisées 4 727 577,73 2 918 272,56",
                "null": ""
            },
            {
                "TABLEAU DE FINANCEMENT\n(MODÈLE NORMAL) du 01/01/2023 au 31/12/2023": "AUGMENTATIONS DES CAPITAUX PROPRES ET\nASSIMILÉS (C)",
                "null": ""
            },
            {
                "TABLEAU DE FINANCEMENT\n(MODÈLE NORMAL) du 01/01/2023 au 31/12/2023": "+ Augmentations de capital, apports\n+ Subventions d’investissement",
                "null": ""
            },
            {
                "TABLEAU DE FINANCEMENT\n(MODÈLE NORMAL) du 01/01/2023 au 31/12/2023": "AUGMENTATION DES DETTES DE FINANCEMENT (D)\n(nettes de primes de remboursement)",
                "null": ""
            },
            {
                "TABLEAU DE FINANCEMENT\n(MODÈLE NORMAL) du 01/01/2023 au 31/12/2023": "TOTAL I. RESSOURCES STABLES (A+B+C+D)",
                "null": ""
            },
            {
                "TABLEAU DE FINANCEMENT\n(MODÈLE NORMAL) du 01/01/2023 au 31/12/2023": "II.EMPLOIS STABLES DE L’EXERCICE",
                "null": ""
            },
            {
                "TABLEAU DE FINANCEMENT\n(MODÈLE NORMAL) du 01/01/2023 au 31/12/2023": "ACQUISITIONS ET AUGMENTATIONS\n81 128 755,91 119 053 998,66\nD’IMMOBILISATIONS (E )",
                "null": ""
            },
            {
                "TABLEAU DE FINANCEMENT\n(MODÈLE NORMAL) du 01/01/2023 au 31/12/2023": "+ Acquisitions d’immobilisations incorporelles 15 000,00\n+ Acquisitions d’immobilisations corporelles 78 505 971,39 59 033 584,31\n+ Acquisitions d’immobilisations financières 56 482 804,98\n+ Augmentation des créances immobilisées 2 622 784,52 3 522 609,37",
                "null": ""
            },
            {
                "TABLEAU DE FINANCEMENT\n(MODÈLE NORMAL) du 01/01/2023 au 31/12/2023": "REMBOURSEMENT DES CAPITAUX PROPRES (F) 24 420 861,83",
                "null": ""
            },
            {
                "TABLEAU DE FINANCEMENT\n(MODÈLE NORMAL) du 01/01/2023 au 31/12/2023": "REMBOURSEMENT DES DETTES DE FINANCEMENT\n(G)",
                "null": ""
            },
            {
                "TABLEAU DE FINANCEMENT\n(MODÈLE NORMAL) du 01/01/2023 au 31/12/2023": "EMPLOIS EN NON VALEURS (H)",
                "null": ""
            },
            {
                "TABLEAU DE FINANCEMENT\n(MODÈLE NORMAL) du 01/01/2023 au 31/12/2023": "TOTAL II. EMPLOIS STABLES (E+F+G+H) 105 549 617,74 119 053 998,66",
                "null": ""
            },
            {
                "TABLEAU DE FINANCEMENT\n(MODÈLE NORMAL) du 01/01/2023 au 31/12/2023": "III. VARIATION DU BESOIN DE FINANCEMENT GLOBAL\n283 621 403,41 6 077 137,33\n(B.F.G.)",
                "null": ""
            },
            {
                "TABLEAU DE FINANCEMENT\n(MODÈLE NORMAL) du 01/01/2023 au 31/12/2023": "IV. VARIATION DE LA TRÉSORERIE 157 618 287,80 106 120 763,44",
                "null": ""
            },
            {
                "TABLEAU DE FINANCEMENT\n(MODÈLE NORMAL) du 01/01/2023 au 31/12/2023": "TOTAL GÉNÉRAL 263 167 905,54 263 167 905,53 225 174 762,10 225 174 762,10",
                "null": ""
            }
        ],
        [
            {
                "ÉTAT DES DÉROGATIONS\ndu 01/01/2023 au 31/12/2023": "Indication des Dérogations",
                "null": "Influence des Dérogations\nsur le Patrimoine, la Situation\nFinancière et les Résultats"
            },
            {
                "ÉTAT DES DÉROGATIONS\ndu 01/01/2023 au 31/12/2023": "INDICATION DES DÉROGATIONS",
                "null": ""
            },
            {
                "ÉTAT DES DÉROGATIONS\ndu 01/01/2023 au 31/12/2023": "I- Dérogations aux principes comptables fondamentaux NÉANT NÉANT\nII- Dérogations aux méthodes d’évaluation NÉANT NÉANT\nIII- Dérogations aux règles d’établissement et de\nNÉANT NÉANT\nprésentation des états de synthèse",
                "null": ""
            }
        ],
        [
            {
                "DÉTAIL DES NON-VALEURS\ndu 01/01/2023 au 31/12/2023": "Compte Principal Intitulé Montant"
            },
            {
                "DÉTAIL DES NON-VALEURS\ndu 01/01/2023 au 31/12/2023": "211 FRAIS PRELIMINAIRES\n2111 Frais de constitution\n2112 Frais préalables au démarrage\n2113 Frais d’augmentation du capital\n2114 Frais sur opérations de fusions, scissions et transformations\n2116 Frais de prospection\n2117 Frais de publicité\n2118 Autres frais préléminaires\n212 CHARGES A REPARTIR SUR PLUSIEURS EXERCICES 88 634 261,74\n2121 Frais d’acquisitions des immobilisations\n2125 Frais d’émission des emprunts\n2128 Autres charges à répartir\n213 PRIME DE REMBOURSEMENT DES OBLIGATIONS\n2130 Primes de reboursements des obligations"
            },
            {
                "DÉTAIL DES NON-VALEURS\ndu 01/01/2023 au 31/12/2023": "T O T A L 88 634 261,74"
            }
        ],
        [
            {
                "ÉTAT DES CHANGEMENTS DE MÉTHODES\ndu 01/01/2023 au 31/12/2023": "Nature des Changements",
                "null": "Influence sur le Patrimoine, la\nSituation Financière et\nles Résultats"
            },
            {
                "ÉTAT DES CHANGEMENTS DE MÉTHODES\ndu 01/01/2023 au 31/12/2023": "I CHANGEMENT AFFECTANT LES METHODES D’EVALUATION",
                "null": ""
            },
            {
                "ÉTAT DES CHANGEMENTS DE MÉTHODES\ndu 01/01/2023 au 31/12/2023": "NEANT NEANT NEANT\nNEANT NEANT NEANT\nNEANT NEANT NEANT",
                "null": ""
            },
            {
                "ÉTAT DES CHANGEMENTS DE MÉTHODES\ndu 01/01/2023 au 31/12/2023": "II CHANGEMENT AFFECTANT LES RECLES DE PRESENTATION",
                "null": ""
            },
            {
                "ÉTAT DES CHANGEMENTS DE MÉTHODES\ndu 01/01/2023 au 31/12/2023": "NEANT NEANT NEANT\nNEANT NEANT NEANT\nNEANT NEANT NEANT",
                "null": ""
            }
        ],
        [
            {
                "ÉTATS FINANCIERS SOCIAUX\nEXERCICE CLOS LE 31 DÉCEMBRE 2023": "TABLEAU DES IMMOBILISATIONS AUTRES QUE FINANCIÈRES\ndu 01/01/2023 au 31/12/2023\nAUGMENTATION DIMINUTION\nMONTANT BRUT DEBUT MONTANT BRUT\nN A T U R E EXERCICE Acquisition Production par l’entre- Virement Cession Retrait Virement FIN EXERCICE\nprise pour elle-même\nIMMOBILISATION EN NON-VALEURS 50 619 597,87 24 420 861,83 13 593 802,04 88 634 261,74\n* Frais préliminaires\n* Charges à répartir sur plusieurs exercices 50 619 597,87 24 420 861,83 13 593 802,04 88 634 261,74\n* Primes de remboursement obligations\nIMMOBILISATIONS INCORPORELLES 232 950 561,51 232 950 561,51\n* Immobilisation en recherche et développement\n* Brevets, marques, droits et valeurs similaires 142 681 873,13 142 681 873,13\n* Fonds commercial 90 268 688,38 90 268 688,38\n* Autres immobilisations incorporelles\nIMMOBILISATIONS CORPORELLES 2 151 795 755,55 79 701 009,58 20 155 059,85 10 786 739,18 34 943 900,03 2 205 921 185,77\n* Terrains 64 771 013,48 64 771 013,48\n* Constructions 283 096 117,39 910 342,66 11 995 618,33 296 002 078,38\n* Installat. techniques, matériel et outillage 1 579 559 416,52 21 050 182,08 8 159 441,52 1 608 769 040,12\n* Matériel de transport 80 135 593,33 10 786 739,18 69 348 854,15\n* Mobilier, matériel bureau et aménagements 101 845 867,22 5 195 770,31 107 041 637,53\n* Autres immobilisations corporelles\n* Immobilisations corporelles en cours 42 387 747,61 52 544 714,53 34 943 900,03 59 988 562,11\nTOTAL GÉNÉRAL 2 435 365 914,93 104 121 871,41 33 748 861,89 10 786 739,18 34 943 900,03 2 527 506 009,02\nTABLEAU DES AMORTISSEMENTS\ndu 01/01/2023 au 31/12/2023\nCumul début exercice Dotation de l’exercice Amortissement sur les immobilisations sorties Cumul d’amortissement en fin d’exercice\nN A T U R E\n1 2 3 4 = 1 + 2 - 3\nIMMOBILISATION EN NON-VALEURS 34 925 016,49 8 859 479,99 43 784 496,48\n* Frais préliminaires\n* Charges à répartir sur plusieurs exercices 34 925 016,49 8 859 479,99 43 784 496,48\n* Primes de remboursement des obligations\nIMMOBILISATIONS INCORPORELLES 44 201 293,71 4 185 624,41 48 386 918,12\n* Immobilisation en recherche et développement\n* Brevets, marques droits et valeurs similaires 44 201 293,71 4 185 624,41 48 386 918,12\n* Fonds commercial\n* Autres immobilisations incorporelles\nIMMOBILISATIONS CORPORELLES 1 796 067 566,72 55 734 485,47 10 786 739,18 1 841 015 313,01\n* Terrains\n* Constructions 221 955 239,37 10 663 472,74 232 618 712,11\n* Installations techniques, matériel et outillage 1 395 605 538,56 44 172 956,64 1 439 778 495,20\n* Matériel de transport 80 135 593,33 10 786 739,18 69 348 854,15\n* Mobilier, matériel de bureau et aménagements divers 98 371 195,46 898 056,09 99 269 251,55\n* Autres immobilisations corporelles\n* Immobilisations corporelles en cours\nTOTAL GÉNÉRAL 1 875 193 876,92 68 779 589,87 10 786 739,18 1 933 186 727,61\nTABLEAU DES TITRES DE PARTICIPATION\ndu 01/01/2023 au 31/12/2023\nExtrait des derniers états de synthèse de la société émettrice Produits inscrits\nParticipation au Prix d’acquisition Valeur nette\ntR ra icis eon sociale de la société émet- Secteur d’activité Capital social capital en % global comptable Date de clôture Situation nette Résultat net au l ’C ex.P e. rC c id ce e\n1 2 3 4 5 6 7 8 9\nSCI YAM IMMOBILIER 10 000,00 50,00 5 000,00 5 000,00 31/12/2023 -532 294,01 -34 676,47 0,00\nD A M A IMMOBILIER 4 000,00 98,75 217 250,00 217 250,00 31/12/2023 0,00 0,00 0,00\nC E L A C O DISTRIBUTION 3 000 000,00 23,99 719 700,00 0,00 31/12/2023 0,00 0,00 0,00\nASTRA MAROC DIVERS 400 000,00 99,93 566 923,30 0,00 31/12/2023 -1 403 009,02 -128 715,25 0,00\nFIREAL (C & F ) DIVERS 4 000 000,00 99,96 19 420 445,71 19 420 445,71 31/12/2023 29 739 042,64 853 125,78 1 253 626,99\nS O T R A N I DIVERS 250 000,00 2,51 6 280,00 0,00 31/12/2023 0,00 0,00 0,00\nLA RAFFINERIE AFRICAINE OLEAGINEUX 12 678 084,06 34,00 17 163 234,01 17 163 234,01 31/12/2023 2 275 590,52 162 017,97 3 829 918,96\nCRISTAL TUNISIE OLEAGINEUX 20 697 509,55 93,88 48 398 062,04 0,00 31/12/2023 -7 989 900,74 -29 298 827,90 274 102 407,58\nSTE D EXPLOITATION OLIVE OLEOCULTURE 32 000 000,00 100,00 31 999 700,00 31 999 700,00 31/12/2023 33 682 422,16 -4 097 923,65 296 080 903,29\nLES DOMAINES JAWHARA OLEOCULTURE 32 000 000,00 100,00 32 000 000,00 32 000 000,00 31/12/2023 32 208 626,28 32 953 831,87 90 049 392,63\nGIOM GIE - OLEAGINEUX 300 000,00 66,67 200 000,00 0,00 31/12/2023 -9 767 757,44 -2 910 634,40 57 600 893,42\nLESIEUR CRISTAL COTE D IVOIRE INDUSTRIEM 166 398,08 100,00 166 398,08 0,00 31/12/2023 0,00 0,00 0,00\nOLIVCO OLEOCULTURE 100 000,00 100,00 5 000 000,00 5 000 000,00 31/12/2023 -20 787 716,43 1 353 089,25 13 396 811,42\nLESIEUR CRISTAL INC HUIILE D OLIVE 9 929 000,00 100,00 9 929 000,00 0,00 31/12/2023 0,00 0,00 0,00\nINDUSALIM MARGARINE 10 000 000,00 100,00 175 000 000,00 175 000 000,00 31/12/2023 88 787 995,73 30 919 993,02 205 928 361,17\nTLC DISTRIBUTION 3 000 000,00 100,00 3 000 000,00 0,00 31/12/2023 -9 718 115,62 -585 484,99 0,00\nC O S T O M A OLEAGINEUX 5 400,00 0,00 1 082,00 1 082,00 31/12/2023 0,00 0,00 0,00\nC I C A V E T PROVENDIERS 10 000,00 0,00 500,00 500,00 31/12/2023 0,00 0,00 0,00\nCITE III DES JEUNES IMMOBILIER 1 598 000,00 0,00 4 505,00 4 505,00 31/12/2023 0,00 0,00 0,00\nH S M DIVERS 2 760 000,00 0,00 359,10 359,10 31/12/2023 0,00 0,00 0,00\nS G A DIVERS 0,00 0,00 100,00 100,00 31/12/2023 0,00 0,00 0,00\nDISTRA DIVERS 127 936 000,00 0,00 1,00 1,00 31/12/2023 0,00 0,00 0,00\nO LEOR OLEAGINEUX 20 250 000,00 100,00 90 000 000,00 45 357 154,57 31/12/2023 45 357 154,57 1 235 522,80 1 772 657,80\nC O M A H A OLEAGINEUX 21 000,00 49,05 9 984,00 0,00 31/12/2023 0,00 0,00 0,00\nS I K A F OLEAGINEUX 300 000,00 99,90 499 624,43 0,00 30/09/2023 -4 472 455,89 -53 545,35 0,00\nH G M O OLEAGINEUX 1 500 000,00 99,96 4 874 940,92 1 350 520,58 31/12/2023 1 351 061,00 37 109,59 57 585,52\nSous-Total 282 915 391,69 -- 439 183 089,59 327 519 851,97 -- 178 730 643,75 30 404 882,27 944 072 558,78"
            }
        ],
        [
            {
                "TABLEAU DES IMMOBILISATIONS AUTRES QUE FINANCIÈRES\ndu 01/01/2023 au 31/12/2023": "N A T U R E",
                "null": "MONTANT BRUT\nFIN EXERCICE"
            },
            {
                "TABLEAU DES IMMOBILISATIONS AUTRES QUE FINANCIÈRES\ndu 01/01/2023 au 31/12/2023": "",
                "null": ""
            },
            {
                "TABLEAU DES IMMOBILISATIONS AUTRES QUE FINANCIÈRES\ndu 01/01/2023 au 31/12/2023": "IMMOBILISATION EN NON-VALEURS 50 619 597,87 24 420 861,83 13 593 802,04 88 634 261,74",
                "null": ""
            },
            {
                "TABLEAU DES IMMOBILISATIONS AUTRES QUE FINANCIÈRES\ndu 01/01/2023 au 31/12/2023": "* Frais préliminaires\n* Charges à répartir sur plusieurs exercices 50 619 597,87 24 420 861,83 13 593 802,04 88 634 261,74\n* Primes de remboursement obligations\nIMMOBILISATIONS INCORPORELLES 232 950 561,51 232 950 561,51\n* Immobilisation en recherche et développement\n* Brevets, marques, droits et valeurs similaires 142 681 873,13 142 681 873,13\n* Fonds commercial 90 268 688,38 90 268 688,38\n* Autres immobilisations incorporelles",
                "null": ""
            },
            {
                "TABLEAU DES IMMOBILISATIONS AUTRES QUE FINANCIÈRES\ndu 01/01/2023 au 31/12/2023": "IMMOBILISATIONS CORPORELLES 2 151 795 755,55 79 701 009,58 20 155 059,85 10 786 739,18 34 943 900,03 2 205 921 185,77",
                "null": ""
            },
            {
                "TABLEAU DES IMMOBILISATIONS AUTRES QUE FINANCIÈRES\ndu 01/01/2023 au 31/12/2023": "* Terrains 64 771 013,48 64 771 013,48\n* Constructions 283 096 117,39 910 342,66 11 995 618,33 296 002 078,38\n* Installat. techniques, matériel et outillage 1 579 559 416,52 21 050 182,08 8 159 441,52 1 608 769 040,12\n* Matériel de transport 80 135 593,33 10 786 739,18 69 348 854,15\n* Mobilier, matériel bureau et aménagements 101 845 867,22 5 195 770,31 107 041 637,53\n* Autres immobilisations corporelles\n* Immobilisations corporelles en cours 42 387 747,61 52 544 714,53 34 943 900,03 59 988 562,11",
                "null": ""
            },
            {
                "TABLEAU DES IMMOBILISATIONS AUTRES QUE FINANCIÈRES\ndu 01/01/2023 au 31/12/2023": "TOTAL GÉNÉRAL 2 435 365 914,93 104 121 871,41 33 748 861,89 10 786 739,18 34 943 900,03 2 527 506 009,02",
                "null": ""
            }
        ],
        [
            {
                "TABLEAU DES AMORTISSEMENTS\ndu 01/01/2023 au 31/12/2023": "N A T U R E",
                "null": "Cumul d’amortissement en fin d’exercice"
            },
            {
                "TABLEAU DES AMORTISSEMENTS\ndu 01/01/2023 au 31/12/2023": "",
                "null": "4 = 1 + 2 - 3"
            },
            {
                "TABLEAU DES AMORTISSEMENTS\ndu 01/01/2023 au 31/12/2023": "IMMOBILISATION EN NON-VALEURS 34 925 016,49 8 859 479,99 43 784 496,48",
                "null": ""
            },
            {
                "TABLEAU DES AMORTISSEMENTS\ndu 01/01/2023 au 31/12/2023": "* Frais préliminaires\n* Charges à répartir sur plusieurs exercices 34 925 016,49 8 859 479,99 43 784 496,48\n* Primes de remboursement des obligations",
                "null": ""
            },
            {
                "TABLEAU DES AMORTISSEMENTS\ndu 01/01/2023 au 31/12/2023": "IMMOBILISATIONS INCORPORELLES 44 201 293,71 4 185 624,41 48 386 918,12",
                "null": ""
            },
            {
                "TABLEAU DES AMORTISSEMENTS\ndu 01/01/2023 au 31/12/2023": "* Immobilisation en recherche et développement\n* Brevets, marques droits et valeurs similaires 44 201 293,71 4 185 624,41 48 386 918,12\n* Fonds commercial\n* Autres immobilisations incorporelles",
                "null": ""
            },
            {
                "TABLEAU DES AMORTISSEMENTS\ndu 01/01/2023 au 31/12/2023": "IMMOBILISATIONS CORPORELLES 1 796 067 566,72 55 734 485,47 10 786 739,18 1 841 015 313,01",
                "null": ""
            },
            {
                "TABLEAU DES AMORTISSEMENTS\ndu 01/01/2023 au 31/12/2023": "* Terrains\n* Constructions 221 955 239,37 10 663 472,74 232 618 712,11\n* Installations techniques, matériel et outillage 1 395 605 538,56 44 172 956,64 1 439 778 495,20\n* Matériel de transport 80 135 593,33 10 786 739,18 69 348 854,15\n* Mobilier, matériel de bureau et aménagements divers 98 371 195,46 898 056,09 99 269 251,55\n* Autres immobilisations corporelles\n* Immobilisations corporelles en cours",
                "null": ""
            },
            {
                "TABLEAU DES AMORTISSEMENTS\ndu 01/01/2023 au 31/12/2023": "TOTAL GÉNÉRAL 1 875 193 876,92 68 779 589,87 10 786 739,18 1 933 186 727,61",
                "null": ""
            }
        ],
        [
            {
                "TABLEAU DES TITRES DE PARTICIPATION\ndu 01/01/2023 au 31/12/2023": "Raison sociale de la société émet-\ntrice",
                "null": "Produits inscrits\nau C.P.C de\nl’exercice"
            },
            {
                "TABLEAU DES TITRES DE PARTICIPATION\ndu 01/01/2023 au 31/12/2023": "",
                "null": ""
            },
            {
                "TABLEAU DES TITRES DE PARTICIPATION\ndu 01/01/2023 au 31/12/2023": "",
                "null": "9"
            },
            {
                "TABLEAU DES TITRES DE PARTICIPATION\ndu 01/01/2023 au 31/12/2023": "SCI YAM IMMOBILIER 10 000,00 50,00 5 000,00 5 000,00 31/12/2023 -532 294,01 -34 676,47 0,00\nD A M A IMMOBILIER 4 000,00 98,75 217 250,00 217 250,00 31/12/2023 0,00 0,00 0,00\nC E L A C O DISTRIBUTION 3 000 000,00 23,99 719 700,00 0,00 31/12/2023 0,00 0,00 0,00\nASTRA MAROC DIVERS 400 000,00 99,93 566 923,30 0,00 31/12/2023 -1 403 009,02 -128 715,25 0,00\nFIREAL (C & F ) DIVERS 4 000 000,00 99,96 19 420 445,71 19 420 445,71 31/12/2023 29 739 042,64 853 125,78 1 253 626,99\nS O T R A N I DIVERS 250 000,00 2,51 6 280,00 0,00 31/12/2023 0,00 0,00 0,00\nLA RAFFINERIE AFRICAINE OLEAGINEUX 12 678 084,06 34,00 17 163 234,01 17 163 234,01 31/12/2023 2 275 590,52 162 017,97 3 829 918,96\nCRISTAL TUNISIE OLEAGINEUX 20 697 509,55 93,88 48 398 062,04 0,00 31/12/2023 -7 989 900,74 -29 298 827,90 274 102 407,58\nSTE D EXPLOITATION OLIVE OLEOCULTURE 32 000 000,00 100,00 31 999 700,00 31 999 700,00 31/12/2023 33 682 422,16 -4 097 923,65 296 080 903,29\nLES DOMAINES JAWHARA OLEOCULTURE 32 000 000,00 100,00 32 000 000,00 32 000 000,00 31/12/2023 32 208 626,28 32 953 831,87 90 049 392,63\nGIOM GIE - OLEAGINEUX 300 000,00 66,67 200 000,00 0,00 31/12/2023 -9 767 757,44 -2 910 634,40 57 600 893,42\nLESIEUR CRISTAL COTE D IVOIRE INDUSTRIEM 166 398,08 100,00 166 398,08 0,00 31/12/2023 0,00 0,00 0,00\nOLIVCO OLEOCULTURE 100 000,00 100,00 5 000 000,00 5 000 000,00 31/12/2023 -20 787 716,43 1 353 089,25 13 396 811,42\nLESIEUR CRISTAL INC HUIILE D OLIVE 9 929 000,00 100,00 9 929 000,00 0,00 31/12/2023 0,00 0,00 0,00\nINDUSALIM MARGARINE 10 000 000,00 100,00 175 000 000,00 175 000 000,00 31/12/2023 88 787 995,73 30 919 993,02 205 928 361,17\nTLC DISTRIBUTION 3 000 000,00 100,00 3 000 000,00 0,00 31/12/2023 -9 718 115,62 -585 484,99 0,00\nC O S T O M A OLEAGINEUX 5 400,00 0,00 1 082,00 1 082,00 31/12/2023 0,00 0,00 0,00\nC I C A V E T PROVENDIERS 10 000,00 0,00 500,00 500,00 31/12/2023 0,00 0,00 0,00\nCITE III DES JEUNES IMMOBILIER 1 598 000,00 0,00 4 505,00 4 505,00 31/12/2023 0,00 0,00 0,00\nH S M DIVERS 2 760 000,00 0,00 359,10 359,10 31/12/2023 0,00 0,00 0,00\nS G A DIVERS 0,00 0,00 100,00 100,00 31/12/2023 0,00 0,00 0,00\nDISTRA DIVERS 127 936 000,00 0,00 1,00 1,00 31/12/2023 0,00 0,00 0,00\nO LEOR OLEAGINEUX 20 250 000,00 100,00 90 000 000,00 45 357 154,57 31/12/2023 45 357 154,57 1 235 522,80 1 772 657,80\nC O M A H A OLEAGINEUX 21 000,00 49,05 9 984,00 0,00 31/12/2023 0,00 0,00 0,00\nS I K A F OLEAGINEUX 300 000,00 99,90 499 624,43 0,00 30/09/2023 -4 472 455,89 -53 545,35 0,00\nH G M O OLEAGINEUX 1 500 000,00 99,96 4 874 940,92 1 350 520,58 31/12/2023 1 351 061,00 37 109,59 57 585,52",
                "null": ""
            },
            {
                "TABLEAU DES TITRES DE PARTICIPATION\ndu 01/01/2023 au 31/12/2023": "Sous-Total 282 915 391,69 -- 439 183 089,59 327 519 851,97 -- 178 730 643,75 30 404 882,27 944 072 558,78",
                "null": ""
            }
        ],
        [
            {
                "ÉTATS FINANCIERS SOCIAUX\nEXERCICE CLOS LE 31 DÉCEMBRE 2023": "TABLEAU DES TITRES DE PARTICIPATION du 01/01/2023 au 31/12/2023\nExtrait des derniers états de synthèse de la société émettrice Produits inscrits\nParticipation au Prix d’acquisition Valeur nette\nR tra icis eon sociale de la société émet- Secteur d’activité Capital social capital en % global comptable Date de clôture Situation nette Résultat net au l ’C ex.P e. rC c id ce e\n1 2 3 4 5 6 7 8 9\nS O P R O T A PROVENDIERS 5 000 000,00 73,61 3 926 778,98 0,00 31/12/2023 -27 425 028,45 -1 254 022,19 0,00\nS H O M SAVONNERIE 100 000,00 99,70 9 310 687,78 9 310 687,78 31/12/2023 12 586 123,06 426 101,97 548 161,46\nP O S A M A PRODUITS MER 400 000,00 99,63 912 191,38 912 191,38 31/12/2023 0,00 0,00 0,00\nHAY EL HABAIB IMMOBILIER 100 000,00 100,00 46 083 755,04 46 083 755,04 31/12/2023 57 111 182,09 566 175,61 880 622,81\nCITE MNE SIDI OTHMANE IMMOBILIER 1 097 660,00 0,24 2 630,00 2 630,00 31/12/2023 0,00 0,00 0,00\nCITE I DES JEUNES IMMOBILIER 739 200,00 0,34 2 500,00 2 500,00 31/12/2023 0,00 0,00 0,00\nCITE II DES JEUNES IMMOBILIER 1 458 000,00 0,69 14 500,00 14 500,00 31/12/2023 0,00 0,00 0,00\nS O C I C A IMMOBILIER 956 760,00 2,25 13 605,00 13 605,00 31/12/2023 0,00 0,00 0,00\nOLEOSEN OLEAGINEUX 142 563 330,00 90,16 56 590 345,85 0,00 31/12/2023 -45 762 735,94 -34 637 898,03 296 764 052,28\nT o t a l 435 330 341,69 -- 556 040 083,62 383 859 721,17 -- 175 240 184,51 -4 494 760,37 1 242 265 395,33\nTABLEAU DES PROVISIONS\ndu 01/01/2023 au 31/12/2023\nMONTANT DEBUT DOTATIONS REPRISES\nN A T U R E MONTANT FIN EXERCICE\nEXERCICE D’exploitation Financières Non courantes D’exploitation Financières Non courantes\n1. Provisions pour dépréciation de l’actif immobilisé 172 347 846,41 5 880 567,43 24 801 156,48 1 277 617,55 201 751 952,77\n2. Provisions réglementées 96 235 942,59 3 550 014,37 21 978 532,22 77 807 424,74\n3. Provisons durables pour risques et charges 9 928 656,78 12 509 299,00 1 976 332,22 20 461 623,56\nSOUS TOTAL (A) 278 512 445,78 18 389 866,43 24 801 156,48 3 550 014,37 1 976 332,22 1 277 617,55 21 978 532,22 300 021 001,07\n4. Provisions pour dépréciation de l’actif circulant\n321 261 120,18 45 626 059,72 4 910 372,47 48 453 155,50 347 510,31 322 996 886,56\n(hors trésorerie)\n5. Autres Provisions pour risques et charge 86 230 743,53 40 392 318,92 42 000 476,00 25 193 960,32 59 428 626,13\n6. Provisions pour dépréciation des comptes de\ntrésorerie\nSOUS TOTAL (B) 407 491 863,71 86 018 378,64 4 910 372,47 90 453 631,50 347 510,31 25 193 960,32 382 425 512,69\nTOTAL (A+B) 686 004 309,49 104 408 245,07 29 711 528,95 3 550 014,37 92 429 963,72 1 625 127,86 47 172 492,54 682 446 513,76\nTABLEAU DES CRÉANCES\ndu 01/01/2023 au 31/12/2023\nAnalyse par Échéance Autres Analyses\nCréances Total Montants sur l’État Montants sur Montants\nPlus d’un an Moins d’un an Échues et non recouvrées Montants en Devises et Organismes les Entreprises Représentés par\nPublics liées Effets\nDe l’Actif Immobilisé 8 257 887,88 8 257 887,88\n- Prêts immobilisés 5 136 224,66 5 136 224,66\n- Autres créances financières 3 121 663,22 3 121 663,22\nDe l’actif circulant 1 533 342 046,49 110 293 555,64 959 730 490,53 463 318 000,32 72 183 627,14 335 000 184,68 257 925 601,78 23 573 756,55\n- Fournisseurs débiteurs avances et acomptes 45 903 965,65 26 733 926,24 19 170 039,41 38 791 541,24\n- Clients et comptes rattachés 880 011 155,82 72 023 392,28 631 983 945,36 176 003 818,18 11 530 452,66 10 646 889,48 23 573 756,55\n- Personnel 11 160 202,68 6 182 815,63 4 977 387,05\n- État 335 000 184,68 53 764 262,59 281 235 922,09 335 000 184,68\n- Comptes d’associés 249 035 571,67 1 756 859,37 247 278 712,30 21 861 633,24 247 278 712,30\n- Autres débiteurs 7 655 418,54 3 596 562,12 2 957 983,42 1 100 873,00\n- Compte de régularisation actif 4 575 547,45 4 575 547,45\nT O T A U X 1 541 599 934,37 118 551 443,52 959 730 490,53 463 318 000,32 72 183 627,14 335 000 184,68 257 925 601,78 23 573 756,55\nTABLEAU DES DETTES\ndu 01/01/2023 au 31/12/2023\nAnalyse par Échéance Autres Analyses\nDettes Total Montants sur l’État Montants sur Montants\nPlus d’un an Moins d’un an Échues et non payées Montants en Devises et Organismes les Entreprises Représentés par\nPublics liées Effets\nDE FINANCEMENT\n- Emprunts obligataires\n- Autres dettes de financement\nDU PASSIF CIRCULANT 1 995 378 776,99 543 967 636,97 1 451 411 140,02 1 061 148 606,17 62 861 155,50 172 561 603,01 1 055 462 994,31\n- Fournisseurs et comptes rattachés 1 735 521 090,72 393 661 759,49 1 341 859 331,23 1 061 148 606,17 28 829 725,53 1 055 462 994,31\n- Clients créditeurs, avances et acomptes 1 228 870,14 1 026 246,69 202 623,45\n- Personnel 34 412 303,65 72 118,13 34 340 185,52\n- Organismes sociaux 21 790 866,30 21 790 866,30 21 790 866,30\n- État 41 070 289,20 15 988 499,97 25 081 789,23 41 070 289,20\n- Comptes d’associés 154 563 640,45 131 142 085,96 23 421 554,49 143 731 877,48\n- Autres créanciers 5 770 062,96 2 076 926,73 3 693 136,23\n- Comptes de régularisation - Passif 1 021 653,57 1 021 653,57\nT O T A U X 1 995 378 776,99 543 967 636,97 1 451 411 140,02 1 061 148 606,17 62 861 155,50 172 561 603,01 1 055 462 994,31\nTABLEAU DES SURETES RÉELLES DONNÉES OU REÇUES ENGAGEMENTS FINANCIERS REÇUS OU DONNÉS HORS\ndu 01/01/2023 au 31/12/2023\nOPÉRATIONS DE CRÉDIT-BAIL\ndu 01/01/2023 au 31/12/2023\nMontant\nTiers Débiteurs ou V.N.C. de la\ncouvert par la Nature (1) Date et Lieu d’inscription Objet (2)(3) Montants Montants Exercice\nTiers Créditeurs sureté donnée Engagements Donnés\nsureté Exercice Précèdent\nSureté donnée Engagement donné\nSureté reçue Avals et cautions 382 468 866,99 359 956 098,02\nDonnées par les Engagements en matière de pensions de retraites et obligations 200 045 817,00 263 258 801,00\nHypothèques sur prêts 1 170 000,00 2 1990 à 1996 - Casablanca\nbénéficiaires Autres engagements donnés (1) 1 627 868 537,26 3 969 610 631,09\n* Couvertures à terme en devise, soit :\n- 151 574 931,18 $ au cours moyen de 9,8870 soit 1 498 620 171,45 DH\n- 12 060 730,09 € au cours moyen de 10,7165 soit 129 248 365,82 DH\nEngagements reçus\nEngagements reçus (2) 111 217 890,13 275 485 583,50\n* Couvertures à terme en devise , soit :\n- 774 079,98 $ au cours moyen de 9,8380 soit 7 615 399,55 DH\n- 9 719 585,43€ au cours moyen de 10,6591 soit 103 602 490,58 DH"
            }
        ],
        [
            {
                "TABLEAU DES TITRES DE PARTICIPATION du 01/01/2023 au 31/12/2023": "Raison sociale de la société émet-\ntrice",
                "null": "Produits inscrits\nau C.P.C de\nl’exercice"
            },
            {
                "TABLEAU DES TITRES DE PARTICIPATION du 01/01/2023 au 31/12/2023": "",
                "null": ""
            },
            {
                "TABLEAU DES TITRES DE PARTICIPATION du 01/01/2023 au 31/12/2023": "",
                "null": "9"
            },
            {
                "TABLEAU DES TITRES DE PARTICIPATION du 01/01/2023 au 31/12/2023": "S O P R O T A PROVENDIERS 5 000 000,00 73,61 3 926 778,98 0,00 31/12/2023 -27 425 028,45 -1 254 022,19 0,00\nS H O M SAVONNERIE 100 000,00 99,70 9 310 687,78 9 310 687,78 31/12/2023 12 586 123,06 426 101,97 548 161,46\nP O S A M A PRODUITS MER 400 000,00 99,63 912 191,38 912 191,38 31/12/2023 0,00 0,00 0,00\nHAY EL HABAIB IMMOBILIER 100 000,00 100,00 46 083 755,04 46 083 755,04 31/12/2023 57 111 182,09 566 175,61 880 622,81\nCITE MNE SIDI OTHMANE IMMOBILIER 1 097 660,00 0,24 2 630,00 2 630,00 31/12/2023 0,00 0,00 0,00\nCITE I DES JEUNES IMMOBILIER 739 200,00 0,34 2 500,00 2 500,00 31/12/2023 0,00 0,00 0,00\nCITE II DES JEUNES IMMOBILIER 1 458 000,00 0,69 14 500,00 14 500,00 31/12/2023 0,00 0,00 0,00\nS O C I C A IMMOBILIER 956 760,00 2,25 13 605,00 13 605,00 31/12/2023 0,00 0,00 0,00\nOLEOSEN OLEAGINEUX 142 563 330,00 90,16 56 590 345,85 0,00 31/12/2023 -45 762 735,94 -34 637 898,03 296 764 052,28\nT o t a l 435 330 341,69 -- 556 040 083,62 383 859 721,17 -- 175 240 184,51 -4 494 760,37 1 242 265 395,33",
                "null": ""
            }
        ],
        [
            {
                "TABLEAU DES PROVISIONS\ndu 01/01/2023 au 31/12/2023": "N A T U R E",
                "null": "MONTANT FIN EXERCICE"
            },
            {
                "TABLEAU DES PROVISIONS\ndu 01/01/2023 au 31/12/2023": "",
                "null": ""
            },
            {
                "TABLEAU DES PROVISIONS\ndu 01/01/2023 au 31/12/2023": "1. Provisions pour dépréciation de l’actif immobilisé 172 347 846,41 5 880 567,43 24 801 156,48 1 277 617,55 201 751 952,77\n2. Provisions réglementées 96 235 942,59 3 550 014,37 21 978 532,22 77 807 424,74\n3. Provisons durables pour risques et charges 9 928 656,78 12 509 299,00 1 976 332,22 20 461 623,56",
                "null": ""
            },
            {
                "TABLEAU DES PROVISIONS\ndu 01/01/2023 au 31/12/2023": "SOUS TOTAL (A) 278 512 445,78 18 389 866,43 24 801 156,48 3 550 014,37 1 976 332,22 1 277 617,55 21 978 532,22 300 021 001,07",
                "null": ""
            },
            {
                "TABLEAU DES PROVISIONS\ndu 01/01/2023 au 31/12/2023": "4. Provisions pour dépréciation de l’actif circulant\n321 261 120,18 45 626 059,72 4 910 372,47 48 453 155,50 347 510,31 322 996 886,56\n(hors trésorerie)\n5. Autres Provisions pour risques et charge 86 230 743,53 40 392 318,92 42 000 476,00 25 193 960,32 59 428 626,13\n6. Provisions pour dépréciation des comptes de\ntrésorerie",
                "null": ""
            },
            {
                "TABLEAU DES PROVISIONS\ndu 01/01/2023 au 31/12/2023": "SOUS TOTAL (B) 407 491 863,71 86 018 378,64 4 910 372,47 90 453 631,50 347 510,31 25 193 960,32 382 425 512,69",
                "null": ""
            },
            {
                "TABLEAU DES PROVISIONS\ndu 01/01/2023 au 31/12/2023": "TOTAL (A+B) 686 004 309,49 104 408 245,07 29 711 528,95 3 550 014,37 92 429 963,72 1 625 127,86 47 172 492,54 682 446 513,76",
                "null": ""
            }
        ],
        [
            {
                "TABLEAU DES CRÉANCES\ndu 01/01/2023 au 31/12/2023": "Créances",
                "null": ""
            },
            {
                "TABLEAU DES CRÉANCES\ndu 01/01/2023 au 31/12/2023": "",
                "null": "Montants\nReprésentés par\nEffets"
            },
            {
                "TABLEAU DES CRÉANCES\ndu 01/01/2023 au 31/12/2023": "De l’Actif Immobilisé 8 257 887,88 8 257 887,88",
                "null": ""
            },
            {
                "TABLEAU DES CRÉANCES\ndu 01/01/2023 au 31/12/2023": "- Prêts immobilisés 5 136 224,66 5 136 224,66\n- Autres créances financières 3 121 663,22 3 121 663,22",
                "null": ""
            },
            {
                "TABLEAU DES CRÉANCES\ndu 01/01/2023 au 31/12/2023": "De l’actif circulant 1 533 342 046,49 110 293 555,64 959 730 490,53 463 318 000,32 72 183 627,14 335 000 184,68 257 925 601,78 23 573 756,55",
                "null": ""
            },
            {
                "TABLEAU DES CRÉANCES\ndu 01/01/2023 au 31/12/2023": "- Fournisseurs débiteurs avances et acomptes 45 903 965,65 26 733 926,24 19 170 039,41 38 791 541,24\n- Clients et comptes rattachés 880 011 155,82 72 023 392,28 631 983 945,36 176 003 818,18 11 530 452,66 10 646 889,48 23 573 756,55\n- Personnel 11 160 202,68 6 182 815,63 4 977 387,05\n- État 335 000 184,68 53 764 262,59 281 235 922,09 335 000 184,68\n- Comptes d’associés 249 035 571,67 1 756 859,37 247 278 712,30 21 861 633,24 247 278 712,30\n- Autres débiteurs 7 655 418,54 3 596 562,12 2 957 983,42 1 100 873,00\n- Compte de régularisation actif 4 575 547,45 4 575 547,45",
                "null": ""
            },
            {
                "TABLEAU DES CRÉANCES\ndu 01/01/2023 au 31/12/2023": "T O T A U X 1 541 599 934,37 118 551 443,52 959 730 490,53 463 318 000,32 72 183 627,14 335 000 184,68 257 925 601,78 23 573 756,55",
                "null": ""
            }
        ],
        [
            {
                "TABLEAU DES DETTES\ndu 01/01/2023 au 31/12/2023": "Dettes",
                "null": ""
            },
            {
                "TABLEAU DES DETTES\ndu 01/01/2023 au 31/12/2023": "",
                "null": "Montants\nReprésentés par\nEffets"
            },
            {
                "TABLEAU DES DETTES\ndu 01/01/2023 au 31/12/2023": "DE FINANCEMENT",
                "null": ""
            },
            {
                "TABLEAU DES DETTES\ndu 01/01/2023 au 31/12/2023": "- Emprunts obligataires\n- Autres dettes de financement",
                "null": ""
            },
            {
                "TABLEAU DES DETTES\ndu 01/01/2023 au 31/12/2023": "DU PASSIF CIRCULANT 1 995 378 776,99 543 967 636,97 1 451 411 140,02 1 061 148 606,17 62 861 155,50 172 561 603,01 1 055 462 994,31",
                "null": ""
            },
            {
                "TABLEAU DES DETTES\ndu 01/01/2023 au 31/12/2023": "- Fournisseurs et comptes rattachés 1 735 521 090,72 393 661 759,49 1 341 859 331,23 1 061 148 606,17 28 829 725,53 1 055 462 994,31\n- Clients créditeurs, avances et acomptes 1 228 870,14 1 026 246,69 202 623,45\n- Personnel 34 412 303,65 72 118,13 34 340 185,52\n- Organismes sociaux 21 790 866,30 21 790 866,30 21 790 866,30\n- État 41 070 289,20 15 988 499,97 25 081 789,23 41 070 289,20\n- Comptes d’associés 154 563 640,45 131 142 085,96 23 421 554,49 143 731 877,48\n- Autres créanciers 5 770 062,96 2 076 926,73 3 693 136,23\n- Comptes de régularisation - Passif 1 021 653,57 1 021 653,57",
                "null": ""
            },
            {
                "TABLEAU DES DETTES\ndu 01/01/2023 au 31/12/2023": "T O T A U X 1 995 378 776,99 543 967 636,97 1 451 411 140,02 1 061 148 606,17 62 861 155,50 172 561 603,01 1 055 462 994,31",
                "null": ""
            }
        ],
        [
            {
                "TABLEAU DES SURETES RÉELLES DONNÉES OU REÇUES\ndu 01/01/2023 au 31/12/2023": "Tiers Débiteurs ou\nTiers Créditeurs",
                "null": "V.N.C. de la\nsureté donnée"
            },
            {
                "TABLEAU DES SURETES RÉELLES DONNÉES OU REÇUES\ndu 01/01/2023 au 31/12/2023": "Sureté donnée\nSureté reçue",
                "null": ""
            },
            {
                "TABLEAU DES SURETES RÉELLES DONNÉES OU REÇUES\ndu 01/01/2023 au 31/12/2023": "Données par les\nHypothèques sur prêts 1 170 000,00 2 1990 à 1996 - Casablanca\nbénéficiaires",
                "null": ""
            }
        ],
        [
            {
                "ENGAGEMENTS FINANCIERS REÇUS OU DONNÉS HORS\nOPÉRATIONS DE CRÉDIT-BAIL\ndu 01/01/2023 au 31/12/2023": "Engagements Donnés",
                "null": "Montants Exercice\nPrécèdent"
            },
            {
                "ENGAGEMENTS FINANCIERS REÇUS OU DONNÉS HORS\nOPÉRATIONS DE CRÉDIT-BAIL\ndu 01/01/2023 au 31/12/2023": "Engagement donné",
                "null": ""
            },
            {
                "ENGAGEMENTS FINANCIERS REÇUS OU DONNÉS HORS\nOPÉRATIONS DE CRÉDIT-BAIL\ndu 01/01/2023 au 31/12/2023": "Avals et cautions 382 468 866,99 359 956 098,02\nEngagements en matière de pensions de retraites et obligations 200 045 817,00 263 258 801,00\nAutres engagements donnés (1) 1 627 868 537,26 3 969 610 631,09\n* Couvertures à terme en devise, soit :\n- 151 574 931,18 $ au cours moyen de 9,8870 soit 1 498 620 171,45 DH",
                "null": ""
            },
            {
                "ENGAGEMENTS FINANCIERS REÇUS OU DONNÉS HORS\nOPÉRATIONS DE CRÉDIT-BAIL\ndu 01/01/2023 au 31/12/2023": "- 12 060 730,09 € au cours moyen de 10,7165 soit 129 248 365,82 DH",
                "null": ""
            },
            {
                "ENGAGEMENTS FINANCIERS REÇUS OU DONNÉS HORS\nOPÉRATIONS DE CRÉDIT-BAIL\ndu 01/01/2023 au 31/12/2023": "Engagements reçus",
                "null": ""
            },
            {
                "ENGAGEMENTS FINANCIERS REÇUS OU DONNÉS HORS\nOPÉRATIONS DE CRÉDIT-BAIL\ndu 01/01/2023 au 31/12/2023": "Engagements reçus (2) 111 217 890,13 275 485 583,50\n* Couvertures à terme en devise , soit :\n- 774 079,98 $ au cours moyen de 9,8380 soit 7 615 399,55 DH\n- 9 719 585,43€ au cours moyen de 10,6591 soit 103 602 490,58 DH",
                "null": ""
            }
        ],
        [
            {
                "2. DEPRECIATION DES CREANCES CLIENTS\nRisque identifié Notre réponse\nLes créances clients s’élèvent à KMAD 661.708 Les travaux sur les comptes au 31 décembre\nen valeur nette au 31 décembre 2023 dont un 2023, ont notamment consisté en :\nÉTATS FINANCIERS SOCIAUX montant de KMAD 218.303 de provision pour\ndépréciation. - La fiabilisation de la balance âgée des\ncréances clients en testant pour un\nEXERCICE CLOS LE 31 DÉCEMBRE 2023 Ces provisions sont déterminées sur la base échantillon l’ancienneté retenue ;\nd’une méthode statistique qui se base sur - La réalisation de tests relatifs à l’apurement\nl’ancienneté de la créance (100% de solde pour des créances en période subséquente ;\nles créances antérieures à 1 an et 50% pour les - Le recalcul de la provision sur la base de la\ncréances antérieures à 6 mois). Cependant, le méthode statistique retenue par la société ;\nmanagement complète éventuellement cette - L’examen des PV de réunions tenues par\nrègle par une analyse au cas par cas intégrant les responsables commerciaux pour": "d’autres indices de dépréciation (relation l’estimation du risque de recouvrement sur\ncommerciale, couverture assurance, feed-back les créances clients ;\ndes opérationnels...). - L’établissement des entretiens avec les\nopérationnels pour s’assurer de l’absence\nNous avons considéré l’estimation du montant de créances clients bien que récentes\nde la provision pour dépréciation des créances présentant un risque de recouvrement ;\nclients comme un point clé de l’audit compte\ntenu du caractère estimatif de ce processus et\n4, Rue Maati Jazouli (ex rue Friol) son impact significatif sur les comptes.\nAnfa- Casablanca\nMaroc\n37, Bd Abdellatif Ben Kaddour\n20 050 Casablanca\nMaroc\nResponsabilités de la direction et des responsables de la gouvernance à l’égard des\nétats de synthèse\nLa direction est responsable de la préparation et de la présentation fidèle des états de\nAux Actionnaires de la société\nsynthèse, conformément au référentiel comptable en vigueur au Maroc, ainsi que du contrôle\nLESIEUR CRISTAL S.A.\n1, rue Caporal Corbi interne qu’elle considère comme nécessaire pour permettre la préparation d’états de\nCasablanca synthèse exempts d’anomalies significatives, que celles-ci résultent de fraudes ou d’erreurs.\nLors de la préparation des états de synthèse, c’est à la direction qu’il incombe d’évaluer la\nRAPPORT GENERAL DES COMMISSAIRES AUX COMPTES capacité de la société à poursuivre son exploitation, de communiquer, le cas échéant, les\nEXERCICE DU 1er JANVIER AU 31 DECEMBRE 2023 questions se rapportant à la continuité de l’exploitation et d’appliquer le principe comptable\nde continuité d’exploitation, sauf si la direction a l’intention de liquider la société ou de cesser\nOpinion son activité ou si aucune autre solution réaliste ne s’offre à elle.\nConformément à la mission qui nous a été confiée par votre Assemblée Générale, nous Il incombe aux responsables de la gouvernance de surveiller le processus d’information\navons effectué l'audit des états de synthèse ci-joints de la société Lesieur Cristal S.A., qui fRineasnpcoiènrsea dbeil ilaté sso dceié tlé’a.uditeur à l’égard de l’audit des états de synthèse\ncomprennent le bilan au 31 décembre 2023, le compte de produits et charges, l'état des\nsoldes de gestion, le tableau de financement pour l’exercice clos à cette date, ainsi que l’état Nos objectifs sont d’obtenir l’assurance raisonnable que les états de synthèse pris dans leur\ndes informations complémentaires (ETIC). Ces états de synthèse font ressortir un montant ensemble sont exempts d’anomalies significatives, que celles-ci résultent de fraudes ou\nde capitaux propres et assimilés de MAD 1.733.931.893,21 dont un bénéfice net de MAD d’erreurs et de délivrer un rapport de l’auditeur contenant notre opinion. L’assurance\n8.872.574,29. raisonnable correspond à un niveau élevé d’assurance, qui ne garantit toutefois pas qu’un\naudit réalisé conformément aux normes de la profession au Maroc permettra toujours de\nNous certifions que les états de synthèse cités au premier paragraphe ci-dessus sont détecter toute anomalie significative qui pourrait exister. Les anomalies peuvent résulter de\nréguliers et sincères et donnent, dans tous leurs aspects significatifs, une image fidèle du fraudes ou d’erreurs et elles sont considérées comme significatives lorsqu’il est raisonnable\nrésultat des opérations de l’exercice écoulé ainsi que de la situation financière et du de s’attendre à ce que, individuellement ou collectivement, elles puissent influer sur les\npatrimoine de la société Lesieur Cristal S.A. au 31 décembre 2023, conformément au décisions économiques que les utilisateurs des états de synthèse prennent en se fondant\nréférentiel comptable admis au Maroc. sur ceux-ci.\n3\nDans le cadre d’un audit réalisé conformément aux normes de la profession au Maroc, nous\nFondement de l’opinion\nexerçons notre jugement professionnel et faisons preuve d’esprit critique tout au long de cet\naudit. En outre :\nNous avons effectué notre audit selon les Normes de la Profession au Maroc. Les\nresponsabilités qui nous incombent en vertu de ces normes sont plus amplement décrites\ndans la section « Responsabilités de l’auditeur à l’égard de l’audit des états de synthèse » o nous identifions et évaluons les risques que les états de synthèse comportent des\nanomalies significatives, que celles-ci résultent de fraudes ou d’erreurs, concevons et\ndu présent rapport. Nous sommes indépendants de la société conformément aux règles de\nmettons en œuvre des procédures d’audit en réponse à ces risques, et réunissons des\ndéontologie qui s’appliquent à l’audit des états de synthèse au Maroc et nous nous sommes\néléments probants suffisants et appropriés pour fonder notre opinion. Le risque de non-\nacquittés des autres responsabilités déontologiques qui nous incombent selon ces règles.\ndétection d’une anomalie significative résultant d’une fraude est plus élevé que celui\nNous estimons que les éléments probants que nous avons obtenus sont suffisants et\nd’une anomalie significative résultant d’une erreur, car la fraude peut impliquer la\nappropriés pour fonder notre opinion d’audit.\ncollusion, la falsification, les omissions volontaires, les fausses déclarations ou le\nQuestions clés de l’audit contournement du contrôle interne ;\nLes questions clés de l’audit sont les questions qui, selon notre jugement professionnel, ont o nous acquérons une compréhension des éléments du contrôle interne pertinents pour\nété les plus importantes dans l’audit des états de synthèse de la période considérée. Ces l’audit afin de concevoir des procédures d’audit appropriées aux circonstances, et non\nquestions ont été traitées dans le contexte de notre audit des états de synthèse pris dans dans le but d’exprimer une opinion sur l’efficacité du contrôle interne de la société ;\nleur ensemble et aux fins de la formation de notre opinion sur ceux-ci, et nous n’exprimons\npas une opinion distincte sur ces questions. o nous apprécions le caractère approprié des méthodes comptables retenues et le\ncaractère raisonnable des estimations comptables faites par la direction, de même que\ndes informations y afférentes fournies par cette dernière ;\n1\n1. TITRES DE PARTICIPATION\no nous tirons une conclusion quant au caractère approprié de l’utilisation par la direction\nRisque identifié Notre réponse du principe comptable de continuité d’exploitatio²n et, selon les éléments probants\nobtenus, quant à l’existence ou non d’une incertitude significative liée à des événements\nou situations susceptibles de jeter un doute important sur la capacité de la société à\nLes titres de participation sont comptabilisés au Nos travaux ont consisté principalement à :\npoursuivre son exploitation. Si nous concluons à l’existence d’une incertitude\nbilan pour une valeur nette comptable de KMAD\n383.860 - Examiner, sur la base d’échantillons, la significative, nous sommes tenus d’attirer l’attention des lecteurs de notre rapport sur les\njustification des méthodes d’évaluation et informations fournies dans les états de synthèse au sujet de cette incertitude ou, si ces\nIls sont comptabilisés individuellement à leur des éléments chiffrés utilisés par la société informations ne sont pas adéquates, d’exprimer une opinion modifiée. Nos conclusions\nvaleur d’acquisition et lorsque la valeur actuelle pour déterminer les valeurs actuelles, s’appuient sur les éléments probants obtenus jusqu’à la date de notre rapport. Des\ndes titres est inférieure à la valeur nette - S’assurer que les données retenues dans la événements ou situations futurs pourraient par ailleurs amener la société à cesser son\ncomptable, une analyse est effectuée par le réalisation des tests de dépréciation des exploitation ;\nmanagement pour déterminer la dépréciation à titres de participation sont cohérentes avec\nconstater. - Tle es s d teo rn nées p as ro urce s od ne ds ae gn eti tés ; l’exactitude o n syo nu ts h èé sv ea , lu yo cn os m l pa r isp r lé es se in nt fa ot ri mon a tid o’ ne sn s foe um rnb il ee s, dla a ns str u l’Ect Tu Ir Ce , e et t ale p pc ro én ct ioe nn su sd i e les s é ét ta at ts s dde e\nLa valeur actuelle est déterminée, pour chaque arithmétique des calculs des valeurs d’utilité synthèse représentent les opérations et événements sous-jacents d’une manière propre\ntitre, par référence à une méthode d’évaluation retenues par la société. à donner une image fidèle.\nfondée sur les éléments disponibles tels que\nl’actualisation des flux futurs, la juste valeur Enfin, nous avons examiné les informations\npour le cas des actifs biologiques ou l’actif net relatives aux titres de participation publiées dans\nréévalué communément utilisés qui leurs sont l’état des informations complémentaires (ETIC).\nrelatifs pour apprécier les perspectives de\nrentabilité.\n4\nCompte tenu du poids des titres de participation\nau bilan, du niveau de jugement exercé pour\nl’estimation du risque sur les titres de\nparticipation ainsi que le degré d’incertitude lié\nà cette estimation à cause de la sensibilité des\nmodèles utilisés ou variations de données et\nd’hypothèses sur lesquelles se fondent ces\nestimations, nous avons considéré que\nl’évaluation des titres de participation constituait\n2. uDnE pPoRinEt CclIéA dTeIO nNot rDeE aSu dCitR.EANCES CLIENTS\nRisque identifié Notre réponse\nLes créances clients s’élèvent à KMAD 661.708 Les travaux sur les comptes au 31 décembre\nen valeur nette au 31 décembre 2023 dont un 2023, ont notamment consisté en :\nmontant de KMAD 218.303 de provision pour\ndépréciation. - La fiabilisation de la balance âgée des\ncréances clients en testant pour un\nCes provisions sont déterminées sur la base échantillon l’ancienneté retenue ;\nd’une méthode statistique qui se base sur - La réalisation de tests relatifs à l’apurement\nl’ancienneté de la créance (100% de solde pour des créances en période subséquente ;\nles créances antérieures à 1 an et 50% pour les - Le recalcul de la provision sur la base de la\ncréances antérieures à 6 mois). Cependant, le méthode statistique retenue par la société ;\nmanagement complète éventuellement cette - L’examen des PV de réunions tenues par\nrègle par une analyse au cas par cas intégrant les responsables commerciaux pour\nd’autres indices de dépréciation (relation l’estimation du risque de recouvrement sur2\ncommerciale, couverture assurance, feed-back les créances clients ;\ndes opérationnels...). - L’établissement des entretiens avec les\nopérationnels pour s’assurer de l’absence\nNous avons considéré l’estimation du montant de créances clients bien que récentes\nde la provision pour dépréciation des créances présentant un risque de recouvrement ;\nclients comme un point clé de l’audit compte\ntenu du caractère estimatif de ce processus et\nson impact significatif sur les comptes.\nSiège social : 1, rue caporal Corbi, Pour consulter les états financiers de Lesieur Cristal :\n20 300 Roches Noires - Casablanca - R.C 4171 https://www.lesieur-cristal.com/communication_\nICE 001569079000005 - Tél. : (+212) 522 67 93 00 financiere/etats-financiers/\nResponsabilités de la direction et des responsables de la gouvernance à l’égard des\nétats de synthèse"
            }
        ]
    ]
}