{
    "text": "BANQUE CENTRALE POPULAIRE\nNOTICE D’INFORMATION\nRelative au programme de rachat d’actions BCP en vue de\nfavoriser la liquidité\nProposé à l’Assemblée Générale Ordinaire prévue le 28 juin 2024\nOrganisme Conseil\nVISA DE L’AUTORITE MAROCAINE DU MARCHE DES CAPITAUX\nConformément aux dispositions de la Circulaire de l’AMMC, prise en application des dispositions de l’article\n281 de la loi 17-95, telle que modifiée et complétée, l'original de la présente notice d'information a été visé par\nl’AMMC le 12 juin 2024 sous la référence n° VI/EM/015/2024\nSOMMAIRE\nABREVIATIONS 3\nAVERTISSEMENT 4\nI. ATTESTATIONS ET COORDONNEES 5\n1. Le Président du Conseil d’Administration 5\n2. Le Conseil Financier 6\n3. Le Responsable de l’Information et de la Communication Financières 7\n4. Société de bourse en charge de l’exécution du programme de rachat 7\nII. LE PROGRAMME DE RACHAT 8\n1. Cadre légal et réglementaire 8\n2. Objectifs du programme 10\n3. Caractéristiques du programme 11\n4. Eléments d'appréciation des caractéristiques du programme 12\n5. Incidence du programme sur la situation financière de la BCP 16\n6. Financement du programme 16\n7. Modalités de réalisation du programme 16\n8. Contrat de liquidité 17\n9. Traitement comptable et fiscal des rachats 18\nIII. EVOLUTION DU COURS BCP DEPUIS JANVIER 2023 19\nIV. PROGRAMMES DE RACHAT PRECEDENTS 21\nV. ANNEXES 26\nNotice d’information – Programme de rachat d’actions 2\nABREVIATIONS\nAMMC Autorité Marocaine des Marchés de Capitaux\nBCP Banque Centrale Populaire\nBOA Bank Of Africa\nBMCI Banque Marocaine du Commerce et de l’Industrie\nCPM Crédit Populaire du Maroc\nMAD Dirham Marocain\nGBP Groupe Banques Populaires\nKMAD Milliers de Dirhams\nMMAD Millions de Dirhams\nMds Milliards\nUCF Upline Corporate Finance\nNotice d’information – Programme de rachat d’actions 3\nAVERTISSEMENT\nLe visa de l’AMMC n’implique ni approbation du programme de rachat ni authentification des\ninformations présentées. Il a été attribué après examen de la pertinence et de la cohérence de\nl’information donnée dans la perspective du programme de rachat envisagé.\nNotice d’information – Programme de rachat d’actions 4\nI. ATTESTATIONS ET COORDONNEES\n1. LE PRESIDENT DU CONSEIL D’ADMINISTRATION\nDénomination ou raison sociale Banque Centrale Populaire\nReprésentant légal Mohamed Karim MOUNIR\nFonction Président Directeur Général\nAdresse 101, Bd Zerktouni 20 100 - Casablanca\nNuméro de téléphone 05 22 20 25 33\nNuméro de télécopieur 05 22 22 26 99\nAdresse électronique mkmounir@cpm.co.ma\nAttestation\nObjet : Programme de rachat par la BCP de ses propres actions\nLe Président du Conseil d’Administration, Monsieur Mohamed Karim Mounir, atteste que :\n La BCP détient directement 249 676 actions représentant 0,12% de son capital social ;\n La BCP ne détient indirectement aucune action de son capital social.\nIl atteste également que les données de la présente notice d'information dont il assume la responsabilité,\nsont conformes à la réalité. Elles comprennent toutes les informations nécessaires aux actionnaires pour\nfonder leur jugement sur le programme de rachat d'actions proposé. Elles ne comportent pas d'omissions\nde nature à en altérer la portée.\nMohamed Karim MOUNIR\nPrésident du Conseil d’Administration\nBanque Centrale Populaire\nNotice d’information – Programme de rachat d’actions 5\n2. LE CONSEIL FINANCIER\nOrganisme conseil Upline Corporate Finance\nReprésentant légal Mohammed Kamal MOKDAD\nFonction Président Directeur Général\nAdresse 101, Bd Zerktouni 20 100 - Casablanca\nNuméro de téléphone 05 22 20 25 33\nNuméro de télécopieur 05 22 22 26 99\nAdresse électronique kmokdad@cpm.co.ma\nAttestation\nObjet : Programme de rachat par la BCP de ses propres actions\nLa présente notice d’information a été préparée par nos soins et sous notre responsabilité. Nous attestons\navoir effectué les diligences nécessaires pour nous assurer de la sincérité des informations qu’elle\ncontient et de leur pertinence au regard du programme de rachat proposé.\nCes diligences ont notamment concerné l’analyse de l’environnement économique et financier de la\nBCP à travers :\n- Les requêtes d’informations et d’éléments de compréhension recueillis auprès de la Direction Générale\nde la banque ;\n- L’analyse des comptes sociaux et consolidés au 31/12/2022, au 31/12/2023 ainsi qu’au 31/03/2024 ;\n- L’étude de l’évolution de l’historique du cours en 2023 et 2024 à travers l’analyse de la liquidité, la\nvolatilité et l’évolution du titre ayant permis de fixer les prix maximums d’achat et minimum de vente\ntels que présentés dans la notice d’information ;\n- Et l’examen des procès-verbaux des réunions du Conseil d’Administration.\nNous attestons avoir pris toutes les mesures nécessaires pour faire en sorte que notre appartenance à la\nBanque Centrale Populaire (Upline Corporate Finance étant filiale à 100% de Upline Group, filiale à\n100% du Groupe constitué par la Banque Centrale Populaire et les Banques Populaires Régionales)\nn’affecte pas l’objectivité de notre analyse et la qualité de la présente mission pour laquelle nous avons\nété mandaté\nMohammed Kamal MOKDAD\nPrésident Directeur Général\nUpline Corporate Finance\nNotice d’information – Programme de rachat d’actions 6\n3. LE RESPONSABLE DE L’INFORMATION ET DE LA COMMUNICATION FINANCIERES\nDénomination ou raison sociale Banque Centrale Populaire\nReprésentant légal Anouar MESKINE\nFonction Directeur Pôle Finances, Stratégie et\nPerformances\nAdresse 101, Bd. ZERKTOUNI 20 100 - Casablanca\nNuméro de téléphone 05 22 22 41 11\nNuméro de télécopieur 05 22 20 93 40\nAdresse électronique ameskine@cpm.co.ma\n4. SOCIETE DE BOURSE EN CHARGE DE L’EXECUTION DU PROGRAMME DE RACHAT\nDénomination ou raison sociale Upline Securities\nReprésentant légal Ali HACHAMI\nFonction Président du Directoire\nAdresse 101, Boulevard Mohamed Zerktouni à\nCasablanca\nNuméro de téléphone 05 22 99 71 71\nAdresse électronique ali.hachami@uplinegroup.ma\nNotice d’information – Programme de rachat d’actions 7\nII. LE PROGRAMME DE RACHAT\n1. CADRE LEGAL ET REGLEMENTAIRE\nLe programme de rachat par la BCP de ses propres actions en vue de favoriser la liquidité du marché de\nses titres, est une opération régie, notamment, par les dispositions :\n (i) des articles 279 et 281 de la loi n°17-95 du Rabii II 1417 (30 août 1996) relative aux sociétés\nanonymes telle que modifiée et complétée :\no l’article 279 stipule «La société ne peut posséder, directement ou par l'intermédiaire\nd'une personne agissant en son propre nom pour le compte de la société, plus d'un\npourcentage du capital fixé par voie réglementaire. Pour les sociétés dont les actions ne\nsont pas inscrites à la bourse des valeurs, les actions possédées doivent être mises sous\nla forme nominative et entièrement libérées lors de son acquisition.\nÀ défaut, les membres du conseil d'administration ou du directoire sont tenus, dans les\nconditions prévues à l'article 352 de libérer les actions.\nL'acquisition d'actions de la société ne peut avoir pour effet d'abaisser la situation nette\nà un montant inférieur à celui du capital augmenté des réserves non distribuables.\nLa société doit disposer de réserves, autres que la réserve légale, d'un montant au moins\négal à la valeur de l'ensemble des actions qu'elle possède.\nLes actions possédées par la société ne donnent droit ni au vote ni aux dividendes.\nEn cas d'augmentation de capital par souscription d'actions en numéraire, la société ne\npeut exercer par elle-même le droit préférentiel de souscription L'assemblée générale\npeut décider de ne pas tenir compte de ces actions pour la détermination des droits\npréférentiels de souscription attachés aux autres actions ; à défaut, les droits attachés\naux actions possédées par la société doivent être, avant la clôture du délai de\nsouscription, soit vendus en bourse, soit répartis entre les actionnaires au prorata des\ndroits de chacun. »\no l’article 281 stipule «Par dérogation aux dispositions du paragraphe 1) de l'article 280\nci-dessus, les sociétés dont les titres sont inscrits à la cote de la bourse des valeurs\npeuvent acheter en bourse leurs propres actions, en vue de favoriser la liquidité du\nmarché desdites actions, ou de les céder, à titre onéreux ou à titre gratuit, aux salariés\nou aux dirigeants de la société.\nA cette fin, l'assemblée générale ordinaire doit avoir expressément autorisé la société à\nopérer en bourse sur ses propres actions. Elle fixe les modalités de l'opération et\nnotamment les prix maximum d'achat et minimum de vente, le nombre maximum\nd'actions à acquérir et le délai dans lequel l'acquisition doit être effectuée. Cette\nautorisation ne peut être donnée pour une durée supérieure à dix-huit mois.\nLadite opération ne peut être décidée, sous peine de nullité, que sur la base d'un\ndocument d'information élaboré et visé par l'Autorité marocaine du marché des capitaux\net publié, dans les conditions et les formes requises par la loi n° 44-12 relative à l'appel\npublic à l'épargne et aux informations exigées des personnes morales et organismes\nfaisant appel public à l'épargne.\nLes actions possédées au-delà de la durée de dix-huit mois ci-dessus, doivent être cédées\ndans un délai de six mois.\nLes formes et conditions dans lesquelles peuvent s'effectuer ces rachats sont fixées par\nl'administration après avis de l'Autorité marocaine du marché des capitaux. »;\n (ii) le décret 2-02-556 du 22 Dou-al Hijja 1423 (24 février 2003) fixant les formes et les\nNotice d’information – Programme de rachat d’actions 8\nconditions dans lesquelles peuvent s’effectuer les rachats en bourse par les sociétés anonymes\nde leurs propres actions, tel que modifié et complété par le décret n°2-10-44 du 17 Rajab 1431\n(30 juin 2010) ;\n (iii) le décret N 2-18-306 du 6 Chaoual 1439 (20 juin 2018) fixant le pourcentage du capital que\nla société peut posséder directement ou par l’intermédiaire d’une personne agissant en son\npropre nom pour le compte de la société ;\n (iv) des circulaires de l’AMMC en vigueur ; et\n (v) des dispositions du Règlement Général de la Bourse de Casablanca.\nEn application des dispositions précitées, le Conseil d’Administration de la BCP, réuni le 13 mars 2024,\na décidé ce qui suit :\n D’abroger le programme de rachat de ses propres actions en cours1 ;\n De proposer un programme de rachat et un contrat de liquidité adossé à ce programme à\nl’Assemblée Générale Ordinaire qui sera tenue le 28 juin 2024 statuant aux conditions de\nquorum et de majorité requises pour les assemblées générales ordinaires.\nsera soumis à l’autorisation de l’Assemblée Générale Ordinaire convoquée le 28 juin 2024, statuant aux\nconditions de quorum et de majorité requise après examen de l’ensemble des éléments contenus dans la\nnotice d’information et du rapport du Conseil d’Administration.\nA cette fin, le Conseil d’Administration a décidé de recourir aux services d’une société de bourse unique,\nla société Upline Securities, pour l’exécution du programme de rachat qui sera décidé par l’Assemblée\nGénérale Ordinaire. Avant de procéder à cette désignation, le Conseil d’Administration a considéré les\nstipulations de la circulaire de l’AMMC qui énonce que : « l’émetteur doit permettre à la société de\nbourse qui exécute son programme de rachat d’agir en toute indépendance dans la gestion du\nprogramme et la réalisation des transactions y afférentes. »\nL’autorisation du programme de rachat par la BCP de ses propres actions fera l’objet de la résolution\nsuivante :\n«L’Assemblée Générale Ordinaire, statuant conformément aux dispositions statutaires et légales de\nquorum et de majorité,\n• agissant conformément aux dispositions légales et notamment les articles 279 et 281 de la loi\nn°17-95 relative aux sociétés anonymes, telle que modifiée, complétée et amendée, du décret n°2-02-\n556 du 24 février 2003 tel que modifié et complété par le décret n° 2-10-44 du 30 juin 2010 fixant les\nformes et conditions dans lesquelles peuvent s'effectuer les rachats en bourse par les sociétés anonymes\nde leurs propres actions, et de la circulaire de l’AMMC,\n• et, après avoir entendu la lecture du rapport du Conseil d’Administration relatif au programme\nde rachat en bourse par la Banque Centrale Populaire de ses propres actions en vue de favoriser la\nliquidité du marché desdites actions, et examiné l’ensemble des éléments contenus dans la notice\nd’information visée par l’AMMC,\n• décide d’abroger le programme de rachat des actions de la BCP autorisé par l’Assemblée\nGénérale du 28 juin 2024;\n• autorise expressément la mise en place d’un nouveau projet de programme de rachat portant\nsur 5% du capital social, soit 10 165 623 actions, tel qu’arrêté par le Conseil d’Administration réuni\nen date du 13 mars 2024 selon les modalités suivantes :\n1 Programme de rachat en vue de favoriser la liquidité du titre visé le 12 juin 2023 sous la référence n° VI/EM/018/2023\nNotice d’information – Programme de rachat d’actions 9\nTitres concernés Actions BCP\nCalendrier de l’opération Du 15 juillet 2024 au 15 janvier 2026\n10 165 623 actions, soit 5% du capital, y compris\nNombre maximum d’actions à détenir\nles actions visées par le contrat de liquidité\nMontant maximum du programme 3 801 943 002 MAD\nDélai de l’autorisation 18 mois\nMode de financement du programme : Par la trésorerie\nPrix d’intervention (hors frais d’achat et de vente)\n Prix minimum unitaire de vente 201,00 MAD\n Prix maximum unitaire d’achat 374,00 MAD\nL’Assemblée Générale entérine la proposition du Conseil d’Administration de permettre à la BCP de\nmettre en place un contrat de liquidité adossé au programme de rachat, dans la limite de la fourchette\nde prix autorisée et ce, selon les modalités suivantes :\nTitres concernés Actions BCP\nCalendrier de l’opération Du 15 juillet 2024 au 15 janvier 2026\nNombre maximum d’actions à détenir 2 033 124 actions, soit 1% du capital\nMontant maximum du programme 760 388 376 MAD\nDélai de l’autorisation 18 mois\nMode de financement du programme : Par la trésorerie\nPrix d’intervention (hors frais d’achat et de vente)\n Prix minimum unitaire de vente 201,00 MAD\n Prix maximum unitaire d’achat 374,00 MAD\nL’Assemblée Générale Ordinaire donne les pouvoirs les plus étendus au Conseil d’Administration et à\nson Président, avec faculté de subdélégation, à l’effet de procéder, à l’exécution dudit programme de\nrachat et du contrat de liquidité dans les conditions de date qu’il juge opportun et dans les limites des\ncaractéristiques déclinées en haut.»\nEn vertu des dispositions de la circulaire de l’AMMC, la BCP prévoit d’insérer dans le rapport de gestion\ndu Conseil d’Administration soumis à l’Assemblée Générale Ordinaire statuant sur les comptes annuels\nune partie consacrée au programme de rachat d’actions.\n2. OBJECTIFS DU PROGRAMME\nLe Conseil d’Administration de la BCP, en vue de favoriser la liquidité du titre, souhaite proposer à\nl’Assemblée Générale la mise en place d’un programme de rachat par la BCP de ses propres actions.\nA travers ce programme la BCP ne vise pas :\n L’annulation postérieure des titres rachetés ;\n La recherche d’un résultat financier ;\n Le soutien du cours en s’opposant à une tendance forte du marché ;\n La constitution d’un stock de titres afin de procéder ultérieurement à une opération financière\nou à une allocation aux salariés\nNotice d’information – Programme de rachat d’actions 10\nPar ailleurs et conformément à la circulaire de l’AMMC telle que modifiée et complétée, un contrat de\nliquidité, sera adossé au présent programme de rachat selon les modalités suivantes :\n Le contrat de liquidité porte sur 20% du programme de rachat, soit 2 033 124 actions ;\n Le compte titres affecté au contrat de liquidité doit impérativement être soldé au plus tard à la\nfin du programme de rachat\n Le contrat de liquidité doit être géré dans un compte distinct.\n3. CARACTERISTIQUES DU PROGRAMME\n3.1. LES TITRES CONCERNES PAR LE PRESENT PROGRAMME DE RACHAT\nActions BCP.\n3.2. PART MAXIMALE DU CAPITAL A DETENIR\nSous réserve de l’approbation par l’Assemblée Générale Ordinaire prévue le 28 juin 2024, du projet de\nrésolution relatif à l’autorisation du programme de rachat, la société pourrait détenir un maximum de\n10 165 623 actions, soit 5% du capital. La part maximale à détenir inclut les actions auto-détenues, soit\n1 095 999 actions, dans le cadre du programme de rachat en vigueur au 30 avril 2024.\n3.3. FOURCHETTE DU PRIX D’INTERVENTION\nFourchette du programme de rachat et du contrat de liquidité, (hors frais d’achat et de vente)\nPrix minimum unitaire de vente : 201,00 MAD\nPrix maximum unitaire d’achat : 374,00 MAD\n3.4. MONTANT MAXIMAL A ENGAGER PAR LA SOCIETE\nConformément à l’article 279 de la loi n°17-95 relative aux sociétés anonymes telle que modifiée et\ncomplétée, la valeur de l’ensemble des actions BCP détenues par la société, ne pourra être supérieure\nau montant des réserves de la BCP, autres que la réserve légale.\nDétail des réserves et primes\nAu 31 décembre 2023(1) Au 31 mars 2024(1)\nliées au capital (en MMAD)\nAutres réserves 11 002 11 002\nPrimes d’émission, de fusion\n16 104 16 104\net d’apport\n1BCP comptes sociaux\nLe montant maximum à engager lors de ce programme de rachat, soumis à l’autorisation de l’Assemblée\nGénérale, est de 3 801 943 002 dirhams. Eu égard au niveau actuel des réserves autres que la réserve\nlégale, la société pourrait acquérir ses actions sur le marché central sans pour autant dépasser ce montant.\nToutefois, dans le cas où la BCP procéderait, pendant la durée du présent programme de rachat, à la\nmise en distribution, voire la réduction de ses réserves autres que légales à un montant inférieur au\nmontant autorisé par l’Assemblée Générale Ordinaire du 28 juin 2024, elle ne pourrait acquérir ses\npropres actions pour un montant dépassant lesdites réserves.\nPar ailleurs, il est à préciser que conformément aux dispositions de l’article 333 de la loi 17-95 telle que\nmodifiée et complétée, ne seront pas disponibles, pour une éventuelle mise en distribution par\nl’assemblée générale, les réserves correspondant au montant total de la détention propre.\nNotice d’information – Programme de rachat d’actions 11\n3.5. DUREE ET CALENDRIER DU PROGRAMME\nConformément au projet de résolutions relatif à l’autorisation du programme de rachat, celui-ci s’étalera\nsur une période de 18 mois du 15 juillet 2024 au 15 janvier 2026.\nPar ailleurs, conformément à l’article 4.1.12 du règlement général de la bourse des valeurs qui stipule\nque l’émetteur désirant mettre en œuvre un programme de rachat doit informer la société gestionnaire\ndes modalités dudit programme au moins 5 jours de bourse avant son démarrage. Tout retard dans\nl’information de la société gestionnaire est susceptible de retarder la date de début du programme. Ce\ndernier ne démarrera que 5 jours de bourse après avoir informé la société gestionnaire sans pour autant\nmodifier la date de fin du programme.\n4. ELEMENTS D'APPRECIATION DES CARACTERISTIQUES DU PROGRAMME\n4.1. FOURCHETTE DE PRIX D’INTERVENTION\nLe graphique ci-dessous présente la fourchette du programme par rapport à l’évolution du cours de la\nBCP sur la période allant du 2 janvier 2023 au 30 avril 2024 :\nEvolution du cours de la BCP entre le 2 janvier 2023 et le 30 avril 2024\nPrix maximum de vente 374 MAD\n400 Nouveau programme de rachat\n350 Prix maximum d'achat 296 MAD\nProgramme de rachat précédent*\n300\n250\n200\nPrix minimum de vente 201 MAD\nNouveau programme de rachat\n150\nPrix minimum de vente 159 MAD\nProgramme de rachat précédent*\n100\nSource : Bourse de Casablanca\n*Le programme de rachat précédent a été abrogé à la date de mise en place du nouveau programme de rachat soit le 10 juillet 2023\nDurant la période d’observation, le titre BCP a oscillé entre le cours le plus bas de 194,60 MAD et le\ncours le plus haut de 309,00 MAD. Le cours moyen pondéré a été de 264,95 MAD.\nEvolution de du volume d'échange entre le 2 janvier 2023 et le 30 avril 2024 (en nombre de titres)\n700000\n600000\n500000\n400000\n300000\n200000\n100000\n0\n02/01/2023 02/04/2023 02/07/2023 02/10/2023 02/01/2024 02/04/2024\nSource : Bourse de Casablanca\nNotice d’information – Programme de rachat d’actions 12\nPlus de 16,2 millions d’actions ont été transigées sur le Marché Central de la Bourse de Casablanca, au\ncours de la période étudiée, entre le 2 janvier 2023 et le 30 avril 2024, soit une quantité journalière\nmoyenne de 49 003 titres. Le volume d’échange maximum a été enregistré le 24 avril 2024, totalisant\nprès de 173,5 MMAD soit 594 201 titres.\n1. Interprétation des bornes proposées\nLa fourchette proposée dans le cadre du présent programme de rachat en vue de favoriser la liquidité\ndes titres est présentée ci-dessous :\n Prix maximum d'achat : 201,00 MAD\n Prix minimum de vente : 374,00 MAD\nCette fourchette a été proposée au Conseil d’Administration du 13 mars 2024, et a été déterminée en\nréférence à un cours moyen pondéré de 287,7 MAD calculé sur la période allant du 11 décembre 2023\nau 11 mars 2024, avec une variation de plus ou moins 30%.\nEn effet, compte tenue de l’évolution du cours moyen pondéré de la BCP durant les trois derniers mois\npar rapport au cours de référence du programme de rachat précédent qui représentait 227,46 MAD1\n(+26,5%), ladite fourchette a été revue.\n4.2. NOMBRE MAXIMUM D’ACTIONS\nConformément à la réglementation du programme de rachat qui permet de fixer le maximum d’actions\nà détenir à 10% du capital social ainsi qu’aux programmes de rachat précédent prévoyant une limite de\n5%, la BCP a décidé de fixer une limite 5% de son capital social.\nLa société pourrait acquérir un maximum de 10 165 623 actions, soit 5% du capital.\n4.3. DUREE DU PROGRAMME\nConformément au projet de résolutions relatif à l’autorisation du programme de rachat, celui-ci s’étalera\nsur une période de 18 mois, du 15 juillet 2024 au 15 janvier 2026.\nUne période de 18 mois permettra de favoriser durablement la liquidité du titre.\n4.4. EVOLUTION DE LA LIQUIDITE\nEvolution de la liquidité du titre BCP entre le 2 janvier 2023 et le 30 avril 2024\n200\n180\n160\n140\n120\n100\n80\n60\n40\n20\n0\nSource : Bourse de Casablanca\n1 Cours moyen pondéré calculé sur la période allant du 21 novembre 2022 au 20 février 2023\nNotice d’information – Programme de rachat d’actions 13\nAu cours de la période allant du 2 janvier 2023 au 30 avril 2024, les échanges sur le marché central\nportant sur le titre BCP ont atteint un total de 16 220 032 de titres. Ces échanges ont cumulé un volume\nglobal de plus de 4 297 MMAD.\nDurant cette même période, le cours moyen pondéré a été de l’ordre de 264,95 MAD. La moyenne\nquotidienne des volumes traités a été de 12,98 MMAD correspondant à une moyenne de 49 003 titres\néchangés, par séance.\nLe volume maximum a été atteint le 24 avril 2024, avec 173,5 MMAD pour une quantité échangée de\n594 201 titres et un CMP journalier de 291,96 MAD. Courant de cette même période, le titre BCP n’a\npas fait objet de transactions durant la séance du 13 février 2023.\nLe tableau ci-après présente les principaux indicateurs boursiers de l’action BCP sur la période\nd’observation :\nCoefficient de liquidité* 8,0%\nCours minimum** 194,60 MAD\nCours maximum** 309,00 MAD\nTaux de cotation*** 99,7%\nPerformance du titre BCP**** 28,6%\n*Nombre d’actions échangées, rapporté au nombre d’actions formant le capital\n**Cours de clôture\n***Nombre de jours où l’action BCP a été traitée, rapporté au nombre de jours de bourse sur la période\n****Performance du titre BCP calculée sur la base du cours de clôture au 30 avril 2024 rapporté au cours de clôture au\n2 janvier 2023\nSource : Analyse UCF\nLe cours minimum enregistré durant la période d’observation s’établit à 194,60 MAD au\n06/01/2023, et le cours maximum est enregistré au 28/02/2024, à hauteur de 309,00 MAD.\nNotice d’information – Programme de rachat d’actions 14\nLe tableau suivant présente les séances les plus actives sur la période d’observation ainsi que leurs\nquotes-parts dans les volumes globaux :\nSéance Volume en MAD QP sur volumes globaux1\n24/04/2024 173 482 449 4,04%\n21/11/2023 170 272 467 3,96%\n28/06/2023 153 965 852 3,58%\n07/08/2023 153 481 023 3,57%\n29/05/2023 111 348 983 2,59%\n08/02/2024 87 306 542 2,03%\n05/10/2023 69 841 856 1,63%\n29/12/2023 69 466 251 1,62%\n05/06/2023 68 936 053 1,60%\n22/02/2023 65 562 287 1,53%\nSource : Bourse de Casablanca\nLe tableau ci-après retrace l’évolution mensuelle du titre BCP entre janvier 2023 et avril 2024 :\nTransactions\nCours moyen pondéré en Transactions en\nMois Plus haut en MAD (*) Plus bas en MAD(*) en capitaux en\nMAD nombre de titres\nMAD\njanv-23 213,1 227,00 194,60 425 674 90 732 075\nfévr-23 229,7 242,00 218,00 1 024 526 235 324 393\nmars-23 234,7 239,00 227,00 559 198 131 222 007\navr-23 230,6 235,95 227,50 406 300 93 695 384\nmai-23 232,7 236,00 227,00 844 687 196 554 343\njuin-23 250,6 264,00 234,05 1 569 572 393 284 205\njuil-23 261,7 266,00 253,15 1 067 293 279 362 803\naoût-23 262,2 265,00 254,10 1 271 466 333 422 488\nsept-23 255,0 260,00 252,00 274 176 69 901 528\noct-23 264,7 270,00 252,00 877 908 232 373 546\nnov-23 264,5 268,00 259,00 1 544 105 408 364 751\ndéc-23 273,5 277,05 266,00 1 458 619 399 004 625\njanv-24 287,3 295,05 275,00 1 252 168 359 767 663\nfévr-24 296,2 309,00 286,00 1 584 146 469 207 627\nmars-24 297,4 302,00 292,00 507 325 150 871 288\navr-24 292,6 296,00 290,00 1 552 869 454 342 189\n(*) Cours de clôture\nSource : Bourse de Casablanca\nDurant la période analysée, les transactions en valeur portant sur le titre BCP ont atteint un maximum\nde 469,2 MMAD observé au cours du mois de février 2024, correspondant à 1 584 146 actions\néchangées. Le montant minimum des transactions a été enregistré durant le mois de septembre 2023,\nsoit 69,9 MMAD pour 274 176 titres transigés.\n1 La Quote part est calculée par rapport au volume global (en MAD)\nNotice d’information – Programme de rachat d’actions 15\n5. INCIDENCE DU PROGRAMME SUR LA SITUATION FINANCIERE DE LA BCP\nL’opération de rachat d’actions n’aurait comme incidence que la constatation des plus ou moins-values\néventuelles au niveau du compte de résultat en fonction de l’évolution du cours du titre, dans la mesure\noù celle-ci n’aie pas pour objectif l’annulation des actions acquises. Les fluctuations des cours\npourraient, par ailleurs, donner lieu à des ajustements, ayant des conséquences sur les provisions en cas\nde moins-values constatées au moment de la clôture de l’exercice comptable.\nDans l’hypothèse où la BCP rachète l’ensemble des titres concernés par le programme de rachat en vue\nde favoriser la liquidité du titre, à savoir 10 165 623 actions, dans la fourchette haute du prix soit\n374 MAD et qu’elle les revende au prix minimum de 201 MAD, chaque achat et vente des 5% donnerait\nlieu à une moins-value de 1 759 MMAD1.\n6. FINANCEMENT DU PROGRAMME\nLe programme de rachat d’actions que la BCP compte mettre en place sera financé par ses ressources\npropres, sachant que dans le bilan social arrêté au 31 mars 2024, la trésorerie disponible ressort à\n4,58 Mds MAD2.\n7. MODALITES DE REALISATION DU PROGRAMME\nLes achats et les cessions dans le cadre du programme de rachat, se feront sur le marché central de la\nBourse de Casablanca, dans la fourchette du prix maximum à l’achat et du prix minimum à la vente, à\nautoriser par l’Assemblée Générale Ordinaire du 28 juin 2024, sous réserve des ajustements liées à des\néventuelles opération sur le capital de la société. Ces ajustements seront approuvés dans le cadre des\nautorisations par les organes sociaux desdites opérations sur capital.\nLe 06 juin 2024, la BCP a mis en place un mandat de gestion avec la société de Bourse, Upline Securities,\nreprésentée par son Président du directoire, M. Ali Hachami, devant opérer pour son compte sur la\nBourse de Casablanca. Ce mandat de gestion est d’une durée de 18 mois, à partir de la date de début du\nprogramme de rachat et du contrat de liquidité. La BCP s’engage, conformément aux réglementations\nen vigueur à informer le marché au moment de la mise en place dudit programme de rachat.\nCe mandat a été signé sous la double condition suspensive de (i) l’approbation de la convention précitée\npar le conseil de surveillance de Upline Securities en application des dispositions\ndes articles 56 et 58 alinéa 1 de la loi n°17-95 relative aux sociétés anonymes et (ii) l’adoption du\nprogramme de rachat par l’Assemblée Générale Ordinaire de la BCP prévue le 28 juin 2024.\nDans le cadre global de ce mandat de gestion, les opérations de rachat et de vente se feront par\nl’intermédiaire de Upline Securities, qui agira en pleine indépendance. La BCP s’engage à ne transmettre\naucune instruction, ou information destinée à orienter les interventions du mandataire.\nA cet effet, dans le cadre du programme de rachat, la société de bourse Upline Securities est libre de\nprendre l’initiative de réaliser les transactions à l’achat ou à la vente des actions BCP, sous réserve du\nrespect :\n Des conditions fixées par l’Assemblée Générale Ordinaire du 28 juin 2024 ;\n Du respect de l’article 279 de la loi 17-95 relative aux sociétés anonymes telle que modifiée,\ncomplétée et amendée ;\n Des dispositions légales et réglementaires régissant les programmes de rachat d’actions ;\n1 Valeur de la moins-value correspond au calcul suivant : (Prix maximum * Total des titres concernés par le programme de rachat) – (Prix\nminimum * Total des titres concernés par le programme de rachat)\n2 La trésorerie au titre des comptes sociaux au 31 mars 2024 est retraitée du montant correspondant à la réserve obligatoire, celui-ci étant nul\nen 2023\nNotice d’information – Programme de rachat d’actions 16\n Des réserves, hors réserves légales, de la BCP si ces dernières deviennent inférieures au\nmontant maximum à engager par la société ;\n De la circulaire de l’AMMC en matière de l’information exigée des sociétés cotées à\nl’occasion du rachat en Bourse de leurs propres actions et aux modalités de mise en œuvre\ndes opérations de rachat en Bourse par les sociétés anonymes de leurs propres actions.\nLa BCP a la faculté de résilier le contrat de prestation avec Upline Securities. Dans ce cas, la BCP devra\ninformer, sans délais, l’AMMC et la Bourse de Casablanca.\nPar ailleurs, et conformément à l’article 4.1.13 du règlement général de la bourse des valeurs : « Toute\nmodification des modalités du programme de rachat doit être portée, sans délai, par l’émetteur à la\nconnaissance de la Société Gestionnaire. »\nLa BCP est tenue, lors de toute opération sur titres pouvant affecter le nombre d’actions ou le nominal,\nde faire valider par anticipation, par son Assemblée générale et l’AMMC, les nouvelles caractéristiques\ndu programme et en informer à l’avance Upline Securities afin d’éviter toute interruption dudit\nprogramme. La société de bourse chargé de la gestion du programme de rachat, en l’occurrence Upline\nSecurities, devra agir sans entrave au bon fonctionnement du marché et ne doit pas non plus fourvoyer\nsur le marché de l’action notamment l’identité, la qualité ou les intentions des acheteurs ou vendeurs\nlors de l’exécution du programme de rachat.\nUpline Securities s’engage à communiquer un avis d’opéré à la BCP pour chaque opération réalisée\nentrant dans le programme de rachat et du contrat de liquidité qui lui est adossé, comportant toutes les\ncaractéristiques de la transaction : date de l’opération, date de règlement, lieu d’exécution (marché\ncentral), sens de l’opération (achat/vente), cours d’exécution, montant brut, commissions Société de\nBourse, commissions Bourse de Casablanca, montant de la TVA et montant net.\nEn outre, Upline Securities devra transmettre à la BCP un état mensuel comprenant l’ensemble des\ntransactions effectuées, le nombre d’actions achetées et d’actions éventuellement cédées au plus tard le\n2ème jour ouvré suivant le mois concerné.\nUpline Securities est responsable de l’établissement et la transmission à l’AMMC et à la Bourse de\nCasablanca, en temps utiles, de tout document relatif au déroulement et à la réalisation de l’opération.\nLa BCP est dans l’obligation d’informer l’AMMC, dans un délai de cinq (5) jours après la fin de chaque\nmois, sur les transactions exécutées sur l’action (date, volume et prix par action) pour le compte de ses\ndirigeants et de toutes autres personnes morales que ledit émetteur contrôle au sens de la loi sur la société\nanonyme. Par ailleurs, l’émetteur informe également l’AMMC dans les mêmes conditions, des cessions\net annulations d’actions réalisées à la suite de l’exécution des opérations de rachat.\n8. CONTRAT DE LIQUIDITE\nConformément à l’article I.4.18 bis de la circulaire de l’AMMC, l’émetteur peut mettre en place un\ncontrat de liquidité adossé au programme de rachat sous réserve que les conditions suivantes soient\nremplies :\n L’option d’un contrat de liquidité est explicitement autorisée par l’Assemblée Générale du\n28 juin 2024 ;\n Le contrat de liquidité ne peut porter sur un pourcentage excédant 20% du programme de\nrachat autorisé par l’Assemblée Générale. La BCP compte engager, à cet effet, un maximum\nde 2 033 124 actions dans le cadre du contrat de liquidité, soit 1% du capital de la société.\nLe compte titres affecté au contrat de liquidité doit impérativement être soldé au plus tard à\nla fin du programme de rachat, soit le 15 janvier 2026 ;\n Le contrat de liquidité doit être géré dans un compte distinct.\nDe même et conformément à l’article I.4.18 ter de la même circulaire, l’exécution du contrat de liquidité\ndoit respecter les principes suivants :\nNotice d’information – Programme de rachat d’actions 17\n Le principe d’indépendance : la personne en charge du contrat de liquidité doit être distincte\nde celle en charge du programme de rachat. A aucun moment, il ne peut y avoir d’entente\nentre lesdites personnes pour leurs interventions sur la valeur ;\n Le principe de permanence : il doit se traduire par une fréquence minimale de présence sur\nle carnet d’ordres, d’au moins 50% du nombre de séances de cotation durant le programme\nde rachat ;\n Le principe de présence : la société de bourse doit assurer une présence sur le carnet d’ordres\nde la BCP par des ordres d’achat et de vente portant sur au moins 100 actions par sens (achat\net vente) ;\n Le principe d’une fourchette achat/vente maximale : la fourchette s’entend limite\nsupérieure/limite inférieure telle que définie dans le cadre du programme de rachat, soit\n[201 MAD – 374 MAD]. De plus, Upline Securities, s’engage à respecter un spread quotidien\nmaximal entre les cours à l’achat et à la vente plafonné à 4% ;\n Le principe de non-accumulation : Le contrat de liquidité ne doit pas avoir pour objectif\nl’accumulation d’un stock de titres.\n9. TRAITEMENT COMPTABLE ET FISCAL DES RACHATS\nTraitement comptable\nA la suite du rachat par la BCP de ses propres actions, l’opération devra être comptabilisée à sa valeur\nd’acquisition et figurer au niveau des titres et valeurs de placement. Au moment de la cession desdites\nactions, celle-ci donnera lieu à une constatation des plus ou moins-values au niveau du compte de\nrésultat, d’une part, et d’autre part à la comptabilisation au crédit du compte concerné, de la valeur\nd’acquisition des titres cédés.\nLors du passage des comptes sociaux aux comptes consolidés, les plus et moins-values sont neutralisées\nen les comptabilisant en capitaux propres et les actions auto-détenues sont portées en déduction des\ncapitaux propres.\nPar ailleurs, une analyse de la valeur des titres en portefeuille sera réalisée à la fin de chaque exercice\npour être comparée au cours moyen boursier du mois de décembre. Ainsi, dans l’éventualité d’une\nconstatation d’une moins-value latente, une provision pour dépréciation serait constituée.\nTraitement fiscal\nLes bénéfices nets issus de la cession des titres sont imposables en totalité, qu’ils soient en cours ou en\nfin d’exploitation.\nL’opération de rachat de ses propres actions par la BCP pourrait avoir un impact sur le résultat imposable\ndu groupe dans le cas d’une éventuelle différence de prix au moment de la cession, donnant ainsi lieu à\ndes gains ou pertes soumis au régime des plus ou moins-values.\nLes provisions pour dépréciation des titres auto-détenus sont fiscalement déductibles.\nTraitement comptable et régime fiscal applicable aux dividendes\nLes actions possédées par la société ne donnent pas droit aux dividendes. Ces derniers seront intégrés\nen report à nouveau dès leurs mises en paiements.\nNotice d’information – Programme de rachat d’actions 18\nIII. EVOLUTION DU COURS BCP DEPUIS JANVIER 2023\nEvolution du cours de bourse de BCP entre le 2 janvier 2023 et le 30 avril 2024\n350 200\n180\n300\n160\n250 140\n200 120\n100\n150 80\n100 60\n40\n50\n20\n0 0\nVolumes Cours de clôture\nSource : Bourse de Casablanca\nL’analyse de l’évolution du cours de la BCP durant la période d’observation fait ressortir les tendances\nprincipales suivantes :\n Hausse progressive du cours moyen pondéré entre janvier 2023 et mars 2023 passant de\n213,1 MAD à 234,7 MAD\n Légère baisse ponctuelle du cours moyen pondéré en avril 2023 pour se fixer à 230,6 MAD,\nsoit un repli de 1,7% par rapport à mars 2023\n Le cours moyen pondéré entamera une nouvelle amélioration entre mai 2023 et août 2023 pour\nse situer à 262,2 MAD, avant d’accuser un nouveau recul à 255,0 MAD, en septembre 2023\n En octobre 2023, le CMP augmente à 264,7 MAD, avant de connaître une baisse durant le mois\nde novembre 2023, à 264,5 MAD\n A partir de décembre 2023, le cours moyen pondéré se renforce graduellement pour atteindre\nun maximum de 297,4 MAD en mars 2024, avant de reculer à 292,6 MAD en avril 2024\nCi-dessous un tableau récapitulatif de l’évolution du titre BCP et celle des principaux indices de\nréférence :\nPerformance du titre BCP1 : 28,6%\nPerformance du MASI : 24,4%\nPerformance du MSI 20 : 25,7%\nPerformance de l’indice sectoriel : 29,5%\nLa période étudiée s’étale du 2 janvier 2023 au 30 avril 2024 pour l’ensemble des indices\nSource : Bourse de Casablanca\nSur la période qui s’étale du 2 janvier 2023 au 30 avril 2024, le titre BCP, affiche une performance de\n28,6 %, soit un niveau supérieur à ceux de l’indice du MASI et du MASI20 qui ont enregistré une\ncroissance de 24,4% et 25,7%, respectivement sur la même période. L’indice du secteur bancaire a,\nquant à lui, réalisé une performance de 29,5%, contre 28,6% observé pour le titre BCP.\n1 Performance du titre BCP calculée comme suit : (Cours de clôture au 30 avril 2024 / Cours de clôture au 2 janvier 2023) - 1\nNotice d’information – Programme de rachat d’actions 19\nLe tableau suivant présente la volatilité annualisée du titre BCP, ainsi que sa volatilité relative par\nrapport au MSI 20 et au MASI :\nVolatilité (*) 3 mois 6 mois 12 mois\nBCP 5,49% 7,57% 15,13%\nMSI 20 3,64% 5,28% 10,67%\nVolatilité relative MSI 20 (**) 0,89 0,76 0,87\nMASI 3,25% 4,66% 9,47%\nVolatilité relative MASI (***) 0,97 0,85 0,97\n(*) : Produit de l’écart-type des performances quotidiennes par la racine carrée du nombre de séances durant l’année\n(**) : Rapport entre la covariance du rendement du titre BCP et le rendement du MSI 20 divisé par la variance du rendement du MSI 20\n(***) Rapport entre la covariance du rendement du titre BCP et le rendement du MASI divisé par la variance du rendement du MASI\nSource : Bourse de Casablanca et UCF\nLa volatilité sur 12 mois se situe à 15,13%, la deuxième plus faible du secteur, après celle enregistrée\npar Attijariwafa Bank (voir tableau ci-dessous). Celle-ci est en baisse par rapport à l’année d’avant où\nelle représentait 23,10%.\nComportement de la volatilité des titres des opérateurs du secteur bancaire au 30 avril 2024 :\nVolatilité 3 mois 6 mois 12 mois\nAttijariwafa Bank 5,01% 6,59% 13,77%\nBOA 10,40% 13,58% 19,33%\nBMCI 14,22% 25,01% 32,38%\nCDM 12,11% 20,55% 25,65%\nCIH Bank 10,43% 21,34% 27,55%\nBCP 5,49% 7,57% 15,13%\nIndice Secteur Bancaire 4,38% 5,88% 11,55%\nSource : Bourse de Casablanca\nNotice d’information – Programme de rachat d’actions 20\nIV. PROGRAMMES DE RACHAT PRECEDENTS\nEn 2017, la BCP a mis en œuvre un 5ème programme de rachat de ses propres actions par des\ninterventions en contre-tendance des variations excessives du cours sur le marché, que ce soit à la hausse\ncomme à la baisse. Les caractéristiques dudit programme se présentent comme suit :\nTitres concernés : Actions BCP\nNombre maximum d’actions à détenir : 9 112 733 actions, soit 5% du capital\nMontant maximum du programme : 3 198 569 283 MAD\nDélai de l’autorisation : 18 mois\nCalendrier de l’opération : Du 4 juillet 2017 au 3 janvier 2019\nMode de financement du programme : Par la trésorerie\nFourchette d’intervention :\n Prix minimum unitaire de vente : 189,00 MAD\n Prix maximum unitaire d’achat : 351,00 MAD\nA l’issue du programme de rachat, la BCP détenait directement 64 787 actions représentant 0,036% de\nson capital social.\nPar ailleurs, la BCP détenait indirectement 70 286 actions représentant 0,04% de son capital social à\ntravers la société MEDIAFINANCE.\nAu cours de ce programme de rachat arrivé à échéance le 3 janvier 2019, la BCP a acheté\n181 250 titres et a vendu 148 293 titres.\nLa BCP a adossé à son 5ème programme de rachat un contrat de liquidité, répondant aux modalités de\nl’article I.4.18 ter de la circulaire de l’AMMC, dans la limite de la fourchette de prix autorisée et ce,\nselon les modalités suivantes :\nTitres concernés : Actions BCP\nNombre maximum d’actions à détenir : 1 822 547 actions, soit 1% du capital\nMontant maximum du programme : 639 713 997 MAD\nDélai de l’autorisation : 18 mois\nCalendrier de l’opération : Du 4 juillet 2017 au 3 janvier 2019\nMode de financement du programme : Par la trésorerie\nFourchette d’intervention :\n Prix minimum unitaire de vente : 189,00 MAD\n Prix maximum unitaire d’achat : 351,00 MAD\nA noter que lors de ce contrat de liquidité ayant pris fin le 3 janvier 2019, la BCP a acheté et vendu\n644 343 titres.\nEn 2019, la BCP a mis en œuvre le 6eme programme afin de favoriser la liquidité des titres. Les\ncaractéristiques dudit programme se présentent comme suit :\nTitres concernés : Actions BCP\nNombre maximum d’actions à détenir : 9 112 733 actions, soit 5% du capital\nMontant maximum du programme : 3 198 569 283 MAD\nDélai de l’autorisation : 18 mois\nCalendrier de l’opération : Du 8 juillet 2019 au 7 janvier 2021\nMode de financement du programme : Par la trésorerie\nFourchette d’intervention :\n Prix minimum unitaire de vente : 189,00 MAD\n Prix maximum unitaire d’achat : 351,00 MAD\nNotice d’information – Programme de rachat d’actions 21\nA l’issue du programme de rachat, la BCP détenait directement 7 978 actions représentant 0,0039% de\nson capital social.\nPar ailleurs, la BCP disposait indirectement de 248 286 actions représentant 0,12% de son capital social\npar le biais de la société MEDIAFINANCE.\nA noter que lors de ce programme de rachat ayant pris fin le 7 janvier 2021, la BCP a acheté\n217 197 titres et a vendu 274 006 titres.\nLa BCP a adossé à son 6ème programme de rachat un contrat de liquidité, répondant aux modalités de\nl’article I.4.18 ter de la circulaire de l’AMMC, dans la limite de la fourchette de prix autorisée et ce,\nselon les modalités suivantes :\nTitres concernés : Actions BCP\nNombre maximum d’actions à détenir : 1 822 547 actions, soit 1% du capital\nMontant maximum du programme : 639 713 997 MAD\nDélai de l’autorisation : 18 mois\nCalendrier de l’opération : Du 8 juillet 2019 au 7 janvier 2021\nMode de financement du programme : Par la trésorerie\nPrix d’intervention (hors frais d’achat et de vente)\n Prix minimum unitaire de vente : 189,00 MAD\n Prix maximum unitaire d’achat : 351,00 MAD\nA noter qu’à l’échéance de ce contrat de liquidité le 7 janvier 2021, la BCP aurait acheté et vendu\n613 030 titres.\nEn 2021, la BCP a mis en œuvre le 7ème programme de rachat de ses propres actions afin de favoriser la\nliquidité des titres et de céder une partie de ses titres au management de la BCP. Les caractéristiques\ndudit programme se présentent comme suit :\nTitres concernés : Actions BCP\nNombre maximum d’actions à détenir : 10 112 733 actions, soit 5% du capital\nMontant maximum du programme : 3 549 569 283 MAD\nDélai de l’autorisation : 18 mois\nCalendrier de l’opération : Du 5 juillet 2021 au 4 janvier 2023\nMode de financement du programme : Par la trésorerie\nFourchette d’intervention :\n Prix minimum unitaire de vente : 189,00 MAD\n Prix maximum unitaire d’achat : 351,00 MAD\nA noter que ce programme de rachat n’a fait l’objet d’aucune opération d’acquisition ou de cession\nd’actions.\nLa BCP a adossé à son 7ème programme de rachat un contrat de liquidité, répondant aux modalités de\nl’article I.4.18 ter de la circulaire de l’AMMC, dans la limite de la fourchette de prix autorisée et ce,\nselon les modalités suivantes :\nTitres concernés : Actions BCP\nNombre maximum d’actions à détenir : 2 022 547 actions, soit 1% du capital\nMontant maximum du programme : 709 913 997 MAD\nDélai de l’autorisation : 18 mois\nCalendrier de l’opération : Du 5 juillet 2021 au 4 janvier 2023\nMode de financement du programme : Par la trésorerie\nPrix d’intervention (hors frais d’achat et de vente)\n Prix minimum unitaire de vente : 189,00 MAD\n Prix maximum unitaire d’achat : 351,00 MAD\nNotice d’information – Programme de rachat d’actions 22\nA noter qu’au 31 mai 2022, la BCP a acheté 393 020 titres et vendu 266 503 titres. Elle détient à la\nmême date 126 517 actions soit 0,062% de son capital social.\nPar ailleurs, le programme ayant prévu la cession d’une partie des titres aux management de la BCP n’a\nfait l’objet d’aucune opération de cette nature.\nEn 2022, la BCP a mis en œuvre un 8ème programme de rachat afin de favoriser la liquidité des titres.\nLes caractéristiques dudit programme se présentent comme suit :\nTitres concernés : Actions BCP\nNombre maximum d’actions à détenir : 10 165 623 actions, soit 5% du capital\nMontant maximum du programme : 3 568 133 673 MAD\nDélai de l’autorisation : 18 mois\nCalendrier de l’opération : Du 15 juillet 2022 au 15 janvier 2024*\nMode de financement du programme : Par la trésorerie\nFourchette d’intervention :\n Prix minimum unitaire de vente : 189,00 MAD\n Prix maximum unitaire d’achat : 351,00 MAD\n(*) Programme abrogé le 10 juillet 2023\nAu 9 juillet 2023, la BCP détenait directement 35 777 actions, soit 0,018% de son capital social, et\n50 790 actions de façon indirecte, par l’intermédiaire de sa filiale BCP2S (anciennement\nMEDIAFINANCE), soit 0,025% du capital social.\nA noter que lors de ce programme de rachat, ayant été abrogé à la date du 10 juillet 2023, la BCP a\nprocédé au rachat de 185 545 titres et à la vente de 149 768 titres.\nLa BCP a adossé à son 8ème programme de rachat un contrat de liquidité, répondant aux modalités de\nl’article I.4.18 ter de la circulaire de l’AMMC, dans la limite de la fourchette de prix autorisée et ce,\nselon les modalités suivantes :\nTitres concernés : Actions BCP\nNombre maximum d’actions à détenir : 2 033 124 actions, soit 1% du capital\nMontant maximum du programme : 713 626 524 MAD\nDélai de l’autorisation : 18 mois\nCalendrier de l’opération : Du 15 juillet 2022 au 15 janvier 2024\nMode de financement du programme : Par la trésorerie\nPrix d’intervention (hors frais d’achat et de vente)\n Prix minimum unitaire de vente : 189,00 MAD\n Prix maximum unitaire d’achat : 351,00 MAD\nA noter qu’au 9 juillet 2023, la BCP a acheté et vendu 1 356 936 titres. Elle ne détient directement\naucune action de son capital social, dans le cadre du contrat de liquidité et 105 995 titres à travers sa\nfiliale BCP2S (anciennement MEDIAFINANCE), soit 0,052% du capital social.\nEn 2023, la BCP a mis en œuvre un 9eme programme de rachat de ses propres actions afin de favoriser\nla liquidité des titres. Les caractéristiques dudit programme se présentent comme suit :\nNotice d’information – Programme de rachat d’actions 23\nTitres concernés : Actions BCP\nNombre maximum d’actions à détenir : 10 165 623 actions, soit 5% du capital\nMontant maximum du programme : 3 009 024 408 MAD\nDélai de l’autorisation : 18 mois\nCalendrier de l’opération : Du 10 juillet 2023 au 09 janvier 2025*\nMode de financement du programme : Par la trésorerie\nFourchette d’intervention :\n Prix minimum unitaire de vente : 159,00 MAD\n Prix maximum unitaire d’achat : 296,00 MAD\n(*) Programme devant être abrogé le 15 juillet 2024\nAu 03 juin 2024, la BCP détenait directement 207 817 actions, soit 0,102% de son capital social, et\naucune action de façon indirecte, par l’intermédiaire de sa filiale BCP2S (anciennement\nMEDIAFINANCE). A cette date, la BCP a procédé au rachat de 551 510 titres et à la vente de 379 470\ntitres.\nA noter que ce programme de rachat sera abrogé à la date d’entrée du nouveau programme de rachat.\nLa BCP a adossé à son 9ème programme de rachat un contrat de liquidité, répondant aux modalités de\nl’article I.4.18 ter de la circulaire de l’AMMC, dans la limite de la fourchette de prix autorisée et ce,\nselon les modalités suivantes :\nTitres concernés : Actions BCP\nNombre maximum d’actions à détenir : 2 033 124 actions, soit 1% du capital\nMontant maximum du programme : 601 804 704 MAD\nDélai de l’autorisation : 18 mois\nCalendrier de l’opération : Du 10 juillet 2023 au 09 janvier 2025\nMode de financement du programme : Par la trésorerie\nPrix d’intervention (hors frais d’achat et de vente)\n Prix minimum unitaire de vente : 159,00 MAD\n Prix maximum unitaire d’achat : 296,00 MAD\nA noter qu’au 03 juin 2024, la BCP a acheté 2 752 091 titres et vendu 1 988 293 titres. Elle détient à la\nmême date 763 798 actions soit 0,376% de son capital social.\nNotice d’information – Programme de rachat d’actions 24\nTableau récapitulatif des programmes précédents1\n(*) Programme ayant été abrogé au 06/06/2022\n(**) Programme ayant été abrogé au 10/07/2023\n(***) Programme devant être abrogé à la date de mise en place du nouveau programme\n(****) (Cours de clôture date fin du programme - CMP de la période) * stock fin\n1 Tableau n’incluant pas les réalisations des contrats de liquidité et de cession des titres au Management\nNotice d’information – Programme de rachat d’actions 25\nD\nD\nF\nP\nP\nN\nP\nM\nC\nC\nC\nT\nV\nV\nV\nN\nN\nS\nS\n%\nP\nC\nu ré e d u p ro g ra m m e\né b u t d u p ro g ra m m e\nin d u p ro g ra m m e\nrix m a x im u m d ’A c h a t\nrix m in im u m d e V e n te\no m b re d 'a c tio n s\no u rc e n ta g e d u C a p ita l\no n ta n t m a x im a l à e n g a g e r\no u rs le p lu s h a u t (in tra -s é a n c e )\no u rs le p lu s b a s (in tra -s é a n c e )\no u rs m o y e n p o n d é ré\na u x d e c o ta tio n\no la tilité 3 m o is\no la tilité 1 2 m o is\no la tilité p é rio d e\nb a c tio n s a c h e té e s\nb a c tio n s v e n d u e s\nto c k d é b u t\nto c k fin\nc a p ita l d é te n u\nlu s /m o in s -v a lu e ré a lis é e d u p ro g ra m m\nu m u l d e s p lu s / m o in s -v a lu e la te n te (*\ne\n* * * )\n3\nR é c a p it u la t if d\nP r o g r a m m e V\n1 8 m o is\n0 4 /0 7 /2 0 1 7\n0 3 /0 1 /2 0 1 9\n3 5 1 M A D\n1 8 9 M A D\n9 1 1 2 7 3 3\n5 ,0 %\n1 9 8 5 6 9 K M A D\n3 1 2 ,0 0\n2 5 8 ,5 0\n2 8 6 ,3 2\n9 8 ,6 6 %\n8 ,3 8 %\n1 4 ,5 1 %\n1 9 ,9 5 %\n1 8 1 2 5 0\n1 5 0 1 9 1\n3 3 7 2 8\n6 4 7 8 7\n0 ,0 4 0 %\n1 2 4 6 9 6 6\n-6 0 3 7 8 8\ne s p r o g r a m m e s d e\nP r o g r a m m e\n1 8 m o is\n0 8 /0 7 /2 0 1\n0 7 /0 1 /2 0 2\n3 5 1 M A D\n1 8 9 M A D\n9 1 1 2 7 3 3\n5 ,0 %\n3 1 9 8 5 6 9 K M\n2 7 7 ,5 0\n1 9 0 ,0 0\n2 5 1 ,1 5\n9 8 ,6 6 %\n4 ,6 3 %\n2 4 ,6 5 %\n2 7 ,1 9 %\n2 1 5 4 2 0\n2 6 5 7 8 3\n6 4 7 8 7\n1 4 4 2 4\n0 ,0 3 9 %\n1 2 6 7 6 1 9\n-5 9 8 8 0\nr\nV\n9\n1\nA\na c\nI\nD\nh a t p r é c é d e n t s\nP r o g r a m m e V\n1 8 m o is\n0 5 /0 7 /2 0 2 1\n0 4 /0 1 /2 0 2 3\n3 5 1 M A D\n1 8 9 M A D\n1 0 1 1 2 7 3 3\n5 ,0 %\n3 5 4 9 5 6 9 K M\n2 9 5 ,0 0\n2 4 5 ,0 0\n2 7 2 ,1 4\n9 9 ,2 2 %\n5 ,1 2 %\n1 6 ,1 0 %\n1 6 ,3 2 %\n0\n0\n1 4 4 2 4\n0\n0 ,0 0 0 %\n0\n0\nI\nA\nI *\nD\nP r o\n3 5 6\ng r a m m e V I I\n1 8 m o is\n1 5 /0 7 /2 0 2 2\n1 5 /0 1 /2 0 2 4\n3 5 1 M A D\n1 8 9 M A D\n1 0 1 6 5 6 2 3\n5 ,0 %\n8 1 3 3 6 7 3 K M\n2 6 4 ,0 0\n1 9 4 ,6 0\n2 3 6 ,4 2\n9 9 ,6 0 %\n7 ,2 1 %\n2 3 ,1 3 %\n2 2 ,8 2 %\n1 8 5 5 4 5\n1 4 9 7 6 8\n0\n3 5 7 7 7\n0 ,0 1 8 %\n2 4 0 2 0 2 7\n8 8 2 9 7 5\nI *\nA\n*\nD\nP\n3\nr o g r a m m e I X\n1 8 m o is\n1 0 /0 7 /2 0 2 3\n0 9 /0 1 /2 0 2 5\n2 9 6 M A D\n1 5 9 M A D\n1 0 1 6 5 6 2 3\n5 ,0 %\n0 0 9 0 2 4 4 0 8 K\n3 0 9 ,0 0\n2 5 2 ,0 0\n2 7 7 ,4 1\n1 0 0 ,0 0 %\n1 0 ,0 7 %\nn .a\n1 2 ,8 8 %\n5 5 1 5 1 0\n3 7 9 4 7 0\n3 5 7 7 7\n2 0 7 8 1 7\n0 ,1 0 2 %\n4 6 4 8 2 6 6\n3 0 3 1 1 3 8\n* *\nD\n*\nH\nV. ANNEXES\nANNEXE 1 MANDAT DE GESTION\nNotice d’information – Programme de rachat d’actions 26\nNotice d’information – Programme de rachat d’actions 27\nNotice d’information – Programme de rachat d’actions 28\nNotice d’information – Programme de rachat d’actions 29\nNotice d’information – Programme de rachat d’actions 30\nNotice d’information – Programme de rachat d’actions 31\nNotice d’information – Programme de rachat d’actions 32\nNotice d’information – Programme de rachat d’actions 33\nNotice d’information – Programme de rachat d’actions 34\nANNEXE 2 : PROJET DE RESOLUTIONS SOUMIS A L’ASSEMBLEE GENERALE\nRESOLUTION RELATIVE AU PROGRAMME DE RACHAT\nL’Assemblée Générale,\n agissant au terme des dispositions légales et agissant aux termes des articles 279 et 281 de la loi\nn°17-95 relative aux sociétés anonymes, telle que modifiée, complétée et amendée, du décret\nn°2-02-556 du 24 février 2003 tel que modifié et complété par le décret n° 2-10-44 du 30 juin\n2010 fixant les formes et conditions dans lesquelles peuvent s'effectuer les rachats en bourse\npar les sociétés anonymes de leurs propres actions, et de la circulaire de l’AMMC,\n autorise le projet de programme de rachat de 5% du capital social, soit\n10 165 623 actions, tel qu’arrêté par le Conseil d’Administration réuni en date du 13 mars 2024\nselon les modalités suivantes :\nTitres concernés : Actions BCP\nNombre maximum d’actions à détenir : 10 165 623 actions, soit 5% du capital\nMontant maximum du programme : 3 801 943 002 MAD\nDélai de l’autorisation : 18 mois\nCalendrier de l’opération : Du 15 juillet 2024 au 15 janvier 2026\nMode de financement du programme : Par la trésorerie\nPrix d’intervention (hors frais d’achat et de vente)\n- Prix minimum de vente : 201 MAD\n- Prix maximum d’achat : 374 MAD\nL’Assemblée Générale entérine la proposition du Conseil d’Administration de permettre à la BCP de\nmettre en place un contrat de liquidité adossé au programme de rachat, dans la limite de la fourchette de\nprix autorisée et ce, selon les modalités suivantes :\nTitres concernés : Actions BCP\nNombre maximum d’actions à détenir : 2 033 124 actions, soit 1% du capital\nMontant maximum du contrat : 760 388 376 MAD\nDélai de l’autorisation : 18 mois\nCalendrier de l’opération : Du 15 juillet 2024 au 15 janvier 2026\nMode de financement du programme : Par la trésorerie\nPrix d’intervention (hors frais d’achat et de vente)\n- Prix minimum de vente : 201 MAD\n- Prix maximum d’achat : 374 MAD\nL’Assemblée Générale Ordinaire donne les pouvoirs les plus étendus au Conseil d’Administration et à\nson Président à l’effet de procéder, à l’exécution dudit programme de rachat et du contrat de liquidité\ndans les conditions de date qu’il juge opportun et dans les limites des caractéristiques déclinées en haut.\nNotice d’information – Programme de rachat d’actions 35",
    "tables": [
        [
            {
                "Titres concernés Actions BCP": "Calendrier de l’opération Du 15 juillet 2024 au 15 janvier 2026"
            },
            {
                "Titres concernés Actions BCP": "10 165 623 actions, soit 5% du capital, y compris\nNombre maximum d’actions à détenir\nles actions visées par le contrat de liquidité"
            },
            {
                "Titres concernés Actions BCP": "Montant maximum du programme 3 801 943 002 MAD"
            },
            {
                "Titres concernés Actions BCP": "Délai de l’autorisation 18 mois"
            },
            {
                "Titres concernés Actions BCP": "Mode de financement du programme : Par la trésorerie"
            },
            {
                "Titres concernés Actions BCP": "Prix d’intervention (hors frais d’achat et de vente)"
            },
            {
                "Titres concernés Actions BCP": " Prix minimum unitaire de vente 201,00 MAD"
            },
            {
                "Titres concernés Actions BCP": " Prix maximum unitaire d’achat 374,00 MAD"
            }
        ],
        [
            {
                "Titres concernés Actions BCP": "Calendrier de l’opération Du 15 juillet 2024 au 15 janvier 2026"
            },
            {
                "Titres concernés Actions BCP": "Nombre maximum d’actions à détenir 2 033 124 actions, soit 1% du capital"
            },
            {
                "Titres concernés Actions BCP": "Montant maximum du programme 760 388 376 MAD"
            },
            {
                "Titres concernés Actions BCP": "Délai de l’autorisation 18 mois"
            },
            {
                "Titres concernés Actions BCP": "Mode de financement du programme : Par la trésorerie"
            },
            {
                "Titres concernés Actions BCP": "Prix d’intervention (hors frais d’achat et de vente)"
            },
            {
                "Titres concernés Actions BCP": " Prix minimum unitaire de vente 201,00 MAD"
            },
            {
                "Titres concernés Actions BCP": " Prix maximum unitaire d’achat 374,00 MAD"
            }
        ],
        [
            {
                "Prix minimum unitaire de vente :": "Prix maximum unitaire d’achat :",
                "201,00 MAD": "374,00 MAD"
            }
        ],
        [
            {
                "Détail des réserves et primes\nliées au capital (en MMAD)": "Autres réserves",
                "Au 31 décembre 2023(1)": "11 002",
                "Au 31 mars 2024(1)": "11 002"
            },
            {
                "Détail des réserves et primes\nliées au capital (en MMAD)": "Primes d’émission, de fusion\net d’apport",
                "Au 31 décembre 2023(1)": "16 104",
                "Au 31 mars 2024(1)": "16 104"
            }
        ],
        [
            {
                "": "",
                "Séance": "",
                "Volume en MAD": "",
                "QP sur volumes globaux1": "4,04%"
            },
            {
                "": "",
                "Séance": "",
                "Volume en MAD": "",
                "QP sur volumes globaux1": "3,96%"
            },
            {
                "": "",
                "Séance": "",
                "Volume en MAD": "",
                "QP sur volumes globaux1": "3,58%"
            },
            {
                "": "",
                "Séance": "",
                "Volume en MAD": "",
                "QP sur volumes globaux1": "3,57%"
            },
            {
                "": "",
                "Séance": "",
                "Volume en MAD": "",
                "QP sur volumes globaux1": "2,59%"
            },
            {
                "": "",
                "Séance": "",
                "Volume en MAD": "",
                "QP sur volumes globaux1": "2,03%"
            },
            {
                "": "",
                "Séance": "",
                "Volume en MAD": "",
                "QP sur volumes globaux1": "1,63%"
            },
            {
                "": "",
                "Séance": "",
                "Volume en MAD": "",
                "QP sur volumes globaux1": "1,62%"
            },
            {
                "": "",
                "Séance": "",
                "Volume en MAD": "",
                "QP sur volumes globaux1": "1,60%"
            },
            {
                "": "",
                "Séance": "",
                "Volume en MAD": "",
                "QP sur volumes globaux1": "1,53%"
            }
        ],
        [
            {
                "Mois": "",
                "Cours moyen pondéré en\nMAD": "",
                "Plus haut en MAD (*)": "",
                "Plus bas en MAD(*)": "",
                "null": "",
                "Transactions en\nnombre de titres": "",
                "": "",
                "Transactions": "en capitaux en"
            },
            {
                "Mois": "",
                "Cours moyen pondéré en\nMAD": "",
                "Plus haut en MAD (*)": "",
                "Plus bas en MAD(*)": "",
                "null": "",
                "Transactions en\nnombre de titres": "",
                "": "",
                "Transactions": "MAD"
            },
            {
                "Mois": "janv-23",
                "Cours moyen pondéré en\nMAD": "213,1",
                "Plus haut en MAD (*)": "227,00",
                "Plus bas en MAD(*)": "",
                "null": "194,60",
                "Transactions en\nnombre de titres": "425 674",
                "": "",
                "Transactions": ""
            },
            {
                "Mois": "févr-23",
                "Cours moyen pondéré en\nMAD": "229,7",
                "Plus haut en MAD (*)": "242,00",
                "Plus bas en MAD(*)": "",
                "null": "218,00",
                "Transactions en\nnombre de titres": "1 024 526",
                "": "",
                "Transactions": ""
            },
            {
                "Mois": "mars-23",
                "Cours moyen pondéré en\nMAD": "234,7",
                "Plus haut en MAD (*)": "239,00",
                "Plus bas en MAD(*)": "",
                "null": "227,00",
                "Transactions en\nnombre de titres": "559 198",
                "": "",
                "Transactions": ""
            },
            {
                "Mois": "avr-23",
                "Cours moyen pondéré en\nMAD": "230,6",
                "Plus haut en MAD (*)": "235,95",
                "Plus bas en MAD(*)": "",
                "null": "227,50",
                "Transactions en\nnombre de titres": "406 300",
                "": "",
                "Transactions": ""
            },
            {
                "Mois": "mai-23",
                "Cours moyen pondéré en\nMAD": "232,7",
                "Plus haut en MAD (*)": "236,00",
                "Plus bas en MAD(*)": "",
                "null": "227,00",
                "Transactions en\nnombre de titres": "844 687",
                "": "",
                "Transactions": ""
            },
            {
                "Mois": "juin-23",
                "Cours moyen pondéré en\nMAD": "250,6",
                "Plus haut en MAD (*)": "264,00",
                "Plus bas en MAD(*)": "",
                "null": "234,05",
                "Transactions en\nnombre de titres": "1 569 572",
                "": "",
                "Transactions": ""
            },
            {
                "Mois": "juil-23",
                "Cours moyen pondéré en\nMAD": "261,7",
                "Plus haut en MAD (*)": "266,00",
                "Plus bas en MAD(*)": "",
                "null": "253,15",
                "Transactions en\nnombre de titres": "1 067 293",
                "": "",
                "Transactions": ""
            },
            {
                "Mois": "août-23",
                "Cours moyen pondéré en\nMAD": "262,2",
                "Plus haut en MAD (*)": "265,00",
                "Plus bas en MAD(*)": "",
                "null": "254,10",
                "Transactions en\nnombre de titres": "1 271 466",
                "": "",
                "Transactions": ""
            },
            {
                "Mois": "sept-23",
                "Cours moyen pondéré en\nMAD": "255,0",
                "Plus haut en MAD (*)": "260,00",
                "Plus bas en MAD(*)": "",
                "null": "252,00",
                "Transactions en\nnombre de titres": "274 176",
                "": "",
                "Transactions": ""
            },
            {
                "Mois": "oct-23",
                "Cours moyen pondéré en\nMAD": "264,7",
                "Plus haut en MAD (*)": "270,00",
                "Plus bas en MAD(*)": "",
                "null": "252,00",
                "Transactions en\nnombre de titres": "877 908",
                "": "",
                "Transactions": ""
            },
            {
                "Mois": "nov-23",
                "Cours moyen pondéré en\nMAD": "264,5",
                "Plus haut en MAD (*)": "268,00",
                "Plus bas en MAD(*)": "",
                "null": "259,00",
                "Transactions en\nnombre de titres": "1 544 105",
                "": "",
                "Transactions": ""
            },
            {
                "Mois": "déc-23",
                "Cours moyen pondéré en\nMAD": "273,5",
                "Plus haut en MAD (*)": "277,05",
                "Plus bas en MAD(*)": "",
                "null": "266,00",
                "Transactions en\nnombre de titres": "1 458 619",
                "": "",
                "Transactions": ""
            },
            {
                "Mois": "janv-24",
                "Cours moyen pondéré en\nMAD": "287,3",
                "Plus haut en MAD (*)": "295,05",
                "Plus bas en MAD(*)": "",
                "null": "275,00",
                "Transactions en\nnombre de titres": "1 252 168",
                "": "",
                "Transactions": ""
            },
            {
                "Mois": "févr-24",
                "Cours moyen pondéré en\nMAD": "296,2",
                "Plus haut en MAD (*)": "309,00",
                "Plus bas en MAD(*)": "",
                "null": "286,00",
                "Transactions en\nnombre de titres": "1 584 146",
                "": "",
                "Transactions": ""
            },
            {
                "Mois": "mars-24",
                "Cours moyen pondéré en\nMAD": "297,4",
                "Plus haut en MAD (*)": "302,00",
                "Plus bas en MAD(*)": "",
                "null": "292,00",
                "Transactions en\nnombre de titres": "507 325",
                "": "",
                "Transactions": ""
            },
            {
                "Mois": "avr-24",
                "Cours moyen pondéré en\nMAD": "292,6",
                "Plus haut en MAD (*)": "296,00",
                "Plus bas en MAD(*)": "",
                "null": "290,00",
                "Transactions en\nnombre de titres": "1 552 869",
                "": "",
                "Transactions": ""
            }
        ],
        [
            {
                "Cours moyen pondéré en": "MAD"
            }
        ],
        [
            {
                "Transactions en": "nombre de titres"
            }
        ],
        [],
        [],
        [
            {
                "Titres concernés : Actions BCP": "Nombre maximum d’actions à détenir : 9 112 733 actions, soit 5% du capital"
            },
            {
                "Titres concernés : Actions BCP": "Montant maximum du programme : 3 198 569 283 MAD"
            },
            {
                "Titres concernés : Actions BCP": "Délai de l’autorisation : 18 mois"
            },
            {
                "Titres concernés : Actions BCP": "Calendrier de l’opération : Du 4 juillet 2017 au 3 janvier 2019"
            },
            {
                "Titres concernés : Actions BCP": "Mode de financement du programme : Par la trésorerie"
            },
            {
                "Titres concernés : Actions BCP": "Fourchette d’intervention :"
            },
            {
                "Titres concernés : Actions BCP": " Prix minimum unitaire de vente : 189,00 MAD\n Prix maximum unitaire d’achat : 351,00 MAD"
            }
        ],
        [
            {
                "Titres concernés : Actions BCP": "Nombre maximum d’actions à détenir : 1 822 547 actions, soit 1% du capital"
            },
            {
                "Titres concernés : Actions BCP": "Montant maximum du programme : 639 713 997 MAD"
            },
            {
                "Titres concernés : Actions BCP": "Délai de l’autorisation : 18 mois"
            },
            {
                "Titres concernés : Actions BCP": "Calendrier de l’opération : Du 4 juillet 2017 au 3 janvier 2019"
            },
            {
                "Titres concernés : Actions BCP": "Mode de financement du programme : Par la trésorerie"
            },
            {
                "Titres concernés : Actions BCP": "Fourchette d’intervention :"
            },
            {
                "Titres concernés : Actions BCP": " Prix minimum unitaire de vente : 189,00 MAD\n Prix maximum unitaire d’achat : 351,00 MAD"
            }
        ],
        [
            {
                "Titres concernés : Actions BCP": "Nombre maximum d’actions à détenir : 9 112 733 actions, soit 5% du capital"
            },
            {
                "Titres concernés : Actions BCP": "Montant maximum du programme : 3 198 569 283 MAD"
            },
            {
                "Titres concernés : Actions BCP": "Délai de l’autorisation : 18 mois"
            },
            {
                "Titres concernés : Actions BCP": "Calendrier de l’opération : Du 8 juillet 2019 au 7 janvier 2021"
            },
            {
                "Titres concernés : Actions BCP": "Mode de financement du programme : Par la trésorerie"
            },
            {
                "Titres concernés : Actions BCP": "Fourchette d’intervention :"
            },
            {
                "Titres concernés : Actions BCP": " Prix minimum unitaire de vente : 189,00 MAD\n Prix maximum unitaire d’achat : 351,00 MAD"
            }
        ],
        [
            {
                "Titres concernés : Actions BCP": "Nombre maximum d’actions à détenir : 1 822 547 actions, soit 1% du capital"
            },
            {
                "Titres concernés : Actions BCP": "Montant maximum du programme : 639 713 997 MAD"
            },
            {
                "Titres concernés : Actions BCP": "Délai de l’autorisation : 18 mois"
            },
            {
                "Titres concernés : Actions BCP": "Calendrier de l’opération : Du 8 juillet 2019 au 7 janvier 2021"
            },
            {
                "Titres concernés : Actions BCP": "Mode de financement du programme : Par la trésorerie"
            },
            {
                "Titres concernés : Actions BCP": "Prix d’intervention (hors frais d’achat et de vente)"
            },
            {
                "Titres concernés : Actions BCP": " Prix minimum unitaire de vente : 189,00 MAD\n Prix maximum unitaire d’achat : 351,00 MAD"
            }
        ],
        [
            {
                "Titres concernés : Actions BCP": "Nombre maximum d’actions à détenir : 10 112 733 actions, soit 5% du capital"
            },
            {
                "Titres concernés : Actions BCP": "Montant maximum du programme : 3 549 569 283 MAD"
            },
            {
                "Titres concernés : Actions BCP": "Délai de l’autorisation : 18 mois"
            },
            {
                "Titres concernés : Actions BCP": "Calendrier de l’opération : Du 5 juillet 2021 au 4 janvier 2023"
            },
            {
                "Titres concernés : Actions BCP": "Mode de financement du programme : Par la trésorerie"
            },
            {
                "Titres concernés : Actions BCP": "Fourchette d’intervention :"
            },
            {
                "Titres concernés : Actions BCP": " Prix minimum unitaire de vente : 189,00 MAD\n Prix maximum unitaire d’achat : 351,00 MAD"
            }
        ],
        [
            {
                "Titres concernés : Actions BCP": "Nombre maximum d’actions à détenir : 2 022 547 actions, soit 1% du capital"
            },
            {
                "Titres concernés : Actions BCP": "Montant maximum du programme : 709 913 997 MAD"
            },
            {
                "Titres concernés : Actions BCP": "Délai de l’autorisation : 18 mois"
            },
            {
                "Titres concernés : Actions BCP": "Calendrier de l’opération : Du 5 juillet 2021 au 4 janvier 2023"
            },
            {
                "Titres concernés : Actions BCP": "Mode de financement du programme : Par la trésorerie"
            },
            {
                "Titres concernés : Actions BCP": "Prix d’intervention (hors frais d’achat et de vente)"
            },
            {
                "Titres concernés : Actions BCP": " Prix minimum unitaire de vente : 189,00 MAD\n Prix maximum unitaire d’achat : 351,00 MAD"
            }
        ],
        [
            {
                "Titres concernés : Actions BCP": "Nombre maximum d’actions à détenir : 10 165 623 actions, soit 5% du capital"
            },
            {
                "Titres concernés : Actions BCP": "Montant maximum du programme : 3 568 133 673 MAD"
            },
            {
                "Titres concernés : Actions BCP": "Délai de l’autorisation : 18 mois"
            },
            {
                "Titres concernés : Actions BCP": "Calendrier de l’opération : Du 15 juillet 2022 au 15 janvier 2024*"
            },
            {
                "Titres concernés : Actions BCP": "Mode de financement du programme : Par la trésorerie"
            },
            {
                "Titres concernés : Actions BCP": "Fourchette d’intervention :"
            },
            {
                "Titres concernés : Actions BCP": " Prix minimum unitaire de vente : 189,00 MAD\n Prix maximum unitaire d’achat : 351,00 MAD"
            }
        ],
        [
            {
                "Titres concernés : Actions BCP": "Nombre maximum d’actions à détenir : 2 033 124 actions, soit 1% du capital"
            },
            {
                "Titres concernés : Actions BCP": "Montant maximum du programme : 713 626 524 MAD"
            },
            {
                "Titres concernés : Actions BCP": "Délai de l’autorisation : 18 mois"
            },
            {
                "Titres concernés : Actions BCP": "Calendrier de l’opération : Du 15 juillet 2022 au 15 janvier 2024"
            },
            {
                "Titres concernés : Actions BCP": "Mode de financement du programme : Par la trésorerie"
            },
            {
                "Titres concernés : Actions BCP": "Prix d’intervention (hors frais d’achat et de vente)"
            },
            {
                "Titres concernés : Actions BCP": " Prix minimum unitaire de vente : 189,00 MAD\n Prix maximum unitaire d’achat : 351,00 MAD"
            }
        ],
        [
            {
                "Titres concernés : Actions BCP": "Nombre maximum d’actions à détenir : 10 165 623 actions, soit 5% du capital"
            },
            {
                "Titres concernés : Actions BCP": "Montant maximum du programme : 3 009 024 408 MAD"
            },
            {
                "Titres concernés : Actions BCP": "Délai de l’autorisation : 18 mois"
            },
            {
                "Titres concernés : Actions BCP": "Calendrier de l’opération : Du 10 juillet 2023 au 09 janvier 2025*"
            },
            {
                "Titres concernés : Actions BCP": "Mode de financement du programme : Par la trésorerie"
            },
            {
                "Titres concernés : Actions BCP": "Fourchette d’intervention :"
            },
            {
                "Titres concernés : Actions BCP": " Prix minimum unitaire de vente : 159,00 MAD\n Prix maximum unitaire d’achat : 296,00 MAD"
            }
        ],
        [
            {
                "Titres concernés : Actions BCP": "Nombre maximum d’actions à détenir : 2 033 124 actions, soit 1% du capital"
            },
            {
                "Titres concernés : Actions BCP": "Montant maximum du programme : 601 804 704 MAD"
            },
            {
                "Titres concernés : Actions BCP": "Délai de l’autorisation : 18 mois"
            },
            {
                "Titres concernés : Actions BCP": "Calendrier de l’opération : Du 10 juillet 2023 au 09 janvier 2025"
            },
            {
                "Titres concernés : Actions BCP": "Mode de financement du programme : Par la trésorerie"
            },
            {
                "Titres concernés : Actions BCP": "Prix d’intervention (hors frais d’achat et de vente)"
            },
            {
                "Titres concernés : Actions BCP": " Prix minimum unitaire de vente : 159,00 MAD\n Prix maximum unitaire d’achat : 296,00 MAD"
            }
        ],
        [
            {
                "RESOLUTION RELATIVE AU PROGRAMME DE RACHAT": ""
            }
        ],
        [
            {
                "L’Assemblée Générale Ordinaire donne les pouvoirs les plus étendus au Conseil d’Administration et à": "son Président à l’effet de procéder, à l’exécution dudit programme de rachat et du contrat de liquidité"
            },
            {
                "L’Assemblée Générale Ordinaire donne les pouvoirs les plus étendus au Conseil d’Administration et à": "dans les conditions de date qu’il juge opportun et dans les limites des caractéristiques déclinées en haut."
            }
        ]
    ]
}