{
    "text": "NOTE D’OPERATION\nCIH Bank S.A\nEMISSION D’ACTIONS ORDINAIRES A TRAVERS UNE\nAUGMENTATION DE CAPITAL PAR APPORT EN NUMERAIRE\nSouscription destinée aux actionnaires et aux détenteurs de droits préférentiels de\nsouscription de CIH Bank\nLe visa de l’AMMC porte sur le prospectus composé des documents suivants :\n• La présente Note d’Opération ;\n• Le document de référence de CIH Bank relatif à l’exercice 2023 et au premier trimestre 2024\nenregistré par l’AMMC en date du 28 juin 2024 sous la référence EN/EM/007/2024\nNombre maximal d’actions à émettre : 977 499 actions\nValeur nominale du titre : 100 MAD\nPrime d’émission unitaire : 258 MAD\nPrix de souscription : 358 MAD\nParité de souscription : 9 actions nouvelles pour 281 DPS\nMontant nominal maximal de l’offre : 97 749 900 MAD\nPrime d’émission maximale : 252 194 742 MAD\nMontant maximal de l’offre : 349 944 642 MAD\nPériode de souscription : du 12 juillet 2024 au 19 août 2024 inclus\nConseiller financier & coordinateur Global Organisme chargé de l’enregistrement\nVisa de l’Autorité Marocaine du Marché des Capitaux (AMMC)\nConformément aux dispositions de la circulaire de l’AMMC, prise en application de l’article 5 de la loi n° 44-12 relative à\nl’appel public à l’épargne et aux informations exigées des personnes morales et organismes faisant appel public à l’épargne,\nle prospectus a été visé par l’AMMC en date du 28 juin 2024 sous la référence VI/EM/020/2024. La présente Note\nd’Opération ne constitue qu'une partie du prospectus visé par l'AMMC. Ce dernier est composé des documents suivants :\n▪ La présente Note d’Opération ;\n▪ Le document de référence de CIH Bank relatif à l’exercice 2023 et au premier trimestre 2024 tel qu’enregistré par\nl’AMMC en date du 28 juin 2024 sous la référence EN/EM/007/2024\nAvertissement\nLe visa de l’Autorité Marocaine du Marché des Capitaux (AMMC) porte sur le prospectus composé des\ndocuments suivants :\n• La présente Note d’Opération ;\n• Le document de référence de CIH Bank relatif à l’exercice 2023 et au premier trimestre 2024 enregistré\npar l’AMMC en date du 28 juin 2024 sous la référence EN/EM/007/2024.\nLes investisseurs potentiels sont appelés à prendre connaissance des informations contenues dans l’ensemble des\ndocuments précités avant de prendre leur décision de participation à l’Opération objet de la présente Note\nd’Opération.\nLe visa de l’Autorité Marocaine du Marché des Capitaux (AMMC) n’implique ni approbation de l’opportunité de\nl’Opération ni authentification des informations présentées. Il a été attribué après examen de la pertinence et de\nla cohérence de l’information donnée dans la perspective de l’opération proposée aux investisseurs.\nL’attention des investisseurs potentiels est attirée sur le fait qu’un investissement en instruments financiers\ncomporte des risques.\nL’AMMC ne se prononce pas sur l’opportunité de l’Opération proposée ni sur la qualité de la situation de\nl’émetteur. Le visa de l’AMMC ne constitue pas une garantie contre les risques associés à l’émetteur ou aux titres\nproposés dans le cadre de l’Opération objet du présent prospectus.\nAinsi, l’investisseur doit s’assurer, préalablement à la souscription, de sa bonne compréhension de la nature et des\ncaractéristiques des titres offerts, ainsi que de la maitrise de son exposition aux risques inhérents auxdits titres. A\ncette fin, l’investisseur est appelé à :\n▪ Attentivement prendre connaissance de l’ensemble des documents et informations qui lui sont remis, et\nnotamment celles figurant à la section « Facteurs de risques » ci-après ;\n▪ Consulter, en cas de besoin, tout professionnel compétent en matière d’investissement dans les\ninstruments financiers.\nLe prospectus précité ne s’adresse pas aux personnes dont les lois du lieu de résidence n’autorisent pas la\nparticipation à l’opération proposée. Les personnes en la possession desquelles ledit prospectus viendrait à se\ntrouver, sont invitées à s’informer et à respecter la réglementation dont elles dépendent en matière de participation\nà ce type d’opération.\nChaque établissement collecteur d’ordres ne proposera les instruments financiers objet du prospectus précité qu’en\nconformité avec les lois et règlements en vigueur dans tout pays où il fera une telle offre.\nL’Autorité Marocaine du Marché des Capitaux (AMMC) n’encourt pas de responsabilité du fait du non-respect\nde ces lois ou règlements par un ou les établissements collecteurs d’ordres.\n2\nTable des matières\nAvertissement .......................................................................................................................................... 2\nDéfinition ................................................................................................................................................. 3\nAttestations et coordonnées ..................................................................................................................... 5\nI. Montant global de l’opération...................................................................................................... 11\nII. Instruments financiers offerts ...................................................................................................... 11\nIII. Cadre de l’opération..................................................................................................................... 17\nIV. Objectifs de l’opération ............................................................................................................... 18\nV. Intentions de participation à l’opération ...................................................................................... 18\nVI. Investisseurs visés par l’opération ............................................................................................... 18\nVII. Impacts de l’opération ................................................................................................................. 18\nVIII. Charges liées à l’opération ........................................................................................................... 19\nIX. Commissions facturées aux souscripteurs ................................................................................... 19\nX. Déroulement de l’opération ....................................................................................................... 211\nXI. Modèle de bulletin de souscription ............................................................................................ 277\n3\nPARTIE I. ATTESTATIONS ET COORDONNÉES\n4\nAttestations et coordonnées\nI.1. Le Président du Conseil d’administration\nIdentité\nDénomination ou raison sociale CIH Bank\nReprésentant légal M. Lotfi SEKKAT\nFonction Président Directeur Général\nAdresse 187, avenue Hassan II, Casablanca\nNuméro de téléphone +212 5 22 47 99 00\nNuméro de fax +212 5 22 47 99 09\nAdresse électronique lotfi.sekkat@cihbank.ma\nAttestation du Président du Conseil d’administration relative à l’Augmentation de capital par apport en\nnuméraire de CIH Bank\nLe Président du conseil d'administration atteste qu'il assume la responsabilité des informations contenues dans le\nprospectus composé de la présente Note d’Opération et du document référence de CIH Bank relatif à l’exercice\n2023 et au premier trimestre 2024 tel qu’enregistré par l’AMMC.\nIl atteste que lesdites informations sont conformes à la réalité, et que les documents précités comprennent toutes\nles informations nécessaires aux investisseurs potentiels pour fonder leur jugement sur le patrimoine l’activité, la\nsituation financière, les résultats et les perspectives de CIH Bank. Elles ne comportent pas d'omissions de nature\nà en altérer la portée.\nPar ailleurs, il atteste que les documents précités ont été réexaminés et que l'ensemble des informations qu'ils\ncontiennent demeurent valides et ne nécessitent aucune actualisation ou rectification.\nM. LOTFI SEKKAT\nPrésident Directeur Général\n5\nI.2. Les Commissaires aux comptes\nIdentité\nDénomination ou raison sociale : Deloitte Audit Mazars Audit et Conseil Fidaroc Grant Thornton\nM. Taha FERDAOUS\nReprésentant légal : Hicham BELEMQADEM\n& Abdou Souleye DIOP\nGhali Guessous\nFonction : Associé Associé Associé\nBd Sidi Mohammed Benabdellah Finance City, Tour 33, Avia\nAdresse : Bâtiment C, Ivoire 3, La Marina - Business Center, Bd Moulay 7 Bd. Driss Slaoui Casablanca\nCasablanca Abdellah Cherif, Casablanca\nNuméro de téléphone : +212 5 22 22 47 34 +212 5 22 42 34 25 +212 5 22 54 48 00\nNuméro de fax : +212 5 22 22 47 59 +212 5 22 42 34 00 +212 5 22 29 66 70\nAdresse électronique : h.belemqadem@deloitte.com Taha.Ferdaous@mazars.ma Ghali.Guessous@ma.gt.com\n1er exercice soumis au contrôle des\n2024 2021 2015\nCAC :\nDernière date de renouvellement\n- Juin 2024 2021\ndu mandat :\nAGO appelée à statuer sur l’exercice AGO appelée à statuer sur AGO ayant statué sur\nDate de Fin du mandat actuel :\n2026 l’exercice 2026 l’exercice 2023\nAttestation de concordance des commissaires aux comptes relative aux comptes sociaux et aux états\nfinanciers consolidés en norme IFRS du Crédit Immobilier et Hôtelier pour les exercices clos aux 31\ndécembre 2021, 2022 et 2023 et au trimestre clos au 31 Mars 2023 et 31 Mars 2024.\nNous avons procédé à la vérification des informations comptables et financières contenues dans la présente note\nd'opération en effectuant les diligences nécessaires et compte tenu des dispositions légales et réglementaires en\nvigueur. Nos diligences ont consisté à nous assurer de la concordance desdites informations avec :\n• Les états de synthèse annuels sociaux du Crédit Immobilier et Hôtelier tels qu’audités par les soins des\nco-commissaires aux comptes Mazars Audit et Conseil et Fidaroc Grant Thornton au titre de l’exercice\nclos au 31/12/2021, 31/12/2022 et au 31/12/2023 ;\n• Les états financiers annuels consolidés en normes IFRS du Crédit Immobilier et Hôtelier tels qu’audités\npar les soins des co-commissaires aux comptes Mazars Audit et Conseil et Fidaroc Grant Thornton au\ntitre de l’exercice clos au 31/12/2021, 31/12/2022 et au 31/12/2023 ;\n• Les états de synthèse trimestriels sociaux du Crédit Immobilier et Hôtelier ayant fait l’objet d’un examen\nlimité par nos soins au titre du trimestre clos au 31/03/2024 et par les soins des co-commissaires aux\ncomptes Mazars Audit et Conseil et Fidaroc Grant Thornton au titre du trimestre clos au 31/03/2023 ;\n• Les états financiers trimestriels consolidés en normes IFRS du Crédit Immobilier et Hôtelier ayant fait\nl’objet d’un examen limité par nos soins au titre du trimestre clos au 31/03/2024 et par les soins des co-\ncommissaires aux comptes Mazars Audit et Conseil et Fidaroc Grant Thornton au titre du trimestre clos\nau 31/03/2023 ;\nSur la base des diligences ci-dessus, nous n'avons pas d'observation à formuler sur la concordance des\ninformations comptables et financières fournies dans la présente note d'opération, avec les états de synthèse\nprécisés.\nCasablanca, le 27 juin 2024\nLes commissaires aux comptes\nM. Hicham Belemqadem M. Abdou Souleye DIOP\nAssocié Associé\nDeloitte Audit Forvis Mazars\n6\nI.3. L’Organisme Conseil\nIdentité\nDénomination ou raison sociale CIH Bank\nReprésentant légal M. Younes ZOUBIR\nFonction Directeur Général Délégué\nAdresse 187, avenue Hassan II, Casablanca\nNuméro de téléphone +212 5 22 47 97 91\nNuméro de fax +212 5 22 47 97 89\nAdresse électronique younes.zoubir@cihbank.ma\nAttestation de l’Organisme de Conseil relative à l’Augmentation de capital par apport en numéraire de\nCIH Bank\nLa présente Note d’Opération a été préparée par nos soins et sous notre responsabilité. Elle fait partie du\nprospectus complété par le document référence de CIH Bank relatif à l’exercice 2023 et au premier trimestre 2024\ntel qu’enregistré par l’AMMC.\nNous attestons avoir effectué les diligences nécessaires pour nous assurer de la sincérité des informations\ncontenues dans les documents précités. Ces diligences ont notamment concerné l’analyse de l’environnement\néconomique et financier de CIH Bank à travers :\n▪ Les commentaires, analyses et statistiques fournis par la Direction Générale de CIH Bank ;\n▪ Les procès-verbaux des conseils d’administration et des Assemblées Générales d’Actionnaires de CIH\nBank tenues durant les exercices 2021, 2022, 2023 et de l’exercice en cours jusqu’à la date du visa.\nPar ailleurs, nous attestons avoir procédé au réexamen des documents précités en effectuant les diligences\nnécessaires pour nous assurer que l’ensemble des informations qu’ils contiennent demeurent valides et ne\nnécessitent aucune actualisation ou rectification.\nCompte tenu de ce qui précède, nous attestons avoir mis en œuvre toutes les mesures nécessaires pour garantir\nl’objectivité de notre analyse et la qualité de la mission pour laquelle nous avons été mandatée.\nM. Younes ZOUBIR\nDirecteur Général Délégué\n7\nI.4. Le Conseiller Juridique\nIdentité\nDénomination ou raison sociale RAMID LAW FIRM\nReprésentant légal Mme Zineb Ramid\nFonction Avocat gérant\nAdresse 10, avenue 2 mars, Casablanca\nNuméro de téléphone +212 5 22 20 40 45- +212 6 63 32 14 14\nAdresse électronique zineb.ramid@ramidlf.com\nAttestation du Conseiller Juridique relative à l’Augmentation de capital par apport en numéraire de CIH\nBank\nL’Opération, objet du présent prospectus est conforme aux dispositions statutaires de CIH Bank et à la législation\nmarocaine.\nMme Zineb Ramid\nAvocat Gérant\n8\nI.5. Le Responsable de l’information et de la communication financière\nPour toute information et/ou communication financière, prière de contacter :\nIdentité\nDénomination ou raison sociale CIH Bank\nReprésentant légal M. Nasreddine EL HAOUAT\nFonction Responsable communication financière\nAdresse 187, avenue Hassan II, Casablanca\nNuméro de téléphone +212 522 47 97 65\nAdresse électronique Nasreddine.ElHaouat@cihbank.ma\nI.6. Agence de Notation\nDénomination ou raison sociale Fitch Ratings\nAdresse 30 North Colonnade, London E14 5GN\nNuméro de téléphone +44 20 3530 1969\nAdresse électronique jamal.elmellali@fitchratings.com\n9\nPARTIE II. PRÉSENTATION DE L’OPÉRATION\n10\nI. Montant global de l’opération\nCIH Bank envisage de procéder à une augmentation de capital en numéraire pour un montant maximum de 349\n944 642 dirhams, prime d’émission incluse, à travers l’émission de 977 499 actions nouvelles d’une valeur\nnominale de 100 dirhams par action, avec une prime d’émission de 258 dirhams par action, soit un prix d’émission\nqui s’élève à 358 dirhams par action.\nLa présente opération donnera lieu à une augmentation du capital social de 97 749 900 MAD et à une prime\nd’émission de 252 194 742 MAD.\nII. Instruments financiers offerts\nII.1. Renseignements relatifs aux titres à émettre\nNature des titres Actions CIH toutes de même catégorie entièrement libérées\nForme juridique des titres Actions au porteur, entièrement dématérialisées et admises aux\nopérations de Maroclear\nMontant maximal de l’opération 349 944 642 MAD\nNombre maximal de titres à émettre 977 499 actions\nValeur nominale unitaire 100 MAD\nPrime d’émission unitaire 258 MAD\nPrix de souscription unitaire 358 MAD\nValeur nominale global 97 749 900 MAD\nPrime d’émission maximale 252 194 742 MAD\nPériode de souscription Du 12 juillet 2024 au 19 août 2024 inclus\nDate de jouissance 1er janvier 2024\nLibération des actions nouvelles Les actions nouvelles seront entièrement libérées et libre de tout\nengagement\nCotation des actions nouvelles Les actions issues de la présente augmentation de capital seront\nassimilées aux anciennes actions et seront cotées en 1Ère ligne à la\nBourse de Casablanca\nNégociabilité des titres Les actions, objets du présent prospectus, seront librement\nnégociables à la Bourse de Casablanca\nMode de libération des actions En numéraire\nDroits attachés aux titres Toutes les actions bénéficieront des mêmes droits tant dans la\nrépartition des bénéfices que dans la répartition du boni de\nliquidation. Chaque action donne à son détenteur un droit de vote\naux assemblées générales.\nSecteur d'activité Banques\nLibellé CIH\nTicker CIH\nCode ISIN MA0000011454\nCompartiment Principal A\nLigne de cotation 1ère ligne\nDate de cotation des actions nouvelles 02 septembre 2024\nCycle de négociation Continu\nOrganisme chargé de l’enregistrement CDG Capital Bourse\nde l’opération\n11\nII.2. Caractéristiques des DPS offerts\nModalités d’exercice du DPS Lors de la réalisation de l'augmentation de capital, la souscription aux actions\nnouvelles est destinée aux actionnaires de la société et aux porteurs de droits\npréférentiels de souscription. Par conséquent, ils auront un droit de\nsouscription irréductible sur les actions nouvelles à émettre.\nPour la souscription des actions nouvelles émises dans le cadre de\nl'augmentation de capital, objet du présent prospectus, les droits préférentiels\nde souscription réservés aux actionnaires en application des dispositions de\nl'article 189 de la loi 17-95 sur les sociétés anonymes, telle que modifiée et\ncomplétée, seront maintenus à raison d'un droit préférentiel de souscription\npour une action existante.\nLes titulaires des droits préférentiels de souscription pourront souscrire à titre\nirréductible, à raison 9 actions nouvelles pour 281 droits préférentiels de\nsouscription. Un actionnaire personne physique a renoncé à l’exercice de 93\ndroits préférentiels de souscription.\nChaque actionnaire pourra, s'il le souhaite, renoncer à titre individuel à son\ndroit préférentiel de souscription.\nLes actionnaires auront également un droit de souscription à titre réductible,\nen vue de la répartition des actions non absorbées par l’exercice du droit de\nsouscription à titre irréductible. Cette répartition s’effectuera au prorata de\nleurs parts dans le capital, dans la limite de leurs demandes et sans attribution\nde fraction.\nLes droits préférentiels de souscription ne pourront être exercés qu’à\nconcurrence d’un nombre de droits préférentiels de souscription permettant la\nsouscription d’un nombre entier d’actions nouvelles. Les titulaires de droits\npréférentiels de souscription qui ne posséderaient pas, au titre de leur\nsouscription à titre irréductible, un nombre suffisant de droits préférentiels de\nsouscription pour obtenir un nombre entier d’actions nouvelles, pourront\nprocéder, à l’achat ou à la vente de droits préférentiels de souscription aux\nconditions du marché, lors de la période de souscription.\nLes droits préférentiels de souscription formant rompus pourront être cédés\nou complétés sur le marché pendant la période de souscription.\nLe prix théorique des droits préférentiels de souscription (DPS) est calculé de\nla manière suivante : DPS= (Cours clôture de l'action CIH à la veille de la\ndate du détachement du DPS - Dividende - prix de souscription) * ([nombre\nd'actions nouvelles] / [nombre d'actions anciennes + nombre d'actions\nnouvelles])\nNégociation du DPS Les droits préférentiels de souscription relatifs à la présente augmentation de\ncapital seront librement négociables à la Bourse de Casablanca dans les\nmêmes conditions que l'action CIH elle-même, pendant toute la période de\nsouscription allant du 12 juillet 2024 au 19 août 2024 inclus.\nSort des DPS non exercés Le droit préférentiel de souscription des actionnaires aux actions nouvelles\némises devra être exercé durant la période souscription sous peine de\ndéchéance.\nDate de cotation prévue 12 juillet 2024\nCycle de négociation Fixing\nLibellé DS CIH 9/281 2024\nTicker SCIHC\nEn date du 9 Juillet 2024, La bourse de Casablanca procédera également au détachement de dividende brut relatif\nà l’exercice 2023 (14 Dirhams), à la purge du carnet d’ordre et à l’ajustement du cours de référence de l’action\nCIH BANK.\n12\nII.3. Eléments d’appréciation des termes de l’offre\nII.3.1 Prix des titres offerts\nConformément à l’article 186 de la loi 17-95 sur les sociétés anonymes, telle que modifiée et complétée,\nl’Assemblée Générale Extraordinaire réunie en date du 06 mai 2024 a conféré tous les pouvoirs au Conseil\nd’administration afin de fixer les modalités de l’augmentation de capital par apport en numéraire.\nConformément aux pouvoirs qui lui ont été conférés par l’Assemblée Générale Extraordinaire du 06 mai 2024, le\nConseil d’Administration réuni en date du 16 mai 2024 a fixé le prix de souscription des actions nouvelles à 358\ndirhams par action, prime d’émission comprise.\nA titre indicatif, le prix de souscription présente une décote de 7,5% par rapport au cours de clôture du 15 mai\n2024, soit la veille de la date de tenue du conseil d’administration de CIH Bank.\nII.3.2 Valorisation des titres offerts\na. Méthode des comparables boursiers (présentée à titre indicatif)\nRappel de la méthodologie\nLa méthode des comparables boursiers est une approche analogique fondée sur les paramètres de rentabilité de la\nsociété.\nCette méthode consiste à appliquer aux agrégats financiers consolidés de CIH Bank, les multiples de valorisation\nobservés sur un échantillon de banques cotées à la bourse de Casablanca.\nL’échantillon établi comporte les banques suivantes : Attijariwafa Bank, BMCI, Bank of Africa, Crédit du Maroc\net BCP.\nComparables boursiers\nCette méthode consiste à comparer le multiple implicite du résultat net (P/E) et le multiple des fonds propres (P/B)\nde CIH Bank issus du prix de l’augmentation de capital, aux multiples moyens d’un échantillon de sociétés\ncomparables cotées à la Bourse de Casablanca, en considérant leurs comptes consolidés au 31/12/2023.\nCapitaux\nCours de RNPG\nNombre de propres part du\nEchantillon Clôture 2023 P/E2 P/B3\ntitres groupe 2023\n(MAD)1 (En KMAD)\n(En KMAD)\nAWB 460 215 140 839 57 836 828 7 507 605 13,2 1,71\nBMCI 540 13 279 286 7 191 346 171 224 41,88 0,99\nBank Of Africa 179,5 212 565 642 26 748 586 2 662 160 14,33 1,43\nCDM 797 10 881 214 7 034 195 503 089 17,24 1,22\nBCP 275 203 312 473 38 676 326 3 475 287 16,09 1,45\nMoyenne 20,69 1,14\nSource : Bourse de Casablanca\nCFG BANK n’a pas été incluse dans cet échantillon en raison des différences de stratégie de financement et\ndivergences de pondération de l’activité bancaire et non bancaire.\n1 Cours de clôture au 31 décembre 2023\n2 P/E = Cours de clôture / Bénéfice net par action\n3 P/B = Cours de clôture / Capitaux propres par action\n13\nLes ratios de valorisation ressortent comme suit :\n• P/B « Price to Book »\nEléments de valorisation Moyenne\nCapitaux propres part du groupe (en milliers de Dirhams) (*) 6 807 782\nMoyenne des P/B 1,14\nValorisation totale (en milliers de Dirhams) 7 760 871\nNombre d'actions 30 519 784\nValorisation par action (en MAD/action) 254\n(*) Données arrêtées au 31 décembre 2023\nSur la base de la méthode des comparables boursiers marocains, la valorisation de CIH Bank s’établit à 254 Dh/\naction.\n• P/E « Price Earning »\nEléments de valorisation Moyenne\nRésultat net part du groupe (en milliers de Dirhams) (*) 710 393\nMoyenne des P/E 20,69\nValorisation totale (en milliers de Dirhams) 14 698 031\nNombre d'actions 30 519 784\nValorisation par action (en MAD/action) 482\n(*) Données arrêtées au 31 décembre 2023\nSur la base de la méthode des comparables boursiers marocains, la valorisation de CIH Bank s’établit à 482 Dh/\naction.\nb. Moyenne des cours boursiers moyens pondérés\nLa méthode de valorisation retenue est la méthode de la moyenne des cours boursiers.\nCette méthode consiste à retenir comme valeur des fonds propres, la capitalisation boursière moyenne de la société\nprise sur une période significative.\nLa moyenne des cours utilisée est le cours moyen pondéré (CMP) sur une période qui correspond au rapport du\nvolume traité (montant en dirhams) durant ladite période et de la quantité (nombre) de titres échangés.\nLe CMP sur une période donnée est multiplié par le nombre d’actions de la société pour obtenir la valeur de ses\nfonds propres.\nUne analyse du cours moyen pondéré de l’action sur plusieurs horizons allant de 1 mois à 12 mois a été réalisée\net la moyenne des cours sur 12 mois a été retenue.\nCours moyen Quantité échangée Volume\nPériode Date début Date fin\npondéré (en Dirhams) (en milliers de Dirhams) (En milliers de Dirhams)\n1 mois 15/04/2024 15/05/2024 376 86 903 32 660 100\n2 mois 15/03/2024 15/05/2024 375 261 996 98 230 803\n3 mois 15/02/2024 15/05/2024 371 476 808 176 713 118\n6 mois 15/11/2023 15/05/2024 355 1 263 402 448 908 586\n9 mois 15/08/2023 15/05/2024 358 1 449 895 519 222 626\n12 mois 15/05/2023 15/05/2024 358 1 767 408 631 928 996\nSource : Bourse de Casablanca\nLe cours de clôture au 15 mai 2024 est de 387 MAD.\n14\nII.3.3 Eléments d’appréciation du prix de l’offre\nAu cours des 12 derniers mois, la valeur du titre CIH a évolué comme suit :\n410,00\n390,00\n370,00\n350,00\n330,00\n310,00\n290,00\n270,00\n250,00\nCours de clôture Prix de souscription\nSource : Bourse de Casablanca\nLes multiples de valorisation boursiers de CIH Bank, calculés sur la base d’un prix de 358 dirhams par action\nainsi que sur la base des données financières des comptes consolidés arrêtées au 31 décembre 2023, s’établissent\ncomme suit :\n2023\nRésultat net part du groupe (en milliers de Dirhams) 710 393\nCapitaux propres part du groupe (en milliers de Dirhams) 6 807 782\nNombre d'actions 30 519 784\nBénéfice net par action 23,28\nCapitaux propres par action 223,06\nP/E (Price Earning)4 15,40\nP/B (Price to Book)5 1,6\nSource : CIH Bank\nLe tableau ci-dessous présente le niveau de décote sur la base du dernier cours de clôture en bourse de CIH Bank au\n15 mai 2024 et des moyennes des cours de clôture pondérés à cette date :\nCours moyen pondéré Prix d'émission Décote par rapport\n(En Dirhams) (En Dirhams) au prix d'émission\nAu 15 mai 2024 387 358 -7,47%\n3 mois 371 358 -3,50%\n6 mois 355 358 0,84%\n9 mois 358 358 0,00%\nSource : Bourse de Casablanca\n4 P/E = Prix de souscription / Bénéfice net par action\n5 P/B = Prix de souscription / Capitaux propres par action\n15\nII.3.4. Evolution du cours de CIH Bank\na. Présentation du cours de CIH Bank\nLes cours de clôture enregistrés ainsi que le volume de transactions sur le marché central des titres CIH Bank se\nprésentent comme suit :\nPériode d’observation annuelle\n2021 2022 2023 15-mai-24\nCours plus haut (en Dirhams) 351 359 408 389\nCours plus bas (en Dirhams) 271 285 290 330\nNombre de titres traités 579 703 1 816 800 1 234 662 755 787\nVolume des transactions (en milliers de Dirhams) 176 361 726 593 426 837 429 005 009 271 530 670\nSource : Bourse de Casablanca\nPériode d’observation trimestrielle\nMai-Août 23 Sept-Nov 23 Déc 23-Fév 24 Mars-Mai 24\nCours plus haut (en Dirhams) 377 408 387 389\nCours plus bas (en Dirhams) 315 335 320 345\nNombre de titres traités 317 513 186 493 786 594 476 808\nVolume des transactions (en milliers de Dirhams) 112 706 370 70 314 040 272 195 468 176 713 118\nSource : Bourse de Casablanca\nPériode d’observation mensuelle\nJanv-24 Févr-24 Mars-24 Avr-24 15-mai-24\nCours plus haut (en Dirhams) 351 378 374 388 389\nCours plus bas (en Dirhams) 330 333 360 364 370\nNombre de titres traités 193 433 169 225 185 253 184 226 23 650\nVolume des transactions (en milliers de Dirhams) 65 703 609 59 773 860 67 598 595 69 444 816 9 009 791\nSource : Bourse de Casablanca\nII.3.5. Facteurs de risque liés aux instruments financiers offerts\na. Le risque de perte de valeur de l’investissement\nL’investisseur – actionnaire dans le titre CIH Bank, comme tout actionnaire dans une société (cotée ou non cotée)\nencourt un risque de perte d’une partie (voir de la totalité) de son investissement. Il s’agit d’un risque inhérent à\nsa situation d’actionnaire, si l’évolution du cours n’est pas favorable.\nb. La volatilité du prix sur le marché\nL’action CIH Bank étant cotée à la Bourse de Casablanca, elle répond aux règles de l’offre et de la demande pour\ndéterminer la valeur de la cotation. Le cours des actions est en grande partie déterminé par les perspectives de\nprofits futurs des sociétés cotées anticipées par les investisseurs. Ainsi, dépendamment de l’appréciation du titre\nchez les investisseurs, celui-ci peut subir des fluctuations importantes en fonction de divers paramètres (annonces,\ncommuniqués des résultats, perspectives, stratégie de développement, etc.). De ce fait, l’investisseur peut voir son\ntitre se déprécier comme s’apprécier sur le marché boursier marocain.\nc. La liquidité du titre\nLes souscripteurs aux actions de CIH Bank peuvent être soumis à un risque de liquidité du titre sur le marché\nboursier. En effet, dépendamment des conditions du marché et du prix de vente, la liquidité du titre peut se trouver\nmomentanément affectée. Un actionnaire souhaitant vendre rapidement sa participation dans le capital de CIH\nBank pourrait, dans certaines conditions, ne pas pouvoir réaliser ladite cession dans des conditions optimales.\n16\nCependant, la valeur CIH Bank présente un certain dynamisme de la liquidité du titre avec une moyenne\nquotidienne de quantités échangées de 10 272 titres au cours des 6 derniers mois, ces échanges pouvant aller de 0\nà 98 984 titres par jour.\nd. Les risques relatifs aux DPS\nEn cas de non-participation à l’opération, les titulaires de DPS n’ayant pas exercé leur DPS encourent un risque\nde dilution.\nPar ailleurs, les détenteurs de DPS encourent également un risque de perte de valeur du DPS à la clôture de la\npériode de souscription.\nEnfin, les titulaires de DPS encourent un risque relatif à la parité de souscription. En effet, ils pourraient ne pas\nêtre en mesure d’acquérir un nombre suffisant de DPS pour obtenir la parité exigée.\nIII. Cadre de l’opération\nLe Conseil d’Administration de CIH Bank tenu en date du 4 avril 2024, a décidé de proposer à l’Assemblée\nGénérale Extraordinaire du 06 mai 2024, une augmentation du capital social, d’un montant maximum de 350 000\n000 MAD par voie d’apport en numéraire, prime d’émission incluse.\nEn outre, ladite Assemblée Générale Extraordinaire (l’AGE) réunie 06 mai 2024 a autorisé le Conseil\nd’Administration à augmenter le capital social de CIH Bank d’un montant maximum de 350 000 000 dirhams,\nprime d’émission comprise, par émission d’actions nouvelles à libérer par des apports en numéraire et a conféré\ntous les pouvoirs au Conseil d’administration et au Président Directeur Général, aux fins de :\n▪ Réaliser cette augmentation de capital en une ou plusieurs fois, d’en fixer les modalités, d’en constater la\nréalisation et de procéder à la modification corrélative des statuts ;\n▪ Fixer l’intégralité des modalités financières et pratiques pour l’opération d’augmentation de capital,\nnotamment le prix d’émission des actions nouvelles, décider des périodes de souscription, fixer le nombre\nd’actions maximum réservé à chaque souscripteur, la date de jouissance des actions nouvelles, prendre\ntoutes les mesures pour assurer la souscription de toutes les actions disponibles à titre irréductible et, le cas\néchéant, à titre réductible, recueillir les souscriptions, effectuer et signer la déclaration de souscription et\nde versement prévue par la loi, et procéder et effectuer tout acte requis, conformément aux dispositions\nlégales et réglementaires en la matière.\nL’autorisation conférée par l’AGE est valable pour une durée de trois ans à compter de sa date de tenue.\nLe Conseil d'Administration devra rendre compte à la plus prochaine Assemblée Générale de l'utilisation faite des\npouvoirs conférés en application de la présente résolution et ce, au moyen d'un rapport décrivant notamment les\nconditions définitives des opérations réalisées, conformément aux dispositions légales et réglementaires en\nvigueur.\nConformément aux pouvoirs qui lui ont été délégués par l’Assemblée Générale Extraordinaire du 06 mai 2024, le\nconseil d’administration a fixé le 16 mai 2024 les modalités de l’opération d’augmentation de capital portant sur\nun montant maximum de deux cents millions (349 944 642) de dirhams, prime d’émission comprise,\ncorrespondant à 977 499 actions, à un prix de souscription de 358 MAD par action, incluant une valeur nominale\nunitaire de 100 MAD et une prime d’émission de 258 MAD. La parité de souscription est de 9 actions nouvelles\npour 281 DPS. Le Conseil d’administration tenu en date du 16 mai 2024 a fixé la date de jouissance au 1er janvier\n2024.\nEn nominal, le montant de l’augmentation du capital social destinée aux actionnaires et aux détenteurs de droits\npréférentiel sera de 97 749 900 dirhams par la création de 977 499 nouvelles actions.\n17\nIl est à noter que le capital social de CIH Bank sera porté de 3 051 978 400 dirhams à 3 149 728 300 dirhams,\nsuite à cette opération d’augmentation de capital, destinée aux actionnaires CIH Bank et détenteurs de\ndroits préférentiels de souscription.\nIV. Objectifs de l’opération\nL’augmentation de capital s’inscrit dans la lignée du plan de développement de la banque et vise les principaux\nobjectifs suivants :\n▪ Renforcer les fonds propres réglementaires actuels et répondre aux exigences réglementaires en matière de\nsolvabilité ;\n▪ Anticiper les différentes évolutions réglementaires ;\n▪ Financer son plan de développement et soutenir sa dynamique de croissance de l’activité.\nV. Intentions de participation à l’opération\nÀ la connaissance du management de la Banque, les actionnaires de références ont l’intention de souscrire à titre\nirréductible à l’augmentation de capital, objet du présent prospectus.\nVI. Investisseurs visés par l’opération\nL’augmentation de capital, objet du présent prospectus, est destinée aux actionnaires de CIH Bank et aux\ndétenteurs de droits préférentiels de souscription.\nEn application des dispositions de l’article 189 de la loi 17-95, les actionnaires de CIH Bank ont un droit de\npréférence à la souscription des actions nouvelles, proportionnellement au nombre d’actions qu’ils possèdent.\nAinsi, ces derniers auront un droit de souscription irréductible sur les actions nouvelles à émettre.\nLes actionnaires auront également un droit de souscription à titre réductible, en cas de non souscription par certains\nactionnaires aux actions auxquelles ils avaient droit à titre irréductible.\nL’attribution se fera proportionnellement à la part des actionnaires dans le capital social, dans la limite de leurs\ndemandes et sans attribution de fractions.\nVII. Impacts de l’opération\nVII.1 Impact sur les fonds propres de CIH Bank\nDans l’hypothèse où les souscriptions absorbent la totalité de l’augmentation de capital objet du présent\nprospectus, l’augmentation de capital en numéraire impactera les fonds propres de CIH Bank de la manière\nsuivante :\nRéserves et Capitaux\nCapital Fonds\nPrimes liées propres\nNombre social propres\nImpact fonds propres\nd’actions (En milliers de\nau capital (en\n(En milliers de\nconsolidés\nDirhams)\nmilliers de\nDirhams)6\n(En milliers de\nDirhams) Dirhams)7\nSituation avant l’opération d’augmentation de capital 30 519 784 3 051 978 1 776 513 6 465 815 7 729 305\nImpact de l’opération de l’augmentation de capital 350 MDH 977 499 97 750 252 195 349 944 349 944\nSituation après l’augmentation de capital de 350 MDH 31 497 283 3 149 728 2 028 708 6 815 759 8 079 250\nSource : CIH Bank Comptes sociaux et consolidés\n6 Situation des comptes sociaux arrêtées au 31 mars 2024\n7 Situation des comptes consolidés arrêtées au 31 mars 2024\n18\nL’impact des opérations sur les capitaux propres de CIH Bank se fonde sur l’hypothèse que les souscriptions ont\nabsorbé la totalité des opérations d’augmentation de capital.\nVII.2 Actionnariat avant et après l’opération\nLe tableau ci-dessous reprend la structure de l’actionnariat de CIH Bank avant et après l’opération d’augmentation\nde capital, objet du présent prospectus dans l’hypothèse où l’ensemble des actionnaires actuels de CIH Bank\nparticipent à l’opération à titre irréductible.\nSituation avant l’opération Situation après l’augmentation de\nd’augmentation de capital capital de 350 MDH\nActionnaires Nombre % du capital % du capital\nNombre d’actions\nd’actions & des droits de & des droits\ndétenues\ndétenues vote de vote\nMASSIRA CAPITAL MANAGEMENT 17 530 564 57,44% 18 092 041 57,44%\nCDG EP 2 105 865 6,90% 2 173 313 6,90%\nRCAR 1 077 250 3,53% 1 111 753 3,53%\nGroupe HOLMARCOM 36 624 0,12% 37 797 0,12%\nATLANTASANAD 3 543 347 11,61% 3 656 835 11,61%\nFlottant en Bourse 4 858 848 15,92% 5 014 469 15,92%\nPersonnel Groupe CIH BANK 1 367 286 4,48% 1 411 075 4,48%\nTotal 30 519 784 100% 31 497 283 100%\nSource : CIH Bank\nL’impact de l’opération sur la structure de l’actionnariat de CIH Bank se fonde sur l’hypothèse que les\nsouscriptions ont absorbé la totalité de l’opération d’augmentation de capital.\nVII.3 Impact de l’opération sur la gouvernance\nLa présente opération n’a pas d’impact sur la gouvernance de CIH Bank.\nVII.4 Impact de l’opération sur l’endettement\nEtant donné que l’opération objet du présent prospectus est une augmentation de capital, elle n’a aucun impact\nsur l’endettement de CIH Bank.\nVII.5 Impact de l’opération sur les orientations stratégiques de CIH Bank et sur ses\nperspectives\nEtant donné que l’opération d’augmentation de capital, objet du présent prospectus, est destinée aux actionnaires\nde CIH Bank et aux détenteurs des droits préférentiels de souscription, celle-ci n’a pas d’impact sur les orientations\nstratégiques portées par les actionnaires principaux de CIH Bank.\nVIII. Charges liées à l’opération\nLes frais de l’opération à la charge de l’émetteur sont estimés à environ 0,35% hors taxes du montant de\nl’opération. La nature de ces frais est détaillée ci-dessous :\n▪ Les frais légaux ;\n▪ Le conseiller juridique ;\n▪ La commission de l’Autorité Marocaine du Marché des Capitaux ;\n▪ Le Dépositaire Central, Maroclear ;\n▪ La Bourse de Casablanca ;\n▪ Les frais de courtage ;\n▪ Etc.\n19\nIX. Commissions facturées aux souscripteurs\nDans le cadre de la présente Opération, l’organisme collecteur d’ordres de souscriptions s’engage explicitement\net irrévocablement, à l’égard de l’Emetteur et du conseiller financier, à facturer aux souscripteurs, pour tous les\nordres enregistrés à la Bourse de Casablanca les commissions suivantes :\n▪ 0,1% (hors taxes) pour la Bourse de Casablanca au titre de la commission d’admission lui revenant lors de\nl’enregistrement en Bourse ;\n▪ Commissions de règlement et de livraison : correspond aux commissions arrêtées entre les souscripteurs et leur\nteneur de compte ;\n▪ 0,4% (hors taxes) pour l’organisme chargé de l’enregistrement. Elle s’applique sur le montant qui correspond à\nl’allocation effective lors du règlement / livraison.\n▪ La taxe sur la valeur ajoutée (TVA) au taux de 10% sera appliquée en sus. Elle s’applique sur le montant des\ncommissions correspondant à l’allocation effective lors du règlement / livraison.\nAfin d’assurer une égalité de traitement des souscripteurs quel que soit le lieu de souscription, l’organisme\ncollecteur d’ordres de souscriptions s’engage formellement et expressément à ne pratiquer aucune ristourne aux\nsouscripteurs ni reversement de quelque sorte que ce soit simultanément ou postérieurement à la souscription.\nCes commissions seront dues par les souscripteurs et seront payables avec le paiement du prix de souscription\ndes actions CIH Bank.\n20\nX. Déroulement de l’opération\nX.1. Calendrier indicatif de l’opération\nOrdre Etapes Date\n1 Émission par la Bourse de Casablanca de l'avis d'approbation de l'opération 28/06/2024\n2 Réception par la Bourse de Casablanca du prospectus visé par l’AMMC 28/06/2024\n3 Publication de l’extrait du prospectus sur le site internet de CIH Bank 28/06/2024\n4 Publication par la Bourse de Casablanca de l’avis relatif à l'opération 01/07/2024\n5 Publication d'un communiqué de presse par CIH Bank dans un journal d'annonces 01/07/2024\nlégales\n6 Publication par CIH Bank de l’avis d’émission d’actions nouvelles dans un\n05/07/2024\njournal d’annonces légales et au bulletin officiel\n7 - Détachement des droits de souscription\n- Publication de la valeur théorique du droit de souscription\n09/07/2024\n- Ajustement du cours de la valeur\n- Purge du carnet d’ordres\n8 Ouverture de la période de souscription et Cotation des droits préférentiels de\n12/07/2024\nsouscription\n9 Clôture de la période de souscription 19/08/2024\n10 Radiation des droits préférentiels de souscription 22/08/2024\n11 Réception du montant des souscriptions par le centralisateur 23/08/2024\n12 Centralisation définitive et allocation des souscriptions 26/08/2024\n13 Tenue de l'instance devant constater la réalisation de l'augmentation de capital 28/08/2024\n14 Réception par la Bourse de Casablanca du procès-verbal de l'instance ayant\nconstaté la réalisation de l'augmentation de capital en numéraire et des résultats de 29/08/2024\nl'augmentation de capital en numéraire\n15 - Livraison des nouveaux titres\n- Admissions des actions nouvelles à la cote de la Bourse de Casablanca\n- Enregistrement de l'augmentation de capital en numéraire en Bourse 02/09/2024\n- Publication par la Bourse de Casablanca des résultats de l’opération\n- Restitution des reliquats aux souscripteurs\n16 Publication des résultats de l'augmentation de capital en numéraire par CIH Bank 03/09/2024\nEn date du 9 Juillet 2024, La bourse de Casablanca procédera également au détachement de dividende brut relatif\nà l’exercice 2023 (14 Dirhams), à la purge du carnet d’ordre et à l’ajustement du cours de référence de l’action\nCIH BANK.\nX.2. Conseiller et intermédiaires financiers\nIntervenants Identité Adresse\nConseillers financiers et coordinateurs 187, Avenue Hassan II,\nCIH Bank\nglobaux Casablanca\n187, Avenue Hassan II,\nOrganisme Centralisateur CIH Bank\nCasablanca\nOrganisme chargé de l’enregistrement de 9, Boulevard Kennedy,\nCDG Capital Bourse\nl’opération à la Bourse de Casablanca Anfa, Casablanca\nCollecteurs d’ordres de souscription Tous les teneurs de comptes de titres/ DPS à exercer\nCDG Capital Bourse est une filiale de CDG Capital laquelle a le même actionnaire de référence que CIH\nBANK.\n21\nX.3. Modalités de souscription\nX.3.1 Période de souscription\nLa souscription à l’augmentation de capital, objet du présent prospectus, sera ouverte auprès de CIH Bank,\norganisme centralisateur et collecteur d’ordres de souscription, ainsi qu’auprès de tous les teneurs de comptes\ndurant la période de souscription qui s’étalera du 12 juillet 2024 au 19 août 2024 inclus.\nL’opération se fera par la remise par les souscripteurs d’un bulletin de souscription conforme au modèle mis à\nleur disposition et annexé au prospectus, dûment signé par le souscripteur ou son mandataire et horodaté par le\ncollecteur d’ordres.\nLes actionnaires actuels de CIH Bank et les porteurs de DPS devront s’adresser directement à leur teneur de\ncompte (banques teneurs de compte et sociétés de bourse teneurs de compte) pour souscrire à l’opération.\nX.3.2 Identification des souscripteurs\nLes collecteurs d’ordres de souscription, dans le cadre de la présente opération d’augmentation de capital, doivent\ns’assurer préalablement à l’acceptation de la souscription, que le souscripteur est porteur de DPS CIH Bank, et\nque ces derniers sont suffisants afin de couvrir sa souscription.\nA cet effet, ils doivent obtenir une copie du document qui atteste de cette identification et la joindre au bulletin de\nsouscription.\nLes collecteurs d’ordres de souscription doivent par ailleurs obtenir les documents justifiant l’appartenance du\nsouscripteur à l’une des catégories décrites ci-dessous.\nCatégorie d’investisseur Document à joindre\nPersonnes physiques marocaines résidentes Photocopie de la carte d’identité nationale\nPersonnes physiques marocaines résidentes à Photocopie de la carte d’identité nationale\nl’étranger\nPersonnes physiques résidentes et non marocaines Photocopie de la carte de résident\nPersonnes physiques non résidentes et non marocaines Photocopie des pages du passeport contenant l’identité de la\npersonne ainsi que les dates d’émission et d’échéance du\ndocument\nPersonnes morales de droit marocain (hors OPCVM) Photocopie du registre de commerce\nPersonnes morales de droit étranger Tout document faisant foi dans le pays d’origine et attestant de\nl’appartenance à la catégorie ou tout autre moyen jugé acceptable\npar le collecteur d’ordres\nOPCVM de droit marocain Photocopie de la décision d’agrément et en plus :\n- pour les FCP, le certificat de dépôt au greffe du tribunal\n- pour les SICAV, le certificat de dépôt au greffe du tribunal et le\nmodèle des inscriptions au registre de commerce.\nInvestisseurs qualifiés de droit marocain (hors Photocopie de la décision d’agrément et photocopie du registre de\nOPCVM) commerce comprenant l’objet social faisant ressortir\nl’appartenance du souscripteur à cette catégorie\nInstitutionnels de l’investissement agréé de droit Photocopie des statuts ou tout document faisant foi dans le pays\nétranger d'origine et photocopie de la décision d'agrément délivrée par\nl'autorité compétente\nBanques de droit marocain Modèle de l’inscription au registre de commerce comprenant\nl’objet social faisant ressortir l’appartenance du souscripteur à\ncette catégorie\n22\nCatégorie d’investisseur Document à joindre\nAssociations marocaines Photocopie des statuts et du récépissé du dépôt de dossier\nd’admission\nEnfant mineur Photocopie de la page du livret de famille attestant de la date de\nnaissance de l’enfant\nToutes les souscriptions ne respectant pas les conditions d’identification susmentionnées seront frappées de\nnullité. Les ordres de souscription sont irrévocables après la clôture de la période de souscription.\nX.3.3 Ouverture de comptes pour les futurs porteurs de Droits Préférentiels de Souscription\nLes opérations de souscription, pour les futurs porteurs de droit(s) préférentiel(s) de souscription, sont enregistrées\ndans un compte titres et espèces au nom du souscripteur.\nEn plus des conditions relatives à l’identification et à la constitution d’un dossier par client, les souscripteurs\ndevront signer une convention d’ouverture de comptes « titre / espèces » auprès d’un teneur de comptes.\nLes ouvertures de comptes ne peuvent être réalisées que par le souscripteur lui-même. Il est strictement interdit\nd’ouvrir un compte par procuration.\nUne procuration pour une souscription ne peut en aucun cas permettre l’ouverture d’un compte pour le mandant.\nLes ouvertures de compte pour enfants mineurs ne peuvent être réalisées que par le représentant légal de l’enfant\nmineur (père ou mère ou tuteur).\nPour les enfants mineurs, les souscriptions peuvent être enregistrées soit sur leur compte soit sur celui du\nreprésentant légal (père ou mère ou tuteur).\nLes ouvertures de compte pour incapables majeurs ne peuvent être réalisées que par le représentant légal (père ou\nmère ou tuteur).\nEn ce sens les teneurs de comptes exigent tout document justifiant l’incapacité du majeur incapable dont la\nsouscription a été réalisée par son représentant légal.\nX.3.4 Souscription pour compte de tiers\nLes souscriptions pour compte de tiers sont autorisées mais dans les limites suivantes :\n▪ Les souscriptions pour compte de tiers sont acceptées à condition que le souscripteur présente une\nprocuration dûment signée et légalisée par son mandant délimitant exactement le champ d’application de\nla procuration (procuration sur tous types de mouvements titres et espèces sur le compte, ou procuration\nspécifique à la souscription à l’opération d’augmentation de capital de CIH Bank). Le collecteur d’ordres\nde souscription est tenu, au cas où il ne disposerait pas déjà de cette copie, d’en obtenir une et de la joindre\nau bulletin de souscription.\n▪ Le mandataire doit préciser les références des comptes titres et espèces du mandant, dans lesquels seront\ninscrits respectivement les mouvements sur titres ou sur espèces liés aux actions CIH, objet de l’opération\n;\n▪ Les souscriptions pour compte d’enfants mineurs dont l’âge est inférieur ou égal à 18 ans sont autorisées\nà condition d’être effectuées par le père, la mère, le tuteur ou le représentant légal de l’enfant mineur. Le\ncollecteur d’ordres de souscription est tenu, au cas où il n’en disposerait pas déjà, d’obtenir une copie de\nla page du livret de famille faisant ressortir la date de naissance de l’enfant mineur. En ce cas, les\nmouvements sont portés soit sur un compte ouvert au nom de l’enfant mineur, soit sur le compte titres ou\nespèces ouvert au nom du père, de la mère, du tuteur ou du représentant légal ;\n▪ Dans le cas d’un mandat de gestion de portefeuille, le gestionnaire ne peut souscrire pour le compte du\nclient dont il gère le portefeuille qu’en présentant une procuration dûment signée et légalisée par son\nmandant. Les sociétés de gestion sont dispensées de présenter ces justificatifs pour les OPCVM qu’elles\ngèrent.\n23\nX.3.5 Modalités de souscription et de traitement des ordres\nLa souscription doit être réalisée auprès du teneur de compte dépositaire des titres ou de DPS à exercer.\nLesdits teneurs de compte procèderont immédiatement au blocage des DPS correspondant à la souscription.\nToutes les souscriptions se feront en numéraire et doivent être exprimées en nombre de titres.\nLes actions nouvelles seront réservées à titre préférentiel et irréductible aux porteurs de DPS à raison de 9 actions\nnouvelles pour 281 DPS. Les bulletins de souscription seront signés par le souscripteur ou son mandataire et\nhorodatés par l’organisme collecteur des souscriptions.\nPar application des dispositions de l’article 189 dernier alinéa de la loi n°17-95 du 30 août 1996 sur les sociétés\nanonymes telle que modifiée et complétée, la souscription aux actions nouvelles est destinée aux actionnaires de\nla société et aux porteurs de droits préférentiels de souscription au moment de la réalisation de l’augmentation de\ncapital. Ils auront, en conséquence, un droit de souscription irréductible sur les actions nouvelles à émettre.\nLes actionnaires de la société auront également un droit de souscription à titre réductible, en vue de la répartition\ndes actions non absorbées par l’exercice du droit de souscription à titre irréductible. Cette répartition s’effectuera\nau prorata de leur part dans le capital, dans la limite de leurs demandes et sans attribution de fractions.\nLa souscription, au même titre que les actionnaires actuels, est possible en achetant des droits de souscription sur\nle marché. Ces droits de souscription seront mis en vente par les actionnaires actuels qui ne souhaitent pas\nsouscrire ou souhaitent souscrire partiellement à l’augmentation de capital. Ils seront cotés durant toute la période\nde souscription. Les achats et les ventes de DPS pourront être effectués par l’entremise d’un intermédiaire agréé\n(société de bourse).\nLes collecteurs d’ordres de souscription doivent s’assurer, préalablement à l’acceptation d’une souscription, que\nle souscripteur a la capacité financière d’honorer ses engagements. Ils sont tenus d’accepter les ordres de\nsouscription de toute personne habilitée à participer à l’opération à condition que ladite personne fournisse les\ngaranties financières nécessaires.\nDans le cas où les souscriptions à titre irréductible et les attributions à titre réductible n'ont pas absorbé la totalité\nde l’augmentation de capital, le Conseil d’Administration a décidé d'attribuer proportionnellement le solde aux\nsouscriptions à titre réductible non satisfaites.\nDans le cas où les souscriptions reçues, tant à titre irréductible que réductible n’absorbent pas la totalité de\nl’augmentation de capital, le Conseil d’Administration a décidé que le montant de l'augmentation peut être limité\nau montant des souscriptions recueillies.\nX.3.6 Procédure d’exercice des droits préférentiels de souscription\nPour l’exercice de leurs DPS, les titulaires de DPS devront en faire la demande exclusivement auprès de leurs\nteneurs de comptes durant la période de souscription et régler le prix de souscription correspondant (majoré des\ncommissions de bourse, de courtage et de règlement livraison toutes taxes comprises). Les DPS doivent être\nexercés par leur titulaire, sous peine de déchéance, avant la fin de la période souscription. Le teneur de compte\nprocèdera immédiatement au blocage des DPS correspondant à la souscription.\nEn application des dispositions de l’article I.2.25 de la circulaire de l’AMMC, les teneurs de compte sont tenus,\nen cas de risque avéré de dépérissement des DPS, d’agir au mieux pour les intérêts des actionnaires, en cas\nd’absence d’instruction parvenue de la part de ces derniers. En revanche, les teneurs de comptes prendront en\nconsidération l’impact du prélèvement des commissions et taxes sur les opérations de vente compte tenu du cours\ndes DPS.\n24\nA la veille de la clôture de la période de souscription, les sociétés de bourse sont tenues de communiquer la liste\ndes ordres de vente en cours portant sur les DPS CIH Bank aux teneurs de comptes des clients ayant formulé\nlesdits ordres.\nPar ailleurs et conformément à l’article I.2.27 de la circulaire de l’AMMC, les ordres de cession de droits doivent\nêtre transmis à la société de bourse à travers les teneurs de comptes. Toutefois, si la société de bourse reçoit\ndirectement de son client un ordre de cession, elle en informe immédiatement le teneur de compte desdits droits.\nLes sociétés de bourse ne doivent pas prendre, le dernier jour de validité des droits de souscription, des ordres de\ncession sur lesdits droits dont elles n’assurent pas la conservation.\nX.3.7 Modalités d’allocation\nLes actions souscrites à titre irréductible seront allouées proportionnellement au nombre de DPS détenus par\nchaque souscripteur.\nAinsi, en plus des souscriptions à titre irréductible, les actionnaires peuvent souscrire à titre réductible. En ce sens,\nles actions émises et non souscrites à titre irréductible seront allouées aux souscripteurs à titre réductible dans la\nlimite de leur demande et au prorata des actions détenues.\nSi le nombre de titres à répartir à titre réductible en fonction de la règle du prorata ci-dessus n’est pas nombre\nentier, ce nombre de titres sera arrondi à l’unité inférieure. Les rompus seront alloués par palier d’une action par\nsouscripteur avec priorité aux demandes les plus fortes.\nX.3.8 Traitement des rompus\nLes DPS ne pourront être exercés qu’à concurrence d’un nombre de DPS permettant la souscription d’un nombre\nentier d’actions nouvelles.\nLes titulaires des droits préférentiels de souscription pourront souscrire à titre irréductible, à raison 9 actions\nnouvelles pour 281 droits préférentiels de souscription.\nLes titulaires de DPS qui ne détiendraient pas, au titre de leur souscription à titre irréductible, un nombre suffisant\nde DPS pour obtenir un nombre entier d’actions nouvelles, devront procéder à l’achat ou à la vente de droits de\nsouscriptions nécessaires lors de la période de souscription.\nX.4. Modalités de Centralisation, de couverture des souscriptions et d’enregistrement de\nl’opération\nX.4.1 Modalités de centralisation des ordres de souscription\nCIH Bank, en tant qu’organisme centralisateur, recueillera auprès des teneurs de comptes habilités, tous les\nbulletins de souscription renseignés et liés à la présente opération d’augmentation de capital réservée aux\nactionnaires et aux détenteurs de DPS.\nLes bulletins de souscription ainsi que la liste détaillée des souscripteurs doivent être remis au centralisateur en\ndeux phases :\no Le lendemain, concernant les actionnaires détenant des droits préférentiels de souscription ;\no 3 jours plus tard pour les souscripteurs ayant acheté des droits préférentiels de souscription non\nencore dénoués.\nLes teneurs de compte devront transférer les droits de souscription exercés sur le compte de centralisation de\nl’opération au nom de CIH Bank, ouvert auprès du Dépositaire central Maroclear.\nLes teneurs de compte devront virer à CIH Bank via SRBM, les montants de souscription à titre irréductible et\nréductible, majorés des commissions de bourse, de courtage et de règlement/livraison toutes taxes comprises.\n25\nAu plus tard le 4ème jour ouvré après la clôture de la période de souscription, et dès le dénouement des DPS achetés\npar le souscripteur en bourse durant les trois derniers jours de cette même période, les teneurs de compte\ncollecteurs d’ordres de souscription devront transmettre à CIH Bank le Bulletin de souscription correspondant,\ntransférer le complément de droits de souscription sur le compte de centralisation au niveau de Maroclear et\nprocéder au virement du montant de souscription correspondant via SRBM, majoré des commissions de bourse,\nde courtage et de règlement/livraison toutes taxes comprises.\nAu plus tard deux jours ouvrés après l’allocation, CIH Bank communiquera à l’AMMC, à la Bourse de\nCasablanca, à CDG Capital Bourse et aux teneurs de comptes les résultats globaux de l’opération.\nX.4.2 Modalités de règlement des souscriptions et d’inscriptions en compte\nLa libération des montants correspondants aux souscriptions en numéraire à la présente opération d’augmentation\nde capital doit être réalisée en espèce (par remise de chèque ou par débit du compte bancaire du souscripteur\nouvert sur les livres de son teneur de comptes) et versée au centralisateur le 4ème jour ouvré après la date de clôture\nde la période de souscription soit le 27 août 2024.\nIl est à noter que les chèques devront être présentés à l’encaissement avant la validation de la souscription et avant\nla clôture de la période de souscription.\nPour les DPS dénoués le 3ème jour après la clôture des souscriptions, la libération des montants correspondants\nauxdites souscriptions se feront le même jour, soit le 4ème jour ouvré après la date de clôture de la période de\nsouscription soit le 27 août 2024.\nLe montant des souscriptions doit être égal au montant souscrit augmenté de la commission de bourse (0,1% hors\ntaxes du montant souscrit), de la commission de courtage (0,4% hors taxes du montant souscrit) et de la\ncommission de règlement / livraison (correspond aux commissions arrêtées entre les souscripteurs et les teneurs\nde comptes). Les commissions sont facturées par les teneurs de comptes. Une TVA de 10% est appliquée en sus\naux différentes commissions.\nCIH Bank, organisme centralisateur et collecteur d’ordres, versera ces montants dans un compte spécial réservé\nà l’opération, objet du présent prospectus : « Augmentation de capital CIH Bank ».\nCIH Bank est chargé de l’inscription, auprès de Maroclear, des actions nouvelles.\nLa date d’inscription en compte des actions nouvelles correspondra au jour de livraison, soit le 02 septembre 2024.\nX.4.3 Modalités de livraison des titres\nLa livraison des titres, objet de la présente augmentation de capital, se fera en date du 02 septembre 2024.\nX.4.4 Société de bourse chargée de l’enregistrement de l’opération\nCDG Capital Bourse est chargé de l’enregistrement de l’opération à la Bourse de Casablanca. L’enregistrement\nde l’opération en bourse s’opérera le 02 septembre 2024.\nLe prix d’enregistrement correspond au prix de souscription tel que fixé dans le cadre de cette opération, soit 358\nMAD par action.\nX.4.5 Modalités de publication des résultats de l’opération\nLa publication des résultats sera opérée par la Bourse de Casablanca le 02 septembre 2024.\nLe CIH Bank publiera également les résultats de l’opération dans un journal d’annonces légales et sur son site\ninternet le 03 septembre 2024.\nX.4.6 Modalités de restitution du reliquat\nLa restitution des reliquats espèces aux souscripteurs interviendra le 02 Septembre 2024.\n26\nXI. Modèle de bulletin de souscription\nBULLETIN DE SOUSCRIPTION À L’AUGMENTATION DE CAPITAL EN NUMERAIRE DESTINEE AUX\nACTIONNAIRES\nMontant maximum de l’opération : 349 944 642 dirhams avec émission d’un maximum de 977 499 actions au prix de\nsouscription par action de 358 dirhams dont une prime d’émission de 258 dirhams par action\nPériode de souscription : du 12 juillet 2024 au 19 août 2024 inclus\nRèglement livraison le 02 septembre 2024\nJe soussigné :\nDénomination ou raison Sociale :\nNom :\nPrénom : Catégorie :\nDate de naissance : Siege social :\nNationalité : Nationalité\nNuméro et nature pièce d’identité : Numéro et nature du document exigé :\nAdresse :\nAdresse :\nTéléphone :\nTéléphone : Fax :\nFax : Signature et fonction\nTitulaire : du compte titres numéro………………………………………………………………………et du compte espèces\nnuméro……………………………………………………………………….\nAprès avoir pris connaissance des conditions d’émission des actions nouvelles CIH Bank énoncées dans le prospectus visé par l’AMMC\nsous la référence n° VI/EM/020/2024 en date du 28 juin 2024.\nDéclare / Déclarons :\n1. Présenter ………………………………droits préférentiels de souscription CIH Bank\nPour souscrire à titre irréductible à ……………actions nouvelles pour ………………actions anciennes (soit une parité de ……actions\nnouvelles pour ………actions anciennes).\nÀ l’appui de ma /notre souscription à titre irréductible, je/nous verse (ons) ………………………dirhams par actions, soit la somme\nde ……………………\n2. Souscrire à titre réductible à …………………actions nouvelles\nÀ l’appui de ma / notre souscription à titre réductible, je / nous verse (ons) ……………dirhams par action, soit la somme de\n………………………\nSoit un total de………………actions nouvelles pour un montant total dei ………………………\nDéclare / Déclarons effectuer le paiement [mode de paiement et ses détails : espèce/chèque/virement] auprès de [nom du teneur de\ncompte titre], sis à [adresse], [n° de compte titres], [n° de compte espèces].\nUne copie du bulletin de souscription sera remise au souscripteur avec accusé de réception et horodatée par [______].\nA…………………, le …………………\nSignatureii\n27\ni Au montant des versements s’ajoute les commissions de l’opération qui se présentent comme suit : la commission de Bourse de Casablanca (0.1% hors taxes du montant\nsouscrit), de la commission de courtage (0,4% hors taxes du montant souscrit) et de la commission de règlement/livraison (correspond aux commissions arrêtées entre les\nsouscripteurs et leur teneur de compte). Une TVA de 10% sera appliquée en sus.\nii Faire précéder des mentions suivantes :\n« Lu et approuvé »\n« Bon pour souscrire à ………………………actions à titres irréductibles »\n« Bon pour souscrire à ………………………actions à titres réductibles »\nAvertissement : L’attention des souscripteurs est attirée sur le fait que tout investissement en instruments financiers comporte des risques et que la\nvaleur de l’investissement est susceptible d’évoluer à la hausse comme à la baisse, sous l’influence des facteurs internes ou externes à l’émetteur.\nLe souscripteur reconnait avoir lu le prospectus relatif à l’opération visé par l’AMMC et déclare adhérer à l’ensemble des règles et conditions de l’offre\nqui y sont présentées.\nUn prospectus visé par l’AMMC est disponible, sans frais, au siège social de l’émetteur et sur son site internet, auprès des établissements chargés de\nrecueillir les demandes de souscription et à la Bourse des valeurs de Casablanca.\n28\nAnnexe\nStatuts :\nhttps://www.cihbank.ma/sites/default/files/2023-08/Scan%20statuts%20mis%20a%20jour01-03-2023.pdf\nDocument de référence :\nhttps://www.cihbank.ma/sites/default/files/2024-06/Document de re%CC%81fe%CC%81rence CIH Bank\n2023 %26 T1 2024 VF.pdf\n29",
    "tables": [
        [
            {
                "": "",
                "Nombre maximal d’actions à émettre : 977 499 actions": "Valeur nominale du titre : 100 MAD"
            },
            {
                "": "",
                "Nombre maximal d’actions à émettre : 977 499 actions": "Prime d’émission unitaire : 258 MAD"
            },
            {
                "": "",
                "Nombre maximal d’actions à émettre : 977 499 actions": "Prix de souscription : 358 MAD"
            },
            {
                "": "",
                "Nombre maximal d’actions à émettre : 977 499 actions": "Parité de souscription : 9 actions nouvelles pour 281 DPS"
            },
            {
                "": "",
                "Nombre maximal d’actions à émettre : 977 499 actions": "Montant nominal maximal de l’offre : 97 749 900 MAD"
            },
            {
                "": "",
                "Nombre maximal d’actions à émettre : 977 499 actions": "Prime d’émission maximale : 252 194 742 MAD"
            },
            {
                "": "",
                "Nombre maximal d’actions à émettre : 977 499 actions": "Montant maximal de l’offre : 349 944 642 MAD"
            },
            {
                "": "",
                "Nombre maximal d’actions à émettre : 977 499 actions": "Période de souscription : du 12 juillet 2024 au 19 août 2024 inclus"
            }
        ],
        [
            {
                "": "",
                "Conseiller financier & coordinateur Global": "",
                "Organisme chargé de l’enregistrement": ""
            }
        ],
        [
            {
                "": "",
                "Dénomination ou raison sociale": "Représentant légal"
            },
            {
                "": "",
                "Dénomination ou raison sociale": "Fonction"
            },
            {
                "": "",
                "Dénomination ou raison sociale": "Adresse"
            },
            {
                "": "",
                "Dénomination ou raison sociale": "Numéro de téléphone"
            },
            {
                "": "",
                "Dénomination ou raison sociale": "Numéro de fax"
            },
            {
                "": "",
                "Dénomination ou raison sociale": "Adresse électronique"
            }
        ],
        [
            {
                "Dénomination ou raison sociale :": "Représentant légal :",
                "Deloitte Audit": "Hicham BELEMQADEM",
                "Mazars Audit et Conseil Fidaroc Grant Thornton": "M. Taha FERDAOUS\nGhali Guessous\n& Abdou Souleye DIOP",
                "null": ""
            },
            {
                "Dénomination ou raison sociale :": "Fonction :",
                "Deloitte Audit": "Associé",
                "Mazars Audit et Conseil Fidaroc Grant Thornton": "Associé Associé",
                "null": ""
            },
            {
                "Dénomination ou raison sociale :": "Adresse :",
                "Deloitte Audit": "Bd Sidi Mohammed Benabdellah\nBâtiment C, Ivoire 3, La Marina -\nCasablanca",
                "Mazars Audit et Conseil Fidaroc Grant Thornton": "Finance City, Tour 33, Avia\nBusiness Center, Bd Moulay\nAbdellah Cherif, Casablanca",
                "null": "7 Bd. Driss Slaoui Casablanca"
            },
            {
                "Dénomination ou raison sociale :": "Numéro de téléphone :",
                "Deloitte Audit": "+212 5 22 22 47 34",
                "Mazars Audit et Conseil Fidaroc Grant Thornton": "+212 5 22 42 34 25 +212 5 22 54 48 00",
                "null": ""
            },
            {
                "Dénomination ou raison sociale :": "Numéro de fax :",
                "Deloitte Audit": "+212 5 22 22 47 59",
                "Mazars Audit et Conseil Fidaroc Grant Thornton": "+212 5 22 42 34 00 +212 5 22 29 66 70",
                "null": ""
            },
            {
                "Dénomination ou raison sociale :": "Adresse électronique :",
                "Deloitte Audit": "h.belemqadem@deloitte.com",
                "Mazars Audit et Conseil Fidaroc Grant Thornton": "Taha.Ferdaous@mazars.ma",
                "null": "Ghali.Guessous@ma.gt.com"
            },
            {
                "Dénomination ou raison sociale :": "1er exercice soumis au contrôle des\nCAC :",
                "Deloitte Audit": "2024",
                "Mazars Audit et Conseil Fidaroc Grant Thornton": "2021",
                "null": "2015"
            },
            {
                "Dénomination ou raison sociale :": "Dernière date de renouvellement\ndu mandat :",
                "Deloitte Audit": "-",
                "Mazars Audit et Conseil Fidaroc Grant Thornton": "Juin 2024",
                "null": "2021"
            },
            {
                "Dénomination ou raison sociale :": "Date de Fin du mandat actuel :",
                "Deloitte Audit": "AGO appelée à statuer sur l’exercice\n2026",
                "Mazars Audit et Conseil Fidaroc Grant Thornton": "AGO appelée à statuer sur\nl’exercice 2026",
                "null": "AGO ayant statué sur\nl’exercice 2023"
            }
        ],
        [
            {
                "": "",
                "Dénomination ou raison sociale": "Représentant légal"
            },
            {
                "": "",
                "Dénomination ou raison sociale": "Fonction"
            },
            {
                "": "",
                "Dénomination ou raison sociale": "Adresse"
            },
            {
                "": "",
                "Dénomination ou raison sociale": "Numéro de téléphone"
            },
            {
                "": "",
                "Dénomination ou raison sociale": "Numéro de fax"
            },
            {
                "": "",
                "Dénomination ou raison sociale": "Adresse électronique"
            }
        ],
        [
            {
                "": "",
                "Dénomination ou raison sociale": "Représentant légal"
            },
            {
                "": "",
                "Dénomination ou raison sociale": "Fonction"
            },
            {
                "": "",
                "Dénomination ou raison sociale": "Adresse"
            },
            {
                "": "",
                "Dénomination ou raison sociale": "Numéro de téléphone"
            },
            {
                "": "",
                "Dénomination ou raison sociale": "Adresse électronique"
            }
        ],
        [
            {
                "": "",
                "Dénomination ou raison sociale": "Représentant légal"
            },
            {
                "": "",
                "Dénomination ou raison sociale": "Fonction"
            },
            {
                "": "",
                "Dénomination ou raison sociale": "Adresse"
            },
            {
                "": "",
                "Dénomination ou raison sociale": "Numéro de téléphone"
            },
            {
                "": "",
                "Dénomination ou raison sociale": "Adresse électronique"
            }
        ],
        [
            {
                "": "",
                "Dénomination ou raison sociale": "Adresse"
            },
            {
                "": "",
                "Dénomination ou raison sociale": "Numéro de téléphone"
            },
            {
                "": "",
                "Dénomination ou raison sociale": "Adresse électronique"
            }
        ],
        [
            {
                "": "",
                "Nature des titres": "Forme juridique des titres"
            },
            {
                "": "",
                "Nature des titres": "Montant maximal de l’opération"
            },
            {
                "": "",
                "Nature des titres": "Nombre maximal de titres à émettre"
            },
            {
                "": "",
                "Nature des titres": "Valeur nominale unitaire"
            },
            {
                "": "",
                "Nature des titres": "Prime d’émission unitaire"
            },
            {
                "": "",
                "Nature des titres": "Prix de souscription unitaire"
            },
            {
                "": "",
                "Nature des titres": "Valeur nominale global"
            },
            {
                "": "",
                "Nature des titres": "Prime d’émission maximale"
            },
            {
                "": "",
                "Nature des titres": "Période de souscription"
            },
            {
                "": "",
                "Nature des titres": "Date de jouissance"
            },
            {
                "": "",
                "Nature des titres": "Libération des actions nouvelles"
            },
            {
                "": "",
                "Nature des titres": ""
            },
            {
                "": "",
                "Nature des titres": ""
            },
            {
                "": "",
                "Nature des titres": "Mode de libération des actions"
            },
            {
                "": "",
                "Nature des titres": "Droits attachés aux titres"
            },
            {
                "": "",
                "Nature des titres": "Secteur d'activité"
            },
            {
                "": "",
                "Nature des titres": "Libellé"
            },
            {
                "": "",
                "Nature des titres": "Ticker"
            },
            {
                "": "",
                "Nature des titres": "Code ISIN"
            },
            {
                "": "",
                "Nature des titres": "Compartiment"
            },
            {
                "": "",
                "Nature des titres": "Ligne de cotation"
            },
            {
                "": "",
                "Nature des titres": "Date de cotation des actions nouvelles"
            },
            {
                "": "",
                "Nature des titres": "Cycle de négociation"
            },
            {
                "": "",
                "Nature des titres": "Organisme chargé de l’enregistrement"
            },
            {
                "": "",
                "Nature des titres": "de l’opération"
            }
        ],
        [
            {
                "Modalités d’exercice du DPS": "Négociation du DPS",
                "null": "",
                "Lors de la réalisation de l'augmentation de capital, la souscription aux actions\nnouvelles est destinée aux actionnaires de la société et aux porteurs de droits\npréférentiels de souscription. Par conséquent, ils auront un droit de\nsouscription irréductible sur les actions nouvelles à émettre.\nPour la souscription des actions nouvelles émises dans le cadre de\nl'augmentation de capital, objet du présent prospectus, les droits préférentiels\nde souscription réservés aux actionnaires en application des dispositions de\nl'article 189 de la loi 17-95 sur les sociétés anonymes, telle que modifiée et\ncomplétée, seront maintenus à raison d'un droit préférentiel de souscription\npour une action existante.\nLes titulaires des droits préférentiels de souscription pourront souscrire à titre\nirréductible, à raison 9 actions nouvelles pour 281 droits préférentiels de\nsouscription. Un actionnaire personne physique a renoncé à l’exercice de 93\ndroits préférentiels de souscription.\nChaque actionnaire pourra, s'il le souhaite, renoncer à titre individuel à son\ndroit préférentiel de souscription.\nLes actionnaires auront également un droit de souscription à titre réductible,\nen vue de la répartition des actions non absorbées par l’exercice du droit de\nsouscription à titre irréductible. Cette répartition s’effectuera au prorata de\nleurs parts dans le capital, dans la limite de leurs demandes et sans attribution\nde fraction.\nLes droits préférentiels de souscription ne pourront être exercés qu’à\nconcurrence d’un nombre de droits préférentiels de souscription permettant la\nsouscription d’un nombre entier d’actions nouvelles. Les titulaires de droits\npréférentiels de souscription qui ne posséderaient pas, au titre de leur\nsouscription à titre irréductible, un nombre suffisant de droits préférentiels de\nsouscription pour obtenir un nombre entier d’actions nouvelles, pourront\nprocéder, à l’achat ou à la vente de droits préférentiels de souscription aux\nconditions du marché, lors de la période de souscription.\nLes droits préférentiels de souscription formant rompus pourront être cédés\nou complétés sur le marché pendant la période de souscription.\nLe prix théorique des droits préférentiels de souscription (DPS) est calculé de\nla manière suivante : DPS= (Cours clôture de l'action CIH à la veille de la\ndate du détachement du DPS - Dividende - prix de souscription) * ([nombre\nd'actions nouvelles] / [nombre d'actions anciennes + nombre d'actions\nnouvelles])": "Les droits préférentiels de souscription relatifs à la présente augmentation de\ncapital seront librement négociables à la Bourse de Casablanca dans les\nmêmes conditions que l'action CIH elle-même, pendant toute la période de\nsouscription allant du 12 juillet 2024 au 19 août 2024 inclus."
            },
            {
                "Modalités d’exercice du DPS": "Sort des DPS non exercés",
                "null": "",
                "Lors de la réalisation de l'augmentation de capital, la souscription aux actions\nnouvelles est destinée aux actionnaires de la société et aux porteurs de droits\npréférentiels de souscription. Par conséquent, ils auront un droit de\nsouscription irréductible sur les actions nouvelles à émettre.\nPour la souscription des actions nouvelles émises dans le cadre de\nl'augmentation de capital, objet du présent prospectus, les droits préférentiels\nde souscription réservés aux actionnaires en application des dispositions de\nl'article 189 de la loi 17-95 sur les sociétés anonymes, telle que modifiée et\ncomplétée, seront maintenus à raison d'un droit préférentiel de souscription\npour une action existante.\nLes titulaires des droits préférentiels de souscription pourront souscrire à titre\nirréductible, à raison 9 actions nouvelles pour 281 droits préférentiels de\nsouscription. Un actionnaire personne physique a renoncé à l’exercice de 93\ndroits préférentiels de souscription.\nChaque actionnaire pourra, s'il le souhaite, renoncer à titre individuel à son\ndroit préférentiel de souscription.\nLes actionnaires auront également un droit de souscription à titre réductible,\nen vue de la répartition des actions non absorbées par l’exercice du droit de\nsouscription à titre irréductible. Cette répartition s’effectuera au prorata de\nleurs parts dans le capital, dans la limite de leurs demandes et sans attribution\nde fraction.\nLes droits préférentiels de souscription ne pourront être exercés qu’à\nconcurrence d’un nombre de droits préférentiels de souscription permettant la\nsouscription d’un nombre entier d’actions nouvelles. Les titulaires de droits\npréférentiels de souscription qui ne posséderaient pas, au titre de leur\nsouscription à titre irréductible, un nombre suffisant de droits préférentiels de\nsouscription pour obtenir un nombre entier d’actions nouvelles, pourront\nprocéder, à l’achat ou à la vente de droits préférentiels de souscription aux\nconditions du marché, lors de la période de souscription.\nLes droits préférentiels de souscription formant rompus pourront être cédés\nou complétés sur le marché pendant la période de souscription.\nLe prix théorique des droits préférentiels de souscription (DPS) est calculé de\nla manière suivante : DPS= (Cours clôture de l'action CIH à la veille de la\ndate du détachement du DPS - Dividende - prix de souscription) * ([nombre\nd'actions nouvelles] / [nombre d'actions anciennes + nombre d'actions\nnouvelles])": "Le droit préférentiel de souscription des actionnaires aux actions nouvelles\némises devra être exercé durant la période souscription sous peine de\ndéchéance."
            },
            {
                "Modalités d’exercice du DPS": "",
                "null": "",
                "Lors de la réalisation de l'augmentation de capital, la souscription aux actions\nnouvelles est destinée aux actionnaires de la société et aux porteurs de droits\npréférentiels de souscription. Par conséquent, ils auront un droit de\nsouscription irréductible sur les actions nouvelles à émettre.\nPour la souscription des actions nouvelles émises dans le cadre de\nl'augmentation de capital, objet du présent prospectus, les droits préférentiels\nde souscription réservés aux actionnaires en application des dispositions de\nl'article 189 de la loi 17-95 sur les sociétés anonymes, telle que modifiée et\ncomplétée, seront maintenus à raison d'un droit préférentiel de souscription\npour une action existante.\nLes titulaires des droits préférentiels de souscription pourront souscrire à titre\nirréductible, à raison 9 actions nouvelles pour 281 droits préférentiels de\nsouscription. Un actionnaire personne physique a renoncé à l’exercice de 93\ndroits préférentiels de souscription.\nChaque actionnaire pourra, s'il le souhaite, renoncer à titre individuel à son\ndroit préférentiel de souscription.\nLes actionnaires auront également un droit de souscription à titre réductible,\nen vue de la répartition des actions non absorbées par l’exercice du droit de\nsouscription à titre irréductible. Cette répartition s’effectuera au prorata de\nleurs parts dans le capital, dans la limite de leurs demandes et sans attribution\nde fraction.\nLes droits préférentiels de souscription ne pourront être exercés qu’à\nconcurrence d’un nombre de droits préférentiels de souscription permettant la\nsouscription d’un nombre entier d’actions nouvelles. Les titulaires de droits\npréférentiels de souscription qui ne posséderaient pas, au titre de leur\nsouscription à titre irréductible, un nombre suffisant de droits préférentiels de\nsouscription pour obtenir un nombre entier d’actions nouvelles, pourront\nprocéder, à l’achat ou à la vente de droits préférentiels de souscription aux\nconditions du marché, lors de la période de souscription.\nLes droits préférentiels de souscription formant rompus pourront être cédés\nou complétés sur le marché pendant la période de souscription.\nLe prix théorique des droits préférentiels de souscription (DPS) est calculé de\nla manière suivante : DPS= (Cours clôture de l'action CIH à la veille de la\ndate du détachement du DPS - Dividende - prix de souscription) * ([nombre\nd'actions nouvelles] / [nombre d'actions anciennes + nombre d'actions\nnouvelles])": "12 juillet 2024"
            },
            {
                "Modalités d’exercice du DPS": "",
                "null": "",
                "Lors de la réalisation de l'augmentation de capital, la souscription aux actions\nnouvelles est destinée aux actionnaires de la société et aux porteurs de droits\npréférentiels de souscription. Par conséquent, ils auront un droit de\nsouscription irréductible sur les actions nouvelles à émettre.\nPour la souscription des actions nouvelles émises dans le cadre de\nl'augmentation de capital, objet du présent prospectus, les droits préférentiels\nde souscription réservés aux actionnaires en application des dispositions de\nl'article 189 de la loi 17-95 sur les sociétés anonymes, telle que modifiée et\ncomplétée, seront maintenus à raison d'un droit préférentiel de souscription\npour une action existante.\nLes titulaires des droits préférentiels de souscription pourront souscrire à titre\nirréductible, à raison 9 actions nouvelles pour 281 droits préférentiels de\nsouscription. Un actionnaire personne physique a renoncé à l’exercice de 93\ndroits préférentiels de souscription.\nChaque actionnaire pourra, s'il le souhaite, renoncer à titre individuel à son\ndroit préférentiel de souscription.\nLes actionnaires auront également un droit de souscription à titre réductible,\nen vue de la répartition des actions non absorbées par l’exercice du droit de\nsouscription à titre irréductible. Cette répartition s’effectuera au prorata de\nleurs parts dans le capital, dans la limite de leurs demandes et sans attribution\nde fraction.\nLes droits préférentiels de souscription ne pourront être exercés qu’à\nconcurrence d’un nombre de droits préférentiels de souscription permettant la\nsouscription d’un nombre entier d’actions nouvelles. Les titulaires de droits\npréférentiels de souscription qui ne posséderaient pas, au titre de leur\nsouscription à titre irréductible, un nombre suffisant de droits préférentiels de\nsouscription pour obtenir un nombre entier d’actions nouvelles, pourront\nprocéder, à l’achat ou à la vente de droits préférentiels de souscription aux\nconditions du marché, lors de la période de souscription.\nLes droits préférentiels de souscription formant rompus pourront être cédés\nou complétés sur le marché pendant la période de souscription.\nLe prix théorique des droits préférentiels de souscription (DPS) est calculé de\nla manière suivante : DPS= (Cours clôture de l'action CIH à la veille de la\ndate du détachement du DPS - Dividende - prix de souscription) * ([nombre\nd'actions nouvelles] / [nombre d'actions anciennes + nombre d'actions\nnouvelles])": "Fixing"
            },
            {
                "Modalités d’exercice du DPS": "",
                "null": "",
                "Lors de la réalisation de l'augmentation de capital, la souscription aux actions\nnouvelles est destinée aux actionnaires de la société et aux porteurs de droits\npréférentiels de souscription. Par conséquent, ils auront un droit de\nsouscription irréductible sur les actions nouvelles à émettre.\nPour la souscription des actions nouvelles émises dans le cadre de\nl'augmentation de capital, objet du présent prospectus, les droits préférentiels\nde souscription réservés aux actionnaires en application des dispositions de\nl'article 189 de la loi 17-95 sur les sociétés anonymes, telle que modifiée et\ncomplétée, seront maintenus à raison d'un droit préférentiel de souscription\npour une action existante.\nLes titulaires des droits préférentiels de souscription pourront souscrire à titre\nirréductible, à raison 9 actions nouvelles pour 281 droits préférentiels de\nsouscription. Un actionnaire personne physique a renoncé à l’exercice de 93\ndroits préférentiels de souscription.\nChaque actionnaire pourra, s'il le souhaite, renoncer à titre individuel à son\ndroit préférentiel de souscription.\nLes actionnaires auront également un droit de souscription à titre réductible,\nen vue de la répartition des actions non absorbées par l’exercice du droit de\nsouscription à titre irréductible. Cette répartition s’effectuera au prorata de\nleurs parts dans le capital, dans la limite de leurs demandes et sans attribution\nde fraction.\nLes droits préférentiels de souscription ne pourront être exercés qu’à\nconcurrence d’un nombre de droits préférentiels de souscription permettant la\nsouscription d’un nombre entier d’actions nouvelles. Les titulaires de droits\npréférentiels de souscription qui ne posséderaient pas, au titre de leur\nsouscription à titre irréductible, un nombre suffisant de droits préférentiels de\nsouscription pour obtenir un nombre entier d’actions nouvelles, pourront\nprocéder, à l’achat ou à la vente de droits préférentiels de souscription aux\nconditions du marché, lors de la période de souscription.\nLes droits préférentiels de souscription formant rompus pourront être cédés\nou complétés sur le marché pendant la période de souscription.\nLe prix théorique des droits préférentiels de souscription (DPS) est calculé de\nla manière suivante : DPS= (Cours clôture de l'action CIH à la veille de la\ndate du détachement du DPS - Dividende - prix de souscription) * ([nombre\nd'actions nouvelles] / [nombre d'actions anciennes + nombre d'actions\nnouvelles])": "DS CIH 9/281 2024"
            },
            {
                "Modalités d’exercice du DPS": "",
                "null": "",
                "Lors de la réalisation de l'augmentation de capital, la souscription aux actions\nnouvelles est destinée aux actionnaires de la société et aux porteurs de droits\npréférentiels de souscription. Par conséquent, ils auront un droit de\nsouscription irréductible sur les actions nouvelles à émettre.\nPour la souscription des actions nouvelles émises dans le cadre de\nl'augmentation de capital, objet du présent prospectus, les droits préférentiels\nde souscription réservés aux actionnaires en application des dispositions de\nl'article 189 de la loi 17-95 sur les sociétés anonymes, telle que modifiée et\ncomplétée, seront maintenus à raison d'un droit préférentiel de souscription\npour une action existante.\nLes titulaires des droits préférentiels de souscription pourront souscrire à titre\nirréductible, à raison 9 actions nouvelles pour 281 droits préférentiels de\nsouscription. Un actionnaire personne physique a renoncé à l’exercice de 93\ndroits préférentiels de souscription.\nChaque actionnaire pourra, s'il le souhaite, renoncer à titre individuel à son\ndroit préférentiel de souscription.\nLes actionnaires auront également un droit de souscription à titre réductible,\nen vue de la répartition des actions non absorbées par l’exercice du droit de\nsouscription à titre irréductible. Cette répartition s’effectuera au prorata de\nleurs parts dans le capital, dans la limite de leurs demandes et sans attribution\nde fraction.\nLes droits préférentiels de souscription ne pourront être exercés qu’à\nconcurrence d’un nombre de droits préférentiels de souscription permettant la\nsouscription d’un nombre entier d’actions nouvelles. Les titulaires de droits\npréférentiels de souscription qui ne posséderaient pas, au titre de leur\nsouscription à titre irréductible, un nombre suffisant de droits préférentiels de\nsouscription pour obtenir un nombre entier d’actions nouvelles, pourront\nprocéder, à l’achat ou à la vente de droits préférentiels de souscription aux\nconditions du marché, lors de la période de souscription.\nLes droits préférentiels de souscription formant rompus pourront être cédés\nou complétés sur le marché pendant la période de souscription.\nLe prix théorique des droits préférentiels de souscription (DPS) est calculé de\nla manière suivante : DPS= (Cours clôture de l'action CIH à la veille de la\ndate du détachement du DPS - Dividende - prix de souscription) * ([nombre\nd'actions nouvelles] / [nombre d'actions anciennes + nombre d'actions\nnouvelles])": "SCIHC"
            }
        ],
        [
            {
                "Echantillon": "",
                "Cours de\nClôture\n(MAD)1": "",
                "Nombre de\ntitres": "",
                "": "",
                "Capitaux": "propres part du",
                "RNPG\n2023\n(En KMAD)": "",
                "P/E2": "",
                "P/B3": ""
            },
            {
                "Echantillon": "",
                "Cours de\nClôture\n(MAD)1": "",
                "Nombre de\ntitres": "",
                "": "",
                "Capitaux": "groupe 2023",
                "RNPG\n2023\n(En KMAD)": "",
                "P/E2": "",
                "P/B3": ""
            },
            {
                "Echantillon": "",
                "Cours de\nClôture\n(MAD)1": "",
                "Nombre de\ntitres": "",
                "": "",
                "Capitaux": "(En KMAD)",
                "RNPG\n2023\n(En KMAD)": "",
                "P/E2": "",
                "P/B3": ""
            }
        ],
        [
            {
                "Cours de": "Clôture"
            },
            {
                "Cours de": "(MAD)1"
            }
        ],
        [
            {
                "RNPG": "2023"
            },
            {
                "RNPG": "(En KMAD)"
            }
        ],
        [
            {
                "Nombre de": "titres"
            }
        ],
        [],
        [],
        [
            {
                "Période": "",
                "Date début": "",
                "Date fin": "",
                "": "",
                "Cours moyen": "pondéré (en Dirhams)",
                "Quantité échangée": "(en milliers de Dirhams)",
                "Volume": "(En milliers de Dirhams)"
            }
        ],
        [],
        [
            {
                "": "",
                "2023": ""
            },
            {
                "": "",
                "2023": ""
            },
            {
                "": "",
                "2023": ""
            },
            {
                "": "",
                "2023": ""
            },
            {
                "": "",
                "2023": ""
            },
            {
                "": "",
                "2023": ""
            },
            {
                "": "",
                "2023": ""
            }
        ],
        [
            {
                "": "",
                "Cours moyen pondéré": "(En Dirhams)",
                "Prix d'émission": "(En Dirhams)",
                "Décote par rapport": "au prix d'émission"
            }
        ],
        [],
        [],
        [],
        [
            {
                "Impact fonds propres": "",
                "Nombre\nd’actions": "",
                "Capital\nsocial\n(En milliers de\nDirhams)": "",
                "": "",
                "Réserves et": "Primes liées",
                "Fonds\npropres\n(En milliers de\nDirhams)6": "",
                "Capitaux\npropres\nconsolidés\n(En milliers de\nDirhams)7": ""
            },
            {
                "Impact fonds propres": "",
                "Nombre\nd’actions": "",
                "Capital\nsocial\n(En milliers de\nDirhams)": "",
                "": "",
                "Réserves et": "au capital (en",
                "Fonds\npropres\n(En milliers de\nDirhams)6": "",
                "Capitaux\npropres\nconsolidés\n(En milliers de\nDirhams)7": ""
            },
            {
                "Impact fonds propres": "",
                "Nombre\nd’actions": "",
                "Capital\nsocial\n(En milliers de\nDirhams)": "",
                "": "",
                "Réserves et": "milliers de",
                "Fonds\npropres\n(En milliers de\nDirhams)6": "",
                "Capitaux\npropres\nconsolidés\n(En milliers de\nDirhams)7": ""
            },
            {
                "Impact fonds propres": "",
                "Nombre\nd’actions": "",
                "Capital\nsocial\n(En milliers de\nDirhams)": "",
                "": "",
                "Réserves et": "Dirhams)",
                "Fonds\npropres\n(En milliers de\nDirhams)6": "",
                "Capitaux\npropres\nconsolidés\n(En milliers de\nDirhams)7": ""
            }
        ],
        [
            {
                "Capitaux": "propres"
            },
            {
                "Capitaux": "consolidés"
            },
            {
                "Capitaux": "(En milliers de"
            }
        ],
        [
            {
                "Capital": "social"
            },
            {
                "Capital": "(En milliers de"
            },
            {
                "Capital": "Dirhams)"
            }
        ],
        [
            {
                "Fonds": "propres"
            },
            {
                "Fonds": "(En milliers de"
            },
            {
                "Fonds": "Dirhams)6"
            }
        ],
        [
            {
                "Nombre": "d’actions"
            }
        ],
        [
            {
                "Actionnaires": "",
                "": "",
                "Situation avant l’opération": "d’augmentation de capital",
                "null": "",
                "Situation après l’augmentation de": "capital de 350 MDH"
            },
            {
                "Actionnaires": "",
                "": "",
                "Situation avant l’opération": "Nombre",
                "null": "% du capital",
                "Situation après l’augmentation de": ""
            },
            {
                "Actionnaires": "",
                "": "",
                "Situation avant l’opération": "d’actions",
                "null": "& des droits",
                "Situation après l’augmentation de": ""
            },
            {
                "Actionnaires": "",
                "": "",
                "Situation avant l’opération": "détenues",
                "null": "de vote",
                "Situation après l’augmentation de": ""
            }
        ],
        [
            {
                "Nombre d’actions": "détenues"
            }
        ],
        [],
        [
            {
                "": "",
                "Intervenants": "Conseillers financiers et coordinateurs",
                "Identité": "",
                "Adresse": ""
            },
            {
                "": "",
                "Intervenants": "globaux",
                "Identité": "",
                "Adresse": ""
            },
            {
                "": "",
                "Intervenants": "",
                "Identité": "",
                "Adresse": ""
            },
            {
                "": "",
                "Intervenants": "Organisme chargé de l’enregistrement de",
                "Identité": "",
                "Adresse": ""
            },
            {
                "": "",
                "Intervenants": "l’opération à la Bourse de Casablanca",
                "Identité": "",
                "Adresse": ""
            },
            {
                "": "",
                "Intervenants": "Collecteurs d’ordres de souscription",
                "Identité": "",
                "Adresse": ""
            }
        ],
        [
            {
                "": "",
                "Catégorie d’investisseur": "Personnes physiques marocaines résidentes",
                "null": "",
                "Document à joindre": ""
            },
            {
                "": "",
                "Catégorie d’investisseur": "Personnes physiques marocaines résidentes à",
                "null": "",
                "Document à joindre": ""
            },
            {
                "": "",
                "Catégorie d’investisseur": "l’étranger",
                "null": "",
                "Document à joindre": ""
            },
            {
                "": "",
                "Catégorie d’investisseur": "Personnes physiques résidentes et non marocaines",
                "null": "",
                "Document à joindre": ""
            },
            {
                "": "",
                "Catégorie d’investisseur": "Personnes physiques non résidentes et non marocaines",
                "null": "",
                "Document à joindre": ""
            },
            {
                "": "",
                "Catégorie d’investisseur": "",
                "null": "",
                "Document à joindre": ""
            },
            {
                "": "",
                "Catégorie d’investisseur": "",
                "null": "",
                "Document à joindre": ""
            },
            {
                "": "",
                "Catégorie d’investisseur": "",
                "null": "",
                "Document à joindre": ""
            },
            {
                "": "",
                "Catégorie d’investisseur": "",
                "null": "",
                "Document à joindre": ""
            },
            {
                "": "",
                "Catégorie d’investisseur": "",
                "null": "",
                "Document à joindre": ""
            },
            {
                "": "",
                "Catégorie d’investisseur": "",
                "null": "",
                "Document à joindre": ""
            }
        ],
        [
            {
                "Investisseurs qualifiés de droit marocain (hors": "OPCVM)"
            }
        ],
        [
            {
                "Institutionnels de l’investissement agréé de droit": "étranger"
            }
        ],
        [
            {
                "": "",
                "Catégorie d’investisseur": "Associations marocaines",
                "Document à joindre": ""
            },
            {
                "": "",
                "Catégorie d’investisseur": "",
                "Document à joindre": ""
            }
        ],
        [
            {
                "Nom :": "Prénom :",
                "": "",
                "Dénomination ou raison Sociale :": "Catégorie :"
            },
            {
                "Nom :": "Date de naissance :",
                "": "",
                "Dénomination ou raison Sociale :": "Siege social :"
            },
            {
                "Nom :": "Nationalité :",
                "": "",
                "Dénomination ou raison Sociale :": "Nationalité"
            },
            {
                "Nom :": "Numéro et nature pièce d’identité :",
                "": "",
                "Dénomination ou raison Sociale :": "Numéro et nature du document exigé :"
            },
            {
                "Nom :": "Adresse :",
                "": "",
                "Dénomination ou raison Sociale :": "Adresse :\nTéléphone :"
            },
            {
                "Nom :": "Téléphone :\nFax :",
                "": "",
                "Dénomination ou raison Sociale :": "Fax :\nSignature et fonction"
            },
            {
                "Nom :": "",
                "": "",
                "Dénomination ou raison Sociale :": ""
            }
        ]
    ]
}