{
    "text": "AVIS DE\nRÉUNION VALANT\nCONVOCATION\nAVIS DE RÉUNION VALANT CONVOCATION\nLes actionnaires de la société « LES EAUX MINERALES D’OULMES », société anonyme au capital de 198.000.000,00 de dirhams, sont convoqués,\nen Assemblée Générale Ordinaire, au siège social de la société Holding Marocaine Commerciale et Financière « HOLMARCOM », sis à Casablanca,\n20, rue Mostafa EL MAANI, le :\nMardi 14 mai 2024 à 10 heures\nÀ l’effet de délibérer sur l’ordre du jour suivant :\n1. Rapport de gestion du Conseil d’Administration sur les comptes et les opérations réalisées durant l’exercice clos le 31 décembre 2023 ;\n2. Rapport des Commissaires aux Comptes concernant le même exercice ;\n3. Rapport spécial des Commissaires aux Comptes sur les conventions réglementées visées à l’article 56 de la Loi 17-95 ;\n4. Approbation des comptes et opérations de l’exercice ; Affectation du résultat ;\n5. Approbation, s’il y a lieu, des conventions visées à l’article 56 de la Loi 17-95 ;\n6. Quitus aux administrateurs et décharge aux Commissaires aux Comptes ;\n7. Renouvellement des mandats de trois Administrateurs de la Société ;\n8. Mandats des Commissaires aux comptes de la Société ;\n9. Allocation de jetons de présence au Conseil d’Administration ;\n10. Pouvoirs pour accomplissement des formalités légales.\nLes actionnaires peuvent assister à cette Assemblée sur simple justification de leur identité, à la condition, soit d’être inscrits sur les registres sociaux\nau moins cinq jours avant l’Assemblée, s’ils sont titulaires d’actions nominatives, soit de produire un certificat attestant le dépôt de leurs actions\nauprès d’un établissement agréé, s’ils sont titulaires d’actions au porteur.\nUn actionnaire empêché d’assister à cette Assemblée peut s’y faire représenter par un autre actionnaire, par son tuteur, par son conjoint ou par un\nascendant ou descendant ou par une personne morale ayant pour objet social la gestion de portefeuilles de valeurs mobilières. Il peut également\nexercer son droit de vote par correspondance.\nDes formules de procuration et de vote par correspondance sont à la disposition des actionnaires au siège social et seront disponibles sur le\nsite internet www.oulmes.ma conformément aux dispositions de la loi n° 17-95 telle que modifiée et complétée. Ces formulaires doivent être\naccompagnés de l’attestation de blocage des actions et de la pièce d’identité de l’actionnaire concerné. Ils doivent être adressés par courriel, à\nl’adresse assembleegenerale@oulmes.ma, ou au moins deux (2) jours francs avant la tenue de l’Assemblée générale afin d’être pris en compte,\nsoit au plus tard le 09 mai 2024.\nTout actionnaire a le droit de prendre connaissance, au siège social, des documents dont la communication est prescrite par l’article 141 de la loi\n17-95 telle que modifiée et complétée.\nConformément à l’article 121 de la loi 17-95 telle que modifiée et complétée, les actionnaires détenteurs du pourcentage d’actions prévu par l’article\n117 de la même loi, disposent d’un délai de 10 jours à compter de la publication du présent avis pour demander, par lettre recommandée adressée\nau siège social, l’inscription de projets de résolutions à l’ordre du jour de l’Assemblée.\nCet avis ainsi que le texte des projets de résolutions seront publiés, conformément aux dispositions de la loi n° 17-95 telle que modifiée et complétée,\nsur le site internet www.oulmes.ma.\nPREMIÈRE RÉSOLUTION\nL’Assemblée Générale, après avoir entendu les explications du Conseil d’Administration et la lecture du rapport des Commissaires aux Comptes,\napprouve intégralement les comptes de l’exercice clos le 31 décembre 2023 tels qu’ils résultent du Bilan et du Compte de Produits et Charges arrêtés\nà cette date et qui présentent un bénéfice net comptable de 73.975.309,16 dirhams.\nDEUXIÈME RÉSOLUTION\nL’Assemblée Générale décide d’affecter le bénéfice net comptable de l’exercice, soit 73.975.309,16 dirhams, comme suit :\nBénéfice net de l’exercice (DH) : 73.975.309,16\n-\nDotation à la Réserve Légale : Néant\n(Entièrement dotée)\nSolde (DH) : 73.975.309,16\n+\nReport à nouveau antérieur : 118.425.503,75\nBénéfice distribuable (DH) : 192.400.812,91\n-\nDividendes (DH) : 43.560.000,00\nLe reste (DH) : 148.840.812,91\nÀ affecter au crédit du compte report à nouveau.\nSoit un dividende de 22,00 dirhams par action que l’Assemblée Générale décide de mettre en paiement à compter du 17 juin 2024.\nTROISIÈME RÉSOLUTION :\nL’Assemblée Générale, après avoir entendu la lecture du rapport spécial des Commissaires aux Comptes sur les conventions relevant de l’article 56\nde la Loi 17-95 sur la société anonyme, approuve chacune des opérations et conventions qui y sont mentionnées.\nQUATRIÈME RÉSOLUTION :\nL’Assemblée Générale donne quitus entier et définitif de sa gestion au Conseil d’Administration pour l’exercice clos le 31 décembre 2023.\nElle donne également décharge de leur mission aux Commissaires aux Comptes pour le même exercice.\nCINQUIÈME RÉSOLUTION\nL’Assemblée Générale constate que les mandats de trois (3) administrateurs, à savoir :\n• HOLMARCOM, dont le représentant permanent est M. Mohamed Hassan BENSALAH ;\n• OMI, dont le représentant permanent est M. Karim CHIOUAR ;\n• ATLANTASANAD, dont le représentant permanent est M. Jalal BENCHEKROUN.\narrivent à expiration à l’issue de la présente Assemblée Générale.\nElle décide, conformément aux dispositions de la loi et des statuts, de renouveler leurs mandats pour une durée de trois (3) années, qui expirera à\nl’issue de l’Assemblée Générale Ordinaire qui sera appelée à statuer sur les comptes de l’exercice clos le 31 décembre 2026.\nSIXIÈME RÉSOLUTION\nL’Assemblée Générale constatant que les mandats des cabinets ERNST & YOUNG et FIDAROC GRANT THORNTON, Commissaires aux comptes\nde la Société, arrivent à expiration à l’issue de la présente Assemblée, décide, conformément aux dispositions légales limitant la durée des mandats\nà un maximum de 12 ans, de ne pas les renouveler.\nElle nomme, en qualité de Commissaires aux Comptes de la Société, le cabinet MAZARS sis à Casablanca, Avia Business Center, Boulevard Sidi\nAbdellah Cherif, Anfa et le cabinet HDID Consultants sis à Casablanca, 4, Rue Maati Jazouli (Ex rue Friol).\nLes cabinets MAZARS et HDID Consultants sont nommés pour une durée de trois (3) années correspondant aux exercices sociaux 2024,2025 et\n2026.\nL’Assemblée Générale donne tous pouvoirs au Président Directeur Général pour fixer avec les Commissaires aux Comptes le montant de leurs\nhonoraires annuels.\nSEPTIÈME RÉSOLUTION\nL’Assemblée Générale décide d’allouer, au Conseil d’Administration, pour l’exercice en cours, des jetons de présence d’un montant brut de 1.450.000,00\ndirhams.\nIl appartiendra au Conseil d’Administration de les répartir entre ses membres dans les proportions qu’il jugera convenables.\nHUITIÈME RÉSOLUTION\nL’Assemblée Générale donne tous pouvoirs au porteur d’un exemplaire, d’un extrait ou d’une copie du présent procès-verbal pour accomplir les\nformalités prévues par la Loi.\nLE CONSEIL D’ADMINISTRATION\nÀ propos de “Les Eaux Minérales d’Oulmès”\nCréée en 1933, Les Eaux Minérales d’Oulmès est une société anonyme cotée à la bourse de Casablanca depuis Pour information :\n1943, leader marocain de l’hydratation saine et des boissons rafraîchissantes. Avec plus de 2 000 collaborateurs\nNabil SAID\net 8 sites de production, LEMO œuvre continuellement pour offrir à ses clients des produits de qualité supérieure.\nDirecteur Financier & Juridique\nEngagée dans une croissance durable et responsable, LEMO est membre du « Global Compact » des Nations\nUnies et est détentrice de plusieurs Labels RSE nationaux et internationaux. Acteur international, la société opère nsaid@oulmes.ma\négalement en Afrique subsaharienne, à travers sa filiale E.T.E. située au Bénin. Les Eaux Minérales d’Oulmès est une\nfiliale du groupe Holmarcom.\nÉTATS FINANCIERS CONSOLIDÉS\nEXERCICE CLOS LE 31 DÉCEMBRE 2023\nBILAN ACTIF (en milliers de dirhams) BILAN PASSIF (en milliers de dirhams)\nACTIF 31/12/2023 31/12/2022 PASSIF 31/12/2023 31/12/2022\nActif Non Courant 1 848 777 1 580 126 Capitaux Propres Part du Groupe 706 983 673 334\nCapital 198 000 198 000\nÉcart d’Acquisition 1 700 3 401\nPrime d’émission 166 980 166 980\nImmobilisations en non valeur - -\nRéserves 278 825 247 399\nImmobilisations Incorporelles 14 215 15 508 Résultat net de l’exercice 63 923 60 891\nImmobilisations Corporelles 1 819 785 1 545 901 Écart de conversion -745 64\nIntérêts Minoritaires 18 220 14 855\nImmobilisations Financières 12 943 15 149\nCapitaux propres de l’ensemble consolidé 725 204 688 189\nTitres mis en équivalence - -\nPassif Non Courant 1 102 907 868 511\nImpôts Différés Actif 133 168 Emprunts et Dettes Financières 1 054 224 831 077\nImpôts Différés Passif 47 977 36 712\nActif Courant 1 154 320 1 110 148\nProvisions durables pour risques et charges 706 721\nStocks et Encours 314 113 313 386\nPassif Courant 1 174 987 1 133 574\nClients et Comptes Rattachés 434 218 458 431 Fournisseurs et Comptes Rattachés 265 494 343 060\nAutres Créances et Comptes de Régularisation 286 641 220 485 Autres Dettes et Comptes de Régularisation 505 068 351 602\nValeurs Mobilières de Placement 890 58 Autres provisions pour risques et charges 5 105 11 450\nÉcarts de conversion - Passif - -\nDisponibilités 118 458 117 788\nTrésorerie - Passif 399 319 427 463\nTOTAL DE L’ACTIF 3 003 097 2 690 275 TOTAL DU PASSIF 3 003 097 2 690 275\nCOMPTE DE PRODUITS ET CHARGES (HORS TAXES) TABLEAU DES FLUX DE TRÉSORERIE\n(en milliers de dirhams) 31/12/2023 31/12/2022 (en milliers de dirhams) 31/12/2023 31/12/2022\nPRODUITS D’EXPLOITATION 2 660 646 2 201 023 Flux de trésorerie liés à l’activité\nRésultat net des sociétés consolidées 67 288 61 826\nChiffre d’affaires 2 624 900 2 195 729\nÉlimination des charges et produits sans incidence sur la trésorerie ou non liés à l’activité\nAutres produits d’exploitation 35 746 5 294\n- D otations aux amortissements et aux provisions nettes des reprises 237 856 194 550\nCHARGES D’EXPLOITATION 2 477 552 2 084 266\n- Variation des impôts différés -36 565\nAchats consommés 1 008 544 833 521\n- Plus-values de cession, nettes d’impôt -13 848 -1 098\nCharges externes 696 110 574 196 - Quote-part dans le résultat des sociétés mises en équivalence\nImpôts et taxes 227 590 201 430 Capacité d’autofinancement des sociétés intégrées 254 732 255 278\nCharges de personnel 305 300 266 351 Dividendes reçus des sociétés mises en équivalence\nAutres charges d’exploitation 8 781 6 214 Variation du besoin en fonds de roulement lié à l’activité 37 338 -49 218\nFlux nets de trésorerie générés par l’activité 292 070 206 060\nDotations d’exploitation 231 227 202 553\nFlux de trésorerie liés aux opérations d’investissement\nRÉSULTAT D’EXPLOITATION (I-II) 183 095 116 758\nAcquisition d’immobilisations -471 607 -260 528\nCHARGES ET PRODUITS FINANCIERS -65 011 -41 862\nCession d’immobilisations 8 384 1 187\nRÉSULTAT COURANT DES ENTREPRISES INTÉGRÉES 118 084 74 896\nIncidence des variations de périmètre\nCHARGES ET PRODUITS NON COURANTS -8 242 2 539 Flux nets de trésorerie liés aux opérations d’investissement -463 223 -259 341\nImpôts sur les résultats 41 188 24 440 Flux de trésorerie liés aux opérations de financement\nImpôts sur les résultats différés -335 -10 532 Dividendes versés aux actionnaires -36 314 -25 498\nRÉSULTAT NET DES ENTREPRISES INTÉGRÉES 68 989 63 526 Émission de prêts nets des remboursements 1 861\nSubvention d’investissement 9 800 5 838\nQuote part des résultats des entreprises mises en équivalence - -\nAugmentation de capital en numéraire 1 750\nDotations aux amortissements des écarts d’acquisition 1 700 1 700\nÉmissions d’emprunts nets des remboursements 225 476 -24 319\nReprises sur écarts d’acquisition négatif - -\nFlux nets de trésorerie liés aux opérations de financement 200 712 -42 119\nRÉSULTAT NET DE L’ENSEMBLE CONSOLIDÉ 67 288 61 826\nIncidence des variations des monnaies étrangères -745\nINTÉRÊTS MINORITAIRES 3 365 935\nVariation de trésorerie nette 28 814 -95 400\nRÉSULTAT NET PART DU GROUPE 63 923 60 891 Trésorerie nette d’ouverture -309 675 -214 276\nRésultat par action en DH 32,28 30,75 Trésorerie nette de clôture -280 861 -309 675\nTABLEAU DE VARIATION DES CAPITAUX PROPRES\n(en milliers de dirhams) Capital Primes d’émission Réserves consolidées Résultat consolidé PG Intérêts minoritaires Écart de conversion Total\nCapitaux propres consolidés au 31/12/2022 198 000 166 980 247 400 60 891 14 855 64 688 190\nAffectation du résultat 2022 60 891 -60 891 -\nDistribution par la société consolidante -32 670 -32 670\nDistributions versées aux minoritaires -\nVariation de périmètre -\nRésultat consolidé 2023 63 923 3 365 67 288\nOpérations sur capital 14 483 14 483\nÉcart de conversion -809 -809\nAutres éléments * -11 279 -11 279\nCapitaux propres consolidés au 31/12/2023 198 000 166 980 278 825 63 923 18 221 -745 725 204\n(*) Traitement rétrospectif du changement d’estimation liée à l’impôt différé sur les retraitements de consolidation constatés au 31.12.2022, (taux d’imposition prospectif de 32% au lieu de 24,5%).\nÉTATS FINANCIERS CONSOLIDÉS\nEXERCICE CLOS LE 31 DÉCEMBRE 2023\nNOTE 1 : DESCRIPTION DE L’ACTIVITÉ D-CONVERSION DES ÉTATS FINANCIERS DES FILIALES ÉTRANGÈRES\nLes Eaux Minérales d’Oulmès S.A. (LEMO), société anonyme au capital social de 198.000.000 de Dirhams, La monnaie fonctionnelle d’une entité est la monnaie de l’environnement économique dans lequel cette\na été créée le 7 mars 1934 sous la dénomination « Compagnie Fermière des Eaux Minérales d’Oulmès- entité opère principalement. Le Dirham est la monnaie de fonctionnement du Groupe. Ainsi, les comptes\nEtat » et dont le siège social est établi dans la zone industrielle de BOUSKOURA à Casablanca. Les Eaux des filiales installées à l’étranger ont été convertis en MAD la monnaie de présentation.\nMinérales d’Oulmès fait partie du groupe HOLMARCOM.\nE- DATE DE CLÔTURE DES EXERCICES\nLes domaines d’activité des Eaux minérales d’Oulmès couvrent le captage, la production, la mise en Les résultats des sociétés consolidées correspondent à une période de 12 mois se terminant le 31\nbouteille et la commercialisation d’eaux minérales naturelles plates (Sidi Ali et Ain Atlas) et gazeuses décembre de chaque année.\n(Oulmès), la fabrication de préformes, ainsi que la mise en bouteille et la commercialisation d’eau de table\nToutes les sociétés entrant dans le périmètre de consolidation du Groupe ont établi des comptes arrêtés\n(Bahia).\nau 31 décembre 2023.\nLEMO est présent également à l’international via sa filiale ETE opérant au Bénin.\nF-COMPTES ET OPÉRATIONS RÉCIPROQUES\nNOTE 2 : RÈGLES ET MÉTHODES COMPTABLES Toutes les transactions intragroupes, ainsi que les actifs et passifs réciproques entre les sociétés consolidées\nA-PRINCIPES COMPTABLES par intégration globale sont éliminés. Il en est de même pour les résultats internes au Groupe (dividendes,\nLes comptes consolidés ont été établis en application de l’avis n°5 du Conseil National de la Comptabilité plus-values...).\n(CNC) du 26 mai 2005 et conformément aux dispositions de l’Annexe III.2.A. de la circulaire de l’AMMC qui\nLes soldes bilanciels, les produits et les charges résultant des transactions intragroupes sont éliminés lors\nfixe le contenu de l’information proforma et l’Annexe III.2.I. portant sur les États de synthèse semestriels.\nde la préparation des états financiers consolidés.\nB-MÉTHODES DE CONSOLIDATION\nG-RETRAITEMENTS DE CONSOLIDATION\nLes méthodes de consolidation appliquées dépendent du type de contrôle liant l’entreprise concernée à\n• Immobilisations en non-valeurs\nla maison-mère :\n• Intégration globale (IG) : Les immobilisations en non-valeurs, constituées des frais préliminaires et des charges à répartir, sont\nannulées en consolidation, ces immobilisations constituent des charges de l’exercice au cours duquel elles\nCette méthode est appliquée lorsque le Groupe détient un contrôle exclusif sur sa filiale. Le contrôle\nont été engagées, au même titre leurs amortissements sont annulés.\nexclusif est le pouvoir de diriger les politiques financières et opérationnelles d’une entreprise afin de tirer\navantage de ses activités. La méthode de l’intégration globale permet de répartir le résultat et les capitaux • Écarts de conversion\npropres entre les intérêts du Groupe et les intérêts hors Groupe (intérêts minoritaires). Les gains de change latents, comptabilisés en écarts de conversion passif dans le bilan devraient être\n• Intégration proportionnelle (IP) : enregistrés au compte de produits et charges au cours de la période à laquelle ils se rapportent. Aussi,\nles écarts de conversion actifs ont été annulés en contrepartie de la provision pour risques et charges\nCette méthode s’applique aux entreprises soumises au contrôle conjoint. Le contrôle conjoint est le\ncorrespondante.\npartage du contrôle d’une entreprise exploitée en commun par un nombre limité d’actionnaires, de sorte\nque les politiques financières et opérationnelles résultent de leur accord. La méthode de l’intégration • Immobilisations acquises par crédit-bail\nproportionnelle consiste à intégrer uniquement les pourcentages d’actifs, de passifs, de charges et de Les actifs détenus en vertu d’un contrat de crédit-bail devraient être comptabilisés au bilan sous forme\nproduits revenant aux seuls intérêts du Groupe. d’une immobilisation corporelle et d’un emprunt correspondant, au compte de produits et charges, sous\n• Mise en équivalence (MEE) : forme d’une dotation aux amortissements et d’une charge financière.\nCette méthode s’applique aux entreprises sur lesquelles le Groupe a une influence notable. L’influence • Écart d’acquisition\nnotable est le pouvoir de participer aux politiques financières et opérationnelles d’une entreprise sans en Les écarts d’acquisition représentent la différence entre le prix d’acquisition des titres des sociétés consolidées\ndétenir le contrôle. La méthode de la mise en équivalence consiste à valoriser les titres de participation de et la part du Groupe dans leur actif net à la date des prises de participations après comptabilisation des\nl’entreprise consolidée en fonction des capitaux propres de celle-ci, la quote-part de résultat de la filiale éventuelles plus ou moins-values latentes sur actifs identifiables. Lorsqu’ils sont positifs, ces écarts sont\nétant prise en compte dans le résultat consolidé. inscrits à l’actif du bilan consolidé sous la rubrique « écarts d’acquisition » et amortis sur une durée qui doit\nC-PÉRIMÈTRE ET RÈGLES DE CONSOLIDATION refléter aussi raisonnablement que possible les hypothèses retenues et les objectifs fixés et documentés\nlors de l’acquisition. Cependant, lorsque ces écarts sont négatifs, ces derniers sont inscrits en provision pour\nLe périmètre de consolidation comprend la société mère Les Eaux Minérales d’Oulmès et ses filiales :\nrisques et charges et repris sur une durée qui doit refléter aussi raisonnablement que possible les mêmes\nMéthode de % de %\nEntité Activité consolidation contrôle d’intérêt hypothèses retenues et les objectifs fixés et documentés lors de l’acquisition.\nCaptage, exploitation, industrie\nEau Technologie Intégration Les comptes consolidés du Groupe comprennent un écart d’acquisition suite à l’entrée en périmètre de la\net commerce de toutes sortes 55% 55%\nEnvironnement « ETE » de boissons globale filiale ETE, amorti sur une durée de 10 ans.\nOULMES DRINKS Extraire, fabriquer, importer, Intégration • Impôts différés\nexporter, embouteiller, promouvoir 100% 100%\nDEVELOPMENT « ODD » globale\net distribuer tout type de boissons Les impositions différées résultent de la neutralisation des différences temporaires introduites par les\nPromotion et distribution de tout règles fiscales et les retraitements d’homogénéisation qui ont une incidence sur la base taxable. Les actifs\nMise en\nORANGINA MAROC type de boissons appartenant au 34% 34% et passifs d’impôt différé sont évalués aux taux dont l’application est attendue sur l’exercice au cours\néquivalence\ngroupe Suntory Food & Beverages\nduquel l’actif sera réalisé ou le passif réglé.\nETE\n• Homogénéisation des durées d’amortissement des immobilisations corporelles :\nEau Technologie Environnement, société de droit béninois, détenue par Les Eaux Minérales d’Oulmès\ndans le cadre de la mise en œuvre de sa stratégie de développement en Afrique et plus particulièrement Le retraitement d’homogénéisation des durées d’amortissement des immobilisations corporelles consiste\nl’Afrique Sub-saharienne. Les comptes sociaux de la société ETE ont fait l’objet d’un audit d’un commissaire à harmoniser la durée d’amortissement de ces dites immobilisations en fixant une durée économique au\naux comptes pour les exercices 2017-2022 ayant servi de base aux travaux de consolidation. lieu d’une durée admise fiscalement.\nODD H- RÈGLES ET MÉTHODES D’ÉVALUATION\nOulmes Drinks Development, société créée au mois d’avril 2016 et détenue à 100% par les Eaux Minérales Les règles d’évaluation présidant à l’établissement des comptes consolidés sont les mêmes que celles\nd’Oulmes, avec un capital passant de MMAD 30 à 25,5 MMAD en 2023. La société a pour activité la appliquées pour les comptes annuels individuels et édictées par le Code Général de la Normalisation\nfabrication et la distribution de tout type de boissons. Elle devrait constituer le fournisseur exclusif Comptable (C.G.N.C.).\nd’Orangina Maroc.\nLes principales méthodes d’évaluation utilisées sont les suivantes :\nCourant 2023, la société a effectué une opération d’accordéon afin d’absorber les pertes cumulées, • Immobilisations incorporelles\nl’opération consistait en l’absorption des pertes cumulées via la réduction du capital de MMAD 22,8\nLes immobilisations incorporelles sont évaluées à leur coût d’acquisition (prix d’achat et frais accessoires)\npassant ainsi de MMAD 30 à MMAD 7,2 et l’augmentation du capital d’un montant de MMAD 18,2 par\nou à leur coût de production. Elles sont constituées essentiellement des brevets, licences, logiciels et droits\ncompensation de créances envers LEMO.\nsimilaires correspondant à des dépenses faites pour l’obtention de l’avantage représenté par la protection\nORANGINA MAROC accordée au bénéficiaire du droit d’utilisation. La durée d’amortissement de ces immobilisations s’étale\nOrangina Maroc, détenue par les Eaux Minérales d’Oulmès à hauteur de 34% depuis avril 2016. Elle sur 5 ans.\na essentiellement pour objet le commerce, la promotion et la distribution de tout type de boissons\n• Immobilisations incorporelles\nappartenant au groupe Suntory Food and Beverages. Il est à noter qu’Orangina Maroc n’a pas été\nconsolidée au titre de l’exercice 2022 car elle est en cours de liquidation. A leur entrée dans le patrimoine de la société, les immobilisations corporelles acquises à titre onéreux\nsont enregistrées à leur coût d‘acquisition, celles produites par l’entreprise pour elle-même, à leur coût de\nEn 2023, sortie des titres de participations de Orangina Maroc pour MMAD (7,4) suite à sa liquidation\nproduction. Ces coûts s’entendent hors TVA récupérable. L’amortissement des immobilisations corporelles\ncourant le deuxième semestre de l’exercice 2023. Il est à noter que le titre de OM était totalement déprécié\nest calculé sur la valeur d’origine du bien dans la limite des taux indiqués par l’administration fiscale et\ndans les comptes de LEMO.\nadmis par l’usage de la profession.\n• Stock\nLes stocks des matières premières sont évalués au coût d’achat et suivant la méthode du coût moyen\npondéré.\nLes Eaux Minérales d’Oulmès S.A. au capital de 198.000.000 DHS\nZ.I. Bouskoura 20180 - Casablanca\nwww.leseauxmineralesdoulmes.ma\nRAPPORT D’AUDIT SUR LES ÉTATS\nFINANCIERS CONSOLIDÉS\nEXERCICE DU 1ER JANVIER AU 31 DECEMBRE 2023\n1. Provision pour dépréciation des créances clients\nRisque identifié Notre réponse\nAu 31 décembre 2023, la valeur des créances Nos travaux ont notamment consisté à :\nclients nettes de provisions s’élève à 434,2\n37, Bd Abdellatif Ben Kaddour 7 2, 0 B 1d 6 0D r Cis as s aS bla lao nu ci a millions de dirhams. - P d’r ide en nd tr ie fi cac tio on nn ai ds es sa nc ce r éad ne cs e s pr co lic eé nd tsu re às\n20 050 Casablanca Maroc\nMaroc La détermination des créances à déprécier déprécier et de détermination du montant\nrequiert l’exercice du jugement de la direction des dépréciations à constater ;\nsur la base d’une analyse continue de\n- Tester le fonctionnement des contrôles dans\nAux Actionnaires de la société l’évolution du risque client.\nle cadre des procédures mises en œuvre\nLes Eaux Minérales d’Oulmès\nQuartier industriel Bouskoura Compte tenu du caractère significatif du poste pour déterminer le niveau des dépréciations\nCasablanca au regard du bilan du groupe, du jugement des créances clients ;\nnécessaire à l’estimation des créances à\n- Apprécier le caractère raisonnable des\ndéprécier, et de la conjoncture de crise actuelle,\nhypothèses retenues par la Direction pour\nRAPPORT DES COMMISSAIRES AUX COMPTES SUR LES ETATS FINANCIERS CONSOLIDES nous avons considéré que ce sujet constitue un\nEXERCICE DU 1er JANVIER AU 31 DECEMBRE 2023 point clé de l’audit. évaluer les dépréciations à constater ;\n- Examiner la correcte évaluation des\ndépréciations à constater selon la méthode\nOpinion de provisionnement du Groupe.\nNous avons effectué l'audit des états financiers consolidés de la société LES EAUX MINERALES\nD’OULMES et de ses filiales (Groupe LES EAUX MINERALES D’OULMES), qui comprennent le bilan\nconsolidé au 31 décembre 2023, ainsi que le compte de produits et charges consolidé, l’état consolidé Responsabilités de la direction et des responsables de la gouvernance à l’égard des états\ndes variations des capitaux propre, le tableau consolidé des flux de trésorerie pour l’exercice clos à financiers consolidés\ncette date, ainsi que les notes annexes y compris un résumé des principales méthodes comptables.\nCes états financiers consolidés font ressortir un montant de capitaux propres consolidés de KMAD\nLa direction est responsable de la préparation et de la présentation fidèle des états financiers consolidés\n725.204 dont un bénéfice net consolidé de KMAD 67.288.\nconformément au référentiel comptable en vigueur au Maroc, ainsi que du contrôle interne qu'elle\nNous certifions que les états financiers consolidés cités au premier paragraphe ci- dessus, sont réguliers considère comme nécessaire pour permettre la préparation d'états financiers consolidés exempts\net sincères et donnent dans tous leurs aspects significatifs, une image fidèle du patrimoine et de la d'anomalies significatives, que celles-ci résultent de fraudes ou d'erreurs.\nsituation financière du groupe au 31 décembre 2023, ainsi que du résultat de l’ensemble consolidé pour\nl’exercice clos à cette date, conformément au référentiel comptable en vigueur au Maroc. Lors de la préparation des états financiers consolidés, c’est à la direction qu’il incombe d’évaluer la\ncapacité du groupe à poursuivre son exploitation, de communiquer, le cas échéant, les questions se\nFondement de l’opinion rapportant à la continuité de l’exploitation et d’appliquer le principe comptable de continuité\nd’exploitation, sauf si la direction a l’intention de liquider le groupe ou de cesser son activité ou si aucune\nNous avons effectué notre audit selon les Normes de la Profession au Maroc. Les responsabilités qui autre solution réaliste ne s’offre à elle.\nnous incombent en vertu de ces normes sont plus amplement décrites dans la section « Responsabilités\nde l’auditeur à l’égard de l’audit des états financiers consolidés » du présent rapport. Nous sommes Il incombe aux responsables de la gouvernance de surveiller le processus d’information financière de\nindépendants du groupe conformément aux règles de déontologie qui s’appliquent à l’audit des états du groupe.\nfinanciers au Maroc et nous nous sommes acquittés des autres responsabilités déontologiques qui nous\nincombent selon ces règles. Nous estimons que les éléments probants que nous avons obtenus sont Responsabilités de l’auditeur à l’égard de l’audit des états financiers consolidés\nsuffisants et appropriés pour fonder notre opinion d’audit.\nNos objectifs sont d’obtenir l’assurance raisonnable que les états financiers consolidés pris dans leur\nQuestions clés de l’audit\nensemble sont exempts d’anomalies significatives, que celles-ci résultent de fraudes ou d’erreurs et de\nLes questions clés de l’audit sont les questions qui, selon notre jugement professionnel, ont été les plus délivrer un rapport de l’auditeur contenant notre opinion.\nimportantes dans l’audit des états financiers consolidés de la période considérée. Ces questions ont été\ntraitées dans le contexte de notre audit des états financiers consolidés pris dans leur ensemble et aux L’assurance raisonnable correspond à un niveau élevé d’assurance, qui ne garantit toutefois pas qu’un\nfins de la formation de notre opinion sur ceux-ci, et nous n’exprimons pas une opinion distincte sur ces audit réalisé conformément aux normes de la profession au Maroc permettra toujours de détecter toute\nquestions. anomalie significative qui pourrait exister. Les anomalies peuvent résulter de fraudes ou d’erreurs et\nelles sont considérées comme significatives lorsqu’il est raisonnable de s’attendre à ce que,\nindividuellement ou collectivement, elles puissent influer sur les décisions économiques que les\nutilisateurs des états financiers consolidés prennent en se fondant sur ceux-ci.\n1\nDans le cadre d’un audit réalisé conformément aux normes de la profession au Maroc, nous exerçons 2\nnotre jugement professionnel et faisons preuve d’esprit critique tout au long de cet audit. En outre :\n nous identifions et évaluons les risques que les états financiers consolidés comportent des\nanomalies significatives, que celles-ci résultent de fraudes ou d’erreurs, concevons et mettons en\nœuvre des procédures d’audit en réponse à ces risques, et réunissons des éléments probants\nsuffisants et appropriés pour fonder notre opinion. Le risque de non-détection d’une anomalie\nsignificative résultant d’une fraude est plus élevé que celui d’une anomalie significative résultant\nd’une erreur, car la fraude peut impliquer la collusion, la falsification, les omissions volontaires, les\nfausses déclarations ou le contournement du contrôle interne ;\n nous acquérons une compréhension des éléments du contrôle interne pertinents pour l’audit afin\nde concevoir des procédures d’audit appropriées aux circonstances, et non dans le but d’exprimer\nune opinion sur l’efficacité du contrôle interne du groupe ;\n nous apprécions le caractère approprié des méthodes comptables retenues et le caractère\nraisonnable des estimations comptables faites par la direction, de même que des informations y\nafférentes fournies par cette dernière ;\n nous tirons une conclusion quant au caractère approprié de l’utilisation par la direction du principe\ncomptable de continuité d’exploitation et, selon les éléments probants obtenus, quant à l’existence\nou non d’une incertitude significative liée à des événements ou situations susceptibles de jeter un\ndoute important sur la capacité du groupe à poursuivre son exploitation. Si nous concluons à\nl’existence d’une incertitude significative, nous sommes tenus d’attirer l’attention des lecteurs de\nnotre rapport sur les informations fournies dans les états financiers au sujet de cette incertitude ou,\nsi ces informations ne sont pas adéquates, d’exprimer une opinion modifiée. Nos conclusions\ns’appuient sur les éléments probants obtenus jusqu’à la date de notre rapport. Des événements ou\nsituations futurs pourraient par ailleurs amener le groupe à cesser son exploitation ;\n nous évaluons la présentation d’ensemble, la structure et le contenu des états financiers\nconsolidés, y compris les informations fournies dans les notes, et apprécions si les états financiers\nconsolidés représentent les opérations et événements sous-jacents d’une manière propre à donner\nune image fidèle.\n nous obtenons des éléments probants suffisants et appropriés concernant les informations\nfinancières des entités et activités du groupe pour exprimer une opinion sur les états financiers\nconsolidés. Nous sommes responsables de la direction, de la supervision et de la réalisation de\nl’audit du groupe. Nous assumons l’entière responsabilité de l’opinion d’audit.\nNous communiquons aux responsables de la gouvernance notamment l’étendue et le calendrier prévus\ndes travaux d’audit et nos constatations importantes, y compris toute déficience importante du contrôle\ninterne que nous aurions relevée au cours de notre audit.\nCasablanca, le 9 avril 2024\nLes Commissaires aux Comptes\nERNST & YOUNG FIDAROC GRANT THORNTON\nAbdeslam BERRADA ALLAM Faïçal MEKOUAR\nAssocié Associé\n3\nLes Eaux Minérales d’Oulmès S.A. au capital de 198.000.000 DHS\nZ.I. Bouskoura 20180 - Casablanca\nwww.leseauxmineralesdoulmes.ma\nCOMPTE DE PRODUITS ET CHARGES (Hors Taxes)\n(Montants en dhs) Exercice du 1 janvier 2023 au 31 décembre 2023\nOPÉRATIONS\nConcernant TOTAUX DE TOTAUX DE Propres à NATURE les exercices L’EXERCICE L’EXERCICE l’exercice précédents PRÉCÉDENT\n(1) (2) 3= 1 + 2\nNOITATIOLPXE\nI Produits d’exploitation\nVentes de marchandises (en l’état) 80 787 231 80 787 231 62 744 467\nVentes de biens et services produits 2 413 537 046 2 413 537 046 2 083 406 116\nChiffre d’affaires 2 494 324 277 - 2 494 324 277 2 146 150 583\nVariation de stocks de produits ( + ou -) (1) 11 446 786 11 446 786 3 505 773\nImmobilisations produites par l’entreprise pour elle-même - -\nSubventions d’exploitation - -\nAutres produits d’exploitation 6 756 744 6 756 744 -\nReprises d’exploitation : transferts de charges 8 107 212 8 107 212 1 052 587\nTOTAL I 2 520 635 019 - 2 520 635 019 2 150 708 943\nII Charges d’exploitation\nAchats revendus (2) de marchandises 79 872 508 79 872 508 69 964 769\nAchats consommés (2) de matières et fournitures 873 621 805 873 621 805 774 088 172\nAutres charges externes 687 537 779 687 537 779 556 182 741\nImpôts et taxes 217 868 573 48 632 217 917 205 193 438 189\nCharges de personnel 292 842 068 292 842 068 255 329 406\nAutres charges d’exploitation 1 450 001 1 450 001 1 700 004\nDotations d’exploitation 193 578 341 193 578 341 187 990 986\nTOTAL II 2 346 771 076 48 632 2 346 819 708 2 038 694 267\nIII RÉSULTAT D’EXPLOITATION ( I - II ) 173 863 944 -48 632 173 815 312 112 014 677\nREICNANIF\nIV Produits financiers\nP etro ad uu ti rt es s d te its r eti st r imes m d oe bp ia lisrt éi sc ipation - 2 123 841\nGains de change 6 082 820 6 082 820 1 850 715\nIntérêts et autres produits financiers 1 199 604 1 199 604 1 685 307\nReprises financières : transferts de charges 2 018 386 2 018 386 666 179\nTOTAL IV 9 300 811 - 9 300 811 6 326 042\nV Charges financières\nCharges d’intérêts 58 087 428 58 087 428 38 994 693\nPertes de change 4 031 353 4 031 353 3 393 937\nAutres charges financières - - -\nDotations financières 3 342 241 3 342 241 2 093 502\nTOTAL V 65 461 022 - 65 461 022 44 482 132\nVI RÉSULTAT FINANCIER ( IV - V ) -56 160 211 - -56 160 211 -38 156 090\nVII RÉSULTAT COURANT ( III + VI ) 117 703 732 -48 632 117 655 100 73 858 587\nTNARUOC\nNON\nBILAN ACTIF\n31-déc-23 31-déc-22\n(Montants en dhs)\nBrut Amortissement Net Net\nVIII Produits non courants\nProduits de cessions d’immobilisations 71 940 71 940 1 119 472\nSubvention d’équilibre - - -\nReprises sur subventions d’investissement - - -\nAutres produits non courants 4 399 647 4 399 647 5 947 507\nReprises non courantes : transferts de charges 31 866 800 31 866 800 -\nTOTAL VIII 36 338 388 - 36 338 388 7 066 980\nIX Charges non courantes\nV dea sle iu mrs m n oe bt it le iss a d ti’ oa nm so cr éti ds ése em s ent 13 904 768 - 13 904 768 21 220\nSubventions accordées - - - -\nAutres charges non courantes 23 712 546 4 399 724 28 112 270 3 974 653\nDotations non courantes aux - - - 510 394\namortissements et aux provisions\nTOTAL IX 37 617 313 4 399 724 42 017 038 4 506 268\nX RÉSULTAT NON COURANT ( VIII - IX ) -1 278 926 -4 399 724 -5 678 650 2 560 712 XI RÉSULTAT AVANT IMPÔTS ( VII+ ou - X) 116 424 807 -4 448 356 111 976 450 76 419 299\nXII IMPÔTS SUR LES RÉSULTATS 38 001 141 38 001 141 22 231 162\nXIII RÉSULTAT NET ( XI - XII ) 78 423 666 -4 448 356 73 975 309 54 188 137\nXIV TOTAL DES PRODUITS ( I + IV + VIII ) 2 566 274 217 0 2 566 274 217 2 164 101 965\nXV TOTAL DES CHARGES ( II + V + IX + XII ) 2 487 850 552 4 448 356 2 492 298 908 2 109 913 828\nXVI RÉSULTAT NET ( total produits - total charges ) 78 423 666 -4 448 356 73 975 309 54 188 137\nESILIBOMMI\nFITCA\nImmobilisations en non valeur (A) 74 193 964 52 594 255 21 599 708 25 664 272\nFrais préliminaires\nCharges à répartir 74 193 964 52 594 255 21 599 708 25 664 272\nPrimes de remboursement des obligations\nImmobilisations incorporelles (B) 37 692 496 23 695 041 13 997 455 15 262 514\nImmobilisations en recherche et développement\nBrevets, marques, droits et valeurs similaires 37 692 496 23 695 041 13 997 455 15 262 514\nFonds commercial\nAutres immobilisations incorporelles\nImmobilisations corporelles (C) 3 705 748 731 2 241 544 638 1 464 204 092 1 260 223 269\nTerrains 48 325 324 - 48 325 324 48 325 324\nConstructions 636 164 558 322 244 591 313 919 968 320 162 149\nInstallations techniques, matériel et outillage 2 589 649 032 1 842 691 862 746 957 170 587 153 057\nMatériel de transport 14 367 551 11 966 220 2 401 330 1 513 954\nMobilier de bureau, aménagements divers 80 669 051 64 641 966 16 027 085 18 348 476\nAutres immobilisations corporelles - - - -\nImmobilisations corporelles en cours 336 573 214 - 336 573 214 284 720 310\nImmobilisations financières (D) 62 597 390 3 000 000 59 597 390 85 149 373\nPrêts immobilisés - - - 27 197 450\nAutres créances financières 4 449 454 - 4 449 454 3 603 988\nTitres de participation 58 147 935 3 000 000 55 147 935 54 347 935\nAutres titres immobilisés\nÉcart de conversion - Actif (E) - - - -\nDiminution des créances immobilisées\nAugmentation des dettes financières\nTOTAL I (A+B+C+D+E) 3 880 232 580 2 320 833 935 1 559 398 646 1 386 299 428\nTNALUCRIC\nFITCA\nStocks (F) 290 467 831 4 344 461 286 123 370 288 821 189\nMarchandises 12 151 942 - 12 151 942 9 881 259\nMatières et fournitures consommables 247 227 716 4 344 461 242 883 255 259 298 542\nProduits en cours - - - -\nProduits intermédiaires et résiduels - - - -\nProduits finis 31 088 173 - 31 088 173 19 641 388\nCréances de l’actif circulant (G) 742 842 064 89 661 719 653 180 345 665 579 047\nFournisseurs débiteurs, avances & acomptes 166 049 345 - 166 049 345 77 312 025\nClients et comptes rattachés 468 135 661 80 172 426 387 963 236 457 661 162\nPersonnel 3 289 963 - 3 289 963 2 260 940\nÉtat 50 296 609 50 296 609 82 169 339\nComptes d’associés 13 401 499 - 13 401 499 17 993 688\nAutres débiteurs 22 829 939 9 489 294 13 340 645 8 598 413\nComptes de régularisation - Actif 18 839 050 18 839 050 19 583 479\nTitres et valeurs de placement (H) 58 000 58 000 58 000\nÉcarts de conversion - Actif (I) 417 357 417 357 2 093 502\nTOTAL II (F+G+H+I) 1 033 785 252 94 006 180 939 779 072 956 551 737\nEIREROSÉRT\nBILAN PASSIF\n(Montants en dhs) 31-déc-23 31-déc-22\nChèques et valeurs à encaisser 43 707 193 43 707 193 46 363 917 Banques, T.G et C.C.P 58 785 406 58 785 406 59 565 204\nCaisses, Régies d’avances et accréditifs 2 706 559 2 706 559 1 783 173\nTOTAL III 105 199 157 - 105 199 157 107 712 294\nTOTAL GÉNÉRAL 5 019 216 990 2 414 840 115 2 604 376 875 2 450 563 460\nTNENAMREP\nTNEMECNANIF\nFonds propres\nCapital social ou personnel ( 1) 198 000 000 198 000 000\nMoins : actionnaires, capital souscrit non appelé\nCapital appelé\ndont versé\nPrimes d’émission, de fusion , d’apport 166 980 000 166 980 000\nÉcarts de réévaluation\nRéserve légale 19 800 000 19 800 000\nAutres réserves 37 687 000 37 687 000\nReport à nouveau ( 2 ) 118 425 504 96 907 367\nRésultats nets en instance d’affectation ( 2) -\nRésultat net de l’exercice ( 2) 73 975 309 54 188 137\nTotal des capitaux propres (A) 614 867 813 573 562 504\nCapitaux propres assimilés (B) 14 874 109 5 451 955\nSubventions d’investissement 14 874 109 5 451 955\nProvisions réglementées\nDettes de financement (C) 984 065 950 801 478 526\nEmprunts obligataires 458 333 333 300 000 000\nAutres dettes de financement 525 732 616 501 478 526\nProvisions durables pour risques et charges (D) - -\nProvisions pour risques\nProvisions pour charges\nÉcart de conversion - Passif (E) - -\nAugmentation de créances immobilisées\nDiminution des dettes de financement\nTOTAL I ( A + B + C + D + E ) 1 613 807 872 1 380 492 985\nTNALUCRIC\nFISSAP\nDettes du passif circulant (F) 614 047 040 663 744 613\nFournisseurs et comptes rattachés 252 534 748 330 197 091\nClients créditeurs , avances et acomptes 15 356 549 13 468 816\nPersonnel 11 508 739 18 178 149\nOrganismes sociaux 20 281 086 16 227 676\nÉtat 296 738 521 271 820 722\nComptes d’associés 1 699 951 1 698 949\nAutres créanciers\nComptes de régularisation - Passif 15 927 447 12 153 211\nAutres provisions pour risques et charges (G) 1 462 185 9 538 330\nÉcarts de conversion - Passif ( éléments circulants ) (H) 266 949 2 482 626\nTOTAL II ( F + G + H ) 615 776 174 675 765 569\nEIREROSÉRT\nÉTATS FINANCIERS SOCIAUX\nEXERCICE CLOS LE 31 DÉCEMBRE 2023\nTrésorerie - Passif\nCrédits d’escompte 47 267 951 59 453 813\nCrédits de trésorerie 279 999 987 317 769 495\nBanques de régularisation 47 524 891 17 081 598\nTOTAL III 374 792 829 394 304 906\nTOTAL GÉNÉRAL ( I + II + III ) 2 604 376 875 2 450 563 460\n( 1 ) Capital personnel débiteur\n(2) Bénéficiaire (+) , déficitaire ( - )\nÉTAT DES SOLDES DE GESTION ( E S G )\nI TABLEAU DE FORMATION DES RÉSULTATS ( T F R )\nExercice du 1 janvier 2023\nau 31 décembre 2023 (Montants en dhs) EXERCICE EXERCICE PRÉCÉDENT\n1 Ventes de marchandises (en l’état ) 80 787 231 62 744 467\n2 - Achats revendus de marchandises 79 872 508 69 964 769\nI = MARGE BRUTE SUR VENTES EN L’ÉTAT 914 722 -7 220 302\n+ PRODUCTION DE L’ EXERCICE : (3 + 4 + 5 ) 2 424 983 832 2 086 911 889\n3 Ventes de biens et services produits 2 413 537 046 2 083 406 116\nII\n4 Variation de stocks de produits 11 446 786 3 505 773\n5 Immobilisations produites par l’entreprise pour elle-même - -\n- CONSOMMATION DE L’EXERCICE : ( 6 + 7 ) 1 561 159 584 1 330 270 913\nIII 6 Achats consommés de matières et fournitures 873 621 805 774 088 172\n7 Autres charges externes 687 537 779 556 182 741\nIV = VALEUR AJOUTÉE : ( I + II + III ) 864 738 970 749 420 675\n8 + Subventions d’exploitation - -\nV 9 - Impôts et taxes 217 917 205 193 438 189\n10 - Charges de personnel 292 842 068 255 329 406\n= EXCÉDENT BRUT D’EXPLOITATION ( E B E ) 353 979 697 300 653 079\n= OU INSUFFISANCE BRUTE D’EXPLOITATION ( I B E) - -\n11 + Autres produits d’exploitation 6 756 744 -\n12 - Autres charges d’exploitation 1 450 001 1 700 004\n13 + Reprises d’exploitation : transferts de charges 8 107 212 1 052 587\n14 - Dotations d’exploitation 193 578 341 187 990 986\nVI = RÉSULTAT D’EXPLOITATION ( + ou - ) 173 815 312 112 014 677\nVII RÉSULTAT FINANCIER -56 160 211 -38 156 090\nVIII = RÉSULTAT COURANT ( + ou - ) 117 655 100 73 858 587\nIX RÉSULTAT NON COURANT -5 678 650 2 560 712\n15 - Impôts sur les résultats 38 001 141 22 231 162\nX = RÉSULTAT NET DE L’EXERCICE ( + ou - ) 73 975 309 54 188 137\nII CAPACITÉ D’AUTOFINANCEMENT ( C A F ) - AUTOFINANCEMENT\nRésultat de l’exercice 73 975 309 54 188 137\n1 * Bénéfice 73 975 309 54 188 137\n* Perte\n2 + Dotations d’exploitation (1) 184 254 716 180 431 390\n3 + Dotations financières (1) 3 000 000\n4 + Dotations non courantes (1) - - 5 - Reprises d’exploitation (2) - -\n6 - Reprises financières (2)\n7 - Reprises non courantes (2) (3) - -\n8 - Produits des cessions des immobilisations 71 940 1 119 472\n9 + Valeurs nettes des immobilisations cédées 13 904 768 21 220\nI CAPACITÉ D’AUTOFINANCEMENT ( C.A.F ) 275 062 853 233 521 275\n10 - Distributions de bénéfices 32 670 000 23 760 000\nII AUTOFINANCEMENT 242 392 853 209 761 275\n(1) à l’exclusion des dotations relatives aux actifs et passifs circulants et à la trésorerie\n(2) à l’exclusion des reprises relatives aux actifs circulants et à la trésorerie\n(3) Y compris reprises sur subventions d’investissement\nÉTATS FINANCIERS SOCIAUX\nEXERCICE CLOS LE 31 DÉCEMBRE 2023\nTABLEAU DE FINANCEMENT DE L’EXERCICE\nI Synthèse des masses du bilan\nExercice du 1 janvier 2023\n(Montants en dhs)\nau 31 décembre 2023\nExercice Exercice Variation (a-b)\nMASSES précédent\n(a) (b) Emplois (c) Ressources (d)\n1 Financement permanent 1 613 807 872 1 380 492 985 233 314 887\n2 Moins actif immobilisé 1 559 398 646 1 386 299 428 173 099 218\n3 = Fonds de roulement fonctionnel (1-2) (A) 54 409 226 -5 806 444 - 60 215 670\n4 Actif circulant 939 779 072 956 551 737 16 772 666\n5 Moins passif circulant 615 776 174 675 765 569 59 989 395\n6 = Besoins de financement global (4-5) (B) 324 002 897 280 786 168 43 216 729 -\n7 = Trésorerie nette (actif-passif) (A - B) -269 593 671 -286 592 612 16 998 941 -\nII Emplois et Ressources\nEXERCICE EXERCICE PRÉCÉDENT\nEMPLOIS RESSOURCES EMPLOIS RESSOURCES\nRESSOURCES STABLES DE L’EXERCICE (FLUX)\nAUTOFINANCEMENT (A) - 242 392 853 - 209 761 275\nCapacité d’autofinancement - 275 062 853 - 233 521 275\n- Distribution de bénéfices - 32 670 000 - 23 760 000\nCESSIONS ET RÉDUCTIONS D’IMMOBILISATIONS (B) - 27 269 391 - 12 119 314\nCession d’immobilisations incorporelles - -\nCession d’immobilisations corporelles 71 940 1 119 472\nCession d’immobilisations financières\nRécupérations sur créances immobilisées 27 197 450 10 999 841\nAUGMENTATIONS DES CAPITAUX PROPRES ET ASSIMILÉS (C) - 9 422 155 - 5 451 955\nAugmentations de capital, apports - -\nSubventions d’investissement 9 422 155 5 451 955\nAUGMENTATIONS DES DETTES DE FINANCEMENT (D) 600 000 000 - 260 000 000\nI. TOTAL DES RESSOURCES STABLES (A+B+C+D) - 879 084 398 - 487 332 543\nEMPLOIS STABLES DE L’EXERCICE (FLUX)\nACQUISITIONS ET AUGMENTATIONS D’IMMOBILISATIONS (E) 393 543 469 233 794 681\nAcquisition d’immobilisations incorporelles 1 412 226 1 603 342\nAcquisition d’immobilisations corporelles 373 582 336 230 924 507\nAcquisition d’immobilisations financières 18 288 000 1 266 831\nAugmentation des créances immobilisées 260 907\nREMBOURSEMENTS DES CAPITAUX PROPRES (F) - -\nREMBOURSEMENTS DES DETTES DE FINANCEMENT (G) 417 412 576 292 133 532\nEMPLOIS EN NON VALEURS (H) 7 912 682 - 7 875 477\nII. TOTAL - EMPLOIS STABLES (E+F+G+H) 818 868 728 533 803 690 -\nIII. VARIATION DU BESOIN DE FINANCEMENT GLOBAL (BFG ) 43 216 729 - 36 432 880\nIV. VARIATION DE LA TRÉSORERIE 16 998 941 - 82 904 027\nTOTAL GÉNÉRAL 879 084 398 879 084 398 570 236 570 570 236 570\nÉTAT DES DÉROGATIONS\nExercice Clos au 31 décembre 2023\nINDICATION DES DÉROGATIONS JUSTIFICATIONS DES DÉROGATIONS INFLUENCE DES DÉROGATIONS SUR LE PATRIMOINE, LA SITUATION FINANCIÈRE ET LES RÉSULTATS\nI Dérogations aux principes comptables fondamentaux NÉANT NÉANT\nII Dérogations aux méthodes d’évaluation NÉANT NÉANT\nIII Dérogations aux règles d’établissement des états de synthèse NÉANT NÉANT\nÉTAT DES CHANGEMENTS DE MÉTHODES\nExercice Clos au 31 décembre 2023\nNATURE DES CHANGEMENTS JUSTIFICATION DU CHANGEMENT INFLUENCE SUR LE PATRIMOINE, LA SITUATION FINANCIÈRE ET LES RÉSULTATS\n\"I. Changements affectant les méthodes d'évaluation\" NÉANT NÉANT\n\"II. Changements affectant les règles de présentation\" NÉANT NÉANT\nTABLEAU DES IMMOBILISATIONS AUTRES QUE FINANCIÈRES\n(Montants en dhs) Exercice Clos au 31 décembre 2023\nAUGMENTATION DIMINUTION\nMONTANT\nNATURE MONTANT BRUT Production par BRUT\nDÉBUT EXERCICE Acquisition l’entreprise Virement Cession Retrait Virement FIN EXERCICE\npour elle-même\nIMMOBILISATION EN NON-VALEURS 63 897 992 7 912 682 - 2 383 290 - - - 74 193 964\n* Frais préliminaires - - - -\n* Charges à répartir sur plusieurs exercices 63 897 992 7 912 682 2 383 290 - 74 193 964\n* Primes de remboursement obligations - - - -\nIMMOBILISATIONS INCORPORELLES 36 280 270 1 412 226 - - - - - 37 692 496\n* Immobilisation en recherche et développement - - - -\n* Brevets, marques, droits et valeurs similaires 36 280 270 1 412 226 - 37 692 496\n* Fonds commercial - - - -\n* Autres immobilisations incorporelles - - - -\nIMMOBILISATIONS CORPORELLES 3 342 903 470 373 582 336 - 219 780 653 8 353 786 - 222 163 943 3 705 748 731\n* Terrains 48 325 324 - 48 325 324\n* Constructions 616 068 457 7 018 180 13 077 921 636 164 558\n* Installations techniques, matériel et outillage 2 303 011 842 88 141 656 206 702 732 8 207 198 2 589 649 032\n* Matériel de transport 12 896 896 1 601 142 130 487 14 367 551\n* Mobilier, matériel de bureau et aménagements 77 880 641 2 804 511 16 100 80 669 051\n* Autres immobilisations corporelles Informatiques - - -\n* Immobilisations corporelles en cours 284 720 310 274 016 847 222 163 943 336 573 214\nTABLEAU DES TITRES DE PARTICIPATION\n(Montants en dhs) Exercice Clos au 31 décembre 2023\nParticipation Prix Valeur Extraits des derniers états de synthèse de la société\nRaison sociale de la société Secteur d’activité Capital social au capital d’acquisition Comptable émettrice Produits inscrits au\nC P C de l’exercice\némettrice 1 2 en % global Nette Date de clôture Situation nette Résultat net 9\n3 4 5 6 7 8\nEau Technologie Environnement Captage, exploitation, industrie et commerce de toutes\n5 438 400 55% 22 762 339 22 762 339 31/12/2023 38 902 152 7 253 427 -\n“ETE” sortes de boissons\nOULMES DRINKS DEVELOPMENT Extraire fabriquer importer et exporter embouteiller\n25 500 000 100% 25 500 000 25 500 000 31/12/2023 26 193 166 693 314 -\n“ODD” promouvoir et distribuer tout type de boissons\nSÉNÉGAL WATER & BEVERAGES Extraire fabriquer importer et exporter embouteiller\n3 107 105 100% 3 107 105 3 107 105 31/12/2023 1 472 132 -322 432 -\nCOMPANY SA promouvoir et distribuer tout type de boissons\nSOCIÉTÉ AFRICAINE DES BOISSONS Extraire fabriquer importer et exporter embouteiller\n12 570 817 54% 6 778 491 3 778 491 31/12/2022 12 570 817 - -\nET EAUX MINÉRALES \"SABEM\" promouvoir et distribuer tout type de boissons\nTOTAL 46 616 322 - 58 147 935 55 147 935 - 79 138 267 7 624 309 -\nÉTATS FINANCIERS SOCIAUX\nEXERCICE CLOS LE 31 DÉCEMBRE 2023\nTABLEAU DES PROVISIONS\n(Montants en dhs) Exercice Clos au 31 décembre 2023\nMontant début Dotations Reprises\nNature Montant fin d’exercice\nd’exercice d’exploitation financières non courantes d’exploitation financières non courantes\n1 Provisions pour dépréciation de l’actif immobilisé 15 779 800 3 000 000 - - 15 779 800 3 000 000\n2 Provisions réglementées\n3 Provisions durables pour risques et charges\nSOUS TOTAL (A) 15 779 800 - 3 000 000 - - - 15 779 800 3 000 000\n4 Provisions pour dépréciation de l’actif circulant 90 498 627 9 324 765 5 817 212 94 006 180,38\n( hors trésorerie )(Clients et stocks)\n5 Autres provisions pour risques et charges 9 538 330 342 241 2 018 386 6 400 000 1 462 185\n(Écarts de conversion)\n6 Provisions pour dépréciation des comptes de trésorerie - - - - - - - -\nSOUS TOTAL (B) 100 036 957 9 324 765 342 241 - 5 817 212 2 018 386 6 400 000 95 468 365\nTOTAL ( A + B ) 115 816 757 9 324 765 3 342 241 - 5 817 212 2 018 386 22 179 800 98 468 365\nTABLEAU DES CRÉANCES\n(Montants en dhs) Exercice Clos au 31 décembre 2023\nANALYSE PAR ÉCHÉANCE AUTRE ANALYSE\nCRÉANCES TOTAL Échues et non Montants Montants sur l’État et Montants sur les Montants représentés\nPlus d’un an Moins d’un an\nrecouvrées en devises organismes publics entreprises liées par des effets\nDE L’ACTIF IMMOBILISÉ 4 449 454 4 449 454 - - - - - -\n* Prêts immobilisés\n* Autres créances financières 4 449 454 4 449 454\nDE L’ACTIF CIRCULANT 742 842 064 - 492 668 218 245 310 296 117 900 333 50 296 609 82 581 402 89 058 173\n* Fournisseurs débiteurs 166 049 345 166 049 345 90 197 647 26 500 000\n* Clients et comptes rattachés 468 135 661 236 919 503 231 216 159 10 793 359 15 299 982 89 058 173\n* Personnel 3 289 963 3 289 963\n* État 50 296 609 50 296 609 50 296 609\n* Comptes d’associés 13 401 499 13 401 499 13 401 499 13 401 499\n* Autres débiteurs 22 829 939 3 872 252 14 094 137 3 507 829 12 737 957\n* Comptes de régularisation - Actif 18 839 050 18 839 050 14 641 964\nTABLEAU DES DETTES\n(Montants en dhs) Exercice Clos au 31 décembre 2023\nANALYSE PAR ÉCHÉANCE Autres analyse\nDETTES TOTAL Échues et non Montants Montants sur l’État Montants sur les Montants représentés\nPlus d’un an Moins d’un an\nrecouvrées en devises et organismes publics entreprises liées par des effets\nDE FINANCEMENT 984 065 950 537 392 410 447 173 539 - - - - -\n* Emprunts obligataires 458 333 333 238 833 333 220 000 000\n* Autres dettes de financement 525 732 616 298 559 077 227 173 539\nDU PASSIF CIRCULANT 614 047 040 - 587 113 678 26 933 363 15 346 217 317 019 607 7 456 562 -33 434 109\n* Fournisseurs 252 534 748 225 601 385 26 933 363 15 346 217 1 032 558 -33 434 109\n* Clients créditeurs consignation 15 356 549 15 356 549\n* Personnel 11 508 739 11 508 739\n* Organismes sociaux 20 281 086 20 281 086 20 281 086\n* État 296 738 521 296 738 521 296 738 521\n* Comptes d’associés 1 699 951 1 699 951 1 699 951\n* Autres créanciers - - -\n* Comptes de régularisation - Passif 15 927 447 15 927 447 4 724 053\nTABLEAU DES SÛRETÉS RÉELLES DONNÉES OU REÇUES\nExercice Clos au 31 décembre 2023\nMONTANT COUVERT PAR LA NATURE DATE ET LIEU OBJET VALEUR COMPTABLE NETTE DE LA SÛRETÉ DONNÉE\nTIERS CRÉDITEURS OU DÉBITEURS\nSÛRETÉ (1) D’INSCRIPTION (2) (3) À LA DATE DE CLÔTURE\n* Sûretés données\nN É A N T\n* Sûretés reçues\n(1) Gage : 1- Hypothèque : 2- Nantissement : 3- Warrant : 4- Autres : 5- (à préciser)\n(2) préciser si la sûreté est donnée au profit d’entreprises ou de personnes tierces (sûretés données)\n(entreprises liées, associés, membres du personnel)\n(3) préciser si la sûreté reçue par l’entreprise provient de personnes tierces autres que le débiteur (sûretés reçues)\nENGAGEMENTS FINANCIERS REÇUS OU DONNÉS HORS OPÉRATIONS DE CRÉDIT-BAIL\n(Montants en dhs) Exercice Clos au 31 décembre 2023\nMONTANTS\nMONTANTS\nENGAGEMENTS DONNÉS EXERCICE\nEXERCICE\nPRÉCÉDENT\n* Avals et cautions\n* Engagements en matière de pensions de retraites et obligations similaires\n* Autres engagements donnés ( vis-à-vis de l'Administration des douanes ) 10 000 000 10 000 000\n* Garantie de restitution de paiement anticipé dans le cadre de l'accord de subvention conclu entre LEMO et L'UNOPS \"Bureau des Nations Unies pour les services d’appui aux projets\". 20 562 367 21 310 330\n* Une caution en faveur du MINURSO 202 489 202 489\n* Une caution définitive en faveur de la DPEFLCD* 10 000\n* Direction provinciale des Eaux et Forêts et à la Lutte Contre la Désertification\n* Une caution définitive en faveur de HCEFLCD* portant reconduction d'amodiation du droit de chasse 10 000\n* Haut commissariat aux Eaux et Forêts et à la Lutte Contre la Désertification\n* Une quittance subrogative dans le cadre du contrat d'affacturage avec la Banque Centrale Populaire 84 101 504 88 679 462\nTotal (1) 114 866 359 120 212 281\n(1) dont engagements à l'égard d'entreprises liées ……………….\nENGAGEMENTS REÇUS MONTANTS EXERCICE MONTANTS EXERCICE PRÉCÉDENT\n* Avals et cautions\nCaution bancaire: Limonades Sidi Bannour\nCaution bancaire: Yassine Boissons\nCautions solidaires 112 100 000 77 400 000\n* Autres engagements donnés\nTotal 112 100 000 77 400 000\n(1) Gage : 1- Hypothèque : 2- Nantissement : 3- Warrant : 4- Autres : 5- (à préciser)\n(2) préciser si la sûreté est donnée au profit d’entreprises ou de personnes tierces (sûretés données) (entreprises liées, associés, membres du personnel)\n(3) préciser si la sûreté reçue par l’entreprise provient de personnes tierces autres que le débiteur (sûretés reçues)\nÉTAT DES PASSIFS ÉVENTUELS\nExercice Clos au 31 décembre 2023\n* Conformément à la législation fiscale les exercices, 2020, 2021, 2022 et 2023 ne sont pas encore prescrit. Les déclarations fiscales des Eaux Minérales d’Oulmès au titre de l’impôt sur les sociétés (IS), de la TVA et de l’impôt sur les revenus salariaux (IR)\npeuvent faire l’objet de contrôle par l’administration et de rappels éventuels d’impôts, taxes.\n* Les déclarations sociales au titre de la CNSS peuvent faire l’objet de contrôle et de rappels éventuels de cotisations.\nRAPPORT GÉNÉRAL DES\nCOMMISSAIRES AUX COMPTES\nEXERCICE DU 1ER JANVIER AU 31 DECEMBRE 2023\n1. Provision pour dépréciation des créances clients\nRisque identifié Notre réponse\nAu 31 décembre 2023, les créances clients dont Nos travaux ont notamment consisté à :\nla valeur brute s’élève à 468,1 millions de - Prendre connaissance des procédures\ndirhams sont provisionnées à hauteur de 80,2 d’identification des créances clients à\n7, Bd Driss Slaoui millions de dirhams. déprécier et de détermination du montant\n3 27 0, 0B 5d 0 A Cb ad se al bla latif n B caen Kaddour 2 M0 a r1 o6 c0 Casablanca L rea q ud ieé rt te r l’m exin ea rcti io cn e dd ue s j ugc eré ma en nc te s d eà l a d dé ip reré ctc ioie nr - Tde es s td eé r p ler é foc nia ct tio ion ns n à e mco en ns t t da ete sr c ; ontrôles dans\nMaroc sur la base d’une analyse continue de le cadre des procédures mises en œuvre\nl’évolution du risque client. pour déterminer le niveau des dépréciations\nCompte tenu du caractère significatif du poste des créances clients ;\nau regard du bilan de la société, du jugement - Apprécier le caractère raisonnable des\nnécessaire à l’estimation des créances à hypothèses retenues par la Direction pour\nAux Actionnaires de la société déprécier, nous avons considéré que ce sujet évaluer les dépréciations à constater ;\nLes Eaux Minérales d’Oulmès S.A. constitue un point clé de l’audit. - Examiner la correcte évaluation des\nQuartier industriel Bouskoura dépréciations à constater selon la méthode\nCasablanca de provisionnement de la société.\n2. Evaluation des titres de participation\nRAPPORT GENERAL DES COMMISSAIRES AUX COMPTES Risque identifié Notre réponse\nEXERCICE DU 1er JANVIER AU 31 DECEMBRE 2023 Au 31 décembre 2023, la valeur nette des titres Nos travaux ont consisté à :\nde participation s’élève à 55,1 millions de - Prendre connaissance du processus mis en\nOpinion dirhams. Les titres de participation sont place par la direction dans le cadre des tests\nenregistrés à leur prix d’acquisition diminués de dépréciation;\nConformément à la mission qui nous a été confiée par votre Assemblée Générale, nous avons effectué d’une provision pour dépréciation, le cas - Examiner les hypothèses et les prévisions\nl'audit des états de synthèse ci-joints de la société LES EAUX MINERALES D’OULMES S.A., échéant. de croissance retenues au regard de\ncomprenant le bilan au 31 décembre 2023, le compte de produits et charges, l’état des soldes de Les techniques retenues par la direction pour l’environnement économique en les\ngestion, le tableau de financement pour l’exercice clos à cette date, ainsi que l’état des informations procéder à la valorisation nette de ces titres comparant aux données disponibles pour\ncomplémentaires (ETIC). Ces états de synthèse font ressortir un montant de capitaux propres et comportent une part significative de jugement l’industrie et aux tendances historiques\nassimilés de MAD 629.741.922 dont un bénéfice net de MAD 73.975.309. quant aux choix de la méthodologie et des récentes des participations;\nhypothèses utilisées. - Effectuer des tests de sensibilité sur la\nNous certifions que les états de synthèse cités au premier paragraphe ci-dessus sont réguliers et En raison du montant significatif des titres de valeur d’inventaire.\nsincères et donnent, dans tous leurs aspects significatifs, une image fidèle du résultat des opérations participation, et de l’importance du jugement de\nd M vie gI N ul’ eEe uRx re A ar Lc ui Ec MSe a é D roc ’o cO .u Ulé L Mai En Ssi Squ .Ae . d ae u la 3 1s i dtu éa ct eio mn b f ri en a 2n 0c 2iè 3r ,e ce ot n fd ou r mp éa mtri em no t in ae u d re é féla re s no tic ei lé t cé o mLE pS ta bE leA U eX n l d d da ’ e ’ i an sD uv di ter i ie tn tr .c etat si io ren d, e p no pou aur rs ti l ca a i pvd o aé n tit s oe nr cm o ci n on s ma it d mio én eré d ule ’ né vl pa a o lu iv na a t l te i cou ln ér\nFondement de l’opinion Responsabilités de la direction et des responsables de la gouvernance pour les états de\nsynthèse\nNous avons effectué notre audit selon les Normes de la Profession au Maroc. Les responsabilités qui\nnous incombent en vertu de ces normes sont plus amplement décrites dans la section « Responsabilités La direction est responsable de la préparation et de la présentation fidèle des états de synthèse,\nde l’auditeur à l’égard de l’audit des états de synthèse » du présent rapport. Nous sommes indépendants conformément au référentiel comptable en vigueur au Maroc, ainsi que du contrôle interne qu'elle\nde la société conformément aux règles de déontologie qui s’appliquent à l’audit des états de synthèse considère comme nécessaire pour permettre la préparation d'états de synthèse exempts d'anomalies\nau Maroc et nous nous sommes acquittés des autres responsabilités déontologiques qui nous significatives, que celles-ci résultent de fraudes ou d'erreurs.\nincombent selon ces règles. Nous estimons que les éléments probants que nous avons obtenus sont\nsuffisants et appropriés pour fonder notre opinion d’audit. Lors de la préparation des états de synthèse, c’est à la direction qu’il incombe d’évaluer la capacité de\nla société à poursuivre son exploitation, de communiquer, le cas échéant, les questions se rapportant à\nQuestions clés de l’audit la continuité de l’exploitation et d’appliquer le principe comptable de continuité d’exploitation, sauf si la\ndirection a l’intention de liquider la société ou de cesser son activité ou si aucune autre solution réaliste\nLes questions clés de l’audit sont les questions qui, selon notre jugement professionnel, ont été les plus ne s’offre à elle.\nimportantes dans l’audit des états de synthèse de la période considérée. Ces questions ont été traitées\ndans le contexte de notre audit des états de synthèse pris dans leur ensemble et aux fins de la formation Il incombe aux responsables de la gouvernance de surveiller le processus d’information financière de\nde notre opinion sur ceux-ci, et nous n’exprimons pas une opinion distincte sur ces questions. la société.\nResponsabilités de l’auditeur à l’égard de l’audit des états de synthèse\nNos objectifs sont d’obtenir l’assurance raisonnable que les états de synthèse pris dans leur ensemble\nsont exempts d’anomalies significatives, que celles-ci résultent de fraudes ou d’erreurs et de délivrer un\nrapport de l’auditeur contenant notre opinion.\nL’assurance raisonnable correspond à un niveau élevé d’assurance, qui ne garantit toutefois pas qu’un\naudit réalisé conformément aux normes de la profession au Maroc permettra toujours de détecter toute\nanomalie significative qui pourrait exister. Les anomalies peuvent résulter de fraudes ou d’erreurs et\nelles sont considérées comme significatives lorsqu’il est raisonnable de s’attendre à ce que,\n1\n2\nindividuellement ou collectivement, elles puissent influer sur les décisions économiques que les\nutilisateurs des états de synthèse prennent en se fondant sur ceux-ci.\nDans le cadre d’un audit réalisé conformément aux normes de la profession au Maroc, nous exerçons\nnotre jugement professionnel et faisons preuve d’esprit critique tout au long de cet audit. En outre :\n nous identifions et évaluons les risques que les états de synthèse comportent des anomalies\nsignificatives, que celles-ci résultent de fraudes ou d’erreurs, concevons et mettons en œuvre des\nprocédures d’audit en réponse à ces risques, et réunissons des éléments probants suffisants et\nappropriés pour fonder notre opinion. Le risque de non-détection d’une anomalie significative\nrésultant d’une fraude est plus élevé que celui d’une anomalie significative résultant d’une erreur,\ncar la fraude peut impliquer la collusion, la falsification, les omissions volontaires, les fausses\ndéclarations ou le contournement du contrôle interne ;\n nous acquérons une compréhension des éléments du contrôle interne pertinents pour l’audit afin\nde concevoir des procédures d’audit appropriées aux circonstances, et non dans le but d’exprimer\nune opinion sur l’efficacité du contrôle interne de la société ;\n nous apprécions le caractère approprié des méthodes comptables retenues et le caractère\nraisonnable des estimations comptables faites par la direction, de même que des informations y\nafférentes fournies par cette dernière ;\n nous tirons une conclusion quant au caractère approprié de l’utilisation par la direction du principe\ncomptable de continuité d’exploitation et, selon les éléments probants obtenus, quant à l’existence\nou non d’une incertitude significative liée à des événements ou situations susceptibles de jeter un\ndoute important sur la capacité de la société à poursuivre son exploitation. Si nous concluons à\nl’existence d’une incertitude significative, nous sommes tenus d’attirer l’attention des lecteurs de\nnotre rapport sur les informations fournies dans les états de synthèse au sujet de cette incertitude\nou, si ces informations ne sont pas adéquates, d’exprimer une opinion modifiée. Nos conclusions\ns’appuient sur les éléments probants obtenus jusqu’à la date de notre rapport. Des événements ou\nsituations futurs pourraient par ailleurs amener la société à cesser son exploitation ;\n nous évaluons la présentation d’ensemble, la structure et le contenu des états de synthèse, y\ncompris les informations fournies dans l’ETIC, et apprécions si les états de synthèse représentent\nles opérations et événements sous-jacents d’une manière propre à donner une image fidèle\nNous communiquons aux responsables de la gouvernance notamment l’étendue et le calendrier prévus\ndes travaux d’audit et nos constatations importantes, y compris toute déficience importante du contrôle\ninterne que nous aurions relevée au cours de notre audit.\nVérifications et informations spécifiques\nNous avons procédé également aux vérifications spécifiques prévues par la loi et nous nous sommes\nassurés notamment de la sincérité et de la concordance, des informations données dans le rapport de\ngestion du Conseil d'administration destiné aux actionnaires avec les états de synthèse de la société.\nCasablanca, le 9 avril 2024\nLes Commissaires aux Comptes\nERNST & YOUNG FIDAROC GRANT THORNTON\nAbdeslam BERRADA ALLAM Faïçal MEKOUAR\nAssocié Associé\n3\nLes Eaux Minérales d’Oulmès S.A. au capital de 198.000.000 DHS\nZ.I. Bouskoura 20180 - Casablanca\nwww.leseauxmineralesdoulmes.ma",
    "tables": [
        [
            {
                "AVIS DE\nRÉUNION VALANT\nCONVOCATION": "AVIS DE RÉUNION VALANT CONVOCATION\nLes actionnaires de la société « LES EAUX MINERALES D’OULMES », société anonyme au capital de 198.000.000,00 de dirhams, sont convoqués,\nen Assemblée Générale Ordinaire, au siège social de la société Holding Marocaine Commerciale et Financière « HOLMARCOM », sis à Casablanca,\n20, rue Mostafa EL MAANI, le :\nMardi 14 mai 2024 à 10 heures\nÀ l’effet de délibérer sur l’ordre du jour suivant :\n1. Rapport de gestion du Conseil d’Administration sur les comptes et les opérations réalisées durant l’exercice clos le 31 décembre 2023 ;\n2. Rapport des Commissaires aux Comptes concernant le même exercice ;\n3. Rapport spécial des Commissaires aux Comptes sur les conventions réglementées visées à l’article 56 de la Loi 17-95 ;\n4. Approbation des comptes et opérations de l’exercice ; Affectation du résultat ;\n5. Approbation, s’il y a lieu, des conventions visées à l’article 56 de la Loi 17-95 ;\n6. Quitus aux administrateurs et décharge aux Commissaires aux Comptes ;\n7. Renouvellement des mandats de trois Administrateurs de la Société ;\n8. Mandats des Commissaires aux comptes de la Société ;\n9. Allocation de jetons de présence au Conseil d’Administration ;\n10. Pouvoirs pour accomplissement des formalités légales.\nLes actionnaires peuvent assister à cette Assemblée sur simple justification de leur identité, à la condition, soit d’être inscrits sur les registres sociaux\nau moins cinq jours avant l’Assemblée, s’ils sont titulaires d’actions nominatives, soit de produire un certificat attestant le dépôt de leurs actions\nauprès d’un établissement agréé, s’ils sont titulaires d’actions au porteur.\nUn actionnaire empêché d’assister à cette Assemblée peut s’y faire représenter par un autre actionnaire, par son tuteur, par son conjoint ou par un\nascendant ou descendant ou par une personne morale ayant pour objet social la gestion de portefeuilles de valeurs mobilières. Il peut également\nexercer son droit de vote par correspondance.\nDes formules de procuration et de vote par correspondance sont à la disposition des actionnaires au siège social et seront disponibles sur le\nsite internet www.oulmes.ma conformément aux dispositions de la loi n° 17-95 telle que modifiée et complétée. Ces formulaires doivent être\naccompagnés de l’attestation de blocage des actions et de la pièce d’identité de l’actionnaire concerné. Ils doivent être adressés par courriel, à\nl’adresse assembleegenerale@oulmes.ma, ou au moins deux (2) jours francs avant la tenue de l’Assemblée générale afin d’être pris en compte,\nsoit au plus tard le 09 mai 2024.\nTout actionnaire a le droit de prendre connaissance, au siège social, des documents dont la communication est prescrite par l’article 141 de la loi\n17-95 telle que modifiée et complétée.\nConformément à l’article 121 de la loi 17-95 telle que modifiée et complétée, les actionnaires détenteurs du pourcentage d’actions prévu par l’article\n117 de la même loi, disposent d’un délai de 10 jours à compter de la publication du présent avis pour demander, par lettre recommandée adressée\nau siège social, l’inscription de projets de résolutions à l’ordre du jour de l’Assemblée."
            }
        ],
        [
            {
                "ÉTATS FINANCIERS CONSOLIDÉS\nEXERCICE CLOS LE 31 DÉCEMBRE 2023": "BILAN ACTIF (en milliers de dirhams) BILAN PASSIF (en milliers de dirhams)\nACTIF 31/12/2023 31/12/2022 PASSIF 31/12/2023 31/12/2022\nActif Non Courant 1 848 777 1 580 126 Capitaux Propres Part du Groupe 706 983 673 334\nCapital 198 000 198 000\nÉcart d’Acquisition 1 700 3 401\nPrime d’émission 166 980 166 980\nImmobilisations en non valeur - -\nRéserves 278 825 247 399\nImmobilisations Incorporelles 14 215 15 508 Résultat net de l’exercice 63 923 60 891\nImmobilisations Corporelles 1 819 785 1 545 901 Écart de conversion -745 64\nIntérêts Minoritaires 18 220 14 855\nImmobilisations Financières 12 943 15 149\nCapitaux propres de l’ensemble consolidé 725 204 688 189\nTitres mis en équivalence - -\nPassif Non Courant 1 102 907 868 511\nImpôts Différés Actif 133 168 Emprunts et Dettes Financières 1 054 224 831 077\nImpôts Différés Passif 47 977 36 712\nActif Courant 1 154 320 1 110 148\nProvisions durables pour risques et charges 706 721\nStocks et Encours 314 113 313 386\nPassif Courant 1 174 987 1 133 574\nClients et Comptes Rattachés 434 218 458 431 Fournisseurs et Comptes Rattachés 265 494 343 060\nAutres Créances et Comptes de Régularisation 286 641 220 485 Autres Dettes et Comptes de Régularisation 505 068 351 602\nValeurs Mobilières de Placement 890 58 Autres provisions pour risques et charges 5 105 11 450\nÉcarts de conversion - Passif - -\nDisponibilités 118 458 117 788\nTrésorerie - Passif 399 319 427 463\nTOTAL DE L’ACTIF 3 003 097 2 690 275 TOTAL DU PASSIF 3 003 097 2 690 275\nCOMPTE DE PRODUITS ET CHARGES (HORS TAXES) TABLEAU DES FLUX DE TRÉSORERIE\n(en milliers de dirhams) 31/12/2023 31/12/2022 (en milliers de dirhams) 31/12/2023 31/12/2022\nPRODUITS D’EXPLOITATION 2 660 646 2 201 023 Flux de trésorerie liés à l’activité\nRésultat net des sociétés consolidées 67 288 61 826\nChiffre d’affaires 2 624 900 2 195 729\nÉlimination des charges et produits sans incidence sur la trésorerie ou non liés à l’activité\nAutres produits d’exploitation 35 746 5 294\n- D otations aux amortissements et aux provisions nettes des reprises 237 856 194 550\nCHARGES D’EXPLOITATION 2 477 552 2 084 266\n- Variation des impôts différés -36 565\nAchats consommés 1 008 544 833 521\n- Plus-values de cession, nettes d’impôt -13 848 -1 098\nCharges externes 696 110 574 196 - Quote-part dans le résultat des sociétés mises en équivalence\nImpôts et taxes 227 590 201 430 Capacité d’autofinancement des sociétés intégrées 254 732 255 278\nCharges de personnel 305 300 266 351 Dividendes reçus des sociétés mises en équivalence\nAutres charges d’exploitation 8 781 6 214 Variation du besoin en fonds de roulement lié à l’activité 37 338 -49 218\nFlux nets de trésorerie générés par l’activité 292 070 206 060\nDotations d’exploitation 231 227 202 553\nFlux de trésorerie liés aux opérations d’investissement\nRÉSULTAT D’EXPLOITATION (I-II) 183 095 116 758\nAcquisition d’immobilisations -471 607 -260 528\nCHARGES ET PRODUITS FINANCIERS -65 011 -41 862\nCession d’immobilisations 8 384 1 187\nRÉSULTAT COURANT DES ENTREPRISES INTÉGRÉES 118 084 74 896\nIncidence des variations de périmètre\nCHARGES ET PRODUITS NON COURANTS -8 242 2 539 Flux nets de trésorerie liés aux opérations d’investissement -463 223 -259 341\nImpôts sur les résultats 41 188 24 440 Flux de trésorerie liés aux opérations de financement\nImpôts sur les résultats différés -335 -10 532 Dividendes versés aux actionnaires -36 314 -25 498\nRÉSULTAT NET DES ENTREPRISES INTÉGRÉES 68 989 63 526 Émission de prêts nets des remboursements 1 861\nSubvention d’investissement 9 800 5 838\nQuote part des résultats des entreprises mises en équivalence - -\nAugmentation de capital en numéraire 1 750\nDotations aux amortissements des écarts d’acquisition 1 700 1 700\nÉmissions d’emprunts nets des remboursements 225 476 -24 319\nReprises sur écarts d’acquisition négatif - -\nFlux nets de trésorerie liés aux opérations de financement 200 712 -42 119\nRÉSULTAT NET DE L’ENSEMBLE CONSOLIDÉ 67 288 61 826\nIncidence des variations des monnaies étrangères -745\nINTÉRÊTS MINORITAIRES 3 365 935\nVariation de trésorerie nette 28 814 -95 400\nRÉSULTAT NET PART DU GROUPE 63 923 60 891 Trésorerie nette d’ouverture -309 675 -214 276\nRésultat par action en DH 32,28 30,75 Trésorerie nette de clôture -280 861 -309 675\nTABLEAU DE VARIATION DES CAPITAUX PROPRES\n(en milliers de dirhams) Capital Primes d’émission Réserves consolidées Résultat consolidé PG Intérêts minoritaires Écart de conversion Total\nCapitaux propres consolidés au 31/12/2022 198 000 166 980 247 400 60 891 14 855 64 688 190\nAffectation du résultat 2022 60 891 -60 891 -\nDistribution par la société consolidante -32 670 -32 670\nDistributions versées aux minoritaires -\nVariation de périmètre -\nRésultat consolidé 2023 63 923 3 365 67 288\nOpérations sur capital 14 483 14 483\nÉcart de conversion -809 -809\nAutres éléments * -11 279 -11 279\nCapitaux propres consolidés au 31/12/2023 198 000 166 980 278 825 63 923 18 221 -745 725 204\n(*) Traitement rétrospectif du changement d’estimation liée à l’impôt différé sur les retraitements de consolidation constatés au 31.12.2022, (taux d’imposition prospectif de 32% au lieu de 24,5%)."
            }
        ],
        [
            {
                "BILAN ACTIF (en milliers de dirhams)": "ACTIF",
                "null": "31/12/2022"
            },
            {
                "BILAN ACTIF (en milliers de dirhams)": "Actif Non Courant",
                "null": "1 580 126"
            },
            {
                "BILAN ACTIF (en milliers de dirhams)": "Écart d’Acquisition",
                "null": "3 401"
            },
            {
                "BILAN ACTIF (en milliers de dirhams)": "Immobilisations en non valeur",
                "null": "-"
            },
            {
                "BILAN ACTIF (en milliers de dirhams)": "Immobilisations Incorporelles",
                "null": "15 508"
            },
            {
                "BILAN ACTIF (en milliers de dirhams)": "Immobilisations Corporelles",
                "null": "1 545 901"
            },
            {
                "BILAN ACTIF (en milliers de dirhams)": "Immobilisations Financières",
                "null": "15 149"
            },
            {
                "BILAN ACTIF (en milliers de dirhams)": "Titres mis en équivalence",
                "null": "-"
            },
            {
                "BILAN ACTIF (en milliers de dirhams)": "Impôts Différés Actif",
                "null": "168"
            },
            {
                "BILAN ACTIF (en milliers de dirhams)": "Actif Courant",
                "null": "1 110 148"
            },
            {
                "BILAN ACTIF (en milliers de dirhams)": "Stocks et Encours",
                "null": "313 386"
            },
            {
                "BILAN ACTIF (en milliers de dirhams)": "Clients et Comptes Rattachés",
                "null": "458 431"
            },
            {
                "BILAN ACTIF (en milliers de dirhams)": "Autres Créances et Comptes de Régularisation",
                "null": "220 485"
            },
            {
                "BILAN ACTIF (en milliers de dirhams)": "Valeurs Mobilières de Placement",
                "null": "58"
            },
            {
                "BILAN ACTIF (en milliers de dirhams)": "Disponibilités",
                "null": "117 788"
            },
            {
                "BILAN ACTIF (en milliers de dirhams)": "TOTAL DE L’ACTIF",
                "null": "2 690 275"
            }
        ],
        [
            {
                "BILAN PASSIF (en milliers de dirhams)": "PASSIF",
                "null": "31/12/2022"
            },
            {
                "BILAN PASSIF (en milliers de dirhams)": "Capitaux Propres Part du Groupe",
                "null": "673 334"
            },
            {
                "BILAN PASSIF (en milliers de dirhams)": "Capital",
                "null": "198 000"
            },
            {
                "BILAN PASSIF (en milliers de dirhams)": "Prime d’émission",
                "null": "166 980"
            },
            {
                "BILAN PASSIF (en milliers de dirhams)": "Réserves",
                "null": "247 399"
            },
            {
                "BILAN PASSIF (en milliers de dirhams)": "Résultat net de l’exercice",
                "null": "60 891"
            },
            {
                "BILAN PASSIF (en milliers de dirhams)": "Écart de conversion",
                "null": "64"
            },
            {
                "BILAN PASSIF (en milliers de dirhams)": "Intérêts Minoritaires",
                "null": "14 855"
            },
            {
                "BILAN PASSIF (en milliers de dirhams)": "Capitaux propres de l’ensemble consolidé",
                "null": "688 189"
            },
            {
                "BILAN PASSIF (en milliers de dirhams)": "Passif Non Courant",
                "null": "868 511"
            },
            {
                "BILAN PASSIF (en milliers de dirhams)": "Emprunts et Dettes Financières",
                "null": "831 077"
            },
            {
                "BILAN PASSIF (en milliers de dirhams)": "Impôts Différés Passif",
                "null": "36 712"
            },
            {
                "BILAN PASSIF (en milliers de dirhams)": "Provisions durables pour risques et charges",
                "null": "721"
            },
            {
                "BILAN PASSIF (en milliers de dirhams)": "Passif Courant",
                "null": "1 133 574"
            },
            {
                "BILAN PASSIF (en milliers de dirhams)": "Fournisseurs et Comptes Rattachés",
                "null": "343 060"
            },
            {
                "BILAN PASSIF (en milliers de dirhams)": "Autres Dettes et Comptes de Régularisation",
                "null": "351 602"
            },
            {
                "BILAN PASSIF (en milliers de dirhams)": "Autres provisions pour risques et charges",
                "null": "11 450"
            },
            {
                "BILAN PASSIF (en milliers de dirhams)": "Écarts de conversion - Passif",
                "null": "-"
            },
            {
                "BILAN PASSIF (en milliers de dirhams)": "Trésorerie - Passif",
                "null": "427 463"
            },
            {
                "BILAN PASSIF (en milliers de dirhams)": "TOTAL DU PASSIF",
                "null": "2 690 275"
            }
        ],
        [
            {
                "COMPTE DE PRODUITS ET CHARGES (HORS TAXES)": "(en milliers de dirhams)",
                "null": "31/12/2022"
            },
            {
                "COMPTE DE PRODUITS ET CHARGES (HORS TAXES)": "PRODUITS D’EXPLOITATION",
                "null": "2 201 023"
            },
            {
                "COMPTE DE PRODUITS ET CHARGES (HORS TAXES)": "Chiffre d’affaires",
                "null": "2 195 729"
            },
            {
                "COMPTE DE PRODUITS ET CHARGES (HORS TAXES)": "Autres produits d’exploitation",
                "null": "5 294"
            },
            {
                "COMPTE DE PRODUITS ET CHARGES (HORS TAXES)": "CHARGES D’EXPLOITATION",
                "null": "2 084 266"
            },
            {
                "COMPTE DE PRODUITS ET CHARGES (HORS TAXES)": "Achats consommés",
                "null": "833 521"
            },
            {
                "COMPTE DE PRODUITS ET CHARGES (HORS TAXES)": "Charges externes",
                "null": "574 196"
            },
            {
                "COMPTE DE PRODUITS ET CHARGES (HORS TAXES)": "Impôts et taxes",
                "null": "201 430"
            },
            {
                "COMPTE DE PRODUITS ET CHARGES (HORS TAXES)": "Charges de personnel",
                "null": "266 351"
            },
            {
                "COMPTE DE PRODUITS ET CHARGES (HORS TAXES)": "Autres charges d’exploitation",
                "null": "6 214"
            },
            {
                "COMPTE DE PRODUITS ET CHARGES (HORS TAXES)": "Dotations d’exploitation",
                "null": "202 553"
            },
            {
                "COMPTE DE PRODUITS ET CHARGES (HORS TAXES)": "RÉSULTAT D’EXPLOITATION (I-II)",
                "null": "116 758"
            },
            {
                "COMPTE DE PRODUITS ET CHARGES (HORS TAXES)": "CHARGES ET PRODUITS FINANCIERS",
                "null": "-41 862"
            },
            {
                "COMPTE DE PRODUITS ET CHARGES (HORS TAXES)": "RÉSULTAT COURANT DES ENTREPRISES INTÉGRÉES",
                "null": "74 896"
            },
            {
                "COMPTE DE PRODUITS ET CHARGES (HORS TAXES)": "CHARGES ET PRODUITS NON COURANTS",
                "null": "2 539"
            },
            {
                "COMPTE DE PRODUITS ET CHARGES (HORS TAXES)": "Impôts sur les résultats",
                "null": "24 440"
            },
            {
                "COMPTE DE PRODUITS ET CHARGES (HORS TAXES)": "Impôts sur les résultats différés",
                "null": "-10 532"
            },
            {
                "COMPTE DE PRODUITS ET CHARGES (HORS TAXES)": "RÉSULTAT NET DES ENTREPRISES INTÉGRÉES",
                "null": "63 526"
            },
            {
                "COMPTE DE PRODUITS ET CHARGES (HORS TAXES)": "Quote part des résultats des entreprises mises en équivalence",
                "null": "-"
            },
            {
                "COMPTE DE PRODUITS ET CHARGES (HORS TAXES)": "Dotations aux amortissements des écarts d’acquisition",
                "null": "1 700"
            },
            {
                "COMPTE DE PRODUITS ET CHARGES (HORS TAXES)": "Reprises sur écarts d’acquisition négatif",
                "null": "-"
            },
            {
                "COMPTE DE PRODUITS ET CHARGES (HORS TAXES)": "RÉSULTAT NET DE L’ENSEMBLE CONSOLIDÉ",
                "null": "61 826"
            },
            {
                "COMPTE DE PRODUITS ET CHARGES (HORS TAXES)": "INTÉRÊTS MINORITAIRES",
                "null": "935"
            },
            {
                "COMPTE DE PRODUITS ET CHARGES (HORS TAXES)": "RÉSULTAT NET PART DU GROUPE",
                "null": "60 891"
            },
            {
                "COMPTE DE PRODUITS ET CHARGES (HORS TAXES)": "Résultat par action en DH",
                "null": "30,75"
            }
        ],
        [
            {
                "TABLEAU DES FLUX DE TRÉSORERIE": "(en milliers de dirhams)",
                "null": "31/12/2022"
            },
            {
                "TABLEAU DES FLUX DE TRÉSORERIE": "Flux de trésorerie liés à l’activité",
                "null": ""
            },
            {
                "TABLEAU DES FLUX DE TRÉSORERIE": "Résultat net des sociétés consolidées",
                "null": "61 826"
            },
            {
                "TABLEAU DES FLUX DE TRÉSORERIE": "Élimination des charges et produits sans incidence sur la trésorerie ou non liés à l’activité",
                "null": ""
            },
            {
                "TABLEAU DES FLUX DE TRÉSORERIE": "- D otations aux amortissements et aux provisions nettes des reprises",
                "null": "194 550"
            },
            {
                "TABLEAU DES FLUX DE TRÉSORERIE": "- Variation des impôts différés",
                "null": ""
            },
            {
                "TABLEAU DES FLUX DE TRÉSORERIE": "- Plus-values de cession, nettes d’impôt",
                "null": "-1 098"
            },
            {
                "TABLEAU DES FLUX DE TRÉSORERIE": "- Quote-part dans le résultat des sociétés mises en équivalence",
                "null": ""
            },
            {
                "TABLEAU DES FLUX DE TRÉSORERIE": "Capacité d’autofinancement des sociétés intégrées",
                "null": "255 278"
            },
            {
                "TABLEAU DES FLUX DE TRÉSORERIE": "Dividendes reçus des sociétés mises en équivalence",
                "null": ""
            },
            {
                "TABLEAU DES FLUX DE TRÉSORERIE": "Variation du besoin en fonds de roulement lié à l’activité",
                "null": "-49 218"
            },
            {
                "TABLEAU DES FLUX DE TRÉSORERIE": "Flux nets de trésorerie générés par l’activité",
                "null": "206 060"
            },
            {
                "TABLEAU DES FLUX DE TRÉSORERIE": "Flux de trésorerie liés aux opérations d’investissement",
                "null": ""
            },
            {
                "TABLEAU DES FLUX DE TRÉSORERIE": "Acquisition d’immobilisations",
                "null": "-260 528"
            },
            {
                "TABLEAU DES FLUX DE TRÉSORERIE": "Cession d’immobilisations",
                "null": "1 187"
            },
            {
                "TABLEAU DES FLUX DE TRÉSORERIE": "Incidence des variations de périmètre",
                "null": ""
            },
            {
                "TABLEAU DES FLUX DE TRÉSORERIE": "Flux nets de trésorerie liés aux opérations d’investissement",
                "null": "-259 341"
            },
            {
                "TABLEAU DES FLUX DE TRÉSORERIE": "Flux de trésorerie liés aux opérations de financement",
                "null": ""
            },
            {
                "TABLEAU DES FLUX DE TRÉSORERIE": "Dividendes versés aux actionnaires",
                "null": "-25 498"
            },
            {
                "TABLEAU DES FLUX DE TRÉSORERIE": "Émission de prêts nets des remboursements",
                "null": "1 861"
            },
            {
                "TABLEAU DES FLUX DE TRÉSORERIE": "Subvention d’investissement",
                "null": "5 838"
            },
            {
                "TABLEAU DES FLUX DE TRÉSORERIE": "Augmentation de capital en numéraire",
                "null": ""
            },
            {
                "TABLEAU DES FLUX DE TRÉSORERIE": "Émissions d’emprunts nets des remboursements",
                "null": "-24 319"
            },
            {
                "TABLEAU DES FLUX DE TRÉSORERIE": "Flux nets de trésorerie liés aux opérations de financement",
                "null": "-42 119"
            },
            {
                "TABLEAU DES FLUX DE TRÉSORERIE": "Incidence des variations des monnaies étrangères",
                "null": ""
            },
            {
                "TABLEAU DES FLUX DE TRÉSORERIE": "Variation de trésorerie nette",
                "null": "-95 400"
            },
            {
                "TABLEAU DES FLUX DE TRÉSORERIE": "Trésorerie nette d’ouverture",
                "null": "-214 276"
            },
            {
                "TABLEAU DES FLUX DE TRÉSORERIE": "Trésorerie nette de clôture",
                "null": "-309 675"
            }
        ],
        [
            {
                "TABLEAU DE VARIATION DES CAPITAUX PROPRES": "(en milliers de dirhams) Capital Primes d’émission Réserves consolidées Résultat consolidé PG Intérêts minoritaires Écart de conversion Total",
                "null": ""
            },
            {
                "TABLEAU DE VARIATION DES CAPITAUX PROPRES": "Capitaux propres consolidés au 31/12/2022 198 000 166 980 247 400 60 891 14 855 64 688 190",
                "null": ""
            },
            {
                "TABLEAU DE VARIATION DES CAPITAUX PROPRES": "Affectation du résultat 2022 60 891 -60 891 -",
                "null": ""
            },
            {
                "TABLEAU DE VARIATION DES CAPITAUX PROPRES": "Distribution par la société consolidante -32 670 -32 670",
                "null": ""
            },
            {
                "TABLEAU DE VARIATION DES CAPITAUX PROPRES": "Distributions versées aux minoritaires -",
                "null": ""
            },
            {
                "TABLEAU DE VARIATION DES CAPITAUX PROPRES": "Variation de périmètre -",
                "null": ""
            },
            {
                "TABLEAU DE VARIATION DES CAPITAUX PROPRES": "Résultat consolidé 2023 63 923 3 365 67 288",
                "null": ""
            },
            {
                "TABLEAU DE VARIATION DES CAPITAUX PROPRES": "Opérations sur capital 14 483 14 483",
                "null": ""
            },
            {
                "TABLEAU DE VARIATION DES CAPITAUX PROPRES": "Écart de conversion -809 -809",
                "null": ""
            },
            {
                "TABLEAU DE VARIATION DES CAPITAUX PROPRES": "Autres éléments * -11 279 -11 279",
                "null": ""
            },
            {
                "TABLEAU DE VARIATION DES CAPITAUX PROPRES": "Capitaux propres consolidés au 31/12/2023",
                "null": "725 204"
            }
        ],
        [
            {
                "ÉTATS FINANCIERS CONSOLIDÉS\nEXERCICE CLOS LE 31 DÉCEMBRE 2023": "NOTE 1 : DESCRIPTION DE L’ACTIVITÉ D-CONVERSION DES ÉTATS FINANCIERS DES FILIALES ÉTRANGÈRES\nLes Eaux Minérales d’Oulmès S.A. (LEMO), société anonyme au capital social de 198.000.000 de Dirhams, La monnaie fonctionnelle d’une entité est la monnaie de l’environnement économique dans lequel cette\na été créée le 7 mars 1934 sous la dénomination « Compagnie Fermière des Eaux Minérales d’Oulmès- entité opère principalement. Le Dirham est la monnaie de fonctionnement du Groupe. Ainsi, les comptes\nEtat » et dont le siège social est établi dans la zone industrielle de BOUSKOURA à Casablanca. Les Eaux des filiales installées à l’étranger ont été convertis en MAD la monnaie de présentation.\nMinérales d’Oulmès fait partie du groupe HOLMARCOM.\nE- DATE DE CLÔTURE DES EXERCICES\nLes domaines d’activité des Eaux minérales d’Oulmès couvrent le captage, la production, la mise en Les résultats des sociétés consolidées correspondent à une période de 12 mois se terminant le 31\nbouteille et la commercialisation d’eaux minérales naturelles plates (Sidi Ali et Ain Atlas) et gazeuses décembre de chaque année.\n(Oulmès), la fabrication de préformes, ainsi que la mise en bouteille et la commercialisation d’eau de table\nToutes les sociétés entrant dans le périmètre de consolidation du Groupe ont établi des comptes arrêtés\n(Bahia).\nau 31 décembre 2023.\nLEMO est présent également à l’international via sa filiale ETE opérant au Bénin.\nF-COMPTES ET OPÉRATIONS RÉCIPROQUES\nNOTE 2 : RÈGLES ET MÉTHODES COMPTABLES Toutes les transactions intragroupes, ainsi que les actifs et passifs réciproques entre les sociétés consolidées\nA-PRINCIPES COMPTABLES par intégration globale sont éliminés. Il en est de même pour les résultats internes au Groupe (dividendes,\nLes comptes consolidés ont été établis en application de l’avis n°5 du Conseil National de la Comptabilité plus-values...).\n(CNC) du 26 mai 2005 et conformément aux dispositions de l’Annexe III.2.A. de la circulaire de l’AMMC qui\nLes soldes bilanciels, les produits et les charges résultant des transactions intragroupes sont éliminés lors\nfixe le contenu de l’information proforma et l’Annexe III.2.I. portant sur les États de synthèse semestriels.\nde la préparation des états financiers consolidés.\nB-MÉTHODES DE CONSOLIDATION\nG-RETRAITEMENTS DE CONSOLIDATION\nLes méthodes de consolidation appliquées dépendent du type de contrôle liant l’entreprise concernée à\n• Immobilisations en non-valeurs\nla maison-mère :\n• Intégration globale (IG) : Les immobilisations en non-valeurs, constituées des frais préliminaires et des charges à répartir, sont\nannulées en consolidation, ces immobilisations constituent des charges de l’exercice au cours duquel elles\nCette méthode est appliquée lorsque le Groupe détient un contrôle exclusif sur sa filiale. Le contrôle\nont été engagées, au même titre leurs amortissements sont annulés.\nexclusif est le pouvoir de diriger les politiques financières et opérationnelles d’une entreprise afin de tirer\navantage de ses activités. La méthode de l’intégration globale permet de répartir le résultat et les capitaux • Écarts de conversion\npropres entre les intérêts du Groupe et les intérêts hors Groupe (intérêts minoritaires). Les gains de change latents, comptabilisés en écarts de conversion passif dans le bilan devraient être\n• Intégration proportionnelle (IP) : enregistrés au compte de produits et charges au cours de la période à laquelle ils se rapportent. Aussi,\nles écarts de conversion actifs ont été annulés en contrepartie de la provision pour risques et charges\nCette méthode s’applique aux entreprises soumises au contrôle conjoint. Le contrôle conjoint est le\ncorrespondante.\npartage du contrôle d’une entreprise exploitée en commun par un nombre limité d’actionnaires, de sorte\nque les politiques financières et opérationnelles résultent de leur accord. La méthode de l’intégration • Immobilisations acquises par crédit-bail\nproportionnelle consiste à intégrer uniquement les pourcentages d’actifs, de passifs, de charges et de Les actifs détenus en vertu d’un contrat de crédit-bail devraient être comptabilisés au bilan sous forme\nproduits revenant aux seuls intérêts du Groupe. d’une immobilisation corporelle et d’un emprunt correspondant, au compte de produits et charges, sous\n• Mise en équivalence (MEE) : forme d’une dotation aux amortissements et d’une charge financière.\nCette méthode s’applique aux entreprises sur lesquelles le Groupe a une influence notable. L’influence • Écart d’acquisition\nnotable est le pouvoir de participer aux politiques financières et opérationnelles d’une entreprise sans en Les écarts d’acquisition représentent la différence entre le prix d’acquisition des titres des sociétés consolidées\ndétenir le contrôle. La méthode de la mise en équivalence consiste à valoriser les titres de participation de et la part du Groupe dans leur actif net à la date des prises de participations après comptabilisation des\nl’entreprise consolidée en fonction des capitaux propres de celle-ci, la quote-part de résultat de la filiale éventuelles plus ou moins-values latentes sur actifs identifiables. Lorsqu’ils sont positifs, ces écarts sont\nétant prise en compte dans le résultat consolidé. inscrits à l’actif du bilan consolidé sous la rubrique « écarts d’acquisition » et amortis sur une durée qui doit\nC-PÉRIMÈTRE ET RÈGLES DE CONSOLIDATION refléter aussi raisonnablement que possible les hypothèses retenues et les objectifs fixés et documentés\nlors de l’acquisition. Cependant, lorsque ces écarts sont négatifs, ces derniers sont inscrits en provision pour\nLe périmètre de consolidation comprend la société mère Les Eaux Minérales d’Oulmès et ses filiales :\nrisques et charges et repris sur une durée qui doit refléter aussi raisonnablement que possible les mêmes\nMéthode de % de %\nEntité Activité consolidation contrôle d’intérêt hypothèses retenues et les objectifs fixés et documentés lors de l’acquisition.\nCaptage, exploitation, industrie\nEau Technologie Intégration Les comptes consolidés du Groupe comprennent un écart d’acquisition suite à l’entrée en périmètre de la\net commerce de toutes sortes 55% 55%\nEnvironnement « ETE » de boissons globale filiale ETE, amorti sur une durée de 10 ans.\nOULMES DRINKS Extraire, fabriquer, importer, Intégration • Impôts différés\nexporter, embouteiller, promouvoir 100% 100%\nDEVELOPMENT « ODD » globale\net distribuer tout type de boissons Les impositions différées résultent de la neutralisation des différences temporaires introduites par les\nPromotion et distribution de tout règles fiscales et les retraitements d’homogénéisation qui ont une incidence sur la base taxable. Les actifs\nMise en\nORANGINA MAROC type de boissons appartenant au 34% 34% et passifs d’impôt différé sont évalués aux taux dont l’application est attendue sur l’exercice au cours\néquivalence\ngroupe Suntory Food & Beverages\nduquel l’actif sera réalisé ou le passif réglé.\nETE\n• Homogénéisation des durées d’amortissement des immobilisations corporelles :\nEau Technologie Environnement, société de droit béninois, détenue par Les Eaux Minérales d’Oulmès\ndans le cadre de la mise en œuvre de sa stratégie de développement en Afrique et plus particulièrement Le retraitement d’homogénéisation des durées d’amortissement des immobilisations corporelles consiste\nl’Afrique Sub-saharienne. Les comptes sociaux de la société ETE ont fait l’objet d’un audit d’un commissaire à harmoniser la durée d’amortissement de ces dites immobilisations en fixant une durée économique au\naux comptes pour les exercices 2017-2022 ayant servi de base aux travaux de consolidation. lieu d’une durée admise fiscalement.\nODD H- RÈGLES ET MÉTHODES D’ÉVALUATION\nOulmes Drinks Development, société créée au mois d’avril 2016 et détenue à 100% par les Eaux Minérales Les règles d’évaluation présidant à l’établissement des comptes consolidés sont les mêmes que celles\nd’Oulmes, avec un capital passant de MMAD 30 à 25,5 MMAD en 2023. La société a pour activité la appliquées pour les comptes annuels individuels et édictées par le Code Général de la Normalisation\nfabrication et la distribution de tout type de boissons. Elle devrait constituer le fournisseur exclusif Comptable (C.G.N.C.).\nd’Orangina Maroc.\nLes principales méthodes d’évaluation utilisées sont les suivantes :\nCourant 2023, la société a effectué une opération d’accordéon afin d’absorber les pertes cumulées, • Immobilisations incorporelles\nl’opération consistait en l’absorption des pertes cumulées via la réduction du capital de MMAD 22,8\nLes immobilisations incorporelles sont évaluées à leur coût d’acquisition (prix d’achat et frais accessoires)\npassant ainsi de MMAD 30 à MMAD 7,2 et l’augmentation du capital d’un montant de MMAD 18,2 par\nou à leur coût de production. Elles sont constituées essentiellement des brevets, licences, logiciels et droits\ncompensation de créances envers LEMO.\nsimilaires correspondant à des dépenses faites pour l’obtention de l’avantage représenté par la protection\nORANGINA MAROC accordée au bénéficiaire du droit d’utilisation. La durée d’amortissement de ces immobilisations s’étale\nOrangina Maroc, détenue par les Eaux Minérales d’Oulmès à hauteur de 34% depuis avril 2016. Elle sur 5 ans.\na essentiellement pour objet le commerce, la promotion et la distribution de tout type de boissons\n• Immobilisations incorporelles\nappartenant au groupe Suntory Food and Beverages. Il est à noter qu’Orangina Maroc n’a pas été\nconsolidée au titre de l’exercice 2022 car elle est en cours de liquidation. A leur entrée dans le patrimoine de la société, les immobilisations corporelles acquises à titre onéreux\nsont enregistrées à leur coût d‘acquisition, celles produites par l’entreprise pour elle-même, à leur coût de\nEn 2023, sortie des titres de participations de Orangina Maroc pour MMAD (7,4) suite à sa liquidation\nproduction. Ces coûts s’entendent hors TVA récupérable. L’amortissement des immobilisations corporelles\ncourant le deuxième semestre de l’exercice 2023. Il est à noter que le titre de OM était totalement déprécié\nest calculé sur la valeur d’origine du bien dans la limite des taux indiqués par l’administration fiscale et\ndans les comptes de LEMO.\nadmis par l’usage de la profession.\n• Stock\nLes stocks des matières premières sont évalués au coût d’achat et suivant la méthode du coût moyen\npondéré.\nLes Eaux Minérales d’Oulmès S.A. au capital de 198.000.000 DHS\nZ.I. Bouskoura 20180 - Casablanca\nwww.leseauxmineralesdoulmes.ma"
            }
        ],
        [
            {
                "Entité": "Eau Technologie\nEnvironnement « ETE »",
                "Activité": "Captage, exploitation, industrie\net commerce de toutes sortes\nde boissons",
                "Méthode de\nconsolidation": "Intégration\nglobale",
                "% de\ncontrôle": "55%",
                "%\nd’intérêt": "55%"
            },
            {
                "Entité": "OULMES DRINKS\nDEVELOPMENT « ODD »",
                "Activité": "Extraire, fabriquer, importer,\nexporter, embouteiller, promouvoir\net distribuer tout type de boissons",
                "Méthode de\nconsolidation": "Intégration\nglobale",
                "% de\ncontrôle": "100%",
                "%\nd’intérêt": "100%"
            },
            {
                "Entité": "ORANGINA MAROC",
                "Activité": "Promotion et distribution de tout\ntype de boissons appartenant au\ngroupe Suntory Food & Beverages",
                "Méthode de\nconsolidation": "Mise en\néquivalence",
                "% de\ncontrôle": "34%",
                "%\nd’intérêt": "34%"
            }
        ],
        [
            {
                "RAPPORT D’AUDIT SUR LES ÉTATS\nFINANCIERS CONSOLIDÉS\nEXERCICE DU 1ER JANVIER AU 31 DECEMBRE 2023": "1. Provision pour dépréciation des créances clients\nRisque identifié Notre réponse\nAu 31 décembre 2023, la valeur des créances Nos travaux ont notamment consisté à :\nclients nettes de provisions s’élève à 434,2\n37, Bd Abdellatif Ben Kaddour 7 2, 0 B 1d 6 0D r Cis as s aS bla lao nu ci a millions de dirhams. - P d’r ide en nd tr ie fi cac tio on nn ai ds es sa nc ce r éad ne cs e s pr co lic eé nd tsu re às\n20 050 Casablanca Maroc\nMaroc La détermination des créances à déprécier déprécier et de détermination du montant\nrequiert l’exercice du jugement de la direction des dépréciations à constater ;\nsur la base d’une analyse continue de\n- Tester le fonctionnement des contrôles dans\nAux Actionnaires de la société l’évolution du risque client.\nle cadre des procédures mises en œuvre\nLes Eaux Minérales d’Oulmès\nQuartier industriel Bouskoura Compte tenu du caractère significatif du poste pour déterminer le niveau des dépréciations\nCasablanca au regard du bilan du groupe, du jugement des créances clients ;\nnécessaire à l’estimation des créances à\n- Apprécier le caractère raisonnable des\ndéprécier, et de la conjoncture de crise actuelle,\nhypothèses retenues par la Direction pour\nRAPPORT DES COMMISSAIRES AUX COMPTES SUR LES ETATS FINANCIERS CONSOLIDES nous avons considéré que ce sujet constitue un\nEXERCICE DU 1er JANVIER AU 31 DECEMBRE 2023 point clé de l’audit. évaluer les dépréciations à constater ;\n- Examiner la correcte évaluation des\ndépréciations à constater selon la méthode\nOpinion de provisionnement du Groupe.\nNous avons effectué l'audit des états financiers consolidés de la société LES EAUX MINERALES\nD’OULMES et de ses filiales (Groupe LES EAUX MINERALES D’OULMES), qui comprennent le bilan\nconsolidé au 31 décembre 2023, ainsi que le compte de produits et charges consolidé, l’état consolidé Responsabilités de la direction et des responsables de la gouvernance à l’égard des états\ndes variations des capitaux propre, le tableau consolidé des flux de trésorerie pour l’exercice clos à financiers consolidés\ncette date, ainsi que les notes annexes y compris un résumé des principales méthodes comptables.\nCes états financiers consolidés font ressortir un montant de capitaux propres consolidés de KMAD\nLa direction est responsable de la préparation et de la présentation fidèle des états financiers consolidés\n725.204 dont un bénéfice net consolidé de KMAD 67.288.\nconformément au référentiel comptable en vigueur au Maroc, ainsi que du contrôle interne qu'elle\nNous certifions que les états financiers consolidés cités au premier paragraphe ci- dessus, sont réguliers considère comme nécessaire pour permettre la préparation d'états financiers consolidés exempts\net sincères et donnent dans tous leurs aspects significatifs, une image fidèle du patrimoine et de la d'anomalies significatives, que celles-ci résultent de fraudes ou d'erreurs.\nsituation financière du groupe au 31 décembre 2023, ainsi que du résultat de l’ensemble consolidé pour\nl’exercice clos à cette date, conformément au référentiel comptable en vigueur au Maroc. Lors de la préparation des états financiers consolidés, c’est à la direction qu’il incombe d’évaluer la\ncapacité du groupe à poursuivre son exploitation, de communiquer, le cas échéant, les questions se\nFondement de l’opinion rapportant à la continuité de l’exploitation et d’appliquer le principe comptable de continuité\nd’exploitation, sauf si la direction a l’intention de liquider le groupe ou de cesser son activité ou si aucune\nNous avons effectué notre audit selon les Normes de la Profession au Maroc. Les responsabilités qui autre solution réaliste ne s’offre à elle.\nnous incombent en vertu de ces normes sont plus amplement décrites dans la section « Responsabilités\nde l’auditeur à l’égard de l’audit des états financiers consolidés » du présent rapport. Nous sommes Il incombe aux responsables de la gouvernance de surveiller le processus d’information financière de\nindépendants du groupe conformément aux règles de déontologie qui s’appliquent à l’audit des états du groupe.\nfinanciers au Maroc et nous nous sommes acquittés des autres responsabilités déontologiques qui nous\nincombent selon ces règles. Nous estimons que les éléments probants que nous avons obtenus sont Responsabilités de l’auditeur à l’égard de l’audit des états financiers consolidés\nsuffisants et appropriés pour fonder notre opinion d’audit.\nNos objectifs sont d’obtenir l’assurance raisonnable que les états financiers consolidés pris dans leur\nQuestions clés de l’audit\nensemble sont exempts d’anomalies significatives, que celles-ci résultent de fraudes ou d’erreurs et de\nLes questions clés de l’audit sont les questions qui, selon notre jugement professionnel, ont été les plus délivrer un rapport de l’auditeur contenant notre opinion.\nimportantes dans l’audit des états financiers consolidés de la période considérée. Ces questions ont été\ntraitées dans le contexte de notre audit des états financiers consolidés pris dans leur ensemble et aux L’assurance raisonnable correspond à un niveau élevé d’assurance, qui ne garantit toutefois pas qu’un\nfins de la formation de notre opinion sur ceux-ci, et nous n’exprimons pas une opinion distincte sur ces audit réalisé conformément aux normes de la profession au Maroc permettra toujours de détecter toute\nquestions. anomalie significative qui pourrait exister. Les anomalies peuvent résulter de fraudes ou d’erreurs et\nelles sont considérées comme significatives lorsqu’il est raisonnable de s’attendre à ce que,\nindividuellement ou collectivement, elles puissent influer sur les décisions économiques que les\nutilisateurs des états financiers consolidés prennent en se fondant sur ceux-ci.\n1\nDans le cadre d’un audit réalisé conformément aux normes de la profession au Maroc, nous exerçons 2\nnotre jugement professionnel et faisons preuve d’esprit critique tout au long de cet audit. En outre :\n nous identifions et évaluons les risques que les états financiers consolidés comportent des\nanomalies significatives, que celles-ci résultent de fraudes ou d’erreurs, concevons et mettons en\nœuvre des procédures d’audit en réponse à ces risques, et réunissons des éléments probants\nsuffisants et appropriés pour fonder notre opinion. Le risque de non-détection d’une anomalie\nsignificative résultant d’une fraude est plus élevé que celui d’une anomalie significative résultant\nd’une erreur, car la fraude peut impliquer la collusion, la falsification, les omissions volontaires, les\nfausses déclarations ou le contournement du contrôle interne ;\n nous acquérons une compréhension des éléments du contrôle interne pertinents pour l’audit afin\nde concevoir des procédures d’audit appropriées aux circonstances, et non dans le but d’exprimer\nune opinion sur l’efficacité du contrôle interne du groupe ;\n nous apprécions le caractère approprié des méthodes comptables retenues et le caractère\nraisonnable des estimations comptables faites par la direction, de même que des informations y\nafférentes fournies par cette dernière ;\n nous tirons une conclusion quant au caractère approprié de l’utilisation par la direction du principe\ncomptable de continuité d’exploitation et, selon les éléments probants obtenus, quant à l’existence\nou non d’une incertitude significative liée à des événements ou situations susceptibles de jeter un\ndoute important sur la capacité du groupe à poursuivre son exploitation. Si nous concluons à\nl’existence d’une incertitude significative, nous sommes tenus d’attirer l’attention des lecteurs de\nnotre rapport sur les informations fournies dans les états financiers au sujet de cette incertitude ou,\nsi ces informations ne sont pas adéquates, d’exprimer une opinion modifiée. Nos conclusions\ns’appuient sur les éléments probants obtenus jusqu’à la date de notre rapport. Des événements ou\nsituations futurs pourraient par ailleurs amener le groupe à cesser son exploitation ;\n nous évaluons la présentation d’ensemble, la structure et le contenu des états financiers\nconsolidés, y compris les informations fournies dans les notes, et apprécions si les états financiers\nconsolidés représentent les opérations et événements sous-jacents d’une manière propre à donner\nune image fidèle.\n nous obtenons des éléments probants suffisants et appropriés concernant les informations\nfinancières des entités et activités du groupe pour exprimer une opinion sur les états financiers\nconsolidés. Nous sommes responsables de la direction, de la supervision et de la réalisation de\nl’audit du groupe. Nous assumons l’entière responsabilité de l’opinion d’audit.\nNous communiquons aux responsables de la gouvernance notamment l’étendue et le calendrier prévus\ndes travaux d’audit et nos constatations importantes, y compris toute déficience importante du contrôle\ninterne que nous aurions relevée au cours de notre audit.\nCasablanca, le 9 avril 2024\nLes Commissaires aux Comptes\nERNST & YOUNG FIDAROC GRANT THORNTON\nAbdeslam BERRADA ALLAM Faïçal MEKOUAR\nAssocié Associé\n3\nLes Eaux Minérales d’Oulmès S.A. au capital de 198.000.000 DHS\nZ.I. Bouskoura 20180 - Casablanca\nwww.leseauxmineralesdoulmes.ma"
            }
        ],
        [],
        [
            {
                "ÉTATS FINANCIERS SOCIAUX\nEXERCICE CLOS LE 31 DÉCEMBRE 2023": "BILAN ACTIF BILAN PASSIF\n31-déc-23 31-déc-22\n(Montants en dhs) (Montants en dhs) 31-déc-23 31-déc-22\nBrut Amortissement Net Net\nImmobilisations en non valeur (A) 74 193 964 52 594 255 21 599 708 25 664 272 Fonds propres\nFrais préliminaires Capital social ou personnel ( 1) 198 000 000 198 000 000\nCharges à répartir 74 193 964 52 594 255 21 599 708 25 664 272 Moins : actionnaires, capital souscrit non appelé\nPrimes de remboursement des obligations Capital appelé\nImmobilisations incorporelles (B) 37 692 496 23 695 041 13 997 455 15 262 514 dont versé\nImmobilisations en recherche et développement Primes d’émission, de fusion , d’apport 166 980 000 166 980 000\nBrevets, marques, droits et valeurs similaires 37 692 496 23 695 041 13 997 455 15 262 514 Écarts de réévaluation\nFonds commercial TNENAMREP Réserve légale 19 800 000 19 800 000\nESILIBOMMI Autres immobilisations incorporelles Autres réserves 37 687 000 37 687 000\nImmobilisations corporelles (C) 3 705 748 731 2 241 544 638 1 464 204 092 1 260 223 269 Report à nouveau ( 2 ) 118 425 504 96 907 367\nTerrains 48 325 324 - 48 325 324 48 325 324\nRésultats nets en instance d’affectation ( 2) -\nConstructions 636 164 558 322 244 591 313 919 968 320 162 149\nRésultat net de l’exercice ( 2) 73 975 309 54 188 137\nInstallations techniques, matériel et outillage 2 589 649 032 1 842 691 862 746 957 170 587 153 057\nMatériel de transport 14 367 551 11 966 220 2 401 330 1 513 954 TNEMECNANIF Total des capitaux propres (A) 614 867 813 573 562 504\nMobilier de bureau, aménagements divers 80 669 051 64 641 966 16 027 085 18 348 476 Capitaux propres assimilés (B) 14 874 109 5 451 955\nFITCA Subventions d’investissement 14 874 109 5 451 955\nAutres immobilisations corporelles - - - -\nProvisions réglementées\nImmobilisations corporelles en cours 336 573 214 - 336 573 214 284 720 310\nDettes de financement (C) 984 065 950 801 478 526\nImmobilisations financières (D) 62 597 390 3 000 000 59 597 390 85 149 373\nEmprunts obligataires 458 333 333 300 000 000\nPrêts immobilisés - - - 27 197 450\nAutres créances financières 4 449 454 - 4 449 454 3 603 988 Autres dettes de financement 525 732 616 501 478 526\nTitres de participation 58 147 935 3 000 000 55 147 935 54 347 935 Provisions durables pour risques et charges (D) - -\nAutres titres immobilisés Provisions pour risques\nÉcart de conversion - Actif (E) - - - - Provisions pour charges\nDiminution des créances immobilisées Écart de conversion - Passif (E) - -\nAugmentation des dettes financières Augmentation de créances immobilisées\nTOTAL I (A+B+C+D+E) 3 880 232 580 2 320 833 935 1 559 398 646 1 386 299 428 Diminution des dettes de financement\nStocks (F) 290 467 831 4 344 461 286 123 370 288 821 189 TOTAL I ( A + B + C + D + E ) 1 613 807 872 1 380 492 985\nMarchandises 12 151 942 - 12 151 942 9 881 259 Dettes du passif circulant (F) 614 047 040 663 744 613\nMatières et fournitures consommables 247 227 716 4 344 461 242 883 255 259 298 542 Fournisseurs et comptes rattachés 252 534 748 330 197 091\nProduits en cours - - - - TNALUCRIC Clients créditeurs , avances et acomptes 15 356 549 13 468 816\nTNALUCRIC Produits intermédiaires et résiduels - - - - Personnel 11 508 739 18 178 149\nProduits finis 31 088 173 - 31 088 173 19 641 388 Organismes sociaux 20 281 086 16 227 676\nCréances de l’actif circulant (G) 742 842 064 89 661 719 653 180 345 665 579 047 État 296 738 521 271 820 722\nFournisseurs débiteurs, avances & acomptes 166 049 345 - 166 049 345 77 312 025 Comptes d’associés 1 699 951 1 698 949\nClients et comptes rattachés 468 135 661 80 172 426 387 963 236 457 661 162 FISSAP Autres créanciers\nPersonnel 3 289 963 - 3 289 963 2 260 940 Comptes de régularisation - Passif 15 927 447 12 153 211\nFITCA État 50 296 609 50 296 609 82 169 339 Autres provisions pour risques et charges (G) 1 462 185 9 538 330\nComptes d’associés 13 401 499 - 13 401 499 17 993 688 Écarts de conversion - Passif ( éléments circulants ) (H) 266 949 2 482 626\nAutres débiteurs 22 829 939 9 489 294 13 340 645 8 598 413\nTOTAL II ( F + G + H ) 615 776 174 675 765 569\nComptes de régularisation - Actif 18 839 050 18 839 050 19 583 479\nTrésorerie - Passif\nTitres et valeurs de placement (H) 58 000 58 000 58 000 EIREROSÉRT Crédits d’escompte 47 267 951 59 453 813\nÉcarts de conversion - Actif (I) 417 357 417 357 2 093 502 Crédits de trésorerie 279 999 987 317 769 495\nTOTAL II (F+G+H+I) 1 033 785 252 94 006 180 939 779 072 956 551 737\nBanques de régularisation 47 524 891 17 081 598\nEIREROSÉRT Chèques et valeurs à encaisser 43 707 193 43 707 193 46 363 917 Banques, T.G et C.C.P 58 785 406 58 785 406 59 565 204 TOTAL III 374 792 829 394 304 906\nCaisses, Régies d’avances et accréditifs 2 706 559 2 706 559 1 783 173 TOTAL GÉNÉRAL ( I + II + III ) 2 604 376 875 2 450 563 460\nTOTAL III 105 199 157 - 105 199 157 107 712 294 ( 1 ) Capital personnel débiteur\nTOTAL GÉNÉRAL 5 019 216 990 2 414 840 115 2 604 376 875 2 450 563 460 (2) Bénéficiaire (+) , déficitaire ( - )\nCOMPTE DE PRODUITS ET CHARGES (Hors Taxes) ÉTAT DES SOLDES DE GESTION ( E S G )\n(Montants en dhs) Exercice du 1 janvier 2023 au 31 décembre 2023 I TABLEAU DE FORMATION DES RÉSULTATS ( T F R )\nOPÉRATIONS Exercice du 1 janvier 2023\nConcernant TOTAUX DE TOTAUX DE Propres à NATURE les exercices L’EXERCICE L’EXERCICE l’exercice précédents PRÉCÉDENT au 31 décembre 2023 (Montants en dhs) EXERCICE EXERCICE PRÉCÉDENT\n(1) (2) 3= 1 + 2 1 Ventes de marchandises (en l’état ) 80 787 231 62 744 467\nI Produits d’exploitation 2 - Achats revendus de marchandises 79 872 508 69 964 769\nVentes de marchandises (en l’état) 80 787 231 80 787 231 62 744 467\nVentes de biens et services produits 2 413 537 046 2 413 537 046 2 083 406 116 I = MARGE BRUTE SUR VENTES EN L’ÉTAT 914 722 -7 220 302\nChiffre d’affaires 2 494 324 277 - 2 494 324 277 2 146 150 583 + PRODUCTION DE L’ EXERCICE : (3 + 4 + 5 ) 2 424 983 832 2 086 911 889\nVariation de stocks de produits ( + ou -) (1) 11 446 786 11 446 786 3 505 773\n3 Ventes de biens et services produits 2 413 537 046 2 083 406 116\nImmobilisations produites par l’entreprise pour elle-même - - II\nNOITATIOLPXE Subventions d’exploitation - - 4 Variation de stocks de produits 11 446 786 3 505 773\nAutres produits d’exploitation 6 756 744 6 756 744 - 5 Immobilisations produites par l’entreprise pour elle-même - -\nReprises d’exploitation : transferts de charges 8 107 212 8 107 212 1 052 587\nTOTAL I 2 520 635 019 - 2 520 635 019 2 150 708 943 - CONSOMMATION DE L’EXERCICE : ( 6 + 7 ) 1 561 159 584 1 330 270 913\nII Charges d’exploitation III 6 Achats consommés de matières et fournitures 873 621 805 774 088 172\nAchats revendus (2) de marchandises 79 872 508 79 872 508 69 964 769\n7 Autres charges externes 687 537 779 556 182 741\nAchats consommés (2) de matières et fournitures 873 621 805 873 621 805 774 088 172\nAutres charges externes 687 537 779 687 537 779 556 182 741 IV = VALEUR AJOUTÉE : ( I + II + III ) 864 738 970 749 420 675\nImpôts et taxes 217 868 573 48 632 217 917 205 193 438 189 8 + Subventions d’exploitation - -\nCharges de personnel 292 842 068 292 842 068 255 329 406\nAutres charges d’exploitation 1 450 001 1 450 001 1 700 004 V 9 - Impôts et taxes 217 917 205 193 438 189\nDotations d’exploitation 193 578 341 193 578 341 187 990 986 10 - Charges de personnel 292 842 068 255 329 406\nTOTAL II 2 346 771 076 48 632 2 346 819 708 2 038 694 267\nIII RÉSULTAT D’EXPLOITATION ( I - II ) 173 863 944 -48 632 173 815 312 112 014 677 = EXCÉDENT BRUT D’EXPLOITATION ( E B E ) 353 979 697 300 653 079\nIV Produits financiers = OU INSUFFISANCE BRUTE D’EXPLOITATION ( I B E) - -\nP etro ad uu ti rt es s d te its r eti st r imes m d oe bp ia lisrt éi sc ipation - 2 123 841 11 + Autres produits d’exploitation 6 756 744 -\nGains de change 6 082 820 6 082 820 1 850 715 12 - Autres charges d’exploitation 1 450 001 1 700 004\nREICNANIF Intérêts et autres produits financiers 1 199 604 1 199 604 1 685 307 13 + Reprises d’exploitation : transferts de charges 8 107 212 1 052 587\nReprises financières : transferts de charges 2 018 386 2 018 386 666 179\nTOTAL IV 9 300 811 - 9 300 811 6 326 042 14 - Dotations d’exploitation 193 578 341 187 990 986\nV Charges financières VI = RÉSULTAT D’EXPLOITATION ( + ou - ) 173 815 312 112 014 677\nCharges d’intérêts 58 087 428 58 087 428 38 994 693\nVII RÉSULTAT FINANCIER -56 160 211 -38 156 090\nPertes de change 4 031 353 4 031 353 3 393 937\nAutres charges financières - - - VIII = RÉSULTAT COURANT ( + ou - ) 117 655 100 73 858 587\nDotations financières 3 342 241 3 342 241 2 093 502 IX RÉSULTAT NON COURANT -5 678 650 2 560 712\nTOTAL V 65 461 022 - 65 461 022 44 482 132\nVI RÉSULTAT FINANCIER ( IV - V ) -56 160 211 - -56 160 211 -38 156 090 15 - Impôts sur les résultats 38 001 141 22 231 162\nVII RÉSULTAT COURANT ( III + VI ) 117 703 732 -48 632 117 655 100 73 858 587 X = RÉSULTAT NET DE L’EXERCICE ( + ou - ) 73 975 309 54 188 137\nVIII Produits non courants II CAPACITÉ D’AUTOFINANCEMENT ( C A F ) - AUTOFINANCEMENT\nProduits de cessions d’immobilisations 71 940 71 940 1 119 472\nSubvention d’équilibre - - - Résultat de l’exercice 73 975 309 54 188 137\nReprises sur subventions d’investissement - - - 1 * Bénéfice 73 975 309 54 188 137\nTNARUOC Autres produits non courants 4 399 647 4 399 647 5 947 507 * Perte\nReprises non courantes : transferts de charges 31 866 800 31 866 800 - 2 + Dotations d’exploitation (1) 184 254 716 180 431 390\nTOTAL VIII 36 338 388 - 36 338 388 7 066 980\nIX Charges non courantes 3 + Dotations financières (1) 3 000 000\nNON V dea sle iu mrs m n oe bt it le iss a d ti’ oa nm so cr éti ds ése em s ent 13 904 768 - 13 904 768 21 220 4 + Dotations non courantes (1) - - 5 - Reprises d’exploitation (2) - -\nSubventions accordées - - - - 6 - Reprises financières (2)\nAutres charges non courantes 23 712 546 4 399 724 28 112 270 3 974 653\nDotations non courantes aux - - - 510 394 7 - Reprises non courantes (2) (3) - -\namortissements et aux provisions 8 - Produits des cessions des immobilisations 71 940 1 119 472\nTOTAL IX 37 617 313 4 399 724 42 017 038 4 506 268 9 + Valeurs nettes des immobilisations cédées 13 904 768 21 220\nX RÉSULTAT NON COURANT ( VIII - IX ) -1 278 926 -4 399 724 -5 678 650 2 560 712 XI RÉSULTAT AVANT IMPÔTS ( VII+ ou - X) 116 424 807 -4 448 356 111 976 450 76 419 299 I CAPACITÉ D’AUTOFINANCEMENT ( C.A.F ) 275 062 853 233 521 275\nXII IMPÔTS SUR LES RÉSULTATS 38 001 141 38 001 141 22 231 162 10 - Distributions de bénéfices 32 670 000 23 760 000\nXIII RÉSULTAT NET ( XI - XII ) 78 423 666 -4 448 356 73 975 309 54 188 137 II AUTOFINANCEMENT 242 392 853 209 761 275\nXIV TOTAL DES PRODUITS ( I + IV + VIII ) 2 566 274 217 0 2 566 274 217 2 164 101 965 (1) à l’exclusion des dotations relatives aux actifs et passifs circulants et à la trésorerie\nXV TOTAL DES CHARGES ( II + V + IX + XII ) 2 487 850 552 4 448 356 2 492 298 908 2 109 913 828 (2) à l’exclusion des reprises relatives aux actifs circulants et à la trésorerie\nXVI RÉSULTAT NET ( total produits - total charges ) 78 423 666 -4 448 356 73 975 309 54 188 137 (3) Y compris reprises sur subventions d’investissement"
            }
        ],
        [
            {
                "BILAN ACTIF": "(Montants en dhs)",
                "null": "31-déc-22"
            },
            {
                "BILAN ACTIF": "",
                "null": "Net"
            },
            {
                "BILAN ACTIF": "ESILIBOMMI\nFITCA",
                "null": "25 664 272"
            },
            {
                "BILAN ACTIF": "",
                "null": ""
            },
            {
                "BILAN ACTIF": "",
                "null": "25 664 272"
            },
            {
                "BILAN ACTIF": "",
                "null": ""
            },
            {
                "BILAN ACTIF": "",
                "null": "15 262 514"
            },
            {
                "BILAN ACTIF": "",
                "null": ""
            },
            {
                "BILAN ACTIF": "",
                "null": "15 262 514"
            },
            {
                "BILAN ACTIF": "",
                "null": ""
            },
            {
                "BILAN ACTIF": "",
                "null": ""
            },
            {
                "BILAN ACTIF": "",
                "null": "1 260 223 269"
            },
            {
                "BILAN ACTIF": "",
                "null": "48 325 324"
            },
            {
                "BILAN ACTIF": "",
                "null": "320 162 149"
            },
            {
                "BILAN ACTIF": "",
                "null": "587 153 057"
            },
            {
                "BILAN ACTIF": "",
                "null": "1 513 954"
            },
            {
                "BILAN ACTIF": "",
                "null": "18 348 476"
            },
            {
                "BILAN ACTIF": "",
                "null": "-"
            },
            {
                "BILAN ACTIF": "",
                "null": "284 720 310"
            },
            {
                "BILAN ACTIF": "",
                "null": "85 149 373"
            },
            {
                "BILAN ACTIF": "",
                "null": "27 197 450"
            },
            {
                "BILAN ACTIF": "",
                "null": "3 603 988"
            },
            {
                "BILAN ACTIF": "",
                "null": "54 347 935"
            },
            {
                "BILAN ACTIF": "",
                "null": ""
            },
            {
                "BILAN ACTIF": "",
                "null": "-"
            },
            {
                "BILAN ACTIF": "",
                "null": ""
            },
            {
                "BILAN ACTIF": "",
                "null": ""
            },
            {
                "BILAN ACTIF": "",
                "null": "1 386 299 428"
            },
            {
                "BILAN ACTIF": "TNALUCRIC\nFITCA",
                "null": "288 821 189"
            },
            {
                "BILAN ACTIF": "",
                "null": "9 881 259"
            },
            {
                "BILAN ACTIF": "",
                "null": "259 298 542"
            },
            {
                "BILAN ACTIF": "",
                "null": "-"
            },
            {
                "BILAN ACTIF": "",
                "null": "-"
            },
            {
                "BILAN ACTIF": "",
                "null": "19 641 388"
            },
            {
                "BILAN ACTIF": "",
                "null": "665 579 047"
            },
            {
                "BILAN ACTIF": "",
                "null": "77 312 025"
            },
            {
                "BILAN ACTIF": "",
                "null": "457 661 162"
            },
            {
                "BILAN ACTIF": "",
                "null": "2 260 940"
            },
            {
                "BILAN ACTIF": "",
                "null": "82 169 339"
            },
            {
                "BILAN ACTIF": "",
                "null": "17 993 688"
            },
            {
                "BILAN ACTIF": "",
                "null": "8 598 413"
            },
            {
                "BILAN ACTIF": "",
                "null": "19 583 479"
            },
            {
                "BILAN ACTIF": "",
                "null": "58 000"
            },
            {
                "BILAN ACTIF": "",
                "null": "2 093 502"
            },
            {
                "BILAN ACTIF": "",
                "null": "956 551 737"
            },
            {
                "BILAN ACTIF": "EIREROSÉRT",
                "null": "46 363 917"
            },
            {
                "BILAN ACTIF": "",
                "null": "59 565 204"
            },
            {
                "BILAN ACTIF": "",
                "null": "1 783 173"
            },
            {
                "BILAN ACTIF": "",
                "null": "107 712 294"
            },
            {
                "BILAN ACTIF": "",
                "null": "2 450 563 460"
            }
        ],
        [
            {
                "BILAN PASSIF": "(Montants en dhs)",
                "null": "31-déc-22"
            },
            {
                "BILAN PASSIF": "TNENAMREP\nTNEMECNANIF",
                "null": ""
            },
            {
                "BILAN PASSIF": "",
                "null": "198 000 000"
            },
            {
                "BILAN PASSIF": "",
                "null": ""
            },
            {
                "BILAN PASSIF": "",
                "null": ""
            },
            {
                "BILAN PASSIF": "",
                "null": ""
            },
            {
                "BILAN PASSIF": "",
                "null": "166 980 000"
            },
            {
                "BILAN PASSIF": "",
                "null": ""
            },
            {
                "BILAN PASSIF": "",
                "null": "19 800 000"
            },
            {
                "BILAN PASSIF": "",
                "null": "37 687 000"
            },
            {
                "BILAN PASSIF": "",
                "null": "96 907 367"
            },
            {
                "BILAN PASSIF": "",
                "null": ""
            },
            {
                "BILAN PASSIF": "",
                "null": "54 188 137"
            },
            {
                "BILAN PASSIF": "",
                "null": "573 562 504"
            },
            {
                "BILAN PASSIF": "",
                "null": "5 451 955"
            },
            {
                "BILAN PASSIF": "",
                "null": "5 451 955"
            },
            {
                "BILAN PASSIF": "",
                "null": ""
            },
            {
                "BILAN PASSIF": "",
                "null": "801 478 526"
            },
            {
                "BILAN PASSIF": "",
                "null": "300 000 000"
            },
            {
                "BILAN PASSIF": "",
                "null": "501 478 526"
            },
            {
                "BILAN PASSIF": "",
                "null": "-"
            },
            {
                "BILAN PASSIF": "",
                "null": ""
            },
            {
                "BILAN PASSIF": "",
                "null": ""
            },
            {
                "BILAN PASSIF": "",
                "null": "-"
            },
            {
                "BILAN PASSIF": "",
                "null": ""
            },
            {
                "BILAN PASSIF": "",
                "null": ""
            },
            {
                "BILAN PASSIF": "",
                "null": "1 380 492 985"
            },
            {
                "BILAN PASSIF": "TNALUCRIC\nFISSAP",
                "null": "663 744 613"
            },
            {
                "BILAN PASSIF": "",
                "null": "330 197 091"
            },
            {
                "BILAN PASSIF": "",
                "null": "13 468 816"
            },
            {
                "BILAN PASSIF": "",
                "null": "18 178 149"
            },
            {
                "BILAN PASSIF": "",
                "null": "16 227 676"
            },
            {
                "BILAN PASSIF": "",
                "null": "271 820 722"
            },
            {
                "BILAN PASSIF": "",
                "null": "1 698 949"
            },
            {
                "BILAN PASSIF": "",
                "null": ""
            },
            {
                "BILAN PASSIF": "",
                "null": "12 153 211"
            },
            {
                "BILAN PASSIF": "",
                "null": "9 538 330"
            },
            {
                "BILAN PASSIF": "",
                "null": "2 482 626"
            },
            {
                "BILAN PASSIF": "",
                "null": "675 765 569"
            },
            {
                "BILAN PASSIF": "EIREROSÉRT",
                "null": ""
            },
            {
                "BILAN PASSIF": "",
                "null": "59 453 813"
            },
            {
                "BILAN PASSIF": "",
                "null": "317 769 495"
            },
            {
                "BILAN PASSIF": "",
                "null": "17 081 598"
            },
            {
                "BILAN PASSIF": "",
                "null": "394 304 906"
            },
            {
                "BILAN PASSIF": "",
                "null": "2 450 563 460"
            }
        ],
        [
            {
                "COMPTE DE PRODUITS ET CHARGES (Hors Taxes)": "",
                "null": ""
            },
            {
                "COMPTE DE PRODUITS ET CHARGES (Hors Taxes)": "",
                "null": "TOTAUX DE\nL’EXERCICE\nPRÉCÉDENT"
            },
            {
                "COMPTE DE PRODUITS ET CHARGES (Hors Taxes)": "",
                "null": ""
            },
            {
                "COMPTE DE PRODUITS ET CHARGES (Hors Taxes)": "",
                "null": ""
            },
            {
                "COMPTE DE PRODUITS ET CHARGES (Hors Taxes)": "NOITATIOLPXE",
                "null": ""
            },
            {
                "COMPTE DE PRODUITS ET CHARGES (Hors Taxes)": "",
                "null": "62 744 467"
            },
            {
                "COMPTE DE PRODUITS ET CHARGES (Hors Taxes)": "",
                "null": "2 083 406 116"
            },
            {
                "COMPTE DE PRODUITS ET CHARGES (Hors Taxes)": "",
                "null": "2 146 150 583"
            },
            {
                "COMPTE DE PRODUITS ET CHARGES (Hors Taxes)": "",
                "null": "3 505 773"
            },
            {
                "COMPTE DE PRODUITS ET CHARGES (Hors Taxes)": "",
                "null": "-"
            },
            {
                "COMPTE DE PRODUITS ET CHARGES (Hors Taxes)": "",
                "null": "-"
            },
            {
                "COMPTE DE PRODUITS ET CHARGES (Hors Taxes)": "",
                "null": "-"
            },
            {
                "COMPTE DE PRODUITS ET CHARGES (Hors Taxes)": "",
                "null": "1 052 587"
            },
            {
                "COMPTE DE PRODUITS ET CHARGES (Hors Taxes)": "",
                "null": "2 150 708 943"
            },
            {
                "COMPTE DE PRODUITS ET CHARGES (Hors Taxes)": "",
                "null": ""
            },
            {
                "COMPTE DE PRODUITS ET CHARGES (Hors Taxes)": "",
                "null": "69 964 769"
            },
            {
                "COMPTE DE PRODUITS ET CHARGES (Hors Taxes)": "",
                "null": "774 088 172"
            },
            {
                "COMPTE DE PRODUITS ET CHARGES (Hors Taxes)": "",
                "null": "556 182 741"
            },
            {
                "COMPTE DE PRODUITS ET CHARGES (Hors Taxes)": "",
                "null": "193 438 189"
            },
            {
                "COMPTE DE PRODUITS ET CHARGES (Hors Taxes)": "",
                "null": "255 329 406"
            },
            {
                "COMPTE DE PRODUITS ET CHARGES (Hors Taxes)": "",
                "null": "1 700 004"
            },
            {
                "COMPTE DE PRODUITS ET CHARGES (Hors Taxes)": "",
                "null": "187 990 986"
            },
            {
                "COMPTE DE PRODUITS ET CHARGES (Hors Taxes)": "",
                "null": "2 038 694 267"
            },
            {
                "COMPTE DE PRODUITS ET CHARGES (Hors Taxes)": "",
                "null": "112 014 677"
            },
            {
                "COMPTE DE PRODUITS ET CHARGES (Hors Taxes)": "REICNANIF",
                "null": ""
            },
            {
                "COMPTE DE PRODUITS ET CHARGES (Hors Taxes)": "",
                "null": "2 123 841"
            },
            {
                "COMPTE DE PRODUITS ET CHARGES (Hors Taxes)": "",
                "null": "1 850 715"
            },
            {
                "COMPTE DE PRODUITS ET CHARGES (Hors Taxes)": "",
                "null": "1 685 307"
            },
            {
                "COMPTE DE PRODUITS ET CHARGES (Hors Taxes)": "",
                "null": "666 179"
            },
            {
                "COMPTE DE PRODUITS ET CHARGES (Hors Taxes)": "",
                "null": "6 326 042"
            },
            {
                "COMPTE DE PRODUITS ET CHARGES (Hors Taxes)": "",
                "null": ""
            },
            {
                "COMPTE DE PRODUITS ET CHARGES (Hors Taxes)": "",
                "null": "38 994 693"
            },
            {
                "COMPTE DE PRODUITS ET CHARGES (Hors Taxes)": "",
                "null": "3 393 937"
            },
            {
                "COMPTE DE PRODUITS ET CHARGES (Hors Taxes)": "",
                "null": "-"
            },
            {
                "COMPTE DE PRODUITS ET CHARGES (Hors Taxes)": "",
                "null": "2 093 502"
            },
            {
                "COMPTE DE PRODUITS ET CHARGES (Hors Taxes)": "",
                "null": "44 482 132"
            },
            {
                "COMPTE DE PRODUITS ET CHARGES (Hors Taxes)": "",
                "null": "-38 156 090"
            },
            {
                "COMPTE DE PRODUITS ET CHARGES (Hors Taxes)": "",
                "null": "73 858 587"
            },
            {
                "COMPTE DE PRODUITS ET CHARGES (Hors Taxes)": "TNARUOC\nNON",
                "null": ""
            },
            {
                "COMPTE DE PRODUITS ET CHARGES (Hors Taxes)": "",
                "null": "1 119 472"
            },
            {
                "COMPTE DE PRODUITS ET CHARGES (Hors Taxes)": "",
                "null": "-"
            },
            {
                "COMPTE DE PRODUITS ET CHARGES (Hors Taxes)": "",
                "null": "-"
            },
            {
                "COMPTE DE PRODUITS ET CHARGES (Hors Taxes)": "",
                "null": "5 947 507"
            },
            {
                "COMPTE DE PRODUITS ET CHARGES (Hors Taxes)": "",
                "null": "-"
            },
            {
                "COMPTE DE PRODUITS ET CHARGES (Hors Taxes)": "",
                "null": "7 066 980"
            },
            {
                "COMPTE DE PRODUITS ET CHARGES (Hors Taxes)": "",
                "null": ""
            },
            {
                "COMPTE DE PRODUITS ET CHARGES (Hors Taxes)": "",
                "null": "21 220"
            },
            {
                "COMPTE DE PRODUITS ET CHARGES (Hors Taxes)": "",
                "null": "-"
            },
            {
                "COMPTE DE PRODUITS ET CHARGES (Hors Taxes)": "",
                "null": "3 974 653"
            },
            {
                "COMPTE DE PRODUITS ET CHARGES (Hors Taxes)": "",
                "null": "510 394"
            },
            {
                "COMPTE DE PRODUITS ET CHARGES (Hors Taxes)": "",
                "null": "4 506 268"
            },
            {
                "COMPTE DE PRODUITS ET CHARGES (Hors Taxes)": "",
                "null": "2 560 712"
            },
            {
                "COMPTE DE PRODUITS ET CHARGES (Hors Taxes)": "",
                "null": "76 419 299"
            },
            {
                "COMPTE DE PRODUITS ET CHARGES (Hors Taxes)": "",
                "null": "22 231 162"
            },
            {
                "COMPTE DE PRODUITS ET CHARGES (Hors Taxes)": "",
                "null": "54 188 137"
            },
            {
                "COMPTE DE PRODUITS ET CHARGES (Hors Taxes)": "",
                "null": "2 164 101 965"
            },
            {
                "COMPTE DE PRODUITS ET CHARGES (Hors Taxes)": "",
                "null": "2 109 913 828"
            },
            {
                "COMPTE DE PRODUITS ET CHARGES (Hors Taxes)": "",
                "null": "54 188 137"
            }
        ],
        [
            {
                "ÉTAT DES SOLDES DE GESTION ( E S G )": "I TABLEAU DE FORMATION DES RÉSULTATS ( T F R )",
                "null": ""
            },
            {
                "ÉTAT DES SOLDES DE GESTION ( E S G )": "(Montants en dhs)",
                "null": ""
            },
            {
                "ÉTAT DES SOLDES DE GESTION ( E S G )": "",
                "null": "EXERCICE\nPRÉCÉDENT"
            },
            {
                "ÉTAT DES SOLDES DE GESTION ( E S G )": "",
                "null": "62 744 467"
            },
            {
                "ÉTAT DES SOLDES DE GESTION ( E S G )": "",
                "null": "69 964 769"
            },
            {
                "ÉTAT DES SOLDES DE GESTION ( E S G )": "I",
                "null": "-7 220 302"
            },
            {
                "ÉTAT DES SOLDES DE GESTION ( E S G )": "II",
                "null": "2 086 911 889"
            },
            {
                "ÉTAT DES SOLDES DE GESTION ( E S G )": "",
                "null": "2 083 406 116"
            },
            {
                "ÉTAT DES SOLDES DE GESTION ( E S G )": "",
                "null": "3 505 773"
            },
            {
                "ÉTAT DES SOLDES DE GESTION ( E S G )": "",
                "null": "-"
            },
            {
                "ÉTAT DES SOLDES DE GESTION ( E S G )": "III",
                "null": "1 330 270 913"
            },
            {
                "ÉTAT DES SOLDES DE GESTION ( E S G )": "",
                "null": "774 088 172"
            },
            {
                "ÉTAT DES SOLDES DE GESTION ( E S G )": "",
                "null": "556 182 741"
            },
            {
                "ÉTAT DES SOLDES DE GESTION ( E S G )": "IV",
                "null": "749 420 675"
            },
            {
                "ÉTAT DES SOLDES DE GESTION ( E S G )": "V",
                "null": "-"
            },
            {
                "ÉTAT DES SOLDES DE GESTION ( E S G )": "",
                "null": "193 438 189"
            },
            {
                "ÉTAT DES SOLDES DE GESTION ( E S G )": "",
                "null": "255 329 406"
            },
            {
                "ÉTAT DES SOLDES DE GESTION ( E S G )": "",
                "null": "300 653 079"
            },
            {
                "ÉTAT DES SOLDES DE GESTION ( E S G )": "",
                "null": "-"
            },
            {
                "ÉTAT DES SOLDES DE GESTION ( E S G )": "",
                "null": "-"
            },
            {
                "ÉTAT DES SOLDES DE GESTION ( E S G )": "",
                "null": "1 700 004"
            },
            {
                "ÉTAT DES SOLDES DE GESTION ( E S G )": "",
                "null": "1 052 587"
            },
            {
                "ÉTAT DES SOLDES DE GESTION ( E S G )": "",
                "null": "187 990 986"
            },
            {
                "ÉTAT DES SOLDES DE GESTION ( E S G )": "VI",
                "null": "112 014 677"
            },
            {
                "ÉTAT DES SOLDES DE GESTION ( E S G )": "VII",
                "null": "-38 156 090"
            },
            {
                "ÉTAT DES SOLDES DE GESTION ( E S G )": "VIII",
                "null": "73 858 587"
            },
            {
                "ÉTAT DES SOLDES DE GESTION ( E S G )": "IX",
                "null": "2 560 712"
            },
            {
                "ÉTAT DES SOLDES DE GESTION ( E S G )": "",
                "null": "22 231 162"
            },
            {
                "ÉTAT DES SOLDES DE GESTION ( E S G )": "X",
                "null": "54 188 137"
            },
            {
                "ÉTAT DES SOLDES DE GESTION ( E S G )": "II CAPACITÉ D’AUTOFINANCEMENT ( C A F ) - AUTOFINANCEMENT",
                "null": ""
            },
            {
                "ÉTAT DES SOLDES DE GESTION ( E S G )": "",
                "null": "54 188 137"
            },
            {
                "ÉTAT DES SOLDES DE GESTION ( E S G )": "",
                "null": "54 188 137"
            },
            {
                "ÉTAT DES SOLDES DE GESTION ( E S G )": "",
                "null": ""
            },
            {
                "ÉTAT DES SOLDES DE GESTION ( E S G )": "",
                "null": "180 431 390"
            },
            {
                "ÉTAT DES SOLDES DE GESTION ( E S G )": "",
                "null": ""
            },
            {
                "ÉTAT DES SOLDES DE GESTION ( E S G )": "",
                "null": "-"
            },
            {
                "ÉTAT DES SOLDES DE GESTION ( E S G )": "",
                "null": "-"
            },
            {
                "ÉTAT DES SOLDES DE GESTION ( E S G )": "",
                "null": ""
            },
            {
                "ÉTAT DES SOLDES DE GESTION ( E S G )": "",
                "null": "-"
            },
            {
                "ÉTAT DES SOLDES DE GESTION ( E S G )": "",
                "null": "1 119 472"
            },
            {
                "ÉTAT DES SOLDES DE GESTION ( E S G )": "",
                "null": "21 220"
            },
            {
                "ÉTAT DES SOLDES DE GESTION ( E S G )": "I",
                "null": "233 521 275"
            },
            {
                "ÉTAT DES SOLDES DE GESTION ( E S G )": "",
                "null": "23 760 000"
            },
            {
                "ÉTAT DES SOLDES DE GESTION ( E S G )": "II",
                "null": "209 761 275"
            }
        ],
        [
            {
                "ÉTATS FINANCIERS SOCIAUX\nEXERCICE CLOS LE 31 DÉCEMBRE 2023": "TABLEAU DE FINANCEMENT DE L’EXERCICE\nI Synthèse des masses du bilan\nExercice du 1 janvier 2023\n(Montants en dhs)\nau 31 décembre 2023\nExercice Exercice Variation (a-b)\nMASSES précédent\n(a) (b) Emplois (c) Ressources (d)\n1 Financement permanent 1 613 807 872 1 380 492 985 233 314 887\n2 Moins actif immobilisé 1 559 398 646 1 386 299 428 173 099 218\n3 = Fonds de roulement fonctionnel (1-2) (A) 54 409 226 -5 806 444 - 60 215 670\n4 Actif circulant 939 779 072 956 551 737 16 772 666\n5 Moins passif circulant 615 776 174 675 765 569 59 989 395\n6 = Besoins de financement global (4-5) (B) 324 002 897 280 786 168 43 216 729 -\n7 = Trésorerie nette (actif-passif) (A - B) -269 593 671 -286 592 612 16 998 941 -\nII Emplois et Ressources\nEXERCICE EXERCICE PRÉCÉDENT\nEMPLOIS RESSOURCES EMPLOIS RESSOURCES\nRESSOURCES STABLES DE L’EXERCICE (FLUX)\nAUTOFINANCEMENT (A) - 242 392 853 - 209 761 275\nCapacité d’autofinancement - 275 062 853 - 233 521 275\n- Distribution de bénéfices - 32 670 000 - 23 760 000\nCESSIONS ET RÉDUCTIONS D’IMMOBILISATIONS (B) - 27 269 391 - 12 119 314\nCession d’immobilisations incorporelles - -\nCession d’immobilisations corporelles 71 940 1 119 472\nCession d’immobilisations financières\nRécupérations sur créances immobilisées 27 197 450 10 999 841\nAUGMENTATIONS DES CAPITAUX PROPRES ET ASSIMILÉS (C) - 9 422 155 - 5 451 955\nAugmentations de capital, apports - -\nSubventions d’investissement 9 422 155 5 451 955\nAUGMENTATIONS DES DETTES DE FINANCEMENT (D) 600 000 000 - 260 000 000\nI. TOTAL DES RESSOURCES STABLES (A+B+C+D) - 879 084 398 - 487 332 543\nEMPLOIS STABLES DE L’EXERCICE (FLUX)\nACQUISITIONS ET AUGMENTATIONS D’IMMOBILISATIONS (E) 393 543 469 233 794 681\nAcquisition d’immobilisations incorporelles 1 412 226 1 603 342\nAcquisition d’immobilisations corporelles 373 582 336 230 924 507\nAcquisition d’immobilisations financières 18 288 000 1 266 831\nAugmentation des créances immobilisées 260 907\nREMBOURSEMENTS DES CAPITAUX PROPRES (F) - -\nREMBOURSEMENTS DES DETTES DE FINANCEMENT (G) 417 412 576 292 133 532\nEMPLOIS EN NON VALEURS (H) 7 912 682 - 7 875 477\nII. TOTAL - EMPLOIS STABLES (E+F+G+H) 818 868 728 533 803 690 -\nIII. VARIATION DU BESOIN DE FINANCEMENT GLOBAL (BFG ) 43 216 729 - 36 432 880\nIV. VARIATION DE LA TRÉSORERIE 16 998 941 - 82 904 027\nTOTAL GÉNÉRAL 879 084 398 879 084 398 570 236 570 570 236 570\nÉTAT DES DÉROGATIONS\nExercice Clos au 31 décembre 2023\nINDICATION DES DÉROGATIONS JUSTIFICATIONS DES DÉROGATIONS INFLUENCE DES DÉROGATIONS SUR LE PATRIMOINE, LA SITUATION FINANCIÈRE ET LES RÉSULTATS\nI Dérogations aux principes comptables fondamentaux NÉANT NÉANT\nII Dérogations aux méthodes d’évaluation NÉANT NÉANT\nIII Dérogations aux règles d’établissement des états de synthèse NÉANT NÉANT\nÉTAT DES CHANGEMENTS DE MÉTHODES\nExercice Clos au 31 décembre 2023\nNATURE DES CHANGEMENTS JUSTIFICATION DU CHANGEMENT INFLUENCE SUR LE PATRIMOINE, LA SITUATION FINANCIÈRE ET LES RÉSULTATS\n\"I. Changements affectant les méthodes d'évaluation\" NÉANT NÉANT\n\"II. Changements affectant les règles de présentation\" NÉANT NÉANT\nTABLEAU DES IMMOBILISATIONS AUTRES QUE FINANCIÈRES\n(Montants en dhs) Exercice Clos au 31 décembre 2023\nAUGMENTATION DIMINUTION\nMONTANT\nNATURE MONTANT BRUT Production par BRUT\nDÉBUT EXERCICE Acquisition l’entreprise Virement Cession Retrait Virement FIN EXERCICE\npour elle-même\nIMMOBILISATION EN NON-VALEURS 63 897 992 7 912 682 - 2 383 290 - - - 74 193 964\n* Frais préliminaires - - - -\n* Charges à répartir sur plusieurs exercices 63 897 992 7 912 682 2 383 290 - 74 193 964\n* Primes de remboursement obligations - - - -\nIMMOBILISATIONS INCORPORELLES 36 280 270 1 412 226 - - - - - 37 692 496\n* Immobilisation en recherche et développement - - - -\n* Brevets, marques, droits et valeurs similaires 36 280 270 1 412 226 - 37 692 496\n* Fonds commercial - - - -\n* Autres immobilisations incorporelles - - - -\nIMMOBILISATIONS CORPORELLES 3 342 903 470 373 582 336 - 219 780 653 8 353 786 - 222 163 943 3 705 748 731\n* Terrains 48 325 324 - 48 325 324\n* Constructions 616 068 457 7 018 180 13 077 921 636 164 558\n* Installations techniques, matériel et outillage 2 303 011 842 88 141 656 206 702 732 8 207 198 2 589 649 032\n* Matériel de transport 12 896 896 1 601 142 130 487 14 367 551\n* Mobilier, matériel de bureau et aménagements 77 880 641 2 804 511 16 100 80 669 051\n* Autres immobilisations corporelles Informatiques - - -\n* Immobilisations corporelles en cours 284 720 310 274 016 847 222 163 943 336 573 214\nTABLEAU DES TITRES DE PARTICIPATION\n(Montants en dhs) Exercice Clos au 31 décembre 2023\nParticipation Prix Valeur Extraits des derniers états de synthèse de la société\nRaison sociale de la société Secteur d’activité Capital social au capital d’acquisition Comptable émettrice Produits inscrits au\nC P C de l’exercice\némettrice 1 2 en % global Nette Date de clôture Situation nette Résultat net 9\n3 4 5 6 7 8\nEau Technologie Environnement Captage, exploitation, industrie et commerce de toutes\n5 438 400 55% 22 762 339 22 762 339 31/12/2023 38 902 152 7 253 427 -\n“ETE” sortes de boissons\nOULMES DRINKS DEVELOPMENT Extraire fabriquer importer et exporter embouteiller\n25 500 000 100% 25 500 000 25 500 000 31/12/2023 26 193 166 693 314 -\n“ODD” promouvoir et distribuer tout type de boissons\nSÉNÉGAL WATER & BEVERAGES Extraire fabriquer importer et exporter embouteiller\n3 107 105 100% 3 107 105 3 107 105 31/12/2023 1 472 132 -322 432 -\nCOMPANY SA promouvoir et distribuer tout type de boissons\nSOCIÉTÉ AFRICAINE DES BOISSONS Extraire fabriquer importer et exporter embouteiller\n12 570 817 54% 6 778 491 3 778 491 31/12/2022 12 570 817 - -\nET EAUX MINÉRALES \"SABEM\" promouvoir et distribuer tout type de boissons\nTOTAL 46 616 322 - 58 147 935 55 147 935 - 79 138 267 7 624 309 -"
            }
        ],
        [
            {
                "TABLEAU DE FINANCEMENT DE L’EXERCICE": "",
                "null": ""
            },
            {
                "TABLEAU DE FINANCEMENT DE L’EXERCICE": "",
                "null": ""
            },
            {
                "TABLEAU DE FINANCEMENT DE L’EXERCICE": "",
                "null": ""
            },
            {
                "TABLEAU DE FINANCEMENT DE L’EXERCICE": "",
                "null": "Ressources (d)"
            },
            {
                "TABLEAU DE FINANCEMENT DE L’EXERCICE": "1\n2\n3\n4\n5\n6",
                "null": "233 314 887\n60 215 670\n16 772 666\n-"
            },
            {
                "TABLEAU DE FINANCEMENT DE L’EXERCICE": "",
                "null": ""
            },
            {
                "TABLEAU DE FINANCEMENT DE L’EXERCICE": "",
                "null": ""
            },
            {
                "TABLEAU DE FINANCEMENT DE L’EXERCICE": "",
                "null": ""
            },
            {
                "TABLEAU DE FINANCEMENT DE L’EXERCICE": "",
                "null": ""
            },
            {
                "TABLEAU DE FINANCEMENT DE L’EXERCICE": "",
                "null": ""
            },
            {
                "TABLEAU DE FINANCEMENT DE L’EXERCICE": "7",
                "null": "-"
            },
            {
                "TABLEAU DE FINANCEMENT DE L’EXERCICE": "II Emplois et Ressources",
                "null": ""
            },
            {
                "TABLEAU DE FINANCEMENT DE L’EXERCICE": "",
                "null": ""
            },
            {
                "TABLEAU DE FINANCEMENT DE L’EXERCICE": "",
                "null": "RESSOURCES"
            },
            {
                "TABLEAU DE FINANCEMENT DE L’EXERCICE": "RESSOURCES STABLES DE L’EXERCICE (FLUX)",
                "null": ""
            },
            {
                "TABLEAU DE FINANCEMENT DE L’EXERCICE": "AUTOFINANCEMENT",
                "null": "209 761 275"
            },
            {
                "TABLEAU DE FINANCEMENT DE L’EXERCICE": "Capacité d’autofinancement",
                "null": "233 521 275"
            },
            {
                "TABLEAU DE FINANCEMENT DE L’EXERCICE": "- Distribution de bénéfices",
                "null": "23 760 000"
            },
            {
                "TABLEAU DE FINANCEMENT DE L’EXERCICE": "CESSIONS ET RÉDUCTIONS D’IMMOBILISATIONS",
                "null": "12 119 314"
            },
            {
                "TABLEAU DE FINANCEMENT DE L’EXERCICE": "Cession d’immobilisations incorporelles",
                "null": "-"
            },
            {
                "TABLEAU DE FINANCEMENT DE L’EXERCICE": "Cession d’immobilisations corporelles",
                "null": "1 119 472"
            },
            {
                "TABLEAU DE FINANCEMENT DE L’EXERCICE": "Cession d’immobilisations financières",
                "null": ""
            },
            {
                "TABLEAU DE FINANCEMENT DE L’EXERCICE": "Récupérations sur créances immobilisées",
                "null": "10 999 841"
            },
            {
                "TABLEAU DE FINANCEMENT DE L’EXERCICE": "AUGMENTATIONS DES CAPITAUX PROPRES ET ASSIMILÉS",
                "null": "5 451 955"
            },
            {
                "TABLEAU DE FINANCEMENT DE L’EXERCICE": "Augmentations de capital, apports",
                "null": "-"
            },
            {
                "TABLEAU DE FINANCEMENT DE L’EXERCICE": "Subventions d’investissement",
                "null": "5 451 955"
            },
            {
                "TABLEAU DE FINANCEMENT DE L’EXERCICE": "AUGMENTATIONS DES DETTES DE FINANCEMENT",
                "null": "260 000 000"
            },
            {
                "TABLEAU DE FINANCEMENT DE L’EXERCICE": "I. TOTAL DES RESSOURCES STABLES (A+B+C+D)",
                "null": "487 332 543"
            },
            {
                "TABLEAU DE FINANCEMENT DE L’EXERCICE": "EMPLOIS STABLES DE L’EXERCICE (FLUX)",
                "null": ""
            },
            {
                "TABLEAU DE FINANCEMENT DE L’EXERCICE": "ACQUISITIONS ET AUGMENTATIONS D’IMMOBILISATIONS",
                "null": ""
            },
            {
                "TABLEAU DE FINANCEMENT DE L’EXERCICE": "Acquisition d’immobilisations incorporelles",
                "null": ""
            },
            {
                "TABLEAU DE FINANCEMENT DE L’EXERCICE": "Acquisition d’immobilisations corporelles",
                "null": ""
            },
            {
                "TABLEAU DE FINANCEMENT DE L’EXERCICE": "Acquisition d’immobilisations financières",
                "null": ""
            },
            {
                "TABLEAU DE FINANCEMENT DE L’EXERCICE": "Augmentation des créances immobilisées",
                "null": ""
            },
            {
                "TABLEAU DE FINANCEMENT DE L’EXERCICE": "REMBOURSEMENTS DES CAPITAUX PROPRES",
                "null": ""
            },
            {
                "TABLEAU DE FINANCEMENT DE L’EXERCICE": "REMBOURSEMENTS DES DETTES DE FINANCEMENT",
                "null": ""
            },
            {
                "TABLEAU DE FINANCEMENT DE L’EXERCICE": "EMPLOIS EN NON VALEURS",
                "null": ""
            },
            {
                "TABLEAU DE FINANCEMENT DE L’EXERCICE": "II. TOTAL - EMPLOIS STABLES (E+F+G+H)",
                "null": "-"
            },
            {
                "TABLEAU DE FINANCEMENT DE L’EXERCICE": "III. VARIATION DU BESOIN DE FINANCEMENT GLOBAL (BFG )",
                "null": ""
            },
            {
                "TABLEAU DE FINANCEMENT DE L’EXERCICE": "IV. VARIATION DE LA TRÉSORERIE",
                "null": "82 904 027"
            },
            {
                "TABLEAU DE FINANCEMENT DE L’EXERCICE": "TOTAL GÉNÉRAL",
                "null": "570 236 570"
            }
        ],
        [
            {
                "ÉTAT DES DÉROGATIONS": "Exercice Clos au 31 décembre 2023",
                "null": ""
            },
            {
                "ÉTAT DES DÉROGATIONS": "INDICATION DES DÉROGATIONS",
                "null": "INFLUENCE DES DÉROGATIONS SUR LE PATRIMOINE, LA SITUATION FINANCIÈRE ET LES RÉSULTATS"
            },
            {
                "ÉTAT DES DÉROGATIONS": "I Dérogations aux principes comptables fondamentaux",
                "null": "NÉANT"
            },
            {
                "ÉTAT DES DÉROGATIONS": "II Dérogations aux méthodes d’évaluation",
                "null": "NÉANT"
            },
            {
                "ÉTAT DES DÉROGATIONS": "III Dérogations aux règles d’établissement des états de synthèse",
                "null": "NÉANT"
            }
        ],
        [
            {
                "ÉTAT DES CHANGEMENTS DE MÉTHODES": "Exercice Clos au 31 décembre 2023",
                "null": ""
            },
            {
                "ÉTAT DES CHANGEMENTS DE MÉTHODES": "NATURE DES CHANGEMENTS",
                "null": "INFLUENCE SUR LE PATRIMOINE, LA SITUATION FINANCIÈRE ET LES RÉSULTATS"
            },
            {
                "ÉTAT DES CHANGEMENTS DE MÉTHODES": "\"I. Changements affectant les méthodes d'évaluation\"",
                "null": "NÉANT"
            },
            {
                "ÉTAT DES CHANGEMENTS DE MÉTHODES": "\"II. Changements affectant les règles de présentation\"",
                "null": "NÉANT"
            }
        ],
        [
            {
                "TABLEAU DES IMMOBILISATIONS AUTRES QUE FINANCIÈRES": "(Montants en dhs) Exercice Clos au 31 décembre 2023",
                "null": ""
            },
            {
                "TABLEAU DES IMMOBILISATIONS AUTRES QUE FINANCIÈRES": "NATURE",
                "null": "MONTANT\nBRUT\nFIN EXERCICE"
            },
            {
                "TABLEAU DES IMMOBILISATIONS AUTRES QUE FINANCIÈRES": "",
                "null": ""
            },
            {
                "TABLEAU DES IMMOBILISATIONS AUTRES QUE FINANCIÈRES": "IMMOBILISATION EN NON-VALEURS",
                "null": "74 193 964"
            },
            {
                "TABLEAU DES IMMOBILISATIONS AUTRES QUE FINANCIÈRES": "* Frais préliminaires\n* Charges à répartir sur plusieurs exercices\n* Primes de remboursement obligations",
                "null": "-"
            },
            {
                "TABLEAU DES IMMOBILISATIONS AUTRES QUE FINANCIÈRES": "",
                "null": "74 193 964"
            },
            {
                "TABLEAU DES IMMOBILISATIONS AUTRES QUE FINANCIÈRES": "",
                "null": "-"
            },
            {
                "TABLEAU DES IMMOBILISATIONS AUTRES QUE FINANCIÈRES": "IMMOBILISATIONS INCORPORELLES",
                "null": "37 692 496"
            },
            {
                "TABLEAU DES IMMOBILISATIONS AUTRES QUE FINANCIÈRES": "* Immobilisation en recherche et développement\n* Brevets, marques, droits et valeurs similaires\n* Fonds commercial\n* Autres immobilisations incorporelles",
                "null": "-"
            },
            {
                "TABLEAU DES IMMOBILISATIONS AUTRES QUE FINANCIÈRES": "",
                "null": "37 692 496"
            },
            {
                "TABLEAU DES IMMOBILISATIONS AUTRES QUE FINANCIÈRES": "",
                "null": "-"
            },
            {
                "TABLEAU DES IMMOBILISATIONS AUTRES QUE FINANCIÈRES": "",
                "null": "-"
            },
            {
                "TABLEAU DES IMMOBILISATIONS AUTRES QUE FINANCIÈRES": "IMMOBILISATIONS CORPORELLES",
                "null": "3 705 748 731"
            },
            {
                "TABLEAU DES IMMOBILISATIONS AUTRES QUE FINANCIÈRES": "* Terrains\n* Constructions\n* Installations techniques, matériel et outillage\n* Matériel de transport\n* Mobilier, matériel de bureau et aménagements\n* Autres immobilisations corporelles Informatiques\n* Immobilisations corporelles en cours",
                "null": "48 325 324"
            },
            {
                "TABLEAU DES IMMOBILISATIONS AUTRES QUE FINANCIÈRES": "",
                "null": "636 164 558"
            },
            {
                "TABLEAU DES IMMOBILISATIONS AUTRES QUE FINANCIÈRES": "",
                "null": "2 589 649 032"
            },
            {
                "TABLEAU DES IMMOBILISATIONS AUTRES QUE FINANCIÈRES": "",
                "null": "14 367 551"
            },
            {
                "TABLEAU DES IMMOBILISATIONS AUTRES QUE FINANCIÈRES": "",
                "null": "80 669 051"
            },
            {
                "TABLEAU DES IMMOBILISATIONS AUTRES QUE FINANCIÈRES": "",
                "null": "-"
            },
            {
                "TABLEAU DES IMMOBILISATIONS AUTRES QUE FINANCIÈRES": "",
                "null": "336 573 214"
            }
        ],
        [
            {
                "TABLEAU DES TITRES DE PARTICIPATION": "(Montants en dhs) Exercice Clos au 31 décembre 2023",
                "null": ""
            },
            {
                "TABLEAU DES TITRES DE PARTICIPATION": "Raison sociale de la société\némettrice",
                "null": "Produits inscrits au\nC P C de l’exercice\n9"
            },
            {
                "TABLEAU DES TITRES DE PARTICIPATION": "",
                "null": ""
            },
            {
                "TABLEAU DES TITRES DE PARTICIPATION": "Eau Technologie Environnement\n“ETE”",
                "null": "-"
            },
            {
                "TABLEAU DES TITRES DE PARTICIPATION": "OULMES DRINKS DEVELOPMENT\n“ODD”",
                "null": "-"
            },
            {
                "TABLEAU DES TITRES DE PARTICIPATION": "SÉNÉGAL WATER & BEVERAGES\nCOMPANY SA",
                "null": "-"
            },
            {
                "TABLEAU DES TITRES DE PARTICIPATION": "SOCIÉTÉ AFRICAINE DES BOISSONS\nET EAUX MINÉRALES \"SABEM\"",
                "null": "-"
            },
            {
                "TABLEAU DES TITRES DE PARTICIPATION": "TOTAL",
                "null": "-"
            }
        ],
        [
            {
                "ÉTATS FINANCIERS SOCIAUX\nEXERCICE CLOS LE 31 DÉCEMBRE 2023": "TABLEAU DES PROVISIONS\n(Montants en dhs) Exercice Clos au 31 décembre 2023\nMontant début Dotations Reprises\nNature Montant fin d’exercice\nd’exercice d’exploitation financières non courantes d’exploitation financières non courantes\n1 Provisions pour dépréciation de l’actif immobilisé 15 779 800 3 000 000 - - 15 779 800 3 000 000\n2 Provisions réglementées\n3 Provisions durables pour risques et charges\nSOUS TOTAL (A) 15 779 800 - 3 000 000 - - - 15 779 800 3 000 000\n4 Provisions pour dépréciation de l’actif circulant 90 498 627 9 324 765 5 817 212 94 006 180,38\n( hors trésorerie )(Clients et stocks)\n5 Autres provisions pour risques et charges 9 538 330 342 241 2 018 386 6 400 000 1 462 185\n(Écarts de conversion)\n6 Provisions pour dépréciation des comptes de trésorerie - - - - - - - -\nSOUS TOTAL (B) 100 036 957 9 324 765 342 241 - 5 817 212 2 018 386 6 400 000 95 468 365\nTOTAL ( A + B ) 115 816 757 9 324 765 3 342 241 - 5 817 212 2 018 386 22 179 800 98 468 365\nTABLEAU DES CRÉANCES\n(Montants en dhs) Exercice Clos au 31 décembre 2023\nANALYSE PAR ÉCHÉANCE AUTRE ANALYSE\nCRÉANCES TOTAL Échues et non Montants Montants sur l’État et Montants sur les Montants représentés\nPlus d’un an Moins d’un an\nrecouvrées en devises organismes publics entreprises liées par des effets\nDE L’ACTIF IMMOBILISÉ 4 449 454 4 449 454 - - - - - -\n* Prêts immobilisés\n* Autres créances financières 4 449 454 4 449 454\nDE L’ACTIF CIRCULANT 742 842 064 - 492 668 218 245 310 296 117 900 333 50 296 609 82 581 402 89 058 173\n* Fournisseurs débiteurs 166 049 345 166 049 345 90 197 647 26 500 000\n* Clients et comptes rattachés 468 135 661 236 919 503 231 216 159 10 793 359 15 299 982 89 058 173\n* Personnel 3 289 963 3 289 963\n* État 50 296 609 50 296 609 50 296 609\n* Comptes d’associés 13 401 499 13 401 499 13 401 499 13 401 499\n* Autres débiteurs 22 829 939 3 872 252 14 094 137 3 507 829 12 737 957\n* Comptes de régularisation - Actif 18 839 050 18 839 050 14 641 964\nTABLEAU DES DETTES\n(Montants en dhs) Exercice Clos au 31 décembre 2023\nANALYSE PAR ÉCHÉANCE Autres analyse\nDETTES TOTAL Échues et non Montants Montants sur l’État Montants sur les Montants représentés\nPlus d’un an Moins d’un an\nrecouvrées en devises et organismes publics entreprises liées par des effets\nDE FINANCEMENT 984 065 950 537 392 410 447 173 539 - - - - -\n* Emprunts obligataires 458 333 333 238 833 333 220 000 000\n* Autres dettes de financement 525 732 616 298 559 077 227 173 539\nDU PASSIF CIRCULANT 614 047 040 - 587 113 678 26 933 363 15 346 217 317 019 607 7 456 562 -33 434 109\n* Fournisseurs 252 534 748 225 601 385 26 933 363 15 346 217 1 032 558 -33 434 109\n* Clients créditeurs consignation 15 356 549 15 356 549\n* Personnel 11 508 739 11 508 739\n* Organismes sociaux 20 281 086 20 281 086 20 281 086\n* État 296 738 521 296 738 521 296 738 521\n* Comptes d’associés 1 699 951 1 699 951 1 699 951\n* Autres créanciers - - -\n* Comptes de régularisation - Passif 15 927 447 15 927 447 4 724 053\nTABLEAU DES SÛRETÉS RÉELLES DONNÉES OU REÇUES\nExercice Clos au 31 décembre 2023\nMONTANT COUVERT PAR LA NATURE DATE ET LIEU OBJET VALEUR COMPTABLE NETTE DE LA SÛRETÉ DONNÉE\nTIERS CRÉDITEURS OU DÉBITEURS\nSÛRETÉ (1) D’INSCRIPTION (2) (3) À LA DATE DE CLÔTURE\n* Sûretés données\nN É A N T\n* Sûretés reçues\n(1) Gage : 1- Hypothèque : 2- Nantissement : 3- Warrant : 4- Autres : 5- (à préciser)\n(2) préciser si la sûreté est donnée au profit d’entreprises ou de personnes tierces (sûretés données)\n(entreprises liées, associés, membres du personnel)\n(3) préciser si la sûreté reçue par l’entreprise provient de personnes tierces autres que le débiteur (sûretés reçues)\nENGAGEMENTS FINANCIERS REÇUS OU DONNÉS HORS OPÉRATIONS DE CRÉDIT-BAIL\n(Montants en dhs) Exercice Clos au 31 décembre 2023\nMONTANTS\nMONTANTS\nENGAGEMENTS DONNÉS EXERCICE\nEXERCICE\nPRÉCÉDENT\n* Avals et cautions\n* Engagements en matière de pensions de retraites et obligations similaires\n* Autres engagements donnés ( vis-à-vis de l'Administration des douanes ) 10 000 000 10 000 000\n* Garantie de restitution de paiement anticipé dans le cadre de l'accord de subvention conclu entre LEMO et L'UNOPS \"Bureau des Nations Unies pour les services d’appui aux projets\". 20 562 367 21 310 330\n* Une caution en faveur du MINURSO 202 489 202 489\n* Une caution définitive en faveur de la DPEFLCD* 10 000\n* Direction provinciale des Eaux et Forêts et à la Lutte Contre la Désertification\n* Une caution définitive en faveur de HCEFLCD* portant reconduction d'amodiation du droit de chasse 10 000\n* Haut commissariat aux Eaux et Forêts et à la Lutte Contre la Désertification\n* Une quittance subrogative dans le cadre du contrat d'affacturage avec la Banque Centrale Populaire 84 101 504 88 679 462\nTotal (1) 114 866 359 120 212 281\n(1) dont engagements à l'égard d'entreprises liées ……………….\nENGAGEMENTS REÇUS MONTANTS EXERCICE MONTANTS EXERCICE PRÉCÉDENT\n* Avals et cautions\nCaution bancaire: Limonades Sidi Bannour\nCaution bancaire: Yassine Boissons\nCautions solidaires 112 100 000 77 400 000\n* Autres engagements donnés\nTotal 112 100 000 77 400 000\n(1) Gage : 1- Hypothèque : 2- Nantissement : 3- Warrant : 4- Autres : 5- (à préciser)\n(2) préciser si la sûreté est donnée au profit d’entreprises ou de personnes tierces (sûretés données) (entreprises liées, associés, membres du personnel)\n(3) préciser si la sûreté reçue par l’entreprise provient de personnes tierces autres que le débiteur (sûretés reçues)\nÉTAT DES PASSIFS ÉVENTUELS\nExercice Clos au 31 décembre 2023\n* Conformément à la législation fiscale les exercices, 2020, 2021, 2022 et 2023 ne sont pas encore prescrit. Les déclarations fiscales des Eaux Minérales d’Oulmès au titre de l’impôt sur les sociétés (IS), de la TVA et de l’impôt sur les revenus salariaux (IR)\npeuvent faire l’objet de contrôle par l’administration et de rappels éventuels d’impôts, taxes.\n* Les déclarations sociales au titre de la CNSS peuvent faire l’objet de contrôle et de rappels éventuels de cotisations."
            }
        ],
        [
            {
                "TABLEAU DES PROVISIONS": "(Montants en dhs) Exercice Clos au 31 décembre 2023",
                "null": ""
            },
            {
                "TABLEAU DES PROVISIONS": "Nature",
                "null": "Montant fin d’exercice"
            },
            {
                "TABLEAU DES PROVISIONS": "",
                "null": ""
            },
            {
                "TABLEAU DES PROVISIONS": "1 Provisions pour dépréciation de l’actif immobilisé\n2 Provisions réglementées",
                "null": "3 000 000"
            },
            {
                "TABLEAU DES PROVISIONS": "",
                "null": ""
            },
            {
                "TABLEAU DES PROVISIONS": "3 Provisions durables pour risques et charges",
                "null": ""
            },
            {
                "TABLEAU DES PROVISIONS": "SOUS TOTAL (A)",
                "null": "3 000 000"
            },
            {
                "TABLEAU DES PROVISIONS": "4 Provisions pour dépréciation de l’actif circulant",
                "null": "94 006 180,38"
            },
            {
                "TABLEAU DES PROVISIONS": "( hors trésorerie )(Clients et stocks)",
                "null": ""
            },
            {
                "TABLEAU DES PROVISIONS": "5 Autres provisions pour risques et charges",
                "null": "1 462 185"
            },
            {
                "TABLEAU DES PROVISIONS": "(Écarts de conversion)",
                "null": ""
            },
            {
                "TABLEAU DES PROVISIONS": "6 Provisions pour dépréciation des comptes de trésorerie",
                "null": "-"
            },
            {
                "TABLEAU DES PROVISIONS": "SOUS TOTAL (B)",
                "null": "95 468 365"
            },
            {
                "TABLEAU DES PROVISIONS": "TOTAL ( A + B )",
                "null": "98 468 365"
            }
        ],
        [
            {
                "TABLEAU DES CRÉANCES": "(Montants en dhs)",
                "null": ""
            },
            {
                "TABLEAU DES CRÉANCES": "CRÉANCES",
                "null": ""
            },
            {
                "TABLEAU DES CRÉANCES": "",
                "null": "Montants représentés\npar des effets"
            },
            {
                "TABLEAU DES CRÉANCES": "DE L’ACTIF IMMOBILISÉ",
                "null": "-"
            },
            {
                "TABLEAU DES CRÉANCES": "* Prêts immobilisés\n* Autres créances financières",
                "null": ""
            },
            {
                "TABLEAU DES CRÉANCES": "DE L’ACTIF CIRCULANT",
                "null": "89 058 173"
            },
            {
                "TABLEAU DES CRÉANCES": "* Fournisseurs débiteurs\n* Clients et comptes rattachés\n* Personnel",
                "null": "89 058 173"
            },
            {
                "TABLEAU DES CRÉANCES": "* État",
                "null": ""
            },
            {
                "TABLEAU DES CRÉANCES": "* Comptes d’associés\n* Autres débiteurs\n* Comptes de régularisation - Actif",
                "null": ""
            }
        ],
        [
            {
                "TABLEAU DES DETTES": "(Montants en dhs) Exercice Clos au 31 décembre 2023",
                "null": ""
            },
            {
                "TABLEAU DES DETTES": "DETTES",
                "null": ""
            },
            {
                "TABLEAU DES DETTES": "",
                "null": "Montants représentés\npar des effets"
            },
            {
                "TABLEAU DES DETTES": "DE FINANCEMENT",
                "null": "-"
            },
            {
                "TABLEAU DES DETTES": "* Emprunts obligataires\n* Autres dettes de financement",
                "null": ""
            },
            {
                "TABLEAU DES DETTES": "DU PASSIF CIRCULANT",
                "null": "-33 434 109"
            },
            {
                "TABLEAU DES DETTES": "* Fournisseurs\n* Clients créditeurs consignation\n* Personnel\n* Organismes sociaux",
                "null": "-33 434 109"
            },
            {
                "TABLEAU DES DETTES": "* État",
                "null": ""
            },
            {
                "TABLEAU DES DETTES": "* Comptes d’associés\n* Autres créanciers\n* Comptes de régularisation - Passif",
                "null": ""
            }
        ],
        [
            {
                "TABLEAU DES SÛRETÉS RÉELLES DONNÉES OU REÇUES": "Exercice Clos au 31 décembre 2023",
                "null": ""
            },
            {
                "TABLEAU DES SÛRETÉS RÉELLES DONNÉES OU REÇUES": "TIERS CRÉDITEURS OU DÉBITEURS",
                "null": "VALEUR COMPTABLE NETTE DE LA SÛRETÉ DONNÉE\nÀ LA DATE DE CLÔTURE"
            },
            {
                "TABLEAU DES SÛRETÉS RÉELLES DONNÉES OU REÇUES": "* Sûretés données",
                "null": ""
            },
            {
                "TABLEAU DES SÛRETÉS RÉELLES DONNÉES OU REÇUES": "* Sûretés reçues",
                "null": ""
            }
        ],
        [
            {
                "ENGAGEMENTS FINANCIERS REÇUS OU DONNÉS HORS OPÉRATIONS DE CRÉDIT-BAIL": "(Montants en dhs)",
                "null": ""
            },
            {
                "ENGAGEMENTS FINANCIERS REÇUS OU DONNÉS HORS OPÉRATIONS DE CRÉDIT-BAIL": "ENGAGEMENTS DONNÉS",
                "null": "MONTANTS\nEXERCICE\nPRÉCÉDENT"
            },
            {
                "ENGAGEMENTS FINANCIERS REÇUS OU DONNÉS HORS OPÉRATIONS DE CRÉDIT-BAIL": "* Avals et cautions",
                "null": ""
            },
            {
                "ENGAGEMENTS FINANCIERS REÇUS OU DONNÉS HORS OPÉRATIONS DE CRÉDIT-BAIL": "* Engagements en matière de pensions de retraites et obligations similaires",
                "null": ""
            },
            {
                "ENGAGEMENTS FINANCIERS REÇUS OU DONNÉS HORS OPÉRATIONS DE CRÉDIT-BAIL": "* Autres engagements donnés ( vis-à-vis de l'Administration des douanes )",
                "null": "10 000 000"
            },
            {
                "ENGAGEMENTS FINANCIERS REÇUS OU DONNÉS HORS OPÉRATIONS DE CRÉDIT-BAIL": "* Garantie de restitution de paiement anticipé dans le cadre de l'accord de subvention conclu entre LEMO et L'UNOPS \"Bureau des Nations Unies pour les services d’appui aux projets\".",
                "null": "21 310 330"
            },
            {
                "ENGAGEMENTS FINANCIERS REÇUS OU DONNÉS HORS OPÉRATIONS DE CRÉDIT-BAIL": "* Une caution en faveur du MINURSO",
                "null": "202 489"
            },
            {
                "ENGAGEMENTS FINANCIERS REÇUS OU DONNÉS HORS OPÉRATIONS DE CRÉDIT-BAIL": "* Une caution définitive en faveur de la DPEFLCD*",
                "null": "10 000"
            },
            {
                "ENGAGEMENTS FINANCIERS REÇUS OU DONNÉS HORS OPÉRATIONS DE CRÉDIT-BAIL": "* Direction provinciale des Eaux et Forêts et à la Lutte Contre la Désertification",
                "null": ""
            },
            {
                "ENGAGEMENTS FINANCIERS REÇUS OU DONNÉS HORS OPÉRATIONS DE CRÉDIT-BAIL": "* Une caution définitive en faveur de HCEFLCD* portant reconduction d'amodiation du droit de chasse",
                "null": "10 000"
            },
            {
                "ENGAGEMENTS FINANCIERS REÇUS OU DONNÉS HORS OPÉRATIONS DE CRÉDIT-BAIL": "* Haut commissariat aux Eaux et Forêts et à la Lutte Contre la Désertification",
                "null": ""
            },
            {
                "ENGAGEMENTS FINANCIERS REÇUS OU DONNÉS HORS OPÉRATIONS DE CRÉDIT-BAIL": "* Une quittance subrogative dans le cadre du contrat d'affacturage avec la Banque Centrale Populaire",
                "null": "88 679 462"
            },
            {
                "ENGAGEMENTS FINANCIERS REÇUS OU DONNÉS HORS OPÉRATIONS DE CRÉDIT-BAIL": "Total (1)",
                "null": "120 212 281"
            },
            {
                "ENGAGEMENTS FINANCIERS REÇUS OU DONNÉS HORS OPÉRATIONS DE CRÉDIT-BAIL": "(1) dont engagements à l'égard d'entreprises liées ……………….",
                "null": ""
            },
            {
                "ENGAGEMENTS FINANCIERS REÇUS OU DONNÉS HORS OPÉRATIONS DE CRÉDIT-BAIL": "ENGAGEMENTS REÇUS",
                "null": "MONTANTS EXERCICE PRÉCÉDENT"
            },
            {
                "ENGAGEMENTS FINANCIERS REÇUS OU DONNÉS HORS OPÉRATIONS DE CRÉDIT-BAIL": "* Avals et cautions",
                "null": ""
            },
            {
                "ENGAGEMENTS FINANCIERS REÇUS OU DONNÉS HORS OPÉRATIONS DE CRÉDIT-BAIL": "Caution bancaire: Limonades Sidi Bannour",
                "null": ""
            },
            {
                "ENGAGEMENTS FINANCIERS REÇUS OU DONNÉS HORS OPÉRATIONS DE CRÉDIT-BAIL": "Caution bancaire: Yassine Boissons",
                "null": ""
            },
            {
                "ENGAGEMENTS FINANCIERS REÇUS OU DONNÉS HORS OPÉRATIONS DE CRÉDIT-BAIL": "Cautions solidaires",
                "null": "77 400 000"
            },
            {
                "ENGAGEMENTS FINANCIERS REÇUS OU DONNÉS HORS OPÉRATIONS DE CRÉDIT-BAIL": "* Autres engagements donnés",
                "null": ""
            },
            {
                "ENGAGEMENTS FINANCIERS REÇUS OU DONNÉS HORS OPÉRATIONS DE CRÉDIT-BAIL": "Total",
                "null": "77 400 000"
            }
        ],
        [
            {
                "ÉTAT DES PASSIFS ÉVENTUELS": "Exercice Clos au 31 décembre 2023"
            },
            {
                "ÉTAT DES PASSIFS ÉVENTUELS": "* Conformément à la législation fiscale les exercices, 2020, 2021, 2022 et 2023 ne sont pas encore prescrit. Les déclarations fiscales des Eaux Minérales d’Oulmès au titre de l’impôt sur les sociétés (IS), de la TVA et de l’impôt sur les revenus salariaux (IR)\npeuvent faire l’objet de contrôle par l’administration et de rappels éventuels d’impôts, taxes.\n* Les déclarations sociales au titre de la CNSS peuvent faire l’objet de contrôle et de rappels éventuels de cotisations."
            }
        ],
        [
            {
                "RAPPORT GÉNÉRAL DES\nCOMMISSAIRES AUX COMPTES\nEXERCICE DU 1ER JANVIER AU 31 DECEMBRE 2023": "1. Provision pour dépréciation des créances clients\nRisque identifié Notre réponse\nAu 31 décembre 2023, les créances clients dont Nos travaux ont notamment consisté à :\nla valeur brute s’élève à 468,1 millions de - Prendre connaissance des procédures\ndirhams sont provisionnées à hauteur de 80,2 d’identification des créances clients à\n7, Bd Driss Slaoui millions de dirhams. déprécier et de détermination du montant\n3 27 0, 0B 5d 0 A Cb ad se al bla latif n B caen Kaddour 2 M0 a r1 o6 c0 Casablanca L rea q ud ieé rt te r l’m exin ea rcti io cn e dd ue s j ugc eré ma en nc te s d eà l a d dé ip reré ctc ioie nr - Tde es s td eé r p ler é foc nia ct tio ion ns n à e mco en ns t t da ete sr c ; ontrôles dans\nMaroc sur la base d’une analyse continue de le cadre des procédures mises en œuvre\nl’évolution du risque client. pour déterminer le niveau des dépréciations\nCompte tenu du caractère significatif du poste des créances clients ;\nau regard du bilan de la société, du jugement - Apprécier le caractère raisonnable des\nnécessaire à l’estimation des créances à hypothèses retenues par la Direction pour\nAux Actionnaires de la société déprécier, nous avons considéré que ce sujet évaluer les dépréciations à constater ;\nLes Eaux Minérales d’Oulmès S.A. constitue un point clé de l’audit. - Examiner la correcte évaluation des\nQuartier industriel Bouskoura dépréciations à constater selon la méthode\nCasablanca de provisionnement de la société.\n2. Evaluation des titres de participation\nRAPPORT GENERAL DES COMMISSAIRES AUX COMPTES Risque identifié Notre réponse\nEXERCICE DU 1er JANVIER AU 31 DECEMBRE 2023 Au 31 décembre 2023, la valeur nette des titres Nos travaux ont consisté à :\nde participation s’élève à 55,1 millions de - Prendre connaissance du processus mis en\nOpinion dirhams. Les titres de participation sont place par la direction dans le cadre des tests\nenregistrés à leur prix d’acquisition diminués de dépréciation;\nConformément à la mission qui nous a été confiée par votre Assemblée Générale, nous avons effectué d’une provision pour dépréciation, le cas - Examiner les hypothèses et les prévisions\nl'audit des états de synthèse ci-joints de la société LES EAUX MINERALES D’OULMES S.A., échéant. de croissance retenues au regard de\ncomprenant le bilan au 31 décembre 2023, le compte de produits et charges, l’état des soldes de Les techniques retenues par la direction pour l’environnement économique en les\ngestion, le tableau de financement pour l’exercice clos à cette date, ainsi que l’état des informations procéder à la valorisation nette de ces titres comparant aux données disponibles pour\ncomplémentaires (ETIC). Ces états de synthèse font ressortir un montant de capitaux propres et comportent une part significative de jugement l’industrie et aux tendances historiques\nassimilés de MAD 629.741.922 dont un bénéfice net de MAD 73.975.309. quant aux choix de la méthodologie et des récentes des participations;\nhypothèses utilisées. - Effectuer des tests de sensibilité sur la\nNous certifions que les états de synthèse cités au premier paragraphe ci-dessus sont réguliers et En raison du montant significatif des titres de valeur d’inventaire.\nsincères et donnent, dans tous leurs aspects significatifs, une image fidèle du résultat des opérations participation, et de l’importance du jugement de\nd M vie gI N ul’ eEe uRx re A ar Lc ui Ec MSe a é D roc ’o cO .u Ulé L Mai En Ssi Squ .Ae . d ae u la 3 1s i dtu éa ct eio mn b f ri en a 2n 0c 2iè 3r ,e ce ot n fd ou r mp éa mtri em no t in ae u d re é féla re s no tic ei lé t cé o mLE pS ta bE leA U eX n l d d da ’ e ’ i an sD uv di ter i ie tn tr .c etat si io ren d, e p no pou aur rs ti l ca a i pvd o aé n tit s oe nr cm o ci n on s ma it d mio én eré d ule ’ né vl pa a o lu iv na a t l te i cou ln ér\nFondement de l’opinion Responsabilités de la direction et des responsables de la gouvernance pour les états de\nsynthèse\nNous avons effectué notre audit selon les Normes de la Profession au Maroc. Les responsabilités qui\nnous incombent en vertu de ces normes sont plus amplement décrites dans la section « Responsabilités La direction est responsable de la préparation et de la présentation fidèle des états de synthèse,\nde l’auditeur à l’égard de l’audit des états de synthèse » du présent rapport. Nous sommes indépendants conformément au référentiel comptable en vigueur au Maroc, ainsi que du contrôle interne qu'elle\nde la société conformément aux règles de déontologie qui s’appliquent à l’audit des états de synthèse considère comme nécessaire pour permettre la préparation d'états de synthèse exempts d'anomalies\nau Maroc et nous nous sommes acquittés des autres responsabilités déontologiques qui nous significatives, que celles-ci résultent de fraudes ou d'erreurs.\nincombent selon ces règles. Nous estimons que les éléments probants que nous avons obtenus sont\nsuffisants et appropriés pour fonder notre opinion d’audit. Lors de la préparation des états de synthèse, c’est à la direction qu’il incombe d’évaluer la capacité de\nla société à poursuivre son exploitation, de communiquer, le cas échéant, les questions se rapportant à\nQuestions clés de l’audit la continuité de l’exploitation et d’appliquer le principe comptable de continuité d’exploitation, sauf si la\ndirection a l’intention de liquider la société ou de cesser son activité ou si aucune autre solution réaliste\nLes questions clés de l’audit sont les questions qui, selon notre jugement professionnel, ont été les plus ne s’offre à elle.\nimportantes dans l’audit des états de synthèse de la période considérée. Ces questions ont été traitées\ndans le contexte de notre audit des états de synthèse pris dans leur ensemble et aux fins de la formation Il incombe aux responsables de la gouvernance de surveiller le processus d’information financière de\nde notre opinion sur ceux-ci, et nous n’exprimons pas une opinion distincte sur ces questions. la société.\nResponsabilités de l’auditeur à l’égard de l’audit des états de synthèse\nNos objectifs sont d’obtenir l’assurance raisonnable que les états de synthèse pris dans leur ensemble\nsont exempts d’anomalies significatives, que celles-ci résultent de fraudes ou d’erreurs et de délivrer un\nrapport de l’auditeur contenant notre opinion.\nL’assurance raisonnable correspond à un niveau élevé d’assurance, qui ne garantit toutefois pas qu’un\naudit réalisé conformément aux normes de la profession au Maroc permettra toujours de détecter toute\nanomalie significative qui pourrait exister. Les anomalies peuvent résulter de fraudes ou d’erreurs et\nelles sont considérées comme significatives lorsqu’il est raisonnable de s’attendre à ce que,\n1\n2\nindividuellement ou collectivement, elles puissent influer sur les décisions économiques que les\nutilisateurs des états de synthèse prennent en se fondant sur ceux-ci.\nDans le cadre d’un audit réalisé conformément aux normes de la profession au Maroc, nous exerçons\nnotre jugement professionnel et faisons preuve d’esprit critique tout au long de cet audit. En outre :\n nous identifions et évaluons les risques que les états de synthèse comportent des anomalies\nsignificatives, que celles-ci résultent de fraudes ou d’erreurs, concevons et mettons en œuvre des\nprocédures d’audit en réponse à ces risques, et réunissons des éléments probants suffisants et\nappropriés pour fonder notre opinion. Le risque de non-détection d’une anomalie significative\nrésultant d’une fraude est plus élevé que celui d’une anomalie significative résultant d’une erreur,\ncar la fraude peut impliquer la collusion, la falsification, les omissions volontaires, les fausses\ndéclarations ou le contournement du contrôle interne ;\n nous acquérons une compréhension des éléments du contrôle interne pertinents pour l’audit afin\nde concevoir des procédures d’audit appropriées aux circonstances, et non dans le but d’exprimer\nune opinion sur l’efficacité du contrôle interne de la société ;\n nous apprécions le caractère approprié des méthodes comptables retenues et le caractère\nraisonnable des estimations comptables faites par la direction, de même que des informations y\nafférentes fournies par cette dernière ;\n nous tirons une conclusion quant au caractère approprié de l’utilisation par la direction du principe\ncomptable de continuité d’exploitation et, selon les éléments probants obtenus, quant à l’existence\nou non d’une incertitude significative liée à des événements ou situations susceptibles de jeter un\ndoute important sur la capacité de la société à poursuivre son exploitation. Si nous concluons à\nl’existence d’une incertitude significative, nous sommes tenus d’attirer l’attention des lecteurs de\nnotre rapport sur les informations fournies dans les états de synthèse au sujet de cette incertitude\nou, si ces informations ne sont pas adéquates, d’exprimer une opinion modifiée. Nos conclusions\ns’appuient sur les éléments probants obtenus jusqu’à la date de notre rapport. Des événements ou\nsituations futurs pourraient par ailleurs amener la société à cesser son exploitation ;\n nous évaluons la présentation d’ensemble, la structure et le contenu des états de synthèse, y\ncompris les informations fournies dans l’ETIC, et apprécions si les états de synthèse représentent\nles opérations et événements sous-jacents d’une manière propre à donner une image fidèle\nNous communiquons aux responsables de la gouvernance notamment l’étendue et le calendrier prévus\ndes travaux d’audit et nos constatations importantes, y compris toute déficience importante du contrôle\ninterne que nous aurions relevée au cours de notre audit.\nVérifications et informations spécifiques\nNous avons procédé également aux vérifications spécifiques prévues par la loi et nous nous sommes\nassurés notamment de la sincérité et de la concordance, des informations données dans le rapport de\ngestion du Conseil d'administration destiné aux actionnaires avec les états de synthèse de la société.\nCasablanca, le 9 avril 2024\nLes Commissaires aux Comptes\nERNST & YOUNG FIDAROC GRANT THORNTON\nAbdeslam BERRADA ALLAM Faïçal MEKOUAR\nAssocié Associé\n3\nLes Eaux Minérales d’Oulmès S.A. au capital de 198.000.000 DHS\nZ.I. Bouskoura 20180 - Casablanca\nwww.leseauxmineralesdoulmes.ma"
            }
        ],
        [],
        []
    ]
}