{
    "text": "COMMUNIQUÉ FINANCIER\nRÉSULTATS ANNUELS 2023\nMISE A DISPOSITION DU RAPPORT FINANCIER ANNUEL 2023\nSALAFIN annonce avoir mis à disposition du public et déposé auprès de l’Autorité Marocaine des Marchés Financiers (AMMC) son rapport financier annuel\nau 31 décembre 2023.\nLe rapport financier annuel peut être consulté sur le site Internet de la société à l’adresse : https://www.salafin.com/corporate, dans la rubrique\n«Communication financière – Rapports d’activité».\n-0,8%\nPRODUIT NET BANCAIRE STABLE\n-5,9%\nUN NIVEAU DE RISQUE EN AMÉLIORATION DE\n90,6 +5,6%\nRÉSULTAT BÉNÉFICIAIRE DE MDH EN HAUSSE DE\n16,4%\nUN NIVEAU DE RATIO DE SOLVABILITÉ ÉLEVÉ DE\nLe Directoire de SALAFIN s’est réuni le 21 février 2024 sous la présidence de Monsieur Aziz CHERKAOUI, en vue d’examiner l’activité de la Société\nau titre de l’exercice 2023 et d’arrêter les comptes dudit exercice.\nRéalisations commerciales\nL’année 2023 s’est caractérisée par la mise en œuvre d’une nouvelle feuille de route commerciale qui introduit de nombreux changements profonds, parmi\nlesquels une réorganisation de la force de vente, la réorientation de sa stratégie d’animation, l’instauration de nouvelles méthodes de travail et le pilotage\nde la tarification. Ainsi, SALAFIN se donne les moyens de poser les fondations qui lui permettront d’atteindre ses objectifs de développement.\nDans ce contexte, la production nette de SALAFIN pour l’année 2023 a atteint 985 MDH, en retrait de -24,7% par rapport à l’exercice précédent, tirée par\nla baisse du segment des prêts personnels de -23,2% à 533 MDH et celle du segment des prêts automobiles de -26,4% à 452 MDH. Toutefois, parmi les\npremiers effets positifs de la nouvelle stratégie commerciale, cette production a été réalisée avec de meilleurs rendements.\nProduit Net Bancaire et Résultats\nAu 31/12/2023, Le Produit Net Bancaire ressort à 396 MDH, soit un niveau stable par rapport à l’année dernière, affichant ainsi une bonne résilience au\nregard de la baisse des encours fin de période qui présentent un solde de 3053 MDH (-7,7%). Dans le détail, la marge d’intérêt et les résultats de\nl’activité Location avec Option d’Achat (LOA) affichent des baisses respectives de -3,0% à 183 MDH et de -3,9% à 68 MDH. La marge sur commissions\npour sa part progresse de +3,7% à 136 MDH.\nLes charges générales d’exploitation s’établissent à 148 MDH en baisse de -3,6% par rapport à l’année dernière.\nLes dotations nettes aux provisions (pour créances en souffrances) enregistrent une amélioration de -5,9% par rapport à 2022 à 95 MDH.\nLe résultat avant impôt s’établit à 149 MDH en hausse de +7,0% versus 2022.\nEn définitive, le résultat net ressort à 90,6 MDH, en progression de +5,6% par rapport à l’exercice précédent, grâce à la maitrise des coûts et à la baisse\ndu risque.\nProposition de dividende au titre de l’exercice 2023\nLe Directoire propose à l’Assemblée Générale Ordinaire de distribuer un dividende total par action de 28,5 dirhams.\nPost distribution, le ratio de solvabilité 2023 s’établit à 16,4%, soit un niveau supérieur au minimum réglementaire de 12% et le ROE 2023 atteint 16,9%.\nÉléments financiers (MDH)\nTotal Bilan Encours financiers fin de période Production nette\n1 309\n4 206 3 308\n-7,1%\n694 985\n3 905 3 053\n-7,7% -24,7%\nCrédits\n533\nPersonnels\n614\nFinancemts\n452\nAutomobiles\n2022 2023 2022 2023 2022 2023\nLe total bilan s’établit à 3 905 MDH, en baisse Les encours financiers fin de période enregistrent un La production nette s’élève à 985 MDH en recul\nde -7,1% par rapport à l’exercice 2022. solde de 3 053 MDH, en retrait de -7,7% par rapport à 2022. de -24,7% versus 2022.\nProduit Net Bancaire Dotations nettes aux provisions Résultat net\n-0,8%\n399 396 -5,9% +5,6% 91\n101 86\n95\n2022 2023 Déc. 22 Déc. 23 2022 2023\nLe Produit Net Bancaire affiche un niveau stable par Les DAP nettes totales enregistrent un solde de 95 MDH, Le Résultat Net ressort à 91 MDH, en hausse de +5,6%.\nrapport à 2022 et s’établit à 396 MDH. en amélioration de -5,9% par rapport à 2022.\nCommunication financière\nSituation au 31 décembre 2023\nBILAN ACTIF BILAN PASSIF\nen milliers de DH en milliers de DH\nACTIF 31/12/2023 31/12/2022 PASSIF 31/12/2023 31/12/2022\nValeurs en caisse, Banques centrales, Trésor public, Service 77 80 Banques centrales, Trésor public, Service des chèques postaux 0 0\ndes chèques postaux\nDettes envers les établissements de crédit et assimilés 456 849 414 102\nCréances sur les établissements de crédit et assimilés 0 0 . A vue 156 339 113 592\n. A vue 0 0 . A terme 300 510 300 510\n. A terme 0 0\nDépôts de la clientèle 149 718 227 922\nCréances sur la clientèle 2 290 160 2 399 674 . Comptes à vue créditeurs 0 0\n. Crédits de trésorerie et à la consommation 2 124 371 2 197 340 . Comptes d'épargne 0 0\n. Crédits à l'équipement 0 0 . Dépôts à terme 0 0\n. Crédits immobiliers 0 0 . Autres comptes créditeurs 149 718 227 922\n. Autres crédits 165 789 202 334 Titres de créance émis 1 498 178 1 744 207\n. Titres de créance négociables 1 498 178 1 744 207\nCréances acquises par affacturage 0 0 . Emprunts obligataires 0 0\n. Autres titres de créance émis 0 0\nTitres de transaction et de placement 861 861\n. Bons du Trésor et valeurs assimilées 0 0 Autres passifs 879 832 904 415\n. Autres titres de créance 0 0\n. Titres de propriété 861 861 Provisions pour risques et charges 36 437 36 437\nProvisions réglementées 21 549 22 242\nAutres actifs 225 305 196 555\nSubventions, fonds publics affectés et fonds spéciaux de garantie 0 0\nTitres d'investissement 0 0\n. Bons du Trésor et valeurs assimilées 0 0 Dettes subordonnées 0 0\n. Autres titres de créance 0 0\nEcarts de réévaluation 0 0\nTitres de participation et emplois assimilés 401 401\nRéserves et primes liées au capital 459 779 458 380\nCréances subordonnées 0 0 Capital 312 412 312 412\nImmobilisations données en crédit-bail et en location 1 059 110 1 272 436 Actionnaires. Capital non versé (-) 0 0\nImmobilisations incorporelles 250 981 253 684 Report à nouveau (+/-) 0 0\nImmobilisations corporelles 78 436 82 177 Résultats nets en instance d'affectation (+/-) 0 0\nRésultat net de l'exercice (+/-) 90 577 85 750\nTotal de l'Actif 3 905 331 4 205 867 Total du Passif 3 905 331 4 205 867\nHORS BILAN ETAT DES SOLDES DE GESTION\nen milliers de DH\nI - TABLEAU DE FORMATION DES RESULTATS en milliers de DH\nHORS BILAN 31/12/2023 31/12/2022\nENGAGEMENTS DONNES 32 334 38 733 31/12/2023 31/12/2022\n+ Intérêts et produits assimilés 250 717 257 624\nEngagements de financement donnés en faveur d'établissements de crédit - Intérêts et charges assimilées 67 247 68 511\net assimilés\nEngagements de financement donnés en faveur de la clientèle 32 334 38 733 MARGE D'INTERET 183 470 189 113\nEngagements de garantie d'ordre d'établissements de crédit et assimilés\nEngagements de garantie d'ordre de la clientèle + Produits sur immobilisations en crédit-bail et en location 465 509 470 020\nTitres achetés à réméré - Charges sur immobilisations en crédit-bail et en location 397 773 399 500\nAutres titres à livrer\nRésultat des opérations de crédit-bail et de location 67 736 70 519\nENGAGEMENTS RECUS 1 218 307 1 260 014\nEngagements de financement reçus d'établissements de crédit et assimilés 1 218 307 1 260 014 + Commissions perçues 146 028 141 310\nEngagements de garantie reçus d'établissements de crédit et assimilés - Commissions servies 9 911 10 049\nEngagements de garantie reçus de l'Etat et d'organismes de garantie divers\nTitres vendus à réméré Marge sur commissions 136 118 131 261\nAutres titres à recevoir\n+ Résultat des opérations sur titres de transaction 0 0\n+ Résultat des opérations sur titres de placement 2 718 2 589\nCOMPTE DE PRODUITS ET CHARGES + Résultat des opérations de change 0 0\n+ Résultat des opérations sur produits dérivés 0 0\nen milliers de DH\n31/12/2023 31/12/2022 Résultat des opérations de marché 2 718 2 589\nPRODUITS D'EXPLOITATION BANCAIRE 871 238 877 491\n+ Divers autres produits bancaires 6 266 5 948\nIntérêts et produits assimilés sur opérations avec les établissements de crédit 0 0\nIntérêts et produits assimilés sur opérations avec la clientèle 250 717 257 624 - Diverses autres charges bancaires 138 138\nIntérêts et produits assimilés sur titres de créance 0 0\nProduits sur titres de propriété 2 718 2 589 PRODUIT NET BANCAIRE 396 169 399 292\nProduits sur immobilisations en crédit-bail et en location 465 509 470 020\nCommissions sur prestations de service 146 028 141 310 + Résultat des opérations sur immobilisations financières 0 0\nAutres produits bancaires 6 266 5 948 + Autres produits d'exploitation non bancaire 3 322 3 403\n- Autres charges d'exploitation non bancaire 0 0\nCHARGES D'EXPLOITATION BANCAIRE 475 069 478 199 - Charges générales d'exploitation 147 898 153 403\nIntérêts et charges assimilées sur opérations avec les établissements de crédit 15 080 12 067\nIntérêts et charges assimilées sur opérations avec la clientèle 0 0 RESULTAT BRUT D'EXPLOITATION 251 593 249 293\nIntérêts et charges assimilées sur titres de créance émis 52 167 56 444\nCharges sur immobilisations en crédit-bail et en location 397 773 399 500 + Dotations nettes des reprises aux provisions pour créances -95 371 -101 321\nAutres charges bancaires 10 049 10 187 et engagements par signature en souffrance\n+ Autres dotations nettes des reprises aux provisions 693 -644\nPRODUIT NET BANCAIRE 396 169 399 292\nRESULTAT COURANT 156 915 147 329\nProduits d'exploitation non bancaire 3 322 3 403\nCharges d'exploitation non bancaire 0 0 RESULTAT NON COURANT -7 604 -7 757\n- Impôts sur les résultats 58 733 53 821\nCHARGES GENERALES D'EXPLOITATION 147 898 153 403\nRESULTAT NET DE L'EXERCICE 90 577 85 750\nCharges de personnel 67 447 70 571\nImpôts et taxes 1 170 798 II - CAPACITE D’AUTOFINANCEMENT en milliers de DH\nCharges externes 66 051 68 892 31/12/2023 31/12/2022\nAutres charges générales d'exploitation 1 249 589 + RESULTAT NET DE L'EXERCICE 90 577 85 750\nDotations aux amortissements et aux provisions des immobilisations incorporelles et corporelles 11 981 12 552\n+ Dotations aux amortissements et aux provisions des 11 981 12 552\nDOTATIONS AUX PROVISIONS ET PERTES SUR CREANCES IRRECOUVRABLES 101 966 117 095\nimmobilisations incorporelles et corporelles\nDotations aux provisions pour créances et engagements par signature en souffrance 101 878 115 269 + Dotations aux provisions pour dépréciation des 0 0\nPertes sur créances irrécouvrables 0 5 immobilisations financières\nAutres dotations aux provisions 88 1 825 + Dotations aux provisions pour risques généraux 0 0\n+ Dotations aux provisions réglementées 88 1 825\nREPRISES DE PROVISIONS ET RECUPERATIONS SUR CREANCES AMORTIES 7 287 15 131 + Dotations non courantes 0 0\n- Reprises de provisions 780 1 182\nReprises de provisions pour créances et engagements par signature en souffrance 1 141 8 742\n- Plus-values de cession sur immobilisations 0 0\nRécupérations sur créances amorties 5 365 5 207\nAutres reprises de provisions 780 1 182 incorporelles et corporelles\n+ Moins-values de cession sur immobilisations 0 0\nRESULTAT COURANT 156 915 147 329 incorporelles et corporelles\n- Plus-values de cession sur immobilisations financières 0 0\nProduits non courants 428 1 708 + Moins-values de cession sur immobilisations financières 0 0\nCharges non courantes 8 032 9 466 - Reprises de subventions d'investissement reçues 0 0\n+ CAPACITE D'AUTOFINANCEMENT 101 866 98 946\nRESULTAT AVANT IMPOTS SUR LES RESULTATS 149 310 139 571\nImpôts sur les résultats 58 733 53 821 - Bénéfices distribués 84 351 162 454\nRESULTAT NET DE L'EXERCICE 90 577 85 750 + AUTOFINANCEMENT 17 514 -63 508\nCommunication financière\nSituation au 31 décembre 2023\nTABLEAU DES FLUX DE TRESORERIE PROVISIONS\nen milliers de DH en milliers de DH\n31/12/2023 31/12/2022 PROVISIONS Encours Dotations Reprises Autres Encours\n31/12/2022 variations 31/12/2023\nPROVISIONS, DEDUITES DE L'ACTIF, SUR: 994 629 101 878 1 141 1 095 365\nProduits d'exploitation bancaire perçus 871 238 877 491\nRécupérations sur créances amorties 5 365 5 207 créances sur les établissements de crédit et assimilés\nProduits d'exploitation non bancaire perçus 3 322 3 403 créances sur la clientèle 779 278 85 222 889 863 610\nCharges d'exploitation bancaire versées 77 296 78 698 titres de placement\nCharges d'exploitation non bancaire versées titres de participation et emplois assimilés\nimmobilisations en crédit-bail et en location 215 351 16 656 252 231 755\nCharges générales d'exploitation versées 135 917 140 851\nautres actifs\nImpôts sur les résultats versés 58 733 53 821\nPROVISIONS INSCRITES AU PASSIF 58 679 88 780 57 986\nFlux de trésorerie nets provenant du compte de produits et charges 607 980 612 731\nVariation de : Provisions pour risques d'exécution d'engagements par\nsignature\nCréances sur les établissements de crédit et assimilés\nProvisions pour risques de change\nCréances sur la clientèle 109 514 15 096\nProvisions pour risques généraux\nTitres de transaction et de placement\nProvisions pour pensions de retraite et obligations\nAutres actifs -28 751 830\nsimilaires\nImmobilisations données en crédit-bail et en location -295 506 -506 282 Provisions pour autres risques et charges 36 437 36 437\nDettes envers les établissements de crédit et assimilés 300 510 Provisions réglementées 22 242 88 780 21 549\nDépôts de la clientèle -78 204 -135 755\nTitres de créance émis -246 030 -169 393 TOTAL GENERAL 1 053 308 101 965 1 922 1 153 351\nAutres passifs -24 583 101 074\nVENTILATION DES EMPLOIS ET DES RESSOURCES SUIVANT LA DUREE RESIDUELLE\nen milliers de DH\nSolde des variations des actifs et passifs d'exploitation -563 559 -393 920 1 mois<D< 3\nD< 1 mois 3 mois<D< 1 an 1 an <D< 5 ans D> 5 ans TOTAL\nmois\nFLUX DE TRESORERIE NETS PROVENANT DES ACTIVITES 44 420 218 811\nACTIF\nD'EXPLOITATION\nCréances sur les établissements de crédit et assimilés\nProduit des cessions d'immobilisations financières\nCréances sur la clientèle 377 7 971 91 184 1 529 461 661 167 2 290 160\nProduit des cessions d'immobilisations incorporelles et corporelles\nTitres de créance\nAcquisition d'immobilisations financières Créances subordonnées\nAcquisition d'immobilisations incorporelles et corporelles 5 537 8 434 Crédit-bail et assimilé 268 4 099 52 600 973 420 28 723 1 059 110\nIntérêts perçus TOTAL 645 12 070 143 783 2 502 881 689 890 3 349 270\nDividendes perçus -2 718 -2 589\nFLUX DE TRESORERIE NETS PROVENANT DES ACTIVITES -2 819 -5 845 PASSIF\nD'INVESTISSEMENT Dettes envers les établissements de crédit et assimilés 156 339 300 510 456 849\nDettes envers la clientèle (*) 25 521 5 961 99 988 43 223 149 718\nSubventions, fonds publics et fonds spéciaux de garantie reçus Titres de créance émis 162 178 100 000 776 000 460 000 1 498 178\nEmission de dettes subordonnées Emprunts subordonnés\nEmission d'actions\nRemboursement des capitaux propres et assimilés TOTAL 318 542 100 521 781 961 860 498 43 223 2 104 745\nCommentaires\nIntérêts versés (*) Relatif aux opérations de LOA\nDividendes versés 84 351 162 454\nCREANCES SUR LA CLIENTELE\nen milliers de DH\nFLUX DE TRESORERIE NETS PROVENANT DES ACTIVITES DE -84 351 -162 454\nSecteur privé\nFINANCEMENT CREANCES S pe uc bte liu cr Entreprises Entr ne op nri ses Autre 31/ 1To 2/t 2a 0l 23 31/ 1To 2/t 2a 0l 22\nVARIATION NETTE DE LA TRESORERIE -42 750 50 512 financières financières clientèle\nCREDITS DE TRESORERIE\nTRESORERIE A L'OUVERTURE DE L'EXERCICE -113 512 -164 024\n- Comptes à vue débiteurs\n- Créances commerciales sur le Maroc\nTRESORERIE A LA CLOTURE DE L'EXERCICE -156 262 -113 512\n- Crédits à l'exportation\n- Autres crédits de trésorerie\nTITRES DE PARTICIPATION ET EMPLOIS ASSIMILES (*)\nen milliers de DH CREDITS A LA CONSOMMATION 2 124 371 2 124 371 2 197 340\nDénomination de la société Secteur d'activité Capital Participation Prix Valeur Extrait des d se or cn ii ée tr és é é mta et ts t td re i cs eynthèse de la inP sr co rd itu si t as u CREDITS A L'EQUIPEMENT\nau capital d'acquisition comptable CREDITS IMMOBILIERS\némettrice social en % global nette Date de clôture de Situation Résultat CPC de\nl'exercice nette net l'exercice AUTRES CREDITS\nParticipations dans les CREANCES ACQUISES PAR AFFACTURAGE\nentreprises liées\nINTERETS COURUS A RECEVOIR\nCREANCES EN SOUFFRANCE 165 789 165 789 202 334\n- Créances pré-douteuses 43 034 43 034 63 637\nAutres titres de participation 400 401 401 2 879\n- Créances douteuses 1 678 1 678 5 131\nDivers Ste. de Crédit à la Crédit à la 0 NS 1 1 31/12/2023 - Créances compromises 121 076 121 076 133 566\nconsommation consommation\nORUS Services SA Informatique 300 100% 300 300 31/12/2023 6727 2879 13366\nORUS ASSURANCE SA Assurance 100 100% 100 100 31/12/2023\nTOTAL 2 290 160 2 290 160 2 399 674\nTOTAL 401 401 2 879\nCommentaires Commentaires\n(*)situation provisoire au 31/12/2022 CREANCES EN SOUFFRANCE NETTES des Agios et des Provisions\nCommunication financière\nSituation au 31 décembre 2023\nIMMOBILISATIONS DONNEES EN CREDIT-BAIL, EN LOCATION AVEC OPTION D’ACHAT ET EN LOCATION SIMPLE\nen milliers de DH\nMontant des Amortissements Provisions\nMontant des\nMontant brut au cessions ou Montant brut à la Montant net à la\nNature acquisitions au\ndébut de l'exercice retraits au cours fin de l'exercice fin de l'exercice\ncours de l'exercice Dotations au titre de Cumul des Dotations au titre Reprises de Cumul des\nde l'exercice\nl'exercice amortissements de l'exercice provisions provisions\nIMMOBILISATIONS DONNEES EN CREDIT-BAIL ET 10 872 648 341 823 195 480 11 018 992 397 773 9 728 128 16 656 231 755 1 059 110\nEN LOCATION AVEC OPTION D'ACHAT\nCREDIT-BAIL SUR IMMOBILISATIONS INCORPORELLES\nCREDIT-BAIL MOBILIER 10 250 501 294 553 195 480 10 349 575 397 773 9 728 128 621 447\n- Crédit-bail mobilier en cours\n- Crédit-bail mobilier loué 10 250 501 294 553 195 480 10 349 575 397 773 9 728 128 621 447\n- Crédit-bail mobilier non loué après résiliation\nCREDIT-BAIL IMMOBILIER\n- Crédit-bail immobilier en cours\n- Crédit-bail immobilier loué\n- Crédit-bail immobilier non loué après résiliation\nLOYERS COURUS A RECEVOIR 42 611 7 627 50 238 50 238\nLOYERS RESTRUCTURES\nLOYERS IMPAYES 233 619 18 334 251 953 251 953\nCREANCES EN SOUFFRANCE 345 916 21 310 367 226 16 656 231 755 135 471\nIMMOBILISATIONS DONNEES EN LOCATION SIMPLE\nBIENS MOBILIERS EN LOCATION SIMPLE\nBIENS IMMOBILIERS EN LOCATION SIMPLE\nLOYERS COURUS A RECEVOIR\nLOYERS RESTRUCTURES\nLOYERS IMPAYES\nLOYERS EN SOUFFRANCE\nTotal 10 872 648 341 823 195 480 11 018 992 397 773 9 728 128 16 656 231 755 1 059 110\nDETTES ENVERS LES ETABLISSEMENTS DE CREDIT ET ASSIMILES PRINCPALES METHODES D’EVALUATION APPLIQUEES\nen milliers de DH\nINDICATION DES METHODES D'EVALUATION APPLIQUEES PAR L'ETABLISSEMENT\nDETTES Etablissements de crédit et assimilés au Maroc\nAutres Etablissements de Total Total\nBank Al-Maghrib, établissements crédit à l’étranger 31/12/2023 31/12/2022\nTrésor Public et Banques au Les méthodes d'évaluation appliquées par SALAFIN sont celles requises par le Plan Comptable des Etablissements de Crédit (PCEC)\nde crédit et\nService des Chèques Maroc\nassimilés au\nPostaux\nMaroc\nCOMPTES ORDINAIRES CREDITEURS 156 339 156 339 113 592 ETAT DES DEROGATIONS\nVALEURS DONNEES EN PENSION\n- au jour le jour INFLUENCE DES DEROGATIONS SUR LE\n- à terme\nINDICATIONS DES DEROGATIONS JUSTIFICATIONS DES DEROGATIONS PATRIMOINE, LA SITUATION FINANCIERE ET\nEMPRUNTS DE TRESORERIE LES RESULTATS\n- au jour le jour\n- à terme\nI. Dérogations aux principes\nEMPRUNTS FINANCIERS 300 510 300 510 300 510 comptables fondamentaux A N T\nE\nAUTRES DETTES N\nINTERETS COURUS A PAYER\nTotal 456 849 456 849 414 102\nT\nOPERATIONS DE CHANGE A TERME ET ENGAGEMENTS SUR PRODUITS DÉRIVÉS II. Dérogations aux méthodes E A N\nd'évaluation N\nen milliers de DH\nOpérations de couverture Autres opérations\n31/12/2023 31/12/2022 31/12/2023 31/12/2022 III. Dérogations aux règles N T\nOpérations de change à terme d'établissement et de E A\nDevises à recevoir présentation des états de synthèse N\nDevises à livrer\nDirhams à recevoir T\nDirhams à livrer N\nA ETAT DES CHANGEMENTS DE METHODES\nDont swaps financiers de devises\nE\nEngagements sur produits dérivés N NATURE DES CHANGEMENTS JUSTIFICATIONS DES CHANGEMENTS INFLUENCE SUR LE PATRIMOINE, LA SITUATION\nEngagements sur marchés réglementés de taux d'intérêt FINANCIERE ET LES RESULTATS\nEngagements sur marchés de gré à gré de taux d'intérêt\nEngagements sur marchés réglementés de cours de change I. Changements affectant les T\nEngagements sur marchés de gré à gré de cours de change méthodes d'évaluation N\nEngagements sur marchés réglementés d'autres instruments A\nEngagements sur marchés de gré à gré d'autres instruments N E\nVALEURS ET SURETES RECUES ET DONNEES EN GARANTIE\nII. Changements affectant les règles T\nN\nValeurs et sûretés reçues en garantie Valeur comptable nette R eu neb gnr ai r gq e eu g me iss et rd nae tn s l t' p a l aec rt s i sf c i ro géu na and tcu ue rh s e o o dr us o lb nei nsla én s M peo atn r d t sea igsn c net os an u td g vue a ers g e r tec d sr m é oa e nn n nc t ése s s de présentation N E A\nBons duTrésor et valeurs assimilées\nAutres titres\nHypothèques 406 048 Créances sur la clientèle (Bilan) 99 835\nAutres valeurs et sûretés réelles\nLE TABLEAU DE CONCENTRATION DES RISQUES SUR UN MÊME BÉNÉFICIAIRE\nTOTAL 406 048 99 835\nRubriques du passif ou du hors Montants des dettes ou NOMBRE DE BENEFICIAIRES TOTAL ENGAGEMENT\nValeurs et sûretés données en garantie Valeur comptable nette bilan enregistrant les dettes ou les des engagements par\nengagements par signature reçus signature reçus couverts T\nN\nBons du Trésor et valeurs assimilées N T A\nA Hu yptr oe ts h t èit qre us e s N E A N E\nAutres valeurs et sûretés réelles\nTOTAL\nCCCooommmmmmuuunnniiicccaaatttiiiooonnn fififinnnaaannnccciiièèèrrreee\nSituation au 31 décembre 2023\nVALEURS DES TITRES DE TRANSACTION ET DE PLACEMENT ET DES TITRES D’INVESTISSEMENT PASSAGE DU RESULTAT NET COMPTABLE AU RESULTAT NET FISCAL\nen milliers de DH en milliers de DH\nValeur comptable Valeur de Plus-values Moins-values INTITULES MONTANTS MONTANTS\nValeur actuelle Provisions\nbrute remboursement latentes latentes\nI - RESULTAT NET COMPTABLE\nTITRES DE TRANSACTION . Bénéfice net 90 577\nBONS DU TRESOR ET VALEURS ASSIMILEES 0 0 0 . Perte nette\nOBLIGATIONS 0 0\nII - REINTEGRATIONS FISCALES 67 724\nAUTRES TITRES DE CREANCE 0 0 0 1- Courantes 8 991\nTITRES DE PROPRIETE 3 3 0 * Fraction non déductible des redevances de CB 296\nTITRES DE PLACEMENT * Provision pour Risque & charges 0\nBONS DU TRESOR ET VALEURS ASSIMILEES 0 0 0 * Autres élèments non déductibles CSS 7 273\n* Autres élèments non déductibles Plus Value de Fusion 1 422\nOBLIGATIONS 0 0\nAUTRES TITRES DE CREANCE 0 0 0 2- Non courantes 58 733\nTITRES DE PROPRIETE 1 995 858 1 137 * Impôt sur les sociétés 58 733\nTITRES D'INVESTISSEMENT * Rappel d’impôt 0\nBONS DU TRESOR ET VALEURS ASSIMILEES\nOBLIGATIONS\nIII - DEDUCTIONS FISCALES 2 718\nAUTRES TITRES DE CREANCE 1- Courantes 0\n* Reprise de la provision pour investissements 0\n* Reprise de la provision pour risques généraux 0\nDÉTAIL DES AUTRES ACTIFS * Provisions pour investissements\n* Encaissements et reprises sur provisions redressées lors du contrôle fiscal 0\nen milliers de DH\n2- Non courantes 2 718\nEléments 31/12/2023 31/12/2022\n* Produit des titres de participations 2 718\nDEBITEURS DIVERS 152 963 119 716\nEtat débiteur 31 864 34 307\nTOTAL 158 302 2 718\nDébiteurs Divers 121 098 85 409 IV - RESULTAT BRUT FISCAL\nCompte de régul Actif 72 342 76 839 . Bénéfice brut si T1 > T2 (A) 155 584\n. Déficit brut fiscal si T2 > T1 (B) …………………\nTotal 225 305 196 555\nV - REPORTS DEFICITAIRES IMPUTES (C) (1) 0\nDÉTAIL DES AUTRES PASSIFS . Exercice n-4 ……………….\n. Exercice n-3 ……………….\nen milliers de DH\n. Exercice n-2 ………………\nEléments 31/12/2023 31/12/2022 . Exercice n-1 ………………\nCréditeurs Divers 554 372 534 231\nVI - RESULTAT NET FISCAL\nEtat créditeurs 272 960 254 678 . Bénéfice net fiscal ( A - C) 155 584\nAutres créditeurs 281 412 279 553 OU\n. Déficit net fiscal (B) ………………\nCompte de régul Passif 325 460 370 185 VII - CUMUL DES AMORTISSEMENTS FISCALEMENT DIFFERES …………….\nAutres Passif 879 832 904 415 VIII - CUMUL DES DEFICITS FISCAUX RESTANT A REPORTER …………………\n. Exercice n-4 ……………….\n. Exercice n-3 ……………….\nLE TABLEAU DES ENGAGEMENTS SUR TITRES . Exercice n-2 ……………\n. Exercice n-1 ……………\nRUBRIQUE MONTANT COMMENTAIRE\n(1) Dans la limite du montant du bénéfice brut fiscal (A)\nENGAGEMENTS DONNES\nTitres achetés à réméré RESULTATS ET AUTRES ELEMENTS DES TROIS DERNIERS EXERCICES\nTitres à livrer\n- Marché primaire en milliers de DH\n- Marché gris 2023 2022 2021\n- Marchés réglementés\nT\n- Marché gré à gré N CAPITAUX PROPRES ET ASSIMILES 862 768 856 541 933 245\n- Autres A\nE\nENGAGEMENTS RECUS N OPERATIONS ET RESULTATS DE L'EXERCICE\nTitres vendus à réméré 1- Produit net bancaire 396 169 399 292 389 127\nTitres à recevoir 2- Résultat avant impôts 149 310 139 571 136 953\n- Marché primaire 3- Impôts sur les résultats 58 733 53 821 52 225\n- Marché gris\n4- Bénéfices distribués 84 351 162 454 162 294\n- Marchés réglementés\n5- Résultats non distribués ( mis en réserve ou 90 577 85 750 84 728\n- Marché gré à gré\nen instance d'affectation)\n- Autres\nRESULTAT PAR TITRE (en dirhams)\nLA VENTILATION DU TOTAL DE L’ACTIF, DU PASSIF ET DE L’HORS BILAN EN MONNAIE ÉTRANGÈRE Résultat net par action ou part sociale 29 27 27\nBénéfice distribué par action ou part sociale 27 52 52\nDESIGNATION MONTANT\nACTIF : PERSONNEL\nValeurs en caisse,Banques centrales,Trésor public, Service des chéques postaux Montants des rémunérations brutes de l'exercice 54 673 57 038 53 700\nCréances sur les établissements de crédit et assimilés Effectif moyen des salariés employés pendant l'exercice 320 338 330\nCréances sur la clientéle\nT\nAutres actifs\nTitres de participation et emplois assimilées\nN\nCréances subordonnées REPARTITION DU CAPITAL SOCIAL\nA\nTOTAL ACTIF Montant du capital: 312 411 900,00\nMontant du capital social souscrit et non appelé :\nPASSIF: E Valeur nominale des titres : 1 00,00 Dhs\nDettes envers les établissements de crédit et assimilés\nDépôts de la clientèle N Nom des pr oin uc aip ssa ou cx ié a sc tionnaires Adresse Nombre de titres détenus Pa dr ét td eu n uca ep %ital\nAutres passifs Exercice précédent Exercice actuel\nTOTAL PASSIF BMCE BANK 140, avenues hassan II. Casa, 1 935 692 1 935 692 61,96%\nHORS-BILAN:\nENGAGEMENTS DONNES SAHAM Assurance 216, Boulevard Zerktouni, Casa 442 061 442 061 14,15%\nENGAGEMENTS RECUS\nAutres 746 366 746 366 23,89%\nAFFECTATION DES RESULTATS INTERVENUE AU COURS DE L’EXERCICE\nen milliers de DH\nMontants Montants\nTITRES ET AUTRES ACTIFS GERES OU EN DEPOTS\nA- Origine des résultats affectés 85 750B- Affectation des résultats 85 750\nTITRES Nombre de comptes Montants en milliers de DH\nDécision de l'AGO du 09/05/2023\n31/12/2023 31/12/2022 31/12/2023 31/12/2022\nRéserve légale 0\nTitres dont l'établissement est dépositaire\nReport à nouveau Dividendes 84 351 T\nRésultats nets en instance d'affectation Autres affectations 1 399 Titres gérés en vertu d'un mandat de gestion N\nRésultat net de l'exercice 85 750 Titres d'OPCVM dont l'établissement est dépositaire A\nTitres d'OPCVM gérés en vertu d'un mandat de gestion E\nPrélèvement sur les bénéfices Autres actifs dont l'établissement est dépositaire N\nAutres prélèvements 0\nAutres actifs gérés en vertu d'un mandat de gestion\nTOTAL A 85 750 TOTAL B 85 750\nCCoommmmuunniiccaattiioonn fifinnaanncciièèrree\nSituation au 31 décembre 2023\nEFFECTIFS RESEAU\n(en nombre)\nRESEAU 31/12/2023 31/12/2022\nEFFECTIFS 31/12/2021 31/12/2022\nEffectifs rémunérés 320 338 Guichets permanents 23 23\nEffectifs utilisés 320 338 Guichets périodiques\nEffectifs équivalents plein temps 320 338 Guichets automatiques de banque\nEffectifs administratifs et techniques (équivalent plein temps) 203 221 Succursales et agences à l'étranger\nEffectifs affectés à des tâches bancaires (équivalent plein temps) 117 117\nBureaux de représentation à l'étranger\nCadres (équivalent plein temps) 330 338\nEmployés (équivalent plein temps) 0 0\nCOMPTES DE LA CLIENTELE\ndont effectifs employés à l'étranger 0 0\nCOMPTES DE LA CLIENTELE\n31/12/2023 31/12/2022\nDATATION ET EVENEMENTS POSTERIEURS\nComptes courants\nI. DATATION\nComptes chèques, hors MRE\nT\n. Date de clôture (1) Comptes MRE N\n31/12/2023 Comptes d'affacturage A\nE\nComptes d'épargne N\n. Date d'établissement des états de synthèse (2)\n23/02/2024 Comptes à terme\nBons de caisse\n(1) Justification en cas de changement de la date de clôture de l'exercice\n(2) Justification en cas de dépassement du délai réglementaire de trois mois prévu pour\nl'élaboration des états de synthèse.\nII. EVENEMENTS NES POSTERIEUREMENT A LA CLOTURE DE L'EXERCICE NON RATTACHABLES A CET EXERCICE ET CONNUS AVANT LA 1ERE COMMUNICATION\nEXTERNE DES ETATS DE SYNTHESE\nDates Indications des événements\n. Favorables\n-Enregistrement des règlements subséquents et encaissements sur créances en souffrances\n.Défavorables\n- Baisse continue du TEG\n- Retours d'impayées et détérioration de la situation des créances en souffrances en terme de nombre d'impayés et de classification des créances\net leurs provisions.\nATTESTATION DES COMMISSAIRES AUX COMPTES",
    "tables": [
        [
            {
                "694": "614"
            }
        ],
        [
            {
                "533": "452"
            }
        ],
        [
            {
                "Communication financière": "Situation au 31 décembre 2023\nBILAN ACTIF BILAN PASSIF\nen milliers de DH en milliers de DH\nACTIF 31/12/2023 31/12/2022 PASSIF 31/12/2023 31/12/2022\nValeurs en caisse, Banques centrales, Trésor public, Service 77 80 Banques centrales, Trésor public, Service des chèques postaux 0 0\ndes chèques postaux\nDettes envers les établissements de crédit et assimilés 456 849 414 102\nCréances sur les établissements de crédit et assimilés 0 0 . A vue 156 339 113 592\n. A vue 0 0 . A terme 300 510 300 510\n. A terme 0 0\nDépôts de la clientèle 149 718 227 922\nCréances sur la clientèle 2 290 160 2 399 674 . Comptes à vue créditeurs 0 0\n. Crédits de trésorerie et à la consommation 2 124 371 2 197 340 . Comptes d'épargne 0 0\n. Crédits à l'équipement 0 0 . Dépôts à terme 0 0\n. Crédits immobiliers 0 0 . Autres comptes créditeurs 149 718 227 922\n. Autres crédits 165 789 202 334 Titres de créance émis 1 498 178 1 744 207\n. Titres de créance négociables 1 498 178 1 744 207\nCréances acquises par affacturage 0 0 . Emprunts obligataires 0 0\n. Autres titres de créance émis 0 0\nTitres de transaction et de placement 861 861\n. Bons du Trésor et valeurs assimilées 0 0 Autres passifs 879 832 904 415\n. Autres titres de créance 0 0\n. Titres de propriété 861 861 Provisions pour risques et charges 36 437 36 437\nProvisions réglementées 21 549 22 242\nAutres actifs 225 305 196 555\nSubventions, fonds publics affectés et fonds spéciaux de garantie 0 0\nTitres d'investissement 0 0\n. Bons du Trésor et valeurs assimilées 0 0 Dettes subordonnées 0 0\n. Autres titres de créance 0 0\nEcarts de réévaluation 0 0\nTitres de participation et emplois assimilés 401 401\nRéserves et primes liées au capital 459 779 458 380\nCréances subordonnées 0 0 Capital 312 412 312 412\nImmobilisations données en crédit-bail et en location 1 059 110 1 272 436 Actionnaires. Capital non versé (-) 0 0\nImmobilisations incorporelles 250 981 253 684 Report à nouveau (+/-) 0 0\nImmobilisations corporelles 78 436 82 177 Résultats nets en instance d'affectation (+/-) 0 0\nRésultat net de l'exercice (+/-) 90 577 85 750\nTotal de l'Actif 3 905 331 4 205 867 Total du Passif 3 905 331 4 205 867\nHORS BILAN ETAT DES SOLDES DE GESTION\nen milliers de DH\nI - TABLEAU DE FORMATION DES RESULTATS en milliers de DH\nHORS BILAN 31/12/2023 31/12/2022\nENGAGEMENTS DONNES 32 334 38 733 31/12/2023 31/12/2022\n+ Intérêts et produits assimilés 250 717 257 624\nEngagements de financement donnés en faveur d'établissements de crédit - Intérêts et charges assimilées 67 247 68 511\net assimilés\nEngagements de financement donnés en faveur de la clientèle 32 334 38 733 MARGE D'INTERET 183 470 189 113\nEngagements de garantie d'ordre d'établissements de crédit et assimilés\nEngagements de garantie d'ordre de la clientèle + Produits sur immobilisations en crédit-bail et en location 465 509 470 020\nTitres achetés à réméré - Charges sur immobilisations en crédit-bail et en location 397 773 399 500\nAutres titres à livrer\nRésultat des opérations de crédit-bail et de location 67 736 70 519\nENGAGEMENTS RECUS 1 218 307 1 260 014\nEngagements de financement reçus d'établissements de crédit et assimilés 1 218 307 1 260 014 + Commissions perçues 146 028 141 310\nEngagements de garantie reçus d'établissements de crédit et assimilés - Commissions servies 9 911 10 049\nEngagements de garantie reçus de l'Etat et d'organismes de garantie divers\nTitres vendus à réméré Marge sur commissions 136 118 131 261\nAutres titres à recevoir\n+ Résultat des opérations sur titres de transaction 0 0\n+ Résultat des opérations sur titres de placement 2 718 2 589\nCOMPTE DE PRODUITS ET CHARGES + Résultat des opérations de change 0 0\n+ Résultat des opérations sur produits dérivés 0 0\nen milliers de DH\n31/12/2023 31/12/2022 Résultat des opérations de marché 2 718 2 589\nPRODUITS D'EXPLOITATION BANCAIRE 871 238 877 491\n+ Divers autres produits bancaires 6 266 5 948\nIntérêts et produits assimilés sur opérations avec les établissements de crédit 0 0\nIntérêts et produits assimilés sur opérations avec la clientèle 250 717 257 624 - Diverses autres charges bancaires 138 138\nIntérêts et produits assimilés sur titres de créance 0 0\nProduits sur titres de propriété 2 718 2 589 PRODUIT NET BANCAIRE 396 169 399 292\nProduits sur immobilisations en crédit-bail et en location 465 509 470 020\nCommissions sur prestations de service 146 028 141 310 + Résultat des opérations sur immobilisations financières 0 0\nAutres produits bancaires 6 266 5 948 + Autres produits d'exploitation non bancaire 3 322 3 403\n- Autres charges d'exploitation non bancaire 0 0\nCHARGES D'EXPLOITATION BANCAIRE 475 069 478 199 - Charges générales d'exploitation 147 898 153 403\nIntérêts et charges assimilées sur opérations avec les établissements de crédit 15 080 12 067\nIntérêts et charges assimilées sur opérations avec la clientèle 0 0 RESULTAT BRUT D'EXPLOITATION 251 593 249 293\nIntérêts et charges assimilées sur titres de créance émis 52 167 56 444\nCharges sur immobilisations en crédit-bail et en location 397 773 399 500 + Dotations nettes des reprises aux provisions pour créances -95 371 -101 321\nAutres charges bancaires 10 049 10 187 et engagements par signature en souffrance\n+ Autres dotations nettes des reprises aux provisions 693 -644\nPRODUIT NET BANCAIRE 396 169 399 292\nRESULTAT COURANT 156 915 147 329\nProduits d'exploitation non bancaire 3 322 3 403\nCharges d'exploitation non bancaire 0 0 RESULTAT NON COURANT -7 604 -7 757\n- Impôts sur les résultats 58 733 53 821\nCHARGES GENERALES D'EXPLOITATION 147 898 153 403\nRESULTAT NET DE L'EXERCICE 90 577 85 750\nCharges de personnel 67 447 70 571\nImpôts et taxes 1 170 798 II - CAPACITE D’AUTOFINANCEMENT en milliers de DH\nCharges externes 66 051 68 892 31/12/2023 31/12/2022\nAutres charges générales d'exploitation 1 249 589 + RESULTAT NET DE L'EXERCICE 90 577 85 750\nDotations aux amortissements et aux provisions des immobilisations incorporelles et corporelles 11 981 12 552\n+ Dotations aux amortissements et aux provisions des 11 981 12 552\nDOTATIONS AUX PROVISIONS ET PERTES SUR CREANCES IRRECOUVRABLES 101 966 117 095\nimmobilisations incorporelles et corporelles\nDotations aux provisions pour créances et engagements par signature en souffrance 101 878 115 269 + Dotations aux provisions pour dépréciation des 0 0\nPertes sur créances irrécouvrables 0 5 immobilisations financières\nAutres dotations aux provisions 88 1 825 + Dotations aux provisions pour risques généraux 0 0\n+ Dotations aux provisions réglementées 88 1 825\nREPRISES DE PROVISIONS ET RECUPERATIONS SUR CREANCES AMORTIES 7 287 15 131 + Dotations non courantes 0 0\n- Reprises de provisions 780 1 182\nReprises de provisions pour créances et engagements par signature en souffrance 1 141 8 742\n- Plus-values de cession sur immobilisations 0 0\nRécupérations sur créances amorties 5 365 5 207\nAutres reprises de provisions 780 1 182 incorporelles et corporelles\n+ Moins-values de cession sur immobilisations 0 0\nRESULTAT COURANT 156 915 147 329 incorporelles et corporelles\n- Plus-values de cession sur immobilisations financières 0 0\nProduits non courants 428 1 708 + Moins-values de cession sur immobilisations financières 0 0\nCharges non courantes 8 032 9 466 - Reprises de subventions d'investissement reçues 0 0\n+ CAPACITE D'AUTOFINANCEMENT 101 866 98 946\nRESULTAT AVANT IMPOTS SUR LES RESULTATS 149 310 139 571\nImpôts sur les résultats 58 733 53 821 - Bénéfices distribués 84 351 162 454\nRESULTAT NET DE L'EXERCICE 90 577 85 750 + AUTOFINANCEMENT 17 514 -63 508"
            },
            {
                "Communication financière": ""
            }
        ],
        [
            {
                "ACTIF": "Valeurs en caisse, Banques centrales, Trésor public, Service\ndes chèques postaux\nCréances sur les établissements de crédit et assimilés\n. A vue\n. A terme\nCréances sur la clientèle\n. Crédits de trésorerie et à la consommation\n. Crédits à l'équipement\n. Crédits immobiliers\n. Autres crédits\nCréances acquises par affacturage\nTitres de transaction et de placement\n. Bons du Trésor et valeurs assimilées\n. Autres titres de créance\n. Titres de propriété\nAutres actifs\nTitres d'investissement\n. Bons du Trésor et valeurs assimilées\n. Autres titres de créance\nTitres de participation et emplois assimilés\nCréances subordonnées\nImmobilisations données en crédit-bail et en location\nImmobilisations incorporelles\nImmobilisations corporelles",
                "31/12/2023": "77\n0\n0\n0\n2 290 160\n2 124 371\n0\n0\n165 789\n0\n861\n0\n0\n861\n225 305\n0\n0\n0\n401\n0\n1 059 110\n250 981\n78 436",
                "31/12/2022": "80\n0\n0\n0\n2 399 674\n2 197 340\n0\n0\n202 334\n0\n861\n0\n0\n861\n196 555\n0\n0\n0\n401\n0\n1 272 436\n253 684\n82 177"
            },
            {
                "ACTIF": "Total de l'Actif",
                "31/12/2023": "3 905 331",
                "31/12/2022": "4 205 867"
            },
            {
                "ACTIF": "HORS BILAN",
                "31/12/2023": "",
                "31/12/2022": ""
            }
        ],
        [
            {
                "PASSIF": "Banques centrales, Trésor public, Service des chèques postaux\nDettes envers les établissements de crédit et assimilés\n. A vue\n. A terme\nDépôts de la clientèle\n. Comptes à vue créditeurs\n. Comptes d'épargne\n. Dépôts à terme\n. Autres comptes créditeurs\nTitres de créance émis\n. Titres de créance négociables\n. Emprunts obligataires\n. Autres titres de créance émis\nAutres passifs\nProvisions pour risques et charges\nProvisions réglementées\nSubventions, fonds publics affectés et fonds spéciaux de garantie\nDettes subordonnées\nEcarts de réévaluation\nRéserves et primes liées au capital\nCapital\nActionnaires. Capital non versé (-)\nReport à nouveau (+/-)\nRésultats nets en instance d'affectation (+/-)\nRésultat net de l'exercice (+/-)",
                "31/12/2023": "0\n456 849\n156 339\n300 510\n149 718\n0\n0\n0\n149 718\n1 498 178\n1 498 178\n0\n0\n879 832\n36 437\n21 549\n0\n0\n0\n459 779\n312 412\n0\n0\n0\n90 577",
                "31/12/2022": "0\n414 102\n113 592\n300 510\n227 922\n0\n0\n0\n227 922\n1 744 207\n1 744 207\n0\n0\n904 415\n36 437\n22 242\n0\n0\n0\n458 380\n312 412\n0\n0\n0\n85 750"
            },
            {
                "PASSIF": "Total du Passif",
                "31/12/2023": "3 905 331",
                "31/12/2022": "4 205 867"
            }
        ],
        [
            {
                "HORS BILAN": "ENGAGEMENTS DONNES\nEngagements de financement donnés en faveur d'établissements de crédit\net assimilés\nEngagements de financement donnés en faveur de la clientèle\nEngagements de garantie d'ordre d'établissements de crédit et assimilés\nEngagements de garantie d'ordre de la clientèle\nTitres achetés à réméré\nAutres titres à livrer\nENGAGEMENTS RECUS\nEngagements de financement reçus d'établissements de crédit et assimilés\nEngagements de garantie reçus d'établissements de crédit et assimilés\nEngagements de garantie reçus de l'Etat et d'organismes de garantie divers\nTitres vendus à réméré\nAutres titres à recevoir",
                "31/12/2023": "32 334\n32 334\n1 218 307\n1 218 307",
                "31/12/2022": "38 733\n38 733\n1 260 014\n1 260 014"
            }
        ],
        [
            {
                "": "+ Intérêts et produits assimilés",
                "31/12/2023": "250 717",
                "31/12/2022": "257 624"
            },
            {
                "": "- Intérêts et charges assimilées",
                "31/12/2023": "67 247",
                "31/12/2022": "68 511"
            },
            {
                "": "",
                "31/12/2023": "",
                "31/12/2022": ""
            },
            {
                "": "MARGE D'INTERET",
                "31/12/2023": "183 470",
                "31/12/2022": "189 113"
            },
            {
                "": "",
                "31/12/2023": "",
                "31/12/2022": ""
            },
            {
                "": "+ Produits sur immobilisations en crédit-bail et en location",
                "31/12/2023": "465 509",
                "31/12/2022": "470 020"
            },
            {
                "": "- Charges sur immobilisations en crédit-bail et en location",
                "31/12/2023": "397 773",
                "31/12/2022": "399 500"
            },
            {
                "": "",
                "31/12/2023": "",
                "31/12/2022": ""
            },
            {
                "": "Résultat des opérations de crédit-bail et de location",
                "31/12/2023": "67 736",
                "31/12/2022": "70 519"
            },
            {
                "": "",
                "31/12/2023": "",
                "31/12/2022": ""
            },
            {
                "": "+ Commissions perçues",
                "31/12/2023": "146 028",
                "31/12/2022": "141 310"
            },
            {
                "": "- Commissions servies",
                "31/12/2023": "9 911",
                "31/12/2022": "10 049"
            },
            {
                "": "",
                "31/12/2023": "",
                "31/12/2022": ""
            },
            {
                "": "Marge sur commissions",
                "31/12/2023": "136 118",
                "31/12/2022": "131 261"
            },
            {
                "": "",
                "31/12/2023": "",
                "31/12/2022": ""
            },
            {
                "": "+ Résultat des opérations sur titres de transaction",
                "31/12/2023": "0",
                "31/12/2022": "0"
            },
            {
                "": "+ Résultat des opérations sur titres de placement",
                "31/12/2023": "2 718",
                "31/12/2022": "2 589"
            },
            {
                "": "+ Résultat des opérations de change",
                "31/12/2023": "0",
                "31/12/2022": "0"
            },
            {
                "": "+ Résultat des opérations sur produits dérivés",
                "31/12/2023": "0",
                "31/12/2022": "0"
            },
            {
                "": "",
                "31/12/2023": "",
                "31/12/2022": ""
            },
            {
                "": "Résultat des opérations de marché",
                "31/12/2023": "2 718",
                "31/12/2022": "2 589"
            },
            {
                "": "",
                "31/12/2023": "",
                "31/12/2022": ""
            },
            {
                "": "+ Divers autres produits bancaires",
                "31/12/2023": "6 266",
                "31/12/2022": "5 948"
            },
            {
                "": "- Diverses autres charges bancaires",
                "31/12/2023": "138",
                "31/12/2022": "138"
            },
            {
                "": "",
                "31/12/2023": "",
                "31/12/2022": ""
            },
            {
                "": "PRODUIT NET BANCAIRE",
                "31/12/2023": "396 169",
                "31/12/2022": "399 292"
            },
            {
                "": "",
                "31/12/2023": "",
                "31/12/2022": ""
            },
            {
                "": "+ Résultat des opérations sur immobilisations financières",
                "31/12/2023": "0",
                "31/12/2022": "0"
            },
            {
                "": "+ Autres produits d'exploitation non bancaire",
                "31/12/2023": "3 322",
                "31/12/2022": "3 403"
            },
            {
                "": "- Autres charges d'exploitation non bancaire",
                "31/12/2023": "0",
                "31/12/2022": "0"
            },
            {
                "": "- Charges générales d'exploitation",
                "31/12/2023": "147 898",
                "31/12/2022": "153 403"
            },
            {
                "": "",
                "31/12/2023": "",
                "31/12/2022": ""
            },
            {
                "": "RESULTAT BRUT D'EXPLOITATION",
                "31/12/2023": "251 593",
                "31/12/2022": "249 293"
            },
            {
                "": "",
                "31/12/2023": "",
                "31/12/2022": ""
            },
            {
                "": "+ Dotations nettes des reprises aux provisions pour créances",
                "31/12/2023": "-95 371",
                "31/12/2022": "-101 321"
            },
            {
                "": "et engagements par signature en souffrance",
                "31/12/2023": "",
                "31/12/2022": ""
            },
            {
                "": "+ Autres dotations nettes des reprises aux provisions",
                "31/12/2023": "693",
                "31/12/2022": "-644"
            },
            {
                "": "",
                "31/12/2023": "",
                "31/12/2022": ""
            },
            {
                "": "RESULTAT COURANT",
                "31/12/2023": "156 915",
                "31/12/2022": "147 329"
            },
            {
                "": "RESULTAT NON COURANT",
                "31/12/2023": "-7 604",
                "31/12/2022": "-7 757"
            },
            {
                "": "- Impôts sur les résultats",
                "31/12/2023": "58 733",
                "31/12/2022": "53 821"
            },
            {
                "": "",
                "31/12/2023": "",
                "31/12/2022": ""
            },
            {
                "": "RESULTAT NET DE L'EXERCICE",
                "31/12/2023": "90 577",
                "31/12/2022": "85 750"
            }
        ],
        [
            {
                "": "PRODUITS D'EXPLOITATION BANCAIRE",
                "31/12/2023": "871 238",
                "31/12/2022": "877 491"
            },
            {
                "": "Intérêts et produits assimilés sur opérations avec les établissements de crédit\nIntérêts et produits assimilés sur opérations avec la clientèle\nIntérêts et produits assimilés sur titres de créance\nProduits sur titres de propriété\nProduits sur immobilisations en crédit-bail et en location\nCommissions sur prestations de service\nAutres produits bancaires",
                "31/12/2023": "0\n250 717\n0\n2 718\n465 509\n146 028\n6 266",
                "31/12/2022": "0\n257 624\n0\n2 589\n470 020\n141 310\n5 948"
            },
            {
                "": "CHARGES D'EXPLOITATION BANCAIRE",
                "31/12/2023": "475 069",
                "31/12/2022": "478 199"
            },
            {
                "": "Intérêts et charges assimilées sur opérations avec les établissements de crédit\nIntérêts et charges assimilées sur opérations avec la clientèle\nIntérêts et charges assimilées sur titres de créance émis\nCharges sur immobilisations en crédit-bail et en location\nAutres charges bancaires",
                "31/12/2023": "15 080\n0\n52 167\n397 773\n10 049",
                "31/12/2022": "12 067\n0\n56 444\n399 500\n10 187"
            },
            {
                "": "PRODUIT NET BANCAIRE",
                "31/12/2023": "396 169",
                "31/12/2022": "399 292"
            },
            {
                "": "Produits d'exploitation non bancaire\nCharges d'exploitation non bancaire",
                "31/12/2023": "3 322\n0",
                "31/12/2022": "3 403\n0"
            },
            {
                "": "CHARGES GENERALES D'EXPLOITATION",
                "31/12/2023": "147 898",
                "31/12/2022": "153 403"
            },
            {
                "": "Charges de personnel\nImpôts et taxes\nCharges externes\nAutres charges générales d'exploitation\nDotations aux amortissements et aux provisions des immobilisations incorporelles et corporelles",
                "31/12/2023": "67 447\n1 170\n66 051\n1 249\n11 981",
                "31/12/2022": "70 571\n798\n68 892\n589\n12 552"
            },
            {
                "": "DOTATIONS AUX PROVISIONS ET PERTES SUR CREANCES IRRECOUVRABLES",
                "31/12/2023": "101 966",
                "31/12/2022": "117 095"
            },
            {
                "": "Dotations aux provisions pour créances et engagements par signature en souffrance\nPertes sur créances irrécouvrables\nAutres dotations aux provisions",
                "31/12/2023": "101 878\n0\n88",
                "31/12/2022": "115 269\n5\n1 825"
            },
            {
                "": "REPRISES DE PROVISIONS ET RECUPERATIONS SUR CREANCES AMORTIES",
                "31/12/2023": "7 287",
                "31/12/2022": "15 131"
            },
            {
                "": "Reprises de provisions pour créances et engagements par signature en souffrance\nRécupérations sur créances amorties\nAutres reprises de provisions",
                "31/12/2023": "1 141\n5 365\n780",
                "31/12/2022": "8 742\n5 207\n1 182"
            },
            {
                "": "RESULTAT COURANT",
                "31/12/2023": "156 915",
                "31/12/2022": "147 329"
            },
            {
                "": "Produits non courants\nCharges non courantes",
                "31/12/2023": "428\n8 032",
                "31/12/2022": "1 708\n9 466"
            },
            {
                "": "RESULTAT AVANT IMPOTS SUR LES RESULTATS",
                "31/12/2023": "149 310",
                "31/12/2022": "139 571"
            },
            {
                "": "Impôts sur les résultats",
                "31/12/2023": "58 733",
                "31/12/2022": "53 821"
            },
            {
                "": "RESULTAT NET DE L'EXERCICE",
                "31/12/2023": "90 577",
                "31/12/2022": "85 750"
            }
        ],
        [
            {
                "": "+ RESULTAT NET DE L'EXERCICE",
                "31/12/2023": "90 577",
                "31/12/2022": "85 750"
            },
            {
                "": "+ Dotations aux amortissements et aux provisions des\nimmobilisations incorporelles et corporelles\n+ Dotations aux provisions pour dépréciation des\nimmobilisations financières\n+ Dotations aux provisions pour risques généraux\n+ Dotations aux provisions réglementées\n+ Dotations non courantes\n- Reprises de provisions\n- Plus-values de cession sur immobilisations\nincorporelles et corporelles\n+ Moins-values de cession sur immobilisations\nincorporelles et corporelles\n- Plus-values de cession sur immobilisations financières\n+ Moins-values de cession sur immobilisations financières\n- Reprises de subventions d'investissement reçues",
                "31/12/2023": "11 981\n0\n0\n88\n0\n780\n0\n0\n0\n0\n0",
                "31/12/2022": "12 552\n0\n0\n1 825\n0\n1 182\n0\n0\n0\n0\n0"
            },
            {
                "": "+ CAPACITE D'AUTOFINANCEMENT",
                "31/12/2023": "101 866",
                "31/12/2022": "98 946"
            },
            {
                "": "- Bénéfices distribués",
                "31/12/2023": "84 351",
                "31/12/2022": "162 454"
            },
            {
                "": "+ AUTOFINANCEMENT",
                "31/12/2023": "17 514",
                "31/12/2022": "-63 508"
            }
        ],
        [
            {
                "Communication financière": "Situation au 31 décembre 2023\nTABLEAU DES FLUX DE TRESORERIE PROVISIONS\nen milliers de DH en milliers de DH\n31/12/2023 31/12/2022 PROVISIONS Encours Dotations Reprises Autres Encours\n31/12/2022 variations 31/12/2023\nPROVISIONS, DEDUITES DE L'ACTIF, SUR: 994 629 101 878 1 141 1 095 365\nProduits d'exploitation bancaire perçus 871 238 877 491\nRécupérations sur créances amorties 5 365 5 207 créances sur les établissements de crédit et assimilés\nProduits d'exploitation non bancaire perçus 3 322 3 403 créances sur la clientèle 779 278 85 222 889 863 610\nCharges d'exploitation bancaire versées 77 296 78 698 titres de placement\nCharges d'exploitation non bancaire versées titres de participation et emplois assimilés\nimmobilisations en crédit-bail et en location 215 351 16 656 252 231 755\nCharges générales d'exploitation versées 135 917 140 851\nautres actifs\nImpôts sur les résultats versés 58 733 53 821\nPROVISIONS INSCRITES AU PASSIF 58 679 88 780 57 986\nFlux de trésorerie nets provenant du compte de produits et charges 607 980 612 731\nVariation de : Provisions pour risques d'exécution d'engagements par\nsignature\nCréances sur les établissements de crédit et assimilés\nProvisions pour risques de change\nCréances sur la clientèle 109 514 15 096\nProvisions pour risques généraux\nTitres de transaction et de placement\nProvisions pour pensions de retraite et obligations\nAutres actifs -28 751 830\nsimilaires\nImmobilisations données en crédit-bail et en location -295 506 -506 282 Provisions pour autres risques et charges 36 437 36 437\nDettes envers les établissements de crédit et assimilés 300 510 Provisions réglementées 22 242 88 780 21 549\nDépôts de la clientèle -78 204 -135 755\nTitres de créance émis -246 030 -169 393 TOTAL GENERAL 1 053 308 101 965 1 922 1 153 351\nAutres passifs -24 583 101 074\nVENTILATION DES EMPLOIS ET DES RESSOURCES SUIVANT LA DUREE RESIDUELLE\nen milliers de DH\nSolde des variations des actifs et passifs d'exploitation -563 559 -393 920 1 mois<D< 3\nD< 1 mois 3 mois<D< 1 an 1 an <D< 5 ans D> 5 ans TOTAL\nmois\nFLUX DE TRESORERIE NETS PROVENANT DES ACTIVITES 44 420 218 811\nACTIF\nD'EXPLOITATION\nCréances sur les établissements de crédit et assimilés\nProduit des cessions d'immobilisations financières\nCréances sur la clientèle 377 7 971 91 184 1 529 461 661 167 2 290 160\nProduit des cessions d'immobilisations incorporelles et corporelles\nTitres de créance\nAcquisition d'immobilisations financières Créances subordonnées\nAcquisition d'immobilisations incorporelles et corporelles 5 537 8 434 Crédit-bail et assimilé 268 4 099 52 600 973 420 28 723 1 059 110\nIntérêts perçus TOTAL 645 12 070 143 783 2 502 881 689 890 3 349 270\nDividendes perçus -2 718 -2 589\nFLUX DE TRESORERIE NETS PROVENANT DES ACTIVITES -2 819 -5 845 PASSIF\nD'INVESTISSEMENT Dettes envers les établissements de crédit et assimilés 156 339 300 510 456 849\nDettes envers la clientèle (*) 25 521 5 961 99 988 43 223 149 718\nSubventions, fonds publics et fonds spéciaux de garantie reçus Titres de créance émis 162 178 100 000 776 000 460 000 1 498 178\nEmission de dettes subordonnées Emprunts subordonnés\nEmission d'actions\nRemboursement des capitaux propres et assimilés TOTAL 318 542 100 521 781 961 860 498 43 223 2 104 745\nCommentaires\nIntérêts versés (*) Relatif aux opérations de LOA\nDividendes versés 84 351 162 454\nCREANCES SUR LA CLIENTELE\nen milliers de DH\nFLUX DE TRESORERIE NETS PROVENANT DES ACTIVITES DE -84 351 -162 454\nSecteur privé\nFINANCEMENT CREANCES S pe uc bte liu cr Entreprises Entr ne op nri ses Autre 31/ 1To 2/t 2a 0l 23 31/ 1To 2/t 2a 0l 22\nVARIATION NETTE DE LA TRESORERIE -42 750 50 512 financières financières clientèle\nCREDITS DE TRESORERIE\nTRESORERIE A L'OUVERTURE DE L'EXERCICE -113 512 -164 024\n- Comptes à vue débiteurs\n- Créances commerciales sur le Maroc\nTRESORERIE A LA CLOTURE DE L'EXERCICE -156 262 -113 512\n- Crédits à l'exportation\n- Autres crédits de trésorerie\nTITRES DE PARTICIPATION ET EMPLOIS ASSIMILES (*)\nen milliers de DH CREDITS A LA CONSOMMATION 2 124 371 2 124 371 2 197 340\nDénomination de la société Secteur d'activité Capital Participation Prix Valeur Extrait des d se or cn ii ée tr és é é mta et ts t td re i cs eynthèse de la inP sr co rd itu si t as u CREDITS A L'EQUIPEMENT\nau capital d'acquisition comptable CREDITS IMMOBILIERS\némettrice social en % global nette Date de clôture de Situation Résultat CPC de\nl'exercice nette net l'exercice AUTRES CREDITS\nParticipations dans les CREANCES ACQUISES PAR AFFACTURAGE\nentreprises liées\nINTERETS COURUS A RECEVOIR\nCREANCES EN SOUFFRANCE 165 789 165 789 202 334\n- Créances pré-douteuses 43 034 43 034 63 637\nAutres titres de participation 400 401 401 2 879\n- Créances douteuses 1 678 1 678 5 131\nDivers Ste. de Crédit à la Crédit à la 0 NS 1 1 31/12/2023 - Créances compromises 121 076 121 076 133 566\nconsommation consommation\nORUS Services SA Informatique 300 100% 300 300 31/12/2023 6727 2879 13366\nORUS ASSURANCE SA Assurance 100 100% 100 100 31/12/2023\nTOTAL 2 290 160 2 290 160 2 399 674\nTOTAL 401 401 2 879\nCommentaires Commentaires\n(*)situation provisoire au 31/12/2022 CREANCES EN SOUFFRANCE NETTES des Agios et des Provisions"
            },
            {
                "Communication financière": ""
            }
        ],
        [
            {
                "": "",
                "31/12/2023": "",
                "31/12/2022": ""
            },
            {
                "": "Produits d'exploitation bancaire perçus",
                "31/12/2023": "871 238",
                "31/12/2022": "877 491"
            },
            {
                "": "Récupérations sur créances amorties",
                "31/12/2023": "5 365",
                "31/12/2022": "5 207"
            },
            {
                "": "Produits d'exploitation non bancaire perçus",
                "31/12/2023": "3 322",
                "31/12/2022": "3 403"
            },
            {
                "": "Charges d'exploitation bancaire versées",
                "31/12/2023": "77 296",
                "31/12/2022": "78 698"
            },
            {
                "": "Charges d'exploitation non bancaire versées",
                "31/12/2023": "",
                "31/12/2022": ""
            },
            {
                "": "Charges générales d'exploitation versées",
                "31/12/2023": "135 917",
                "31/12/2022": "140 851"
            },
            {
                "": "Impôts sur les résultats versés",
                "31/12/2023": "58 733",
                "31/12/2022": "53 821"
            },
            {
                "": "",
                "31/12/2023": "",
                "31/12/2022": ""
            },
            {
                "": "Flux de trésorerie nets provenant du compte de produits et charges",
                "31/12/2023": "607 980",
                "31/12/2022": "612 731"
            },
            {
                "": "Variation de :",
                "31/12/2023": "",
                "31/12/2022": ""
            },
            {
                "": "Créances sur les établissements de crédit et assimilés",
                "31/12/2023": "",
                "31/12/2022": ""
            },
            {
                "": "Créances sur la clientèle",
                "31/12/2023": "109 514",
                "31/12/2022": "15 096"
            },
            {
                "": "Titres de transaction et de placement",
                "31/12/2023": "",
                "31/12/2022": ""
            },
            {
                "": "Autres actifs",
                "31/12/2023": "-28 751",
                "31/12/2022": "830"
            },
            {
                "": "Immobilisations données en crédit-bail et en location",
                "31/12/2023": "-295 506",
                "31/12/2022": "-506 282"
            },
            {
                "": "Dettes envers les établissements de crédit et assimilés",
                "31/12/2023": "",
                "31/12/2022": "300 510"
            },
            {
                "": "Dépôts de la clientèle",
                "31/12/2023": "-78 204",
                "31/12/2022": "-135 755"
            },
            {
                "": "Titres de créance émis",
                "31/12/2023": "-246 030",
                "31/12/2022": "-169 393"
            },
            {
                "": "Autres passifs",
                "31/12/2023": "-24 583",
                "31/12/2022": "101 074"
            },
            {
                "": "",
                "31/12/2023": "",
                "31/12/2022": ""
            },
            {
                "": "Solde des variations des actifs et passifs d'exploitation",
                "31/12/2023": "-563 559",
                "31/12/2022": "-393 920"
            },
            {
                "": "FLUX DE TRESORERIE NETS PROVENANT DES ACTIVITES",
                "31/12/2023": "44 420",
                "31/12/2022": "218 811"
            },
            {
                "": "D'EXPLOITATION",
                "31/12/2023": "",
                "31/12/2022": ""
            },
            {
                "": "Produit des cessions d'immobilisations financières",
                "31/12/2023": "",
                "31/12/2022": ""
            },
            {
                "": "Produit des cessions d'immobilisations incorporelles et corporelles",
                "31/12/2023": "",
                "31/12/2022": ""
            },
            {
                "": "Acquisition d'immobilisations financières",
                "31/12/2023": "",
                "31/12/2022": ""
            },
            {
                "": "Acquisition d'immobilisations incorporelles et corporelles",
                "31/12/2023": "5 537",
                "31/12/2022": "8 434"
            },
            {
                "": "Intérêts perçus",
                "31/12/2023": "",
                "31/12/2022": ""
            },
            {
                "": "Dividendes perçus",
                "31/12/2023": "-2 718",
                "31/12/2022": "-2 589"
            },
            {
                "": "FLUX DE TRESORERIE NETS PROVENANT DES ACTIVITES",
                "31/12/2023": "-2 819",
                "31/12/2022": "-5 845"
            },
            {
                "": "D'INVESTISSEMENT",
                "31/12/2023": "",
                "31/12/2022": ""
            },
            {
                "": "",
                "31/12/2023": "",
                "31/12/2022": ""
            },
            {
                "": "Subventions, fonds publics et fonds spéciaux de garantie reçus",
                "31/12/2023": "",
                "31/12/2022": ""
            },
            {
                "": "Emission de dettes subordonnées",
                "31/12/2023": "",
                "31/12/2022": ""
            },
            {
                "": "Emission d'actions",
                "31/12/2023": "",
                "31/12/2022": ""
            },
            {
                "": "Remboursement des capitaux propres et assimilés",
                "31/12/2023": "",
                "31/12/2022": ""
            },
            {
                "": "Intérêts versés",
                "31/12/2023": "",
                "31/12/2022": ""
            },
            {
                "": "Dividendes versés",
                "31/12/2023": "84 351",
                "31/12/2022": "162 454"
            },
            {
                "": "",
                "31/12/2023": "",
                "31/12/2022": ""
            },
            {
                "": "FLUX DE TRESORERIE NETS PROVENANT DES ACTIVITES DE",
                "31/12/2023": "-84 351",
                "31/12/2022": "-162 454"
            },
            {
                "": "FINANCEMENT",
                "31/12/2023": "",
                "31/12/2022": ""
            },
            {
                "": "VARIATION NETTE DE LA TRESORERIE",
                "31/12/2023": "-42 750",
                "31/12/2022": "50 512"
            },
            {
                "": "",
                "31/12/2023": "",
                "31/12/2022": ""
            },
            {
                "": "TRESORERIE A L'OUVERTURE DE L'EXERCICE",
                "31/12/2023": "-113 512",
                "31/12/2022": "-164 024"
            },
            {
                "": "",
                "31/12/2023": "",
                "31/12/2022": ""
            },
            {
                "": "TRESORERIE A LA CLOTURE DE L'EXERCICE",
                "31/12/2023": "-156 262",
                "31/12/2022": "-113 512"
            },
            {
                "": "",
                "31/12/2023": "",
                "31/12/2022": ""
            }
        ],
        [
            {
                "PROVISIONS": "PROVISIONS, DEDUITES DE L'ACTIF, SUR:",
                "Encours\n31/12/2022": "994 629",
                "Dotations": "101 878",
                "Reprises": "1 141",
                "Autres\nvariations": "",
                "Encours\n31/12/2023": "1 095 365"
            },
            {
                "PROVISIONS": "",
                "Encours\n31/12/2022": "",
                "Dotations": "",
                "Reprises": "",
                "Autres\nvariations": "",
                "Encours\n31/12/2023": ""
            },
            {
                "PROVISIONS": "créances sur les établissements de crédit et assimilés",
                "Encours\n31/12/2022": "",
                "Dotations": "",
                "Reprises": "",
                "Autres\nvariations": "",
                "Encours\n31/12/2023": ""
            },
            {
                "PROVISIONS": "créances sur la clientèle",
                "Encours\n31/12/2022": "779 278",
                "Dotations": "85 222",
                "Reprises": "889",
                "Autres\nvariations": "",
                "Encours\n31/12/2023": "863 610"
            },
            {
                "PROVISIONS": "titres de placement",
                "Encours\n31/12/2022": "",
                "Dotations": "",
                "Reprises": "",
                "Autres\nvariations": "",
                "Encours\n31/12/2023": ""
            },
            {
                "PROVISIONS": "titres de participation et emplois assimilés",
                "Encours\n31/12/2022": "",
                "Dotations": "",
                "Reprises": "",
                "Autres\nvariations": "",
                "Encours\n31/12/2023": ""
            },
            {
                "PROVISIONS": "immobilisations en crédit-bail et en location",
                "Encours\n31/12/2022": "215 351",
                "Dotations": "16 656",
                "Reprises": "252",
                "Autres\nvariations": "",
                "Encours\n31/12/2023": "231 755"
            },
            {
                "PROVISIONS": "autres actifs",
                "Encours\n31/12/2022": "",
                "Dotations": "",
                "Reprises": "",
                "Autres\nvariations": "",
                "Encours\n31/12/2023": ""
            },
            {
                "PROVISIONS": "",
                "Encours\n31/12/2022": "",
                "Dotations": "",
                "Reprises": "",
                "Autres\nvariations": "",
                "Encours\n31/12/2023": ""
            },
            {
                "PROVISIONS": "PROVISIONS INSCRITES AU PASSIF",
                "Encours\n31/12/2022": "58 679",
                "Dotations": "88",
                "Reprises": "780",
                "Autres\nvariations": "",
                "Encours\n31/12/2023": "57 986"
            },
            {
                "PROVISIONS": "",
                "Encours\n31/12/2022": "",
                "Dotations": "",
                "Reprises": "",
                "Autres\nvariations": "",
                "Encours\n31/12/2023": ""
            },
            {
                "PROVISIONS": "Provisions pour risques d'exécution d'engagements par\nsignature",
                "Encours\n31/12/2022": "",
                "Dotations": "",
                "Reprises": "",
                "Autres\nvariations": "",
                "Encours\n31/12/2023": ""
            },
            {
                "PROVISIONS": "Provisions pour risques de change",
                "Encours\n31/12/2022": "",
                "Dotations": "",
                "Reprises": "",
                "Autres\nvariations": "",
                "Encours\n31/12/2023": ""
            },
            {
                "PROVISIONS": "Provisions pour risques généraux",
                "Encours\n31/12/2022": "",
                "Dotations": "",
                "Reprises": "",
                "Autres\nvariations": "",
                "Encours\n31/12/2023": ""
            },
            {
                "PROVISIONS": "Provisions pour pensions de retraite et obligations",
                "Encours\n31/12/2022": "",
                "Dotations": "",
                "Reprises": "",
                "Autres\nvariations": "",
                "Encours\n31/12/2023": ""
            },
            {
                "PROVISIONS": "similaires",
                "Encours\n31/12/2022": "",
                "Dotations": "",
                "Reprises": "",
                "Autres\nvariations": "",
                "Encours\n31/12/2023": ""
            },
            {
                "PROVISIONS": "Provisions pour autres risques et charges",
                "Encours\n31/12/2022": "36 437",
                "Dotations": "",
                "Reprises": "",
                "Autres\nvariations": "",
                "Encours\n31/12/2023": "36 437"
            },
            {
                "PROVISIONS": "Provisions réglementées",
                "Encours\n31/12/2022": "22 242",
                "Dotations": "88",
                "Reprises": "780",
                "Autres\nvariations": "",
                "Encours\n31/12/2023": "21 549"
            },
            {
                "PROVISIONS": "",
                "Encours\n31/12/2022": "",
                "Dotations": "",
                "Reprises": "",
                "Autres\nvariations": "",
                "Encours\n31/12/2023": ""
            },
            {
                "PROVISIONS": "TOTAL GENERAL",
                "Encours\n31/12/2022": "1 053 308",
                "Dotations": "101 965",
                "Reprises": "1 922",
                "Autres\nvariations": "",
                "Encours\n31/12/2023": "1 153 351"
            }
        ],
        [
            {
                "": "ACTIF",
                "D< 1 mois": "",
                "1 mois<D< 3\nmois": "",
                "3 mois<D< 1 an": "",
                "1 an <D< 5 ans": "",
                "D> 5 ans": "",
                "TOTAL": ""
            },
            {
                "": "Créances sur les établissements de crédit et assimilés",
                "D< 1 mois": "",
                "1 mois<D< 3\nmois": "",
                "3 mois<D< 1 an": "",
                "1 an <D< 5 ans": "",
                "D> 5 ans": "",
                "TOTAL": ""
            },
            {
                "": "Créances sur la clientèle",
                "D< 1 mois": "377",
                "1 mois<D< 3\nmois": "7 971",
                "3 mois<D< 1 an": "91 184",
                "1 an <D< 5 ans": "1 529 461",
                "D> 5 ans": "661 167",
                "TOTAL": "2 290 160"
            },
            {
                "": "Titres de créance",
                "D< 1 mois": "",
                "1 mois<D< 3\nmois": "",
                "3 mois<D< 1 an": "",
                "1 an <D< 5 ans": "",
                "D> 5 ans": "",
                "TOTAL": ""
            },
            {
                "": "Créances subordonnées",
                "D< 1 mois": "",
                "1 mois<D< 3\nmois": "",
                "3 mois<D< 1 an": "",
                "1 an <D< 5 ans": "",
                "D> 5 ans": "",
                "TOTAL": ""
            },
            {
                "": "Crédit-bail et assimilé",
                "D< 1 mois": "268",
                "1 mois<D< 3\nmois": "4 099",
                "3 mois<D< 1 an": "52 600",
                "1 an <D< 5 ans": "973 420",
                "D> 5 ans": "28 723",
                "TOTAL": "1 059 110"
            },
            {
                "": "TOTAL",
                "D< 1 mois": "645",
                "1 mois<D< 3\nmois": "12 070",
                "3 mois<D< 1 an": "143 783",
                "1 an <D< 5 ans": "2 502 881",
                "D> 5 ans": "689 890",
                "TOTAL": "3 349 270"
            },
            {
                "": "",
                "D< 1 mois": "",
                "1 mois<D< 3\nmois": "",
                "3 mois<D< 1 an": "",
                "1 an <D< 5 ans": "",
                "D> 5 ans": "",
                "TOTAL": ""
            },
            {
                "": "PASSIF",
                "D< 1 mois": "",
                "1 mois<D< 3\nmois": "",
                "3 mois<D< 1 an": "",
                "1 an <D< 5 ans": "",
                "D> 5 ans": "",
                "TOTAL": ""
            },
            {
                "": "Dettes envers les établissements de crédit et assimilés",
                "D< 1 mois": "156 339",
                "1 mois<D< 3\nmois": "",
                "3 mois<D< 1 an": "",
                "1 an <D< 5 ans": "300 510",
                "D> 5 ans": "",
                "TOTAL": "456 849"
            },
            {
                "": "Dettes envers la clientèle (*)",
                "D< 1 mois": "25",
                "1 mois<D< 3\nmois": "521",
                "3 mois<D< 1 an": "5 961",
                "1 an <D< 5 ans": "99 988",
                "D> 5 ans": "43 223",
                "TOTAL": "149 718"
            },
            {
                "": "Titres de créance émis",
                "D< 1 mois": "162 178",
                "1 mois<D< 3\nmois": "100 000",
                "3 mois<D< 1 an": "776 000",
                "1 an <D< 5 ans": "460 000",
                "D> 5 ans": "",
                "TOTAL": "1 498 178"
            },
            {
                "": "Emprunts subordonnés",
                "D< 1 mois": "",
                "1 mois<D< 3\nmois": "",
                "3 mois<D< 1 an": "",
                "1 an <D< 5 ans": "",
                "D> 5 ans": "",
                "TOTAL": ""
            },
            {
                "": "",
                "D< 1 mois": "",
                "1 mois<D< 3\nmois": "",
                "3 mois<D< 1 an": "",
                "1 an <D< 5 ans": "",
                "D> 5 ans": "",
                "TOTAL": ""
            },
            {
                "": "TOTAL",
                "D< 1 mois": "318 542",
                "1 mois<D< 3\nmois": "100 521",
                "3 mois<D< 1 an": "781 961",
                "1 an <D< 5 ans": "860 498",
                "D> 5 ans": "43 223",
                "TOTAL": "2 104 745"
            }
        ],
        [
            {
                "CREANCES": "",
                "Secteur\npublic": "",
                "Secteur privé": "Entreprises\nfinancières",
                "null": "Autre\nclientèle",
                "Total\n31/12/2023": "",
                "Total\n31/12/2022": ""
            },
            {
                "CREANCES": "",
                "Secteur\npublic": "",
                "Secteur privé": "",
                "null": "",
                "Total\n31/12/2023": "",
                "Total\n31/12/2022": ""
            },
            {
                "CREANCES": "CREDITS DE TRESORERIE",
                "Secteur\npublic": "",
                "Secteur privé": "",
                "null": "",
                "Total\n31/12/2023": "",
                "Total\n31/12/2022": ""
            },
            {
                "CREANCES": "- Comptes à vue débiteurs",
                "Secteur\npublic": "",
                "Secteur privé": "",
                "null": "",
                "Total\n31/12/2023": "",
                "Total\n31/12/2022": ""
            },
            {
                "CREANCES": "- Créances commerciales sur le Maroc",
                "Secteur\npublic": "",
                "Secteur privé": "",
                "null": "",
                "Total\n31/12/2023": "",
                "Total\n31/12/2022": ""
            },
            {
                "CREANCES": "- Crédits à l'exportation",
                "Secteur\npublic": "",
                "Secteur privé": "",
                "null": "",
                "Total\n31/12/2023": "",
                "Total\n31/12/2022": ""
            },
            {
                "CREANCES": "- Autres crédits de trésorerie",
                "Secteur\npublic": "",
                "Secteur privé": "",
                "null": "",
                "Total\n31/12/2023": "",
                "Total\n31/12/2022": ""
            },
            {
                "CREANCES": "",
                "Secteur\npublic": "",
                "Secteur privé": "",
                "null": "",
                "Total\n31/12/2023": "",
                "Total\n31/12/2022": ""
            },
            {
                "CREANCES": "CREDITS A LA CONSOMMATION",
                "Secteur\npublic": "",
                "Secteur privé": "",
                "null": "2 124 371",
                "Total\n31/12/2023": "2 124 371",
                "Total\n31/12/2022": "2 197 340"
            },
            {
                "CREANCES": "CREDITS A L'EQUIPEMENT",
                "Secteur\npublic": "",
                "Secteur privé": "",
                "null": "",
                "Total\n31/12/2023": "",
                "Total\n31/12/2022": ""
            },
            {
                "CREANCES": "CREDITS IMMOBILIERS",
                "Secteur\npublic": "",
                "Secteur privé": "",
                "null": "",
                "Total\n31/12/2023": "",
                "Total\n31/12/2022": ""
            },
            {
                "CREANCES": "AUTRES CREDITS",
                "Secteur\npublic": "",
                "Secteur privé": "",
                "null": "",
                "Total\n31/12/2023": "",
                "Total\n31/12/2022": ""
            },
            {
                "CREANCES": "CREANCES ACQUISES PAR AFFACTURAGE",
                "Secteur\npublic": "",
                "Secteur privé": "",
                "null": "",
                "Total\n31/12/2023": "",
                "Total\n31/12/2022": ""
            },
            {
                "CREANCES": "INTERETS COURUS A RECEVOIR",
                "Secteur\npublic": "",
                "Secteur privé": "",
                "null": "",
                "Total\n31/12/2023": "",
                "Total\n31/12/2022": ""
            },
            {
                "CREANCES": "CREANCES EN SOUFFRANCE",
                "Secteur\npublic": "",
                "Secteur privé": "",
                "null": "165 789",
                "Total\n31/12/2023": "165 789",
                "Total\n31/12/2022": "202 334"
            },
            {
                "CREANCES": "- Créances pré-douteuses",
                "Secteur\npublic": "",
                "Secteur privé": "",
                "null": "43 034",
                "Total\n31/12/2023": "43 034",
                "Total\n31/12/2022": "63 637"
            },
            {
                "CREANCES": "- Créances douteuses",
                "Secteur\npublic": "",
                "Secteur privé": "",
                "null": "1 678",
                "Total\n31/12/2023": "1 678",
                "Total\n31/12/2022": "5 131"
            },
            {
                "CREANCES": "- Créances compromises",
                "Secteur\npublic": "",
                "Secteur privé": "",
                "null": "121 076",
                "Total\n31/12/2023": "121 076",
                "Total\n31/12/2022": "133 566"
            },
            {
                "CREANCES": "",
                "Secteur\npublic": "",
                "Secteur privé": "",
                "null": "",
                "Total\n31/12/2023": "",
                "Total\n31/12/2022": ""
            },
            {
                "CREANCES": "TOTAL",
                "Secteur\npublic": "",
                "Secteur privé": "",
                "null": "2 290 160",
                "Total\n31/12/2023": "2 290 160",
                "Total\n31/12/2022": "2 399 674"
            }
        ],
        [
            {
                "Dénomination de la société\némettrice": "",
                "Secteur d'activité": "",
                "Capital\nsocial": "",
                "Participation\nau capital\nen %": "",
                "Prix\nd'acquisition\nglobal": "",
                "Valeur\ncomptable\nnette": "",
                "Extrait des derniers états de synthèse de la\nsociété émetttrice": "Date de clôture de\nl'exercice",
                "null": "Résultat\nnet",
                "Produits\ninscrits au\nCPC de\nl'exercice": ""
            },
            {
                "Dénomination de la société\némettrice": "Participations dans les",
                "Secteur d'activité": "",
                "Capital\nsocial": "",
                "Participation\nau capital\nen %": "",
                "Prix\nd'acquisition\nglobal": "",
                "Valeur\ncomptable\nnette": "",
                "Extrait des derniers états de synthèse de la\nsociété émetttrice": "",
                "null": "",
                "Produits\ninscrits au\nCPC de\nl'exercice": ""
            },
            {
                "Dénomination de la société\némettrice": "entreprises liées",
                "Secteur d'activité": "",
                "Capital\nsocial": "",
                "Participation\nau capital\nen %": "",
                "Prix\nd'acquisition\nglobal": "",
                "Valeur\ncomptable\nnette": "",
                "Extrait des derniers états de synthèse de la\nsociété émetttrice": "",
                "null": "",
                "Produits\ninscrits au\nCPC de\nl'exercice": ""
            },
            {
                "Dénomination de la société\némettrice": "",
                "Secteur d'activité": "",
                "Capital\nsocial": "",
                "Participation\nau capital\nen %": "",
                "Prix\nd'acquisition\nglobal": "",
                "Valeur\ncomptable\nnette": "",
                "Extrait des derniers états de synthèse de la\nsociété émetttrice": "",
                "null": "",
                "Produits\ninscrits au\nCPC de\nl'exercice": ""
            },
            {
                "Dénomination de la société\némettrice": "",
                "Secteur d'activité": "",
                "Capital\nsocial": "",
                "Participation\nau capital\nen %": "",
                "Prix\nd'acquisition\nglobal": "",
                "Valeur\ncomptable\nnette": "",
                "Extrait des derniers états de synthèse de la\nsociété émetttrice": "",
                "null": "",
                "Produits\ninscrits au\nCPC de\nl'exercice": ""
            },
            {
                "Dénomination de la société\némettrice": "",
                "Secteur d'activité": "",
                "Capital\nsocial": "",
                "Participation\nau capital\nen %": "",
                "Prix\nd'acquisition\nglobal": "",
                "Valeur\ncomptable\nnette": "",
                "Extrait des derniers états de synthèse de la\nsociété émetttrice": "",
                "null": "",
                "Produits\ninscrits au\nCPC de\nl'exercice": ""
            },
            {
                "Dénomination de la société\némettrice": "Autres titres de participation",
                "Secteur d'activité": "",
                "Capital\nsocial": "400",
                "Participation\nau capital\nen %": "",
                "Prix\nd'acquisition\nglobal": "401",
                "Valeur\ncomptable\nnette": "401",
                "Extrait des derniers états de synthèse de la\nsociété émetttrice": "",
                "null": "2 879",
                "Produits\ninscrits au\nCPC de\nl'exercice": ""
            },
            {
                "Dénomination de la société\némettrice": "",
                "Secteur d'activité": "",
                "Capital\nsocial": "",
                "Participation\nau capital\nen %": "",
                "Prix\nd'acquisition\nglobal": "",
                "Valeur\ncomptable\nnette": "",
                "Extrait des derniers états de synthèse de la\nsociété émetttrice": "",
                "null": "",
                "Produits\ninscrits au\nCPC de\nl'exercice": ""
            },
            {
                "Dénomination de la société\némettrice": "Divers Ste. de Crédit à la\nconsommation",
                "Secteur d'activité": "Crédit à la\nconsommation",
                "Capital\nsocial": "0",
                "Participation\nau capital\nen %": "NS",
                "Prix\nd'acquisition\nglobal": "1",
                "Valeur\ncomptable\nnette": "1",
                "Extrait des derniers états de synthèse de la\nsociété émetttrice": "31/12/2023",
                "null": "",
                "Produits\ninscrits au\nCPC de\nl'exercice": ""
            },
            {
                "Dénomination de la société\némettrice": "ORUS Services SA",
                "Secteur d'activité": "Informatique",
                "Capital\nsocial": "300",
                "Participation\nau capital\nen %": "100%",
                "Prix\nd'acquisition\nglobal": "300",
                "Valeur\ncomptable\nnette": "300",
                "Extrait des derniers états de synthèse de la\nsociété émetttrice": "31/12/2023",
                "null": "2879",
                "Produits\ninscrits au\nCPC de\nl'exercice": "13366"
            },
            {
                "Dénomination de la société\némettrice": "ORUS ASSURANCE SA",
                "Secteur d'activité": "Assurance",
                "Capital\nsocial": "100",
                "Participation\nau capital\nen %": "100%",
                "Prix\nd'acquisition\nglobal": "100",
                "Valeur\ncomptable\nnette": "100",
                "Extrait des derniers états de synthèse de la\nsociété émetttrice": "31/12/2023",
                "null": "",
                "Produits\ninscrits au\nCPC de\nl'exercice": ""
            },
            {
                "Dénomination de la société\némettrice": "TOTAL",
                "Secteur d'activité": "",
                "Capital\nsocial": "",
                "Participation\nau capital\nen %": "",
                "Prix\nd'acquisition\nglobal": "401",
                "Valeur\ncomptable\nnette": "401",
                "Extrait des derniers états de synthèse de la\nsociété émetttrice": "",
                "null": "2 879",
                "Produits\ninscrits au\nCPC de\nl'exercice": ""
            }
        ],
        [
            {
                "Communication financière": "Situation au 31 décembre 2023\nIMMOBILISATIONS DONNEES EN CREDIT-BAIL, EN LOCATION AVEC OPTION D’ACHAT ET EN LOCATION SIMPLE\nen milliers de DH\nMontant des Amortissements Provisions\nMontant des\nMontant brut au cessions ou Montant brut à la Montant net à la\nNature acquisitions au\ndébut de l'exercice retraits au cours fin de l'exercice fin de l'exercice\ncours de l'exercice Dotations au titre de Cumul des Dotations au titre Reprises de Cumul des\nde l'exercice\nl'exercice amortissements de l'exercice provisions provisions\nIMMOBILISATIONS DONNEES EN CREDIT-BAIL ET 10 872 648 341 823 195 480 11 018 992 397 773 9 728 128 16 656 231 755 1 059 110\nEN LOCATION AVEC OPTION D'ACHAT\nCREDIT-BAIL SUR IMMOBILISATIONS INCORPORELLES\nCREDIT-BAIL MOBILIER 10 250 501 294 553 195 480 10 349 575 397 773 9 728 128 621 447\n- Crédit-bail mobilier en cours\n- Crédit-bail mobilier loué 10 250 501 294 553 195 480 10 349 575 397 773 9 728 128 621 447\n- Crédit-bail mobilier non loué après résiliation\nCREDIT-BAIL IMMOBILIER\n- Crédit-bail immobilier en cours\n- Crédit-bail immobilier loué\n- Crédit-bail immobilier non loué après résiliation\nLOYERS COURUS A RECEVOIR 42 611 7 627 50 238 50 238\nLOYERS RESTRUCTURES\nLOYERS IMPAYES 233 619 18 334 251 953 251 953\nCREANCES EN SOUFFRANCE 345 916 21 310 367 226 16 656 231 755 135 471\nIMMOBILISATIONS DONNEES EN LOCATION SIMPLE\nBIENS MOBILIERS EN LOCATION SIMPLE\nBIENS IMMOBILIERS EN LOCATION SIMPLE\nLOYERS COURUS A RECEVOIR\nLOYERS RESTRUCTURES\nLOYERS IMPAYES\nLOYERS EN SOUFFRANCE\nTotal 10 872 648 341 823 195 480 11 018 992 397 773 9 728 128 16 656 231 755 1 059 110\nDETTES ENVERS LES ETABLISSEMENTS DE CREDIT ET ASSIMILES PRINCPALES METHODES D’EVALUATION APPLIQUEES\nen milliers de DH\nINDICATION DES METHODES D'EVALUATION APPLIQUEES PAR L'ETABLISSEMENT\nDETTES Etablissements de crédit et assimilés au Maroc\nAutres Etablissements de Total Total\nBank Al-Maghrib, établissements crédit à l’étranger 31/12/2023 31/12/2022\nTrésor Public et Banques au Les méthodes d'évaluation appliquées par SALAFIN sont celles requises par le Plan Comptable des Etablissements de Crédit (PCEC)\nde crédit et\nService des Chèques Maroc\nassimilés au\nPostaux\nMaroc\nCOMPTES ORDINAIRES CREDITEURS 156 339 156 339 113 592 ETAT DES DEROGATIONS\nVALEURS DONNEES EN PENSION\n- au jour le jour INFLUENCE DES DEROGATIONS SUR LE\n- à terme\nINDICATIONS DES DEROGATIONS JUSTIFICATIONS DES DEROGATIONS PATRIMOINE, LA SITUATION FINANCIERE ET\nEMPRUNTS DE TRESORERIE LES RESULTATS\n- au jour le jour\n- à terme\nI. Dérogations aux principes\nEMPRUNTS FINANCIERS 300 510 300 510 300 510 comptables fondamentaux A N T\nE\nAUTRES DETTES N\nINTERETS COURUS A PAYER\nTotal 456 849 456 849 414 102\nT\nOPERATIONS DE CHANGE A TERME ET ENGAGEMENTS SUR PRODUITS DÉRIVÉS II. Dérogations aux méthodes E A N\nd'évaluation N\nen milliers de DH\nOpérations de couverture Autres opérations\n31/12/2023 31/12/2022 31/12/2023 31/12/2022 III. Dérogations aux règles N T\nOpérations de change à terme d'établissement et de E A\nDevises à recevoir présentation des états de synthèse N\nDevises à livrer\nDirhams à recevoir T\nDirhams à livrer N\nA ETAT DES CHANGEMENTS DE METHODES\nDont swaps financiers de devises\nE\nEngagements sur produits dérivés N NATURE DES CHANGEMENTS JUSTIFICATIONS DES CHANGEMENTS INFLUENCE SUR LE PATRIMOINE, LA SITUATION\nEngagements sur marchés réglementés de taux d'intérêt FINANCIERE ET LES RESULTATS\nEngagements sur marchés de gré à gré de taux d'intérêt\nEngagements sur marchés réglementés de cours de change I. Changements affectant les T\nEngagements sur marchés de gré à gré de cours de change méthodes d'évaluation N\nEngagements sur marchés réglementés d'autres instruments A\nEngagements sur marchés de gré à gré d'autres instruments N E\nVALEURS ET SURETES RECUES ET DONNEES EN GARANTIE\nII. Changements affectant les règles T\nN\nValeurs et sûretés reçues en garantie Valeur comptable nette R eu neb gnr ai r gq e eu g me iss et rd nae tn s l t' p a l aec rt s i sf c i ro géu na and tcu ue rh s e o o dr us o lb nei nsla én s M peo atn r d t sea igsn c net os an u td g vue a ers g e r tec d sr m é oa e nn n nc t ése s s de présentation N E A\nBons duTrésor et valeurs assimilées\nAutres titres\nHypothèques 406 048 Créances sur la clientèle (Bilan) 99 835\nAutres valeurs et sûretés réelles\nLE TABLEAU DE CONCENTRATION DES RISQUES SUR UN MÊME BÉNÉFICIAIRE\nTOTAL 406 048 99 835\nRubriques du passif ou du hors Montants des dettes ou NOMBRE DE BENEFICIAIRES TOTAL ENGAGEMENT\nValeurs et sûretés données en garantie Valeur comptable nette bilan enregistrant les dettes ou les des engagements par\nengagements par signature reçus signature reçus couverts T\nN\nBons du Trésor et valeurs assimilées N T A\nA Hu yptr oe ts h t èit qre us e s N E A N E\nAutres valeurs et sûretés réelles\nTOTAL"
            },
            {
                "Communication financière": ""
            }
        ],
        [
            {
                "Nature": "",
                "Montant brut au\ndébut de l'exercice": "",
                "Montant des\nacquisitions au\ncours de l'exercice": "",
                "Montant des\ncessions ou\nretraits au cours\nde l'exercice": "",
                "Montant brut à la\nfin de l'exercice": "",
                "Amortissements": "Dotations au titre de\nl'exercice",
                "null": "Cumul des\nprovisions",
                "Provisions": "Dotations au titre\nde l'exercice",
                "Montant net à la\nfin de l'exercice": ""
            },
            {
                "Nature": "IMMOBILISATIONS DONNEES EN CREDIT-BAIL ET",
                "Montant brut au\ndébut de l'exercice": "10 872 648",
                "Montant des\nacquisitions au\ncours de l'exercice": "341 823",
                "Montant des\ncessions ou\nretraits au cours\nde l'exercice": "195 480",
                "Montant brut à la\nfin de l'exercice": "11 018 992",
                "Amortissements": "397 773",
                "null": "231 755",
                "Provisions": "16 656",
                "Montant net à la\nfin de l'exercice": "1 059 110"
            },
            {
                "Nature": "EN LOCATION AVEC OPTION D'ACHAT",
                "Montant brut au\ndébut de l'exercice": "",
                "Montant des\nacquisitions au\ncours de l'exercice": "",
                "Montant des\ncessions ou\nretraits au cours\nde l'exercice": "",
                "Montant brut à la\nfin de l'exercice": "",
                "Amortissements": "",
                "null": "",
                "Provisions": "",
                "Montant net à la\nfin de l'exercice": ""
            },
            {
                "Nature": "",
                "Montant brut au\ndébut de l'exercice": "",
                "Montant des\nacquisitions au\ncours de l'exercice": "",
                "Montant des\ncessions ou\nretraits au cours\nde l'exercice": "",
                "Montant brut à la\nfin de l'exercice": "",
                "Amortissements": "",
                "null": "",
                "Provisions": "",
                "Montant net à la\nfin de l'exercice": ""
            },
            {
                "Nature": "CREDIT-BAIL SUR IMMOBILISATIONS INCORPORELLES",
                "Montant brut au\ndébut de l'exercice": "",
                "Montant des\nacquisitions au\ncours de l'exercice": "",
                "Montant des\ncessions ou\nretraits au cours\nde l'exercice": "",
                "Montant brut à la\nfin de l'exercice": "",
                "Amortissements": "",
                "null": "",
                "Provisions": "",
                "Montant net à la\nfin de l'exercice": ""
            },
            {
                "Nature": "",
                "Montant brut au\ndébut de l'exercice": "",
                "Montant des\nacquisitions au\ncours de l'exercice": "",
                "Montant des\ncessions ou\nretraits au cours\nde l'exercice": "",
                "Montant brut à la\nfin de l'exercice": "",
                "Amortissements": "",
                "null": "",
                "Provisions": "",
                "Montant net à la\nfin de l'exercice": ""
            },
            {
                "Nature": "CREDIT-BAIL MOBILIER",
                "Montant brut au\ndébut de l'exercice": "10 250 501",
                "Montant des\nacquisitions au\ncours de l'exercice": "294 553",
                "Montant des\ncessions ou\nretraits au cours\nde l'exercice": "195 480",
                "Montant brut à la\nfin de l'exercice": "10 349 575",
                "Amortissements": "397 773",
                "null": "",
                "Provisions": "",
                "Montant net à la\nfin de l'exercice": "621 447"
            },
            {
                "Nature": "- Crédit-bail mobilier en cours",
                "Montant brut au\ndébut de l'exercice": "",
                "Montant des\nacquisitions au\ncours de l'exercice": "",
                "Montant des\ncessions ou\nretraits au cours\nde l'exercice": "",
                "Montant brut à la\nfin de l'exercice": "",
                "Amortissements": "",
                "null": "",
                "Provisions": "",
                "Montant net à la\nfin de l'exercice": ""
            },
            {
                "Nature": "- Crédit-bail mobilier loué",
                "Montant brut au\ndébut de l'exercice": "10 250 501",
                "Montant des\nacquisitions au\ncours de l'exercice": "294 553",
                "Montant des\ncessions ou\nretraits au cours\nde l'exercice": "195 480",
                "Montant brut à la\nfin de l'exercice": "10 349 575",
                "Amortissements": "397 773",
                "null": "",
                "Provisions": "",
                "Montant net à la\nfin de l'exercice": "621 447"
            },
            {
                "Nature": "- Crédit-bail mobilier non loué après résiliation",
                "Montant brut au\ndébut de l'exercice": "",
                "Montant des\nacquisitions au\ncours de l'exercice": "",
                "Montant des\ncessions ou\nretraits au cours\nde l'exercice": "",
                "Montant brut à la\nfin de l'exercice": "",
                "Amortissements": "",
                "null": "",
                "Provisions": "",
                "Montant net à la\nfin de l'exercice": ""
            },
            {
                "Nature": "",
                "Montant brut au\ndébut de l'exercice": "",
                "Montant des\nacquisitions au\ncours de l'exercice": "",
                "Montant des\ncessions ou\nretraits au cours\nde l'exercice": "",
                "Montant brut à la\nfin de l'exercice": "",
                "Amortissements": "",
                "null": "",
                "Provisions": "",
                "Montant net à la\nfin de l'exercice": ""
            },
            {
                "Nature": "CREDIT-BAIL IMMOBILIER",
                "Montant brut au\ndébut de l'exercice": "",
                "Montant des\nacquisitions au\ncours de l'exercice": "",
                "Montant des\ncessions ou\nretraits au cours\nde l'exercice": "",
                "Montant brut à la\nfin de l'exercice": "",
                "Amortissements": "",
                "null": "",
                "Provisions": "",
                "Montant net à la\nfin de l'exercice": ""
            },
            {
                "Nature": "- Crédit-bail immobilier en cours",
                "Montant brut au\ndébut de l'exercice": "",
                "Montant des\nacquisitions au\ncours de l'exercice": "",
                "Montant des\ncessions ou\nretraits au cours\nde l'exercice": "",
                "Montant brut à la\nfin de l'exercice": "",
                "Amortissements": "",
                "null": "",
                "Provisions": "",
                "Montant net à la\nfin de l'exercice": ""
            },
            {
                "Nature": "- Crédit-bail immobilier loué",
                "Montant brut au\ndébut de l'exercice": "",
                "Montant des\nacquisitions au\ncours de l'exercice": "",
                "Montant des\ncessions ou\nretraits au cours\nde l'exercice": "",
                "Montant brut à la\nfin de l'exercice": "",
                "Amortissements": "",
                "null": "",
                "Provisions": "",
                "Montant net à la\nfin de l'exercice": ""
            },
            {
                "Nature": "- Crédit-bail immobilier non loué après résiliation",
                "Montant brut au\ndébut de l'exercice": "",
                "Montant des\nacquisitions au\ncours de l'exercice": "",
                "Montant des\ncessions ou\nretraits au cours\nde l'exercice": "",
                "Montant brut à la\nfin de l'exercice": "",
                "Amortissements": "",
                "null": "",
                "Provisions": "",
                "Montant net à la\nfin de l'exercice": ""
            },
            {
                "Nature": "",
                "Montant brut au\ndébut de l'exercice": "",
                "Montant des\nacquisitions au\ncours de l'exercice": "",
                "Montant des\ncessions ou\nretraits au cours\nde l'exercice": "",
                "Montant brut à la\nfin de l'exercice": "",
                "Amortissements": "",
                "null": "",
                "Provisions": "",
                "Montant net à la\nfin de l'exercice": ""
            },
            {
                "Nature": "LOYERS COURUS A RECEVOIR",
                "Montant brut au\ndébut de l'exercice": "42 611",
                "Montant des\nacquisitions au\ncours de l'exercice": "7 627",
                "Montant des\ncessions ou\nretraits au cours\nde l'exercice": "",
                "Montant brut à la\nfin de l'exercice": "50 238",
                "Amortissements": "",
                "null": "",
                "Provisions": "",
                "Montant net à la\nfin de l'exercice": "50 238"
            },
            {
                "Nature": "",
                "Montant brut au\ndébut de l'exercice": "",
                "Montant des\nacquisitions au\ncours de l'exercice": "",
                "Montant des\ncessions ou\nretraits au cours\nde l'exercice": "",
                "Montant brut à la\nfin de l'exercice": "",
                "Amortissements": "",
                "null": "",
                "Provisions": "",
                "Montant net à la\nfin de l'exercice": ""
            },
            {
                "Nature": "LOYERS RESTRUCTURES",
                "Montant brut au\ndébut de l'exercice": "",
                "Montant des\nacquisitions au\ncours de l'exercice": "",
                "Montant des\ncessions ou\nretraits au cours\nde l'exercice": "",
                "Montant brut à la\nfin de l'exercice": "",
                "Amortissements": "",
                "null": "",
                "Provisions": "",
                "Montant net à la\nfin de l'exercice": ""
            },
            {
                "Nature": "",
                "Montant brut au\ndébut de l'exercice": "",
                "Montant des\nacquisitions au\ncours de l'exercice": "",
                "Montant des\ncessions ou\nretraits au cours\nde l'exercice": "",
                "Montant brut à la\nfin de l'exercice": "",
                "Amortissements": "",
                "null": "",
                "Provisions": "",
                "Montant net à la\nfin de l'exercice": ""
            },
            {
                "Nature": "LOYERS IMPAYES",
                "Montant brut au\ndébut de l'exercice": "233 619",
                "Montant des\nacquisitions au\ncours de l'exercice": "18 334",
                "Montant des\ncessions ou\nretraits au cours\nde l'exercice": "",
                "Montant brut à la\nfin de l'exercice": "251 953",
                "Amortissements": "",
                "null": "",
                "Provisions": "",
                "Montant net à la\nfin de l'exercice": "251 953"
            },
            {
                "Nature": "",
                "Montant brut au\ndébut de l'exercice": "",
                "Montant des\nacquisitions au\ncours de l'exercice": "",
                "Montant des\ncessions ou\nretraits au cours\nde l'exercice": "",
                "Montant brut à la\nfin de l'exercice": "",
                "Amortissements": "",
                "null": "",
                "Provisions": "",
                "Montant net à la\nfin de l'exercice": ""
            },
            {
                "Nature": "CREANCES EN SOUFFRANCE",
                "Montant brut au\ndébut de l'exercice": "345 916",
                "Montant des\nacquisitions au\ncours de l'exercice": "21 310",
                "Montant des\ncessions ou\nretraits au cours\nde l'exercice": "",
                "Montant brut à la\nfin de l'exercice": "367 226",
                "Amortissements": "",
                "null": "231 755",
                "Provisions": "16 656",
                "Montant net à la\nfin de l'exercice": "135 471"
            },
            {
                "Nature": "",
                "Montant brut au\ndébut de l'exercice": "",
                "Montant des\nacquisitions au\ncours de l'exercice": "",
                "Montant des\ncessions ou\nretraits au cours\nde l'exercice": "",
                "Montant brut à la\nfin de l'exercice": "",
                "Amortissements": "",
                "null": "",
                "Provisions": "",
                "Montant net à la\nfin de l'exercice": ""
            },
            {
                "Nature": "IMMOBILISATIONS DONNEES EN LOCATION SIMPLE",
                "Montant brut au\ndébut de l'exercice": "",
                "Montant des\nacquisitions au\ncours de l'exercice": "",
                "Montant des\ncessions ou\nretraits au cours\nde l'exercice": "",
                "Montant brut à la\nfin de l'exercice": "",
                "Amortissements": "",
                "null": "",
                "Provisions": "",
                "Montant net à la\nfin de l'exercice": ""
            },
            {
                "Nature": "",
                "Montant brut au\ndébut de l'exercice": "",
                "Montant des\nacquisitions au\ncours de l'exercice": "",
                "Montant des\ncessions ou\nretraits au cours\nde l'exercice": "",
                "Montant brut à la\nfin de l'exercice": "",
                "Amortissements": "",
                "null": "",
                "Provisions": "",
                "Montant net à la\nfin de l'exercice": ""
            },
            {
                "Nature": "BIENS MOBILIERS EN LOCATION SIMPLE",
                "Montant brut au\ndébut de l'exercice": "",
                "Montant des\nacquisitions au\ncours de l'exercice": "",
                "Montant des\ncessions ou\nretraits au cours\nde l'exercice": "",
                "Montant brut à la\nfin de l'exercice": "",
                "Amortissements": "",
                "null": "",
                "Provisions": "",
                "Montant net à la\nfin de l'exercice": ""
            },
            {
                "Nature": "",
                "Montant brut au\ndébut de l'exercice": "",
                "Montant des\nacquisitions au\ncours de l'exercice": "",
                "Montant des\ncessions ou\nretraits au cours\nde l'exercice": "",
                "Montant brut à la\nfin de l'exercice": "",
                "Amortissements": "",
                "null": "",
                "Provisions": "",
                "Montant net à la\nfin de l'exercice": ""
            },
            {
                "Nature": "BIENS IMMOBILIERS EN LOCATION SIMPLE",
                "Montant brut au\ndébut de l'exercice": "",
                "Montant des\nacquisitions au\ncours de l'exercice": "",
                "Montant des\ncessions ou\nretraits au cours\nde l'exercice": "",
                "Montant brut à la\nfin de l'exercice": "",
                "Amortissements": "",
                "null": "",
                "Provisions": "",
                "Montant net à la\nfin de l'exercice": ""
            },
            {
                "Nature": "",
                "Montant brut au\ndébut de l'exercice": "",
                "Montant des\nacquisitions au\ncours de l'exercice": "",
                "Montant des\ncessions ou\nretraits au cours\nde l'exercice": "",
                "Montant brut à la\nfin de l'exercice": "",
                "Amortissements": "",
                "null": "",
                "Provisions": "",
                "Montant net à la\nfin de l'exercice": ""
            },
            {
                "Nature": "LOYERS COURUS A RECEVOIR",
                "Montant brut au\ndébut de l'exercice": "",
                "Montant des\nacquisitions au\ncours de l'exercice": "",
                "Montant des\ncessions ou\nretraits au cours\nde l'exercice": "",
                "Montant brut à la\nfin de l'exercice": "",
                "Amortissements": "",
                "null": "",
                "Provisions": "",
                "Montant net à la\nfin de l'exercice": ""
            },
            {
                "Nature": "",
                "Montant brut au\ndébut de l'exercice": "",
                "Montant des\nacquisitions au\ncours de l'exercice": "",
                "Montant des\ncessions ou\nretraits au cours\nde l'exercice": "",
                "Montant brut à la\nfin de l'exercice": "",
                "Amortissements": "",
                "null": "",
                "Provisions": "",
                "Montant net à la\nfin de l'exercice": ""
            },
            {
                "Nature": "LOYERS RESTRUCTURES",
                "Montant brut au\ndébut de l'exercice": "",
                "Montant des\nacquisitions au\ncours de l'exercice": "",
                "Montant des\ncessions ou\nretraits au cours\nde l'exercice": "",
                "Montant brut à la\nfin de l'exercice": "",
                "Amortissements": "",
                "null": "",
                "Provisions": "",
                "Montant net à la\nfin de l'exercice": ""
            },
            {
                "Nature": "",
                "Montant brut au\ndébut de l'exercice": "",
                "Montant des\nacquisitions au\ncours de l'exercice": "",
                "Montant des\ncessions ou\nretraits au cours\nde l'exercice": "",
                "Montant brut à la\nfin de l'exercice": "",
                "Amortissements": "",
                "null": "",
                "Provisions": "",
                "Montant net à la\nfin de l'exercice": ""
            },
            {
                "Nature": "LOYERS IMPAYES",
                "Montant brut au\ndébut de l'exercice": "",
                "Montant des\nacquisitions au\ncours de l'exercice": "",
                "Montant des\ncessions ou\nretraits au cours\nde l'exercice": "",
                "Montant brut à la\nfin de l'exercice": "",
                "Amortissements": "",
                "null": "",
                "Provisions": "",
                "Montant net à la\nfin de l'exercice": ""
            },
            {
                "Nature": "",
                "Montant brut au\ndébut de l'exercice": "",
                "Montant des\nacquisitions au\ncours de l'exercice": "",
                "Montant des\ncessions ou\nretraits au cours\nde l'exercice": "",
                "Montant brut à la\nfin de l'exercice": "",
                "Amortissements": "",
                "null": "",
                "Provisions": "",
                "Montant net à la\nfin de l'exercice": ""
            },
            {
                "Nature": "LOYERS EN SOUFFRANCE",
                "Montant brut au\ndébut de l'exercice": "",
                "Montant des\nacquisitions au\ncours de l'exercice": "",
                "Montant des\ncessions ou\nretraits au cours\nde l'exercice": "",
                "Montant brut à la\nfin de l'exercice": "",
                "Amortissements": "",
                "null": "",
                "Provisions": "",
                "Montant net à la\nfin de l'exercice": ""
            },
            {
                "Nature": "",
                "Montant brut au\ndébut de l'exercice": "",
                "Montant des\nacquisitions au\ncours de l'exercice": "",
                "Montant des\ncessions ou\nretraits au cours\nde l'exercice": "",
                "Montant brut à la\nfin de l'exercice": "",
                "Amortissements": "",
                "null": "",
                "Provisions": "",
                "Montant net à la\nfin de l'exercice": ""
            },
            {
                "Nature": "Total",
                "Montant brut au\ndébut de l'exercice": "10 872 648",
                "Montant des\nacquisitions au\ncours de l'exercice": "341 823",
                "Montant des\ncessions ou\nretraits au cours\nde l'exercice": "195 480",
                "Montant brut à la\nfin de l'exercice": "11 018 992",
                "Amortissements": "397 773",
                "null": "231 755",
                "Provisions": "16 656",
                "Montant net à la\nfin de l'exercice": "1 059 110"
            }
        ],
        [
            {
                "INDICATION DES METHODES D'EVALUATION APPLIQUEES PAR L'ETABLISSEMENT": "Les méthodes d'évaluation appliquées par SALAFIN sont celles requises par le Plan Comptable des Etablissements de Crédit (PCEC)"
            }
        ],
        [
            {
                "DETTES": "",
                "Etablissements de crédit et assimilés au Maroc": "Bank Al-Maghrib,\nTrésor Public et\nService des Chèques\nPostaux",
                "null": "Autres\nétablissements\nde crédit et\nassimilés au\nMaroc",
                "Etablissements de\ncrédit à l’étranger": "",
                "Total\n31/12/2023": "",
                "Total\n31/12/2022": ""
            },
            {
                "DETTES": "COMPTES ORDINAIRES CREDITEURS\nVALEURS DONNEES EN PENSION\n- au jour le jour\n- à terme\nEMPRUNTS DE TRESORERIE\n- au jour le jour\n- à terme\nEMPRUNTS FINANCIERS\nAUTRES DETTES\nINTERETS COURUS A PAYER",
                "Etablissements de crédit et assimilés au Maroc": "",
                "null": "",
                "Etablissements de\ncrédit à l’étranger": "",
                "Total\n31/12/2023": "156 339\n300 510",
                "Total\n31/12/2022": "113 592\n300 510"
            },
            {
                "DETTES": "Total",
                "Etablissements de crédit et assimilés au Maroc": "",
                "null": "",
                "Etablissements de\ncrédit à l’étranger": "",
                "Total\n31/12/2023": "456 849",
                "Total\n31/12/2022": "414 102"
            }
        ],
        [
            {
                "INDICATIONS DES DEROGATIONS": "I. Dérogations aux principes\ncomptables fondamentaux",
                "JUSTIFICATIONS DES DEROGATIONS": "N\nA\nE\nN",
                "INFLUENCE DES DEROGATIONS SUR LE\nPATRIMOINE, LA SITUATION FINANCIERE ET\nLES RESULTATS": "T"
            },
            {
                "INDICATIONS DES DEROGATIONS": "II. Dérogations aux méthodes\nd'évaluation",
                "JUSTIFICATIONS DES DEROGATIONS": "N\nA\nE\nN",
                "INFLUENCE DES DEROGATIONS SUR LE\nPATRIMOINE, LA SITUATION FINANCIERE ET\nLES RESULTATS": "T"
            },
            {
                "INDICATIONS DES DEROGATIONS": "III. Dérogations aux règles\nd'établissement et de\nprésentation des états de synthèse",
                "JUSTIFICATIONS DES DEROGATIONS": "A\nE\nN",
                "INFLUENCE DES DEROGATIONS SUR LE\nPATRIMOINE, LA SITUATION FINANCIERE ET\nLES RESULTATS": "T\nN"
            }
        ],
        [
            {
                "": "",
                "Opérations": "31/12/2023",
                "de couverture": "31/12/2022",
                "Autres o": "31/12/2023",
                "pérations": "31/12/2022"
            },
            {
                "": "Opérations de change à terme",
                "Opérations": "",
                "de couverture": "",
                "Autres o": "",
                "pérations": ""
            },
            {
                "": "Devises à recevoir",
                "Opérations": "",
                "de couverture": "",
                "Autres o": "",
                "pérations": ""
            },
            {
                "": "Devises à livrer",
                "Opérations": "",
                "de couverture": "",
                "Autres o": "",
                "pérations": ""
            },
            {
                "": "Dirhams à recevoir",
                "Opérations": "",
                "de couverture": "",
                "Autres o": "",
                "pérations": ""
            },
            {
                "": "Dirhams à livrer",
                "Opérations": "",
                "de couverture": "",
                "Autres o": "",
                "pérations": ""
            },
            {
                "": "",
                "Opérations": "",
                "de couverture": "",
                "Autres o": "",
                "pérations": ""
            },
            {
                "": "Dont swaps financiers de devises",
                "Opérations": "",
                "de couverture": "",
                "Autres o": "",
                "pérations": "T"
            },
            {
                "": "",
                "Opérations": "",
                "de couverture": "",
                "Autres o": "N",
                "pérations": ""
            },
            {
                "": "Engagements sur produits dérivés",
                "Opérations": "",
                "de couverture": "",
                "Autres o": "A",
                "pérations": ""
            },
            {
                "": "Engagements sur marchés réglementés de taux d'intérêt",
                "Opérations": "",
                "de couverture": "E",
                "Autres o": "",
                "pérations": ""
            },
            {
                "": "Engagements sur marchés de gré à gré de taux d'intérêt",
                "Opérations": "",
                "de couverture": "",
                "Autres o": "",
                "pérations": ""
            },
            {
                "": "Engagements sur marchés réglementés de cours de change",
                "Opérations": "N",
                "de couverture": "",
                "Autres o": "",
                "pérations": ""
            },
            {
                "": "Engagements sur marchés de gré à gré de cours de change",
                "Opérations": "",
                "de couverture": "",
                "Autres o": "",
                "pérations": ""
            },
            {
                "": "Engagements sur marchés réglementés d'autres instruments",
                "Opérations": "",
                "de couverture": "",
                "Autres o": "",
                "pérations": ""
            },
            {
                "": "Engagements sur marchés de gré à gré d'autres instruments",
                "Opérations": "",
                "de couverture": "",
                "Autres o": "",
                "pérations": ""
            },
            {
                "": "",
                "Opérations": "",
                "de couverture": "",
                "Autres o": "",
                "pérations": ""
            }
        ],
        [
            {
                "ETAT DES CHANGEMENTS DE METHODES": "NATURE DES CHANGEMENTS",
                "null": "INFLUENCE SUR LE PATRIMOINE, LA SITUATION\nFINANCIERE ET LES RESULTATS"
            },
            {
                "ETAT DES CHANGEMENTS DE METHODES": "I. Changements affectant les\nméthodes d'évaluation",
                "null": "T\nN"
            },
            {
                "ETAT DES CHANGEMENTS DE METHODES": "II. Changements affectant les règles\nde présentation",
                "null": "T\nN\nA"
            }
        ],
        [
            {
                "Valeurs et sûretés reçues en garantie": "Bons duTrésor et valeurs assimilées\nAutres titres\nHypothèques\nAutres valeurs et sûretés réelles",
                "Valeur comptable nette": "406 048",
                "Rubriques de l'actif ou du hors bilan\nenregistrant les créances ou les\nengagements par signature donnés": "Créances sur la clientèle (Bilan)",
                "Montants des créances\net des engagements\npar signature donnés\ncouverts": "99 835"
            },
            {
                "Valeurs et sûretés reçues en garantie": "TOTAL",
                "Valeur comptable nette": "406 048",
                "Rubriques de l'actif ou du hors bilan\nenregistrant les créances ou les\nengagements par signature donnés": "",
                "Montants des créances\net des engagements\npar signature donnés\ncouverts": "99 835"
            }
        ],
        [
            {
                "Valeurs et sûretés données en garantie": "Bons du Trésor et valeurs assimilées\nAutres titres\nHypothèques\nAutres valeurs et sûretés réelles",
                "Valeur comptable nette": "",
                "Rubriques du passif ou du hors\nbilan enregistrant les dettes ou les\nengagements par signature reçus": "N T\nN E A",
                "Montants des dettes ou\ndes engagements par\nsignature reçus couverts": ""
            },
            {
                "Valeurs et sûretés données en garantie": "TOTAL",
                "Valeur comptable nette": "",
                "Rubriques du passif ou du hors\nbilan enregistrant les dettes ou les\nengagements par signature reçus": "",
                "Montants des dettes ou\ndes engagements par\nsignature reçus couverts": ""
            }
        ],
        [
            {
                "NOMBRE DE BENEFICIAIRES": "",
                "TOTAL ENGAGEMENT": "T\nN\nA\nE\nN"
            }
        ],
        [
            {
                "CCCooommmmmmuuunnniiicccaaatttiiiooonnn fififinnnaaannnccciiièèèrrreee": "Situation au 31 décembre 2023\nVALEURS DES TITRES DE TRANSACTION ET DE PLACEMENT ET DES TITRES D’INVESTISSEMENT PASSAGE DU RESULTAT NET COMPTABLE AU RESULTAT NET FISCAL\nen milliers de DH en milliers de DH\nValeur comptable Valeur de Plus-values Moins-values INTITULES MONTANTS MONTANTS\nValeur actuelle Provisions\nbrute remboursement latentes latentes\nI - RESULTAT NET COMPTABLE\nTITRES DE TRANSACTION . Bénéfice net 90 577\nBONS DU TRESOR ET VALEURS ASSIMILEES 0 0 0 . Perte nette\nOBLIGATIONS 0 0\nII - REINTEGRATIONS FISCALES 67 724\nAUTRES TITRES DE CREANCE 0 0 0 1- Courantes 8 991\nTITRES DE PROPRIETE 3 3 0 * Fraction non déductible des redevances de CB 296\nTITRES DE PLACEMENT * Provision pour Risque & charges 0\nBONS DU TRESOR ET VALEURS ASSIMILEES 0 0 0 * Autres élèments non déductibles CSS 7 273\n* Autres élèments non déductibles Plus Value de Fusion 1 422\nOBLIGATIONS 0 0\nAUTRES TITRES DE CREANCE 0 0 0 2- Non courantes 58 733\nTITRES DE PROPRIETE 1 995 858 1 137 * Impôt sur les sociétés 58 733\nTITRES D'INVESTISSEMENT * Rappel d’impôt 0\nBONS DU TRESOR ET VALEURS ASSIMILEES\nOBLIGATIONS\nIII - DEDUCTIONS FISCALES 2 718\nAUTRES TITRES DE CREANCE 1- Courantes 0\n* Reprise de la provision pour investissements 0\n* Reprise de la provision pour risques généraux 0\nDÉTAIL DES AUTRES ACTIFS * Provisions pour investissements\n* Encaissements et reprises sur provisions redressées lors du contrôle fiscal 0\nen milliers de DH\n2- Non courantes 2 718\nEléments 31/12/2023 31/12/2022\n* Produit des titres de participations 2 718\nDEBITEURS DIVERS 152 963 119 716\nEtat débiteur 31 864 34 307\nTOTAL 158 302 2 718\nDébiteurs Divers 121 098 85 409 IV - RESULTAT BRUT FISCAL\nCompte de régul Actif 72 342 76 839 . Bénéfice brut si T1 > T2 (A) 155 584\n. Déficit brut fiscal si T2 > T1 (B) …………………\nTotal 225 305 196 555\nV - REPORTS DEFICITAIRES IMPUTES (C) (1) 0\nDÉTAIL DES AUTRES PASSIFS . Exercice n-4 ……………….\n. Exercice n-3 ……………….\nen milliers de DH\n. Exercice n-2 ………………\nEléments 31/12/2023 31/12/2022 . Exercice n-1 ………………\nCréditeurs Divers 554 372 534 231\nVI - RESULTAT NET FISCAL\nEtat créditeurs 272 960 254 678 . Bénéfice net fiscal ( A - C) 155 584\nAutres créditeurs 281 412 279 553 OU\n. Déficit net fiscal (B) ………………\nCompte de régul Passif 325 460 370 185 VII - CUMUL DES AMORTISSEMENTS FISCALEMENT DIFFERES …………….\nAutres Passif 879 832 904 415 VIII - CUMUL DES DEFICITS FISCAUX RESTANT A REPORTER …………………\n. Exercice n-4 ……………….\n. Exercice n-3 ……………….\nLE TABLEAU DES ENGAGEMENTS SUR TITRES . Exercice n-2 ……………\n. Exercice n-1 ……………\nRUBRIQUE MONTANT COMMENTAIRE\n(1) Dans la limite du montant du bénéfice brut fiscal (A)\nENGAGEMENTS DONNES\nTitres achetés à réméré RESULTATS ET AUTRES ELEMENTS DES TROIS DERNIERS EXERCICES\nTitres à livrer\n- Marché primaire en milliers de DH\n- Marché gris 2023 2022 2021\n- Marchés réglementés\nT\n- Marché gré à gré N CAPITAUX PROPRES ET ASSIMILES 862 768 856 541 933 245\n- Autres A\nE\nENGAGEMENTS RECUS N OPERATIONS ET RESULTATS DE L'EXERCICE\nTitres vendus à réméré 1- Produit net bancaire 396 169 399 292 389 127\nTitres à recevoir 2- Résultat avant impôts 149 310 139 571 136 953\n- Marché primaire 3- Impôts sur les résultats 58 733 53 821 52 225\n- Marché gris\n4- Bénéfices distribués 84 351 162 454 162 294\n- Marchés réglementés\n5- Résultats non distribués ( mis en réserve ou 90 577 85 750 84 728\n- Marché gré à gré\nen instance d'affectation)\n- Autres\nRESULTAT PAR TITRE (en dirhams)\nLA VENTILATION DU TOTAL DE L’ACTIF, DU PASSIF ET DE L’HORS BILAN EN MONNAIE ÉTRANGÈRE Résultat net par action ou part sociale 29 27 27\nBénéfice distribué par action ou part sociale 27 52 52\nDESIGNATION MONTANT\nACTIF : PERSONNEL\nValeurs en caisse,Banques centrales,Trésor public, Service des chéques postaux Montants des rémunérations brutes de l'exercice 54 673 57 038 53 700\nCréances sur les établissements de crédit et assimilés Effectif moyen des salariés employés pendant l'exercice 320 338 330\nCréances sur la clientéle\nT\nAutres actifs\nTitres de participation et emplois assimilées\nN\nCréances subordonnées REPARTITION DU CAPITAL SOCIAL\nA\nTOTAL ACTIF Montant du capital: 312 411 900,00\nMontant du capital social souscrit et non appelé :\nPASSIF: E Valeur nominale des titres : 1 00,00 Dhs\nDettes envers les établissements de crédit et assimilés\nDépôts de la clientèle N Nom des pr oin uc aip ssa ou cx ié a sc tionnaires Adresse Nombre de titres détenus Pa dr ét td eu n uca ep %ital\nAutres passifs Exercice précédent Exercice actuel\nTOTAL PASSIF BMCE BANK 140, avenues hassan II. Casa, 1 935 692 1 935 692 61,96%\nHORS-BILAN:\nENGAGEMENTS DONNES SAHAM Assurance 216, Boulevard Zerktouni, Casa 442 061 442 061 14,15%\nENGAGEMENTS RECUS\nAutres 746 366 746 366 23,89%\nAFFECTATION DES RESULTATS INTERVENUE AU COURS DE L’EXERCICE\nen milliers de DH\nMontants Montants\nTITRES ET AUTRES ACTIFS GERES OU EN DEPOTS\nA- Origine des résultats affectés 85 750B- Affectation des résultats 85 750\nTITRES Nombre de comptes Montants en milliers de DH\nDécision de l'AGO du 09/05/2023\n31/12/2023 31/12/2022 31/12/2023 31/12/2022\nRéserve légale 0\nTitres dont l'établissement est dépositaire\nReport à nouveau Dividendes 84 351 T\nRésultats nets en instance d'affectation Autres affectations 1 399 Titres gérés en vertu d'un mandat de gestion N\nRésultat net de l'exercice 85 750 Titres d'OPCVM dont l'établissement est dépositaire A\nTitres d'OPCVM gérés en vertu d'un mandat de gestion E\nPrélèvement sur les bénéfices Autres actifs dont l'établissement est dépositaire N\nAutres prélèvements 0\nAutres actifs gérés en vertu d'un mandat de gestion\nTOTAL A 85 750 TOTAL B 85 750"
            },
            {
                "CCCooommmmmmuuunnniiicccaaatttiiiooonnn fififinnnaaannnccciiièèèrrreee": ""
            }
        ],
        [
            {
                "": "",
                "Valeur comptable\nbrute": "",
                "Valeur actuelle": "",
                "Valeur de\nremboursement": "",
                "Plus-values\nlatentes": "",
                "Moins-values\nlatentes": "",
                "Provisions": ""
            },
            {
                "": "TITRES DE TRANSACTION",
                "Valeur comptable\nbrute": "",
                "Valeur actuelle": "",
                "Valeur de\nremboursement": "",
                "Plus-values\nlatentes": "",
                "Moins-values\nlatentes": "",
                "Provisions": ""
            },
            {
                "": "BONS DU TRESOR ET VALEURS ASSIMILEES",
                "Valeur comptable\nbrute": "0",
                "Valeur actuelle": "0",
                "Valeur de\nremboursement": "",
                "Plus-values\nlatentes": "",
                "Moins-values\nlatentes": "",
                "Provisions": "0"
            },
            {
                "": "OBLIGATIONS",
                "Valeur comptable\nbrute": "0",
                "Valeur actuelle": "0",
                "Valeur de\nremboursement": "",
                "Plus-values\nlatentes": "",
                "Moins-values\nlatentes": "",
                "Provisions": ""
            },
            {
                "": "AUTRES TITRES DE CREANCE",
                "Valeur comptable\nbrute": "0",
                "Valeur actuelle": "0",
                "Valeur de\nremboursement": "",
                "Plus-values\nlatentes": "",
                "Moins-values\nlatentes": "",
                "Provisions": "0"
            },
            {
                "": "TITRES DE PROPRIETE",
                "Valeur comptable\nbrute": "3",
                "Valeur actuelle": "3",
                "Valeur de\nremboursement": "",
                "Plus-values\nlatentes": "",
                "Moins-values\nlatentes": "",
                "Provisions": "0"
            },
            {
                "": "TITRES DE PLACEMENT",
                "Valeur comptable\nbrute": "",
                "Valeur actuelle": "",
                "Valeur de\nremboursement": "",
                "Plus-values\nlatentes": "",
                "Moins-values\nlatentes": "",
                "Provisions": ""
            },
            {
                "": "BONS DU TRESOR ET VALEURS ASSIMILEES",
                "Valeur comptable\nbrute": "0",
                "Valeur actuelle": "0",
                "Valeur de\nremboursement": "",
                "Plus-values\nlatentes": "",
                "Moins-values\nlatentes": "",
                "Provisions": "0"
            },
            {
                "": "OBLIGATIONS",
                "Valeur comptable\nbrute": "0",
                "Valeur actuelle": "0",
                "Valeur de\nremboursement": "",
                "Plus-values\nlatentes": "",
                "Moins-values\nlatentes": "",
                "Provisions": ""
            },
            {
                "": "AUTRES TITRES DE CREANCE",
                "Valeur comptable\nbrute": "0",
                "Valeur actuelle": "0",
                "Valeur de\nremboursement": "",
                "Plus-values\nlatentes": "",
                "Moins-values\nlatentes": "",
                "Provisions": "0"
            },
            {
                "": "TITRES DE PROPRIETE",
                "Valeur comptable\nbrute": "1 995",
                "Valeur actuelle": "858",
                "Valeur de\nremboursement": "",
                "Plus-values\nlatentes": "",
                "Moins-values\nlatentes": "",
                "Provisions": "1 137"
            },
            {
                "": "TITRES D'INVESTISSEMENT",
                "Valeur comptable\nbrute": "",
                "Valeur actuelle": "",
                "Valeur de\nremboursement": "",
                "Plus-values\nlatentes": "",
                "Moins-values\nlatentes": "",
                "Provisions": ""
            },
            {
                "": "BONS DU TRESOR ET VALEURS ASSIMILEES",
                "Valeur comptable\nbrute": "",
                "Valeur actuelle": "",
                "Valeur de\nremboursement": "",
                "Plus-values\nlatentes": "",
                "Moins-values\nlatentes": "",
                "Provisions": ""
            },
            {
                "": "OBLIGATIONS",
                "Valeur comptable\nbrute": "",
                "Valeur actuelle": "",
                "Valeur de\nremboursement": "",
                "Plus-values\nlatentes": "",
                "Moins-values\nlatentes": "",
                "Provisions": ""
            },
            {
                "": "AUTRES TITRES DE CREANCE",
                "Valeur comptable\nbrute": "",
                "Valeur actuelle": "",
                "Valeur de\nremboursement": "",
                "Plus-values\nlatentes": "",
                "Moins-values\nlatentes": "",
                "Provisions": ""
            },
            {
                "": "",
                "Valeur comptable\nbrute": "",
                "Valeur actuelle": "",
                "Valeur de\nremboursement": "",
                "Plus-values\nlatentes": "",
                "Moins-values\nlatentes": "",
                "Provisions": ""
            }
        ],
        [
            {
                "INTITULES": "",
                "MONTANTS": ""
            },
            {
                "INTITULES": "I - RESULTAT NET COMPTABLE",
                "MONTANTS": ""
            },
            {
                "INTITULES": ". Bénéfice net",
                "MONTANTS": ""
            },
            {
                "INTITULES": ". Perte nette",
                "MONTANTS": ""
            },
            {
                "INTITULES": "",
                "MONTANTS": ""
            },
            {
                "INTITULES": "II - REINTEGRATIONS FISCALES",
                "MONTANTS": ""
            },
            {
                "INTITULES": "1- Courantes",
                "MONTANTS": ""
            },
            {
                "INTITULES": "* Fraction non déductible des redevances de CB",
                "MONTANTS": ""
            },
            {
                "INTITULES": "* Provision pour Risque & charges",
                "MONTANTS": ""
            },
            {
                "INTITULES": "* Autres élèments non déductibles CSS",
                "MONTANTS": ""
            },
            {
                "INTITULES": "* Autres élèments non déductibles Plus Value de Fusion",
                "MONTANTS": ""
            },
            {
                "INTITULES": "",
                "MONTANTS": ""
            },
            {
                "INTITULES": "2- Non courantes",
                "MONTANTS": ""
            },
            {
                "INTITULES": "* Impôt sur les sociétés",
                "MONTANTS": ""
            },
            {
                "INTITULES": "* Rappel d’impôt",
                "MONTANTS": ""
            },
            {
                "INTITULES": "",
                "MONTANTS": ""
            },
            {
                "INTITULES": "",
                "MONTANTS": ""
            },
            {
                "INTITULES": "III - DEDUCTIONS FISCALES",
                "MONTANTS": "2 718"
            },
            {
                "INTITULES": "1- Courantes",
                "MONTANTS": "0"
            },
            {
                "INTITULES": "* Reprise de la provision pour investissements",
                "MONTANTS": "0"
            },
            {
                "INTITULES": "* Reprise de la provision pour risques généraux",
                "MONTANTS": "0"
            },
            {
                "INTITULES": "* Provisions pour investissements",
                "MONTANTS": ""
            },
            {
                "INTITULES": "* Encaissements et reprises sur provisions redressées lors du contrôle fiscal",
                "MONTANTS": "0"
            },
            {
                "INTITULES": "",
                "MONTANTS": ""
            },
            {
                "INTITULES": "2- Non courantes",
                "MONTANTS": "2 718"
            },
            {
                "INTITULES": "* Produit des titres de participations",
                "MONTANTS": "2 718"
            },
            {
                "INTITULES": "",
                "MONTANTS": ""
            },
            {
                "INTITULES": "",
                "MONTANTS": ""
            },
            {
                "INTITULES": "TOTAL",
                "MONTANTS": "2 718"
            },
            {
                "INTITULES": "IV - RESULTAT BRUT FISCAL",
                "MONTANTS": ""
            },
            {
                "INTITULES": ". Bénéfice brut si T1 > T2 (A)",
                "MONTANTS": "155 584"
            },
            {
                "INTITULES": ". Déficit brut fiscal si T2 > T1 (B)",
                "MONTANTS": "…………………"
            },
            {
                "INTITULES": "",
                "MONTANTS": ""
            },
            {
                "INTITULES": "V - REPORTS DEFICITAIRES IMPUTES (C) (1)",
                "MONTANTS": "0"
            },
            {
                "INTITULES": ". Exercice n-4",
                "MONTANTS": ""
            },
            {
                "INTITULES": ". Exercice n-3",
                "MONTANTS": ""
            },
            {
                "INTITULES": ". Exercice n-2",
                "MONTANTS": ""
            },
            {
                "INTITULES": ". Exercice n-1",
                "MONTANTS": ""
            },
            {
                "INTITULES": "",
                "MONTANTS": ""
            },
            {
                "INTITULES": "VI - RESULTAT NET FISCAL",
                "MONTANTS": ""
            },
            {
                "INTITULES": ". Bénéfice net fiscal ( A - C)",
                "MONTANTS": "155 584"
            },
            {
                "INTITULES": "OU",
                "MONTANTS": ""
            },
            {
                "INTITULES": ". Déficit net fiscal (B)",
                "MONTANTS": "………………"
            },
            {
                "INTITULES": "",
                "MONTANTS": ""
            },
            {
                "INTITULES": "VII - CUMUL DES AMORTISSEMENTS FISCALEMENT DIFFERES",
                "MONTANTS": "……………."
            },
            {
                "INTITULES": "VIII - CUMUL DES DEFICITS FISCAUX RESTANT A REPORTER",
                "MONTANTS": "…………………"
            },
            {
                "INTITULES": ". Exercice n-4",
                "MONTANTS": ""
            },
            {
                "INTITULES": ". Exercice n-3",
                "MONTANTS": ""
            },
            {
                "INTITULES": ". Exercice n-2",
                "MONTANTS": ""
            },
            {
                "INTITULES": ". Exercice n-1",
                "MONTANTS": ""
            }
        ],
        [
            {
                "Eléments": "DEBITEURS DIVERS",
                "31/12/2023": "152 963",
                "31/12/2022": "119 716"
            },
            {
                "Eléments": "Etat débiteur",
                "31/12/2023": "31 864",
                "31/12/2022": "34 307"
            },
            {
                "Eléments": "Débiteurs Divers",
                "31/12/2023": "121 098",
                "31/12/2022": "85 409"
            },
            {
                "Eléments": "Compte de régul Actif",
                "31/12/2023": "72 342",
                "31/12/2022": "76 839"
            },
            {
                "Eléments": "Total",
                "31/12/2023": "225 305",
                "31/12/2022": "196 555"
            }
        ],
        [
            {
                "Eléments": "Créditeurs Divers",
                "31/12/2023": "554 372",
                "31/12/2022": "534 231"
            },
            {
                "Eléments": "Etat créditeurs",
                "31/12/2023": "272 960",
                "31/12/2022": "254 678"
            },
            {
                "Eléments": "Autres créditeurs",
                "31/12/2023": "281 412",
                "31/12/2022": "279 553"
            },
            {
                "Eléments": "",
                "31/12/2023": "",
                "31/12/2022": ""
            },
            {
                "Eléments": "Compte de régul Passif",
                "31/12/2023": "325 460",
                "31/12/2022": "370 185"
            },
            {
                "Eléments": "Autres Passif",
                "31/12/2023": "879 832",
                "31/12/2022": "904 415"
            },
            {
                "Eléments": "LE TABLEAU DES ENGAGEMENTS SUR TITRES",
                "31/12/2023": "",
                "31/12/2022": ""
            }
        ],
        [
            {
                "RUBRIQUE": "ENGAGEMENTS DONNES\nTitres achetés à réméré\nTitres à livrer\n- Marché primaire\n- Marché gris\n- Marchés réglementés\n- Marché gré à gré\n- Autres\nENGAGEMENTS RECUS\nTitres vendus à réméré\nTitres à recevoir\n- Marché primaire\n- Marché gris\n- Marchés réglementés\n- Marché gré à gré\n- Autres",
                "MONTANT": "N\nA\nE\nN",
                "COMMENTAIRE": "T"
            }
        ],
        [
            {
                "": "",
                "2023": "",
                "2022": "",
                "2021": ""
            },
            {
                "": "CAPITAUX PROPRES ET ASSIMILES",
                "2023": "862 768",
                "2022": "856 541",
                "2021": "933 245"
            },
            {
                "": "",
                "2023": "",
                "2022": "",
                "2021": ""
            },
            {
                "": "OPERATIONS ET RESULTATS DE L'EXERCICE",
                "2023": "",
                "2022": "",
                "2021": ""
            },
            {
                "": "1- Produit net bancaire",
                "2023": "396 169",
                "2022": "399 292",
                "2021": "389 127"
            },
            {
                "": "2- Résultat avant impôts",
                "2023": "149 310",
                "2022": "139 571",
                "2021": "136 953"
            },
            {
                "": "3- Impôts sur les résultats",
                "2023": "58 733",
                "2022": "53 821",
                "2021": "52 225"
            },
            {
                "": "4- Bénéfices distribués",
                "2023": "84 351",
                "2022": "162 454",
                "2021": "162 294"
            },
            {
                "": "5- Résultats non distribués ( mis en réserve ou",
                "2023": "90 577",
                "2022": "85 750",
                "2021": "84 728"
            },
            {
                "": "en instance d'affectation)",
                "2023": "",
                "2022": "",
                "2021": ""
            },
            {
                "": "",
                "2023": "",
                "2022": "",
                "2021": ""
            },
            {
                "": "RESULTAT PAR TITRE (en dirhams)",
                "2023": "",
                "2022": "",
                "2021": ""
            },
            {
                "": "Résultat net par action ou part sociale",
                "2023": "29",
                "2022": "27",
                "2021": "27"
            },
            {
                "": "Bénéfice distribué par action ou part sociale",
                "2023": "27",
                "2022": "52",
                "2021": "52"
            },
            {
                "": "",
                "2023": "",
                "2022": "",
                "2021": ""
            },
            {
                "": "PERSONNEL",
                "2023": "",
                "2022": "",
                "2021": ""
            },
            {
                "": "Montants des rémunérations brutes de l'exercice",
                "2023": "54 673",
                "2022": "57 038",
                "2021": "53 700"
            },
            {
                "": "Effectif moyen des salariés employés pendant l'exercice",
                "2023": "320",
                "2022": "338",
                "2021": "330"
            },
            {
                "": "",
                "2023": "",
                "2022": "",
                "2021": ""
            },
            {
                "": "",
                "2023": "",
                "2022": "",
                "2021": ""
            }
        ],
        [
            {
                "DESIGNATION": "ACTIF :\nValeurs en caisse,Banques centrales,Trésor public, Service des chéques postaux\nCréances sur les établissements de crédit et assimilés\nCréances sur la clientéle\nAutres actifs\nTitres de participation et emplois assimilées\nCréances subordonnées",
                "MONTANT": "T"
            },
            {
                "DESIGNATION": "TOTAL ACTIF",
                "MONTANT": "N"
            },
            {
                "DESIGNATION": "PASSIF:\nE\nDettes envers les établissements de crédit et assimilés\nDépôts de la clientèle\nAutres passifs",
                "MONTANT": "A"
            },
            {
                "DESIGNATION": "N\nTOTAL PASSIF",
                "MONTANT": ""
            },
            {
                "DESIGNATION": "HORS-BILAN:\nENGAGEMENTS DONNES\nENGAGEMENTS RECUS",
                "MONTANT": ""
            },
            {
                "DESIGNATION": "AFFECTATION DES RESULTATS INTERVENUE AU COURS DE L’EXERCICE",
                "MONTANT": ""
            }
        ],
        [
            {
                "Nom des principaux actionnaires\nou associés": "",
                "Adresse": "",
                "Nombre de titres détenus": "Exercice précédent",
                "null": "Exercice actuel",
                "Part du capital\ndétenue %": ""
            },
            {
                "Nom des principaux actionnaires\nou associés": "",
                "Adresse": "",
                "Nombre de titres détenus": "1 935 692\n442 061\n746 366",
                "null": "",
                "Part du capital\ndétenue %": ""
            },
            {
                "Nom des principaux actionnaires\nou associés": "BMCE BANK",
                "Adresse": "140, avenues hassan II. Casa,",
                "Nombre de titres détenus": "",
                "null": "1 935 692",
                "Part du capital\ndétenue %": "61,96%"
            },
            {
                "Nom des principaux actionnaires\nou associés": "",
                "Adresse": "",
                "Nombre de titres détenus": "",
                "null": "",
                "Part du capital\ndétenue %": ""
            },
            {
                "Nom des principaux actionnaires\nou associés": "SAHAM Assurance",
                "Adresse": "216, Boulevard Zerktouni, Casa",
                "Nombre de titres détenus": "",
                "null": "442 061",
                "Part du capital\ndétenue %": "14,15%"
            },
            {
                "Nom des principaux actionnaires\nou associés": "",
                "Adresse": "",
                "Nombre de titres détenus": "",
                "null": "",
                "Part du capital\ndétenue %": ""
            },
            {
                "Nom des principaux actionnaires\nou associés": "Autres",
                "Adresse": "",
                "Nombre de titres détenus": "",
                "null": "746 366",
                "Part du capital\ndétenue %": "23,89%"
            },
            {
                "Nom des principaux actionnaires\nou associés": "",
                "Adresse": "",
                "Nombre de titres détenus": "",
                "null": "",
                "Part du capital\ndétenue %": ""
            }
        ],
        [
            {
                "": "B- Affectation des résultats\nRéserve légale\nDividendes\nAutres affectations",
                "Montants": "85 750\n0\n84 351\n1 399"
            },
            {
                "": "TOTAL B",
                "Montants": "85 750"
            }
        ],
        [
            {
                "TITRES": "",
                "Nombre de comptes": "31/12/2023",
                "null": "31/12/2022",
                "Montants en milliers de DH": "31/12/2023"
            },
            {
                "TITRES": "Titres dont l'établissement est dépositaire\nTitres gérés en vertu d'un mandat de gestion\nTitres d'OPCVM dont l'établissement est dépositaire\nTitres d'OPCVM gérés en vertu d'un mandat de gestion\nAutres actifs dont l'établissement est dépositaire\nAutres actifs gérés en vertu d'un mandat de gestion",
                "Nombre de comptes": "",
                "null": "",
                "Montants en milliers de DH": "T\nN\nA"
            }
        ],
        [
            {
                "CCoommmmuunniiccaattiioonn fifinnaanncciièèrree": "Situation au 31 décembre 2023\nEFFECTIFS RESEAU\n(en nombre)\nRESEAU 31/12/2023 31/12/2022\nEFFECTIFS 31/12/2021 31/12/2022\nEffectifs rémunérés 320 338 Guichets permanents 23 23\nEffectifs utilisés 320 338 Guichets périodiques\nEffectifs équivalents plein temps 320 338 Guichets automatiques de banque\nEffectifs administratifs et techniques (équivalent plein temps) 203 221 Succursales et agences à l'étranger\nEffectifs affectés à des tâches bancaires (équivalent plein temps) 117 117\nBureaux de représentation à l'étranger\nCadres (équivalent plein temps) 330 338\nEmployés (équivalent plein temps) 0 0\nCOMPTES DE LA CLIENTELE\ndont effectifs employés à l'étranger 0 0\nCOMPTES DE LA CLIENTELE\n31/12/2023 31/12/2022\nDATATION ET EVENEMENTS POSTERIEURS\nComptes courants\nI. DATATION\nComptes chèques, hors MRE\nT\n. Date de clôture (1) Comptes MRE N\n31/12/2023 Comptes d'affacturage A\nE\nComptes d'épargne N\n. Date d'établissement des états de synthèse (2)\n23/02/2024 Comptes à terme\nBons de caisse\n(1) Justification en cas de changement de la date de clôture de l'exercice\n(2) Justification en cas de dépassement du délai réglementaire de trois mois prévu pour\nl'élaboration des états de synthèse.\nII. EVENEMENTS NES POSTERIEUREMENT A LA CLOTURE DE L'EXERCICE NON RATTACHABLES A CET EXERCICE ET CONNUS AVANT LA 1ERE COMMUNICATION\nEXTERNE DES ETATS DE SYNTHESE\nDates Indications des événements\n. Favorables\n-Enregistrement des règlements subséquents et encaissements sur créances en souffrances\n.Défavorables\n- Baisse continue du TEG\n- Retours d'impayées et détérioration de la situation des créances en souffrances en terme de nombre d'impayés et de classification des créances\net leurs provisions.\nATTESTATION DES COMMISSAIRES AUX COMPTES"
            },
            {
                "CCoommmmuunniiccaattiioonn fifinnaanncciièèrree": ""
            }
        ],
        [
            {
                "31/12/2023": "23",
                "31/12/2022": "23"
            }
        ],
        [
            {
                "31/12/2023": "A\nE\nN",
                "31/12/2022": "T\nN"
            }
        ],
        [
            {
                "Dates": "",
                "Indications des événements\n. Favorables\n-Enregistrement des règlements subséquents et encaissements sur créances en souffrances\n.Défavorables\n- Baisse continue du TEG\n- Retours d'impayées et détérioration de la situation des créances en souffrances en terme de nombre d'impayés et de classification des créances\net leurs provisions.": ""
            },
            {
                "Dates": "",
                "Indications des événements\n. Favorables\n-Enregistrement des règlements subséquents et encaissements sur créances en souffrances\n.Défavorables\n- Baisse continue du TEG\n- Retours d'impayées et détérioration de la situation des créances en souffrances en terme de nombre d'impayés et de classification des créances\net leurs provisions.": ""
            },
            {
                "Dates": "",
                "Indications des événements\n. Favorables\n-Enregistrement des règlements subséquents et encaissements sur créances en souffrances\n.Défavorables\n- Baisse continue du TEG\n- Retours d'impayées et détérioration de la situation des créances en souffrances en terme de nombre d'impayés et de classification des créances\net leurs provisions.": ""
            },
            {
                "Dates": "",
                "Indications des événements\n. Favorables\n-Enregistrement des règlements subséquents et encaissements sur créances en souffrances\n.Défavorables\n- Baisse continue du TEG\n- Retours d'impayées et détérioration de la situation des créances en souffrances en terme de nombre d'impayés et de classification des créances\net leurs provisions.": ""
            },
            {
                "Dates": "",
                "Indications des événements\n. Favorables\n-Enregistrement des règlements subséquents et encaissements sur créances en souffrances\n.Défavorables\n- Baisse continue du TEG\n- Retours d'impayées et détérioration de la situation des créances en souffrances en terme de nombre d'impayés et de classification des créances\net leurs provisions.": ""
            },
            {
                "Dates": "",
                "Indications des événements\n. Favorables\n-Enregistrement des règlements subséquents et encaissements sur créances en souffrances\n.Défavorables\n- Baisse continue du TEG\n- Retours d'impayées et détérioration de la situation des créances en souffrances en terme de nombre d'impayés et de classification des créances\net leurs provisions.": ""
            },
            {
                "Dates": "",
                "Indications des événements\n. Favorables\n-Enregistrement des règlements subséquents et encaissements sur créances en souffrances\n.Défavorables\n- Baisse continue du TEG\n- Retours d'impayées et détérioration de la situation des créances en souffrances en terme de nombre d'impayés et de classification des créances\net leurs provisions.": ""
            },
            {
                "Dates": "",
                "Indications des événements\n. Favorables\n-Enregistrement des règlements subséquents et encaissements sur créances en souffrances\n.Défavorables\n- Baisse continue du TEG\n- Retours d'impayées et détérioration de la situation des créances en souffrances en terme de nombre d'impayés et de classification des créances\net leurs provisions.": ""
            },
            {
                "Dates": "",
                "Indications des événements\n. Favorables\n-Enregistrement des règlements subséquents et encaissements sur créances en souffrances\n.Défavorables\n- Baisse continue du TEG\n- Retours d'impayées et détérioration de la situation des créances en souffrances en terme de nombre d'impayés et de classification des créances\net leurs provisions.": ""
            }
        ]
    ]
}